Workbook
Name _: #REF!
Name _: #REF!
Name _: #REF!
Name _: #REF!
Name _: #REF!
Name _: #REF!
Name _: #REF!
Name _: #REF!
Name _: #REF!
Name _?: #N/A
Name ______R3_t: #N/A
Name ______R3_t1: #N/A
Name __DAT10: #REF!
Name __DAT10: #REF!
Name __DAT10: #REF!
Name __DAT10: #REF!
Name __DAT10: #REF!
Name __DAT10: #REF!
Name __DAT10: #REF!
Name __DAT10: #REF!
Name __DAT10: #REF!
Name __DAT4: #REF!
Name __DAT4: #REF!
Name __DAT4: #REF!
Name __DAT4: #REF!
Name __DAT4: #REF!
Name __DAT4: #REF!
Name __DAT4: #REF!
Name __DAT4: #REF!
Name __DAT4: #REF!
Name __DAT6: #REF!
Name __DAT6: #REF!
Name __DAT6: #REF!
Name __DAT6: #REF!
Name __DAT6: #REF!
Name __DAT6: #REF!
Name __DAT6: #REF!
Name __DAT6: #REF!
Name __DAT6: #REF!
Name __DAT7: #REF!
Name __DAT7: #REF!
Name __DAT7: #REF!
Name __DAT7: #REF!
Name __DAT7: #REF!
Name __DAT7: #REF!
Name __DAT7: #REF!
Name __DAT7: #REF!
Name __DAT7: #REF!
Name _￡A￡´1: #N/A
Name _00년: #REF!
Name _00년: #REF!
Name _00년: #REF!
Name _00년: #REF!
Name _00년: #REF!
Name _00년: #REF!
Name _00년: #REF!
Name _00년: #REF!
Name _00년: #REF!
Name _111: #REF!
Name _111: #REF!

Sheet BS(연결)
B3: 재무상태표(연결)
C4: 2012년 | D4: 2013년 | E4: 2014년 | F4: 2015년 | K4: 과 목 | L4: 제 40 기 | M4: 제 41 기 | N4: 제 42 기 | O4: 제 43 기 반기
B5: 백만원 | C5: 12월 31일 | D5: 12월 31일 | E5: 12월 31일 | F5: 6월 30일 | K5: 자산
B6: 유동자산 | C6: =SUM(C7:C11) -> 261377254740 | D6: =SUM(D7:D11) -> 264091049999 | E6: =SUM(E7:E11) -> 286167352689 | F6: =SUM(F7:F11) -> 296318785179 | K6: 유동자산
B7: 현금및현금성자산 | C7: =SUMIF($J$7:$J$52,$B7,L$7:L$52) -> 5544530351 | D7: =SUMIF($J$7:$J$52,$B7,M$7:M$52) -> 4242192463 | E7: =SUMIF($J$7:$J$52,$B7,N$7:N$52) -> 4845599991 | F7: =SUMIF($J$7:$J$52,$B7,O$7:O$52) -> 4244334407 | J7: 현금및현금성자산 | K7: 현금및현금성자산 | L7: 5544530351 | M7: 4242192463 | N7: 4845599991 | O7: 4244334407
B8: 매출채권 | C8: =SUMIF($J$7:$J$52,$B8,L$7:L$52) -> 134027043446 | D8: =SUMIF($J$7:$J$52,$B8,M$7:M$52) -> 121963019140 | E8: =SUMIF($J$7:$J$52,$B8,N$7:N$52) -> 141439063302 | F8: =SUMIF($J$7:$J$52,$B8,O$7:O$52) -> 147684814458 | J8: 매출채권 | K8: 매출채권 | L8: 134027043446 | M8: 121963019140 | N8: 141439063302 | O8: 147684814458
B9: 기타유동채권 | C9: =SUMIF($J$7:$J$52,$B9,L$7:L$52) -> 10499566621 | D9: =SUMIF($J$7:$J$52,$B9,M$7:M$52) -> 11618278163 | E9: =SUMIF($J$7:$J$52,$B9,N$7:N$52) -> 14635562527 | F9: =SUMIF($J$7:$J$52,$B9,O$7:O$52) -> 11204996806 | J9: 기타유동채권 | K9: 기타수취채권 | L9: 10499566621 | M9: 11618278163 | N9: 14635562527 | O9: 11204996806
B10: 재고자산 | C10: =SUMIF($J$7:$J$52,$B10,L$7:L$52) -> 85484663552 | D10: =SUMIF($J$7:$J$52,$B10,M$7:M$52) -> 83641773916 | E10: =SUMIF($J$7:$J$52,$B10,N$7:N$52) -> 95167542674 | F10: =SUMIF($J$7:$J$52,$B10,O$7:O$52) -> 96860821055 | J10: 기타자산 | K10: 기타금융자산 | L10: 2740918526 | M10: 11862329380 | N10: 2051673356 | O10: 1697906040
B11: 기타자산 | C11: =SUMIF($J$7:$J$52,$B11,L$7:L$52) -> 25821450770 | D11: =SUMIF($J$7:$J$52,$B11,M$7:M$52) -> 42625786317 | E11: =SUMIF($J$7:$J$52,$B11,N$7:N$52) -> 30079584195 | F11: =SUMIF($J$7:$J$52,$B11,O$7:O$52) -> 36323818453 | J11: 기타자산 | K11: 기타유동자산 | L11: 23080532244 | M11: 30763456937 | N11: 28027910839 | O11: 34625912413
B12: 비유동자산 | C12: =SUM(C13:C17) -> 234184304425 | D12: =SUM(D13:D17) -> 234439865763 | E12: =SUM(E13:E17) -> 270204201617 | F12: =SUM(F13:F17) -> 291084772593 | J12: 재고자산 | K12: 재고자산 | L12: 85484663552 | M12: 83641773916 | N12: 95167542674 | O12: 96860821055
B13: 유형자산 | C13: =SUMIF($J$7:$J$52,$B13,L$7:L$52) -> 177579210031 | D13: =SUMIF($J$7:$J$52,$B13,M$7:M$52) -> 186123687777 | E13: =SUMIF($J$7:$J$52,$B13,N$7:N$52) -> 208778336913 | F13: =SUMIF($J$7:$J$52,$B13,O$7:O$52) -> 226445724446 | K13: 유동자산 합계 | L13: 261377254740 | M13: 264091049999 | N13: 286167352689 | O13: 296318785179
B14: 무형자산 | C14: =SUMIF($J$7:$J$52,$B14,L$7:L$52) -> 28650256306 | D14: =SUMIF($J$7:$J$52,$B14,M$7:M$52) -> 25716603900 | E14: =SUMIF($J$7:$J$52,$B14,N$7:N$52) -> 27925711452 | F14: =SUMIF($J$7:$J$52,$B14,O$7:O$52) -> 29882456335 | K14: 비유동자산
B15: 기타비유동채권 | C15: =SUMIF($J$7:$J$52,$B15,L$7:L$52) -> 1461979493 | D15: =SUMIF($J$7:$J$52,$B15,M$7:M$52) -> 2549448756 | E15: =SUMIF($J$7:$J$52,$B15,N$7:N$52) -> 1892003938 | F15: =SUMIF($J$7:$J$52,$B15,O$7:O$52) -> 2035011461 | J15: 기타비유동채권 | K15: 기타수취채권 | L15: 1461979493 | M15: 2549448756 | N15: 1892003938 | O15: 2035011461
B16: 관계기업투자 | C16: =SUMIF($J$7:$J$52,$B16,L$7:L$52) -> 1041203397 | D16: =SUMIF($J$7:$J$52,$B16,M$7:M$52) -> 450392393 | E16: =SUMIF($J$7:$J$52,$B16,N$7:N$52) -> 555691371 | F16: =SUMIF($J$7:$J$52,$B16,O$7:O$52) -> 572767736 | J16: 관계기업투자 | K16: 관계기업투자 | L16: 1041203397 | M16: 450392393 | N16: 555691371 | O16: 572767736
B17: 기타비유동자산 | C17: =SUMIF($J$7:$J$52,$B17,L$7:L$52) -> 25451655198 | D17: =SUMIF($J$7:$J$52,$B17,M$7:M$52) -> 19599732937 | E17: =SUMIF($J$7:$J$52,$B17,N$7:N$52) -> 31052457943 | F17: =SUMIF($J$7:$J$52,$B17,O$7:O$52) -> 32148812615 | J17: 기타비유동자산 | K17: 기타금융자산 | L17: 10000684407 | M17: 2305467574 | N17: 9648881832 | O17: 9831951621
B18: 자산총계 | C18: =SUM(C6,C12) -> 495561559165 | D18: =SUM(D6,D12) -> 498530915762 | E18: =SUM(E6,E12) -> 556371554306 | F18: =SUM(F6,F12) -> 587403557772 | J18: 기타비유동자산 | K18: 기타비유동자산 | L18: 4250190497 | M18: 3749916418 | N18: 4001965247 | O18: 4417134793
B19: 유동부채 | C19: =SUM(C20:C24) -> 299019546178 | D19: =SUM(D20:D24) -> 305664657223 | E19: =SUM(E20:E24) -> 318270087163 | F19: =SUM(F20:F24) -> 291619447443 | J19: 유형자산 | K19: 유형자산 | L19: 177579210031 | M19: 186123687777 | N19: 208778336913 | O19: 226445724446
B20: 매입채무 | C20: =SUMIF($J$7:$J$52,$B20,L$7:L$52) -> 102894859202 | D20: =SUMIF($J$7:$J$52,$B20,M$7:M$52) -> 102471380257 | E20: =SUMIF($J$7:$J$52,$B20,N$7:N$52) -> 124685230949 | F20: =SUMIF($J$7:$J$52,$B20,O$7:O$52) -> 116247704145 | J20: 무형자산 | K20: 무형자산 | L20: 28650256306 | M20: 25716603900 | N20: 27925711452 | O20: 29882456335
B21: 유동성차입금 | C21: =SUMIF($J$7:$J$52,$B21,L$7:L$52) -> 149311842286 | D21: =SUMIF($J$7:$J$52,$B21,M$7:M$52) -> 154506362734 | E21: =SUMIF($J$7:$J$52,$B21,N$7:N$52) -> 133507577291 | F21: =SUMIF($J$7:$J$52,$B21,O$7:O$52) -> 102543566496 | J21: 기타비유동자산 | K21: 이연법인세자산 | L21: 11200780294 | M21: 13544348945 | N21: 17401610864 | O21: 17899726201
B22: 기타유동채무 | C22: =SUMIF($J$7:$J$52,$B22,L$7:L$52) -> 32469137975 | D22: =SUMIF($J$7:$J$52,$B22,M$7:M$52) -> 36508298384 | E22: =SUMIF($J$7:$J$52,$B22,N$7:N$52) -> 48955326168 | F22: =SUMIF($J$7:$J$52,$B22,O$7:O$52) -> 60211618620 | K22: 비유동자산 합계 | L22: 234184304425 | M22: 234439865763 | N22: 270204201617 | O22: 291084772593
B23: 기타유동부채 | C23: =SUMIF($J$7:$J$52,$B23,L$7:L$52) -> 6242519371 | D23: =SUMIF($J$7:$J$52,$B23,M$7:M$52) -> 9107419707 | E23: =SUMIF($J$7:$J$52,$B23,N$7:N$52) -> 8294545054 | F23: =SUMIF($J$7:$J$52,$B23,O$7:O$52) -> 9853687570 | K23: 자산 총계 | L23: 495561559165 | M23: 498530915762 | N23: 556371554306 | O23: 587403557772
B24: 유동충당부채 | C24: =SUMIF($J$7:$J$52,$B24,L$7:L$52) -> 8101187344 | D24: =SUMIF($J$7:$J$52,$B24,M$7:M$52) -> 3071196141 | E24: =SUMIF($J$7:$J$52,$B24,N$7:N$52) -> 2827407701 | F24: =SUMIF($J$7:$J$52,$B24,O$7:O$52) -> 2762870612 | K24: 부채 및 자본
B25: 비유동부채 | C25: =SUM(C26:C30) -> 95886027877 | D25: =SUM(D26:D30) -> 81528111339 | E25: =SUM(E26:E30) -> 111898977025 | F25: =SUM(F26:F30) -> 161787435048 | K25: 부채
B26: 장기차입금 | C26: =SUMIF($J$7:$J$52,$B26,L$7:L$52) -> 87812640000 | D26: =SUMIF($J$7:$J$52,$B26,M$7:M$52) -> 73327683244 | E26: =SUMIF($J$7:$J$52,$B26,N$7:N$52) -> 104368114158 | F26: =SUMIF($J$7:$J$52,$B26,O$7:O$52) -> 151924564710 | K26: 유동부채
B27: 장기충당부채 | C27: =SUMIF($J$7:$J$52,$B27,L$7:L$52) -> 3694774530 | D27: =SUMIF($J$7:$J$52,$B27,M$7:M$52) -> 5648636272 | E27: =SUMIF($J$7:$J$52,$B27,N$7:N$52) -> 3807153549 | F27: =SUMIF($J$7:$J$52,$B27,O$7:O$52) -> 4184526164 | J27: 매입채무 | K27: 매입채무 | L27: 102894859202 | M27: 102471380257 | N27: 124685230949 | O27: 116247704145
B28: 확정급여부채 | C28: =SUMIF($J$7:$J$52,$B28,L$7:L$52) -> 2489595196 | D28: =SUMIF($J$7:$J$52,$B28,M$7:M$52) -> 1499045866 | E28: =SUMIF($J$7:$J$52,$B28,N$7:N$52) -> 1631293702 | F28: =SUMIF($J$7:$J$52,$B28,O$7:O$52) -> 3220547296 | J28: 기타유동채무 | K28: 기타지급채무 | L28: 32469137975 | M28: 36508298384 | N28: 48955326168 | O28: 60211618620
B29: 기타비유동채무 | C29: =SUMIF($J$7:$J$52,$B29,L$7:L$52) -> 153000000 | D29: =SUMIF($J$7:$J$52,$B29,M$7:M$52) -> 153500000 | E29: =SUMIF($J$7:$J$52,$B29,N$7:N$52) -> 203500000 | F29: =SUMIF($J$7:$J$52,$B29,O$7:O$52) -> 188000000 | J29: 기타유동부채 | K29: 기타금융부채 | L29: 248156907 | M29: 279060337 | N29: 851520002 | O29: 1461268342
B30: 기타비유동부채 | C30: =SUMIF($J$7:$J$52,$B30,L$7:L$52) -> 1736018151 | D30: =SUMIF($J$7:$J$52,$B30,M$7:M$52) -> 899245957 | E30: =SUMIF($J$7:$J$52,$B30,N$7:N$52) -> 1888915616 | F30: =SUMIF($J$7:$J$52,$B30,O$7:O$52) -> 2269796878 | J30: 유동성차입금 | K30: 차입금 | L30: 149311842286 | M30: 154506362734 | N30: 133507577291 | O30: 102543566496
B31: 부채총계 | C31: =SUM(C25,C19) -> 394905574055 | D31: =SUM(D25,D19) -> 387192768562 | E31: =SUM(E25,E19) -> 430169064188 | F31: =SUM(F25,F19) -> 453406882491 | J31: 기타유동부채 | K31: 기타유동부채 | L31: 5173904274 | M31: 7912481143 | N31: 5986319276 | O31: 6662345190
B32: 자본금 | C32: =SUMIF($J$7:$J$52,$B32,L$7:L$52) -> 49333300000 | D32: =SUMIF($J$7:$J$52,$B32,M$7:M$52) -> 49333300000 | E32: =SUMIF($J$7:$J$52,$B32,N$7:N$52) -> 49333300000 | F32: =SUMIF($J$7:$J$52,$B32,O$7:O$52) -> 49333300000 | J32: 기타유동부채 | K32: 당기법인세부채 | L32: 820458190 | M32: 915878227 | N32: 1456705776 | O32: 1730074038
B33: 이익잉여금 | C33: =SUMIF($J$7:$J$52,$B33,L$7:L$52) -> 48816890244 | D33: =SUMIF($J$7:$J$52,$B33,M$7:M$52) -> 60378173983 | E33: =SUMIF($J$7:$J$52,$B33,N$7:N$52) -> 77164223212 | F33: =SUMIF($J$7:$J$52,$B33,O$7:O$52) -> 84292873023 | J33: 유동충당부채 | K33: 충당부채 | L33: 8101187344 | M33: 3071196141 | N33: 2827407701 | O33: 2762870612
B34: 기타자본 | C34: =SUMIF($J$7:$J$52,$B34,L$7:L$52) -> 2505794866 | D34: =SUMIF($J$7:$J$52,$B34,M$7:M$52) -> 1626673217 | E34: =SUMIF($J$7:$J$52,$B34,N$7:N$52) -> -295033094 | F34: =SUMIF($J$7:$J$52,$B34,O$7:O$52) -> 370502258 | K34: 유동부채 합계 | L34: 299019546178 | M34: 305664657223 | N34: 318270087163 | O34: 291619447443
B35: 자본총계 | C35: =SUM(C32:C34) -> 100655985110 | D35: =SUM(D32:D34) -> 111338147200 | E35: =SUM(E32:E34) -> 126202490118 | F35: =SUM(F32:F34) -> 133996675281 | K35: 비유동부채
B36: 자본과부채총계 | C36: =C31+C35 -> 495561559165 | D36: =D31+D35 -> 498530915762 | E36: =E31+E35 -> 556371554306 | F36: =F31+F35 -> 587403557772 | J36: 기타비유동채무 | K36: 기타지급채무 | L36: 153000000 | M36: 153500000 | N36: 203500000 | O36: 188000000
B37: Source : 감사보고서 | J37: 기타비유동부채 | K37: 기타금융부채 | L37: 21799188 | M37: 2512273 | N37: 980424849 | O37: 1467995424
B38: 총차입금 | C38: =C21+C26 -> 237124482286 | D38: =D21+D26 -> 227834045978 | E38: =E21+E26 -> 237875691449 | F38: =F21+F26 -> 254468131206 | J38: 장기차입금 | K38: 차입금 | L38: 87812640000 | M38: 73327683244 | N38: 104368114158 | O38: 151924564710
B39: 순차입금 | C39: =C38-C7 -> 231579951935 | D39: =D38-D7 -> 223591853515 | E39: =E38-E7 -> 233030091458 | F39: =F38-F7 -> 250223796799 | J39: 기타비유동부채 | K39: 기타비유동부채 | L39: 1250836455 | M39: 491273989 | N39: 908490767 | O39: 801801454
C40: =C6-L13 -> 0 | D40: =D6-M13 -> 0 | E40: =E6-N13 -> 0 | F40: =F6-O13 -> 0 | J40: 확정급여부채 | K40: 확정급여부채 | L40: 2489595196 | M40: 1499045866 | N40: 1631293702 | O40: 3220547296
C41: =C12-L22 -> 0 | D41: =D12-M22 -> 0 | E41: =E12-N22 -> 0 | F41: =F12-O22 -> 0 | J41: 기타비유동부채 | K41: 이연법인세부채 | L41: 463382508 | M41: 405459695 | N41: 0 | O41: 0
C42: =C18-L23 -> 0 | D42: =D18-M23 -> 0 | E42: =E18-N23 -> 0 | F42: =F18-O23 -> 0 | J42: 장기충당부채 | K42: 충당부채 | L42: 3694774530 | M42: 5648636272 | N42: 3807153549 | O42: 4184526164
C43: =C19-L34 -> 0 | D43: =D19-M34 -> 0 | E43: =E19-N34 -> 0 | F43: =F19-O34 -> 0 | K43: 비유동부채 합계 | L43: 95886027877 | M43: 81528111339 | N43: 111898977025 | O43: 161787435048
C44: =C25-L43 -> 0 | D44: =D25-M43 -> 0 | E44: =E25-N43 -> 0 | F44: =F25-O43 -> 0 | K44: 부채 총계 | L44: 394905574055 | M44: 387192768562 | N44: 430169064188 | O44: 453406882491
C45: =C31-L44 -> 0 | D45: =D31-M44 -> 0 | E45: =E31-N44 -> 0 | F45: =F31-O44 -> 0 | K45: 자본
C46: =C35-L50 -> 0 | D46: =D35-M50 -> 0 | E46: =E35-N50 -> 0 | F46: =F35-O50 -> 0 | J46: 자본금 | K46: 자본금 | L46: 49333300000 | M46: 49333300000 | N46: 49333300000 | O46: 49333300000
C47: =C36-L52 -> 0 | D47: =D36-M52 -> 0 | E47: =E36-N52 -> 0 | F47: =F36-O52 -> 0 | J47: 기타자본 | K47: 기타불입자본 | L47: -147000000 | M47: -147000000 | N47: -147000000 | O47: 0
J48: 기타자본 | K48: 기타포괄손익누계액 | L48: 2652794866 | M48: 1773673217 | N48: -148033094 | O48: 370502258
J49: 이익잉여금 | K49: 이익잉여금 | L49: 48816890244 | M49: 60378173983 | N49: 77164223212 | O49: 84292873023
K50: 자본 총계 | L50: 100655985110 | M50: 111338147200 | N50: 126202490118 | O50: 133996675281
K51: 비지배주주지분 | L51: - | M51: - | N51: - | O51: -
K52: 부채 및 자본의 총계 | L52: 495561559165 | M52: 498530915762 | N52: 556371554306 | O52: 587403557772
K54: 총 차입금 | L54: =L30+L38 -> 237124482286 | M54: =M30+M38 -> 227834045978 | N54: =N30+N38 -> 237875691449 | O54: =O30+O38 -> 254468131206
K55: 순차입금 | L55: =L54-L7 -> 231579951935 | M55: =M54-M7 -> 223591853515 | N55: =N54-N7 -> 233030091458 | O55: =O54-O7 -> 250223796799

Sheet IS(연결)
J1: >>PL | R1: >>주석 | S1: 21. 매출 및 매출원가
B3: 손익계산서(연결) | O3: 제43기 반기 | P3: 제42기 반기 | S3: 매출 및 매출원가의 구성내역은 다음과 같습니다.
C4: 2012년 | D4: 2013년 | E4: 2014년 | F4: 2015년 | G4: 2014년 | L4: 제 40 기 | M4: 제 41 기 | N4: 제42기 | O4: 누적 | P4: 누적
B5: 백만원 | C5: 12개월 | D5: 12개월 | E5: 12개월 | F5: 6개월 | G5: 6개월 | K5: 매출액 | L5: 630029985686 | M5: 663544930549 | N5: 715524023057 | O5: 395994844226 | P5: 350888124224 | U5: (단위: 천원) | W5: 제43기 반기 | X5: 제42기 반기
B6: 매출액 | C6: =L5 -> 630029985686 | D6: =M5 -> 663544930549 | E6: =N5 -> 715524023057 | F6: =O5 -> 395994844226 | G6: =P5 -> 350888124224 | K6: 매출원가 | L6: -553066763867 | M6: -579821491067 | N6: -622518118746 | O6: -348423501816 | P6: -304107584364 | S6: 구 분 | T6: 40기 | U6: 41기 | V6: 42기 | W6: 누적 | X6: 누적
B7: 제품 | C7: =T8*1000 -> 615876336000 | D7: =U8*1000 -> 635518071000 | E7: =V8*1000 -> 678355903000 | F7: =W8*1000 -> 380479517000 | G7: =X8*1000 -> 335150823000 | K7: 매출총이익 | L7: 76963221819 | M7: 83723439482 | N7: 93005904311 | O7: 47571342410 | P7: 46780539860 | T7: 매 출 | U7: 매 출 | V7: 매 출 | W7: 매출 | X7: 매출
B8: 상품 | C8: =T9*1000 -> 10383056000 | D8: =U9*1000 -> 15210139000 | E8: =V9*1000 -> 18115732000 | F8: =W9*1000 -> 8735931000 | G8: =X9*1000 -> 8866811000 | K8: 판매비와 관리비 | L8: -58366193312 | M8: -56020716937 | N8: -62304729229 | O8: -33278007890 | P8: -31791284647 | S8: 제품 | T8: 615876336 | U8: 635518071 | V8: 678355903 | W8: 380479517 | X8: 335150823
B9: 기타 | C9: =T10*1000 -> 3770594000 | D9: =U10*1000 -> 12816721000 | E9: =V10*1000 -> 19052388000 | F9: =W10*1000 -> 6779396000 | G9: =X10*1000 -> 6870490000 | K9: 영업이익 | L9: 18597028507 | M9: 27702722545 | N9: 30701175082 | O9: 14293334520 | P9: 14989255213 | S9: 상품 | T9: 10383056 | U9: 15210139 | V9: 18115732 | W9: 8735931 | X9: 8866811
B10: 매출원가 | C10: =-L6 -> 553066763867 | D10: =-M6 -> 579821491067 | E10: =-N6 -> 622518118746 | F10: =-O6 -> 348423501816 | G10: =-P6 -> 304107584364 | K10: 기타수익 | L10: 13239968936 | M10: 14230268654 | N10: 10541257569 | O10: 6217643451 | P10: 4435845918 | S10: 기타 | T10: 3770594 | U10: 12816721 | V10: 19052388 | W10: 6779396 | X10: 6870490
B11: 매출총이익 | C11: =L7 -> 76963221819 | D11: =M7 -> 83723439482 | E11: =N7 -> 93005904311 | F11: =O7 -> 47571342410 | G11: =P7 -> 46780539860 | K11: 기타비용 | L11: -13880117986 | M11: -17945651821 | N11: -11258377098 | O11: -5298808385 | P11: -5594656175 | S11: 합 계 | T11: 630029986 | U11: 663544931 | V11: 715524023 | W11: 395994844 | X11: 350888124
B12: 매출총이익률(%) | C12: =C11/C6 -> 0.12215803 | D12: =D11/D6 -> 0.12617599 | E12: =E11/E6 -> 0.12998292 | F12: =F11/F6 -> 0.12013122 | G12: =G11/G6 -> 0.13332039 | K12: 금융수익 | L12: 1239939426 | M12: 1102821813 | N12: 728115463 | O12: 383069856 | P12: 514083633 | T12: 매 출 원 가 | U12: 매 출 원 가 | V12: 매 출 원 가 | W12: 매 출 원 가 | X12: 매 출 원 가
B13: 판매관리비 | C13: =-L8 -> 58366193312 | D13: =-M8 -> 56020716937 | E13: =-N8 -> 62304729229 | F13: =-O8 -> 33278007890 | G13: =-P8 -> 31791284647 | K13: 금융원가 | L13: -16492753645 | M13: -12048493747 | N13: -10452219619 | O13: -4711750873 | P13: -5375889067 | S13: 제품 | T13: 538337008 | U13: 556201802 | V13: 593953652 | W13: 335936674 | X13: 291895647
B14: 인건비 | C14: =SUMIF($R$41:$R$61,$B14,T$41:T$61)*1000 -> 17006439000 | D14: =SUMIF($R$41:$R$61,$B14,U$41:U$61)*1000 -> 18778456000 | E14: =SUMIF($R$41:$R$61,$B14,V$41:V$61)*1000 -> 21736145000 | F14: =SUMIF($R$41:$R$61,$B14,W$41:W$61)*1000 -> 12219122000 | G14: =SUMIF($R$41:$R$61,$B14,X$41:X$61)*1000 -> 11382101000 | K14: 기타영업외수익 | L14: 2896217661 | M14: 3964675848 | N14: 2003977004 | O14: 955193324 | P14: 2035683770 | S14: 상품 | T14: 9881621 | U14: 13364215 | V14: 15892892 | W14: 7645948 | X14: 7744846
B15: 감가상각비 | C15: =SUMIF($R$41:$R$61,$B15,T$41:T$61)*1000 -> 1355553000 | D15: =SUMIF($R$41:$R$61,$B15,U$41:U$61)*1000 -> 1166656000 | E15: =SUMIF($R$41:$R$61,$B15,V$41:V$61)*1000 -> 1109796000 | F15: =SUMIF($R$41:$R$61,$B15,W$41:W$61)*1000 -> 594707000 | G15: =SUMIF($R$41:$R$61,$B15,X$41:X$61)*1000 -> 613767000 | K15: 기타영업외비용 | L15: -1428273667 | M15: -4472718136 | N15: -3126126383 | O15: -2067508256 | P15: -1275481124 | S15: 기타 | T15: 4848135 | U15: 10255474 | V15: 12671575 | W15: 4840880 | X15: 4467091
B16: 무형자산상각비 | C16: =SUMIF($R$41:$R$61,$B16,T$41:T$61)*1000 -> 2614854000 | D16: =SUMIF($R$41:$R$61,$B16,U$41:U$61)*1000 -> 2851846000 | E16: =SUMIF($R$41:$R$61,$B16,V$41:V$61)*1000 -> 3071807000 | F16: =SUMIF($R$41:$R$61,$B16,W$41:W$61)*1000 -> 1283485000 | G16: =SUMIF($R$41:$R$61,$B16,X$41:X$61)*1000 -> 1514298000 | K16: 법인세비용차감전순이익 | L16: 4172009232 | M16: 12533625156 | N16: 19137802018 | O16: 9771173637 | P16: 9728842168 | S16: 합 계 | T16: 553066764 | U16: 579821491 | V16: 622518119 | W16: 348423502 | X16: 304107584
B17: 판매보증비 | C17: =SUMIF($R$41:$R$61,$B17,T$41:T$61)*1000 -> 11958237000 | D17: =SUMIF($R$41:$R$61,$B17,U$41:U$61)*1000 -> 8478016000 | E17: =SUMIF($R$41:$R$61,$B17,V$41:V$61)*1000 -> 8009624000 | F17: =SUMIF($R$41:$R$61,$B17,W$41:W$61)*1000 -> 3609776000 | G17: =SUMIF($R$41:$R$61,$B17,X$41:X$61)*1000 -> 5380269000 | K17: 법인세비용 | L17: 1893814540 | M17: 438342545 | N17: 1186573100 | O17: 2495523826 | P17: 491120397
B18: 지급수수료 | C18: =SUMIF($R$41:$R$61,$B18,T$41:T$61)*1000 -> 6809576000 | D18: =SUMIF($R$41:$R$61,$B18,U$41:U$61)*1000 -> 6711804000 | E18: =SUMIF($R$41:$R$61,$B18,V$41:V$61)*1000 -> 6122827000 | F18: =SUMIF($R$41:$R$61,$B18,W$41:W$61)*1000 -> 3230879000 | G18: =SUMIF($R$41:$R$61,$B18,X$41:X$61)*1000 -> 2613853000 | K18: 당기순이익(손실) | L18: 2278194692 | M18: 12095282611 | N18: 17951228918 | O18: 7275649811 | P18: 9237721771 | S18: 22. 영업이익
B19: 경상개발비 | C19: =SUMIF($R$41:$R$61,$B19,T$41:T$61)*1000 -> 628511000 | D19: =SUMIF($R$41:$R$61,$B19,U$41:U$61)*1000 -> 957991000 | E19: =SUMIF($R$41:$R$61,$B19,V$41:V$61)*1000 -> 1873905000 | F19: =SUMIF($R$41:$R$61,$B19,W$41:W$61)*1000 -> 1357388000 | G19: =SUMIF($R$41:$R$61,$B19,X$41:X$61)*1000 -> 497528000 | K19: 지배기업소유주지분 | L19: 2278194692 | M19: 12095282611 | N19: 17951228918 | O19: 7275649811 | P19: 9237721771
B20: 세금과공과 | C20: =SUMIF($R$41:$R$61,$B20,T$41:T$61)*1000 -> 1700694000 | D20: =SUMIF($R$41:$R$61,$B20,U$41:U$61)*1000 -> 1513848000 | E20: =SUMIF($R$41:$R$61,$B20,V$41:V$61)*1000 -> 1476984000 | F20: =SUMIF($R$41:$R$61,$B20,W$41:W$61)*1000 -> 1141027000 | G20: =SUMIF($R$41:$R$61,$B20,X$41:X$61)*1000 -> 713797000 | K20: 비지배지분 | L20: - | M20: - | N20: - | O20: - | P20: - | S20: 22-1 종업원급여의 내역은 다음과 같습니다.
B21: 임차료 | C21: =SUMIF($R$41:$R$61,$B21,T$41:T$61)*1000 -> 2303696000 | D21: =SUMIF($R$41:$R$61,$B21,U$41:U$61)*1000 -> 2175444000 | E21: =SUMIF($R$41:$R$61,$B21,V$41:V$61)*1000 -> 1983554000 | F21: =SUMIF($R$41:$R$61,$B21,W$41:W$61)*1000 -> 1114943000 | G21: =SUMIF($R$41:$R$61,$B21,X$41:X$61)*1000 -> 973429000 | K21: 기타포괄손익
B22: 여비교통비 | C22: =SUMIF($R$41:$R$61,$B22,T$41:T$61)*1000 -> 1440485000 | D22: =SUMIF($R$41:$R$61,$B22,U$41:U$61)*1000 -> 1334925000 | E22: =SUMIF($R$41:$R$61,$B22,V$41:V$61)*1000 -> 1716085000 | F22: =SUMIF($R$41:$R$61,$B22,W$41:W$61)*1000 -> 899655000 | G22: =SUMIF($R$41:$R$61,$B22,X$41:X$61)*1000 -> 929305000 | K22: 후속적으로 당기손익으로 | S22: (단위: 천원) | W22: 제43기 반기 | X22: 제42기 반기
B23: 기타비용 | C23: =SUMIF($R$41:$R$61,$B23,T$41:T$61)*1000 -> 12548148000 | D23: =SUMIF($R$41:$R$61,$B23,U$41:U$61)*1000 -> 12051731000 | E23: =SUMIF($R$41:$R$61,$B23,V$41:V$61)*1000 -> 15204002000 | F23: =SUMIF($R$41:$R$61,$B23,W$41:W$61)*1000 -> 7827026000 | G23: =SUMIF($R$41:$R$61,$B23,X$41:X$61)*1000 -> 7172939000 | K23: 재분류될 수 있는 항목 | S23: 구 분 | T23: 40기 | U23: 41기 | V23: 42기 | W23: 누적 | X23: 누적
B24: 영업이익 | C24: =L9 -> 18597028507 | D24: =M9 -> 27702722545 | E24: =N9 -> 30701175082 | F24: =O9 -> 14293334520 | G24: =P9 -> 14989255213 | K24: 매도가능금융자산평가 | L24: 6463649 | M24: 47898287 | N24: 34134329 | O24: 494535 | P24: 25600325 | S24: 급여 | T24: 61154623 | U24: 67282344 | V24: 73032007 | W24: 42,847,588 | X24: 37496312
B25: 영업이익(%) | C25: =C24/C6 -> 0.029517688 | D25: =D24/D6 -> 0.041749581 | E25: =E24/E6 -> 0.04290726 | F25: =F24/F6 -> 0.036094749 | G25: =G24/G6 -> 0.042718047 | K25: 손익 | S25: 퇴직급여 | T25: 2825870 | U25: 3124638 | V25: 3781544 | W25: 2,059,328 | X25: 1871434
B26: 금융수익 | C26: =L12 -> 1239939426 | D26: =M12 -> 1102821813 | E26: =N12 -> 728115463 | F26: =O12 -> 383069856 | G26: =P12 -> 514083633 | K26: 파생상품평가손익 | L26: 4495184394 | M26: 1029089110 | N26: -3126264406 | O26: -1021354171 | P26: 2550811422 | S26: 복리후생비 | T26: 6985488 | U26: 8160878 | V26: 8921195 | W26: 5,077,360 | X26: 4453121
B27: 금융비용 | C27: =-L13 -> 16492753645 | D27: =-M13 -> 12048493747 | E27: =-N13 -> 10452219619 | F27: =-O13 -> 4711750873 | G27: =-P13 -> 5375889067 | K27: 해외사업환산손익 | L27: -2204769985 | M27: -1956109046 | N27: 1170423766 | O27: 1539394988 | P27: -3277445051 | S27: 합 계 | T27: 70965981 | U27: 78567860 | V27: 85734746 | W27: 49,984,276 | X27: 43820867
B28: 기타수익 | C28: =L10+L14 -> 16136186597 | D28: =M10+M14 -> 18194944502 | E28: =N10+N14 -> 12545234573 | F28: =O10+O14 -> 7172836775 | G28: =P10+P14 -> 6471529688 | H28: 기타수익+기타영업외수익 | K28: 후속적으로 당기손익으로
B29: 기타비용 | C29: =-(L11+L15) -> 15308391653 | D29: =-(M11+M15) -> 22418369957 | E29: =-(N11+N15) -> 14384503481 | F29: =-(O11+O15) -> 7366316641 | G29: =-(P11+P15) -> 6870137299 | H29: 기타비용+기타영업외비용 | K29: 재분류되지 않는 항목 | S29: 22-2 감가상각비와 무형자산상각비의 내역은 다음과 같습니다.
B30: 법인세비용 | C30: =L17 -> 1893814540 | D30: =M17 -> 438342545 | E30: =N17 -> 1186573100 | F30: =O17 -> 2495523826 | G30: =P17 -> 491120397 | K30: 순확정급여부채의 재측정 | L30: -743596242 | M30: -533998872 | N30: -1165179689 | O30: - | P30: -
B31: 당기순이익 | C31: =L18 -> 2278194692 | D31: =M18 -> 12095282611 | E31: =N18 -> 17951228918 | F31: =O18 -> 7275649811 | G31: =P18 -> 9237721771 | K31: 요소 | S31: (단위: 천원) | W31: 제43기 반기 | X31: 제42기 반기
B32: 당기순이익률(%) | C32: =C31/C6 -> 0.0036160099 | D32: =D31/D6 -> 0.01822828 | E32: =E31/E6 -> 0.025088227 | F32: =F31/F6 -> 0.018373092 | G32: =G31/G6 -> 0.026326687 | K32: 총포괄손익 | L32: 3831476508 | M32: 10682162090 | N32: 14864342918 | O32: 7794185163 | P32: 8536688467 | S32: 구 분 | T32: 40기 | U32: 41기 | V32: 42기 | W32: 누적 | X32: 누적
B33: EBITDA | C33: =C24+C39 -> 54172121980 | D33: =D24+D39 -> 65010014708 | E33: =E24+E39 -> 69121406676 | F33: =F24+F39 -> 34728224867 | G33: =G24+G39 -> 34301816293 | K33: 총포괄손익의 귀속: | S33: 유형자산감가상각비 | T33: 27615340 | U33: 29666486 | V33: 31190193 | W33: 16973713 | X33: 15696912
B34: EBITDA(%) | C34: =C33/C6 -> 0.085983403 | D34: =D33/D6 -> 0.097973795 | E34: =E33/E6 -> 0.096602496 | F34: =F33/F6 -> 0.087698679 | G34: =G33/G6 -> 0.097757131 | K34: 지배기업소유주지분 | L34: 3831476508 | M34: 10682162090 | N34: 14864342918 | O34: 7794185163 | P34: 8536688467 | S34: 무형자산상각비 | T34: 7959753 | U34: 7640807 | V34: 7230038 | W34: 3461177 | X34: 3615649
B35: Source : 감사보고서 | K35: 비지배지분 | L35: - | M35: - | N35: - | O35: - | P35: - | S35: 합 계 | T35: 35575093 | U35: 37307293 | V35: 38420231 | W35: 20434890 | X35: 19312561
K36: 주당손익
B37: 감가상각비 | C37: ='CF(연결)'!B14 -> 27615340495 | D37: ='CF(연결)'!C14 -> 29666485532 | E37: ='CF(연결)'!D14 -> 31190193327 | F37: ='CF(연결)'!E14 -> 16973712924 | G37: ='CF(연결)'!F14 -> 15696912464 | K37: 기본주당손익 | L37: 231 | M37: 1226 | N37: 1819 | O37: 737 | P37: 936 | S37: 22-3 판매비와관리비의 내역은 다음과 같습니다.
B38: 무형자산상각비 | C38: ='CF(연결)'!B15 -> 7959752978 | D38: ='CF(연결)'!C15 -> 7640806631 | E38: ='CF(연결)'!D15 -> 7230038267 | F38: ='CF(연결)'!E15 -> 3461177423 | G38: ='CF(연결)'!F15 -> 3615648616
B39: D&A | C39: =SUM(C37:C38) -> 35575093473 | D39: =SUM(D37:D38) -> 37307292163 | E39: =SUM(E37:E38) -> 38420231594 | F39: =SUM(F37:F38) -> 20434890347 | G39: =SUM(G37:G38) -> 19312561080 | S39: (단위: 천원) | W39: 제43기 반기 | X39: 제42기 반기
C40: =C39-T35*1000 -> 473 | D40: =D39-U35*1000 -> -837 | E40: =E39-V35*1000 -> 594 | F40: =F39-W35*1000 -> 347 | G40: =G39-X35*1000 -> 80 | S40: 구 분 | T40: 40기 | U40: 41기 | V40: 42기 | W40: 누적 | X40: 누적
R41: 인건비 | S41: 급여 | T41: 14133305 | U41: 15847320 | V41: 18094369 | W41: 10132688 | X41: 9568584
C42: =SUM(C7:C9)-C6 -> 314 | D42: =SUM(D7:D9)-D6 -> 451 | E42: =SUM(E7:E9)-E6 -> -57 | F42: =SUM(F7:F9)-F6 -> -226 | G42: =SUM(G7:G9)-G6 -> -224 | R42: 인건비 | S42: 퇴직급여 | T42: 610852 | U42: 635051 | V42: 866836 | W42: 469070 | X42: 431872
C43: =C6-C10-C11 -> 0 | D43: =D6-D10-D11 -> 0 | E43: =E6-E10-E11 -> 0 | F43: =F6-F10-F11 -> 0 | G43: =G6-G10-G11 -> 0 | R43: 기타비용 | S43: 운반비 | T43: 9081078 | U43: 8832738 | V43: 11800511 | W43: 5630024 | X43: 5576866
C44: =SUM(C14:C23)-C13 -> -312 | D44: =SUM(D14:D23)-D13 -> 63 | E44: =SUM(E14:E23)-E13 -> -229 | F44: =SUM(F14:F23)-F13 -> 110 | G44: =SUM(G14:G23)-G13 -> 1353 | R44: 감가상각비 | S44: 감가상각비 | T44: 1355553 | U44: 1166656 | V44: 1109796 | W44: 594707 | X44: 613767
C45: =C11-C13-C24 -> 0 | D45: =D11-D13-D24 -> 0 | E45: =E11-E13-E24 -> 0 | F45: =F11-F13-F24 -> 0 | G45: =G11-G13-G24 -> 0 | R45: 기타비용 | S45: 소모품비 | T45: 301283 | U45: 264622 | V45: 282962 | W45: 185920 | X45: 111807
C46: =C24+C26-C27+C28-C29-C30-C31 -> 0 | D46: =D24+D26-D27+D28-D29-D30-D31 -> 0 | E46: =E24+E26-E27+E28-E29-E30-E31 -> 0 | F46: =F24+F26-F27+F28-F29-F30-F31 -> 0 | G46: =G24+G26-G27+G28-G29-G30-G31 -> 0 | R46: 세금과공과 | S46: 세금과공과 | T46: 1700694 | U46: 1513848 | V46: 1476984 | W46: 1141027 | X46: 713797
R47: 임차료 | S47: 임차료 | T47: 2303696 | U47: 2175444 | V47: 1983554 | W47: 1114943 | X47: 973429
R48: 기타비용 | S48: 보험료 | T48: 245587 | U48: 303879 | V48: 357399 | W48: 185614 | X48: 169984
R49: 인건비 | S49: 복리후생비 | T49: 2262282 | U49: 2296085 | V49: 2774940 | W49: 1617364 | X49: 1381645
R50: 여비교통비 | S50: 여비교통비 | T50: 1440485 | U50: 1334925 | V50: 1716085 | W50: 899655 | X50: 929305
R51: 기타비용 | S51: 통신비 | T51: 383194 | U51: 447737 | V51: 277704 | W51: 135653 | X51: 148314
R52: 지급수수료 | S52: 지급수수료 | T52: 6809576 | U52: 6711804 | V52: 6122827 | W52: 3230879 | X52: 2613853
R53: 기타비용 | S53: 접대비 | T53: 531273 | U53: 686345 | V53: 817734 | W53: 435907 | X53: 393290
R54: 기타비용 | S54: 교육훈련비 | T54: 395488 | U54: 395904 | V54: 462492 | W54: 208063 | X54: 175823
R55: 기타비용 | S55: 차량유지비 | T55: 422158 | U55: 414541 | V55: 426397 | W55: 161547 | X55: 222217
R56: 경상개발비 | S56: 경상개발비 | T56: 628511 | U56: 957991 | V56: 1873905 | W56: 1357388 | X56: 497528
R57: 기타비용 | S57: 광고선전비 | T57: 583713 | U57: 117596 | V57: 270193 | W57: 145828 | X57: 130010
R58: 기타비용 | S58: 대손상각비 | T58: 184177 | U58: 169658 | V58: -6745 | W58: 474167 | X58: -18090
... R61: 기타비용 | S61: 기타판관비 | T61: 420197 | U61: 418711 | V61: 515355 | W61: 264303 | X61: 262718
S62: 합 계 | T62: 58366193 | U62: 56020717 | V62: 62304729 | W62: 33278008 | X62: 31791286
S64: 23. 조정영업이익
S66: 23-1 조정영업이익
S68: 손익계산서의 영업이익에 포함된 항목 외에 연결기업의 영업성과를 반영하는 항목을추가하여 산정한 연결기업이 자체 분류한 조정영업이익의 산정내역은 다음과 같습니다.
S71: (단위: 천원) | W71: 제43기 반기 | X71: 제42기 반기
S72: 구 분 | T72: 40기 | U72: 41기 | V72: 42기 | W72: 누적 | X72: 누적
S73: 영업이익 | T73: 18597029 | U73: 27702723 | V73: 30701175 | W73: 14293335 | X73: 14989255
S74: 기타수익 | T74: 13239969 | U74: 14230269 | V74: 10541258 | W74: 6217643 | X74: 4435846
S75: 기타비용 | T75: -13880118 | U75: -17945652 | V75: -11258377 | W75: -5298808 | X75: -5594656
S76: 조정영업이익 | T76: 17956879 | U76: 23987340 | V76: 29984056 | W76: 15212170 | X76: 13830445
S78: 23-2 기타수익
S80: 기타수익의 내역은 다음과 같습니다.
S82: (단위: 천원) | W82: 제43기 반기 | X82: 제42기 반기
S83: 구 분 | T83: 40기 | U83: 41기 | V83: 42기 | W83: 누적 | X83: 누적
S84: 임대료수익 | T84: 173232 | U84: 180631 | V84: 129088 | W84: 59707 | X84: 66251
S85: 외환차익 | T85: 3231416 | U85: 5755236 | V85: 4702005 | W85: 2241192 | X85: 2162596
S86: 외화환산이익 | T86: 3647012 | U86: 5561474 | V86: 1970346 | W86: 2054552 | X86: 774400
S87: 유형자산처분이익 | T87: 402605 | U87: 555074 | V87: 468508 | W87: 294728 | X87: 73665
S88: 무형자산처분이익 | T88: 71528 | U88: 117216 | V88: 3272 | W88: 1514 | X88: 3272
S89: 부산물처분이익 | T89: 1055827 | U89: 885892 | V89: 744734 | W89: 390089 | X89: 411446
S90: 기타의대손충당금환입 | T90: 0 | U90: 0 | V90: 522150 | W90: 0 | X90: 494955
S91: 기타 | T91: 4658349 | U91: 1174745 | V91: 2001155 | W91: 1175861 | X91: 449261
S92: 합 계 | T92: 13239969 | U92: 14230268 | V92: 10541258 | W92: 6217643 | X92: 4435846
S94: 23-3 기타비용
S96: 기타비용의 내역은 다음과 같습니다.
S98: (단위: 천원) | W98: 제43기 반기 | X98: 제42기 반기
S99: 구 분 | T99: 40기 | U99: 41기 | V99: 42기 | W99: 누적 | X99: 누적
S100: 외환차손 | T100: 5448035 | U100: 6964290 | V100: 4527327 | W100: 2909408 | X100: 2773212
S101: 외화환산손실 | T101: 4971114 | U101: 5676171 | V101: 1953664 | W101: 398453 | X101: 1274095
S102: 유형자산처분손실 | T102: 366733 | U102: 1432123 | V102: 837207 | W102: 31974 | X102: 319425
S103: 유형자산폐기손실 | T103: 0 | U103: 0 | V103: 0 | W103: 48652 | X103: 250
S104: 유형자산손상차손 | T104: 9882 | U104: 0 | V104: 185326 | W104: 47259 | X104: 116036
S105: 무형자산손상차손 | T105: 1304314 | U105: 0 | V105: 530089 | W105: 4065 | X105: 434335
S106: 기타의대손상각비 | T106: 336662 | U106: 1473827 | V106: 0 | W106: 0 | X106: 0
S107: 기타 | T107: 1443378 | U107: 2399240 | V107: 3224764 | W107: 1858997 | X107: 677303
S108: 합 계 | T108: 13880118 | U108: 17945651 | V108: 11258377 | W108: 5298808 | X108: 5594656
S109: >>유형자산처분손실 41기 금액
T110: 2013년보고서 | U110: 2014년보고서
S111: 유형자산처분손실 | T111: 1340326 | U111: 1432123
S112: 유형자산손상차손 | T112: 91797 | U112: 0
T113: =SUM(T111:T112) -> 1432123 | U113: =SUM(U111:U112) -> 1432123
S114: 24. 기타영업외손익
...

Sheet BS(별도)
B3: 재무상태표(별도)
C4: 2012년 | D4: 2013년 | E4: 2014년 | F4: 2015년 | K4: 제 40(전) 기 | L4: 제 41 기 | M4: 제42기 | N4: 제43기 반기
B5: 백만원 | C5: 12월 31일 | D5: 12월 31일 | E5: 12월 31일 | F5: 6월 30일 | J5: 자산
B6: 유동자산 | C6: =SUM(C7:C11) -> 211238127888 | D6: =SUM(D7:D11) -> 199622976692 | E6: =SUM(E7:E11) -> 205592191931 | F6: =SUM(F7:F11) -> 220246389494 | J6: 유동자산
B7: 현금및현금성자산 | C7: =SUMIF($I$7:$I$52,$B7,K$7:K$52) -> 1184687591 | D7: =SUMIF($I$7:$I$52,$B7,L$7:L$52) -> 1087185146 | E7: =SUMIF($I$7:$I$52,$B7,M$7:M$52) -> 417039167 | F7: =SUMIF($I$7:$I$52,$B7,N$7:N$52) -> 1461974937 | I7: 현금및현금성자산 | J7: 현금및현금성자산 | K7: 1184687591 | L7: 1087185146 | M7: 417039167 | N7: 1461974937
B8: 매출채권 | C8: =SUMIF($I$7:$I$52,$B8,K$7:K$52) -> 120379543299 | D8: =SUMIF($I$7:$I$52,$B8,L$7:L$52) -> 102474614868 | E8: =SUMIF($I$7:$I$52,$B8,M$7:M$52) -> 115353171617 | F8: =SUMIF($I$7:$I$52,$B8,N$7:N$52) -> 130106672965 | I8: 매출채권 | J8: 매출채권 | K8: 120379543299 | L8: 102474614868 | M8: 115353171617 | N8: 130106672965
B9: 기타유동채권 | C9: =SUMIF($I$7:$I$52,$B9,K$7:K$52) -> 14234388283 | D9: =SUMIF($I$7:$I$52,$B9,L$7:L$52) -> 14336060255 | E9: =SUMIF($I$7:$I$52,$B9,M$7:M$52) -> 16867836496 | F9: =SUMIF($I$7:$I$52,$B9,N$7:N$52) -> 11401302774 | I9: 기타유동채권 | J9: 기타수취채권 | K9: 14234388283 | L9: 14336060255 | M9: 16867836496 | N9: 11401302774
B10: 재고자산 | C10: =SUMIF($I$7:$I$52,$B10,K$7:K$52) -> 55691710382 | D10: =SUMIF($I$7:$I$52,$B10,L$7:L$52) -> 51320265478 | E10: =SUMIF($I$7:$I$52,$B10,M$7:M$52) -> 52799613163 | F10: =SUMIF($I$7:$I$52,$B10,N$7:N$52) -> 53472768284 | I10: 기타자산 | J10: 기타금융자산 | K10: 2740918526 | L10: 11857306080 | M10: 1943290771 | N10: 1697906040
B11: 기타자산 | C11: =SUMIF($I$7:$I$52,$B11,K$7:K$52) -> 19747798333 | D11: =SUMIF($I$7:$I$52,$B11,L$7:L$52) -> 30404850945 | E11: =SUMIF($I$7:$I$52,$B11,M$7:M$52) -> 20154531488 | F11: =SUMIF($I$7:$I$52,$B11,N$7:N$52) -> 23803670534 | I11: 기타자산 | J11: 기타유동자산 | K11: 17006879807 | L11: 18547544865 | M11: 18211240717 | N11: 22105764494
B12: 비유동자산 | C12: =SUM(C13:C17) -> 225811386041 | D12: =SUM(D13:D17) -> 234460843739 | E12: =SUM(E13:E17) -> 252216100401 | F12: =SUM(F13:F17) -> 264696937078 | I12: 재고자산 | J12: 재고자산 | K12: 55691710382 | L12: 51320265478 | M12: 52799613163 | N12: 53472768284
B13: 유형자산 | C13: =SUMIF($I$7:$I$52,$B13,K$7:K$52) -> 134926702287 | D13: =SUMIF($I$7:$I$52,$B13,L$7:L$52) -> 136471693354 | E13: =SUMIF($I$7:$I$52,$B13,M$7:M$52) -> 142852502572 | F13: =SUMIF($I$7:$I$52,$B13,N$7:N$52) -> 152962175674 | J13: 유동자산 합계 | K13: 211238127888 | L13: 199622976692 | M13: 205592191931 | N13: 220246389494
B14: 무형자산 | C14: =SUMIF($I$7:$I$52,$B14,K$7:K$52) -> 25547393194 | D14: =SUMIF($I$7:$I$52,$B14,L$7:L$52) -> 22464615704 | E14: =SUMIF($I$7:$I$52,$B14,M$7:M$52) -> 24698243277 | F14: =SUMIF($I$7:$I$52,$B14,N$7:N$52) -> 26346040695 | J14: 비유동자산
B15: 종속/관계기업투자 | C15: =SUMIF($I$7:$I$52,$B15,K$7:K$52) -> 42802883132 | D15: =SUMIF($I$7:$I$52,$B15,L$7:L$52) -> 59677570199 | E15: =SUMIF($I$7:$I$52,$B15,M$7:M$52) -> 59701592440 | F15: =SUMIF($I$7:$I$52,$B15,N$7:N$52) -> 59701592440 | I15: 기타비유동채권 | J15: 기타수취채권(비유동) | K15: 1003927240 | L15: 1843483490 | M15: 1393483598 | N15: 1454110198
B16: 기타비유동자산 | C16: =SUMIF($I$7:$I$52,$B16,K$7:K$52) -> 21530480188 | D16: =SUMIF($I$7:$I$52,$B16,L$7:L$52) -> 14003480992 | E16: =SUMIF($I$7:$I$52,$B16,M$7:M$52) -> 23570278514 | F16: =SUMIF($I$7:$I$52,$B16,N$7:N$52) -> 24233018071 | I16: 종속/관계기업투자 | J16: 종속기업투자 | K16: 42035573230 | L16: 58910260297 | M16: 58934282538 | N16: 58934282538
B17: 기타비유동채권 | C17: =SUMIF($I$7:$I$52,$B17,K$7:K$52) -> 1003927240 | D17: =SUMIF($I$7:$I$52,$B17,L$7:L$52) -> 1843483490 | E17: =SUMIF($I$7:$I$52,$B17,M$7:M$52) -> 1393483598 | F17: =SUMIF($I$7:$I$52,$B17,N$7:N$52) -> 1454110198 | I17: 종속/관계기업투자 | J17: 관계기업투자 | K17: 767309902 | L17: 767309902 | M17: 767309902 | N17: 767309902
B18: 자산총계 | C18: =SUM(C6,C12) -> 437049513929 | D18: =SUM(D6,D12) -> 434083820431 | E18: =SUM(E6,E12) -> 457808292332 | F18: =SUM(F6,F12) -> 484943326572 | I18: 기타비유동자산 | J18: 기타금융자산(비유동) | K18: 10000684407 | L18: 2232023574 | M18: 9510057792 | N18: 9690725781
B19: 유동부채 | C19: =SUM(C20:C24) -> 243604132305 | D19: =SUM(D20:D24) -> 240396486022 | E19: =SUM(E20:E24) -> 220981013216 | F19: =SUM(F20:F24) -> 189213052315 | I19: 기타비유동자산 | J19: 기타비유동자산 | K19: 362600000 | L19: 245000000 | M19: 127400000 | N19: 68600000
B20: 매입채무 | C20: =SUMIF($I$7:$I$52,$B20,K$7:K$52) -> 85327446900 | D20: =SUMIF($I$7:$I$52,$B20,L$7:L$52) -> 87060497363 | E20: =SUMIF($I$7:$I$52,$B20,M$7:M$52) -> 89756694650 | F20: =SUMIF($I$7:$I$52,$B20,N$7:N$52) -> 86451917731 | I20: 유형자산 | J20: 유형자산 | K20: 134926702287 | L20: 136471693354 | M20: 142852502572 | N20: 152962175674
B21: 유동성차입금 | C21: =SUMIF($I$7:$I$52,$B21,K$7:K$52) -> 118407328966 | D21: =SUMIF($I$7:$I$52,$B21,L$7:L$52) -> 116047831073 | E21: =SUMIF($I$7:$I$52,$B21,M$7:M$52) -> 83755237204 | F21: =SUMIF($I$7:$I$52,$B21,N$7:N$52) -> 47937549078 | I21: 무형자산 | J21: 무형자산 | K21: 25547393194 | L21: 22464615704 | M21: 24698243277 | N21: 26346040695
B22: 기타유동채무 | C22: =SUMIF($I$7:$I$52,$B22,K$7:K$52) -> 27910621869 | D22: =SUMIF($I$7:$I$52,$B22,L$7:L$52) -> 30052768206 | E22: =SUMIF($I$7:$I$52,$B22,M$7:M$52) -> 39226679543 | F22: =SUMIF($I$7:$I$52,$B22,N$7:N$52) -> 45648977245 | I22: 기타비유동자산 | J22: 이연법인세자산 | K22: 11167195781 | L22: 11526457418 | M22: 13932820722 | N22: 14473692290
B23: 기타유동부채 | C23: =SUMIF($I$7:$I$52,$B23,K$7:K$52) -> 3857547226 | D23: =SUMIF($I$7:$I$52,$B23,L$7:L$52) -> 4164193239 | E23: =SUMIF($I$7:$I$52,$B23,M$7:M$52) -> 5414994118 | F23: =SUMIF($I$7:$I$52,$B23,N$7:N$52) -> 6411737649 | J23: 비유동자산 합계 | K23: 225811386041 | L23: 234460843739 | M23: 252216100401 | N23: 264696937078
B24: 유동충당부채 | C24: =SUMIF($I$7:$I$52,$B24,K$7:K$52) -> 8101187344 | D24: =SUMIF($I$7:$I$52,$B24,L$7:L$52) -> 3071196141 | E24: =SUMIF($I$7:$I$52,$B24,M$7:M$52) -> 2827407701 | F24: =SUMIF($I$7:$I$52,$B24,N$7:N$52) -> 2762870612 | J24: 자산 총계 | K24: 437049513929 | L24: 434083820431 | M24: 457808292332 | N24: 484943326572
B25: 비유동부채 | C25: =SUM(C26:C30) -> 90403197736 | D25: =SUM(D26:D30) -> 77877190465 | E25: =SUM(E26:E30) -> 108703653706 | F25: =SUM(F26:F30) -> 158430974248 | J25: 부채 및 자본
B26: 장기차입금 | C26: =SUMIF($I$7:$I$52,$B26,K$7:K$52) -> 83000000000 | D26: =SUMIF($I$7:$I$52,$B26,L$7:L$52) -> 70674159941 | E26: =SUMIF($I$7:$I$52,$B26,M$7:M$52) -> 101663363183 | F26: =SUMIF($I$7:$I$52,$B26,N$7:N$52) -> 149156785150 | J26: 부채
B27: 장기충당부채 | C27: =SUMIF($I$7:$I$52,$B27,K$7:K$52) -> 3559330293 | D27: =SUMIF($I$7:$I$52,$B27,L$7:L$52) -> 5063239907 | E27: =SUMIF($I$7:$I$52,$B27,M$7:M$52) -> 3366299886 | F27: =SUMIF($I$7:$I$52,$B27,N$7:N$52) -> 3654647722 | J27: 유동부채
B28: 확정급여부채 | C28: =SUMIF($I$7:$I$52,$B28,K$7:K$52) -> 2418231800 | D28: =SUMIF($I$7:$I$52,$B28,L$7:L$52) -> 1456725348 | E28: =SUMIF($I$7:$I$52,$B28,M$7:M$52) -> 1558047624 | F28: =SUMIF($I$7:$I$52,$B28,N$7:N$52) -> 3122252019 | I28: 매입채무 | J28: 매입채무 | K28: 85327446900 | L28: 87060497363 | M28: 89756694650 | N28: 86451917731
B29: 기타비유동부채 | C29: =SUMIF($I$7:$I$52,$B29,K$7:K$52) -> 1272635643 | D29: =SUMIF($I$7:$I$52,$B29,L$7:L$52) -> 529565269 | E29: =SUMIF($I$7:$I$52,$B29,M$7:M$52) -> 1912443013 | F29: =SUMIF($I$7:$I$52,$B29,N$7:N$52) -> 2286889357 | I29: 기타유동채무 | J29: 기타지급채무 | K29: 27910621869 | L29: 30052768206 | M29: 39226679543 | N29: 45648977245
B30: 기타비유동채무 | C30: =SUMIF($I$7:$I$52,$B30,K$7:K$52) -> 153000000 | D30: =SUMIF($I$7:$I$52,$B30,L$7:L$52) -> 153500000 | E30: =SUMIF($I$7:$I$52,$B30,M$7:M$52) -> 203500000 | F30: =SUMIF($I$7:$I$52,$B30,N$7:N$52) -> 210400000 | I30: 기타유동부채 | J30: 기타금융부채 | K30: 0 | L30: 151591904 | M30: 953460060 | N30: 1471013766 | O30: 84183844
B31: 부채총계 | C31: =SUM(C25,C19) -> 334007330041 | D31: =SUM(D25,D19) -> 318273676487 | E31: =SUM(E25,E19) -> 329684666922 | F31: =SUM(F25,F19) -> 347644026563 | I31: 유동성차입금 | J31: 차입금 | K31: 118407328966 | L31: 116047831073 | M31: 83755237204 | N31: 47937549078
B32: 자본금 | C32: =SUMIF($I$7:$I$52,$B32,K$7:K$52) -> 49333300000 | D32: =SUMIF($I$7:$I$52,$B32,L$7:L$52) -> 49333300000 | E32: =SUMIF($I$7:$I$52,$B32,M$7:M$52) -> 49333300000 | F32: =SUMIF($I$7:$I$52,$B32,N$7:N$52) -> 49333300000 | I32: 기타유동부채 | J32: 기타유동부채 | K32: 3857547226 | L32: 4012601335 | M32: 4418304399 | N32: 4588917068 | O32: 4080009395
B33: 이익잉여금 | C33: =SUMIF($I$7:$I$52,$B33,K$7:K$52) -> 51009874738 | D33: =SUMIF($I$7:$I$52,$B33,L$7:L$52) -> 62700847397 | E33: =SUMIF($I$7:$I$52,$B33,M$7:M$52) -> 78106458940 | F33: =SUMIF($I$7:$I$52,$B33,N$7:N$52) -> 88155993175 | I33: 기타유동부채 | J33: 당기법인세부채 | K33: 0 | L33: 0 | M33: 43229659 | N33: 351806815
B34: 기타자본 | C34: =SUMIF($I$7:$I$52,$B34,K$7:K$52) -> 2699009150 | D34: =SUMIF($I$7:$I$52,$B34,L$7:L$52) -> 3775996547 | E34: =SUMIF($I$7:$I$52,$B34,M$7:M$52) -> 683866470 | F34: =SUMIF($I$7:$I$52,$B34,N$7:N$52) -> -189993166 | I34: 유동충당부채 | J34: 충당부채 | K34: 8101187344 | L34: 3071196141 | M34: 2827407701 | N34: 2762870612
B35: 자본총계 | C35: =SUM(C32:C34) -> 103042183888 | D35: =SUM(D32:D34) -> 115810143944 | E35: =SUM(E32:E34) -> 128123625410 | F35: =SUM(F32:F34) -> 137299300009 | J35: 유동부채 합계 | K35: 243604132305 | L35: 240396486022 | M35: 220981013216 | N35: 189213052315
B36: 자본과부채총계 | C36: =C31+C35 -> 437049513929 | D36: =D31+D35 -> 434083820431 | E36: =E31+E35 -> 457808292332 | F36: =F31+F35 -> 484943326572 | J36: 비유동부채
B37: Source : 감사보고서 | I37: 기타비유동채무 | J37: 기타지급채무(비유동) | K37: 153000000 | L37: 153500000 | M37: 203500000 | N37: 210400000
B38: 총차입금 | C38: =C21+C26 -> 201407328966 | D38: =D21+D26 -> 186721991014 | E38: =E21+E26 -> 185418600387 | F38: =F21+F26 -> 197094334228 | I38: 기타비유동부채 | J38: 기타금융부채(비유동) | K38: 21799188 | L38: 38291280 | M38: 1003952246 | N38: 1485087903 | O38: 2512273
B39: 순차입금 | C39: =C38-C7 -> 200222641375 | D39: =D38-D7 -> 185634805868 | E39: =E38-E7 -> 185001561220 | F39: =F38-F7 -> 195632359291 | I39: 장기차입금 | J39: 차입금(비유동) | K39: 83000000000 | L39: 70674159941 | M39: 101663363183 | N39: 149156785150
C40: =C6-K13 -> 0 | D40: =D6-L13 -> 0 | E40: =E6-M13 -> 0 | F40: =F6-N13 -> 0 | I40: 기타비유동부채 | J40: 기타비유동부채 | K40: 1250836455 | L40: 491273989 | M40: 908490767 | N40: 801801454 | O40: 527052996
C41: =C6-K13 -> 0 | D41: =D6-L13 -> 0 | E41: =E6-M13 -> 0 | F41: =F6-N13 -> 0 | I41: 확정급여부채 | J41: 확정급여부채 | K41: 2418231800 | L41: 1456725348 | M41: 1558047624 | N41: 3122252019
C42: =C12-K23 -> 0 | D42: =D12-L23 -> 0 | E42: =E12-M23 -> 0 | F42: =F12-N23 -> 0 | I42: 장기충당부채 | J42: 충당부채(비유동) | K42: 3559330293 | L42: 5063239907 | M42: 3366299886 | N42: 3654647722
C43: =C18-K24 -> 0 | D43: =D18-L24 -> 0 | E43: =E18-M24 -> 0 | F43: =F18-N24 -> 0 | J43: 비유동부채 합계 | K43: 90403197736 | L43: 77877190465 | M43: 108703653706 | N43: 158430974248
C44: =C19-K35 -> 0 | D44: =D19-L35 -> 0 | E44: =E19-M35 -> 0 | F44: =F19-N35 -> 0 | J44: 부채 총계 | K44: 334007330041 | L44: 318273676487 | M44: 329684666922 | N44: 347644026563
C45: =C25-K43 -> 0 | D45: =D25-L43 -> 0 | E45: =E25-M43 -> 0 | F45: =F25-N43 -> 0 | J45: 자본
C46: =C31-K44 -> 0 | D46: =D31-L44 -> 0 | E46: =E31-M44 -> 0 | F46: =F31-N44 -> 0 | I46: 자본금 | J46: 자본금 | K46: 49333300000 | L46: 49333300000 | M46: 49333300000 | N46: 49333300000
C47: =C35-K50 -> 0 | D47: =D35-L50 -> 0 | E47: =E35-M50 -> 0 | F47: =F35-N50 -> 0 | I47: 기타자본 | J47: 기타불입자본 | K47: -147000000 | L47: -147000000 | M47: -147000000 | N47: -
C48: =C36-K51 -> 0 | D48: =D36-L51 -> 0 | E48: =E36-M51 -> 0 | F48: =F36-N51 -> 0 | I48: 기타자본 | J48: 기타포괄손익누계액 | K48: 2846009150 | L48: 3922996547 | M48: 830866470 | N48: -189993166
I49: 이익잉여금 | J49: 이익잉여금 | K49: 51009874738 | L49: 62700847397 | M49: 78106458940 | N49: 88155993175
J50: 자본 총계 | K50: 103042183888 | L50: 115810143944 | M50: 128123625410 | N50: 137299300009
J51: 부채 및 자본의 총계 | K51: 437049513929 | L51: 434083820431 | M51: 457808292332 | N51: 484943326572

Sheet IS(별도)
J1: >>PL | U1: >>주석
B3: 손익계산서(별도) | M3: 2015년 반기 보고서기준 | O3: 제 43 기 반기 | P3: 제 42 기 반기 | Q3: 2014년 기말 감사보고서기준
C4: 2012년 | D4: 2013년 | E4: 2014년 | F4: 2015년 | G4: 2014년 | K4: 과 목 | L4: 제 40기 | M4: 제 41 기 | N4: 제 42 기 | O4: 누적 | P4: 누적 | Q4: 제 41 기 | R4: 제 42 기 | S4: 41기 차이 | T4: 42기 차이
B5: 백만원 | C5: 12개월 | D5: 12개월 | E5: 12개월 | F5: 6개월 | G5: 6개월 | K5: 매출액 | L5: 528569510350 | M5: 559856533781 | N5: 591196611310 | O5: 303923046949 | P5: 296493708547 | Q5: 555740268125 | R5: 584672320904 | S5: =M5-Q5 -> 4116265656 | T5: =N5-R5 -> 6524290406
B6: 매출액 | C6: =L5 -> 528569510350 | D6: =M5 -> 559856533781 | E6: =N5 -> 591196611310 | F6: =O5 -> 303923046949 | G6: =P5 -> 296493708547 | K6: 매출원가 | L6: -475725626210 | M6: -499445340398 | N6: -524218029958 | O6: -273015109365 | P6: -261870076026 | Q6: -499445340398 | R6: -524218029958 | S6: =M6-Q6 -> 0 | T6: =N6-R6 -> 0
B7: HMI | C7: =Sheet16!P5*1000000 -> 343953000000 | D7: =Sheet16!F5*1000000 -> 387385000000 | E7: =Sheet16!G5*1000000 -> 422384000000 | F7: =Sheet16!H5*1000000 -> 220196000000 | K7: 매출총이익 | L7: 52843884140 | M7: 60411193383 | N7: 66978581352 | O7: 30907937584 | P7: 34623632521 | Q7: 56294927727 | R7: 60454290946 | S7: =M7-Q7 -> 4116265656 | T7: =N7-R7 -> 6524290406
B8: MC | C8: =(Sheet16!P11+Sheet16!P14)*1000000 -> 119987000000 | D8: =Sheet16!F11*1000000 -> 106950000000 | E8: =Sheet16!G11*1000000 -> 96262000000 | F8: =Sheet16!H11*1000000 -> 43272000000 | H8: 2012년 스위치램프 추가 | K8: 판매비와 관리비 | L8: -43792009823 | M8: -41361745470 | N8: -44247827700 | O8: -20978070672 | P8: -23767040887 | Q8: -41361745470 | R8: -44247827700 | S8: =M8-Q8 -> 0 | T8: =N8-R8 -> 0
B9: BCS | C9: =Sheet16!P8*1000000 -> 64629000000 | D9: =Sheet16!F8*1000000 -> 65522000000 | E9: =Sheet16!G8*1000000 -> 72550000000 | F9: =Sheet16!H8*1000000 -> 40455000000 | K9: 영업이익 | L9: 9051874317 | M9: 19049447913 | N9: 22730753652 | O9: 9929866912 | P9: 10856591634 | Q9: 14933182257 | R9: 16206463246 | S9: =M9-Q9 -> 4116265656 | T9: =N9-R9 -> 6524290406
B10: 매출원가 | C10: =-L6 -> 475725626210 | D10: =-M6 -> 499445340398 | E10: =-N6 -> 524218029958 | F10: =-O6 -> 273015109365 | G10: =-P6 -> 261870076026 | K10: 기타수익 | L10: 13026278480 | M10: 8492636959 | N10: 8106806758 | O10: 5213424386 | P10: 3562355144 | Q10: 12608902615 | R10: 14631097164 | S10: =M10-Q10 -> -4116265656 | T10: =N10-R10 -> -6524290406
B11: 매출총이익 | C11: =L7 -> 52843884140 | D11: =M7 -> 60411193383 | E11: =N7 -> 66978581352 | F11: =O7 -> 30907937584 | G11: =P7 -> 34623632521 | K11: 기타비용 | L11: -8610783775 | M11: -9571376805 | N11: -6730976780 | O11: -3743910653 | P11: -4805623865 | Q11: -9571376805 | R11: -6730976780 | S11: =M11-Q11 -> 0 | T11: =N11-R11 -> 0
B12: 매출총이익률(%) | C12: =C11/C6 -> 0.099975279 | D12: =D11/D6 -> 0.10790478 | E12: =E11/E6 -> 0.11329324 | F12: =F11/F6 -> 0.10169659 | G12: =G11/G6 -> 0.11677696 | K12: 금융수익 | L12: 3164239607 | M12: 3794577895 | N12: 2738057029 | O12: 4214581286 | P12: 2592352436 | Q12: 3794577895 | R12: 2738057029 | S12: =M12-Q12 -> 0 | T12: =N12-R12 -> 0
B13: 판매관리비 | C13: =-L8 -> 43792009823 | D13: =-M8 -> 41361745470 | E13: =-N8 -> 44247827700 | F13: =-O8 -> 20978070672 | G13: =-P8 -> 23767040887 | K13: 금융비용 | L13: -13034533243 | M13: -10424964533 | N13: -9110101151 | O13: -3980264818 | P13: -4726004172 | Q13: -10424964533 | R13: -9110101151 | S13: =M13-Q13 -> 0 | T13: =N13-R13 -> 0
B14: 인건비 | C14: =SUMIF($U$52:$U$72,$B14,W$52:W$72)*1000 -> 12090408000 | D14: =SUMIF($U$52:$U$72,$B14,X$52:X$72)*1000 -> 13107754000 | E14: =SUMIF($U$52:$U$72,$B14,Y$52:Y$72)*1000 -> 15759100000 | F14: =SUMIF($U$52:$U$72,$B14,Z$52:Z$72)*1000 -> 8735298000 | G14: =SUMIF($U$52:$U$72,$B14,AA$52:AA$72)*1000 -> 8084205000 | K14: 기타영업외수익 | L14: 2410270709 | M14: 2704255678 | N14: 952009841 | O14: 825116507 | P14: 1181918968 | Q14: 2704255678 | R14: 952009841 | S14: =M14-Q14 -> 0 | T14: =N14-R14 -> 0
B15: 감가상각비 | C15: =SUMIF($U$52:$U$72,$B15,W$52:W$72)*1000 -> 613048000 | D15: =SUMIF($U$52:$U$72,$B15,X$52:X$72)*1000 -> 550311000 | E15: =SUMIF($U$52:$U$72,$B15,Y$52:Y$72)*1000 -> 553004000 | F15: =SUMIF($U$52:$U$72,$B15,Z$52:Z$72)*1000 -> 287627000 | G15: =SUMIF($U$52:$U$72,$B15,AA$52:AA$72)*1000 -> 287454000 | K15: 기타영업외비용 | L15: -985641402 | M15: -1803476575 | N15: -2290914213 | O15: -1614021963 | P15: -583124654 | Q15: -1803476575 | R15: -2290914213 | S15: =M15-Q15 -> 0 | T15: =N15-R15 -> 0
B16: 무형자산상각비 | C16: =SUMIF($U$52:$U$72,$B16,W$52:W$72)*1000 -> 2312602000 | D16: =SUMIF($U$52:$U$72,$B16,X$52:X$72)*1000 -> 2638971000 | E16: =SUMIF($U$52:$U$72,$B16,Y$52:Y$72)*1000 -> 2979017000 | F16: =SUMIF($U$52:$U$72,$B16,Z$52:Z$72)*1000 -> 1224904000 | G16: =SUMIF($U$52:$U$72,$B16,AA$52:AA$72)*1000 -> 1462090000 | K16: 법인세비용차감전순이익 | L16: 5021704693 | M16: 12241100532 | N16: 16395635136 | O16: 10844791657 | P16: 8078465491 | Q16: 12241100532 | R16: 16395635136 | S16: =M16-Q16 -> 0 | T16: =N16-R16 -> 0
B17: 판매보증비 | C17: =SUMIF($U$52:$U$72,$B17,W$52:W$72)*1000 -> 11004711000 | D17: =SUMIF($U$52:$U$72,$B17,X$52:X$72)*1000 -> 7646333000 | E17: =SUMIF($U$52:$U$72,$B17,Y$52:Y$72)*1000 -> 7159190000 | F17: =SUMIF($U$52:$U$72,$B17,Z$52:Z$72)*1000 -> 3121228000 | G17: =SUMIF($U$52:$U$72,$B17,AA$52:AA$72)*1000 -> 5095133000 | K17: 법인세비용(혜택) | L17: 781096574 | M17: 14227147 | N17: -165484440 | O17: 648257422 | P17: -383715942 | Q17: 14227147 | R17: -165484440 | S17: =M17-Q17 -> 0 | T17: =N17-R17 -> 0
B18: 지급수수료 | C18: =SUMIF($U$52:$U$72,$B18,W$52:W$72)*1000 -> 5345304000 | D18: =SUMIF($U$52:$U$72,$B18,X$52:X$72)*1000 -> 5284352000 | E18: =SUMIF($U$52:$U$72,$B18,Y$52:Y$72)*1000 -> 3496597000 | F18: =SUMIF($U$52:$U$72,$B18,Z$52:Z$72)*1000 -> 1405797000 | G18: =SUMIF($U$52:$U$72,$B18,AA$52:AA$72)*1000 -> 1569508000 | K18: 당기순이익 | L18: 4240608119 | M18: 12226873385 | N18: 16561119576 | O18: 10196534235 | P18: 8462181433 | Q18: 12226873385 | R18: 16561119576 | S18: =M18-Q18 -> 0 | T18: =N18-R18 -> 0
B19: 경상개발비 | C19: =SUMIF($U$52:$U$72,$B19,W$52:W$72)*1000 -> 243199000 | D19: =SUMIF($U$52:$U$72,$B19,X$52:X$72)*1000 -> 948237000 | E19: =SUMIF($U$52:$U$72,$B19,Y$52:Y$72)*1000 -> 833108000 | F19: =SUMIF($U$52:$U$72,$B19,Z$52:Z$72)*1000 -> 304128000 | G19: =SUMIF($U$52:$U$72,$B19,AA$52:AA$72)*1000 -> 445060000 | K19: 법인세비용차감후 기타포괄손익 | S19: =M19-Q19 -> 0 | T19: =N19-R19 -> 0 | V19: 매출 및 매출원가의 구성내역은 다음과 같습니다.
B20: 세금과공과 | C20: =SUMIF($U$52:$U$72,$B20,W$52:W$72)*1000 -> 704385000 | D20: =SUMIF($U$52:$U$72,$B20,X$52:X$72)*1000 -> 566459000 | E20: =SUMIF($U$52:$U$72,$B20,Y$52:Y$72)*1000 -> 563143000 | F20: =SUMIF($U$52:$U$72,$B20,Z$52:Z$72)*1000 -> 284982000 | G20: =SUMIF($U$52:$U$72,$B20,AA$52:AA$72)*1000 -> 318150000 | K20: 후속적으로 당기손익으로 재분류될 수 있는 항목 | S20: =M20-Q20 -> 0 | T20: =N20-R20 -> 0 | V20: (단위: 천원) | Z20: 제43기 반기 | AA20: 제42기 반기
B21: 임차료 | C21: =SUMIF($U$52:$U$72,$B21,W$52:W$72)*1000 -> 1378681000 | D21: =SUMIF($U$52:$U$72,$B21,X$52:X$72)*1000 -> 1314861000 | E21: =SUMIF($U$52:$U$72,$B21,Y$52:Y$72)*1000 -> 1123636000 | F21: =SUMIF($U$52:$U$72,$B21,Z$52:Z$72)*1000 -> 556810000 | G21: =SUMIF($U$52:$U$72,$B21,AA$52:AA$72)*1000 -> 558667000 | K21: 매도가능증권평가손익 | L21: 6463649 | M21: 47898287 | N21: 34134329 | O21: 494535 | P21: 25600325 | Q21: 47898287 | R21: 34134329 | S21: =M21-Q21 -> 0 | T21: =N21-R21 -> 0 | V21: 구 분 | W21: 40기 | X21: 41기 | Y21: 42기 | Z21: 누적 | AA21: 누적
B22: 여비교통비 | C22: =SUMIF($U$52:$U$72,$B22,W$52:W$72)*1000 -> 823868000 | D22: =SUMIF($U$52:$U$72,$B22,X$52:X$72)*1000 -> 760129000 | E22: =SUMIF($U$52:$U$72,$B22,Y$52:Y$72)*1000 -> 1201955000 | F22: =SUMIF($U$52:$U$72,$B22,Z$52:Z$72)*1000 -> 613269000 | G22: =SUMIF($U$52:$U$72,$B22,AA$52:AA$72)*1000 -> 649647000 | K22: 파생상품평가손익 | L22: 4495184394 | M22: 1029089110 | N22: -3126264406 | O22: -1021354171 | P22: 2550811422 | Q22: 1029089110 | R22: -3126264406 | S22: =M22-Q22 -> 0 | T22: =N22-R22 -> 0 | W22: 매 출 | X22: 매 출 | Y22: 매 출
B23: 기타비용 | C23: =SUMIF($U$52:$U$72,$B23,W$52:W$72)*1000 -> 9275804000 | D23: =SUMIF($U$52:$U$72,$B23,X$52:X$72)*1000 -> 8544337000 | E23: =SUMIF($U$52:$U$72,$B23,Y$52:Y$72)*1000 -> 10579078000 | F23: =SUMIF($U$52:$U$72,$B23,Z$52:Z$72)*1000 -> 4444028000 | G23: =SUMIF($U$52:$U$72,$B23,AA$52:AA$72)*1000 -> 5297127000 | K23: 후속적으로 당기손익으로 재분류되지 않는 항목 | S23: =M23-Q23 -> 0 | T23: =N23-R23 -> 0 | V23: 제품 | W23: 526517113 | X23: 544246783 | Y23: 566780439 | Z23: 294177848 | AA23: 287076014
B24: 영업이익 | C24: =L9 -> 9051874317 | D24: =M9 -> 19049447913 | E24: =N9 -> 22730753652 | F24: =O9 -> 9929866912 | G24: =P9 -> 10856591634 | K24: 확정급여제도의 재측정요소 | L24: -713736032 | M24: -535900726 | N24: -1155508033 | O24: - | P24: - | Q24: -535900726 | R24: -1155508033 | S24: =M24-Q24 -> 0 | T24: =N24-R24 -> 0 | V24: 기타 | W24: 2052397 | X24: 11493485 | Y24: 17891882 | Z24: 9745199 | AA24: 9417695
B25: 영업이익(%) | C25: =C24/C6 -> 0.01712523 | D25: =D24/D6 -> 0.034025588 | E25: =E24/E6 -> 0.038448721 | F25: =F24/F6 -> 0.032672306 | G25: =G24/G6 -> 0.0366166 | K25: 총포괄이익 | L25: 8028520130 | M25: 12767960056 | N25: 12313481466 | O25: 9175674599 | P25: 11038593180 | Q25: 12767960056 | R25: 12313481466 | S25: =M25-Q25 -> 0 | T25: =N25-R25 -> 0 | V25: 합 계 | W25: 528569510 | X25: 555740268 | Y25: 584672321 | Z25: 303923047 | AA25: 296493709
B26: 금융수익 | C26: =L12 -> 3164239607 | D26: =M12 -> 3794577895 | E26: =N12 -> 2738057029 | F26: =O12 -> 4214581286 | G26: =P12 -> 2592352436 | K26: 주당손익 | S26: =M26-Q26 -> 0 | T26: =N26-R26 -> 0 | W26: 매 출 원 가 | X26: 매 출 원 가 | Y26: 매 출 원 가
B27: 금융비용 | C27: =-L13 -> 13034533243 | D27: =-M13 -> 10424964533 | E27: =-N13 -> 9110101151 | F27: =-O13 -> 3980264818 | G27: =-P13 -> 4726004172 | K27: 기본 및 희석주당손익 | L27: 430 | M27: 1239 | N27: 1678 | O27: 1033 | P27: 858 | Q27: 1239 | R27: 1678 | S27: =M27-Q27 -> 0 | T27: =N27-R27 -> 0 | V27: 제품 | W27: 475725626 | X27: 492941309 | Y27: 514315745 | Z27: 269948747 | AA27: 258838374
B28: 기타수익 | C28: =L10+L14 -> 15436549189 | D28: =M10+M14 -> 11196892637 | E28: =N10+N14 -> 9058816599 | F28: =O10+O14 -> 6038540893 | G28: =P10+P14 -> 4744274112 | H28: 기타수익+기타영업외수익 | V28: 기타 | W28: - | X28: 6504031 | Y28: 9902285 | Z28: 3066362 | AA28: 3031702
B29: 기타비용 | C29: =-(L11+L15) -> 9596425177 | D29: =-(M11+M15) -> 11374853380 | E29: =-(N11+N15) -> 9021890993 | F29: =-(O11+O15) -> 5357932616 | G29: =-(P11+P15) -> 5388748519 | H29: 기타비용+기타영업외비용 | V29: 합 계 | W29: 475725626 | X29: 499445340 | Y29: 524218030 | Z29: 273015109 | AA29: 261870076
B30: 법인세비용 | C30: =L17 -> 781096574 | D30: =M17 -> 14227147 | E30: =N17 -> -165484440 | F30: =O17 -> 648257422 | G30: =P17 -> -383715942
B31: 당기순이익 | C31: =L18 -> 4240608119 | D31: =M18 -> 12226873385 | E31: =N18 -> 16561119576 | F31: =O18 -> 10196534235 | G31: =P18 -> 8462181433 | V31: 22. 영업이익
B32: 당기순이익률(%) | C32: =C31/C6 -> 0.0080228012 | D32: =D31/D6 -> 0.021839297 | E32: =E31/E6 -> 0.02801288 | F32: =F31/F6 -> 0.033549724 | G32: =G31/G6 -> 0.028540847
B33: EBITDA | C33: =C24+C39 -> 37439779939 | D33: =D24+D39 -> 48220330377 | E33: =E24+E39 -> 52741648712 | F33: =F24+F39 -> 25278568327 | G33: =G24+G39 -> 25570961548 | V33: 22-1 종업원급여의 내역은 다음과 같습니다.
B34: EBITDA(%) | C34: =C33/C6 -> 0.070832273 | D34: =D33/D6 -> 0.086129798 | E34: =E33/E6 -> 0.08921169 | F34: =F33/F6 -> 0.08317424 | G34: =G33/G6 -> 0.086244533
B35: Source : 감사보고서 | V35: (단위: 천원) | Z35: 제43기 반기 | AA35: 제42기 반기
V36: 구 분 | W36: 40기 | X36: 41기 | Y36: 42기 | Z36: 누적 | AA36: 누적
B37: 감가상각비 | C37: ='CF(별도)'!B14 -> 20738867867 | D37: ='CF(별도)'!C14 -> 21766783544 | E37: ='CF(별도)'!D14 -> 23080308849 | F37: ='CF(별도)'!E14 -> 12278805441 | G37: ='CF(별도)'!F14 -> 11214198818 | V37: 급여 | W37: 42368676 | X37: 48051854 | Y37: 53158533 | Z37: 29219947 | AA37: 26753807
B38: 무형자산상각비 | C38: ='CF(별도)'!B15 -> 7649037755 | D38: ='CF(별도)'!C15 -> 7404098920 | E38: ='CF(별도)'!D15 -> 6930586211 | F38: ='CF(별도)'!E15 -> 3069895974 | G38: ='CF(별도)'!F15 -> 3500171096 | V38: 퇴직급여 | W38: 2746268 | X38: 3037008 | Y38: 3701975 | Z38: 2041980 | AA38: 1831649
B39: D&A | C39: =SUM(C37:C38) -> 28387905622 | D39: =SUM(D37:D38) -> 29170882464 | E39: =SUM(E37:E38) -> 30010895060 | F39: =SUM(F37:F38) -> 15348701415 | G39: =SUM(G37:G38) -> 14714369914 | V39: 복리후생비 | W39: 5469302 | X39: 6562561 | Y39: 6875849 | Z39: 3893106 | AA39: 3427477
C40: =C39-W48*1000 -> -378 | D40: =D39-X48*1000 -> -536 | E40: =E39-Y48*1000 -> 60 | F40: =F39-Z48*1000 -> 415 | G40: =G39-AA48*1000 -> -86 | V40: 합 계 | W40: 50584246 | X40: 57651423 | Y40: 63736357 | Z40: 35155033 | AA40: 32012933
C42: =SUM(C7:C9)-C6 -> -510350 | D42: =SUM(D7:D9)-D6 -> 466219 | E42: =SUM(E7:E9)-E6 -> -611310 | F42: =SUM(F7:F9)-F6 -> -46949 | G42: =SUM(G7:G9)-G6 -> -296493708547 | V42: 22-2 감가상각비와 무형자산상각비의 내역은 다음과 같습니다.
C43: =C6-C10-C11 -> 0 | D43: =D6-D10-D11 -> 0 | E43: =E6-E10-E11 -> 0 | F43: =F6-F10-F11 -> 0 | G43: =G6-G10-G11 -> 0
C44: =SUM(C14:C23)-C13 -> 177 | D44: =SUM(D14:D23)-D13 -> -1470 | E44: =SUM(E14:E23)-E13 -> 300 | F44: =SUM(F14:F23)-F13 -> 328 | G44: =SUM(G14:G23)-G13 -> 113 | V44: (단위: 천원) | Z44: 제43기 반기 | AA44: 제42기 반기
C45: =C11-C13-C24 -> 0 | D45: =D11-D13-D24 -> 0 | E45: =E11-E13-E24 -> 0 | F45: =F11-F13-F24 -> 0 | G45: =G11-G13-G24 -> 0 | V45: 구 분 | W45: 40기 | X45: 41기 | Y45: 42기 | Z45: 누적 | AA45: 누적
C46: =C24+C26-C27+C28-C29-C30-C31 -> 0 | D46: =D24+D26-D27+D28-D29-D30-D31 -> 0 | E46: =E24+E26-E27+E28-E29-E30-E31 -> 0 | F46: =F24+F26-F27+F28-F29-F30-F31 -> 0 | G46: =G24+G26-G27+G28-G29-G30-G31 -> 0 | V46: 유형자산감가상각비 | W46: 20738868 | X46: 21766784 | Y46: 23080309 | Z46: 12278805 | AA46: 11214199
V47: 무형자산상각비 | W47: 7649038 | X47: 7404099 | Y47: 6930586 | Z47: 3069896 | AA47: 3500171
V48: 합 계 | W48: 28387906 | X48: 29170883 | Y48: 30010895 | Z48: 15348701 | AA48: 14714370
V49: 22-3 판매비와관리비의 내역은 다음과 같습니다.
V50: (단위: 천원) | Z50: 제43기 반기 | AA50: 제42기 반기
V51: 구 분 | W51: 40기 | X51: 41기 | Y51: 42기 | Z51: 누적 | AA51: 누적
U52: 인건비 | V52: 급여 | W52: 9985630 | X52: 11011668 | Y52: 13142790 | Z52: 7256073 | AA52: 6809795
U53: 인건비 | V53: 퇴직급여 | W53: 602096 | X53: 627512 | Y53: 864169 | Z53: 467945 | AA53: 430538
U54: 기타비용 | V54: 운반비 | W54: 7247663 | X54: 6780132 | Y54: 8715411 | Z54: 3528347 | AA54: 4410037
U55: 감가상각비 | V55: 감가상각비 | W55: 613048 | X55: 550311 | Y55: 553004 | Z55: 287627 | AA55: 287454
U56: 기타비용 | V56: 소모품비 | W56: 104926 | X56: 93141 | Y56: 43628 | Z56: 29589 | AA56: 22267 | AC56: 수도광열비 | AD56: 15212 | AE56: 14362
U57: 세금과공과 | V57: 세금과공과 | W57: 704385 | X57: 566459 | Y57: 563143 | Z57: 284982 | AA57: 318150 | AC57: 수선비 | AD57: 57432 | AE57: 40613
U58: 임차료 | V58: 임차료 | W58: 1378681 | X58: 1314861 | Y58: 1123636 | Z58: 556810 | AA58: 558667 | AC58: 도서인쇄비 | AD58: 16337 | AE58: 10336
U59: 기타비용 | V59: 보험료 | W59: 171805 | X59: 204197 | Y59: 275820 | Z59: 136440 | AA59: 133154 | AC59: 회의비 | AD59: 3648 | AE59: 4526
U60: 인건비 | V60: 복리후생비 | W60: 1502682 | X60: 1468574 | Y60: 1752141 | Z60: 1011280 | AA60: 843872 | AC60: 기타판관비 | AD60: 38856 | AE60: 59903
U61: 여비교통비 | V61: 여비교통비 | W61: 823868 | X61: 760129 | Y61: 1201955 | Z61: 613269 | AA61: 649647 | AD61: =SUM(AD56:AD60) -> 131485 | AE61: =SUM(AE56:AE60) -> 129740
U62: 기타비용 | V62: 통신비 | W62: 222431 | X62: 263974 | Y62: 67272 | Z62: 22995 | AA62: 35254
U63: 지급수수료 | V63: 지급수수료 | W63: 5345304 | X63: 5284352 | Y63: 3496597 | Z63: 1405797 | AA63: 1569508
U64: 기타비용 | V64: 접대비 | W64: 253286 | X64: 319679 | Y64: 451176 | Z64: 198338 | AA64: 226018
U65: 기타비용 | V65: 교육훈련비 | W65: 224974 | X65: 275590 | Y65: 294078 | Z65: 175802 | AA65: 126614
U66: 기타비용 | V66: 차량유지비 | W66: 157520 | X66: 155202 | Y66: 187980 | Z66: 83115 | AA66: 97297
U67: 경상개발비 | V67: 경상개발비 | W67: 243199 | X67: 948237 | Y67: 833108 | Z67: 304128 | AA67: 445060
U68: 기타비용 | V68: 광고선전비 | W68: 552003 | X68: 112310 | Y68: 246666 | Z68: 137917 | AA68: 116746
U69: 기타비용 | V69: 대손상각비 | W69: 139602 | X69: 60881 | Y69: 0 | Z69: 0 | AA69: 0
U70: 무형자산상각비 | V70: 무형자산상각비 | W70: 2312602 | X70: 2638971 | Y70: 2979017 | Z70: 1224904 | AA70: 1462090
U71: 판매보증비 | V71: 판매보증충당부채전입액 | W71: 11004711 | X71: 7646333 | Y71: 7159190 | Z71: 3121228 | AA71: 5095133
U72: 기타비용 | V72: 기타판관비 | W72: 201594 | X72: 279231 | Y72: 297047 | Z72: 131485 | AA72: 129740
V73: 합 계 | W73: 43792010 | X73: 41361744 | Y73: 44247828 | Z73: 20978071 | AA73: 23767041
V77: 23. 조정영업이익
V79: 23-1 조정영업이익
V80: 손익계산서의 영업이익에 포함된 항목 외에 당사의 영업성과를 반영하는 항목을 추가하여 산정한 당사가 자체 분류한 조정영업이익의 산정내역은 다음과 같습니다.
V83: (단위: 천원) | Z83: 제43기 반기 | AA83: 제42기 반기
V84: 구 분 | W84: 40기 | X84: 41기 | Y84: 42기 | Z84: 누적 | AA84: 누적
V85: 영업이익 | W85: 9051874 | X85: 14933182 | Y85: 16206463 | Z85: 9929867 | AA85: 10856592
V86: 기타수익 | W86: 13026278 | X86: 12608903 | Y86: 14631097 | Z86: 5213425 | AA86: 3562355
V87: 기타비용 | W87: -8610784 | X87: -9571377 | Y87: -6730976 | Z87: -3743911 | AA87: -4805624
V88: 조정영업이익 | W88: 13467368 | X88: 17970708 | Y88: 24106584 | Z88: 11399381 | AA88: 9613323
V90: 23-2 기타수익
V92: 기타수익의 내역은 다음과 같습니다.
V94: (단위: 천원) | Z94: 제43기 반기 | AA94: 제42기 반기
V95: 구 분 | W95: 40기 | X95: 41기 | Y95: 42기 | Z95: 누적 | AA95: 누적
V96: 임대료수익 | W96: 107415 | X96: 111266 | Y96: 123015 | Z96: 59707 | AA96: 60007
V97: 외환차익 | W97: 2944402 | X97: 5036575 | Y97: 3719449 | Z97: 1993038 | AA97: 1541675
V98: 외화환산이익 | W98: 874927 | X98: 542930 | Y98: 2222678 | Z98: 1969974 | AA98: 632230
V99: 유형자산처분이익 | W99: 1117707 | X99: 1148931 | Y99: 426705 | Z99: 18391 | AA99: 209320
V100: 무형자산처분이익 | W100: 71528 | X100: 117216 | Y100: 3272 | Z100: 1514 | AA100: 3272
V101: 기타의대손충당금 | W101: 0 | X101: 0 | Y101: 494955 | Z101: 0 | AA101: 494955
V102: 로열티수익 | W102: 2731350 | X102: 4116266 | Y102: 6524290 | Z102: 0 | AA102: 0
V103: 부산물처분이익 | W103: 1055827 | X103: 885892 | Y103: 744734 | Z103: 390089 | AA103: 411445
V104: 기타 | W104: 4123122 | X104: 649826 | Y104: 371999 | Z104: 780711 | AA104: 209451
V105: 합 계 | W105: 13026278 | X105: 12608902 | Y105: 14631097 | Z105: 5213424 | AA105: 3562355
V107: 23-3 기타비용
V109: 기타비용의 내역은 다음과 같습니다.
V110: (단위: 천원) | Z110: 제43기 반기 | AA110: 제42기 반기
V111: 구 분 | W111: 40기 | X111: 41기 | Y111: 42기 | Z111: 누적 | AA111: 누적
V112: 외환차손 | W112: 3773320 | X112: 4344100 | Y112: 3620676 | Z112: 2282187 | AA112: 2313762
V113: 외화환산손실 | W113: 1965467 | X113: 837681 | Y113: 780889 | Z113: 415895 | AA113: 1310716
...

Sheet Sheet16
K1: (단위 : 백만원)
A2: 구분 | B2: 사업부문 | C2: 매출유형 | D2: 품 목 | F2: 2013년 | G2: 2014년 | H2: 2015년 반기 | K2: 구분 | L2: 사업부문 | M2: 매출유형 | N2: 품 목 | P2: 2012년 | Q2: 2013년 | R2: 2014년
A3: 대성전기공업㈜ | B3: 자동차부품 | C3: 제품 | D3: HMI | E3: 수출 | F3: 102861 | G3: 138573 | H3: 74785 | I3: =G3=R3 -> FALSE | J3: =F3=Q3 -> FALSE | K3: 대성전기공업㈜ | L3: 자동차부품 | M3: 제품 | N3: HMI | O3: 수출 | P3: 78129 | Q3: 99181 | R3: 132445
C4: 상품 | E4: 내수 | F4: 284524 | G4: 283811 | H4: 145412 | I4: =G4=R4 -> TRUE | J4: =F4=Q4 -> TRUE | M4: 상품 | O4: 내수 | P4: 265824 | Q4: 284524 | R4: 283811
C5: 용역 | E5: 합계 | F5: 387385 | G5: 422384 | H5: 220196 | I5: =G5=R5 -> FALSE | J5: =F5=Q5 -> FALSE | O5: 합계 | P5: 343953 | Q5: 383705 | R5: 416256
D6: BCS | E6: 수출 | F6: 15044 | G6: 14525 | H6: 8736 | I6: =G6=R6 -> FALSE | J6: =F6=Q6 -> FALSE | N6: BCS | O6: 수출 | P6: 13914 | Q6: 14995 | R6: 14434
E7: 내수 | F7: 50478 | G7: 58025 | H7: 31719 | I7: =G7=R7 -> TRUE | J7: =F7=Q7 -> TRUE | O7: 내수 | P7: 50715 | Q7: 50478 | R7: 58025
E8: 합계 | F8: 65522 | G8: 72550 | H8: 40455 | I8: =G8=R8 -> FALSE | J8: =F8=Q8 -> FALSE | O8: 합계 | P8: 64629 | Q8: 65473 | R8: 72459
D9: MC | E9: 수출 | F9: 52302 | G9: 54375 | H9: 25622 | I9: =G9=R9 -> FALSE | J9: =F9=Q9 -> FALSE | N9: MC | O9: 수출 | P9: 46546 | Q9: 51915 | R9: 54070
E10: 내수 | F10: 54648 | G10: 41887 | H10: 17650 | I10: =G10=R10 -> TRUE | J10: =F10=Q10 -> TRUE | O10: 내수 | P10: 68026 | Q10: 54648 | R10: 41887
E11: 합계 | F11: 106950 | G11: 96262 | H11: 43272 | I11: =G11=R11 -> FALSE | J11: =F11=Q11 -> FALSE | O11: 합계 | P11: 114572 | Q11: 106562 | R11: 95957
B12: 소 계 | E12: 수출 | F12: 170207 | G12: 207473 | H12: 109143 | I12: =G12=R12 -> FALSE | J12: =F12=Q12 -> FALSE | L12: 비자동차부품 | M12: 제품 | N12: 가전용 Switch 등 | O12: 수출 | P12: 547 | Q12: 0 | R12: 0
E13: 내수 | F13: 389650 | G13: 383723 | H13: 194780 | I13: =G13=R13 -> FALSE | J13: =F13=Q13 -> FALSE | M13: 상품 | O13: 내수 | P13: 4868 | Q13: 0 | R13: 0
E14: 합계 | F14: 559857 | G14: 591197 | H14: 303923 | I14: =G14=R14 -> FALSE | J14: =F14=Q14 -> FALSE | O14: 합계 | P14: 5415 | Q14: 0 | R14: 0
A15: 청도대성전자 | B15: 자동차부품 | C15: 제품 | D15: Switch, | E15: 수출 | F15: 8358 | G15: 13998 | H15: 10431 | I15: =G15=R15 -> FALSE | J15: =F15=Q15 -> FALSE | L15: 소 계 | O15: 수출 | P15: 138590 | Q15: 166091 | R15: 200949
A16: 유한공사 | C16: 상품 | D16: Room Lamp 등 | E16: 내수 | F16: 87508 | G16: 91322 | H16: 56054 | I16: =G16=R16 -> FALSE | J16: =F16=Q16 -> FALSE | O16: 내수 | P16: 384565 | Q16: 389649 | R16: 383723
E17: 합계 | F17: 95866 | G17: 105320 | H17: 66485 | I17: =G17=R17 -> FALSE | J17: =F17=Q17 -> FALSE | O17: 합계 | P17: 528570 | Q17: 555740 | R17: 584672
A18: 무석대성전자 | B18: 자동차부품 | C18: 제품 | D18: ABS coil housing,BCM, Switch 등 | E18: 수출 | F18: 11798 | G18: 23398 | H18: 12331 | I18: =G18=R18 -> FALSE | J18: =F18=Q18 -> FALSE | K18: 청도대성전자 | L18: 자동차 및 | M18: 제품 | N18: Switch, Relay 등 | O18: 수출 | P18: 8645 | Q18: 8358 | R18: 13998
A19: 유한공사 | C19: 상품 | E19: 내수 | F19: 40135 | G19: 39505 | H19: 25352 | I19: =G19=R19 -> FALSE | J19: =F19=Q19 -> FALSE | K19: 유한공사 | L19: 비자동차부품 | M19: 상품 | O19: 내수 | P19: 66962 | Q19: 87508 | R19: 91322
E20: 합계 | F20: 51933 | G20: 62904 | H20: 37683 | I20: =G20=R20 -> FALSE | J20: =F20=Q20 -> FALSE | O20: 합계 | P20: 75608 | Q20: 95866 | R20: 105320
A21: Daesung Electric | B21: 자동차부품 | C21: 제품 | D21: Switch, | E21: 수출 | F21: 3049 | G21: 4612 | H21: 3954 | I21: =G21=R21 -> FALSE | J21: =F21=Q21 -> FALSE | K21: 무석대성전자 | L21: 자동차부품 | M21: 제품 | N21: Switch, Relay 등 | O21: 수출 | P21: 7057 | Q21: 11798 | R21: 23398
A22: India Private | C22: 상품 | D22: Audio Panel 등 | E22: 내수 | F22: 30054 | G22: 44372 | H22: 33480 | I22: =G22=R22 -> FALSE | J22: =F22=Q22 -> FALSE | K22: 유한공사 | M22: 상품 | O22: 내수 | P22: 43078 | Q22: 40135 | R22: 39505
A23: Limited | E23: 합계 | F23: 33103 | G23: 48984 | H23: 37433 | I23: =G23=R23 -> FALSE | J23: =F23=Q23 -> FALSE | O23: 합계 | P23: 50134 | Q23: 51933 | R23: 62904
A24: 비고) 대성전기공업㈜ 매출은 Ⅲ.6.가.(1)재무제표 재작성 등 유의사항에 따른 계정과목 재분류에 따라 | K24: 비고) 품목별 매출액은 2014년 제품군 재편에 따라 조정 후 금액임
A25: 재작성함

Sheet CF(연결)
A1: 연 결 현 금 흐 름 표
A2: 제43기 반기 2015년 01월 01일부터 2015년 06월 30일까지
A3: 제42기 반기 2014년 01월 01일부터 2014년 06월 30일까지
A4: 제42기 2014년 01월 01일부터 2014년 12월 31일까지
A5: 제41기 2013년 01월 01일부터 2013년 12월 31일까지
A6: 제40기 2012년 01월 01일부터 2012년 12월 31일까지
A7: 회사명 : 대성전기공업 주식회사와 그 종속기업
B8: 제 40 기 | C8: 제 41 기 | D8: 제42기 | E8: 제43기 반기 | F8: 제42기 반기
A9: Ⅰ.영업활동현금흐름
A10: 1.당기순이익 | B10: 2278194692 | C10: 12095282611 | D10: 17951228918 | E10: 7275649811 | F10: 9237721771
A11: 2.비현금 항목의 조정
A12: 재고자산폐기손실 | B12: 1304314370 | C12: 0 | D12: 0 | E12: 0 | F12: 0
A13: 퇴직급여 | B13: 2825869513 | C13: 3124636778 | D13: 3781544359 | E13: 2075099701 | F13: 1871434141
A14: 감가상각비 | B14: 27615340495 | C14: 29666485532 | D14: 31190193327 | E14: 16973712924 | F14: 15696912464
A15: 무형자산상각비 | B15: 7959752978 | C15: 7640806631 | D15: 7230038267 | E15: 3461177423 | F15: 3615648616
A16: 외화환산이익 | B16: -4063350790 | C16: -7144755369 | D16: -3041578670 | E16: -2447825653 | F16: -2104401417
A17: 외화환산손실 | B17: 5566046633 | C17: 6530627800 | D17: 3924060409 | E17: 1550268036 | F17: 1941670171
A18: 판매보증충당부채전입액 | B18: 11958236601 | C18: 8478016247 | D18: 8009624176 | E18: 3609775726 | F18: 5380269276
A19: 유형자산처분이익 | B19: -402604693 | C19: -555073824 | D19: -468507740 | E19: -294727852 | F19: -73664914
A20: 유형자산처분손실 | B20: 376615133 | C20: 1432122978 | D20: 837206683 | E20: 80626125 | F20: 319674521
A21: 유형자산손상차손 | B21: 0 | C21: 0 | D21: 185325879 | E21: 47258667 | F21: 116036292
A22: 무형자산처분이익 | B22: -71528274 | C22: -117216472 | D22: -3272324 | E22: -1513571 | F22: -3272324
A23: 무형자산손상차손 | B23: 0 | C23: 0 | D23: 530089449 | E23: 4064600 | F23: 434334706
... A25: 대손상각비(환입) | B25: 520839044 | C25: 169657745 | D25: -6745213 | E25: 474167375 | F25: -513045070
A26: 기타의 대손상각비(환입) | B26: - | C26: 1473827476 | D26: -522149911 | E26: - | F26: -
A27: 금융수익 | B27: -1109646265 | C27: -1102821813 | D27: -728115463 | E27: -383069856 | F27: -514083633
A28: 금융원가 | B28: 16492753645 | C28: 12048493747 | D28: 10452219619 | E28: 4711750873 | F28: 5375889067
A29: 파생상품평가손실(이익) | B29: 257830232 | C29: 205678876 | D29: -104778210 | E29: 16544425 | F29: -136664901
A30: 지분법 손실(이익) | B30: -12874266 | C30: 590811004 | D30: -105298978 | E30: -17076365 | F30: -97422003
A31: 잡이익 | B31: -96897634 | C31: - | D31: - | E31: - | F31: -
A32: 법인세비용(혜택) | B32: 1893814540 | C32: 438342545 | D32: 1186573100 | E32: 2495523826 | F32: 491120397
A33: 소 계 | B33: 70884218101 | C33: 62879639881 | D33: 62346428759 | E33: 32355756404 | F33: 31800435389
A34: 3.운전자본 조정
A35: 매출채권 | B35: 24904813783 | C35: 13305408307 | D35: -18707835017 | E35: -5163758612 | F35: 3178257999
A36: 기타수취채권 | B36: 3356349416 | C36: -3973777260 | D36: 5182683347 | E36: 1993630909 | F36: -844554678
A37: 기타유동자산 | B37: -890254646 | C37: -8660324062 | D37: -5492326479 | E37: -8240227052 | F37: 273839072
A38: 기타비유동자산 | B38: 517968904 | C38: -46775921 | D38: -252048829 | E38: -315164563 | F38: 200012726
A39: 재고자산 | B39: 4444880470 | C39: 1842889636 | D39: -11525768758 | E39: -1693278381 | F39: -730589059
A40: 매입채무 | B40: -8049276108 | C40: -2902483390 | D40: 19847831460 | E40: -8759598728 | F40: -5876462219
A41: 기타지급채무 | B41: -5187959756 | C41: -24639002 | D41: 5599410454 | E41: 6924091505 | F41: 4105408210
A42: 기타유동부채 | B42: -327128743 | C42: 2738576869 | D42: -1926161867 | E42: 676025914 | F42: 2087566544
A43: 정부보조금의 사용 | B43: -2451487901 | C43: -759562466 | D43: -216998694 | E43: -106689313 | F43: -76017254
A44: 판매보증충당부채 | B44: -4214491980 | C44: -11623774339 | D44: -10023867967 | E44: -3309576192 | F44: -7375975475
A45: 기타충당부채 | B45: - | C45: 84149005 | D45: -77300708 | E45: - | F45: -77300708
A46: 사외적립자산 | B46: -1473011364 | C46: -3399209688 | D46: -3074373455 | E46: 1372114454 | F46: 950235372
A47: 퇴직금의 지급 | B47: -2771859932 | C47: -1246708938 | D47: -2067210652 | E47: -1857960561 | F47: -1109111414
A48: 소 계 | B48: 7858542143 | C48: -14666231249 | D48: -22733967165 | E48: -18480390620 | F48: -5294690884
A49: 이자의 수취 | B49: 293976206 | C49: 220784112 | D49: 2132612695 | E49: 104943770 | F49: 49422489
A50: 법인세의 납부 | B50: -3235904381 | C50: -2279582596 | D50: -2754547474 | E50: -1538547244 | F50: -1698164708
A51: 영업활동으로 인한 순현금흐름 | B51: 78079026761 | C51: 58249892759 | D51: 56941755733 | E51: 19717412121 | F51: 34094724057
A52: Ⅱ.투자활동현금흐름
A53: 기타금융자산의 처분 | B53: 537495135 | C53: 35094014 | D53: 1062752132 | E53: 68945816 | F53: 354125518
A54: 기타금융자산의 취득 | B54: -470898953 | C54: -1055224338 | D54: -505968145 | E54: -367693880 | F54: -126650137
A55: 단기대여금의 회수 | B55: - | C55: 3756546455 | D55: 2594699313 | E55: 2705723720 | F55: 1632665845
A56: 단기대여금의 증가 | B56: -1981600000 | C56: -4782998330 | D56: -4182973822 | E56: -865920694 | F56: -2109746330
A57: 매도가능금융자산의 감소 | B57: 200030201 | C57: 170032696 | D57: - | E57: - | F57: -
A58: 매도가능금융자산의 취득 | B58: - | C58: - | D58: -1028300 | E58: - | F58: -
A59: 만기보유금융자산의 감소 | B59: - | C59: - | D59: 8463000000 | E59: - | F59: -
A60: 만기보유금융자산의 취득 | B60: - | C60: - | D60: -8020000000 | E60: - | F60: -
A61: 장기대여금의 회수 | B61: 82323996 | C61: 82324004 | D61: - | E61: - | F61: -
A62: 유형자산의 처분 | B62: 4375109210 | C62: 12023783701 | D62: 3520246675 | E62: 500416911 | F62: 968975693
A63: 유형자산의 취득 | B63: -41710461557 | C63: -44360976961 | D63: -52863221337 | E63: -29219144523 | F63: -25180362452
A64: 무형자산의 처분 | B64: 90621346 | C64: 319771628 | D64: 5319500 | E64: 3000000 | F64: 5319500
A65: 무형자산의 취득 | B65: -8331994712 | C65: -5257453321 | D65: -6561271393 | E65: -4276189664 | F65: -3317118383
A66: 배당금의 수취 | B66: 46916686 | C66: 8660808 | D66: - | E66: - | F66: -
A67: 투자활동으로 인한 순현금흐름 | B67: -47162458648 | C67: -39060439644 | D67: -56488445377 | E67: -31450862314 | F67: -27772790746
A68: Ⅲ.재무활동현금흐름
A69: 단기차입금의 차입 | B69: 99259579747 | C69: 76206144709 | D69: 73568270624 | E69: 76648297800 | F69: 63348107921
A70: 단기차입금의 상환 | B70: -130988889946 | C70: -98101021440 | D70: -74697974734 | E70: -75817393455 | F70: -65639821243
A71: 장기차입금의 차입 | B71: 21050281498 | C71: 18567100000 | D71: 658500000 | E71: - | F71: 0
A72: 장기차입금의 상환 | B72: - | C72: -4896716697 | D72: - | E72: - | F72: 0
A73: 임대보증금의 증가 | B73: 48000000 | C73: 500000 | D73: 50000000 | E73: 17500000 | F73: 0
A74: 임대보증금의 감소 | B74: -48000000 | C74: 0 | D74: 0 | E74: -33000000 | F74: 0
A75: 유동화채무의 상환 | B75: -15000000000 | C75: 0 | D75: 0 | E75: 0 | F75: 0
A76: 유동성장기차입금의 상환 | B76: -866666664 | C76: -144444452 | D76: 0 | E76: -5000000000 | F76: 0
A77: 사채의 발행 | B77: - | C77: 49804200000 | D77: 44921300000 | E77: 49979900000 | F77: 0
A78: 사채의 상환 | B78: - | C78: -50000000000 | D78: -35000000000 | E78: -30000000000 | F78: 0
A79: 정부보조금의 수령 | B79: 2310542464 | C79: 0 | D79: 634215472 | E79: 0 | F79: 0
A80: 이자의 지급 | B80: -15847562946 | C80: -11059509193 | D80: -9469111353 | E80: -4290308219 | F80: -4064489215
A81: 재무활동으로 인한 순현금흐름 | B81: -40082715847 | C81: -19623747073 | D81: 665200009 | E81: 11504996126 | F81: -6356202537
A82: Ⅳ.현금및현금성자산의 증감 | B82: -9166147734 | C82: -434293958 | D82: 1118510365 | E82: -228454067 | F82: -34269226
A83: V.환율변동효과 | B83: 839514983 | C83: -868043930 | D83: -515102837 | E83: -372811517 | F83: -298728583
A84: VI.기초 현금및현금성자산 | B84: 13871163102 | C84: 5544530351 | D84: 4242192463 | E84: 4845599991 | F84: 4242192463
A85: VII.기말 현금및현금성자산 | B85: 5544530351 | C85: 4242192463 | D85: 4845599991 | E85: 4244334407 | F85: 3909194654

Sheet CF(별도)
A1: 현 금 흐 름 표
A2: 제43기 반기 2015년 01월 01일부터 2015년 06월 30일까지
A3: 제42기 반기 2014년 01월 01일부터 2014년 06월 30일까지
A4: 제42기 2014년 01월 01일부터 2014년 12월 31일까지
A5: 제41기 2013년 01월 01일부터 2013년 12월 31일까지
A6: 제40기 2012년 01월 01일부터 2012년 12월 31일까지
A7: 회사명 : 대성전기공업 주식회사 | E7: (단위 : 원)
A8: 과 목 | B8: 제 40 기 | C8: 제 41 기 | D8: 제 42 기 | E8: 제 43 기 반기 | F8: 제 42 기 반기
A9: Ⅰ.영업활동현금흐름
A10: 1.당기순이익(손실) | B10: 4240608119 | C10: 12226873385 | D10: 16561119576 | E10: 10196534235 | F10: 8462181433
A11: 2.비현금 항목의 조정
A12: 재고자산폐기손실 | B12: 1304314370 | C12: 0 | D12: 0 | E12: 0 | F12: 0
A13: 퇴직급여 | B13: 2746267555 | C13: 3037008358 | D13: 3701974854 | E13: 2041979592 | F13: 1831649389
A14: 감가상각비 | B14: 20738867867 | C14: 21766783544 | D14: 23080308849 | E14: 12278805441 | F14: 11214198818
A15: 무형자산상각비 | B15: 7649037755 | C15: 7404098920 | D15: 6930586211 | E15: 3069895974 | F15: 3500171096
A16: 외화환산이익 | B16: -1634955840 | C16: -2046833941 | D16: -2703406329 | E16: -2325968748 | F16: -1534369091
A17: 외화환산손실 | B17: 2411414967 | C17: 1358670238 | D17: 2499869534 | E17: 1484568862 | F17: 1693301229
A18: 판매보증충당부채전입액 | B18: 11004711400 | C18: 7646332814 | D18: 7159190049 | E18: 3121228000 | F18: 5095132711
A19: 유형자산처분이익 | B19: -1117707277 | C19: -1148930720 | D19: -426705391 | E19: -18391088 | F19: -209320110
A20: 유형자산처분손실 | B20: 225800497 | C20: 823983234 | D20: 566769170 | E20: 14109033 | F20: 152954407
A21: 유형자산손상차손 | B21: - | C21: - | D21: 185325879 | E21: 47258667 | F21: 116036292
A22: 무형자산처분이익 | B22: -71528274 | C22: -117216472 | D22: -3272324 | E22: -1513571 | F22: -3272324
A23: 무형자산손상차손 | B23: - | C23: - | D23: 530089449 | E23: 4064600 | F23: 434334706
A24: 대손상각비(환입) | B24: 476264051 | C24: 60881455 | D24: - | E24: - | F24: -
A25: 기타의 대손상각비(환입) | C25: 1445492145 | D25: -494955312 | E25: - | F25: -494955312
A26: 금융수익 | B26: -3164239607 | C26: -3794577895 | D26: -2738057029 | E26: -4214581286 | F26: -2592352436
A27: 금융원가 | B27: 13034533243 | C27: 10424964533 | D27: 9110101151 | E27: 3980264818 | F27: 4726004172
A28: 파생상품자산/부채평가이익 | B28: 0 | C28: 0 | D28: 0 | E28: -26631230 | F28: 0
A29: 잡이익 | B29: -15690000 | C29: 0 | D29: -1741853 | E29: -54343630 | F29: -34609083
A30: 법인세비용(혜택) | B30: 781096574 | C30: 14227147 | D30: -165484440 | E30: 648257422 | F30: -383715942
A31: 소 계 | B31: 54368187281 | C31: 46874883360 | D31: 47230592468 | E31: 20049002856 | F31: 23511188522
A32: 3.운전자본 조정
A33: 매출채권 | B33: 19391248843 | C33: 16220763394 | D33: -10879950502 | E33: -13339355901 | F33: 1505574318
A34: 기타수취채권 | B34: -1368525160 | C34: -278987959 | D34: -1811950888 | E34: 4721092900 | F34: 1744429319
A35: 기타유동자산 | B35: -59087293 | C35: -4811332679 | D35: -1450282993 | E35: -5537113424 | F35: -1351878817
A36: 기타비유동자산 | B36: 117600000 | C36: 117600000 | D36: 117600000 | E36: 58800000 | F36: 58800000
A37: 재고자산 | B37: 6150461092 | C37: 4371444904 | D37: -1479347685 | E37: -673155121 | F37: -549536017
A38: 매입채무 | B38: -4789671402 | C38: 2117203034 | D38: 2432568592 | E38: -3492869683 | F38: -5236522066
A39: 기타지급채무 | B39: -5449208 | C39: -923270136 | D39: 2193935962 | E39: 2339955007 | F39: 1960497510
A40: 기타유동부채 | B40: -538700816 | C40: 155054109 | D40: 405703064 | E40: 170612669 | F40: -872137990
A41: 정부보조금의 사용 | B41: -2451487901 | C41: -759562466 | D41: -216998694 | E41: -106689313 | F41: -76017254
A42: 판매보증충당부채 | B42: -3282389965 | C42: -11172414403 | D42: -9099918510 | E42: -2897417253 | F42: -6935740743
A43: 사외적립자산 | B43: -1248539560 | C43: -3388891257 | D43: -3054819093 | E43: 1233426613 | F43: 932890638
A44: 퇴직금의 지급 | B44: -2609500360 | C44: -1188154100 | D44: -2027254040 | E44: -1711201810 | F44: -1091766680
... A46: 이자의 수취 | B46: 193230837 | C46: 133715074 | D46: 1966452702 | E46: 87015184 | F46: 28196426
A47: 법인세의 납부 | B47: -518050439 | C47: -24283920 | D47: -344823338 | E47: - | F47: 41222290
A48: 영업활동으로 인한 순현금흐름 | B48: 67589934068 | C48: 59670640340 | D48: 40542626621 | E48: 11098636959 | F48: 22131380889
A49: Ⅱ.투자활동현금흐름
A50: 기타금융자산의 처분 | B50: 537495135 | C50: 2550740 | D50: 728569000 | E50: 13699216 | F50: 73125000
A51: 기타금융자산의 취득 | B51: -59305800 | C51: -936270994 | D51: -303580308 | E51: -238739256 | F51: -6787358
A52: 단기대여금의 회수 | B52: - | C52: 3756546455 | D52: 2594699313 | E52: 2705723720 | F52: 1632665845
A53: 단기대여금의 증가 | B53: -1981600000 | C53: -4782998330 | D53: -4182973822 | E53: -865920694 | F53: -2109746330
A54: 종속기업주식의 취득 | B54: -699605000 | C54: -16771500000 | D54: - | E54: - | F54: -
A55: 매도가능금융자산의 감소 | B55: 200030201 | C55: 170032696 | D55: - | E55: - | F55: -
A56: 매도가능금융자산의 취득 | B56: - | C56: - | D56: -1028300 | E56: - | F56: -
A57: 만기보유금융자산의 감소 | B57: - | C57: - | D57: 8463000000 | E57: - | F57: -
A58: 만기보유금융자산의 취득 | B58: - | C58: - | D58: -8020000000 | E58: - | F58: -
A59: 장기대여금의 회수 | B59: 82323996 | C59: 82324004 | D59: - | E59: - | F59: -
A60: 유형자산의 처분 | B60: 3853046467 | C60: 11887939287 | D60: 1262127554 | E60: 89421097 | F60: 874155681
A61: 유형자산의 취득 | B61: -30280436993 | C61: -28417043607 | D61: -27174454939 | E61: -18482319381 | F61: -9171824538
A62: 무형자산의 처분 | B62: 90621346 | C62: 319771628 | D62: 5319500 | E62: 3000000 | F62: 5319500
A63: 무형자산의 취득 | B63: -7200710990 | C63: -4500197161 | D63: -6404181251 | E63: -3651220309 | F63: -3091964286
A64: 배당금의 수취 | B64: 2071962236 | C64: 2787485928 | D64: 2104403380 | E64: 3090842529 | F64: 2104403380
A65: 투자활동으로 인한 순현금흐름 | B65: -33386179402 | C65: -36401359354 | D65: -30928099873 | E65: -17335513078 | F65: -9690653106
A66: Ⅲ.재무활동현금흐름
A67: 단기차입금의 차입 | B67: 68766003955 | C67: 39137891595 | D67: 25781066174 | E67: 21993566867 | F67: 29106567268
A68: 단기차입금의 상환 | B68: -98492225101 | C68: -68309632174 | D68: -38047831073 | E68: -26065053368 | F68: -38047831073
A69: 장기차입금의 차입 | B69: 20000000000 | C69: 15829500000 | D69: - | E69: - | F69: -
A70: 임대보증금의 증가 | B70: 48000000 | C70: 500000 | D70: 50000000 | E70: 39900000 | F70: -
A71: 임대보증금의 감소 | B71: -48000000 | C71: - | D71: - | E71: -33000000 | F71: -
A72: 유동화채무의 상환 | B72: -15000000000 | C72: 0 | D72: 0 | E72: 0 | F72: 0
A73: 유동성장기차입금의 상환 | B73: -866666664 | C73: -144444452 | D73: - | E73: -5000000000 | F73: -
A74: 사채의 발행 | B74: - | C74: 49804200000 | D74: 44921300000 | E74: 49979900000 | F74: -
A75: 사채의 상환 | B75: - | C75: -50000000000 | D75: -35000000000 | E75: -30000000000 | F75: -
A76: 정부보조금의 수령 | B76: 2310542464 | C76: - | D76: 634215472 | E76: - | F76: -
A77: 이자의 지급 | B77: -12220822017 | C77: -9577653041 | D77: -8327658656 | E77: -3635281406 | F77: -3545131006
A78: 재무활동으로 인한 순현금흐름 | B78: -35503167363 | C78: -23259638072 | D78: -9988908083 | E78: 7280032093 | F78: -12486394811
A79: Ⅳ.현금및현금성자산의 증감 | B79: -1299412697 | C79: 9642914 | D79: -374381335 | E79: 1043155974 | F79: -45667028
A80: V.외화표시 현금및현금성자산의 환율변동효과 | B80: -142377119 | C80: -107145359 | D80: -295764644 | E80: 1779796 | F80: -266758761
A81: VI.기초 현금및현금성자산 | B81: 2626477407 | C81: 1184687591 | D81: 1087185146 | E81: 417039167 | F81: 1087185146
A82: VII.기말 현금및현금성자산 | B82: 1184687591 | C82: 1087185146 | D82: 417039167 | E82: 1461974937 | F82: 774759357

Sheet 무석>>

Sheet FCF
B2: 현금흐름 분석
C3: 2012년 | D3: 2013년 | E3: 2014년 | F3: 2015년
B4: RMB'000 | C4: 12개월 | D4: 12개월 | E4: 12개월 | F4: 6개월
B5: EBITDA | C5: ='IS(RMB)'!C30 -> 13440859 | D5: ='IS(RMB)'!D30 -> 10965573 | E5: ='IS(RMB)'!E30 -> 32850385 | F5: ='IS(RMB)'!F30 -> 19887912
B6: 운전자본 변동 | C6: =C31 -> -16987805 | D6: =D31 -> -2557557.7 | E6: =E31 -> -7499323.1 | F6: =F31 -> -6160829
B7: CAPEX | C7: =SUM(C8:C9) -> -41287318 | D7: =SUM(D8:D9) -> -53925016 | E7: =SUM(E8:E9) -> -74304860 | F7: =SUM(F8:F9) -> -27954641
B8: 취득 | C8: =C22 -> -41294677 | D8: =D22 -> -54137734 | E8: =E22 -> -74431878 | F8: =F22 -> -28205890
B9: 처분 | C9: =C23 -> 7358.98 | D9: =D23 -> 212717.95 | E9: =E23 -> 127018.05 | F9: =F23 -> 251248.88
B10: FCF | C10: =SUM(C5:C7) -> -44834264 | D10: =SUM(D5:D7) -> -45517001 | E10: =SUM(E5:E7) -> -48953798 | F10: =SUM(F5:F7) -> -14227558
B11: 차입(상환) | C11: =C34 -> 9665820 | D11: =D34 -> 45170499 | E11: =E34 -> 28934082 | F11: =F34 -> 13693750
B12: 세금 | C12: =C39 -> -13846362 | D12: =D39 -> -5661467.7 | E12: =E39 -> 14051370
B13: 환율 | C13: =C42 -> -145335.84 | D13: =D42 -> -785804.3 | E13: =E42 -> 532367.29 | F13: =F42 -> -120042.33
B14: 기타 | C14: =C15-SUM(C10:C13) -> 40886901 | D14: =D15-SUM(D10:D13) -> 6007969.9 | E14: =E15-SUM(E10:E13) -> 5968345.7 | F14: =F15-SUM(F10:F13) -> -2777855.6
B15: 현금흐름 | C15: =C17 -> -8273241.3 | D15: =D17 -> -785804.3 | E15: =E17 -> 532367.29 | F15: =F17 -> -3431706.1
B16: source: 감사 보고서
C17: =C21-B21 -> -8273241.3 | D17: =D21-C21 -> -785804.3 | E17: =E21-D21 -> 532367.29 | F17: =F21-E21 -> -3431706.1
A21: 현금 | B21: 14817388 | C21: ='BS(RMB,)'!C6 -> 6544146.5 | D21: ='BS(RMB,)'!D6 -> 5758342.2 | E21: ='BS(RMB,)'!E6 -> 6290709.5 | F21: ='BS(RMB,)'!F6 -> 2859003.5
B22: CAPEX_취득 | C22: -41294677 | D22: -54137734 | E22: -74431878 | F22: -28205890
B23: CAPEX_처분 | C23: 7358.98 | D23: 212717.95 | E23: 127018.05 | F23: 251248.88
B25: 2011년 | C25: 2012년 | D25: 2013년 | E25: 2014년 | F25: 2015년
A26: RMB'000 | B26: 11월31일 | C26: 12월 31일 | D26: 12월 31일 | E26: 12월 31일 | F26: 6월 30일
A27: 매출채권 | B27: 58631323 | C27: 80351270 | D27: 86422336 | E27: 98504881 | F27: 1.2749784e+08
A28: 재고자산 | B28: 63527066 | C28: 61491932 | D28: 64345113 | E28: 70443675 | F28: 71854417
A29: 매입채무 | B29: 45082989 | C29: 47779997 | D29: 54146686 | E29: 64828470 | F29: 89071341
A30: NWC | B30: =B27+B28-B29 -> 77075400 | C30: =C27+C28-C29 -> 94063205 | D30: =D27+D28-D29 -> 96620763 | E30: =E27+E28-E29 -> 1.0412009e+08 | F30: =F27+F28-F29 -> 1.1028091e+08
C31: =B30-C30 -> -16987805 | D31: =C30-D30 -> -2557557.7 | E31: =D30-E30 -> -7499323.1 | F31: =E30-F30 -> -6160829
B32: 차입 | C32: 111059000 | D32: 1.9114237e+08 | E32: 1.9622792e+08 | F32: 48646959
B33: 상환 | C33: -101393180 | D33: -1.4597187e+08 | E33: -1.6729384e+08 | F33: -34953209
C34: =SUM(C32:C33) -> 9665820 | D34: =SUM(D32:D33) -> 45170499 | E34: =SUM(E32:E33) -> 28934082 | F34: =SUM(F32:F33) -> 13693750
B36: 세금 | C36: 2012 | D36: 2013 | E36: 2014 | F36: 2015
B37: refund | D37: 3939851.9 | E37: 16867473
B38: paid | C38: 13846362 | D38: 9601319.6 | E38: 2816102.9
C39: =C37-C38 -> -13846362 | D39: =D37-D38 -> -5661467.7 | E39: =E37-E38 -> 14051370
B42: 환율 | C42: -145335.84 | D42: -785804.3 | E42: 532367.29 | F42: -120042.33

Sheet IS
B2: 손익계산서_무석 | H2: 연결계정코드 | I2: 연결계정명 | J2: 2012년 | K2: 2013년 | L2: 2014년 | M2: 2015년 6개월
C3: 2012년 | D3: 2013년 | E3: 2014년 | F3: 2015년 | H3: 41000000 | I3: 매출 | J3: 50134470589 | K3: 51932650497 | L3: 62903783760 | M3: 37682967779
B4: 백만원 | C4: 12개월 | D4: 12개월 | E4: 12개월 | F4: 6개월 | H4: 41010000 | I4: 제품매출 | J4: 46077062082 | K4: 46217012631 | L4: 58882890707 | M4: 35766529976
B5: 매출액 | C5: =J3 -> 50134470589 | D5: =K3 -> 51932650497 | E5: =L3 -> 62903783760 | F5: =M3 -> 37682967779 | H5: 41010020 | I5: 제품매출:외화 | J5: 46077062082 | K5: 46217012631 | L5: 58882890707 | M5: 35766529976
B6: 제품 | C6: =J4 -> 46077062082 | D6: =K4 -> 46217012631 | E6: =L4 -> 58882890707 | F6: =M4 -> 35766529976 | H6: 41011000 | I6: 상품매출 | J6: 4057408507 | K6: 4721617013 | L6: 3890202059 | M6: 1479226945
B7: 상품 | C7: =J6 -> 4057408507 | D7: =K6 -> 4721617013 | E7: =L6 -> 3890202059 | F7: =M6 -> 1479226945 | H7: 41011020 | I7: 상품매출:외화 | J7: 4057408507 | K7: 4721617013 | L7: 3890202059 | M7: 1479226945
B8: 기타 | C8: =J8 -> 0 | D8: =K8 -> 994020853 | E8: =L8 -> 130690994 | F8: =M8 -> 437210858 | H8: 41089000 | I8: 기타매출 | J8: 0 | K8: 994020853 | L8: 130690994 | M8: 437210858
B9: 매출원가 | C9: =J10 -> 45284652457 | D9: =K10 -> 47389383262 | E9: =L10 -> 54416712509 | F9: =M10 -> 32454251989 | H9: 41089990 | I9: 기타매출 | J9: 0 | K9: 994020853 | L9: 130690994 | M9: 437210858
B10: 매출총이익 | C10: =J14 -> 4849818132 | D10: =K14 -> 4543267235 | E10: =L14 -> 8487071251 | F10: =M14 -> 5228715790 | H10: 42100000 | I10: 매출원가 | J10: 45284652457 | K10: 47389383262 | L10: 54416712509 | M10: 32454251989
B11: 매출총이익% | C11: =C10/C5 -> 0.096736199 | D11: =D10/D5 -> 0.087483831 | E11: =E10/E5 -> 0.13492147 | F11: =F10/F5 -> 0.13875541 | H11: 42010010 | I11: 제품매출원가 | J11: 41305957710 | K11: 42349213255 | L11: 50694765776 | M11: 30764757903
B12: 판매관리비 | C12: =J15 -> 4676706678 | D12: =K15 -> 4816674103 | E12: =L15 -> 5616292581 | F12: =M15 -> 3208380350 | H12: 42011010 | I12: 상품매출원가 | J12: 3978694747 | K12: 4157916935 | L12: 3636502347 | M12: 1392095611
B13: 인건비 | C13: =SUM(J16,J17,J25) -> 1469541488 | D13: =SUM(K16,K17,K25) -> 1409641772 | E13: =SUM(L16,L17,L25) -> 864497139 | F13: =SUM(M16,M17,M25) -> 491962077 | H13: 42089990 | I13: 기타매출원가 | J13: 0 | K13: 882253072 | L13: 85444386 | M13: 297398475
B14: 운반비 | C14: =J18 -> 453138342 | D14: =K18 -> 572859305 | E14: =L18 -> 393730669 | F14: =M18 -> 237559255 | H14: 49000000 | I14: 매출총이익 | J14: 4849818132 | K14: 4543267235 | L14: 8487071251 | M14: 5228715790
B15: 경상개발비 | C15: =J33 -> 572269457 | D15: =K33 -> 984744400 | E15: =L33 -> 1761314382 | F15: =M33 -> 1261330476 | H15: 60000000 | I15: 판매비와관리비 | J15: 4676706678 | K15: 4816674103 | L15: 5616292581 | M15: 3208380350
B16: 지급수수료 | C16: =J28 -> 389968935 | D16: =K28 -> 806193236 | E16: =L28 -> 1586293666 | F16: =M28 -> 529503423 | H16: 61000100 | I16: 급료와임금 | J16: 997697953 | K16: 930891192 | L16: 435703681 | M16: 276548547
B17: 품질보증충당부채전입액 | C17: =J38 -> 4099029 | D17: =K38 -> 144741184 | E17: =L38 -> 102558000 | F17: =M38 -> 97102500 | H17: 61000400 | I17: 잡급 | J17: 68810446 | K17: 69678063 | L17: 68621558 | M17: 34745040
B18: D&A | C18: =J19+J36 -> 273494087 | D18: =K19+K36 -> 207138558 | E18: =L19+L36 -> 150677496 | F18: =M19+M36 -> 87687934 | H18: 61000600 | I18: 운반비 | J18: 453138342 | K18: 572859305 | L18: 393730669 | M18: 237559255
B19: A/S비 | C19: =J37 -> 377324220 | D19: =K37 -> 0 | E19: =L37 -> 68039531 | F19: =M37 -> 82107118 | H19: 61000700 | I19: 감가상각비 | J19: 184846795 | K19: 127474619 | L19: 122331731 | M19: 68822320
B20: 대손상각비(환입) | C20: =J39+J35 -> 168806397 | D20: =K39+K35 -> -165403169 | E20: =L39+L35 -> 4549435 | F20: =M39+M35 -> 0 | H20: 61000800 | I20: 수선비 | J20: 21023581 | K20: 11720909 | L20: 15703339 | M20: 6070204
B21: 기타 | C21: =SUM(J20,J21,J22,J23,J24,J26,J27,J29,J30,J31,J32,J34,J40) -> 968064723 | D21: =SUM(K20,K21,K22,K23,K24,K26,K27,K29,K30,K31,K32,K34,K40) -> 856758817 | E21: =SUM(L20,L21,L22,L23,L24,L26,L27,L29,L30,L31,L32,L34,L40) -> 684632263 | F21: =SUM(M20,M21,M22,M23,M24,M26,M27,M29,M30,M31,M32,M34,M40) -> 421127567 | H21: 61000900 | I21: 소모품비 | J21: 31362480 | K21: 42937003 | L21: 34632549 | M21: 19768049
B22: 영업이익 | C22: =J41 -> 173111454 | D22: =K41 -> -273406868 | E22: =L41 -> 2870778670 | F22: =M41 -> 2020335440 | H22: 61001000 | I22: 세금과공과 | J22: 374452851 | K22: 255666718 | L22: 233532010 | M22: 188366470
B23: 영업이익% | C23: =C22/C5 -> 0.0034529427 | D23: =D22/D5 -> -0.0052646431 | E23: =E22/E5 -> 0.045637615 | F23: =F22/F5 -> 0.053614021 | H23: 61001200 | I23: 임차료 | J23: 58813110 | K23: 52208330 | L23: 10919578 | M23: 5872503
B24: 영업외수익 | C24: =J42+J54 -> 2962163239 | D24: =K42+K54 -> 2872718685 | E24: =L42+L54 -> 3275940091 | F24: =M42+M54 -> 1695377647 | H24: 61001300 | I24: 보험료 | J24: 30728002 | K24: 34107030 | L24: 29776662 | M24: 19468354
B25: 영업외비용 | C25: =J47+J63 -> 1606122476 | D25: =K47+K63 -> 1535865147 | E25: =L47+L63 -> 3162587491 | F25: =M47+M63 -> 1715025584 | H25: 61001400 | I25: 복리후생비 | J25: 403033089 | K25: 409072517 | L25: 360171900 | M25: 180668490
B26: 법인세비용 | C26: =J74 -> -75934266 | D26: =K74 -> -290963756 | E26: =L74 -> 463335816 | F26: =M74 -> 750009594 | H26: 61001500 | I26: 여비교통비 | J26: 130117563 | K26: 137641153 | L26: 29151383 | M26: 39466864
B27: 당기순이익 | C27: =J75 -> 1605086483 | D27: =K75 -> 1354410426 | E27: =L75 -> 2520795454 | F27: =M75 -> 1250677909 | H27: 61001600 | I27: 통신비 | J27: 49942644 | K27: 58614975 | L27: 63600997 | M27: 27715778
B28: 당기순이익% | C28: =C27/C5 -> 0.032015626 | D28: =D27/D5 -> 0.026080133 | E28: =E27/E5 -> 0.040073829 | F28: =F27/F5 -> 0.033189475 | H28: 61001900 | I28: 지급수수료 | J28: 389968935 | K28: 806193236 | L28: 1586293666 | M28: 529503423
B29: D&A | C29: =C18+C32*C33*1000 -> 2.4142156e+09 | D29: =D18+D32*D33*1000 -> 2.2675869e+09 | E29: =E18+E32*E33*1000 -> 2.7443376e+09 | F29: =F18+F32*F33*1000 -> 1.4908754e+09 | H29: 61002000 | I29: 접대비 | J29: 52541359 | K29: 61132693 | L29: 78147372 | M29: 42181096
B30: EBITDA | C30: =C22+C29 -> 2.587327e+09 | D30: =D22+D29 -> 1.9941801e+09 | E30: =E22+E29 -> 5.6151163e+09 | F30: =F22+F29 -> 3.5112108e+09 | H30: 61002100 | I30: 도서인쇄비 | J30: 6520199 | K30: 6661887 | L30: 7178175 | M30: 1850887
B31: EBITDA(%) | C31: =C30/C5 -> 0.051607746 | D31: =D30/D5 -> 0.038399351 | E31: =E30/E5 -> 0.08926516 | F31: =F30/F5 -> 0.093177661 | H31: 61002200 | I31: 교육훈련비 | J31: 25352054 | K31: 40770764 | L31: 61319389 | M31: 21133501
B32: 매출원가 D&A(천RMB) | C32: =마진!F22 -> 10939.988 | D32: =마진!H22 -> 11337.658 | E32: =마진!J22 -> 15173.815 | F32: =마진!L22 -> 7947.8188 | H32: 61002300 | I32: 차량유지비 | J32: 99200936 | K32: 90263805 | L32: 62842876 | M32: 19414695
B33: 환율 | C33: =C5/(C35*1000) -> 195.6786 | D33: =D5/(D35*1000) -> 181.73493 | E33: =E5/(E35*1000) -> 170.93 | F33: =F5/(F35*1000) -> 176.55 | H33: 61002500 | I33: 경상개발비 | J33: 572269457 | K33: 984744400 | L33: 1761314382 | M33: 1261330476
H34: 61002700 | I34: 광고선전비 | J34: 27685881 | K34: 4871630 | L34: 88029 | M34: 0
B35: 매출액_RMB | C35: =마진!F8 -> 256208.25 | D35: =마진!H8 -> 285760.43 | E35: =마진!J8 -> 368009.03 | F35: =마진!L8 -> 213440.77 | H35: 61002900 | I35: 대손상각비 | J35: 168806397 | K35: 0 | L35: 4549435 | M35: 0
H36: 61003000 | I36: 무형자산상각비 | J36: 88647292 | K36: 79663939 | L36: 28345765 | M36: 18865614
C37: =C5=SUM(C6,C7,C8) -> TRUE | D37: =D5=SUM(D6,D8) -> FALSE | E37: =E5=SUM(E6,E8) -> FALSE | F37: =F5=SUM(F6,F8) -> FALSE | H37: 61003500 | I37: A/S 비 | J37: 377324220 | K37: 0 | L37: 68039531 | M37: 82107118
C38: =C10=C5-C9 -> TRUE | D38: =D10=D5-D9 -> TRUE | E38: =E10=E5-E9 -> TRUE | F38: =F10=F5-F9 -> TRUE | H38: 61003800 | I38: 품질보증충당부채전입액 | J38: 4099029 | K38: 144741184 | L38: 102558000 | M38: 97102500
C39: =C12=SUM(C15,C16,C13,C14,C19,C20,C18,C17,C21) -> TRUE | D39: =D12=SUM(D15,D16,D13,D14,D19,D20,D18,D17,D21) -> TRUE | E39: =E12=SUM(E15,E16,E13,E14,E19,E20,E18,E17,E21) -> TRUE | F39: =F12=SUM(F15,F16,F13,F14,F19,F20,F18,F17,F21) -> TRUE | H39: 71101800 | I39: 대손충당금환입 | J39: 0 | K39: -165403169 | L39: 0 | M39: 0
C40: =C22=C10-C12 -> TRUE | D40: =D22=D10-D12 -> TRUE | E40: =E22=E10-E12 -> TRUE | F40: =F22=F10-F12 -> TRUE | H40: 61004100 | I40: 기타판관비 | J40: 60324063 | K40: 60161920 | L40: 57739904 | M40: 29819166
C41: =C27=C22+C24-C25-C26 -> TRUE | D41: =D27=D22+D24-D25-D26 -> TRUE | E41: =E27=E22+E24-E25-E26 -> TRUE | F41: =F27=F22+F24-F25-F26 -> TRUE | H41: 70000000 | I41: 영업이익 | J41: 173111454 | K41: -273406868 | L41: 2870778670 | M41: 2020335440
H42: 71000000 | I42: 기타수익 | J42: 2637850952 | K42: 2318127369 | L42: 3183996561 | M42: 1536911056
B43: 569796209 | C43: 993089459 | D43: 1765593366 | E43: 1280666024 | H43: 71100300 | I43: 외환차익(영업활동) | J43: 151542997 | K43: 80426471 | L43: 114136321 | M43: 57059329
B44: 572269457 | C44: 984744400 | D44: 1761314382 | E44: 1261330476 | H44: 71100400 | I44: 외화환산이익(영업활동) | J44: -4548224 | K44: 35721811 | L44: -32711312 | M44: 62330826
B45: =B43/B44 -> 0.99567818 | H45: 71100500 | I45: 유형자산처분이익 | J45: 0 | K45: 444507 | L45: 3801687 | M45: 375654
B46: =B44/C5 -> 0.01141469 | C46: =C44/D5 -> 0.018961952 | D46: =D44/E5 -> 0.028000134 | E46: =E44/F5 -> 0.033472164 | H46: 71102200 | I46: 잡이익(영업활동) | J46: 2490856179 | K46: 2201534580 | L46: 3098769865 | M46: 1417145247
H47: 72000000 | I47: 기타비용 | J47: 599382994 | K47: 519036798 | L47: 2395408604 | M47: 1187613537
H48: 72100100 | I48: 외환차손(영업활동) | J48: 125739151 | K48: 121041905 | L48: 102645220 | M48: 307384939
H49: 72100200 | I49: 외화환산손실(영업활동) | J49: -57714577 | K49: 11138782 | L49: 81016687 | M49: -89913449
H50: 72100300 | I50: 유형자산처분손실 | J50: 36748703 | K50: 5568215 | L50: 0 | M50: 5721071
H51: 72100400 | I51: 유형자산폐기손실 | J51: 9882476 | K51: 91797351 | L51: 663196 | M51: 48652263
H52: 72102600 | I52: 잡손실(영업활동) | J52: 484727241 | K52: 289490545 | L52: 2211083501 | M52: 915768713
H53: 72900000 | I53: 조정영업이익 | J53: 2211579412 | K53: 1525683703 | L53: 3659366627 | M53: 2369632959
H54: 73000000 | I54: 영업외수익 | J54: 324312287 | K54: 554591316 | L54: 91943530 | M54: 158466591
H55: 73100000 | I55: 금융수익 | J55: 34103128 | K55: 13843610 | L55: 16236892 | M55: 4268859
H56: 73100100 | I56: 이자수익 | J56: 34103128 | K56: 13843610 | L56: 16236892 | M56: 4268859
H57: 73110000 | I57: 기타 영업외수익 | J57: 290209159 | K57: 540747706 | L57: 75706638 | M57: 154197732
H58: 73110200 | I58: 외환차익(비영업활동) | J58: 19550167 | K58: 555049621 | L58: 16851794 | M58: 93842107
H59: 73110300 | I59: 외화환산이익(비영업활동) | J59: 88679898 | K59: -164236860 | L59: -64431412 | M59: 37518499
H60: 73110800 | I60: 파생상품자산/부채 평가이익(비영업활동) | J60: 0 | K60: 0 | L60: 41680597 | M60: 0
H61: 73110900 | I61: 파생상품자산/부채 거래이익(비영업활동) | J61: 0 | K61: 0 | L61: 47128307 | M61: 0
H62: 73119900 | I62: 기타영업외수익 | J62: 181979094 | K62: 149934945 | L62: 34477352 | M62: 22837126
H63: 74000000 | I63: 영업외비용 | J63: 1006739482 | K63: 1016828349 | L63: 767178887 | M63: 527412047
H64: 74100000 | I64: 금융비용 | J64: 730139186 | K64: 708289815 | L64: 642594360 | M64: 367873842
H65: 74100100 | I65: 이자비용 | J65: 730139186 | K65: 708289815 | L65: 642594360 | M65: 367873842
H66: 74110000 | I66: 기타 영업외비용 | J66: 276600296 | K66: 308538534 | L66: 124584527 | M66: 159538205
H67: 74110200 | I67: 외환차손(비영업활동) | J67: 13772781 | K67: 40909241 | L67: 11481108 | M67: 3970945
H68: 74110300 | I68: 외화환산손실(비영업활동) | J68: 147306240 | K68: -15024927 | L68: 39297257 | M68: 25633768
H69: 74110800 | I69: 파생상품자산/부채 평가손실(비영업활동) | J69: 103924988 | K69: 49105198 | L69: 0 | M69: 17368459
H70: 74110900 | I70: 파생상품자산/부채 거래손실(비영업활동) | J70: 0 | K70: 184534397 | L70: 34186000 | M70: 43051011
H71: 74119900 | I71: 기타영업외비용 | J71: 11596287 | K71: 49014625 | L71: 39620162 | M71: 69514022
H72: 75000000 | I72: 법인세비용차감전계속사업손익 | J72: 1529152217 | K72: 1063446670 | L72: 2984131270 | M72: 2000687503
H73: 76000000 | I73: 계속사업손익법인세비용 | J73: -75934266 | K73: -290963756 | L73: 463335816 | M73: 750009594
H74: 76100000 | I74: 법인세비용 | J74: -75934266 | K74: -290963756 | L74: 463335816 | M74: 750009594
H75: 88000000 | I75: 총당기순이익 | J75: 1605086483 | K75: 1354410426 | L75: 2520795454 | M75: 1250677909

Sheet BS
B2: 재무상태표_무석 | I2: 연결계정코드 | J2: 연결계정명 | K2: 2012년 | L2: 2013년 | M2: 2014년 | N2: 2015년 6월말 | S2: 中國計定科目 | T2: 2012년말 | U2: 2013년말 | W2: 中國計定科目 | X2: 2014년말 | Y2: 2015년 6월말
C3: 2012년 | D3: 2013년 | E3: 2014년 | F3: 2015년 | I3: 10000000 | J3: 자산 | K3: 47161263465 | L3: 58015489673 | M3: 70919652314 | N3: 80443477566 | S3: 1.資 産 | T3: 2.7438482e+08 | U3: 3.3275753e+08 | W3: 1.資 産 | X3: 4.0051574e+08 | Y3: 4.4395126e+08
B4: 백만원 | C4: 12월 31일 | D4: 12월 31일 | E4: 12월 31일 | F4: 6월 30일 | I4: 11000000 | J4: 유동자산 | K4: 26714724266 | L4: 32023904562 | M4: 33649507707 | N4: 39071492039 | W4: (1)流 動 資 産 | X4: 1.8991094e+08 | Y4: 2.1579528e+08
B5: 유동자산 | C5: =K4 -> 26714724266 | D5: =L4 -> 32023904562 | E5: =M4 -> 33649507707 | F5: =N4 -> 39071492039 | J5: 당좌자산 | K5: 15033614715 | L5: 16193311195 | M5: 18875818716 | N5: 23985736215 | S5: (1)流 動 資 産 | T5: 1.554266e+08 | U5: 1.8365681e+08 | W5: 1)現 金 | X5: 37000.27 | Y5: 8615.71
B6: 현금및현금성자산 | C6: =K6 -> 1124807905 | D6: =L6 -> 1002469799 | E6: =M6 -> 1112260350 | F6: =N6 -> 517736935 | I6: 11101000 | J6: 현금및현금성자산 | K6: 1124807905 | L6: 1002469799 | M6: 1112260350 | N6: 517736935 | T6: =T7+T9 -> 6544146.5 | U6: =U7+U9 -> 5758342.2 | W6: (R. M. B) | X6: 37000.27 | Y6: 8615.71
B7: 매출채권 | C7: =K10+K13 -> 13810776245 | D7: =L10+L13 -> 15045264398 | E7: =M10+M13 -> 17416648030 | F7: =N10+N13 -> 23088583594 | I7: 11101001 | J7: 현금 | K7: 272065 | L7: 194528 | M7: 6542018 | N7: 1560219 | S7: 1)現 金 | T7: 1582.88 | U7: 1117.4 | W7: 2)銀 行 存 款 | X7: 6253709.2 | Y7: 2850387.7
B8: 재고자산 | C8: =K20 -> 10569233260 | D8: =L20 -> 11201840784 | E8: =M20 -> 12455146090 | F8: =N20 -> 13012116352 | I8: 11101007 | J8: 외화기타 | K8: 1124535840 | L8: 1002275271 | M8: 1105718332 | N8: 516176716 | S8: (R. M. B) | T8: 1582.88 | U8: 1117.4 | W8: (R. M. B) | X8: 4095024.8 | Y8: 1121758
B9: 기타유동자산 | C9: =SUM(K15,K31,K19) -> 1209906856 | D9: =SUM(L15,L31,L19) -> 4774329581 | E9: =SUM(M15,M31,M19) -> 2665453237 | F9: =SUM(N15,N31,N19) -> 2453055158 | I9: 11110000 | J9: 매출채권 및 기타채권 | K9: 13908806810 | L9: 15190841396 | M9: 17720443955 | N9: 23467999280 | S9: 2)銀 行 存 款 | T9: 6542563.7 | U9: 5757224.8 | W9: (U. S. D) | X9: 2158423.5 | Y9: 1185979
B10: 비유동자산 | C10: =K36 -> 20446539199 | D10: =L36 -> 25991585111 | E10: =M36 -> 37270144607 | F10: =N36 -> 41371985527 | I10: 11111000 | J10: 매출채권 | K10: 13974287428 | L10: 15049198933 | M10: 17425349975 | N10: 23097496185 | S10: (R. M. B) | T10: 5811976 | U10: 2930748.1 | W10: (E. U. R) | X10: 261.02 | Y10: 542650.72
B11: 유형자산 | C11: =K40 -> 15976795669 | D11: =L40 -> 20384658401 | E11: =M40 -> 30926546063 | F11: =N40 -> 34936947543 | I11: 11111002 | J11: 외화외상매출금 | K11: 9158046035 | L11: 11571340785 | M11: 15925346978 | N11: 21829866185 | S11: (U. S. D) | T11: 526941.49 | U11: 693794.6 | W11: 3)應 收 票 据 | X11: 8483700 | Y11: 7000000
B12: 무형자산 | C12: =K64 -> 1021538278 | D12: =L64 -> 2095456222 | E12: =M64 -> 2384216778 | F12: =N64 -> 2447890154 | I12: 11111003 | J12: 받을어음 | K12: 4816241393 | L12: 3477858148 | M12: 1500002997 | N12: 1267630000 | S12: (E. U. R) | T12: 203646.12 | U12: 2132682.1 | W12: 4)應 收 帳 款 | X12: 90070397 | Y12: 1.2054705e+08
B13: 기타비유동자산 | C13: =K70+K73+K38 -> 3448205252 | D13: =L70+L73+L38 -> 3511470488 | E13: =M70+M73+M38 -> 3959381766 | F13: =N70+N73+N38 -> 3987147830 | I13: 11111100 | J13: (매출채권 대손충당금) | K13: -163511183 | L13: -3934535 | M13: -8701945 | N13: -8912591 | S13: 3)應 收 票 据 | T13: 28020953 | U13: 19977357 | W13: 5)坏账准备 | X13: -49216.36 | Y13: -49216.36
B14: 자산총계 | C14: =K3 -> 47161263465 | D14: =L3 -> 58015489673 | E14: =M3 -> 70919652314 | F14: =N3 -> 80443477566 | I14: 11111102 | J14: (대손충당금:외화외상매출금) | K14: -163511183 | L14: -3934535 | M14: -8701945 | N14: -8912591 | S14: 4)應 收 帳 款 | T14: 53281627 | U14: 66467579 | W14: 6)預 付 貨 款 | X14: 8304987.2 | Y14: 7760995.9
B15: 유동부채 | C15: =K75 -> 20802310901 | D15: =L75 -> 33032953836 | E15: =M75 -> 43409271335 | F15: =N75 -> 51174969569 | I15: 11111701 | J15: 미수금 | K15: 98030565 | L15: 145576998 | M15: 303795925 | N15: 379415686 | S15: 5)坏账准备 | T15: -951310.12 | U15: -22600.58 | W15: 7)其 他 應 收 款 | X15: 947383.99 | Y15: 2324064.1
B16: 매입채무 | C16: =K77 -> 8212425826 | D16: =L77 -> 9426396602 | E16: =M77 -> 11462321751 | F16: =N77 -> 16129929084 | I16: 11111801 | J16: (미수금대손충당금) | K16: 0 | L16: 0 | M16: 0 | N16: 0 | S16: 6)預 付 貨 款 | T16: 6301006.3 | U16: 22505091 | W16: 8)待 灘 費 用 | X16: 339375.23 | Y16: 770923.32
B17: 단기차입금 | C17: =K85 -> 9399060138 | D17: =L85 -> 19222626909 | E17: =M85 -> 24718570603 | F17: =N85 -> 27773665899 | I17: 11120000 | J17: (유동성)당기손익인식금융자산 | K17: 0 | L17: 0 | M17: 43114411 | N17: 0 | S17: 7)其 他 應 收 款 | T17: 570343.06 | U17: 1035202.4 | W17: 9)應 收 补 贴 款 | X17: 958078.07 | Y17: 76039.38
B18: 미지급금 | C18: =K80 -> 2283665573 | D18: =L80 -> 3321996113 | E18: =M80 -> 5175075565 | F18: =N80 -> 4994577782 | I18: 11150000 | J18: (유동성)위험회피파생상품자산 | K18: 0 | L18: 0 | M18: 43114411 | N18: 0 | S18: 8)待 灘 費 用 | T18: 167903.96 | U18: 374845.28 | W18: 10)存 貨 | X18: 74321675 | Y18: 74506417
B19: 기타유동부채 | C19: =SUM(K87,K81,K83) -> 907159364 | D19: =SUM(L87,L81,L83) -> 1061934212 | E19: =SUM(M87,M81,M83) -> 2053303416 | F19: =SUM(N87,N81,N83) -> 2276796804 | I19: 11151001 | J19: (유동성)공정가치위험회피파생상품자산:금융 | K19: 0 | L19: 0 | M19: 43114411 | N19: 0 | S19: 10)存 貨 | T19: 61491932 | U19: 67560993 | W19: (部 品) | X19: 30515722 | Y19: 31232712
B20: 비유동부채 | C20: =K93 -> 4851480492 | D20: =L93 -> 2923167361 | E20: =M93 -> 2901970533 | F20: =N93 -> 3069372668 | I20: 11160000 | J20: 재고자산 | K20: 10569233260 | L20: 11201840784 | M20: 12455146090 | N20: 13012116352 | S20: (主 要 材 料) | T20: 17095250 | U20: 23687083 | W20: (副 资 材) | X20: 825606.16 | Y20: 747001.55
B21: 장기차입금 | C21: =K94 -> 4812640000 | D21: =L94 -> 2653523303 | E21: =M94 -> 2704750975 | F21: =N94 -> 2767779560 | I21: 11161001 | J21: 상품 | K21: 1684970993 | L21: 72394059 | M21: 72624078 | N21: 186595237 | S21: (補 助 材 料) | T21: 546730.82 | U21: 840172.9 | W21: （原 资 材） | X21: 2822038.9 | Y21: 2761272.5
B22: 판매보증충당부채 | C22: =K96 -> 38840492 | D22: =L96 -> 269644058 | E22: =M96 -> 197219558 | F22: =N96 -> 301593108 | I22: 11161101 | J22: (상품평가충당금) | K22: 0 | L22: 0 | M22: 0 | N22: 0 | S22: （原 资 材） | T22: 1491727.2 | U22: 2423991.8 | W22: (在 工 品) | X22: 0 | Y22: 0
B23: 부채총계 | C23: =K74 -> 25653791393 | D23: =L74 -> 35956121197 | E23: =M74 -> 46311241868 | F23: =N74 -> 54244342237 | I23: 11161201 | J23: 제품 | K23: 4124596175 | L23: 5826848529 | M23: 5981731857 | N23: 6416410823 | S23: (在 工 品) | T23: 0 | U23: 0 | W23: (製 品) | X23: 32201615 | Y23: 33666533
B24: 자본금 | C24: =K100 -> 7113847214 | D24: =L100 -> 12836847214 | E24: =M100 -> 12836847214 | F24: =N100 -> 12836847214 | I24: 11161301 | J24: (제품평가충당금) | K24: -22029255 | L24: -230660149 | M24: -288164247 | N24: -319738341 | S24: (製 品) | T24: 23868786 | U24: 32145375 | W24: (商 品) | X24: 4288746.4 | Y24: 3682400.6
B25: 이익잉여금 | C25: =K104 -> 14361106659 | D25: =L104 -> 8926938564 | E25: =M104 -> 11050512418 | F25: =N104 -> 12027793399 | I25: 11161401 | J25: 반제품 | K25: 3105530554 | L25: 4356378816 | M25: 5619417007 | N25: 5978084273 | S25: (商 品) | T25: 9803182.4 | U25: 3631722.1 | W25: (在 涂 品) | X25: 3667945.6 | Y25: 2416497.1
B26: 기타자본 | C26: =K102 -> 32518199 | D26: =L102 -> 295582698 | E26: =M102 -> 721050814 | F26: =N102 -> 1334494716 | I26: 11161501 | J26: (반제품평가충당금) | K26: -167199066 | L26: -232694462 | M26: -223932190 | N26: -322152440 | S26: (在 涂 品) | T26: 8686256 | U26: 4832647.3 | W26: 11)交易性金融资产 | X26: 243846 | Y26: 0
B27: 자본총계 | C27: =K98 -> 21507472072 | D27: =L98 -> 22059368476 | E27: =M98 -> 24608410446 | F27: =N98 -> 26199135329 | I27: 11161802 | J27: 원재료 | K27: 355926261 | L27: 576437432 | M27: 650628847 | N27: 648635302 | S27: (2)固 定 資 産 | T27: 86145367 | U27: 1.0429589e+08 | W27: (2)固 定 資 産 | X27: 1.3080492e+08 | Y27: 1.4046686e+08
B28: 자본과부채총계 | C28: =K74+K98 -> 47161263465 | D28: =L74+L98 -> 58015489673 | E28: =M74+M98 -> 70919652314 | F28: =N74+N98 -> 80443477566 | I28: 11161901 | J28: (원재료평가충당금) | K28: -5556090 | L28: -8179004 | M28: -5688720 | N28: -13321964 | S28: 1）固定资产_房屋建筑物 | T28: 20582009 | U28: 20970009 | W28: 1）固定资产_房屋建筑物 | X28: 20970009 | Y28: 20970009
B29: Net debt | C29: =C21+C17-C6 -> 13086892233 | D29: =D21+D17-D6 -> 20873680413 | E29: =E21+E17-E6 -> 26311061228 | F29: =F21+F17-F6 -> 30023708524 | I29: 11162200 | J29: 미착품 | K29: 1492993688 | L29: 841315563 | M29: 648529458 | N29: 437603462 | S29: (累 計 折 舊) | T29: 514550.21 | U29: 1030717.1 | W29: (累 計 折 舊) | X29: 1554967.3 | Y29: 1817092.4
B30: 매출채권 충당금 설정률 | C30: =-K13/K10 -> 0.01170086 | D30: =-L13/L10 -> 0.00026144481 | E30: =-M13/M10 -> 0.00049938423 | F30: =-N13/N10 -> 0.00038586827 | I30: 11162202 | J30: 미착품:원재료 | K30: 1492993688 | L30: 841315563 | M30: 648529458 | N30: 437603462 | S30: 2)機 械 設 備 | T30: 59003852 | U30: 75154055 | W30: 2)機 械 設 備 | X30: 1.0441171e+08 | Y30: 1.1306754e+08
B31: 제품 충당금 설정률 | C31: =-K24/K23 -> 0.0053409483 | D31: =-L24/L23 -> 0.039585747 | E31: =-M24/M23 -> 0.04817405 | F31: =-N24/N23 -> 0.049831339 | I31: 11190000 | J31: 기타유동자산 | K31: 1111876291 | L31: 4628752583 | M31: 2318542901 | N31: 2073639472 | S31: (累 計 折 舊) | T31: 18624182 | U31: 24975137 | W31: (累 計 折 舊) | X31: 33512029 | Y31: 37633306
B32: 반제품 충당금 설정률 | C32: =-K26/K25 -> 0.053839131 | D32: =-L26/L25 -> 0.053414653 | E32: =-M26/M25 -> 0.039849719 | F32: =-N26/N25 -> 0.053888909 | I32: 11191101 | J32: 선급부가가치세(매입부가세) | K32: 0 | L32: 85731970 | M32: 104464002 | N32: 48343533 | S32: 3)其 他 設 備 | T32: 3424701.5 | U32: 4198990.4 | W32: 3)其 他 設 備 | X32: 4629231.3 | Y32: 5030808.7
B33: 원재료 충당금 설정률 | C33: =-K28/K27 -> 0.015610228 | D33: =-L28/L27 -> 0.014188884 | E33: =-M28/M27 -> 0.008743418 | F33: =-N28/N27 -> 0.02053845 | I33: 11191201 | J33: 선급금 | K33: 1083016958 | L33: 4477763798 | M33: 2154073965 | N33: 1885689435 | S33: (累 計 折 舊) | T33: 1758587.8 | U33: 2053173.1 | W33: (累 計 折 舊) | X33: 2267385.7 | Y33: 2457099.6
I34: 11191301 | J34: (선급금대손충당금) | K34: 0 | L34: 0 | M34: 0 | N34: 0 | S34: 4)電 子 設 備 | T34: 17295761 | U34: 20542919 | W34: 4)電 子 設 備 | X34: 22595195 | Y34: 25822451
C35: =C5=SUM(C6,C7,C8,C9) -> TRUE | D35: =D5=SUM(D6,D7,D8,D9) -> TRUE | E35: =E5=SUM(E6,E7,E8,E9) -> TRUE | F35: =F5=SUM(F6,F7,F8,F9) -> TRUE | I35: 11191501 | J35: (유동성)선급비용 | K35: 28859333 | L35: 65256815 | M35: 60004934 | N35: 139606504 | S35: (累 計 折 舊) | T35: 10829829 | U35: 11768736 | W35: (累 計 折 舊) | X35: 11822924 | Y35: 12858485
C36: =C10=SUM(C11,C12,C13) -> TRUE | D36: =D10=SUM(D11,D12,D13) -> TRUE | E36: =E10=SUM(E11,E12,E13) -> TRUE | F36: =F10=SUM(F11,F12,F13) -> TRUE | I36: 12000000 | J36: 비유동자산 | K36: 20446539199 | L36: 25991585111 | M36: 37270144607 | N36: 41371985527 | S36: 5)交 通 工 具 | T36: 2623692.2 | U36: 2567498 | W36: 5)交 通 工 具 | X36: 2456384.9 | Y36: 2566028.8
C37: =C14=SUM(C5,C10) -> TRUE | D37: =D14=SUM(D5,D10) -> TRUE | E37: =E14=SUM(E5,E10) -> TRUE | F37: =F14=SUM(F5,F10) -> TRUE | I37: 12100000 | J37: 장기매출채권및기타채권 | K37: 0 | L37: 34641386 | M37: 33108822 | N37: 55219049 | S37: (累 計 折 舊) | T37: 1058619.9 | U37: 1216753.4 | W37: (累 計 折 舊) | X37: 1512176.6 | Y37: 1706431.1
C38: =C15=SUM(C16,C17,C19,C18) -> TRUE | D38: =D15=SUM(D16,D17,D19,D18) -> TRUE | E38: =E15=SUM(E16,E17,E19,E18) -> TRUE | F38: =F15=SUM(F16,F17,F19,F18) -> TRUE | I38: 12102000 | J38: 장기보증금 | K38: 0 | L38: 34641386 | M38: 33108822 | N38: 55219049 | S38: 6)家 具 用 具 | T38: 587571.35 | U38: 590971.35 | W38: 6)家 具 用 具 | X38: 821243.12 | Y38: 859539.7
C39: =C27=SUM(C24,C25,C26) -> TRUE | D39: =D27=SUM(D24,D25,D26) -> TRUE | E39: =E27=SUM(E24,E25,E26) -> TRUE | F39: =F27=SUM(F24,F25,F26) -> TRUE | I39: 12102005 | J39: 기타 | K39: 0 | L39: 34641386 | M39: 33108822 | N39: 55219049 | S39: (累 計 折 舊) | T39: 468409.05 | U39: 495272.68 | W39: (累 計 折 舊) | X39: 531938.74 | Y39: 559556.7
C40: =C28=C14 -> TRUE | D40: =D28=D14 -> TRUE | E40: =E28=E14 -> TRUE | F40: =F28=F14 -> TRUE | I40: 12170000 | J40: 유형자산 | K40: 15976795669 | L40: 20384658401 | M40: 30926546063 | N40: 34936947543 | S40: 7)器 具 工 具 | T40: 4731339.2 | U40: 5696232.9 | W40: 7)器 具 工 具 | X40: 5739838.7 | Y40: 6303952.1
I41: 12171100 | J41: 건물 | K41: 3449194741 | L41: 3471231252 | M41: 3432773445 | N41: 3468401585 | S41: (累 計 折 舊) | T41: 2581806.9 | U41: 3065965.3 | W41: (累 計 折 舊) | X41: 2495005.4 | Y41: 2815734.4
I42: 12171101 | J42: 건물 | K42: 3537635631 | L42: 3650668790 | M42: 3707707213 | N42: 3797458850 | S42: 8)固定资产改良支出 | T42: 0 | U42: 0 | W42: 8)固定资产改良支出 | X42: 0 | Y42: 0
I43: 12171102 | J43: (건물감가상각누계액) | K43: -88440890 | L43: -179437538 | M43: -274933768 | N43: -329057265 | S43: (累 計 折 舊) | T43: 0 | U43: 0 | W43: (累 計 折 舊) | X43: 0 | Y43: 0
I44: 12171300 | J44: 기계장치 | K44: 6940457646 | L44: 8735647901 | M44: 12535772244 | N44: 13660385117 | S44: 9)模具 | T44: 22711747 | U44: 32916261 | W44: 9)模具 | X44: 42959651 | Y44: 49253783
I45: 12171301 | J45: 기계장치 | K45: 10141582016 | L45: 13083569501 | M45: 18461034079 | N45: 20475400571 | S45: (累 計 折 舊) | T45: 8979321 | U45: 13735290 | W45: (累 計 折 舊) | X45: 20081916 | Y45: 23559549
I46: 12171302 | J46: (기계장치감가상각누계액) | K46: -3201124370 | L46: -4347921600 | M46: -5925261835 | N46: -6815015454 | S46: (3)其他长期资产 | T46: 70000 | U46: 70000 | W46: (3)其他长期资产 | X46: 70000 | Y46: 70000
I47: 12171400 | J47: 차량운반구 | K47: 269004625 | L47: 235151125 | M47: 166945468 | N47: 155664540 | S47: (4)在 建 工 程 | T47: 6737830.5 | U47: 12726752 | W47: (4)固定資産淸理 | X47: 0 | Y47: 0
I48: 12171401 | J48: 차량운반구 | K48: 450960212 | L48: 446975723 | M48: 434313418 | N48: 464682157 | S48: (5)無 形 資 産 | T48: 22145451 | U48: 27900956 | W48: (5)在 建 工 程 | X48: 44039093 | Y48: 52389023
I49: 12171402 | J49: (차량운반구감가상각누계액) | K49: -181955587 | L49: -211824598 | M49: -267367950 | N49: -309017617 | S49: (6)長期待灘費用 | T49: 1836516.9 | U49: 1335755.4 | W49: 1)在 建 工 程 | X49: 44039093 | Y49: 52389023
I50: 12171500 | J50: 공구와기구 | K50: 369461621 | L50: 457903292 | M50: 573718986 | N50: 631681345 | S50: 1)开 办 费 | T50: 0 | U50: 0 | W50: (6)無 形 資 産 | X50: 29011158 | Y50: 28295166
I51: 12171501 | J51: 공구와기구 | K51: 813222582 | L51: 991657186 | M51: 1014860884 | N51: 1141582682 | S51: 2)高 尔 夫 会 员 费 | T51: 350000 | U51: 350000 | W51: 1)無 形 資 産 | X51: 29011158 | Y51: 28295166
I52: 12171502 | J52: (공구와기구감가상각누계액) | K52: -443760961 | L52: -533753894 | M52: -441141898 | N52: -509901337 | S52: 3)装 修 费 | T52: 1486516.9 | U52: 985755.37 | W52: (7)長期待灘費用 | X52: 2444326.4 | Y52: 3516439.2
... I65: 12191100 | J65: 소프트웨어 | K65: 961380278 | L65: 2034524722 | M65: 2322333278 | N65: 2279476454 | S65: 8)其 他 應 付 款 | T65: 13113829 | U65: 18885328 | W65: 5)應 付 工 資 | X65: 1193574.1 | Y65: 1209526.9
I66: 12191101 | J66: 소프트웨어 | K66: 961380278 | L66: 2034524722 | M66: 2322333278 | N66: 2279476454 | O66: 181.09 | P66: =N66/O66 -> 12587534 | S66: 9)預 提 費 用 | T66: 2891422.4 | U66: 3534934.4 | W66: 6)應 交 稅 金 | X66: 4374018.3 | Y66: 2310412.6
I67: 12191400 | J67: 회원권 | K67: 60158000 | L67: 60931500 | M67: 61883500 | N67: 168413700 | S67: 10)職工福利及奬勵基金 | T67: 0 | U67: 0 | W67: 7)應 付 股 利 | X67: 0 | Y67: 0
I68: 12191401 | J68: 회원권 | K68: 60158000 | L68: 60931500 | M68: 61883500 | N68: 168413700 | S68: 11)其 他 应 交 款 | T68: 172566.08 | U68: 196733.2 | W68: 8)預 收 貨 款 | X68: 329478.6 | Y68: 308831.92
I69: 12191402 | J69: (회원권손상차손누계액) | K69: 0 | L69: 0 | M69: 0 | N69: 0 | S69: 12)递延税款贷项 | T69: 0 | U69: 0 | W69: 9)其 他 應 付 款 | X69: 28866100 | Y69: 31635067
I70: 12210000 | J70: 기타비유동자산 | K70: 3100482400 | L70: 2994362883 | M70: 3177427405 | N70: 3312873413 | S70: 13)交易性金融负债 | T70: 581952 | U70: 275717 | W70: 10)預 提 費 用 | X70: 5125152.9 | Y70: 3958952.9
I71: 12211401 | J71: 장기선급비용 | K71: 255502526 | L71: 171610152 | M71: 370297856 | N71: 468378278 | S71: (2)長 期 負 債 | T71: 28225974 | U71: 16791127 | W71: 11)職工福利及奬勵基金 | X71: 0 | Y71: 0
I72: 12211402 | J72: 장기선급비용_토지사용권 | K72: 2844979874 | L72: 2822752731 | M72: 2807129549 | N72: 2844495135 | O72: =N72/O66 -> 15707632 | S72: 1)長 期 借 款 | T72: 28000000 | U72: 15242250 | W72: 12)其 他 应 交 款 | X72: 403033.95 | Y72: 365247.94
I73: 12201001 | J73: 이연법인세자산 | K73: 347722852 | L73: 482466219 | M73: 748845539 | N73: 619055368 | S73: 2)長 期 應 付 款 | T73: 0 | U73: 0 | W73: 13)递延税款贷项 | X73: 0 | Y73: 0
I74: 20000000 | J74: 부채 | K74: 25653791393 | L74: 35956121197 | M74: 46311241868 | N74: 54244342237 | S74: 3）销售保证准备负债 | T74: 225974.47 | U74: 1548877.4 | W74: 14)交易性金融负债 | X74: 0 | Y74: 98377
I75: 21000000 | J75: 유동부채 | K75: 20802310901 | L75: 33032953836 | M75: 43409271335 | N75: 51174969569 | S75: 3.所有者權益 | T75: 1.2513074e+08 | U75: 1.2586994e+08 | W75: (2)長 期 負 債 | X75: 16412932 | Y75: 16949432
I76: 21100000 | J76: 매입채무및기타채무 | K76: 11195959829 | L76: 13597360958 | M76: 17802817760 | N76: 22102088142 | S76: 1)實 收 資 本 | T76: 54568890 | U76: 85407390 | W76: 1)長 期 借 款 | X76: 15297500 | Y76: 15284000
I77: 21101000 | J77: 매입채무 | K77: 8212425826 | L77: 9426396602 | M77: 11462321751 | N77: 16129929084 | S77: 2)資 本 公 積 | T77: 0 | U77: 0 | W77: 2)長 期 應 付 款 | X77: 0 | Y77: 0
I78: 21101002 | J78: 외상매입금:외화 | K78: 5978413482 | L78: 8461886092 | M78: 10144768162 | N78: 15142995864 | S78: 3)儲 備 基 金 | T78: 10419809 | U78: 10419809 | W78: 3）销售保证准备负债 | X78: 1115432.1 | Y78: 1665432.1
I79: 21101003 | J79: 미확정매입채무:GL | K79: 2234012344 | L79: 964510510 | M79: 1317553589 | N79: 986933220 | S79: 4)未 分 配 利 潤 | T79: 60142044 | U79: 30042740 | W79: 3.所有者權益 | X79: 1.3917997e+08 | Y79: 1.4467467e+08
I80: 21101101 | J80: 미지급금 | K80: 2283665573 | L80: 3321996113 | M80: 5175075565 | N80: 4994577782 | S80: a.移越利益剩餘金 | T80: 51353668 | U80: 23280465 | W80: 1)實 收 資 本 | X80: 85407390 | Y80: 85407390
I81: 21101201 | J81: 미지급비용 | K81: 699868430 | L81: 848968243 | M81: 1165420444 | N81: 977581276 | S81: b.淨 利 潤 | T81: 8788375.4 | U81: 6762275 | W81: 2)資 本 公 積 | X81: 0 | Y81: 0
I82: 21120000 | J82: (유동성)위험회피파생상품부채 | K82: 100025910 | L82: 47999573 | M82: 0 | N82: 17815091 | S82: 權 益 合 計 | T82: 2.7438482e+08 | U82: 3.3275753e+08 | W82: 3)儲 備 基 金 | X82: 12655040 | Y82: 12655040
I83: 21121000 | J83: (유동성)공정가치위험회피파생상품부채 | K83: 100025910 | L83: 47999573 | M83: 0 | N83: 17815091 | W83: 4)未 分 配 利 潤 | X83: 41117540 | Y83: 46612237
I84: 21121001 | J84: (유동성)공정가치위험회피파생상품부채:금융 | K84: 100025910 | L84: 47999573 | M84: 0 | N84: 17815091 | W84: a.移越利益剩餘金 | X84: 26370009 | Y84: 39528250
I85: 21130000 | J85: 단기차입금 | K85: 9399060138 | L85: 19222626909 | M85: 24718570603 | N85: 27773665899 | W85: b.淨 利 潤 | X85: 14747531 | Y85: 7083987
I86: 21131002 | J86: 단기차입금:외화 | K86: 9399060138 | L86: 19222626909 | M86: 24718570603 | N86: 27773665899 | W86: 權 益 合 計 | X86: 4.0051574e+08 | Y86: 443951262
I87: 21190000 | J87: 기타유동부채 | K87: 107265024 | L87: 164966396 | M87: 887882972 | N87: 1281400437
I88: 21191101 | J88: 선수금 | K88: 729751 | L88: 137660809 | M88: 58255111 | N88: 55926372
I89: 21191201 | J89: 예수금 | K89: 17987421 | L89: 20550484 | M89: 18230642 | N89: 18746183
I90: 21191401 | J90: 매출부가세 | K90: -142552837 | L90: 0 | M90: 0 | N90: 0
I91: 21191501 | J91: 미지급법인세 | K91: 231100689 | L91: 6755103 | M91: 811397219 | N91: 406368682
I92: 21201001 | J92: (유동성)미지급배당금 | K92: 0 | L92: 0 | M92: 0 | N92: 800359200
I93: 22000000 | J93: 비유동부채 | K93: 4851480492 | L93: 2923167361 | M93: 2901970533 | N93: 3069372668
I94: 22130000 | J94: 장기차입금 | K94: 4812640000 | L94: 2653523303 | M94: 2704750975 | N94: 2767779560
I95: 22131002 | J95: 장기차입금:외화 | K95: 4812640000 | L95: 2653523303 | M95: 2704750975 | N95: 2767779560
I96: 22170000 | J96: 충당부채 | K96: 38840492 | L96: 269644058 | M96: 197219558 | N96: 301593108
I97: 22171201 | J97: 판매보증충당부채 | K97: 38840492 | L97: 269644058 | M97: 197219558 | N97: 301593108
I98: 30000000 | J98: 자본 | K98: 21507472072 | L98: 22059368476 | M98: 24608410446 | N98: 26199135329
... I107: 31141016 | J107: 당기순이익 | K107: 1605086483 | L107: 1354410426 | M107: 2520795454 | N107: 1250677909
K109: =K107=IS!J75 -> TRUE | L109: =L107=IS!K75 -> TRUE | M109: =M107=IS!L75 -> TRUE | N109: =N107=IS!M75 -> TRUE

Sheet IS(RMB)
H2: =(E8-C8)/C8 -> 0.31085563
J3: =J6+J45+J58 -> 2.9570178e+08 | K3: =K6+K45+K58 -> 3.0468625e+08 | L3: =L6+L45+L58 -> 3.8673151e+08 | M3: =M6+M45+M58 -> 2.2217019e+08
C4: =C16/C8 -> 0.01141469 | D4: =D16/D8 -> 0.018961952 | E4: =E16/E8 -> 0.028000134 | F4: =F16/F8 -> 0.033472164 | Q4: 178.58 | R4: 178.1 | S4: 170.93 | T4: 176.55
B5: 손익계산서_무석 | H5: 연결계정코드 | I5: 연결계정명 | J5: 2012년 | K5: 2013년 | L5: 2014년 | M5: 2015년 6개월 | O5: 연결계정명 | P5: 연결계정코드 | Q5: 2012 | R5: 2013 | S5: 2014 | T5: 2015
C6: 2012년 | D6: 2013년 | E6: 2014년 | F6: 2015년 | H6: 41000000 | I6: 매출 | J6: =VLOOKUP(H6,$P$7:$T$185,2,FALSE) -> 2.8073956e+08 | K6: =VLOOKUP($H6,$P$7:$T$185,3,FALSE) -> 2.9159265e+08 | L6: =VLOOKUP($H6,$P$7:$T$185,4,FALSE) -> 3.6800903e+08 | M6: =VLOOKUP($H6,$P$7:$T$185,5,FALSE) -> 2.1344077e+08 | Q6: K-GAAP(CNY) | R6: K-GAAP(CNY) | S6: K-GAAP(CNY) | T6: K-GAAP(CNY)
B7: RMB'000 | C7: 12개월 | D7: 12개월 | E7: 12개월 | F7: 6개월 | H7: 41010000 | I7: 제품매출 | J7: =VLOOKUP(H7,$P$7:$T$185,2,FALSE) -> 2.5801916e+08 | K7: =VLOOKUP($H7,$P$7:$T$185,3,FALSE) -> 2.5950035e+08 | L7: =VLOOKUP($H7,$P$7:$T$185,4,FALSE) -> 3.4448541e+08 | M7: =VLOOKUP($H7,$P$7:$T$185,5,FALSE) -> 2.0258584e+08 | O7: 매출 | P7: 41000000 | Q7: 2.8073956e+08 | R7: 2.9159265e+08 | S7: 3.6800903e+08 | T7: 2.1344077e+08
B8: 매출액 | C8: =J6 -> 2.8073956e+08 | D8: =K6 -> 2.9159265e+08 | E8: =L6 -> 3.6800903e+08 | F8: =M6 -> 2.1344077e+08 | H8: 41010020 | I8: 제품매출:외화 | J8: =VLOOKUP(H8,$P$7:$T$185,2,FALSE) -> 2.5801916e+08 | K8: =VLOOKUP($H8,$P$7:$T$185,3,FALSE) -> 2.5950035e+08 | L8: =VLOOKUP($H8,$P$7:$T$185,4,FALSE) -> 3.4448541e+08 | M8: =VLOOKUP($H8,$P$7:$T$185,5,FALSE) -> 2.0258584e+08 | O8: 제품매출 | P8: 41010000 | Q8: 2.5801916e+08 | R8: 2.5950035e+08 | S8: 3.4448541e+08 | T8: 2.0258584e+08
B9: 제품 | C9: =J7 -> 2.5801916e+08 | D9: =K7 -> 2.5950035e+08 | E9: =L7 -> 3.4448541e+08 | F9: =M7 -> 2.0258584e+08 | H9: 41011000 | I9: 상품매출 | J9: =VLOOKUP(H9,$P$7:$T$185,2,FALSE) -> 22720397 | K9: =VLOOKUP($H9,$P$7:$T$185,3,FALSE) -> 26511044 | L9: =VLOOKUP($H9,$P$7:$T$185,4,FALSE) -> 22759036 | M9: =VLOOKUP($H9,$P$7:$T$185,5,FALSE) -> 8378515.7 | O9: 제품매출:원화 | P9: 41010010 | Q9: 0 | R9: 0 | S9: 0 | T9: 0
B10: 상품 | C10: =J9 -> 22720397 | D10: =K9 -> 26511044 | E10: =L9 -> 22759036 | F10: =M9 -> 8378515.7 | H10: 41011020 | I10: 상품매출:외화 | J10: =VLOOKUP(H10,$P$7:$T$185,2,FALSE) -> 22720397 | K10: =VLOOKUP($H10,$P$7:$T$185,3,FALSE) -> 26511044 | L10: =VLOOKUP($H10,$P$7:$T$185,4,FALSE) -> 22759036 | M10: =VLOOKUP($H10,$P$7:$T$185,5,FALSE) -> 8378515.7 | O10: 제품매출:외화 | P10: 41010020 | Q10: 2.5801916e+08 | R10: 2.5950035e+08 | S10: 3.4448541e+08 | T10: 2.0258584e+08
B11: 기타 | C11: =J11 -> 0 | D11: =K11 -> 5581251.3 | E11: =L11 -> 764587.81 | F11: =M11 -> 2476413.8 | G11: 일시불 금형 매출이며 크라이슬러, FIAT에서 발생함.(주로 FIAT) 2013년 증가 원인에 대해서는 사유 확인 필요 | H11: 41089000 | I11: 기타매출 | J11: =VLOOKUP(H11,$P$7:$T$185,2,FALSE) -> 0 | K11: =VLOOKUP($H11,$P$7:$T$185,3,FALSE) -> 5581251.3 | L11: =VLOOKUP($H11,$P$7:$T$185,4,FALSE) -> 764587.81 | M11: =VLOOKUP($H11,$P$7:$T$185,5,FALSE) -> 2476413.8 | O11: (매출할인 및 매출에누리) | P11: 41010030 | Q11: 0 | R11: 0 | S11: 0 | T11: 0
B12: 매출원가 | C12: =J13 -> 2.5358188e+08 | D12: =K13 -> 2.6608301e+08 | E12: =L13 -> 3.1835671e+08 | F12: =M13 -> 1.8382471e+08 | H12: 41089990 | I12: 기타매출 | J12: =VLOOKUP(H12,$P$7:$T$185,2,FALSE) -> 0 | K12: =VLOOKUP($H12,$P$7:$T$185,3,FALSE) -> 5581251.3 | L12: =VLOOKUP($H12,$P$7:$T$185,4,FALSE) -> 764587.81 | M12: =VLOOKUP($H12,$P$7:$T$185,5,FALSE) -> 2476413.8 | O12: 상품매출 | P12: 41011000 | Q12: 22720397 | R12: 26511044 | S12: 22759036 | T12: 8378515.7
B13: 매출총이익 | C13: =J17 -> 27157678 | D13: =K17 -> 25509642 | E13: =L17 -> 49652321 | F13: =M17 -> 29616062 | H13: 42100000 | I13: 매출원가 | J13: =VLOOKUP(H13,$P$7:$T$185,2,FALSE) -> 2.5358188e+08 | K13: =VLOOKUP($H13,$P$7:$T$185,3,FALSE) -> 2.6608301e+08 | L13: =VLOOKUP($H13,$P$7:$T$185,4,FALSE) -> 3.1835671e+08 | M13: =VLOOKUP($H13,$P$7:$T$185,5,FALSE) -> 1.8382471e+08 | O13: 상품매출:원화 | P13: 41011010 | Q13: 0 | R13: 0 | S13: 0 | T13: 0
B14: 매출총이익% | C14: =C13/C8 -> 0.096736199 | D14: =D13/D8 -> 0.087483831 | E14: =E13/E8 -> 0.13492147 | F14: =F13/F8 -> 0.13875541 | H14: 42010010 | I14: 제품매출원가 | J14: =VLOOKUP(H14,$P$7:$T$185,2,FALSE) -> 2.3130226e+08 | K14: =VLOOKUP($H14,$P$7:$T$185,3,FALSE) -> 2.3778334e+08 | L14: =VLOOKUP($H14,$P$7:$T$185,4,FALSE) -> 2.9658203e+08 | M14: =VLOOKUP($H14,$P$7:$T$185,5,FALSE) -> 1.7425521e+08 | O14: 상품매출:외화 | P14: 41011020 | Q14: 22720397 | R14: 26511044 | S14: 22759036 | T14: 8378515.7
B15: 판매관리비 | C15: =J18 -> 26188300 | D15: =K18 -> 27044773 | E15: =L18 -> 32857267 | F15: =M18 -> 18172644 | H15: 42011010 | I15: 상품매출원가 | J15: =VLOOKUP(H15,$P$7:$T$185,2,FALSE) -> 22279621 | K15: =VLOOKUP($H15,$P$7:$T$185,3,FALSE) -> 23345968 | L15: =VLOOKUP($H15,$P$7:$T$185,4,FALSE) -> 21274805 | M15: =VLOOKUP($H15,$P$7:$T$185,5,FALSE) -> 7884993.5 | O15: 공사매출 | P15: 41012000 | Q15: 0 | R15: 0 | S15: 0 | T15: 0
B16: 경상개발비 | C16: =J36 -> 3204555.1 | D16: =K36 -> 5529165.6 | E16: =L36 -> 10304302 | F16: =M36 -> 7144324.4 | G16: 로열티 전장 5%, 스위치 3%, 15년도부터 변동 | H16: 42089990 | I16: 기타매출원가 | J16: =VLOOKUP(H16,$P$7:$T$185,2,FALSE) -> 0 | K16: =VLOOKUP($H16,$P$7:$T$185,3,FALSE) -> 4953695 | L16: =VLOOKUP($H16,$P$7:$T$185,4,FALSE) -> 499879.4 | M16: =VLOOKUP($H16,$P$7:$T$185,5,FALSE) -> 1684500 | O16: 공사매출:원화 | P16: 41012010 | Q16: 0 | R16: 0 | S16: 0 | T16: 0
B17: 지급수수료 | C17: =J31 -> 2183721.2 | D17: =K31 -> 4526632.4 | E17: =L31 -> 9280370.1 | F17: =M31 -> 2999169.8 | G17: 해외 수출 운반비 및 관련 비용이 지급수수료로 분류되어 2014년 증가함.(2014년 수출 증가), 2014년 세금 관련 컨설팅 1,500천RMB 존재함 | H17: 49000000 | I17: 매출총이익 | J17: =VLOOKUP(H17,$P$7:$T$185,2,FALSE) -> 27157678 | K17: =VLOOKUP($H17,$P$7:$T$185,3,FALSE) -> 25509642 | L17: =VLOOKUP($H17,$P$7:$T$185,4,FALSE) -> 49652321 | M17: =VLOOKUP($H17,$P$7:$T$185,5,FALSE) -> 29616062 | O17: 공사매출:외화 | P17: 41012020 | Q17: 0 | R17: 0 | S17: 0 | T17: 0
B18: 인건비 | C18: =SUM(J19,J20,J28) -> 8229037.3 | D18: =SUM(K19,K20,K28) -> 7914889.2 | E18: =SUM(L19,L20,L28) -> 5057609.2 | F18: =SUM(M19,M20,M28) -> 2786531.2 | G18: 2014년 판관비 관련 인원 구조조정 단행으로 인건비 감소 | H18: 60000000 | I18: 판매비와관리비 | J18: =VLOOKUP(H18,$P$7:$T$185,2,FALSE) -> 26188300 | K18: =VLOOKUP($H18,$P$7:$T$185,3,FALSE) -> 27044773 | L18: =VLOOKUP($H18,$P$7:$T$185,4,FALSE) -> 32857267 | M18: =VLOOKUP($H18,$P$7:$T$185,5,FALSE) -> 18172644 | O18: 공사매출:진행기준조정 | P18: 41012030 | Q18: 0 | R18: 0 | S18: 0 | T18: 0
B19: 운반비 | C19: =J21 -> 2537452.9 | D19: =K21 -> 3216503.7 | E19: =L21 -> 2303461.5 | F19: =M21 -> 1345563.6 | G19: 매출 및 매입 관련 운송비. 큰 변동 없음. | H19: 61000100 | I19: 급료와임금 | J19: =VLOOKUP(H19,$P$7:$T$185,2,FALSE) -> 5586840.4 | K19: =VLOOKUP($H19,$P$7:$T$185,3,FALSE) -> 5226789.4 | L19: =VLOOKUP($H19,$P$7:$T$185,4,FALSE) -> 2549018.2 | M19: =VLOOKUP($H19,$P$7:$T$185,5,FALSE) -> 1566403.5 | O19: 기타매출 | P19: 41089000 | Q19: 0 | R19: 5581251.3 | S19: 764587.81 | T19: 2476413.8
B20: 품질보증충당부채전입액 | C20: =J41 -> 22953.46 | D20: =K41 -> 812696.15 | E20: =L41 -> 600000 | F20: =M41 -> 550000 | G20: 본사와 동일한 기준으로 쌓고 있음. 2012년 필드 클레임 발생(사유 확인 해 봐야 됨)으로 2013년 충당금 설정 | H20: 61000400 | I20: 잡급 | J20: =VLOOKUP(H20,$P$7:$T$185,2,FALSE) -> 385320 | K20: =VLOOKUP($H20,$P$7:$T$185,3,FALSE) -> 391230 | L20: =VLOOKUP($H20,$P$7:$T$185,4,FALSE) -> 401460 | M20: =VLOOKUP($H20,$P$7:$T$185,5,FALSE) -> 196800 | O20: 임대매출 | P20: 41089040 | Q20: 0 | R20: 0 | S20: 0 | T20: 0
B21: 기타 | C21: =C15-SUM(C16:C20) -> 10010580 | D21: =D15-SUM(D16:D20) -> 5044886.1 | E21: =E15-SUM(E16:E20) -> 5311523.6 | F21: =F15-SUM(F16:F20) -> 3347055.3 | G21: A/S비(필드 클레임)로 인하여 2012년 증가. | H21: 61000600 | I21: 운반비 | J21: =VLOOKUP(H21,$P$7:$T$185,2,FALSE) -> 2537452.9 | K21: =VLOOKUP($H21,$P$7:$T$185,3,FALSE) -> 3216503.7 | L21: =VLOOKUP($H21,$P$7:$T$185,4,FALSE) -> 2303461.5 | M21: =VLOOKUP($H21,$P$7:$T$185,5,FALSE) -> 1345563.6 | O21: 기타매출 | P21: 41089990 | Q21: 0 | R21: 5581251.3 | S21: 764587.81 | T21: 2476413.8
B22: 영업이익 | C22: =J44 -> 969377.6 | D22: =K44 -> -1535131.2 | E22: =L44 -> 16795055 | F22: =M44 -> 11443418 | H22: 61000700 | I22: 감가상각비 | J22: =VLOOKUP(H22,$P$7:$T$185,2,FALSE) -> 1035092.4 | K22: =VLOOKUP($H22,$P$7:$T$185,3,FALSE) -> 715747.44 | L22: =VLOOKUP($H22,$P$7:$T$185,4,FALSE) -> 715683.21 | M22: =VLOOKUP($H22,$P$7:$T$185,5,FALSE) -> 389817.73 | O22: 매출원가 | P22: 42100000 | Q22: 2.5358188e+08 | R22: 2.6608301e+08 | S22: 3.1835671e+08 | T22: 1.8382471e+08
B23: 영업이익% | C23: =C22/C8 -> 0.0034529427 | D23: =D22/D8 -> -0.0052646431 | E23: =E22/E8 -> 0.045637615 | F23: =F22/F8 -> 0.053614021 | H23: 61000800 | I23: 수선비 | J23: =VLOOKUP(H23,$P$7:$T$185,2,FALSE) -> 117726.4 | K23: =VLOOKUP($H23,$P$7:$T$185,3,FALSE) -> 65810.83 | L23: =VLOOKUP($H23,$P$7:$T$185,4,FALSE) -> 91870 | M23: =VLOOKUP($H23,$P$7:$T$185,5,FALSE) -> 34382.35 | O23: 제품매출원가 | P23: 42010010 | Q23: 2.3130226e+08 | R23: 2.3778334e+08 | S23: 2.9658203e+08 | T23: 1.7425521e+08
B24: 영업외수익 | C24: =J45+J57 -> 16587318 | D24: =K45+K57 -> 16129807 | E24: =L45+L57 -> 19165390 | F24: =M45+M57 -> 9602818.7 | G24: 잡이익 및 잡손실 개발비 관련 손익을 잡이익 및 잡손실로 처리(개발후 완성차 업체들이 관련 비용을 보전해 주는 경우) | H24: 61000900 | I24: 소모품비 | J24: =VLOOKUP(H24,$P$7:$T$185,2,FALSE) -> 175621.46 | K24: =VLOOKUP($H24,$P$7:$T$185,3,FALSE) -> 241083.68 | L24: =VLOOKUP($H24,$P$7:$T$185,4,FALSE) -> 202612.47 | M24: =VLOOKUP($H24,$P$7:$T$185,5,FALSE) -> 111968.56 | O24: (매입할인 및 에누리) | P24: 42010020 | Q24: 0 | R24: 0 | S24: 0 | T24: 0
B25: 영업외비용 | C25: =J50+J66 -> 8993854.2 | D25: =K50+K66 -> 8623611.2 | E25: =L50+L66 -> 18502238 | F25: =M50+M66 -> 9714107 | G25: 연결정산표 상 금액으로는 매출로 인식하며, 별도에서도 올해부터 조정할 것이라고 함(연결 정산표 확인해 봐야 됨) | H25: 61001000 | I25: 세금과공과 | J25: =VLOOKUP(H25,$P$7:$T$185,2,FALSE) -> 2096835.3 | K25: =VLOOKUP($H25,$P$7:$T$185,3,FALSE) -> 1435523.4 | L25: =VLOOKUP($H25,$P$7:$T$185,4,FALSE) -> 1366243.5 | M25: =VLOOKUP($H25,$P$7:$T$185,5,FALSE) -> 1066929.9 | O25: 재고자산평가손실 | P25: 42010030 | Q25: 0 | R25: 0 | S25: 0 | T25: 0
B26: 법인세비용 | C26: =J77 -> -225534.06 | D26: =K77 -> -1633710 | E26: =L77 -> 2710675.8 | F26: =M77 -> 4248142.7 | G26: 차입금 증가에 비해 이자비용 감소하는 이유 설명 안됨.(확인 후 알려준다고 함) | H26: 61001200 | I26: 임차료 | J26: =VLOOKUP(H26,$P$7:$T$185,2,FALSE) -> 329337.61 | K26: =VLOOKUP($H26,$P$7:$T$185,3,FALSE) -> 293140.54 | L26: =VLOOKUP($H26,$P$7:$T$185,4,FALSE) -> 63883.33 | M26: =VLOOKUP($H26,$P$7:$T$185,5,FALSE) -> 33262.55 | O26: 상품매출원가 | P26: 42011010 | Q26: 22279621 | R26: 23345968 | S26: 21274805 | T26: 7884993.5
B27: 당기순이익 | C27: =J78 -> 8788375.4 | D27: =K78 -> 7604775 | E27: =L78 -> 14747531 | F27: =M78 -> 7083987 | H27: 61001300 | I27: 보험료 | J27: =VLOOKUP(H27,$P$7:$T$185,2,FALSE) -> 172068.55 | K27: =VLOOKUP($H27,$P$7:$T$185,3,FALSE) -> 191504.94 | L27: =VLOOKUP($H27,$P$7:$T$185,4,FALSE) -> 174203.84 | M27: =VLOOKUP($H27,$P$7:$T$185,5,FALSE) -> 110271.05 | O27: 공사매출원가 | P27: 42012010 | Q27: 0 | R27: 0 | S27: 0 | T27: 0
B28: 당기순이익% | C28: =C27/C8 -> 0.031304371 | D28: =D27/D8 -> 0.026080133 | E28: =E27/E8 -> 0.040073829 | F28: =F27/F8 -> 0.033189475 | H28: 61001400 | I28: 복리후생비 | J28: =VLOOKUP(H28,$P$7:$T$185,2,FALSE) -> 2256877 | K28: =VLOOKUP($H28,$P$7:$T$185,3,FALSE) -> 2296869.8 | L28: =VLOOKUP($H28,$P$7:$T$185,4,FALSE) -> 2107131 | M28: =VLOOKUP($H28,$P$7:$T$185,5,FALSE) -> 1023327.6 | O28: 기타매출원가 | P28: 42089990 | Q28: 0 | R28: 4953695 | S28: 499879.4 | T28: 1684500
B29: D&A | C29: =J22+J39+C32*1000 -> 12471481 | D29: =K22+K39+D32*1000 -> 12500704 | E29: =L22+L39+E32*1000 -> 16055330 | F29: =M22+M39+F32*1000 -> 8444493.6 | H29: 61001500 | I29: 여비교통비 | J29: =VLOOKUP(H29,$P$7:$T$185,2,FALSE) -> 728623.38 | K29: =VLOOKUP($H29,$P$7:$T$185,3,FALSE) -> 772830.73 | L29: =VLOOKUP($H29,$P$7:$T$185,4,FALSE) -> 170545.74 | M29: =VLOOKUP($H29,$P$7:$T$185,5,FALSE) -> 223544.97 | O29: 매출총이익 | P29: 49000000 | Q29: 27157678 | R29: 25509642 | S29: 49652321 | T29: 29616062
B30: EBITDA | C30: =C22+C29 -> 13440859 | D30: =D22+D29 -> 10965573 | E30: =E22+E29 -> 32850385 | F30: =F22+F29 -> 19887912 | H30: 61001600 | I30: 통신비 | J30: =VLOOKUP(H30,$P$7:$T$185,2,FALSE) -> 279665.38 | K30: =VLOOKUP($H30,$P$7:$T$185,3,FALSE) -> 329112.72 | L30: =VLOOKUP($H30,$P$7:$T$185,4,FALSE) -> 372087.97 | M30: =VLOOKUP($H30,$P$7:$T$185,5,FALSE) -> 156985.43 | O30: 판매비와관리비 | P30: 60000000 | Q30: 26188300 | R30: 27044773 | S30: 32857267 | T30: 18172644
B31: EBITDA(%) | C31: =C30/C8 -> 0.047876612 | D31: =D30/D8 -> 0.037605793 | E31: =E30/E8 -> 0.08926516 | F31: =F30/F8 -> 0.093177661 | H31: 61001900 | I31: 지급수수료 | J31: =VLOOKUP(H31,$P$7:$T$185,2,FALSE) -> 2183721.2 | K31: =VLOOKUP($H31,$P$7:$T$185,3,FALSE) -> 4526632.4 | L31: =VLOOKUP($H31,$P$7:$T$185,4,FALSE) -> 9280370.1 | M31: =VLOOKUP($H31,$P$7:$T$185,5,FALSE) -> 2999169.8 | O31: 급료와임금 | P31: 61000100 | Q31: 5586840.4 | R31: 5226789.4 | S31: 2549018.2 | T31: 1566403.5
B32: 매출원가 D&A(천RMB) | C32: =마진!F22 -> 10939.988 | D32: =마진!H22 -> 11337.658 | E32: =마진!J22 -> 15173.815 | F32: =마진!L22 -> 7947.8188 | H32: 61002000 | I32: 접대비 | J32: =VLOOKUP(H32,$P$7:$T$185,2,FALSE) -> 294217.49 | K32: =VLOOKUP($H32,$P$7:$T$185,3,FALSE) -> 343249.26 | L32: =VLOOKUP($H32,$P$7:$T$185,4,FALSE) -> 457189.33 | M32: =VLOOKUP($H32,$P$7:$T$185,5,FALSE) -> 238918.7 | O32: 상여금 | P32: 61000200 | Q32: 0 | R32: 0 | S32: 0 | T32: 0
C33: 569796209 | D33: 993089459 | E33: 1765593366 | F33: 1280666024 | H33: 61002100 | I33: 도서인쇄비 | J33: =VLOOKUP(H33,$P$7:$T$185,2,FALSE) -> 36511.36 | K33: =VLOOKUP($H33,$P$7:$T$185,3,FALSE) -> 37405.32 | L33: =VLOOKUP($H33,$P$7:$T$185,4,FALSE) -> 41994.82 | M33: =VLOOKUP($H33,$P$7:$T$185,5,FALSE) -> 10483.64 | O33: 퇴직급여 | P33: 61000300 | Q33: 0 | R33: 0 | S33: 0 | T33: 0
C34: =C20+#REF! -> #REF! | D34: =D20+#REF! -> #REF! | E34: =E20+#REF! -> #REF! | F34: =F20+#REF! -> #REF! | H34: 61002200 | I34: 교육훈련비 | J34: =VLOOKUP(H34,$P$7:$T$185,2,FALSE) -> 141964.69 | K34: =VLOOKUP($H34,$P$7:$T$185,3,FALSE) -> 228920.63 | L34: =VLOOKUP($H34,$P$7:$T$185,4,FALSE) -> 358739.77 | M34: =VLOOKUP($H34,$P$7:$T$185,5,FALSE) -> 119702.64 | O34: 잡급 | P34: 61000400 | Q34: 385320 | R34: 391230 | S34: 401460 | T34: 196800
H35: 61002300 | I35: 차량유지비 | J35: =VLOOKUP(H35,$P$7:$T$185,2,FALSE) -> 555498.58 | K35: =VLOOKUP($H35,$P$7:$T$185,3,FALSE) -> 506815.3 | L35: =VLOOKUP($H35,$P$7:$T$185,4,FALSE) -> 367652.7 | M35: =VLOOKUP($H35,$P$7:$T$185,5,FALSE) -> 109967.12 | O35: 수도광열비 | P35: 61000500 | Q35: 0 | R35: 0 | S35: 0 | T35: 0
H36: 61002500 | I36: 경상개발비 | J36: =VLOOKUP(H36,$P$7:$T$185,2,FALSE) -> 3204555.1 | K36: =VLOOKUP($H36,$P$7:$T$185,3,FALSE) -> 5529165.6 | L36: =VLOOKUP($H36,$P$7:$T$185,4,FALSE) -> 10304302 | M36: =VLOOKUP($H36,$P$7:$T$185,5,FALSE) -> 7144324.4 | O36: 운반비 | P36: 61000600 | Q36: 2537452.9 | R36: 3216503.7 | S36: 2303461.5 | T36: 1345563.6
C37: =C27=J78 -> TRUE | D37: =D27=K78 -> TRUE | E37: =E27=L78 -> TRUE | F37: =F27=M78 -> TRUE | H37: 61002700 | I37: 광고선전비 | J37: =VLOOKUP(H37,$P$7:$T$185,2,FALSE) -> 155033.49 | K37: =VLOOKUP($H37,$P$7:$T$185,3,FALSE) -> 27353.34 | L37: =VLOOKUP($H37,$P$7:$T$185,4,FALSE) -> 515 | M37: =VLOOKUP($H37,$P$7:$T$185,5,FALSE) -> 0 | O37: 감가상각비 | P37: 61000700 | Q37: 1035092.4 | R37: 715747.44 | S37: 715683.21 | T37: 389817.73
H38: 61002900 | I38: 대손상각비 | J38: =VLOOKUP(H38,$P$7:$T$185,2,FALSE) -> 945270.45 | K38: =VLOOKUP($H38,$P$7:$T$185,3,FALSE) -> 0 | L38: =VLOOKUP($H38,$P$7:$T$185,4,FALSE) -> 26615.78 | M38: =VLOOKUP($H38,$P$7:$T$185,5,FALSE) -> 0 | O38: 수선비 | P38: 61000800 | Q38: 117726.4 | R38: 65810.83 | S38: 91870 | T38: 34382.35
H39: 61003000 | I39: 무형자산상각비 | J39: =VLOOKUP(H39,$P$7:$T$185,2,FALSE) -> 496401.01 | K39: =VLOOKUP($H39,$P$7:$T$185,3,FALSE) -> 447298.93 | L39: =VLOOKUP($H39,$P$7:$T$185,4,FALSE) -> 165832.59 | M39: =VLOOKUP($H39,$P$7:$T$185,5,FALSE) -> 106857.06 | O39: 소모품비 | P39: 61000900 | Q39: 175621.46 | R39: 241083.68 | S39: 202612.47 | T39: 111968.56
H40: 61003500 | I40: A/S 비 | J40: =VLOOKUP(H40,$P$7:$T$185,2,FALSE) -> 2112914.2 | K40: =VLOOKUP($H40,$P$7:$T$185,3,FALSE) -> 0 | L40: =VLOOKUP($H40,$P$7:$T$185,4,FALSE) -> 398054.94 | M40: =VLOOKUP($H40,$P$7:$T$185,5,FALSE) -> 465064.39 | N40: 필드클레임 | O40: 세금과공과 | P40: 61001000 | Q40: 2096835.3 | R40: 1435523.4 | S40: 1366243.5 | T40: 1066929.9
H41: 61003800 | I41: 품질보증충당부채전입액 | J41: =VLOOKUP(H41,$P$7:$T$185,2,FALSE) -> 22953.46 | K41: =VLOOKUP($H41,$P$7:$T$185,3,FALSE) -> 812696.15 | L41: =VLOOKUP($H41,$P$7:$T$185,4,FALSE) -> 600000 | M41: =VLOOKUP($H41,$P$7:$T$185,5,FALSE) -> 550000 | N41: 대량 A/S | O41: 리스료 | P41: 61001100 | Q41: 0 | R41: 0 | S41: 0 | T41: 0
H42: 71101800 | I42: 대손충당금환입 | J42: =VLOOKUP(H42,$P$7:$T$185,2,FALSE) -> 0 | K42: =VLOOKUP($H42,$P$7:$T$185,3,FALSE) -> -928709.54 | L42: =VLOOKUP($H42,$P$7:$T$185,4,FALSE) -> 0 | M42: =VLOOKUP($H42,$P$7:$T$185,5,FALSE) -> 0 | O42: 임차료 | P42: 61001200 | Q42: 329337.61 | R42: 293140.54 | S42: 63883.33 | T42: 33262.55
H43: 61004100 | I43: 기타판관비 | J43: =VLOOKUP(H43,$P$7:$T$185,2,FALSE) -> 337798.54 | K43: =VLOOKUP($H43,$P$7:$T$185,3,FALSE) -> 337798.54 | L43: =VLOOKUP($H43,$P$7:$T$185,4,FALSE) -> 337798.54 | M43: =VLOOKUP($H43,$P$7:$T$185,5,FALSE) -> 168899.27 | O43: 보험료 | P43: 61001300 | Q43: 172068.55 | R43: 191504.94 | S43: 174203.84 | T43: 110271.05
H44: 70000000 | I44: 영업이익 | J44: =VLOOKUP(H44,$P$7:$T$185,2,FALSE) -> 969377.6 | K44: =VLOOKUP($H44,$P$7:$T$185,3,FALSE) -> -1535131.2 | L44: =VLOOKUP($H44,$P$7:$T$185,4,FALSE) -> 16795055 | M44: =VLOOKUP($H44,$P$7:$T$185,5,FALSE) -> 11443418 | O44: 복리후생비 | P44: 61001400 | Q44: 2256877 | R44: 2296869.8 | S44: 2107131 | T44: 1023327.6
H45: 71000000 | I45: 기타수익 | J45: =VLOOKUP(H45,$P$7:$T$185,2,FALSE) -> 14771256 | K45: =VLOOKUP($H45,$P$7:$T$185,3,FALSE) -> 13015875 | L45: =VLOOKUP($H45,$P$7:$T$185,4,FALSE) -> 18627488 | M45: =VLOOKUP($H45,$P$7:$T$185,5,FALSE) -> 8705245.3 | O45: 여비교통비 | P45: 61001500 | Q45: 728623.38 | R45: 772830.73 | S45: 170545.74 | T45: 223544.97
H46: 71100300 | I46: 외환차익(영업활동) | J46: =VLOOKUP(H46,$P$7:$T$185,2,FALSE) -> 848600.05 | K46: =VLOOKUP($H46,$P$7:$T$185,3,FALSE) -> 451580.41 | L46: =VLOOKUP($H46,$P$7:$T$185,4,FALSE) -> 667737.21 | M46: =VLOOKUP($H46,$P$7:$T$185,5,FALSE) -> 323190.76 | O46: 통신비 | P46: 61001600 | Q46: 279665.38 | R46: 329112.72 | S46: 372087.97 | T46: 156985.43
H47: 71100400 | I47: 외화환산이익(영업활동) | J47: =VLOOKUP(H47,$P$7:$T$185,2,FALSE) -> -25468.83 | K47: =VLOOKUP($H47,$P$7:$T$185,3,FALSE) -> 200571.65 | L47: =VLOOKUP($H47,$P$7:$T$185,4,FALSE) -> -191372.56 | M47: =VLOOKUP($H47,$P$7:$T$185,5,FALSE) -> 353049.14 | O47: 포장비 | P47: 61001700 | Q47: 0 | R47: 0 | S47: 0 | T47: 0
H48: 71100500 | I48: 유형자산처분이익 | J48: =VLOOKUP(H48,$P$7:$T$185,2,FALSE) -> 0 | K48: =VLOOKUP($H48,$P$7:$T$185,3,FALSE) -> 2495.83 | L48: =VLOOKUP($H48,$P$7:$T$185,4,FALSE) -> 22241.19 | M48: =VLOOKUP($H48,$P$7:$T$185,5,FALSE) -> 2127.75 | O48: 외주가공비 | P48: 61001800 | Q48: 0 | R48: 0 | S48: 0 | T48: 0
H49: 71102200 | I49: 잡이익(영업활동) | J49: =VLOOKUP(H49,$P$7:$T$185,2,FALSE) -> 13948125 | K49: =VLOOKUP($H49,$P$7:$T$185,3,FALSE) -> 12361227 | L49: =VLOOKUP($H49,$P$7:$T$185,4,FALSE) -> 18128882 | M49: =VLOOKUP($H49,$P$7:$T$185,5,FALSE) -> 8026877.6 | N49: 개발비 회수내역 | O49: 지급수수료 | P49: 61001900 | Q49: 2183721.2 | R49: 4526632.4 | S49: 9280370.1 | T49: 2999169.8
H50: 72000000 | I50: 기타비용 | J50: =VLOOKUP(H50,$P$7:$T$185,2,FALSE) -> 3356383.7 | K50: =VLOOKUP($H50,$P$7:$T$185,3,FALSE) -> 2914299.8 | L50: =VLOOKUP($H50,$P$7:$T$185,4,FALSE) -> 14013974 | M50: =VLOOKUP($H50,$P$7:$T$185,5,FALSE) -> 6726783 | N50: 매출로 대체 | O50: 접대비 | P50: 61002000 | Q50: 294217.49 | R50: 343249.26 | S50: 457189.33 | T50: 238918.7
H51: 72100100 | I51: 외환차손(영업활동) | J51: =VLOOKUP(H51,$P$7:$T$185,2,FALSE) -> 704105.45 | K51: =VLOOKUP($H51,$P$7:$T$185,3,FALSE) -> 679628.89 | L51: =VLOOKUP($H51,$P$7:$T$185,4,FALSE) -> 600510.27 | M51: =VLOOKUP($H51,$P$7:$T$185,5,FALSE) -> 1741064.5 | O51: 도서인쇄비 | P51: 61002100 | Q51: 36511.36 | R51: 37405.32 | S51: 41994.82 | T51: 10483.64
H52: 72100200 | I52: 외화환산손실(영업활동) | J52: =VLOOKUP(H52,$P$7:$T$185,2,FALSE) -> -323186.12 | K52: =VLOOKUP($H52,$P$7:$T$185,3,FALSE) -> 62542.29 | L52: =VLOOKUP($H52,$P$7:$T$185,4,FALSE) -> 473975.82 | M52: =VLOOKUP($H52,$P$7:$T$185,5,FALSE) -> -509280.37 | O52: 교육훈련비 | P52: 61002200 | Q52: 141964.69 | R52: 228920.63 | S52: 358739.77 | T52: 119702.64
H53: 72100300 | I53: 유형자산처분손실 | J53: =VLOOKUP(H53,$P$7:$T$185,2,FALSE) -> 205782.86 | K53: =VLOOKUP($H53,$P$7:$T$185,3,FALSE) -> 31264.54 | L53: =VLOOKUP($H53,$P$7:$T$185,4,FALSE) -> 0 | M53: =VLOOKUP($H53,$P$7:$T$185,5,FALSE) -> 32404.82 | O53: 차량유지비 | P53: 61002300 | Q53: 555498.58 | R53: 506815.3 | S53: 367652.7 | T53: 109967.12
H54: 72100400 | I54: 유형자산폐기손실 | J54: =VLOOKUP(H54,$P$7:$T$185,2,FALSE) -> 55339.21 | K54: =VLOOKUP($H54,$P$7:$T$185,3,FALSE) -> 515425.89 | L54: =VLOOKUP($H54,$P$7:$T$185,4,FALSE) -> 3879.93 | M54: =VLOOKUP($H54,$P$7:$T$185,5,FALSE) -> 275572.15 | O54: 회의비 | P54: 61002400 | Q54: 0 | R54: 0 | S54: 0 | T54: 0
H55: 72102600 | I55: 잡손실(영업활동) | J55: =VLOOKUP(H55,$P$7:$T$185,2,FALSE) -> 2714342.3 | K55: =VLOOKUP($H55,$P$7:$T$185,3,FALSE) -> 1625438.2 | L55: =VLOOKUP($H55,$P$7:$T$185,4,FALSE) -> 12935608 | M55: =VLOOKUP($H55,$P$7:$T$185,5,FALSE) -> 5187021.9 | O55: 경상개발비 | P55: 61002500 | Q55: 3204555.1 | R55: 5529165.6 | S55: 10304302 | T55: 7144324.4
H56: 72900000 | I56: 조정영업이익 | J56: =VLOOKUP(H56,$P$7:$T$185,2,FALSE) -> 12384250 | K56: =VLOOKUP($H56,$P$7:$T$185,3,FALSE) -> 8566444.1 | L56: =VLOOKUP($H56,$P$7:$T$185,4,FALSE) -> 21408569 | M56: =VLOOKUP($H56,$P$7:$T$185,5,FALSE) -> 13421880 | O56: 연구비 | P56: 61002600 | Q56: 0 | R56: 0 | S56: 0 | T56: 0
H57: 73000000 | I57: 영업외수익 | J57: =VLOOKUP(H57,$P$7:$T$185,2,FALSE) -> 1816061.6 | K57: =VLOOKUP($H57,$P$7:$T$185,3,FALSE) -> 3113932.2 | L57: =VLOOKUP($H57,$P$7:$T$185,4,FALSE) -> 537901.65 | M57: =VLOOKUP($H57,$P$7:$T$185,5,FALSE) -> 897573.44 | O57: 광고선전비 | P57: 61002700 | Q57: 155033.49 | R57: 27353.34 | S57: 515 | T57: 0
H58: 73100000 | I58: 금융수익 | J58: =VLOOKUP(H58,$P$7:$T$185,2,FALSE) -> 190968.35 | K58: =VLOOKUP($H58,$P$7:$T$185,3,FALSE) -> 77729.42 | L58: =VLOOKUP($H58,$P$7:$T$185,4,FALSE) -> 94991.47 | M58: =VLOOKUP($H58,$P$7:$T$185,5,FALSE) -> 24179.32 | O58: 견본비 | P58: 61002800 | Q58: 0 | R58: 0 | S58: 0 | T58: 0
H59: 73100100 | I59: 이자수익 | J59: =VLOOKUP(H59,$P$7:$T$185,2,FALSE) -> 190968.35 | K59: =VLOOKUP($H59,$P$7:$T$185,3,FALSE) -> 77729.42 | L59: =VLOOKUP($H59,$P$7:$T$185,4,FALSE) -> 94991.47 | M59: =VLOOKUP($H59,$P$7:$T$185,5,FALSE) -> 24179.32 | O59: 대손상각비 | P59: 61002900 | Q59: 945270.45 | R59: 0 | S59: 26615.78 | T59: 0
H60: 73110000 | I60: 기타 영업외수익 | J60: =VLOOKUP(H60,$P$7:$T$185,2,FALSE) -> 1625093.3 | K60: =VLOOKUP($H60,$P$7:$T$185,3,FALSE) -> 3036202.7 | L60: =VLOOKUP($H60,$P$7:$T$185,4,FALSE) -> 442910.18 | M60: =VLOOKUP($H60,$P$7:$T$185,5,FALSE) -> 873394.12 | O60: 무형자산상각비 | P60: 61003000 | Q60: 496401.01 | R60: 447298.93 | S60: 165832.59 | T60: 106857.06
H61: 73110200 | I61: 외환차익(비영업활동) | J61: =VLOOKUP(H61,$P$7:$T$185,2,FALSE) -> 109475.68 | K61: =VLOOKUP($H61,$P$7:$T$185,3,FALSE) -> 3116505.5 | L61: =VLOOKUP($H61,$P$7:$T$185,4,FALSE) -> 98588.86 | M61: =VLOOKUP($H61,$P$7:$T$185,5,FALSE) -> 531532.75 | O61: 수출제비용 | P61: 61003200 | Q61: 0 | R61: 0 | S61: 0 | T61: 0
H62: 73110300 | I62: 외화환산이익(비영업활동) | J62: =VLOOKUP(H62,$P$7:$T$185,2,FALSE) -> 496583.59 | K62: =VLOOKUP($H62,$P$7:$T$185,3,FALSE) -> -922160.92 | L62: =VLOOKUP($H62,$P$7:$T$185,4,FALSE) -> -376946.19 | M62: =VLOOKUP($H62,$P$7:$T$185,5,FALSE) -> 212509.2 | O62: 해외시장개척비 | P62: 61003300 | Q62: 0 | R62: 0 | S62: 0 | T62: 0
H63: 73110800 | I63: 파생상품자산/부채 평가이익(비영업활동) | J63: =VLOOKUP(H63,$P$7:$T$185,2,FALSE) -> 0 | K63: =VLOOKUP($H63,$P$7:$T$185,3,FALSE) -> 0 | L63: =VLOOKUP($H63,$P$7:$T$185,4,FALSE) -> 243846 | M63: =VLOOKUP($H63,$P$7:$T$185,5,FALSE) -> 0 | O63: 판매수수료 | P63: 61003400 | Q63: 0 | R63: 0 | S63: 0 | T63: 0
H64: 73110900 | I64: 파생상품자산/부채 거래이익(비영업활동) | J64: =VLOOKUP(H64,$P$7:$T$185,2,FALSE) -> 0 | K64: =VLOOKUP($H64,$P$7:$T$185,3,FALSE) -> 0 | L64: =VLOOKUP($H64,$P$7:$T$185,4,FALSE) -> 275717 | M64: =VLOOKUP($H64,$P$7:$T$185,5,FALSE) -> 0 | O64: A/S 비 | P64: 61003500 | Q64: 2112914.2 | R64: 0 | S64: 398054.94 | T64: 465064.39
H65: 73119900 | I65: 기타영업외수익 | J65: =VLOOKUP(H65,$P$7:$T$185,2,FALSE) -> 1019034 | K65: =VLOOKUP($H65,$P$7:$T$185,3,FALSE) -> 841858.2 | L65: =VLOOKUP($H65,$P$7:$T$185,4,FALSE) -> 201704.51 | M65: =VLOOKUP($H65,$P$7:$T$185,5,FALSE) -> 129352.17 | O65: 공사하도급비 | P65: 61003600 | Q65: 0 | R65: 0 | S65: 0 | T65: 0
H66: 74000000 | I66: 영업외비용 | J66: =VLOOKUP(H66,$P$7:$T$185,2,FALSE) -> 5637470.5 | K66: =VLOOKUP($H66,$P$7:$T$185,3,FALSE) -> 5709311.3 | L66: =VLOOKUP($H66,$P$7:$T$185,4,FALSE) -> 4488263.5 | M66: =VLOOKUP($H66,$P$7:$T$185,5,FALSE) -> 2987324 | O66: 보상비 | P66: 61003700 | Q66: 0 | R66: 0 | S66: 0 | T66: 0
H67: 74100000 | I67: 금융비용 | J67: =VLOOKUP(H67,$P$7:$T$185,2,FALSE) -> 4088583.2 | K67: =VLOOKUP($H67,$P$7:$T$185,3,FALSE) -> 3976922 | L67: =VLOOKUP($H67,$P$7:$T$185,4,FALSE) -> 3759400.7 | M67: =VLOOKUP($H67,$P$7:$T$185,5,FALSE) -> 2083680.8 | O67: 품질보증충당부채전입액 | P67: 61003800 | Q67: 22953.46 | R67: 812696.15 | S67: 600000 | T67: 550000
H68: 74100100 | I68: 이자비용 | J68: =VLOOKUP(H68,$P$7:$T$185,2,FALSE) -> 4088583.2 | K68: =VLOOKUP($H68,$P$7:$T$185,3,FALSE) -> 3976922 | L68: =VLOOKUP($H68,$P$7:$T$185,4,FALSE) -> 3759400.7 | M68: =VLOOKUP($H68,$P$7:$T$185,5,FALSE) -> 2083680.8 | O68: 손실부담충당부채전입 | P68: 61003900 | Q68: 0 | R68: 0 | S68: 0 | T68: 0
H69: 74110000 | I69: 기타 영업외비용 | J69: =VLOOKUP(H69,$P$7:$T$185,2,FALSE) -> 1548887.3 | K69: =VLOOKUP($H69,$P$7:$T$185,3,FALSE) -> 1732389.3 | L69: =VLOOKUP($H69,$P$7:$T$185,4,FALSE) -> 728862.85 | M69: =VLOOKUP($H69,$P$7:$T$185,5,FALSE) -> 903643.19 | O69: 구조조정부채전입 | P69: 61004000 | Q69: 0 | R69: 0 | S69: 0 | T69: 0
H70: 74110200 | I70: 외환차손(비영업활동) | J70: =VLOOKUP(H70,$P$7:$T$185,2,FALSE) -> 77123.87 | K70: =VLOOKUP($H70,$P$7:$T$185,3,FALSE) -> 229698.15 | L70: =VLOOKUP($H70,$P$7:$T$185,4,FALSE) -> 67168.48 | M70: =VLOOKUP($H70,$P$7:$T$185,5,FALSE) -> 22491.9 | O70: 기타(손실)충당부채전입 | P70: 61004090 | Q70: 0 | R70: 0 | S70: 0 | T70: 0
H71: 74110300 | I71: 외화환산손실(비영업활동) | J71: =VLOOKUP(H71,$P$7:$T$185,2,FALSE) -> 824875.35 | K71: =VLOOKUP($H71,$P$7:$T$185,3,FALSE) -> -84362.31 | L71: =VLOOKUP($H71,$P$7:$T$185,4,FALSE) -> 229902.63 | M71: =VLOOKUP($H71,$P$7:$T$185,5,FALSE) -> 145192.68 | O71: 품질보증부채환입 | P71: 71101600 | Q71: 0 | R71: 0 | S71: 0 | T71: 0
H72: 74110800 | I72: 파생상품자산/부채 평가손실(비영업활동) | J72: =VLOOKUP(H72,$P$7:$T$185,2,FALSE) -> 581952 | K72: =VLOOKUP($H72,$P$7:$T$185,3,FALSE) -> 275717 | L72: =VLOOKUP($H72,$P$7:$T$185,4,FALSE) -> 0 | M72: =VLOOKUP($H72,$P$7:$T$185,5,FALSE) -> 98377 | O72: 손실부담계약충당부채환입 | P72: 71101700 | Q72: 0 | R72: 0 | S72: 0 | T72: 0
H73: 74110900 | I73: 파생상품자산/부채 거래손실(비영업활동) | J73: =VLOOKUP(H73,$P$7:$T$185,2,FALSE) -> 0 | K73: =VLOOKUP($H73,$P$7:$T$185,3,FALSE) -> 1036128 | L73: =VLOOKUP($H73,$P$7:$T$185,4,FALSE) -> 200000 | M73: =VLOOKUP($H73,$P$7:$T$185,5,FALSE) -> 243846 | O73: 구조조정충당부채환입 | P73: 71101730 | Q73: 0 | R73: 0 | S73: 0 | T73: 0
H74: 74119900 | I74: 기타영업외비용 | J74: =VLOOKUP(H74,$P$7:$T$185,2,FALSE) -> 64936.09 | K74: =VLOOKUP($H74,$P$7:$T$185,3,FALSE) -> 275208.45 | L74: =VLOOKUP($H74,$P$7:$T$185,4,FALSE) -> 231791.74 | M74: =VLOOKUP($H74,$P$7:$T$185,5,FALSE) -> 393735.61 | O74: 기타(손실)충당부채환입 | P74: 71101790 | Q74: 0 | R74: 0 | S74: 0 | T74: 0
H75: 75000000 | I75: 법인세비용차감전계속사업손익 | J75: =VLOOKUP(H75,$P$7:$T$185,2,FALSE) -> 8562841.4 | K75: =VLOOKUP($H75,$P$7:$T$185,3,FALSE) -> 5971065 | L75: =VLOOKUP($H75,$P$7:$T$185,4,FALSE) -> 17458207 | M75: =VLOOKUP($H75,$P$7:$T$185,5,FALSE) -> 11332130 | O75: 대손충당금환입 | P75: 71101800 | Q75: 0 | R75: -928709.54 | S75: 0 | T75: 0
H76: 76000000 | I76: 계속사업손익법인세비용 | J76: =VLOOKUP(H76,$P$7:$T$185,2,FALSE) -> -225534.06 | K76: =VLOOKUP($H76,$P$7:$T$185,3,FALSE) -> -1633710 | L76: =VLOOKUP($H76,$P$7:$T$185,4,FALSE) -> 2710675.8 | M76: =VLOOKUP($H76,$P$7:$T$185,5,FALSE) -> 4248142.7 | O76: 퇴직위로금 | P76: 72102100 | Q76: 0 | R76: 0 | S76: 0 | T76: 0
H77: 76100000 | I77: 법인세비용 | J77: =VLOOKUP(H77,$P$7:$T$185,2,FALSE) -> -225534.06 | K77: =VLOOKUP($H77,$P$7:$T$185,3,FALSE) -> -1633710 | L77: =VLOOKUP($H77,$P$7:$T$185,4,FALSE) -> 2710675.8 | M77: =VLOOKUP($H77,$P$7:$T$185,5,FALSE) -> 4248142.7 | O77: 기타판관비 | P77: 61004100 | Q77: 337798.54 | R77: 337798.54 | S77: 337798.54 | T77: 168899.27
H78: 88000000 | I78: 총당기순이익 | J78: =VLOOKUP(H78,$P$7:$T$185,2,FALSE) -> 8788375.4 | K78: =VLOOKUP($H78,$P$7:$T$185,3,FALSE) -> 7604775 | L78: =VLOOKUP($H78,$P$7:$T$185,4,FALSE) -> 14747531 | M78: =VLOOKUP($H78,$P$7:$T$185,5,FALSE) -> 7083987 | O78: 영업이익 | P78: 70000000 | Q78: 969377.6 | R78: -1535131.2 | S78: 16795055 | T78: 11443418
O79: 기타수익 | P79: 71000000 | Q79: 14771256 | R79: 13015875 | S79: 18627488 | T79: 8705245.3
O80: 임대료수익 | P80: 71100100 | Q80: 0 | R80: 0 | S80: 0 | T80: 0
O81: 수수료수익 | P81: 71100200 | Q81: 0 | R81: 0 | S81: 0 | T81: 0
O82: 외환차익(영업활동) | P82: 71100300 | Q82: 848600.05 | R82: 451580.41 | S82: 667737.21 | T82: 323190.76
O83: 외화환산이익(영업활동) | P83: 71100400 | Q83: -25468.83 | R83: 200571.65 | S83: -191372.56 | T83: 353049.14
E84: 12년도에 고정이었다가 13년부터 변동 | O84: 유형자산처분이익 | P84: 71100500 | Q84: 0 | R84: 2495.83 | S84: 22241.19 | T84: 2127.75
O85: 유형자산손상차손환입 | P85: 71100600 | Q85: 0 | R85: 0 | S85: 0 | T85: 0
O86: 무형자산처분이익 | P86: 71100700 | Q86: 0 | R86: 0 | S86: 0 | T86: 0
O87: 무형자산손상차손환입 | P87: 71100800 | Q87: 0 | R87: 0 | S87: 0 | T87: 0
O88: 기타투자자산처분이익 | P88: 71100900 | Q88: 0 | R88: 0 | S88: 0 | T88: 0
O89: 기타투자자산손상차손환입 | P89: 71101000 | Q89: 0 | R89: 0 | S89: 0 | T89: 0
O90: 파생상품자산/부채 평가이익(영업활동) | P90: 71101400 | Q90: 0 | R90: 0 | S90: 0 | T90: 0
O91: 파생상품자산/부채 거래이익(영업활동) | P91: 71101500 | Q91: 0 | R91: 0 | S91: 0 | T91: 0
O92: 기타의대손충당금환입 | P92: 71101900 | Q92: 0 | R92: 0 | S92: 0 | T92: 0
O93: 기타영업수익(영업활동) | P93: 71102200 | Q93: 13948125 | R93: 12361227 | S93: 18128882 | T93: 8026877.6
O94: 기타비용 | P94: 72000000 | Q94: 3356383.7 | R94: 2914299.8 | S94: 14013974 | T94: 6726783
O95: 외환차손(영업활동) | P95: 72100100 | Q95: 704105.45 | R95: 679628.89 | S95: 600510.27 | T95: 1741064.5
O96: 외화환산손실(영업활동) | P96: 72100200 | Q96: -323186.12 | R96: 62542.29 | S96: 473975.82 | T96: -509280.37
... O116: 영업외수익 | P116: 73000000 | Q116: 1816061.6 | R116: 3113932.2 | S116: 537901.65 | T116: 897573.44
O117: 금융수익 | P117: 73100000 | Q117: 190968.35 | R117: 77729.42 | S117: 94991.47 | T117: 24179.32
O118: 이자수익 | P118: 73100100 | Q118: 190968.35 | R118: 77729.42 | S118: 94991.47 | T118: 24179.32
O119: 배당금수익(기타회사용) | P119: 73100200 | Q119: 0 | R119: 0 | S119: 0 | T119: 0
O120: 단기매매증권평가이익 | P120: 73100300 | Q120: 0 | R120: 0 | S120: 0 | T120: 0
...

Sheet BS(RMB,)
D1: =D7/'IS(RMB)'!D8 -> 0.29638037 | E1: =E7/'IS(RMB)'!E8 -> 0.26766974 | F1: =F7/'IS(RMB)'!F8 -> 0.59734529 | W1: 171.88 | X1: 174.09 | Y1: 176.81 | Z1: 181.09
B2: 재무상태표_무석 | I2: 연결계정코드 | J2: 연결계정명 | K2: 2012년 | L2: 2013년 | M2: 2014년 | N2: 2015년 6월말 | U2: 연결계정코드 | V2: 연결계정명 | W2: 2012 | X2: 2013 | Y2: 2014 | Z2: 2015
C3: 2012년 | D3: 2013년 | E3: 2014년 | F3: 2015년 | I3: 10000000 | J3: 자산 | K3: =VLOOKUP($I3,$U$4:$Z$468,3,FALSE) -> 2.7438482e+08 | L3: =VLOOKUP($I3,$U$4:$Z$468,4,FALSE) -> 3.3324998e+08 | M3: =VLOOKUP($I3,$U$4:$Z$468,5,FALSE) -> 4.0110657e+08 | N3: =VLOOKUP($I3,$U$4:$Z$468,6,FALSE) -> 4.4421822e+08 | W3: K-GAAP(CNY) | X3: K-GAAP(CNY) | Y3: K-GAAP(CNY) | Z3: K-GAAP(CNY)
B4: RMB'000 | C4: 12월 31일 | D4: 12월 31일 | E4: 12월 31일 | F4: 6월 30일 | I4: 11000000 | J4: 유동자산 | K4: =VLOOKUP($I4,$U$4:$Z$468,3,FALSE) -> 1.554266e+08 | L4: =VLOOKUP($I4,$U$4:$Z$468,4,FALSE) -> 1.8395028e+08 | M4: =VLOOKUP($I4,$U$4:$Z$468,5,FALSE) -> 1.9031451e+08 | N4: =VLOOKUP($I4,$U$4:$Z$468,6,FALSE) -> 2.1575731e+08 | U4: 10000000 | V4: 자산 | W4: 2.7438482e+08 | X4: 3.3324998e+08 | Y4: 4.0110657e+08 | Z4: 4.4421822e+08
B5: 유동자산 | C5: =K4 -> 1.554266e+08 | D5: =L4 -> 1.8395028e+08 | E5: =M4 -> 1.9031451e+08 | F5: =N4 -> 2.1575731e+08 | J5: 당좌자산 | K5: 0 | L5: 0 | M5: 0 | N5: 0 | U5: 11000000 | V5: 유동자산 | W5: 1.554266e+08 | X5: 1.8395028e+08 | Y5: 1.9031451e+08 | Z5: 2.1575731e+08
B6: 현금및현금성자산 | C6: =K6 -> 6544146.5 | D6: =L6 -> 5758342.2 | E6: =M6 -> 6290709.5 | F6: =N6 -> 2859003.5 | I6: 11101000 | J6: 현금및현금성자산 | K6: =VLOOKUP($I6,$U$4:$Z$468,3,FALSE) -> 6544146.5 | L6: =VLOOKUP($I6,$U$4:$Z$468,4,FALSE) -> 5758342.2 | M6: =VLOOKUP($I6,$U$4:$Z$468,5,FALSE) -> 6290709.5 | N6: =VLOOKUP($I6,$U$4:$Z$468,6,FALSE) -> 2859003.5 | V6: 당좌자산 | W6: 87465759 | X6: 93016895 | Y6: 1.0675764e+08 | Z6: 1.3245202e+08
B7: 매출채권 | C7: =K10+K13 -> 80351270 | D7: =L10+L13 -> 86422336 | E7: =M10+M13 -> 98504881 | F7: =N10+N13 -> 1.2749784e+08 | G7: 중국 OEM 업체 매출 증가에 따라 2015년 증가함 | I7: 11101001 | J7: 현금 | K7: =VLOOKUP($I7,$U$4:$Z$468,3,FALSE) -> 1582.88 | L7: =VLOOKUP($I7,$U$4:$Z$468,4,FALSE) -> 1117.4 | M7: =VLOOKUP($I7,$U$4:$Z$468,5,FALSE) -> 37000.27 | N7: =VLOOKUP($I7,$U$4:$Z$468,6,FALSE) -> 8615.71 | U7: 11101000 | V7: 현금및현금성자산 | W7: 6544146.5 | X7: 5758342.2 | Y7: 6290709.5 | Z7: 2859003.5
B8: 재고자산 | C8: =K20 -> 61491932 | D8: =L20 -> 64345113 | E8: =M20 -> 70443675 | F8: =N20 -> 71854417 | G8: 현재 제품 재고를 늘리고 원재료 재고를 줄이는 노력을 하여 안전재고 수준이 낮아짐 | I8: 11101007 | J8: 외화기타 | K8: =VLOOKUP($I8,$U$4:$Z$468,3,FALSE) -> 6542563.6 | L8: =VLOOKUP($I8,$U$4:$Z$468,4,FALSE) -> 5757224.8 | M8: =VLOOKUP($I8,$U$4:$Z$468,5,FALSE) -> 6253709.2 | N8: =VLOOKUP($I8,$U$4:$Z$468,6,FALSE) -> 2850387.7 | U8: 11101001 | V8: 현금 | W8: 1582.88 | X8: 1117.4 | Y8: 37000.27 | Z8: 8615.71
B9: 기타유동자산 | C9: =SUM(K15,K31,K19) -> 7039253.3 | D9: =SUM(L15,L31,L19) -> 27424491 | E9: =SUM(M15,M31,M19) -> 15075240 | F9: =SUM(N15,N31,N19) -> 13546055 | I9: 11110000 | J9: 매출채권 및 기타채권 | K9: =VLOOKUP($I9,$U$4:$Z$468,3,FALSE) -> 80921613 | L9: =VLOOKUP($I9,$U$4:$Z$468,4,FALSE) -> 87258552 | M9: =VLOOKUP($I9,$U$4:$Z$468,5,FALSE) -> 1.0022309e+08 | N9: =VLOOKUP($I9,$U$4:$Z$468,6,FALSE) -> 1.2959302e+08 | U9: 11101002 | V9: 원화당좌 | W9: 0 | X9: 0 | Y9: 0 | Z9: 0
B10: 비유동자산 | C10: =K36 -> 1.1895822e+08 | D10: =L36 -> 1.492997e+08 | E10: =M36 -> 2.1079206e+08 | F10: =N36 -> 2.2846091e+08 | I10: 11111000 | J10: 매출채권 | K10: =VLOOKUP($I10,$U$4:$Z$468,3,FALSE) -> 81302580 | L10: =VLOOKUP($I10,$U$4:$Z$468,4,FALSE) -> 86444936 | M10: =VLOOKUP($I10,$U$4:$Z$468,5,FALSE) -> 98554097 | N10: =VLOOKUP($I10,$U$4:$Z$468,6,FALSE) -> 1.2754705e+08 | U10: 11101003 | V10: 원화보통 | W10: 0 | X10: 0 | Y10: 0 | Z10: 0
B11: 유형자산 | C11: =K40 -> 92953198 | D11: =L40 -> 1.1709264e+08 | E11: =M40 -> 1.7491401e+08 | F11: =N40 -> 1.9292588e+08 | G11: 2014년 전장 사업 관련 기계장치 구입으로 인하여 증가. | I11: 11111002 | J11: 외화외상매출금 | K11: =VLOOKUP($I11,$U$4:$Z$468,3,FALSE) -> 53281627 | L11: =VLOOKUP($I11,$U$4:$Z$468,4,FALSE) -> 66467579 | M11: =VLOOKUP($I11,$U$4:$Z$468,5,FALSE) -> 90070397 | N11: =VLOOKUP($I11,$U$4:$Z$468,6,FALSE) -> 1.2054705e+08 | U11: 11101004 | V11: 원화기타 | W11: 0 | X11: 0 | Y11: 0 | Z11: 0
B12: 무형자산 | C12: =K64 -> 5943322.5 | D12: =L64 -> 12036626 | E12: =M64 -> 13484626 | F12: =N64 -> 13517534 | I12: 11111003 | J12: 받을어음 | K12: =VLOOKUP($I12,$U$4:$Z$468,3,FALSE) -> 28020953 | L12: =VLOOKUP($I12,$U$4:$Z$468,4,FALSE) -> 19977357 | M12: =VLOOKUP($I12,$U$4:$Z$468,5,FALSE) -> 8483700 | N12: =VLOOKUP($I12,$U$4:$Z$468,6,FALSE) -> 7000000 | U12: 11101005 | V12: 외화당좌 | W12: 0 | X12: 0 | Y12: 0 | Z12: 0
B13: 기타비유동자산 | C13: =K70+K73+K38 -> 20061701 | D13: =L70+L73+L38 -> 20170432 | E13: =M70+M73+M38 -> 22393427 | F13: =N70+N73+N38 -> 22017493 | I13: 11111100 | J13: (매출채권 대손충당금) | K13: =VLOOKUP($I13,$U$4:$Z$468,3,FALSE) -> -951310.12 | L13: =VLOOKUP($I13,$U$4:$Z$468,4,FALSE) -> -22600.58 | M13: =VLOOKUP($I13,$U$4:$Z$468,5,FALSE) -> -49216.36 | N13: =VLOOKUP($I13,$U$4:$Z$468,6,FALSE) -> -49216.36 | U13: 11101006 | V13: 외화보통 | W13: 0 | X13: 0 | Y13: 0 | Z13: 0
B14: 자산총계 | C14: =K3 -> 2.7438482e+08 | D14: =L3 -> 3.3324998e+08 | E14: =M3 -> 4.0110657e+08 | F14: =N3 -> 4.4421822e+08 | I14: 11111102 | J14: (대손충당금:외화외상매출금) | K14: =VLOOKUP($I14,$U$4:$Z$468,3,FALSE) -> -951310.12 | L14: =VLOOKUP($I14,$U$4:$Z$468,4,FALSE) -> -22600.58 | M14: =VLOOKUP($I14,$U$4:$Z$468,5,FALSE) -> -49216.36 | N14: =VLOOKUP($I14,$U$4:$Z$468,6,FALSE) -> -49216.36 | U14: 11101007 | V14: 외화기타 | W14: 6542563.6 | X14: 5757224.8 | Y14: 6253709.2 | Z14: 2850387.7
B15: 유동부채 | C15: =K75 -> 1.2102811e+08 | D15: =L75 -> 1.8974642e+08 | E15: =M75 -> 2.4551367e+08 | F15: =N75 -> 2.8259412e+08 | I15: 11111701 | J15: 미수금 | K15: =VLOOKUP($I15,$U$4:$Z$468,3,FALSE) -> 570343.06 | L15: =VLOOKUP($I15,$U$4:$Z$468,4,FALSE) -> 836216.89 | M15: =VLOOKUP($I15,$U$4:$Z$468,5,FALSE) -> 1718205.6 | N15: =VLOOKUP($I15,$U$4:$Z$468,6,FALSE) -> 2095177.5 | U15: 11101008 | V15: 현금등가물 | W15: 0 | X15: 0 | Y15: 0 | Z15: 0
B16: 매입채무 | C16: =K77 -> 47779997 | D16: =L77 -> 54146686 | E16: =M77 -> 64828470 | F16: =N77 -> 89071341 | I16: 11111801 | J16: (미수금대손충당금) | K16: =VLOOKUP($I16,$U$4:$Z$468,3,FALSE) -> 0 | L16: =VLOOKUP($I16,$U$4:$Z$468,4,FALSE) -> 0 | M16: =VLOOKUP($I16,$U$4:$Z$468,5,FALSE) -> 0 | N16: =VLOOKUP($I16,$U$4:$Z$468,6,FALSE) -> 0 | U16: 11111200 | V16: 단기금융상품 | W16: 0 | X16: 0 | Y16: 0 | Z16: 0
B17: 단기차입금 | C17: =K85 -> 54683850 | D17: =L85 -> 1.1041775e+08 | E17: =M85 -> 1.3980301e+08 | F17: =N85 -> 1.5336941e+08 | I17: 11120000 | J17: (유동성)당기손익인식금융자산 | K17: =VLOOKUP($I17,$U$4:$Z$468,3,FALSE) -> 0 | L17: =VLOOKUP($I17,$U$4:$Z$468,4,FALSE) -> 0 | M17: =VLOOKUP($I17,$U$4:$Z$468,5,FALSE) -> 243846 | N17: =VLOOKUP($I17,$U$4:$Z$468,6,FALSE) -> 0 | U17: 11111201 | V17: 단기정기예/적금 | W17: 0 | X17: 0 | Y17: 0 | Z17: 0
B18: 미지급금 | C18: =K80 -> 13286395 | D18: =L80 -> 19082062 | E18: =M80 -> 29269134 | F18: =N80 -> 27580638 | I18: 11150000 | J18: (유동성)위험회피파생상품자산 | K18: =VLOOKUP($I18,$U$4:$Z$468,3,FALSE) -> 0 | L18: =VLOOKUP($I18,$U$4:$Z$468,4,FALSE) -> 0 | M18: =VLOOKUP($I18,$U$4:$Z$468,5,FALSE) -> 243846 | N18: =VLOOKUP($I18,$U$4:$Z$468,6,FALSE) -> 0 | U18: 11111202 | V18: 단기특정금전신탁 | W18: 0 | X18: 0 | Y18: 0 | Z18: 0
B19: 기타유동부채 | C19: =SUM(K87,K81,K83) -> 5277864.6 | D19: =SUM(L87,L81,L83) -> 6099915.1 | E19: =SUM(M87,M81,M83) -> 11613050 | F19: =SUM(N87,N81,N83) -> 12572736 | I19: 11151001 | J19: (유동성)공정가치위험회피파생상품자산:금융 | K19: =VLOOKUP($I19,$U$4:$Z$468,3,FALSE) -> 0 | L19: =VLOOKUP($I19,$U$4:$Z$468,4,FALSE) -> 0 | M19: =VLOOKUP($I19,$U$4:$Z$468,5,FALSE) -> 243846 | N19: =VLOOKUP($I19,$U$4:$Z$468,6,FALSE) -> 0 | U19: 11111203 | V19: 기타단기금융상품 | W19: 0 | X19: 0 | Y19: 0 | Z19: 0
B20: 비유동부채 | C20: =K93 -> 28225974 | D20: =L93 -> 16791127 | E20: =M93 -> 16412932 | F20: =N93 -> 16949432 | I20: 11160000 | J20: 재고자산 | K20: =VLOOKUP($I20,$U$4:$Z$468,3,FALSE) -> 61491932 | L20: =VLOOKUP($I20,$U$4:$Z$468,4,FALSE) -> 64345113 | M20: =VLOOKUP($I20,$U$4:$Z$468,5,FALSE) -> 70443675 | N20: =VLOOKUP($I20,$U$4:$Z$468,6,FALSE) -> 71854417 | U20: 11110000 | V20: 매출채권 및 기타채권 | W20: 80921613 | X20: 87258552 | Y20: 1.0022309e+08 | Z20: 1.2959302e+08
B21: 장기차입금 | C21: =K94 -> 28000000 | D21: =L94 -> 15242250 | E21: =M94 -> 15297500 | F21: =N94 -> 15284000 | I21: 11161001 | J21: 상품 | K21: =VLOOKUP($I21,$U$4:$Z$468,3,FALSE) -> 9803182.4 | L21: =VLOOKUP($I21,$U$4:$Z$468,4,FALSE) -> 415842.72 | M21: =VLOOKUP($I21,$U$4:$Z$468,5,FALSE) -> 410746.44 | N21: =VLOOKUP($I21,$U$4:$Z$468,6,FALSE) -> 1030400.6 | P21: 2012 | Q21: 2013 | R21: 2014 | S21: 2015 | U21: 11111000 | V21: 매출채권 | W21: 81302580 | X21: 86444936 | Y21: 98554097 | Z21: 1.2754705e+08
B22: 판매보증충당부채 | C22: =K96 -> 225974.47 | D22: =L96 -> 1548877.4 | E22: =M96 -> 1115432.1 | F22: =N96 -> 1665432.1 | I22: 11161101 | J22: (상품평가충당금) | K22: =VLOOKUP($I22,$U$4:$Z$468,3,FALSE) -> 0 | L22: =VLOOKUP($I22,$U$4:$Z$468,4,FALSE) -> 0 | M22: =VLOOKUP($I22,$U$4:$Z$468,5,FALSE) -> 0 | N22: =VLOOKUP($I22,$U$4:$Z$468,6,FALSE) -> 0 | O22: 상품 | P22: =K21/K$20 -> 0.15942225 | Q22: =L21/L$20 -> 0.0064626931 | R22: =M21/M$20 -> 0.0058308492 | S22: =N21/N$20 -> 0.014340114 | U22: 11111001 | V22: 원화외상매출금 | W22: 0 | X22: 0 | Y22: 0 | Z22: 0
B23: 부채총계 | C23: =K74 -> 1.4925408e+08 | D23: =L74 -> 2.0653754e+08 | E23: =M74 -> 2.619266e+08 | F23: =N74 -> 2.9954355e+08 | I23: 11161201 | J23: 제품 | K23: =VLOOKUP($I23,$U$4:$Z$468,3,FALSE) -> 23996952 | L23: =VLOOKUP($I23,$U$4:$Z$468,4,FALSE) -> 33470323 | M23: =VLOOKUP($I23,$U$4:$Z$468,5,FALSE) -> 33831411 | N23: =VLOOKUP($I23,$U$4:$Z$468,6,FALSE) -> 35432165 | O23: 제품 | P23: =(K23+K24)/K$20 -> 0.38816126 | Q23: =(L23+L24)/L$20 -> 0.49957757 | R23: =(M23+M24)/M$20 -> 0.45712572 | S23: =(N23+N24)/N$20 -> 0.46853812 | U23: 11111002 | V23: 외화외상매출금 | W23: 53281627 | X23: 66467579 | Y23: 90070397 | Z23: 1.2054705e+08
B24: 자본금 | C24: =K100 -> 54568890 | D24: =L100 -> 85407390 | E24: =M100 -> 85407390 | F24: =N100 -> 85407390 | I24: 11161301 | J24: (제품평가충당금) | K24: =VLOOKUP($I24,$U$4:$Z$468,3,FALSE) -> -128166.48 | L24: =VLOOKUP($I24,$U$4:$Z$468,4,FALSE) -> -1324947.7 | M24: =VLOOKUP($I24,$U$4:$Z$468,5,FALSE) -> -1629796.1 | N24: =VLOOKUP($I24,$U$4:$Z$468,6,FALSE) -> -1765632.2 | O24: 반제품 | P24: =(K25+K26)/K20 -> 0.27800801 | Q24: =(L25+L26)/L20 -> 0.3681256 | R24: =(M25+M26)/M20 -> 0.43319322 | S24: =(N25+N26)/N20 -> 0.43466656 | U24: 11111003 | V24: 받을어음 | W24: 28020953 | X24: 19977357 | Y24: 8483700 | Z24: 7000000
B25: 이익잉여금 | C25: =K104 -> 70561853 | D25: =L104 -> 41305049 | E25: =M104 -> 53772580 | F25: =N104 -> 59267276 | I25: 11161401 | J25: 반제품 | K25: =VLOOKUP($I25,$U$4:$Z$468,3,FALSE) -> 18068016 | L25: =VLOOKUP($I25,$U$4:$Z$468,4,FALSE) -> 25023717 | M25: =VLOOKUP($I25,$U$4:$Z$468,5,FALSE) -> 31782235 | N25: =VLOOKUP($I25,$U$4:$Z$468,6,FALSE) -> 33011675 | O25: 원재료 | P25: =(K27+K28+K29)/K20 -> 0.17440848 | Q25: =(L27+L28+L29)/L20 -> 0.12583414 | R25: =(M27+M28+M29)/M20 -> 0.10385021 | S25: =(N27+N28+N29)/N20 -> 0.082455211 | U25: 11111004 | V25: 부도어음 | W25: 0 | X25: 0 | Y25: 0 | Z25: 0
B26: 자본총계 | C26: =K98 -> 1.2513074e+08 | D26: =L98 -> 1.2671244e+08 | E26: =M98 -> 1.3917997e+08 | F26: =N98 -> 1.4467467e+08 | I26: 11161501 | J26: (반제품평가충당금) | K26: =VLOOKUP($I26,$U$4:$Z$468,3,FALSE) -> -972766.27 | L26: =VLOOKUP($I26,$U$4:$Z$468,4,FALSE) -> -1336633.1 | M26: =VLOOKUP($I26,$U$4:$Z$468,5,FALSE) -> -1266513.1 | N26: =VLOOKUP($I26,$U$4:$Z$468,6,FALSE) -> -1778963.2 | U26: 11111005 | V26: 공사채권 | W26: 0 | X26: 0 | Y26: 0 | Z26: 0
B27: 자본과부채총계 | C27: =K74+K98 -> 2.7438482e+08 | D27: =L74+L98 -> 3.3324998e+08 | E27: =M74+M98 -> 4.0110657e+08 | F27: =N74+N98 -> 4.4421822e+08 | I27: 11161802 | J27: 원재료 | K27: =VLOOKUP($I27,$U$4:$Z$468,3,FALSE) -> 2070783.5 | L27: =VLOOKUP($I27,$U$4:$Z$468,4,FALSE) -> 3311146.1 | M27: =VLOOKUP($I27,$U$4:$Z$468,5,FALSE) -> 3679819.3 | N27: =VLOOKUP($I27,$U$4:$Z$468,6,FALSE) -> 3581839.4 | U27: 11111006 | V27: 기타어음 | W27: 0 | X27: 0 | Y27: 0 | Z27: 0
B28: Net debt | C28: =C21+C17-C6 -> 76139703 | D28: =D21+D17-D6 -> 1.1990166e+08 | E28: =E21+E17-E6 -> 1.488098e+08 | F28: =F21+F17-F6 -> 1.657944e+08 | I28: 11161901 | J28: (원재료평가충당금) | K28: =VLOOKUP($I28,$U$4:$Z$468,3,FALSE) -> -32325.4 | L28: =VLOOKUP($I28,$U$4:$Z$468,4,FALSE) -> -46981.47 | M28: =VLOOKUP($I28,$U$4:$Z$468,5,FALSE) -> -32174.2 | N28: =VLOOKUP($I28,$U$4:$Z$468,6,FALSE) -> -73565.43 | O28: =N28+N26+N24 -> -3618160.8 | P28: =N30+N27+N25+N23+N21 -> 75472578 | Q28: =O28/P28 -> -0.047940072 | U28: 11111100 | V28: (매출채권 대손충당금) | W28: -951310.12 | X28: -22600.58 | Y28: -49216.36 | Z28: -49216.36
B29: 매출채권 충당금 설정률 | C29: =-K13/K10 -> 0.01170086 | D29: =-L13/L10 -> 0.00026144481 | E29: =-M13/M10 -> 0.00049938421 | F29: =-N13/N10 -> 0.00038586826 | I29: 11162200 | J29: 미착품 | K29: =VLOOKUP($I29,$U$4:$Z$468,3,FALSE) -> 8686256 | L29: =VLOOKUP($I29,$U$4:$Z$468,4,FALSE) -> 4832647.3 | M29: =VLOOKUP($I29,$U$4:$Z$468,5,FALSE) -> 3667945.6 | N29: =VLOOKUP($I29,$U$4:$Z$468,6,FALSE) -> 2416497.1 | U29: 11111101 | V29: (대손충당금:원화외상매출금) | W29: 0 | X29: 0 | Y29: 0 | Z29: 0
B30: 제품 충당금 설정률 | C30: =-K24/K23 -> 0.0053409482 | D30: =-L24/L23 -> 0.039585746 | E30: =-M24/M23 -> 0.04817405 | F30: =-N24/N23 -> 0.049831339 | I30: 11162202 | J30: 미착품:원재료 | K30: =VLOOKUP($I30,$U$4:$Z$468,3,FALSE) -> 8686256 | L30: =VLOOKUP($I30,$U$4:$Z$468,4,FALSE) -> 4832647.3 | M30: =VLOOKUP($I30,$U$4:$Z$468,5,FALSE) -> 3667945.6 | N30: =VLOOKUP($I30,$U$4:$Z$468,6,FALSE) -> 2416497.1 | U30: 11111102 | V30: (대손충당금:외화외상매출금) | W30: -951310.12 | X30: -22600.58 | Y30: -49216.36 | Z30: -49216.36
B31: 반제품 충당금 설정률 | C31: =-K26/K25 -> 0.053839131 | D31: =-L26/L25 -> 0.053414653 | E31: =-M26/M25 -> 0.039849719 | F31: =-N26/N25 -> 0.053888909 | I31: 11190000 | J31: 기타유동자산 | K31: =VLOOKUP($I31,$U$4:$Z$468,3,FALSE) -> 6468910.2 | L31: =VLOOKUP($I31,$U$4:$Z$468,4,FALSE) -> 26588274 | M31: =VLOOKUP($I31,$U$4:$Z$468,5,FALSE) -> 13113189 | N31: =VLOOKUP($I31,$U$4:$Z$468,6,FALSE) -> 11450878 | U31: 11111103 | V31: (대손충당금:받을어음) | W31: 0 | X31: 0 | Y31: 0 | Z31: 0
B32: 원재료 충당금 설정률 | C32: =-K28/K27 -> 0.015610227 | D32: =-L28/L27 -> 0.014188884 | E32: =-M28/M27 -> 0.0087434185 | F32: =-N28/N27 -> 0.02053845 | I32: 11191101 | J32: 선급부가가치세(매입부가세) | K32: =VLOOKUP($I32,$U$4:$Z$468,3,FALSE) -> 0 | L32: =VLOOKUP($I32,$U$4:$Z$468,4,FALSE) -> 492457.75 | M32: =VLOOKUP($I32,$U$4:$Z$468,5,FALSE) -> 590826.32 | N32: =VLOOKUP($I32,$U$4:$Z$468,6,FALSE) -> 266958.6 | U32: 11111104 | V32: (대손충당금:부도어음) | W32: 0 | X32: 0 | Y32: 0 | Z32: 0
I33: 11191201 | J33: 선급금 | K33: =VLOOKUP($I33,$U$4:$Z$468,3,FALSE) -> 6301006.3 | L33: =VLOOKUP($I33,$U$4:$Z$468,4,FALSE) -> 25720971 | M33: =VLOOKUP($I33,$U$4:$Z$468,5,FALSE) -> 12182987 | N33: =VLOOKUP($I33,$U$4:$Z$468,6,FALSE) -> 10412996 | U33: 11111105 | V33: (대손충당금:공사채권) | W33: 0 | X33: 0 | Y33: 0 | Z33: 0
C34: =C5=SUM(C6,C7,C8,C9) -> TRUE | D34: =D5=SUM(D6,D7,D8,D9) -> TRUE | E34: =E5=SUM(E6,E7,E8,E9) -> TRUE | F34: =F5=SUM(F6,F7,F8,F9) -> TRUE | I34: 11191301 | J34: (선급금대손충당금) | K34: =VLOOKUP($I34,$U$4:$Z$468,3,FALSE) -> 0 | L34: =VLOOKUP($I34,$U$4:$Z$468,4,FALSE) -> 0 | M34: =VLOOKUP($I34,$U$4:$Z$468,5,FALSE) -> 0 | N34: =VLOOKUP($I34,$U$4:$Z$468,6,FALSE) -> 0 | U34: 11111106 | V34: (대손충당금:기타) | W34: 0 | X34: 0 | Y34: 0 | Z34: 0
C35: =C10=SUM(C11,C12,C13) -> TRUE | D35: =D10=SUM(D11,D12,D13) -> TRUE | E35: =E10=SUM(E11,E12,E13) -> TRUE | F35: =F10=SUM(F11,F12,F13) -> TRUE | I35: 11191501 | J35: (유동성)선급비용 | K35: =VLOOKUP($I35,$U$4:$Z$468,3,FALSE) -> 167903.96 | L35: =VLOOKUP($I35,$U$4:$Z$468,4,FALSE) -> 374845.28 | M35: =VLOOKUP($I35,$U$4:$Z$468,5,FALSE) -> 339375.23 | N35: =VLOOKUP($I35,$U$4:$Z$468,6,FALSE) -> 770923.32 | U35: 11111301 | V35: 단기대여금 | W35: 0 | X35: 0 | Y35: 0 | Z35: 0
C36: =C14=SUM(C5,C10) -> TRUE | D36: =D14=SUM(D5,D10) -> TRUE | E36: =E14=SUM(E5,E10) -> TRUE | F36: =F14=SUM(F5,F10) -> TRUE | I36: 12000000 | J36: 비유동자산 | K36: =VLOOKUP($I36,$U$4:$Z$468,3,FALSE) -> 1.1895822e+08 | L36: =VLOOKUP($I36,$U$4:$Z$468,4,FALSE) -> 1.492997e+08 | M36: =VLOOKUP($I36,$U$4:$Z$468,5,FALSE) -> 2.1079206e+08 | N36: =VLOOKUP($I36,$U$4:$Z$468,6,FALSE) -> 2.2846091e+08 | U36: 11111401 | V36: (단기대여금대손충당금) | W36: 0 | X36: 0 | Y36: 0 | Z36: 0
C37: =C15=SUM(C16,C17,C19,C18) -> TRUE | D37: =D15=SUM(D16,D17,D19,D18) -> TRUE | E37: =E15=SUM(E16,E17,E19,E18) -> TRUE | F37: =F15=SUM(F16,F17,F19,F18) -> TRUE | I37: 12100000 | J37: 장기매출채권및기타채권 | K37: =VLOOKUP($I37,$U$4:$Z$468,3,FALSE) -> 0 | L37: =VLOOKUP($I37,$U$4:$Z$468,4,FALSE) -> 0 | M37: =VLOOKUP($I37,$U$4:$Z$468,5,FALSE) -> 0 | N37: =VLOOKUP($I37,$U$4:$Z$468,6,FALSE) -> 0 | U37: 11111501 | V37: 단기보증금 | W37: 0 | X37: 0 | Y37: 0 | Z37: 0
C38: =C26=SUM(C24,C25,#REF!) -> #REF! | D38: =D26=SUM(D24,D25,#REF!) -> #REF! | E38: =E26=SUM(E24,E25,#REF!) -> #REF! | F38: =F26=SUM(F24,F25,#REF!) -> #REF! | I38: 12102000 | J38: 장기보증금 | K38: =VLOOKUP($I38,$U$4:$Z$468,3,FALSE) -> 0 | L38: =VLOOKUP($I38,$U$4:$Z$468,4,FALSE) -> 198985.5 | M38: =VLOOKUP($I38,$U$4:$Z$468,5,FALSE) -> 187256.5 | N38: =VLOOKUP($I38,$U$4:$Z$468,6,FALSE) -> 304926 | U38: 11111601 | V38: (단기보증금대손충당금) | W38: 0 | X38: 0 | Y38: 0 | Z38: 0
C39: =C27=C14 -> TRUE | D39: =D27=D14 -> TRUE | E39: =E27=E14 -> TRUE | F39: =F27=F14 -> TRUE | I39: 12102005 | J39: 기타 | K39: =VLOOKUP($I39,$U$4:$Z$468,3,FALSE) -> 0 | L39: =VLOOKUP($I39,$U$4:$Z$468,4,FALSE) -> 198985.5 | M39: =VLOOKUP($I39,$U$4:$Z$468,5,FALSE) -> 187256.5 | N39: =VLOOKUP($I39,$U$4:$Z$468,6,FALSE) -> 304926 | U39: 11111701 | V39: 미수금 | W39: 570343.06 | X39: 836216.89 | Y39: 1718205.6 | Z39: 2095177.5
I40: 12170000 | J40: 유형자산 | K40: =VLOOKUP($I40,$U$4:$Z$468,3,FALSE) -> 92953198 | L40: =VLOOKUP($I40,$U$4:$Z$468,4,FALSE) -> 1.1709264e+08 | M40: =VLOOKUP($I40,$U$4:$Z$468,5,FALSE) -> 1.7491401e+08 | N40: =VLOOKUP($I40,$U$4:$Z$468,6,FALSE) -> 1.9292588e+08 | U40: 11111801 | V40: (미수금대손충당금) | W40: 0 | X40: 0 | Y40: 0 | Z40: 0
I41: 12171100 | J41: 건물 | K41: =VLOOKUP($I41,$U$4:$Z$468,3,FALSE) -> 20067458 | L41: =VLOOKUP($I41,$U$4:$Z$468,4,FALSE) -> 19939291 | M41: =VLOOKUP($I41,$U$4:$Z$468,5,FALSE) -> 19415041 | N41: =VLOOKUP($I41,$U$4:$Z$468,6,FALSE) -> 19152916 | O41: =N41/$N$40 -> 0.099276034 | U41: 11111901 | V41: 미수수익 | W41: 0 | X41: 0 | Y41: 0 | Z41: 0
B42: 차입금 합계 | C42: =C17+C21 -> 82683850 | D42: =D17+D21 -> 1.2566e+08 | E42: =E17+E21 -> 1.5510051e+08 | F42: =F17+F21 -> 1.6865341e+08 | I42: 12171101 | J42: 건물 | K42: =VLOOKUP($I42,$U$4:$Z$468,3,FALSE) -> 20582009 | L42: =VLOOKUP($I42,$U$4:$Z$468,4,FALSE) -> 20970009 | M42: =VLOOKUP($I42,$U$4:$Z$468,5,FALSE) -> 20970009 | N42: =VLOOKUP($I42,$U$4:$Z$468,6,FALSE) -> 20970009 | U42: 11120000 | V42: (유동성)당기손익인식금융자산 | W42: 0 | X42: 0 | Y42: 243846 | Z42: 0
B43: 이자비용 | C43: ='IS(RMB)'!J68 -> 4088583.2 | D43: ='IS(RMB)'!K68 -> 3976922 | E43: ='IS(RMB)'!L68 -> 3759400.7 | F43: ='IS(RMB)'!M68 -> 2083680.8 | I43: 12171102 | J43: (건물감가상각누계액) | K43: =VLOOKUP($I43,$U$4:$Z$468,3,FALSE) -> -514550.21 | L43: =VLOOKUP($I43,$U$4:$Z$468,4,FALSE) -> -1030717.1 | M43: =VLOOKUP($I43,$U$4:$Z$468,5,FALSE) -> -1554967.3 | N43: =VLOOKUP($I43,$U$4:$Z$468,6,FALSE) -> -1817092.4 | U43: 11121000 | V43: 단기매매증권 | W43: 0 | X43: 0 | Y43: 0 | Z43: 0
C44: =C43/C42 -> 0.049448389 | D44: =D43/D42 -> 0.031648272 | E44: =E43/E42 -> 0.02423848 | F44: =F43/F42 -> 0.01235481 | I44: 12171300 | J44: 기계장치 | K44: =VLOOKUP($I44,$U$4:$Z$468,3,FALSE) -> 40379670 | L44: =VLOOKUP($I44,$U$4:$Z$468,4,FALSE) -> 50178918 | M44: =VLOOKUP($I44,$U$4:$Z$468,5,FALSE) -> 70899679 | N44: =VLOOKUP($I44,$U$4:$Z$468,6,FALSE) -> 75434232 | O44: =N44/$N$40 -> 0.39100111 | U44: 11121001 | V44: 단기매매증권-주식 | W44: 0 | X44: 0 | Y44: 0 | Z44: 0
I45: 12171301 | J45: 기계장치 | K45: =VLOOKUP($I45,$U$4:$Z$468,3,FALSE) -> 59003852 | L45: =VLOOKUP($I45,$U$4:$Z$468,4,FALSE) -> 75154055 | M45: =VLOOKUP($I45,$U$4:$Z$468,5,FALSE) -> 1.0441171e+08 | N45: =VLOOKUP($I45,$U$4:$Z$468,6,FALSE) -> 1.1306754e+08 | U45: 11121002 | V45: 단기매매증권-사채 | W45: 0 | X45: 0 | Y45: 0 | Z45: 0
I46: 12171302 | J46: (기계장치감가상각누계액) | K46: =VLOOKUP($I46,$U$4:$Z$468,3,FALSE) -> -18624182 | L46: =VLOOKUP($I46,$U$4:$Z$468,4,FALSE) -> -24975137 | M46: =VLOOKUP($I46,$U$4:$Z$468,5,FALSE) -> -33512029 | N46: =VLOOKUP($I46,$U$4:$Z$468,6,FALSE) -> -37633306 | U46: 11121003 | V46: 단기매매증권-국.공채 | W46: 0 | X46: 0 | Y46: 0 | Z46: 0
I47: 12171400 | J47: 차량운반구 | K47: =VLOOKUP($I47,$U$4:$Z$468,3,FALSE) -> 1565072.3 | L47: =VLOOKUP($I47,$U$4:$Z$468,4,FALSE) -> 1350744.6 | M47: =VLOOKUP($I47,$U$4:$Z$468,5,FALSE) -> 944208.29 | N47: =VLOOKUP($I47,$U$4:$Z$468,6,FALSE) -> 859597.66 | O47: =N47/$N$40 -> 0.004455585 | U47: 11121004 | V47: 단기매매증권-기타 | W47: 0 | X47: 0 | Y47: 0 | Z47: 0
I48: 12171401 | J48: 차량운반구 | K48: =VLOOKUP($I48,$U$4:$Z$468,3,FALSE) -> 2623692.2 | L48: =VLOOKUP($I48,$U$4:$Z$468,4,FALSE) -> 2567498 | M48: =VLOOKUP($I48,$U$4:$Z$468,5,FALSE) -> 2456384.9 | N48: =VLOOKUP($I48,$U$4:$Z$468,6,FALSE) -> 2566028.8 | U48: 11121101 | V48: (유동성)당기손익인식지정금융자산 | W48: 0 | X48: 0 | Y48: 0 | Z48: 0
I49: 12171402 | J49: (차량운반구감가상각누계액) | K49: =VLOOKUP($I49,$U$4:$Z$468,3,FALSE) -> -1058619.9 | L49: =VLOOKUP($I49,$U$4:$Z$468,4,FALSE) -> -1216753.4 | M49: =VLOOKUP($I49,$U$4:$Z$468,5,FALSE) -> -1512176.6 | N49: =VLOOKUP($I49,$U$4:$Z$468,6,FALSE) -> -1706431.1 | U49: 11121201 | V49: (유동성)매매목적파생상품자산:금융 | W49: 0 | X49: 0 | Y49: 0 | Z49: 0
I50: 12171500 | J50: 공구와기구 | K50: =VLOOKUP($I50,$U$4:$Z$468,3,FALSE) -> 2149532.4 | L50: =VLOOKUP($I50,$U$4:$Z$468,4,FALSE) -> 2630267.6 | M50: =VLOOKUP($I50,$U$4:$Z$468,5,FALSE) -> 3244833.4 | N50: =VLOOKUP($I50,$U$4:$Z$468,6,FALSE) -> 3488217.7 | O50: =N50/$N$40 -> 0.018080611 | U50: 11121202 | V50: (유동성))매매목적파생상품자산:상품 | W50: 0 | X50: 0 | Y50: 0 | Z50: 0
I51: 12171501 | J51: 공구와기구 | K51: =VLOOKUP($I51,$U$4:$Z$468,3,FALSE) -> 4731339.2 | L51: =VLOOKUP($I51,$U$4:$Z$468,4,FALSE) -> 5696232.9 | M51: =VLOOKUP($I51,$U$4:$Z$468,5,FALSE) -> 5739838.7 | N51: =VLOOKUP($I51,$U$4:$Z$468,6,FALSE) -> 6303952.1 | U51: 11130000 | V51: (유동성)매도가능금융자산 | W51: 0 | X51: 0 | Y51: 0 | Z51: 0
I52: 12171502 | J52: (공구와기구감가상각누계액) | K52: =VLOOKUP($I52,$U$4:$Z$468,3,FALSE) -> -2581806.9 | L52: =VLOOKUP($I52,$U$4:$Z$468,4,FALSE) -> -3065965.3 | M52: =VLOOKUP($I52,$U$4:$Z$468,5,FALSE) -> -2495005.4 | N52: =VLOOKUP($I52,$U$4:$Z$468,6,FALSE) -> -2815734.4 | U52: 11131001 | V52: (유동성)매도가능증권-주식 | W52: 0 | X52: 0 | Y52: 0 | Z52: 0
I53: 12171600 | J53: 비품 | K53: =VLOOKUP($I53,$U$4:$Z$468,3,FALSE) -> 119162.3 | L53: =VLOOKUP($I53,$U$4:$Z$468,4,FALSE) -> 95698.67 | M53: =VLOOKUP($I53,$U$4:$Z$468,5,FALSE) -> 289304.38 | N53: =VLOOKUP($I53,$U$4:$Z$468,6,FALSE) -> 299983 | O53: =N53/$N$40 -> 0.0015549132 | U53: 11131002 | V53: (유동성)매도가능증권-사채 | W53: 0 | X53: 0 | Y53: 0 | Z53: 0
I54: 12171601 | J54: 비품 | K54: =VLOOKUP($I54,$U$4:$Z$468,3,FALSE) -> 587571.35 | L54: =VLOOKUP($I54,$U$4:$Z$468,4,FALSE) -> 590971.35 | M54: =VLOOKUP($I54,$U$4:$Z$468,5,FALSE) -> 821243.12 | N54: =VLOOKUP($I54,$U$4:$Z$468,6,FALSE) -> 859539.7 | U54: 11131003 | V54: (유동성)매도가능증권-국.공채 | W54: 0 | X54: 0 | Y54: 0 | Z54: 0
I55: 12171602 | J55: (비품감가상각누계액) | K55: =VLOOKUP($I55,$U$4:$Z$468,3,FALSE) -> -468409.05 | L55: =VLOOKUP($I55,$U$4:$Z$468,4,FALSE) -> -495272.68 | M55: =VLOOKUP($I55,$U$4:$Z$468,5,FALSE) -> -531938.74 | N55: =VLOOKUP($I55,$U$4:$Z$468,6,FALSE) -> -559556.7 | U55: 11131004 | V55: (유동성)매도가능증권-기타 | W55: 0 | X55: 0 | Y55: 0 | Z55: 0
I56: 12171700 | J56: 금형 | K56: =VLOOKUP($I56,$U$4:$Z$468,3,FALSE) -> 13732426 | L56: =VLOOKUP($I56,$U$4:$Z$468,4,FALSE) -> 19180971 | M56: =VLOOKUP($I56,$U$4:$Z$468,5,FALSE) -> 22877735 | N56: =VLOOKUP($I56,$U$4:$Z$468,6,FALSE) -> 25694235 | O56: =N56/$N$40 -> 0.1331819 | U56: 11131005 | V56: (유동성)(매도가능증권손상차손누계액) | W56: 0 | X56: 0 | Y56: 0 | Z56: 0
I57: 12171701 | J57: 금형 | K57: =VLOOKUP($I57,$U$4:$Z$468,3,FALSE) -> 22711747 | L57: =VLOOKUP($I57,$U$4:$Z$468,4,FALSE) -> 32916261 | M57: =VLOOKUP($I57,$U$4:$Z$468,5,FALSE) -> 42959651 | N57: =VLOOKUP($I57,$U$4:$Z$468,6,FALSE) -> 49253783 | U57: 11140000 | V57: (유동성)만기보유금융자산 | W57: 0 | X57: 0 | Y57: 0 | Z57: 0
I58: 12171702 | J58: (금형감가상각누계액) | K58: =VLOOKUP($I58,$U$4:$Z$468,3,FALSE) -> -8979321 | L58: =VLOOKUP($I58,$U$4:$Z$468,4,FALSE) -> -13735290 | M58: =VLOOKUP($I58,$U$4:$Z$468,5,FALSE) -> -20081916 | N58: =VLOOKUP($I58,$U$4:$Z$468,6,FALSE) -> -23559549 | U58: 11141001 | V58: (유동성)만기보유증권-사채 | W58: 0 | X58: 0 | Y58: 0 | Z58: 0
I59: 12171800 | J59: 건설중인유형자산 | K59: =VLOOKUP($I59,$U$4:$Z$468,3,FALSE) -> 6737830.5 | L59: =VLOOKUP($I59,$U$4:$Z$468,4,FALSE) -> 12726752 | M59: =VLOOKUP($I59,$U$4:$Z$468,5,FALSE) -> 44039093 | N59: =VLOOKUP($I59,$U$4:$Z$468,6,FALSE) -> 52389023 | O59: =N59/$N$40 -> 0.27155 | U59: 11141002 | V59: (유동성)만기보유증권-국.공채 | W59: 0 | X59: 0 | Y59: 0 | Z59: 0
I60: 12171801 | J60: 건설중인유형자산 | K60: =VLOOKUP($I60,$U$4:$Z$468,3,FALSE) -> 6737830.5 | L60: =VLOOKUP($I60,$U$4:$Z$468,4,FALSE) -> 12726752 | M60: =VLOOKUP($I60,$U$4:$Z$468,5,FALSE) -> 44039093 | N60: =VLOOKUP($I60,$U$4:$Z$468,6,FALSE) -> 52389023 | U60: 11141003 | V60: (유동성)만기보유증권-기타 | W60: 0 | X60: 0 | Y60: 0 | Z60: 0
I61: 12171900 | J61: 기타의유형자산 | K61: =VLOOKUP($I61,$U$4:$Z$468,3,FALSE) -> 8202046.1 | L61: =VLOOKUP($I61,$U$4:$Z$468,4,FALSE) -> 10990000 | M61: =VLOOKUP($I61,$U$4:$Z$468,5,FALSE) -> 13204116 | N61: =VLOOKUP($I61,$U$4:$Z$468,6,FALSE) -> 15607675 | O61: =N61/$N$40 -> 0.080899851 | U61: 11141004 | V61: (유동성)(만기보유증권손상차손누계액) | W61: 0 | X61: 0 | Y61: 0 | Z61: 0
I62: 12171901 | J62: 기타의유형자산 | K62: =VLOOKUP($I62,$U$4:$Z$468,3,FALSE) -> 20790463 | L62: =VLOOKUP($I62,$U$4:$Z$468,4,FALSE) -> 24811909 | M62: =VLOOKUP($I62,$U$4:$Z$468,5,FALSE) -> 27294426 | N62: =VLOOKUP($I62,$U$4:$Z$468,6,FALSE) -> 30923259 | U62: 11150000 | V62: (유동성)위험회피파생상품자산 | W62: 0 | X62: 0 | Y62: 243846 | Z62: 0
I63: 12171902 | J63: (기타유형자산감가상각누계액) | K63: =VLOOKUP($I63,$U$4:$Z$468,3,FALSE) -> -12588416 | L63: =VLOOKUP($I63,$U$4:$Z$468,4,FALSE) -> -13821909 | M63: =VLOOKUP($I63,$U$4:$Z$468,5,FALSE) -> -14090310 | N63: =VLOOKUP($I63,$U$4:$Z$468,6,FALSE) -> -15315584 | U63: 11151001 | V63: (유동성)공정가치위험회피파생상품자산:금융 | W63: 0 | X63: 0 | Y63: 243846 | Z63: 0
I64: 12190000 | J64: 무형자산 | K64: =VLOOKUP($I64,$U$4:$Z$468,3,FALSE) -> 5943322.5 | L64: =VLOOKUP($I64,$U$4:$Z$468,4,FALSE) -> 12036626 | M64: =VLOOKUP($I64,$U$4:$Z$468,5,FALSE) -> 13484626 | N64: =VLOOKUP($I64,$U$4:$Z$468,6,FALSE) -> 13517534 | U64: 11151002 | V64: (유동성)공정가치위험회피파생상품자산:상품 | W64: 0 | X64: 0 | Y64: 0 | Z64: 0
I65: 12191100 | J65: 소프트웨어 | K65: =VLOOKUP($I65,$U$4:$Z$468,3,FALSE) -> 5593322.5 | L65: =VLOOKUP($I65,$U$4:$Z$468,4,FALSE) -> 11686626 | M65: =VLOOKUP($I65,$U$4:$Z$468,5,FALSE) -> 13134626 | N65: =VLOOKUP($I65,$U$4:$Z$468,6,FALSE) -> 12587534 | U65: 11151003 | V65: (유동성)공정가치위험회피파생상품자산:확정계약 | W65: 0 | X65: 0 | Y65: 0 | Z65: 0
I66: 12191101 | J66: 소프트웨어 | K66: =VLOOKUP($I66,$U$4:$Z$468,3,FALSE) -> 5593322.5 | L66: =VLOOKUP($I66,$U$4:$Z$468,4,FALSE) -> 11686626 | M66: =VLOOKUP($I66,$U$4:$Z$468,5,FALSE) -> 13134626 | N66: =VLOOKUP($I66,$U$4:$Z$468,6,FALSE) -> 12587534 | T66: 181.09 | U66: 11151100 | V66: (유동성)현금흐름위험회피파생상품자산 | W66: 0 | X66: 0 | Y66: 0 | Z66: 0
I67: 12191400 | J67: 회원권 | K67: =VLOOKUP($I67,$U$4:$Z$468,3,FALSE) -> 350000 | L67: =VLOOKUP($I67,$U$4:$Z$468,4,FALSE) -> 350000 | M67: =VLOOKUP($I67,$U$4:$Z$468,5,FALSE) -> 350000 | N67: =VLOOKUP($I67,$U$4:$Z$468,6,FALSE) -> 930000 | U67: 11151101 | V67: (유동성)현금흐름위험회피파생상품자산:금융 | W67: 0 | X67: 0 | Y67: 0 | Z67: 0
I68: 12191401 | J68: 회원권 | K68: =VLOOKUP($I68,$U$4:$Z$468,3,FALSE) -> 350000 | L68: =VLOOKUP($I68,$U$4:$Z$468,4,FALSE) -> 350000 | M68: =VLOOKUP($I68,$U$4:$Z$468,5,FALSE) -> 350000 | N68: =VLOOKUP($I68,$U$4:$Z$468,6,FALSE) -> 930000 | O68: =N68-M68 -> 580000 | U68: 11151102 | V68: (유동성)현금흐름위험회피파생상품자산:상품 | W68: 0 | X68: 0 | Y68: 0 | Z68: 0
I69: 12191402 | J69: (회원권손상차손누계액) | K69: =VLOOKUP($I69,$U$4:$Z$468,3,FALSE) -> 0 | L69: =VLOOKUP($I69,$U$4:$Z$468,4,FALSE) -> 0 | M69: =VLOOKUP($I69,$U$4:$Z$468,5,FALSE) -> 0 | N69: =VLOOKUP($I69,$U$4:$Z$468,6,FALSE) -> 0 | U69: 11160000 | V69: 재고자산 | W69: 61491932 | X69: 64345113 | Y69: 70443675 | Z69: 71854417
I70: 12210000 | J70: 기타비유동자산 | K70: =VLOOKUP($I70,$U$4:$Z$468,3,FALSE) -> 18038646 | L70: =VLOOKUP($I70,$U$4:$Z$468,4,FALSE) -> 17200085 | M70: =VLOOKUP($I70,$U$4:$Z$468,5,FALSE) -> 17970858 | N70: =VLOOKUP($I70,$U$4:$Z$468,6,FALSE) -> 18294072 | U70: 11161001 | V70: 상품 | W70: 9803182.4 | X70: 415842.72 | Y70: 410746.44 | Z70: 1030400.6
I71: 12211401 | J71: 장기선급비용 | K71: =VLOOKUP($I71,$U$4:$Z$468,3,FALSE) -> 1486516.9 | L71: =VLOOKUP($I71,$U$4:$Z$468,4,FALSE) -> 985755.37 | M71: =VLOOKUP($I71,$U$4:$Z$468,5,FALSE) -> 2094326.4 | N71: =VLOOKUP($I71,$U$4:$Z$468,6,FALSE) -> 2586439.2 | U71: 11161101 | V71: (상품평가충당금) | W71: 0 | X71: 0 | Y71: 0 | Z71: 0
I72: 12211402 | J72: 장기선급비용_토지사용권 | K72: =VLOOKUP($I72,$U$4:$Z$468,3,FALSE) -> 16552129 | L72: =VLOOKUP($I72,$U$4:$Z$468,4,FALSE) -> 16214330 | M72: =VLOOKUP($I72,$U$4:$Z$468,5,FALSE) -> 15876532 | N72: =VLOOKUP($I72,$U$4:$Z$468,6,FALSE) -> 15707632 | T72: =N72/T66 -> 86739.369 | U72: 11161201 | V72: 제품 | W72: 23996952 | X72: 33470323 | Y72: 33831411 | Z72: 35432165
I73: 12201001 | J73: 이연법인세자산 | K73: =VLOOKUP($I73,$U$4:$Z$468,3,FALSE) -> 2023055.9 | L73: =VLOOKUP($I73,$U$4:$Z$468,4,FALSE) -> 2771360.9 | M73: =VLOOKUP($I73,$U$4:$Z$468,5,FALSE) -> 4235312.1 | N73: =VLOOKUP($I73,$U$4:$Z$468,6,FALSE) -> 3418495.6 | U73: 11161301 | V73: (제품평가충당금) | W73: -128166.48 | X73: -1324947.7 | Y73: -1629796.1 | Z73: -1765632.2
I74: 20000000 | J74: 부채 | K74: =VLOOKUP($I74,$U$4:$Z$468,3,FALSE) -> 1.4925408e+08 | L74: =VLOOKUP($I74,$U$4:$Z$468,4,FALSE) -> 2.0653754e+08 | M74: =VLOOKUP($I74,$U$4:$Z$468,5,FALSE) -> 2.619266e+08 | N74: =VLOOKUP($I74,$U$4:$Z$468,6,FALSE) -> 2.9954355e+08 | U74: 11161401 | V74: 반제품 | W74: 18068016 | X74: 25023717 | Y74: 31782235 | Z74: 33011675
I75: 21000000 | J75: 유동부채 | K75: =VLOOKUP($I75,$U$4:$Z$468,3,FALSE) -> 1.2102811e+08 | L75: =VLOOKUP($I75,$U$4:$Z$468,4,FALSE) -> 1.8974642e+08 | M75: =VLOOKUP($I75,$U$4:$Z$468,5,FALSE) -> 2.4551367e+08 | N75: =VLOOKUP($I75,$U$4:$Z$468,6,FALSE) -> 2.8259412e+08 | U75: 11161501 | V75: (반제품평가충당금) | W75: -972766.27 | X75: -1336633.1 | Y75: -1266513.1 | Z75: -1778963.2
I76: 21100000 | J76: 매입채무및기타채무 | K76: =VLOOKUP($I76,$U$4:$Z$468,3,FALSE) -> 65138235 | L76: =VLOOKUP($I76,$U$4:$Z$468,4,FALSE) -> 78105353 | M76: =VLOOKUP($I76,$U$4:$Z$468,5,FALSE) -> 1.0068898e+08 | N76: =VLOOKUP($I76,$U$4:$Z$468,6,FALSE) -> 1.220503e+08 | U76: 11161601 | V76: 재공품 | W76: 0 | X76: 0 | Y76: 0 | Z76: 0
I77: 21101000 | J77: 매입채무 | K77: =VLOOKUP($I77,$U$4:$Z$468,3,FALSE) -> 47779997 | L77: =VLOOKUP($I77,$U$4:$Z$468,4,FALSE) -> 54146686 | M77: =VLOOKUP($I77,$U$4:$Z$468,5,FALSE) -> 64828470 | N77: =VLOOKUP($I77,$U$4:$Z$468,6,FALSE) -> 89071341 | U77: 11161701 | V77: (재공품평가충당금) | W77: 0 | X77: 0 | Y77: 0 | Z77: 0
I78: 21101002 | J78: 외상매입금:외화 | K78: =VLOOKUP($I78,$U$4:$Z$468,3,FALSE) -> 34782485 | L78: =VLOOKUP($I78,$U$4:$Z$468,4,FALSE) -> 48606388 | M78: =VLOOKUP($I78,$U$4:$Z$468,5,FALSE) -> 57376665 | N78: =VLOOKUP($I78,$U$4:$Z$468,6,FALSE) -> 83621381 | U78: 11161801 | V78: 스크랩 | W78: 0 | X78: 0 | Y78: 0 | Z78: 0
I79: 21101003 | J79: 미확정매입채무:GL | K79: =VLOOKUP($I79,$U$4:$Z$468,3,FALSE) -> 12997512 | L79: =VLOOKUP($I79,$U$4:$Z$468,4,FALSE) -> 5540298.2 | M79: =VLOOKUP($I79,$U$4:$Z$468,5,FALSE) -> 7451804.7 | N79: =VLOOKUP($I79,$U$4:$Z$468,6,FALSE) -> 5449959.8 | U79: 11161802 | V79: 원재료 | W79: 2070783.5 | X79: 3311146.1 | Y79: 3679819.3 | Z79: 3581839.4
I80: 21101101 | J80: 미지급금 | K80: =VLOOKUP($I80,$U$4:$Z$468,3,FALSE) -> 13286395 | L80: =VLOOKUP($I80,$U$4:$Z$468,4,FALSE) -> 19082062 | M80: =VLOOKUP($I80,$U$4:$Z$468,5,FALSE) -> 29269134 | N80: =VLOOKUP($I80,$U$4:$Z$468,6,FALSE) -> 27580638 | U80: 11161901 | V80: (원재료평가충당금) | W80: -32325.4 | X80: -46981.47 | Y80: -32174.2 | Z80: -73565.43
I81: 21101201 | J81: 미지급비용 | K81: =VLOOKUP($I81,$U$4:$Z$468,3,FALSE) -> 4071843.3 | L81: =VLOOKUP($I81,$U$4:$Z$468,4,FALSE) -> 4876605.5 | M81: =VLOOKUP($I81,$U$4:$Z$468,5,FALSE) -> 6591371.8 | N81: =VLOOKUP($I81,$U$4:$Z$468,6,FALSE) -> 5398317.3 | U81: 11162001 | V81: 저장품 | W81: 0 | X81: 0 | Y81: 0 | Z81: 0
I82: 21120000 | J82: (유동성)위험회피파생상품부채 | K82: =VLOOKUP($I82,$U$4:$Z$468,3,FALSE) -> 581952 | L82: =VLOOKUP($I82,$U$4:$Z$468,4,FALSE) -> 275717 | M82: =VLOOKUP($I82,$U$4:$Z$468,5,FALSE) -> 0 | N82: =VLOOKUP($I82,$U$4:$Z$468,6,FALSE) -> 98377 | U82: 11162101 | V82: (저장품평가충당금) | W82: 0 | X82: 0 | Y82: 0 | Z82: 0
I83: 21121000 | J83: (유동성)공정가치위험회피파생상품부채 | K83: =VLOOKUP($I83,$U$4:$Z$468,3,FALSE) -> 581952 | L83: =VLOOKUP($I83,$U$4:$Z$468,4,FALSE) -> 275717 | M83: =VLOOKUP($I83,$U$4:$Z$468,5,FALSE) -> 0 | N83: =VLOOKUP($I83,$U$4:$Z$468,6,FALSE) -> 98377 | U83: 11162200 | V83: 미착품 | W83: 8686256 | X83: 4832647.3 | Y83: 3667945.6 | Z83: 2416497.1
I84: 21121001 | J84: (유동성)공정가치위험회피파생상품부채:금융 | K84: =VLOOKUP($I84,$U$4:$Z$468,3,FALSE) -> 581952 | L84: =VLOOKUP($I84,$U$4:$Z$468,4,FALSE) -> 275717 | M84: =VLOOKUP($I84,$U$4:$Z$468,5,FALSE) -> 0 | N84: =VLOOKUP($I84,$U$4:$Z$468,6,FALSE) -> 98377 | U84: 11162201 | V84: 미착품:상품 | W84: 0 | X84: 0 | Y84: 0 | Z84: 0
... I107: 31141016 | J107: 당기순이익 | K107: =VLOOKUP($I107,$U$4:$Z$468,3,FALSE) -> 8788375.4 | L107: =VLOOKUP($I107,$U$4:$Z$468,4,FALSE) -> 7604775 | M107: =VLOOKUP($I107,$U$4:$Z$468,5,FALSE) -> 14747531 | N107: =VLOOKUP($I107,$U$4:$Z$468,6,FALSE) -> 7083987 | U107: 11191600 | V107: 기타 매출채권 및 기타채권 | W107: 0 | X107: 0 | Y107: 0 | Z107: 0
U108: 11191601 | V108: 기타 당좌자산 | W108: 0 | X108: 0 | Y108: 0 | Z108: 0
U109: 11191701 | V109: 선급법인세 | W109: 0 | X109: 0 | Y109: 0 | Z109: 0
U110: 11191702 | V110: 미수법인세환급액 | W110: 0 | X110: 0 | Y110: 0 | Z110: 0
U111: 11191703 | V111: 선급제세기타 | W111: 0 | X111: 0 | Y111: 0 | Z111: 0
U112: 11201001 | V112: 매각예정자산 | W112: 0 | X112: 0 | Y112: 0 | Z112: 0
U113: 12000000 | V113: 비유동자산 | W113: 1.1895822e+08 | X113: 1.492997e+08 | Y113: 2.1079206e+08 | Z113: 2.2846091e+08
U114: 12100000 | V114: 장기매출채권및기타채권 | W114: 0 | X114: 0 | Y114: 0 | Z114: 0
U115: 12101000 | V115: 장기성매출채권 | W115: 0 | X115: 0 | Y115: 0 | Z115: 0
U116: 12101001 | V116: 장기성매출채권:원화 | W116: 0 | X116: 0 | Y116: 0 | Z116: 0
U117: 12101002 | V117: 장기성매출채권:외화 | W117: 0 | X117: 0 | Y117: 0 | Z117: 0
U118: 12101003 | V118: 부도어음 | W118: 0 | X118: 0 | Y118: 0 | Z118: 0
U119: 12101004 | V119: 공사채권 | W119: 0 | X119: 0 | Y119: 0 | Z119: 0
... U468: 32101006 | V468: 비지배지분_당기순이익 | W468: 0 | X468: 0 | Y468: 0 | Z468: 0
W469: TRUE | X469: TRUE | Y469: TRUE | Z469: TRUE
X470: 0

Sheet BS(RMB)
O1: 181.09
B2: 재무상태표_무석 | J2: 中國計定科目 | K2: 2012년말 | L2: 2013년말 | M2: 中國計定科目 | N2: 2014년말 | O2: 2015년 6월말 | R2: 연결계정명 | S2: 2015년 6월말
C3: 2012년 | D3: 2013년 | E3: 2014년 | F3: 2015년 | J3: 1.資産 | K3: 2.7438482e+08 | L3: 3.3275753e+08 | M3: 1.資産 | N3: 4.0051574e+08 | O3: 4.4395126e+08 | R3: 자산 | S3: 80443477566
B4: RMB('000) | C4: 12월 31일 | D4: 12월 31일 | E4: 12월 31일 | F4: 6월 30일 | J4: (1)流動資産 | K4: 1.554266e+08 | L4: 1.8365681e+08 | M4: (1)流動資産 | N4: 1.8991094e+08 | O4: 2.1579528e+08 | R4: 유동자산 | S4: 39071492039
B5: 유동자산 | C5: =K4 -> 1.554266e+08 | D5: =L4 -> 1.8365681e+08 | E5: =N4 -> 1.8991094e+08 | F5: =O4 -> 2.1579528e+08 | K5: =K6+K8 -> 6544146.5 | L5: =L6+L8 -> 5758342.2 | R5: 당좌자산 | S5: 23985736215
B6: 현금및현금성자산 | C6: =K6+K8 -> 6544146.5 | D6: =L6+L8 -> 5758342.2 | E6: =N6+N8 -> 6290709.5 | F6: =O6+O8 -> 2859003.5 | J6: 1)현금 | K6: 1582.88 | L6: 1117.4 | M6: 1)현금 | N6: 37000.27 | O6: 8615.71 | P6: =(O6+O8)*O1 -> 5.1773693e+08 | Q6: =P6-S6 -> -0.23949999 | R6: 현금및현금성자산 | S6: 517736935 | T6: =P6-S6 -> -0.23949999
B7: 매출채권 | C7: =K13+K14+K12 -> 80351270 | D7: =L13+L14+L12 -> 86422336 | E7: =N13+N14+N12 -> 98504881 | F7: =O13+O14+O12 -> 1.2749784e+08 | J7: (R.M.B) | K7: 1582.88 | L7: 1117.4 | M7: (R.M.B) | N7: 37000.27 | O7: 8615.71 | R7: 현금 | S7: 1560219
B8: 재고자산 | C8: =K19 -> 61491932 | D8: =L19 -> 67560993 | E8: =N19 -> 74321675 | F8: =O19 -> 74506417 | J8: 2)은행예금 | K8: 6542563.7 | L8: 5757224.8 | M8: 2)은행예금 | N8: 6253709.2 | O8: 2850387.7 | R8: 외화기타 | S8: 516176716
B9: 기타유동자산 | C9: =C5-SUM(C6:C8) -> 7039253.3 | D9: =D5-SUM(D6:D8) -> 23915139 | E9: =E5-SUM(E6:E8) -> 10793670 | F9: =F5-SUM(F6:F8) -> 10932023 | J9: (R.M.B) | K9: 5811976 | L9: 2930748.1 | M9: (R.M.B) | N9: 4095024.8 | O9: 1121758 | R9: 매출채권 및 기타채권 | S9: 23467999280
B10: 비유동자산 | C10: =K28+K47+K48+K49+K52+K56+K58 -> 1.1895822e+08 | D10: =L28+L47+L48+L49+L52+L56+L58 -> 1.4910072e+08 | E10: =N28+N47+N48+N49+N51+N53+N57+N58 -> 2.1060481e+08 | F10: =O28+O47+O48+O49+O51+O53+O57+O58 -> 2.2815598e+08 | J10: (U.S.D) | K10: 526941.49 | L10: 693794.6 | M10: (U.S.D) | N10: 2158423.5 | O10: 1185979 | R10: 매출채권 | S10: 23097496185
B11: 유형자산 | C11: =K28+K48+K55 -> 94369715 | D11: =L28+L48+L55 -> 1.180084e+08 | E11: =N28+N49+N56 -> 1.7693834e+08 | F11: =O28+O49+O56 -> 1.9544232e+08 | J11: (E.U.R) | K11: 203646.12 | L11: 2132682.1 | M11: (E.U.R) | N11: 261.02 | O11: 542650.72 | R11: 외화외상매출금 | S11: 21829866185
B12: 무형자산 | C12: =K49+K53+K54 -> 22495451 | D12: =L49+L53+L54 -> 28250956 | E12: =N51+N54+N55 -> 29361158 | F12: =O51+O54+O55 -> 29225166 | J12: 3)수취어음 | K12: 28020953 | L12: 19977357 | M12: 3)수취어음 | N12: 8483700 | O12: 7000000 | P12: =O12*O1 -> 1267630000 | R12: 받을어음 | S12: 1267630000
B13: 기타비유동자산 | C13: =C10-C11-C12 -> 2093055.9 | D13: =D10-D11-D12 -> 2841360.9 | E13: =E10-E11-E12 -> 4305312.1 | F13: =F10-F11-F12 -> 3488495.6 | J13: 4)수취계좌 | K13: 53281627 | L13: 66467579 | M13: 4)수취계좌 | N13: 90070397 | O13: 1.2054705e+08 | P13: =O13*O1 -> 2.1829866e+10 | R13: (매출채권 대손충당금) | S13: -8912591
B14: 자산총계 | C14: =C5+C10 -> 2.7438482e+08 | D14: =D5+D10 -> 3.3275753e+08 | E14: =E5+E10 -> 4.0051574e+08 | F14: =F5+F10 -> 443951262 | J14: 5)대손준비 | K14: -951310.12 | L14: -22600.58 | M14: 5)대손준비 | N14: -49216.36 | O14: -49216.36 | R14: (대손충당금:외화외상매출금) | S14: -8912591
B15: 유동부채 | C15: =K61 -> 1.2102811e+08 | D15: =L61 -> 1.9009646e+08 | E15: =N61 -> 2.4492284e+08 | F15: =O61 -> 2.8232716e+08 | J15: 6)대금선급 | K15: 6301006.3 | L15: 22505091 | M15: 6)대금선급 | N15: 8304987.2 | O15: 7760995.9 | P15: =O15*$O$1 -> 1.4054388e+09 | R15: 미수금 | S15: 379415686
B16: 매입채무 | C16: =K64 -> 47779997 | D16: =L64 -> 54146686 | E16: =N65 -> 64828470 | F16: =O65 -> 89071341 | J16: 7)기타미수금 | K16: 570343.06 | L16: 1035202.4 | M16: 7)기타미수금 | N16: 947383.99 | O16: 2324064.1 | P16: =O16*$O$1 -> 4.2086476e+08 | R16: (미수금대손충당금) | S16: 0
B17: 단기차입금 | C17: =K62 -> 54683850 | D17: =L62 -> 1.1041775e+08 | E17: =N62 -> 1.3980301e+08 | F17: =O62 -> 1.5336941e+08 | J17: 8)업무비용비치 | K17: 167903.96 | L17: 374845.28 | M17: 8)업무비용비치 | N17: 339375.23 | O17: 770923.32 | P17: =O17*$O$1 -> 1.396065e+08 | R17: (유동성)당기손익인식금융자산 | S17: 0
B18: 기타유동부채 | C18: =C15-C16-C17 -> 18564260 | D18: =D15-D16-D17 -> 25532019 | E18: =E15-E16-E17 -> 40291358 | F18: =F15-F16-F17 -> 39886416 | M18: 9)미수보조금 | N18: 958078.07 | O18: 76039.38 | P18: =O18*$O$1 -> 13769971 | R18: (유동성)위험회피파생상품자산 | S18: 0
B19: 비유동부채 | C19: =SUM(C20:C21) -> 28225974 | D19: =SUM(D20:D21) -> 16791127 | E19: =SUM(E20:E21) -> 16412932 | F19: =SUM(F20:F21) -> 16949432 | J19: 10)재고 | K19: 61491932 | L19: 67560993 | M19: 10)재고 | N19: 74321675 | O19: 74506417 | P19: =O19*O1 -> 1.3492367e+10 | R19: (유동성)공정가치위험회피파생상품자산:금융 | S19: 0
B20: 장기차입금 | C20: =K77 -> 28000000 | D20: =L77 -> 15242250 | E20: =N77 -> 15297500 | F20: =O77 -> 15284000 | J20: (주재료) | K20: 17095250 | L20: 23687083 | M20: (部品) | N20: 30515722 | O20: 31232712 | R20: 재고자산 | S20: 13012116352
B21: 판매보증충당부채 | C21: =K79 -> 225974.47 | D21: =L79 -> 1548877.4 | E21: =N79 -> 1115432.1 | F21: =O79 -> 1665432.1 | J21: (보조재료) | K21: 546730.82 | L21: 840172.9 | M21: (副资材) | N21: 825606.16 | O21: 747001.55 | P21: =O21*$O$1 -> 1.3527451e+08 | R21: 상품 | S21: 186595237
B22: 부채총계 | C22: =C15+C19 -> 1.4925408e+08 | D22: =D15+D19 -> 2.0688759e+08 | E22: =E15+E19 -> 2.6133577e+08 | F22: =F15+F19 -> 2.992766e+08 | J22: (기존자재） | K22: 1491727.2 | L22: 2423991.8 | M22: （原资材） | N22: 2822038.9 | O22: 2761272.5 | P22: =O22*$O$1 -> 5.0003883e+08 | R22: (상품평가충당금) | S22: 0
B23: 자본금 | C23: =K81 -> 54568890 | D23: =L81 -> 85407390 | E23: =N81 -> 85407390 | F23: =O81 -> 85407390 | J23: (재공품) | K23: 0 | L23: 0 | M23: (在工品) | N23: 0 | O23: 0 | P23: =O23*$O$1 -> 0 | R23: 제품 | S23: 6416410823
B24: 이익잉여금 | C24: =K84 -> 60142044 | D24: =L84 -> 30042740 | E24: =N84 -> 41117540 | F24: =O84 -> 46612237 | J24: (제품) | K24: 23868786 | L24: 32145375 | M24: (製品) | N24: 32201615 | O24: 33666533 | P24: =O24*$O$1 -> 6.0966725e+09 | Q24: =O19-O26 -> 72089920 | R24: (제품평가충당금) | S24: -319738341
B25: 기타자본 | C25: =K83 -> 10419809 | D25: =L83 -> 10419809 | E25: =N83 -> 12655040 | F25: =O83 -> 12655040 | J25: (상품) | K25: 9803182.4 | L25: 3631722.1 | M25: (商品) | N25: 4288746.4 | O25: 3682400.6 | P25: =O25*$O$1 -> 6.6684592e+08 | R25: 반제품 | S25: 5978084273
B26: 자본총계 | C26: =SUM(C23:C25) -> 1.2513074e+08 | D26: =SUM(D23:D25) -> 1.2586994e+08 | E26: =SUM(E23:E25) -> 1.3917997e+08 | F26: =SUM(F23:F25) -> 1.4467467e+08 | J26: (在涂品) | K26: 8686256 | L26: 4832647.3 | M26: (在涂品) | N26: 3667945.6 | O26: 2416497.1 | P26: =O26*$O$1 -> 4.3760346e+08 | Q26: =N19-N26 -> 70653729 | R26: (반제품평가충당금) | S26: -322152440
B27: 자본과부채총계 | C27: =C22+C26 -> 2.7438482e+08 | D27: =D22+D26 -> 3.3275753e+08 | E27: =E22+E26 -> 4.0051574e+08 | F27: =F22+F26 -> 443951262 | M27: 11)交易性金融资产 | N27: 243846 | O27: 0 | P27: =O27*$O$1 -> 0 | Q27: =O19-O26 -> 72089920 | R27: 원재료 | S27: 648635302
B28: Net debt | C28: =C20+C17-C6 -> 76139703 | D28: =D20+D17-D6 -> 1.1990166e+08 | E28: =E20+E17-E6 -> 1.488098e+08 | F28: =F20+F17-F6 -> 1.657944e+08 | J28: (2)고정자산 | K28: 86145367 | L28: 1.0429589e+08 | M28: (2)固定資産 | N28: 1.3080492e+08 | O28: 1.4046686e+08 | P28: =O28*$O$1 -> 2.5437143e+10 | R28: (원재료평가충당금) | S28: -13321964
J29: 1）固定资产_房屋建筑物 | K29: 20582009 | L29: 20970009 | M29: 1）固定资产_房屋建筑物 | N29: 20970009 | O29: 20970009 | P29: =O29*$O$1 -> 3.7974589e+09 | Q29: =S42 -> 3797458850 | R29: 미착품 | S29: 437603462
B30: 환율 | C30: =BS!C14/'BS(RMB)'!C14 -> 171.88 | D30: =BS!D14/'BS(RMB)'!D14 -> 174.34764 | E30: =BS!E14/'BS(RMB)'!E14 -> 177.07082 | F30: =BS!F14/'BS(RMB)'!F14 -> 181.19889 | J30: (累計折舊) | K30: -514550.21 | L30: -1030717.1 | M30: (累計折舊) | N30: -1554967.3 | O30: -1817092.4 | P30: =O30*$O$1 -> -3.2905726e+08 | R30: 미착품:원재료 | S30: 437603462
C31: =C14=C27 -> TRUE | D31: =D14=D27 -> TRUE | E31: =E14=E27 -> TRUE | F31: =F14=F27 -> TRUE | J31: 2)기계설비 | K31: 59003852 | L31: 75154055 | M31: 2)기계설비 | N31: 1.0441171e+08 | O31: 1.1306754e+08 | P31: =O31*$O$1 -> 2.0475401e+10 | Q31: =S45 -> 20475400571 | R31: 기타유동자산 | S31: 2073639472
J32: (累計折舊) | K32: -18624182 | L32: -24975137 | M32: (累計折舊) | N32: -33512029 | O32: -37633306 | P32: =O32*$O$1 -> -6.8150155e+09 | R32: 선급부가가치세(매입부가세) | S32: 48343533
J33: 3)다른설비 | K33: 3424701.5 | L33: 4198990.4 | M33: 3)다른설비 | N33: 4629231.3 | O33: 5030808.7 | P33: =O33*$O$1 -> 9.1102915e+08 | R33: 선급금 | S33: 1885689435
J34: (累計折舊) | K34: -1758587.8 | L34: -2053173.1 | M34: (累計折舊) | N34: -2267385.7 | O34: -2457099.6 | P34: =O34*$O$1 -> -4.4495617e+08 | R34: (선급금대손충당금) | S34: 0
J35: 4)전자장비 | K35: 17295761 | L35: 20542919 | M35: 4)전자장비 | N35: 22595195 | O35: 25822451 | P35: =O35*$O$1 -> 4.6761876e+09 | R35: (유동성)선급비용 | S35: 139606504
J36: (累計折舊) | K36: -10829829 | L36: -11768736 | M36: (累計折舊) | N36: -11822924 | O36: -12858485 | P36: =O36*$O$1 -> -2.328543e+09 | R36: 비유동자산 | S36: 41371985527
J37: 5)교통수단 | K37: 2623692.2 | L37: 2567498 | M37: 5)교통수단 | N37: 2456384.9 | O37: 2566028.8 | P37: =O37*$O$1 -> 4.6468216e+08 | Q37: =S48 -> 464682157 | R37: 장기매출채권및기타채권 | S37: 55219049
J38: (累計折舊) | K38: -1058619.9 | L38: -1216753.4 | M38: (累計折舊) | N38: -1512176.6 | O38: -1706431.1 | P38: =O38*$O$1 -> -3.0901762e+08 | R38: 장기보증금 | S38: 55219049
J39: 6)가구집기 | K39: 587571.35 | L39: 590971.35 | M39: 6)가구집기 | N39: 821243.12 | O39: 859539.7 | P39: =O39*$O$1 -> 1.5565404e+08 | R39: 기타 | S39: 55219049
J40: (累計折舊) | K40: -468409.05 | L40: -495272.68 | M40: (累計折舊) | N40: -531938.74 | O40: -559556.7 | P40: =O40*$O$1 -> -1.0133012e+08 | R40: 유형자산 | S40: 34936947543
J41: 7)공구기구 | K41: 4731339.2 | L41: 5696232.9 | M41: 7)공구기구 | N41: 5739838.7 | O41: 6303952.1 | P41: =O41*$O$1 -> 1.1415827e+09 | Q41: =S51 -> 1141582682 | R41: 건물 | S41: 3468401585
J42: (累計折舊) | K42: -2581806.9 | L42: -3065965.3 | M42: (累計折舊) | N42: -2495005.4 | O42: -2815734.4 | P42: =O42*$O$1 -> -5.0990134e+08 | R42: 건물 | S42: 3797458850
J43: 8)개량고정자산지출 | K43: 0 | L43: 0 | M43: 8)개량고정자산지출 | N43: 0 | O43: 0 | P43: =O43*$O$1 -> 0 | R43: (건물감가상각누계액) | S43: -329057265
J44: (累計折舊) | K44: 0 | L44: 0 | M44: (累計折舊) | N44: 0 | O44: 0 | P44: =O44*$O$1 -> 0 | R44: 기계장치 | S44: 13660385117
J45: 9)금형 | K45: 22711747 | L45: 32916261 | M45: 9)금형 | N45: 42959651 | O45: 49253783 | P45: =O45*$O$1 -> 8.9193676e+09 | R45: 기계장치 | S45: 20475400571
J46: (累計折舊) | K46: -8979321 | L46: -13735290 | M46: (累計折舊) | N46: -20081916 | O46: -23559549 | P46: =O46*$O$1 -> -4.2663987e+09 | R46: (기계장치감가상각누계액) | S46: -6815015454
J47: (3)다른장기자산 | K47: 70000 | L47: 70000 | M47: (3)其他长期资产 | N47: 70000 | O47: 70000 | P47: =O47*$O$1 -> 12676300 | R47: 차량운반구 | S47: 155664540
J48: (4)건설가계정 | K48: 6737830.5 | L48: 12726752 | M48: (4)固定資産淸理 | N48: 0 | O48: 0 | P48: =O48*$O$1 -> 0 | R48: 차량운반구 | S48: 464682157
J49: (5)무형자산 | K49: 22145451 | L49: 27900956 | M49: (5)건설가계정 | N49: 44039093 | O49: 52389023 | P49: =O49*$O$1 -> 9.4871282e+09 | Q49: =S59 -> 9487128238 | R49: (차량운반구감가상각누계액) | S49: -309017617
M50: 1)在建工程 | N50: 44039093 | O50: 52389023 | P50: =O50*$O$1 -> 9.4871282e+09 | R50: 공구와기구 | S50: 631681345
M51: (6)무형자산 | N51: 29011158 | O51: 28295166 | P51: =O51*$O$1 -> 5.1239716e+09 | R51: 공구와기구 | S51: 1141582682
J52: (6)비용비치오래 | K52: 1836516.9 | L52: 1335755.4 | M52: 1)無形資産 | N52: 29011158 | O52: 28295166 | P52: =O52*$O$1 -> 5.1239716e+09 | R52: (공구와기구감가상각누계액) | S52: -509901337
J53: 1)창업비 | K53: 0 | L53: 0 | M53: (7)長期待灘費用 | N53: 2444326.4 | O53: 3516439.2 | P53: =O53*$O$1 -> 6.3679198e+08 | R53: 비품 | S53: 54323921
J54: 2)골프회원비 | K54: 350000 | L54: 350000 | M54: 1)开办费 | N54: 0 | O54: 0 | P54: =O54*$O$1 -> 0 | R54: 비품 | S54: 155654044 | T54: 15707632
J55: 3)인테리어비 | K55: 1486516.9 | L55: 985755.37 | M55: 2)高尔夫会员费 | N55: 350000 | O55: 930000 | P55: =O55*$O$1 -> 168413700 | R55: (비품감가상각누계액) | S55: -101330123 | T55: =T54*O1 -> 2.8444951e+09
J56: (7)대기처리재산 | K56: 0 | L56: 0 | M56: 3)装修费 | N56: 2094326.4 | O56: 2586439.2 | P56: =O56*$O$1 -> 4.6837828e+08 | R56: 금형 | S56: 4652968933
M57: (8)待处理财产损溢 | N57: 0 | O57: 0 | P57: =O57*$O$1 -> 0 | R57: 금형 | S57: 8919367643
J58: （9）이연법인세 | K58: 2023055.9 | L58: 2771360.9 | M58: （9）递延税款借项 | N58: 4235312.1 | O58: 3418495.6 | P58: =O58*$O$1 -> 6.1905537e+08 | R58: (금형감가상각누계액) | S58: -4266398710
J59: 資産合計 | K59: 2.7438482e+08 | L59: 3.3275753e+08 | M59: 資産合計 | N59: 4.0051574e+08 | O59: 4.4395126e+08 | P59: =O59*$O$1 -> 8.0395134e+10 | R59: 건설중인유형자산 | S59: 9487128238
J60: 2.負債 | K60: 1.4925408e+08 | L60: 2.0688759e+08 | M60: 2.負債 | N60: 2.6133577e+08 | O60: 2.992766e+08 | P60: =O60*$O$1 -> 5.4195999e+10 | R60: 건설중인유형자산 | S60: 9487128238
J61: (1)流動負債 | K61: 1.2102811e+08 | L61: 1.9009646e+08 | M61: (1)流動負債 | N61: 2.4492284e+08 | O61: 2.8232716e+08 | P61: =O61*$O$1 -> 5.1126626e+10 | R61: 기타의유형자산 | S61: 2826393864
J62: 1)단기차입금 | K62: 54683850 | L62: 1.1041775e+08 | M62: 1)短期借款 | N62: 1.3980301e+08 | O62: 1.5336941e+08 | P62: =O62*$O$1 -> 2.7773666e+10 | R62: 기타의유형자산 | S62: 5599893039
J63: 应付信用证 | K63: 0 | L63: 0 | M63: 2）应付信用证 | N63: 0 | O63: 0 | P63: =O63*$O$1 -> 0 | R63: (기타유형자산감가상각누계액) | S63: -2773499175
J64: 2)외상매입금 | K64: 47779997 | L64: 54146686 | M64: 3）应付票据 | N64: 0 | O64: 0 | P64: =O64*$O$1 -> 0 | R64: 무형자산 | S64: 2447890154
J65: 3)미지급급여 | K65: 996801.26 | L65: 1196534 | M65: 4)외상매입금 | N65: 64828470 | O65: 89071341 | P65: =O65*$O$1 -> 1.6129929e+10 | R65: 소프트웨어 | S65: 2279476454
J66: 4)應交稅金 | K66: 803443.24 | L66: 652026.84 | M66: 5)應付工資 | N66: 1193574.1 | O66: 1209526.9 | P66: =O66*$O$1 -> 2.1903323e+08 | R66: 소프트웨어 | S66: 2279476454
J67: 6)應付股利 | K67: 0 | L67: 0 | M67: 6)應交稅金 | N67: 4374018.3 | O67: 2310412.6 | P67: =O67*$O$1 -> 4.1839261e+08 | R67: 회원권 | S67: 168413700
J68: 7)선수금 | K68: 4245.7 | L68: 790745.07 | M68: 7)應付股利 | N68: 0 | O68: 0 | P68: =O68*$O$1 -> 0 | R68: 회원권 | S68: 168413700
J69: 8)기타미지급금 | K69: 13113829 | L69: 18885328 | M69: 8)預收貨款 | N69: 329478.6 | O69: 308831.92 | P69: =O69*$O$1 -> 55926372 | R69: (회원권손상차손누계액) | S69: 0
... J74: 13)거래적금융부채 | K74: 581952 | L74: 275717 | M74: 13)递延税款贷项 | N74: 0 | O74: 0 | P74: =O74*$O$1 -> 0 | R74: 부채 | S74: 54244342237
M75: 14)交易性金融负债 | N75: 0 | O75: 98377 | P75: =O75*$O$1 -> 17815091 | R75: 유동부채 | S75: 51174969569
J76: (2)장기부채 | K76: 28225974 | L76: 16791127 | M76: (2)長期負債 | N76: 16412932 | O76: 16949432 | P76: =O76*$O$1 -> 3.0693727e+09 | R76: 매입채무및기타채무 | S76: 22102088142
J77: 1)장기차입금 | K77: 28000000 | L77: 15242250 | M77: 1)장기차입금 | N77: 15297500 | O77: 15284000 | P77: =O77*$O$1 -> 2767779560 | R77: 매입채무 | S77: 16129929084
J78: 2)長期應付款 | K78: 0 | L78: 0 | M78: 2)長期應付款 | N78: 0 | O78: 0 | P78: =O78*$O$1 -> 0 | R78: 외상매입금:외화 | S78: 15142995864
J79: 3）판매보증충당부채 | K79: 225974.47 | L79: 1548877.4 | M79: 3）销售保证准备负债 | N79: 1115432.1 | O79: 1665432.1 | P79: =O79*$O$1 -> 3.0159311e+08 | R79: 미확정매입채무:GL | S79: 986933220
J80: 3.所有者權益 | K80: 1.2513074e+08 | L80: 1.2586994e+08 | M80: 3.所有者權益 | N80: 1.3917997e+08 | O80: 1.4467467e+08 | P80: =O80*$O$1 -> 2.6199135e+10 | R80: 미지급금 | S80: 4994577782
J81: 1)납입자본 | K81: 54568890 | L81: 85407390 | M81: 1)實收資本 | N81: 85407390 | O81: 85407390 | P81: =O81*$O$1 -> 1.5466424e+10 | R81: 미지급비용 | S81: 977581276
J82: 2)資本公積 | K82: 0 | L82: 0 | M82: 2)資本公積 | N82: 0 | O82: 0 | P82: =O82*$O$1 -> 0 | R82: (유동성)위험회피파생상품부채 | S82: 17815091
J83: 3)기금 비축 | K83: 10419809 | L83: 10419809 | M83: 3)儲備基金 | N83: 12655040 | O83: 12655040 | P83: =O83*$O$1 -> 2.2917011e+09 | R83: (유동성)공정가치위험회피파생상품부채 | S83: 17815091
J84: 4)미처분이익잉여금 | K84: 60142044 | L84: 30042740 | M84: 4)未分配利潤 | N84: 41117540 | O84: 46612237 | P84: =O84*$O$1 -> 8.44101e+09 | R84: (유동성)공정가치위험회피파생상품부채:금융 | S84: 17815091
J85: a.移越利益剩餘金 | K85: 51353668 | L85: 23280465 | M85: a.移越利益剩餘金 | N85: 26370009 | O85: 39528250 | P85: =O85*$O$1 -> 7.1581708e+09 | R85: 단기차입금 | S85: 27773665899
J86: b.淨利潤 | K86: 8788375.4 | L86: 6762275 | M86: b.淨利潤 | N86: 14747531 | O86: 7083987 | P86: =O86*$O$1 -> 1.2828392e+09 | R86: 단기차입금:외화 | S86: 27773665899
J87: 權益合計 | K87: 2.7438482e+08 | L87: 3.3275753e+08 | M87: 權益合計 | N87: 4.0051574e+08 | O87: 443951262 | P87: =O87*$O$1 -> 8.0395134e+10 | R87: 기타유동부채 | S87: 1281400437
R88: 선수금 | S88: 55926372
R89: 예수금 | S89: 18746183
R90: 매출부가세 | S90: 0
R91: 미지급법인세 | S91: 406368682
R92: (유동성)미지급배당금 | S92: 800359200
R93: 비유동부채 | S93: 3069372668
R94: 장기차입금 | S94: 2767779560
R95: 장기차입금:외화 | S95: 2767779560
R96: 충당부채 | S96: 301593108
R97: 판매보증충당부채 | S97: 301593108
R98: 자본 | S98: 26199135329
R99: 지배주주지분 | S99: 26199135329
... R107: 당기순이익 | S107: 1250677909
S109: TRUE

Sheet 제품군별 매출
B4: 제품 매출액(제품군별) | H4: 제품군별 매출원가 | N4: 제품군별 마진
C5: 2012년 | D5: 2013년 | E5: 2014년 | F5: 2015년 | I5: 2012년 | J5: 2013년 | K5: 2014년 | L5: 2015년 | O5: 2012년 | P5: 2013년 | Q5: 2014년 | R5: 2015년
B6: RMB'000 | C6: 12개월 | D6: 12개월 | E6: 12개월 | F6: 6개월 | H6: RMB'000 | I6: 12개월 | J6: 12개월 | K6: 12개월 | L6: 6개월 | N6: RMB'000 | O6: 12개월 | P6: 12개월 | Q6: 12개월 | R6: 6개월
B7: HMI 사업부 | C7: =SUM(C8:C10) -> 1.8149328e+08 | D7: =SUM(D8:D10) -> 1.9897776e+08 | E7: =SUM(E8:E10) -> 2.6850984e+08 | F7: =SUM(F8:F10) -> 1.4300114e+08 | H7: HMI 사업부 | I7: =SUM(I8:I10) -> 1.4919835e+08 | J7: =SUM(J8:J10) -> 1.7115965e+08 | K7: =SUM(K8:K10) -> 2.2675932e+08 | L7: =SUM(L8:L10) -> 1.227648e+08 | N7: HMI 사업부 | O7: =SUM(O8:O10) -> 32294933 | P7: =SUM(P8:P10) -> 27818111 | Q7: =SUM(Q8:Q10) -> 41750519 | R7: =SUM(R8:R10) -> 20236345
B8: =B27 -> SWITCH-I/P | C8: =C27 -> 71335701 | D8: =D27 -> 91449554 | E8: =E27 -> 1.7119898e+08 | F8: =F27 -> 94578446 | H8: =H27 -> SWITCH-I/P | I8: =I27 -> 62923263 | J8: =J27 -> 85044507 | K8: =K27 -> 1.4757185e+08 | L8: =L27 -> 82418008 | N8: =N27 -> SWITCH-I/P | O8: =O27 -> 8412438.3 | P8: =P27 -> 6405047.4 | Q8: =Q27 -> 23627138 | R8: =R27 -> 12160437
B9: =B28 -> SWITCH-P/W | C9: =C28 -> 99826736 | D9: =D28 -> 92762593 | E9: =E28 -> 85943333 | F9: =F28 -> 42129351 | H9: =H28 -> SWITCH-P/W | I9: =I28 -> 78533790 | J9: =J28 -> 75252158 | K9: =K28 -> 70444817 | L9: =L28 -> 34826231 | N9: =N28 -> SWITCH-P/W | O9: =O28 -> 21292946 | P9: =P28 -> 17510434 | Q9: =Q28 -> 15498516 | R9: =R28 -> 7303120.9
B10: =B33 -> SWITCH-M/F | C10: =C33 -> 10330845 | D10: =D33 -> 14765611 | E10: =E33 -> 11367519 | F10: =F33 -> 6293345.7 | H10: =H33 -> SWITCH-M/F | I10: =I33 -> 7741296.7 | J10: =J33 -> 10862981 | K10: =K33 -> 8742653.5 | L10: =L33 -> 5520559.2 | N10: =N33 -> SWITCH-M/F | O10: =O33 -> 2589548.2 | P10: =P33 -> 3902629.4 | Q10: =Q33 -> 2624865.2 | R10: =R33 -> 772786.48
B11: MC 사업부 | C11: =SUM(C12:C14) -> 33859428 | D11: =SUM(D12:D14) -> 44049291 | E11: =SUM(E12:E14) -> 54664322 | F11: =SUM(F12:F14) -> 36431072 | H11: MC 사업부 | I11: =SUM(I13:I14) -> 19911170 | J11: =SUM(J13:J14) -> 25784420 | K11: =SUM(K13:K14) -> 22395479 | L11: =SUM(L13:L14) -> 8009026.1 | N11: MC 사업부 | O11: =SUM(O13:O14) -> -5783874 | P11: =SUM(P13:P14) -> -7800922.2 | Q11: =SUM(Q13:Q14) -> -5631658.3 | R11: =SUM(R13:R14) -> -772977.34
B12: =B29 -> ABS | C12: =C29 -> 19732131 | D12: =D29 -> 26065794 | E12: =E29 -> 37900501 | F12: =F29 -> 29195023 | H12: =H29 -> ABS | I12: =I29 -> 18075829 | J12: =J29 -> 23154915 | K12: =K29 -> 28427851 | L12: =L29 -> 22528427 | N12: =N29 -> ABS | O12: =O29 -> 1656302.8 | P12: =P29 -> 2910879 | Q12: =Q29 -> 9472649.7 | R12: =R29 -> 6666596.4
B13: =B34 -> RELAY | C13: =C34 -> 14127296 | D13: =D34 -> 17983497 | E13: =E34 -> 15236853 | F13: =F34 -> 5545216.5 | H13: =H34 -> RELAY | I13: =I34 -> 19911170 | J13: =J34 -> 25784420 | K13: =K34 -> 20923744 | L13: =L34 -> 6450447.8 | N13: =N34 -> RELAY | O13: =O34 -> -5783874 | P13: =P34 -> -7800922.2 | Q13: =Q34 -> -5686891.8 | R13: =R34 -> -905231.29 | S13: 정리중임
B14: =B36 -> UNIT | C14: =C36 -> 0 | D14: =D36 -> 0 | E14: =E36 -> 1526968 | F14: =F36 -> 1690832.3 | H14: =H36 -> UNIT | I14: =I36 -> 0 | J14: =J36 -> 0 | K14: =K36 -> 1471734.5 | L14: =L36 -> 1558578.3 | N14: =N36 -> UNIT | O14: =O36 -> 0 | P14: =P36 -> 0 | Q14: =Q36 -> 55233.48 | R14: =R36 -> 132253.94
B15: BCS 사업부 | C15: =SUM(C16:C18) -> 17984636 | D15: =SUM(D16:D18) -> 16473303 | E15: =SUM(E16:E18) -> 21324010 | F15: =SUM(F16:F18) -> 23195963 | H15: BCS 사업부 | I15: =SUM(I17:I18) -> 19976653 | J15: =SUM(J17:J18) -> 16808119 | K15: =SUM(K17:K18) -> 18187928 | L15: =SUM(L17:L18) -> 8754449.8 | N15: BCS 사업부 | O15: =SUM(O17:O18) -> -1992017.2 | P15: =SUM(P17:P18) -> -334815.86 | Q15: =SUM(Q17:Q18) -> 3136082.2 | R15: =SUM(R17:R18) -> 1962284.9
B16: =B30 -> BCM | C16: =C30 -> 0 | D16: =D30 -> 0 | E16: =E30 -> 0 | F16: =F30 -> 12479228 | H16: =H30 -> BCM | I16: =I30 -> 0 | J16: =J30 -> 0 | K16: =K30 -> 0 | L16: =L30 -> 11855183 | N16: =N30 -> BCM | O16: =O30 -> 0 | P16: =P30 -> 0 | Q16: =Q30 -> 0 | R16: =R30 -> 624044.91
B17: =B31 -> SENSOR | C17: =C31 -> 5482605.3 | D17: =D31 -> 9111775.4 | E17: =E31 -> 16700967 | F17: =F31 -> 8871643.4 | H17: =H31 -> SENSOR | I17: =I31 -> 4747940.2 | J17: =J31 -> 7962159.3 | K17: =K31 -> 12353070 | L17: =L31 -> 6348058.9 | N17: =N31 -> SENSOR | O17: =O31 -> 734665.14 | P17: =P31 -> 1149616 | Q17: =Q31 -> 4347896.9 | R17: =R31 -> 2523584.5
B18: =B35 -> BEC | C18: =C35 -> 12502031 | D18: =D35 -> 7361527.4 | E18: =E35 -> 4623043 | F18: =F35 -> 1845091.3 | H18: =H35 -> BEC | I18: =I35 -> 15228713 | J18: =J35 -> 8845959.3 | K18: =K35 -> 5834857.7 | L18: =L35 -> 2406390.9 | N18: =N35 -> BEC | O18: =O35 -> -2726682.3 | P18: =P35 -> -1484431.9 | Q18: =Q35 -> -1211814.7 | R18: =R35 -> -561299.59 | S18: 정리중임
B19: 합계 | C19: =C7+C15+C11 -> 2.3333735e+08 | D19: =D7+D15+D11 -> 2.5950035e+08 | E19: =E7+E15+E11 -> 3.4449817e+08 | F19: =F7+F15+F11 -> 2.0262818e+08 | H19: 합계 | I19: =I7+I15+I11 -> 1.8908617e+08 | J19: =J7+J15+J11 -> 2.1375218e+08 | K19: =K7+K15+K11 -> 2.6734272e+08 | L19: =L7+L15+L11 -> 1.3952827e+08 | N19: 합계 | O19: =O7+O15+O11 -> 24519041 | P19: =P7+P15+P11 -> 19682373 | Q19: =Q7+Q15+Q11 -> 39254943 | R19: =R7+R15+R11 -> 21425652
B20: source: FDD_73,74_무석 매출,매출원가
B24: 제품군별 매출액 | H24: 제품군별 매출원가 | N24: 제품군별 마진
C25: 2012년 | D25: 2013년 | E25: 2014년 | F25: 2015년 | I25: 2012년 | J25: 2013년 | K25: 2014년 | L25: 2015년 | O25: 2012년 | P25: 2013년 | Q25: 2014년 | R25: 2015년
B26: RMB'000 | C26: 12개월 | D26: 12개월 | E26: 12개월 | F26: 6개월 | H26: RMB'000 | I26: 12개월 | J26: 12개월 | K26: 12개월 | L26: 6개월 | N26: RMB'000 | O26: 12개월 | P26: 12개월 | Q26: 12개월 | R26: 6개월
