Workbook

Sheet Legend
B2: Title | D2: Project dummy Financial Model
B4: Version | D4: Draft
B6: Date | D6: 46022
B8: Currency | D8: 별도표시가 없는 한 모든통화는 원(KRW)임
B10: Legend
B12: 구분 | D12: 설 명
B13: Value | D13: 상수
B14: Value | D14: Control 변수
B15: Value | D15: 참조값
B16: Value | D16: 수식결과값
B17: Value | D17: 총 합계
B18: Value | D18: 운영기간 합계
B19: VBA | D19: VBA참조셀 [삭제금지]
B20: Text | D20: 출처/설명
B21: Flag | D21: FALSE(논리값)
B22: Flag | D22: TRUE(논리값)
D23: Blank

Sheet Input
B1: =Legend!D2 | N1: DRAFT - For Discussion Purposes Only
B2: Assumptions
B4: Time Period
B6: Actual/Forecast | G6: Actual | H6: Actual | I6: Actual | J6: Forecast | K6: Forecast | L6: Forecast | M6: Forecast | N6: Forecast | O6: Forecast
B7: Period Start | G7: =DATE(G10,1,1) | H7: =DATE(H10,1,1) | I7: =DATE(I10,1,1) | J7: =DATE(J10,1,1) | K7: =DATE(K10,1,1) | L7: =DATE(L10,1,1) | M7: =DATE(M10,1,1) | N7: =DATE(N10,1,1) | O7: TV
B8: Period End | G8: =DATE(G10,12,31) | H8: =DATE(H10,12,31) | I8: =DATE(I10,12,31) | J8: =DATE(J10,12,31) | K8: =DATE(K10,12,31) | L8: =DATE(L10,12,31) | M8: =DATE(M10,12,31) | N8: =DATE(N10,12,31)
B9: Month | G9: =DATEDIF(G7,G8,"m")+1 | H9: =DATEDIF(H7,H8,"m")+1 | I9: =DATEDIF(I7,I8,"m")+1 | J9: =DATEDIF(J7,J8,"m")+1 | K9: =DATEDIF(K7,K8,"m")+1 | L9: =DATEDIF(L7,L8,"m")+1 | M9: =DATEDIF(M7,M8,"m")+1 | N9: =DATEDIF(N7,N8,"m")+1
B10: Year | G10: =H10-1 | H10: =I10-1 | I10: =E16 | J10: =I10+1 | K10: =J10+1 | L10: =K10+1 | M10: =L10+1 | N10: =M10+1
B11: Days | G11: =_xlfn.DAYS(G8,G7) | H11: =_xlfn.DAYS(H8,H7) | I11: =_xlfn.DAYS(I8,I7) | J11: =_xlfn.DAYS(J8,J7) | K11: =_xlfn.DAYS(K8,K7) | L11: =_xlfn.DAYS(L8,L7) | M11: =_xlfn.DAYS(M8,M7) | N11: =_xlfn.DAYS(N8,N7)
B13: 1. General Assumptions
B15: Model Date | E15: =Legend!D6
B16: Model Year | E16: =YEAR(E15)
B17: Unit | E17: 1000000 | F17: KRW
B18: WACC | E18: 0.1 | F18: %
B19: Perpetual Growth | E19: 0.01 | F19: %
B20: Industry Growth | J20: 1.03 | K20: 1.03 | L20: 1.03 | M20: 1.03 | N20: 1.03
B21: Nominal Wage Growth | J21: 1.02 | K21: 1.02 | L21: 1.02 | M21: 1.02 | N21: 1.02
B22: CPI | J22: 1.02 | K22: 1.02 | L22: 1.02 | M22: 1.02 | N22: 1.02
B23: PPI | J23: 1.02 | K23: 1.02 | L23: 1.02 | M23: 1.02 | N23: 1.02
B25: 2. Historical Financials
B27: [Profit & Loss] | G27: ="FY"&G10 | H27: ="FY"&H10 | I27: ="FY"&I10
B28: 매출 | G28: 1000 | H28: 1200 | I28: 1400
B29: 원가 | G29: =SUM(G30:G33) | H29: =SUM(H30:H33) | I29: =SUM(I30:I33)
B30: 재료비 | G30: 200 | H30: 200 | I30: 200
B31: 인건비 | G31: 100 | H31: 100 | I31: 100
B32: 기타경비 -변동비 | G32: 100 | H32: 100 | I32: 100
B33: 기타경비 -고정비 | G33: 200 | H33: 200 | I33: 200
B34: 매출총이익 | G34: =G28-G29 | H34: =H28-H29 | I34: =I28-I29
B35: 판관비 | G35: =SUM(G36:G40) | H35: =SUM(H36:H40) | I35: =SUM(I36:I40)
B36: 인건비 | G36: 100 | H36: 100 | I36: 100
B37: 변동비-#1 | G37: 50 | H37: 50 | I37: 50
B38: 변동비-#2 | G38: 60 | H38: 60 | I38: 60
B39: 변동비-#3 | G39: 70 | H39: 70 | I39: 70
B40: 고정비 | G40: 50 | H40: 50 | I40: 50
B41: 영업이익 | G41: =G34-G35 | H41: =H34-H35 | I41: =I34-I35
B42: 감가상각비 | G42: 10 | H42: 10 | I42: 10
B43: EBITDA | G43: =G41+G42 | H43: =H41+H42 | I43: =I41+I42
B44: 영업외손익 | G44: =G45-G48 | H44: =H45-H48 | I44: =I45-I48
B45: 영업외수익 | G45: =SUM(G46:G47) | H45: =SUM(H46:H47) | I45: =SUM(I46:I47)
B46: 이자손익 | G46: 10 | H46: 10 | I46: 10
B47: 기타 | G47: 10 | H47: 10 | I47: 10
B48: 영업외비용 | G48: =SUM(G49:G50) | H48: =SUM(H49:H50) | I48: =SUM(I49:I50)
B49: 이자비용 | G49: 10 | H49: 10 | I49: 10
B50: 기타 | G50: 10 | H50: 10 | I50: 10
B51: 세전이익 | G51: =G41+G44 | H51: =H41+H44 | I51: =I41+I44
B52: 법인세 | G52: 20 | H52: 30 | I52: 40
B53: 당기순이익 | G53: =G51-G52 | H53: =H51-H52 | I53: =I51-I52
B55: [Balance Sheet] | G55: ="Dec"&G10 | H55: ="Dec"&H10 | I55: ="Dec"&I10
B56: 유동자산 | G56: =SUM(G57:G60) | H56: =SUM(H57:H60) | I56: =SUM(I57:I60)
B57: 현금및현금성자산 | G57: 50 | H57: 50 | I57: 50
B58: 매출채권 | G58: 100 | H58: 100 | I58: 100
B59: 재고자산 | G59: 100 | H59: 100 | I59: 100
B60: 기타유동자산
B61: 비유동자산 | G61: =SUM(G62:G65) | H61: =SUM(H62:H65) | I61: =SUM(I62:I65)
B62: 유형자산
B63: 무형자산
B64: 투자자산
B65: 지분법투자주식
B66: 기타비유동자산
B67: 총자산 | G67: =+G56+G61 | H67: =+H56+H61 | I67: =+I56+I61
B68: 유동부채 | G68: =SUM(G69:G72) | H68: =SUM(H69:H72) | I68: =SUM(I69:I72)
B69: 매입채무 | G69: 200 | H69: 200 | I69: 200
B70: 미지급금
B71: 단기차입금 | G71: 100 | H71: 100 | I71: 100
B72: 기타유동부채
B73: 비유동부채 | G73: =SUM(G74:G77) | H73: =SUM(H74:H77) | I73: =SUM(I74:I77)
B74: 장기차입금 | G74: 200 | H74: 200 | I74: 200
B75: 사채
B76: 퇴직급여충당부채
B77: 기타비유동부채
B78: 총부채 | G78: =+G68+G73 | H78: =+H68+H73 | I78: =+I68+I73
B79: 순자산 | G79: =G67-G78 | H79: =H67-H78 | I79: =I67-I78
B81: 3. Revenue Assumptions
B84: [Revenue breakdown] - #1
B85: Price | E85: 30000 | F85: KRW/kg | J85: =$E85 | K85: =$E85 | L85: =$E85 | M85: =$E85 | N85: =$E85
B86: Quantity | E86: 30000 | F86: kg | J86: =$E$86 | K86: =J86 | L86: =K86 | M86: =L86 | N86: =M86
B90: [Revenue breakdown] - #2
B91: Price | E91: 20000 | F91: KRW/kg | J91: =$E91 | K91: =$E91 | L91: =$E91 | M91: =$E91 | N91: =$E91
B92: Quantity | E92: 20000 | F92: kg | J92: =$E$92 | K92: =J92 | L92: =K92 | M92: =L92 | N92: =M92
B96: [Revenue breakdown] - #3
B97: Price | E97: 30000 | F97: KRW/kg | J97: =$E97 | K97: =$E97 | L97: =$E97 | M97: =$E97 | N97: =$E97
B98: Quantity | E98: 0 | F98: kg | J98: =$E$98 | K98: =J98 | L98: =K98 | M98: =L98 | N98: =M98
B102: [Revenue breakdown] - #4
B103: Price | E103: 40000 | F103: KRW/kg | J103: =$E103 | K103: =$E103 | L103: =$E103 | M103: =$E103 | N103: =$E103
B104: Quantity | E104: 20000 | F104: kg | J104: =$E$104 | K104: =J104 | L104: =K104 | M104: =L104 | N104: =M104
B108: [Revenue breakdown] - #5
B109: Price | E109: 50000 | F109: KRW/kg | J109: =$E109 | K109: =$E109 | L109: =$E109 | M109: =$E109 | N109: =$E109
B110: Quantity | E110: 0 | F110: kg | J110: =$E$110 | K110: =J110 | L110: =K110 | M110: =L110 | N110: =M110
B115: 4. COGS Assumptions
B118: [COGS breakdown] - 재료비 (P*Q)
B119: Price | E119: 20000 | F119: KRW/kg | J119: =E119 | K119: =J119 | L119: =K119 | M119: =L119 | N119: =M119
B120: Quantity | E120: 20000 | F120: kg | J120: =E120 | K120: =J120 | L120: =K120 | M120: =L120 | N120: =M120
B124: [COGS breakdown] - 기타경비(변동비)
B125: 기타경비 | F125: KRW mn | G125: =G32 | H125: =H32 | I125: =I32 | J125: =E125 | K125: =J125 | L125: =K125 | M125: =L125 | N125: =M125
B126: % of revenue | E126: =AVERAGE(G126:I126) | F126: % | G126: =G125/G$28 | H126: =H125/H$28 | I126: =I125/I$28 | J126: =E126 | K126: =J126 | L126: =K126 | M126: =L126 | N126: =M126
B130: [COGS breakdown] - 기타경비(고정비)
B131: 기타경비 | E131: =I131 | F131: KRW mn | G131: =G33 | H131: =H33 | I131: =I33 | J131: =E131 | K131: =J131 | L131: =K131 | M131: =L131 | N131: =M131
B135: [COGS breakdown] - 별도 추정- #1
B136: Price | E136: 0 | F136: KRW/kg | J136: =E136 | K136: =J136 | L136: =K136 | M136: =L136 | N136: =M136
B137: Quantity | E137: 0 | F137: kg | J137: =E137 | K137: =J137 | L137: =K137 | M137: =L137 | N137: =M137
...

Sheet Calculation
B1: =Legend!D2
B2: Calculations
B4: Time Period
B6: Actual/Forecast | G6: =Input!G6 | H6: =Input!H6 | I6: =Input!I6 | J6: =Input!J6 | K6: =Input!K6 | L6: =Input!L6 | M6: =Input!M6 | N6: =Input!N6 | O6: =Input!O6
B7: Period Start | G7: =Input!G7 | H7: =Input!H7 | I7: =Input!I7 | J7: =Input!J7 | K7: =Input!K7 | L7: =Input!L7 | M7: =Input!M7 | N7: =Input!N7 | O7: TV
B8: Period End | G8: =Input!G8 | H8: =Input!H8 | I8: =Input!I8 | J8: =Input!J8 | K8: =Input!K8 | L8: =Input!L8 | M8: =Input!M8 | N8: =Input!N8
B9: Month | G9: =Input!G9 | H9: =Input!H9 | I9: =Input!I9 | J9: =Input!J9 | K9: =Input!K9 | L9: =Input!L9 | M9: =Input!M9 | N9: =Input!N9
B10: Year | G10: =Input!G10 | H10: =Input!H10 | I10: =Input!I10 | J10: =Input!J10 | K10: =Input!K10 | L10: =Input!L10 | M10: =Input!M10 | N10: =Input!N10
B11: Days | G11: =Input!G11 | H11: =Input!H11 | I11: =Input!I11 | J11: =Input!J11 | K11: =Input!K11 | L11: =Input!L11 | M11: =Input!M11 | N11: =Input!N11
B13: Revenue
B15: [Total revenue]
B16: Revenue #1 | F16: KRW mn | G16: =G29 | H16: =H29 | I16: =I29 | J16: =J29 | K16: =K29 | L16: =L29 | M16: =M29 | N16: =N29
B17: Revenue #2 | F17: KRW mn | G17: =G36 | H17: =H36 | I17: =I36 | J17: =J36 | K17: =K36 | L17: =L36 | M17: =M36 | N17: =N36
B18: Revenue #3 | F18: KRW mn | G18: =G43 | H18: =H43 | I18: =I43 | J18: =J43 | K18: =K43 | L18: =L43 | M18: =M43 | N18: =N43
B19: Revenue #4 | F19: KRW mn | G19: =G50 | H19: =H50 | I19: =I50 | J19: =J50 | K19: =K50 | L19: =L50 | M19: =M50 | N19: =N50
B20: Revenue #5 | F20: KRW mn | G20: =G57 | H20: =H57 | I20: =I57 | J20: =J57 | K20: =K57 | L20: =L57 | M20: =M57 | N20: =N57
B21: Total Revenue | F21: KRW mn | G21: =SUM(G16:G20) | H21: =SUM(H16:H20) | I21: =SUM(I16:I20) | J21: =SUM(J16:J20) | K21: =SUM(K16:K20) | L21: =SUM(L16:L20) | M21: =SUM(M16:M20) | N21: =SUM(N16:N20)
B22: check | G22: =G21=Input!G28 | H22: =H21=Input!H28 | I22: =I21=Input!I28
B24: [Revenue breakdown] - #1
B25: Price_real | F25: KRW/Kg | G25: =SUMIFS(Input!$G$85:$N$85,Input!$G$7:$N$7,Calculation!G$7) | H25: =SUMIFS(Input!$G$85:$N$85,Input!$G$7:$N$7,Calculation!H$7) | I25: =SUMIFS(Input!$G$85:$N$85,Input!$G$7:$N$7,Calculation!I$7) | J25: =SUMIFS(Input!$G$85:$N$85,Input!$G$7:$N$7,Calculation!J$7) | K25: =SUMIFS(Input!$G$85:$N$85,Input!$G$7:$N$7,Calculation!K$7) | L25: =SUMIFS(Input!$G$85:$N$85,Input!$G$7:$N$7,Calculation!L$7) | M25: =SUMIFS(Input!$G$85:$N$85,Input!$G$7:$N$7,Calculation!M$7) | N25: =SUMIFS(Input!$G$85:$N$85,Input!$G$7:$N$7,Calculation!N$7)
B26: Industry Growth | F26: % | G26: =SUMIFS(Input!$G$20:$N$20,Input!$G$7:$N$7,Calculation!G$7) | H26: =SUMIFS(Input!$G$20:$N$20,Input!$G$7:$N$7,Calculation!H$7) | I26: =SUMIFS(Input!$G$20:$N$20,Input!$G$7:$N$7,Calculation!I$7) | J26: =SUMIFS(Input!$G$20:$N$20,Input!$G$7:$N$7,Calculation!J$7) | K26: =SUMIFS(Input!$G$20:$N$20,Input!$G$7:$N$7,Calculation!K$7) | L26: =SUMIFS(Input!$G$20:$N$20,Input!$G$7:$N$7,Calculation!L$7) | M26: =SUMIFS(Input!$G$20:$N$20,Input!$G$7:$N$7,Calculation!M$7) | N26: =SUMIFS(Input!$G$20:$N$20,Input!$G$7:$N$7,Calculation!N$7)
B27: Price_Nominal | F27: KRW/Kg | G27: =IFERROR(G25*G26,"") | H27: =IFERROR(H25*H26,"") | I27: =IFERROR(I25*I26,"") | J27: =IFERROR(J25*J26,"") | K27: =IFERROR(J27*K26,"") | L27: =IFERROR(K27*L26,"") | M27: =IFERROR(L27*M26,"") | N27: =IFERROR(M27*N26,"")
B28: Quantity | F28: Kg | G28: =SUMIFS(Input!$G$86:$N$86,Input!$G$7:$N$7,Calculation!G$7) | H28: =SUMIFS(Input!$G$86:$N$86,Input!$G$7:$N$7,Calculation!H$7) | I28: =SUMIFS(Input!$G$86:$N$86,Input!$G$7:$N$7,Calculation!I$7) | J28: =SUMIFS(Input!$G$86:$N$86,Input!$G$7:$N$7,Calculation!J$7) | K28: =SUMIFS(Input!$G$86:$N$86,Input!$G$7:$N$7,Calculation!K$7) | L28: =SUMIFS(Input!$G$86:$N$86,Input!$G$7:$N$7,Calculation!L$7) | M28: =SUMIFS(Input!$G$86:$N$86,Input!$G$7:$N$7,Calculation!M$7) | N28: =SUMIFS(Input!$G$86:$N$86,Input!$G$7:$N$7,Calculation!N$7)
B29: Revenue | F29: KRW mn | G29: =G27*G28/mn | H29: =H27*H28/mn | I29: =I27*I28/mn | J29: =J27*J28/mn | K29: =K27*K28/mn | L29: =L27*L28/mn | M29: =M27*M28/mn | N29: =N27*N28/mn
B31: [Revenue breakdown] - #2
B32: Price_real | F32: KRW/Kg | G32: =SUMIFS(Input!$G$91:$N$91,Input!$G$7:$N$7,Calculation!G$7) | H32: =SUMIFS(Input!$G$91:$N$91,Input!$G$7:$N$7,Calculation!H$7) | I32: =SUMIFS(Input!$G$91:$N$91,Input!$G$7:$N$7,Calculation!I$7) | J32: =SUMIFS(Input!$G$91:$N$91,Input!$G$7:$N$7,Calculation!J$7) | K32: =SUMIFS(Input!$G$91:$N$91,Input!$G$7:$N$7,Calculation!K$7) | L32: =SUMIFS(Input!$G$91:$N$91,Input!$G$7:$N$7,Calculation!L$7) | M32: =SUMIFS(Input!$G$91:$N$91,Input!$G$7:$N$7,Calculation!M$7) | N32: =SUMIFS(Input!$G$91:$N$91,Input!$G$7:$N$7,Calculation!N$7)
B33: Industry Growth | F33: % | G33: =SUMIFS(Input!$G$20:$N$20,Input!$G$7:$N$7,Calculation!G$7) | H33: =SUMIFS(Input!$G$20:$N$20,Input!$G$7:$N$7,Calculation!H$7) | I33: =SUMIFS(Input!$G$20:$N$20,Input!$G$7:$N$7,Calculation!I$7) | J33: =SUMIFS(Input!$G$20:$N$20,Input!$G$7:$N$7,Calculation!J$7) | K33: =SUMIFS(Input!$G$20:$N$20,Input!$G$7:$N$7,Calculation!K$7) | L33: =SUMIFS(Input!$G$20:$N$20,Input!$G$7:$N$7,Calculation!L$7) | M33: =SUMIFS(Input!$G$20:$N$20,Input!$G$7:$N$7,Calculation!M$7) | N33: =SUMIFS(Input!$G$20:$N$20,Input!$G$7:$N$7,Calculation!N$7)
B34: Price_Nominal | F34: KRW/Kg | G34: =IFERROR(G32*G33,"") | H34: =IFERROR(H32*H33,"") | I34: =IFERROR(I32*I33,"") | J34: =IFERROR(J32*J33,"") | K34: =IFERROR(J34*K33,"") | L34: =IFERROR(K34*L33,"") | M34: =IFERROR(L34*M33,"") | N34: =IFERROR(M34*N33,"")
B35: Quantity | F35: Kg | G35: =SUMIFS(Input!$G$92:$N$92,Input!$G$7:$N$7,Calculation!G$7) | H35: =SUMIFS(Input!$G$92:$N$92,Input!$G$7:$N$7,Calculation!H$7) | I35: =SUMIFS(Input!$G$92:$N$92,Input!$G$7:$N$7,Calculation!I$7) | J35: =SUMIFS(Input!$G$92:$N$92,Input!$G$7:$N$7,Calculation!J$7) | K35: =SUMIFS(Input!$G$92:$N$92,Input!$G$7:$N$7,Calculation!K$7) | L35: =SUMIFS(Input!$G$92:$N$92,Input!$G$7:$N$7,Calculation!L$7) | M35: =SUMIFS(Input!$G$92:$N$92,Input!$G$7:$N$7,Calculation!M$7) | N35: =SUMIFS(Input!$G$92:$N$92,Input!$G$7:$N$7,Calculation!N$7)
B36: Revenue | F36: KRW mn | G36: =G34*G35/mn | H36: =H34*H35/mn | I36: =I34*I35/mn | J36: =J34*J35/mn | K36: =K34*K35/mn | L36: =L34*L35/mn | M36: =M34*M35/mn | N36: =N34*N35/mn
B38: [Revenue breakdown] - #3
B39: Price_real | F39: KRW/Kg | G39: =SUMIFS(Input!$G$97:$N$97,Input!$G$7:$N$7,Calculation!G$7) | H39: =SUMIFS(Input!$G$97:$N$97,Input!$G$7:$N$7,Calculation!H$7) | I39: =SUMIFS(Input!$G$97:$N$97,Input!$G$7:$N$7,Calculation!I$7) | J39: =SUMIFS(Input!$G$97:$N$97,Input!$G$7:$N$7,Calculation!J$7) | K39: =SUMIFS(Input!$G$97:$N$97,Input!$G$7:$N$7,Calculation!K$7) | L39: =SUMIFS(Input!$G$97:$N$97,Input!$G$7:$N$7,Calculation!L$7) | M39: =SUMIFS(Input!$G$97:$N$97,Input!$G$7:$N$7,Calculation!M$7) | N39: =SUMIFS(Input!$G$97:$N$97,Input!$G$7:$N$7,Calculation!N$7)
B40: Industry Growth | F40: % | G40: =SUMIFS(Input!$G$20:$N$20,Input!$G$7:$N$7,Calculation!G$7) | H40: =SUMIFS(Input!$G$20:$N$20,Input!$G$7:$N$7,Calculation!H$7) | I40: =SUMIFS(Input!$G$20:$N$20,Input!$G$7:$N$7,Calculation!I$7) | J40: =SUMIFS(Input!$G$20:$N$20,Input!$G$7:$N$7,Calculation!J$7) | K40: =SUMIFS(Input!$G$20:$N$20,Input!$G$7:$N$7,Calculation!K$7) | L40: =SUMIFS(Input!$G$20:$N$20,Input!$G$7:$N$7,Calculation!L$7) | M40: =SUMIFS(Input!$G$20:$N$20,Input!$G$7:$N$7,Calculation!M$7) | N40: =SUMIFS(Input!$G$20:$N$20,Input!$G$7:$N$7,Calculation!N$7)
B41: Price_Nominal | F41: KRW/Kg | G41: =IFERROR(G39*G40,"") | H41: =IFERROR(H39*H40,"") | I41: =IFERROR(I39*I40,"") | J41: =IFERROR(J39*J40,"") | K41: =IFERROR(J41*K40,"") | L41: =IFERROR(K41*L40,"") | M41: =IFERROR(L41*M40,"") | N41: =IFERROR(M41*N40,"")
B42: Quantity | F42: Kg | G42: =SUMIFS(Input!$G$98:$N$98,Input!$G$7:$N$7,Calculation!G$7) | H42: =SUMIFS(Input!$G$98:$N$98,Input!$G$7:$N$7,Calculation!H$7) | I42: =SUMIFS(Input!$G$98:$N$98,Input!$G$7:$N$7,Calculation!I$7) | J42: =SUMIFS(Input!$G$98:$N$98,Input!$G$7:$N$7,Calculation!J$7) | K42: =SUMIFS(Input!$G$98:$N$98,Input!$G$7:$N$7,Calculation!K$7) | L42: =SUMIFS(Input!$G$98:$N$98,Input!$G$7:$N$7,Calculation!L$7) | M42: =SUMIFS(Input!$G$98:$N$98,Input!$G$7:$N$7,Calculation!M$7) | N42: =SUMIFS(Input!$G$98:$N$98,Input!$G$7:$N$7,Calculation!N$7)
B43: Revenue | F43: KRW mn | G43: =G41*G42/mn | H43: =H41*H42/mn | I43: =I41*I42/mn | J43: =J41*J42/mn | K43: =K41*K42/mn | L43: =L41*L42/mn | M43: =M41*M42/mn | N43: =N41*N42/mn
B45: [Revenue breakdown] - #4
B46: Price_real | F46: KRW/Kg | G46: =SUMIFS(Input!$G$103:$N$103,Input!$G$7:$N$7,Calculation!G$7) | H46: =SUMIFS(Input!$G$103:$N$103,Input!$G$7:$N$7,Calculation!H$7) | I46: =SUMIFS(Input!$G$103:$N$103,Input!$G$7:$N$7,Calculation!I$7) | J46: =SUMIFS(Input!$G$103:$N$103,Input!$G$7:$N$7,Calculation!J$7) | K46: =SUMIFS(Input!$G$103:$N$103,Input!$G$7:$N$7,Calculation!K$7) | L46: =SUMIFS(Input!$G$103:$N$103,Input!$G$7:$N$7,Calculation!L$7) | M46: =SUMIFS(Input!$G$103:$N$103,Input!$G$7:$N$7,Calculation!M$7) | N46: =SUMIFS(Input!$G$103:$N$103,Input!$G$7:$N$7,Calculation!N$7)
B47: Industry Growth | F47: % | G47: =SUMIFS(Input!$G$20:$N$20,Input!$G$7:$N$7,Calculation!G$7) | H47: =SUMIFS(Input!$G$20:$N$20,Input!$G$7:$N$7,Calculation!H$7) | I47: =SUMIFS(Input!$G$20:$N$20,Input!$G$7:$N$7,Calculation!I$7) | J47: =SUMIFS(Input!$G$20:$N$20,Input!$G$7:$N$7,Calculation!J$7) | K47: =SUMIFS(Input!$G$20:$N$20,Input!$G$7:$N$7,Calculation!K$7) | L47: =SUMIFS(Input!$G$20:$N$20,Input!$G$7:$N$7,Calculation!L$7) | M47: =SUMIFS(Input!$G$20:$N$20,Input!$G$7:$N$7,Calculation!M$7) | N47: =SUMIFS(Input!$G$20:$N$20,Input!$G$7:$N$7,Calculation!N$7)
B48: Price_Nominal | F48: KRW/Kg | G48: =IFERROR(G46*G47,"") | H48: =IFERROR(H46*H47,"") | I48: =IFERROR(I46*I47,"") | J48: =IFERROR(J46*J47,"") | K48: =IFERROR(J48*K47,"") | L48: =IFERROR(K48*L47,"") | M48: =IFERROR(L48*M47,"") | N48: =IFERROR(M48*N47,"")
B49: Quantity | F49: Kg | G49: =SUMIFS(Input!$G$104:$N$104,Input!$G$7:$N$7,Calculation!G$7) | H49: =SUMIFS(Input!$G$104:$N$104,Input!$G$7:$N$7,Calculation!H$7) | I49: =SUMIFS(Input!$G$104:$N$104,Input!$G$7:$N$7,Calculation!I$7) | J49: =SUMIFS(Input!$G$104:$N$104,Input!$G$7:$N$7,Calculation!J$7) | K49: =SUMIFS(Input!$G$104:$N$104,Input!$G$7:$N$7,Calculation!K$7) | L49: =SUMIFS(Input!$G$104:$N$104,Input!$G$7:$N$7,Calculation!L$7) | M49: =SUMIFS(Input!$G$104:$N$104,Input!$G$7:$N$7,Calculation!M$7) | N49: =SUMIFS(Input!$G$104:$N$104,Input!$G$7:$N$7,Calculation!N$7)
B50: Revenue | F50: KRW mn | G50: =G48*G49/mn | H50: =H48*H49/mn | I50: =I48*I49/mn | J50: =J48*J49/mn | K50: =K48*K49/mn | L50: =L48*L49/mn | M50: =M48*M49/mn | N50: =N48*N49/mn
B52: [Revenue breakdown] - #5
B53: Price_real | F53: KRW/Kg | G53: =SUMIFS(Input!$G$109:$N$109,Input!$G$7:$N$7,Calculation!G$7) | H53: =SUMIFS(Input!$G$109:$N$109,Input!$G$7:$N$7,Calculation!H$7) | I53: =SUMIFS(Input!$G$109:$N$109,Input!$G$7:$N$7,Calculation!I$7) | J53: =SUMIFS(Input!$G$109:$N$109,Input!$G$7:$N$7,Calculation!J$7) | K53: =SUMIFS(Input!$G$109:$N$109,Input!$G$7:$N$7,Calculation!K$7) | L53: =SUMIFS(Input!$G$109:$N$109,Input!$G$7:$N$7,Calculation!L$7) | M53: =SUMIFS(Input!$G$109:$N$109,Input!$G$7:$N$7,Calculation!M$7) | N53: =SUMIFS(Input!$G$109:$N$109,Input!$G$7:$N$7,Calculation!N$7)
B54: Industry Growth | F54: % | G54: =SUMIFS(Input!$G$20:$N$20,Input!$G$7:$N$7,Calculation!G$7) | H54: =SUMIFS(Input!$G$20:$N$20,Input!$G$7:$N$7,Calculation!H$7) | I54: =SUMIFS(Input!$G$20:$N$20,Input!$G$7:$N$7,Calculation!I$7) | J54: =SUMIFS(Input!$G$20:$N$20,Input!$G$7:$N$7,Calculation!J$7) | K54: =SUMIFS(Input!$G$20:$N$20,Input!$G$7:$N$7,Calculation!K$7) | L54: =SUMIFS(Input!$G$20:$N$20,Input!$G$7:$N$7,Calculation!L$7) | M54: =SUMIFS(Input!$G$20:$N$20,Input!$G$7:$N$7,Calculation!M$7) | N54: =SUMIFS(Input!$G$20:$N$20,Input!$G$7:$N$7,Calculation!N$7)
B55: Price_Nominal | F55: KRW/Kg | G55: =IFERROR(G53*G54,"") | H55: =IFERROR(H53*H54,"") | I55: =IFERROR(I53*I54,"") | J55: =IFERROR(J53*J54,"") | K55: =IFERROR(J55*K54,"") | L55: =IFERROR(K55*L54,"") | M55: =IFERROR(L55*M54,"") | N55: =IFERROR(M55*N54,"")
B56: Quantity | F56: Kg | G56: =SUMIFS(Input!$G$110:$N$110,Input!$G$7:$N$7,Calculation!G$7) | H56: =SUMIFS(Input!$G$110:$N$110,Input!$G$7:$N$7,Calculation!H$7) | I56: =SUMIFS(Input!$G$110:$N$110,Input!$G$7:$N$7,Calculation!I$7) | J56: =SUMIFS(Input!$G$110:$N$110,Input!$G$7:$N$7,Calculation!J$7) | K56: =SUMIFS(Input!$G$110:$N$110,Input!$G$7:$N$7,Calculation!K$7) | L56: =SUMIFS(Input!$G$110:$N$110,Input!$G$7:$N$7,Calculation!L$7) | M56: =SUMIFS(Input!$G$110:$N$110,Input!$G$7:$N$7,Calculation!M$7) | N56: =SUMIFS(Input!$G$110:$N$110,Input!$G$7:$N$7,Calculation!N$7)
B57: Revenue | F57: KRW mn | G57: =G55*G56/mn | H57: =H55*H56/mn | I57: =I55*I56/mn | J57: =J55*J56/mn | K57: =K55*K56/mn | L57: =L55*L56/mn | M57: =M55*M56/mn | N57: =N55*N56/mn
B61: COGS
B63: [Total COGS]
B64: [COGS breakdown] - 재료비 (P*Q) | F64: KRW mn | G64: =G77 | H64: =H77 | I64: =I77 | J64: =J77 | K64: =K77 | L64: =L77 | M64: =M77 | N64: =N77
B65: [COGS breakdown] - 인건비 | F65: KRW mn | G65: =G150 | H65: =H150 | I65: =I150 | J65: =J150 | K65: =K150 | L65: =L150 | M65: =M150 | N65: =N150
B66: [COGS breakdown] - 기타경비(변동비) | F66: KRW mn | G66: =G81 | H66: =H81 | I66: =I81 | J66: =J81 | K66: =K81 | L66: =L81 | M66: =M81 | N66: =N81
B67: [COGS breakdown] - 기타경비(고정비) | F67: KRW mn | G67: =G85 | H67: =H85 | I67: =I85 | J67: =J85 | K67: =K85 | L67: =L85 | M67: =M85 | N67: =N85
B68: [COGS breakdown] - 별도 추정- #1 | F68: KRW mn | G68: =G92 | H68: =H92 | I68: =I92 | J68: =J92 | K68: =K92 | L68: =L92 | M68: =M92 | N68: =N92
B69: [COGS breakdown] - 별도 추정- #2 | F69: KRW mn | G69: =G99 | H69: =H99 | I69: =I99 | J69: =J99 | K69: =K99 | L69: =L99 | M69: =M99 | N69: =N99
B70: Total COGS | F70: KRW mn | G70: =SUM(G64:G69) | H70: =SUM(H64:H69) | I70: =SUM(I64:I69) | J70: =SUM(J64:J69) | K70: =SUM(K64:K69) | L70: =SUM(L64:L69) | M70: =SUM(M64:M69) | N70: =SUM(N64:N69)
B72: [COGS breakdown] - 재료비 (P*Q)
B73: Price_real | F73: KRW/Kg | G73: =SUMIFS(Input!$G$119:$N$119,Input!$G$7:$N$7,Calculation!G$7) | H73: =SUMIFS(Input!$G$119:$N$119,Input!$G$7:$N$7,Calculation!H$7) | I73: =SUMIFS(Input!$G$119:$N$119,Input!$G$7:$N$7,Calculation!I$7) | J73: =SUMIFS(Input!$G$119:$N$119,Input!$G$7:$N$7,Calculation!J$7) | K73: =SUMIFS(Input!$G$119:$N$119,Input!$G$7:$N$7,Calculation!K$7) | L73: =SUMIFS(Input!$G$119:$N$119,Input!$G$7:$N$7,Calculation!L$7) | M73: =SUMIFS(Input!$G$119:$N$119,Input!$G$7:$N$7,Calculation!M$7) | N73: =SUMIFS(Input!$G$119:$N$119,Input!$G$7:$N$7,Calculation!N$7)
B74: PPI | F74: % | G74: =SUMIFS(Input!$G$23:$N$23,Input!$G$7:$N$7,Calculation!G$7) | H74: =SUMIFS(Input!$G$23:$N$23,Input!$G$7:$N$7,Calculation!H$7) | I74: =SUMIFS(Input!$G$23:$N$23,Input!$G$7:$N$7,Calculation!I$7) | J74: =SUMIFS(Input!$G$23:$N$23,Input!$G$7:$N$7,Calculation!J$7) | K74: =SUMIFS(Input!$G$23:$N$23,Input!$G$7:$N$7,Calculation!K$7) | L74: =SUMIFS(Input!$G$23:$N$23,Input!$G$7:$N$7,Calculation!L$7) | M74: =SUMIFS(Input!$G$23:$N$23,Input!$G$7:$N$7,Calculation!M$7) | N74: =SUMIFS(Input!$G$23:$N$23,Input!$G$7:$N$7,Calculation!N$7)
B75: Price_Nominal | F75: KRW/Kg | G75: =IFERROR(G73*G74,"") | H75: =IFERROR(H73*H74,"") | I75: =IFERROR(I73*I74,"") | J75: =IFERROR(J73*J74,"") | K75: =IFERROR(J75*K74,"") | L75: =IFERROR(K75*L74,"") | M75: =IFERROR(L75*M74,"") | N75: =IFERROR(M75*N74,"")
B76: Quantity | F76: Kg | G76: =SUMIFS(Input!$G$120:$N$120,Input!$G$7:$N$7,Calculation!G$7) | H76: =SUMIFS(Input!$G$120:$N$120,Input!$G$7:$N$7,Calculation!H$7) | I76: =SUMIFS(Input!$G$120:$N$120,Input!$G$7:$N$7,Calculation!I$7) | J76: =SUMIFS(Input!$G$120:$N$120,Input!$G$7:$N$7,Calculation!J$7) | K76: =SUMIFS(Input!$G$120:$N$120,Input!$G$7:$N$7,Calculation!K$7) | L76: =SUMIFS(Input!$G$120:$N$120,Input!$G$7:$N$7,Calculation!L$7) | M76: =SUMIFS(Input!$G$120:$N$120,Input!$G$7:$N$7,Calculation!M$7) | N76: =SUMIFS(Input!$G$120:$N$120,Input!$G$7:$N$7,Calculation!N$7)
B77: 재료비 | F77: KRW mn | G77: =G75*G76/mn | H77: =H75*H76/mn | I77: =I75*I76/mn | J77: =J75*J76/mn | K77: =K75*K76/mn | L77: =L75*L76/mn | M77: =M75*M76/mn | N77: =N75*N76/mn
B79: [COGS breakdown] - 기타경비(변동비)
B80: % of revenue | E80: =Input!E126 | F80: % | J80: =$E80 | K80: =$E80 | L80: =$E80 | M80: =$E80 | N80: =$E80
B81: 기타경비 | F81: KRW mn | J81: =J$21*J80 | K81: =K$21*K80 | L81: =L$21*L80 | M81: =M$21*M80 | N81: =N$21*N80
B83: [COGS breakdown] - 기타경비(고정비)
B84: PPI | F84: % | G84: =SUMIFS(Input!$G$23:$N$23,Input!$G$7:$N$7,Calculation!G$7) | H84: =SUMIFS(Input!$G$23:$N$23,Input!$G$7:$N$7,Calculation!H$7) | I84: =SUMIFS(Input!$G$23:$N$23,Input!$G$7:$N$7,Calculation!I$7) | J84: =SUMIFS(Input!$G$23:$N$23,Input!$G$7:$N$7,Calculation!J$7) | K84: =SUMIFS(Input!$G$23:$N$23,Input!$G$7:$N$7,Calculation!K$7) | L84: =SUMIFS(Input!$G$23:$N$23,Input!$G$7:$N$7,Calculation!L$7) | M84: =SUMIFS(Input!$G$23:$N$23,Input!$G$7:$N$7,Calculation!M$7) | N84: =SUMIFS(Input!$G$23:$N$23,Input!$G$7:$N$7,Calculation!N$7)
B85: 기타경비 | E85: =Input!E131 | F85: KRW mn | J85: =E$85*J84 | K85: =J$85*K84 | L85: =K$85*L84 | M85: =L$85*M84 | N85: =M$85*N84
B87: [COGS breakdown] - 별도 추정- #1
B88: Price_real | F88: KRW/Kg | G88: =SUMIFS(Input!$G$136:$N$136,Input!$G$7:$N$7,Calculation!G$7) | H88: =SUMIFS(Input!$G$136:$N$136,Input!$G$7:$N$7,Calculation!H$7) | I88: =SUMIFS(Input!$G$136:$N$136,Input!$G$7:$N$7,Calculation!I$7) | J88: =SUMIFS(Input!$G$136:$N$136,Input!$G$7:$N$7,Calculation!J$7) | K88: =SUMIFS(Input!$G$136:$N$136,Input!$G$7:$N$7,Calculation!K$7) | L88: =SUMIFS(Input!$G$136:$N$136,Input!$G$7:$N$7,Calculation!L$7) | M88: =SUMIFS(Input!$G$136:$N$136,Input!$G$7:$N$7,Calculation!M$7) | N88: =SUMIFS(Input!$G$136:$N$136,Input!$G$7:$N$7,Calculation!N$7)
B89: PPI | F89: % | G89: =SUMIFS(Input!$G$23:$N$23,Input!$G$7:$N$7,Calculation!G$7) | H89: =SUMIFS(Input!$G$23:$N$23,Input!$G$7:$N$7,Calculation!H$7) | I89: =SUMIFS(Input!$G$23:$N$23,Input!$G$7:$N$7,Calculation!I$7) | J89: =SUMIFS(Input!$G$23:$N$23,Input!$G$7:$N$7,Calculation!J$7) | K89: =SUMIFS(Input!$G$23:$N$23,Input!$G$7:$N$7,Calculation!K$7) | L89: =SUMIFS(Input!$G$23:$N$23,Input!$G$7:$N$7,Calculation!L$7) | M89: =SUMIFS(Input!$G$23:$N$23,Input!$G$7:$N$7,Calculation!M$7) | N89: =SUMIFS(Input!$G$23:$N$23,Input!$G$7:$N$7,Calculation!N$7)
B90: Price_Nominal | F90: KRW/Kg | G90: =IFERROR(G88*G89,"") | H90: =IFERROR(H88*H89,"") | I90: =IFERROR(I88*I89,"") | J90: =IFERROR(J88*J89,"") | K90: =IFERROR(J90*K89,"") | L90: =IFERROR(K90*L89,"") | M90: =IFERROR(L90*M89,"") | N90: =IFERROR(M90*N89,"")
B91: Quantity | F91: Kg | G91: =SUMIFS(Input!$G$137:$N$137,Input!$G$7:$N$7,Calculation!G$7) | H91: =SUMIFS(Input!$G$137:$N$137,Input!$G$7:$N$7,Calculation!H$7) | I91: =SUMIFS(Input!$G$137:$N$137,Input!$G$7:$N$7,Calculation!I$7) | J91: =SUMIFS(Input!$G$137:$N$137,Input!$G$7:$N$7,Calculation!J$7) | K91: =SUMIFS(Input!$G$137:$N$137,Input!$G$7:$N$7,Calculation!K$7) | L91: =SUMIFS(Input!$G$137:$N$137,Input!$G$7:$N$7,Calculation!L$7) | M91: =SUMIFS(Input!$G$137:$N$137,Input!$G$7:$N$7,Calculation!M$7) | N91: =SUMIFS(Input!$G$137:$N$137,Input!$G$7:$N$7,Calculation!N$7)
B92: 별도 추정 | F92: KRW mn | G92: =G90*G91/mn | H92: =H90*H91/mn | I92: =I90*I91/mn | J92: =J90*J91/mn | K92: =K90*K91/mn | L92: =L90*L91/mn | M92: =M90*M91/mn | N92: =N90*N91/mn
B94: [COGS breakdown] - 별도 추정- #2
B95: Price_real | F95: KRW/Kg | G95: =SUMIFS(Input!$G$142:$N$142,Input!$G$7:$N$7,Calculation!G$7) | H95: =SUMIFS(Input!$G$142:$N$142,Input!$G$7:$N$7,Calculation!H$7) | I95: =SUMIFS(Input!$G$142:$N$142,Input!$G$7:$N$7,Calculation!I$7) | J95: =SUMIFS(Input!$G$142:$N$142,Input!$G$7:$N$7,Calculation!J$7) | K95: =SUMIFS(Input!$G$142:$N$142,Input!$G$7:$N$7,Calculation!K$7) | L95: =SUMIFS(Input!$G$142:$N$142,Input!$G$7:$N$7,Calculation!L$7) | M95: =SUMIFS(Input!$G$142:$N$142,Input!$G$7:$N$7,Calculation!M$7) | N95: =SUMIFS(Input!$G$142:$N$142,Input!$G$7:$N$7,Calculation!N$7)
B96: PPI | F96: % | G96: =SUMIFS(Input!$G$23:$N$23,Input!$G$7:$N$7,Calculation!G$7) | H96: =SUMIFS(Input!$G$23:$N$23,Input!$G$7:$N$7,Calculation!H$7) | I96: =SUMIFS(Input!$G$23:$N$23,Input!$G$7:$N$7,Calculation!I$7) | J96: =SUMIFS(Input!$G$23:$N$23,Input!$G$7:$N$7,Calculation!J$7) | K96: =SUMIFS(Input!$G$23:$N$23,Input!$G$7:$N$7,Calculation!K$7) | L96: =SUMIFS(Input!$G$23:$N$23,Input!$G$7:$N$7,Calculation!L$7) | M96: =SUMIFS(Input!$G$23:$N$23,Input!$G$7:$N$7,Calculation!M$7) | N96: =SUMIFS(Input!$G$23:$N$23,Input!$G$7:$N$7,Calculation!N$7)
B97: Price_Nominal | F97: KRW/Kg | G97: =IFERROR(G95*G96,"") | H97: =IFERROR(H95*H96,"") | I97: =IFERROR(I95*I96,"") | J97: =IFERROR(J95*J96,"") | K97: =IFERROR(J97*K96,"") | L97: =IFERROR(K97*L96,"") | M97: =IFERROR(L97*M96,"") | N97: =IFERROR(M97*N96,"")
B98: Quantity | F98: Kg | G98: =SUMIFS(Input!$G$143:$N$143,Input!$G$7:$N$7,Calculation!G$7) | H98: =SUMIFS(Input!$G$143:$N$143,Input!$G$7:$N$7,Calculation!H$7) | I98: =SUMIFS(Input!$G$143:$N$143,Input!$G$7:$N$7,Calculation!I$7) | J98: =SUMIFS(Input!$G$143:$N$143,Input!$G$7:$N$7,Calculation!J$7) | K98: =SUMIFS(Input!$G$143:$N$143,Input!$G$7:$N$7,Calculation!K$7) | L98: =SUMIFS(Input!$G$143:$N$143,Input!$G$7:$N$7,Calculation!L$7) | M98: =SUMIFS(Input!$G$143:$N$143,Input!$G$7:$N$7,Calculation!M$7) | N98: =SUMIFS(Input!$G$143:$N$143,Input!$G$7:$N$7,Calculation!N$7)
B99: 별도 추정 | F99: KRW mn | G99: =G97*G98/mn | H99: =H97*H98/mn | I99: =I97*I98/mn | J99: =J97*J98/mn | K99: =K97*K98/mn | L99: =L97*L98/mn | M99: =M97*M98/mn | N99: =N97*N98/mn
B104: SG&A
B106: [Total COGS]
B107: [SG&A breakdown] - 인건비 | F107: KRW mn | G107: =G151 | H107: =H151 | I107: =I151 | J107: =J151 | K107: =K151 | L107: =L151 | M107: =M151 | N107: =N151
B108: [SG&A breakdown] - Variable cost #1 | F108: KRW mn | G108: =G117 | H108: =H117 | I108: =I117 | J108: =J117 | K108: =K117 | L108: =L117 | M108: =M117 | N108: =N117
B109: [SG&A breakdown] - Variable cost #2 | F109: KRW mn | G109: =G121 | H109: =H121 | I109: =I121 | J109: =J121 | K109: =K121 | L109: =L121 | M109: =M121 | N109: =N121
B110: [SG&A breakdown] - Variable cost #3 | F110: KRW mn | G110: =G125 | H110: =H125 | I110: =I125 | J110: =J125 | K110: =K125 | L110: =L125 | M110: =M125 | N110: =N125
B111: [SG&A breakdown] - Fixed cost | F111: KRW mn | G111: =G129 | H111: =H129 | I111: =I129 | J111: =J129 | K111: =K129 | L111: =L129 | M111: =M129 | N111: =N129
B112: [SG&A breakdown] - 별도 추정 | F112: KRW mn | G112: =G136 | H112: =H136 | I112: =I136 | J112: =J136 | K112: =K136 | L112: =L136 | M112: =M136 | N112: =N136
B113: Total COGS | F113: KRW mn | G113: =SUM(G107:G112) | H113: =SUM(H107:H112) | I113: =SUM(I107:I112) | J113: =SUM(J107:J112) | K113: =SUM(K107:K112) | L113: =SUM(L107:L112) | M113: =SUM(M107:M112) | N113: =SUM(N107:N112)
B115: [SG&A breakdown] - Variable cost #1
B116: % of revenue | E116: =Input!E153 | F116: % | J116: =$E116 | K116: =$E116 | L116: =$E116 | M116: =$E116 | N116: =$E116
B117: 판관 변동비 | F117: KRW mn | J117: =J$21*J116 | K117: =K$21*K116 | L117: =L$21*L116 | M117: =M$21*M116 | N117: =N$21*N116
B119: [SG&A breakdown] - Variable cost #2
B120: % of revenue | E120: =Input!E158 | F120: % | J120: =$E120 | K120: =$E120 | L120: =$E120 | M120: =$E120 | N120: =$E120
B121: 판관 변동비 | F121: KRW mn | J121: =J$21*J120 | K121: =K$21*K120 | L121: =L$21*L120 | M121: =M$21*M120 | N121: =N$21*N120
B123: [SG&A breakdown] - Variable cost #3
B124: % of revenue | E124: =Input!E163 | F124: % | J124: =$E124 | K124: =$E124 | L124: =$E124 | M124: =$E124 | N124: =$E124
B125: 판관 변동비 | F125: KRW mn | J125: =J$21*J124 | K125: =K$21*K124 | L125: =L$21*L124 | M125: =M$21*M124 | N125: =N$21*N124
B127: [SG&A breakdown] - Fixed cost
...

Sheet DCF
B1: =Legend!D2
B2: DCF
B4: Time Period
B6: Actual/Forecast | G6: =Input!G6 | H6: =Input!H6 | I6: =Input!I6 | J6: =Input!J6 | K6: =Input!K6 | L6: =Input!L6 | M6: =Input!M6 | N6: =Input!N6 | O6: =Input!O6
B7: Period Start | G7: =Input!G7 | H7: =Input!H7 | I7: =Input!I7 | J7: =Input!J7 | K7: =Input!K7 | L7: =Input!L7 | M7: =Input!M7 | N7: =Input!N7 | O7: TV
B8: Period End | G8: =Input!G8 | H8: =Input!H8 | I8: =Input!I8 | J8: =Input!J8 | K8: =Input!K8 | L8: =Input!L8 | M8: =Input!M8 | N8: =Input!N8
B9: Month | G9: =Input!G9 | H9: =Input!H9 | I9: =Input!I9 | J9: =Input!J9 | K9: =Input!K9 | L9: =Input!L9 | M9: =Input!M9 | N9: =Input!N9
B10: Year | G10: =Input!G10 | H10: =Input!H10 | I10: =Input!I10 | J10: =Input!J10 | K10: =Input!K10 | L10: =Input!L10 | M10: =Input!M10 | N10: =Input!N10
B11: Days | G11: =Input!G11 | H11: =Input!H11 | I11: =Input!I11 | J11: =Input!J11 | K11: =Input!K11 | L11: =Input!L11 | M11: =Input!M11 | N11: =Input!N11
B13: DCF
B15: WACC | E15: =Input!E18
B16: Perptual Growth | E16: =Input!E19
G18: Actual | J18: Forecast
B19: Currency: KRW mn | G19: ="FY"&G10 | H19: ="FY"&H10 | I19: ="FY"&I10 | J19: ="FY"&J10 | K19: ="FY"&K10 | L19: ="FY"&L10 | M19: ="FY"&M10 | N19: ="FY"&N10 | O19: TV
B20: Revenue | G20: =Input!G28 | H20: =Input!H28 | I20: =Input!I28 | J20: =Calculation!J21 | K20: =Calculation!K21 | L20: =Calculation!L21 | M20: =Calculation!M21 | N20: =Calculation!N21 | O20: =N20*(1+$E$16)
B21: Growth% | H21: =H20/G20-1 | I21: =I20/H20-1 | J21: =J20/I20-1 | K21: =K20/J20-1 | L21: =L20/K20-1 | M21: =M20/L20-1 | N21: =N20/M20-1 | O21: =O20/N20-1
B22: COGS | G22: =Input!G29 | H22: =Input!H29 | I22: =Input!I29 | J22: =Calculation!J70 | K22: =Calculation!K70 | L22: =Calculation!L70 | M22: =Calculation!M70 | N22: =Calculation!N70 | O22: =N22*(1+$E$16)
B23: Gross profit | G23: =G20-G22 | H23: =H20-H22 | I23: =I20-I22 | J23: =J20-J22 | K23: =K20-K22 | L23: =L20-L22 | M23: =M20-M22 | N23: =N20-N22 | O23: =O20-O22
B24: Gross margin | G24: =G23/G20 | H24: =H23/H20 | I24: =I23/I20 | J24: =J23/J20 | K24: =K23/K20 | L24: =L23/L20 | M24: =M23/M20 | N24: =N23/N20 | O24: =O23/O20
B25: SG&A | G25: =Input!G35 | H25: =Input!H35 | I25: =Input!I35 | J25: =Calculation!J113 | K25: =Calculation!K113 | L25: =Calculation!L113 | M25: =Calculation!M113 | N25: =Calculation!N113 | O25: =N25*(1+$E$16)
B26: SG&A% | G26: =G25/G20 | H26: =H25/H20 | I26: =I25/I20 | J26: =J25/J20 | K26: =K25/K20 | L26: =L25/L20 | M26: =M25/M20 | N26: =N25/N20 | O26: =O25/O20
B27: EBIT | G27: =G23-G25 | H27: =H23-H25 | I27: =I23-I25 | J27: =J23-J25 | K27: =K23-K25 | L27: =L23-L25 | M27: =M23-M25 | N27: =N23-N25 | O27: =O23-O25
B28: EBIT% | G28: =G27/G20 | H28: =H27/H20 | I28: =I27/I20 | J28: =J27/J20 | K28: =K27/K20 | L28: =L27/L20 | M28: =M27/M20 | N28: =N27/N20 | O28: =O27/O20
B29: Dep&Amor. | G29: =Input!G42 | H29: =Input!H42 | I29: =Input!I42
B30: EBITDA | G30: =G27+G29 | H30: =H27+H29 | I30: =I27+I29 | J30: =J27+J29 | K30: =K27+K29 | L30: =L27+L29 | M30: =M27+M29 | N30: =N27+N29 | O30: =O27+O29
B31: EBITDA % | G31: =G30/G20 | H31: =H30/H23 | I31: =I30/I23 | J31: =J30/J23 | K31: =K30/K23 | L31: =L30/L23 | M31: =M30/M23 | N31: =N30/N23 | O31: =O30/O23
B32: CIT | G32: =Input!G52 | H32: =Input!H52 | I32: =Input!I52 | J32: =IF(J27<=200, J27*0.1*1.1, IF(J27<=30000, ((J27-200)*0.2 + 200*0.1)*1.1, IF(J27<=300000, ((J27-30000)*0.22 + (30000-200)*0.2 + 200*0.1)*1.1, ((J27-300000)*0.24 + (300000-30000)*0.22 + (30000-200)*0.2 + 200*0.1)*1.1))) | K32: =IF(K27<=200, K27*0.1*1.1, IF(K27<=30000, ((K27-200)*0.2 + 200*0.1)*1.1, IF(K27<=300000, ((K27-30000)*0.22 + (30000-200)*0.2 + 200*0.1)*1.1, ((K27-300000)*0.24 + (300000-30000)*0.22 + (30000-200)*0.2 + 200*0.1)*1.1))) | L32: =IF(L27<=200, L27*0.1*1.1, IF(L27<=30000, ((L27-200)*0.2 + 200*0.1)*1.1, IF(L27<=300000, ((L27-30000)*0.22 + (30000-200)*0.2 + 200*0.1)*1.1, ((L27-300000)*0.24 + (300000-30000)*0.22 + (30000-200)*0.2 + 200*0.1)*1.1))) | M32: =IF(M27<=200, M27*0.1*1.1, IF(M27<=30000, ((M27-200)*0.2 + 200*0.1)*1.1, IF(M27<=300000, ((M27-30000)*0.22 + (30000-200)*0.2 + 200*0.1)*1.1, ((M27-300000)*0.24 + (300000-30000)*0.22 + (30000-200)*0.2 + 200*0.1)*1.1))) | N32: =IF(N27<=200, N27*0.1*1.1, IF(N27<=30000, ((N27-200)*0.2 + 200*0.1)*1.1, IF(N27<=300000, ((N27-30000)*0.22 + (30000-200)*0.2 + 200*0.1)*1.1, ((N27-300000)*0.24 + (300000-30000)*0.22 + (30000-200)*0.2 + 200*0.1)*1.1))) | O32: =IF(O27<=200, O27*0.1*1.1, IF(O27<=30000, ((O27-200)*0.2 + 200*0.1)*1.1, IF(O27<=300000, ((O27-30000)*0.22 + (30000-200)*0.2 + 200*0.1)*1.1, ((O27-300000)*0.24 + (300000-30000)*0.22 + (30000-200)*0.2 + 200*0.1)*1.1)))
B33: NOPLAT | G33: =G30-G32 | H33: =H30-H32 | I33: =I30-I32 | J33: =J30-J32 | K33: =K30-K32 | L33: =L30-L32 | M33: =M30-M32 | N33: =N30-N32 | O33: =O30-O32
B34: Dep&Amor. | G34: =G29 | H34: =H29 | I34: =I29
B35: △Net working capital | G35: =Input!G203 | H35: =Input!H203 | I35: =Input!I203 | J35: =Calculation!J170 | K35: =Calculation!K170 | L35: =Calculation!L170 | M35: =Calculation!M170 | N35: =Calculation!N170 | O35: =Calculation!O170
B36: CAPEX
B37: Free cash flow | G37: =SUM(G33:G36) | H37: =SUM(H33:H36) | I37: =SUM(I33:I36) | J37: =SUM(J33:J36) | K37: =SUM(K33:K36) | L37: =SUM(L33:L36) | M37: =SUM(M33:M36) | N37: =SUM(N33:N36) | O37: =SUM(O33:O36)
B38: Discount period | J38: =(J8-Input!E15)/DCF!J11/2 | K38: =J38+1 | L38: =K38+1 | M38: =L38+1 | N38: =M38+1 | O38: =N38
B39: PV factor | J39: =1/(1+$E$15)^DCF!J38 | K39: =1/(1+$E$15)^DCF!K38 | L39: =1/(1+$E$15)^DCF!L38 | M39: =1/(1+$E$15)^DCF!M38 | N39: =1/(1+$E$15)^DCF!N38 | O39: =1/(1+$E$15)^DCF!O38
B40: PV of FCF | J40: =J37*J39 | K40: =K37*K39 | L40: =L37*L39 | M40: =M37*M39 | N40: =N37*N39 | O40: =O37*O39
B41: Operating value | O41: =SUM(J40:O40)
B42: Non-operating assets | O42: =Input!I253
B43: Enterprise value | O43: =O41+O42
B44: Net debt | O44: =Input!I248
B45: Equity value (100%) | O45: =O43-O44
B46: 지분율
B47: Equity value | O47: =O45*O46
B49: Sensitivity
L51: Perpetual growth rate
J52: KRW mn | K52: =O45 | L52: 0.005 | M52: 0.01 | N52: 0.015
J53: WACC | K53: 0.09 | L53: 2429.0533 | M53: 2431.0371 | N53: 2433.0208
K54: 0.1 | L54: 2363.2933 | M54: 2365.1972 | N54: 2367.101
K55: 0.11 | L55: 2300.1948 | M55: 2302.0227 | N55: 2303.8505
B57: Profit & Loss
G59: Actual | J59: Forecast
B60: Currency: KRW mn | G60: ="FY"&G10 | H60: ="FY"&H10 | I60: ="FY"&I10 | J60: ="FY"&J10 | K60: ="FY"&K10 | L60: ="FY"&L10 | M60: ="FY"&M10 | N60: ="FY"&N10
B61: Revenue | G61: =G20 | H61: =H20 | I61: =I20 | J61: =J20 | K61: =K20 | L61: =L20 | M61: =M20 | N61: =N20
B62: Growth% | G62: =G21 | H62: =H21 | I62: =I21 | J62: =J21 | K62: =K21 | L62: =L21 | M62: =M21 | N62: =N21
B63: COGS | G63: =G22 | H63: =H22 | I63: =I22 | J63: =J22 | K63: =K22 | L63: =L22 | M63: =M22 | N63: =N22
B64: Gross profit | G64: =G23 | H64: =H23 | I64: =I23 | J64: =J23 | K64: =K23 | L64: =L23 | M64: =M23 | N64: =N23
B65: Gross margin | G65: =G24 | H65: =H24 | I65: =I24 | J65: =J24 | K65: =K24 | L65: =L24 | M65: =M24 | N65: =N24
B66: SG&A | G66: =G25 | H66: =H25 | I66: =I25 | J66: =J25 | K66: =K25 | L66: =L25 | M66: =M25 | N66: =N25
B67: SG&A% | G67: =G26 | H67: =H26 | I67: =I26 | J67: =J26 | K67: =K26 | L67: =L26 | M67: =M26 | N67: =N26
B68: EBIT | G68: =G27 | H68: =H27 | I68: =I27 | J68: =J27 | K68: =K27 | L68: =L27 | M68: =M27 | N68: =N27
B69: EBIT% | G69: =G28 | H69: =H28 | I69: =I28 | J69: =J28 | K69: =K28 | L69: =L28 | M69: =M28 | N69: =N28
B70: Dep&Amor. | G70: =G29 | H70: =H29 | I70: =I29 | J70: =J29 | K70: =K29 | L70: =L29 | M70: =M29 | N70: =N29
B71: EBITDA | G71: =G30 | H71: =H30 | I71: =I30 | J71: =J30 | K71: =K30 | L71: =L30 | M71: =M30 | N71: =N30
B72: EBITDA % | G72: =G31 | H72: =H31 | I72: =I31 | J72: =J31 | K72: =K31 | L72: =L31 | M72: =M31 | N72: =N31
B73: OOI/OOE | G73: =G74+G75-G76-G77 | H73: =H74+H75-H76-H77 | I73: =I74+I75-I76-I77 | J73: =J74+J75-J76-J77 | K73: =K74+K75-K76-K77 | L73: =L74+L75-L76-L77 | M73: =M74+M75-M76-M77 | N73: =N74+N75-N76-N77
B74: 이자손익 | G74: =Input!G46 | H74: =Input!H46 | I74: =Input!I46 | J74: =Calculation!J177 | K74: =Calculation!K177 | L74: =Calculation!L177 | M74: =Calculation!M177 | N74: =Calculation!N177
B75: 기타 | G75: =Input!G47 | H75: =Input!H47 | I75: =Input!I47 | J75: =Calculation!J178 | K75: =Calculation!K178 | L75: =Calculation!L178 | M75: =Calculation!M178 | N75: =Calculation!N178
B76: 이자비용 | G76: =Input!G49 | H76: =Input!H49 | I76: =Input!I49 | J76: =Calculation!J181 | K76: =Calculation!K181 | L76: =Calculation!L181 | M76: =Calculation!M181 | N76: =Calculation!N181
B77: 기타 | G77: =Input!G50 | H77: =Input!H50 | I77: =Input!I50 | J77: =Calculation!J182 | K77: =Calculation!K182 | L77: =Calculation!L182 | M77: =Calculation!M182 | N77: =Calculation!N182
B78: PBT | G78: =G68-G73 | H78: =H68-H73 | I78: =I68-I73 | J78: =J68-J73 | K78: =K68-K73 | L78: =L68-L73 | M78: =M68-M73 | N78: =N68-N73
B79: CIT | G79: =Input!G52 | H79: =Input!H52 | I79: =Input!I52 | J79: =J32 | K79: =K32 | L79: =L32 | M79: =M32 | N79: =N32
B80: Net income | G80: =G78-G79 | H80: =H78-H79 | I80: =I78-I79 | J80: =J78-J79 | K80: =K78-K79 | L80: =L78-L79 | M80: =M78-M79 | N80: =N78-N79
B82: Balance Sheet
G84: Actual | J84: Forecast
B85: Currency: KRW mn | G85: ="Dec"&G10 | H85: ="Dec"&H10 | I85: ="Dec"&I10 | J85: ="Dec"&J10 | K85: ="Dec"&K10 | L85: ="Dec"&L10 | M85: ="Dec"&M10 | N85: ="Dec"&N10
B86: 유동자산 | G86: =SUM(G87:G90) | H86: =SUM(H87:H90) | I86: =SUM(I87:I90) | J86: =SUM(J87:J90) | K86: =SUM(K87:K90) | L86: =SUM(L87:L90) | M86: =SUM(M87:M90) | N86: =SUM(N87:N90)
B87: 현금및현금성자산 | G87: =Input!G57 | H87: =Input!H57 | I87: =Input!I57 | J87: =J129 | K87: =K129 | L87: =L129 | M87: =M129 | N87: =N129
B88: 매출채권 | G88: =Input!G58 | H88: =Input!H58 | I88: =Input!I58 | J88: =Calculation!J165 | K88: =Calculation!K165 | L88: =Calculation!L165 | M88: =Calculation!M165 | N88: =Calculation!N165
B89: 재고자산 | G89: =Input!G59 | H89: =Input!H59 | I89: =Input!I59 | J89: =Calculation!J166 | K89: =Calculation!K166 | L89: =Calculation!L166 | M89: =Calculation!M166 | N89: =Calculation!N166
B90: 기타유동자산 | G90: =Input!G60 | H90: =Input!H60 | I90: =Input!I60 | J90: =I90 | K90: =J90 | L90: =K90 | M90: =L90 | N90: =M90
B91: 비유동자산 | G91: =SUM(G92:G96) | H91: =SUM(H92:H96) | I91: =SUM(I92:I96) | J91: =SUM(J92:J96) | K91: =SUM(K92:K96) | L91: =SUM(L92:L96) | M91: =SUM(M92:M96) | N91: =SUM(N92:N96)
B92: 유형자산 | G92: =Input!G62 | H92: =Input!H62 | I92: =Input!I62 | J92: =I92 | K92: =J92 | L92: =K92 | M92: =L92 | N92: =M92
B93: 무형자산 | G93: =Input!G63 | H93: =Input!H63 | I93: =Input!I63 | J93: =I93 | K93: =J93 | L93: =K93 | M93: =L93 | N93: =M93
B94: 투자자산 | G94: =Input!G64 | H94: =Input!H64 | I94: =Input!I64 | J94: =I94 | K94: =J94 | L94: =K94 | M94: =L94 | N94: =M94
B95: 지분법투자주식 | G95: =Input!G65 | H95: =Input!H65 | I95: =Input!I65 | J95: =I95 | K95: =J95 | L95: =K95 | M95: =L95 | N95: =M95
B96: 기타비유동자산 | G96: =Input!G66 | H96: =Input!H66 | I96: =Input!I66 | J96: =I96 | K96: =J96 | L96: =K96 | M96: =L96 | N96: =M96
B97: 총자산 | G97: =SUM(G91,G86) | H97: =SUM(H91,H86) | I97: =SUM(I91,I86) | J97: =SUM(J91,J86) | K97: =SUM(K91,K86) | L97: =SUM(L91,L86) | M97: =SUM(M91,M86) | N97: =SUM(N91,N86)
B98: 유동부채 | G98: =SUM(G99:G102) | H98: =SUM(H99:H102) | I98: =SUM(I99:I102) | J98: =SUM(J99:J102) | K98: =SUM(K99:K102) | L98: =SUM(L99:L102) | M98: =SUM(M99:M102) | N98: =SUM(N99:N102)
B99: 매입채무 | G99: =Input!G69 | H99: =Input!H69 | I99: =Input!I69 | J99: =Calculation!J168 | K99: =Calculation!K168 | L99: =Calculation!L168 | M99: =Calculation!M168 | N99: =Calculation!N168
B100: 미지급금 | G100: =Input!G70 | H100: =Input!H70 | I100: =Input!I70 | J100: =I100 | K100: =J100 | L100: =K100 | M100: =L100 | N100: =M100
B101: 단기차입금 | G101: =Input!G71 | H101: =Input!H71 | I101: =Input!I71 | J101: =Calculation!J188 | K101: =Calculation!K188 | L101: =Calculation!L188 | M101: =Calculation!M188 | N101: =Calculation!N188
B102: 기타유동부채 | G102: =Input!G72 | H102: =Input!H72 | I102: =Input!I72 | J102: =I102 | K102: =J102 | L102: =K102 | M102: =L102 | N102: =M102
B103: 비유동부채 | G103: =SUM(G104:G107) | H103: =SUM(H104:H107) | I103: =SUM(I104:I107) | J103: =SUM(J104:J107) | K103: =SUM(K104:K107) | L103: =SUM(L104:L107) | M103: =SUM(M104:M107) | N103: =SUM(N104:N107)
B104: 장기차입금 | G104: =Input!G74 | H104: =Input!H74 | I104: =Input!I74 | J104: =Calculation!J194 | K104: =Calculation!K194 | L104: =Calculation!L194 | M104: =Calculation!M194 | N104: =Calculation!N194
B105: 사채 | G105: =Input!G75 | H105: =Input!H75 | I105: =Input!I75 | J105: =Calculation!J200 | K105: =Calculation!K200 | L105: =Calculation!L200 | M105: =Calculation!M200 | N105: =Calculation!N200
B106: 퇴직급여충당부채 | G106: =Input!G76 | H106: =Input!H76 | I106: =Input!I76 | J106: =I106 | K106: =J106 | L106: =K106 | M106: =L106 | N106: =M106
B107: 기타비유동부채 | G107: =Input!G77 | H107: =Input!H77 | I107: =Input!I77 | J107: =I107 | K107: =J107 | L107: =K107 | M107: =L107 | N107: =M107
B108: 총부채 | G108: =SUM(G103,G98) | H108: =SUM(H103,H98) | I108: =SUM(I103,I98) | J108: =SUM(J103,J98) | K108: =SUM(K103,K98) | L108: =SUM(L103,L98) | M108: =SUM(M103,M98) | N108: =SUM(N103,N98)
B109: 순자산 | G109: =G97-G108 | H109: =H97-H108 | I109: =I97-I108 | J109: =J97-J108 | K109: =K97-K108 | L109: =L97-L108 | M109: =M97-M108 | N109: =N97-N108
B112: CashFlow
G114: Actual | J114: Forecast
...

Sheet WACC
B1: =Legend!D2
B2: WACC Analysis
B4: Time Period
B6: Actual/Forecast | G6: =Input!G6 | H6: =Input!H6 | I6: =Input!I6 | J6: =Input!J6 | K6: =Input!K6 | L6: =Input!L6 | M6: =Input!M6 | N6: =Input!N6 | O6: =Input!O6
B7: Period Start | G7: =Input!G7 | H7: =Input!H7 | I7: =Input!I7 | J7: =Input!J7 | K7: =Input!K7 | L7: =Input!L7 | M7: =Input!M7 | N7: =Input!N7 | O7: TV
B8: Period End | G8: =Input!G8 | H8: =Input!H8 | I8: =Input!I8 | J8: =Input!J8 | K8: =Input!K8 | L8: =Input!L8 | M8: =Input!M8 | N8: =Input!N8
B9: Month | G9: =Input!G9 | H9: =Input!H9 | I9: =Input!I9 | J9: =Input!J9 | K9: =Input!K9 | L9: =Input!L9 | M9: =Input!M9 | N9: =Input!N9
B10: Year | G10: =Input!G10 | H10: =Input!H10 | I10: =Input!I10 | J10: =Input!J10 | K10: =Input!K10 | L10: =Input!L10 | M10: =Input!M10 | N10: =Input!N10 | O10: =Input!O10
B11: Days | G11: =Input!G11 | H11: =Input!H11 | I11: =Input!I11 | J11: =Input!J11 | K11: =Input!K11 | L11: =Input!L11 | M11: =Input!M11 | N11: =Input!N11
B13: Weighted Average Cost of Capital (WACC)
B15: [Cost of Equity - CAPM]
B17: Risk-free Rate (Rf) | E17: 0.035 | F17: %
B18: Equity Risk Premium (ERP) | E18: 0.06 | F18: %
B19: Beta (β) | E19: 1 | F19: x
B20: Size Premium | E20: 0.02 | F20: %
B21: Country Risk Premium | E21: 0.01 | F21: %
B22: Cost of Equity (Ke) | E22: =E17+E19*E18+E20+E21 | F22: %
B24: [Cost of Debt]
B26: Pre-tax Cost of Debt | E26: =Input!E217 | F26: %
B27: Effective Tax Rate | E27: 0.22 | F27: %
B28: After-tax Cost of Debt (Kd) | E28: =E26*(1-E27) | F28: %
B30: [Capital Structure]
B32: Equity Value (Market Cap) | E32: =DCF!O45 | F32: KRW mn
B33: Debt Value (Book Value) | E33: =Input!I248 | F33: KRW mn
B34: Total Capital | E34: =E32+E33 | F34: KRW mn
B35: Equity Weight (We) | E35: =IFERROR(E32/E34,0) | F35: %
B36: Debt Weight (Wd) | E36: =IFERROR(E33/E34,0) | F36: %
B38: WACC Calculation
B40: WACC | E40: =E35*E22+E36*E28 | F40: %
B42: vs Input WACC | E42: =Input!E18
B45: WACC Sensitivity Analysis
B47: Cost of Equity (Ke)
D48: ERP → | E48: 0.04 | F48: 0.05 | G48: 0.06 | H48: 0.07 | I48: 0.08
C49: β ↓ | D49: 0.8 | E49: =$E$17+$D49*E$48+$E$20+$E$21 | F49: =$E$17+$D49*F$48+$E$20+$E$21 | G49: =$E$17+$D49*G$48+$E$20+$E$21 | H49: =$E$17+$D49*H$48+$E$20+$E$21 | I49: =$E$17+$D49*I$48+$E$20+$E$21
D50: 0.9 | E50: =$E$17+$D50*E$48+$E$20+$E$21 | F50: =$E$17+$D50*F$48+$E$20+$E$21 | G50: =$E$17+$D50*G$48+$E$20+$E$21 | H50: =$E$17+$D50*H$48+$E$20+$E$21 | I50: =$E$17+$D50*I$48+$E$20+$E$21
D51: 1 | E51: =$E$17+$D51*E$48+$E$20+$E$21 | F51: =$E$17+$D51*F$48+$E$20+$E$21 | G51: =$E$17+$D51*G$48+$E$20+$E$21 | H51: =$E$17+$D51*H$48+$E$20+$E$21 | I51: =$E$17+$D51*I$48+$E$20+$E$21
D52: 1.1 | E52: =$E$17+$D52*E$48+$E$20+$E$21 | F52: =$E$17+$D52*F$48+$E$20+$E$21 | G52: =$E$17+$D52*G$48+$E$20+$E$21 | H52: =$E$17+$D52*H$48+$E$20+$E$21 | I52: =$E$17+$D52*I$48+$E$20+$E$21
D53: 1.2 | E53: =$E$17+$D53*E$48+$E$20+$E$21 | F53: =$E$17+$D53*F$48+$E$20+$E$21 | G53: =$E$17+$D53*G$48+$E$20+$E$21 | H53: =$E$17+$D53*H$48+$E$20+$E$21 | I53: =$E$17+$D53*I$48+$E$20+$E$21

Sheet GPCM
B1: =Legend!D2
B2: Guideline Public Company Method (GPCM)
B4: Time Period
B6: Actual/Forecast | G6: =Input!G6 | H6: =Input!H6 | I6: =Input!I6 | J6: =Input!J6 | K6: =Input!K6 | L6: =Input!L6 | M6: =Input!M6 | N6: =Input!N6 | O6: =Input!O6
B7: Period Start | G7: =Input!G7 | H7: =Input!H7 | I7: =Input!I7 | J7: =Input!J7 | K7: =Input!K7 | L7: =Input!L7 | M7: =Input!M7 | N7: =Input!N7 | O7: TV
B8: Period End | G8: =Input!G8 | H8: =Input!H8 | I8: =Input!I8 | J8: =Input!J8 | K8: =Input!K8 | L8: =Input!L8 | M8: =Input!M8 | N8: =Input!N8
B9: Month | G9: =Input!G9 | H9: =Input!H9 | I9: =Input!I9 | J9: =Input!J9 | K9: =Input!K9 | L9: =Input!L9 | M9: =Input!M9 | N9: =Input!N9
B10: Year | G10: =Input!G10 | H10: =Input!H10 | I10: =Input!I10 | J10: =Input!J10 | K10: =Input!K10 | L10: =Input!L10 | M10: =Input!M10 | N10: =Input!N10 | O10: =Input!O10
B11: Days | G11: =Input!G11 | H11: =Input!H11 | I11: =Input!I11 | J11: =Input!J11 | K11: =Input!K11 | L11: =Input!L11 | M11: =Input!M11 | N11: =Input!N11
B13: Comparable Company Analysis
B15: [Comparable Companies]
B17: Company | C17: Ticker | D17: Market Cap (KRW mn) | E17: EV (KRW mn) | F17: Revenue (KRW mn) | G17: EBITDA (KRW mn) | H17: EBIT (KRW mn) | I17: Net Income (KRW mn) | J17: EV/Revenue | K17: EV/EBITDA | L17: EV/EBIT | M17: P/E
B18: Comp #1 | K18: =IFERROR(E18/G18,"-") | L18: =IFERROR(E18/H18,"-") | M18: =IFERROR(E18/I18,"-") | N18: =IFERROR(D18/J18,"-")
B19: Comp #2 | K19: =IFERROR(E19/G19,"-") | L19: =IFERROR(E19/H19,"-") | M19: =IFERROR(E19/I19,"-") | N19: =IFERROR(D19/J19,"-")
B20: Comp #3 | K20: =IFERROR(E20/G20,"-") | L20: =IFERROR(E20/H20,"-") | M20: =IFERROR(E20/I20,"-") | N20: =IFERROR(D20/J20,"-")
B21: Comp #4 | K21: =IFERROR(E21/G21,"-") | L21: =IFERROR(E21/H21,"-") | M21: =IFERROR(E21/I21,"-") | N21: =IFERROR(D21/J21,"-")
B22: Comp #5 | K22: =IFERROR(E22/G22,"-") | L22: =IFERROR(E22/H22,"-") | M22: =IFERROR(E22/I22,"-") | N22: =IFERROR(D22/J22,"-")
B24: [Multiple Summary Statistics]
K26: EV/Revenue | L26: EV/EBITDA | M26: EV/EBIT | N26: P/E
B27: Mean | K27: =IFERROR(AVERAGE(K18:K22),"-") | L27: =IFERROR(AVERAGE(L18:L22),"-") | M27: =IFERROR(AVERAGE(M18:M22),"-") | N27: =IFERROR(AVERAGE(N18:N22),"-")
B28: Median | K28: =IFERROR(MEDIAN(K18:K22),"-") | L28: =IFERROR(MEDIAN(L18:L22),"-") | M28: =IFERROR(MEDIAN(M18:M22),"-") | N28: =IFERROR(MEDIAN(N18:N22),"-")
B29: Max | K29: =IFERROR(MAX(K18:K22),"-") | L29: =IFERROR(MAX(L18:L22),"-") | M29: =IFERROR(MAX(M18:M22),"-") | N29: =IFERROR(MAX(N18:N22),"-")
B30: Min | K30: =IFERROR(MIN(K18:K22),"-") | L30: =IFERROR(MIN(L18:L22),"-") | M30: =IFERROR(MIN(M18:M22),"-") | N30: =IFERROR(MIN(N18:N22),"-")
B32: [Selected Multiples & Valuation]
B34: Selected Multiple
B36: Target Company Financials
B37: Revenue | F37: KRW mn | G37: =DCF!N20
B38: EBITDA | F38: KRW mn | G38: =DCF!N30
B39: EBIT | F39: KRW mn | G39: =DCF!N27
B40: Net Income | F40: KRW mn | G40: =DCF!N80
B42: Implied Enterprise Value
B43: EV (Revenue multiple) | F43: KRW mn | G43: =K34*G37
B44: EV (EBITDA multiple) | F44: KRW mn | G44: =L34*G38
B45: EV (EBIT multiple) | F45: KRW mn | G45: =M34*G39
B47: Implied Equity Value
B48: Equity (P/E multiple) | F48: KRW mn | G48: =N34*G40
B49: Equity (EV-based, EBITDA) | F49: KRW mn | G49: =G44-Input!I248

Sheet GTM
B1: =Legend!D2
B2: Guideline Transaction Method (GTM)
B4: Time Period
B6: Actual/Forecast | G6: =Input!G6 | H6: =Input!H6 | I6: =Input!I6 | J6: =Input!J6 | K6: =Input!K6 | L6: =Input!L6 | M6: =Input!M6 | N6: =Input!N6 | O6: =Input!O6
B7: Period Start | G7: =Input!G7 | H7: =Input!H7 | I7: =Input!I7 | J7: =Input!J7 | K7: =Input!K7 | L7: =Input!L7 | M7: =Input!M7 | N7: =Input!N7 | O7: TV
B8: Period End | G8: =Input!G8 | H8: =Input!H8 | I8: =Input!I8 | J8: =Input!J8 | K8: =Input!K8 | L8: =Input!L8 | M8: =Input!M8 | N8: =Input!N8
B9: Month | G9: =Input!G9 | H9: =Input!H9 | I9: =Input!I9 | J9: =Input!J9 | K9: =Input!K9 | L9: =Input!L9 | M9: =Input!M9 | N9: =Input!N9
B10: Year | G10: =Input!G10 | H10: =Input!H10 | I10: =Input!I10 | J10: =Input!J10 | K10: =Input!K10 | L10: =Input!L10 | M10: =Input!M10 | N10: =Input!N10 | O10: =Input!O10
B11: Days | G11: =Input!G11 | H11: =Input!H11 | I11: =Input!I11 | J11: =Input!J11 | K11: =Input!K11 | L11: =Input!L11 | M11: =Input!M11 | N11: =Input!N11
B13: Comparable Transaction Analysis
B15: [Comparable Transactions]
B17: Date | C17: Target | D17: Acquirer | E17: Deal Value (KRW mn) | F17: Revenue (KRW mn) | G17: EBITDA (KRW mn) | H17: EBIT (KRW mn) | I17: EV/Revenue | J17: EV/EBITDA | K17: EV/EBIT | L17: Control Premium
C18: Target #1 | D18: Acquirer #1 | J18: =IFERROR(E18/G18,"-") | K18: =IFERROR(E18/H18,"-") | L18: =IFERROR(E18/I18,"-")
C19: Target #2 | D19: Acquirer #2 | J19: =IFERROR(E19/G19,"-") | K19: =IFERROR(E19/H19,"-") | L19: =IFERROR(E19/I19,"-")
C20: Target #3 | D20: Acquirer #3 | J20: =IFERROR(E20/G20,"-") | K20: =IFERROR(E20/H20,"-") | L20: =IFERROR(E20/I20,"-")
C21: Target #4 | D21: Acquirer #4 | J21: =IFERROR(E21/G21,"-") | K21: =IFERROR(E21/H21,"-") | L21: =IFERROR(E21/I21,"-")
C22: Target #5 | D22: Acquirer #5 | J22: =IFERROR(E22/G22,"-") | K22: =IFERROR(E22/H22,"-") | L22: =IFERROR(E22/I22,"-")
B24: [Transaction Multiple Summary]
J26: EV/Revenue | K26: EV/EBITDA | L26: EV/EBIT
B27: Mean | J27: =IFERROR(AVERAGE(J18:J22),"-") | K27: =IFERROR(AVERAGE(K18:K22),"-") | L27: =IFERROR(AVERAGE(L18:L22),"-") | M27: =IFERROR(AVERAGE(M18:M22),"-")
B28: Median | J28: =IFERROR(MEDIAN(J18:J22),"-") | K28: =IFERROR(MEDIAN(K18:K22),"-") | L28: =IFERROR(MEDIAN(L18:L22),"-")
B29: Max | J29: =IFERROR(MAX(J18:J22),"-") | K29: =IFERROR(MAX(K18:K22),"-") | L29: =IFERROR(MAX(L18:L22),"-")
B30: Min | J30: =IFERROR(MIN(J18:J22),"-") | K30: =IFERROR(MIN(K18:K22),"-") | L30: =IFERROR(MIN(L18:L22),"-")
B32: [Selected Transaction Multiples & Valuation]
B34: Selected Multiple
B35: Control Premium Applied | E35: 0
B37: Target Company Financials
B38: Revenue | F38: KRW mn | G38: =DCF!N20
B39: EBITDA | F39: KRW mn | G39: =DCF!N30
B40: EBIT | F40: KRW mn | G40: =DCF!N27
B42: Implied Enterprise Value
B43: EV (Revenue multiple) | F43: KRW mn | G43: =J34*G38*(1+$E$35)
B44: EV (EBITDA multiple) | F44: KRW mn | G44: =K34*G39*(1+$E$35)
B45: EV (EBIT multiple) | F45: KRW mn | G45: =L34*G40*(1+$E$35)
B47: Implied Equity Value
B48: Equity (EV/EBITDA-based) | F48: KRW mn | G48: =G44-Input!I248
B49: Equity (EV/EBIT-based) | F49: KRW mn | G49: =G45-Input!I248
B51: Valuation Summary (Cross-Method)
B53: DCF Equity Value | F53: KRW mn | G53: =DCF!O45
B54: GPCM Equity Value (EV/EBITDA) | F54: KRW mn | G54: =GPCM!G49
B55: GTM Equity Value (EV/EBITDA) | F55: KRW mn | G55: =G48
B57: Average Equity Value | F57: KRW mn | G57: =AVERAGE(G53:G55)
