Workbook

Sheet 1. Results▶
B8: Section <1>
B9: <Results>

Sheet Control
B1: Control Panel - 주요 가정 조정
B4: 구분 | C4: Driver | D4: 2026 | E4: 2027 | F4: 2028 | G4: 2029 | H4: 2030 | J4: 비고
B5: 1. 트라우마 (TRAUMA)
B6: 음반 발매수 | C6: 개 | D6: 1 | E6: 2 | F6: 2 | G6: 3 | H6: 3 | J6: 데뷔 1개→점진증가
B7: 음반 당 판매량 | C7: 장 | D7: 130000 | E7: 155000 | F7: 210000 | G7: 250000 | H7: 300000 | J7: BM: ILLIT 82K~NJ 169K
B8: 스트리밍 (M streams) | C8: 백만 | D8: 50 | E8: 80 | F8: 150 | G8: 250 | H8: 400 | J8: BM: NJ 2.3B/yr
B9: 콘서트 관객수 | C9: 명 | D9: 0 | E9: 12000 | F9: 40000 | G9: 95000 | H9: 155000 | J9: Hall→Arena→Dome
B10: 팬플랫폼 가입자 | C10: 명 | D10: 80000 | E10: 140000 | F10: 220000 | G10: 310000 | H10: 400000
B11: 아티스트 정산율 | C11: % | D11: 0.15 | E11: 0.15 | F11: 0.15 | G11: 0.15 | H11: 0.15 | J11: SM/JYP 12-18% 범위
B13: 2. 드랍잇 (Drop It) - US
B14: 음반 발매수 | C14: 개 | D14: 0 | E14: 1 | F14: 2 | G14: 2 | H14: 3 | J14: 2027년 데뷔
B15: 음반 당 판매량 | C15: 장 | D15: 0 | E15: 80000 | F15: 100000 | G15: 130000 | H15: 145000 | J15: BM: FIFTY FIFTY 수준
B16: 스트리밍 (M streams) | C16: 백만 | D16: 0 | E16: 55 | F16: 90 | G16: 120 | H16: 150
B17: 콘서트 관객수 | C17: 명 | D17: 0 | E17: 8000 | F17: 25000 | G17: 50000 | H17: 80000
B18: 팬플랫폼 가입자 | C18: 명 | D18: 20000 | E18: 60000 | F18: 110000 | G18: 170000 | H18: 220000
B19: 로열티율 | C19: % | D19: 0.3 | E19: 0.3 | F19: 0.3 | G19: 0.3 | H19: 0.3 | J19: IR Pitch: 30%
B21: 3. 찰리 (Charlie) - Asia
B22: 음반 발매수 | C22: 개 | D22: 0 | E22: 1 | F22: 2 | G22: 2 | H22: 3 | J22: 2027년 데뷔
B23: 음반 당 판매량 | C23: 장 | D23: 0 | E23: 75000 | F23: 95000 | G23: 125000 | H23: 140000 | J23: BM: ILLIT JP데뷔
B24: 스트리밍 (M streams) | C24: 백만 | D24: 0 | E24: 50 | F24: 80 | G24: 110 | H24: 140
B25: 콘서트 관객수 | C25: 명 | D25: 0 | E25: 7000 | F25: 22000 | G25: 45000 | H25: 75000
B26: 팬플랫폼 가입자 | C26: 명 | D26: 15000 | E26: 50000 | F26: 100000 | G26: 150000 | H26: 210000
B27: 로열티율 | C27: % | D27: 0.3 | E27: 0.3 | F27: 0.3 | G27: 0.3 | H27: 0.3
B29: 4. 태깅 (Tagging) - IP/애니메이션
B30: IP 라이선싱 | C30: 백만원 | D30: 1000 | E30: 1500 | F30: 2500 | G30: 3800 | H30: 6500
B31: 캐릭터 MD | C31: 백만원 | D31: 200 | E31: 600 | F31: 1500 | G31: 2800 | H31: 5500
B32: 애니메이션 콘텐츠 | C32: 백만원 | D32: 500 | E32: 1000 | F32: 1500 | G32: 2300 | H32: 4200
B33: 팬플랫폼 (캐릭터) | C33: 백만원 | D33: 400 | E33: 800 | F33: 1200 | G33: 2200 | H33: 4500
B34: 로열티율 | C34: % | D34: 0.3 | E34: 0.3 | F34: 0.3 | G34: 0.3 | H34: 0.3
B36: 5. 라이트 (Light) - 콘텐츠
B37: 유튜브 매출 | C37: 백만원 | D37: 400 | E37: 900 | F37: 1800 | G37: 3000 | H37: 5500
B38: 방송 매출 | C38: 백만원 | D38: 800 | E38: 1400 | F38: 2500 | G38: 4200 | H38: 7500
B39: 콘텐츠 라이선싱 | C39: 백만원 | D39: 500 | E39: 1200 | F39: 2500 | G39: 4500 | H39: 9500
B40: 로열티율 | C40: % | D40: 0.3 | E40: 0.3 | F40: 0.3 | G40: 0.3 | H40: 0.3
B42: 6. 원가/판관비 주요 가정
B43: TRAUMA 음반원가율 | C43: % | D43: 0.6 | E43: 0.52 | F43: 0.48 | G43: 0.45 | H43: 0.43 | J43: 규모경제 반영
B44: TRAUMA 공연원가율 | C44: % | D44: 0.8 | E44: 0.72 | F44: 0.64 | G44: 0.58 | H44: 0.55 | J44: 규모경제 반영
B45: Drop It/Charlie 원가율 | C45: % | D45: 0.42 | E45: 0.38 | F45: 0.35 | G45: 0.35 | H45: 0.34
B46: 인당 매출액 | C46: 백만원 | D46: 1135 | E46: 1135 | F46: 1135 | G46: 1135 | H46: 1135 | J46: SM FY24 기준
B47: CAPEX | C47: 백만원 | D47: 200 | E47: 300 | F47: 400 | G47: 500 | H47: =G47 -> 500
B48: D&A | C48: 백만원 | D48: 500 | E48: 500 | F48: 500 | G48: 500 | H48: 500

Sheet Model
B1: Financial Model
B2: Value analysis as of Feb, 2026
B3: KRW in millions
I5: Actual | M5: Projection
B6: KRW in millions | I6: 2022 | J6: 2023 | K6: 2024 | L6: 2025 | M6: 2026 | N6: 2027 | O6: 2028 | P6: 2029 | Q6: 2030
B7: Sales | M7: =M36 -> 14148.6 | N7: =N36 -> 35740.285 | O7: =O36 -> 67959.627 | P7: =P36 -> 114419.38 | Q7: =Q36 -> 178981.66
B8: Cost of Sales | M8: =M45 -> 10586.8 | N8: =N45 -> 25809.51 | O8: =O45 -> 49511.603 | P8: =P45 -> 81896.336 | Q8: =Q45 -> 124804.06
B9: Gross Profit | M9: =M7-M8 -> 3561.8 | N9: =N7-N8 -> 9930.775 | O9: =O7-O8 -> 18448.024 | P9: =P7-P8 -> 32523.044 | Q9: =Q7-Q8 -> 54177.593
B10: SG&A (w/o D&A) | M10: =M256 -> 1545.5494 | N10: =N256 -> 4034.9671 | O10: =O256 -> 7929.842 | P10: =P256 -> 13630.98 | Q10: =Q256 -> 21805.741
B11: EBITDA | M11: =M9-M10 -> 2016.2506 | N11: =N9-N10 -> 5895.8079 | O11: =O9-O10 -> 10518.182 | P11: =P9-P10 -> 18892.064 | Q11: =Q9-Q10 -> 32371.852
B12: D&A | M12: =M263 -> 200 | N12: =N263 -> 300 | O12: =O263 -> 400 | P12: =P263 -> 500 | Q12: =Q263 -> 500
B13: EBIT | M13: =M11-M12 -> 1816.2506 | N13: =N11-N12 -> 5595.8079 | O13: =O11-O12 -> 10118.182 | P13: =P11-P12 -> 18392.064 | Q13: =Q11-Q12 -> 31871.852
B15: Sales Growth % | N15: =N7/M7-1 -> 1.5260651 | O15: =O7/N7-1 -> 0.90148531 | P15: =P7/O7-1 -> 0.68363756 | Q15: =Q7/P7-1 -> 0.56425996
B16: EBITDA % | M16: =IF(M7=0,0,M11/M7) -> 0.14250531 | N16: =IF(N7=0,0,N11/N7) -> 0.16496253 | O16: =IF(O7=0,0,O11/O7) -> 0.15477104 | P16: =IF(P7=0,0,P11/P7) -> 0.16511245 | Q16: =IF(Q7=0,0,Q11/Q7) -> 0.18086687
B17: EBIT % | M17: =IF(M7=0,0,M13/M7) -> 0.12836964 | N17: =IF(N7=0,0,N13/N7) -> 0.15656864 | O17: =IF(O7=0,0,O13/O7) -> 0.14888519 | P17: =IF(P7=0,0,P13/P7) -> 0.16074256 | Q17: =IF(Q7=0,0,Q13/Q7) -> 0.17807329
B19: Macro Indicator_South Korea
B20: Growth in Average Wages (LCU; % pa) | M20: 0.028 | N20: 0.036 | O20: 0.035 | P20: 0.035 | Q20: 0.035 | R20: Source: EIU Korea, Average Wage Growth forecast
B21: Consumer Prices (% change pa; av) | M21: 0.015 | N21: 0.015 | O21: 0.018 | P21: 0.017 | Q21: 0.018 | R21: Source: EIU Korea, CPI forecast 2026-2030
B24: Key Performance Indicators
B25: Trainees | M25: 33 | N25: 33 | O25: 33 | P25: 33 | Q25: 33 | R25: IR Pitch: 33명 연습생 운영 계획
B28: Revenue & Cost Consolidation by Project
B29: Revenue by Project
M30: 2026 | N30: 2027 | O30: 2028 | P30: 2029 | Q30: 2030
B31: 트라우마 (TRAUMA) | M31: =M107 -> 8373.6 | N31: =N107 -> 17358.96 | O31: =O107 -> 27677.865 | P31: =P107 -> 49345.841 | Q31: =Q107 -> 67091.059
B32: 드랍잇 (Drop It) | M32: =M153 -> 1050 | N32: =N153 -> 5837.74 | O32: =O153 -> 14015.205 | P32: =P153 -> 22183.202 | Q32: =Q153 -> 35459.125
B33: 찰리 (Charlie) | M33: =M189 -> 925 | N33: =N189 -> 5143.585 | O33: =O189 -> 12766.557 | P33: =P189 -> 20090.337 | Q33: =Q189 -> 33231.471
B34: 태깅 (Tagging) | M34: =M209 -> 2100 | N34: =N209 -> 3900 | O34: =O209 -> 6700 | P34: =P209 -> 11100 | Q34: =Q209 -> 20700
B35: 라이트 (Light) | M35: =M226 -> 1700 | N35: =N226 -> 3500 | O35: =O226 -> 6800 | P35: =P226 -> 11700 | Q35: =Q226 -> 22500
B36: Total Revenue | M36: =M31+M32+M33+M34+M35 -> 14148.6 | N36: =N31+N32+N33+N34+N35 -> 35740.285 | O36: =O31+O32+O33+O34+O35 -> 67959.627 | P36: =P31+P32+P33+P34+P35 -> 114419.38 | Q36: =Q31+Q32+Q33+Q34+Q35 -> 178981.66
B38: Cost of Sales by Project (incl. Royalty)
M39: 2026 | N39: 2027 | O39: 2028 | P39: 2029 | Q39: 2030
B40: 트라우마 (TRAUMA) | M40: =M122 -> 6246.8 | N40: =N122 -> 12109.45 | O40: =O122 -> 20113.646 | P40: =P122 -> 34975.711 | Q40: =Q122 -> 46229.208
B41: 드랍잇 (Drop It) | M41: =M158 -> 882 | N41: =N158 -> 4670.192 | O41: =O158 -> 10791.708 | P41: =P158 -> 17081.066 | Q41: =Q158 -> 26948.935
B42: 찰리 (Charlie) | M42: =M194 -> 777 | N42: =N194 -> 4114.868 | O42: =O194 -> 9830.2492 | P42: =P194 -> 15469.559 | Q42: =Q194 -> 25255.918
B43: 태깅 (Tagging) | M43: =M213 -> 1491 | N43: =N213 -> 2535 | O43: =O213 -> 4288 | P43: =P213 -> 6882 | Q43: =Q213 -> 12420
B44: 라이트 (Light) | M44: =M230 -> 1190 | N44: =N230 -> 2380 | O44: =O230 -> 4488 | P44: =P230 -> 7488 | Q44: =Q230 -> 13950
B45: Total COS | M45: =M40+M41+M42+M43+M44 -> 10586.8 | N45: =N40+N41+N42+N43+N44 -> 25809.51 | O45: =O40+O41+O42+O43+O44 -> 49511.603 | P45: =P40+P41+P42+P43+P44 -> 81896.336 | Q45: =Q40+Q41+Q42+Q43+Q44 -> 124804.06
B47: 1. 트라우마 (TRAUMA) - 메인 걸그룹 Full Group | R47: TRAUMA = 메인 걸그룹, Full Group 활동
B48: KRW in millions | M48: 2026 | N48: 2027 | O48: 2028 | P48: 2029 | Q48: 2030
B50: 음반 매출 | R50: BM: NewJeans 데뷔앨범 1개, ILLIT 1개 (걸그룹 시트)
B51: 음반 발매수: 데뷔연도 1개, 이후 점진 증가
B52: 연도별 음반 발매수 | M52: 1 | N52: 2 | O52: 2 | P52: 3 | Q52: 3 | R52: BM: ILLIT 초동 82만, NewJeans 초동 169만 → BASE 수준 적용
C53: x 음반 당 판매량 | M53: 130000 | N53: 155000 | O53: 210000 | P53: 250000 | Q53: 300000
C54: x 음반 당 단가 | F54: 25000 | G54: 원 | M54: 25000 | N54: =M54*(1+N21) -> 25375 | O54: =N54*(1+O21) -> 25831.75 | P54: =O54*(1+P21) -> 26270.89 | Q54: =P54*(1+Q21) -> 26743.766 | R54: IR Pitch 기준, CPI 연동 인상
C55: x (1-유통수수료율) | F55: 0.8 | M55: 0.8 | N55: 0.8 | O55: 0.8 | P55: 0.8 | Q55: 0.8
B56: Total | M56: =M52*M53*M54*M55/10^6 -> 2600 | N56: =N52*N53*N54*N55/10^6 -> 6293 | O56: =O52*O53*O54*O55/10^6 -> 8679.468 | P56: =P52*P53*P54*P55/10^6 -> 15762.534 | Q56: =Q52*Q53*Q54*Q55/10^6 -> 19255.511 | R56: BM: 엔터사 시트 - SM/JYP 유통수수료율 약 20%
B58: 음원 매출
B59: 연도별 타이틀곡 스트리밍 수 (백만) | M59: 80 | N59: 130 | O59: 170 | P59: 210 | Q59: 250 | R59: BM: NewJeans 2.3B/yr, ILLIT 1.0B/yr (유튜브 시트)
C60: x 수록곡 Multiplier | F60: 1.5 | M60: 1.5 | N60: 1.5 | O60: 1.5 | P60: 1.5 | Q60: 1.5
C61: x 연도별 음반 발매수 | M61: =M52 -> 1 | N61: =N52 -> 2 | O61: =O52 -> 2 | P61: =P52 -> 3 | Q61: =Q52 -> 3 | R61: Source: Spotify RPM $3.5-4.0/1,000 streams
C62: x 스트리밍 당 단가 | F62: 10 | M62: 10 | N62: 10 | O62: 10 | P62: 10 | Q62: 10
C63: x (1-유통수수료율) | M63: 0.8 | N63: 0.8 | O63: 0.8 | P63: 0.8 | Q63: 0.8
B64: Total | M64: =M59*M60*M61*M62*M63 -> 960 | N64: =N59*N60*N61*N62*N63 -> 3120 | O64: =O59*O60*O61*O62*O63 -> 4080 | P64: =P59*P60*P61*P62*P63 -> 7560 | Q64: =Q59*Q60*Q61*Q62*Q63 -> 9000
B65: 음반/음원 매출 합계 | M65: =M56+M64 -> 3560 | N65: =N56+N64 -> 9413 | O65: =O56+O64 -> 12759.468 | P65: =P56+P64 -> 23322.534 | Q65: =Q56+Q64 -> 28255.511 | R65: BM: 음반원 시트 - 음반 판매와 스트리밍 비례 관계
B67: 공연 매출
B68: 연도별 콘서트 관객 수 | M68: 0 | N68: 12000 | O68: 40000 | P68: 95000 | Q68: 155000
C69: x 콘서트 티켓 단가 | F69: 100000 | G69: 원 | M69: 100000 | N69: =M69*(1+N21) -> 101500 | O69: =N69*(1+O21) -> 103327 | P69: =O69*(1+P21) -> 105083.56 | Q69: =P69*(1+Q21) -> 106975.06 | R69: BM: 콘서트 시트 - Hall(5K)→Arena(15K)→Dome(50K) 단계적 확장
B70: Total | M70: =M68*M69/10^6 -> 0 | N70: =N68*N69/10^6 -> 1218 | O70: =O68*O69/10^6 -> 4133.08 | P70: =P68*P69/10^6 -> 9982.9381 | Q70: =Q68*Q69/10^6 -> 16581.135
R71: BM: 콘서트 시트 평균 10만원, CPI 연동
B72: 방송/광고/행사 매출
B73: 광고 매출
B74: 광고 횟수 | M74: 1 | N74: 1.5 | O74: 2 | P74: 2.5 | Q74: 3
C75: x 광고 회당 단가 (백만원) | M75: 75 | N75: 100 | O75: 130 | P75: 160 | Q75: 200
C76: x 활동지역 Multiplier | M76: 4 | N76: 4 | O76: 4 | P76: 4 | Q76: 4
C77: x (1-에이전시수수료율) | M77: 0.85 | N77: 0.85 | O77: 0.85 | P77: 0.85 | Q77: 0.85
B78: 광고 매출 소계 | M78: =M74*M75*M76*M77 -> 255 | N78: =N74*N75*N76*N77 -> 510 | O78: =O74*O75*O76*O77 -> 884 | P78: =P74*P75*P76*P77 -> 1360 | Q78: =Q74*Q75*Q76*Q77 -> 2040 | R78: BM: 걸그룹 시트 - AESPA 광고 4억/건, NewJeans 3억/건 (6개월)
B79: 방송 매출
B80: 방송 횟수 | M80: 13 | N80: 13 | O80: 13 | P80: 13 | Q80: 13 | R80: IR Pitch 기준 단가, 인지도 성장 반영
C81: x 방송 회당 단가 (백만원) | M81: 3 | N81: 3 | O81: 4 | P81: 5 | Q81: 5
C82: x 활동지역 Multiplier | M82: 4 | N82: 4 | O82: 4 | P82: 4 | Q82: 4 | R82: BM: 걸그룹 시트 - 활동지역 Asia 4개국 기준
C83: x (1-에이전시수수료율) | M83: 0.85 | N83: 0.85 | O83: 0.85 | P83: 0.85 | Q83: 0.85
B84: 방송 매출 소계 | M84: =M80*M81*M82*M83 -> 132.6 | N84: =N80*N81*N82*N83 -> 132.6 | O84: =O80*O81*O82*O83 -> 176.8 | P84: =P80*P81*P82*P83 -> 221 | Q84: =Q80*Q81*Q82*Q83 -> 221
B85: 행사 매출
B86: 행사 횟수 | M86: 30 | N86: 35 | O86: 38 | P86: 40 | Q86: 45
C87: x 행사 회당 단가 (백만원) | M87: 13 | N87: 16 | O87: 18 | P87: 20 | Q87: 23
C88: x 활동지역 Multiplier | M88: 4 | N88: 4 | O88: 4 | P88: 4 | Q88: 4 | R88: BM: 걸그룹 시트 - 방송 회당 500-1000만원
C89: x (1-에이전시수수료율) | M89: 0.85 | N89: 0.85 | O89: 0.85 | P89: 0.85 | Q89: 0.85
B90: 행사 매출 소계 | M90: =M86*M87*M88*M89 -> 1326 | N90: =N86*N87*N88*N89 -> 1904 | O90: =O86*O87*O88*O89 -> 2325.6 | P90: =P86*P87*P88*P89 -> 2720 | Q90: =Q86*Q87*Q88*Q89 -> 3519
B91: 방송/광고/행사 매출 합계 | M91: =M78+M84+M90 -> 1713.6 | N91: =N78+N84+N90 -> 2546.6 | O91: =O78+O84+O90 -> 3386.4 | P91: =P78+P84+P90 -> 4301 | Q91: =Q78+Q84+Q90 -> 5780
B93: MD 매출
B94: 콘서트 관객 수 | M94: =M68 -> 0 | N94: =N68 -> 12000 | O94: =O68 -> 40000 | P94: =P68 -> 95000 | Q94: =Q68 -> 155000
C95: x MD 구입 개수 | M95: 1 | N95: 1 | O95: 1 | P95: 1 | Q95: 1
C96: x MD 단가 | F96: 27000 | M96: 27000 | N96: =M96*(1+N21) -> 27405 | O96: =N96*(1+O21) -> 27898.29 | P96: =O96*(1+P21) -> 28372.561 | Q96: =P96*(1+Q21) -> 28883.267 | R96: BM: 걸그룹 시트 - 행사 회당 1300-2500만원
B97: Total | M97: =M94*M95*M96/10^6 -> 0 | N97: =N94*N95*N96/10^6 -> 328.86 | O97: =O94*O95*O96/10^6 -> 1115.9316 | P97: =P94*P95*P96/10^6 -> 2695.3933 | Q97: =Q94*Q95*Q96/10^6 -> 4476.9064
B99: 기타 매출
B100: 팬플랫폼 가입자 수 | M100: 80000 | N100: 140000 | O100: 220000 | P100: 310000 | Q100: 400000
C101: x 연간 가입비 | F101: 25000 | M101: 25000 | N101: =M101*(1+N21) -> 25375 | O101: =N101*(1+O21) -> 25831.75 | P101: =O101*(1+P21) -> 26270.89 | Q101: =P101*(1+Q21) -> 26743.766
B102: 팬플랫폼 소계 | M102: =M100*M101/10^6 -> 2000 | N102: =N100*N101/10^6 -> 3552.5 | O102: =O100*O101/10^6 -> 5682.985 | P102: =P100*P101/10^6 -> 8143.9758 | Q102: =Q100*Q101/10^6 -> 10697.506
B103: 유튜브 매출 | M103: 100 | N103: 300 | O103: 600 | P103: 900 | Q103: 1300
B104: 판권 매출 | M104: 1000 | N104: 0 | O104: 0 | P104: 0 | Q104: 0
B105: 기타 매출 합계 | M105: =M102+M103+M104 -> 3100 | N105: =N102+N103+N104 -> 3852.5 | O105: =O102+O103+O104 -> 6282.985 | P105: =P102+P103+P104 -> 9043.9758 | Q105: =Q102+Q103+Q104 -> 11997.506
B107: TRAUMA 매출 합계 | M107: =M65+M70+M91+M97+M105 -> 8373.6 | N107: =N65+N70+N91+N97+N105 -> 17358.96 | O107: =O65+O70+O91+O97+O105 -> 27677.865 | P107: =P65+P70+P91+P97+P105 -> 49345.841 | Q107: =Q65+Q70+Q91+Q97+Q105 -> 67091.059 | R107: →음반+음원+공연+bae+md+기타 합산
B109: TRAUMA 직접비
B110: 음반 제작/생산 원가 | C110: (매출의 55%→45%) | M110: 0.6 | N110: 0.52 | O110: 0.48 | P110: 0.45 | Q110: 0.43 | R110: Source: 엔터사 시트 - SM 원가율, 초기 60% (프로덕션 셋업 비용) → 43%
B111: 음반/음원 원가 | M111: =M65*M110 -> 2136 | N111: =N65*N110 -> 4894.76 | O111: =O65*O110 -> 6124.5446 | P111: =P65*P110 -> 10495.14 | Q111: =Q65*Q110 -> 12149.87 | R111: BM: 엔터사 시트 - SM 원가율 55%→43% (규모경제 반영)
B112: 공연 원가율 | M112: 0.8 | N112: 0.72 | O112: 0.64 | P112: 0.58 | Q112: 0.55
B113: 공연 원가 | M113: =M70*M112 -> 0 | N113: =N70*N112 -> 876.96 | O113: =O70*O112 -> 2645.1712 | P113: =P70*P112 -> 5790.1041 | Q113: =Q70*Q112 -> 9119.6241 | R113: BM: 콘서트 시트 - 초기 80% → 규모경제로 55%까지 개선
B114: 방송/광고/행사 원가율 | M114: 0.3 | N114: 0.3 | O114: 0.28 | P114: 0.28 | Q114: 0.25
B115: 방송/광고/행사 원가 | M115: =M91*M114 -> 514.08 | N115: =N91*N114 -> 763.98 | O115: =O91*O114 -> 948.192 | P115: =P91*P114 -> 1204.28 | Q115: =Q91*Q114 -> 1445 | R115: BM: 엔터사 시트 - JYP 25-30% 수준
B116: MD 원가율 | M116: 0.3 | N116: 0.3 | O116: 0.3 | P116: 0.3 | Q116: 0.3
...

Sheet IS
B1: 손익계산서 (Income Statement)
B2: KRW in millions
B3: 구분 | D3: 2026 | E3: 2027 | F3: 2028 | G3: 2029 | H3: 2030
B4: 매출액 (Revenue) | D4: =Model!M7 -> 14148.6 | E4: =Model!N7 -> 35740.285 | F4: =Model!O7 -> 67959.627 | G4: =Model!P7 -> 114419.38 | H4: =Model!Q7 -> 178981.66
B5: 트라우마 (TRAUMA) | D5: =Model!M31 -> 8373.6 | E5: =Model!N31 -> 17358.96 | F5: =Model!O31 -> 27677.865 | G5: =Model!P31 -> 49345.841 | H5: =Model!Q31 -> 67091.059
B6: 드랍잇 (Drop It) | D6: =Model!M32 -> 1050 | E6: =Model!N32 -> 5837.74 | F6: =Model!O32 -> 14015.205 | G6: =Model!P32 -> 22183.202 | H6: =Model!Q32 -> 35459.125
B7: 찰리 (Charlie) | D7: =Model!M33 -> 925 | E7: =Model!N33 -> 5143.585 | F7: =Model!O33 -> 12766.557 | G7: =Model!P33 -> 20090.337 | H7: =Model!Q33 -> 33231.471
B8: 태깅 (Tagging) | D8: =Model!M34 -> 2100 | E8: =Model!N34 -> 3900 | F8: =Model!O34 -> 6700 | G8: =Model!P34 -> 11100 | H8: =Model!Q34 -> 20700
B9: 라이트 (Light) | D9: =Model!M35 -> 1700 | E9: =Model!N35 -> 3500 | F9: =Model!O35 -> 6800 | G9: =Model!P35 -> 11700 | H9: =Model!Q35 -> 22500
B10: 매출원가 (COGS) | D10: =Model!M8 -> 10586.8 | E10: =Model!N8 -> 25809.51 | F10: =Model!O8 -> 49511.603 | G10: =Model!P8 -> 81896.336 | H10: =Model!Q8 -> 124804.06
B11: 매출총이익 (Gross Profit) | D11: =Model!M9 -> 3561.8 | E11: =Model!N9 -> 9930.775 | F11: =Model!O9 -> 18448.024 | G11: =Model!P9 -> 32523.044 | H11: =Model!Q9 -> 54177.593
B12: GP Margin % | D12: =IF(D4=0,0,D11/D4) -> 0.25174222 | E12: =IF(E4=0,0,E11/E4) -> 0.27785942 | F12: =IF(F4=0,0,F11/F4) -> 0.27145564 | G12: =IF(G4=0,0,G11/G4) -> 0.28424419 | H12: =IF(H4=0,0,H11/H4) -> 0.30269914
B13: 판관비 (SG&A) | D13: =Model!M10 -> 1545.5494 | E13: =Model!N10 -> 4034.9671 | F13: =Model!O10 -> 7929.842 | G13: =Model!P10 -> 13630.98 | H13: =Model!Q10 -> 21805.741
B14: EBITDA | D14: =Model!M11 -> 2016.2506 | E14: =Model!N11 -> 5895.8079 | F14: =Model!O11 -> 10518.182 | G14: =Model!P11 -> 18892.064 | H14: =Model!Q11 -> 32371.852
B15: EBITDA Margin % | D15: =IF(D4=0,0,D14/D4) -> 0.14250531 | E15: =IF(E4=0,0,E14/E4) -> 0.16496253 | F15: =IF(F4=0,0,F14/F4) -> 0.15477104 | G15: =IF(G4=0,0,G14/G4) -> 0.16511245 | H15: =IF(H4=0,0,H14/H4) -> 0.18086687
B16: 감가상각비 (D&A) | D16: =Model!M12 -> 200 | E16: =Model!N12 -> 300 | F16: =Model!O12 -> 400 | G16: =Model!P12 -> 500 | H16: =Model!Q12 -> 500
B17: 영업이익 (EBIT) | D17: =Model!M13 -> 1816.2506 | E17: =Model!N13 -> 5595.8079 | F17: =Model!O13 -> 10118.182 | G17: =Model!P13 -> 18392.064 | H17: =Model!Q13 -> 31871.852
B18: EBIT Margin % | D18: =IF(D4=0,0,D17/D4) -> 0.12836964 | E18: =IF(E4=0,0,E17/E4) -> 0.15656864 | F18: =IF(F4=0,0,F17/F4) -> 0.14888519 | G18: =IF(G4=0,0,G17/G4) -> 0.16074256 | H18: =IF(H4=0,0,H17/H4) -> 0.17807329
B19: 영업외수익 | D19: 0 | E19: 0 | F19: 0 | G19: 0 | H19: 0
B20: 영업외비용 | D20: 0 | E20: 0 | F20: 0 | G20: 0 | H20: 0
B21: 세전이익 (EBT) | D21: =D17+D19-D20 -> 1816.2506 | E21: =E17+E19-E20 -> 5595.8079 | F21: =F17+F19-F20 -> 10118.182 | G21: =G17+G19-G20 -> 18392.064 | H21: =H17+H19-H20 -> 31871.852
B22: 법인세 | D22: =IF(D21<=0,0,IF(D21<=200,D21*0.099,IF(D21<=20000,200*0.099+(D21-200)*0.209,IF(D21<=300000,200*0.099+19800*0.209+(D21-20000)*0.231,200*0.099+19800*0.209+280000*0.231+(D21-300000)*0.264)))) -> 357.59638 | E22: =IF(E21<=0,0,IF(E21<=200,E21*0.099,IF(E21<=20000,200*0.099+(E21-200)*0.209,IF(E21<=300000,200*0.099+19800*0.209+(E21-20000)*0.231,200*0.099+19800*0.209+280000*0.231+(E21-300000)*0.264)))) -> 1147.5238 | F22: =IF(F21<=0,0,IF(F21<=200,F21*0.099,IF(F21<=20000,200*0.099+(F21-200)*0.209,IF(F21<=300000,200*0.099+19800*0.209+(F21-20000)*0.231,200*0.099+19800*0.209+280000*0.231+(F21-300000)*0.264)))) -> 2092.7 | G22: =IF(G21<=0,0,IF(G21<=200,G21*0.099,IF(G21<=20000,200*0.099+(G21-200)*0.209,IF(G21<=300000,200*0.099+19800*0.209+(G21-20000)*0.231,200*0.099+19800*0.209+280000*0.231+(G21-300000)*0.264)))) -> 3821.9413 | H22: =IF(H21<=0,0,IF(H21<=200,H21*0.099,IF(H21<=20000,200*0.099+(H21-200)*0.209,IF(H21<=300000,200*0.099+19800*0.209+(H21-20000)*0.231,200*0.099+19800*0.209+280000*0.231+(H21-300000)*0.264)))) -> 6900.3978
B23: 당기순이익 (Net Income) | D23: =D21-D22 -> 1458.6543 | E23: =E21-E22 -> 4448.284 | F23: =F21-F22 -> 8025.4819 | G23: =G21-G22 -> 14570.122 | H23: =H21-H22 -> 24971.454

Sheet BS
B1: 재무상태표 (Balance Sheet)
B2: KRW in millions
B3: 구분 | D3: 2026 | E3: 2027 | F3: 2028 | G3: 2029 | H3: 2030
B4: 자산 (Assets)
B5: 현금및현금성자산 | D5: =CF!D27 -> 3823.9043 | E5: =CF!E27 -> 6376.4129 | F5: =CF!F27 -> 11894.766 | G5: =CF!G27 -> 22769.688 | H5: =CF!H27 -> 42344.229
B6: 매출채권 | D6: =IS!D4/12*2 -> 2358.1 | E6: =IS!E4/12*2 -> 5956.7142 | F6: =IS!F4/12*2 -> 11326.604 | G6: =IS!G4/12*2 -> 19069.897 | H6: =IS!H4/12*2 -> 29830.276
B7: 기타유동자산 | D7: 500 | E7: 500 | F7: 500 | G7: 500 | H7: 500
B8: 유동자산 합계 | D8: =D5+D6+D7 -> 6682.0043 | E8: =E5+E6+E7 -> 12833.127 | F8: =F5+F6+F7 -> 23721.371 | G8: =G5+G6+G7 -> 42339.585 | H8: =H5+H6+H7 -> 72674.505
B10: 유형자산 | D10: 1000 | E10: 1000 | F10: 1000 | G10: 1000 | H10: 1000
B11: 무형자산 (프로그램) | D11: 0 | E11: 0 | F11: 0 | G11: 0 | H11: 0
B12: 기타비유동자산 | D12: 200 | E12: 200 | F12: 200 | G12: 200 | H12: 200
B13: 비유동자산 합계 | D13: =D10+D11+D12 -> 1200 | E13: =E10+E11+E12 -> 1200 | F13: =F10+F11+F12 -> 1200 | G13: =G10+G11+G12 -> 1200 | H13: =H10+H11+H12 -> 1200
B15: 자산총계 | D15: =D8+D13 -> 7882.0043 | E15: =E8+E13 -> 14033.127 | F15: =F8+F13 -> 24921.371 | G15: =G8+G13 -> 43539.585 | H15: =H8+H13 -> 73874.505
B17: 부채 및 자본 (Liabilities & Equity)
B18: 매입채무 | D18: =Model!M8/12*1.5 -> 1323.35 | E18: =Model!N8/12*1.5 -> 3226.1888 | F18: =Model!O8/12*1.5 -> 6188.9504 | G18: =Model!P8/12*1.5 -> 10237.042 | H18: =Model!Q8/12*1.5 -> 15600.508
B19: 기타유동부채 | D19: 300 | E19: 300 | F19: 300 | G19: 300 | H19: 300
B20: 유동부채 합계 | D20: =D18+D19 -> 1623.35 | E20: =E18+E19 -> 3526.1888 | F20: =F18+F19 -> 6488.9504 | G20: =G18+G19 -> 10537.042 | H20: =H18+H19 -> 15900.508
B22: 장기차입금 | D22: 0 | E22: 0 | F22: 0 | G22: 0 | H22: 0
B23: 기타비유동부채 | D23: 100 | E23: 100 | F23: 100 | G23: 100 | H23: 100
B24: 비유동부채 합계 | D24: =D22+D23 -> 100 | E24: =E22+E23 -> 100 | F24: =F22+F23 -> 100 | G24: =G22+G23 -> 100 | H24: =H22+H23 -> 100
B26: 부채총계 | D26: =D20+D24 -> 1723.35 | E26: =E20+E24 -> 3626.1888 | F26: =F20+F24 -> 6588.9504 | G26: =G20+G24 -> 10637.042 | H26: =H20+H24 -> 16000.508
B28: 자본금 | D28: 5000 | E28: 5000 | F28: 5000 | G28: 5000 | H28: 5000
B29: 이익잉여금 | D29: =IS!D23 -> 1458.6543 | E29: =D29+IS!E23 -> 5906.9383 | F29: =E29+IS!F23 -> 13932.42 | G29: =F29+IS!G23 -> 28502.543 | H29: =G29+IS!H23 -> 53473.997
B30: 자본총계 | D30: =D28+D29 -> 6458.6543 | E30: =E28+E29 -> 10906.938 | F30: =F28+F29 -> 18932.42 | G30: =G28+G29 -> 33502.543 | H30: =H28+H29 -> 58473.997
B32: 부채+자본총계 | D32: =D26+D30 -> 8182.0043 | E32: =E26+E30 -> 14533.127 | F32: =F26+F30 -> 25521.371 | G32: =G26+G30 -> 44139.585 | H32: =H26+H30 -> 74474.505

Sheet CF
B1: 현금흐름표 (Cash Flow Statement)
B2: KRW in millions
B3: 구분 | D3: 2026 | E3: 2027 | F3: 2028 | G3: 2029 | H3: 2030
B4: I. 영업활동 현금흐름
B5: 당기순이익 | D5: =IS!D23 -> 1458.6543 | E5: =IS!E23 -> 4448.284 | F5: =IS!F23 -> 8025.4819 | G5: =IS!G23 -> 14570.122 | H5: =IS!H23 -> 24971.454
B6: 감가상각비 (가산) | D6: =Model!M12 -> 200 | E6: =Model!N12 -> 300 | F6: =Model!O12 -> 400 | G6: =Model!P12 -> 500 | H6: =Model!Q12 -> 500
B7: 매출채권 증감 | D7: =-BS!D6 -> -2358.1 | E7: =-(BS!E6-BS!D6) -> -3598.6142 | F7: =-(BS!F6-BS!E6) -> -5369.8903 | G7: =-(BS!G6-BS!F6) -> -7743.2922 | H7: =-(BS!H6-BS!G6) -> -10760.379
B8: 매입채무 증감 | D8: =BS!D18 -> 1323.35 | E8: =BS!E18-BS!D18 -> 1902.8388 | F8: =BS!F18-BS!E18 -> 2962.7616 | G8: =BS!G18-BS!F18 -> 4048.0917 | H8: =BS!H18-BS!G18 -> 5363.4657
B9: 기타유동자산 증감 | D9: =-BS!D7 -> -500 | E9: =-(BS!E7-BS!D7) -> 0 | F9: =-(BS!F7-BS!E7) -> 0 | G9: =-(BS!G7-BS!F7) -> 0 | H9: =-(BS!H7-BS!G7) -> 0
B10: 기타유동부채 증감 | D10: =BS!D19 -> 300 | E10: =BS!E19-BS!D19 -> 0 | F10: =BS!F19-BS!E19 -> 0 | G10: =BS!G19-BS!F19 -> 0 | H10: =BS!H19-BS!G19 -> 0
B11: 영업활동 현금흐름 | D11: =SUM(D5:D10) -> 423.90426 | E11: =SUM(E5:E10) -> 3052.5086 | F11: =SUM(F5:F10) -> 6018.3533 | G11: =SUM(G5:G10) -> 11374.922 | H11: =SUM(H5:H10) -> 20074.541
B13: II. 투자활동 현금흐름
B14: CAPEX | D14: =-Model!M264 -> -500 | E14: =-Model!N264 -> -500 | F14: =-Model!O264 -> -500 | G14: =-Model!P264 -> -500 | H14: =-Model!Q264 -> -500
B15: 유형자산 증감 | D15: =-BS!D10 -> -1000 | E15: =-(BS!E10-BS!D10) -> 0 | F15: =-(BS!F10-BS!E10) -> 0 | G15: =-(BS!G10-BS!F10) -> 0 | H15: =-(BS!H10-BS!G10) -> 0
B16: 기타비유동자산 증감 | D16: =-BS!D12 -> -200 | E16: =-(BS!E12-BS!D12) -> 0 | F16: =-(BS!F12-BS!E12) -> 0 | G16: =-(BS!G12-BS!F12) -> 0 | H16: =-(BS!H12-BS!G12) -> 0
B17: 투자활동 현금흐름 | D17: =SUM(D14:D16) -> -1700 | E17: =SUM(E14:E16) -> -500 | F17: =SUM(F14:F16) -> -500 | G17: =SUM(G14:G16) -> -500 | H17: =SUM(H14:H16) -> -500
B19: III. 재무활동 현금흐름
B20: 신규 투자유치 | D20: 5000 | E20: 0 | F20: 0 | G20: 0 | H20: 0
B21: 차입금 증감 | D21: 0 | E21: 0 | F21: 0 | G21: 0 | H21: 0
B22: 기타비유동부채 증감 | D22: =BS!D23 -> 100 | E22: =BS!E23-BS!D23 -> 0 | F22: =BS!F23-BS!E23 -> 0 | G22: =BS!G23-BS!F23 -> 0 | H22: =BS!H23-BS!G23 -> 0
B23: 재무활동 현금흐름 | D23: =SUM(D20:D22) -> 5100 | E23: =SUM(E20:E22) -> 0 | F23: =SUM(F20:F22) -> 0 | G23: =SUM(G20:G22) -> 0 | H23: =SUM(H20:H22) -> 0
B25: 현금 순증감 | D25: =D11+D17+D23 -> 3823.9043 | E25: =E11+E17+E23 -> 2552.5086 | F25: =F11+F17+F23 -> 5518.3533 | G25: =G11+G17+G23 -> 10874.922 | H25: =H11+H17+H23 -> 19574.541
B26: 기초 현금 | D26: 0 | E26: =D27 -> 3823.9043 | F26: =E27 -> 6376.4129 | G26: =F27 -> 11894.766 | H26: =G27 -> 22769.688
B27: 기말 현금 | D27: =D26+D25 -> 3823.9043 | E27: =E26+E25 -> 6376.4129 | F27: =F26+F25 -> 11894.766 | G27: =G26+G25 -> 22769.688 | H27: =H26+H25 -> 42344.229

Sheet Investment Flow
B1: 투자금 흐름 분석 (Investment Flow Analysis)
B2: KRW in millions
B3: 구분 | D3: 2026 | E3: 2027 | F3: 2028 | G3: 2029 | H3: 2030
B4: 1. 투자금 집행 계획 (운영비)
B5: 투자금 유입 (50억) | D5: 5000 | E5: 0 | F5: 0 | G5: 0 | H5: 0
B7: 집행 항목:
B8: 인건비 (초기인력 9명) | D8: 1800 | E8: 0 | F8: 0 | G8: 0 | H8: 0
B9: 사무실 임차/보증금 | D9: 600 | E9: 0 | F9: 0 | G9: 0 | H9: 0
B10: 아티스트 트레이닝비 | D10: 1200 | E10: 0 | F10: 0 | G10: 0 | H10: 0
B11: 마케팅/프로모션 | D11: 800 | E11: 0 | F11: 0 | G11: 0 | H11: 0
B12: 기타 운영비 | D12: 600 | E12: 0 | F12: 0 | G12: 0 | H12: 0
B13: 투자 집행 합계 | D13: =D8+D9+D10+D11+D12 -> 5000 | E13: =E8+E9+E10+E11+E12 -> 0 | F13: =F8+F9+F10+F11+F12 -> 0 | G13: =G8+G9+G10+G11+G12 -> 0 | H13: =H8+H9+H10+H11+H12 -> 0
B14: 잔여 투자금 | D14: =D5-D13 -> 0 | E14: =E5-E13 -> 0 | F14: =F5-F13 -> 0 | G14: =G5-G13 -> 0 | H14: =H5-H13 -> 0
B16: 2. 투자 수익 분석
B17: 매출액 | D17: =Model!M7 -> 14148.6 | E17: =Model!N7 -> 35740.285 | F17: =Model!O7 -> 67959.627 | G17: =Model!P7 -> 114419.38 | H17: =Model!Q7 -> 178981.66
B18: 영업이익 (EBIT) | D18: =Model!M13 -> 1816.2506 | E18: =Model!N13 -> 5595.8079 | F18: =Model!O13 -> 10118.182 | G18: =Model!P13 -> 18392.064 | H18: =Model!Q13 -> 31871.852
B19: 당기순이익 | D19: =IS!D23 -> 1458.6543 | E19: =IS!E23 -> 4448.284 | F19: =IS!F23 -> 8025.4819 | G19: =IS!G23 -> 14570.122 | H19: =IS!H23 -> 24971.454
B20: 누적 순이익 | D20: =D19 -> 1458.6543 | E20: =D20+E19 -> 5906.9383 | F20: =E20+F19 -> 13932.42 | G20: =F20+G19 -> 28502.543 | H20: =G20+H19 -> 53473.997
B21: 투자금 회수율 (누적NI/투자금) | D21: =D20/5000 -> 0.29173085 | E21: =E20/5000 -> 1.1813877 | F21: =F20/5000 -> 2.786484 | G21: =G20/5000 -> 5.7005085 | H21: =H20/5000 -> 10.694799
B23: FCFF | D23: =#REF! -> #REF! | E23: =#REF! -> #REF! | F23: =#REF! -> #REF! | G23: =#REF! -> #REF! | H23: =#REF! -> #REF!
B24: 누적 FCFF | D24: =D23 -> #REF! | E24: =D24+E23 -> #REF! | F24: =E24+F23 -> #REF! | G24: =F24+G23 -> #REF! | H24: =G24+H23 -> #REF!
B25: 투자금 대비 FCFF 회수율 | D25: =D24*0.25/5000 -> #REF! | E25: =E24*0.25/5000 -> #REF! | F25: =F24*0.25/5000 -> #REF! | G25: =G24*0.25/5000 -> #REF! | H25: =H24*0.25/5000 -> #REF!
B28: 3. 투자 가치 요약
B29: 투자금액 | D29: 5,000M KRW (50억원)
B30: 투자 시점 | D30: 2026년 초
B31: 자금 용도 | D31: 인건비 36%, 트레이닝 24%, 마케팅 16%, 임차 12%, 기타 12%
B32: BEP 도달 예상 | D32: 2027년 (EBIT 기준, 당기순이익 기준)
B33: 5년 누적 FCFF | D33: =D23+E23+F23+G23+H23 -> #REF!
B34: 투자배수 (MOIC) | D34: =H24*0.25/5000 -> #REF!
B35: 지분율 | D35: 25% (50억/200억)

Sheet KPI
B1: Key Performance Indicator
B3: KRW in millions
E6: 추정
B7: 구분 | E7: 2026 | F7: 2027 | G7: 2028 | H7: 2029 | I7: 2030
B8: 음반 발매수 (전체) | E8: =Model!M52+Model!M129+Model!M165 -> 1 | F8: =Model!N52+Model!N129+Model!N165 -> 4 | G8: =Model!O52+Model!O129+Model!O165 -> 6 | H8: =Model!P52+Model!P129+Model!P165 -> 7 | I8: =Model!Q52+Model!Q129+Model!Q165 -> 9
B9: 음반 판매수 (전체) | E9: =Model!M52*Model!M53+Model!M129*Model!M130+Model!M165*Model!M166 -> 130000 | F9: =Model!N52*Model!N53+Model!N129*Model!N130+Model!N165*Model!N166 -> 465000 | G9: =Model!O52*Model!O53+Model!O129*Model!O130+Model!O165*Model!O166 -> 810000 | H9: =Model!P52*Model!P53+Model!P129*Model!P130+Model!P165*Model!P166 -> 1260000 | I9: =Model!Q52*Model!Q53+Model!Q129*Model!Q130+Model!Q165*Model!Q166 -> 1755000
B10: 스트리밍 수 (백만, TRAUMA) | E10: =Model!M59+Model!M133+Model!M169 -> 80 | F10: =Model!N59+Model!N133+Model!N169 -> 235 | G10: =Model!O59+Model!O133+Model!O169 -> 340 | H10: =Model!P59+Model!P133+Model!P169 -> 440 | I10: =Model!Q59+Model!Q133+Model!Q169 -> 540
B11: 콘서트 관객 수 (전체) | E11: =Model!M68+Model!M138+Model!M174 -> 0 | F11: =Model!N68+Model!N138+Model!N174 -> 27000 | G11: =Model!O68+Model!O138+Model!O174 -> 87000 | H11: =Model!P68+Model!P138+Model!P174 -> 190000 | I11: =Model!Q68+Model!Q138+Model!Q174 -> 310000
B12: 광고 촬영수 (TRAUMA) | E12: =Model!M74 -> 1 | F12: =Model!N74 -> 1.5 | G12: =Model!O74 -> 2 | H12: =Model!P74 -> 2.5 | I12: =Model!Q74 -> 3
B13: 행사 수 (TRAUMA) | E13: =Model!M86 -> 30 | F13: =Model!N86 -> 35 | G13: =Model!O86 -> 38 | H13: =Model!P86 -> 40 | I13: =Model!Q86 -> 45
B14: 팬 플랫폼 가입자 (전체) | E14: =Model!M100+Model!M148+Model!M184 -> 115000 | F14: =Model!N100+Model!N148+Model!N184 -> 250000 | G14: =Model!O100+Model!O148+Model!O184 -> 430000 | H14: =Model!P100+Model!P148+Model!P184 -> 630000 | I14: =Model!Q100+Model!Q148+Model!Q184 -> 830000
B15: 직원 수 | E15: =Model!M239 -> 12 | F15: =Model!N239 -> 31 | G15: =Model!O239 -> 60 | H15: =Model!P239 -> 101 | I15: =Model!Q239 -> 158
B16: 매출액 (백만원) | E16: =Model!M7 -> 14148.6 | F16: =Model!N7 -> 35740.285 | G16: =Model!O7 -> 67959.627 | H16: =Model!P7 -> 114419.38 | I16: =Model!Q7 -> 178981.66
B17: 영업이익 (백만원) | E17: =Model!M13 -> 1816.2506 | F17: =Model!N13 -> 5595.8079 | G17: =Model!O13 -> 10118.182 | H17: =Model!P13 -> 18392.064 | I17: =Model!Q13 -> 31871.852
B18: 영업이익률 | E18: =Model!M17 -> 0.12836964 | F18: =Model!N17 -> 0.15656864 | G18: =Model!O17 -> 0.14888519 | H18: =Model!P17 -> 0.16074256 | I18: =Model!Q17 -> 0.17807329

Sheet 2. Reference▶
B8: Section <2>
B9: <Reference>

Sheet 음반원
B1: 음반/음원 매출
B2: Value analysis as of August 31, 2025
B3: KRW in millions
E4: 4 | F4: 5
B7: 걸그룹 음반 판매량
B9: 걸그룹 | D9: 2021 | E9: 2022 | F9: 2023 | G9: 2024 | H9: 합계 | I9: 판매량합계 | J9: 평균 판매량 | K9: 구분 | M9: 구분 | N9: 판매량
B10: 아이브 | D10: =COUNTA(D26:D31) -> 1 | E10: =COUNTA(E26:E31) -> 2 | F10: =COUNTA(F26:F31) -> 2 | G10: =COUNTA(G26:G31) -> 1 | H10: =SUM(D10:G10) -> 6 | I10: =SUM(D26:G31) -> 8957249 | J10: =I10/H10 -> 1492874.8 | K10: BEST | M10: BEST | N10: =AVERAGEIF($K$10:$K$17,M10,$J$10:$J$17) -> 1565413.4
B11: 에스파 | D11: =COUNTA(D33:D38) -> 1 | E11: =COUNTA(E33:E38) -> 1 | F11: =COUNTA(F33:F38) -> 2 | G11: =COUNTA(G33:G38) -> 2 | H11: =SUM(D11:G11) -> 6 | I11: =SUM(D33:G38) -> 8744139 | J11: =I11/H11 -> 1457356.5 | K11: BEST | M11: BASE | N11: =AVERAGEIF($K$10:$K$17,M11,$J$10:$J$17) -> 647810
B12: 뉴진스 | D12: =COUNTA(D40:D43) -> 0 | E12: =COUNTA(E40:E43) -> 1 | F12: =COUNTA(F40:F43) -> 2 | G12: =COUNTA(G40:G43) -> 1 | H12: =SUM(D12:G12) -> 4 | I12: =SUM(D40:G43) -> 6984036 | J12: =I12/H12 -> 1746009 | K12: BEST | M12: WORST | N12: =AVERAGEIF($K$10:$K$17,M12,$J$10:$J$17) -> 140503.01
B13: 엔믹스 | D13: =COUNTA(D45:D50) -> 0 | E13: =COUNTA(E45:E50) -> 2 | F13: =COUNTA(F45:F50) -> 2 | G13: =COUNTA(G45:G50) -> 2 | H13: =SUM(D13:G13) -> 6 | I13: =SUM(D45:G50) -> 4317723 | J13: =I13/H13 -> 719620.5 | K13: BASE
B14: 아일릿 | D14: =COUNTA(D52:D53) -> 0 | E14: =COUNTA(E52:E53) -> 0 | F14: =COUNTA(F52:F53) -> 0 | G14: =COUNTA(G52:G53) -> 2 | H14: =SUM(D14:G14) -> 2 | I14: =SUM(D52:G53) -> 1151999 | J14: =I14/H14 -> 575999.5 | K14: BASE
B15: 케플러 | D15: =COUNTA(D55:D61) -> 0 | E15: =COUNTA(E55:E61) -> 3 | F15: =COUNTA(F55:F61) -> 2 | G15: =COUNTA(G55:G61) -> 2 | H15: =SUM(D15:G15) -> 7 | I15: =SUM(D55:G61) -> 1651555 | J15: =I15/H15 -> 235936.43 | K15: WORST
B16: 트리플에스 | D16: =COUNTA(D63:D69) -> 0 | E16: =COUNTA(E63:E69) -> 1 | F16: =COUNTA(F63:F69) -> 4 | G16: =COUNTA(G63:G69) -> 2 | H16: =SUM(D16:G16) -> 7 | I16: =SUM(D63:G69) -> 729546 | J16: =I16/H16 -> 104220.86 | K16: WORST
B17: 키스오브라이프 | D17: =COUNTA(D71:D74) -> 0 | E17: =COUNTA(E71:E74) -> 0 | F17: =COUNTA(F71:F74) -> 2 | G17: =COUNTA(G71:G74) -> 2 | H17: =SUM(D17:G17) -> 4 | I17: =SUM(D71:G74) -> 325407 | J17: =I17/H17 -> 81351.75 | K17: WORST
B18: Total | D18: =SUBTOTAL(9,D10:D17) -> 2 | E18: =SUBTOTAL(9,E10:E17) -> 10 | F18: =SUBTOTAL(9,F10:F17) -> 16 | G18: =SUBTOTAL(9,G10:G17) -> 14 | H18: =SUBTOTAL(9,H10:H17) -> 42
B20: Source : https://chartndata.tistory.com/8
B22: 써클차트
B24: 구분 | D24: 2021 | E24: 2022 | F24: 2023 | G24: 2024
B25: 아이브
B26: ELEVEN | D26: 574061
B27: LOVE DIVE | E27: 1041801
B28: I've IVE | F28: 1720057
B29: IVE SWITCH | G29: 1745222
B30: After Like | E30: 1768220
B31: I've MINE | F31: 2107888
B32: 에스파
B33: Savage | D33: 822655
B34: Girls | E34: 1880677
B35: Drama | F35: 1355469
B36: My World | F36: 2172570
B37: Whiplash | G37: 1103799
B38: Armageddon | G38: 1408969
B39: 뉴진스
B40: New Jeans | E40: 1732952
B41: OMG | F41: 1774798
B42: Get Up | F42: 2232598
B43: How Sweet | G43: 1243688
B44: 엔믹스
B45: AD MARE | E45: 500543
B46: ENTWURF | E46: 569763
B47: Expergo | F47: 953087
B48: Midsummer | F48: 850607
B49: Stick Out | G49: 652024
B50: Break | G50: 791699
B51: 아일릿
B52: I'll like you | G52: 458702
B53: Super real me | G53: 693297
B54: 케플러
B55: Shooting Star | G55: 118737
B56: Galileo | F56: 144425
B57: Tipi-tap | G57: 177684
B58: Giddy | F58: 193730
B59: We Fresh | E59: 267476
B60: Up! | E60: 353401
B61: WA DA DA | E61: 396102
B62: 트리플에스
B63: Acid Angel | E63: 26274
B64: Evolution | F64: 31101
B65: Lovelution | F65: 33629
B66: Assemble | F66: 49361
B67: Krystal eyes | F67: 51972
B68: Assemble24 | G68: 202650
B69: Performante | G69: 334559
B70: 키스오브라이프
B71: Shhh | F71: 28371
B72: Bad News | F72: 76408
B73: Midas Touch | G73: 100904
B74: Lose Yourself | G74: 119724
B76: Source : https://chartndata.tistory.com/8
B79: 음원스트리밍 시장점유율
B81: 구분 | C81: 점유율
B82: 스포티파이 | C82: 0.32
B83: 텐센트뮤직 | C83: 0.14
B84: 애플뮤직 | C84: 0.13
B85: 아마존뮤직 | C85: 0.11
B86: 유튜브뮤직 | C86: 0.1
B87: 기타 | C87: 0.2
B89: Source : https://www.hankyung.com/article/202410156254i
B92: 플랫폼별 정산금액
B94: 구분 | C94: 정산금액(USD) | D94: KRW | F94: 환율
B95: 스포티파이 | C95: 0.004 | D95: =C95*$F$95 -> 5.88 | F95: 1470 | G95: 2024년말
B96: 애플뮤직 | C96: 0.0078 | D96: =C96*$F$95 -> 11.466
B97: 유튜브뮤직 | C97: 0.008 | D97: =C97*$F$95 -> 11.76
B98: 평균 | C98: =AVERAGE(C95:C97) -> 0.0066 | D98: =ROUND(AVERAGE(D95:D97),) -> 10
B100: Source : https://routenote.com/kr/blog/
B103: K-POP 누적 음원 스트리밍 수 (18년 이후 데뷔 걸그룹, Spotify, 2024년 12월 기준)
G104: 45657
B105: 구분 | C105: 곡명 | D105: 발매일 | E105: 누적스트리밍수 | F105: 구간 | G105: 기간 | H105: 월평균 | I105: 구분
B106: 아일릿 | C106: Magnetic | D106: 45352 | E106: 493047000 | F106: 4억+ | G106: =DATEDIF(D106,$G$104,"m") -> 9 | H106: =E106/G106 -> 54783000 | I106: Base | K106: Best | L106: =AVERAGEIF($I$106:$I$152,K106,$H$106:$H$152) -> 21638035
B107: 에스파 | C107: Whiplash | D107: 45566 | E107: 102251000 | F107: 1억+ | G107: =DATEDIF(D107,$G$104,"m") -> 2 | H107: =E107/G107 -> 51125500 | I107: Best | K107: Base | L107: =AVERAGEIF($I$106:$I$152,K107,$H$106:$H$152) -> 14385324
B108: 피프티피프티 | C108: Cupid | D108: 44958 | E108: 939269000 | F108: 4억+ | G108: =DATEDIF(D108,$G$104,"m") -> 22 | H108: =E108/G108 -> 42694045 | I108: Best | K108: Worst | L108: =AVERAGEIF($I$106:$I$152,K108,$H$106:$H$152) -> 2654318.4
B109: 뉴진스 | C109: Super Shy | D109: 45108 | E109: 658157000 | F109: 4억+ | G109: =DATEDIF(D109,$G$104,"m") -> 17 | H109: =E109/G109 -> 38715118 | I109: Best
B110: 르세라핌 | C110: Crazy | D110: 45505 | E110: 147011000 | F110: 1억+ | G110: =DATEDIF(D110,$G$104,"m") -> 4 | H110: =E110/G110 -> 36752750 | I110: Best
B111: 에스파 | C111: Supernova | D111: 45413 | E111: 234288000 | F111: 2억+ | G111: =DATEDIF(D111,$G$104,"m") -> 7 | H111: =E111/G111 -> 33469714 | I111: Best
B112: 뉴진스 | C112: OMG | D112: 44927 | E112: 761183000 | F112: 4억+ | G112: =DATEDIF(D112,$G$104,"m") -> 23 | H112: =E112/G112 -> 33094913 | I112: Best
B113: 키오라 | C113: Igloo | D113: 45566 | E113: 62007000 | F113: 5천만+ | G113: =DATEDIF(D113,$G$104,"m") -> 2 | H113: =E113/G113 -> 31003500 | I113: Base
B114: 뉴진스 | C114: Ditto | D114: 44896 | E114: 702736000 | F114: 4억+ | G114: =DATEDIF(D114,$G$104,"m") -> 24 | H114: =E114/G114 -> 29280667 | I114: Best
B115: 르세라핌 | C115: Perfect Night | D115: 45200 | E115: 379761000 | F115: 2억+ | G115: =DATEDIF(D115,$G$104,"m") -> 14 | H115: =E115/G115 -> 27125786 | I115: Best
B116: 르세라핌 | C116: Smart | D116: 45323 | E116: 270190000 | F116: 2억+ | G116: =DATEDIF(D116,$G$104,"m") -> 10 | H116: =E116/G116 -> 27019000 | I116: Best
B117: 에스파 | C117: Armageddon | D117: 45413 | E117: 180523000 | F117: 1억+ | G117: =DATEDIF(D117,$G$104,"m") -> 7 | H117: =E117/G117 -> 25789000 | I117: Best
...

Sheet 콘서트
B1: 콘서트(공연) 매출
B2: Value analysis as of August 31, 2025
B3: KRW in millions
E4: 4 | F4: 5
E6: Business Plan | P6: PwC_Base | AA6: PwC_Worst
E7: 개최 수 | J7: 관객 수 | P7: 개최 수_사업계획 50% | U7: 관객 수 | AA7: 개최 수_사업계획 70%, 스타디움 제외 | AF7: 관객 수
B8: 구분 | C8: 콘서트분류 | D8: 좌석수 | E8: 2026 | F8: 2027 | G8: 2028 | H8: 2029 | I8: 2030 | J8: 2026 | K8: 2027 | L8: 2028 | M8: 2029 | N8: 2030 | P8: 2026 | Q8: 2027 | R8: 2028 | S8: 2029 | T8: 2030 | U8: 2026 | V8: 2027 | W8: 2028 | X8: 2029 | Y8: 2030 | AA8: 2026 | AB8: 2027 | AC8: 2028 | AD8: 2029 | AE8: 2030 | AF8: 2026 | AG8: 2027 | AH8: 2028 | AI8: 2029 | AJ8: 2030
B9: JTOPT | C9: 홀급 | D9: 5000 | E9: 0 | F9: 1 | G9: 1 | H9: 3 | I9: 20 | J9: =SUMPRODUCT($D9,E9) -> 0 | K9: =SUMPRODUCT($D9,F9) -> 5000 | L9: =SUMPRODUCT($D9,G9) -> 5000 | M9: =SUMPRODUCT($D9,H9) -> 15000 | N9: =SUMPRODUCT($D9,I9) -> 100000 | P9: =ROUND(E9/2,) -> 0 | Q9: =ROUND(F9/2,) -> 1 | R9: =ROUND(G9/2,) -> 1 | S9: =ROUND(H9/2,) -> 2 | T9: =ROUND(I9/2,) -> 10 | U9: =SUMPRODUCT($D9,P9) -> 0 | V9: =SUMPRODUCT($D9,Q9) -> 5000 | W9: =SUMPRODUCT($D9,R9) -> 5000 | X9: =SUMPRODUCT($D9,S9) -> 10000 | Y9: =SUMPRODUCT($D9,T9) -> 50000 | AA9: =IF(E9=0,0,IF(ROUND(E9*0.3,)<1,1,ROUND(E9*0.3,))) -> 0 | AB9: =IF(F9=0,0,IF(ROUND(F9*0.3,)<1,1,ROUND(F9*0.3,))) -> 1 | AC9: =IF(G9=0,0,IF(ROUND(G9*0.3,)<1,1,ROUND(G9*0.3,))) -> 1 | AD9: =IF(H9=0,0,IF(ROUND(H9*0.3,)<1,1,ROUND(H9*0.3,))) -> 1 | AE9: =IF(I9=0,0,IF(ROUND(I9*0.3,)<1,1,ROUND(I9*0.3,))) -> 6 | AF9: =SUMPRODUCT($D9,AA9) -> 0 | AG9: =SUMPRODUCT($D9,AB9) -> 5000 | AH9: =SUMPRODUCT($D9,AC9) -> 5000 | AI9: =SUMPRODUCT($D9,AD9) -> 5000 | AJ9: =SUMPRODUCT($D9,AE9) -> 30000
B10: JTOPT | C10: 아레나급 | D10: 15000 | E10: 0 | F10: 0 | G10: 2 | H10: 5 | I10: 10 | J10: =SUMPRODUCT($D10,E10) -> 0 | K10: =SUMPRODUCT($D10,F10) -> 0 | L10: =SUMPRODUCT($D10,G10) -> 30000 | M10: =SUMPRODUCT($D10,H10) -> 75000 | N10: =SUMPRODUCT($D10,I10) -> 150000 | P10: =ROUND(E10/2,) -> 0 | Q10: =ROUND(F10/2,) -> 0 | R10: =ROUND(G10/2,) -> 1 | S10: =ROUND(H10/2,) -> 3 | T10: =ROUND(I10/2,) -> 5 | U10: =SUMPRODUCT($D10,P10) -> 0 | V10: =SUMPRODUCT($D10,Q10) -> 0 | W10: =SUMPRODUCT($D10,R10) -> 15000 | X10: =SUMPRODUCT($D10,S10) -> 45000 | Y10: =SUMPRODUCT($D10,T10) -> 75000 | AA10: =IF(E10=0,0,IF(ROUND(E10*0.3,)<1,1,ROUND(E10*0.3,))) -> 0 | AB10: =IF(F10=0,0,IF(ROUND(F10*0.3,)<1,1,ROUND(F10*0.3,))) -> 0 | AC10: =IF(G10=0,0,IF(ROUND(G10*0.3,)<1,1,ROUND(G10*0.3,))) -> 1 | AD10: =IF(H10=0,0,IF(ROUND(H10*0.3,)<1,1,ROUND(H10*0.3,))) -> 2 | AE10: =IF(I10=0,0,IF(ROUND(I10*0.3,)<1,1,ROUND(I10*0.3,))) -> 3 | AF10: =SUMPRODUCT($D10,AA10) -> 0 | AG10: =SUMPRODUCT($D10,AB10) -> 0 | AH10: =SUMPRODUCT($D10,AC10) -> 15000 | AI10: =SUMPRODUCT($D10,AD10) -> 30000 | AJ10: =SUMPRODUCT($D10,AE10) -> 45000
B11: JTOPT | C11: 돔급 | D11: 50000 | E11: 0 | F11: 0 | G11: 0 | H11: 5 | I11: 10 | J11: =SUMPRODUCT($D11,E11) -> 0 | K11: =SUMPRODUCT($D11,F11) -> 0 | L11: =SUMPRODUCT($D11,G11) -> 0 | M11: =SUMPRODUCT($D11,H11) -> 250000 | N11: =SUMPRODUCT($D11,I11) -> 500000 | P11: =ROUND(E11/2,) -> 0 | Q11: =ROUND(F11/2,) -> 0 | R11: =ROUND(G11/2,) -> 0 | S11: =ROUND(H11/2,) -> 3 | T11: =ROUND(I11/2,) -> 5 | U11: =SUMPRODUCT($D11,P11) -> 0 | V11: =SUMPRODUCT($D11,Q11) -> 0 | W11: =SUMPRODUCT($D11,R11) -> 0 | X11: =SUMPRODUCT($D11,S11) -> 150000 | Y11: =SUMPRODUCT($D11,T11) -> 250000 | AA11: =IF(E11=0,0,IF(ROUND(E11*0.3,)<1,1,ROUND(E11*0.3,))) -> 0 | AB11: =IF(F11=0,0,IF(ROUND(F11*0.3,)<1,1,ROUND(F11*0.3,))) -> 0 | AC11: =IF(G11=0,0,IF(ROUND(G11*0.3,)<1,1,ROUND(G11*0.3,))) -> 0 | AD11: =IF(H11=0,0,IF(ROUND(H11*0.3,)<1,1,ROUND(H11*0.3,))) -> 2 | AE11: =IF(I11=0,0,IF(ROUND(I11*0.3,)<1,1,ROUND(I11*0.3,))) -> 3 | AF11: =SUMPRODUCT($D11,AA11) -> 0 | AG11: =SUMPRODUCT($D11,AB11) -> 0 | AH11: =SUMPRODUCT($D11,AC11) -> 0 | AI11: =SUMPRODUCT($D11,AD11) -> 100000 | AJ11: =SUMPRODUCT($D11,AE11) -> 150000
B12: JTOPT | C12: 스타디움급 | D12: 80000 | E12: 0 | F12: 0 | G12: 0 | H12: 0 | I12: 5 | J12: =SUMPRODUCT($D12,E12) -> 0 | K12: =SUMPRODUCT($D12,F12) -> 0 | L12: =SUMPRODUCT($D12,G12) -> 0 | M12: =SUMPRODUCT($D12,H12) -> 0 | N12: =SUMPRODUCT($D12,I12) -> 400000 | P12: =ROUND(E12/2,) -> 0 | Q12: =ROUND(F12/2,) -> 0 | R12: =ROUND(G12/2,) -> 0 | S12: =ROUND(H12/2,) -> 0 | T12: =ROUND(I12/2,) -> 3 | U12: =SUMPRODUCT($D12,P12) -> 0 | V12: =SUMPRODUCT($D12,Q12) -> 0 | W12: =SUMPRODUCT($D12,R12) -> 0 | X12: =SUMPRODUCT($D12,S12) -> 0 | Y12: =SUMPRODUCT($D12,T12) -> 240000 | AA12: 0 | AB12: 0 | AC12: 0 | AD12: 0 | AE12: 0 | AF12: =SUMPRODUCT($D12,AA12) -> 0 | AG12: =SUMPRODUCT($D12,AB12) -> 0 | AH12: =SUMPRODUCT($D12,AC12) -> 0 | AI12: =SUMPRODUCT($D12,AD12) -> 0 | AJ12: =SUMPRODUCT($D12,AE12) -> 0
B13: 한국 | C13: 홀급 | D13: 5000 | E13: 0 | F13: 1 | G13: 0 | H13: 0 | I13: 0 | J13: =SUMPRODUCT($D13,E13) -> 0 | K13: =SUMPRODUCT($D13,F13) -> 5000 | L13: =SUMPRODUCT($D13,G13) -> 0 | M13: =SUMPRODUCT($D13,H13) -> 0 | N13: =SUMPRODUCT($D13,I13) -> 0 | P13: =ROUND(E13/2,) -> 0 | Q13: =ROUND(F13/2,) -> 1 | R13: =ROUND(G13/2,) -> 0 | S13: =ROUND(H13/2,) -> 0 | T13: =ROUND(I13/2,) -> 0 | U13: =SUMPRODUCT($D13,P13) -> 0 | V13: =SUMPRODUCT($D13,Q13) -> 5000 | W13: =SUMPRODUCT($D13,R13) -> 0 | X13: =SUMPRODUCT($D13,S13) -> 0 | Y13: =SUMPRODUCT($D13,T13) -> 0 | AA13: =IF(E13=0,0,IF(ROUND(E13*0.3,)<1,1,ROUND(E13*0.3,))) -> 0 | AB13: =IF(F13=0,0,IF(ROUND(F13*0.3,)<1,1,ROUND(F13*0.3,))) -> 1 | AC13: =IF(G13=0,0,IF(ROUND(G13*0.3,)<1,1,ROUND(G13*0.3,))) -> 0 | AD13: =IF(H13=0,0,IF(ROUND(H13*0.3,)<1,1,ROUND(H13*0.3,))) -> 0 | AE13: =IF(I13=0,0,IF(ROUND(I13*0.3,)<1,1,ROUND(I13*0.3,))) -> 0 | AF13: =SUMPRODUCT($D13,AA13) -> 0 | AG13: =SUMPRODUCT($D13,AB13) -> 5000 | AH13: =SUMPRODUCT($D13,AC13) -> 0 | AI13: =SUMPRODUCT($D13,AD13) -> 0 | AJ13: =SUMPRODUCT($D13,AE13) -> 0
B14: 한국 | C14: 아레나급 | D14: 15000 | E14: 0 | F14: 0 | G14: 2 | H14: 2 | I14: 2 | J14: =SUMPRODUCT($D14,E14) -> 0 | K14: =SUMPRODUCT($D14,F14) -> 0 | L14: =SUMPRODUCT($D14,G14) -> 30000 | M14: =SUMPRODUCT($D14,H14) -> 30000 | N14: =SUMPRODUCT($D14,I14) -> 30000 | P14: =ROUND(E14/2,) -> 0 | Q14: =ROUND(F14/2,) -> 0 | R14: =ROUND(G14/2,) -> 1 | S14: =ROUND(H14/2,) -> 1 | T14: =ROUND(I14/2,) -> 1 | U14: =SUMPRODUCT($D14,P14) -> 0 | V14: =SUMPRODUCT($D14,Q14) -> 0 | W14: =SUMPRODUCT($D14,R14) -> 15000 | X14: =SUMPRODUCT($D14,S14) -> 15000 | Y14: =SUMPRODUCT($D14,T14) -> 15000 | AA14: =IF(E14=0,0,IF(ROUND(E14*0.3,)<1,1,ROUND(E14*0.3,))) -> 0 | AB14: =IF(F14=0,0,IF(ROUND(F14*0.3,)<1,1,ROUND(F14*0.3,))) -> 0 | AC14: =IF(G14=0,0,IF(ROUND(G14*0.3,)<1,1,ROUND(G14*0.3,))) -> 1 | AD14: =IF(H14=0,0,IF(ROUND(H14*0.3,)<1,1,ROUND(H14*0.3,))) -> 1 | AE14: =IF(I14=0,0,IF(ROUND(I14*0.3,)<1,1,ROUND(I14*0.3,))) -> 1 | AF14: =SUMPRODUCT($D14,AA14) -> 0 | AG14: =SUMPRODUCT($D14,AB14) -> 0 | AH14: =SUMPRODUCT($D14,AC14) -> 15000 | AI14: =SUMPRODUCT($D14,AD14) -> 15000 | AJ14: =SUMPRODUCT($D14,AE14) -> 15000
B15: 한국 | C15: 돔급 | D15: 50000 | E15: 0 | F15: 0 | G15: 0 | H15: 0 | I15: 1 | J15: =SUMPRODUCT($D15,E15) -> 0 | K15: =SUMPRODUCT($D15,F15) -> 0 | L15: =SUMPRODUCT($D15,G15) -> 0 | M15: =SUMPRODUCT($D15,H15) -> 0 | N15: =SUMPRODUCT($D15,I15) -> 50000 | P15: =ROUND(E15/2,) -> 0 | Q15: =ROUND(F15/2,) -> 0 | R15: =ROUND(G15/2,) -> 0 | S15: =ROUND(H15/2,) -> 0 | T15: =ROUND(I15/2,) -> 1 | U15: =SUMPRODUCT($D15,P15) -> 0 | V15: =SUMPRODUCT($D15,Q15) -> 0 | W15: =SUMPRODUCT($D15,R15) -> 0 | X15: =SUMPRODUCT($D15,S15) -> 0 | Y15: =SUMPRODUCT($D15,T15) -> 50000 | AA15: =IF(E15=0,0,IF(ROUND(E15*0.3,)<1,1,ROUND(E15*0.3,))) -> 0 | AB15: =IF(F15=0,0,IF(ROUND(F15*0.3,)<1,1,ROUND(F15*0.3,))) -> 0 | AC15: =IF(G15=0,0,IF(ROUND(G15*0.3,)<1,1,ROUND(G15*0.3,))) -> 0 | AD15: =IF(H15=0,0,IF(ROUND(H15*0.3,)<1,1,ROUND(H15*0.3,))) -> 0 | AE15: =IF(I15=0,0,IF(ROUND(I15*0.3,)<1,1,ROUND(I15*0.3,))) -> 1 | AF15: =SUMPRODUCT($D15,AA15) -> 0 | AG15: =SUMPRODUCT($D15,AB15) -> 0 | AH15: =SUMPRODUCT($D15,AC15) -> 0 | AI15: =SUMPRODUCT($D15,AD15) -> 0 | AJ15: =SUMPRODUCT($D15,AE15) -> 50000
B16: 한국 | C16: 스타디움급 | D16: 80000 | E16: 0 | F16: 0 | G16: 0 | H16: 0 | I16: 1 | J16: =SUMPRODUCT($D16,E16) -> 0 | K16: =SUMPRODUCT($D16,F16) -> 0 | L16: =SUMPRODUCT($D16,G16) -> 0 | M16: =SUMPRODUCT($D16,H16) -> 0 | N16: =SUMPRODUCT($D16,I16) -> 80000 | P16: =ROUND(E16/2,) -> 0 | Q16: =ROUND(F16/2,) -> 0 | R16: =ROUND(G16/2,) -> 0 | S16: =ROUND(H16/2,) -> 0 | T16: =ROUND(I16/2,) -> 1 | U16: =SUMPRODUCT($D16,P16) -> 0 | V16: =SUMPRODUCT($D16,Q16) -> 0 | W16: =SUMPRODUCT($D16,R16) -> 0 | X16: =SUMPRODUCT($D16,S16) -> 0 | Y16: =SUMPRODUCT($D16,T16) -> 80000 | AA16: 0 | AB16: 0 | AC16: 0 | AD16: 0 | AE16: 0 | AF16: =SUMPRODUCT($D16,AA16) -> 0 | AG16: =SUMPRODUCT($D16,AB16) -> 0 | AH16: =SUMPRODUCT($D16,AC16) -> 0 | AI16: =SUMPRODUCT($D16,AD16) -> 0 | AJ16: =SUMPRODUCT($D16,AE16) -> 0
B17: 일본 | C17: 홀급 | D17: 5000 | E17: 0 | F17: 1 | G17: 3 | H17: 3 | I17: 3 | J17: =SUMPRODUCT($D17,E17) -> 0 | K17: =SUMPRODUCT($D17,F17) -> 5000 | L17: =SUMPRODUCT($D17,G17) -> 15000 | M17: =SUMPRODUCT($D17,H17) -> 15000 | N17: =SUMPRODUCT($D17,I17) -> 15000 | P17: =ROUND(E17/2,) -> 0 | Q17: =ROUND(F17/2,) -> 1 | R17: =ROUND(G17/2,) -> 2 | S17: =ROUND(H17/2,) -> 2 | T17: =ROUND(I17/2,) -> 2 | U17: =SUMPRODUCT($D17,P17) -> 0 | V17: =SUMPRODUCT($D17,Q17) -> 5000 | W17: =SUMPRODUCT($D17,R17) -> 10000 | X17: =SUMPRODUCT($D17,S17) -> 10000 | Y17: =SUMPRODUCT($D17,T17) -> 10000 | AA17: =IF(E17=0,0,IF(ROUND(E17*0.3,)<1,1,ROUND(E17*0.3,))) -> 0 | AB17: =IF(F17=0,0,IF(ROUND(F17*0.3,)<1,1,ROUND(F17*0.3,))) -> 1 | AC17: =IF(G17=0,0,IF(ROUND(G17*0.3,)<1,1,ROUND(G17*0.3,))) -> 1 | AD17: =IF(H17=0,0,IF(ROUND(H17*0.3,)<1,1,ROUND(H17*0.3,))) -> 1 | AE17: =IF(I17=0,0,IF(ROUND(I17*0.3,)<1,1,ROUND(I17*0.3,))) -> 1 | AF17: =SUMPRODUCT($D17,AA17) -> 0 | AG17: =SUMPRODUCT($D17,AB17) -> 5000 | AH17: =SUMPRODUCT($D17,AC17) -> 5000 | AI17: =SUMPRODUCT($D17,AD17) -> 5000 | AJ17: =SUMPRODUCT($D17,AE17) -> 5000
B18: 일본 | C18: 아레나급 | D18: 15000 | E18: 0 | F18: 0 | G18: 2 | H18: 3 | I18: 5 | J18: =SUMPRODUCT($D18,E18) -> 0 | K18: =SUMPRODUCT($D18,F18) -> 0 | L18: =SUMPRODUCT($D18,G18) -> 30000 | M18: =SUMPRODUCT($D18,H18) -> 45000 | N18: =SUMPRODUCT($D18,I18) -> 75000 | P18: =ROUND(E18/2,) -> 0 | Q18: =ROUND(F18/2,) -> 0 | R18: =ROUND(G18/2,) -> 1 | S18: =ROUND(H18/2,) -> 2 | T18: =ROUND(I18/2,) -> 3 | U18: =SUMPRODUCT($D18,P18) -> 0 | V18: =SUMPRODUCT($D18,Q18) -> 0 | W18: =SUMPRODUCT($D18,R18) -> 15000 | X18: =SUMPRODUCT($D18,S18) -> 30000 | Y18: =SUMPRODUCT($D18,T18) -> 45000 | AA18: =IF(E18=0,0,IF(ROUND(E18*0.3,)<1,1,ROUND(E18*0.3,))) -> 0 | AB18: =IF(F18=0,0,IF(ROUND(F18*0.3,)<1,1,ROUND(F18*0.3,))) -> 0 | AC18: =IF(G18=0,0,IF(ROUND(G18*0.3,)<1,1,ROUND(G18*0.3,))) -> 1 | AD18: =IF(H18=0,0,IF(ROUND(H18*0.3,)<1,1,ROUND(H18*0.3,))) -> 1 | AE18: =IF(I18=0,0,IF(ROUND(I18*0.3,)<1,1,ROUND(I18*0.3,))) -> 2 | AF18: =SUMPRODUCT($D18,AA18) -> 0 | AG18: =SUMPRODUCT($D18,AB18) -> 0 | AH18: =SUMPRODUCT($D18,AC18) -> 15000 | AI18: =SUMPRODUCT($D18,AD18) -> 15000 | AJ18: =SUMPRODUCT($D18,AE18) -> 30000
B19: 일본 | C19: 돔급 | D19: 50000 | E19: 0 | F19: 0 | G19: 0 | H19: 0 | I19: 2 | J19: =SUMPRODUCT($D19,E19) -> 0 | K19: =SUMPRODUCT($D19,F19) -> 0 | L19: =SUMPRODUCT($D19,G19) -> 0 | M19: =SUMPRODUCT($D19,H19) -> 0 | N19: =SUMPRODUCT($D19,I19) -> 100000 | P19: =ROUND(E19/2,) -> 0 | Q19: =ROUND(F19/2,) -> 0 | R19: =ROUND(G19/2,) -> 0 | S19: =ROUND(H19/2,) -> 0 | T19: =ROUND(I19/2,) -> 1 | U19: =SUMPRODUCT($D19,P19) -> 0 | V19: =SUMPRODUCT($D19,Q19) -> 0 | W19: =SUMPRODUCT($D19,R19) -> 0 | X19: =SUMPRODUCT($D19,S19) -> 0 | Y19: =SUMPRODUCT($D19,T19) -> 50000 | AA19: =IF(E19=0,0,IF(ROUND(E19*0.3,)<1,1,ROUND(E19*0.3,))) -> 0 | AB19: =IF(F19=0,0,IF(ROUND(F19*0.3,)<1,1,ROUND(F19*0.3,))) -> 0 | AC19: =IF(G19=0,0,IF(ROUND(G19*0.3,)<1,1,ROUND(G19*0.3,))) -> 0 | AD19: =IF(H19=0,0,IF(ROUND(H19*0.3,)<1,1,ROUND(H19*0.3,))) -> 0 | AE19: =IF(I19=0,0,IF(ROUND(I19*0.3,)<1,1,ROUND(I19*0.3,))) -> 1 | AF19: =SUMPRODUCT($D19,AA19) -> 0 | AG19: =SUMPRODUCT($D19,AB19) -> 0 | AH19: =SUMPRODUCT($D19,AC19) -> 0 | AI19: =SUMPRODUCT($D19,AD19) -> 0 | AJ19: =SUMPRODUCT($D19,AE19) -> 50000
B20: 일본 | C20: 스타디움급 | D20: 80000 | E20: 0 | F20: 0 | G20: 0 | H20: 0 | I20: 0 | J20: =SUMPRODUCT($D20,E20) -> 0 | K20: =SUMPRODUCT($D20,F20) -> 0 | L20: =SUMPRODUCT($D20,G20) -> 0 | M20: =SUMPRODUCT($D20,H20) -> 0 | N20: =SUMPRODUCT($D20,I20) -> 0 | P20: =ROUND(E20/2,) -> 0 | Q20: =ROUND(F20/2,) -> 0 | R20: =ROUND(G20/2,) -> 0 | S20: =ROUND(H20/2,) -> 0 | T20: =ROUND(I20/2,) -> 0 | U20: =SUMPRODUCT($D20,P20) -> 0 | V20: =SUMPRODUCT($D20,Q20) -> 0 | W20: =SUMPRODUCT($D20,R20) -> 0 | X20: =SUMPRODUCT($D20,S20) -> 0 | Y20: =SUMPRODUCT($D20,T20) -> 0 | AA20: =IF(E20=0,0,IF(ROUND(E20*0.3,)<1,1,ROUND(E20*0.3,))) -> 0 | AB20: =IF(F20=0,0,IF(ROUND(F20*0.3,)<1,1,ROUND(F20*0.3,))) -> 0 | AC20: =IF(G20=0,0,IF(ROUND(G20*0.3,)<1,1,ROUND(G20*0.3,))) -> 0 | AD20: =IF(H20=0,0,IF(ROUND(H20*0.3,)<1,1,ROUND(H20*0.3,))) -> 0 | AE20: =IF(I20=0,0,IF(ROUND(I20*0.3,)<1,1,ROUND(I20*0.3,))) -> 0 | AF20: =SUMPRODUCT($D20,AA20) -> 0 | AG20: =SUMPRODUCT($D20,AB20) -> 0 | AH20: =SUMPRODUCT($D20,AC20) -> 0 | AI20: =SUMPRODUCT($D20,AD20) -> 0 | AJ20: =SUMPRODUCT($D20,AE20) -> 0
B21: 동남아 | C21: 홀급 | D21: 5000 | E21: 0 | F21: 1 | G21: 5 | H21: 10 | I21: 10 | J21: =SUMPRODUCT($D21,E21) -> 0 | K21: =SUMPRODUCT($D21,F21) -> 5000 | L21: =SUMPRODUCT($D21,G21) -> 25000 | M21: =SUMPRODUCT($D21,H21) -> 50000 | N21: =SUMPRODUCT($D21,I21) -> 50000 | P21: =ROUND(E21/2,) -> 0 | Q21: =ROUND(F21/2,) -> 1 | R21: =ROUND(G21/2,) -> 3 | S21: =ROUND(H21/2,) -> 5 | T21: =ROUND(I21/2,) -> 5 | U21: =SUMPRODUCT($D21,P21) -> 0 | V21: =SUMPRODUCT($D21,Q21) -> 5000 | W21: =SUMPRODUCT($D21,R21) -> 15000 | X21: =SUMPRODUCT($D21,S21) -> 25000 | Y21: =SUMPRODUCT($D21,T21) -> 25000 | AA21: =IF(E21=0,0,IF(ROUND(E21*0.3,)<1,1,ROUND(E21*0.3,))) -> 0 | AB21: =IF(F21=0,0,IF(ROUND(F21*0.3,)<1,1,ROUND(F21*0.3,))) -> 1 | AC21: =IF(G21=0,0,IF(ROUND(G21*0.3,)<1,1,ROUND(G21*0.3,))) -> 2 | AD21: =IF(H21=0,0,IF(ROUND(H21*0.3,)<1,1,ROUND(H21*0.3,))) -> 3 | AE21: =IF(I21=0,0,IF(ROUND(I21*0.3,)<1,1,ROUND(I21*0.3,))) -> 3 | AF21: =SUMPRODUCT($D21,AA21) -> 0 | AG21: =SUMPRODUCT($D21,AB21) -> 5000 | AH21: =SUMPRODUCT($D21,AC21) -> 10000 | AI21: =SUMPRODUCT($D21,AD21) -> 15000 | AJ21: =SUMPRODUCT($D21,AE21) -> 15000
B22: 동남아 | C22: 아레나급 | D22: 15000 | E22: 0 | F22: 0 | G22: 0 | H22: 0 | I22: 5 | J22: =SUMPRODUCT($D22,E22) -> 0 | K22: =SUMPRODUCT($D22,F22) -> 0 | L22: =SUMPRODUCT($D22,G22) -> 0 | M22: =SUMPRODUCT($D22,H22) -> 0 | N22: =SUMPRODUCT($D22,I22) -> 75000 | P22: =ROUND(E22/2,) -> 0 | Q22: =ROUND(F22/2,) -> 0 | R22: =ROUND(G22/2,) -> 0 | S22: =ROUND(H22/2,) -> 0 | T22: =ROUND(I22/2,) -> 3 | U22: =SUMPRODUCT($D22,P22) -> 0 | V22: =SUMPRODUCT($D22,Q22) -> 0 | W22: =SUMPRODUCT($D22,R22) -> 0 | X22: =SUMPRODUCT($D22,S22) -> 0 | Y22: =SUMPRODUCT($D22,T22) -> 45000 | AA22: =IF(E22=0,0,IF(ROUND(E22*0.3,)<1,1,ROUND(E22*0.3,))) -> 0 | AB22: =IF(F22=0,0,IF(ROUND(F22*0.3,)<1,1,ROUND(F22*0.3,))) -> 0 | AC22: =IF(G22=0,0,IF(ROUND(G22*0.3,)<1,1,ROUND(G22*0.3,))) -> 0 | AD22: =IF(H22=0,0,IF(ROUND(H22*0.3,)<1,1,ROUND(H22*0.3,))) -> 0 | AE22: =IF(I22=0,0,IF(ROUND(I22*0.3,)<1,1,ROUND(I22*0.3,))) -> 2 | AF22: =SUMPRODUCT($D22,AA22) -> 0 | AG22: =SUMPRODUCT($D22,AB22) -> 0 | AH22: =SUMPRODUCT($D22,AC22) -> 0 | AI22: =SUMPRODUCT($D22,AD22) -> 0 | AJ22: =SUMPRODUCT($D22,AE22) -> 30000
B23: 동남아 | C23: 돔급 | D23: 50000 | E23: 0 | F23: 0 | G23: 0 | H23: 0 | I23: 0 | J23: =SUMPRODUCT($D23,E23) -> 0 | K23: =SUMPRODUCT($D23,F23) -> 0 | L23: =SUMPRODUCT($D23,G23) -> 0 | M23: =SUMPRODUCT($D23,H23) -> 0 | N23: =SUMPRODUCT($D23,I23) -> 0 | P23: =ROUND(E23/2,) -> 0 | Q23: =ROUND(F23/2,) -> 0 | R23: =ROUND(G23/2,) -> 0 | S23: =ROUND(H23/2,) -> 0 | T23: =ROUND(I23/2,) -> 0 | U23: =SUMPRODUCT($D23,P23) -> 0 | V23: =SUMPRODUCT($D23,Q23) -> 0 | W23: =SUMPRODUCT($D23,R23) -> 0 | X23: =SUMPRODUCT($D23,S23) -> 0 | Y23: =SUMPRODUCT($D23,T23) -> 0 | AA23: =IF(E23=0,0,IF(ROUND(E23*0.3,)<1,1,ROUND(E23*0.3,))) -> 0 | AB23: =IF(F23=0,0,IF(ROUND(F23*0.3,)<1,1,ROUND(F23*0.3,))) -> 0 | AC23: =IF(G23=0,0,IF(ROUND(G23*0.3,)<1,1,ROUND(G23*0.3,))) -> 0 | AD23: =IF(H23=0,0,IF(ROUND(H23*0.3,)<1,1,ROUND(H23*0.3,))) -> 0 | AE23: =IF(I23=0,0,IF(ROUND(I23*0.3,)<1,1,ROUND(I23*0.3,))) -> 0 | AF23: =SUMPRODUCT($D23,AA23) -> 0 | AG23: =SUMPRODUCT($D23,AB23) -> 0 | AH23: =SUMPRODUCT($D23,AC23) -> 0 | AI23: =SUMPRODUCT($D23,AD23) -> 0 | AJ23: =SUMPRODUCT($D23,AE23) -> 0
B24: 동남아 | C24: 스타디움급 | D24: 80000 | E24: 0 | F24: 0 | G24: 0 | H24: 0 | I24: 0 | J24: =SUMPRODUCT($D24,E24) -> 0 | K24: =SUMPRODUCT($D24,F24) -> 0 | L24: =SUMPRODUCT($D24,G24) -> 0 | M24: =SUMPRODUCT($D24,H24) -> 0 | N24: =SUMPRODUCT($D24,I24) -> 0 | P24: =ROUND(E24/2,) -> 0 | Q24: =ROUND(F24/2,) -> 0 | R24: =ROUND(G24/2,) -> 0 | S24: =ROUND(H24/2,) -> 0 | T24: =ROUND(I24/2,) -> 0 | U24: =SUMPRODUCT($D24,P24) -> 0 | V24: =SUMPRODUCT($D24,Q24) -> 0 | W24: =SUMPRODUCT($D24,R24) -> 0 | X24: =SUMPRODUCT($D24,S24) -> 0 | Y24: =SUMPRODUCT($D24,T24) -> 0 | AA24: =IF(E24=0,0,IF(ROUND(E24*0.3,)<1,1,ROUND(E24*0.3,))) -> 0 | AB24: =IF(F24=0,0,IF(ROUND(F24*0.3,)<1,1,ROUND(F24*0.3,))) -> 0 | AC24: =IF(G24=0,0,IF(ROUND(G24*0.3,)<1,1,ROUND(G24*0.3,))) -> 0 | AD24: =IF(H24=0,0,IF(ROUND(H24*0.3,)<1,1,ROUND(H24*0.3,))) -> 0 | AE24: =IF(I24=0,0,IF(ROUND(I24*0.3,)<1,1,ROUND(I24*0.3,))) -> 0 | AF24: =SUMPRODUCT($D24,AA24) -> 0 | AG24: =SUMPRODUCT($D24,AB24) -> 0 | AH24: =SUMPRODUCT($D24,AC24) -> 0 | AI24: =SUMPRODUCT($D24,AD24) -> 0 | AJ24: =SUMPRODUCT($D24,AE24) -> 0
B25: 프랑스 | C25: 홀급 | D25: 5000 | E25: 0 | F25: 1 | G25: 5 | H25: 10 | I25: 10 | J25: =SUMPRODUCT($D25,E25) -> 0 | K25: =SUMPRODUCT($D25,F25) -> 5000 | L25: =SUMPRODUCT($D25,G25) -> 25000 | M25: =SUMPRODUCT($D25,H25) -> 50000 | N25: =SUMPRODUCT($D25,I25) -> 50000 | P25: =ROUND(E25/2,) -> 0 | Q25: =ROUND(F25/2,) -> 1 | R25: =ROUND(G25/2,) -> 3 | S25: =ROUND(H25/2,) -> 5 | T25: =ROUND(I25/2,) -> 5 | U25: =SUMPRODUCT($D25,P25) -> 0 | V25: =SUMPRODUCT($D25,Q25) -> 5000 | W25: =SUMPRODUCT($D25,R25) -> 15000 | X25: =SUMPRODUCT($D25,S25) -> 25000 | Y25: =SUMPRODUCT($D25,T25) -> 25000 | AA25: =IF(E25=0,0,IF(ROUND(E25*0.3,)<1,1,ROUND(E25*0.3,))) -> 0 | AB25: =IF(F25=0,0,IF(ROUND(F25*0.3,)<1,1,ROUND(F25*0.3,))) -> 1 | AC25: =IF(G25=0,0,IF(ROUND(G25*0.3,)<1,1,ROUND(G25*0.3,))) -> 2 | AD25: =IF(H25=0,0,IF(ROUND(H25*0.3,)<1,1,ROUND(H25*0.3,))) -> 3 | AE25: =IF(I25=0,0,IF(ROUND(I25*0.3,)<1,1,ROUND(I25*0.3,))) -> 3 | AF25: =SUMPRODUCT($D25,AA25) -> 0 | AG25: =SUMPRODUCT($D25,AB25) -> 5000 | AH25: =SUMPRODUCT($D25,AC25) -> 10000 | AI25: =SUMPRODUCT($D25,AD25) -> 15000 | AJ25: =SUMPRODUCT($D25,AE25) -> 15000
B26: 프랑스 | C26: 아레나급 | D26: 15000 | E26: 0 | F26: 0 | G26: 0 | H26: 0 | I26: 1 | J26: =SUMPRODUCT($D26,E26) -> 0 | K26: =SUMPRODUCT($D26,F26) -> 0 | L26: =SUMPRODUCT($D26,G26) -> 0 | M26: =SUMPRODUCT($D26,H26) -> 0 | N26: =SUMPRODUCT($D26,I26) -> 15000 | P26: =ROUND(E26/2,) -> 0 | Q26: =ROUND(F26/2,) -> 0 | R26: =ROUND(G26/2,) -> 0 | S26: =ROUND(H26/2,) -> 0 | T26: =ROUND(I26/2,) -> 1 | U26: =SUMPRODUCT($D26,P26) -> 0 | V26: =SUMPRODUCT($D26,Q26) -> 0 | W26: =SUMPRODUCT($D26,R26) -> 0 | X26: =SUMPRODUCT($D26,S26) -> 0 | Y26: =SUMPRODUCT($D26,T26) -> 15000 | AA26: =IF(E26=0,0,IF(ROUND(E26*0.3,)<1,1,ROUND(E26*0.3,))) -> 0 | AB26: =IF(F26=0,0,IF(ROUND(F26*0.3,)<1,1,ROUND(F26*0.3,))) -> 0 | AC26: =IF(G26=0,0,IF(ROUND(G26*0.3,)<1,1,ROUND(G26*0.3,))) -> 0 | AD26: =IF(H26=0,0,IF(ROUND(H26*0.3,)<1,1,ROUND(H26*0.3,))) -> 0 | AE26: =IF(I26=0,0,IF(ROUND(I26*0.3,)<1,1,ROUND(I26*0.3,))) -> 1 | AF26: =SUMPRODUCT($D26,AA26) -> 0 | AG26: =SUMPRODUCT($D26,AB26) -> 0 | AH26: =SUMPRODUCT($D26,AC26) -> 0 | AI26: =SUMPRODUCT($D26,AD26) -> 0 | AJ26: =SUMPRODUCT($D26,AE26) -> 15000
B27: 프랑스 | C27: 돔급 | D27: 50000 | E27: 0 | F27: 0 | G27: 0 | H27: 0 | I27: 0 | J27: =SUMPRODUCT($D27,E27) -> 0 | K27: =SUMPRODUCT($D27,F27) -> 0 | L27: =SUMPRODUCT($D27,G27) -> 0 | M27: =SUMPRODUCT($D27,H27) -> 0 | N27: =SUMPRODUCT($D27,I27) -> 0 | P27: =ROUND(E27/2,) -> 0 | Q27: =ROUND(F27/2,) -> 0 | R27: =ROUND(G27/2,) -> 0 | S27: =ROUND(H27/2,) -> 0 | T27: =ROUND(I27/2,) -> 0 | U27: =SUMPRODUCT($D27,P27) -> 0 | V27: =SUMPRODUCT($D27,Q27) -> 0 | W27: =SUMPRODUCT($D27,R27) -> 0 | X27: =SUMPRODUCT($D27,S27) -> 0 | Y27: =SUMPRODUCT($D27,T27) -> 0 | AA27: =IF(E27=0,0,IF(ROUND(E27*0.3,)<1,1,ROUND(E27*0.3,))) -> 0 | AB27: =IF(F27=0,0,IF(ROUND(F27*0.3,)<1,1,ROUND(F27*0.3,))) -> 0 | AC27: =IF(G27=0,0,IF(ROUND(G27*0.3,)<1,1,ROUND(G27*0.3,))) -> 0 | AD27: =IF(H27=0,0,IF(ROUND(H27*0.3,)<1,1,ROUND(H27*0.3,))) -> 0 | AE27: =IF(I27=0,0,IF(ROUND(I27*0.3,)<1,1,ROUND(I27*0.3,))) -> 0 | AF27: =SUMPRODUCT($D27,AA27) -> 0 | AG27: =SUMPRODUCT($D27,AB27) -> 0 | AH27: =SUMPRODUCT($D27,AC27) -> 0 | AI27: =SUMPRODUCT($D27,AD27) -> 0 | AJ27: =SUMPRODUCT($D27,AE27) -> 0
B28: 프랑스 | C28: 스타디움급 | D28: 80000 | E28: 0 | F28: 0 | G28: 0 | H28: 0 | I28: 0 | J28: =SUMPRODUCT($D28,E28) -> 0 | K28: =SUMPRODUCT($D28,F28) -> 0 | L28: =SUMPRODUCT($D28,G28) -> 0 | M28: =SUMPRODUCT($D28,H28) -> 0 | N28: =SUMPRODUCT($D28,I28) -> 0 | P28: =ROUND(E28/2,) -> 0 | Q28: =ROUND(F28/2,) -> 0 | R28: =ROUND(G28/2,) -> 0 | S28: =ROUND(H28/2,) -> 0 | T28: =ROUND(I28/2,) -> 0 | U28: =SUMPRODUCT($D28,P28) -> 0 | V28: =SUMPRODUCT($D28,Q28) -> 0 | W28: =SUMPRODUCT($D28,R28) -> 0 | X28: =SUMPRODUCT($D28,S28) -> 0 | Y28: =SUMPRODUCT($D28,T28) -> 0 | AA28: =IF(E28=0,0,IF(ROUND(E28*0.3,)<1,1,ROUND(E28*0.3,))) -> 0 | AB28: =IF(F28=0,0,IF(ROUND(F28*0.3,)<1,1,ROUND(F28*0.3,))) -> 0 | AC28: =IF(G28=0,0,IF(ROUND(G28*0.3,)<1,1,ROUND(G28*0.3,))) -> 0 | AD28: =IF(H28=0,0,IF(ROUND(H28*0.3,)<1,1,ROUND(H28*0.3,))) -> 0 | AE28: =IF(I28=0,0,IF(ROUND(I28*0.3,)<1,1,ROUND(I28*0.3,))) -> 0 | AF28: =SUMPRODUCT($D28,AA28) -> 0 | AG28: =SUMPRODUCT($D28,AB28) -> 0 | AH28: =SUMPRODUCT($D28,AC28) -> 0 | AI28: =SUMPRODUCT($D28,AD28) -> 0 | AJ28: =SUMPRODUCT($D28,AE28) -> 0
... B40: 호주 | C40: 스타디움급 | D40: 80000 | E40: 0 | F40: 0 | G40: 0 | H40: 0 | I40: 0 | J40: =SUMPRODUCT($D40,E40) -> 0 | K40: =SUMPRODUCT($D40,F40) -> 0 | L40: =SUMPRODUCT($D40,G40) -> 0 | M40: =SUMPRODUCT($D40,H40) -> 0 | N40: =SUMPRODUCT($D40,I40) -> 0 | P40: =ROUND(E40/2,) -> 0 | Q40: =ROUND(F40/2,) -> 0 | R40: =ROUND(G40/2,) -> 0 | S40: =ROUND(H40/2,) -> 0 | T40: =ROUND(I40/2,) -> 0 | U40: =SUMPRODUCT($D40,P40) -> 0 | V40: =SUMPRODUCT($D40,Q40) -> 0 | W40: =SUMPRODUCT($D40,R40) -> 0 | X40: =SUMPRODUCT($D40,S40) -> 0 | Y40: =SUMPRODUCT($D40,T40) -> 0 | AA40: =IF(E40=0,0,IF(ROUND(E40*0.3,)<1,1,ROUND(E40*0.3,))) -> 0 | AB40: =IF(F40=0,0,IF(ROUND(F40*0.3,)<1,1,ROUND(F40*0.3,))) -> 0 | AC40: =IF(G40=0,0,IF(ROUND(G40*0.3,)<1,1,ROUND(G40*0.3,))) -> 0 | AD40: =IF(H40=0,0,IF(ROUND(H40*0.3,)<1,1,ROUND(H40*0.3,))) -> 0 | AE40: =IF(I40=0,0,IF(ROUND(I40*0.3,)<1,1,ROUND(I40*0.3,))) -> 0 | AF40: =SUMPRODUCT($D40,AA40) -> 0 | AG40: =SUMPRODUCT($D40,AB40) -> 0 | AH40: =SUMPRODUCT($D40,AC40) -> 0 | AI40: =SUMPRODUCT($D40,AD40) -> 0 | AJ40: =SUMPRODUCT($D40,AE40) -> 0
B41: 합계 | E41: =SUBTOTAL(9,E9:E40) -> 0 | F41: =SUBTOTAL(9,F9:F40) -> 8 | G41: =SUBTOTAL(9,G9:G40) -> 35 | H41: =SUBTOTAL(9,H9:H40) -> 71 | I41: =SUBTOTAL(9,I9:I40) -> 118 | J41: =SUBTOTAL(9,J9:J40) -> 0 | K41: =SUBTOTAL(9,K9:K40) -> 40000 | L41: =SUBTOTAL(9,L9:L40) -> 235000 | ... N41: =SUBTOTAL(9,N9:N40) -> 1885000 | P41: =SUBTOTAL(9,P9:P40) -> 0 | Q41: =SUBTOTAL(9,Q9:Q40) -> 8 | R41: =SUBTOTAL(9,R9:R40) -> 21 | S41: =SUBTOTAL(9,S9:S40) -> 38 | T41: =SUBTOTAL(9,T9:T40) -> 64 | U41: =SUBTOTAL(9,U9:U40) -> 0 | V41: =SUBTOTAL(9,V9:V40) -> 40000 | W41: =SUBTOTAL(9,W9:W40) -> 135000 | ... Y41: =SUBTOTAL(9,Y9:Y40) -> 1095000 | AA41: =SUBTOTAL(9,AA9:AA40) -> 0 | AB41: =SUBTOTAL(9,AB9:AB40) -> 8 | AC41: =SUBTOTAL(9,AC9:AC40) -> 15 | AD41: =SUBTOTAL(9,AD9:AD40) -> 23 | AE41: =SUBTOTAL(9,AE9:AE40) -> 39 | AF41: =SUBTOTAL(9,AF9:AF40) -> 0 | AG41: =SUBTOTAL(9,AG9:AG40) -> 40000 | AH41: =SUBTOTAL(9,AH9:AH40) -> 105000 | ... AJ41: =SUBTOTAL(9,AJ9:AJ40) -> 540000
B42: 공연 당 관객 수 | K42: =K41/F41 -> 5000 | L42: =L41/G41 -> 6714.2857 | M42: =M41/H41 -> 9577.4648 | N42: =N41/I41 -> 15974.576 | V42: =V41/Q41 -> 5000 | W42: =W41/R41 -> 6428.5714 | X42: =X41/S41 -> 10131.579 | Y42: =Y41/T41 -> 17109.375 | AG42: =AG41/AB41 -> 5000 | AH42: =AH41/AC41 -> 7000 | AI42: =AI41/AD41 -> 10652.174 | AJ42: =AJ41/AE41 -> 13846.154
B45: 걸그룹 공연
B47: 구분 | C47: 공연명 | D47: 시기 | E47: 공연횟수 | F47: 관객수 | G47: 공연/관객
B48: 에스파 | C48: SYNK : PARALLEL LINE | D48: 24년 6월~25년 3월 | E48: 43 | F48: 520000 | G48: =F48/E48 -> 12093.023
B49: 에스파 | C49: SYNK : HYPER LINE | D49: 23년 2월~23년 9월 | E49: 31 | F49: 356000 | G49: =F49/E49 -> 11483.871
B50: 블랙핑크 | C50: BORN PINK | D50: 22년 10월~23년 9월 | E50: 38 | F50: 1815183 | G50: =F50/E50 -> 47767.974
B51: 트와이스 | C51: READY TO BE | D51: 23년 4월~ | E51: 51 | F51: 1500000 | G51: =F51/E51 -> 29411.765
B52: 아이브 | C52: SHOW WHAT I HAVE | D52: 23년 10월~24년9월 | E52: 29 | F52: 420000 | G52: =F52/E52 -> 14482.759

Sheet 유튜브
B1: 유튜브 광고매출
B2: Value analysis as of August 31, 2025
B3: KRW in millions
E4: 4 | F4: 5
B6: Source: https://socialblade.com/youtube
B8: 뉴진스 (데뷔 2022년 7월)
B10: 동영상 수 | C10: 705
B11: 업로드 수(월간) | C11: =C10/COUNTA(C14:AG14) -> 22.741935
B12: 조회수 평균 | C12: =AVERAGE(E17:AG17) -> 40.577612
B14: 구분 | C14: 44743 | D14: 44774 | E14: =EOMONTH(D14,1) -> 44834 | F14: =EOMONTH(E14,1) -> 44865 | G14: =EOMONTH(F14,1) -> 44895 | H14: =EOMONTH(G14,1) -> 44926 | I14: =EOMONTH(H14,1) -> 44957 | J14: =EOMONTH(I14,1) -> 44985 | K14: =EOMONTH(J14,1) -> 45016 | L14: =EOMONTH(K14,1) -> 45046 | ... AG14: =EOMONTH(AF14,1) -> 45688 | AH14: Total
B15: 명 수(누적) | C15: 10000 | D15: 57000 | E15: 633000 | F15: 873000 | G15: 1080000 | H15: 1230000 | I15: 1710000 | J15: 2430000 | K15: 2870000 | L15: 3210000 | M15: 3540000 | N15: 3690000 | O15: 3840000 | P15: 5060000 | Q15: 5530000 | R15: 5800000 | S15: 6040000 | T15: 6190000 | U15: 6380000 | V15: 6550000 | W15: 6650000 | X15: 6750000 | Y15: 6910000 | Z15: 7100000 | AA15: 7360000 | AB15: 7530000 | AC15: 7640000 | AD15: 7750000 | AE15: 7810000 | AF15: 7890000 | AG15: 7930000 | AH15: =AG15 -> 7930000
B16: 조회수(월간) | D16: 72868635 | E16: 72375161 | F16: 53655503 | G16: 60920309 | H16: 104830316 | I16: 240216450 | J16: 175292287 | K16: 147738401 | L16: 143013815 | M16: 100947342 | N16: 85979996 | O16: 453434834 | P16: 281060679 | Q16: 176909863 | R16: 171031247 | S16: 100327958 | T16: 132892288 | U16: 138375481 | V16: 88053478 | W16: 120575852 | X16: 92406177 | Y16: 173610613 | Z16: 212268281 | AA16: 192999650 | AB16: 154156549 | AC16: 115996030 | AD16: 80586976 | AE16: 79990932 | AF16: 82058363 | AG16: 85460435 | AH16: =SUBTOTAL(9,C16:AG16) -> 4190033901
B17: 인당 조회수 | D17: =D16/D15 -> 1278.3971 | E17: =E16/E15 -> 114.33675 | F17: =F16/F15 -> 61.461057 | G17: =G16/G15 -> 56.407694 | H17: =H16/H15 -> 85.227899 | I17: =I16/I15 -> 140.47746 | J17: =J16/J15 -> 72.136744 | K17: =K16/K15 -> 51.476795 | ... AH17: =AH16/AH15 -> 528.37754
B20: 엔믹스 (데뷔 2022년 2월)
B22: 동영상 수 | C22: 1100
B23: 업로드 수(월간) | C23: =C22/COUNTA(C26:AL26) -> 30.555556
B24: 조회수 평균 | C24: =AVERAGE(D30:AL30) -> 19.240615
B26: 구분 | C26: 44593 | D26: 44621 | E26: =EOMONTH(D26,1) -> 44681 | F26: =EOMONTH(E26,1) -> 44712 | G26: =EOMONTH(F26,1) -> 44742 | H26: =EOMONTH(G26,1) -> 44773 | I26: =EOMONTH(H26,1) -> 44804 | J26: =EOMONTH(I26,1) -> 44834 | K26: =EOMONTH(J26,1) -> 44865 | L26: =EOMONTH(K26,1) -> 44895 | ... AL26: =EOMONTH(AK26,1) -> 45688 | AM26: 45698 | AN26: Total
B27: 증감수 | D27: 336000 | E27: 176000 | F27: 136000 | G27: 80000 | H27: 60000 | I27: 50000 | J27: 80000 | K27: 100000 | L27: 50000 | M27: 60000 | N27: 50000 | O27: 40000 | P27: 130000 | Q27: 90000 | R27: 60000 | S27: 50000 | T27: 90000 | U27: 60000 | V27: 30000 | W27: 30000 | X27: 30000 | Y27: 90000 | Z27: 100000 | AA27: 50000 | AB27: 40000 | AC27: 70000 | AD27: 40000 | AE27: 40000 | AF27: 30000 | AG27: 70000 | AH27: 70000 | AI27: 50000 | AJ27: 80000 | AK27: 70000 | AL27: 70000
B28: 명 수(누적) | C28: 10000 | D28: 482000 | E28: 818000 | F28: 994000 | G28: 1130000 | H28: 1210000 | I28: 1270000 | J28: 1320000 | K28: 1400000 | L28: 1500000 | M28: 1550000 | N28: 1610000 | O28: 1660000 | P28: 1700000 | Q28: 1830000 | R28: 1920000 | S28: 1980000 | T28: 2030000 | U28: 2120000 | V28: 2180000 | W28: 2210000 | X28: 2240000 | Y28: 2270000 | Z28: 2360000 | AA28: 2460000 | AB28: 2510000 | AC28: 2550000 | AD28: 2620000 | AE28: 2660000 | AF28: 2700000 | AG28: 2730000 | AH28: 2800000 | AI28: 2870000 | AJ28: 2920000 | AK28: 3000000 | AL28: 3070000 | AM28: 3140000 | AN28: =AM28 -> 3140000
B29: 조회수(월간) | D29: 36185866 | E29: 30452602 | F29: 25480129 | G29: 20653970 | H29: 17107544 | I29: 14214375 | J29: 16792319 | K29: 45675174 | L29: 17085321 | M29: 24198450 | N29: 19319004 | O29: 15819918 | P29: 55698649 | Q29: 66606035 | R29: 34990436 | S29: 25055313 | T29: 60873877 | U29: 40039324 | V29: 22518440 | W29: 19808804 | X29: 13576429 | Y29: 75486271 | Z29: 70977929 | AA29: 53348519 | AB29: 36123377 | AC29: 29308305 | AD29: 40072644 | AE29: 30586039 | AF29: 31827833 | AG29: 45518330 | AH29: 46115890 | AI29: 35363602 | AJ29: 36313221 | AK29: 24788286 | AL29: 24822437 | AN29: =SUBTOTAL(9,I29:AM29) -> 1072924551
B30: 인당 조회수 | D30: =D29/D28 -> 75.074411 | E30: =E29/E28 -> 37.22812 | F30: =F29/F28 -> 25.633933 | G30: =G29/G28 -> 18.27785 | H30: =H29/H28 -> 14.138466 | I30: =I29/I28 -> 11.192421 | J30: =J29/J28 -> 12.721454 | K30: =K29/K28 -> 32.625124 | ... AL30: =AL29/AL28 -> 8.0854844 | AN30: =AN29/AN28 -> 341.69572
B32: 트리플에스 (데뷔 2022년 8월)
B34: 동영상 수 | C34: 2200
B35: 업로드 수(월간) | C35: =C34/COUNTA(C38:AF38) -> 73.333333
B36: 조회수 평균 | C36: =AVERAGE(D42:AF42) -> 17.193231
B38: 구분 | C38: 44774 | D38: 44805 | E38: =EOMONTH(D38,1) -> 44865 | F38: =EOMONTH(E38,1) -> 44895 | G38: =EOMONTH(F38,1) -> 44926 | H38: =EOMONTH(G38,1) -> 44957 | I38: =EOMONTH(H38,1) -> 44985 | J38: =EOMONTH(I38,1) -> 45016 | K38: =EOMONTH(J38,1) -> 45046 | L38: =EOMONTH(K38,1) -> 45077 | ... AF38: =EOMONTH(AE38,1) -> 45688 | AG38: 45698 | AH38: Total
B39: 증감수 | D39: 43000 | E39: 111000 | F39: 201000 | G39: 80000 | H39: 27000 | I39: 314000 | J39: 241000 | K39: 80000 | L39: 370000 | M39: 10000 | N39: 30000 | O39: 30000 | P39: 10000 | Q39: 20000 | R39: 50000 | S39: 90000 | T39: 320000 | U39: 80000 | V39: 10000 | W39: 0 | X39: 260000 | Y39: 20000 | Z39: 20000 | AA39: 10000 | AB39: 10000 | AC39: 150000 | AD39: 10000 | AE39: 0 | AF39: 0
B40: 명 수(누적) | C40: 10000 | D40: =E40-D39 -> 183000 | E40: =F40-E39 -> 226000 | F40: =G40-F39 -> 337000 | G40: =H40-G39 -> 538000 | H40: =I40-H39 -> 618000 | I40: =J40-I39 -> 645000 | J40: =K40-J39 -> 959000 | K40: =L40-K39 -> 1200000 | ... AF40: =AG40-AF39 -> 2780000 | AG40: 2780000 | AH40: =AG40 -> 2780000
B41: 조회수(월간) | D41: 9097769 | E41: 15848370 | F41: 42422017 | G41: 8438597 | H41: 5057746 | I41: 24431034 | J41: 22959013 | K41: 9778878 | L41: 23113151 | M41: 10057544 | N41: 7277968 | O41: 20791553 | P41: 10837835 | Q41: 24317352 | R41: 5733998 | S41: 8769789 | T41: 9400413 | U41: 6037993 | V41: 6132122 | W41: 6208959 | X41: 34906749 | Y41: 23820183 | Z41: 20497834 | AA41: 17078012 | AB41: 13158222 | AC41: 31028650 | AD41: 32056178 | AE41: 9974762 | AF41: 15503685 | AH41: =SUBTOTAL(9,C41:AG41) -> 474736376
B42: 인당 조회수 | D42: =D41/D40 -> 49.714585 | E42: =E41/E40 -> 70.125531 | F42: =F41/F40 -> 125.88136 | G42: =G41/G40 -> 15.685125 | H42: =H41/H40 -> 8.184055 | I42: =I41/I40 -> 37.877572 | J42: =J41/J40 -> 23.940577 | K42: =K41/K40 -> 8.149065 | ... AF42: =AF41/AF40 -> 5.5768651 | AH42: =AH41/AH40 -> 170.76848
B45: 피프티피프티 (데뷔 2022년 11월)
B47: 동영상 수 | C47: 276
B48: 업로드 수(월간) | C48: =C47/COUNTA(C50:AC50) -> 10.222222
B50: 구분 | C50: 44866 | D50: 44926 | E50: 44957 | F50: 44985 | G50: 45016 | H50: 45046 | I50: 45077 | J50: 45107 | K50: 45138 | L50: 45169 | M50: 45199 | N50: 45230 | O50: 45260 | P50: 45291 | Q50: 45322 | R50: 45351 | S50: 45382 | T50: 45412 | U50: 45443 | V50: 45473 | W50: 45504 | X50: 45535 | Y50: 45565 | Z50: 45596 | AA50: 45626 | AB50: 45657 | AC50: 45688 | AD50: 45716
B51: 명 수 | C51: 10000 | D51: 52500 | I51: 785000 | P51: 1590000 | Q51: 1610000 | AB51: 1880000 | AC51: 1900000
B54: 키스오브라이프/키오라 (데뷔 2023년 7월)
B56: 동영상 수 | C56: 1047
B57: 업로드 수(월간) | C57: =C56/COUNTA(C59:V59) -> 52.35
B59: 구분 | C59: 45078 | D59: 45108 | E59: =EOMONTH(D59,1) -> 45169 | F59: =EOMONTH(E59,1) -> 45199 | G59: =EOMONTH(F59,1) -> 45230 | H59: =EOMONTH(G59,1) -> 45260 | I59: =EOMONTH(H59,1) -> 45291 | J59: =EOMONTH(I59,1) -> 45322 | K59: =EOMONTH(J59,1) -> 45351 | L59: =EOMONTH(K59,1) -> 45382 | ... AG59: =EOMONTH(AF59,1) -> 46022
B60: 명 수 | C60: 10000 | D60: 102000 | I60: 594000 | J60: 669000 | P60: 1310000 | V60: 1850000
B63: 르세라핌 (데뷔 22년 5월)
B65: 동영상 수 | C65: 1684
B66: 업로드 수(월간) | C66: =C65/COUNTA(C68:AJ68) -> 49.529412
B68: 구분 | C68: 44652 | D68: =EOMONTH(C68,1) -> 44712 | E68: =EOMONTH(D68,1) -> 44742 | F68: =EOMONTH(E68,1) -> 44773 | G68: =EOMONTH(F68,1) -> 44804 | H68: =EOMONTH(G68,1) -> 44834 | I68: =EOMONTH(H68,1) -> 44865 | J68: =EOMONTH(I68,1) -> 44895 | K68: =EOMONTH(J68,1) -> 44926 | ... AJ68: =EOMONTH(AI68,1) -> 45688
B69: 명 수 | C69: 10000 | D69: 251000 | I69: 594000 | P69: 2830000 | X69: 4390000 | AB69: 5250000 | AJ69: 5690000
B73: 블랙핑크/성숙기
B75: 구분 | C75: 44652 | D75: =EOMONTH(C75,1) -> 44712 | E75: =EOMONTH(D75,1) -> 44742 | F75: =EOMONTH(E75,1) -> 44773 | G75: =EOMONTH(F75,1) -> 44804 | H75: =EOMONTH(G75,1) -> 44834 | I75: =EOMONTH(H75,1) -> 44865 | J75: =EOMONTH(I75,1) -> 44895 | K75: =EOMONTH(J75,1) -> 44926 | ... AJ75: =EOMONTH(AI75,1) -> 45688
B76: 명 수 | X76: 92500000 | AJ76: 95500000
B79: 트와이스/성숙기
B81: 구분 | C81: 44652 | D81: =EOMONTH(C81,1) -> 44712 | E81: =EOMONTH(D81,1) -> 44742 | F81: =EOMONTH(E81,1) -> 44773 | G81: =EOMONTH(F81,1) -> 44804 | H81: =EOMONTH(G81,1) -> 44834 | I81: =EOMONTH(H81,1) -> 44865 | J81: =EOMONTH(I81,1) -> 44895 | K81: =EOMONTH(J81,1) -> 44926 | ... AJ81: =EOMONTH(AI81,1) -> 45688
B82: 명 수 | X82: 16600000 | AJ82: 17800000
B85: 데뷔 이후 월평균 유튜브 구독자 수 증가율
B87: 구분 | C87: +6개월 | D87: +12개월 | E87: +24개월 | F87: 구분
B88: 뉴진스 | C88: 1.3559497 | D88: 0.64195381 | E88: 0.31785145 | F88: BEST | H88: BEST | I88: =AVERAGE(E88:E89) -> 0.30802328
B89: 르세라핌 | C89: 0.97529095 | D89: 0.67066616 | E89: 0.29819512 | F89: BEST | H89: BASE | I89: =AVERAGE(E90:E92) -> 0.25454672
B90: 엔믹스 | C90: 1.2419915 | D90: 0.59502716 | E90: 0.258886 | F90: BASE | H90: 6개월 | I90: =AVERAGE(C88:C93) -> 1.1033937
B91: 트리플에스 | C91: 1.0025957 | D91: 0.59672402 | E91: 0.2609369 | F91: BASE
B92: 피프티 | C92: 1.0692435 | D92: 0.58535677 | E92: 0.24381725 | F92: BASE
B93: 키오라 | C93: 0.97529095 | D93: 0.55768346 | E93: 0 | F93: BASE
B96: 최근 12개월 유튜브 구독자 수 증가율
B98: 구분 | C98: 최근12개월 | D98: 구분
B99: 뉴진스 | C99: 0.019968106 | D99: 안정기
B100: 르세라핌 | C100: 0.023860301 | D100: 안정기
B101: 엔믹스 | C101: 0.024198689 | D101: 안정기
B102: 트리플에스 | C102: 0.035702006 | D102: 안정기
B103: 피프티 | C103: 0.015170255 | D103: 제외 (활동중단)
B104: 키오라 | C104: 0.096878924 | D104: 제외 (데뷔 '23년 7월)
B105: 블랙핑크 | C105: 0.0026633407 | D105: 성숙기
B106: 트와이스 | C106: 0.0058332611 | D106: 성숙기
B109: 유튜브 구독자 수 CAP
B111: 구분 | C111: 구분
B112: 블랙핑크 | C112: 9580만명
B113: 트와이스 | C113: 1790만명
B114: 아이들 | C114: 904만명
B115: 피프티 | C115: 192만명
B118: 월별 동영상 업로드 수
B120: 구분 | C120: 구분
B121: 뉴진스 | C121: =C11 -> 22.741935 | D121: 제외 (활동중단)
B122: 엔믹스 | C122: =C23 -> 30.555556
B123: 트리플에스 | C123: =C35 -> 73.333333
B124: 피프티피프티 | C124: =C48 -> 10.222222 | D124: 제외 (활동중단)
B125: 키오라 | C125: =C57 -> 52.35
B126: 르세라핌 | C126: =C66 -> 49.529412
B127: Average | C127: =ROUND(AVERAGE(C122,C123,C125,C126),) -> 51
B130: 구독자 수 추이 (데뷔 '25년 10월 가정)
B132: 데뷔+6개월 | C132: =I90 -> 1.1033937
B133: 6개월이후 | C133: 0.059420265
B134: 안정기 | C134: =AVERAGE(C99:C102) -> 0.025932276
B135: 성숙기 | C135: =AVERAGE(C105:C106) -> 0.0042483009
B137: 구분 | C137: 45931 | D137: =EOMONTH(C137,1) -> 45991 | E137: =EOMONTH(D137,1) -> 46022 | F137: =EOMONTH(E137,1) -> 46053 | G137: =EOMONTH(F137,1) -> 46081 | H137: =EOMONTH(G137,1) -> 46112 | I137: =EOMONTH(H137,1) -> 46142 | J137: =EOMONTH(I137,1) -> 46173 | K137: =EOMONTH(J137,1) -> 46203 | ... BA137: =EOMONTH(AZ137,1) -> 47483
B138: 명 수 | C138: 10000 | D138: =C138*(1+$C$132) -> 21033.937 | E138: =D138*(1+$C$132) -> 44242.652 | F138: =E138*(1+$C$132) -> 93059.716 | G138: =F138*(1+$C$132) -> 195741.22 | H138: =G138*(1+$C$132) -> 411720.86 | I138: =H138*(1+$C$132) -> 866011.07 | J138: =I138*(1+$C$133) -> 917469.68 | K138: =J138*(1+$C$133) -> 971985.97 | L138: =K138*(1+$C$133) -> 1029741.6 | M138: =L138*(1+$C$133) -> 1090929.2 | N138: =M138*(1+$C$133) -> 1155752.5 | O138: =N138*(1+$C$133) -> 1224427.6 | P138: =O138*(1+$C$133) -> 1297183.4 | Q138: =P138*(1+$C$133) -> 1374262.4 | ... Z138: =Y138*(1+$C$133) -> 2310383.9 | AA138: =Z138*(1+$C$134) -> 2370297.4 | AB138: =AA138*(1+$C$134) -> 2431764.6 | AC138: =AB138*(1+$C$134) -> 2494825.8 | AD138: =AC138*(1+$C$134) -> 2559522.3 | AE138: =AD138*(1+$C$134) -> 2625896.5 | AF138: =AE138*(1+$C$134) -> 2693992 | AG138: =AF138*(1+$C$134) -> 2763853.3 | AH138: =AG138*(1+$C$134) -> 2835526.3 | ... AX138: =AW138*(1+$C$134) -> 4271031.4 | AY138: =AX138*(1+$C$135) -> 4289176.1 | AZ138: =AY138*(1+$C$135) -> 4307397.8 | BA138: =AZ138*(1+$C$135) -> 4325696.9
I139: 866011.07 | Z139: =C138*(1+I89)^24 -> 2310383.9
B141: 명 수 | C141: 2025 | D141: 2026 | E141: 2027 | F141: 2028 | G141: 2029
B142: 연평균 구독자 수 | C142: =AVERAGE(C138:E138) -> 25092.196 | D142: =AVERAGE(F138:Q138) -> 885690.43 | E142: =AVERAGE(R138:AC138) -> 1998937.9 | F142: =AVERAGE(AD138:AO138) -> 2958056.5 | G142: =AVERAGE(AP138:BA138) -> 3974651.1
B145: 유튜브 CPM 단가 (조회수)
B147: 유튜브 수수료율 | C147: 0.45
B148: 9월 말 USD 환율 | C148: 1470
B150: 구분 | C150: 하단 | D150: 상단 | E150: 중간값 | F150: KRW
B151: Nox Influencer | C151: 1.84 | D151: 3.2 | E151: =(C151+D151)/2 -> 2.52 | F151: =E151*$C$148 -> 3704.4
...

Sheet MD,팬클럽
B1: MD/팬클럽, 매출/비용
B2: Value analysis as of August 31, 2025
B3: KRW in millions
E4: 4 | F4: 5
B7: 4대 기획사 대표 그룹 굿즈 현황
C9: 하이브 | D9: SM | E9: YG | F9: JYP
B10: 가격 | C10: BTS | D10: NCT | E10: 블랙핑크 | F10: 트와이스
B11: 응원봉 | C11: 39000 | D11: 38000 | E11: 39000 | F11: 49000 | G11: 제작단가 (1만원)
B12: 앨범 | C12: 30465 | D12: 25554 | E12: 30465 | F12: 20421
B13: 포토북/포토 | C13: 27243 | D13: 14448 | E13: 21867 | F13: 24357
B14: 키링 | C14: 18689 | D14: 18091 | E14: 18667 | F14: 17350
B16: 평균(앨범 제외) | C16: =ROUND(AVERAGE(C11:F11,C13:F14),-3) -> 27000
B18: Source : https://www.newstomato.com/ReadNews.aspx?no=1217571
B21: 코어, 라이트 팬덤 연간 주요 활동 내용 및 예상 비용
B23: 구분 | C23: 주요 내용 | G23: 예상 비용
B24: 음원 | C24: 스트리밍 지원 | G24: 월 평균 6,900~8,900원
B25: 초동 음반 지원 | C25: 초동 음반 판매량 증진 위함 | G25: 1~100만원
B26: 팬사인회 | C26: 음반 구매를 통해 추첨권 획득 | G26: 걸그룹 30~200만원 (인기도에 따라 20장~150장 추정)
B27: 콘서트/팬미팅 | C27: 콘서트 연 2~4회, 팬미팅 연 1~2회 참여 | G27: 콘서트 평균 15.4만원, 팬미팅 평균 9.9만원
B28: MD | C28: 시즌 그리팅 및 공식 MD 등 | G28: 공식 MD 0.5~20만원
B29: 플랫폼 구독료 | C29: 버블, 위버스 | G29: 4,500원
B30: 팬클럽 가입 | C30: 위버스, JYP 등 연 평균 1회 가입 | G30: 위버스 2.2~3만원, JYP 3.5만원
B32: 월 환산 평균 예상 비용 | G32: 라이트 팬덤 : 월 9만원 미만
G33: 로얄 팬덤 : 월 18~150 만원
B35: Source : 대신증권 리포트_해가 지지 않는 팬덤

Sheet 걸그룹
B1: 걸그룹 성과지표
B2: Value analysis as of August 31, 2025
B3: KRW in millions
E4: 4 | G4: 5
D8: 에스파 | E8: 뉴진스 | F8: 엔믹스 | G8: 아일릿 | H8: 케플러 | I8: 트리플에스
B9: 구분 | C9: 데뷔일 | D9: 44152 | E9: 44764 | F9: 44614 | G9: 45010 | H9: 44564 | I9: 44939
C10: 소속사 | D10: SM | E10: HYBE | F10: JYP | G10: HYBE | H10: 웨이크원, 클렙 | I10: 모드하우스
C11: 데뷔 이후 기간 | D11: 4.0833333 | E11: 2.4166667 | F11: 2.8333333 | G11: 1.75 | H11: 2.9166667 | I11: 1.9166667
B12: 음반 | C12: 앨범 발매 횟수 | D12: 6 | E12: 5 | F12: 6 | G12: 2 | H12: 12 | I12: 9
C13: 앨범 판매량 | D13: =음반원!I11 -> 8744139 | E13: =음반원!I12 -> 6984036 | F13: =음반원!I13 -> 4317723 | G13: =음반원!I14 -> 1151999 | H13: =음반원!I15 -> 1651555 | I13: =음반원!I14 -> 1151999
C14: 뮤직비디오 조회수 | D14: 2105228350 | E14: 836531475 | F14: 608066452 | G14: 273077894 | H14: N/A | I14: 508643836
B15: 공연 | C15: 콘서트 | D15: 74 | E15: N/A | F15: 25 | G15: N/A | H15: 20 | I15: 27
C16: 공연장 규모 | D16: 8258.0645 | E16: N/A | F16: 1500 | G16: N/A | H16: 800 | I16: 1500
C17: 행사 | D17: 75 | E17: 30 | F17: 24 | G17: 21 | H17: N/A | I17: 108
C18: 행사 가격 (1회) | D18: 44230769 | E18: 44230769 | F18: 26538462 | G18: 26538462 | H18: 13269231 | I18: 13269231
C19: 콘서트 티켓 가격 (KRW) | D19: 154000 | E19: 140000 | F19: 110000 | G19: 110000 | H19: 130000 | I19: 110000
B20: 광고 | C20: 평균 가격 (6개월, KRW) | D20: 400000000 | E20: 400000000 | F20: 200000000 | G20: 200000000 | H20: 50000000 | I20: 50000000
C21: 광고 횟수 | D21: 51 | E21: 59 | F21: 24 | G21: 6 | H21: 3 | I21: 1
C22: 연평균 광고 횟수 | D22: 12.489796 | E22: 24.413793 | F22: 8.4705882 | G22: 3.4285714 | H22: 1.0285714 | I22: 0.52173913
B23: 방송 | C23: 방송 출연료 (1회) | D23: 10000000 | E23: 10000000 | F23: 5000000 | G23: 5000000 | H23: N/A | I23: N/A
C24: 방송 출연 횟수 | D24: 55 | E24: 22 | F24: 26 | G24: 37 | H24: N/A | I24: N/A
C25: 유튜브 구독자 | D25: 6950000 | E25: 7970000 | F25: 3130000 | G25: 2100000 | H25: 2530000 | I25: 2780000
C26: 플랫폼 구독자 | D26: N/A | E26: 1766502 | F26: N/A | G26: 481010 | H26: N/A | I26: N/A
C27: 구독료 (연간) | D27: N/A | E27: 25000 | F27: N/A | G27: 25000 | H27: N/A | I27: N/A
C28: 연평균 방송 횟수 | D28: 13.469388 | E28: 9.1034483 | F28: 9.1764706 | G28: 21.142857 | H28: N/A | I28: N/A

Sheet 제작비
B1: 프로그램, 걸그룹 제작비
B2: Value analysis as of August 31, 2025
B3: KRW in millions
E4: 4 | F4: 5
B5: 프로그램 제작비
B8: KRW in millions | C8: 금액 | D8: 비중
B9: 제작비 | C9: -100
B10: 편성매출 | C10: 50 | D10: =-C10/$C$9 -> 0.5
B11: 넷플릭스 | C11: 55 | D11: =-C11/$C$9 -> 0.55
B12: PPL/OST | C12: 15 | D12: =-C12/$C$9 -> 0.15
B13: 마진율 | C13: =-SUM(C9:C12)/C9 -> 0.2
B16: 걸그룹 제작비 (데뷔~활동 3년 차)
B18: KRW in millions | C18: 금액
B19: 트레이닝 및 관리비 | C19: 323
B20: 앨범 제작비 | C20: 2547
B21: 인력 채용 | C21: 131
B22: 연습실 임차료 등 | C22: 95
B23: 숙소 임차료 등 | C23: 82
B24: Total | C24: =SUBTOTAL(9,C19:C23) -> 3178
B26: Source : 중앙일보, 판타지오

Sheet 엔터사
B1: 엔터사 재무제표
B2: Value analysis as of August 31, 2025
B3: KRW in millions
F4: 4 | G4: 5
B6: SM 매출액 비중
B8: KRW in millions | C8: FY22 | D8: FY23 | E8: FY24 | F8: YTD3Q24
B9: 음반/음원 | C9: 279791.77 | D9: 317466.24 | E9: 284028 | F9: 200158.91
B10: 출연료 | C10: 135786.99 | D10: 174174.57 | E10: 237016 | F10: 187972.79
B11: 공연, 컨텐츠 | C11: 312806.54 | D11: 375369.8 | E11: 382580 | F11: 267826.96
B12: 광고대행 | C12: 106083.81 | D12: 76948.464 | E12: 71428 | F12: 49664.415
B13: 기타 | C13: 16300.207 | D13: 17110.64 | E13: 14670 | F13: 10544.3
B14: Total | C14: =SUBTOTAL(9,C9:C13) -> 850769.31 | D14: =SUBTOTAL(9,D9:D13) -> 961069.72 | E14: =SUM(E9:E13) -> 989722 | F14: =SUBTOTAL(9,F9:F13) -> 716167.37
B15: % of Total
B16: 음반/음원 | C16: =C9/C$14 -> 0.32886913 | D16: =D9/D$14 -> 0.33032592 | E16: =E9/E$14 -> 0.28697756 | F16: =F9/F$14 -> 0.27948622
B17: 출연료 | C17: =C10/C$14 -> 0.15960494 | D17: =D10/D$14 -> 0.1812299 | E17: =E10/E$14 -> 0.23947735 | F17: =F10/F$14 -> 0.26247047
B18: 공연, 컨텐츠 | C18: =C11/C$14 -> 0.36767492 | D18: =D11/D$14 -> 0.390575 | E18: =E11/E$14 -> 0.38655299 | F18: =F11/F$14 -> 0.37397258
B19: 광고대행 | C19: =C12/C$14 -> 0.12469163 | D19: =D12/D$14 -> 0.080065434 | E19: =E12/E$14 -> 0.072169761 | F19: =F12/F$14 -> 0.069347498
B20: 기타 | C20: =C13/C$14 -> 0.019159374 | D20: =D13/D$14 -> 0.017803745 | E20: =E13/E$14 -> 0.014822344 | F20: =F13/F$14 -> 0.014723234
B23: JYP 매출액 비중
B25: KRW in millions | C25: FY22 | D25: FY23 | E25: FY24 | F25: YTD3Q24
B26: 음반/음원 | C26: 174724.73 | D26: 262795.3 | E26: 217213 | F26: 141426.59
B27: 콘서트 | C27: 24585.691 | D27: 63187.836 | E27: 103581 | F27: 65549.479
B28: 광고,출연료 | C28: 33071.119 | D28: 42621.168 | E28: 61460 | F28: 43579.661
B29: 초상권 등 | C29: 113510.57 | D29: 197896.24 | E29: 219532 | F29: 152127.85
B30: Total | C30: =SUBTOTAL(9,C26:C29) -> 345892.11 | D30: =SUBTOTAL(9,D26:D29) -> 566500.54 | E30: =SUBTOTAL(9,E26:E29) -> 601786 | F30: =SUBTOTAL(9,F26:F29) -> 402683.58
B31: % of Total
B32: 음반/음원 | C32: =C26/C$30 -> 0.50514228 | D32: =D26/D$30 -> 0.4638924 | E32: =E26/E$30 -> 0.36094725 | F32: =F26/F$30 -> 0.35121023
B33: 콘서트 | C33: =C27/C$30 -> 0.071079074 | D33: =D27/D$30 -> 0.11154065 | E33: =E27/E$30 -> 0.17212265 | F33: =F27/F$30 -> 0.16278161
B34: 광고 | C34: =C28/C$30 -> 0.095611082 | D34: =D28/D$30 -> 0.075235882 | E34: =E28/E$30 -> 0.10212933 | F34: =F28/F$30 -> 0.10822309
B35: 초상권 등 | C35: =C29/C$30 -> 0.32816756 | D35: =D29/D$30 -> 0.34933107 | E35: =E29/E$30 -> 0.36480078 | F35: =F29/F$30 -> 0.37778508
B38: YG 매출액 비중
B40: KRW in millions | C40: FY22 | D40: FY23 | E40: FY24 | F40: YTD3Q24 | H40: Note
B41: 상품/제품 | C41: 156694 | D41: 197446 | E41: 152404 | F41: 105190 | H41: 앨범, 콘텐츠, MD
B42: 공연 | C42: 22746 | D42: 111468 | E42: 16987 | F42: 12111
B43: 음악서비스 | C43: 70684 | D43: 88893 | E43: 78601 | F43: 57592 | H43: 음원음반 유통
B44: 광고모델 | C44: 67308 | D44: 58941 | E44: 34931 | F44: 26543
B45: 로열티 | C45: 14736 | D45: 46309 | E45: 25352 | F45: 20521
B46: 출연료 | C46: 17866 | D46: 17465 | E46: 16542 | F46: 9762
B47: 방송제작 | C47: 295 | D47: 876 | E47: 0 | F47: 0
B48: 기타 | C48: 40551 | D48: 47798 | E48: 40340 | F48: 29163
B49: Total | C49: =SUBTOTAL(9,C41:C48) -> 390880 | D49: =SUBTOTAL(9,D41:D48) -> 569196 | E49: =SUBTOTAL(9,E41:E48) -> 365157 | F49: =SUBTOTAL(9,F41:F48) -> 260882
B50: % of Total
B51: 상품/제품 | C51: =C41/C$49 -> 0.40087495 | D51: =D41/D$49 -> 0.34688578 | E51: =E41/E$49 -> 0.41736568 | F51: =F41/F$49 -> 0.40320911
B52: 공연 | C52: =C43/C$49 -> 0.18083299 | D52: =D43/D$49 -> 0.15617292 | E52: =E43/E$49 -> 0.21525262 | F52: =F43/F$49 -> 0.22075881
B53: 음악서비스 | C53: =C42/C$49 -> 0.058191772 | D53: =D42/D$49 -> 0.19583412 | E53: =E42/E$49 -> 0.046519716 | F53: =F42/F$49 -> 0.046423287
B54: 광고모델 | C54: =C44/C$49 -> 0.17219607 | D54: =D44/D$49 -> 0.10355133 | E54: =E44/E$49 -> 0.095660223 | F54: =F44/F$49 -> 0.10174332
B55: 로열티 | C55: =C45/C$49 -> 0.03769955 | D55: =D45/D$49 -> 0.081358618 | E55: =E45/E$49 -> 0.069427671 | F55: =F45/F$49 -> 0.078660084
B56: 출연료 | C56: =C46/C$49 -> 0.045707122 | D56: =D46/D$49 -> 0.030683631 | E56: =E46/E$49 -> 0.045301062 | F56: =F46/F$49 -> 0.037419216
B57: 방송제작 | C57: =C47/C$49 -> 0.00075470733 | D57: =D47/D$49 -> 0.0015390129 | E57: =E47/E$49 -> 0 | F57: =F47/F$49 -> 0
B58: 기타 | C58: =C48/C$49 -> 0.10374284 | D58: =D48/D$49 -> 0.083974589 | E58: =E48/E$49 -> 0.11047303 | F58: =F48/F$49 -> 0.11178617
B61: HYBE 매출액 비중
B63: KRW in millions | C63: FY22 | D63: FY23 | E63: FY24 | F63: YTD3Q24
B64: 음반/음원 | C64: 551989 | D64: 970463 | E64: 860962 | F64: 609174
B65: 공연 | C65: 258167 | D65: 359111 | E65: 450865 | F65: 262014
B66: 광고,출연료 | C66: 161830 | D66: 141899 | E66: 134535 | F66: 92655
B67: MD및라이선싱 | C67: 395554 | D67: 325563 | E67: 420229 | F67: 268982
B68: 콘텐츠 | C68: 341500 | D68: 289872 | E68: 287279 | F68: 224822
B69: 팬클럽 등 | C69: 67113 | D69: 91181 | E69: 101779 | F69: 71582
B70: Total | C70: =SUBTOTAL(9,C64:C69) -> 1776153 | D70: =SUBTOTAL(9,D64:D69) -> 2178089 | E70: =SUBTOTAL(9,E64:E69) -> 2255649 | F70: =SUBTOTAL(9,F64:F69) -> 1529229
B71: % of Total
B72: 음반/음원 | C72: =C64/C$70 -> 0.31077784 | D72: =D64/D$70 -> 0.44555709 | E72: =E64/E$70 -> 0.38169148 | F72: =F64/F$70 -> 0.39835368
B73: 공연 | C73: =C65/C$70 -> 0.14535178 | D73: =D65/D$70 -> 0.16487435 | E73: =E65/E$70 -> 0.19988261 | F73: =F65/F$70 -> 0.17133732
B74: 광고,출연료 | C74: =C66/C$70 -> 0.091112646 | D74: =D66/D$70 -> 0.065148394 | E74: =E66/E$70 -> 0.059643588 | F74: =F66/F$70 -> 0.060589356
B75: MD및라이선싱 | C75: =C67/C$70 -> 0.22270266 | D75: =D67/D$70 -> 0.14947185 | E75: =E67/E$70 -> 0.18630071 | F75: =F67/F$70 -> 0.17589387
B76: 콘텐츠 | C76: =C68/C$70 -> 0.19226947 | D76: =D68/D$70 -> 0.13308547 | E76: =E68/E$70 -> 0.1273598 | F76: =F68/F$70 -> 0.14701657
B77: 팬클럽 등 | C77: =C69/C$70 -> 0.037785596 | D77: =D69/D$70 -> 0.041862844 | E77: =E69/E$70 -> 0.045121825 | F77: =F69/F$70 -> 0.046809209
B81: 엔터4사 매출비중 평균
B83: 구분 | C83: FY22 | D83: FY23 | E83: FY24 | F83: YTD3Q24
B84: 음원/음반매출 | C84: =AVERAGE(C16,C32,C51,C53,C72) -> 0.3207712 | D84: =AVERAGE(D16,D32,D51,D53,D72) -> 0.35649906 | E84: =AVERAGE(E16,E32,E51,E53,E72) -> 0.29870034 | F84: =AVERAGE(F16,F32,F51,F53,F72) -> 0.29573651
B85: 공연매출 | C85: =AVERAGE(C18,C33,C52,C73) -> 0.19123469 | D85: =AVERAGE(D18,D33,D52,D73) -> 0.20579073 | E85: =AVERAGE(E18,E33,E52,E73) -> 0.24345272 | F85: =AVERAGE(F18,F33,F52,F73) -> 0.23221258
B86: 합계 | C86: =SUM(C84:C85) -> 0.51200589 | D86: =SUM(D84:D85) -> 0.56228979 | E86: =SUM(E84:E85) -> 0.54215305 | F86: =SUM(F84:F85) -> 0.52794909
B88: 구분 | C88: FY22 | D88: FY23 | E88: FY24 | F88: YTD3Q24 | H88: Note
B89: 음원/음반매출 | C89: =AVERAGE(C16,C72,C32) -> 0.38159642 | D89: =AVERAGE(D16,D72,D32) -> 0.41325847 | E89: =AVERAGE(E16,E72,E32) -> 0.34320543 | F89: =AVERAGE(F16,F72,F32) -> 0.34301671 | H89: YG제외
B90: 공연매출 | C90: =AVERAGE(C52,C73,C33) -> 0.13242128 | D90: =AVERAGE(D52,D73,D33) -> 0.14419597 | E90: =AVERAGE(E52,E73,E33) -> 0.19575262 | F90: =AVERAGE(F52,F73,F33) -> 0.18495925 | H90: SM제외
B91: 합계 | C91: =SUM(C89:C90) -> 0.5140177 | D91: =SUM(D89:D90) -> 0.55745444 | E91: =SUM(E89:E90) -> 0.53895805 | F91: =SUM(F89:F90) -> 0.52797596
B94: SM (SG&A, excl. D&A)
B96: KRW in millions | C96: FY22 | D96: FY23 | E96: FY24
B97: 인건비 | C97: =SUBTOTAL(9,C98:C101) -> 90416.049 | D97: =SUBTOTAL(9,D98:D101) -> 82106.495
B98: 급여 | C98: 64991.403 | D98: 70294.938
B99: 퇴직급여 | C99: 6362.563 | D99: 5968.768
B100: 복리후생비 | C100: 7944.184 | D100: 6010.479
B101: 주식보상비용 | C101: 11117.899 | D101: -167.69
B102: 변동비성비용 | C102: =SUBTOTAL(9,C103:C108) -> 64045.656 | D102: =SUBTOTAL(9,D103:D108) -> 94888.811
B103: 지급수수료 | C103: 30289.658 | D103: 42429.66
B104: 광고선전비 | C104: 16741.869 | D104: 28563.298
B105: 운반비 | C105: 10716.706 | D105: 16987.969
B106: 여비교통비 | C106: 3429.554 | D106: 3777.38
B107: 외주가공비 | C107: 1914.855 | D107: 1851.186
B108: 소모품비 | C108: 953.014 | D108: 1279.318
B109: 고정비성비용 | C109: =SUBTOTAL(9,C110:C117) -> 24461.298 | D109: =SUBTOTAL(9,D110:D117) -> 24599.055
B110: 기타 | C110: 8210.363 | D110: 5865.593
B111: 수도광열비 | C111: 3848.43 | D111: 4031.237
B112: 세금과공과 | C112: 3757.155 | D112: 3169.079
B113: 보험료 | C113: 3511.564 | D113: 6725.908
B114: 지급임차료 | C114: 2090.381 | D114: 2905.9
B115: 건물관리비 | C115: 1309.841 | D115: 1648.768
B116: 대손상각비 | C116: 1036.145 | D116: -500.746
B117: 통신비 | C117: 697.419 | D117: 753.316
B118: Total | C118: =SUBTOTAL(9,C97:C117) -> 178923 | D118: =SUBTOTAL(9,D97:D117) -> 201594.36
B119: % of Total
...

Sheet 글로벌
B1: 글로벌 음악산업
B2: Value analysis as of August 31, 2025
B3: KRW in millions
E4: 4 | F4: 5
B7: Global Recorded Music Industry Revenues
C9: in USD billions | D9: 2013 | E9: 2014 | F9: 2015 | G9: 2016 | H9: 2017 | I9: 2018 | J9: 2019 | K9: 2020 | L9: 2021 | M9: 2022 | N9: 2023
B10: Physical | D10: 6.1 | E10: 5.3 | F10: 5.1 | G10: 4.9 | H10: 4.6 | I10: 4.1 | J10: 3.9 | K10: 3.7 | L10: 4.3 | M10: 4.5 | N10: 5.1
B11: Streaming | D11: 1.3 | E11: 1.8 | F11: 2.6 | G11: 4.4 | H11: 6.2 | I11: 8.8 | J11: 10.7 | K11: 12.7 | L11: 15.7 | M11: 17.5 | N11: 19.3
B12: Downloads | D12: 4.1 | E12: 3.8 | F12: 3.6 | G12: 3 | H12: 2.5 | I12: 1.6 | J12: 1.4 | K12: 1.2 | L12: 1.1 | M12: 0.9 | N12: 0.9
B13: Performance | D13: 1.6 | E13: 1.7 | F13: 1.8 | G13: 2.1 | H13: 2.2 | I13: 2.5 | J13: 2.4 | K13: 2.2 | L13: 2.3 | M13: 2.5 | N13: 2.7
B14: Others | D14: 0.3 | E14: 0.3 | F14: 0.3 | G14: 0.3 | H14: 0.4 | I14: 0.4 | J14: 0.4 | K14: 0.4 | L14: 0.5 | M14: 0.6 | N14: 0.6
B15: Total | D15: =SUBTOTAL(9,D10:D14) -> 13.4 | E15: =SUBTOTAL(9,E10:E14) -> 12.9 | F15: =SUBTOTAL(9,F10:F14) -> 13.4 | G15: =SUBTOTAL(9,G10:G14) -> 14.7 | H15: =SUBTOTAL(9,H10:H14) -> 15.9 | I15: =SUBTOTAL(9,I10:I14) -> 17.4 | J15: =SUBTOTAL(9,J10:J14) -> 18.8 | K15: =SUBTOTAL(9,K10:K14) -> 20.2 | ... N15: =SUBTOTAL(9,N10:N14) -> 28.6
B17: Source : IFPI 2024 Global Music Report
B45: Global music market forecasts
B47: in USD billions | D47: 2023 | E47: 2024(E) | F47: 2025(E) | G47: 2026(E) | H47: 2027(E) | I47: 2028(E) | J47: 2029(E) | K47: 2030(E) | M47: CAGR '23-30 | N47: CAGR '24-30
B48: Recorded | D48: =SUBTOTAL(9,D49:D53) -> 28.6 | E48: =SUBTOTAL(9,E49:E53) -> 31.1 | F48: =SUBTOTAL(9,F49:F53) -> 34 | G48: =SUBTOTAL(9,G49:G53) -> 37.1 | H48: =SUBTOTAL(9,H49:H53) -> 40.2 | I48: =SUBTOTAL(9,I49:I53) -> 43.3 | J48: =SUBTOTAL(9,J49:J53) -> 46.4 | K48: =SUBTOTAL(9,K49:K53) -> 49.5 | M48: 0.081519033 | N48: 0.080539884
C49: Physical | D49: 5.1 | E49: 5.2 | F49: 5.5 | G49: =F49+($K49-$F49)/5 -> 5.68 | H49: =G49+($K49-$F49)/5 -> 5.86 | I49: =H49+($K49-$F49)/5 -> 6.04 | J49: =I49+($K49-$F49)/5 -> 6.22 | K49: 6.4 | M49: 0.032968585 | N49: 0.035212336
C50: Performance | D50: 2.7 | E50: 2.9 | F50: 3.1 | G50: =F50+($K50-$F50)/5 -> 3.28 | H50: =G50+($K50-$F50)/5 -> 3.46 | I50: =H50+($K50-$F50)/5 -> 3.64 | J50: =I50+($K50-$F50)/5 -> 3.82 | K50: 4 | M50: 0.057755215 | N50: 0.055059613
C51: Sync | D51: 0.6 | E51: 0.7 | F51: 0.8 | G51: =F51+($K51-$F51)/5 -> 0.84 | H51: =G51+($K51-$F51)/5 -> 0.88 | I51: =H51+($K51-$F51)/5 -> 0.92 | J51: =I51+($K51-$F51)/5 -> 0.96 | K51: 1 | M51: 0.07570374 | N51: 0.061248265
C52: Downloads | D52: 0.9 | E52: 0.8 | F52: 0.7 | G52: =F52+($K52-$F52)/5 -> 0.62 | H52: =G52+($K52-$F52)/5 -> 0.54 | I52: =H52+($K52-$F52)/5 -> 0.46 | J52: =I52+($K52-$F52)/5 -> 0.38 | K52: 0.3 | M52: -0.1452486 | N52: -0.15080934
C53: Streaming | D53: 19.3 | E53: 21.5 | F53: 23.9 | G53: =F53+($K53-$F53)/5 -> 26.68 | H53: =G53+($K53-$F53)/5 -> 29.46 | I53: =H53+($K53-$F53)/5 -> 32.24 | J53: =I53+($K53-$F53)/5 -> 35.02 | K53: 37.8 | M53: 0.10079114 | N53: 0.098606649
B54: Music Publishing | D54: 9 | E54: 9.9 | F54: 10.7 | G54: =F54+($K54-$F54)/5 -> 11.62 | H54: =G54+($K54-$F54)/5 -> 12.54 | I54: =H54+($K54-$F54)/5 -> 13.46 | J54: =I54+($K54-$F54)/5 -> 14.38 | K54: 15.3 | M54: 0.078751157 | N54: 0.075249806
B55: Live music market | D55: 33.1 | E55: 35.1 | F55: 37.7 | G55: =F55+($K55-$F55)/5 -> 40.5 | H55: =G55+($K55-$F55)/5 -> 43.3 | I55: =H55+($K55-$F55)/5 -> 46.1 | J55: =I55+($K55-$F55)/5 -> 48.9 | K55: 51.7 | M55: 0.065776349 | N55: 0.066671204
B56: Total | D56: =SUBTOTAL(9,D48:D55) -> 70.7 | E56: =SUBTOTAL(9,E48:E55) -> 76.1 | F56: =SUBTOTAL(9,F48:F55) -> 82.4 | G56: =SUBTOTAL(9,G48:G55) -> 89.22 | H56: =SUBTOTAL(9,H48:H55) -> 96.04 | I56: =SUBTOTAL(9,I48:I55) -> 102.86 | J56: =SUBTOTAL(9,J48:J55) -> 109.68 | K56: =SUBTOTAL(9,K48:K55) -> 116.5 | M56: 0.073956385 | N56: 0.073553136
B58: Source : Goldman Sachs Music in the air, 2024 May
B76: 지역별 해외 스트리밍서비스 매출액 추정치
B78: 억 원 | D78: 2019 | E78: 2020 | F78: 2021 | G78: 2022 | H78: 2023
B79: 아시아 | D79: 1016 | E79: 1176 | F79: 1183 | G79: 1387 | H79: 1566
B80: 유럽 | D80: 88 | E80: 104 | F80: 246 | G80: 348 | H80: 489
B81: 미주 | D81: 149 | E81: 117 | F81: 243 | G81: 310 | H81: 480
B82: 오세아니아 외 | D82: 24 | E82: 45 | F82: 42 | G82: 54 | H82: 68
B83: Total | D83: =SUBTOTAL(9,D79:D82) -> 1277 | E83: =SUBTOTAL(9,E79:E82) -> 1442 | F83: =SUBTOTAL(9,F79:F82) -> 1714 | G83: =SUBTOTAL(9,G79:G82) -> 2099 | H83: =SUBTOTAL(9,H79:H82) -> 2603
B84: % of Total
B85: 아시아 | D85: =D79/D$83 -> 0.79561472 | E85: =E79/E$83 -> 0.81553398 | F85: =F79/F$83 -> 0.69019837 | G85: =G79/G$83 -> 0.66079085 | H85: =H79/H$83 -> 0.60161352
B86: 유럽 | D86: =D80/D$83 -> 0.068911511 | E86: =E80/E$83 -> 0.072122053 | F86: =F80/F$83 -> 0.14352392 | G86: =G80/G$83 -> 0.16579323 | H86: =H80/H$83 -> 0.18786016
B87: 미주 | D87: =D81/D$83 -> 0.11667972 | E87: =E81/E$83 -> 0.081137309 | F87: =F81/F$83 -> 0.14177363 | G87: =G81/G$83 -> 0.14768938 | H87: =H81/H$83 -> 0.18440261
B88: 오세아니아 외 | D88: =D82/D$83 -> 0.018794049 | E88: =E82/E$83 -> 0.031206657 | F88: =F82/F$83 -> 0.024504084 | G88: =G82/G$83 -> 0.025726536 | H88: =H82/H$83 -> 0.026123703
B90: Source : 데이터로 살펴본 K팝 해외 매출액 동향, 한국문화관광연구원
B94: 연도별 피지컬 음반 수출액 추이
B96: 억 원 | D96: 2019 | E96: 2020 | F96: 2021 | G96: 2022 | H96: 2023
B97: 수출액 | D97: 1088 | E97: 2182 | F97: 2871 | G97: 3437 | H97: 3889
B99: Source : 데이터로 살펴본 K팝 해외 매출액 동향, 한국문화관광연구원
B102: 연도별 해외 공연 매출액 추정치
B104: 억 원 | D104: 2019 | E104: 2020 | F104: 2021 | G104: 2022 | H104: 2023
B105: 수출액 | D105: 1088 | E105: 2182 | F105: 2871 | G105: 3437 | H105: 3889
B107: Source : 데이터로 살펴본 K팝 해외 매출액 동향, 한국문화관광연구원
B151: K-POP 시장 성장률
B153: 구분 | E153: CAGR
B154: 2023 | D154: 12.7 | E154: 1.26
B155: 2024(E) | D155: =D154*글로벌!$E$154 -> 16.002
B156: 2025(E) | D156: =D155*글로벌!$E$154 -> 20.16252
B157: 2026(E) | D157: =D156*글로벌!$E$154 -> 25.404775
B176: 기사 정리
B178: 2018년보다 글로벌 기준으로는 362%, 미국에서는 182%나 증가했다.
B179: https://www.yna.co.kr/view/AKR20241008088100005#:~:text=%EB%89%B4%EC%8A%A4%20%EA%B2%80%EC%83%89%20%EB%8B%AB%EA%B8%B0-,K%ED%8C%9D%EC%9D%B4%20%EA%B8%80%EB%A1%9C%EB%B2%8C%20%EC%9D%8C%EC%95%85%20%EC%8B%9C%EC%9E%A5%EC%97%90%EC%84%9C%20%ED%81%B0%20%EC%82%AC%EB%9E%91%EC%9D%84,%EC%97%90%EC%84%9C%EB%8A%94%20182%25%EB%82%98%20%EC%A6%9D%EA%B0%80%ED%96%88%EB%8B%A4.
B181: 골드만삭스 향후 3년 동안 K팝 시장이 매해 26%씩 성장할 것으로 전망
B182: https://www.ft.com/content/212a87ed-adf8-4212-923d-38213d8d98be
B184: 한국문화관광연구원이 24일 발표한 '데이터로 살펴본 K팝 해외 매출액 동향' 분석 결과에 따르면 2023년 K팝 해외 매출액은 전년 대비 34.3％ 증가한 1조2377억원으로 추산됐다.
B185: 이는 실물 음반 수출, 해외 온라인 스트리밍, 공연 등 3개 분야를 합산한 매출 추정치다. K팝 해외 매출이 1조원을 넘은 것은 지난해가 사상 처음이다. 2022년엔 9218억원이었다.
B186: 출처 : 데일리뉴스(http://www.idailynews.co.kr)
B187: https://www.idailynews.co.kr/news/articleView.html?idxno=102958
B189: K팝 시장 규모는 연간 12조7000억원(92억 달러)에 달한다.
B190: https://biz.chosun.com/international/international_general/2024/07/29/QNODNBFN2RB5DI5P3DDLSEP67M/#:~:text=K%ED%8C%9D%20%EC%8B%9C%EC%9E%A5%20%EA%B7%9C%EB%AA%A8%EB%8A%94,%EA%B7%B9%ED%9E%88%20%EC%9D%BC%EB%B6%80%EC%97%90%20%EB%B6%88%EA%B3%BC%ED%95%98%EB%8B%A4.

Sheet 5. WACC▶
B8: Section <5>
B9: <WACC>

Sheet WACC
B1: WACC
B2: As of September 30, 2024
B3: KRW in millions
B5: Items | E5: Figure | G5: Sources
B6: 무위험이자율 (Rf) | E6: 0.02992 | G6: Bloomberg에서 조회된 검토기준일 현재 대한민국의 10년 만기 국채 이자율 적용
B7: 시장위험프리미엄 (Rm) | E7: 0.08 | G7: 한국공인회계사회 제시 한국의 시장위험 프리미엄 가이던스-7%~9% 범위값 중 8% 적용
B8: Re-levered Beta (Beta) | E8: ='Unlevered Beta'!K17*(1+(1-WACC!E13)*'Unlevered Beta'!H17) -> 0.65940039 | G8: Re-levered Beta = Unlevered Beta x [1 + (1 - t) x (타인자본(D) / 자기자본(E))]
B9: Size Premium | E9: ='Size Premium'!H6 -> 0.0473 | G9: 한국의 기업규모 위험 프리미엄 연구결과-5분위수 규모위험 프리미엄율 적용
B10: 자기자본비용 (ke) | E10: =E6+(E7*E8)+E9 -> 0.12997203 | G10: Ke = Rf + (Rm x Beta) + Size Premium
B12: 세전타인자본비용 (i) | E12: 0.0972 | G12: Seibro에서 조회된 한국의 5년 만기 BBB-등급 무보증 회사채 수익률 적용
B13: 한계세율 (t) | E13: 0.209 | G13: 대상회사 한계세율 적용 (법인세*지방세)
B15: 세후타인자본비용 (kd) | E15: =E12*(1-E13) -> 0.0768852 | G15: 세후타인자본비용(kd) = 세전타인자본비용(i) x (1 - t)
B18: Items | C18: Figure (a) | D18: Weight (b) | E18: (a)*(b) | G18: Sources
B19: 자기자본비용 (ke) | C19: =E10 -> 0.12997203 | D19: =1-D20 -> 0.88570364 | E19: =C19*D19 -> 0.1151167
B20: 세후타인자본비용 (kd) | C20: =E15 -> 0.0768852 | D20: ='Unlevered Beta'!O19 -> 0.11429636 | E20: =C20*D20 -> 0.0087876987 | G20: 부채비율은 대상회사와 유사한 영업을 영위하는 동종기업의 자본구조 중위값을 적용
B22: 가중평균자본비용 (WACC) | E22: =SUM(E19:E20) -> 0.1239044 | G22: 가중평균자본비용(WACC) = 자기자본비용(ke) x E/(D+E) + 세후타인자본비용(kd) x (D/D+E)

Sheet Unlevered Beta
B1: Unlevered Beta Calculation
B2: As of September 30, 2024
B3: KRW in millions
C4: Debt | D4: Total Equity (e=b+c+d) | G4: Equity | H4: Unlevered Beta (i=h/(1+(1-g)xf)
C5: IBD | D5: Market | E5: Preferred | F5: Minority | G5: Total | H5: Debt/Equity | I5: Marginal | J5: 2 Years Weekly | K5: Unlevered | M5: f(1+f) | O5: Debt / TIC
B6: Guideline Companies | C6: (a) | D6: Capital (b) | E6: Stock (c) | F6: Interest (d) | G6: Equity (e) | H6: Ratio (f=a/e) | I6: Tax Rate (g) | J6: Beta (h) | K6: Beta (i)
A7: KOSDAQ:A182360 | B7: Cube Entertainment, Inc. (KOSDAQ:A182360) | C7: =CIQ!E7 -> 32532.6 | D7: =CIQ!D7 -> 200467.6 | E7: =CIQ!G7+CIQ!H7+CIQ!I7 -> 0 | F7: =CIQ!J7 -> 1769.4 | G7: =D7+E7+F7 -> 202237 | H7: =IFERROR(C7/G7,0) -> 0.16086374 | I7: =VLOOKUP($A7,Tax!A16:I23,8,FALSE()) -> 0.231 | J7: 0.557 | K7: =IFERROR(J7/(1+(1-I7)*H7),"N/A") -> 0.49568204 | M7: =H7/(1+H7) -> 0.13857246 | O7: =H7/(1+H7) -> 0.13857246
A8: KOSDAQ:A032800 | B8: Fantagio Corp. (KOSDAQ:A032800) | C8: =CIQ!E8 -> 13822.9 | D8: =CIQ!D8 -> 37459.1 | E8: =CIQ!G8+CIQ!H8+CIQ!I8 -> 0 | F8: =CIQ!J8 -> 106.3 | G8: =D8+E8+F8 -> 37565.4 | H8: =IFERROR(C8/G8,0) -> 0.36796893 | I8: =VLOOKUP($A8,Tax!A17:I24,8,FALSE()) -> 0 | J8: 0.961 | K8: =IFERROR(J8/(1+(1-I8)*H8),"N/A") -> 0.70250134 | M8: =H8/(1+H8) -> 0.26898924 | O8: =H8/(1+H8) -> 0.26898924
A9: KOSDAQ:A173940 | B9: FNC ENTERTAINMENT Co., Ltd. (KOSDAQ:A173940) | C9: =CIQ!E9 -> 10015.5 | D9: =CIQ!D9 -> 53639.2 | E9: =CIQ!G9+CIQ!H9+CIQ!I9 -> 0 | F9: =CIQ!J9 -> 93.6 | G9: =D9+E9+F9 -> 53732.8 | H9: =IFERROR(C9/G9,0) -> 0.18639453 | I9: =VLOOKUP($A9,Tax!A18:I25,8,FALSE()) -> 0 | J9: 0.468 | K9: =IFERROR(J9/(1+(1-I9)*H9),"N/A") -> 0.39447249 | M9: =H9/(1+H9) -> 0.15711007 | O9: =H9/(1+H9) -> 0.15711007
A10: KOSE:A352820 | B10: HYBE Co., Ltd. (KOSE:A352820) | C10: =CIQ!E10 -> 1115366.2 | D10: =CIQ!D10 -> 7027393.8 | E10: =CIQ!G10+CIQ!H10+CIQ!I10 -> 0 | F10: =CIQ!J10 -> 290747.7 | G10: =D10+E10+F10 -> 7318141.5 | H10: =IFERROR(C10/G10,0) -> 0.15241113 | I10: =VLOOKUP($A10,Tax!A19:I26,8,FALSE()) -> 0.231 | J10: 0.635 | K10: =IFERROR(J10/(1+(1-I10)*H10),"N/A") -> 0.56838313 | M10: =H10/(1+H10) -> 0.13225413 | O10: =H10/(1+H10) -> 0.13225413
A11: KOSDAQ:A035900 | B11: JYP Entertainment Corporation (KOSDAQ:A035900) | C11: =CIQ!E11 -> 10472.8 | D11: =CIQ!D11 -> 1669079.6 | E11: =CIQ!G11+CIQ!H11+CIQ!I11 -> 0 | F11: =CIQ!J11 -> 3816 | G11: =D11+E11+F11 -> 1672895.6 | H11: =IFERROR(C11/G11,0) -> 0.0062602831 | I11: =VLOOKUP($A11,Tax!A20:I27,8,FALSE()) -> 0.231 | J11: 0.691 | K11: =IFERROR(J11/(1+(1-I11)*H11),"N/A") -> 0.68768936 | M11: =H11/(1+H11) -> 0.0062213357 | O11: =H11/(1+H11) -> 0.0062213357
A12: KOSDAQ:A361570 | B12: RBW Inc. (KOSDAQ:A361570) | C12: =CIQ!E12 -> 12151.3 | D12: =CIQ!D12 -> 72990.6 | E12: =CIQ!G12+CIQ!H12+CIQ!I12 -> 0 | F12: =CIQ!J12 -> 8102 | G12: =D12+E12+F12 -> 81092.6 | H12: =IFERROR(C12/G12,0) -> 0.14984475 | I12: =VLOOKUP($A12,Tax!A21:I28,8,FALSE()) -> 0.209 | J12: 0.785 | K12: =IFERROR(J12/(1+(1-I12)*H12),"N/A") -> 0.70181575 | M12: =H12/(1+H12) -> 0.13031737 | O12: =H12/(1+H12) -> 0.13031737
A13: KOSDAQ:A041510 | B13: SM Entertainment Co., Ltd. (KOSDAQ:A041510) | C13: =CIQ!E13 -> 103970.8 | D13: =CIQ!D13 -> 1513287.7 | E13: =CIQ!G13+CIQ!H13+CIQ!I13 -> 0 | F13: =CIQ!J13 -> 178023.9 | G13: =D13+E13+F13 -> 1691311.6 | H13: =IFERROR(C13/G13,0) -> 0.061473474 | I13: =VLOOKUP($A13,Tax!A22:I29,8,FALSE()) -> 0.231 | J13: 0.493 | K13: =IFERROR(J13/(1+(1-I13)*H13),"N/A") -> 0.47074636 | M13: =H13/(1+H13) -> 0.05791334 | O13: =H13/(1+H13) -> 0.05791334
A14: KOSDAQ:A122870 | B14: YG Entertainment Inc. (KOSDAQ:A122870) | C14: =CIQ!E14 -> 19059 | D14: =CIQ!D14 -> 690529.2 | E14: =CIQ!G14+CIQ!H14+CIQ!I14 -> 160.2 | F14: =CIQ!J14 -> 119157.9 | G14: =D14+E14+F14 -> 809847.3 | H14: =IFERROR(C14/G14,0) -> 0.023534066 | I14: =VLOOKUP($A14,Tax!A23:I30,8,FALSE()) -> 0.231 | J14: 0.746 | K14: =IFERROR(J14/(1+(1-I14)*H14),"N/A") -> 0.73273911 | M14: =H14/(1+H14) -> 0.022992949 | O14: =H14/(1+H14) -> 0.022992949
B15: Min | H15: =MIN(H7:H14) -> 0.0062602831 | J15: =MIN(J7:J14) -> 0.468 | K15: =MIN(K7:K14) -> 0.39447249 | M15: =H15/(1+H15) -> 0.0062213357 | O15: =MIN(O7:O14) -> 0.0062213357
B16: Median | H16: =MEDIAN(H7:H14) -> 0.15112794 | J16: =MEDIAN(J7:J14) -> 0.663 | K16: =MEDIAN(K7:K14) -> 0.62803624 | M16: =H16/(1+H16) -> 0.13128683 | O16: =MEDIAN(O7:O14) -> 0.13128575
B17: Average | H17: =AVERAGE(H7:H14) -> 0.13859386 | J17: =AVERAGE(J7:J14) -> 0.667 | K17: =AVERAGE(K7:K14) -> 0.5942537 | M17: =H17/(1+H17) -> 0.1217237 | O17: =AVERAGE(O7:O14) -> 0.11429636
B18: Max | H18: =MAX(H7:H14) -> 0.36796893 | J18: =MAX(J7:J14) -> 0.961 | K18: =MAX(K7:K14) -> 0.73273911 | M18: =H18/(1+H18) -> 0.26898924 | O18: =MAX(O7:O14) -> 0.26898924
B19: Selected | H19: =H17 -> 0.13859386 | J19: =J17 -> 0.667 | K19: =K17 -> 0.5942537 | M19: =M17 -> 0.1217237 | O19: =O17 -> 0.11429636

Sheet Credit Ratiing
B1: Credit Rating
B2: As of September 30, 2024
B3: KRW in millions
B32: Source : Bizline

Sheet CIQ
B1: CIQ
B2: As of September 30, 2024
B3: KRW in millions
B6: Exchange:Ticker | C6: Company Name | D6: Market Capitalization [My Setting] [09/30/2024] (KRWmm, Historical rate) | E6: Total Debt [CQ3 2024] (KRWmm, Historical rate) | F6: Total Equity [CQ3 2024] (KRWmm, Historical rate) | G6: Pref. Stock, Convertible [CQ3 2024] (KRWmm, Historical rate) | H6: Pref. Stock, Non-Redeem. [CQ3 2024] (KRWmm, Historical rate) | I6: Pref. Stock, Other [CQ3 2024] (KRWmm, Historical rate) | J6: Minority Interest [CQ3 2024] (KRWmm, Historical rate) | K6: Total Enterprise Value [My Setting] [Latest] (KRWmm, Historical rate) | L6: Total Revenue [LTM CQ3 2024] (KRWmm, Historical rate) | M6: EBIT [LTM CQ3 2024] (KRWmm, Historical rate) | N6: EBITDA [LTM CQ3 2024] (KRWmm, Historical rate) | O6: Market Capitalization [My Setting] [12/31/2020] (KRWmm, Historical rate) | P6: Market Capitalization [My Setting] [12/31/2021] (KRWmm, Historical rate) | Q6: Market Capitalization [My Setting] [12/31/2022] (KRWmm, Historical rate) | R6: Market Capitalization [My Setting] [12/31/2023] (KRWmm, Historical rate) | S6: Market Capitalization [My Setting] [09/30/2024] (KRWmm, Historical rate) | T6: Pref. Stock, Non-Redeem. [CY 2020] (KRWmm, Historical rate) | U6: Pref. Stock, Non-Redeem. [CY 2021] (KRWmm, Historical rate) | V6: Pref. Stock, Non-Redeem. [CY 2022] (KRWmm, Historical rate) | W6: Pref. Stock, Non-Redeem. [CY 2023] (KRWmm, Historical rate) | X6: Pref. Stock, Non-Redeem. [CQ3 2024] (KRWmm, Historical rate) | Y6: Pref. Stock, Convertible [CY 2020] (KRWmm, Historical rate) | Z6: Pref. Stock, Convertible [CY 2021] (KRWmm, Historical rate) | AA6: Pref. Stock, Convertible [CY 2022] (KRWmm, Historical rate) | AB6: Pref. Stock, Convertible [CY 2023] (KRWmm, Historical rate) | AC6: Pref. Stock, Convertible [CQ3 2024] (KRWmm, Historical rate) | AD6: Pref. Stock, Other [CY 2020] (KRWmm, Historical rate) | AE6: Pref. Stock, Other [CY 2021] (KRWmm, Historical rate) | AF6: Pref. Stock, Other [CY 2022] (KRWmm, Historical rate) | AG6: Pref. Stock, Other [CY 2023] (KRWmm, Historical rate) | AH6: Pref. Stock, Other [CQ3 2024] (KRWmm, Historical rate) | AI6: Minority Interest [CY 2020] (KRWmm, Historical rate) | AJ6: Minority Interest [CY 2021] (KRWmm, Historical rate) | AK6: Minority Interest [CY 2022] (KRWmm, Historical rate) | AL6: Minority Interest [CY 2023] (KRWmm, Historical rate) | AM6: Minority Interest [CQ3 2024] (KRWmm, Historical rate) | AN6: Total Debt [CY 2020] (KRWmm, Historical rate) | AO6: Total Debt [CY 2021] (KRWmm, Historical rate) | AP6: Total Debt [CY 2022] (KRWmm, Historical rate) | AQ6: Total Debt [CY 2023] (KRWmm, Historical rate) | AR6: Total Debt [CQ3 2024] (KRWmm, Historical rate) | AS6: Total Cash & ST Investments [CY 2020] (KRWmm, Historical rate) | AT6: Total Cash & ST Investments [CY 2021] (KRWmm, Historical rate) | AU6: Total Cash & ST Investments [CY 2022] (KRWmm, Historical rate) | AV6: Total Cash & ST Investments [CY 2023] (KRWmm, Historical rate) | AW6: Total Cash & ST Investments [CQ3 2024] (KRWmm, Historical rate) | AX6: Long-term Investments [CY 2020] (KRWmm, Historical rate) | AY6: Long-term Investments [CY 2021] (KRWmm, Historical rate) | AZ6: Long-term Investments [CY 2022] (KRWmm, Historical rate) | BA6: Long-term Investments [CY 2023] (KRWmm, Historical rate) | BB6: Long-term Investments [CQ3 2024] (KRWmm, Historical rate) | BC6: EBITDA [CY 2020] (KRWmm, Historical rate) | BD6: EBITDA [CY 2021] (KRWmm, Historical rate) | BE6: EBITDA [CY 2022] (KRWmm, Historical rate) | BF6: EBITDA [CY 2023] (KRWmm, Historical rate) | BG6: EBITDA [LTM CQ3 2024] (KRWmm, Historical rate) | BH6: EV_2020 | BI6: EV_2021 | BJ6: EV_2022 | BK6: EV_2023 | BL6: EV_LTM3Q24
B7: KOSDAQ:A182360 | C7: Cube Entertainment, Inc. (KOSDAQ:A182360) | D7: 200467.6 | E7: 32532.6 | F7: 139890.7 | G7: 0 | H7: 0 | I7: 0 | J7: 1769.4 | K7: 178027.5 | L7: 197306.8 | M7: 21072.4 | N7: 24476.1 | O7: 131705.2 | P7: 347315.7 | Q7: 220006.1 | R7: 262180.7 | S7: 200467.6 | T7: 0 | U7: 0 | V7: 0 | W7: 0 | X7: 0 | Y7: 0 | Z7: 0 | AA7: 0 | AB7: 0 | AC7: 0 | AD7: 0 | AE7: 0 | AF7: 0 | AG7: 0 | AH7: 0 | AI7: 577.3 | AJ7: 990.6 | AK7: 912.4 | AL7: 1158.2 | AM7: 1769.4 | AN7: 5627 | AO7: 4539.1 | AP7: 5536.7 | AQ7: 7002.8 | AR7: 32532.6 | AS7: 21359 | AT7: 14089.2 | AU7: 46110.6 | AV7: 33506 | AW7: 70056.8 | AX7: 3682.5 | AY7: 15457.8 | AZ7: 14784.4 | BA7: 61157.8 | BB7: 113147.8 | BC7: 4369.7 | BD7: 5342.8 | BE7: 11162.5 | BF7: 19349.5 | BG7: 24476.1 | BH7: =IF(O7=0,"na",O7+T7+Y7+AD7+AI7+AN7-AX7) -> 134227 | BI7: =IF(P7=0,"na",P7+U7+Z7+AE7+AJ7+AO7-AY7) -> 337387.6 | BJ7: =IF(Q7=0,"na",Q7+V7+AA7+AF7+AK7+AP7-AZ7) -> 211670.8 | BK7: =IF(R7=0,"na",R7+W7+AB7+AG7+AL7+AQ7-BA7) -> 209183.9 | BL7: =IF(S7=0,"na",S7+X7+AC7+AH7+AM7+AR7-BB7) -> 121621.8
B8: KOSDAQ:A032800 | C8: Fantagio Corp. (KOSDAQ:A032800) | D8: 37459.1 | E8: 13822.9 | F8: 56776.2 | G8: 0 | H8: 0 | I8: 0 | J8: 106.3 | K8: -535.2 | L8: 67356.9 | M8: -1758.7 | N8: 2520.7 | O8: 61295.1 | P8: 55851.1 | Q8: 47761.2 | R8: 33784.8 | S8: 37459.1 | T8: 0 | U8: 0 | V8: 0 | W8: 0 | X8: 0 | Y8: 0 | Z8: 0 | AA8: 0 | AB8: 0 | AC8: 0 | AD8: 0 | AE8: 0 | AF8: 0 | AG8: 0 | AH8: 0 | AI8: -1652 | AJ8: 313 | AK8: 0 | AL8: 95.1 | AM8: 106.3 | AN8: 2076.8 | AO8: 16709.2 | AP8: 0 | AQ8: 12633.3 | AR8: 13822.9 | AS8: 4180.8 | AT8: 21062.9 | AU8: 0 | AV8: 5229.6 | AW8: 37727.9 | AX8: 474 | AY8: 9615 | AZ8: 0 | BA8: 3378.4 | BB8: 3563.2 | BC8: -673.4 | BD8: 2486.6 | BE8: 0 | BF8: -95.6 | BG8: 2520.7 | BH8: =IF(O8=0,"na",O8+T8+Y8+AD8+AI8+AN8-AX8) -> 61245.9 | BI8: =IF(P8=0,"na",P8+U8+Z8+AE8+AJ8+AO8-AY8) -> 63258.3 | BJ8: na | BK8: =IF(R8=0,"na",R8+W8+AB8+AG8+AL8+AQ8-BA8) -> 43134.8 | BL8: =IF(S8=0,"na",S8+X8+AC8+AH8+AM8+AR8-BB8) -> 47825.1
B9: KOSDAQ:A173940 | C9: FNC ENTERTAINMENT Co., Ltd. (KOSDAQ:A173940) | D9: 53639.2 | E9: 10015.5 | F9: 34405.9 | G9: 0 | H9: 0 | I9: 0 | J9: 93.6 | K9: 28651 | L9: 98873.2 | M9: -4469.3 | N9: -294.9 | O9: 81741.6 | P9: 113349.8 | Q9: 79198.4 | R9: 75506.2 | S9: 53639.2 | T9: 0 | U9: 0 | V9: 0 | W9: 0 | X9: 0 | Y9: 0 | Z9: 0 | AA9: 0 | AB9: 0 | AC9: 0 | AD9: 0 | AE9: 0 | AF9: 0 | AG9: 0 | AH9: 0 | AI9: 242.3 | AJ9: 123.2 | AK9: 110.5 | AL9: 94.5 | AM9: 93.6 | AN9: 26241.3 | AO9: 30996.7 | AP9: 12992.6 | AQ9: 11270 | AR9: 10015.5 | AS9: 71676.7 | AT9: 39756.9 | AU9: 25006.7 | AV9: 35741.5 | AW9: 23261.4 | AX9: 9748.8 | AY9: 16073.4 | AZ9: 14069.7 | BA9: 15131 | BB9: 16612.4 | BC9: -1491.2 | BD9: 3196.9 | BE9: -8613.8 | BF9: -3573.5 | BG9: -294.9 | BH9: =IF(O9=0,"na",O9+T9+Y9+AD9+AI9+AN9-AX9) -> 98476.4 | BI9: =IF(P9=0,"na",P9+U9+Z9+AE9+AJ9+AO9-AY9) -> 128396.3 | BJ9: =IF(Q9=0,"na",Q9+V9+AA9+AF9+AK9+AP9-AZ9) -> 78231.8 | BK9: =IF(R9=0,"na",R9+W9+AB9+AG9+AL9+AQ9-BA9) -> 71739.7 | BL9: =IF(S9=0,"na",S9+X9+AC9+AH9+AM9+AR9-BB9) -> 47135.9
B10: KOSE:A352820 | C10: HYBE Co., Ltd. (KOSE:A352820) | D10: 7027393.8 | E10: 1115366.2 | F10: 3224754.9 | G10: 0 | H10: 0 | I10: 0 | J10: 290747.7 | K10: 10635628 | L10: 2137834.1 | M10: 208538.2 | N10: 351804.2 | O10: 5700486.3 | P10: 14440622 | Q10: 7137284.9 | R10: 9799510.5 | S10: 7027393.8 | T10: 0 | U10: 0 | V10: 0 | W10: 0 | X10: 0 | Y10: 0 | Z10: 0 | AA10: 0 | AB10: 0 | AC10: 0 | AD10: 0 | AE10: 0 | AF10: 0 | AG10: 0 | AH10: 0 | AI10: 3604.6 | AJ10: 74653.6 | AK10: 158201.3 | AL10: 190516.7 | AM10: 290747.7 | AN10: 343128 | AO10: 1225946 | AP10: 1113821.3 | AQ10: 1105792.5 | AR10: 1115366.2 | AS10: 1163079.9 | AT10: 1648073.2 | AU10: 1674061.5 | AV10: 1394369.7 | AW10: 1102135.3 | AX10: 10933.6 | AY10: 1045474.6 | AZ10: 737158.3 | BA10: 632781 | BB10: 582027.1 | BC10: 180589.7 | BD10: 272935.7 | BE10: 356001.3 | BF10: 422821.5 | BG10: 351804.2 | BH10: =IF(O10=0,"na",O10+T10+Y10+AD10+AI10+AN10-AX10) -> 6036285.3 | BI10: =IF(P10=0,"na",P10+U10+Z10+AE10+AJ10+AO10-AY10) -> 14695747 | BJ10: =IF(Q10=0,"na",Q10+V10+AA10+AF10+AK10+AP10-AZ10) -> 7672149.2 | BK10: =IF(R10=0,"na",R10+W10+AB10+AG10+AL10+AQ10-BA10) -> 10463039 | BL10: =IF(S10=0,"na",S10+X10+AC10+AH10+AM10+AR10-BB10) -> 7851480.6
B11: KOSDAQ:A035900 | C11: JYP Entertainment Corporation (KOSDAQ:A035900) | D11: 1669079.6 | E11: 10472.8 | F11: 453852.5 | G11: 0 | H11: 0 | I11: 0 | J11: 3816 | K11: 2484131.2 | L11: 559753.8 | M11: 129157.8 | N11: 143019.3 | O11: 1271118.1 | P11: 1679035.5 | Q11: 2232310.9 | R11: 3380297.7 | S11: 1669079.6 | T11: 0 | U11: 0 | V11: 0 | W11: 0 | X11: 0 | Y11: 0 | Z11: 0 | AA11: 0 | AB11: 0 | AC11: 0 | AD11: 0 | AE11: 0 | AF11: 0 | AG11: 0 | AH11: 0 | AI11: 3575.6 | AJ11: 4027.5 | AK11: 3943.1 | AL11: 4020.8 | AM11: 3816 | AN11: 2723.2 | AO11: 2359.6 | AP11: 3492.6 | AQ11: 10040.1 | AR11: 10472.8 | AS11: 103628.1 | AT11: 106692.6 | AU11: 159658 | AV11: 262742.4 | AW11: 214386.1 | AX11: 16694.3 | AY11: 80447.6 | AZ11: 87817.1 | BA11: 83052.3 | BB11: 87706.3 | BC11: 48207.5 | BD11: 62584.6 | BE11: 102676.2 | BF11: 180495.8 | BG11: 143019.3 | BH11: =IF(O11=0,"na",O11+T11+Y11+AD11+AI11+AN11-AX11) -> 1260722.6 | BI11: =IF(P11=0,"na",P11+U11+Z11+AE11+AJ11+AO11-AY11) -> 1604975 | BJ11: =IF(Q11=0,"na",Q11+V11+AA11+AF11+AK11+AP11-AZ11) -> 2151929.5 | BK11: =IF(R11=0,"na",R11+W11+AB11+AG11+AL11+AQ11-BA11) -> 3311306.3 | BL11: =IF(S11=0,"na",S11+X11+AC11+AH11+AM11+AR11-BB11) -> 1595662.1
B12: KOSDAQ:A361570 | C12: RBW Inc. (KOSDAQ:A361570) | D12: 72990.6 | E12: 12151.3 | F12: 77383 | G12: 0 | H12: 0 | I12: 0 | J12: 8102 | K12: 71948 | L12: 73698.8 | M12: -10739.3 | N12: -4787.4 | O12: 0 | P12: 215836 | Q12: 123344.2 | R12: 114976.9 | S12: 72990.6 | T12: 0 | U12: 0 | V12: 0 | W12: 0 | X12: 0 | Y12: 0 | Z12: 0 | AA12: 0 | AB12: 0 | AC12: 0 | AD12: 0 | AE12: 0 | AF12: 0 | AG12: 0 | AH12: 0 | AI12: 362.8 | AJ12: 2150.6 | AK12: 11955.7 | AL12: 12088.6 | AM12: 8102 | AN12: 12839.6 | AO12: 2242.7 | AP12: 7806.3 | AQ12: 24410 | AR12: 12151.3 | AS12: 46968.5 | AT12: 26621.4 | AU12: 37826.7 | AV12: 34662.1 | AW12: 21907.8 | AX12: 313.1 | AY12: 1720.3 | AZ12: 8022.1 | BA12: 16022 | BB12: 33991.1 | BC12: 8843.8 | BD12: 12586.8 | BE12: 7691.7 | BF12: 3836.9 | BG12: -4787.4 | BH12: =IF(O12=0,"na",O12+T12+Y12+AD12+AI12+AN12-AX12) -> na | BI12: =IF(P12=0,"na",P12+U12+Z12+AE12+AJ12+AO12-AY12) -> 218509 | BJ12: =IF(Q12=0,"na",Q12+V12+AA12+AF12+AK12+AP12-AZ12) -> 135084.1 | BK12: =IF(R12=0,"na",R12+W12+AB12+AG12+AL12+AQ12-BA12) -> 135453.5 | BL12: =IF(S12=0,"na",S12+X12+AC12+AH12+AM12+AR12-BB12) -> 59252.8
B13: KOSDAQ:A041510 | C13: SM Entertainment Co., Ltd. (KOSDAQ:A041510) | D13: 1513287.7 | E13: 103970.8 | F13: 848264.1 | G13: 0 | H13: 0 | I13: 0 | J13: 178023.9 | K13: 1990814.1 | L13: 967230 | M13: 62193.7 | N13: 125751.6 | O13: 696814.3 | P13: 1737367.6 | Q13: 1804033.4 | R13: 2175069.2 | S13: 1513287.7 | T13: 0 | U13: 0 | V13: 0 | W13: 0 | X13: 0 | Y13: 0 | Z13: 0 | AA13: 0 | AB13: 0 | AC13: 0 | AD13: 0 | AE13: 0 | AF13: 0 | AG13: 0 | AH13: 0 | AI13: 184339.5 | AJ13: 172209.3 | AK13: 189411.2 | AL13: 186891.5 | AM13: 178023.9 | AN13: 56270.3 | AO13: 114700.4 | AP13: 106914.5 | AQ13: 143293.9 | AR13: 103970.8 | AS13: 391454 | AT13: 517862.4 | AU13: 534058.2 | AV13: 500620.3 | AW13: 404721.6 | AX13: 68510.9 | AY13: 144284 | AZ13: 213080.2 | BA13: 212706 | BB13: 208881 | BC13: 76210.7 | BD13: 130762.8 | BE13: 151783.4 | BF13: 171423.6 | BG13: 125751.6 | BH13: =IF(O13=0,"na",O13+T13+Y13+AD13+AI13+AN13-AX13) -> 868913.2 | BI13: =IF(P13=0,"na",P13+U13+Z13+AE13+AJ13+AO13-AY13) -> 1879993.3 | BJ13: =IF(Q13=0,"na",Q13+V13+AA13+AF13+AK13+AP13-AZ13) -> 1887278.9 | BK13: =IF(R13=0,"na",R13+W13+AB13+AG13+AL13+AQ13-BA13) -> 2292548.6 | BL13: =IF(S13=0,"na",S13+X13+AC13+AH13+AM13+AR13-BB13) -> 1586401.4
B14: KOSDAQ:A122870 | C14: YG Entertainment Inc. (KOSDAQ:A122870) | D14: 690529.2 | E14: 19059 | F14: 580087.8 | G14: 0 | H14: 160.2 | I14: 0 | J14: 119157.9 | K14: 914491.1 | L14: 370268 | M14: -18389.5 | N14: 12960.5 | O14: 816784.9 | P14: 1019906.5 | Q14: 807452.9 | R14: 950659.9 | S14: 690529.2 | T14: 160.2 | U14: 160.2 | V14: 160.2 | W14: 160.2 | X14: 160.2 | Y14: 0 | Z14: 0 | AA14: 0 | AB14: 0 | AC14: 0 | AD14: 0 | AE14: 0 | AF14: 0 | AG14: 0 | AH14: 0 | AI14: 71172.5 | AJ14: 105191.8 | AK14: 116638.5 | AL14: 118496.8 | AM14: 119157.9 | AN14: 27887.8 | AO14: 29250.1 | AP14: 22381.1 | AQ14: 15374.8 | AR14: 19059 | AS14: 156793 | AT14: 157132.2 | AU14: 189081.8 | AV14: 223968.7 | AW14: 182925.5 | AX14: 59770 | AY14: 119388.8 | AZ14: 127194.3 | BA14: 137183.8 | BB14: 183502.6 | BC14: 21697 | BD14: 28709.2 | BE14: 55742.2 | BF14: 99002.8 | BG14: 12960.5 | BH14: =IF(O14=0,"na",O14+T14+Y14+AD14+AI14+AN14-AX14) -> 856235.4 | BI14: =IF(P14=0,"na",P14+U14+Z14+AE14+AJ14+AO14-AY14) -> 1035119.8 | BJ14: =IF(Q14=0,"na",Q14+V14+AA14+AF14+AK14+AP14-AZ14) -> 819438.4 | BK14: =IF(R14=0,"na",R14+W14+AB14+AG14+AL14+AQ14-BA14) -> 947507.9 | BL14: =IF(S14=0,"na",S14+X14+AC14+AH14+AM14+AR14-BB14) -> 645403.7

Sheet Size Premium
B1: Size Premium
B2: As of September 30, 2024
B3: KRW in millions
B6: Size Premium | H6: =H15 -> 0.0473
D9: Market Capitalization
B10: KRW in Millions | D10: Min | E10: Max | F10: Median | G10: Mean | H10: Premium
B11: 1분위 | D11: 1660780 | E11: 469000000 | F11: 4089102 | G11: 11400000 | H11: -0.0063
B12: 2분위 | D12: 609450 | E12: 1658212 | F12: 915395 | G12: 995841 | H12: 0.0008
B13: 3분위 | D13: 299250 | E13: 608290 | F13: 412800 | G13: 425863 | H13: 0.0127
B14: 4분위 | D14: 162910 | E14: 299171 | F14: 222198 | G14: 226573 | H14: 0.0247
B15: 5분위 | D15: 22360 | E15: 162876 | F15: 108300 | G15: 105495 | H15: 0.0473
B17: Source: 2024 한국의 기업규모위험 프리미엄 연구결과, 한국공인회계사회

Sheet Bond Yield
B1: Bond Yield
B2: As of September 30, 2024
B3: KRW in millions
B5: Source: SEIBRO
B7: 구분 | D7: 신용등급 | E7: 3M | F7: 6M | G7: 9M | H7: 1Y | I7: 3Y | J7: 5Y | K7: 10Y | L7: 20Y
B8: 국채 | C8: 국고채권 | D8: 양곡, 외평, 재정 | E8: 3.06 | F8: 2.97 | G8: 2.91 | H8: 2.82 | I8: 2.81 | J8: 2.89 | K8: 2.99 | L8: 2.91
B9: 국채 | C9: 국민주택2종 | D9: 국민주택2종 | E9: 2.91 | F9: 2.85 | G9: 2.81 | H9: 2.69 | I9: 2.71 | J9: 2.84 | K9: 3.12 | L9: 3.17
B10: 국채 | C10: 국민주택1종 | D10: 국민주택1종 및 기타국채 | E10: 3.14 | F10: 3.04 | G10: 3 | H10: 2.9 | I10: 2.89 | J10: 3.07 | K10: 0 | L10: 0
B11: 지방채 | C11: 서울도시철도 | D11: 서울도시철도채권 | E11: 3.2 | F11: 3.14 | G11: 3.07 | H11: 2.97 | I11: 3.03 | J11: 3.12 | K11: 0 | L11: 0
B12: 지방채 | C12: 지역개발 | D12: 지역개발채권 및 기타지방채 | E12: 3.2 | F12: 3.14 | G12: 3.07 | H12: 2.97 | I12: 3.03 | J12: 3.12 | K12: 3.38 | L12: 3.38
B13: 특수채 | C13: 공사채 공단채 | D13: 특수채 AAA | E13: 3.43 | F13: 3.37 | G13: 3.24 | H13: 3.19 | I13: 3.08 | J13: 3.14 | K13: 3.18 | L13: 3.12
B14: 특수채 | C14: 공사채 공단채 | D14: 특수채 AA+ | E14: 3.46 | F14: 3.43 | G14: 3.31 | H14: 3.24 | I14: 3.17 | J14: 3.28 | K14: 3.38 | L14: 3.36
B15: 특수채 | C15: 공사채 공단채 | D15: 특수채 AA0 | E15: 3.52 | F15: 3.5 | G15: 3.4 | H15: 3.33 | I15: 3.32 | J15: 3.42 | K15: 3.52 | L15: 3.5
B16: 특수채 | C16: 공사채 공단채 | D16: 특수채 AA- | E16: 3.65 | F16: 3.64 | G16: 3.56 | H16: 3.56 | I16: 3.45 | J16: 3.55 | K16: 3.64 | L16: 3.63
B17: 특수채 | C17: 예금보험 | D17: 예금보험채 | E17: 3.42 | F17: 3.32 | G17: 3.18 | H17: 3.1 | I17: 2.97 | J17: 3.08 | K17: 3.12 | L17: 3.05
B18: 특수채 | C18: MBS | D18: MBS | E18: 3.37 | F18: 3.38 | G18: 3.28 | H18: 3.25 | I18: 3.19 | J18: 3.27 | K18: 3.32 | L18: 3.24
B19: 통안증권 | C19: 통안증권 | D19: 통안증권 | E19: 3.2 | F19: 3.07 | G19: 2.95 | H19: 2.84 | I19: 2.89 | J19: 0 | K19: 0 | L19: 0
... B47: 회사채 | C47: 공모무보증 | D47: 무보증 공모 회사채 BBB- | E47: 5.41 | F47: 6.03 | G47: 6.55 | H47: 6.83 | I47: 9.27 | J47: 9.72 | K47: 10.22 | L47: 10.89

Sheet Beta
B1: Beta
B2: As of September 30, 2024
B3: KRW in millions
B7: No. | C7: Company Name | D7: Beta_adj. | E7: Start date | F7: End date | G7: Period | H7: Rel_Index
B8: 1 | C8: JYP Entertainment Corporation (KOSDAQ:A035900) | D8: 0.691 | E8: 44835 | F8: 45565 | G8: w | H8: KOSPI Index
B9: 2 | C9: SM Entertainment Co., Ltd. (KOSDAQ:A041510) | D9: 0.493 | E9: 44835 | F9: 45565 | G9: w | H9: KOSPI Index
B10: 3 | C10: YG Entertainment Inc. (KOSDAQ:A122870) | D10: 0.746 | E10: 44835 | F10: 45565 | G10: w | H10: KOSPI Index
B11: 4 | C11: Cube Entertainment, Inc. (KOSDAQ:A182360) | D11: 0.557 | E11: 44835 | F11: 45565 | G11: w | H11: KOSPI Index
B12: 5 | C12: FNC ENTERTAINMENT Co., Ltd. (KOSDAQ:A173940) | D12: 0.468 | E12: 44835 | F12: 45565 | G12: w | H12: KOSPI Index
B13: 6 | C13: Fantagio Corp. (KOSDAQ:A032800) | D13: 0.961 | E13: 44835 | F13: 45565 | G13: w | H13: KOSPI Index
B14: 7 | C14: RBW Inc. (KOSDAQ:A361570) | D14: 0.785 | E14: 44835 | F14: 45565 | G14: w | H14: KOSPI Index
B15: 8 | C15: HYBE Co., Ltd. (KOSE:A352820) | D15: 0.635 | E15: 44835 | F15: 45565 | G15: w | H15: KOSPI Index

Sheet Tax
B1: Tax
B2: As of September 30, 2024
B3: KRW in millions
B5: Marginal Tax Rate
B7: % | D7: Marginal Tax
B8: ~ 2억 | C8: 200 | D8: 0.099
B9: 2억 ~ 200억 | C9: 20000 | D9: 0.209
B10: 200억 ~ 3,000억 | C10: 300000 | D10: 0.231
B11: 3,000억 ~ | D11: 0.264
B13: Domestic Company
B15: Company Name | C15: EBIT [CY 2020] (KRWmm, Historical rate) | D15: EBIT [CY 2021] (KRWmm, Historical rate) | E15: EBIT [CY 2022] (KRWmm, Historical rate) | F15: EBIT [CY 2023] (KRWmm, Historical rate) | G15: EBIT [LTM CQ3 2024] (KRWmm, Historical rate) | H15: Marginal tax
A16: KOSDAQ:A182360 | B16: =VLOOKUP($A16,CIQ!$B$6:$N$14,2,FALSE()) -> Cube Entertainment, Inc. (KOSDAQ:A182360) | C16: 1115.5 | D16: 1047.3 | E16: 6924.4 | F16: 15182.6 | G16: 21072.4 | H16: 0.231
A17: KOSDAQ:A032800 | B17: =VLOOKUP($A17,CIQ!$B$6:$N$14,2,FALSE()) -> Fantagio Corp. (KOSDAQ:A032800) | C17: -1708.5 | D17: 1241.2 | E17: -1255.1107 | F17: -3504.5 | G17: -1758.7 | H17: 0 | I17: 손실
A18: KOSDAQ:A173940 | B18: =VLOOKUP($A18,CIQ!$B$6:$N$14,2,FALSE()) -> FNC ENTERTAINMENT Co., Ltd. (KOSDAQ:A173940) | C18: -7322.1 | D18: -4192.2 | E18: -13183.2 | F18: -7568.8 | G18: -4469.3 | H18: 0 | I18: 손실
A19: KOSE:A352820 | B19: =VLOOKUP($A19,CIQ!$B$6:$N$14,2,FALSE()) -> HYBE Co., Ltd. (KOSE:A352820) | C19: 145642.5 | D19: 189640.9 | E19: 237124.5 | F19: 295469 | G19: 208538.2 | H19: 0.231
A20: KOSDAQ:A035900 | B20: =VLOOKUP($A20,CIQ!$B$6:$N$14,2,FALSE()) -> JYP Entertainment Corporation (KOSDAQ:A035900) | C20: 44136.5 | D20: 57893.8 | E20: 96631.5 | F20: 169440.7 | G20: 129157.8 | H20: 0.231
A21: KOSDAQ:A361570 | B21: =VLOOKUP($A21,CIQ!$B$6:$N$14,2,FALSE()) -> RBW Inc. (KOSDAQ:A361570) | C21: 7626.9 | D21: 9577.7 | E21: 2880.9 | F21: -2230.6 | G21: -10739.3 | H21: 0.209 | I21: 손실
A22: KOSDAQ:A041510 | B22: =VLOOKUP($A22,CIQ!$B$6:$N$14,2,FALSE()) -> SM Entertainment Co., Ltd. (KOSDAQ:A041510) | C22: 4479.8 | D22: 66771.9 | E22: 90941.4 | F22: 113410.4 | G22: 62193.7 | H22: 0.231
A23: KOSDAQ:A122870 | B23: =VLOOKUP($A23,CIQ!$B$6:$N$14,2,FALSE()) -> YG Entertainment Inc. (KOSDAQ:A122870) | C23: 5772.8 | D23: 17563.4 | E23: 42314.3 | F23: 79451.4 | G23: -18389.5 | H23: 0.231

Sheet EIU
A2: South Korea
A3: =CONCATENATE("Copyright © ",TEXT(TODAY(),"YYYY")," The Economist Intelligence Unit.") -> Copyright © 2026 The Economist Intelligence Unit.
A4: Legends
A5: Actuals in Black
A6: Estimates in Blue
A7: Forecasts in light blue background
A8: Review months (applicable only for risk products)
A9: Series | B9: Code | C9: Currency | D9: Units | E9: Source | F9: Definition | G9: Note | H9: Published | I9: 2015 | J9: 2016 | K9: 2017 | L9: 2018 | M9: 2019 | N9: 2020 | O9: 2021 | P9: 2022 | Q9: 2023 | R9: 2024 | S9: 2025 | T9: 2026 | U9: 2027 | V9: 2028 | W9: 2029 | X9: 2030 | Y9: 2031 | Z9: 2032 | AA9: 2033 | AB9: 2034 | AC9: 2035 | AD9: 2036 | AE9: 2037 | AF9: 2038 | AG9: 2039 | AH9: 2040 | AI9: 2041 | AJ9: 2042 | AK9: 2043 | AL9: 2044 | AM9: 2045 | AN9: 2046 | AO9: 2047 | AP9: 2048 | AQ9: 2049 | AR9: 2050
A10: % HHs with wealth >US$100k | B10: P100 | E10: EIU estimates | F10: Percentage of households with net financial wealth of more than US$100,000. | G10: Zero (0.0) indicates a small or negligible number of households (<0.5% of households) with wealth above this band. | H10: 19-12-2024 | I10: 18.5 | J10: 18.2 | K10: 22 | L10: 20.4 | M10: 21 | N10: 25.9 | O10: 25.3 | P10: 23.4 | Q10: 24.1 | R10: 26.5 | S10: 28.2 | T10: 28.6 | U10: 30.1 | V10: 31.1 | W10: – | X10: – | Y10: – | Z10: – | AA10: – | AB10: – | AC10: – | AD10: – | AE10: – | AF10: – | AG10: – | AH10: – | AI10: – | AJ10: – | AK10: – | AL10: – | AM10: – | AN10: – | AO10: – | AP10: – | AQ10: – | AR10: –
A11: % HHs with wealth >US$1m | B11: P01M | E11: EIU estimates | F11: Percentage of households with net financial wealth of more than US$1,000,000. | G11: Zero (0.0) indicates a small or negligible number of households (<0.5% of households) with wealth above this band. | H11: 19-12-2024 | I11: 0.6 | J11: 0.6 | K11: 0.9 | L11: 0.7 | M11: 0.8 | N11: 1.1 | O11: 1.1 | P11: 0.9 | Q11: 1 | R11: 1.2 | S11: 1.3 | T11: 1.4 | U11: 1.5 | V11: 1.7 | W11: – | X11: – | Y11: – | Z11: – | AA11: – | AB11: – | AC11: – | AD11: – | AE11: – | AF11: – | AG11: – | AH11: – | AI11: – | AJ11: – | AK11: – | AL11: – | AM11: – | AN11: – | AO11: – | AP11: – | AQ11: – | AR11: –
A12: % HHs with wealth >US$250k | B12: P250 | E12: EIU estimates | F12: Percentage of households with net financial wealth of more than US$250,000. | G12: Zero (0.0) indicates a small or negligible number of households (<0.5% of households) with wealth above this band. | H12: 19-12-2024 | I12: 5.9 | J12: 5.8 | K12: 7.5 | L12: 6.8 | M12: 7 | N12: 9.4 | O12: 9.1 | P12: 8.2 | Q12: 8.5 | R12: 9.8 | S12: 10.7 | T12: 11 | U12: 11.9 | V12: 12.5 | W12: – | X12: – | Y12: – | Z12: – | AA12: – | AB12: – | AC12: – | AD12: – | AE12: – | AF12: – | AG12: – | AH12: – | AI12: – | AJ12: – | AK12: – | AL12: – | AM12: – | AN12: – | AO12: – | AP12: – | AQ12: – | AR12: –
A13: % HHs with wealth >US$500k | B13: P500 | E13: EIU estimates | F13: Percentage of households with net financial wealth of more than US$500,000. | G13: Zero (0.0) indicates a small or negligible number of households (<0.5% of households) with wealth above this band. | H13: 19-12-2024 | I13: 2 | J13: 2 | K13: 2.7 | L13: 2.4 | M13: 2.5 | N13: 3.5 | O13: 3.4 | P13: 3 | Q13: 3.1 | R13: 3.7 | S13: 4.1 | T13: 4.2 | U13: 4.6 | V13: 4.9 | W13: – | X13: – | Y13: – | Z13: – | AA13: – | AB13: – | AC13: – | AD13: – | AE13: – | AF13: – | AG13: – | AH13: – | AI13: – | AJ13: – | AK13: – | AL13: – | AM13: – | AN13: – | AO13: – | AP13: – | AQ13: – | AR13: –
A14: % of HHs earning > US$1,000 p.a. | B14: P001 | E14: EIU calculation | F14: Percentage of households with nominal disposable income of more than US$1,000 per annum | G14: Zero (0.0) indicates a small or negligible number of households earning above this band. | H14: 19-12-2024 | I14: 99.4 | J14: 99.3 | K14: 99.4 | L14: 99.4 | M14: 99.4 | N14: 99.4 | O14: 99.4 | P14: 99.4 | Q14: 99.4 | R14: 99.4 | S14: 99.5 | T14: 99.5 | U14: 99.5 | V14: 99.5 | W14: – | X14: – | Y14: – | Z14: – | AA14: – | AB14: – | AC14: – | AD14: – | AE14: – | AF14: – | AG14: – | AH14: – | AI14: – | AJ14: – | AK14: – | AL14: – | AM14: – | AN14: – | AO14: – | AP14: – | AQ14: – | AR14: –
A15: % of HHs earning > US$1,000 p.a. (constant prices) | B15: S100 | E15: EIU calculation | F15: Percentage of households with disposable income of more than US$1,000 per annum at 2019 constant prices. | G15: Zero (0.0) indicates a small or negligible number of households earning above this band. | H15: 19-12-2024 | I15: 99.4 | J15: 99.3 | K15: 99.3 | L15: 99.4 | M15: 99.4 | N15: 99.4 | O15: 99.4 | P15: 99.4 | Q15: 99.4 | R15: 99.4 | S15: 99.4 | T15: 99.4 | U15: 99.4 | V15: 99.4 | W15: – | X15: – | Y15: – | Z15: – | AA15: – | AB15: – | AC15: – | AD15: – | AE15: – | AF15: – | AG15: – | AH15: – | AI15: – | AJ15: – | AK15: – | AL15: – | AM15: – | AN15: – | AO15: – | AP15: – | AQ15: – | AR15: –
A16: % of HHs earning > US$10,000 p.a. | B16: P010 | E16: EIU calculation | F16: Percentage of households with nominal disposable income of more than US$10,000 per annum | G16: Zero (0.0) indicates a small or negligible number of households earning above this band. | H16: 19-12-2024 | I16: 88.5 | J16: 87.6 | K16: 88.2 | L16: 89 | M16: 88.4 | N16: 88.6 | O16: 89.3 | P16: 88.3 | Q16: 88.5 | R16: 89.4 | S16: 90.3 | T16: 90.6 | U16: 90.9 | V16: 91.1 | W16: – | X16: – | Y16: – | Z16: – | AA16: – | AB16: – | AC16: – | AD16: – | AE16: – | AF16: – | AG16: – | AH16: – | AI16: – | AJ16: – | AK16: – | AL16: – | AM16: – | AN16: – | AO16: – | AP16: – | AQ16: – | AR16: –
A17: % of HHs earning > US$10,000 p.a. (constant prices) | B17: S010 | E17: EIU calculation | F17: Percentage of households with disposable income of more than US$10,000 per annum at 2019 constant prices. | G17: Zero (0.0) indicates a small or negligible number of households earning above this band. | H17: 19-12-2024 | I17: 88.7 | J17: 88 | K17: 88 | L17: 88.2 | M17: 88.4 | N17: 88.6 | O17: 88.5 | P17: 88.6 | Q17: 88.5 | R17: 88.7 | S17: 88.8 | T17: 88.9 | U17: 89 | V17: 89.1 | W17: – | X17: – | Y17: – | Z17: – | AA17: – | AB17: – | AC17: – | AD17: – | AE17: – | AF17: – | AG17: – | AH17: – | AI17: – | AJ17: – | AK17: – | AL17: – | AM17: – | AN17: – | AO17: – | AP17: – | AQ17: – | AR17: –
A18: % of HHs earning > US$15,000 p.a. | B18: P015 | E18: EIU calculation | F18: Percentage of households with nominal disposable income of more than US$15,000 | G18: Zero (0.0) indicates a small or negligible number of households earning above this band. | H18: 19-12-2024 | I18: 80.9 | J18: 79.7 | K18: 80.7 | L18: 81.9 | M18: 81 | N18: 81.3 | O18: 82.4 | P18: 80.9 | Q18: 81.2 | R18: 82.6 | S18: 84 | T18: 84.6 | U18: 85.1 | V18: 85.4 | W18: – | X18: – | Y18: – | Z18: – | AA18: – | AB18: – | AC18: – | AD18: – | AE18: – | AF18: – | AG18: – | AH18: – | AI18: – | AJ18: – | AK18: – | AL18: – | AM18: – | AN18: – | AO18: – | AP18: – | AQ18: – | AR18: –
A19: % of HHs earning > US$15,000 p.a. (constant prices) | B19: S015 | E19: EIU calculation | F19: Percentage of households with disposable income of more than US$15,000 per annum at 2019 constant prices. | G19: Zero (0.0) indicates a small or negligible number of households earning above this band. | H19: 19-12-2024 | I19: 81.3 | J19: 80.4 | K19: 80.4 | L19: 80.8 | M19: 81 | N19: 81.3 | O19: 81.3 | P19: 81.4 | Q19: 81.2 | R19: 81.5 | S19: 81.7 | T19: 81.8 | U19: 81.9 | V19: 82.1 | W19: – | X19: – | Y19: – | Z19: – | AA19: – | AB19: – | AC19: – | AD19: – | AE19: – | AF19: – | AG19: – | AH19: – | AI19: – | AJ19: – | AK19: – | AL19: – | AM19: – | AN19: – | AO19: – | AP19: – | AQ19: – | AR19: –
A20: % of HHs earning > US$25,000 p.a. | B20: P025 | E20: EIU calculation | F20: Percentage of households with nominal disposable income of more than US$25,000 per annum | G20: Zero (0.0) indicates a small or negligible number of households earning above this band. | H20: 19-12-2024 | I20: 65 | J20: 63.5 | K20: 65.2 | L20: 67.3 | M20: 65.7 | N20: 66.1 | O20: 68.1 | P20: 65.5 | Q20: 66.1 | R20: 68.3 | S20: 70.8 | T20: 71.8 | U20: 72.6 | V20: 73.2 | W20: – | X20: – | Y20: – | Z20: – | AA20: – | AB20: – | AC20: – | AD20: – | AE20: – | AF20: – | AG20: – | AH20: – | AI20: – | AJ20: – | AK20: – | AL20: – | AM20: – | AN20: – | AO20: – | AP20: – | AQ20: – | AR20: –
A21: % of HHs earning > US$25,000 p.a. (constant prices) | B21: S025 | E21: EIU calculation | F21: Percentage of households with disposable income of more than US$25,000 per annum at 2019 constant prices. | G21: Zero (0.0) indicates a small or negligible number of households earning above this band. | H21: 19-12-2024 | I21: 65.6 | J21: 64.8 | K21: 64.8 | L21: 65.3 | M21: 65.7 | N21: 66.2 | O21: 66.1 | P21: 66.4 | Q21: 66.1 | R21: 66.5 | S21: 66.8 | T21: 67.1 | U21: 67.3 | V21: 67.5 | W21: – | X21: – | Y21: – | Z21: – | AA21: – | AB21: – | AC21: – | AD21: – | AE21: – | AF21: – | AG21: – | AH21: – | AI21: – | AJ21: – | AK21: – | AL21: – | AM21: – | AN21: – | AO21: – | AP21: – | AQ21: – | AR21: –
... A31: % of HHs earning > US$75,000 p.a. (constant prices) | B31: S075 | E31: EIU calculation | F31: Percentage of households with disposable income of more than US$75,000 per annum at 2019 constant prices. | G31: Zero (0.0) indicates a small or negligible number of households earning above this band. | H31: 19-12-2024 | I31: 11 | J31: 11.1 | K31: 11.1 | L31: 11.6 | M31: 12.1 | N31: 12.6 | O31: 12.5 | P31: 12.8 | Q31: 12.4 | R31: 12.8 | S31: 13.2 | T31: 13.5 | U31: 13.8 | V31: 14.1 | W31: – | X31: – | Y31: – | Z31: – | AA31: – | AB31: – | AC31: – | AD31: – | AE31: – | AF31: – | AG31: – | AH31: – | AI31: – | AJ31: – | AK31: – | AL31: – | AM31: – | AN31: – | AO31: – | AP31: – | AQ31: – | AR31: –
A32: % of population aged 0 -14 | B32: YPOR | E32: UN Population Data | F32: Percentage of people in a country aged between 0 and 14 years | H32: 19-12-2024 | I32: 13.771 | J32: 13.37 | K32: 13.05 | L32: 12.76 | M32: 12.454 | N32: 12.166 | O32: 11.9 | P32: 11.6 | Q32: 11.2 | R32: 10.9 | S32: 10.6 | T32: 10.3 | U32: 10 | V32: 9.7 | W32: 9.5 | X32: 9.3 | Y32: – | Z32: – | AA32: – | AB32: – | AC32: – | AD32: – | AE32: – | AF32: – | AG32: – | AH32: – | AI32: – | AJ32: – | AK32: – | AL32: – | AM32: – | AN32: – | AO32: – | AP32: – | AQ32: – | AR32: –
A33: % of population aged 0-4 | B33: PP05 | E33: UN Population Data | F33: Percentage of people in a country aged between 0 and 4 years | H33: 19-12-2024 | I33: 4.437 | J33: 4.311 | K33: 4.12 | L33: 3.911 | M33: 3.69 | N33: 3.434 | O33: 3.2 | P33: 3 | Q33: 2.9 | R33: 2.8 | S33: 2.8 | T33: 2.8 | U33: 2.8 | V33: 2.9 | W33: 2.9 | X33: 2.9 | Y33: – | Z33: – | AA33: – | AB33: – | AC33: – | AD33: – | AE33: – | AF33: – | AG33: – | AH33: – | AI33: – | AJ33: – | AK33: – | AL33: – | AM33: – | AN33: – | AO33: – | AP33: – | AQ33: – | AR33: –
A34: % of population aged 10-14 | B34: PP15 | E34: UN Population Data | F34: Percentage of people in a country aged between 10 and 14 years | H34: 19-12-2024 | I34: 4.9 | J34: 4.593 | K34: 4.451 | L34: 4.404 | M34: 4.359 | N34: 4.361 | O34: 4.4 | P34: 4.4 | Q34: 4.4 | R34: 4.4 | S34: 4.4 | T34: 4.3 | U34: 4.2 | V34: 4 | W34: 3.7 | X34: 3.5 | Y34: – | Z34: – | AA34: – | AB34: – | AC34: – | AD34: – | AE34: – | AF34: – | AG34: – | AH34: – | AI34: – | AJ34: – | AK34: – | AL34: – | AM34: – | AN34: – | AO34: – | AP34: – | AQ34: – | AR34: –
A35: % of population aged 100 and over | B35: PP01 | E35: UN Population Data | F35: Percentage of people in a country aged 100 years and over | H35: 19-12-2024 | I35: 0.012 | J35: 0.013 | K35: 0.014 | L35: 0.015 | M35: 0.016 | N35: 0.016 | O35: 0 | P35: 0 | Q35: 0 | R35: 0 | S35: 0 | T35: 0 | U35: 0 | V35: 0 | W35: 0 | X35: 0 | Y35: – | Z35: – | AA35: – | AB35: – | AC35: – | AD35: – | AE35: – | AF35: – | AG35: – | AH35: – | AI35: – | AJ35: – | AK35: – | AL35: – | AM35: – | AN35: – | AO35: – | AP35: – | AQ35: – | AR35: –
A36: % of population aged 15-19 | B36: PP20 | E36: UN Population Data | F36: Percentage of people in a country aged between 15 and 19 years | H36: 19-12-2024 | I36: 6.325 | J36: 6.106 | K36: 5.842 | L36: 5.533 | M36: 5.224 | N36: 4.876 | O36: 4.6 | P36: 4.4 | Q36: 4.4 | R36: 4.4 | S36: 4.4 | T36: 4.5 | U36: 4.5 | V36: 4.5 | W36: 4.5 | X36: 4.4 | Y36: – | Z36: – | AA36: – | AB36: – | AC36: – | AD36: – | AE36: – | AF36: – | AG36: – | AH36: – | AI36: – | AJ36: – | AK36: – | AL36: – | AM36: – | AN36: – | AO36: – | AP36: – | AQ36: – | AR36: –
A37: % of population aged 15-64 | B37: LPOR | E37: UN Population Data | F37: Percentage of people in a country aged between 15 and 64 years | H37: 19-12-2024 | I37: 73.271 | J37: 73.266 | K37: 73.077 | L37: 72.787 | M37: 72.481 | N37: 72.005 | O37: 71.5 | P37: 70.9 | Q37: 70.4 | R37: 69.8 | S37: 69 | T37: 68.2 | U37: 67.6 | V37: 66.9 | W37: 66.3 | X37: 65.8 | Y37: – | Z37: – | AA37: – | AB37: – | AC37: – | AD37: – | AE37: – | AF37: – | AG37: – | AH37: – | AI37: – | AJ37: – | AK37: – | AL37: – | AM37: – | AN37: – | AO37: – | AP37: – | AQ37: – | AR37: –
A38: % of population aged 20-24 | B38: PP25 | E38: UN Population Data | F38: Percentage of people in a country aged between 20 and 24 years | H38: 19-12-2024 | I38: 6.894 | J38: 6.906 | K38: 6.862 | L38: 6.762 | M38: 6.637 | N38: 6.481 | O38: 6.3 | P38: 6 | Q38: 5.6 | R38: 5.3 | S38: 4.9 | T38: 4.6 | U38: 4.5 | V38: 4.5 | W38: 4.5 | X38: 4.5 | Y38: – | Z38: – | AA38: – | AB38: – | AC38: – | AD38: – | AE38: – | AF38: – | AG38: – | AH38: – | AI38: – | AJ38: – | AK38: – | AL38: – | AM38: – | AN38: – | AO38: – | AP38: – | AQ38: – | AR38: –
A39: % of population aged 25-29 | B39: PP30 | E39: UN Population Data | F39: Percentage of people in a country aged between 25 and 29 years | H39: 19-12-2024 | I39: 6.403 | J39: 6.423 | K39: 6.54 | L39: 6.707 | M39: 6.872 | N39: 6.992 | O39: 7 | P39: 7 | Q39: 6.9 | R39: 6.7 | S39: 6.5 | T39: 6.3 | U39: 6 | V39: 5.7 | W39: 5.4 | X39: 5 | Y39: – | Z39: – | AA39: – | AB39: – | AC39: – | AD39: – | AE39: – | AF39: – | AG39: – | AH39: – | AI39: – | AJ39: – | AK39: – | AL39: – | AM39: – | AN39: – | AO39: – | AP39: – | AQ39: – | AR39: –
A40: % of population aged 30-34 | B40: PP35 | E40: UN Population Data | F40: Percentage of people in a country aged between 30 and 34 years | H40: 19-12-2024 | I40: 7.56 | J40: 7.196 | K40: 6.824 | L40: 6.528 | M40: 6.379 | N40: 6.356 | O40: 6.42 | P40: 6.57 | Q40: 6.76 | R40: 6.92 | S40: 7.05 | T40: 7.11 | U40: 7.07 | V40: 6.95 | W40: 6.8 | X40: 6.64 | Y40: – | Z40: – | AA40: – | AB40: – | AC40: – | AD40: – | AE40: – | AF40: – | AG40: – | AH40: – | AI40: – | AJ40: – | AK40: – | AL40: – | AM40: – | AN40: – | AO40: – | AP40: – | AQ40: – | AR40: –
A41: % of population aged 35-39 | B41: PP40 | E41: UN Population Data | F41: Percentage of people in a country aged between 35 and 39 years | H41: 19-12-2024 | I41: 7.659 | J41: 7.754 | K41: 7.858 | L41: 7.894 | M41: 7.759 | N41: 7.459 | O41: 7.1 | P41: 6.8 | Q41: 6.5 | R41: 6.4 | S41: 6.4 | T41: 6.5 | U41: 6.6 | V41: 6.8 | W41: 7 | X41: 7.1 | Y41: – | Z41: – | AA41: – | AB41: – | AC41: – | AD41: – | AE41: – | AF41: – | AG41: – | AH41: – | AI41: – | AJ41: – | AK41: – | AL41: – | AM41: – | AN41: – | AO41: – | AP41: – | AQ41: – | AR41: –
A42: % of population aged 40-44 | B42: PP45 | E42: UN Population Data | F42: Percentage of people in a country aged between 40 and 44 years | H42: 19-12-2024 | I42: 8.533 | J42: 8.23 | K42: 7.917 | L42: 7.659 | M42: 7.484 | N42: 7.501 | O42: 7.6 | P42: 7.8 | Q42: 7.9 | R42: 7.8 | S42: 7.5 | T42: 7.1 | U42: 6.8 | V42: 6.6 | W42: 6.4 | X42: 6.4 | Y42: – | Z42: – | AA42: – | AB42: – | AC42: – | AD42: – | AE42: – | AF42: – | AG42: – | AH42: – | AI42: – | AJ42: – | AK42: – | AL42: – | AM42: – | AN42: – | AO42: – | AP42: – | AQ42: – | AR42: –
A43: % of population aged 45-49 | B43: PP50 | E43: UN Population Data | F43: Percentage of people in a country aged between 45 and 49 years | H43: 19-12-2024 | I43: 8.549 | J43: 8.682 | K43: 8.769 | L43: 8.725 | M43: 8.601 | N43: 8.405 | O43: 8.1 | P43: 7.8 | Q43: 7.6 | R43: 7.5 | S43: 7.5 | T43: 7.7 | U43: 7.8 | V43: 7.9 | W43: 7.8 | X43: 7.5 | Y43: – | Z43: – | AA43: – | AB43: – | AC43: – | AD43: – | AE43: – | AF43: – | AG43: – | AH43: – | AI43: – | AJ43: – | AK43: – | AL43: – | AM43: – | AN43: – | AO43: – | AP43: – | AQ43: – | AR43: –
... A55: % of population aged 95-99 | B55: PP00 | E55: UN Population Data | F55: Percentage of people in a country aged between 95 and 99 years | H55: 19-12-2024 | I55: 0.068 | J55: 0.07 | K55: 0.072 | L55: 0.077 | M55: 0.084 | N55: 0.093 | O55: 0.1 | P55: 0.1 | Q55: 0.1 | R55: 0.2 | S55: 0.2 | T55: 0.2 | U55: 0.2 | V55: 0.2 | W55: 0.2 | X55: 0.3 | Y55: – | Z55: – | AA55: – | AB55: – | AC55: – | AD55: – | AE55: – | AF55: – | AG55: – | AH55: – | AI55: – | AJ55: – | AK55: – | AL55: – | AM55: – | AN55: – | AO55: – | AP55: – | AQ55: – | AR55: –
A56: % paved roads | B56: PPRD | E56: World Bank - World Development Indicators | F56: Roads surfaced with crushed stone (macadam) and hydrocarbon binder or bituminised agents, with concrete, or with cobblestones, as a percentage of all the countrys roads. | H56: 19-12-2024 | I56: – | J56: – | K56: – | L56: – | M56: – | N56: – | O56: – | P56: – | Q56: – | R56: – | S56: – | T56: – | U56: – | V56: – | W56: – | X56: – | Y56: – | Z56: – | AA56: – | AB56: – | AC56: – | AD56: – | AE56: – | AF56: – | AG56: – | AH56: – | AI56: – | AJ56: – | AK56: – | AL56: – | AM56: – | AN56: – | AO56: – | AP56: – | AQ56: – | AR56: –
A57: Access of firms to medium-term finance for investment (scored 1-5) | B57: MTRR | E57: EIU, Business Environment Rankings | F57: EIUs business environment rankings quantify the attractiveness of the business environment. The access to medium-term finance indicator scores countries between 1 and 5 on the access of foreigners to the local capital market, with 1 being "very poor" and 5 being "very good". | H57: 19-12-2024 | I57: 4 | J57: 4 | K57: 4 | L57: 4 | M57: 4 | N57: 4 | O57: 4 | P57: 4 | Q57: 4 | R57: 4 | S57: 4 | T57: 4 | U57: 4 | V57: 4 | W57: 4 | X57: – | Y57: – | Z57: – | AA57: – | AB57: – | AC57: – | AD57: – | AE57: – | AF57: – | AG57: – | AH57: – | AI57: – | AJ57: – | AK57: – | AL57: – | AM57: – | AN57: – | AO57: – | AP57: – | AQ57: – | AR57: –
A58: Access of foreigners to local capital market (scored 1-5) | B58: FLMR | E58: EIU, Business Environment Rankings | F58: EIUs business environment rankings quantify the attractiveness of the business environment. The access of foreigners to local market indicator scores countries between 1 and 5 on the access of foreigners to the local capital market, with 1 being "very poor" and 5 being "very good". | H58: 19-12-2024 | I58: 3 | J58: 3 | K58: 3 | L58: 3 | M58: 3 | N58: 3 | O58: 3 | P58: 3 | Q58: 3.2 | R58: 3.4 | S58: 3.6 | T58: 3.8 | U58: 4 | V58: 4 | W58: 4 | X58: – | Y58: – | Z58: – | AA58: – | AB58: – | AC58: – | AD58: – | AE58: – | AF58: – | AG58: – | AH58: – | AI58: – | AJ58: – | AK58: – | AL58: – | AM58: – | AN58: – | AO58: – | AP58: – | AQ58: – | AR58: –
A59: Accommodation and food services (% change pa) | B59: PRAF | E59: Derived from Bank of Korea | F59: Percentage change in real accommodation and food services value-added, over previous period. | H59: 19-12-2024 | I59: 0.35742227 | J59: 4.2147676 | K59: 0.54756226 | L59: 3.6543424 | M59: 3.7065822 | N59: -17.303019 | O59: 5.3230866 | P59: 13.436539 | Q59: 1.4145534 | R59: 2.3128322 | S59: 1.8141529 | T59: 2.3320253 | U59: 1.6594376 | V59: 0.99313107 | W59: 2.3737522 | X59: – | Y59: – | Z59: – | AA59: – | AB59: – | AC59: – | AD59: – | AE59: – | AF59: – | AG59: – | AH59: – | AI59: – | AJ59: – | AK59: – | AL59: – | AM59: – | AN59: – | AO59: – | AP59: – | AQ59: – | AR59: –
A60: Accommodation and food services (% of GDP) | B60: RASS | E60: Derived from Bank of Korea | F60: Real accommodation and food services value-added, as percentage of real GDP at factor cost . GDP at factor cost is GDP at market prices, less indirect taxes, plus subsidies. | H60: 19-12-2024 | I60: 2.6591558 | J60: 2.6887322 | K60: 2.6119924 | L60: 2.6197511 | M60: 2.6517 | N60: 2.2118747 | O60: 2.2277951 | P60: 2.4491589 | Q60: 2.4372422 | R60: 2.440863 | S60: 2.4401749 | T60: 2.440519 | U60: 2.4203469 | V60: 2.3904329 | W60: 2.3903899 | X60: – | Y60: – | Z60: – | AA60: – | AB60: – | AC60: – | AD60: – | AE60: – | AF60: – | AG60: – | AH60: – | AI60: – | AJ60: – | AK60: – | AL60: – | AM60: – | AN60: – | AO60: – | AP60: – | AQ60: – | AR60: –
A61: Accommodation and food services (LCU) | B61: XHRR | C61: LCU | D61: bn | E61: Bank of Korea | F61: Accommodation and food services value-added at constant 2020 prices. | H61: 19-12-2024 | I61: 44896.9 | J61: 46789.2 | K61: 47045.4 | L61: 48764.6 | M61: 50572.1 | N61: 41821.6 | O61: 44047.8 | P61: 49966.3 | Q61: 50673.1 | R61: 51845.084 | S61: 52785.633 | T61: 54016.607 | U61: 54912.979 | V61: 55458.337 | W61: 56774.78 | X61: – | Y61: – | Z61: – | AA61: – | AB61: – | AC61: – | AD61: – | AE61: – | AF61: – | AG61: – | AH61: – | AI61: – | AJ61: – | AK61: – | AL61: – | AM61: – | AN61: – | AO61: – | AP61: – | AQ61: – | AR61: –
A62: Activities related to real estate (% of GDP) | B62: ETSS | E62: Derived from Bank of Korea | F62: Real activities related to real estate value-added, as percentage of real GDP at factor cost . GDP at factor cost is GDP at market prices, less indirect taxes, plus subsidies. | H62: 19-12-2024 | I62: 8.0792687 | J62: 8.2077497 | K62: 8.1880394 | L62: 8.1874435 | M62: 8.1504324 | N62: 8.5166134 | O62: 8.2814896 | P62: 7.864539 | Q62: 7.7320735 | R62: 7.6181573 | S62: 7.5174128 | T62: 7.4177851 | U62: 7.367599 | V62: 7.317692 | W62: 7.3176455 | X62: – | Y62: – | Z62: – | AA62: – | AB62: – | AC62: – | AD62: – | AE62: – | AF62: – | AG62: – | AH62: – | AI62: – | AJ62: – | AK62: – | AL62: – | AM62: – | AN62: – | AO62: – | AP62: – | AQ62: – | AR62: –
A63: Adult literacy rate (% of pop over 15) | B63: ADLR | E63: World Bank - World Development Indicators | F63: Percentage of people aged 15 and over who can, with understanding, read and write a short, simple statement about their everyday life. | H63: 19-12-2024 | I63: – | J63: – | K63: – | L63: 98.8 | M63: – | N63: – | O63: – | P63: – | Q63: – | R63: – | S63: – | T63: – | U63: – | V63: – | W63: – | X63: – | Y63: – | Z63: – | AA63: – | AB63: – | AC63: – | AD63: – | AE63: – | AF63: – | AG63: – | AH63: – | AI63: – | AJ63: – | AK63: – | AL63: – | AM63: – | AN63: – | AO63: – | AP63: – | AQ63: – | AR63: –
A64: Agriculture (% change pa) | B64: DAGR | E64: Derived from Bank of Korea | F64: Percentage change in real agricultural value-added, including livestock, forestry and fishing, over previous year. | H64: 19-12-2024 | I64: -0.254 | J64: -6.578 | K64: 1.25 | L64: -0.774 | M64: 2.915 | N64: -6.685 | O64: 3.439 | P64: 0.797 | Q64: -2.639 | R64: 7.1 | S64: 1.2 | T64: 1.7 | U64: 1.9 | V64: 2.3 | W64: 2.4 | X64: – | Y64: – | Z64: – | AA64: – | AB64: – | AC64: – | AD64: – | AE64: – | AF64: – | AG64: – | AH64: – | AI64: – | AJ64: – | AK64: – | AL64: – | AM64: – | AN64: – | AO64: – | AP64: – | AQ64: – | AR64: –
A65: Agriculture (% of GDP) | B65: AGRP | E65: Derived from Bank of Korea | F65: Agricultural value-added, including livestock, forestry and fishing, as percentage of real GDP at factor cost . GDP at factor cost is GDP at market prices, less indirect taxes, plus subsidies. | H65: 19-12-2024 | I65: 2.134 | J65: 1.935 | K65: 1.893 | L65: 1.817 | M65: 1.825 | N65: 1.718 | O65: 1.699 | P65: 1.66 | Q65: 1.586 | R65: 1.7 | S65: 1.7 | T65: 1.6 | U65: 1.6 | V65: 1.6 | W65: 1.6 | X65: – | Y65: – | Z65: – | AA65: – | AB65: – | AC65: – | AD65: – | AE65: – | AF65: – | AG65: – | AH65: – | AI65: – | AJ65: – | AK65: – | AL65: – | AM65: – | AN65: – | AO65: – | AP65: – | AQ65: – | AR65: –
A66: Agriculture (LCU) | B66: RAGR | C66: LCU | D66: bn | E66: Bank of Korea | F66: Agricultural value-added, including livestock, forestry and fishing, at constant 2020 prices. | H66: 19-12-2024 | I66: 36036.3 | J66: 33666 | K66: 34086.7 | L66: 33822.8 | M66: 34808.6 | N66: 32481.7 | O66: 33598.6 | P66: 33866.3 | Q66: 32972.4 | R66: 35309.3 | S66: 35724.6 | T66: 36341 | U66: 37020 | V66: 37858.1 | W66: 38756.2 | X66: – | Y66: – | Z66: – | AA66: – | AB66: – | AC66: – | AD66: – | AE66: – | AF66: – | AG66: – | AH66: – | AI66: – | AJ66: – | AK66: – | AL66: – | AM66: – | AN66: – | AO66: – | AP66: – | AQ66: – | AR66: –
A67: Air transport (freight) (tonne km per head) | B67: ATFC | E67: Derived from World Bank - World Development Indicators | F67: Sum of the metric tonnes of freight, express and diplomatic bags carried on each flight stage multiplied by the stage distance and divided by the total population. | H67: 19-12-2024 | I67: 221.5 | J67: 210.7 | K67: 223.6 | L67: 223.1 | M67: 206 | N67: 240 | O67: 296 | P67: – | Q67: – | R67: – | S67: – | T67: – | U67: – | V67: – | W67: – | X67: – | Y67: – | Z67: – | AA67: – | AB67: – | AC67: – | AD67: – | AE67: – | AF67: – | AG67: – | AH67: – | AI67: – | AJ67: – | AK67: – | AL67: – | AM67: – | AN67: – | AO67: – | AP67: – | AQ67: – | AR67: –
A68: Air transport (freight) (tonne km) | B68: ATFK | D68: m | E68: World Bank - World Development Indicators | F68: Sum of the metric tonnes of freight, express and diplomatic bags carried on each flight stage multiplied by the stage distance. | H68: 19-12-2024 | I68: 11293.8 | J68: 10806 | K68: 11511.8 | L68: 11518.6 | M68: 10664.4 | N68: 12457 | O68: 15370 | P68: – | Q68: – | R68: – | S68: – | T68: – | U68: – | V68: – | W68: – | X68: – | Y68: – | Z68: – | AA68: – | AB68: – | AC68: – | AD68: – | AE68: – | AF68: – | AG68: – | AH68: – | AI68: – | AJ68: – | AK68: – | AL68: – | AM68: – | AN68: – | AO68: – | AP68: – | AQ68: – | AR68: –
A69: Air transport (passengers per 000 pop) | B69: ATPR | E69: Derived from World Bank - World Development Indicators | F69: Number of domestic and international aircraft passengers per 1,000 people. | H69: 19-12-2024 | I69: 1296.3 | J69: 1498.3 | K69: 1608.6 | L69: 1707.2 | M69: 1785.5 | N69: 579 | O69: 656 | P69: – | Q69: – | R69: – | S69: – | T69: – | U69: – | V69: – | W69: – | X69: – | Y69: – | Z69: – | AA69: – | AB69: – | AC69: – | AD69: – | AE69: – | AF69: – | AG69: – | AH69: – | AI69: – | AJ69: – | AK69: – | AL69: – | AM69: – | AN69: – | AO69: – | AP69: – | AQ69: – | AR69: –
A70: Air transport (passengers) | B70: ATPT | D70: '000 | E70: World Bank - World Development Indicators | F70: Total number of domestic and international aircraft passengers. | H70: 19-12-2024 | I70: 66090 | J70: 76860 | K70: 82820 | L70: 88160 | M70: 92430 | N70: 30030 | O70: 34020 | P70: – | Q70: – | R70: – | S70: – | T70: – | U70: – | V70: – | W70: – | X70: – | Y70: – | Z70: – | AA70: – | AB70: – | AC70: – | AD70: – | AE70: – | AF70: – | AG70: – | AH70: – | AI70: – | AJ70: – | AK70: – | AL70: – | AM70: – | AN70: – | AO70: – | AP70: – | AQ70: – | AR70: –
A71: Armed conflict (scored 1-5) | B71: ACER | E71: EIU, Business Environment Rankings | F71: The EIUs business environment rankings quantify the attractiveness of the business environment. The risk of armed conflict indicator scores countries between 1 and 5, with 1 being "very high" and 5 being "very low". | H71: 19-12-2024 | I71: 3 | J71: 3 | K71: 3 | L71: 3 | M71: 3 | N71: 3 | O71: 3 | P71: 3 | Q71: 3 | R71: 3 | S71: 3 | T71: 3 | U71: 3 | V71: 3 | W71: 3 | X71: – | Y71: – | Z71: – | AA71: – | AB71: – | AC71: – | AD71: – | AE71: – | AF71: – | AG71: – | AH71: – | AI71: – | AJ71: – | AK71: – | AL71: – | AM71: – | AN71: – | AO71: – | AP71: – | AQ71: – | AR71: –
A72: Asset prices (scored 1-5) | B72: ASPR | E72: EIU, Business Environment Rankings | F72: EIUs business environment rankings quantify the attractiveness of the business environment. The risk of a decline in asset prices indicator scores countries between 1 and 5, with 1 being "very high" and 5 being "very low". | H72: 19-12-2024 | I72: 2 | J72: 2 | K72: 2 | L72: 2 | M72: 2 | N72: 2 | O72: 2 | P72: 2 | Q72: 2.1689435 | R72: 2.352158 | S72: 2.550849 | T72: 2.7663237 | U72: 3 | V72: 3 | W72: 3 | X72: – | Y72: – | Z72: – | AA72: – | AB72: – | AC72: – | AD72: – | AE72: – | AF72: – | AG72: – | AH72: – | AI72: – | AJ72: – | AK72: – | AL72: – | AM72: – | AN72: – | AO72: – | AP72: – | AQ72: – | AR72: –
A73: Availability of investment protection schemes (scored 1-5) | B73: IPRS | E73: EIU, Business Environment Rankings | F73: EIUs business environment rankings quantify the attractiveness of the business environment. The availability of investment protection schemes indicator scores countries between 1 and 5, with 1 being "very poor" and 5 being "very good". | H73: 19-12-2024 | I73: 4 | J73: 4 | K73: 4 | L73: 4 | M73: 4 | N73: 4 | O73: 4 | P73: 4 | Q73: 4 | R73: 4 | S73: 4 | T73: 4 | U73: 4 | V73: 4 | W73: 4 | X73: – | Y73: – | Z73: – | AA73: – | AB73: – | AC73: – | AD73: – | AE73: – | AF73: – | AG73: – | AH73: – | AI73: – | AJ73: – | AK73: – | AL73: – | AM73: – | AN73: – | AO73: – | AP73: – | AQ73: – | AR73: –
A74: Availability of skilled labour (scored 1-5) | B74: SLER | E74: EIU, Business Environment Rankings | F74: EIUs business environment rankings quantify the attractiveness of the business environment. The availability of skilled labour indicator scores countries between 1 and 5, with 1 being "very poor" and 5 being "very good". | G74: Average score at the mid-point of a five-year period (eg 2020 refers to the period 2018-2022). To produce a smoothed extrapolation between the historic and forecast periods scores have been weighted according to the ratio of historic to forecast years. | H74: 19-12-2024 | I74: 4 | J74: 4 | K74: 4 | L74: 4 | M74: 4 | N74: 4 | O74: 4 | P74: 4 | Q74: 4.2 | R74: 4.4 | S74: 4.6 | T74: 4.8 | U74: 5 | V74: 5 | W74: 5 | X74: – | Y74: – | Z74: – | AA74: – | AB74: – | AC74: – | AD74: – | AE74: – | AF74: – | AG74: – | AH74: – | AI74: – | AJ74: – | AK74: – | AL74: – | AM74: – | AN74: – | AO74: – | AP74: – | AQ74: – | AR74: –
A75: Average annual GDP growth (scored 1-5) | B75: GDGR | E75: EIU, Business Environment Rankings | F75: EIUs business environment rankings quantify the attractiveness of the business environment. The average annual GDP growth indicator scores countries between 1 and 5, with 1 being "very low" and 5 being "very high". | H75: 19-12-2024 | I75: 3 | J75: 3 | K75: 3 | L75: 3 | M75: 3 | N75: 2 | O75: 2 | P75: 3 | Q75: 3 | R75: 3 | S75: 3 | T75: 3 | U75: 3 | V75: 3 | W75: 3 | X75: – | Y75: – | Z75: – | AA75: – | AB75: – | AC75: – | AD75: – | AE75: – | AF75: – | AG75: – | AH75: – | AI75: – | AJ75: – | AK75: – | AL75: – | AM75: – | AN75: – | AO75: – | AP75: – | AQ75: – | AR75: –
A76: Average annual rate of growth of exports (scored 1-5) | B76: EXGR | E76: EIU, Business Environment Rankings | F76: EIUs business environment rankings quantify the attractiveness of the business environment. The average exports growth indicator scores countries between 1 and 5, with 1 being "very low" and 5 being "very high". | H76: 19-12-2024 | I76: 2 | J76: 2 | K76: 2 | L76: 1 | M76: 2 | N76: 2 | O76: 2 | P76: 2 | Q76: 2 | R76: 2 | S76: 2 | T76: 2 | U76: 2 | V76: 2 | W76: 2 | X76: – | Y76: – | Z76: – | AA76: – | AB76: – | AC76: – | AD76: – | AE76: – | AF76: – | AG76: – | AH76: – | AI76: – | AJ76: – | AK76: – | AL76: – | AM76: – | AN76: – | AO76: – | AP76: – | AQ76: – | AR76: –
A77: Average annual rate of growth of imports (scored 1-5) | B77: IMGR | E77: EIU, Business Environment Rankings | F77: EIUs business environment rankings quantify the attractiveness of the business environment. The average imports growth indicator scores countries between 1 and 5, with 1 being "very low" and 5 being "very high". | H77: 19-12-2024 | I77: 2 | J77: 2 | K77: 2 | L77: 2 | M77: 2 | N77: 1 | O77: 2 | P77: 2 | Q77: 2 | R77: 2 | S77: 2 | T77: 2 | U77: 2 | V77: 2 | W77: 2 | X77: – | Y77: – | Z77: – | AA77: – | AB77: – | AC77: – | AD77: – | AE77: – | AF77: – | AG77: – | AH77: – | AI77: – | AJ77: – | AK77: – | AL77: – | AM77: – | AN77: – | AO77: – | AP77: – | AQ77: – | AR77: –
A78: Average budget balance (% of GDP) (scored 1-5) | B78: BUBL | E78: EIU, Business Environment Rankings | F78: EIUs business environment rankings quantify the attractiveness of the business environment. The budget balnce/GDP indicator scores countries between 1 and 5, with 1 being "very high deficit" and 5 being "surplusor very low deficit". | H78: 19-12-2024 | I78: 5 | J78: 5 | K78: 5 | L78: 5 | M78: 4 | N78: 4 | O78: 4 | P78: 4 | Q78: 4 | R78: 4 | S78: 4 | T78: 4 | U78: 4 | V78: 4 | W78: 4 | X78: – | Y78: – | Z78: – | AA78: – | AB78: – | AC78: – | AD78: – | AE78: – | AF78: – | AG78: – | AH78: – | AI78: – | AJ78: – | AK78: – | AL78: – | AM78: – | AN78: – | AO78: – | AP78: – | AQ78: – | AR78: –
A79: Average current-account balance (% of GDP) (scored 1-5) | B79: EXBL | E79: EIU, Business Environment Rankings | F79: EIUs business environment rankings quantify the attractiveness of the business environment. The current account balance/GDP indicator scores countries between 1 and 5, with 1 being "very high deficit" and 5 being "very low deficit or surplus". | H79: 19-12-2024 | I79: 5 | J79: 5 | K79: 5 | L79: 5 | M79: 5 | N79: 5 | O79: 5 | P79: 5 | Q79: 5 | R79: 5 | S79: 5 | T79: 5 | U79: 5 | V79: 5 | W79: 5 | X79: – | Y79: – | Z79: – | AA79: – | AB79: – | AC79: – | AD79: – | AE79: – | AF79: – | AG79: – | AH79: – | AI79: – | AJ79: – | AK79: – | AL79: – | AM79: – | AN79: – | AO79: – | AP79: – | AQ79: – | AR79: –
A80: Average government debt (% of GDP) (scored 1-5) | B80: GVDB | E80: EIU, Business Environment Rankings | F80: EIUs business environment rankings quantify the attractiveness of the business environment. The government debt as a percentage of GDP indicator scores countries between 1 and 5, with 1 being "very high" and 5 being "very low". | H80: 19-12-2024 | I80: 4 | J80: 4 | K80: 4 | L80: 4 | M80: 4 | N80: 4 | O80: 4 | P80: 4 | Q80: 4 | R80: 4 | S80: 4 | T80: 4 | U80: 4 | V80: 4 | W80: 4 | X80: – | Y80: – | Z80: – | AA80: – | AB80: – | AC80: – | AD80: – | AE80: – | AF80: – | AG80: – | AH80: – | AI80: – | AJ80: – | AK80: – | AL80: – | AM80: – | AN80: – | AO80: – | AP80: – | AQ80: – | AR80: –
A81: Average no per household | B81: NHOU | E81: Korean Statistical Information Service | F81: Average number of people in each household, based on total population divided by number of households | H81: 19-12-2024 | I81: 2.6 | J81: 2.6 | K81: 2.5 | L81: 2.5 | M81: 2.5 | N81: 2.5 | O81: 2.4 | P81: 2.4 | Q81: 2.4 | R81: 2.3 | S81: 2.3 | T81: 2.3 | U81: 2.2 | V81: 2.2 | W81: 2.2 | X81: 2.2 | Y81: 2.1 | Z81: 2.1 | AA81: 2.1 | AB81: – | AC81: – | AD81: – | AE81: – | AF81: – | AG81: – | AH81: – | AI81: – | AJ81: – | AK81: – | AL81: – | AM81: – | AN81: – | AO81: – | AP81: – | AQ81: – | AR81: –
A82: Average nominal wage index (LCU, 2010=100) | B82: CAWI | E82: EIU calculation | F82: The average wage index in local currency rebased to 2010=100 by the EIU. | H82: 19-12-2024 | I82: 117.132 | J82: 121.591 | K82: 124.881 | L82: 131.246 | M82: 135.58 | N82: 136.51 | O82: 143.368 | P82: 150.388 | Q82: 153.7 | R82: 160.7 | S82: 165.2 | T82: 171.2 | U82: 177.1 | V82: 183.3 | W82: 189.8 | X82: – | Y82: – | Z82: – | AA82: – | AB82: – | AC82: – | AD82: – | AE82: – | AF82: – | AG82: – | AH82: – | AI82: – | AJ82: – | AK82: – | AL82: – | AM82: – | AN82: – | AO82: – | AP82: – | AQ82: – | AR82: –
A83: Average real wage index (LCU, 2010=100) | B83: CAWR | E83: EIU calculation | F83: The average real wage index in local currency rebased to 2010=100 by the EIU. | H83: 19-12-2024 | I83: 106.658 | J83: 109.654 | K83: 110.472 | L83: 114.413 | M83: 117.738 | N83: 117.911 | O83: 120.815 | P83: 120.594 | Q83: 119 | R83: 121.6 | S83: 123.1 | T83: 125.6 | U83: 127.7 | V83: 130 | W83: 132.2 | X83: – | Y83: – | Z83: – | AA83: – | AB83: – | AC83: – | AD83: – | AE83: – | AF83: – | AG83: – | AH83: – | AI83: – | AJ83: – | AK83: – | AL83: – | AM83: – | AN83: – | AO83: – | AP83: – | AQ83: – | AR83: –
A84: Average real wages (% change pa) | B84: DRWA | E84: Derived from Korean National Statistical Office | F84: Percentage change in hourly earnings (all industry) in local currency adjusted for inflation, over previous year. | H84: 19-12-2024 | I84: 2.689 | J84: 2.809 | K84: 0.747 | L84: 3.567 | M84: 2.906 | N84: 0.147 | O84: 2.463 | P84: -0.183 | Q84: -1.3 | R84: 2.2 | S84: 1.2 | T84: 2.1 | U84: 1.6 | V84: 1.8 | W84: 1.7 | X84: – | Y84: – | Z84: – | AA84: – | AB84: – | AC84: – | AD84: – | AE84: – | AF84: – | AG84: – | AH84: – | AI84: – | AJ84: – | AK84: – | AL84: – | AM84: – | AN84: – | AO84: – | AP84: – | AQ84: – | AR84: –
A85: Average wages (monthly, US$) | B85: AVWG | C85: $ | E85: KOSIS | F85: Average gross earnings per worker per month | H85: 19-12-2024 | I85: 2590 | J85: 2620 | K85: 2760 | L85: 2980 | M85: 2910 | N85: 2890 | O85: 3140 | P85: 2910 | Q85: 2940 | R85: 3090 | S85: 3390 | T85: 3590 | U85: 3670 | V85: 3750 | W85: – | X85: – | Y85: – | Z85: – | AA85: – | AB85: – | AC85: – | AD85: – | AE85: – | AF85: – | AG85: – | AH85: – | AI85: – | AJ85: – | AK85: – | AL85: – | AM85: – | AN85: – | AO85: – | AP85: – | AQ85: – | AR85: –
A86: Bank deposits (US$) | B86: BP04 | C86: $ | D86: m | E86: OECD, 1990-2009; Financial Supervisory Service, 2010-present | F86: Customer deposits in the banking system (excludes deposits with other banks). | G86: Bank performance indicators are built "bottom-up" from banks' balance sheets and refer to bank' domestic and foreign transactions. They are not comparable to the financial balance sheet indicators which refer to the domestic economy only. | H86: 19-12-2024 | I86: 1020831.1 | J86: 980599.1 | K86: 1214944 | L86: 1221969.4 | M86: 1276549.5 | N86: 1528929.2 | O86: 1547618.4 | P86: 1571734 | Q86: 1578544 | R86: 1624256 | S86: 1701581 | T86: 1771237 | U86: 1852395 | V86: 1906191 | W86: – | X86: – | Y86: – | Z86: – | AA86: – | AB86: – | AC86: – | AD86: – | AE86: – | AF86: – | AG86: – | AH86: – | AI86: – | AJ86: – | AK86: – | AL86: – | AM86: – | AN86: – | AO86: – | AP86: – | AQ86: – | AR86: –
A87: Bank loans (US$) | B87: BP03 | C87: $ | D87: m | E87: OECD, 1990-2009; Financial Supervisory Service, 2010-present | F87: Loans made by the banking system to customers and other non-financial institutions. | G87: Bank performance indicators are built "bottom-up" from banks' balance sheets and refer to bank' domestic and foreign transactions. They are not comparable to the financial balance sheet indicators which refer to the domestic economy only. | H87: 19-12-2024 | I87: 1343314 | J87: 1377982.6 | K87: 1611329.1 | L87: 1650354.2 | M87: 1669345.3 | N87: 1971309.7 | O87: 1979096.6 | P87: 1980013 | Q87: 2039896 | R87: 2083839 | S87: 2165267 | T87: 2235535 | U87: 2319373 | V87: 2367850 | W87: – | X87: – | Y87: – | Z87: – | AA87: – | AB87: – | AC87: – | AD87: – | AE87: – | AF87: – | AG87: – | AH87: – | AI87: – | AJ87: – | AK87: – | AL87: – | AM87: – | AN87: – | AO87: – | AP87: – | AQ87: – | AR87: –
A88: Banking assets (US$) | B88: BP01 | C88: $ | D88: m | E88: OECD, 1990-2009; Financial Supervisory Service, 2010-present | F88: Total assets of the banking system. Assets includes cash and balance with the central bank, interbank deposits, loans, securities and other assets. | G88: Bank performance indicators are built "bottom-up" from banks' balance sheets and refer to bank' domestic and foreign transactions. They are not comparable to the financial balance sheet indicators which refer to the domestic economy only. | H88: 19-12-2024 | I88: 1960302 | J88: 1974064.5 | K88: 2313672.8 | L88: 2356522.7 | M88: 2439317.7 | N88: 2878324.4 | O88: 2903509.2 | P88: 2951768 | Q88: 3003326 | R88: 3068022 | S88: 3187909 | T88: 3291364 | U88: 3414797 | V88: 3486170 | W88: – | X88: – | Y88: – | Z88: – | AA88: – | AB88: – | AC88: – | AD88: – | AE88: – | AF88: – | AG88: – | AH88: – | AI88: – | AJ88: – | AK88: – | AL88: – | AM88: – | AN88: – | AO88: – | AP88: – | AQ88: – | AR88: –
A89: Banks' capital and reserves (US$) | B89: BP02 | C89: $ | D89: m | E89: OECD, 1990-2009; Financial Supervisory Service, 2010-present | F89: Capital and reserves of the banking system including shareholder equity. | G89: Bank performance indicators are built "bottom-up" from banks' balance sheets and refer to bank' domestic and foreign transactions. They are not comparable to the financial balance sheet indicators which refer to the domestic economy only. | H89: 19-12-2024 | I89: 156176.6 | J89: 154471.7 | K89: 183771.7 | L89: 186354.5 | M89: 189784.9 | N89: 217905.3 | O89: 219011.5 | P89: 208688.6 | Q89: – | R89: – | S89: – | T89: – | U89: – | V89: – | W89: – | X89: – | Y89: – | Z89: – | AA89: – | AB89: – | AC89: – | AD89: – | AE89: – | AF89: – | AG89: – | AH89: – | AI89: – | AJ89: – | AK89: – | AL89: – | AM89: – | AN89: – | AO89: – | AP89: – | AQ89: – | AR89: –
A90: Big Mac: actual exchange rate (date of survey; LCU:US$) | B90: BMXR | E90: McDonalds; The Economist | F90: Actual exchange rate against the dollar at the date of the Big Mac survey. | H90: 19-12-2024 | I90: 1143.5 | J90: 1140.95 | K90: 1144.65 | L90: 1116 | M90: 1180.55 | N90: 1201 | O90: – | P90: – | Q90: – | R90: – | S90: – | T90: – | U90: – | V90: – | W90: – | X90: – | Y90: – | Z90: – | AA90: – | AB90: – | AC90: – | AD90: – | AE90: – | AF90: – | AG90: – | AH90: – | AI90: – | AJ90: – | AK90: – | AL90: – | AM90: – | AN90: – | AO90: – | AP90: – | AQ90: – | AR90: –
A91: Big Mac: Implied PPP | B91: BMPP | E91: McDonalds; The Economist | F91: Implied purchasing-power parity. Local price of a Big Mac divided by the price in United States | H91: 19-12-2024 | I91: 1002.331 | J91: 977.778 | K91: 977.778 | L91: 974.026 | M91: 955.414 | N91: 933.6 | O91: – | P91: – | Q91: – | R91: – | S91: – | T91: – | U91: – | V91: – | W91: – | X91: – | Y91: – | Z91: – | AA91: – | AB91: – | AC91: – | AD91: – | AE91: – | AF91: – | AG91: – | AH91: – | AI91: – | AJ91: – | AK91: – | AL91: – | AM91: – | AN91: – | AO91: – | AP91: – | AQ91: – | AR91: –
A92: Big Mac: price (LCU) | B92: BMLC | C92: LCU | E92: McDonalds; The Economist | F92: Big Mac price in local currency. | H92: 19-12-2024 | I92: 4300 | J92: 4400 | K92: 4400 | L92: 4500 | M92: 4500 | N92: 4500 | O92: – | P92: – | Q92: – | R92: – | S92: – | T92: – | U92: – | V92: – | W92: – | X92: – | Y92: – | Z92: – | AA92: – | AB92: – | AC92: – | AD92: – | AE92: – | AF92: – | AG92: – | AH92: – | AI92: – | AJ92: – | AK92: – | AL92: – | AM92: – | AN92: – | AO92: – | AP92: – | AQ92: – | AR92: –
A93: Big Mac: price (US$) | B93: BMUS | C93: $ | E93: McDonalds; The Economist | F93: Big Mac price in dollars. | H93: 19-12-2024 | I93: 3.76 | J93: 3.86 | K93: 3.84 | L93: 4.03 | M93: 3.81 | N93: 3.75 | O93: – | P93: – | Q93: – | R93: – | S93: – | T93: – | U93: – | V93: – | W93: – | X93: – | Y93: – | Z93: – | AA93: – | AB93: – | AC93: – | AD93: – | AE93: – | AF93: – | AG93: – | AH93: – | AI93: – | AJ93: – | AK93: – | AL93: – | AM93: – | AN93: – | AO93: – | AP93: – | AQ93: – | AR93: –
A94: Big Mac: Under(-)/over(+) valuation against the dollar | B94: BMUO | E94: McDonalds; The Economist | F94: Under(-)/over (+) valuation against the dollar in percentage terms. | H94: 19-12-2024 | I94: -12.345 | J94: -14.301 | K94: -14.578 | L94: -12.722 | M94: -19.07 | N94: -22.3 | O94: – | P94: – | Q94: – | R94: – | S94: – | T94: – | U94: – | V94: – | W94: – | X94: – | Y94: – | Z94: – | AA94: – | AB94: – | AC94: – | AD94: – | AE94: – | AF94: – | AG94: – | AH94: – | AI94: – | AJ94: – | AK94: – | AL94: – | AM94: – | AN94: – | AO94: – | AP94: – | AQ94: – | AR94: –
A95: Bilateral M&LT debt (US$) | B95: BILC | C95: $ | D95: m | E95: World Bank, International Debt Statistics; World Bank Quarterly External Debt Statistics; Economist Intelligence Unit | F95: Official medium- and long-term debt owed to foreign governments, notably Paris Club members of official creditors, at end-period. | G95: On a balance-of-payments basis; includes both foreign- and local-currency-denominated debt held by non-residents. | H95: 19-12-2024 | I95: 0 | J95: 0 | K95: 0 | L95: 0 | M95: 0 | N95: 0 | O95: 0 | P95: 0 | Q95: 0 | R95: 0 | S95: 0 | T95: 0 | U95: 0 | V95: 0 | W95: 0 | X95: – | Y95: – | Z95: – | AA95: – | AB95: – | AC95: – | AD95: – | AE95: – | AF95: – | AG95: – | AH95: – | AI95: – | AJ95: – | AK95: – | AL95: – | AM95: – | AN95: – | AO95: – | AP95: – | AQ95: – | AR95: –
A96: Birth rate (per 1,000 pop) | B96: BRTE | E96: UN Population Data | F96: Number of live births per year per 1,000 population estimated at mid-year | H96: 19-12-2024 | I96: 8.367 | J96: 7.798 | K96: 7.019 | L96: 6.375 | M96: 5.92 | N96: 5.676 | O96: 5.579 | P96: 5.515 | Q96: 5.56 | R96: 5.618 | S96: 5.699 | T96: 5.803 | U96: 5.837 | V96: 5.894 | W96: 5.939 | X96: 5.899 | Y96: – | Z96: – | AA96: – | AB96: – | AC96: – | AD96: – | AE96: – | AF96: – | AG96: – | AH96: – | AI96: – | AJ96: – | AK96: – | AL96: – | AM96: – | AN96: – | AO96: – | AP96: – | AQ96: – | AR96: –
A97: BIS banks' liabilities 0-1 year (US$) | B97: BSD1 | C97: $ | D97: m | E97: BIS, The Maturity, Sectoral and Nationality Distribution of International Bank Lending. | F97: Liabilities of less than one year maturity to BIS-reporting banks vis-à-vis all sectors, at end-period. | H97: 19-12-2024 | I97: – | J97: – | K97: – | L97: – | M97: – | N97: – | O97: – | P97: – | Q97: – | R97: – | S97: – | T97: – | U97: – | V97: – | W97: – | X97: – | Y97: – | Z97: – | AA97: – | AB97: – | AC97: – | AD97: – | AE97: – | AF97: – | AG97: – | AH97: – | AI97: – | AJ97: – | AK97: – | AL97: – | AM97: – | AN97: – | AO97: – | AP97: – | AQ97: – | AR97: –
A98: BIS banks' liabilities 1-2 years (US$) | B98: BSD2 | C98: $ | D98: m | E98: BIS, The Maturity, Sectoral and Nationality Distribution of International Bank Lending. | F98: Liabilities of between one and two years maturity to BIS-reporting banks vis-à-vis all sectors, at end-period. | H98: 19-12-2024 | I98: – | J98: – | K98: – | L98: – | M98: – | N98: – | O98: – | P98: – | Q98: – | R98: – | S98: – | T98: – | U98: – | V98: – | W98: – | X98: – | Y98: – | Z98: – | AA98: – | AB98: – | AC98: – | AD98: – | AE98: – | AF98: – | AG98: – | AH98: – | AI98: – | AJ98: – | AK98: – | AL98: – | AM98: – | AN98: – | AO98: – | AP98: – | AQ98: – | AR98: –
A99: BIS banks' liabilities over 2 years (US$) | B99: BSD3 | C99: $ | D99: m | E99: BIS, The Maturity, Sectoral and Nationality Distribution of International Bank Lending. | F99: Liabilities of over two years maturity to BIS-reporting banks vis-à-vis all sectors, at end-period. | H99: 19-12-2024 | I99: – | J99: – | K99: – | L99: – | M99: – | N99: – | O99: – | P99: – | Q99: – | R99: – | S99: – | T99: – | U99: – | V99: – | W99: – | X99: – | Y99: – | Z99: – | AA99: – | AB99: – | AC99: – | AD99: – | AE99: – | AF99: – | AG99: – | AH99: – | AI99: – | AJ99: – | AK99: – | AL99: – | AM99: – | AN99: – | AO99: – | AP99: – | AQ99: – | AR99: –
A100: BIS banks' total liabilities (US$) | B100: BSDT | C100: $ | D100: m | E100: BIS, The Maturity, Sectoral and Nationality Distribution of International Bank Lending. | F100: Total liabilities to BIS-reporting banks vis-à-vis all sectors, broken down by maturity at end-period. | H100: 19-12-2024 | I100: – | J100: – | K100: – | L100: – | M100: – | N100: – | O100: – | P100: – | Q100: – | R100: – | S100: – | T100: – | U100: – | V100: – | W100: – | X100: – | Y100: – | Z100: – | AA100: – | AB100: – | AC100: – | AD100: – | AE100: – | AF100: – | AG100: – | AH100: – | AI100: – | AJ100: – | AK100: – | AL100: – | AM100: – | AN100: – | AO100: – | AP100: – | AQ100: – | AR100: –
A101: BIS banks' undisbursed credit commitments (US$) | B101: UCCB | C101: $ | D101: m | E101: BIS, The Maturity, Sectoral and Nationality Distribution of International Bank Lending | F101: Undisbursed credit commitments and back-up facilities at BIS-reporting banks, at end-period. | G101: From Q4 2004, undisbursed credit commitments are reported on a voluntary basis. Many countries no longer publishing this data. | H101: 19-12-2024 | I101: – | J101: – | K101: – | L101: – | M101: – | N101: – | O101: – | P101: – | Q101: – | R101: – | S101: – | T101: – | U101: – | V101: – | W101: – | X101: – | Y101: – | Z101: – | AA101: – | AB101: – | AC101: – | AD101: – | AE101: – | AF101: – | AG101: – | AH101: – | AI101: – | AJ101: – | AK101: – | AL101: – | AM101: – | AN101: – | AO101: – | AP101: – | AQ101: – | AR101: –
A102: Broadband connection speed (scored 1-5) | B102: BBCS | E102: EIU, Business Environment Rankings | F102: EIUs business environment rankings quantify the attractiveness of the business environment. The average broadband connection speed indicator scores countries between 1 and 5, with 1 being "very low" and 5 being "very high". | H102: 19-12-2024 | I102: 5 | J102: 5 | K102: 5 | L102: 5 | M102: 5 | N102: 5 | O102: 5 | P102: 5 | Q102: 5 | R102: 5 | S102: 5 | T102: 5 | U102: 5 | V102: 5 | W102: 5 | X102: – | Y102: – | Z102: – | AA102: – | AB102: – | AC102: – | AD102: – | AE102: – | AF102: – | AG102: – | AH102: – | AI102: – | AJ102: – | AK102: – | AL102: – | AM102: – | AN102: – | AO102: – | AP102: – | AQ102: – | AR102: –
A103: Budget balance (% of GDP) | B103: PSBR | E103: Derived from Bank of Korea | F103: Central government receipts minus central government outlays, as a percentage of GDP. | H103: 19-12-2024 | I103: -0.009 | J103: 0.923 | K103: 1.242 | L103: 1.553 | M103: -0.588 | N103: -3.457 | O103: -1.372 | P103: -2.779 | Q103: -1.531 | R103: -1.8 | S103: -1.7 | T103: -1.5 | U103: -1.3 | V103: -1 | W103: -0.9 | X103: – | Y103: – | Z103: – | AA103: – | AB103: – | AC103: – | AD103: – | AE103: – | AF103: – | AG103: – | AH103: – | AI103: – | AJ103: – | AK103: – | AL103: – | AM103: – | AN103: – | AO103: – | AP103: – | AQ103: – | AR103: –
A104: Budget balance (LCU) | B104: BBAL | C104: LCU | D104: bn | E104: Bank of Korea | F104: Central government receipts (including grants received and loan repayments) less general government outlays (including loans). | G104: Central government | H104: 19-12-2024 | I104: -165 | J104: 16910 | K104: 24030 | L104: 31163 | M104: -11997 | N104: -71153 | O104: -30494 | P104: -64570 | Q104: -36768 | R104: -46083.4 | S104: -42783.5 | T104: -38834.7 | U104: -35626.3 | V104: -29458.6 | W104: -27839.4 | X104: – | Y104: – | Z104: – | AA104: – | AB104: – | AC104: – | AD104: – | AE104: – | AF104: – | AG104: – | AH104: – | AI104: – | AJ104: – | AK104: – | AL104: – | AM104: – | AN104: – | AO104: – | AP104: – | AQ104: – | AR104: –
A105: Budget balance (US$) | B105: BBAU | C105: $ | D105: m | E105: Bank of Korea | F105: Central government receipts (including grants received and loan repayments) less general government outlays (including loans). | G105: Central government | H105: 19-12-2024 | I105: -145.89472 | J105: 14567.948 | K105: 21246.669 | L105: 28325.794 | M105: -10294.695 | N105: -60285.571 | O105: -26656.565 | P105: -49998.193 | Q105: -28160.417 | R105: -33794.434 | S105: -29290.52 | T105: -26713.349 | U105: -24874.369 | V105: -20903.765 | W105: -19978.075 | X105: – | Y105: – | Z105: – | AA105: – | AB105: – | AC105: – | AD105: – | AE105: – | AF105: – | AG105: – | AH105: – | AI105: – | AJ105: – | AK105: – | AL105: – | AM105: – | AN105: – | AO105: – | AP105: – | AQ105: – | AR105: –
A106: Budget expenditure (% of GDP) | B106: BEXP | E106: Derived from Bank of Korea | F106: Central government outlays (including loans), as a percentage of GDP. | H106: 19-12-2024 | I106: 19.494 | J106: 19.332 | K106: 19.636 | L106: 20.284 | M106: 22.339 | N106: 25.154 | O106: 25.569 | P106: 28.097 | Q106: 24.169 | R106: 25.7 | S106: 26.3 | T106: 26.2 | U106: 25.9 | V106: 25.6 | W106: 25.3 | X106: – | Y106: – | Z106: – | AA106: – | AB106: – | AC106: – | AD106: – | AE106: – | AF106: – | AG106: – | AH106: – | AI106: – | AJ106: – | AK106: – | AL106: – | AM106: – | AN106: – | AO106: – | AP106: – | AQ106: – | AR106: –
A107: Budget expenditure (LCU) | B107: BEXL | C107: LCU | D107: bn | E107: Bank of Korea | F107: Central government outlays (including loans). | G107: Central government | H107: 19-12-2024 | I107: 339351 | J107: 354354 | K107: 379809 | L107: 407099 | M107: 455850 | N107: 517781 | O107: 568113 | P107: 652902 | Q107: 580354 | R107: 646472.7 | S107: 679931 | T107: 701055.8 | U107: 722304.1 | V107: 741248 | W107: 764129.1 | X107: – | Y107: – | Z107: – | AA107: – | AB107: – | AC107: – | AD107: – | AE107: – | AF107: – | AG107: – | AH107: – | AI107: – | AJ107: – | AK107: – | AL107: – | AM107: – | AN107: – | AO107: – | AP107: – | AQ107: – | AR107: –
A108: Budget expenditure (US$) | B108: BEXU | C108: $ | D108: m | E108: Bank of Korea | F108: Central government outlays (including loans). | G108: Central government | H108: 19-12-2024 | I108: 300057.69 | J108: 305275.6 | K108: 335816.73 | L108: 370035.06 | M108: 391167.52 | N108: 438698.63 | O108: 496620.36 | P108: 505558.62 | Q108: 444490.06 | R108: 474079.51 | S108: 465495.2 | T108: 482237.92 | U108: 504314.26 | V108: 525987.58 | W108: 548352.42 | X108: – | Y108: – | Z108: – | AA108: – | AB108: – | AC108: – | AD108: – | AE108: – | AF108: – | AG108: – | AH108: – | AI108: – | AJ108: – | AK108: – | AL108: – | AM108: – | AN108: – | AO108: – | AP108: – | AQ108: – | AR108: –
A109: Budget revenue (% of GDP) | B109: BREP | E109: Derived from Bank of Korea | F109: Central government receipts (including grants received and loan repayments), as a percentage of GDP. | H109: 19-12-2024 | I109: 19.485 | J109: 20.254 | K109: 20.878 | L109: 21.837 | M109: 21.751 | N109: 21.697 | O109: 24.196 | P109: 25.318 | Q109: 22.638 | R109: 23.9 | S109: 24.6 | T109: 24.7 | U109: 24.7 | V109: 24.6 | W109: 24.4 | X109: – | Y109: – | Z109: – | AA109: – | AB109: – | AC109: – | AD109: – | AE109: – | AF109: – | AG109: – | AH109: – | AI109: – | AJ109: – | AK109: – | AL109: – | AM109: – | AN109: – | AO109: – | AP109: – | AQ109: – | AR109: –
A110: Budget revenue (LCU) | B110: BREL | C110: LCU | D110: bn | E110: Bank of Korea | F110: Central government receipts (including grants received and loan repayments). | G110: Central government | H110: 19-12-2024 | I110: 339186 | J110: 371264 | K110: 403839 | L110: 438262 | M110: 443853 | N110: 446628 | O110: 537619 | P110: 588332 | Q110: 543586 | R110: 600389.4 | S110: 637147.5 | T110: 662221.1 | U110: 686677.8 | V110: 711789.4 | W110: 736289.7 | X110: – | Y110: – | Z110: – | AA110: – | AB110: – | AC110: – | AD110: – | AE110: – | AF110: – | AG110: – | AH110: – | AI110: – | AJ110: – | AK110: – | AL110: – | AM110: – | AN110: – | AO110: – | AP110: – | AQ110: – | AR110: –
A111: Budget revenue (US$) | B111: BREU | C111: $ | D111: m | E111: Bank of Korea | F111: Central government receipts (including grants received and loan repayments). | G111: Central government | H111: 19-12-2024 | I111: 299911.8 | J111: 319843.55 | K111: 357063.4 | L111: 398360.85 | M111: 380872.82 | N111: 378413.06 | O111: 469963.8 | P111: 455560.43 | Q111: 416329.64 | R111: 440285.08 | S111: 436204.68 | T111: 455524.57 | U111: 479439.89 | V111: 505083.81 | W111: 528374.35 | X111: – | Y111: – | Z111: – | AA111: – | AB111: – | AC111: – | AD111: – | AE111: – | AF111: – | AG111: – | AH111: – | AI111: – | AJ111: – | AK111: – | AL111: – | AM111: – | AN111: – | AO111: – | AP111: – | AQ111: – | AR111: –
A112: Bureaucracy (scored 1-5) | B112: QBER | E112: EIU, Business Environment Rankings | F112: EIUs business environment rankings quantify the attractiveness of the business environment. The quality of bureaucracy indicator scores countries between 1 and 5, with 1 being "very low" and 5 being "very high". | G112: Average score at the mid-point of a five-year period (eg 2020 refers to the period 2018-2022). To produce a smoothed extrapolation between the historic and forecast periods scores have been weighted according to the ratio of historic to forecast years. | H112: 19-12-2024 | I112: 4 | J112: 4 | K112: 4 | L112: 4 | M112: 4 | N112: 4 | O112: 4 | P112: 4 | Q112: 4.2 | R112: 4.4 | S112: 4.6 | T112: 4.8 | U112: 5 | V112: 5 | W112: 5 | X112: – | Y112: – | Z112: – | AA112: – | AB112: – | AC112: – | AD112: – | AE112: – | AF112: – | AG112: – | AH112: – | AI112: – | AJ112: – | AK112: – | AL112: – | AM112: – | AN112: – | AO112: – | AP112: – | AQ112: – | AR112: –
A113: Cable broadband subscriptions | B113: CMIN | D113: '000 | E113: ITU | F113: Number of internet subscriptions using modems attached to cable television networks. | H113: 19-12-2024 | I113: 4310 | J113: 4120 | K113: 3970 | L113: 3480 | M113: 3170 | N113: 2900 | O113: 2630 | P113: 2410 | Q113: 2054 | R113: 1876 | S113: 1650 | T113: 1438 | U113: 1273 | V113: 1008 | W113: – | X113: – | Y113: – | Z113: – | AA113: – | AB113: – | AC113: – | AD113: – | AE113: – | AF113: – | AG113: – | AH113: – | AI113: – | AJ113: – | AK113: – | AL113: – | AM113: – | AN113: – | AO113: – | AP113: – | AQ113: – | AR113: –
A114: Cable broadband subscriptions (% pa) | B114: CMIG | E114: Derived from ITU | F114: Percentage change in internet subscriptions using modems attached to cable television networks. | H114: 19-12-2024 | I114: -4.435 | J114: -4.408 | K114: -3.641 | L114: -12.343 | M114: -8.908 | N114: -8.517 | O114: -9.31 | P114: -8.365 | Q114: -14.8 | R114: -8.7 | S114: -12 | T114: -12.9 | U114: -11.5 | V114: -20.8 | W114: – | X114: – | Y114: – | Z114: – | AA114: – | AB114: – | AC114: – | AD114: – | AE114: – | AF114: – | AG114: – | AH114: – | AI114: – | AJ114: – | AK114: – | AL114: – | AM114: – | AN114: – | AO114: – | AP114: – | AQ114: – | AR114: –
A115: Cable broadband subscriptions (per 100 people) | B115: CMIP | E115: EIU calculation | F115: Number of internet subscriptions using modems attached to cable television networks per 100 people. | H115: 19-12-2024 | I115: 8.454 | J115: 8.032 | K115: 7.711 | L115: 6.739 | M115: 6.123 | N115: 5.592 | O115: 5.072 | P115: 4.654 | Q115: 3.97 | R115: 3.63 | S115: 3.19 | T115: 2.79 | U115: 2.47 | V115: 1.96 | W115: – | X115: – | Y115: – | Z115: – | AA115: – | AB115: – | AC115: – | AD115: – | AE115: – | AF115: – | AG115: – | AH115: – | AI115: – | AJ115: – | AK115: – | AL115: – | AM115: – | AN115: – | AO115: – | AP115: – | AQ115: – | AR115: –
A116: Cable broadband subscriptions (per 100 people, US=100) | B116: CMIU | E116: EIU calculation | F116: Number of internet subscriptions using modems attached to cable television networks per 100 people indexed to US=100 by the EIU. | H116: 19-12-2024 | I116: 46.17 | J116: 41.744 | K116: 38.689 | L116: 32.642 | M116: 28.521 | N116: 24.388 | O116: 22.346 | P116: 19.805 | Q116: 17.2 | R116: 15.4 | S116: 13.4 | T116: 11.6 | U116: 10.1 | V116: 7.9 | W116: – | X116: – | Y116: – | Z116: – | AA116: – | AB116: – | AC116: – | AD116: – | AE116: – | AF116: – | AG116: – | AH116: – | AI116: – | AJ116: – | AK116: – | AL116: – | AM116: – | AN116: – | AO116: – | AP116: – | AQ116: – | AR116: –
A117: Cable broadbandsubscriptions (share of world total) | B117: CMIW | E117: EIU calculation | F117: Number of internet subscriptions using modems attached to cable television networks as a percentage of the world total. | H117: 19-12-2024 | I117: 2.972 | J117: 2.71 | K117: 2.465 | L117: 2.108 | M117: 1.876 | N117: 1.635 | O117: 1.457 | P117: 1.35 | Q117: 1.2 | R117: 1.1 | S117: 0.9 | T117: 0.8 | U117: 0.7 | V117: 0.6 | W117: – | X117: – | Y117: – | Z117: – | AA117: – | AB117: – | AC117: – | AD117: – | AE117: – | AF117: – | AG117: – | AH117: – | AI117: – | AJ117: – | AK117: – | AL117: – | AM117: – | AN117: – | AO117: – | AP117: – | AQ117: – | AR117: –
A118: Calorie consumption (daily/pc) | B118: CACO | E118: Food and Agriculture Organisation of the United Nations | F118: Average calorie consumption per head. | H118: 19-12-2024 | I118: 3325 | J118: 3325 | K118: 3377 | L118: 3387 | M118: 3382 | N118: 3378 | O118: 3400 | P118: 3440 | Q118: 3480 | R118: 3530 | S118: 3570 | T118: 3620 | U118: 3660 | V118: 3710 | W118: – | X118: – | Y118: – | Z118: – | AA118: – | AB118: – | AC118: – | AD118: – | AE118: – | AF118: – | AG118: – | AH118: – | AI118: – | AJ118: – | AK118: – | AL118: – | AM118: – | AN118: – | AO118: – | AP118: – | AQ118: – | AR118: –
A119: Cancers (age-standardised death rates per 100,000 pop) | B119: CANC | E119: OECD | F119: WHO age-standardised death rates per 100,000 people from cancer | H119: 19-12-2024 | I119: 182.7 | J119: 179.3 | K119: 173.8 | L119: 167.6 | M119: 164.8 | N119: 160.2 | O119: – | P119: – | Q119: – | R119: – | S119: – | T119: – | U119: – | V119: – | W119: – | X119: – | Y119: – | Z119: – | AA119: – | AB119: – | AC119: – | AD119: – | AE119: – | AF119: – | AG119: – | AH119: – | AI119: – | AJ119: – | AK119: – | AL119: – | AM119: – | AN119: – | AO119: – | AP119: – | AQ119: – | AR119: –
A120: Capital account liberalisation (scored 1-5) | B120: CALB | E120: EIU, Business Environment Rankings | F120: EIUs business environment rankings quantify the attractiveness of the business environment. The capital-account liberalisation indicator scores countries between 1 and 5, with 1 being "tightly controlled capital flows" and 5 being "full liberalisation". | H120: 19-12-2024 | I120: 4 | J120: 4 | K120: 4 | L120: 4 | M120: 4 | N120: 4 | O120: 4 | P120: 4 | Q120: 4 | R120: 4 | S120: 4 | T120: 4 | U120: 4 | V120: 4 | W120: 4 | X120: – | Y120: – | Z120: – | AA120: – | AB120: – | AC120: – | AD120: – | AE120: – | AF120: – | AG120: – | AH120: – | AI120: – | AJ120: – | AK120: – | AL120: – | AM120: – | AN120: – | AO120: – | AP120: – | AQ120: – | AR120: –
A121: Capital and reserves/assets - [Y] | B121: BP13 | F121: Capital and reserves of the banking system as a percentage of the total assets of the banking system. | G121: Bank performance indicators are built "bottom-up" from banks' balance sheets and refer to bank' domestic and foreign transactions. They are not comparable to the financial balance sheet indicators which refer to the domestic economy only. | H121: 19-12-2024 | I121: 7.967 | J121: 7.825 | K121: 7.943 | L121: 7.908 | M121: 7.78 | N121: 7.571 | O121: 7.543 | P121: 7.1 | Q121: – | R121: – | S121: – | T121: – | U121: – | V121: – | W121: – | X121: – | Y121: – | Z121: – | AA121: – | AB121: – | AC121: – | AD121: – | AE121: – | AF121: – | AG121: – | AH121: – | AI121: – | AJ121: – | AK121: – | AL121: – | AM121: – | AN121: – | AO121: – | AP121: – | AQ121: – | AR121: –
...

Sheet MRP
B1: MRP
B2: As of September 30, 2024
B3: KRW in millions
H4: 45596 | I4: 기준일
B6: Date | C6: 배당수익률(%) | D6: 성장률(%) | E6: 배당성향(%) | F6: 시장수익률(%) | G6: RF 금리(%) | H6: 프리미엄(%)
B7: 45596 | C7: 2.016 | D7: 26.2677 | E7: 23.7274 | F7: 20.0426 | G7: 3.095 | H7: 16.9476
B8: 45595 | C8: 1.9825 | D8: 26.3728 | E8: 23.7315 | F8: 20.0609 | G8: 3.102 | H8: 16.9589
B9: 45594 | C9: 1.9659 | D9: 26.7948 | E9: 23.7282 | F9: 20.0736 | G9: 3.12 | H9: 16.9536
B10: 45593 | C10: 1.973 | D10: 27.1114 | E10: 23.7108 | F10: 20.0962 | G10: 3.127 | H10: 16.9692
B11: 45590 | C11: 1.8819 | D11: 25.0602 | E11: 23.2122 | F11: 19.3478 | G11: 3.06 | H11: 16.2878
B12: 45589 | C12: 1.8866 | D12: 20.4394 | E12: 23.1474 | F12: 17.0874 | G12: 3.07 | H12: 14.0174
B13: 45588 | C13: 1.8701 | D13: 19.8415 | E13: 23.0452 | F13: 16.8295 | G13: 3.127 | H13: 13.7025
B14: 45587 | C14: 1.8933 | D14: 20.0118 | E14: 23.0236 | F14: 16.9228 | G14: 3.127 | H14: 13.7958
B15: 45586 | C15: 1.872 | D15: 20.1282 | E15: 22.9289 | F15: 16.8704 | G15: 3.057 | H15: 13.8134
B16: 45583 | C16: 1.8939 | D16: 19.8762 | E16: 23.9254 | F16: 16.8249 | G16: 3.08 | H16: 13.7449
B17: 45582 | C17: 1.8786 | D17: 20.1447 | E17: 23.9108 | F17: 16.9296 | G17: 3.037 | H17: 13.8926
B18: 45581 | C18: 1.8771 | D18: 20.1379 | E18: 23.9093 | F18: 16.9653 | G18: 3.005 | H18: 13.9603
... B2006: 42620 | C2006: 1.5954 | D2006: 9.5413 | E2006: 18.4925 | F2006: 10.3268 | G2006: 1.462 | H2006: 8.8648

Sheet 6.Multiple▶
B8: Section <6>
B9: <Multiple>

Sheet Valuation
B1: Valuation Summary
B2: As of September 30, 2024
B3: KRW in millions
E6: GPCM | I6: GTM
B7: KRW in millions | D7: Min | E7: Median | F7: Max | H7: Min | I7: Median | J7: Max
B8: EBITDA (FY 2030) | D8: =Model!Q11 -> 32371.852 | E8: =D8 -> 32371.852 | F8: =E8 -> 32371.852 | H8: =$D$8 -> 32371.852 | I8: =H8 -> 32371.852 | J8: =I8 -> 32371.852
B9: Multiple | D9: =GPCM!G18 -> 11.521567 | E9: =GPCM!G17 -> 19.97163 | F9: =GPCM!G15 -> 21.481554 | H9: =GTM!F15 -> 16.02 | I9: =GTM!F14 -> 18.965 | J9: =GTM!F12 -> 18.24
B11: Enterprise Value | D11: =D8*D9 -> 372974.47 | E11: =E8*E9 -> 646518.64 | F11: =F8*F9 -> 695397.68 | H11: =H8*H9 -> 518597.07 | I11: =I8*I9 -> 613932.17 | J11: =J8*J9 -> 590462.58
B12: plus: NOA | D12: 0 | E12: 0 | F12: 0 | H12: =D12 -> 0 | I12: =H12 -> 0 | J12: =I12 -> 0
B13: less: Net Debt | D13: 0 | E13: 0 | F13: 0 | H13: =D13 -> 0 | I13: =H13 -> 0 | J13: =I13 -> 0
B14: less: Debt-like Items | D14: 0 | E14: 0 | F14: 0 | H14: =D14 -> 0 | I14: =H14 -> 0 | J14: =I14 -> 0
B15: plus: NOL | D15: 0 | E15: 0 | F15: 0 | H15: =D15 -> 0 | I15: =H15 -> 0 | J15: =I15 -> 0
B17: Equity Value | D17: =D11+D12-D13-D14+D15 -> 372974.47 | E17: =E11+E12-E13-E14+E15 -> 646518.64 | F17: =F11+F12-F13-F14+F15 -> 695397.68 | H17: =H11+H12-H13-H14+H15 -> 518597.07 | I17: =I11+I12-I13-I14+I15 -> 613932.17 | J17: =J11+J12-J13-J14+J15 -> 590462.58

Sheet GPCM
B1: Market Approach - Guideline Public Company Method
B2: Value analysis as of September 30, 2024
B3: KRW in millions
B5: Guideline Company | C5: 44196 | D5: 44561 | E5: 44926 | F5: 45291 | G5: 45565
B6: Cube Entertainment, Inc. (KOSDAQ:A182360) | C6: =IFERROR(CIQ!BH7/CIQ!BC7,"na") -> 30.717669 | D6: =IFERROR(CIQ!BI7/CIQ!BD7,"na") -> 63.148087 | E6: =IFERROR(CIQ!BJ7/CIQ!BE7,"na") -> 18.96267 | F6: =IFERROR(CIQ!BK7/CIQ!BF7,"na") -> 10.810817 | G6: =IFERROR(CIQ!BL7/CIQ!BG7,"na") -> 4.9690024
B7: Fantagio Corp. (KOSDAQ:A032800) | C7: =IF(CIQ!BH8/CIQ!BC8<0,"na",IFERROR(CIQ!BH8/CIQ!BC8,"na")) -> na | D7: =IFERROR(CIQ!BI8/CIQ!BD8,"na") -> 25.439677 | E7: =IFERROR(CIQ!BJ8/CIQ!BE8,"na") -> na | F7: =IF(CIQ!BK8/CIQ!BF8<0,"na",IFERROR(CIQ!BK8/CIQ!BF8,"na")) -> na | G7: =IFERROR(CIQ!BL8/CIQ!BG8,"na") -> 18.972944
B8: HYBE Co., Ltd. (KOSE:A352820) | C8: =IFERROR(CIQ!BH10/CIQ!BC10,"na") -> 33.425413 | D8: =IFERROR(CIQ!BI10/CIQ!BD10,"na") -> 53.843257 | E8: =IFERROR(CIQ!BJ10/CIQ!BE10,"na") -> 21.550902 | F8: =IFERROR(CIQ!BK10/CIQ!BF10,"na") -> 24.745758 | G8: =IFERROR(CIQ!BL10/CIQ!BG10,"na") -> 22.317757
B9: JYP Entertainment Corporation (KOSDAQ:A035900) | C9: =IFERROR(CIQ!BH11/CIQ!BC11,"na") -> 26.152001 | D9: =IFERROR(CIQ!BI11/CIQ!BD11,"na") -> 25.644887 | E9: =IFERROR(CIQ!BJ11/CIQ!BE11,"na") -> 20.958406 | F9: =IFERROR(CIQ!BK11/CIQ!BF11,"na") -> 18.345614 | G9: =IFERROR(CIQ!BL11/CIQ!BG11,"na") -> 11.15697
B10: SM Entertainment Co., Ltd. (KOSDAQ:A041510) | C10: =IFERROR(CIQ!BH13/CIQ!BC13,"na") -> 11.401459 | D10: =IFERROR(CIQ!BI13/CIQ!BD13,"na") -> 14.377126 | E10: =IFERROR(CIQ!BJ13/CIQ!BE13,"na") -> 12.434027 | F10: =IFERROR(CIQ!BK13/CIQ!BF13,"na") -> 13.373588 | G10: =IFERROR(CIQ!BL13/CIQ!BG13,"na") -> 12.615358
B11: YG Entertainment Inc. (KOSDAQ:A122870) | C11: =IFERROR(CIQ!BH14/CIQ!BC14,"na") -> 39.463308 | D11: =IFERROR(CIQ!BI14/CIQ!BD14,"na") -> 36.055334 | E11: =IFERROR(CIQ!BJ14/CIQ!BE14,"na") -> 14.700503 | F11: =IFERROR(CIQ!BK14/CIQ!BF14,"na") -> 9.5705162 | G11: =IFERROR(CIQ!BL14/CIQ!BG14,"na") -> 49.797747
B12: FNC ENTERTAINMENT Co., Ltd. (KOSDAQ:A173940) | C12: =IFERROR(CIQ!BH9/CIQ!BC9,"na") -> -66.038358 | D12: =IFERROR(CIQ!BI9/CIQ!BD9,"na") -> 40.162751 | E12: =IFERROR(CIQ!BJ9/CIQ!BE9,"na") -> -9.0821473 | F12: =IFERROR(CIQ!BK9/CIQ!BF9,"na") -> -20.075472 | G12: =IFERROR(CIQ!BL9/CIQ!BG9,"na") -> -159.83689
B13: RBW Inc. (KOSDAQ:A361570) | C13: =IFERROR(CIQ!BH12/CIQ!BC12,"na") -> na | D13: =IFERROR(CIQ!BI12/CIQ!BD12,"na") -> 17.360171 | E13: =IFERROR(CIQ!BJ12/CIQ!BE12,"na") -> 17.56232 | F13: =IFERROR(CIQ!BK12/CIQ!BF12,"na") -> 35.302849 | G13: =IFERROR(CIQ!BL12/CIQ!BG12,"na") -> -12.376822
B14: Max | C14: =MAX(C6:C11) -> 39.463308 | D14: =MAX(D6:D11) -> 63.148087 | E14: =MAX(E6:E11) -> 21.550902 | F14: =MAX(F6:F11) -> 24.745758 | G14: =MAX(G6:G11) -> 49.797747
B15: 75% Quartile | C15: =_xlfn.QUARTILE.INC(C6:C11,3) -> 33.425413 | D15: =_xlfn.QUARTILE.INC(D6:D11,3) -> 49.396276 | E15: =_xlfn.QUARTILE.INC(E6:E11,3) -> 20.958406 | F15: =_xlfn.QUARTILE.INC(F6:F11,3) -> 18.345614 | G15: =_xlfn.QUARTILE.INC(G6:G11,3) -> 21.481554
B16: Median | C16: =MEDIAN(C6:C11) -> 30.717669 | D16: =MEDIAN(D6:D11) -> 30.850111 | E16: =MEDIAN(E6:E11) -> 18.96267 | F16: =MEDIAN(F6:F11) -> 13.373588 | G16: =MEDIAN(G6:G11) -> 15.794151
B17: Average | C17: =AVERAGE(C6:C11) -> 28.23197 | D17: =AVERAGE(D6:D11) -> 36.418061 | E17: =AVERAGE(E6:E11) -> 17.721302 | F17: =AVERAGE(F6:F11) -> 15.369259 | G17: =AVERAGE(G6:G11) -> 19.97163
B18: 25% Quartile | C18: =_xlfn.QUARTILE.INC(C6:C11,1) -> 26.152001 | D18: =_xlfn.QUARTILE.INC(D6:D11,1) -> 25.490979 | E18: =_xlfn.QUARTILE.INC(E6:E11,1) -> 14.700503 | F18: =_xlfn.QUARTILE.INC(F6:F11,1) -> 10.810817 | G18: =_xlfn.QUARTILE.INC(G6:G11,1) -> 11.521567
B19: Min | C19: =MIN(C6:C11) -> 11.401459 | D19: =MIN(D6:D11) -> 14.377126 | E19: =MIN(E6:E11) -> 12.434027 | F19: =MIN(F6:F11) -> 9.5705162 | G19: =MIN(G6:G11) -> 4.9690024
B20: Selected | C20: =C17 -> 28.23197 | D20: =D17 -> 36.418061 | E20: =E17 -> 17.721302 | F20: =F17 -> 15.369259 | G20: =G17 -> 19.97163

Sheet GTM
B1: Market Approach - Guideline Transactions Method
B2: Value analysis as of Septermber 30, 2024
B3: KRW in millions
D4: 4 | E4: 5
B6: Announced Date | C6: Target | D6: EV | E6: LTM EBITDA | F6: EV/LTM EBITDA
B7: 43882 | C7: Cube Entertainment, Inc. (KOSDAQ:A182360) | D7: 90263.63 | E7: =D7/F7 -> 3849.1953 | F7: 23.45
B8: 44992 | C8: SM Entertainment Co., Ltd. (KOSDAQ:A041510) | D8: 3333828.7 | E8: =D8/F8 -> 163183 | F8: 20.43
B9: 44966 | C9: SM Entertainment Co., Ltd. (KOSDAQ:A041510) | D9: 2619096.1 | E9: =D9/F9 -> 163183.56 | F9: 16.05
B10: 44967 | C10: SM Entertainment Co., Ltd. (KOSDAQ:A041510) | D10: 2599192.8 | E10: =D10/F10 -> 163163.39 | F10: 15.93
B11: Max | F11: =MAX(F7:F10) -> 23.45
B12: Median | F12: =MEDIAN(F7:F10) -> 18.24
B13: 75% Quartile | F13: =_xlfn.QUARTILE.INC(F7:F10,3) -> 21.185
B14: Average | F14: =AVERAGE(F7:F10) -> 18.965
B15: 25% Quartile | F15: =_xlfn.QUARTILE.INC(F7:F10,1) -> 16.02
B16: Min | F16: =MIN(F7:F10) -> 15.93
B17: Selected | F17: =F14 -> 18.965
