Workbook

Sheet  Report
B2: 적용환율 : | C2: 1 USD k = | D2: =1131.6/10^3 -> 1.1316
B3: EV/EBIT, EV/EBITDA over 20x and P/E over 40x are presented as NM, and excluded from calculation of mean and median
B5: 1. LG-Hitachi Water Solutions
B6: 18A, LTM, 19E, 20E 적용 예정
C8: Share Price(USD) | F8: Maket Cap | G8: Enterprise Value | I8: EV/EBITDA | M8: P/E | Q8: P/B | R8: Gross Margin (18A) | S8: EBITDA (18A) | T8: Net Income (18A) | U8: PEG (16-18)
B9: (USD m) | C9: Latest | D9: 52W High | E9: 52W Low | I9: 16A | J9: 17A | K9: 18A | M9: 16A | N9: 17A | O9: 18A | Q9: 18A
B10: Korea
B11: 웰크론한텍 | C11: =Summary!C31/' Report'!$D$2/1000 -> 1.9823439 | D11: 3.2211029 | E11: 1.5243902 | F11: =Summary!E31/$D$2/1000 -> 38.383278 | G11: =(Summary!J31/' Report'!$D$2)/1000 -> 20.420831 | I11: =IF('2016'!T31>20,"NM",IF('2016'!T31<0,"NM",'2016'!T31)) -> NM | J11: =IF('2017'!T31>20,"NM",IF('2017'!T31<0,"NM",'2017'!T31)) -> 13.937054 | K11: =IF('2018'!T31>20,"NM",IF('2018'!T31<0,"NM",'2018'!T31)) -> 5.2391951 | M11: =IF('2016'!U31>40,"NM",IF('2016'!U31<0,"NM",'2016'!U31)) -> NM | N11: =IF('2017'!U31>40,"NM",IF('2017'!U31<0,"NM",'2017'!U31)) -> NM | O11: =IF('2018'!U31>40,"NM",IF('2018'!U31<0,"NM",'2018'!U31)) -> NM | Q11: ='2018'!Q31 -> 0.43368761 | R11: =12858.6784614705/D2/1000 -> 11.363272 | S11: ='2018'!O31/$D$2/1000 -> 3.8977039 | T11: ='2018'!P31/$D$2/1000 -> 0.21459593 | U11: =IFERROR(Summary!W31,"NM") -> NM
B12: 우원개발 | C12: =Summary!C33/' Report'!$D$2/1000 -> 4.4846505 | D12: 8.3863556 | E12: 2.7129728 | F12: =Summary!E33/$D$2/1000 -> 76.798191 | G12: =(Summary!J33/' Report'!$D$2)/1000 -> 31.218541 | I12: =IF('2016'!T33>20,"NM",IF('2016'!T33<0,"NM",'2016'!T33)) -> 3.6983242 | J12: =IF('2017'!T33>20,"NM",IF('2017'!T33<0,"NM",'2017'!T33)) -> 7.1005297 | K12: =IF('2018'!T33>20,"NM",IF('2018'!T33<0,"NM",'2018'!T33)) -> 12.843634 | M12: =IF('2016'!U33>40,"NM",IF('2016'!U33<0,"NM",'2016'!U33)) -> 9.971164 | N12: =IF('2017'!U33>40,"NM",IF('2017'!U33<0,"NM",'2017'!U33)) -> NM | O12: =IF('2018'!U33>40,"NM",IF('2018'!U33<0,"NM",'2018'!U33)) -> NM | Q12: ='2018'!Q33 -> 1.4041481 | R12: =20792.4304241782/D2/1000 -> 18.374364 | S12: ='2018'!O33/$D$2/1000 -> 2.4306627 | T12: ='2018'!P33/$D$2/1000 -> -1.2766374 | U12: =IFERROR(Summary!W33,"NM") -> NM
B13: Mean | I13: =AVERAGE(I11:I12) -> 3.6983242 | J13: =AVERAGE(J11:J12) -> 10.518792 | K13: =AVERAGE(K11:K12) -> 9.0414143 | M13: =AVERAGE(M11:M12) -> 9.971164 | N13: NM | O13: NM | Q13: =AVERAGE(Q11:Q12) -> 0.91891784
B14: Median | I14: =MEDIAN(I11:I12) -> 3.6983242 | J14: =MEDIAN(J11:J12) -> 10.518792 | K14: =MEDIAN(K11:K12) -> 9.0414143 | M14: =MEDIAN(M11:M12) -> 9.971164 | N14: NM | O14: NM | Q14: =MEDIAN(Q11:Q12) -> 0.91891784
B15: Global
B16: CITIC Envirotech Ltd | C16: 0.34738 | D16: 0.51988 | E16: 0.23828 | F16: ='Summary (2)'!D8/' Report'!$D$2/1000 -> 766.65718 | G16: ='Summary (2)'!I8/' Report'!D2/1000 -> 1631.9136 | I16: 11.372488 | J16: 12.285238 | K16: =G16/S16 -> 8.2493461 | M16: 26.240082 | N16: 16.81435 | O16: =F16/T16 -> 10.115953 | Q16: 0.9985181 | R16: 285.5 | S16: ='Summary (2)'!N8/' Report'!D2/1000 -> 197.82338 | T16: ='Summary (2)'!O8/' Report'!D2/1000 -> 75.786946 | U16: NM | W16: NM
B17: Nihon Trim Co Ltd | C17: 52.18019 | D17: 55.14467 | E17: 39.2999 | F17: ='Summary (2)'!D11/' Report'!$D$2/1000 -> 239.13749 | G17: ='Summary (2)'!I11/' Report'!$D$2/1000 -> 156.10708 | I17: 10.2 | J17: 16.283582 | K17: =G17/S17 -> 8.0392782 | M17: 22.2547 | N17: 38.960175 | O17: =F17/T17 -> 21.697585 | Q17: 2.9274951 | R17: 94.9 | S17: ='Summary (2)'!N11/' Report'!$D$2/1000 -> 19.418047 | T17: ='Summary (2)'!O11/' Report'!$D$2/1000 -> 11.021387 | U17: NM | W17: NM
B18: AECOM | C18: 29.67 | D18: 36.75 | E18: 24.92 | F18: ='Summary (2)'!D12/' Report'!$D$2/1000 -> 5527.7097 | G18: ='Summary (2)'!I12/' Report'!$D$2/1000 -> 8730.2977 | I18: 10.653434 | J18: 11.433953 | K18: =G18/S18 -> 10.376722 | M18: 33.787771 | N18: 14.055008 | O18: NM | Q18: 1.1357432 | R18: 685.1 | S18: ='Summary (2)'!N12/' Report'!$D$2/1000 -> 841.33484 | T18: ='Summary (2)'!O12/' Report'!$D$2/1000 -> 74.568785 | U18: NM | W18: 0.099242163
B19: Xylem Inc/NY | C19: 79.04 | D19: 81.3374 | E19: 61.1779 | F19: ='Summary (2)'!D13/' Report'!$D$2/1000 -> 4633.6774 | G19: ='Summary (2)'!I13/' Report'!$D$2/1000 -> 6730.1195 | I19: 16.649137 | J19: 18.428248 | K19: =G19/S19 -> 7.0493835 | M19: 34.707367 | N19: NM | O19: =F19/T19 -> 8.5753835 | Q19: 5.1271117 | R19: 2031 | S19: ='Summary (2)'!N13/' Report'!$D$2/1000 -> 954.71036 | T19: ='Summary (2)'!O13/' Report'!$D$2/1000 -> 540.34638 | U19: =O19/W19 -> 17.817191 | W19: 0.48129828
B20: Mean | I20: =AVERAGE(I16:I19) -> 12.218765 | J20: =AVERAGE(J16:J19) -> 14.607755 | K20: =AVERAGE(K16:K19) -> 8.4286824 | M20: =AVERAGE(M16:M19) -> 29.24748 | N20: =AVERAGE(N16:N19) -> 23.276511 | O20: =AVERAGE(O16:O19) -> 13.462974 | Q20: =AVERAGE(Q16:Q19) -> 2.547217
B21: Median | I21: =MEDIAN(I16:I19) -> 11.012961 | J21: =MEDIAN(J16:J19) -> 14.28441 | K21: =MEDIAN(K16:K19) -> 8.1443121 | M21: =MEDIAN(M16:M19) -> 30.013927 | N21: =MEDIAN(N16:N19) -> 16.81435 | O21: =MEDIAN(O16:O19) -> 10.115953 | Q21: =MEDIAN(Q16:Q19) -> 2.0316192
B23: Mean | I23: =AVERAGE(I16:I19,I11:I12) -> 10.514677 | J23: =AVERAGE(J16:J19,J11:J12) -> 13.244767 | K23: =AVERAGE(K16:K19,K11:K12) -> 8.6329264 | M23: =AVERAGE(M16:M19,M11:M12) -> 25.392217 | N23: =AVERAGE(N16:N19,N11:N12) -> 23.276511 | O23: =AVERAGE(O16:O19,O11:O12) -> 13.462974 | Q23: =AVERAGE(Q16:Q19,Q11:Q12) -> 2.0044506
B24: Median | I24: =MEDIAN(,I16:I19,I11:I12) -> 10.426717 | J24: =MEDIAN(,J16:J19,J11:J12) -> 12.285238 | K24: =MEDIAN(,K16:K19,K11:K12) -> 8.0392782 | M24: =MEDIAN(,M16:M19,M11:M12) -> 24.247391 | N24: =MEDIAN(,N16:N19,N11:N12) -> 15.434679 | O24: =MEDIAN(,O16:O19,O11:O12) -> 9.3456682 | Q24: =MEDIAN(,Q16:Q19,Q11:Q12) -> 1.1357432
B26: 한국거래소 기업공시채널 KIND 시스템 상 수도, 하수 및 폐기물 처리, 원료 재생업으로 등록된 상장회사로 조회함.
B27: 국내의 경우 한국거래소 기업공시채널 KIND 시스템 상 수도, 하수 및 폐기물 처리, 원료 재생업으로 등록된 상장회사로 조회하여, 산업상 유사성을 기준으로 선정함.
B28: 해외의 경우, FACTIVA Dow Jones Industry 분류상 "Water Utilities", "Water Treatment Plant Construction" 산업으로 조회함.
B30: 2. HiEntech
C32: Share Price(USD) | F32: Maket Cap | G32: Enterprise Value | I32: EV/EBITDA | M32: P/E | Q32: P/B | R32: Gross Margin (18A) | S32: EBITDA (18A) | T32: Net Income (18A) | U32: PEG (16-18)
B33: (USD m) | C33: Latest | D33: 52W High | E33: 52W Low | I33: 16A | J33: 17A | K33: 18A | M33: 16A | N33: 17A | O33: 18A | Q33: 18A
B34: Korea
B35: KOENTEC CO LTD | C35: =Summary!C9/' Report'!$D$2/1000 -> 6.9613447 | D35: 8.7751856 | E35: 4.5510781 | F35: =Summary!E9/$D$2/1000 -> 348.06723 | G35: =Summary!J9/' Report'!$D$2/1000 -> 287.08454 | I35: =IF('2016'!T9>20,"NM",IF('2016'!T9<0,"NM",'2016'!T9)) -> 6.2632297 | J35: =IF('2017'!T9>20,"NM",IF('2017'!T9<0,"NM",'2017'!T9)) -> 7.8230567 | K35: =IF('2018'!T9>20,"NM",IF('2018'!T9<0,"NM",'2018'!T9)) -> 8.2446291 | M35: =IF('2016'!U9>40,"NM",IF('2016'!U9<0,"NM",'2016'!U9)) -> 9.8045042 | N35: =IF('2017'!U9>40,"NM",IF('2017'!U9<0,"NM",'2017'!U9)) -> 15.709858 | O35: =IF('2018'!U9>40,"NM",IF('2018'!U9<0,"NM",'2018'!U9)) -> 16.08353 | Q35: =Summary!Q9 -> 2.6490179 | R35: 30.039675 | S35: =(Summary!O9/$D$2)/1000 -> 34.820795 | T35: =(Summary!P9/$D$2)/1000 -> 21.641221 | U35: =O35/W35 -> 55.485763 | W35: =Summary!W9 -> 0.28986769
B36: INSUN ENT CO LTD | C36: =Summary!C10/' Report'!$D$2/1000 -> 6.1826363 | D36: 7.6882291 | E36: 4.7720042 | F36: =Summary!E10/$D$2/1000 -> 226.31567 | G36: =Summary!J10/' Report'!$D$2/1000 -> 284.13717 | I36: =IF('2016'!T10>20,"NM",IF('2016'!T10<0,"NM",'2016'!T10)) -> 12.74856 | J36: =IF('2017'!T10>20,"NM",IF('2017'!T10<0,"NM",'2017'!T10)) -> 12.481963 | K36: =IF('2018'!T10>20,"NM",IF('2018'!T10<0,"NM",'2018'!T10)) -> 10.606944 | M36: =IF('2016'!U10>40,"NM",IF('2016'!U10<0,"NM",'2016'!U10)) -> 29.097275 | N36: =IF('2017'!U10>40,"NM",IF('2017'!U10<0,"NM",'2017'!U10)) -> NM | O36: =IF('2018'!U10>40,"NM",IF('2018'!U10<0,"NM",'2018'!U10)) -> 12.827476 | Q36: =Summary!Q10 -> 1.3699514 | R36: 35.754921 | S36: =(Summary!O10/$D$2)/1000 -> 26.787845 | T36: =(Summary!P10/$D$2)/1000 -> 17.643039 | U36: =O36/W36 -> 21.735305 | W36: =Summary!W10 -> 0.59016774
B37: Mean | I37: =AVERAGE(I35:I36) -> 9.5058947 | J37: =AVERAGE(J35:J36) -> 10.15251 | K37: =AVERAGE(K35:K36) -> 9.4257866 | M37: =AVERAGE(M35:M36) -> 19.45089 | N37: =AVERAGE(N35:N36) -> 15.709858 | O37: =AVERAGE(O35:O36) -> 14.455503 | Q37: =AVERAGE(Q35:Q36) -> 2.0094847 | W37: =AVERAGE(W35:W36) -> 0.44001772 | X37: 12배~14배
B38: Median | I38: =MEDIAN(I35:I36) -> 9.5058947 | J38: =MEDIAN(J35:J36) -> 10.15251 | K38: =MEDIAN(K35:K36) -> 9.4257866 | M38: =MEDIAN(M35:M36) -> 19.45089 | N38: =MEDIAN(N35:N36) -> 15.709858 | O38: =MEDIAN(O35:O36) -> 14.455503 | Q38: =MEDIAN(Q35:Q36) -> 2.0094847 | W38: =MEDIAN(W35:W36) -> 0.44001772
B40: Global
B41: Beijing Enterprises Water Group Ltd | C41: 0.61784 | D41: 0.63059 | E41: 0.46067 | F41: ='Summary (2)'!D32/' Report'!$D$2/1000 -> 5494.1125 | G41: ='Summary (2)'!I32/' Report'!$D$2/1000 -> 11342.377 | I41: 16.896862 | J41: 15.288163 | K41: =G41/S41 -> 11.469971 | M41: 15.485728 | N41: 10.232948 | O41: =F41/T41 -> 9.3858368 | Q41: 1.9049761 | R41: 1118 | S41: ='Summary (2)'!N32/' Report'!$D$2/1000 -> 988.8759 | T41: ='Summary (2)'!O32/' Report'!$D$2/1000 -> 585.36203 | U41: =O41/W41 -> 98.337529 | W41: 0.095445115
B42: American Water Works Co Inc | C42: 103.7695 | D42: 106.6957 | E42: 76.8206 | F42: ='Summary (2)'!D34/' Report'!$D$2/1000 -> 17606.045 | G42: ='Summary (2)'!I34/' Report'!$D$2/1000 -> 25951.465 | I42: 12.591589 | J42: 12.911896 | K42: =G42/S42 -> 16.171985 | M42: 29.53378 | N42: 34.324697 | O42: =F42/T42 -> 31.927442 | Q42: 3.2094277 | R42: 1941 | S42: ='Summary (2)'!N34/' Report'!$D$2/1000 -> 1604.7174 | T42: ='Summary (2)'!O34/' Report'!$D$2/1000 -> 551.43924 | U42: NM | W42: 0.087270037
B43: Severn Trent PLC | C43: 25.67417 | D43: 27.53318 | E43: 22.36926 | F43: ='Summary (2)'!D35/' Report'!D2/1000 -> 6076.1532 | G43: ='Summary (2)'!I35/' Report'!D2/1000 -> 13227.529 | I43: 12.695226 | J43: 12.57197 | K43: =G43/S43 -> 11.701069 | M43: 16.132538 | N43: 18.901348 | O43: =F43/T43 -> 18.39305 | Q43: 4.2850393 | R43: 1712.2 | S43: ='Summary (2)'!N35/' Report'!$D$2/1000 -> 1130.4547 | T43: ='Summary (2)'!O35/' Report'!$D$2/1000 -> 330.3505 | U43: NM | W43: NM
B44: Mean | I44: =AVERAGE(I41:I43) -> 14.061226 | J44: =AVERAGE(J41:J43) -> 13.590677 | K44: =AVERAGE(K41:K43) -> 13.114342 | M44: =AVERAGE(M41:M43) -> 20.384015 | N44: =AVERAGE(N41:N43) -> 21.152998 | O44: =AVERAGE(O41:O43) -> 19.90211 | Q44: =AVERAGE(Q41:Q43) -> 3.1331477
B45: Median | I45: =MEDIAN(I41:I43) -> 12.695226 | J45: =MEDIAN(J41:J43) -> 12.911896 | K45: =MEDIAN(K41:K43) -> 11.701069 | M45: =MEDIAN(M41:M43) -> 16.132538 | N45: =MEDIAN(N41:N43) -> 18.901348 | O45: =MEDIAN(O41:O43) -> 18.39305 | Q45: =MEDIAN(Q41:Q43) -> 3.2094277
B47: Mean | I47: =AVERAGE(I35:I36,I41:I43) -> 12.239093 | J47: =AVERAGE(J35:J36,J41:J43) -> 12.21541 | K47: =AVERAGE(K35:K36,K41:K43) -> 11.63892 | M47: =AVERAGE(M35:M36,M41:M43) -> 20.010765 | N47: =AVERAGE(N35:N36,N41:N43) -> 19.792213 | O47: =AVERAGE(O35:O36,O41:O43) -> 17.723467 | Q47: =AVERAGE(Q35:Q36,Q41:Q43) -> 2.6836825
B48: Median | I48: =MEDIAN(I35:I36,I41:I43) -> 12.695226 | J48: =MEDIAN(J35:J36,J41:J43) -> 12.57197 | K48: =MEDIAN(K35:K36,K41:K43) -> 11.469971 | M48: =MEDIAN(M35:M36,M41:M43) -> 16.132538 | N48: =MEDIAN(N35:N36,N41:N43) -> 17.305603 | O48: =MEDIAN(O35:O36,O41:O43) -> 16.08353 | Q48: =MEDIAN(Q35:Q36,Q41:Q43) -> 2.6490179
B50: 국내의 경우 한국거래소 기업공시채널 KIND 시스템 상 주요 제품을 '건설업' 으로 조회하여, 산업상 유사성(수처리 건설업)을 기준으로 선정함.

Sheet Summary (2)
B1: Project AII
B2: Trading Multiple - 해외
A5: 1 | B5: 1. LG-Hitachi Water Solutions
B6: Guideline Public Company | C6: Country | D6: MKT Cap[1] (백만원) | E6: Debt | F6: Cash[2] | G6: NOA[3] | H6: Accumulated Minority Interest | I6: Enterprise Value | J6: LTM[4] | P6: Multiples
I7: of Equity(MM) | J7: BV | K7: Sales | L7: EBIT | M7: Dep. | N7: EBITDA | O7: Net Income | P7: PBR | Q7: EV/Sales | R7: EV/EBIT | S7: EV/EBITDA | T7: PER
A8: =INDEX([59]GPCM!$D$6:$D$24,MATCH(B8,[59]GPCM!$B$6:$B$24,0)) -> 1 | B8: CITIC Envirotech Ltd | C8: SINGAPORE | D8: =[59]GPCM!G7 -> 867549.26 | E8: =[59]유사BS!F5 -> 1130433.2 | F8: =[59]유사BS!G5 -> 307600.81 | G8: =[59]유사BS!E5-[59]유사BS!G5 -> 0 | H8: =[59]GPCM!I7 -> 156291.71 | I8: =D8+E8-F8-G8+H8 -> 1846673.4 | J8: =[59]GPCM!K7 -> 1122584.7 | K8: =[59]GPCM!L7 -> 811157.49 | L8: =[59]GPCM!M7 -> 192015.58 | M8: =[59]GPCM!N7 -> 31841.365 | N8: =[59]GPCM!O7 -> 223856.94 | O8: =[59]GPCM!P7 -> 85760.509 | P8: =IFERROR(IF(OR(ISERROR(D8/J8),D8/J8<0),"n.a.",D8/J8),"") -> 0.77281405 | Q8: =IFERROR(IF(OR(ISERROR(I8/K8),I8/K8<0),"n.a.",I8/K8),"") -> 2.2765904 | R8: =IFERROR(IF(OR(ISERROR(I8/L8),I8/L8<0),"n.a.",I8/L8),"") -> 9.6173103 | S8: =IFERROR(IF(OR(ISERROR(I8/N8),I8/N8<0),"n.a.",I8/N8),"") -> 8.2493461 | T8: =IFERROR(IF(OR(ISERROR(D8/O8),D8/O8<0),"n.a.",D8/O8),"") -> 10.115953
A9: =INDEX([59]GPCM!$D$6:$D$24,MATCH(B9,[59]GPCM!$B$6:$B$24,0)) -> 1 | B9: Kurita Water Industries Ltd | C9: JAPAN | D9: =[59]GPCM!G14 -> 3300191.4 | E9: =[59]유사BS!F12 -> 0 | F9: =[59]유사BS!G12 -> 745430.26 | G9: =[59]유사BS!E12-[59]유사BS!G12 -> 203348.09 | H9: =[59]GPCM!I14 -> 18754.815 | I9: =D9+E9-F9-G9+H9 -> 2370167.8 | J9: =[59]GPCM!K14 -> 2383953.2 | K9: =[59]GPCM!L14 -> 2661159.3 | L9: =[59]GPCM!M14 -> 247881.36 | M9: =[59]GPCM!N14 -> 184239.24 | N9: =[59]GPCM!O14 -> 432120.6 | O9: =[59]GPCM!P14 -> 172310.08 | P9: =IFERROR(IF(OR(ISERROR(D9/J9),D9/J9<0),"n.a.",D9/J9),"") -> 1.3843356 | Q9: =IFERROR(IF(OR(ISERROR(I9/K9),I9/K9<0),"n.a.",I9/K9),"") -> 0.89065237 | R9: =IFERROR(IF(OR(ISERROR(I9/L9),I9/L9<0),"n.a.",I9/L9),"") -> 9.5617027 | S9: =IFERROR(IF(OR(ISERROR(I9/N9),I9/N9<0),"n.a.",I9/N9),"") -> 5.4849684 | T9: =IFERROR(IF(OR(ISERROR(D9/O9),D9/O9<0),"n.a.",D9/O9),"") -> 19.152631
A10: =INDEX([59]GPCM!$D$6:$D$24,MATCH(B10,[59]GPCM!$B$6:$B$24,0)) -> 1 | B10: Organo Corp | C10: JAPAN | D10: =[59]GPCM!G16 -> 340896.22 | E10: =[59]유사BS!F15 -> 186553.03 | F10: =[59]유사BS!G15 -> 100191.53 | G10: =[59]유사BS!E15-[59]유사BS!G15 -> 16104.567 | H10: =[59]GPCM!I16 -> 1177.8877 | I10: =D10+E10-F10-G10+H10 -> 412331.05 | J10: =[59]GPCM!K16 -> 531887.35 | K10: =[59]GPCM!L16 -> 903197.83 | L10: =[59]GPCM!M16 -> 60383.273 | M10: =[59]GPCM!N16 -> 8939.3952 | N10: =[59]GPCM!O16 -> 69322.668 | O10: =[59]GPCM!P16 -> 41667.348 | P10: =IFERROR(IF(OR(ISERROR(D10/J10),D10/J10<0),"n.a.",D10/J10),"") -> 0.64091808 | Q10: =IFERROR(IF(OR(ISERROR(I10/K10),I10/K10<0),"n.a.",I10/K10),"") -> 0.45652352 | R10: =IFERROR(IF(OR(ISERROR(I10/L10),I10/L10<0),"n.a.",I10/L10),"") -> 6.8285641 | S10: =IFERROR(IF(OR(ISERROR(I10/N10),I10/N10<0),"n.a.",I10/N10),"") -> 5.9479974 | T10: =IFERROR(IF(OR(ISERROR(D10/O10),D10/O10<0),"n.a.",D10/O10),"") -> 8.1813755
A11: =INDEX([59]GPCM!$D$6:$D$24,MATCH(B11,[59]GPCM!$B$6:$B$24,0)) -> 1 | B11: Nihon Trim Co Ltd | C11: JAPAN | D11: =[59]GPCM!G19 -> 270607.98 | E11: =[59]유사BS!F18 -> 15323.486 | F11: =[59]유사BS!G18 -> 112303.89 | G11: =[59]유사BS!E18-[59]유사BS!G18 -> 0 | H11: =[59]GPCM!I19 -> 3023.201 | I11: =D11+E11-F11-G11+H11 -> 176650.77 | J11: =[59]GPCM!K19 -> 175259.99 | K11: =[59]GPCM!L19 -> 150260.11 | L11: =[59]GPCM!M19 -> 19501.694 | M11: =[59]GPCM!N19 -> 2471.7677 | N11: =[59]GPCM!O19 -> 21973.462 | O11: =[59]GPCM!P19 -> 12471.802 | P11: =IFERROR(IF(OR(ISERROR(D11/J11),D11/J11<0),"n.a.",D11/J11),"") -> 1.5440374 | Q11: =IFERROR(IF(OR(ISERROR(I11/K11),I11/K11<0),"n.a.",I11/K11),"") -> 1.1756332 | R11: =IFERROR(IF(OR(ISERROR(I11/L11),I11/L11<0),"n.a.",I11/L11),"") -> 9.058227 | S11: =IFERROR(IF(OR(ISERROR(I11/N11),I11/N11<0),"n.a.",I11/N11),"") -> 8.0392782 | T11: =IFERROR(IF(OR(ISERROR(D11/O11),D11/O11<0),"n.a.",D11/O11),"") -> 21.697585
A12: =INDEX([59]GPCM!$D$6:$D$24,MATCH(B12,[59]GPCM!$B$6:$B$24,0)) -> 1 | B12: AECOM | C12: UNITED STATES | D12: =[59]GPCM!G21 -> 6255156.2 | E12: =[59]유사BS!F20 -> 4365282.1 | F12: =[59]유사BS!G20 -> 933457.66 | G12: =[59]유사BS!E20-[59]유사BS!G20 -> 0 | H12: =[59]GPCM!I21 -> 192224.12 | I12: =D12+E12-F12-G12+H12 -> 9879204.8 | J12: =[59]GPCM!K21 -> 4732895.2 | K12: =[59]GPCM!L21 -> 22321433 | L12: =[59]GPCM!M21 -> 657224.17 | M12: =[59]GPCM!N21 -> 294830.33 | N12: =[59]GPCM!O21 -> 952054.5 | O12: =[59]GPCM!P21 -> 84382.037 | P12: =IFERROR(IF(OR(ISERROR(D12/J12),D12/J12<0),"n.a.",D12/J12),"") -> 1.3216342 | Q12: =IFERROR(IF(OR(ISERROR(I12/K12),I12/K12<0),"n.a.",I12/K12),"") -> 0.44258829 | R12: =IFERROR(IF(OR(ISERROR(I12/L12),I12/L12<0),"n.a.",I12/L12),"") -> 15.031712 | S12: =IFERROR(IF(OR(ISERROR(I12/N12),I12/N12<0),"n.a.",I12/N12),"") -> 10.376722 | T12: =IFERROR(IF(OR(ISERROR(D12/O12),D12/O12<0),"n.a.",D12/O12),"") -> 74.129003
A13: =INDEX([59]GPCM!$D$6:$D$24,MATCH(B13,[59]GPCM!$B$6:$B$24,0)) -> 1 | B13: Xylem Inc/NY | C13: UNITED STATES | D13: =[59]GPCM!G22 -> 5243469.4 | E13: =[59]유사BS!F21 -> 2671577.9 | F13: =[59]유사BS!G21 -> 312897.75 | G13: =[59]유사BS!E21-[59]유사BS!G21 -> 0 | H13: =[59]GPCM!I22 -> 13653.72 | I13: =D13+E13-F13-G13+H13 -> 7615803.2 | J13: =[59]GPCM!K22 -> 3194970.5 | K13: =[59]GPCM!L22 -> 5821639.9 | L13: =[59]GPCM!M22 -> 792999.35 | M13: =[59]GPCM!N22 -> 287350.89 | N13: =[59]GPCM!O22 -> 1080350.2 | O13: =[59]GPCM!P22 -> 611455.96 | P13: =IFERROR(IF(OR(ISERROR(D13/J13),D13/J13<0),"n.a.",D13/J13),"") -> 1.6411636 | Q13: =IFERROR(IF(OR(ISERROR(I13/K13),I13/K13<0),"n.a.",I13/K13),"") -> 1.3081886 | R13: =IFERROR(IF(OR(ISERROR(I13/L13),I13/L13<0),"n.a.",I13/L13),"") -> 9.603795 | S13: =IFERROR(IF(OR(ISERROR(I13/N13),I13/N13<0),"n.a.",I13/N13),"") -> 7.0493835 | T13: =IFERROR(IF(OR(ISERROR(D13/O13),D13/O13<0),"n.a.",D13/O13),"") -> 8.5753835
B16: 주요가정 Summary | M16: 1 | N16: Guideline Public Company Method
B17: [1] MKT Cap : 2019년 3월 31일 기준 3개월 평균 주가 | N17: Multiples | P17: PBR | Q17: EV/Sales | R17: EV/EBIT | S17: EV/EBITDA | T17: PER
B18: [2] Cash : 현금및현금성자산 및 단기금융상품 | N18: Min | P18: =MIN(P8:P14) -> 0.64091808 | Q18: =MIN(Q8:Q14) -> 0.44258829 | R18: =MIN(R8:R14) -> 6.8285641 | S18: =MIN(S8:S14) -> 5.4849684 | T18: =MIN(T8:T14) -> 8.1813755
B19: [3] NOA : 투자자산 | N19: Median | P19: =MEDIAN(P8:P14) -> 1.3529849 | Q19: =MEDIAN(Q8:Q14) -> 1.0331428 | R19: =MEDIAN(R8:R14) -> 9.5827488 | S19: =MEDIAN(S8:S14) -> 7.5443309 | T19: =MEDIAN(T8:T14) -> 14.634292
B20: [4] LTM : 국가별 회계보고일 차이로 대상시점에서 일부차이가 있으며 가장 최신 수치를 반영 | N20: Average | P20: =AVERAGE(P8:P14) -> 1.2174838 | Q20: =AVERAGE(Q8:Q14) -> 1.0916961 | R20: =AVERAGE(R8:R14) -> 9.9502186 | S20: =AVERAGE(S8:S14) -> 7.5246159 | T20: =AVERAGE(T8:T14) -> 23.641988
N21: Max | P21: =MAX(P8:P14) -> 1.6411636 | Q21: =MAX(Q8:Q14) -> 2.2765904 | R21: =MAX(R8:R14) -> 15.031712 | S21: =MAX(S8:S14) -> 10.376722 | T21: =MAX(T8:T14) -> 74.129003
B22: 비교 대상기업의 선정
B23: 1. FACTIVA Dow Jones Industry 분류상 "Water Utilities", "Water Treatment Plant Construction" 산업으로 조회함.
B24: 2. 대상회사는 하수 및 폐수 처리 설비의 설계 및 건축을 주업으로 하는 회사이므로 이와 사업구조가 유사한 회사를 선정
B25: 3. Valuation상 평균 범위대비 이상치(Outliar)에 해당될 수 있는 경우 제외
B28: 2. HiEntech
B29: Guideline Public Company | C29: Country | D29: MKT Cap[1] (백만원) | E29: Debt | F29: Cash[2] | G29: NOA[3] | H29: Accumulated Minority Interest | I29: Enterprise Value | J29: LTM[4] | P29: Multiples
I30: of Equity(MM) | J30: BV | K30: Sales | L30: EBIT | M30: Dep. | N30: EBITDA | O30: Net Income | P30: PBR | Q30: EV/Sales | R30: EV/EBIT | S30: EV/EBITDA | T30: PER
A31: =INDEX([59]GPCM!$D$6:$D$24,MATCH(B31,[59]GPCM!$B$6:$B$24,0)) -> 2 | B31: Kangda International Environmental Co Ltd | C31: =[59]GPCM!E6 -> CHINA | D31: =[59]GPCM!G6 -> 299265.99 | E31: =[59]유사BS!F3 -> 1483794.2 | F31: =[59]유사BS!G3 -> 207448.93 | G31: =[59]유사BS!E3-[59]유사BS!G3 -> 0 | H31: =[59]GPCM!I6 -> 34652.726 | I31: =D31+E31-F31-G31+H31 -> 1610264 | J31: =[59]GPCM!K6 -> 709095.67 | K31: =[59]GPCM!L6 -> 517266.08 | L31: =[59]GPCM!M6 -> 159358.14 | M31: =[59]GPCM!N6 -> 7881.652 | N31: =[59]GPCM!O6 -> 167239.79 | O31: =[59]GPCM!P6 -> 71152.996 | P31: =IFERROR(IF(OR(ISERROR(D31/J31),D31/J31<0),"n.a.",D31/J31),"") -> 0.42203895 | Q31: =IFERROR(IF(OR(ISERROR(I31/K31),I31/K31<0),"n.a.",I31/K31),"") -> 3.1130284 | R31: =IFERROR(IF(OR(ISERROR(I31/L31),I31/L31<0),"n.a.",I31/L31),"") -> 10.104686 | S31: =IFERROR(IF(OR(ISERROR(I31/N31),I31/N31<0),"n.a.",I31/N31),"") -> 9.6284737 | T31: =IFERROR(IF(OR(ISERROR(D31/O31),D31/O31<0),"n.a.",D31/O31),"") -> 4.2059507
A32: =INDEX([59]GPCM!$D$6:$D$24,MATCH(B32,[59]GPCM!$B$6:$B$24,0)) -> 2 | B32: Beijing Enterprises Water Group Ltd | C32: HONG KONG | D32: =[59]GPCM!G9 -> 6217137.7 | E32: =[59]유사BS!F7 -> 7965529.5 | F32: =[59]유사BS!G7 -> 1839355.4 | G32: =[59]유사BS!E7-[59]유사BS!G7 -> 357278.73 | H32: =[59]GPCM!I9 -> 849001.26 | I32: =D32+E32-F32-G32+H32 -> 12835034 | J32: =[59]GPCM!K9 -> 5375781.1 | K32: =[59]GPCM!L9 -> 3453867.9 | L32: =[59]GPCM!M9 -> 1047285.9 | M32: =[59]GPCM!N9 -> 71726.064 | N32: =[59]GPCM!O9 -> 1119012 | O32: =[59]GPCM!P9 -> 662395.67 | P32: =IFERROR(IF(OR(ISERROR(D32/J32),D32/J32<0),"n.a.",D32/J32),"") -> 1.1565087 | Q32: =IFERROR(IF(OR(ISERROR(I32/K32),I32/K32<0),"n.a.",I32/K32),"") -> 3.7161335 | R32: =IFERROR(IF(OR(ISERROR(I32/L32),I32/L32<0),"n.a.",I32/L32),"") -> 12.255521 | S32: =IFERROR(IF(OR(ISERROR(I32/N32),I32/N32<0),"n.a.",I32/N32),"") -> 11.469971 | T32: =IFERROR(IF(OR(ISERROR(D32/O32),D32/O32<0),"n.a.",D32/O32),"") -> 9.3858368
A33: =INDEX([59]GPCM!$D$6:$D$24,MATCH(B33,[59]GPCM!$B$6:$B$24,0)) -> 2 | B33: Jiangxi Hongcheng Waterworks Co Ltd | C33: CHINA | D33: =[59]GPCM!G10 -> 759700.32 | E33: =[59]유사BS!F8 -> 633186.33 | F33: =[59]유사BS!G8 -> 275720.1 | G33: =[59]유사BS!E8-[59]유사BS!G8 -> 0 | H33: =[59]GPCM!I10 -> 57467.286 | I33: =D33+E33-F33-G33+H33 -> 1174633.8 | J33: =[59]GPCM!K10 -> 678998.58 | K33: =[59]GPCM!L10 -> 763157.87 | L33: =[59]GPCM!M10 -> 118122.02 | M33: =[59]GPCM!N10 -> 0 | N33: =[59]GPCM!O10 -> 118122.02 | O33: =[59]GPCM!P10 -> 62173.936 | P33: =IFERROR(IF(OR(ISERROR(D33/J33),D33/J33<0),"n.a.",D33/J33),"") -> 1.1188541 | Q33: =IFERROR(IF(OR(ISERROR(I33/K33),I33/K33<0),"n.a.",I33/K33),"") -> 1.5391754 | R33: =IFERROR(IF(OR(ISERROR(I33/L33),I33/L33<0),"n.a.",I33/L33),"") -> 9.9442412 | S33: =IFERROR(IF(OR(ISERROR(I33/N33),I33/N33<0),"n.a.",I33/N33),"") -> 9.9442412 | T33: =IFERROR(IF(OR(ISERROR(D33/O33),D33/O33<0),"n.a.",D33/O33),"") -> 12.218952
A34: =INDEX([59]GPCM!$D$6:$D$24,MATCH(B34,[59]GPCM!$B$6:$B$24,0)) -> 2 | B34: American Water Works Co Inc | C34: UNITED STATES | D34: =[59]GPCM!G12 -> 19923000 | E34: =[59]유사BS!F10 -> 9588434.6 | F34: =[59]유사BS!G10 -> 144756.3 | G34: =[59]유사BS!E10-[59]유사BS!G10 -> 0 | H34: =[59]GPCM!I12 -> 0 | I34: =D34+E34-F34-G34+H34 -> 29366678 | J34: =[59]GPCM!K12 -> 6529622.6 | K34: =[59]GPCM!L12 -> 3785872.6 | L34: =[59]GPCM!M12 -> 1216101.5 | M34: =[59]GPCM!N12 -> 599796.67 | N34: =[59]GPCM!O12 -> 1815898.2 | O34: =[59]GPCM!P12 -> 624008.65 | P34: =IFERROR(IF(OR(ISERROR(D34/J34),D34/J34<0),"n.a.",D34/J34),"") -> 3.0511717 | Q34: =IFERROR(IF(OR(ISERROR(I34/K34),I34/K34<0),"n.a.",I34/K34),"") -> 7.7569115 | R34: =IFERROR(IF(OR(ISERROR(I34/L34),I34/L34<0),"n.a.",I34/L34),"") -> 24.148213 | S34: =IFERROR(IF(OR(ISERROR(I34/N34),I34/N34<0),"n.a.",I34/N34),"") -> 16.171985 | T34: =IFERROR(IF(OR(ISERROR(D34/O34),D34/O34<0),"n.a.",D34/O34),"") -> 31.927442
A35: =INDEX([59]GPCM!$D$6:$D$24,MATCH(B35,[59]GPCM!$B$6:$B$24,0)) -> 2 | B35: Severn Trent PLC | C35: BRITAIN | D35: =[59]GPCM!G13 -> 6875775 | E35: =[59]유사BS!F11 -> 8212351.7 | F35: =[59]유사BS!G11 -> 119854.53 | G35: =[59]유사BS!E11-[59]유사BS!G11 -> 0 | H35: =[59]GPCM!I13 -> 0 | I35: =D35+E35-F35-G35+H35 -> 14968272 | J35: =[59]GPCM!K13 -> 1615285.9 | K35: =[59]GPCM!L13 -> 2541064.8 | L35: =[59]GPCM!M13 -> 782704.52 | M35: =[59]GPCM!N13 -> 496518.05 | N35: =[59]GPCM!O13 -> 1279222.6 | O35: =[59]GPCM!P13 -> 373824.63 | P35: =IFERROR(IF(OR(ISERROR(D35/J35),D35/J35<0),"n.a.",D35/J35),"") -> 4.2566922 | Q35: =IFERROR(IF(OR(ISERROR(I35/K35),I35/K35<0),"n.a.",I35/K35),"") -> 5.8905511 | R35: =IFERROR(IF(OR(ISERROR(I35/L35),I35/L35<0),"n.a.",I35/L35),"") -> 19.123784 | S35: =IFERROR(IF(OR(ISERROR(I35/N35),I35/N35<0),"n.a.",I35/N35),"") -> 11.701069 | T35: =IFERROR(IF(OR(ISERROR(D35/O35),D35/O35<0),"n.a.",D35/O35),"") -> 18.39305
A36: =INDEX([59]GPCM!$D$6:$D$24,MATCH(B36,[59]GPCM!$B$6:$B$24,0)) -> 2 | B36: Yunnan Water Investment Co Ltd | C36: CHINA | D36: =[59]GPCM!G15 -> 390245.17 | E36: =[59]유사BS!F14 -> 2504288.7 | F36: =[59]유사BS!G14 -> 338279.28 | G36: =[59]유사BS!E14-[59]유사BS!G14 -> 5217.0112 | H36: =[59]GPCM!I15 -> 161412.7 | I36: =D36+E36-F36-G36+H36 -> 2712450.3 | J36: =[59]GPCM!K15 -> 1096014.9 | K36: =[59]GPCM!L15 -> 997344.86 | L36: =[59]GPCM!M15 -> 201577.76 | M36: =[59]GPCM!N15 -> 98306.742 | N36: =[59]GPCM!O15 -> 299884.5 | O36: =[59]GPCM!P15 -> 83324.276 | P36: =IFERROR(IF(OR(ISERROR(D36/J36),D36/J36<0),"n.a.",D36/J36),"") -> 0.35605827 | Q36: =IFERROR(IF(OR(ISERROR(I36/K36),I36/K36<0),"n.a.",I36/K36),"") -> 2.7196714 | R36: =IFERROR(IF(OR(ISERROR(I36/L36),I36/L36<0),"n.a.",I36/L36),"") -> 13.456099 | S36: =IFERROR(IF(OR(ISERROR(I36/N36),I36/N36<0),"n.a.",I36/N36),"") -> 9.0449834 | T36: =IFERROR(IF(OR(ISERROR(D36/O36),D36/O36<0),"n.a.",D36/O36),"") -> 4.683451
A37: =INDEX([59]GPCM!$D$6:$D$24,MATCH(B37,[59]GPCM!$B$6:$B$24,0)) -> 2 | B37: Guangxi Nanning Waterworks Co Ltd | C37: CHINA | D37: =[59]GPCM!G17 -> 761285.92 | E37: =[59]유사BS!F16 -> 686243.56 | F37: =[59]유사BS!G16 -> 180679.74 | G37: =[59]유사BS!E16-[59]유사BS!G16 -> 0 | H37: =[59]GPCM!I17 -> 0 | I37: =D37+E37-F37-G37+H37 -> 1266849.7 | J37: =[59]GPCM!K17 -> 524911.57 | K37: =[59]GPCM!L17 -> 218552.63 | L37: =[59]GPCM!M17 -> 80478.121 | M37: =[59]GPCM!N17 -> 0 | N37: =[59]GPCM!O17 -> 80478.121 | O37: =[59]GPCM!P17 -> 46458.431 | P37: =IFERROR(IF(OR(ISERROR(D37/J37),D37/J37<0),"n.a.",D37/J37),"") -> 1.4503127 | Q37: =IFERROR(IF(OR(ISERROR(I37/K37),I37/K37<0),"n.a.",I37/K37),"") -> 5.7965432 | R37: =IFERROR(IF(OR(ISERROR(I37/L37),I37/L37<0),"n.a.",I37/L37),"") -> 15.741542 | S37: =IFERROR(IF(OR(ISERROR(I37/N37),I37/N37<0),"n.a.",I37/N37),"") -> 15.741542 | T37: =IFERROR(IF(OR(ISERROR(D37/O37),D37/O37<0),"n.a.",D37/O37),"") -> 16.386389
B40: 주요가정 Summary | M40: 1 | N40: Guideline Public Company Method
B41: [1] MKT Cap : 2019년 3월 31일 기준 3개월 평균 주가 | N41: Multiples | P41: PBR | Q41: EV/Sales | R41: EV/EBIT | S41: EV/EBITDA | T41: PER
B42: [2] Cash : 현금및현금성자산 및 단기금융상품 | N42: Min | P42: =MIN(P31:P38) -> 0.35605827 | Q42: =MIN(Q31:Q38) -> 1.5391754 | R42: =MIN(R31:R38) -> 9.9442412 | S42: =MIN(S31:S38) -> 9.0449834 | T42: =MIN(T31:T38) -> 4.2059507
B43: [3] NOA : 투자자산 | N43: Median | P43: =MEDIAN(P31:P38) -> 1.1565087 | Q43: =MEDIAN(Q31:Q38) -> 3.7161335 | R43: =MEDIAN(R31:R38) -> 13.456099 | S43: =MEDIAN(S31:S38) -> 11.469971 | T43: =MEDIAN(T31:T38) -> 12.218952
B44: [4] LTM : 국가별 회계보고일 차이로 대상시점에서 일부차이가 있으며 가장 최신 수치를 반영 | N44: Average | P44: =AVERAGE(P31:P38) -> 1.6873767 | Q44: =AVERAGE(Q31:Q38) -> 4.3617164 | R44: =AVERAGE(R31:R38) -> 14.967727 | S44: =AVERAGE(S31:S38) -> 11.957467 | T44: =AVERAGE(T31:T38) -> 13.885867
N45: Max | P45: =MAX(P31:P38) -> 4.2566922 | Q45: =MAX(Q31:Q38) -> 7.7569115 | R45: =MAX(R31:R38) -> 24.148213 | S45: =MAX(S31:S38) -> 16.171985 | T45: =MAX(T31:T38) -> 31.927442
B46: 비교 대상기업의 선정
B47: 1. FACTIVA Dow Jones Industry 분류상 "Water Utilities", "Water Treatment Plant Construction" 산업으로 조회함.
B48: 2. 대상회사는 하수 및 폐수 처리 설비의 운용을 주업으로 하는 회사이므로 이와 사업구조가 유사한 회사를 선정
B49: 3. Valuation상 평균 범위대비 이상치(Outliar)에 해당될 수 있는 경우 제외

Sheet Summary
A1: Project All
A2: Trading Multiple - 국내
A3: (Unit : KRW million, unless otherwise noted)
B5: HiEntech | K5: 2018년 12개월 기준 | Q5: Multiples | W5: =U8/W8 -> 42.939168
B6: 백만원 | C6: Price [1] | D6: Outstanding[2] | E6: Market Cap | F6: Debt | G6: Cash[3] | H6: NOA[4] | I6: 비지배지분 | J6: EV | K6: BV | L6: Revenue | M6: EBIT | N6: Depreciation | O6: EBITDA | P6: Net Income | Q6: PBR | R6: EV/Revenue | S6: EV/EBIT | T6: EV/EBITDA | U6: PER | V6: PEG | W6: =U9/W9 -> 55.485763
B7: Target(HiEntech) | C7: N/A | D7: N/A | E7: N/A | F7: 0 | G7: 0 | H7: 0 | I7: 0 | J7: N/A | K7: =하이엔텍_Dart!E47/10^6 -> 35747.682 | L7: =하이엔텍_Dart!J5/10^6 -> 155484.44 | M7: =하이엔텍_Dart!J9/10^6 -> 10219.599 | N7: =SUM(하이엔텍_Dart!J37:J38)/10^3 -> 513.603 | O7: =M7+N7 -> 10733.202 | P7: =하이엔텍_Dart!J16/10^6 -> 8449.3759 | W7: =U10/W10 -> 21.735305
B8: ='모집단 선정(HiEntech)'!D37 -> 와이엔텍 | C8: =와이엔텍!N3 -> 5768.5593 | D8: =와이엔텍!N7/10^3 -> 18199.659 | E8: =(D8*C8)/1000 -> 104985.81 | F8: =와이엔텍!C$6 -> 75272.804 | G8: =와이엔텍!C$3 -> 14407.688 | H8: =와이엔텍!C$10 -> 4096.857 | I8: 0 | J8: =E8+F8-G8-H8+I8 -> 161754.07 | K8: =와이엔텍!C$15 -> 116581.79 | L8: =와이엔텍!H$4 -> 76070.963 | M8: =와이엔텍!H$5 -> 14934.316 | N8: =와이엔텍!H$6 -> 6461.887 | O8: =M8+N8 -> 21396.203 | P8: =와이엔텍!H$8 -> 9033.2051 | Q8: =E8/K8 -> 0.90053358 | R8: =J8/L8 -> 2.1263576 | S8: =J8/M8 -> 10.831033 | T8: =J8/O8 -> 7.5599428 | U8: =E8/P8 -> 11.622211 | V8: =P8/D8*1000000 -> 496339.25 | W8: =RATE(2,0,-'2016'!V8,Summary!V8) -> 0.27066688
B9: ='모집단 선정(HiEntech)'!D38 -> 코엔텍 | C9: =코엔텍!N$3 -> 7877.4576 | D9: =코엔텍!N7/10^3 -> 50000 | E9: =(D9*C9)/1000 -> 393872.88 | F9: =코엔텍!C$6 -> 25805.2 | G9: =코엔텍!C$3 -> 92869.832 | H9: =코엔텍!C$10 -> 1950.9296 | I9: =코엔텍!C66/10^6 -> 7.545629 | J9: =E9+F9-G9-H9+I9 -> 324864.87 | K9: =코엔텍!C$15 -> 148686.38 | L9: =코엔텍!H$4 -> 72239.031 | M9: =코엔텍!H$5 -> 29310.888 | N9: =코엔텍!H$6 -> 10092.323 | O9: =M9+N9 -> 39403.211 | P9: =코엔텍!H$8 -> 24489.206 | Q9: =E9/K9 -> 2.6490179 | R9: =J9/L9 -> 4.4970823 | S9: =J9/M9 -> 11.083419 | T9: =J9/O9 -> 8.2446291 | U9: =E9/P9 -> 16.08353 | V9: =P9/D9*1000000 -> 489784.12 | W9: =RATE(2,0,-'2016'!V9,Summary!V9) -> 0.28986769
B10: ='모집단 선정(HiEntech)'!D39 -> 인선이엔티 | C10: =인선이엔티!O$3 -> 6996.2712 | D10: =인선이엔티!O7/10^3 -> 36605.043 | E10: =(D10*C10)/1000 -> 256098.81 | F10: =인선이엔티!C$6 -> 90603.868 | G10: =인선이엔티!C$3 -> 26968.662 | H10: =인선이엔티!C$10 -> 2785.2241 | I10: =인선이엔티!C46/10^6 -> 4580.8354 | J10: =E10+F10-G10-H10+I10 -> 321529.63 | K10: =인선이엔티!C$15 -> 186940.06 | L10: =인선이엔티!H$4 -> 175954.97 | M10: =인선이엔티!H$5 -> 23853.49 | N10: =인선이엔티!H$6 -> 6459.635 | O10: =M10+N10 -> 30313.125 | P10: =인선이엔티!H$8 -> 19964.863 | Q10: =E10/K10 -> 1.3699514 | R10: =J10/L10 -> 1.8273405 | S10: =J10/M10 -> 13.479353 | T10: =J10/O10 -> 10.606944 | U10: =E10/P10 -> 12.827476 | V10: =P10/D10*1000000 -> 545412.92 | W10: =RATE(2,0,-'2016'!V10,Summary!V10) -> 0.59016774
B13: 주요가정 Summary | O13: 국내 | P13: Mean | Q13: =AVERAGE(Q8:Q10) -> 1.6398343 | R13: =AVERAGE(R8:R10) -> 2.8169268 | S13: =AVERAGE(S8:S10) -> 11.797935 | T13: =AVERAGE(T8:T10) -> 8.8038386 | U13: =AVERAGE(U8:U10) -> 13.511072
B14: [1] 주가 : 2019년 3월 31일 기준 3개월 평균 주가 | P14: Median | Q14: =MEDIAN(Q8:Q10) -> 1.3699514 | R14: =MEDIAN(R8:R10) -> 2.1263576 | S14: =MEDIAN(S8:S10) -> 11.083419 | T14: =MEDIAN(T8:T10,) -> 7.9022859 | U14: =MEDIAN(U8:U10) -> 12.827476
B15: [2] 발행주식수 2019년 3월 31일 발행 주식수 | P15: Max | Q15: =MAX(Q8:Q10) -> 2.6490179 | R15: =MAX(R8:R10) -> 4.4970823 | S15: =MAX(S8:S10) -> 13.479353 | T15: =MAX(T8:T10) -> 10.606944 | U15: =MAX(U8:U10) -> 16.08353
B16: [3] Cash : 2018년말 현금및현금성자산 및 단기금융상품 | P16: Min | Q16: =MIN(Q8:Q10) -> 0.90053358 | R16: =MIN(R8:R10) -> 1.8273405 | S16: =MIN(S8:S10) -> 10.831033 | T16: =MIN(T8:T10) -> 7.5599428 | U16: =MIN(U8:U10) -> 11.622211
B17: [4] NoA : 2018년말 장기금융상품, 관계기업투자, 매도가능증권, 투자부동산, 매각예정자산, 장단기 대여금
B19: 비교 대상기업의 선정
B20: 1. 한국거래소 기업공시채널 KIND 시스템 상 수도, 하수 및 폐기물 처리, 원료 재생업으로 등록된 상장회사로 조회
B21: 2. 대상회사의 전방산업인 하수 처리업으로 분류된 상장회사가 없으므로 대용으로 폐기물 처리업을 영위하는 회사를 선정
B22: 3. 선정된 회사 중 주요 관계기업투자에 인터넷뉴스광고업을 영위하는 회사가 있어 주가 산정이 왜곡 되거나 영업손실이 발생하여 Multiple이 비교 불가능한 회사를 제외
B28: LG-Hitachi Water Solutions | K28: 2018년 12개월 기준 | Q28: Multiples
B29: Guideline Public Company | C29: Price [1] | D29: Outstanding[2] | E29: Market Cap | F29: Debt | G29: Cash[3] | H29: NOA[4] | I29: 비지배지분 | J29: EV | K29: BV | L29: Revenue | M29: EBIT | N29: Depreciation | O29: EBITDA | P29: Net Income | Q29: PBR | R29: EV/Revenue | S29: EV/EBIT | T29: EV/EBITDA | U29: PER
B30: Target(LG-Hitachi Water Solutions) | C30: N/A | D30: N/A | E30: N/A | F30: 0 | G30: 0 | H30: 0 | I30: 0 | J30: N/A | K30: =히타치_Dart!E37/10^6 -> 64527.186 | L30: =히타치_Dart!J5/10^6 -> 417764.4 | M30: =히타치_Dart!J11/10^6 -> 36889.577 | N30: =SUM(히타치_Dart!J61:J62)/10^3 -> 2568.313 | O30: =M30+N30 -> 39457.89 | P30: =히타치_Dart!J18/10^6 -> 20158.968
B31: 웰크론한텍 | C31: =웰크론한텍!T6 -> 2243.2203 | D31: =웰크론한텍!T10/10^3 -> 19362.573 | E31: =(D31*C31)/(10^3) -> 43434.518 | F31: =웰크론한텍!G6/10^6 -> 37145.171 | G31: =웰크론한텍!G3/10^6 -> 37121.01 | H31: =웰크론한텍!G10/10^6 -> 54434.514 | I31: =웰크론한텍!C73/10^6 -> 34084.049 | J31: =E31+F31-G31-H31+I31 -> 23108.213 | K31: =웰크론한텍!G16/10^6 -> 100151.62 | L31: =웰크론한텍!I31/10^6 -> 264346.51 | M31: =웰크론한텍!C5/10^6 -> 3443.4006 | N31: =웰크론한텍!C6/10^6 -> 967.24115 | O31: =웰크론한텍!C7/10^6 -> 4410.6417 | P31: =웰크론한텍!C8/10^6 -> 242.83676 | Q31: =E31/K31 -> 0.43368761 | R31: =J31/L31 -> 0.08741637 | S31: =J31/M31 -> 6.7108697 | T31: =J31/O31 -> 5.2391951 | U31: =E31/P31 -> 178.86303 | V31: =P31/D31*1000000 -> 12541.554 | W31: =RATE(2,0,-'2016'!V31,Summary!V31) -> #NUM!
B32: 삼부토건 | C32: =삼부토건!U3 -> 4904.5763 | D32: =삼부토건!U7/10^3 -> 24803.131 | E32: =(D32*C32)/(10^3) -> 121648.85 | F32: =삼부토건!G6/10^6 -> 106815.59 | G32: =삼부토건!G3/10^6 -> 116268.68 | H32: =삼부토건!G10/10^6 -> 66637.356 | I32: =삼부토건!C99/10^6 -> -6992.4369 | J32: =E32+F32-G32-H32+I32 -> 38565.961 | K32: =삼부토건!G16/10^6 -> 190254.57 | L32: =삼부토건!J25/10^6 -> 177427.23 | M32: =삼부토건!C5/10^6 -> -9369.4995 | N32: =삼부토건!C6/10^6 -> 454.891 | O32: =-삼부토건!C7/10^6 -> 8914.6085 | P32: =삼부토건!C8/10^6 -> -51492.807 | Q32: =E32/K32 -> 0.6394004 | R32: =J32/L32 -> 0.21736213 | S32: =J32/M32 -> -4.1161174 | T32: =J32/O32 -> 4.326153 | U32: =E32/P32 -> -2.3624435 | V32: =P32/D32*1000000 -> -2076060.8 | W32: =RATE(2,0,-'2016'!V32,Summary!V32) -> #NUM!
B33: 우원개발 | C33: =우원개발!X3 -> 5074.8305 | D33: =우원개발!X7/10^3 -> 17124.677 | E33: =(D33*C33)/(10^3) -> 86904.833 | F33: =우원개발!G6/10^6 -> 28869.473 | G33: =우원개발!G3/10^6 -> 25713.787 | H33: =우원개발!G10/10^6 -> 54733.618 | I33: 0 | J33: =E33+F33-G33-H33+I33 -> 35326.901 | K33: =우원개발!G16/10^6 -> 61891.502 | L33: =우원개발!J26/10^6 -> 218641.54 | M33: =우원개발!C5/10^6 -> 1436.2555 | N33: =우원개발!C6/10^6 -> 1314.2825 | O33: =우원개발!C7/10^6 -> 2750.5379 | P33: =우원개발!C8/10^6 -> -1444.6428 | Q33: =E33/K33 -> 1.4041481 | R33: =J33/L33 -> 0.16157452 | S33: =J33/M33 -> 24.59653 | T33: =J33/O33 -> 12.843634 | U33: =E33/P33 -> -60.156622 | V33: =P33/D33*1000000 -> -84360.297 | W33: =RATE(2,0,-'2016'!V33,Summary!V33) -> #NUM!
B34: 태영건설 | C34: =태영건설!O10 -> 12067.797 | D34: =태영건설!O14/10^3 -> 76400 | E34: =(D34*C34)/(10^3) -> 921979.66 | F34: =태영건설!G6 -> 1728674.6 | G34: =태영건설!G3 -> 539369.79 | H34: =태영건설!G11 -> 886059.96 | I34: =(태영건설!$C$85)/(10^6) -> 467916.59 | J34: =E34+F34-G34-H34+I34 -> 1693141.1 | K34: =태영건설!G19 -> 1482288.3 | L34: =태영건설!C4 -> 3850546 | M34: =태영건설!C5 -> 463519.91 | N34: =태영건설!C6 -> 67464.167 | O34: =태영건설!C7 -> 530984.07 | P34: =태영건설!C8 -> 244140.18 | Q34: =E34/K34 -> 0.62199754 | R34: =J34/L34 -> 0.43971454 | S34: =J34/M34 -> 3.6527905 | T34: =J34/O34 -> 3.1886853 | U34: =E34/P34 -> 3.7764355 | V34: =P34/D34*1000000 -> 3195552.1 | W34: =RATE(2,0,-'2016'!V34,Summary!V34) -> 10.603263
B35: 현대건설 | C35: =현대건설!O20 -> 57727.119 | D35: =현대건설!O24/10^3 -> 111355.76 | E35: =(D35*C35)/(10^3) -> 6428247.5 | F35: =현대건설!G6 -> 2400899 | G35: =현대건설!G3 -> 4066143 | H35: =현대건설!G11 -> 1169462 | I35: =현대건설!$C$94 -> 2017762 | J35: =E35+F35-G35-H35+I35 -> 5611303.5 | K35: =현대건설!G19 -> 8291856 | L35: =현대건설!C4 -> 16730894 | M35: =현대건설!C5 -> 839989 | N35: =현대건설!C6 -> 175573 | O35: =현대건설!C7 -> 1015562 | P35: =현대건설!C8 -> 535303 | Q35: =E35/K35 -> 0.77524832 | R35: =J35/L35 -> 0.33538575 | S35: =J35/M35 -> 6.6802106 | T35: =J35/O35 -> 5.5253185 | U35: =E35/P35 -> 12.008615 | V35: =P35/D35*1000000 -> 4807142.2 | W35: =RATE(2,0,-'2016'!V35,Summary!V35) -> -0.14467837
B36: 코오롱글로벌 | C36: =코오롱글로벌!Q20 -> 8598.6441 | D36: =코오롱글로벌!Q24/10^3 -> 25210.438 | E36: =(D36*C36)/(10^3) -> 216775.58 | F36: =코오롱글로벌!G6 -> 711660 | G36: =코오롱글로벌!G3 -> 82722.734 | H36: =코오롱글로벌!G11 -> 511292.84 | I36: =(코오롱글로벌!$C$72)/(10^6) -> 4097.9329 | J36: =E36+F36-G36-H36+I36 -> 338517.95 | K36: =코오롱글로벌!G18 -> 446731.38 | L36: =코오롱글로벌!C4 -> 3358253.4 | M36: =코오롱글로벌!C5 -> 76764.013 | N36: =코오롱글로벌!C6 -> 19458.894 | O36: =코오롱글로벌!C7 -> 96222.907 | P36: =코오롱글로벌!C8 -> 14451.16 | Q36: =E36/K36 -> 0.48524817 | R36: =J36/L36 -> 0.10080179 | S36: =J36/M36 -> 4.4098521 | T36: =J36/O36 -> 3.5180599 | U36: =E36/P36 -> 15.000567 | V36: =P36/D36*1000000 -> 573221.28 | W36: =RATE(2,0,-'2016'!V36,Summary!V36) -> 0.2440395
B37: 진흥기업 | C37: =진흥기업!Q20 -> 2040.7627 | D37: =진흥기업!Q24/10^3 -> 145471.74 | E37: =(D37*C37)/(10^3) -> 296873.31 | F37: =진흥기업!G6 -> 23703.636 | G37: =진흥기업!G3 -> 13320.055 | H37: =진흥기업!G11 -> 111114.32 | I37: 0 | J37: =E37+F37-G37-H37+I37 -> 196142.57 | K37: =진흥기업!G18 -> 78804.146 | L37: =진흥기업!C4 -> 671155.39 | M37: =진흥기업!C5 -> 35051.376 | N37: =진흥기업!C6 -> 397.3 | O37: =진흥기업!C7 -> 35448.676 | P37: =진흥기업!C8 -> 6053.4942 | Q37: =E37/K37 -> 3.7672296 | R37: =J37/L37 -> 0.29224614 | S37: =J37/M37 -> 5.5958594 | T37: =J37/O37 -> 5.5331424 | U37: =E37/P37 -> 49.041645 | V37: =P37/D37*1000000 -> 41612.852 | W37: =RATE(2,0,-'2016'!V37,Summary!V37) -> #NUM!
B38: 남광토건 | C38: =남광토건!Q20 -> 15253.39 | D38: =남광토건!Q24/10^3 -> 9827.396 | E38: =(D38*C38)/(10^3) -> 149901.1 | F38: =남광토건!G6 -> 9245.011 | G38: =남광토건!G3 -> 37821.764 | H38: =남광토건!G11 -> 35752.198 | I38: 0 | J38: =E38+F38-G38-H38+I38 -> 85572.151 | K38: =남광토건!G18 -> 49112.604 | L38: =남광토건!C4 -> 157172.93 | M38: =남광토건!C5 -> 11141.645 | N38: =남광토건!C6 -> 460.759 | O38: =남광토건!C7 -> 11602.404 | P38: =남광토건!C8 -> 5715.6746 | Q38: =E38/K38 -> 3.0521921 | R38: =J38/L38 -> 0.54444586 | S38: =J38/M38 -> 7.6803876 | T38: =J38/O38 -> 7.3753812 | U38: =E38/P38 -> 26.226318 | V38: =P38/D38*1000000 -> 581606.22 | W38: =RATE(2,0,-'2016'!V38,Summary!V38) -> #NUM!
B39: 세보엠이씨 | C39: =세보엠이씨!P69 -> 9984.9153 | D39: =세보엠이씨!P73/10^3 -> 10530 | E39: =(D39*C39)/(10^3) -> 105141.16 | F39: =세보엠이씨!C21 -> 11620 | G39: =세보엠이씨!C18 -> 19185.185 | H39: =세보엠이씨!C25 -> 9975.4092 | I39: =(세보엠이씨!$E$71)/(10^6) -> 529.14652 | J39: =E39+F39-G39-H39+I39 -> 88129.71 | K39: =세보엠이씨!C30 -> 158899.63 | L39: =세보엠이씨!C9 -> 473844.41 | M39: =세보엠이씨!C10 -> 27985.354 | N39: =세보엠이씨!C11 -> 4126.767 | O39: =M39+N39 -> 32112.121 | P39: =세보엠이씨!C13 -> 21156.52 | Q39: =E39/K39 -> 0.66168282 | R39: =J39/L39 -> 0.18598871 | S39: =J39/M39 -> 3.1491369 | T39: =J39/O39 -> 2.7444376 | U39: =E39/P39 -> 4.9696811 | V39: =P39/D39*1000000 -> 2009166.2 | W39: =RATE(2,0,-'2016'!V39,Summary!V39) -> 0.22636941
B42: 주요가정 Summary | O42: 국내 | P42: Mean | Q42: =AVERAGE(Q31:Q39) -> 1.3156483 | R42: =AVERAGE(R31:R39) -> 0.26277065 | S42: =AVERAGE(S31:S39) -> 6.4843911 | T42: =AVERAGE(T31:T39) -> 5.5882229 | U42: =AVERAGE(U31:U39) -> 25.263025
B43: [1] 주가 : 2019년 3월 31일 기준 3개월 평균 주가 | P43: Median | Q43: =MEDIAN(Q31:Q39) -> 0.66168282 | R43: =MEDIAN(R31:R39) -> 0.21736213 | S43: =MEDIAN(S31:S39) -> 5.5958594 | T43: =MEDIAN(T31:T39) -> 5.2391951 | U43: =MEDIAN(U31:U39) -> 12.008615
B44: [2] 발행주식수 2019년 3월 31일 발행 주식수 | P44: Max | Q44: =MAX(Q31:Q39) -> 3.7672296 | R44: =MAX(R31:R39) -> 0.54444586 | S44: =MAX(S31:S39) -> 24.59653 | T44: =MAX(T31:T39) -> 12.843634 | U44: =MAX(U31:U39) -> 178.86303
B45: [3] Cash : 2018년말 현금및현금성자산 및 단기금융상품 | P45: Min | Q45: =MIN(Q31:Q39) -> 0.43368761 | R45: =MIN(R31:R39) -> 0.08741637 | S45: =MIN(S31:S39) -> -4.1161174 | T45: =MIN(T31:T39) -> 2.7444376 | U45: =MIN(U31:U39) -> -60.156622
B46: [4] NoA : 2018년말 장기금융상품, 관계기업투자, 매도가능증권, 투자부동산, 매각예정자산, 장단기 대여금
B48: 비교 대상기업의 선정
B49: 1. 한국거래소 기업공시채널 KIND 시스템 상 제조업으로 등록된 상장회사 중, 주요 제품을 '건설업' 으로 조회. | Q49: 평균 Multiple
B50: 2. 선정회사 중 수처리, 오염저감시설 등 환경설비 건축과 거리가 먼 업종(예: 주택, 실내인테리어, 전기배선 등)회사 제외 | Q50: 구분 | R50: EV/Revenue | S50: EV/EBIT | T50: EV/EBITDA
B51: 3. 주식거래정지, 건설과 무관한 자회사 매출이 주가에 큰영향이 있는 등 비교가능성이 떨어지는 회사 제외 | Q51: HiEntech | R51: =AVERAGE(R8:R10) -> 2.8169268 | S51: =AVERAGE(S8:S10) -> 11.797935 | T51: =AVERAGE(T8:T10) -> 8.8038386
Q52: LHWS | R52: =AVERAGE(R31:R39) -> 0.26277065 | S52: =AVERAGE(S31:S39) -> 6.4843911 | T52: =AVERAGE(T31:T39) -> 5.5882229

Sheet 모집단 선정(HiEntech)
B2: 유사기업 선정
C4: 1. 모집단 선정
C6: 한국거래소 기업공시채널 KIND 시스템 상 수도, 하수 및 폐기물 처리, 원료 재생업으로 등록된 상장회사로 조회함.
D7: - 해당 방법에 따라 조회된 회사는 하기와 같음. | K7: 57.3
D8: > Source : http://kind.krx.co.kr/corpgeneral/corpList.do?method=loadInitPage
D10: 회사명 | E10: 종목코드 | F10: 업종 | G10: 주요제품 | H10: 상장일 | I10: 결산월 | J10: 대표자명 | K10: 홈페이지 | L10: 지역 | M10: 비고
D11: KG ETS | E11: 151860 | F11: 폐기물 처리업 | G11: 집단에너지(스팀), 산화동, 폐기물 소각 | H11: 41479 | I11: 12월 | J11: 엄기민 | K11: http://www.kgets.co.kr | L11: 경기도 | M11: 환경, 에너지 사업, 신소재 사업 바이오 사업으로 구성되며 환경, 에너지 사업부문이 차지하는 매출 비중은 59.4%임.
D12: 와이엔텍 | E12: 067900 | F12: 폐기물 처리업 | G12: 사업장폐기물중간및최종처리,전문건설,골재제조 | H12: 38709 | I12: 12월 | J12: 김연석, 박용하(각자 대표이사) | K12: http://www.y-entec.co.kr | L12: 전라남도 | M12: 서비스업, 운송, 제조업, 건설업으로 사업부문이 구분되어 있으며 이 중 서비스업에 속한 폐기물 처리 관련 매출이 31.8%를 차지함.
D13: 자연과환경 | E13: 043910 | F13: 환경 정화 및 복원업 | G13: 스테인레스파이프, 다공성식생블록,조경원예자재 | H13: 38674 | I13: 12월 | J13: 이병용 | K13: http://www.e-nne.co.kr | L13: 충청남도 | M13: 환경복원, 조경산업, 환경플랜트와 같이 친환경 사업을 주로 하는 회사임.
D14: 제넨바이오 | E14: 072520 | F14: 폐기물 처리업 | G14: 휴대폰윈도우 | H14: 38289 | I14: 12월 | J14: 이홍민, 김성주 | K14: http://gennbio.co.kr | L14: 대구광역시 | M14: 환경 사업부, 바이오 사업부로 구성되어 있으며 환경 사업부에서 제공하는 사업장 일반 및 지정 폐기물 매립 서비스가 매출의 98.2%를 차지함.
D15: 코엔텍 | E15: 029960 | F15: 폐기물 처리업 | G15: 산업폐기물 소각/매립처리 | H15: 38156 | I15: 12월 | J15: 이민석 | K15: http://www.koentec.co.kr | L15: 울산광역시 | M15: 사업부문이 전부 폐기물 처리 관련으로 소각 및 매립 부문으로 나뉘어져 있음.
D16: 인선이엔티 | E16: 060150 | F16: 폐기물 처리업 | G16: 건축폐기물처리 | H16: 37421 | I16: 12월 | J16: 이준길 | K16: http://www.insun.co.kr | L16: 경기도 | M16: 건설폐기물 중간처리, 폐기물 최종처리, 자동차재활용 등으로 사업부문이 구성되어 있으며, 이 중 폐기물 처리 관련 매출이 57.3%를 차지함.
D17: GMR머티리얼즈 | E17: 032860 | F17: 해체, 선별 및 원료 재생업 | G17: 철스크랩 | H17: 35615 | I17: 12월 | J17: 김동은 | K17: http://www.gmrmaterials.com | L17: 충청남도 | M17: 금속 및 비금속 원료재생사업과 방화문 제조, 판매 및 시공사업을 주된 사업으로 영위하고 있음.
D21: 모집단의 수 | E21: =COUNTA(E11:E17) -> 7
C23: 2. 유사회사 선정 기준
C25: 기준 Ⅰ. 전방산업 유사성
C27: 하이엔텍(대상회사) - 대상회사는 수질오염방지시설 및 하수처리시설의 관리, 운영 등을 주목적으로 하는 회사임
D28: - 대상회사의 전방산업인 하수 처리업으로 분류된 상장회사가 없으므로 대용으로 폐기물 처리업을 영위하는 회사를 선정
D29: - 자연과환경(환경 정화 및 복원업), GMR머티리얼즈(해체, 선별 및 원료 재생업)
D30: > 상기 2개 회사 제외
C32: 유사회사 선정 결과
D33: - 최초 모집단의 7개 대상회사에서 전방산업 유사성 및 비교가능성 고려를 통해 5개 회사를 유사회사로 선정함.
D35: 회사명 | E35: 종목코드 | F35: 업종 | G35: 주요제품 | H35: 상장일 | I35: 결산월 | J35: 대표자명 | K35: 홈페이지 | L35: 지역 | M35: 비고
D36: KG ETS | E36: 151860 | F36: 폐기물 처리업 | G36: 집단에너지(스팀), 산화동, 폐기물 소각 | H36: 41479 | I36: 12월 | J36: 엄기민 | K36: http://www.kgets.co.kr | L36: 경기도 | M36: 환경, 에너지 사업, 신소재 사업 바이오 사업으로 구성되며 환경, 에너지 사업부문이 차지하는 매출 비중은 59.4%임.
A37: 추가제외 | D37: 와이엔텍 | E37: 067900 | F37: 폐기물 처리업 | G37: 사업장폐기물중간및최종처리,전문건설,골재제조 | H37: 38709 | I37: 12월 | J37: 김연석, 박용하(각자 대표이사) | K37: http://www.y-entec.co.kr | L37: 전라남도 | M37: 서비스업, 운송, 제조업, 건설업으로 사업부문이 구분되어 있으며 이 중 서비스업에 속한 폐기물 처리 관련 매출이 31.8%를 차지함.
D38: 코엔텍 | E38: 029960 | F38: 폐기물 처리업 | G38: 산업폐기물 소각/매립처리 | H38: 38156 | I38: 12월 | J38: 이민석 | K38: http://www.koentec.co.kr | L38: 울산광역시 | M38: 사업부문이 전부 폐기물 처리 관련으로 소각 및 매립 부문으로 나뉘어져 있음.
D39: 인선이엔티 | E39: 060150 | F39: 폐기물 처리업 | G39: 건축폐기물처리 | H39: 37421 | I39: 12월 | J39: 이준길 | K39: http://www.insun.co.kr | L39: 경기도 | M39: 건설폐기물 중간처리, 폐기물 최종처리, 자동차재활용 등으로 사업부문이 구성되어 있으며, 이 중 폐기물 처리 관련 매출이 57.3%를 차지함.
D40: 제넨바이오 | E40: 072520 | F40: 폐기물 처리업 | G40: 휴대폰윈도우 | H40: 38289 | I40: 12월 | J40: 이홍민, 김성주 | K40: http://gennbio.co.kr | L40: 대구광역시 | M40: 환경 사업부, 바이오 사업부로 구성되어 있으며 환경 사업부에서 제공하는 사업장 일반 및 지정 폐기물 매립 서비스가 매출의 98.2%를 차지함.

Sheet 모집단 선정(LHWS)
B2: 유사기업 선정
C4: 1. 모집단 선정
C6: 한국거래소 기업공시채널 KIND 시스템 상 제조업으로 등록된 상장회사 중, 주요 제품을 '건설업' 으로 조회함.
D7: - 해당 방법에 따라 조회된 회사는 하기와 같음.
D8: > Source : http://kind.krx.co.kr/corpgeneral/corpList.do?method=loadInitPage
D10: 회사명 | E10: 종목코드 | F10: 업종 | G10: 주요제품 | H10: 상장일 | I10: 결산월 | J10: 대표자명 | K10: 홈페이지 | L10: 지역 | M10: 비고
D11: 금호산업 | E11: 002990 | F11: 건물 건설업 | G11: 종합건설/여객운송,관광/부동산 임대,분양 | H11: 27937 | I11: 12월 | J11: 서재환 | K11: http://www.kumhoenc.com | L11: 전라남도 | M11: 금호아시아나의 모회사로 주가가 아시아나항공 실적에 큰영향을 받음
D12: 삼부토건 | E12: 001470 | F12: 토목 건설업 | G12: 토목공사,건축공사,포장공사,건설업,분양사업/건설자재 제조 | H12: 27937 | I12: 12월 | J12: 이응근 | K12: http://www.sambu.co.kr | L12: 서울특별시
D13: 대림산업 | E13: 000210 | F13: 토목 건설업 | G13: 산업플랜트공사,건축,토목,폴리에틸렌,폴리부텐,각종폴리머 제조,기술용역 | H13: 27792 | I13: 12월 | J13: 김상우, 박상신 (각자 대표이사) | K13: http://www.daelim.co.kr | L13: 서울특별시
D14: 대원 | E14: 007680 | F14: 건물 건설업 | G14: 아파트 시행 및 시공 | H14: 43070 | I14: 12월 | J14: 전응식 | K14: http://daewon.co.kr | L14: 충청북도 | M14: 아파트건설업을 주업
D15: 이엑스티 | E15: 226360 | F15: 토목 건설업 | G15: 기업인수합병 | H15: 42299 | I15: 12월 | J15: 강정식 | L15: 서울특별시 | M15: 지질기반공사를 주업
D16: 남화토건 | E16: 091590 | F16: 건물 건설업 | G16: 건축공사, 토목공사 | H16: 40939 | I16: 12월 | J16: 최상준, 최재훈 | K16: http://www.namhwaconst.co.kr | L16: 전라남도 | M16: SOC(도로, 항만) 및 주택 등 토건업을 주업
D17: 웰크론한텍 | E17: 076080 | F17: 건물 건설업 | G17: 에너지절감설비,자동화배합설비,환경설비 | H17: 39647 | I17: 12월 | J17: 이영규, 이기창, 이영식 | K17: http://www.welcronhantec.co.kr | L17: 경기도
D18: 일진파워 | E18: 094820 | F18: 전기 및 통신 공사업 | G18: 열교환기,압력용기 | H18: 39392 | I18: 12월 | J18: 이광섭 | K18: http://ijeng.com | L18: 울산광역시 | M18: 한전등 전력회사 경상정비 및 유지보수 매출 58%, 화공/플랜트 37%
D19: 코드네이처 | E19: 078940 | F19: 전기 및 통신 공사업 | G19: 전기공사업 | H19: 38226 | I19: 12월 | J19: 박상훈 | K19: http://codenature.com | L19: 서울특별시 | M19: 2019년5월8일 현재 거래정지
D20: 에너전트 | E20: 041590 | F20: 건물설비 설치 공사업 | G20: 에너지저장시스템, 액정표시장치 | H20: 37561 | I20: 12월 | J20: 김상재, 최영석(각자대표) | K20: http://www.enerzent.com | L20: 대전광역시 | M20: 냉난방 설비공사 주업
D21: 국보디자인 | E21: 066620 | F21: 실내건축 및 건축마무리 공사업 | G21: 인테리어디자인 | H21: 37504 | I21: 12월 | J21: 황창연 | K21: http://www.ikukbo.com | L21: 서울특별시 | M21: 실내 인테리어업 주업
D22: 우원개발 | E22: 046940 | F22: 기반조성 및 시설물 축조관련 전문공사업 | G22: 토공사 | H22: 37425 | I22: 12월 | J22: 김기영 | K22: http://www.woowonerd.com | L22: 서울특별시
D23: KT서브마린 | E23: 060370 | F23: 전기 및 통신 공사업 | G23: 해저케이블등의 건설 및 유지보수 업무 | H23: 37302 | I23: 12월 | J23: 이철규 | K23: http://www.ktsubmarine.co.kr | L23: 부산광역시 | M23: 해저케이블 등 전기통신공사
D24: 엑사이엔씨 | E24: 054940 | F24: 실내건축 및 건축마무리 공사업 | G24: 고주파고압변성기(FBT : Flyback Transformer) | H24: 37238 | I24: 12월 | J24: 구자극, 원종일 (각자 대표이사) | K24: http://www.exaenc.com | L24: 서울특별시 | M24: 실내건축업
D25: 까뮤이앤씨 | E25: 013700 | F25: 건물 건설업 | G25: 토목공사,건축공사/부동산 임대 | H25: 32842 | I25: 12월 | J25: 손병재 | K25: http://www.camusenc.com | L25: 경기도 | M25: 플랜트x
D26: 태영건설 | E26: 009410 | F26: 토목 건설업 | G26: 종합건설업(토목공사,도로공사,건축공사,관급공사,환경공사,상하수도공사,하수종말처리공사)/부동산 임대,매매 | H26: 32825 | I26: 12월 | J26: 이재규 | K26: http://www.taeyoung.com | L26: 경기도 | M26: 환경 플랜트
D27: 화성산업 | E27: 002460 | F27: 건물 건설업 | G27: 아파트 건설 | H27: 32415 | I27: 12월 | J27: 이홍중,이종원 | K27: http://www.hwasung.com | L27: 대구광역시 | M27: 환경/신재생에너지 플랜트
D28: 범양건영 | E28: 002410 | F28: 건물 건설업 | G28: 토목공사,주택건설,건축공사,난방공사,전기공사,포장공사 | H28: 32288 | I28: 12월 | J28: 강병주 | K28: http://www.iby.co.kr | L28: 충청남도 | M28: 환경 플랜트의 주요사업은 2015년에 종료
D29: 현대건설 | E29: 000720 | F29: 토목 건설업 | G29: 공사수입,주택분양,건설산업부문 설계,감리 등 엔지니어링서비스 | H29: 31038 | I29: 12월 | J29: 박동욱 | K29: http://www.hdec.kr | L29: 서울특별시 | M29: 정유, 가스, 석유화학, 담수 플랜트
D30: GS건설 | E30: 006360 | F30: 건물 건설업 | G30: 토목공사,건축공사,주택공사,산업플랜트공사,리모델링공사,시설물유지관리공사/산업설비설계,감리 용역,수출입/에너지관리 진단,연구개발 | H30: 29801 | I30: 12월 | J30: 허창수, 임병용(각자 대표이사) | K30: http://www.gsconst.co.kr/ | L30: 서울특별시 | M30: 정유, 가스, 석유화학, 환경 플랜트
D31: 고려개발 | E31: 004200 | F31: 토목 건설업 | G31: 도로건설공사,토목공사,건축공사 | H31: 28793 | I31: 12월 | J31: 곽수윤 | K31: http://www.kdc.co.kr | L31: 경기도 | M31: 플랜트x
D32: 동부건설 | E32: 005960 | F32: 토목 건설업 | G32: 건축공사,토목공사,전기공사,기계설비공사/비금속,철구조물 제조,판매/여객,자동차 운송,항만하역 | H32: 28793 | I32: 12월 | J32: 허상희 | K32: http://dbcon.dongbu.co.kr | L32: 서울특별시 | M32: 환경/에너지 등 플랜트
D33: 코오롱글로벌 | E33: 003070 | F33: 토목 건설업 | G33: 토목공사,일반건설,주택건설,해외건설,소각로설비공사/환경플랜트,폐처리기 제조 | H33: 28748 | I33: 12월 | J33: 윤창운 | K33: http://www.kolonglobal.com | L33: 경기도 | M33: 화학 플랜트
D34: 신한 | E34: 005450 | F34: 건물 건설업 | G34: 건축공사,토목공사,전기공사,통신공사,주택건설,기계설비공사,철골공사/철구조물 제조 | H34: 28699 | I34: 12월 | J34: 조경선 | K34: http://www.seco.co.kr | L34: 경기도 | M34: 정유, 담수화, 발전소 플랜트
... D41: 상지카일룸 | E41: 042940 | F41: 건물 건설업 | G41: 정보통신망 구축, DVR, ITS, 기타방송장비 등 | H41: 36818 | I41: 12월 | J41: 최기보 | K41: http://www.sangji.co.kr/ | L41: 서울특별시 | M41: 일부 플랜트 수행
D42: KD건설 | E42: 044180 | F42: 건물 건설업 | G42: 몰드베이스(Mold Base) | H42: 36846 | I42: 12월 | J42: 안태일 | K42: http://dymoldtech.co.kr | L42: 경기도
D43: 이테크건설 | E43: 016250 | F43: 건물 건설업 | G43: 건축공사, 플랜트설비, 토목공사 | H43: 36522 | I43: 12월 | J43: 이복영, 안찬규 | K43: http://www.etecenc.com | L43: 서울특별시 | M43: 일부 플랜트 수행
D44: 서희건설 | E44: 035890 | F44: 건물 건설업 | G44: 토목, 건축, 부동산임대업 | H44: 36518 | I44: 12월 | J44: 곽선기,김팔수 | K44: http://www.seohee.co.kr | L44: 경기도 | M44: 플랜트 매출 미미[1]; 제외
D45: 특수건설 | E45: 026150 | F45: 토목 건설업 | G45: 보링 | H45: 35648 | I45: 12월 | J45: 김중헌, 김도헌 (각자 대표이사) | K45: http://www.tuksu.co.kr | L45: 서울특별시 | M45: TBM Shield 로 일반적인 플랜트가 아님; 제외
D46: 세보엠이씨 | E46: 011560 | F46: 건물설비 설치 공사업 | G46: 건설관련설비, ACESS FLOOR , 소음기 , CHAMMBER , PFP UNIT, BY-PASS UNIT , DUCT , 철구조물 . | H46: 35422 | I46: 12월 | J46: 김우영, 김진호(각자 대표이사) | K46: http://www.sebo21.co.kr | L46: 서울특별시 | M46: 일부 플랜트 수행
D47: 동신건설 | E47: 025950 | F47: 토목 건설업 | G47: 토목 | H47: 34918 | I47: 12월 | J47: 김근한,김동한 | K47: - | L47: 경상북도 | M47: 플랜트 공사 수행하지 아니함; 제외
D48: 동원개발 | E48: 013120 | F48: 건물 건설업 | G48: 도급공사 | H48: 34697 | I48: 12월 | J48: 장복만 | K48: http://www.dongwonapt.co.kr | L48: 부산광역시 | M48: 플랜트 공사 수행하지 아니함; 제외
D49: 신원종합개발 | E49: 017000 | F49: 건물 건설업 | G49: 토건 | H49: 34675 | I49: 12월 | J49: 우진호 | K49: http://www.swc.co.kr | L49: 경기도 | M49: 플랜트 공사 수행하지 아니함; 제외
D50: 이화공영 | E50: 001840 | F50: 건물 건설업 | G50: 도급공사 | H50: 34661 | I50: 12월 | J50: 최삼규,최종찬 | K50: http://www.ee-hwa.co.kr | L50: 서울특별시 | M50: 플랜트 매출 미미[1]; 제외
D51: 서한 | E51: 011370 | F51: 건물 건설업 | G51: 건축, 토목 | H51: 34478 | I51: 12월 | J51: 조 종 수 | K51: http://www.seo-han.co.kr | L51: 대구광역시 | M51: 플랜트 매출 미미[1]; 제외
D52: 삼일기업공사 | E52: 002290 | F52: 건물 건설업 | G52: 도급공사 | H52: 33938 | I52: 12월 | J52: 박종웅 | K52: http://www.samilenter.com | L52: 서울특별시 | M52: 일부 플랜트 수행
D53: 우진아이엔에스 | E53: 010400 | F53: 건물설비 설치 공사업 | G53: 반도체/디스플레이 코팅덕트 | H53: 43357 | I53: 12월 | J53: 홍평우 | K53: http://www.woojini.com | L53: 서울특별시 | M53: 건축물에 투입되는 다양한 코팅 배관 등을 제작 설치하는 업체로 LWHS와의 연관성 낮음.
D54: HDC현대산업개발 | E54: 294870 | F54: 건물 건설업 | G54: 외주주택, 자체공사, 일반건축, 토목 등 | H54: 43263 | I54: 12월 | J54: 김대철,권순호 | K54: http://www.hdc-dvp.com | L54: 서울특별시 | M54: 종합건설회사로 일부 플랜트 설립업도 겸하고 있으나 2018년 5월초 인적분할로 설립.
D55: HDC아이콘트롤스 | E55: 039570 | F55: 전기 및 통신 공사업 | G55: 기계설비공사, 스마트홈, 지능형 빌딩, SOC | H55: 42271 | I55: 12월 | J55: 김성은 | K55: http://www.icontrols.co.kr | L55: 경기도 | M55: 홈네트워크, 자동제어 등 건축물 등에 투입되는 자동화 장비 등을 설계 등을 하고 있음. LWHS와의 연관성 낮음.
D56: 동아지질 | E56: 028100 | F56: 기반조성 및 시설물 축조관련 전문공사업 | G56: 보링그라우팅공사,토공사,철근콘크리트공사,상하수도공사,비계구조물해체공사,수중공사/지질조사,시공감리 | H56: 39976 | I56: 12월 | J56: 이정우, 최재우 | K56: http://www.dage.co.kr | L56: 부산광역시 | M56: 터널(TBM), 지반 강화 등의 지질 공사를 주력 사업으로 하는 업체로 LWHS와의 연관성 낮음.
D57: 한전KPS | E57: 051600 | F57: 전기 및 통신 공사업 | G57: 일반전기공사,발전설비정비공사,점검,수리,엔지니어링 | H57: 39430 | I57: 12월 | J57: 김범년 | K57: http://www.kps.co.kr | L57: 전라남도 | M57: 한국전력 자회사로 발전설비 유지정비를 주된 사업으로 하는 회사로 LWHS와의 연관성은 낮음.
D58: 한진중공업 | E58: 097230 | F58: 토목 건설업 | G58: 선박건조,기계플랜트 제조/토목공사,건축공사,조경공사,전기공사,가스공사,준설공사,기계설비공사 | H58: 39325 | I58: 12월 | J58: 이병모 | K58: http://www.hanjinsc.com | L58: 부산광역시 | M58: 조선, 건설업을 영위하는 회사로 건설부문 중 플랜트가 포함되어 있으나 수주잔고 기준으로 환경 플랜트는 1% 수준으로 미미함.
D59: 삼호개발 | E59: 010960 | F59: 기반조성 및 시설물 축조관련 전문공사업 | G59: 토공사,철근콘크리트공사,포장공사,미장방수공사,상하수도공사,수중공사,비계구조물해체공사/골재,아스콘 제조,판매,중기임대 | H59: 38484 | I59: 12월 | J59: 김락중, 심재범 | K59: http://www.samhodev.co.kr/ | L59: 충청남도 | M59: 종합건설회사로 수처리 관련 플랜트 시공실적이 있으나 수주잔고 기준으로 환경 플랜트는 1.1%로 미미한 수준임.
D60: 신세계건설 | E60: 034300 | F60: 건물 건설업 | G60: 토목,건축,건축관련기술서비스,빌딩관리용역,골프장,내장공사,시설개보수,설계용역 | H60: 37424 | I60: 12월 | J60: 윤명규 | K60: http://httpswww.shinsegae-enc.com | L60: 서울특별시 | M60: 종합건설회사로 수처리 관련 플랜트 시공실적이 있으나 수주잔고 기준으로 환경 플랜트는 현재 아예 없음.
D61: 대우건설 | E61: 047040 | F61: 건물 건설업 | G61: 아파트건설,토목공사,건축공사,포장공사,전기공사,무역/중장비 대여 | H61: 36973 | I61: 12월 | J61: 김형 | K61: http://daewooenc.co.kr | L61: 서울특별시 | M61: 플랜트의 경우, 석유화확, 발전, 원자력, 산업설비 등을 영위하나 수주잔고가 없음.
D62: 에쓰씨엔지니어링 | E62: 023960 | F62: 토목 건설업 | G62: 기술용역(건축설계) 서비스/화학플랜트 설비,기계 제작(음식료,석유화학사업관련)/유공압기기 판매 | H62: 35604 | I62: 12월 | J62: 장정호 | K62: http://www.sc-eng.com | L62: 서울특별시 | M62: 화공플랜트 전문회사로 이외에도 소재, 산업, 에너지 플랜트를 사업을 영위하는 회사임.
D63: 계룡건설산업 | E63: 013580 | F63: 토목 건설업 | G63: 건축공사,주택공사,토목공사,포장공사,전기공사 | H63: 35094 | I63: 12월 | J63: 한승구, 이승찬 | K63: http://www.krcon.co.kr | L63: 대전광역시 | M63: 종합건설회사로 플랜트 사업 중 발전, 에너지, 산업설비, 환경 등을 영위하나, 환경 플랜트는 수주잔고 기준에서 미미함.
D64: 두산건설 | E64: 011160 | F64: 건물 건설업 | G64: 토목건축,화학기계,전동기,발전기및전기변환장치,레미콘 | H64: 35094 | I64: 12월 | J64: 이병화, 김진설(각자 대표이사) | K64: http://www.doosanenc.com | L64: 서울특별시 | M64: 토목, 건축업을 영위하는 회사로 LWHS와의 연관성이 낮음.
D65: 한라 | E65: 014790 | F65: 토목 건설업 | G65: 토목,건축,전기,환경사업,준설공사,포장공사,주택,중기임대 | H65: 34558 | I65: 12월 | J65: 이석민 | K65: http://www.halla.co.kr | L65: 서울특별시 | M65: 종합건설회사로 토목, 건축, 주택, 플랜트/환경사업, 비건설 등을 영위하지만 수주잔고 기준에서는 환경 플랜트는 1%대의 미미한 수준임.
D66: 일성건설 | E66: 013360 | F66: 토목 건설업 | G66: 건축공사,토목공사,전기공사 | H66: 32844 | I66: 12월 | J66: 강영길 | K66: http://www.ilsungconst.co.kr | L66: 인천광역시 | M66: 종합건설회사로 주택, 건축, 토목, 환경 플랜트 등을 영위하는 회사임.
D69: 모집단의 수 | E69: =COUNTA(E11:E66) -> 56
C71: 2. 유사회사 선정 기준
C73: 기준 Ⅰ. 전방산업 유사성
C75: LHWS(대상회사) - 대상회사는 수처리 설비의 설계 및 건축을 주업으로 하는 회사로, 전방산업은 수처리 운영업임.
D76: - 대상회사의 주된 매출활동과 거리가 먼 아파트, 전기설비건설업, 실내인테리어업 등 제외함.
D77: - 대원, 이엑스티, 남화토건 등
D78: > 34개 회사 제외
C80: 기준 Ⅱ. 비교가능성
C82: 주식거래정지, 건설과 무관한 자회사 매출이 주가에 큰영향이 있는 등 비교가능성이 떨어지는 회사 제외
D83: - 코드네이처 : 2019년 3월 거래정지(업종: 전기공사업)
D84: - 금호산업: 아시아나항공의 모회사로 주가가 아시아나항공 실적에 큰영향을 받음
D85: > 상기 2개 회사 제외
C87: 유사회사 선정 결과
D88: - 최초 모집단의 56개 대상회사에서 전방산업 유사성 등을 통해 20개 회사를 유사회사로 선정함.
D90: 회사명 | E90: 종목코드 | F90: 업종 | G90: 주요제품 | H90: 상장일 | I90: 결산월 | J90: 대표자명 | K90: 홈페이지 | L90: 지역 | M90: 비고
D91: 삼부토건 | E91: 001470 | F91: 토목 건설업 | G91: 토목공사,건축공사,포장공사,건설업,분양사업/건설자재 제조 | H91: 27937 | I91: 12월 | J91: 이응근 | K91: http://www.sambu.co.kr | L91: 서울특별시
D92: 대림산업 | E92: 000210 | F92: 토목 건설업 | G92: 산업플랜트공사,건축,토목,폴리에틸렌,폴리부텐,각종폴리머 제조,기술용역 | H92: 27792 | I92: 12월 | J92: 김상우, 박상신 (각자 대표이사) | K92: http://www.daelim.co.kr | L92: 서울특별시
D93: 웰크론한텍 | E93: 076080 | F93: 건물 건설업 | G93: 에너지절감설비,자동화배합설비,환경설비 | H93: 39647 | I93: 12월 | J93: 이영규, 이기창, 이영식 | K93: http://www.welcronhantec.co.kr | L93: 경기도
D94: 우원개발 | E94: 046940 | F94: 기반조성 및 시설물 축조관련 전문공사업 | G94: 하천/항만 토목공사 전문 | H94: 37425 | I94: 12월 | J94: 김기영 | K94: http://www.woowonerd.com | L94: 서울특별시
D95: 태영건설 | E95: 009410 | F95: 토목 건설업 | G95: 종합건설업(토목공사,도로공사,건축공사,관급공사,환경공사,상하수도공사,하수종말처리공사)/부동산 임대,매매 | H95: 32825 | I95: 12월 | J95: 이재규 | K95: http://www.taeyoung.com | L95: 경기도 | M95: 환경 플랜트
D96: 화성산업 | E96: 002460 | F96: 건물 건설업 | G96: 아파트 건설 | H96: 32415 | I96: 12월 | J96: 이홍중,이종원 | K96: http://www.hwasung.com | L96: 대구광역시 | M96: 환경/신재생에너지 플랜트
D97: 현대건설 | E97: 000720 | F97: 토목 건설업 | G97: 공사수입,주택분양,건설산업부문 설계,감리 등 엔지니어링서비스 | H97: 31038 | I97: 12월 | J97: 박동욱 | K97: http://www.hdec.kr | L97: 서울특별시 | M97: 정유, 가스, 석유화학, 담수 플랜트
D98: GS건설 | E98: 006360 | F98: 건물 건설업 | G98: 토목공사,건축공사,주택공사,산업플랜트공사,리모델링공사,시설물유지관리공사/산업설비설계,감리 용역,수출입/에너지관리 진단,연구개발 | H98: 29801 | I98: 12월 | J98: 허창수, 임병용(각자 대표이사) | K98: http://www.gsconst.co.kr/ | L98: 서울특별시 | M98: 정유, 가스, 석유화학, 환경 플랜트
D99: 동부건설 | E99: 005960 | F99: 토목 건설업 | G99: 건축공사,토목공사,전기공사,기계설비공사/비금속,철구조물 제조,판매/여객,자동차 운송,항만하역 | H99: 28793 | I99: 12월 | J99: 허상희 | K99: http://dbcon.dongbu.co.kr | L99: 서울특별시 | M99: 환경/에너지 등 플랜트
D100: 코오롱글로벌 | E100: 003070 | F100: 토목 건설업 | G100: 토목공사,일반건설,주택건설,해외건설,소각로설비공사/환경플랜트,폐처리기 제조 | H100: 28748 | I100: 12월 | J100: 윤창운 | K100: http://www.kolonglobal.com | L100: 경기도 | M100: 화학 플랜트
D101: 진흥기업 | E101: 002780 | F101: 토목 건설업 | G101: 아파트건설,토목공사,건축공사,국내도급공사 | H101: 28301 | I101: 12월 | J101: 노재봉 | K101: http://www.chinhung.co.kr | L101: 인천광역시 | M101: 환경/공업 플랜트
D102: 남광토건 | E102: 001260 | F102: 토목 건설업 | G102: 토목공사,건축공사,기전공사,측량설계시공,용역/철구조물 제조 | H102: 28122 | I102: 12월 | J102: 김종오 | K102: http://www.namkwang.co.kr | L102: 경기도 | M102: 석유화학/발전소/환경 플랜트
D103: KCC건설 | E103: 021320 | F103: 건물 건설업 | G103: 토목 건축공사, 분양공사 | H103: 37124 | I103: 12월 | J103: 정몽열,윤희영 | K103: http://www.kccworld.net | L103: 서울특별시 | M103: 일부 플랜트 수행
D104: 금화피에스시 | E104: 036190 | F104: 전기 및 통신 공사업 | G104: 설비,철물,전기,강구조물 | H104: 36886 | I104: 12월 | J104: 김경태 | K104: http://www.geumhwa.co.kr | L104: 서울특별시 | M104: 일부 플랜트 수행
D105: 상지카일룸 | E105: 042940 | F105: 건물 건설업 | G105: 정보통신망 구축, DVR, ITS, 기타방송장비 등 | H105: 36818 | I105: 12월 | J105: 최기보 | K105: http://www.sangji.co.kr/ | L105: 서울특별시 | M105: 일부 플랜트 수행
D106: 이테크건설 | E106: 016250 | F106: 건물건설업 | G106: 건축공사, 플랜트설비, 토목공사 | H106: 36522 | I106: 12월 | J106: 이복영, 안찬규 | K106: http://www.etecenc.com | L106: 서울특별시 | M106: 일부 플랜트 수행
... D110: 일성건설 | E110: 013360 | F110: 토목 건설업 | G110: 건축공사,토목공사,전기공사 | H110: 32844 | I110: 12월 | J110: 강영길 | K110: http://www.ilsungconst.co.kr | L110: 인천광역시 | M110: 종합건설회사로 주택, 건축, 토목, 환경 플랜트 등을 영위하는 회사임.

Sheet GPCM
A1: Project All
A2: Guideline Public Company Method
A3: (Unit : KRW million, unless otherwise noted)
B5: HiEntech | P5: 2018년 12개월 기준 | V5: Multiples
B6: 백만원 | C6: 국가 | D6: 산업 | F6: 업종상세 | G6: 상장구분 | H6: Price (*1) | I6: Outstanding | J6: Market Cap | K6: Debt | L6: Cash | M6: NOA | N6: 비지배지분 | O6: EV | P6: BV | Q6: Revenue | R6: EBIT | S6: Depreciation | T6: EBITDA | U6: Net Income | V6: PBR | W6: EV/Revenue | X6: EV/EBIT | Y6: EV/EBITDA | Z6: PER | AA6: 사용여부 | AB6: 제외사유
B7: Target(HiEntech) | C7: 대한민국 | E7: 비상장 | G7: N/A | H7: N/A | I7: N/A | J7: N/A | K7: 0 | L7: 0 | M7: 0 | N7: 0 | O7: N/A | P7: =하이엔텍_Dart!E47/10^6 -> 35747.682 | Q7: =하이엔텍_Dart!J5/10^6 -> 155484.44 | R7: =하이엔텍_Dart!J9/10^6 -> 10219.599 | S7: =SUM(하이엔텍_Dart!J37:J38)/10^3 -> 513.603 | T7: =R7+S7 -> 10733.202 | U7: =하이엔텍_Dart!J16/10^6 -> 8449.3759
B8: ='모집단 선정(HiEntech)'!D36 -> KG ETS | C8: 대한민국 | D8: ='모집단 선정(HiEntech)'!F36 -> 폐기물 처리업 | E8: 상장 | F8: ='모집단 선정(HiEntech)'!G36 -> 집단에너지(스팀), 산화동, 폐기물 소각 | G8: 코스닥 | H8: ='KG ETS'!$N$3 -> 3393.3898 | I8: ='KG ETS'!$V$23/10^3 -> 36000 | J8: =(I8*H8)/1000 -> 122162.03 | K8: ='KG ETS'!$C$6 -> 49214.628 | L8: ='KG ETS'!$C$3 -> 7901.0237 | M8: ='KG ETS'!$C$10 -> 79987.286 | N8: 0 | O8: =J8+K8-L8-M8+N8 -> 83488.353 | P8: ='KG ETS'!$C$15 -> 150131.06 | Q8: ='KG ETS'!$H$4 -> 123739.77 | R8: ='KG ETS'!$H$5 -> 13642.63 | S8: ='KG ETS'!$H$6 -> 8488.226 | T8: =R8+S8 -> 22130.856 | U8: ='KG ETS'!$H$8 -> 11266.355 | V8: =J8/P8 -> 0.81370258 | W8: =O8/Q8 -> 0.67470911 | X8: =O8/R8 -> 6.1196671 | Y8: =O8/T8 -> 3.7724864 | Z8: =J8/U8 -> 10.843084 | AA8: X | AB8: 주요 관계기업투자에 인터넷뉴스(이데일리)광고업을 영위하는 회사가 있어 있어 폐기물 처리업만의 주가 산정에 왜곡
B9: ='모집단 선정(HiEntech)'!D37 -> 와이엔텍 | C9: 대한민국 | D9: ='모집단 선정(HiEntech)'!F37 -> 폐기물 처리업 | E9: 상장 | F9: ='모집단 선정(HiEntech)'!G37 -> 사업장폐기물중간및최종처리,전문건설,골재제조 | G9: 코스닥 | H9: =와이엔텍!$N$3 -> 5768.5593 | I9: =와이엔텍!$V$23/10^3 -> 18199.659 | J9: =(I9*H9)/1000 -> 104985.81 | K9: =와이엔텍!$C$6 -> 75272.804 | L9: =와이엔텍!$C$3 -> 14407.688 | M9: =와이엔텍!$C$10 -> 4096.857 | N9: 0 | O9: =J9+K9-L9-M9+N9 -> 161754.07 | P9: =와이엔텍!$C$15 -> 116581.79 | Q9: =와이엔텍!$H$4 -> 76070.963 | R9: =와이엔텍!$H$5 -> 14934.316 | S9: =와이엔텍!$H$6 -> 6461.887 | T9: =R9+S9 -> 21396.203 | U9: =와이엔텍!$H$8 -> 9033.2051 | V9: =J9/P9 -> 0.90053358 | W9: =O9/Q9 -> 2.1263576 | X9: =O9/R9 -> 10.831033 | Y9: =O9/T9 -> 7.5599428 | Z9: =J9/U9 -> 11.622211 | AA9: O
B10: ='모집단 선정(HiEntech)'!D38 -> 코엔텍 | C10: 대한민국 | D10: ='모집단 선정(HiEntech)'!F38 -> 폐기물 처리업 | E10: 상장 | F10: ='모집단 선정(HiEntech)'!G38 -> 산업폐기물 소각/매립처리 | G10: 코스닥 | H10: =코엔텍!$N$3 -> 7877.4576 | I10: =코엔텍!$V$23/10^3 -> 50000 | J10: =(I10*H10)/1000 -> 393872.88 | K10: =코엔텍!$C$6 -> 25805.2 | L10: =코엔텍!$C$3 -> 92869.832 | M10: =코엔텍!$C$10 -> 1950.9296 | N10: =코엔텍!C66/10^6 -> 7.545629 | O10: =J10+K10-L10-M10+N10 -> 324864.87 | P10: =코엔텍!$C$15 -> 148686.38 | Q10: =코엔텍!$H$4 -> 72239.031 | R10: =코엔텍!$H$5 -> 29310.888 | S10: =코엔텍!$H$6 -> 10092.323 | T10: =R10+S10 -> 39403.211 | U10: =코엔텍!$H$8 -> 24489.206 | V10: =J10/P10 -> 2.6490179 | W10: =O10/Q10 -> 4.4970823 | X10: =O10/R10 -> 11.083419 | Y10: =O10/T10 -> 8.2446291 | Z10: =J10/U10 -> 16.08353 | AA10: O
B11: ='모집단 선정(HiEntech)'!D39 -> 인선이엔티 | C11: 대한민국 | D11: ='모집단 선정(HiEntech)'!F39 -> 폐기물 처리업 | E11: 상장 | F11: ='모집단 선정(HiEntech)'!G39 -> 건축폐기물처리 | G11: 코스닥 | H11: =인선이엔티!$O$3 -> 6996.2712 | I11: =인선이엔티!$W$23/10^3 -> 36605.043 | J11: =(I11*H11)/1000 -> 256098.81 | K11: =인선이엔티!$C$6 -> 90603.868 | L11: =인선이엔티!$C$3 -> 26968.662 | M11: =인선이엔티!$C$10 -> 2785.2241 | N11: =인선이엔티!C46/10^6 -> 4580.8354 | O11: =J11+K11-L11-M11+N11 -> 321529.63 | P11: =인선이엔티!$C$15 -> 186940.06 | Q11: =인선이엔티!$H$4 -> 175954.97 | R11: =인선이엔티!$H$5 -> 23853.49 | S11: =인선이엔티!$H$6 -> 6459.635 | T11: =R11+S11 -> 30313.125 | U11: =인선이엔티!$H$8 -> 19964.863 | V11: =J11/P11 -> 1.3699514 | W11: =O11/Q11 -> 1.8273405 | X11: =O11/R11 -> 13.479353 | Y11: =O11/T11 -> 10.606944 | Z11: =J11/U11 -> 12.827476 | AA11: O
B12: 제넨바이오 | C12: 대한민국 | D12: 폐기물 처리업 | E12: 상장 | F12: 폐기물처리 | G12: 코스닥 | H12: =제넨바이오!$N$3 -> 1730.9322 | I12: =제넨바이오!$V$23/10^3 -> 63794.27 | J12: =(I12*H12)/1000 -> 110423.56 | K12: =제넨바이오!$C$6 -> 25208.694 | L12: =제넨바이오!$C$3 -> 17507.573 | M12: =제넨바이오!$C$10 -> 4776.7662 | N12: =제넨바이오!C66/10^6 -> 304.18004 | O12: =J12+K12-L12-M12+N12 -> 113652.09 | P12: =제넨바이오!$C$15 -> 33349.809 | Q12: =제넨바이오!$H$4 -> 7043.2705 | R12: =제넨바이오!$H$5 -> -2377.1422 | S12: =제넨바이오!$H$6 -> 3492.641 | T12: =R12+S12 -> 1115.4988 | U12: =제넨바이오!$H$8 -> -5104.3844 | V12: =J12/P12 -> 3.3110701 | W12: =O12/Q12 -> 16.136267 | X12: =O12/R12 -> -47.810388 | Y12: =O12/T12 -> 101.88455 | Z12: =J12/U12 -> -21.63308 | AA12: X | AB12: 2018년 영업손실로 멀티플 산정에서 제외
T14: 국내 | U14: Mean | V14: =AVERAGE(V8:V12) -> 1.8088551 | W14: =AVERAGE(W8:W12) -> 5.0523513 | X14: =AVERAGE(X8:X12) -> -1.2593832 | Y14: =AVERAGE(Y8:Y12) -> 26.41371 | Z14: =AVERAGE(Z8:Z12) -> 5.9486441
U15: Median | V15: =MEDIAN(V8:V12) -> 1.3699514 | W15: =MEDIAN(W8:W12) -> 2.1263576 | X15: =MEDIAN(X8:X12) -> 10.831033 | Y15: =MEDIAN(Y8:Y12,) -> 7.9022859 | Z15: =MEDIAN(Z8:Z12) -> 11.622211
U16: Max | V16: =MAX(V8:V12) -> 3.3110701 | W16: =MAX(W8:W12) -> 16.136267 | X16: =MAX(X8:X12) -> 13.479353 | Y16: =MAX(Y8:Y12) -> 101.88455 | Z16: =MAX(Z8:Z12) -> 16.08353
U17: Min | V17: =MIN(V8:V12) -> 0.81370258 | W17: =MIN(W8:W12) -> 0.67470911 | X17: =MIN(X8:X12) -> -47.810388 | Y17: =MIN(Y8:Y12) -> 3.7724864 | Z17: =MIN(Z8:Z12) -> -21.63308
B19: LG-Hitachi Water Solutions | P19: 2018년 12개월 기준 | V19: Multiples
B20: Guideline Public Company | C20: 국가 | D20: 산업 | F20: 업종상세 | G20: 상장구분 | H20: Price (*1) | I20: Outstanding | J20: Market Cap | K20: Debt | L20: Cash | M20: NOA | N20: 비지배지분 | O20: EV | P20: BV | Q20: Revenue | R20: EBIT | S20: Depreciation | T20: EBITDA | U20: Net Income | V20: PBR | W20: EV/Revenue | X20: EV/EBIT | Y20: EV/EBITDA | Z20: PER | AA20: 사용여부 | AB20: 제외사유
B21: Target(LG-Hitachi Water Solutions) | C21: 대한민국 | E21: 비상장 | G21: N/A | H21: N/A | I21: N/A | J21: N/A | K21: 0 | L21: 0 | M21: 0 | N21: 0 | O21: N/A | P21: =히타치_Dart!E37/10^6 -> 64527.186 | Q21: =히타치_Dart!J5/10^6 -> 417764.4 | R21: =히타치_Dart!J11/10^6 -> 36889.577 | S21: =SUM(히타치_Dart!J61:J62)/10^3 -> 2568.313 | T21: =R21+S21 -> 39457.89 | U21: =히타치_Dart!J18/10^6 -> 20158.968
B22: 웰크론한텍 | C22: 대한민국 | D22: 건물 건설업 | E22: 상장 | F22: 에너지절감설비,자동화배합설비,환경설비 | G22: 코스닥 | H22: =웰크론한텍!T2 -> 0 | I22: =웰크론한텍!AB26/10^3 -> 19362.573 | J22: =(I22*H22)/(10^3) -> 0 | K22: =웰크론한텍!G6/10^6 -> 37145.171 | L22: =웰크론한텍!G3/10^6 -> 37121.01 | M22: =웰크론한텍!G10/10^6 -> 54434.514 | N22: =웰크론한텍!C73/10^6 -> 34084.049 | O22: =J22+K22-L22-M22+N22 -> -20326.305 | P22: =웰크론한텍!G16/10^6 -> 100151.62 | Q22: =웰크론한텍!I31/10^6 -> 264346.51 | R22: =웰크론한텍!C5/10^6 -> 3443.4006 | S22: =웰크론한텍!C6/10^6 -> 967.24115 | T22: =웰크론한텍!C7/10^6 -> 4410.6417 | U22: =웰크론한텍!C8/10^6 -> 242.83676 | V22: =J22/P22 -> 0 | W22: =O22/Q22 -> -0.076892654 | X22: =O22/R22 -> -5.9029743 | Y22: =O22/T22 -> -4.6084688 | Z22: =J22/U22 -> 0 | AA22: O
B23: 삼부토건 | C23: 대한민국 | D23: 토목 건설업 | E23: 상장 | F23: 토목공사,건축공사,포장공사,건설업,분양사업/건설자재 제조 | G23: 코스피 | H23: =삼부토건!U6 -> 112854 | I23: =삼부토건!AC21/10^3 -> 24803.131 | J23: =(I23*H23)/(10^3) -> 2799132.5 | K23: =삼부토건!G6/10^6 -> 106815.59 | L23: =삼부토건!G3/10^6 -> 116268.68 | M23: =삼부토건!G10/10^6 -> 66637.356 | N23: =삼부토건!C99/10^6 -> -6992.4369 | O23: =J23+K23-L23-M23+N23 -> 2716049.7 | P23: =삼부토건!G16/10^6 -> 190254.57 | Q23: =삼부토건!J25/10^6 -> 177427.23 | R23: =삼부토건!C5/10^6 -> -9369.4995 | S23: =삼부토건!C6/10^6 -> 454.891 | T23: =-삼부토건!C7/10^6 -> 8914.6085 | U23: =삼부토건!C8/10^6 -> -51492.807 | V23: =J23/P23 -> 14.712564 | W23: =O23/Q23 -> 15.307964 | X23: =O23/R23 -> -289.88204 | Y23: =O23/T23 -> 304.67402 | Z23: =J23/U23 -> -54.359681 | AA23: O
B24: 대림산업 | C24: 대한민국 | D24: 토목 건설업 | E24: 상장 | F24: 산업플랜트공사,건축,토목,폴리에틸렌,폴리부텐,각종폴리머 제조,기술용역 | G24: 코스피 | H24: =대림산업!V3 -> 97396.61 | I24: =대림산업!AD24/10^3 -> 34800 | J24: =(I24*H24)/(10^3) -> 3389402 | K24: =대림산업!G7/10^6 -> 2689205.1 | L24: =대림산업!G4/10^6 -> 2520202.1 | M24: =대림산업!G11/10^6 -> 3001642.5 | N24: =대림산업!E87/10^6 -> 660210.51 | O24: =J24+K24-L24-M24+N24 -> 1216973 | P24: =대림산업!G17/10^6 -> 6050244.1 | Q24: =대림산업!K29/10^6 -> 10984485 | R24: =대림산업!C6/10^6 -> 845358.15 | S24: =대림산업!C7/10^6 -> 127517 | T24: =대림산업!C8/10^6 -> 972875.15 | U24: =대림산업!C9/10^6 -> 678088.77 | V24: =J24/P24 -> 0.56020914 | W24: =O24/Q24 -> 0.11079017 | X24: =O24/R24 -> 1.4395946 | Y24: =O24/T24 -> 1.2509036 | Z24: =J24/U24 -> 4.9984636 | AA24: X | AB24: 투자부동산(1,149억) 및 관계기업투자(1,147억)등 NOA 과다보유(총 3,002억)에 따른 지분가치왜곡
B25: 우원개발 | C25: 대한민국 | D25: 기반조성 및 시설물 축조관련 전문공사업 | E25: 상장 | F25: 토공사 | G25: 코스닥 | H25: =우원개발!X2 -> 4037.4194 | I25: =우원개발!AF21/10^3 -> 17124.677 | J25: =(I25*H25)/(10^3) -> 69139.502 | K25: =우원개발!G6/10^6 -> 28869.473 | L25: =우원개발!G3/10^6 -> 25713.787 | M25: =우원개발!G10/10^6 -> 54733.618 | N25: 0 | O25: =J25+K25-L25-M25+N25 -> 17561.57 | P25: =우원개발!G16/10^6 -> 61891.502 | Q25: =우원개발!J26/10^6 -> 218641.54 | R25: =우원개발!C5/10^6 -> 1436.2555 | S25: =우원개발!C6/10^6 -> 1314.2825 | T25: =우원개발!C7/10^6 -> 2750.5379 | U25: =우원개발!C8/10^6 -> -1444.6428 | V25: =J25/P25 -> 1.1171082 | W25: =O25/Q25 -> 0.08032129 | X25: =O25/R25 -> 12.227331 | Y25: =O25/T25 -> 6.3847766 | Z25: =J25/U25 -> -47.859236 | AA25: O
B26: 태영건설 | C26: 대한민국 | D26: 토목 건설업 | E26: 상장 | F26: 종합건설업(토목공사,도로공사,건축공사,관급공사,환경공사,상하수도공사,하수종말처리공사)/부동산 임대,매매 | G26: 코스피 | H26: =태영건설!O20 -> 12067.797 | I26: =태영건설!P20/10^3 -> 76400 | J26: =(I26*H26)/(10^3) -> 921979.66 | K26: =태영건설!G6 -> 1728674.6 | L26: =태영건설!G3 -> 539369.79 | M26: =태영건설!G11 -> 886059.96 | N26: =(태영건설!$C$85)/(10^6) -> 467916.59 | O26: =J26+K26-L26-M26+N26 -> 1693141.1 | P26: =태영건설!G19 -> 1482288.3 | Q26: =태영건설!C4 -> 3850546 | R26: =태영건설!C5 -> 463519.91 | S26: =태영건설!C6 -> 67464.167 | T26: =태영건설!C7 -> 530984.07 | U26: =태영건설!C8 -> 244140.18 | V26: =J26/P26 -> 0.62199754 | W26: =O26/Q26 -> 0.43971454 | X26: =O26/R26 -> 3.6527905 | Y26: =O26/T26 -> 3.1886853 | Z26: =J26/U26 -> 3.7764355 | AA26: O
B27: 화성산업 | C27: 대한민국 | D27: 건물 건설업 | E27: 상장 | F27: 아파트 건설 | G27: 코스피 | H27: =화성산업!R20 -> 14627.119 | I27: =화성산업!S20/10^3 -> 12450.8 | J27: =(I27*H27)/(10^3) -> 182119.33 | K27: =화성산업!G6 -> 11064 | L27: =화성산업!G3 -> 132124.24 | M27: =화성산업!G10 -> 152156.87 | N27: 0 | O27: =J27+K27-L27-M27+N27 -> -91097.782 | P27: =화성산업!G18 -> 374793.43 | Q27: =화성산업!C4 -> 475191 | R27: =화성산업!C5 -> 67108.169 | S27: =화성산업!C6 -> 2825.879 | T27: =화성산업!C7 -> 69934.048 | U27: =화성산업!C8 -> 49227.488 | V27: =J27/P27 -> 0.48591922 | W27: =O27/Q27 -> -0.19170772 | X27: =O27/R27 -> -1.3574768 | Y27: =O27/T27 -> -1.3026242 | Z27: =J27/U27 -> 3.6995455 | AA27: X | AB27: 매도가능금융자산, 대여금, 관계기업투자주식 등(NOA)의 총자산 대비 비율은 23%를 초과하여 주식가격과 영업활동가치 간 왜곡
B28: 현대건설 | C28: 대한민국 | D28: 토목 건설업 | E28: 상장 | F28: 공사수입,주택분양,건설산업부문 설계,감리 등 엔지니어링서비스 | G28: 코스피 | H28: =현대건설!#REF! -> #REF! | I28: =현대건설!#REF!/10^3 -> #REF! | J28: =(I28*H28)/(10^3) -> #REF! | K28: =현대건설!G6 -> 2400899 | L28: =현대건설!G3 -> 4066143 | M28: =현대건설!G11 -> 1169462 | N28: =현대건설!$C$94 -> 2017762 | O28: =J28+K28-L28-M28+N28 -> #REF! | P28: =현대건설!G19 -> 8291856 | Q28: =현대건설!C4 -> 16730894 | R28: =현대건설!C5 -> 839989 | S28: =현대건설!C6 -> 175573 | T28: =현대건설!C7 -> 1015562 | U28: =현대건설!C8 -> 535303 | V28: =J28/P28 -> #REF! | W28: =O28/Q28 -> #REF! | X28: =O28/R28 -> #REF! | Y28: =O28/T28 -> #REF! | Z28: =J28/U28 -> #REF! | AA28: O
B29: GS건설 | C29: 대한민국 | D29: 건물 건설업 | E29: 상장 | F29: 토목공사,건축공사,주택공사,산업플랜트공사,리모델링공사,시설물유지관리공사/산업설비설계,감리 용역,수출입/에너지관리 진단,연구개발 | G29: 코스피 | H29: =GS건설!Q20 -> 44188.136 | I29: =GS건설!R20/10^3 -> 79528.619 | J29: =(I29*H29)/(10^3) -> 3514221.4 | K29: =GS건설!G6 -> 2265342 | L29: =GS건설!G3 -> 1887823.7 | M29: =GS건설!G11 -> 2039051 | N29: =(GS건설!$C$67)/(10^6) -> 76173.169 | O29: =J29+K29-L29-M29+N29 -> 1928861.8 | P29: =GS건설!G17 -> 3624685.9 | Q29: =GS건설!C4 -> 13139373 | R29: =GS건설!C5 -> 1064489.2 | S29: =GS건설!C6 -> 53561 | T29: =GS건설!C7 -> 1118050.2 | U29: =GS건설!C8 -> 587434.4 | V29: =J29/P29 -> 0.9695244 | W29: =O29/Q29 -> 0.14680014 | X29: =O29/R29 -> 1.812007 | Y29: =O29/T29 -> 1.7252015 | Z29: =J29/U29 -> 5.9823215 | AA29: X | AB29: 2017년 대비 2018년 매출 12.5% 상승, 영업이익 234%, EBITDA 197.5% 상승하며 창사이래 최대실적을 기록함에 따른 2018년 EBITDA를 통한 Multiple 왜곡
B30: 동부건설 | C30: 대한민국 | D30: 토목 건설업 | E30: 상장 | F30: 건축공사,토목공사,전기공사,기계설비공사/비금속,철구조물 제조,판매/여객,자동차 운송,항만하역 | G30: 코스피 | H30: =동부건설!Q20 -> 8135.7627 | I30: =동부건설!R20/10^3 -> 20867.152 | J30: =(I30*H30)/(10^3) -> 169770.2 | K30: =동부건설!G6 -> 6683 | L30: =동부건설!G3 -> 84919.968 | M30: =동부건설!G11 -> 258967.51 | N30: 0 | O30: =J30+K30-L30-M30+N30 -> -167434.28 | P30: =동부건설!G18 -> 361897.85 | Q30: =동부건설!C4 -> 898151.33 | R30: =동부건설!C5 -> 31822.346 | S30: =동부건설!C6 -> 3632 | T30: =동부건설!C7 -> 35454.346 | U30: =동부건설!C8 -> 73948.074 | V30: =J30/P30 -> 0.46911082 | W30: =O30/Q30 -> -0.18642101 | X30: =O30/R30 -> -5.2615315 | Y30: =O30/T30 -> -4.7225318 | Z30: =J30/U30 -> 2.2958028 | AA30: X | AB30: 회생절차 기간 수주 잔고가 줄어 매출이 예전 규모로 회복되지 못하는 등의 사유로 주가 상승이 더뎌 Multiple에 왜곡
B31: 코오롱글로벌 | C31: 대한민국 | D31: 토목 건설업 | E31: 상장 | F31: 토목공사,일반건설,주택건설,해외건설,소각로설비공사/환경플랜트,폐처리기 제조 | G31: 코스피 | H31: =코오롱글로벌!Q20 -> 8598.6441 | I31: =코오롱글로벌!R20/10^3 -> 10.254262 | J31: =(I31*H31)/(10^3) -> 88.172752 | K31: =코오롱글로벌!G6 -> 711660 | L31: =코오롱글로벌!G3 -> 82722.734 | M31: =코오롱글로벌!G11 -> 511292.84 | N31: =(코오롱글로벌!$C$72)/(10^6) -> 4097.9329 | O31: =J31+K31-L31-M31+N31 -> 121830.54 | P31: =코오롱글로벌!G18 -> 446731.38 | Q31: =코오롱글로벌!C4 -> 3358253.4 | R31: =코오롱글로벌!C5 -> 76764.013 | S31: =코오롱글로벌!C6 -> 19458.894 | T31: =코오롱글로벌!C7 -> 96222.907 | U31: =코오롱글로벌!C8 -> 14451.16 | V31: =J31/P31 -> 0.00019737309 | W31: =O31/Q31 -> 0.036277946 | X31: =O31/R31 -> 1.5870788 | Y31: =O31/T31 -> 1.2661282 | Z31: =J31/U31 -> 0.0061014309 | AA31: O
B32: 진흥기업 | C32: 대한민국 | D32: 토목 건설업 | E32: 상장 | F32: 아파트건설,토목공사,건축공사,국내도급공사 | G32: 코스피 | H32: =진흥기업!Q20 -> 2040.7627 | I32: =진흥기업!R20/10^3 -> 2.007541 | J32: =(I32*H32)/(10^3) -> 4.0969148 | K32: =진흥기업!G6 -> 23703.636 | L32: =진흥기업!G3 -> 13320.055 | M32: =진흥기업!G11 -> 111114.32 | N32: 0 | O32: =J32+K32-L32-M32+N32 -> -100726.64 | P32: =진흥기업!G18 -> 78804.146 | Q32: =진흥기업!C4 -> 671155.39 | R32: =진흥기업!C5 -> 35051.376 | S32: =진흥기업!C6 -> 397.3 | T32: =진흥기업!C7 -> 35448.676 | U32: =진흥기업!C8 -> 6053.4942 | V32: =J32/P32 -> 5.1988569e-05 | W32: =O32/Q32 -> -0.15007947 | X32: =O32/R32 -> -2.8736859 | Y32: =O32/T32 -> -2.8414783 | Z32: =J32/U32 -> 0.00067678512 | AA32: O
B33: 남광토건 | C33: 대한민국 | D33: 토목 건설업 | E33: 상장 | F33: 토목공사,건축공사,기전공사,측량설계시공,용역/철구조물 제조 | G33: 코스피 | H33: =남광토건!Q20 -> 15253.39 | I33: =남광토건!R20/10^3 -> 8.6398361 | J33: =(I33*H33)/(10^3) -> 131.78679 | K33: =남광토건!G6 -> 9245.011 | L33: =남광토건!G3 -> 37821.764 | M33: =남광토건!G11 -> 35752.198 | N33: 0 | O33: =J33+K33-L33-M33+N33 -> -64197.165 | P33: =남광토건!G18 -> 49112.604 | Q33: =남광토건!C4 -> 157172.93 | R33: =남광토건!C5 -> 11141.645 | S33: =남광토건!C6 -> 460.759 | T33: =남광토건!C7 -> 11602.404 | U33: =남광토건!C8 -> 5715.6746 | V33: =J33/P33 -> 0.0026833598 | W33: =O33/Q33 -> -0.40844924 | X33: =O33/R33 -> -5.7619109 | Y33: =O33/T33 -> -5.5330918 | Z33: =J33/U33 -> 0.023057084 | AA33: O
B34: KCC건설 | C34: 대한민국 | D34: 건물 건설업 | E34: 상장 | F34: 토목 건축공사, 분양공사 | G34: 코스닥 | H34: =KCC건설!D5 -> 8092.0339 | I34: =KCC건설!K156/10^3 -> 21400 | J34: =(I34*H34)/(10^3) -> 173169.53 | K34: =KCC건설!C21 -> 248253.91 | L34: =KCC건설!C18 -> 214388.04 | M34: =KCC건설!C25 -> 141192.71 | N34: =(KCC건설!$C$151)/(10^6) -> -94.449709 | O34: =J34+K34-L34-M34+N34 -> 65748.24 | P34: =KCC건설!C30 -> 376414.85 | Q34: =KCC건설!C9 -> 1063627.3 | R34: =KCC건설!C10 -> 47771.723 | S34: =KCC건설!C11 -> 1135.6173 | T34: =R34+S34 -> 48907.341 | U34: =KCC건설!C13 -> 24144.269 | V34: =J34/P34 -> 0.46004967 | W34: =O34/Q34 -> 0.061815114 | X34: =O34/R34 -> 1.3763004 | Y34: =O34/T34 -> 1.344343 | Z34: =J34/U34 -> 7.1722828 | AA34: X | AB34: 플랜트 사업도 영위하지만 주로 스위첸 분양 등 주로 부동산, 건설 경기에 따라 주가가 변동하므로 제외
B35: 금화피에스시 | C35: 대한민국 | D35: 전기 및 통신 공사업 | E35: 상장 | F35: 설비,철물,전기,강구조물 | G35: 코스닥 | H35: =금화피에스시!D5 -> 30849.153 | I35: =금화피에스시!K90/10^3 -> 6000 | J35: =(I35*H35)/(10^3) -> 185094.92 | K35: =금화피에스시!C21 -> 10767.872 | L35: =금화피에스시!C18 -> 142314.6 | M35: =금화피에스시!C25 -> 41035.704 | N35: =(금화피에스시!$C$85)/(10^6) -> 369.47549 | O35: =J35+K35-L35-M35+N35 -> 12881.957 | P35: =금화피에스시!C30 -> 220727.04 | Q35: =금화피에스시!C9 -> 233326.73 | R35: =금화피에스시!C10 -> 41384.787 | S35: =금화피에스시!C11 -> 1664.837 | T35: =R35+S35 -> 43049.624 | U35: =금화피에스시!C13 -> 39649.709 | V35: =J35/P35 -> 0.83856929 | W35: =O35/Q35 -> 0.055209948 | X35: =O35/R35 -> 0.31127276 | Y35: =O35/T35 -> 0.29923506 | Z35: =J35/U35 -> 4.6682541 | AA35: X | AB35: 주 사업영업이 전기, 전력 인프라에 집중됨에 따라 제외
B36: 상지카일룸 | C36: 대한민국 | D36: 건물 건설업 | E36: 상장 | F36: 정보통신망 구축, DVR, ITS, 기타방송장비 등 | G36: 코스닥 | H36: =상지카일룸!D5 -> 1941.3559 | I36: =상지카일룸!K80/10^3 -> 39119.974 | J36: =(I36*H36)/(10^3) -> 75945.794 | K36: =상지카일룸!C21 -> 64305.101 | L36: =상지카일룸!C18 -> 9752.2469 | M36: =상지카일룸!C25 -> 17497.55 | N36: 0 | O36: =J36+K36-L36-M36+N36 -> 113001.1 | P36: =상지카일룸!C30 -> 44529.668 | Q36: =상지카일룸!C9 -> 31021.854 | R36: =상지카일룸!C10 -> 1838.3092 | S36: =상지카일룸!C11 -> 574.606 | T36: =R36+S36 -> 2412.9152 | U36: =상지카일룸!C13 -> 9648.7798 | V36: =J36/P36 -> 1.70551 | W36: =O36/Q36 -> 3.6426288 | X36: =O36/R36 -> 61.470125 | Y36: =O36/T36 -> 46.831773 | Z36: =J36/U36 -> 7.8710257 | AA36: X | AB36: 3월 15일 전환사채(CB)의 전환청구가 이루어지는 등 전반적인 자산/부채 및 지분률 환경이 안정적이지 아니하므로 제외
B37: 이테크건설 | C37: 대한민국 | D37: 건물건설업 | E37: 상장 | F37: 건축공사, 플랜트설비, 토목공사 | G37: 코스닥 | H37: =이테크건설!D5 -> 90362.712 | I37: =이테크건설!K89/10^3 -> 2800 | J37: =(I37*H37)/(10^3) -> 253015.59 | K37: =이테크건설!C21 -> 2066.7937 | L37: =이테크건설!C18 -> 135269.33 | M37: =이테크건설!C25 -> 38988.762 | N37: =(이테크건설!$C$84)/(10^6) -> 155074.7 | O37: =J37+K37-L37-M37+N37 -> 235898.99 | P37: =이테크건설!C30 -> 498705.03 | Q37: =이테크건설!C9 -> 1487904.8 | R37: =이테크건설!C10 -> 113025.08 | S37: =이테크건설!C11 -> 69911.585 | T37: =R37+S37 -> 182936.66 | U37: =이테크건설!C13 -> 71126.973 | V37: =J37/P37 -> 0.50734518 | W37: =O37/Q37 -> 0.15854441 | X37: =O37/R37 -> 2.0871385 | Y37: =O37/T37 -> 1.2895118 | Z37: =J37/U37 -> 3.5572383 | AA37: X | AB37: 최근 이미연 테마주 및 대북주 등으로 주가 변동성이 확대됨에 따라 제외.
B38: 세보엠이씨 | C38: 대한민국 | D38: 건물설비 설치 공사업 | E38: 상장 | F38: 건설관련설비, ACESS FLOOR , 소음기 , CHAMMBER , PFP UNIT, BY-PASS UNIT , DUCT , 철구조물 . | G38: 코스닥 | H38: =세보엠이씨!D5 -> 9984.9153 | I38: =KCC건설!K156/10^3 -> 21400 | J38: =(I38*H38)/(10^3) -> 213677.19 | K38: =세보엠이씨!C21 -> 11620 | L38: =세보엠이씨!C18 -> 19185.185 | M38: =세보엠이씨!C25 -> 9975.4092 | N38: =(세보엠이씨!$E$71)/(10^6) -> 529.14652 | O38: =J38+K38-L38-M38+N38 -> 196665.74 | P38: =세보엠이씨!C30 -> 158899.63 | Q38: =세보엠이씨!C9 -> 473844.41 | R38: =세보엠이씨!C10 -> 27985.354 | S38: =세보엠이씨!C11 -> 4126.767 | T38: =R38+S38 -> 32112.121 | U38: =세보엠이씨!C13 -> 21156.52 | V38: =J38/P38 -> 1.3447305 | W38: =O38/Q38 -> 0.41504286 | X38: =O38/R38 -> 7.0274524 | Y38: =O38/T38 -> 6.1243461 | Z38: =J38/U38 -> 10.099827 | AA38: O
B39: 삼일기업공사(*3) | C39: 대한민국 | D39: 건물 건설업 | E39: 상장 | F39: 도급공사 | G39: 코스닥 | H39: =삼일기업공사!D5 -> 3424.9153 | I39: =삼일기업공사!J71/10^3 -> 12400 | J39: =(I39*H39)/(10^3) -> 42468.949 | K39: =삼일기업공사!C21 -> 0 | L39: =삼일기업공사!C18 -> 42486.11 | M39: =삼일기업공사!C25 -> 4171.5691 | N39: 0 | O39: =J39+K39-L39-M39+N39 -> -4188.73 | P39: =삼일기업공사!C30 -> 56772.358 | Q39: =삼일기업공사!C9 -> 56185.007 | R39: =삼일기업공사!C10 -> 3042.0245 | S39: =삼일기업공사!C11 -> 127.94036 | T39: =R39+S39 -> 3169.9648 | U39: =삼일기업공사!C13 -> 3094.3332 | V39: =J39/P39 -> 0.74805681 | W39: =O39/Q39 -> -0.074552451 | X39: =O39/R39 -> -1.3769547 | Y39: =O39/T39 -> -1.3213806 | Z39: =J39/U39 -> 13.72475 | AA39: X | AB39: EV 가 (-) 이므로 Multiple 왜곡이 발생할 수 있으므로 제외
B40: 에쓰씨엔지니어링 | C40: 대한민국 | D40: 건설업 | E40: 상장 | F40: 기술용역(건축설계) 서비스/화학플랜트 설비,기계 제작(음식료,석유화학사업관련)/유공압기기 판매 | G40: 코스피 | H40: =AVERAGE(SC엔지니어링!P43:P101) -> 1723.8983 | I40: =SC엔지니어링!$X$21/10^3 -> 25016.587 | J40: =(I40*H40)/(10^3) -> 43126.052 | K40: =(SC엔지니어링!C6)/(10^6) -> 12611.435 | L40: =(SC엔지니어링!C3)/(10^6) -> 16418.682 | M40: =(SC엔지니어링!C10)/(10^6) -> 68450.959 | N40: =SC엔지니어링!$C$81/10^6 -> 0 | O40: =J40+K40-L40-M40+N40 -> -29132.154 | P40: =(SC엔지니어링!C15)/(10^6) -> 43011.649 | Q40: =(SC엔지니어링!I4)/(10^6) -> 214350.89 | R40: =(SC엔지니어링!I5)/(10^6) -> 1017.2999 | S40: =(SC엔지니어링!I6)/(10^6) -> 4267.128 | T40: =R40+S40 -> 5284.4279 | U40: =(SC엔지니어링!I8)/(10^6) -> 13621.634 | V40: =J40/P40 -> 1.0026598 | W40: =O40/Q40 -> -0.13590872 | X40: =O40/R40 -> -28.636742 | Y40: =O40/T40 -> -5.5128303 | Z40: =J40/U40 -> 3.165997 | AA40: X | AB40: 관계기업투자자산(NOA)의 총자산 대비 비율은 60% 초과하여 주식가격과 영업활동가치 간 왜곡
B41: 일성건설 | C41: 대한민국 | D41: 건설업 | E41: 상장 | F41: 건축공사,토목공사,전기공사 | G41: 코스피 | H41: =AVERAGE(일성건설!P42:P100) -> 4661.9492 | I41: =일성건설!$X$20/10^3 -> 38874.942 | J41: =(I41*H41)/(10^3) -> 181233 | K41: =(일성건설!C6)/(10^6) -> 242991.04 | L41: =(일성건설!C3)/(10^6) -> 95354.042 | M41: =(일성건설!C10)/(10^6) -> 324388.64 | N41: =일성건설!$C$83/10^6 -> 10298.654 | O41: =J41+K41-L41-M41+N41 -> 14780.014 | P41: =(일성건설!C14)/(10^6) -> 265660.46 | Q41: =(일성건설!I4)/(10^6) -> 1320997.3 | R41: =(일성건설!I5)/(10^6) -> 60157.737 | S41: =(일성건설!I6)/10^6 -> 7243.908 | T41: =R41+S41 -> 67401.645 | U41: =(일성건설!I8)/(10^6) -> -12072.114 | V41: =J41/P41 -> 0.68219787 | W41: =O41/Q41 -> 0.011188527 | X41: =O41/R41 -> 0.24568766 | Y41: =O41/T41 -> 0.21928268 | Z41: =J41/U41 -> -15.012533 | AA41: X | AB41: 관계기업투자주식, 매도가능증권(NOA)의 총자산 대비 비율은 18% 초과하며, 비지배지분이 존재하여 주식가격과 영업활동가치 간 왜곡
T43: 국내 | U43: Mean | V43: =AVERAGE(V22:V41) -> #REF! | W43: =AVERAGE(W22:W41) -> #REF! | X43: =AVERAGE(X22:X41) -> #REF! | Y43: =AVERAGE(Y22:Y41) -> #REF! | Z43: =AVERAGE(Z22:Z41) -> #REF!
U44: Median | V44: =MEDIAN(V22:V41) -> #REF! | W44: =MEDIAN(W22:W41) -> #REF! | X44: =MEDIAN(X22:X41) -> #REF! | Y44: =MEDIAN(Y22:Y41) -> #REF! | Z44: =MEDIAN(Z22:Z41) -> #REF!
U45: Max | V45: =MAX(V22:V41) -> #REF! | W45: =MAX(W22:W41) -> #REF! | X45: =MAX(X22:X41) -> #REF! | Y45: =MAX(Y22:Y41) -> #REF! | Z45: =MAX(Z22:Z41) -> #REF!
U46: Min | V46: =MIN(V22:V41) -> #REF! | W46: =MIN(W22:W41) -> #REF! | X46: =MIN(X22:X41) -> #REF! | Y46: =MIN(Y22:Y41) -> #REF! | Z46: =MIN(Z22:Z41) -> #REF!

Sheet 2018
A1: Project All
A2: Trading Multiple - 국내
A3: (Unit : KRW million, unless otherwise noted)
B5: HiEntech | K5: 2018년 12개월 기준 | Q5: Multiples
B6: 백만원 | C6: Price [1] | D6: Outstanding[2] | E6: Market Cap | F6: Debt | G6: Cash[3] | H6: NOA[4] | I6: 비지배지분 | J6: EV | K6: BV | L6: Revenue | M6: EBIT | N6: Depreciation | O6: EBITDA | P6: Net Income | Q6: PBR | R6: EV/Revenue | S6: EV/EBIT | T6: EV/EBITDA | U6: PER
B7: Target(HiEntech) | C7: N/A | D7: N/A | E7: N/A | F7: 0 | G7: 0 | H7: 0 | I7: 0 | J7: N/A | K7: =하이엔텍_Dart!E47/10^6 -> 35747.682 | L7: =하이엔텍_Dart!J5/10^6 -> 155484.44 | M7: =하이엔텍_Dart!J9/10^6 -> 10219.599 | N7: =SUM(하이엔텍_Dart!J37:J38)/10^3 -> 513.603 | O7: =M7+N7 -> 10733.202 | P7: =하이엔텍_Dart!J16/10^6 -> 8449.3759
B8: ='모집단 선정(HiEntech)'!D37 -> 와이엔텍 | C8: =와이엔텍!N3 -> 5768.5593 | D8: =와이엔텍!N7/10^3 -> 18199.659 | E8: =(D8*C8)/1000 -> 104985.81 | F8: =와이엔텍!C$6 -> 75272.804 | G8: =와이엔텍!C$3 -> 14407.688 | H8: =와이엔텍!C$10 -> 4096.857 | I8: 0 | J8: =E8+F8-G8-H8+I8 -> 161754.07 | K8: =와이엔텍!C$15 -> 116581.79 | L8: =와이엔텍!H$4 -> 76070.963 | M8: =와이엔텍!H$5 -> 14934.316 | N8: =와이엔텍!H$6 -> 6461.887 | O8: =M8+N8 -> 21396.203 | P8: =와이엔텍!H$8 -> 9033.2051 | Q8: =E8/K8 -> 0.90053358 | R8: =J8/L8 -> 2.1263576 | S8: =J8/M8 -> 10.831033 | T8: =J8/O8 -> 7.5599428 | U8: =E8/P8 -> 11.622211
B9: ='모집단 선정(HiEntech)'!D38 -> 코엔텍 | C9: =코엔텍!N$3 -> 7877.4576 | D9: =코엔텍!N7/10^3 -> 50000 | E9: =(D9*C9)/1000 -> 393872.88 | F9: =코엔텍!C$6 -> 25805.2 | G9: =코엔텍!C$3 -> 92869.832 | H9: =코엔텍!C$10 -> 1950.9296 | I9: =코엔텍!C66/10^6 -> 7.545629 | J9: =E9+F9-G9-H9+I9 -> 324864.87 | K9: =코엔텍!C$15 -> 148686.38 | L9: =코엔텍!H$4 -> 72239.031 | M9: =코엔텍!H$5 -> 29310.888 | N9: =코엔텍!H$6 -> 10092.323 | O9: =M9+N9 -> 39403.211 | P9: =코엔텍!H$8 -> 24489.206 | Q9: =E9/K9 -> 2.6490179 | R9: =J9/L9 -> 4.4970823 | S9: =J9/M9 -> 11.083419 | T9: =J9/O9 -> 8.2446291 | U9: =E9/P9 -> 16.08353
B10: ='모집단 선정(HiEntech)'!D39 -> 인선이엔티 | C10: =인선이엔티!O$3 -> 6996.2712 | D10: =인선이엔티!O7/10^3 -> 36605.043 | E10: =(D10*C10)/1000 -> 256098.81 | F10: =인선이엔티!C$6 -> 90603.868 | G10: =인선이엔티!C$3 -> 26968.662 | H10: =인선이엔티!C$10 -> 2785.2241 | I10: =인선이엔티!C46/10^6 -> 4580.8354 | J10: =E10+F10-G10-H10+I10 -> 321529.63 | K10: =인선이엔티!C$15 -> 186940.06 | L10: =인선이엔티!H$4 -> 175954.97 | M10: =인선이엔티!H$5 -> 23853.49 | N10: =인선이엔티!H$6 -> 6459.635 | O10: =M10+N10 -> 30313.125 | P10: =인선이엔티!H$8 -> 19964.863 | Q10: =E10/K10 -> 1.3699514 | R10: =J10/L10 -> 1.8273405 | S10: =J10/M10 -> 13.479353 | T10: =J10/O10 -> 10.606944 | U10: =E10/P10 -> 12.827476
B13: 주요가정 Summary | O13: 국내 | P13: Mean | Q13: =AVERAGE(Q8:Q10) -> 1.6398343 | R13: =AVERAGE(R8:R10) -> 2.8169268 | S13: =AVERAGE(S8:S10) -> 11.797935 | T13: =AVERAGE(T8:T10) -> 8.8038386 | U13: =AVERAGE(U8:U10) -> 13.511072
B14: [1] 주가 : 2019년 3월 31일 기준 3개월 평균 주가 | P14: Median | Q14: =MEDIAN(Q8:Q10) -> 1.3699514 | R14: =MEDIAN(R8:R10) -> 2.1263576 | S14: =MEDIAN(S8:S10) -> 11.083419 | T14: =MEDIAN(T8:T10,) -> 7.9022859 | U14: =MEDIAN(U8:U10) -> 12.827476
B15: [2] 발행주식수 2019년 3월 31일 발행 주식수 | P15: Max | Q15: =MAX(Q8:Q10) -> 2.6490179 | R15: =MAX(R8:R10) -> 4.4970823 | S15: =MAX(S8:S10) -> 13.479353 | T15: =MAX(T8:T10) -> 10.606944 | U15: =MAX(U8:U10) -> 16.08353
B16: [3] Cash : 2018년말 현금및현금성자산 및 단기금융상품 | P16: Min | Q16: =MIN(Q8:Q10) -> 0.90053358 | R16: =MIN(R8:R10) -> 1.8273405 | S16: =MIN(S8:S10) -> 10.831033 | T16: =MIN(T8:T10) -> 7.5599428 | U16: =MIN(U8:U10) -> 11.622211
B17: [4] NoA : 2018년말 장기금융상품, 관계기업투자, 매도가능증권, 투자부동산, 매각예정자산, 장단기 대여금
B19: 비교 대상기업의 선정
B20: 1. 한국거래소 기업공시채널 KIND 시스템 상 수도, 하수 및 폐기물 처리, 원료 재생업으로 등록된 상장회사로 조회
B21: 2. 대상회사의 전방산업인 하수 처리업으로 분류된 상장회사가 없으므로 대용으로 폐기물 처리업을 영위하는 회사를 선정
B22: 3. 선정된 회사 중 주요 관계기업투자에 인터넷뉴스광고업을 영위하는 회사가 있어 주가 산정이 왜곡 되거나 영업손실이 발생하여 Multiple이 비교 불가능한 회사를 제외
B28: LG-Hitachi Water Solutions | K28: 2018년 12개월 기준 | Q28: Multiples
B29: Guideline Public Company | C29: Price [1] | D29: Outstanding[2] | E29: Market Cap | F29: Debt | G29: Cash[3] | H29: NOA[4] | I29: 비지배지분 | J29: EV | K29: BV | L29: Revenue | M29: EBIT | N29: Depreciation | O29: EBITDA | P29: Net Income | Q29: PBR | R29: EV/Revenue | S29: EV/EBIT | T29: EV/EBITDA | U29: PER
B30: Target(LG-Hitachi Water Solutions) | C30: N/A | D30: N/A | E30: N/A | F30: 0 | G30: 0 | H30: 0 | I30: 0 | J30: N/A | K30: =히타치_Dart!E37/10^6 -> 64527.186 | L30: =히타치_Dart!J5/10^6 -> 417764.4 | M30: =히타치_Dart!J11/10^6 -> 36889.577 | N30: =SUM(히타치_Dart!J61:J62)/10^3 -> 2568.313 | O30: =M30+N30 -> 39457.89 | P30: =히타치_Dart!J18/10^6 -> 20158.968
B31: 웰크론한텍 | C31: =웰크론한텍!T6 -> 2243.2203 | D31: =웰크론한텍!T10/10^3 -> 19362.573 | E31: =(D31*C31)/(10^3) -> 43434.518 | F31: =웰크론한텍!G6/10^6 -> 37145.171 | G31: =웰크론한텍!G3/10^6 -> 37121.01 | H31: =웰크론한텍!G10/10^6 -> 54434.514 | I31: =웰크론한텍!C73/10^6 -> 34084.049 | J31: =E31+F31-G31-H31+I31 -> 23108.213 | K31: =웰크론한텍!G16/10^6 -> 100151.62 | L31: =웰크론한텍!I31/10^6 -> 264346.51 | M31: =웰크론한텍!C5/10^6 -> 3443.4006 | N31: =웰크론한텍!C6/10^6 -> 967.24115 | O31: =웰크론한텍!C7/10^6 -> 4410.6417 | P31: =웰크론한텍!C8/10^6 -> 242.83676 | Q31: =E31/K31 -> 0.43368761 | R31: =J31/L31 -> 0.08741637 | S31: =J31/M31 -> 6.7108697 | T31: =J31/O31 -> 5.2391951 | U31: =E31/P31 -> 178.86303
B32: 삼부토건 | C32: =삼부토건!U3 -> 4904.5763 | D32: =삼부토건!U7/10^3 -> 24803.131 | E32: =(D32*C32)/(10^3) -> 121648.85 | F32: =삼부토건!G6/10^6 -> 106815.59 | G32: =삼부토건!G3/10^6 -> 116268.68 | H32: =삼부토건!G10/10^6 -> 66637.356 | I32: =삼부토건!C99/10^6 -> -6992.4369 | J32: =E32+F32-G32-H32+I32 -> 38565.961 | K32: =삼부토건!G16/10^6 -> 190254.57 | L32: =삼부토건!J25/10^6 -> 177427.23 | M32: =삼부토건!C5/10^6 -> -9369.4995 | N32: =삼부토건!C6/10^6 -> 454.891 | O32: =-삼부토건!C7/10^6 -> 8914.6085 | P32: =삼부토건!C8/10^6 -> -51492.807 | Q32: =E32/K32 -> 0.6394004 | R32: =J32/L32 -> 0.21736213 | S32: =J32/M32 -> -4.1161174 | T32: =J32/O32 -> 4.326153 | U32: =E32/P32 -> -2.3624435
B33: 우원개발 | C33: =우원개발!X3 -> 5074.8305 | D33: =우원개발!X7/10^3 -> 17124.677 | E33: =(D33*C33)/(10^3) -> 86904.833 | F33: =우원개발!G6/10^6 -> 28869.473 | G33: =우원개발!G3/10^6 -> 25713.787 | H33: =우원개발!G10/10^6 -> 54733.618 | I33: 0 | J33: =E33+F33-G33-H33+I33 -> 35326.901 | K33: =우원개발!G16/10^6 -> 61891.502 | L33: =우원개발!J26/10^6 -> 218641.54 | M33: =우원개발!C5/10^6 -> 1436.2555 | N33: =우원개발!C6/10^6 -> 1314.2825 | O33: =우원개발!C7/10^6 -> 2750.5379 | P33: =우원개발!C8/10^6 -> -1444.6428 | Q33: =E33/K33 -> 1.4041481 | R33: =J33/L33 -> 0.16157452 | S33: =J33/M33 -> 24.59653 | T33: =J33/O33 -> 12.843634 | U33: =E33/P33 -> -60.156622
B34: 태영건설 | C34: =태영건설!O10 -> 12067.797 | D34: =태영건설!O14/10^3 -> 76400 | E34: =(D34*C34)/(10^3) -> 921979.66 | F34: =태영건설!G6 -> 1728674.6 | G34: =태영건설!G3 -> 539369.79 | H34: =태영건설!G11 -> 886059.96 | I34: =(태영건설!$C$85)/(10^6) -> 467916.59 | J34: =E34+F34-G34-H34+I34 -> 1693141.1 | K34: =태영건설!G19 -> 1482288.3 | L34: =태영건설!C4 -> 3850546 | M34: =태영건설!C5 -> 463519.91 | N34: =태영건설!C6 -> 67464.167 | O34: =태영건설!C7 -> 530984.07 | P34: =태영건설!C8 -> 244140.18 | Q34: =E34/K34 -> 0.62199754 | R34: =J34/L34 -> 0.43971454 | S34: =J34/M34 -> 3.6527905 | T34: =J34/O34 -> 3.1886853 | U34: =E34/P34 -> 3.7764355
B35: 현대건설 | C35: =현대건설!O20 -> 57727.119 | D35: =현대건설!O24/10^3 -> 111355.76 | E35: =(D35*C35)/(10^3) -> 6428247.5 | F35: =현대건설!G6 -> 2400899 | G35: =현대건설!G3 -> 4066143 | H35: =현대건설!G11 -> 1169462 | I35: =현대건설!$C$94 -> 2017762 | J35: =E35+F35-G35-H35+I35 -> 5611303.5 | K35: =현대건설!G19 -> 8291856 | L35: =현대건설!C4 -> 16730894 | M35: =현대건설!C5 -> 839989 | N35: =현대건설!C6 -> 175573 | O35: =현대건설!C7 -> 1015562 | P35: =현대건설!C8 -> 535303 | Q35: =E35/K35 -> 0.77524832 | R35: =J35/L35 -> 0.33538575 | S35: =J35/M35 -> 6.6802106 | T35: =J35/O35 -> 5.5253185 | U35: =E35/P35 -> 12.008615
B36: 코오롱글로벌 | C36: =코오롱글로벌!Q20 -> 8598.6441 | D36: =코오롱글로벌!Q24/10^3 -> 25210.438 | E36: =(D36*C36)/(10^3) -> 216775.58 | F36: =코오롱글로벌!G6 -> 711660 | G36: =코오롱글로벌!G3 -> 82722.734 | H36: =코오롱글로벌!G11 -> 511292.84 | I36: =(코오롱글로벌!$C$72)/(10^6) -> 4097.9329 | J36: =E36+F36-G36-H36+I36 -> 338517.95 | K36: =코오롱글로벌!G18 -> 446731.38 | L36: =코오롱글로벌!C4 -> 3358253.4 | M36: =코오롱글로벌!C5 -> 76764.013 | N36: =코오롱글로벌!C6 -> 19458.894 | O36: =코오롱글로벌!C7 -> 96222.907 | P36: =코오롱글로벌!C8 -> 14451.16 | Q36: =E36/K36 -> 0.48524817 | R36: =J36/L36 -> 0.10080179 | S36: =J36/M36 -> 4.4098521 | T36: =J36/O36 -> 3.5180599 | U36: =E36/P36 -> 15.000567
B37: 진흥기업 | C37: =진흥기업!Q20 -> 2040.7627 | D37: =진흥기업!Q24/10^3 -> 145471.74 | E37: =(D37*C37)/(10^3) -> 296873.31 | F37: =진흥기업!G6 -> 23703.636 | G37: =진흥기업!G3 -> 13320.055 | H37: =진흥기업!G11 -> 111114.32 | I37: 0 | J37: =E37+F37-G37-H37+I37 -> 196142.57 | K37: =진흥기업!G18 -> 78804.146 | L37: =진흥기업!C4 -> 671155.39 | M37: =진흥기업!C5 -> 35051.376 | N37: =진흥기업!C6 -> 397.3 | O37: =진흥기업!C7 -> 35448.676 | P37: =진흥기업!C8 -> 6053.4942 | Q37: =E37/K37 -> 3.7672296 | R37: =J37/L37 -> 0.29224614 | S37: =J37/M37 -> 5.5958594 | T37: =J37/O37 -> 5.5331424 | U37: =E37/P37 -> 49.041645
B38: 남광토건 | C38: =남광토건!Q20 -> 15253.39 | D38: =남광토건!Q24/10^3 -> 9827.396 | E38: =(D38*C38)/(10^3) -> 149901.1 | F38: =남광토건!G6 -> 9245.011 | G38: =남광토건!G3 -> 37821.764 | H38: =남광토건!G11 -> 35752.198 | I38: 0 | J38: =E38+F38-G38-H38+I38 -> 85572.151 | K38: =남광토건!G18 -> 49112.604 | L38: =남광토건!C4 -> 157172.93 | M38: =남광토건!C5 -> 11141.645 | N38: =남광토건!C6 -> 460.759 | O38: =남광토건!C7 -> 11602.404 | P38: =남광토건!C8 -> 5715.6746 | Q38: =E38/K38 -> 3.0521921 | R38: =J38/L38 -> 0.54444586 | S38: =J38/M38 -> 7.6803876 | T38: =J38/O38 -> 7.3753812 | U38: =E38/P38 -> 26.226318
B39: 세보엠이씨 | C39: =세보엠이씨!P69 -> 9984.9153 | D39: =세보엠이씨!P73/10^3 -> 10530 | E39: =(D39*C39)/(10^3) -> 105141.16 | F39: =세보엠이씨!C21 -> 11620 | G39: =세보엠이씨!C18 -> 19185.185 | H39: =세보엠이씨!C25 -> 9975.4092 | I39: =(세보엠이씨!$E$71)/(10^6) -> 529.14652 | J39: =E39+F39-G39-H39+I39 -> 88129.71 | K39: =세보엠이씨!C30 -> 158899.63 | L39: =세보엠이씨!C9 -> 473844.41 | M39: =세보엠이씨!C10 -> 27985.354 | N39: =세보엠이씨!C11 -> 4126.767 | O39: =M39+N39 -> 32112.121 | P39: =세보엠이씨!C13 -> 21156.52 | Q39: =E39/K39 -> 0.66168282 | R39: =J39/L39 -> 0.18598871 | S39: =J39/M39 -> 3.1491369 | T39: =J39/O39 -> 2.7444376 | U39: =E39/P39 -> 4.9696811
B42: 주요가정 Summary | O42: 국내 | P42: Mean | Q42: =AVERAGE(Q31:Q39) -> 1.3156483 | R42: =AVERAGE(R31:R39) -> 0.26277065 | S42: =AVERAGE(S31:S39) -> 6.4843911 | T42: =AVERAGE(T31:T39) -> 5.5882229 | U42: =AVERAGE(U31:U39) -> 25.263025
B43: [1] 주가 : 2019년 3월 31일 기준 3개월 평균 주가 | P43: Median | Q43: =MEDIAN(Q31:Q39) -> 0.66168282 | R43: =MEDIAN(R31:R39) -> 0.21736213 | S43: =MEDIAN(S31:S39) -> 5.5958594 | T43: =MEDIAN(T31:T39) -> 5.2391951 | U43: =MEDIAN(U31:U39) -> 12.008615
B44: [2] 발행주식수 2019년 3월 31일 발행 주식수 | P44: Max | Q44: =MAX(Q31:Q39) -> 3.7672296 | R44: =MAX(R31:R39) -> 0.54444586 | S44: =MAX(S31:S39) -> 24.59653 | T44: =MAX(T31:T39) -> 12.843634 | U44: =MAX(U31:U39) -> 178.86303
B45: [3] Cash : 2018년말 현금및현금성자산 및 단기금융상품 | P45: Min | Q45: =MIN(Q31:Q39) -> 0.43368761 | R45: =MIN(R31:R39) -> 0.08741637 | S45: =MIN(S31:S39) -> -4.1161174 | T45: =MIN(T31:T39) -> 2.7444376 | U45: =MIN(U31:U39) -> -60.156622
B46: [4] NoA : 2018년말 장기금융상품, 관계기업투자, 매도가능증권, 투자부동산, 매각예정자산, 장단기 대여금
B48: 비교 대상기업의 선정
B49: 1. 한국거래소 기업공시채널 KIND 시스템 상 제조업으로 등록된 상장회사 중, 주요 제품을 '건설업' 으로 조회. | Q49: 평균 Multiple
B50: 2. 선정회사 중 수처리, 오염저감시설 등 환경설비 건축과 거리가 먼 업종(예: 주택, 실내인테리어, 전기배선 등)회사 제외 | Q50: 구분 | R50: EV/Revenue | S50: EV/EBIT | T50: EV/EBITDA
B51: 3. 주식거래정지, 건설과 무관한 자회사 매출이 주가에 큰영향이 있는 등 비교가능성이 떨어지는 회사 제외 | Q51: HiEntech | R51: =AVERAGE(R8:R10) -> 2.8169268 | S51: =AVERAGE(S8:S10) -> 11.797935 | T51: =AVERAGE(T8:T10) -> 8.8038386
Q52: LHWS | R52: =AVERAGE(R31:R39) -> 0.26277065 | S52: =AVERAGE(S31:S39) -> 6.4843911 | T52: =AVERAGE(T31:T39) -> 5.5882229

Sheet 2017
A1: Project All
A2: Trading Multiple - 국내
A3: (Unit : KRW million, unless otherwise noted)
B5: HiEntech | K5: 2018년 12개월 기준 | Q5: Multiples
B6: 백만원 | C6: Price [1] | D6: Outstanding[2] | E6: Market Cap | F6: Debt | G6: Cash[3] | H6: NOA[4] | I6: 비지배지분 | J6: EV | K6: BV | L6: Revenue | M6: EBIT | N6: Depreciation | O6: EBITDA | P6: Net Income | Q6: PBR | R6: EV/Revenue | S6: EV/EBIT | T6: EV/EBITDA | U6: PER | V6: PEG
B7: Target(HiEntech) | C7: N/A | D7: N/A | E7: N/A | F7: 0 | G7: 0 | H7: 0 | I7: 0 | J7: N/A | K7: =하이엔텍_Dart!E47/10^6 -> 35747.682 | L7: =하이엔텍_Dart!J5/10^6 -> 155484.44 | M7: =하이엔텍_Dart!J9/10^6 -> 10219.599 | N7: =SUM(하이엔텍_Dart!J37:J38)/10^3 -> 513.603 | O7: =M7+N7 -> 10733.202 | P7: =하이엔텍_Dart!J16/10^6 -> 8449.3759
B8: ='모집단 선정(HiEntech)'!D37 -> 와이엔텍 | C8: =와이엔텍!O3 -> 4505.7377 | D8: =와이엔텍!O7/10^3 -> 17842.803 | E8: =(D8*C8)/1000 -> 80394.99 | F8: =와이엔텍!D$6 -> 62194.826 | G8: =와이엔텍!D$3 -> 8495.6814 | H8: =와이엔텍!D$10 -> 4165.3422 | I8: 0 | J8: =E8+F8-G8-H8+I8 -> 129928.79 | K8: =와이엔텍!D$15 -> 107554.18 | L8: =와이엔텍!I$4 -> 75231.069 | M8: =와이엔텍!I$5 -> 12525.143 | N8: =와이엔텍!I$6 -> 6723.52 | O8: =M8+N8 -> 19248.663 | P8: =와이엔텍!I$8 -> 11581.612 | Q8: =E8/K8 -> 0.74748367 | R8: =J8/L8 -> 1.727063 | S8: =J8/M8 -> 10.373438 | T8: =J8/O8 -> 6.7500163 | U8: =E8/P8 -> 6.9416062 | V8: =P8/D8*1000000 -> 649091.52
B9: ='모집단 선정(HiEntech)'!D38 -> 코엔텍 | C9: =코엔텍!O$3 -> 5045.7377 | D9: =코엔텍!O7/10^3 -> 50000 | E9: =(D9*C9)/1000 -> 252286.89 | F9: =코엔텍!D$6 -> 26877 | G9: =코엔텍!D$3 -> 47193.099 | H9: =코엔텍!D$10 -> 2204.8066 | I9: =코엔텍!D66/10^6 -> 7.996312 | J9: =E9+F9-G9-H9+I9 -> 229773.98 | K9: =코엔텍!D$15 -> 125556.41 | L9: =코엔텍!I$4 -> 61255.105 | M9: =코엔텍!I$5 -> 18586.515 | N9: =코엔텍!I$6 -> 10784.866 | O9: =M9+N9 -> 29371.381 | P9: =코엔텍!I$8 -> 16059.145 | Q9: =E9/K9 -> 2.0093508 | R9: =J9/L9 -> 3.7510992 | S9: =J9/M9 -> 12.362403 | T9: =J9/O9 -> 7.8230567 | U9: =E9/P9 -> 15.709858 | V9: =P9/D9*1000000 -> 321182.9
B10: ='모집단 선정(HiEntech)'!D39 -> 인선이엔티 | C10: =인선이엔티!P$3 -> 7432.7869 | D10: =인선이엔티!P7/10^3 -> 35963.93 | E10: =(D10*C10)/1000 -> 267312.23 | F10: =인선이엔티!D$6 -> 97524.714 | G10: =인선이엔티!D$3 -> 8266.7266 | H10: =인선이엔티!D$10 -> 9881.7752 | I10: =인선이엔티!D46/10^6 -> 5434.3274 | J10: =E10+F10-G10-H10+I10 -> 352122.77 | K10: =인선이엔티!D$15 -> 169748.57 | L10: =인선이엔티!I$4 -> 160280.18 | M10: =인선이엔티!I$5 -> 21914.663 | N10: =인선이엔티!I$6 -> 6295.864 | O10: =M10+N10 -> 28210.527 | P10: =인선이엔티!I$8 -> 2700.6853 | Q10: =E10/K10 -> 1.574754 | R10: =J10/L10 -> 2.1969202 | S10: =J10/M10 -> 16.067907 | T10: =J10/O10 -> 12.481963 | U10: =E10/P10 -> 98.979404 | V10: =P10/D10*1000000 -> 75094.278
B13: 주요가정 Summary | Q13: =AVERAGE(Q8:Q10) -> 1.4438628 | R13: =AVERAGE(R8:R10) -> 2.5583608 | S13: =AVERAGE(S8:S10) -> 12.934582 | T13: =AVERAGE(T8:T10) -> 9.0183455 | U13: =AVERAGE(U8:U10) -> 40.543623
B14: [1] 주가 : 2019년 3월 31일 기준 3개월 평균 주가 | Q14: =MEDIAN(Q8:Q10) -> 1.574754 | R14: =MEDIAN(R8:R10) -> 2.1969202 | S14: =MEDIAN(S8:S10) -> 12.362403 | T14: =MEDIAN(T8:T10,) -> 7.2865365 | U14: =MEDIAN(U8:U10) -> 15.709858
B15: [2] 발행주식수 2019년 3월 31일 발행 주식수 | Q15: =MAX(Q8:Q10) -> 2.0093508 | R15: =MAX(R8:R10) -> 3.7510992 | S15: =MAX(S8:S10) -> 16.067907 | T15: =MAX(T8:T10) -> 12.481963 | U15: =MAX(U8:U10) -> 98.979404
B16: [3] Cash : 2018년말 현금및현금성자산 및 단기금융상품 | Q16: =MIN(Q8:Q10) -> 0.74748367 | R16: =MIN(R8:R10) -> 1.727063 | S16: =MIN(S8:S10) -> 10.373438 | T16: =MIN(T8:T10) -> 6.7500163 | U16: =MIN(U8:U10) -> 6.9416062
B17: [4] NoA : 2018년말 장기금융상품, 관계기업투자, 매도가능증권, 투자부동산, 매각예정자산, 장단기 대여금
B19: 비교 대상기업의 선정
B20: 1. 한국거래소 기업공시채널 KIND 시스템 상 수도, 하수 및 폐기물 처리, 원료 재생업으로 등록된 상장회사로 조회
B21: 2. 대상회사의 전방산업인 하수 처리업으로 분류된 상장회사가 없으므로 대용으로 폐기물 처리업을 영위하는 회사를 선정
B22: 3. 선정된 회사 중 주요 관계기업투자에 인터넷뉴스광고업을 영위하는 회사가 있어 주가 산정이 왜곡 되거나 영업손실이 발생하여 Multiple이 비교 불가능한 회사를 제외
B28: LG-Hitachi Water Solutions | K28: 2018년 12개월 기준 | Q28: Multiples
B29: Guideline Public Company | C29: Price [1] | D29: Outstanding[2] | E29: Market Cap | F29: Debt | G29: Cash[3] | H29: NOA[4] | I29: 비지배지분 | J29: EV | K29: BV | L29: Revenue | M29: EBIT | N29: Depreciation | O29: EBITDA | P29: Net Income | Q29: PBR | R29: EV/Revenue | S29: EV/EBIT | T29: EV/EBITDA | U29: PER
B30: Target(LG-Hitachi Water Solutions) | C30: N/A | D30: N/A | E30: N/A | F30: 0 | G30: 0 | H30: 0 | I30: 0 | J30: N/A | K30: =히타치_Dart!E37/10^6 -> 64527.186 | L30: =히타치_Dart!J5/10^6 -> 417764.4 | M30: =히타치_Dart!J11/10^6 -> 36889.577 | N30: =SUM(히타치_Dart!J61:J62)/10^3 -> 2568.313 | O30: =M30+N30 -> 39457.89 | P30: =히타치_Dart!J18/10^6 -> 20158.968
B31: 웰크론한텍 | C31: =웰크론한텍!U6 -> 3213.1148 | D31: =웰크론한텍!U10/10^3 -> 19362.573 | E31: =(D31*C31)/(10^3) -> 62214.169 | F31: =웰크론한텍!H6/10^6 -> 20349.7 | G31: =웰크론한텍!H3/10^6 -> 44899.685 | H31: =웰크론한텍!H10/10^6 -> 19689.192 | I31: =웰크론한텍!D73/10^6 -> 28296.919 | J31: =E31+F31-G31-H31+I31 -> 46271.91 | K31: =웰크론한텍!H16/10^6 -> 95033.711 | L31: =웰크론한텍!J31/10^6 -> 251911.71 | M31: =웰크론한텍!D5/10^6 -> 2371.3897 | N31: =웰크론한텍!D6/10^6 -> 948.6743 | O31: =웰크론한텍!D7/10^6 -> 3320.064 | P31: =웰크론한텍!D8/10^6 -> -4990.1574 | Q31: =E31/K31 -> 0.65465368 | R31: =J31/L31 -> 0.18368305 | S31: =J31/M31 -> 19.512571 | T31: =J31/O31 -> 13.937054 | U31: =E31/P31 -> -12.467376 | V31: =P31/D31*1000000 -> -257721.81
B32: 삼부토건 | C32: =삼부토건!V3 -> 7666.2295 | D32: =삼부토건!V7/10^3 -> 18766.75 | E32: =(D32*C32)/(10^3) -> 143870.21 | F32: =삼부토건!H6/10^6 -> 129382.6 | G32: =삼부토건!H3/10^6 -> 132380 | H32: =삼부토건!H10/10^6 -> 115993.63 | I32: =삼부토건!D99/10^6 -> -110455.53 | J32: =E32+F32-G32-H32+I32 -> -85576.346 | K32: =삼부토건!H16/10^6 -> 125674.05 | L32: =삼부토건!K25/10^6 -> 280423.78 | M32: =삼부토건!D5/10^6 -> -19352.774 | N32: =삼부토건!D6/10^6 -> 843.485 | O32: =-삼부토건!D7/10^6 -> 18509.289 | P32: =삼부토건!D8/10^6 -> -40427.32 | Q32: =E32/K32 -> 1.1447885 | R32: =J32/L32 -> -0.30516793 | S32: =J32/M32 -> 4.4219162 | T32: =J32/O32 -> -4.6234269 | U32: =E32/P32 -> -3.5587374 | V32: =P32/D32*1000000 -> -2154199.3
B33: 우원개발 | C33: =우원개발!Y3 -> 4264.6721 | D33: =우원개발!Y7/10^3 -> 14650.592 | E33: =(D33*C33)/(10^3) -> 62479.971 | F33: =우원개발!H6/10^6 -> 64350.978 | G33: =우원개발!H3/10^6 -> 18144.126 | H33: =우원개발!H10/10^6 -> 53046.43 | I33: 0 | J33: =E33+F33-G33-H33+I33 -> 55640.394 | K33: =우원개발!H16/10^6 -> 58935.705 | L33: =우원개발!K26/10^6 -> 183640.68 | M33: =우원개발!D5/10^6 -> 6317.62 | N33: =우원개발!D6/10^6 -> 1518.4706 | O33: =우원개발!D7/10^6 -> 7836.0906 | P33: =우원개발!D8/10^6 -> -383.20267 | Q33: =E33/K33 -> 1.0601378 | R33: =J33/L33 -> 0.30298513 | S33: =J33/M33 -> 8.8071765 | T33: =J33/O33 -> 7.1005297 | U33: =E33/P33 -> -163.0468 | V33: =P33/D33*1000000 -> -26156.122
B34: 태영건설 | C34: =태영건설!P10 -> 11201.639 | D34: =태영건설!P14/10^3 -> 76400 | E34: =(D34*C34)/(10^3) -> 855805.25 | F34: =태영건설!H6 -> 1543821.5 | G34: =태영건설!H3 -> 561402.23 | H34: =태영건설!H11 -> 746012.51 | I34: =(태영건설!$C$85)/(10^6) -> 467916.59 | J34: =E34+F34-G34-H34+I34 -> 1560128.6 | K34: =태영건설!H19 -> 1435399 | L34: =태영건설!D4 -> 3266415.7 | M34: =태영건설!D5 -> 311131.44 | N34: =태영건설!D6 -> 66866.932 | O34: =태영건설!D7 -> 377998.37 | P34: =태영건설!D8 -> 123275.08 | Q34: =E34/K34 -> 0.59621417 | R34: =J34/L34 -> 0.47762708 | S34: =J34/M34 -> 5.0143714 | T34: =J34/O34 -> 4.1273421 | U34: =E34/P34 -> 6.9422403 | V34: =P34/D34*1000000 -> 1613548.2
B35: 현대건설 | C35: =현대건설!P20 -> 40387.705 | D35: =현대건설!P24/10^3 -> 111355.76 | E35: =(D35*C35)/(10^3) -> 4497403.8 | F35: =현대건설!H6 -> 2209352 | G35: =현대건설!H3 -> 3463893 | H35: =현대건설!H11 -> 1721209 | I35: =현대건설!$C$94 -> 2017762 | J35: =E35+F35-G35-H35+I35 -> 3539415.8 | K35: =현대건설!H19 -> 8472938 | L35: =현대건설!D4 -> 16887090 | M35: =현대건설!D5 -> 986105 | N35: =현대건설!D6 -> 194561 | O35: =현대건설!D7 -> 1180666 | P35: =현대건설!D8 -> 371564 | Q35: =E35/K35 -> 0.53079626 | R35: =J35/L35 -> 0.209593 | S35: =J35/M35 -> 3.5892889 | T35: =J35/O35 -> 2.9978129 | U35: =E35/P35 -> 12.103981 | V35: =P35/D35*1000000 -> 3336728.9
B36: 코오롱글로벌 | C36: =코오롱글로벌!R20 -> 10254.262 | D36: =코오롱글로벌!R24/10^3 -> 25210.438 | E36: =(D36*C36)/(10^3) -> 258514.44 | F36: =코오롱글로벌!H6 -> 653806 | G36: =코오롱글로벌!H3 -> 95937.084 | H36: =코오롱글로벌!H11 -> 479784.73 | I36: =(코오롱글로벌!$C$72)/(10^6) -> 4097.9329 | J36: =E36+F36-G36-H36+I36 -> 340696.57 | K36: =코오롱글로벌!H18 -> 465432.24 | L36: =코오롱글로벌!D4 -> 3653606 | M36: =코오롱글로벌!D5 -> 72509.169 | N36: =코오롱글로벌!D6 -> 16908.48 | O36: =코오롱글로벌!D7 -> 89417.649 | P36: =코오롱글로벌!D8 -> 15249.106 | Q36: =E36/K36 -> 0.55542874 | R36: =J36/L36 -> 0.093249399 | S36: =J36/M36 -> 4.6986688 | T36: =J36/O36 -> 3.8101714 | U36: =E36/P36 -> 16.952761 | V36: =P36/D36*1000000 -> 604872.72
B37: 진흥기업 | C37: =진흥기업!R20 -> 2007.541 | D37: =진흥기업!R24/10^3 -> 145353.08 | E37: =(D37*C37)/(10^3) -> 291802.27 | F37: =진흥기업!H6 -> 22939.727 | G37: =진흥기업!H3 -> 47742.058 | H37: =진흥기업!H11 -> 82705.38 | I37: 0 | J37: =E37+F37-G37-H37+I37 -> 184294.56 | K37: =진흥기업!H18 -> 75873.925 | L37: =진흥기업!D4 -> 573309.88 | M37: =진흥기업!D5 -> 41610.597 | N37: =진흥기업!D6 -> 414.284 | O37: =진흥기업!D7 -> 42024.881 | P37: =진흥기업!D8 -> 21831.87 | Q37: =E37/K37 -> 3.8458834 | R37: =J37/L37 -> 0.32145715 | S37: =J37/M37 -> 4.4290294 | T37: =J37/O37 -> 4.3853678 | U37: =E37/P37 -> 13.365885 | V37: =P37/D37*1000000 -> 150198.88
B38: 남광토건 | C38: =남광토건!R20 -> 8639.8361 | D38: =남광토건!R24/10^3 -> 9826.075 | E38: =(D38*C38)/(10^3) -> 84895.677 | F38: =남광토건!H6 -> 9245.011 | G38: =남광토건!H3 -> 30360.543 | H38: =남광토건!H11 -> 51618.944 | I38: 0 | J38: =E38+F38-G38-H38+I38 -> 12161.201 | K38: =남광토건!H18 -> 43309.99 | L38: =남광토건!D4 -> 115611.17 | M38: =남광토건!D5 -> 1829.2232 | N38: =남광토건!D6 -> 387.408 | O38: =남광토건!D7 -> 2216.6312 | P38: =남광토건!D8 -> 1700.2564 | Q38: =E38/K38 -> 1.960187 | R38: =J38/L38 -> 0.10519053 | S38: =J38/M38 -> 6.6482873 | T38: =J38/O38 -> 5.486344 | U38: =E38/P38 -> 49.931102 | V38: =P38/D38*1000000 -> 173035.16
B39: 세보엠이씨 | C39: =세보엠이씨!Q69 -> 12890.164 | D39: =세보엠이씨!Q73/10^3 -> 10530 | E39: =(D39*C39)/(10^3) -> 135733.43 | F39: =세보엠이씨!D21 -> 4000 | G39: =세보엠이씨!D18 -> 24724.522 | H39: =세보엠이씨!D25 -> 6308.3101 | I39: =세보엠이씨!D71/10^6 -> -1481.4096 | J39: =E39+F39-G39-H39+I39 -> 107219.18 | K39: =세보엠이씨!D30 -> 136913.8 | L39: =세보엠이씨!D9 -> 602536.02 | M39: =세보엠이씨!D10 -> 29088.95 | N39: =세보엠이씨!D11 -> 2160.608 | O39: ='2017'!M39+'2017'!N39 -> 31249.558 | P39: =세보엠이씨!D13 -> 21596.937 | Q39: =E39/K39 -> 0.99137869 | R39: =J39/L39 -> 0.17794651 | S39: =J39/M39 -> 3.6859077 | T39: =J39/O39 -> 3.4310624 | U39: =E39/P39 -> 6.2848461 | V39: =P39/D39*1000000 -> 2050991.2
B42: 주요가정 Summary | Q42: =AVERAGE(Q31:Q39) -> 1.2599409 | R42: =AVERAGE(R31:R39) -> 0.17406266 | S42: =AVERAGE(S31:S39) -> 6.7563575 | T42: =AVERAGE(T31:T39) -> 4.5169174 | U42: =AVERAGE(U31:U39) -> -8.1657891
B43: [1] 주가 : 2019년 3월 31일 기준 3개월 평균 주가 | Q43: =MEDIAN(Q31:Q39) -> 0.99137869 | R43: =MEDIAN(R31:R39) -> 0.18368305 | S43: =MEDIAN(S31:S39) -> 4.6986688 | T43: =MEDIAN(T31:T39) -> 4.1273421 | U43: =MEDIAN(U31:U39) -> 6.9422403
B44: [2] 발행주식수 2019년 3월 31일 발행 주식수 | Q44: =MAX(Q31:Q39) -> 3.8458834 | R44: =MAX(R31:R39) -> 0.47762708 | S44: =MAX(S31:S39) -> 19.512571 | T44: =MAX(T31:T39) -> 13.937054 | U44: =MAX(U31:U39) -> 49.931102
B45: [3] Cash : 2018년말 현금및현금성자산 및 단기금융상품 | Q45: =MIN(Q31:Q39) -> 0.53079626 | R45: =MIN(R31:R39) -> -0.30516793 | S45: =MIN(S31:S39) -> 3.5892889 | T45: =MIN(T31:T39) -> -4.6234269 | U45: =MIN(U31:U39) -> -163.0468
B46: [4] NoA : 2018년말 장기금융상품, 관계기업투자, 매도가능증권, 투자부동산, 매각예정자산, 장단기 대여금
B48: 비교 대상기업의 선정
B49: 1. 한국거래소 기업공시채널 KIND 시스템 상 제조업으로 등록된 상장회사 중, 주요 제품을 '건설업' 으로 조회. | Q49: 평균 Multiple
B50: 2. 선정회사 중 수처리, 오염저감시설 등 환경설비 건축과 거리가 먼 업종(예: 주택, 실내인테리어, 전기배선 등)회사 제외 | Q50: 구분 | R50: EV/Revenue | S50: EV/EBIT | T50: EV/EBITDA
B51: 3. 주식거래정지, 건설과 무관한 자회사 매출이 주가에 큰영향이 있는 등 비교가능성이 떨어지는 회사 제외 | Q51: HiEntech | R51: =AVERAGE(R8:R10) -> 2.5583608 | S51: =AVERAGE(S8:S10) -> 12.934582 | T51: =AVERAGE(T8:T10) -> 9.0183455
Q52: LHWS | R52: =AVERAGE(R31:R39) -> 0.17406266 | S52: =AVERAGE(S31:S39) -> 6.7563575 | T52: =AVERAGE(T31:T39) -> 4.5169174

Sheet 2016
A1: Project All
A2: Trading Multiple - 국내
A3: (Unit : KRW million, unless otherwise noted)
B5: HiEntech | K5: 2018년 12개월 기준 | Q5: Multiples
B6: 백만원 | C6: Price [1] | D6: Outstanding[2] | E6: Market Cap | F6: Debt | G6: Cash[3] | H6: NOA[4] | I6: 비지배지분 | J6: EV | K6: BV | L6: Revenue | M6: EBIT | N6: Depreciation | O6: EBITDA | P6: Net Income | Q6: PBR | R6: EV/Revenue | S6: EV/EBIT | T6: EV/EBITDA | U6: PER | V6: PEG
B7: Target(HiEntech) | C7: N/A | D7: N/A | E7: N/A | F7: 0 | G7: 0 | H7: 0 | I7: 0 | J7: N/A | K7: =하이엔텍_Dart!E47/10^6 -> 35747.682 | L7: =하이엔텍_Dart!J5/10^6 -> 155484.44 | M7: =하이엔텍_Dart!J9/10^6 -> 10219.599 | N7: =SUM(하이엔텍_Dart!J37:J38)/10^3 -> 513.603 | O7: =M7+N7 -> 10733.202 | P7: =하이엔텍_Dart!J16/10^6 -> 8449.3759
B8: ='모집단 선정(HiEntech)'!D37 -> 와이엔텍 | C8: =와이엔텍!P3 -> 3718.7097 | D8: =와이엔텍!P7/10^3 -> 17842.803 | E8: =(D8*C8)/1000 -> 66352.204 | F8: =와이엔텍!E$6 -> 59723.109 | G8: =와이엔텍!E$3 -> 9839.426 | H8: =와이엔텍!E$10 -> 3940.4277 | I8: 0 | J8: =E8+F8-G8-H8+I8 -> 112295.46 | K8: =와이엔텍!E$15 -> 96964.649 | L8: =와이엔텍!J$4 -> 58062.572 | M8: =와이엔텍!J$5 -> 9353.9505 | N8: =와이엔텍!J$6 -> 5813.819 | O8: =M8+N8 -> 15167.769 | P8: =와이엔텍!J$8 -> 5485.0208 | Q8: =E8/K8 -> 0.68429273 | R8: =J8/L8 -> 1.9340421 | S8: =J8/M8 -> 12.005137 | T8: =J8/O8 -> 7.4035579 | U8: =E8/P8 -> 12.096983 | V8: =P8/D8*1000000 -> 307408.02
B9: ='모집단 선정(HiEntech)'!D38 -> 코엔텍 | C9: =코엔텍!P$3 -> 2886.2903 | D9: =코엔텍!P7/10^3 -> 50000 | E9: =(D9*C9)/1000 -> 144314.52 | F9: =코엔텍!E$6 -> 26877 | G9: =코엔텍!E$3 -> 29156.648 | H9: =코엔텍!E$10 -> 2809.1902 | I9: =코엔텍!E66/10^6 -> 8.41041 | J9: =E9+F9-G9-H9+I9 -> 139234.09 | K9: =코엔텍!E$15 -> 110624.03 | L9: =코엔텍!J$4 -> 55095.779 | M9: =코엔텍!J$5 -> 15475.622 | N9: =코엔텍!J$6 -> 6754.7763 | O9: =M9+N9 -> 22230.398 | P9: =코엔텍!J$8 -> 14719.206 | Q9: =E9/K9 -> 1.3045494 | R9: =J9/L9 -> 2.527128 | S9: =J9/M9 -> 8.9969948 | T9: =J9/O9 -> 6.2632297 | U9: =E9/P9 -> 9.8045042 | V9: =P9/D9*1000000 -> 294384.12
B10: ='모집단 선정(HiEntech)'!D39 -> 인선이엔티 | C10: =인선이엔티!Q$3 -> 6276.129 | D10: =인선이엔티!Q7/10^3 -> 34694.211 | E10: =(D10*C10)/1000 -> 217745.34 | F10: =인선이엔티!E$6 -> 101838.3 | G10: =인선이엔티!E$3 -> 6549.2456 | H10: =인선이엔티!E$10 -> 10532.344 | I10: =인선이엔티!E46/10^6 -> 778.07736 | J10: =E10+F10-G10-H10+I10 -> 303280.13 | K10: =인선이엔티!E$15 -> 145681.01 | L10: =인선이엔티!J$4 -> 135518.95 | M10: =인선이엔티!J$5 -> 18063.943 | N10: =인선이엔티!J$6 -> 5725.421 | O10: =M10+N10 -> 23789.364 | P10: =인선이엔티!J$8 -> 7483.3587 | Q10: =E10/K10 -> 1.4946722 | R10: =J10/L10 -> 2.2379167 | S10: =J10/M10 -> 16.789254 | T10: =J10/O10 -> 12.74856 | U10: =E10/P10 -> 29.097275 | V10: =P10/D10*1000000 -> 215694.74
B13: 주요가정 Summary | Q13: =AVERAGE(Q8:Q10) -> 1.1611714 | R13: =AVERAGE(R8:R10) -> 2.233029 | S13: =AVERAGE(S8:S10) -> 12.597129 | T13: =AVERAGE(T8:T10) -> 8.8051158 | U13: =AVERAGE(U8:U10) -> 16.999587
B14: [1] 주가 : 2019년 3월 31일 기준 3개월 평균 주가 | Q14: =MEDIAN(Q8:Q10) -> 1.3045494 | R14: =MEDIAN(R8:R10) -> 2.2379167 | S14: =MEDIAN(S8:S10) -> 12.005137 | T14: =MEDIAN(T8:T10,) -> 6.8333938 | U14: =MEDIAN(U8:U10) -> 12.096983
B15: [2] 발행주식수 2019년 3월 31일 발행 주식수 | Q15: =MAX(Q8:Q10) -> 1.4946722 | R15: =MAX(R8:R10) -> 2.527128 | S15: =MAX(S8:S10) -> 16.789254 | T15: =MAX(T8:T10) -> 12.74856 | U15: =MAX(U8:U10) -> 29.097275
B16: [3] Cash : 2018년말 현금및현금성자산 및 단기금융상품 | Q16: =MIN(Q8:Q10) -> 0.68429273 | R16: =MIN(R8:R10) -> 1.9340421 | S16: =MIN(S8:S10) -> 8.9969948 | T16: =MIN(T8:T10) -> 6.2632297 | U16: =MIN(U8:U10) -> 9.8045042
B17: [4] NoA : 2018년말 장기금융상품, 관계기업투자, 매도가능증권, 투자부동산, 매각예정자산, 장단기 대여금
B19: 비교 대상기업의 선정
B20: 1. 한국거래소 기업공시채널 KIND 시스템 상 수도, 하수 및 폐기물 처리, 원료 재생업으로 등록된 상장회사로 조회
B21: 2. 대상회사의 전방산업인 하수 처리업으로 분류된 상장회사가 없으므로 대용으로 폐기물 처리업을 영위하는 회사를 선정
B22: 3. 선정된 회사 중 주요 관계기업투자에 인터넷뉴스광고업을 영위하는 회사가 있어 주가 산정이 왜곡 되거나 영업손실이 발생하여 Multiple이 비교 불가능한 회사를 제외
B28: LG-Hitachi Water Solutions | K28: 2018년 12개월 기준 | Q28: Multiples
B29: Guideline Public Company | C29: Price [1] | D29: Outstanding[2] | E29: Market Cap | F29: Debt | G29: Cash[3] | H29: NOA[4] | I29: 비지배지분 | J29: EV | K29: BV | L29: Revenue | M29: EBIT | N29: Depreciation | O29: EBITDA | P29: Net Income | Q29: PBR | R29: EV/Revenue | S29: EV/EBIT | T29: EV/EBITDA | U29: PER
B30: Target(LG-Hitachi Water Solutions) | C30: N/A | D30: N/A | E30: N/A | F30: 0 | G30: 0 | H30: 0 | I30: 0 | J30: N/A | K30: =히타치_Dart!E37/10^6 -> 64527.186 | L30: =히타치_Dart!J5/10^6 -> 417764.4 | M30: =히타치_Dart!J11/10^6 -> 36889.577 | N30: =SUM(히타치_Dart!J61:J62)/10^3 -> 2568.313 | O30: =M30+N30 -> 39457.89 | P30: =히타치_Dart!J18/10^6 -> 20158.968
B31: 웰크론한텍 | C31: =웰크론한텍!V6 -> 2798.629 | D31: =웰크론한텍!V10/10^3 -> 18021.293 | E31: =(D31*C31)/(10^3) -> 50434.914 | F31: =웰크론한텍!I6/10^6 -> 19529.136 | G31: =웰크론한텍!I3/10^6 -> 42605.556 | H31: =웰크론한텍!I10/10^6 -> 21999.67 | I31: =웰크론한텍!E73/10^6 -> 32317.45 | J31: =E31+F31-G31-H31+I31 -> 37676.273 | K31: =웰크론한텍!I16/10^6 -> 93800.114 | L31: =웰크론한텍!K31/10^6 -> 132335.96 | M31: =웰크론한텍!E5/10^6 -> -1292.2452 | N31: =웰크론한텍!E6/10^6 -> 1113.5491 | O31: =웰크론한텍!E7/10^6 -> -178.6961 | P31: =웰크론한텍!E8/10^6 -> -700.56041 | Q31: =E31/K31 -> 0.53768499 | R31: =J31/L31 -> 0.28470169 | S31: =J31/M31 -> -29.155669 | T31: =J31/O31 -> -210.83993 | U31: =E31/P31 -> -71.992241 | V31: =P31/D31*1000000 -> -38874.037
B32: 삼부토건 | C32: =삼부토건!W3 -> 5915.1613 | D32: =삼부토건!W7/10^3 -> 9758.395 | E32: =(D32*C32)/(10^3) -> 57722.48 | F32: =삼부토건!I6/10^6 -> 98610.071 | G32: =삼부토건!I3/10^6 -> 93629.91 | H32: =삼부토건!I10/10^6 -> 91843.78 | I32: =삼부토건!E99/10^6 -> -112483.48 | J32: =E32+F32-G32-H32+I32 -> -141624.62 | K32: =삼부토건!I16/10^6 -> 106601.76 | L32: =삼부토건!L25/10^6 -> 390337.42 | M32: =삼부토건!E5/10^6 -> -35105.925 | N32: =삼부토건!E6/10^6 -> 1482.647 | O32: =-삼부토건!E7/10^6 -> 33623.278 | P32: =삼부토건!E8/10^6 -> 261442.37 | Q32: =E32/K32 -> 0.54147774 | R32: =J32/L32 -> -0.36282613 | S32: =J32/M32 -> 4.0342083 | T32: =J32/O32 -> -4.2121002 | U32: =E32/P32 -> 0.22078472 | V32: =P32/D32*1000000 -> 26791534
B33: 우원개발 | C33: =우원개발!Z3 -> 4551.2903 | D33: =우원개발!Z7/10^3 -> 14650.592 | E33: =(D33*C33)/(10^3) -> 66679.098 | F33: =우원개발!I6/10^6 -> 4584.5443 | G33: =우원개발!I3/10^6 -> 21801.827 | H33: =우원개발!I10/10^6 -> 28875.704 | I33: 0 | J33: =E33+F33-G33-H33+I33 -> 20586.111 | K33: =우원개발!I16/10^6 -> 59246.041 | L33: =우원개발!L26/10^6 -> 207133.31 | M33: =우원개발!E5/10^6 -> 4017.2425 | N33: =우원개발!E6/10^6 -> 1549.0924 | O33: =우원개발!E7/10^6 -> 5566.3349 | P33: =우원개발!E8/10^6 -> 6687.1929 | Q33: =E33/K33 -> 1.1254608 | R33: =J33/L33 -> 0.099385809 | S33: =J33/M33 -> 5.1244382 | T33: =J33/O33 -> 3.6983242 | U33: =E33/P33 -> 9.971164 | V33: =P33/D33*1000000 -> 456445.24
B34: 태영건설 | C34: =태영건설!Q10 -> 5477.4194 | D34: =태영건설!Q14/10^3 -> 76400 | E34: =(D34*C34)/(10^3) -> 418474.84 | F34: =태영건설!I6 -> 1027276.1 | G34: =태영건설!I3 -> 524391.26 | H34: =태영건설!I11 -> 639810.66 | I34: =(태영건설!$C$85)/(10^6) -> 467916.59 | J34: =E34+F34-G34-H34+I34 -> 749465.58 | K34: =태영건설!I19 -> 1261379.1 | L34: =태영건설!E4 -> 2059304.9 | M34: =태영건설!E5 -> 97067.251 | N34: =태영건설!E6 -> 68707.518 | O34: =태영건설!E7 -> 165774.77 | P34: =태영건설!E8 -> 1813.339 | Q34: =E34/K34 -> 0.33175976 | R34: =J34/L34 -> 0.36394104 | S34: =J34/M34 -> 7.7210962 | T34: =J34/O34 -> 4.520987 | U34: =E34/P34 -> 230.77585 | V34: =P34/D34*1000000 -> 23734.803
B35: 현대건설 | C35: =현대건설!Q20 -> 45703.226 | D35: =현대건설!Q24/10^3 -> 111355.76 | E35: =(D35*C35)/(10^3) -> 5089317.7 | F35: =현대건설!I6 -> 2510605 | G35: =현대건설!I3 -> 3595219 | H35: =현대건설!I11 -> 1614507 | I35: =현대건설!$C$94 -> 2017762 | J35: =E35+F35-G35-H35+I35 -> 4407958.7 | K35: =현대건설!I19 -> 8124645 | L35: =현대건설!E4 -> 18825015 | M35: =현대건설!E5 -> 1158959 | N35: =현대건설!E6 -> 191201 | O35: =현대건설!E7 -> 1350160 | P35: =현대건설!E8 -> 731713 | Q35: =E35/K35 -> 0.62640493 | R35: =J35/L35 -> 0.23415432 | S35: =J35/M35 -> 3.8033776 | T35: =J35/O35 -> 3.2647676 | U35: =E35/P35 -> 6.9553468 | V35: =P35/D35*1000000 -> 6570948.5
B36: 코오롱글로벌 | C36: =코오롱글로벌!S20 -> 13125.806 | D36: =코오롱글로벌!S24/10^3 -> 16570.088 | E36: =(D36*C36)/(10^3) -> 217495.77 | F36: =코오롱글로벌!I6 -> 586679 | G36: =코오롱글로벌!I3 -> 66732.084 | H36: =코오롱글로벌!I11 -> 466652.94 | I36: =(코오롱글로벌!$C$72)/(10^6) -> 4097.9329 | J36: =E36+F36-G36-H36+I36 -> 274887.68 | K36: =코오롱글로벌!I18 -> 436212.27 | L36: =코오롱글로벌!E4 -> 3185076.1 | M36: =코오롱글로벌!E5 -> 60691.919 | N36: =코오롱글로벌!E6 -> 14320.732 | O36: =코오롱글로벌!E7 -> 75012.651 | P36: =코오롱글로벌!E8 -> 6137.3202 | Q36: =E36/K36 -> 0.49860076 | R36: =J36/L36 -> 0.086304902 | S36: =J36/M36 -> 4.5292303 | T36: =J36/O36 -> 3.6645509 | U36: =E36/P36 -> 35.43823 | V36: =P36/D36*1000000 -> 370385.49
B37: 진흥기업 | C37: =진흥기업!S20 -> 1883.3871 | D37: =진흥기업!S24/10^3 -> 139695.9 | E37: =(D37*C37)/(10^3) -> 263101.46 | F37: =진흥기업!I6 -> 31095.747 | G37: =진흥기업!I3 -> 24071.321 | H37: =진흥기업!I11 -> 88916.966 | I37: 0 | J37: =E37+F37-G37-H37+I37 -> 181208.92 | K37: =진흥기업!I18 -> -10008.709 | L37: =진흥기업!E4 -> 646578.6 | M37: =진흥기업!E5 -> 59522.026 | N37: =진흥기업!E6 -> 316.878 | O37: =진흥기업!E7 -> 59838.904 | P37: =진흥기업!E8 -> -75220.395 | Q37: =E37/K37 -> -26.287253 | R37: =J37/L37 -> 0.28025815 | S37: =J37/M37 -> 3.0444012 | T37: =J37/O37 -> 3.0282795 | U37: =E37/P37 -> -3.4977411 | V37: =P37/D37*1000000 -> -538458.13
B38: 남광토건 | C38: =남광토건!S20 -> 7410.3226 | D38: =남광토건!S24/10^3 -> 9796.455 | E38: =(D38*C38)/(10^3) -> 72594.892 | F38: =남광토건!I6 -> 9245.011 | G38: =남광토건!I3 -> 31786.665 | H38: =남광토건!I11 -> 51079.939 | I38: 0 | J38: =E38+F38-G38-H38+I38 -> -1026.7013 | K38: =남광토건!I18 -> 40652.218 | L38: =남광토건!E4 -> 183598.71 | M38: =남광토건!E5 -> -9299.0578 | N38: =남광토건!E6 -> 306.216 | O38: =남광토건!E7 -> -8992.8418 | P38: =남광토건!E8 -> -2149.1729 | Q38: =E38/K38 -> 1.7857548 | R38: =J38/L38 -> -0.0055920944 | S38: =J38/M38 -> 0.11040918 | T38: =J38/O38 -> 0.11416873 | U38: =E38/P38 -> -33.778061 | V38: =P38/D38*1000000 -> -219382.71
B39: 세보엠이씨 | C39: =세보엠이씨!R69 -> 7896.6129 | D39: =세보엠이씨!R73/10^3 -> 10530 | E39: =(D39*C39)/(10^3) -> 83151.334 | F39: =세보엠이씨!E21 -> 2629.004 | G39: =세보엠이씨!E18 -> 32843.82 | H39: =세보엠이씨!E25 -> 5957.3616 | I39: =세보엠이씨!E71/10^6 -> 529.14652 | J39: =E39+F39-G39-H39+I39 -> 47508.303 | K39: =세보엠이씨!E30 -> 117331.8 | L39: =세보엠이씨!E9 -> 387772.57 | M39: =세보엠이씨!E10 -> 19740.813 | N39: =세보엠이씨!E11 -> 1900.586 | O39: =M39+N39 -> 21641.399 | P39: =세보엠이씨!E13 -> 14067.004 | Q39: =E39/K39 -> 0.70868537 | R39: =J39/L39 -> 0.12251589 | S39: =J39/M39 -> 2.4066032 | T39: =J39/O39 -> 2.195251 | U39: =E39/P39 -> 5.9110905 | V39: =P39/D39*1000000 -> 1335897.8
B42: 주요가정 Summary | Q42: =AVERAGE(Q31:Q39) -> -2.2368249 | R42: =AVERAGE(R31:R39) -> 0.12253818 | S42: =AVERAGE(S31:S39) -> 0.17978832 | T42: =AVERAGE(T31:T39) -> -21.618411 | U42: =AVERAGE(U31:U39) -> 20.000491
B43: [1] 주가 : 2019년 3월 31일 기준 3개월 평균 주가 | Q43: =MEDIAN(Q31:Q39) -> 0.54147774 | R43: =MEDIAN(R31:R39) -> 0.12251589 | S43: =MEDIAN(S31:S39) -> 3.8033776 | T43: =MEDIAN(T31:T39) -> 3.0282795 | U43: =MEDIAN(U31:U39) -> 5.9110905
B44: [2] 발행주식수 2019년 3월 31일 발행 주식수 | Q44: =MAX(Q31:Q39) -> 1.7857548 | R44: =MAX(R31:R39) -> 0.36394104 | S44: =MAX(S31:S39) -> 7.7210962 | T44: =MAX(T31:T39) -> 4.520987 | U44: =MAX(U31:U39) -> 230.77585
B45: [3] Cash : 2018년말 현금및현금성자산 및 단기금융상품 | Q45: =MIN(Q31:Q39) -> -26.287253 | R45: =MIN(R31:R39) -> -0.36282613 | S45: =MIN(S31:S39) -> -29.155669 | T45: =MIN(T31:T39) -> -210.83993 | U45: =MIN(U31:U39) -> -71.992241
B46: [4] NoA : 2018년말 장기금융상품, 관계기업투자, 매도가능증권, 투자부동산, 매각예정자산, 장단기 대여금
B48: 비교 대상기업의 선정
B49: 1. 한국거래소 기업공시채널 KIND 시스템 상 제조업으로 등록된 상장회사 중, 주요 제품을 '건설업' 으로 조회. | Q49: 평균 Multiple
B50: 2. 선정회사 중 수처리, 오염저감시설 등 환경설비 건축과 거리가 먼 업종(예: 주택, 실내인테리어, 전기배선 등)회사 제외 | Q50: 구분 | R50: EV/Revenue | S50: EV/EBIT | T50: EV/EBITDA
B51: 3. 주식거래정지, 건설과 무관한 자회사 매출이 주가에 큰영향이 있는 등 비교가능성이 떨어지는 회사 제외 | Q51: HiEntech | R51: =AVERAGE(R8:R10) -> 2.233029 | S51: =AVERAGE(S8:S10) -> 12.597129 | T51: =AVERAGE(T8:T10) -> 8.8051158
Q52: LHWS | R52: =AVERAGE(R31:R39) -> 0.12253818 | S52: =AVERAGE(S31:S39) -> 0.17978832 | T52: =AVERAGE(T31:T39) -> -21.618411

Sheet 남광토건
B2: PL | C2: 2018 | D2: 2018 | E2: 2018 | F2: BS | G2: 2018.12.31 | H2: 2018.12.31 | I2: 2018.12.31
C3: 12mths | D3: 12mths | E3: 12mths | F3: Cash | G3: =G4+G5 -> 37821.764 | H3: =H4+H5 -> 30360.543 | I3: =I4+I5 -> 31786.665
B4: Revenue | C4: =K29/10^6 -> 157172.93 | D4: =L29/10^6 -> 115611.17 | E4: =M29/10^6 -> 183598.71 | F4: 현금및현금성자산 | G4: =C31/10^6 -> 37806.043 | H4: =D31/10^6 -> 30344.955 | I4: =E31/10^6 -> 27131.991
B5: EBIT | C5: =K33/10^6 -> 11141.645 | D5: =L33/10^6 -> 1829.2232 | E5: =M33/10^6 -> -9299.0578 | F5: 단기금융상품 | G5: =C79/10^3 -> 15.721 | H5: =D79/10^3 -> 15.588 | I5: =E79/10^3 -> 4654.674
B6: Dep | C6: =SUM(K81:K82)/10^3 -> 460.759 | D6: =SUM(L81:L82)/10^3 -> 387.408 | E6: =SUM(M81:M82)/10^3 -> 306.216 | F6: Debt | G6: =SUM(G7:G10) -> 9245.011 | H6: =SUM(H7:H10) -> 9245.011 | I6: =SUM(I7:I10) -> 9245.011
B7: EBITDA | C7: =C5+C6 -> 11602.404 | D7: =D5+D6 -> 2216.6312 | E7: =E5+E6 -> -8992.8418 | F7: 단기차입금 | G7: =F88/10^3 -> 9245.011 | H7: =G88/10^3 -> 9245.011 | I7: =H7 -> 9245.011
B8: NI(Loss) | C8: =K40/10^6 -> 5715.6746 | D8: =L40/10^6 -> 1700.2564 | E8: =M40/10^6 -> -2149.1729 | F8: 유동성장기차입금 | G8: 0 | H8: 0 | I8: 0
F9: 장기차입금 | G9: 0 | H9: 0 | I9: 0
F10: 사채 | G10: 0 | H10: 0 | I10: 0
F11: NOA | G11: =SUM(G12:G17) -> 35752.198 | H11: =SUM(H12:H17) -> 51618.944 | I11: =SUM(I12:I17) -> 51079.939
F12: 장기금융상품 | G12: =C80/10^3 -> 1435.977 | H12: =D80/10^3 -> 1446.978 | I12: =E80/10^3 -> 0
F13: 투자부동산 | G13: =C46/10^6 -> 15557.676 | H13: =D46/10^6 -> 15801.056 | I13: =E46/10^6 -> 16150.913
F14: 관계기업투자 | G14: 0 | H14: 0 | I14: 0
F15: 당기손익-공정가치측정금융자산 | G15: =C41/10^6 -> 16851.35 | H15: =(D40+D47)/10^6 -> 29925.921 | I15: =(E40+E47)/10^6 -> 30484.038
F16: 기타포괄손익-공정가치측정금융자산 | G16: =C42/10^6 -> 174.02215
F17: 대여금 | G17: =(D104+D105+D107+D108)/10^3 -> 1733.174 | H17: =(E104+E105+E107+E108)/10^3 -> 4444.989 | I17: =(F104+F105+F107+F108)/10^3 -> 4444.988
F18: BV | G18: =C72/10^6 -> 49112.604 | H18: =D72/10^6 -> 43309.99 | I18: =E72/10^6 -> 40652.218 | Q18: 종가 | R18: 상장주식수
P19: 2018-10-01~2018-12-31 | Q19: =AVERAGE(Q87:Q148) -> 15087.097 | R19: =AVERAGE(Q331:Q387) -> 6327.3684 | S19: =AVERAGE(Q574:Q636) -> 7863.6508 | T19: 종가
P20: 2019-01-01~2019-03-31 | Q20: =AVERAGE(Q28:Q86) -> 15253.39 | R20: =AVERAGE(Q270:Q330) -> 8639.8361 | S20: =AVERAGE(Q512:Q573) -> 7410.3226 | T20: 종가
P21: 2018-10-01~2019-03-31 | Q21: =AVERAGE(Q28:Q148) -> 15168.182 | R21: =AVERAGE(Q270:Q390) -> 7494.6281 | S21: =AVERAGE(Q512:Q636) -> 7638.8 | T21: 종가
P22: 2018.12.31 | Q22: =X87 -> 116946 | R22: =X331 -> 59210 | S22: =X574 -> 71318 | T22: 시가총액
B23: 연결 재무상태표 | J23: 연결 포괄손익계산서 | P23: 2019.03.31 | Q23: =X28 -> 136601 | R23: =X270 -> 181291 | S23: =X512 -> 67204 | T23: 시가총액
B24: 제 65 기 2018.12.31 현재 | J24: 제 65 기 2018.01.01 부터 2018.12.31 까지 | Q24: =Y28 -> 9827396 | R24: =Y270 -> 9826075 | S24: =Y512 -> 9796455 | T24: 상장주식수
B25: 제 64 기 2017.12.31 현재 | J25: 제 64 기 2017.01.01 부터 2017.12.31 까지 | P25: 3. 일자별시세 | AA25: 4. 제품군
B26: 제 63 기 2016.12.31 현재 | J26: 제 63 기 2016.01.01 부터 2016.12.31 까지
B27: (단위 : 원) | J27: (단위 : 원) | P27: 년/월/일 | Q27: 종가 | R27: 대비 | S27: 거래량(주) | T27: 거래대금(원) | U27: 시가 | V27: 고가 | W27: 저가 | X27: 시가총액(백만) | Y27: 상장주식수(주)
C28: 제 65 기 | D28: 제 64 기 | E28: 제 63 기 | K28: 제 65 기 | L28: 제 64 기 | M28: 제 63 기 | P28: 2019/03/29 | Q28: 13900 | R28: 950 | S28: 70318 | T28: 957954950 | U28: 13000 | V28: 13950 | W28: 12950 | X28: 136601 | Y28: 9827396
B29: 자산 | J29: 매출액 | K29: 157172930507 | L29: 115611172617 | M29: 183598711370 | P29: 2019/03/28 | Q29: 12950 | R29: -200 | S29: 23280 | T29: 304047100 | U29: 13150 | V29: 13300 | W29: 12850 | X29: 127265 | Y29: 9827396
B30: 유동자산 | C30: 99013197944 | D30: 104022537155 | E30: 112638386256 | J30: 매출원가 | K30: 132367835963 | L30: 105448288385 | M30: 184706804845 | P30: 2019/03/27 | Q30: 13150 | R30: -150 | S30: 22173 | T30: 293672050 | U30: 13550 | V30: 13550 | W30: 12950 | X30: 129230 | Y30: 9827396
B31: 현금및현금성자산 | C31: 37806043122 | D31: 30344954657 | E31: 27131991423 | J31: 매출총이익 | K31: 24805094544 | L31: 10162884232 | M31: -1108093475 | P31: 2019/03/26 | Q31: 13300 | R31: 150 | S31: 24713 | T31: 328972350 | U31: 13150 | V31: 13550 | W31: 13050 | X31: 130704 | Y31: 9827396
B32: 단기금융상품 | C32: 15721539 | D32: 15587504 | E32: 4654674199 | J32: 판매비와관리비 | K32: 13663449771 | L32: 8333661073 | M32: 8190964326 | P32: 2019/03/25 | Q32: 13150 | R32: 200 | S32: 32443 | T32: 423958700 | U32: 12800 | V32: 13350 | W32: 12700 | X32: 129230 | Y32: 9827396
B33: 매출채권 | C33: 19227353428 | D33: 35735385707 | E33: 41402800010 | J33: 영업이익(손실) | K33: 11141644773 | L33: 1829223159 | M33: -9299057801 | P33: 2019/03/22 | Q33: 12950 | R33: -300 | S33: 46864 | T33: 608967850 | U33: 13250 | V33: 13500 | W33: 12900 | X33: 127265 | Y33: 9827396
B34: 미청구공사채권 | C34: 21886157074 | D34: 7957925475 | E34: 9744829701 | J34: 기타이익 | K34: 3608077592 | L34: 4886416049 | M34: 7346166330 | P34: 2019/03/21 | Q34: 13250 | R34: -200 | S34: 30700 | T34: 409886250 | U34: 13450 | V34: 13550 | W34: 13200 | X34: 130213 | Y34: 9827396
B35: 기타채권 | C35: 16364759499 | D35: 26525678029 | E35: 24974130552 | J35: 기타손실 | K35: 3958581417 | L35: 4192073514 | M35: 976819707 | P35: 2019/03/20 | Q35: 13450 | R35: -100 | S35: 63589 | T35: 850338100 | U35: 13550 | V35: 13800 | W35: 13000 | X35: 132178 | Y35: 9827396
B36: 재고자산 | C36: 127224000 | D36: 127224000 | E36: 718195224 | J36: 금융수익 | K36: 653474251 | L36: 731611935 | M36: 1252759755 | P36: 2019/03/19 | Q36: 13550 | R36: 250 | S36: 32224 | T36: 437627900 | U36: 13300 | V36: 13800 | W36: 13300 | X36: 133161 | Y36: 9827396
B37: 기타유동자산 | C37: 3585939282 | D37: 3315781783 | E37: 4011765147 | J37: 금융원가 | K37: 5706345494 | L37: 1679205523 | M37: 824659038 | P37: 2019/03/18 | Q37: 13300 | R37: 350 | S37: 30186 | T37: 400442150 | U37: 13000 | V37: 13450 | W37: 13000 | X37: 130704 | Y37: 9827396
B38: 비유동자산 | C38: 49893449019 | D38: 62393529500 | E38: 63255492262 | J38: 법인세비용차감전순이익(손실) | K38: 5738269705 | L38: 1575972106 | M38: -2501610461 | P38: 2019/03/15 | Q38: 12950 | R38: -750 | S38: 88685 | T38: 1176017100 | U38: 13850 | V38: 13900 | W38: 12800 | X38: 127265 | Y38: 9827396
B39: 장기기타채권 | C39: 9981533137 | D39: 8700403860 | E39: 10350954288 | J39: 법인세비용 | K39: -22595108 | L39: 124284330 | M39: 352437582 | P39: 2019/03/14 | Q39: 13700 | R39: 450 | S39: 34801 | T39: 473637300 | U39: 13250 | V39: 13750 | W39: 13250 | X39: 134635 | Y39: 9827396
B40: 매도가능금융자산 | D40: 21664262393 | E40: 22250250967 | J40: 당기순이익(손실) | K40: 5715674597 | L40: 1700256436 | M40: -2149172879 | P40: 2019/03/13 | Q40: 13250 | R40: -150 | S40: 24099 | T40: 318451400 | U40: 13350 | V40: 13550 | W40: 13050 | X40: 130213 | Y40: 9827396
B41: 당기손익-공정가치 측정 지정 금융자산 | C41: 16851349780 | J41: 기타포괄손익 | K41: 80909099 | L41: 856803819 | M41: 2963769830 | P41: 2019/03/12 | Q41: 13400 | R41: 300 | S41: 51920 | T41: 698159800 | U41: 13100 | V41: 13700 | W41: 13100 | X41: 131687 | Y41: 9827396
B42: 기타포괄손익-공정가치 측정 금융자산 | C42: 174022148 | J42: 당기손익으로 재분류되지 않는항목(세후기타포괄손익) | K42: -80109930 | L42: 262849416 | M42: 637083617 | P42: 2019/03/11 | Q42: 13100 | R42: -300 | S42: 48997 | T42: 638289600 | U42: 13400 | V42: 13550 | W42: 12700 | X42: 128739 | Y42: 9827396
B43: 장기금융상품 | C43: 1435977639 | D43: 1446977639 | J43: 확정급여제도의 재측정손익(세후기타포괄손익) | K43: -40366590 | L43: 262849416 | M43: 637083617 | P43: 2019/03/08 | Q43: 13400 | R43: -400 | S43: 84329 | T43: 1127943800 | U43: 13400 | V43: 13800 | W43: 13200 | X43: 131687 | Y43: 9827396
B44: 유형자산 | C44: 3470289578 | D44: 3490661613 | E44: 2523620840 | J44: 지분법 적용대상 관계기업과 공동기업의 기타포괄손익에 대한 지분(세후기타포괄손익) | K44: -39743340 | P44: 2019/03/07 | Q44: 13800 | R44: -650 | S44: 77971 | T44: 1097291000 | U44: 14300 | V44: 14450 | W44: 13700 | X44: 135618 | Y44: 9827396
B45: 무형자산 | C45: 1618482249 | D45: 1789729812 | E45: 1996176552 | J45: 후속적으로 당기손익으로 재분류될 수 있는 항목 | K45: 161019029 | L45: 593954403 | M45: 2326686213 | P45: 2019/03/06 | Q45: 14450 | R45: -800 | S45: 81412 | T45: 1209560200 | U45: 15150 | V45: 15300 | W45: 14450 | X45: 142006 | Y45: 9827396
B46: 투자부동산 | C46: 15557675502 | D46: 15801056321 | E46: 16150912850 | J46: 해외사업장환산외환차이(세후기타포괄손익) | K46: 161019029 | L46: 177795025 | M46: 612467810 | P46: 2019/03/05 | Q46: 15250 | R46: 900 | S46: 542004 | T46: 8486133800 | U46: 14550 | V46: 17000 | W46: 13900 | X46: 149868 | Y46: 9827396
B47: 당기손익인식금융자산 | D47: 8261658698 | E47: 8233786787 | J47: 매도가능금융자산평가손익(세후기타포괄손익) | L47: 416159378 | M47: 1714218403 | P47: 2019/03/04 | Q47: 14350 | R47: -1150 | S47: 173673 | T47: 2507409800 | U47: 14000 | V47: 15100 | W47: 13850 | X47: 141023 | Y47: 9827396
B48: 기타비유동자산 | C48: 804118986 | D48: 1238779164 | E48: 1749789978 | J48: 당기총포괄손익 | K48: 5796583696 | L48: 2557060255 | M48: 814596951 | P48: 2019/02/28 | Q48: 15500 | R48: -2200 | S48: 219418 | T48: 3694722650 | U48: 18400 | V48: 18400 | W48: 15400 | X48: 152325 | Y48: 9827396
B49: 자산총계 | C49: 148906646963 | D49: 166416066655 | E49: 175893878518 | J49: 총 포괄손익의 귀속 | P49: 2019/02/27 | Q49: 17700 | R49: 700 | S49: 95062 | T49: 1667485750 | U49: 17300 | V49: 17950 | W49: 17000 | X49: 173945 | Y49: 9827396
B50: 부채 | J50: 총 포괄손익, 지배기업의 소유주에게 귀속되는 지분 | K50: 5796583696 | L50: 2557060255 | P50: 2019/02/26 | Q50: 17000 | R50: 300 | S50: 53013 | T50: 905899800 | U50: 16850 | V50: 17300 | W50: 16700 | X50: 167066 | Y50: 9827396
B51: 유동부채 | C51: 91946318090 | D51: 106398832617 | E51: 116417686536 | J51: 주당손익 | P51: 2019/02/25 | Q51: 16700 | R51: -300 | S51: 71040 | T51: 1178559250 | U51: 17250 | V51: 17250 | W51: 16100 | X51: 164118 | Y51: 9827396
B52: 단기매입채무 | C52: 20325907367 | D52: 11976068049 | E52: 15037128417 | J52: 기본주당손익 (단위 : 원) | K52: 582 | L52: 174 | M52: -219 | P52: 2019/02/22 | Q52: 17000 | R52: 350 | S52: 41889 | T52: 704231400 | U52: 16300 | V52: 17150 | W52: 16300 | X52: 167066 | Y52: 9827396
B53: 기타채무 | C53: 38704936264 | D53: 51472016059 | E53: 64693260067 | J53: 희석주당손익 (단위 : 원) | K53: 582 | L53: 174 | M53: -219 | P53: 2019/02/21 | Q53: 16650 | R53: -650 | S53: 76308 | T53: 1276963350 | U53: 17300 | V53: 17450 | W53: 16300 | X53: 163626 | Y53: 9827396
B54: 유동회생채무 | C54: 221005014 | D54: 221509244 | E54: 221509244 | P54: 2019/02/20 | Q54: 17300 | R54: -500 | S54: 63840 | T54: 1121498500 | U54: 18250 | V54: 18250 | W54: 17200 | X54: 170014 | Y54: 9827396
B55: 단기선수금 | C55: 5380810239 | D55: 7413286329 | E55: 6242460247 | P55: 2019/02/19 | Q55: 17800 | R55: 0 | S55: 56498 | T55: 1010468150 | U55: 17750 | V55: 18200 | W55: 17450 | X55: 174928 | Y55: 9827396
B56: 단기초과청구공사 | C56: 14000500099 | D56: 21393328393 | E56: 17272200191 | P56: 2019/02/18 | Q56: 17800 | R56: 150 | S56: 46042 | T56: 814350250 | U56: 18000 | V56: 18150 | W56: 17350 | X56: 174928 | Y56: 9827396
B57: 단기차입금 | C57: 9245011352 | D57: 9245011352 | E57: 9245011352 | J57: (2) 발생한 비용(포괄손익계산서의 매출원가 및 판매비와관리비)의 성격별 분류 | P57: 2019/02/15 | Q57: 17650 | R57: 150 | S57: 78810 | T57: 1371029250 | U57: 17000 | V57: 17800 | W57: 16950 | X57: 173454 | Y57: 9827396
B58: 충당부채 | C58: 4068147755 | D58: 4677613191 | E58: 3706117018 | J58: (단위: 천원) | P58: 2019/02/14 | Q58: 17500 | R58: -700 | S58: 108857 | T58: 1912109500 | U58: 18300 | V58: 18300 | W58: 17200 | X58: 171979 | Y58: 9827396
B59: 비유동부채 | C59: 7847725370 | D59: 16707244231 | E59: 18823974050 | J59: 구 분 | K59: 2018 | L59: 2017 | P59: 2019/02/13 | Q59: 18200 | R59: -300 | S59: 67985 | T59: 1231897350 | U59: 18350 | V59: 18650 | W59: 17800 | X59: 178859 | Y59: 9827396
B60: 순확정급여부채 | C60: 130136877 | D60: 2445616715 | E60: 3204237148 | J60: 자재비 | K60: 15237877 | L60: 13925699 | P60: 2019/02/12 | Q60: 18500 | R60: -300 | S60: 81572 | T60: 1513374500 | U60: 18350 | V60: 18900 | W60: 18300 | X60: 181807 | Y60: 9827396
B61: 충당부채 | C61: 7394294996 | D61: 5761718471 | E61: 7119827857 | J61: 종업원급여(*) | K61: 23765115 | L61: 16115521 | P61: 2019/02/11 | Q61: 18800 | R61: 450 | S61: 179973 | T61: 3441236400 | U61: 19350 | V61: 20100 | W61: 18750 | X61: 184755 | Y61: 9827396
B62: 기타비유동금융부채 | C62: 323293497 | D62: 8499909045 | E62: 8499909045 | J62: 감가상각비(*) | K62: 441689 | L62: 343402 | P62: 2019/02/08 | Q62: 18350 | R62: -250 | S62: 103141 | T62: 1891664150 | U62: 18500 | V62: 18800 | W62: 18000 | X62: 180333 | Y62: 9827396
B63: 부채총계 | C63: 99794043460 | D63: 123106076848 | E63: 135241660586 | J63: 무형자산상각비 | K63: 19070 | L63: 44006 | P63: 2019/02/07 | Q63: 18600 | R63: 500 | S63: 174810 | T63: 3253833400 | U63: 19500 | V63: 19700 | W63: 18000 | X63: 182790 | Y63: 9827396
B64: 자본 | J64: 지급수수료 | K64: 22928643 | L64: 13833361 | P64: 2019/02/01 | Q64: 18100 | R64: 950 | S64: 224584 | T64: 3991313700 | U64: 17500 | V64: 18350 | W64: 17000 | X64: 177876 | Y64: 9827396
B65: 지배기업의 소유주에게 귀속되는 자본 | C65: 49112603503 | D65: 43309989807 | E65: 40652217932 | J65: 외주비 | K65: 49789823 | L65: 56662571 | P65: 2019/01/31 | Q65: 17150 | R65: 150 | S65: 173567 | T65: 2987703050 | U65: 17550 | V65: 18000 | W65: 16550 | X65: 168540 | Y65: 9827396
B66: 자본금 | C66: 49136980000 | D66: 49095925000 | E66: 48982275000 | J66: 기타 | K66: 33849068 | L66: 12857389 | P66: 2019/01/30 | Q66: 17000 | R66: 1500 | S66: 446097 | T66: 7576315050 | U66: 16000 | V66: 17850 | W66: 15750 | X66: 167066 | Y66: 9827396
B67: 주식발행초과금 | C67: -32378109910 | D67: -32387706460 | E67: -32463319410 | J67: 합 계 | K67: 146031285 | L67: 113781949 | P67: 2019/01/29 | Q67: 15500 | R67: -500 | S67: 92217 | T67: 1443875400 | U67: 16150 | V67: 16150 | W67: 15200 | X67: 152325 | Y67: 9827396
B68: 기타포괄손익누계액 | C68: -1702882778 | D68: -190313850 | E68: -784268253 | J68: (*) 종업원급여는 급여, 퇴직급여 및 복리후생비가 포함되어 있으며, 감가상각비는 유형자산 및 투자부동산 상각비가 포함되어 있습니다. | P68: 2019/01/28 | Q68: 16000 | R68: 300 | S68: 80772 | T68: 1289915250 | U68: 15700 | V68: 16300 | W68: 15700 | X68: 157238 | Y68: 9827396
B69: 기타자본구성요소 | C69: 18316896373 | D69: 18361517923 | E69: 885981158078 | P69: 2019/01/25 | Q69: 15700 | R69: 250 | S69: 49784 | T69: 780439700 | U69: 15800 | V69: 15800 | W69: 15500 | X69: 154290 | Y69: 9827396
B70: 이익잉여금(결손금) | C70: 15739719818 | D70: 8430567194 | E70: -861063627483 | P70: 2019/01/24 | Q70: 15450 | R70: -250 | S70: 47390 | T70: 737209050 | U70: 15800 | V70: 15900 | W70: 15400 | X70: 151833 | Y70: 9827396
B71: 비지배지분 | P71: 2019/01/23 | Q71: 15700 | R71: -100 | S71: 63564 | T71: 995482150 | U71: 15550 | V71: 15900 | W71: 15350 | X71: 154290 | Y71: 9827396
B72: 자본총계 | C72: 49112603503 | D72: 43309989807 | E72: 40652217932 | P72: 2019/01/22 | Q72: 15800 | R72: 200 | S72: 74286 | T72: 1175862400 | U72: 15750 | V72: 16300 | W72: 15500 | X72: 155273 | Y72: 9827396
B73: 자본과부채총계 | C73: 148906646963 | D73: 166416066655 | E73: 175893878518 | P73: 2019/01/21 | Q73: 15600 | R73: -200 | S73: 68023 | T73: 1069233300 | U73: 16250 | V73: 16300 | W73: 15450 | X73: 153307 | Y73: 9827396
P74: 2019/01/18 | Q74: 15800 | R74: -350 | S74: 100005 | T74: 1587540000 | U74: 16100 | V74: 16350 | W74: 15450 | X74: 155273 | Y74: 9827396
P75: 2019/01/17 | Q75: 16150 | R75: 200 | S75: 141981 | T75: 2303053150 | U75: 17000 | V75: 17000 | W75: 15550 | X75: 158712 | Y75: 9827396
B76: 9. 장ㆍ단기금융상품 | P76: 2019/01/16 | Q76: 15950 | R76: 900 | S76: 273842 | T76: 4348559900 | U76: 15250 | V76: 16500 | W76: 15050 | X76: 156747 | Y76: 9827396
B77: (단위: 천원) | G77: (단위: 천원) | J77: (단위: 천원) | P77: 2019/01/15 | Q77: 15050 | R77: 50 | S77: 69279 | T77: 1040636550 | U77: 15300 | V77: 15300 | W77: 14800 | X77: 147902 | Y77: 9827396
B78: 구 분 | C78: 2018 | D78: 2017 | E78: 2016 | G78: 구 분 | H78: 2017 | J78: 구 분 | K78: 2018 | L78: 2017 | P78: 2019/01/14 | Q78: 15000 | R78: 250 | S78: 78747 | T78: 1184060550 | U78: 15300 | V78: 15300 | W78: 14850 | X78: 147411 | Y78: 9827396
B79: 단기금융상품 | C79: 15721 | D79: 15588 | E79: 4654674 | G79: 단기금융상품 | H79: 15588 | J79: 현금의 유출이 없는 비용 등 가산 | P79: 2019/01/11 | Q79: 14750 | R79: 500 | S79: 90477 | T79: 1331584600 | U79: 14500 | V79: 14950 | W79: 14300 | X79: 144954 | Y79: 9827396
B80: 장기금융상품(*) | C80: 1435977 | D80: 1446978 | G80: 장기금융상품(*) | H80: 1446978 | J80: 퇴직급여 | K80: 923059 | L80: 810901 | P80: 2019/01/10 | Q80: 14250 | R80: -400 | S80: 74446 | T80: 1070995500 | U80: 14950 | V80: 14950 | W80: 14150 | X80: 140040 | Y80: 9827396
B81: (*) 당기말 현재 장기금융상품 중 1,433백만원은 계약이행보증 등과 관련하여 담보 및 질권 등이 설정되어 사용이 제한되어 있으며, 3백만원은 당좌개설보증금으로 사용이 제한되어 있습니다(주석 29참조). | J81: 감가상각비 | K81: 441689 | L81: 343402 | M81: 252647 | P81: 2019/01/09 | Q81: 14650 | R81: 300 | S81: 175923 | T81: 2624843250 | U81: 14650 | V81: 15500 | W81: 14350 | X81: 143971 | Y81: 9827396
J82: 무형자산상각비 | K82: 19070 | L82: 44006 | M82: 53569 | P82: 2019/01/08 | Q82: 14350 | R82: 1300 | S82: 671704 | T82: 9915541550 | U82: 13250 | V82: 15850 | W82: 13050 | X82: 141023 | Y82: 9827396
J83: 대손상각비 | K83: -150672 | L83: 166434 | P83: 2019/01/07 | Q83: 13050 | R83: 450 | S83: 72374 | T83: 936925600 | U83: 13200 | V83: 13250 | W83: 12700 | X83: 128248 | Y83: 9827396
J84: 기타의대손상각비 | K84: - | L84: 789760 | P84: 2019/01/04 | Q84: 12600 | R84: -100 | S84: 61216 | T84: 759832300 | U84: 12650 | V84: 12700 | W84: 12100 | X84: 123825 | Y84: 9827396
B85: 17. 단기차입금 | J85: 외화환산손실 | K85: - | L85: 213354 | P85: 2019/01/03 | Q85: 12700 | R85: 700 | S85: 143163 | T85: 1802169950 | U85: 12000 | V85: 13050 | W85: 11750 | X85: 124808 | Y85: 9827396
B86: (단위: 천원) | J86: 매도가능금융자산처분손실 | K86: - | L86: 31078 | P86: 2019/01/02 | Q86: 12000 | R86: 100 | S86: 48034 | T86: 584359650 | U86: 12550 | V86: 12600 | W86: 11800 | X86: 117929 | Y86: 9827396
B87: 구 분 | C87: 차입일 | D87: 만기일 | E87: 연이자율 | F87: 2018 | G87: 2017 | J87: 충당부채전입 | K87: 341197 | L87: - | P87: 2018/12/28 | Q87: 11900 | R87: 50 | S87: 37853 | T87: 451251400 | U87: 11850 | V87: 12100 | W87: 11750 | X87: 116946 | Y87: 9827396
B88: 건설공제조합 | C88: 43159 | D88: 43523 | E88: 0.0143 | F88: 9245011 | G88: 9245011 | J88: 당기손익-공정가치측정금융자산평가손실 | K88: 5251988 | L88: - | P88: 2018/12/27 | Q88: 11850 | R88: 350 | S88: 36239 | T88: 427380000 | U88: 11550 | V88: 12050 | W88: 11500 | X88: 116455 | Y88: 9827396
B89: (*) 단기차입금과 관련하여 건설공제조합 출자금(장부금액 16,566백만원)이 담보로 제공되어 있습니다(주석 10, 29 참조). | J89: 당기손익-공정가치측정금융자산처분손실 | K89: 16667 | L89: - | P89: 2018/12/26 | Q89: 11500 | R89: -650 | S89: 46360 | T89: 538367800 | U89: 11550 | V89: 11900 | W89: 11450 | X89: 113015 | Y89: 9827396
J90: 금융보증부채전입액 | K90: 85043 | L90: - | P90: 2018/12/24 | Q90: 12150 | R90: -50 | S90: 32933 | T90: 397556850 | U90: 12300 | V90: 12350 | W90: 11900 | X90: 119387 | Y90: 9826075
B91: 6. 매출채권, 기타채권 및 장기기타채권 | J91: 매도가능금융자산손상차손 | K91: - | L91: 1011075 | P91: 2018/12/21 | Q91: 12200 | R91: -50 | S91: 49450 | T91: 600779700 | U91: 12350 | V91: 12350 | W91: 11950 | X91: 119878 | Y91: 9826075
B92: (단위: 천원) | J92: 이자비용 | K92: 132204 | L92: 132204 | P92: 2018/12/20 | Q92: 12250 | R92: 300 | S92: 71017 | T92: 860311650 | U92: 11900 | V92: 12450 | W92: 11800 | X92: 120369 | Y92: 9826075
B93: 구 분 | C93: 내 역 | D93: 2018 | E93: 2017 | J93: 법인세비용 | K93: 22595 | L93: - | P93: 2018/12/19 | Q93: 11950 | R93: -50 | S93: 67422 | T93: 804575450 | U93: 12350 | V93: 12350 | W93: 11750 | X93: 117422 | Y93: 9826075
B94: 매출채권 | C94: 매출채권(*) | D94: 324538816 | E94: 373886617 | J94: 잡손실 | K94: 6030 | L94: 2324764 | P94: 2018/12/18 | Q94: 12000 | R94: -700 | S94: 101769 | T94: 1242891900 | U94: 12550 | V94: 12600 | W94: 12000 | X94: 117913 | Y94: 9826075
C95: (대손충당금) | D95: -305311462 | E95: -338151231 | J95: 무형자산손상차손 | K95: 152177 | L95: 162441 | P95: 2018/12/17 | Q95: 12700 | R95: 300 | S95: 76885 | T95: 954319350 | U95: 12050 | V95: 12750 | W95: 12000 | X95: 124791 | Y95: 9826075
C96: 합 계 | D96: 19227354 | E96: 35735386 | J96: 합 계 | K96: 7241047 | L96: 6029419 | P96: 2018/12/14 | Q96: 12400 | R96: -1050 | S96: 176275 | T96: 2226461500 | U96: 13400 | V96: 13400 | W96: 12300 | X96: 121843 | Y96: 9826075
B97: 미청구공사채권 | C97: 미청구공사채권 | D97: 23668126 | E97: 9878329 | J97: 현금의 유입이 없는 수익 등 차감 | P97: 2018/12/13 | Q97: 13450 | R97: -1000 | S97: 477540 | T97: 6223739250 | U97: 14050 | V97: 14050 | W97: 12200 | X97: 132161 | Y97: 9826075
C98: (대손충당금) | D98: -1781969 | E98: -1920404 | J98: 외화환산이익 | K98: 77592 | L98: - | P98: 2018/12/12 | Q98: 14450 | R98: -400 | S98: 50624 | T98: 737245700 | U98: 14500 | V98: 15250 | W98: 14300 | X98: 141987 | Y98: 9826075
C99: 합 계 | D99: 21886157 | E99: 7957925 | J99: 하자보수충당부채환입 | K99: - | L99: 1034786 | P99: 2018/12/11 | Q99: 14850 | R99: -650 | S99: 37356 | T99: 559352050 | U99: 15200 | V99: 15800 | W99: 14750 | X99: 145917 | Y99: 9826075
B100: 기타채권 | C100: 미수금 | D100: 64898760 | E100: 74144138 | J100: 공사손실충당부채환입 | K100: 2730510 | L100: 1893843 | P100: 2018/12/10 | Q100: 15500 | R100: -1000 | S100: 62477 | T100: 984365600 | U100: 15800 | V100: 16150 | W100: 15300 | X100: 152304 | Y100: 9826075
C101: (대손충당금) | D101: -49770154 | E101: -52072782 | J101: 소송충당부채환입 | K101: - | L101: 9340 | P101: 2018/12/07 | Q101: 16500 | R101: 1050 | S101: 89492 | T101: 1449187150 | U101: 15500 | V101: 16600 | W101: 15500 | X101: 162130 | Y101: 9826075
...

Sheet 세보엠이씨
B3: 세보이엠씨
B4: 원 | C4: 2018.10.01-2019.03.29 | D4: 2019.01.01-2019.03.29 | E4: 2018.10.1-2018.12.31 | F4: MRK
B5: 종가 | C5: =AVERAGE(P77:P197) -> 9521.8182 | D5: =AVERAGE(P77:P135) -> 9984.9153 | E5: =AVERAGE(P136:P197) -> 9081.129 | F5: =AVERAGE(W77:W135) -> 105141.15
A7: 1. PL | C7: 2018 | D7: 2017 | E7: 2016
B8: KRW m | C8: 12month | D8: 12month | E8: 12month
B9: Revenue | C9: =SUMIFS(H:H,$F:$F,"매출")/10^6 -> 473844.41 | D9: =SUMIFS(I:I,$F:$F,"매출")/10^6 -> 602536.02 | E9: =SUMIFS(J:J,$F:$F,"매출")/10^6 -> 387772.57
B10: EBIT | C10: =SUMIFS(H:H,$F:$F,"영업이익")/10^6 -> 27985.354 | D10: =SUMIFS(I:I,$F:$F,"영업이익")/10^6 -> 29088.95 | E10: =SUMIFS(J:J,$F:$F,"영업이익")/10^6 -> 19740.813
B11: Dep | C11: =SUM(M36:M37)/10^3 -> 4126.767 | D11: =SUM(N36:N37)/10^3 -> 2160.608 | E11: =SUM(O36:O37)/10^3 -> 1900.586
B12: EBITDA | C12: =C10+C11 -> 32112.121 | D12: =D10+D11 -> 31249.558 | E12: =E10+E11 -> 21641.399
B13: NI(Loss) | C13: =SUMIFS(H:H,$F:$F,"당기순이익")/10^6 -> 21156.52 | D13: =SUMIFS(I:I,$F:$F,"당기순이익")/10^6 -> 21596.937 | E13: =SUMIFS(J:J,$F:$F,"당기순이익")/10^6 -> 14067.004
A16: 2. BS | C16: 2018 | D16: 2017 | E16: 2016
B17: KRW m | C17: 43830 | D17: 43830 | E17: 43830
B18: Cash | C18: =SUM(C19:C20) -> 19185.185 | D18: =SUM(D19:D20) -> 24724.522 | E18: =SUM(E19:E20) -> 32843.82
B19: 현금및현금성자산 | C19: =SUMIFS(C$35:C$142,$A$35:$A$142,$B19)/10^6 -> 19185.185 | D19: =SUMIFS(D$35:D$142,$A$35:$A$142,$B19)/10^6 -> 22836.522 | E19: =SUMIFS(E$35:E$142,$A$35:$A$142,$B19)/10^6 -> 32843.82
B20: 단기금융상품 | C20: =SUMIFS(C$35:C$142,$A$35:$A$142,$B20)/10^6 -> 0 | D20: =SUMIFS(D$35:D$142,$A$35:$A$142,$B20)/10^6 -> 1888 | E20: =SUMIFS(E$35:E$142,$A$35:$A$142,$B20)/10^6 -> 0
B21: Debt | C21: =SUM(C22:C24) -> 11620 | D21: =SUM(D22:D24) -> 4000 | E21: =SUM(E22:E24) -> 2629.004
B22: 단기차입금 | C22: =SUMIFS(C$35:C$142,$A$35:$A$142,$B22)/10^6 -> 11620 | D22: =SUMIFS(D$35:D$142,$A$35:$A$142,$B22)/10^6 -> 4000 | E22: =SUMIFS(E$35:E$142,$A$35:$A$142,$B22)/10^6 -> 2629.004
B23: 장기차입금 | C23: =SUMIFS(C$35:C$142,$A$35:$A$142,$B23)/10^6 -> 0 | D23: =SUMIFS(D$35:D$142,$A$35:$A$142,$B23)/10^6 -> 0 | E23: =SUMIFS(E$35:E$142,$A$35:$A$142,$B23)/10^6 -> 0
B24: 사채 | C24: =SUMIFS(C$35:C$142,$A$35:$A$142,$B24)/10^6 -> 0 | D24: =SUMIFS(D$35:D$142,$A$35:$A$142,$B24)/10^6 -> 0 | E24: =SUMIFS(E$35:E$142,$A$35:$A$142,$B24)/10^6 -> 0
B25: NOA | C25: =SUM(C26:C29) -> 9975.4092 | D25: =SUM(D26:D29) -> 6308.3101 | E25: =SUM(E26:E29) -> 5957.3616
B26: 장기금융상품 | C26: =SUMIFS(C$35:C$142,$A$35:$A$142,$B26)/10^6 -> 9975.4092 | D26: =SUMIFS(D$35:D$142,$A$35:$A$142,$B26)/10^6 -> 6308.3101 | E26: =SUMIFS(E$35:E$142,$A$35:$A$142,$B26)/10^6 -> 5957.3616
B27: 투자부동산 | C27: =SUMIFS(C$35:C$142,$A$35:$A$142,$B27)/10^6 -> 0 | D27: =SUMIFS(D$35:D$142,$A$35:$A$142,$B27)/10^6 -> 0 | E27: =SUMIFS(E$35:E$142,$A$35:$A$142,$B27)/10^6 -> 0
B28: 관계기업투자 | C28: =SUMIFS(C$35:C$142,$A$35:$A$142,$B28)/10^6 -> 0 | D28: =SUMIFS(D$35:D$142,$A$35:$A$142,$B28)/10^6 -> 0 | E28: =SUMIFS(E$35:E$142,$A$35:$A$142,$B28)/10^6 -> 0
B29: 장단기대여금 | C29: =SUMIFS(C$35:C$142,$A$35:$A$142,$B29)/10^6 -> 0 | D29: =SUMIFS(D$35:D$142,$A$35:$A$142,$B29)/10^6 -> 0 | E29: =SUMIFS(E$35:E$142,$A$35:$A$142,$B29)/10^6 -> 0
B30: BV | C30: =(C51-C63)/10^6 -> 158899.63 | D30: =(D51-D63)/10^6 -> 136913.8 | E30: =(E51-E63)/10^6 -> 117331.8
A32: 3. 연결 FS | B32: Source : Dart
B33: B/S | C33: (단위 : 원) | G33: I/S | H33: (단위 : 원) | M33: (단위 : 천원)
C34: 2018 | D34: 2017 | E34: 2016 | H34: 2018 | I34: 2017 | J34: 2016 | M34: 2018 | N34: 2017 | O34: 2016
B35: 자산 | F35: 매출 | G35: 매출액 | H35: 473844414558 | I35: 602536022166 | J35: 387772566913 | L35: 감가상각비 | M35: =SUM(M36:M37) -> 4126767 | N35: =SUM(N36:N37) -> 2160608 | O35: =SUM(O36:O37) -> 1900586
B36: 유동자산 | C36: 190801811189 | D36: 206788690101 | E36: 160464571091 | G36: 매출원가 | H36: 432375010077 | I36: 559493048617 | J36: 354577305885 | L36: 유형자산상각비 | M36: 2079986 | N36: 2046781 | O36: 1728834
A37: 현금및현금성자산 | B37: 현금및현금성자산 | C37: 19185184590 | D37: 22836521921 | E37: 32843820037 | G37: 매출총이익 | H37: 41469404481 | I37: 43042973549 | J37: 33195261028 | L37: 무형자산상각비 | M37: 2046781 | N37: 113827 | O37: 171752
A38: 단기금융상품 | B38: 단기금융상품 | D38: 1888000000 | G38: 판매비와관리비 | H38: 13484050956 | I38: 13954023360 | J38: 13454448100
B39: 매출채권 및 기타유동채권 | C39: 41443207220 | D39: 69788427256 | E39: 44282204093 | F39: 영업이익 | G39: 영업이익 | H39: 27985353525 | I39: 29088950189 | J39: 19740812928
B40: 미청구공사 | C40: 111541792398 | D40: 88749878010 | E40: 62701285568 | G40: 금융수익 | H40: 911533567 | I40: 566724225 | J40: 1336243426
B41: 재고자산 | C41: 13259348690 | D41: 8387560190 | E41: 4966689524 | G41: 금융비용 | H41: 628604419 | I41: 1576063194 | J41: 258514682
B42: 기타유동자산 | C42: 5372278291 | D42: 15138302724 | E42: 15670571869 | G42: 기타영업외수익 | H42: 1263467634 | I42: 911285930 | J42: 1671286649
B43: 비유동자산 | C43: 55604001487 | D43: 50925303865 | E43: 47632856329 | G43: 기타영업외비용 | H43: 137478634 | I43: 497858429 | J43: 141661050
A44: 장기금융상품 | B44: 장기금융상품 | C44: 21945320 | D44: 21945320 | E44: 21945320 | G44: 지분법적용투자이익 | J44: 44745291
A45: 장기금융상품 | B45: 장기금융자산 | C45: 9953463862 | G45: 법인세비용차감전이익 | H45: 29394271673 | I45: 28493038721 | J45: 22392912562
A46: 장기금융상품 | B46: 매도가능금융자산 | D46: 6286364812 | E46: 5935416283 | G46: 법인세비용 | H46: 8237751859 | I46: 6896101741 | J46: 8325908528
B47: 유형자산 | C47: 31419709849 | D47: 30266707849 | E47: 29032937912 | F47: 당기순이익 | G47: 당기순이익 | H47: 21156519814 | I47: 21596936980 | J47: 14067004034
B48: 무형자산 | C48: 3757427881 | D48: 3799932329 | E48: 3928853804 | G48: 당기순이익의 귀속
B49: 이연법인세자산 | C49: 1094616448 | D49: 1173390722 | E49: 840707017 | G49: 지배기업 소유주지분 | H49: 21747106548 | I49: 23636451342 | J49: 14188434217
B50: 기타비유동자산 | C50: 9356838127 | D50: 9376962833 | E50: 7872995993 | G50: 비지배지분 | H50: -590586734 | I50: -2039514362 | J50: -121430183
B51: 자산총계 | C51: 246405812676 | D51: 257713993966 | E51: 208097427420 | G51: 기타포괄손익 | H51: 882450739 | I51: -14025218 | J51: 324976624
B52: 부채 | G52: 당기손익으로 재분류될 수 있는 항목(세후기타포괄손익) | H52: 79735337 | I52: -588723919 | J52: 78774495
B53: 유동부채 | C53: 85688419477 | D53: 117864286815 | E53: 88467322960 | G53: 해외사업장순투자의 위험회피손익(세후기타포괄손익) | H53: 79735337 | I53: -583573309 | J53: 75576451
B54: 매입채무및기타채무 | C54: 53952725391 | D54: 78704031849 | E54: 64234985449 | G54: 매도가능금융자산평가손익 | I54: -5150610 | J54: 16281840
A55: 단기차입금 | B55: 단기차입금 | C55: 11620000000 | D55: 4000000000 | E55: 2629004000 | G55: 지분법자본변동 | J55: -13083796
B56: 초과청구공사 | C56: 5516728884 | D56: 10977756304 | E56: 5929826263 | G56: 당기손익으로 재분류되지 않는항목(세후기타포괄손익) | H56: 802715402 | I56: 574698701 | J56: 246202129
B57: 기타유동부채 | C57: 8448494559 | D57: 17693745030 | E57: 11459974902 | G57: 확정급여제도의 재측정손익 | H57: 306687782 | I57: 574698701 | J57: 246202129
B58: 당기법인세부채 | C58: 6150470643 | D58: 6488753632 | E58: 4213532346 | G58: 장기금융자산평가손익 | H58: 496027620
B59: 비유동부채 | C59: 1817759270 | D59: 2935904465 | E59: 2298299936 | G59: 총포괄손익 | H59: 22038970553 | I59: 21582911762 | J59: 14391980658
B60: 장기매입채무 및 기타비유동채무 | C60: 44180000 | E60: 17186979 | G60: 총 포괄손익의 귀속
B61: 확정급여채무 | C61: 1091520105 | D61: 2302693320 | E61: 1688886870 | G61: 지배기업 소유주지분 | H61: 22631893474 | I61: 23593467901 | J61: 14529140535
B62: 기타충당부채 | C62: 682059165 | D62: 633211145 | E62: 592226087 | G62: 비지배지분 | H62: -592922921 | I62: -2010556139 | J62: 137159877
B63: 부채총계 | C63: 87506178747 | D63: 120800191280 | E63: 90765622896 | G63: 주당이익
B64: 자본 | G64: 기본주당이익(손실) (단위 : 원) | H64: 2174 | I64: 2362 | J64: 1418
B65: 지배기업의 소유주에게 귀속되는 자본 | C65: 160973966473 | D65: 138395212309 | E65: 116802658008 | G65: 희석주당이익(손실) (단위 : 원) | H65: 2174 | I65: 2362 | J65: 1418
B66: 자본금 | C66: 5265000000 | D66: 5265000000 | E66: 5265000000
B67: 자본잉여금 | C67: 526141894 | D67: 526141894 | E67: 526141894
B68: 자본조정 | C68: -1895644300 | D68: -1895644300 | E68: -1895644300 | M68: 2018-10-01~2018-12-31 | P68: =AVERAGE(P136:P197) -> 9081.129 | Q68: =AVERAGE(P380:P436) -> 11111.404 | R68: =AVERAGE(P623:P685) -> 8053.4921 | S68: 종가
B69: 기타포괄손익누계액 | C69: 3599800655 | D69: 278142269 | E69: 321125710 | M69: 2019-01-01~2019-03-31 | P69: =AVERAGE(P77:P135) -> 9984.9153 | Q69: =AVERAGE(P319:P379) -> 12890.164 | R69: =AVERAGE(P561:P622) -> 7896.6129 | S69: 종가
B70: 이익잉여금 | C70: 153478668224 | D70: 134221572446 | E70: 112586034704 | M70: 2018-10-01~2019-03-31 | P70: =AVERAGE(P77:P197) -> 9521.8182 | Q70: =AVERAGE(P319:P439) -> 12029.339 | R70: =AVERAGE(P561:P685) -> 7975.68 | S70: 종가
B71: 비지배지분 | C71: -2074332544 | D71: -1481409623 | E71: 529146516 | M71: 2018.12.31 | P71: =W136 -> 96876 | Q71: =W380 -> 130572 | R71: =W623 -> 85504 | S71: 시가총액
B72: 자본총계 | C72: 158899633929 | D72: 136913802686 | E72: 117331804524 | M72: 2019.03.31 | P72: =W77 -> 124780 | Q72: =W319 -> 129519 | R72: =W561 -> 86346 | S72: 시가총액
B73: 자본과부채총계 | C73: 246405812676 | D73: 257713993966 | E73: 208097427420 | P73: =X77 -> 10530000 | Q73: =X319 -> 10530000 | R73: =X561 -> 10530000 | S73: 상장주식수
N75: 4. 일자별 시세
M76: 년/월/일 | P76: 종가 | Q76: 대비 | R76: 거래량(주) | S76: 거래대금(원) | T76: 시가 | U76: 고가 | V76: 저가 | W76: 시가총액(백만) | X76: 상장주식수(주)
M77: 2019/03/29 | P77: 11850 | Q77: -200 | R77: 410808 | S77: 4801113500 | T77: 12150 | U77: 12300 | V77: 11300 | W77: 124780 | X77: 10530000
M78: 2019/03/28 | P78: 12050 | Q78: 100 | R78: 959583 | S78: 11971733500 | T78: 12300 | U78: 13100 | V78: 11900 | W78: 126886 | X78: 10530000
M79: 2019/03/27 | P79: 11950 | Q79: 1150 | R79: 2303011 | S79: 28437212150 | T79: 11300 | U79: 13100 | V79: 11250 | W79: 125834 | X79: 10530000
M80: 2019/03/26 | P80: 10800 | Q80: -150 | R80: 480004 | S80: 5376165300 | T80: 11300 | U80: 11700 | V80: 10750 | W80: 113724 | X80: 10530000
M81: 2019/03/25 | P81: 10950 | Q81: 800 | R81: 544895 | S81: 5903101350 | T81: 10300 | U81: 11250 | V81: 10200 | W81: 115304 | X81: 10530000
M82: 2019/03/22 | P82: 10150 | Q82: 100 | R82: 36774 | S82: 373109250 | T82: 10150 | U82: 10200 | V82: 10050 | W82: 106880 | X82: 10530000
M83: 2019/03/21 | P83: 10050 | Q83: -50 | R83: 42718 | S83: 431653110 | T83: 10050 | U83: 10350 | V83: 9970 | W83: 105826 | X83: 10530000
M84: 2019/03/20 | P84: 10100 | Q84: 240 | R84: 26611 | S84: 265000850 | T84: 9860 | U84: 10100 | V84: 9830 | W84: 106353 | X84: 10530000
M85: 2019/03/19 | P85: 9860 | Q85: -140 | R85: 29538 | S85: 293066280 | T85: 10050 | U85: 10100 | V85: 9850 | W85: 103826 | X85: 10530000
M86: 2019/03/18 | P86: 10000 | Q86: 50 | R86: 25170 | S86: 252203600 | T86: 9970 | U86: 10250 | V86: 9950 | W86: 105300 | X86: 10530000
M87: 2019/03/15 | P87: 9950 | Q87: -150 | R87: 28430 | S87: 283602720 | T87: 10100 | U87: 10150 | V87: 9900 | W87: 104774 | X87: 10530000
M88: 2019/03/14 | P88: 10100 | Q88: 320 | R88: 66575 | S88: 667593720 | T88: 9880 | U88: 10200 | V88: 9750 | W88: 106353 | X88: 10530000
... M685: 2016/10/04 | P685: 8780 | Q685: -180 | R685: 144470 | S685: 1272492540 | T685: 8950 | U685: 9080 | V685: 8610 | W685: 92453 | X685: 10530000

Sheet 진흥기업
B2: PL | C2: 2018 | D2: 2018 | E2: 2018 | F2: BS | G2: 2018.12.31 | H2: 2018.12.31 | I2: 2018.12.31
C3: 12mths | D3: 12mths | E3: 12mths | F3: Cash | G3: =G4+G5 -> 13320.055 | H3: =H4+H5 -> 47742.058 | I3: =I4+I5 -> 24071.321
B4: Revenue | C4: =K29/10^6 -> 671155.39 | D4: =L29/10^6 -> 573309.88 | E4: =M29/10^6 -> 646578.6 | F4: 현금및현금성자산 | G4: =C31/10^6 -> 12555.53 | H4: =D31/10^6 -> 46977.533 | I4: =E31/10^6 -> 23306.796
B5: EBIT | C5: =K33/10^6 -> 35051.376 | D5: =L33/10^6 -> 41610.597 | E5: =M33/10^6 -> 59522.026 | F5: 단기금융상품 | G5: =C72/10^3 -> 764.525 | H5: =E72/10^3 -> 764.525 | I5: =E108/10^3 -> 764.525
B6: Dep | C6: =SUM(K72:K73)/10^3 -> 397.3 | D6: =SUM(L72:L73)/10^3 -> 414.284 | E6: =SUM(M72:M73)/10^3 -> 316.878 | F6: Debt | G6: =SUM(G7:G10) -> 23703.636 | H6: =SUM(H7:H10) -> 22939.727 | I6: =SUM(I7:I10) -> 31095.747
B7: EBITDA | C7: =C5+C6 -> 35448.676 | D7: =D5+D6 -> 42024.881 | E7: =E5+E6 -> 59838.904 | F7: 단기차입금 | G7: =C95/10^3 -> 11693.69 | H7: =D95/10^3 -> 11693.69 | I7: =E95/10^3 -> 11693.69
B8: NI(Loss) | C8: =K40/10^6 -> 6053.4942 | D8: =L40/10^6 -> 21831.87 | E8: =M40/10^6 -> -75220.395 | F8: 유동성장기차입금 | G8: =C96/10^3 -> 777.877 | H8: =D96/10^3 -> 9901.3 | I8: =E96/10^3 -> 8986.033
F9: 장기차입금 | G9: =C99/10^3 -> 11232.069 | H9: =D99/10^3 -> 1344.737 | I9: =E99/10^3 -> 10416.024
F10: 사채 | G10: 0 | H10: 0 | I10: 0
F11: NOA | G11: =SUM(G12:G17) -> 111114.32 | H11: =SUM(H12:H17) -> 82705.38 | I11: =SUM(I12:I17) -> 88916.966
F12: 장기금융상품 | G12: =D73/10^3 -> 20 | H12: =F73/10^3 -> 950 | I12: =F109/10^3 -> 260
F13: 투자부동산 | G13: =C43/10^6 -> 220.78876 | H13: =D43/10^6 -> 332.55515 | I13: =E43/10^6 -> 620.08048
F14: 관계기업투자 | G14: 0 | H14: 0 | I14: 0
F15: 당기손익-공정가치측정금융자산 | G15: =SUM(C74:D76)/10^3 -> 74800.542 | H15: =SUM(E74:F76)/10^3 -> 25987.295 | I15: =SUM(H168:I168)/10^3 -> 33049.653
F16: 기타포괄손익-공정가치측정금융자산
F17: 대여금 | G17: =(C77+C78+D79+D80)/10^3 -> 36072.991 | H17: =(E77+E78+F79+F80)/10^3 -> 55435.53 | I17: =SUM(E111:F114)/10^3 -> 54987.233 | J17: =(G77+G78+H79+H80)/10^3 -> 0
F18: BV | G18: =C63/10^6 -> 78804.146 | H18: =D63/10^6 -> 75873.925 | I18: =E63/10^6 -> -10008.709 | Q18: 종가 | R18: 상장주식수
P19: 2018-10-01~2018-12-31 | Q19: =AVERAGE(Q87:Q148) -> 2094.3548 | R19: =AVERAGE(Q331:Q387) -> 1933.0702 | S19: =AVERAGE(Q574:Q636) -> 1833.9683 | T19: 종가
P20: 2019-01-01~2019-03-31 | Q20: =AVERAGE(Q28:Q86) -> 2040.7627 | R20: =AVERAGE(Q270:Q330) -> 2007.541 | S20: =AVERAGE(Q512:Q573) -> 1883.3871 | T20: 종가
P21: 2018-10-01~2019-03-31 | Q21: =AVERAGE(Q28:Q148) -> 2068.2231 | R21: =AVERAGE(Q270:Q390) -> 1972.0661 | S21: =AVERAGE(Q512:Q636) -> 1858.48 | T21: 종가
P22: 2018.12.31 | Q22: =X87 -> 300399 | R22: =X331 -> 278351 | S22: =X574 -> 318855 | T22: 시가총액
B23: 재무상태표 | J23: 손익계산서 | P23: 2019.03.31 | Q23: =X28 -> 274214 | R23: =X270 -> 283439 | S23: =X512 -> 261930 | T23: 시가총액
B24: 제 60 기 2018.12.31 현재 | J24: 제 60 기 2018.01.01 부터 2018.12.31 까지 | Q24: =Y28 -> 145471745 | R24: =Y270 -> 145353082 | S24: =Y512 -> 139695905 | T24: 상장주식수
B25: 제 59 기 2017.12.31 현재 | J25: 제 59 기 2017.01.01 부터 2017.12.31 까지 | P25: 3. 일자별시세 | AA25: 4. 제품군
B26: 제 58 기 2016.12.31 현재 | J26: 제 58 기 2016.01.01 부터 2016.12.31 까지
B27: (단위 : 원) | J27: (단위 : 원) | P27: 년/월/일 | Q27: 종가 | R27: 대비 | S27: 거래량(주) | T27: 거래대금(원) | U27: 시가 | V27: 고가 | W27: 저가 | X27: 시가총액(백만) | Y27: 상장주식수(주)
C28: 제 60 기 | D28: 제 59 기 | E28: 제 58 기 | K28: 제 60 기 | L28: 제 59 기 | M28: 제 58 기 | P28: 2019/03/29 | Q28: 1885 | R28: 70 | S28: 53231 | T28: 98676890 | U28: 1825 | V28: 1890 | W28: 1825 | X28: 274214 | Y28: 145471745
B29: 자산 | J29: 수익(매출액) | K29: 671155389696 | L29: 573309875036 | M29: 646578597991 | P29: 2019/03/28 | Q29: 1815 | R29: -125 | S29: 161195 | T29: 299070110 | U29: 1940 | V29: 1945 | W29: 1815 | X29: 264031 | Y29: 145471745
B30: 유동자산 | C30: 286361415386 | D30: 210500745541 | E30: 208023245282 | J30: 매출원가 | K30: 615955604823 | L30: 515263823021 | M30: 577097370496 | P30: 2019/03/27 | Q30: 1940 | R30: -10 | S30: 46530 | T30: 89797160 | U30: 1950 | V30: 1955 | W30: 1915 | X30: 282215 | Y30: 145471745
B31: 현금및현금성자산 | C31: 12555530444 | D31: 46977532509 | E31: 23306795799 | J31: 매출총이익 | K31: 55199784873 | L31: 58046052015 | M31: 69481227495 | P31: 2019/03/26 | Q31: 1950 | R31: -10 | S31: 38168 | T31: 74349670 | U31: 1960 | V31: 1965 | W31: 1940 | X31: 283670 | Y31: 145471745
B32: 당기손익인식금융자산 | E32: 4293775254 | J32: 판매비와관리비 | K32: 20148408802 | L32: 16435455033 | M32: 9959201786 | P32: 2019/03/25 | Q32: 1960 | R32: -30 | S32: 19395 | T32: 38083650 | U32: 1975 | V32: 1985 | W32: 1950 | X32: 285125 | Y32: 145471745
B33: 매출채권 및 기타유동채권 | C33: 211452005195 | D33: 142616183904 | E33: 150605955478 | J33: 영업이익(손실) | K33: 35051376071 | L33: 41610596982 | M33: 59522025709 | P33: 2019/03/22 | Q33: 1990 | R33: 30 | S33: 35974 | T33: 70425075 | U33: 1960 | V33: 1990 | W33: 1945 | X33: 289489 | Y33: 145471745
B34: 당기법인세자산 | C34: 88483680 | D34: 52781490 | E34: 423665440 | J34: 기타이익 | K34: 1697618475 | L34: 1972761262 | M34: 6885760101 | P34: 2019/03/21 | Q34: 1960 | R34: -30 | S34: 93272 | T34: 184223235 | U34: 1990 | V34: 2020 | W34: 1950 | X34: 285125 | Y34: 145471745
B35: 기타유동금융자산 | C35: 50162325361 | D35: 1871527236 | E35: 6069453599 | J35: 기타손실 | K35: 30604762956 | L35: 20672236931 | M35: 144689738154 | P35: 2019/03/20 | Q35: 1990 | R35: -5 | S35: 32867 | T35: 64555745 | U35: 2000 | V35: 2000 | W35: 1935 | X35: 289489 | Y35: 145471745
B36: 기타유동자산 | C36: 8388083524 | D36: 15037932893 | E36: 19522503254 | J36: 금융수익 | K36: 573516656 | L36: 236325808 | M36: 1918896523 | P36: 2019/03/19 | Q36: 1995 | R36: 0 | S36: 30702 | T36: 61275900 | U36: 2005 | V36: 2005 | W36: 1985 | X36: 290216 | Y36: 145471745
B37: 재고자산 | C37: 3714987182 | D37: 3944787509 | E37: 3801096458 | J37: 금융원가 | K37: 664254089 | L37: 1315577310 | M37: 1340902070 | P37: 2019/03/18 | Q37: 1995 | R37: -5 | S37: 34466 | T37: 69103915 | U37: 2010 | V37: 2020 | W37: 1990 | X37: 290216 | Y37: 145471745
B38: 비유동자산 | C38: 79880405803 | D38: 103101695676 | E38: 94054455626 | J38: 법인세비용차감전순이익(손실) | K38: 6053494157 | L38: 21831869811 | M38: -77703957891 | P38: 2019/03/15 | Q38: 2000 | R38: -30 | S38: 41810 | T38: 84011930 | U38: 2030 | V38: 2035 | W38: 1995 | X38: 290943 | Y38: 145471745
B39: 기타비유동금융자산 | C39: 67215117119 | D39: 89579556552 | E39: 88409316240 | J39: 법인세비용 | M39: -2483562570 | P39: 2019/03/14 | Q39: 2030 | R39: 25 | S39: 73983 | T39: 149365660 | U39: 2015 | V39: 2030 | W39: 2000 | X39: 295308 | Y39: 145471745
B40: 기타비유동자산 | C40: 1395530183 | D40: 1929241876 | J40: 당기순이익(손실) | K40: 6053494157 | L40: 21831869811 | M40: -75220395321 | P40: 2019/03/13 | Q40: 2005 | R40: 10 | S40: 44931 | T40: 89840685 | U40: 2020 | V40: 2020 | W40: 1980 | X40: 291671 | Y40: 145471745
B41: 유형자산 | C41: 10707695970 | D41: 10883949554 | E41: 4117300920 | J41: 주당이익 | P41: 2019/03/12 | Q41: 1995 | R41: -10 | S41: 28900 | T41: 57859060 | U41: 1990 | V41: 2010 | W41: 1990 | X41: 290216 | Y41: 145471745
B42: 영업권 이외의 무형자산 | C42: 341273776 | D42: 376392545 | E42: 907757982 | J42: 기본주당이익(손실) (단위 : 원) | K42: 41 | L42: 166 | M42: -931 | P42: 2019/03/11 | Q42: 2005 | R42: 45 | S42: 77179 | T42: 153536365 | U42: 1970 | V42: 2005 | W42: 1955 | X42: 291671 | Y42: 145471745
B43: 투자부동산 | C43: 220788755 | D43: 332555149 | E43: 620080484 | J43: 희석주당이익(손실) (단위 : 원) | K43: 41 | L43: 166 | M43: -931 | P43: 2019/03/08 | Q43: 1960 | R43: 15 | S43: 21631 | T43: 42309580 | U43: 1930 | V43: 1980 | W43: 1930 | X43: 285125 | Y43: 145471745
B44: 자산총계 | C44: 366241821189 | D44: 313602441217 | E44: 302077700908 | P44: 2019/03/07 | Q44: 1945 | R44: -25 | S44: 50217 | T44: 98995200 | U44: 1960 | V44: 1995 | W44: 1945 | X44: 282943 | Y44: 145471745
B45: 부채 | P45: 2019/03/06 | Q45: 1970 | R45: -25 | S45: 28059 | T45: 55463865 | U45: 1995 | V45: 2000 | W45: 1960 | X45: 286579 | Y45: 145471745
B46: 유동부채 | C46: 228546159408 | D46: 186525218511 | E46: 242110301836 | J46: 23. 비용의 성격별 분류 | P46: 2019/03/05 | Q46: 1995 | R46: 25 | S46: 31865 | T46: 62916050 | U46: 1930 | V46: 1995 | W46: 1930 | X46: 290216 | Y46: 145471745
B47: 매입채무 및 기타유동채무 | C47: 201380157100 | D47: 156467537153 | E47: 209933365914 | P47: 2019/03/04 | Q47: 1970 | R47: 40 | S47: 69199 | T47: 135613620 | U47: 1930 | V47: 1990 | W47: 1910 | X47: 286579 | Y47: 145471745
B48: 단기차입금 | C48: 12471567192 | D48: 21594990326 | E48: 20679722562 | J48: 당기 및 전기 중 발생한 비용의 성격별 분류내역은 다음과 같습니다. | P48: 2019/02/28 | Q48: 1930 | R48: -55 | S48: 138220 | T48: 272038855 | U48: 1995 | V48: 2030 | W48: 1930 | X48: 280760 | Y48: 145471745
B49: 기타유동금융부채 | C49: 8535042101 | D49: 4593921587 | E49: 3883836280 | J49: (당기) | K49: (단위 : 천원) | P49: 2019/02/27 | Q49: 1985 | R49: 35 | S49: 64036 | T49: 127186210 | U49: 1980 | V49: 2000 | W49: 1960 | X49: 288761 | Y49: 145471745
B50: 유동금융보증부채 | C50: 1252676843 | D50: 694600031 | E50: 1686164407 | J50: 구분 | K50: 매출원가 | L50: 판매비와관리비 | M50: 성격별비용 계 | P50: 2019/02/26 | Q50: 1950 | R50: -10 | S50: 128515 | T50: 251627985 | U50: 1960 | V50: 1985 | W50: 1940 | X50: 283670 | Y50: 145471745
B51: 기타유동부채 | C51: 4906716172 | D51: 3174169414 | E51: 5927212673 | J51: 재료비 | K51: 162539123 | L51: - | M51: 162539123 | P51: 2019/02/25 | Q51: 1960 | R51: -40 | S51: 159909 | T51: 314168860 | U51: 2010 | V51: 2015 | W51: 1950 | X51: 285125 | Y51: 145471745
B52: 비유동부채 | C52: 58891515529 | D52: 51203298075 | E52: 69976107895 | J52: 종업원급여 | K52: 22049589 | L52: 5622181 | M52: 27671770 | P52: 2019/02/22 | Q52: 2000 | R52: 0 | S52: 188877 | T52: 381377320 | U52: 2025 | V52: 2070 | W52: 2000 | X52: 290943 | Y52: 145471745
B53: 장기차입금 | C53: 11232068780 | D53: 1344737063 | E53: 10416023589 | J53: 퇴직급여 | K53: 1031534 | L53: 641439 | M53: 1672973 | P53: 2019/02/21 | Q53: 2000 | R53: 0 | S53: 55263 | T53: 111062355 | U53: 2005 | V53: 2030 | W53: 2000 | X53: 290943 | Y53: 145471745
B54: 순확정급여부채 | C54: 9895926868 | D54: 8463140868 | E54: 8481618130 | J54: 외주비 | K54: 357028766 | L54: - | M54: 357028766 | P54: 2019/02/20 | Q54: 2000 | R54: -30 | S54: 93228 | T54: 187202545 | U54: 2030 | V54: 2035 | W54: 2000 | X54: 290943 | Y54: 145471745
B55: 비유동충당부채 | C55: 37678519881 | D55: 41310420144 | E55: 50993466176 | J55: 감가상각비 및 무형자산상각비 | K55: - | L55: 397300 | M55: 397300 | P55: 2019/02/19 | Q55: 2030 | R55: -10 | S55: 65307 | T55: 132092950 | U55: 2045 | V55: 2050 | W55: 2015 | X55: 295308 | Y55: 145471745
B56: 기타비유동금융부채 | C56: 85000000 | D56: 85000000 | E56: 85000000 | J56: 임차료 | K56: 7834007 | L56: 43651 | M56: 7877658 | P56: 2019/02/18 | Q56: 2040 | R56: -5 | S56: 92163 | T56: 186387215 | U56: 2045 | V56: 2055 | W56: 2000 | X56: 296762 | Y56: 145471745
B57: 부채총계 | C57: 287437674937 | D57: 237728516586 | E57: 312086409731 | J57: 세금과공과 | K57: 14470127 | L57: 1113567 | M57: 15583694 | P57: 2019/02/15 | Q57: 2045 | R57: -65 | S57: 204730 | T57: 418394565 | U57: 2125 | V57: 2125 | W57: 2000 | X57: 297490 | Y57: 145471745
B58: 자본 | J58: 하자보수비 | K58: 7838847 | L58: 667230 | M58: 8506077 | P58: 2019/02/14 | Q58: 2110 | R58: 10 | S58: 126490 | T58: 265776650 | U58: 2100 | V58: 2130 | W58: 2085 | X58: 306945 | Y58: 145471745
B59: 자본금 | C59: 73311885500 | D59: 73252554000 | E59: 76857107500 | J59: 지급수수료 | K59: 22962769 | L59: 2359637 | M59: 25322406 | P59: 2019/02/13 | Q59: 2100 | R59: 10 | S59: 192244 | T59: 407315500 | U59: 2090 | V59: 2155 | W59: 2080 | X59: 305491 | Y59: 145471745
B60: 기타불입자본 | C60: 33133368 | D60: 61336418319 | E60: 1122306228 | J60: 대손상각비 | K60: - | L60: 5820390 | M60: 5820390 | P60: 2019/02/12 | Q60: 2090 | R60: 0 | S60: 99138 | T60: 209115780 | U60: 2135 | V60: 2150 | W60: 2080 | X60: 304036 | Y60: 145471745
B61: 이익잉여금(결손금) | C61: -944897318 | D61: -69951439386 | E61: -92206243737 | J61: 기타비용 | K61: 20200843 | L61: 3483014 | M61: 23683857 | P61: 2019/02/11 | Q61: 2090 | R61: -45 | S61: 160533 | T61: 336890180 | U61: 2135 | V61: 2145 | W61: 2075 | X61: 304036 | Y61: 145471745
B62: 기타포괄손익누계액 | C62: 6404024702 | D62: 11236391698 | E62: 4218121186 | J62: 합계 | K62: 615955605 | L62: 20148409 | M62: 636104014 | P62: 2019/02/08 | Q62: 2135 | R62: -25 | S62: 96467 | T62: 206826025 | U62: 2160 | V62: 2180 | W62: 2125 | X62: 310582 | Y62: 145471745
B63: 자본총계 | C63: 78804146252 | D63: 75873924631 | E63: -10008708823 | P63: 2019/02/07 | Q63: 2160 | R63: 10 | S63: 171668 | T63: 376722890 | U63: 2180 | V63: 2230 | W63: 2150 | X63: 314219 | Y63: 145471745
B64: 자본과부채총계 | C64: 366241821189 | D64: 313602441217 | E64: 302077700908 | P64: 2019/02/01 | Q64: 2150 | R64: -65 | S64: 172446 | T64: 372984670 | U64: 2230 | V64: 2230 | W64: 2100 | X64: 312764 | Y64: 145471745
P65: 2019/01/31 | Q65: 2215 | R65: -25 | S65: 195771 | T65: 432535070 | U65: 2240 | V65: 2260 | W65: 2190 | X65: 322220 | Y65: 145471745
B66: 8. 기타금융자산 | J66: (단위: 천원) | P66: 2019/01/30 | Q66: 2240 | R66: 10 | S66: 596437 | T66: 1336644495 | U66: 2280 | V66: 2285 | W66: 2180 | X66: 325857 | Y66: 145471745
J67: 구 분 | K67: 보고된 금액(*1) | P67: 2019/01/29 | Q67: 2230 | R67: 120 | S67: 942431 | T67: 2075631810 | U67: 2115 | V67: 2275 | W67: 2110 | X67: 324402 | Y67: 145471745
B68: (1) 당기말 및 전기말 현재 기타금융자산의 구성내역은 다음과 같습니다. | J68: I. 영업활동으로 인한 현금흐름 | K68: 24270913 | P68: 2019/01/28 | Q68: 2110 | R68: -25 | S68: 113860 | T68: 242047185 | U68: 2140 | V68: 2145 | W68: 2105 | X68: 306945 | Y68: 145471745
C69: (단위 : 천원) | J69: 1. 영업으로부터 창출된 현금흐름 | K69: 23941252 | P69: 2019/01/25 | Q69: 2135 | R69: 15 | S69: 179783 | T69: 381081865 | U69: 2130 | V69: 2150 | W69: 2100 | X69: 310582 | Y69: 145471745
B70: 구 분 | C70: 당기말 | E70: 전기말 | J70: 법인세차감전순이익 | K70: 6053494 | P70: 2019/01/24 | Q70: 2120 | R70: 20 | S70: 246122 | T70: 521300275 | U70: 2125 | V70: 2155 | W70: 2095 | X70: 308400 | Y70: 145471745
C71: 유동 | D71: 비유동 | E71: 유동 | F71: 비유동 | J71: 조정: | P71: 2019/01/23 | Q71: 2100 | R71: -130 | S71: 653414 | T71: 1386615050 | U71: 2190 | V71: 2190 | W71: 2090 | X71: 305491 | Y71: 145471745
B72: 단기금융상품 | C72: 764525 | D72: - | E72: 764525 | F72: - | J72: 감가상각비 | K72: 335137 | L72: 342021 | M72: 216225 | P72: 2019/01/22 | Q72: 2230 | R72: 165 | S72: 3418620 | T72: 7732885075 | U72: 2080 | V72: 2410 | W72: 2035 | X72: 324402 | Y72: 145471745
B73: 장기금융상품 | C73: - | D73: 20000 | E73: - | F73: 950000 | J73: 무형자산상각비 | K73: 62163 | L73: 72263 | M73: 100653 | P73: 2019/01/21 | Q73: 2065 | R73: -50 | S73: 215695 | T73: 449298460 | U73: 2150 | V73: 2150 | W73: 2040 | X73: 300399 | Y73: 145471745
B74: 기타포괄손익-공정가치 측정금융자산 | C74: 1006207 | D74: 2911942 | E74: - | F74: - | J74: 퇴직급여 | K74: 1867132 | P74: 2019/01/18 | Q74: 2115 | R74: 15 | S74: 104214 | T74: 220520200 | U74: 2090 | V74: 2155 | W74: 2065 | X74: 307673 | Y74: 145471745
B75: 당기손익-공정가치 측정금융자산 | C75: 48344195 | D75: 22538198 | E75: - | F75: - | J75: 하자보수충당부채전입액 | K75: 8089041 | P75: 2019/01/17 | Q75: 2100 | R75: -100 | S75: 179461 | T75: 383168450 | U75: 2220 | V75: 2220 | W75: 2075 | X75: 305491 | Y75: 145471745
B76: 매도가능금융자산 | C76: - | D76: - | E76: 1073534 | F76: 24913761 | J76: 대손상각비(환입) | K76: 5820390 | P76: 2019/01/16 | Q76: 2200 | R76: 90 | S76: 301359 | T76: 651622850 | U76: 2135 | V76: 2200 | W76: 2100 | X76: 320038 | Y76: 145471745
B77: 단기대여금 | C77: 81806684 | D77: - | E77: 82046924 | F77: - | J77: 당기손익-공정가치측정금융자산 처분손실 | K77: 6467 | P77: 2019/01/15 | Q77: 2110 | R77: -25 | S77: 141259 | T77: 300168065 | U77: 2140 | V77: 2155 | W77: 2100 | X77: 306945 | Y77: 145471745
B78: 대손충당금 | C78: -81765121 | D78: - | E78: -82017361 | F78: - | J78: 당기손익-공정가치측정금융자산 평가손실 | K78: 18957 | P78: 2019/01/14 | Q78: 2135 | R78: 105 | S78: 346160 | T78: 722979935 | U78: 2080 | V78: 2170 | W78: 2030 | X78: 310582 | Y78: 145471745
B79: 장기대여금 | C79: - | D79: 380836279 | E79: - | F79: 367713056 | J79: 기타의대손상각비 | K79: 22558685 | P79: 2019/01/11 | Q79: 2030 | R79: 30 | S79: 112292 | T79: 226653245 | U79: 2010 | V79: 2035 | W79: 1995 | X79: 295308 | Y79: 145471745
B80: 대손충당금 | C80: - | D80: -344804851 | E80: - | F80: -312307089 | J80: 이자비용 | K80: 664254 | P80: 2019/01/10 | Q80: 2000 | R80: 10 | S80: 53084 | T80: 106208785 | U80: 1995 | V80: 2030 | W80: 1985 | X80: 290943 | Y80: 145471745
B81: 미수수익 | C81: 34586348 | D81: - | E81: 34584418 | F81: - | J81: 금융보증이자 | K81: 2356201 | P81: 2019/01/09 | Q81: 1990 | R81: -25 | S81: 80366 | T81: 161287785 | U81: 2010 | V81: 2045 | W81: 1990 | X81: 289489 | Y81: 145471745
B82: 대손충당금 | C82: -34580513 | D82: - | E82: -34580513 | F82: - | J82: 잡손실 | K82: -79008 | P82: 2019/01/08 | Q82: 2015 | R82: -30 | S82: 68375 | T82: 138669825 | U82: 2060 | V82: 2075 | W82: 2010 | X82: 293126 | Y82: 145471745
B83: 보증금 | C83: - | D83: 5707549 | E83: - | F83: 8303829 | J83: 이자수익 | K83: -573517 | P83: 2019/01/07 | Q83: 2045 | R83: -5 | S83: 85132 | T83: 175348720 | U83: 2100 | V83: 2105 | W83: 2040 | X83: 297490 | Y83: 145471745
B84: 부도어음 | C84: - | D84: 75416 | E84: - | F84: 75416 | J84: 투자부동산처분이익 | K84: -24922 | P84: 2019/01/04 | Q84: 2050 | R84: 55 | S84: 87471 | T84: 174270260 | U84: 1965 | V84: 2060 | W84: 1950 | X84: 298217 | Y84: 145471745
B85: 대손충당금 | C85: - | D85: -75416 | E85: - | F85: -75416 | J85: 유형자산처분이익 | K85: -336 | P85: 2019/01/03 | Q85: 1995 | R85: -50 | S85: 56465 | T85: 113150040 | U85: 2060 | V85: 2060 | W85: 1975 | X85: 290216 | Y85: 145471745
B86: 기타투자자산 | C86: - | D86: 6000 | E86: - | F86: 6000 | J86: 당기손익-공정가치측정금융자산 처분이익 | K86: -3275 | P86: 2019/01/02 | Q86: 2045 | R86: -20 | S86: 118871 | T86: 243484640 | U86: 2055 | V86: 2130 | W86: 1900 | X86: 297490 | Y86: 145471745
B87: 합계 | C87: 50162325 | D87: 67215117 | E87: 1871527 | F87: 89579557 | J87: 당기손익_공정가치측정금융자산 평가이익 | K87: -316652 | P87: 2018/12/28 | Q87: 2065 | R87: -55 | S87: 76109 | T87: 157632690 | U87: 2130 | V87: 2165 | W87: 2045 | X87: 300399 | Y87: 145471745
J88: 금융보증수익 | K88: -701240 | P88: 2018/12/27 | Q88: 2120 | R88: -35 | S88: 62573 | T88: 133776715 | U88: 2140 | V88: 2200 | W88: 2110 | X88: 308400 | Y88: 145471745
B89: 15. 차입금 | J89: 배당금수익 | K89: -434394 | P89: 2018/12/26 | Q89: 2155 | R89: 55 | S89: 216216 | T89: 468241635 | U89: 2060 | V89: 2280 | W89: 2020 | X89: 313492 | Y89: 145471745
J90: 공사미수금 | K90: -74748017 | P90: 2018/12/24 | Q90: 2100 | R90: -70 | S90: 60649 | T90: 128645310 | U90: 2170 | V90: 2170 | W90: 2100 | X90: 305491 | Y90: 145471745
B91: (1) 당기말 및 전기말 현재 차입금의 내역은 다음과 같습니다. | J91: 미수금 | K91: -2919053 | P91: 2018/12/21 | Q91: 2170 | R91: -100 | S91: 277861 | T91: 628844570 | U91: 2270 | V91: 2395 | W91: 2140 | X91: 315674 | Y91: 145471745
C92: (단위 : 천원) | G92: (단위 : 천원) | J92: 미청구공사 | K92: 4825132 | P92: 2018/12/20 | Q92: 2270 | R92: -10 | S92: 64646 | T92: 144894755 | U92: 2240 | V92: 2280 | W92: 2220 | X92: 330221 | Y92: 145471745
B93: 구분 | C93: 당기말 | D93: 전기말 | E93: 2016 | G93: 구분 | H93: 당기말 | J93: 선급금 | K93: -882944 | P93: 2018/12/19 | Q93: 2280 | R93: -65 | S93: 79902 | T93: 181258730 | U93: 2350 | V93: 2360 | W93: 2220 | X93: 331676 | Y93: 145471745
B94: 유동성차입금: | G94: 유동성: | J94: 선급비용 | K94: 1020908 | P94: 2018/12/18 | Q94: 2345 | R94: -95 | S94: 324582 | T94: 798227885 | U94: 2595 | V94: 2595 | W94: 2315 | X94: 341131 | Y94: 145471745
B95: 단기차입금 | C95: 11693690 | D95: 11693690 | E95: 11693690 | G95: 단기차입금 | H95: 11693690 | J95: 선급공사 | K95: 2117565 | P95: 2018/12/17 | Q95: 2440 | R95: 15 | S95: 123494 | T95: 309938220 | U95: 2475 | V95: 2500 | W95: 2425 | X95: 354951 | Y95: 145471745
B96: 유동성장기차입금 | C96: 777877 | D96: 9901300 | E96: 8986033 | G96: 유동성장기차입금 | H96: 9901300 | J96: 재고자산 | K96: 229800 | P96: 2018/12/14 | Q96: 2425 | R96: 0 | S96: 197971 | T96: 479040970 | U96: 2425 | V96: 2480 | W96: 2345 | X96: 352769 | Y96: 145471745
B97: 소계 | C97: 12471567 | D97: 21594990 | E97: 20679723 | G97: 소계 | H97: 21594990 | J97: 매입채무 | K97: 38061040 | P97: 2018/12/13 | Q97: 2425 | R97: 40 | S97: 47674 | T97: 114790490 | U97: 2400 | V97: 2430 | W97: 2345 | X97: 352769 | Y97: 145471745
B98: 비유동성차입금: | G98: 비유동성: | J98: 초과청구공사 | K98: 6897512 | P98: 2018/12/12 | Q98: 2385 | R98: 105 | S98: 49555 | T98: 116595425 | U98: 2325 | V98: 2385 | W98: 2290 | X98: 346950 | Y98: 145471745
B99: 장기차입금 | C99: 11232069 | D99: 1344737 | E99: 10416024 | G99: 장기차입금 | H99: 1344737 | J99: 선수금 | K99: 3251672 | P99: 2018/12/11 | Q99: 2280 | R99: -95 | S99: 91902 | T99: 214210675 | U99: 2445 | V99: 2445 | W99: 2280 | X99: 331676 | Y99: 145471745
B100: 합계 | C100: 23703636 | D100: 22939727 | E100: 31095747 | G100: 합계 | H100: 22939727 | J100: 분양선수금 | K100: -488741 | P100: 2018/12/10 | Q100: 2375 | R100: -35 | S100: 152558 | T100: 358787495 | U100: 2475 | V100: 2480 | W100: 2240 | X100: 345495 | Y100: 145471745
J101: 예수금 | K101: 39573 | P101: 2018/12/07 | Q101: 2410 | R101: 0 | S101: 160379 | T101: 388406365 | U101: 2460 | V101: 2510 | W101: 2365 | X101: 350587 | Y101: 145471745
...

Sheet 코오롱글로벌
B2: PL | C2: 2018 | D2: 2017 | E2: 2016 | F2: BS | G2: 2018.12.31 | H2: 2018.12.31 | I2: 2018.12.31
C3: 12mths | D3: 12mths | E3: 12mths | F3: Cash | G3: =G4+G5 -> 82722.734 | H3: =H4+H5 -> 95937.084 | I3: =I4+I5 -> 66732.084
B4: Revenue | C4: =K29/10^6 -> 3358253.4 | D4: =L29/10^6 -> 3653606 | E4: =M29/10^6 -> 3185076.1 | F4: 현금및현금성자산 | G4: =C31/10^6 -> 82722.734 | H4: =D31/10^6 -> 95937.084 | I4: =E31/10^6 -> 66732.084
B5: EBIT | C5: =K33/10^6 -> 76764.013 | D5: =L33/10^6 -> 72509.169 | E5: =M33/10^6 -> 60691.919 | F5: 단기금융상품 | G5: 0 | H5: 0 | I5: 0
B6: Dep | C6: =SUM(K92,K93,K94)/10^6 -> 19458.894 | D6: =SUM(L92,L93,L94)/10^6 -> 16908.48 | E6: =SUM(M92,M93,M94)/10^6 -> 14320.732 | F6: Debt | G6: =SUM(G7:G10) -> 711660 | H6: =SUM(H7:H10) -> 653806 | I6: =SUM(I7:I10) -> 586679
B7: EBITDA | C7: =C5+C6 -> 96222.907 | D7: =D5+D6 -> 89417.649 | E7: =E5+E6 -> 75012.651 | F7: 단기차입금 | G7: 0 | H7: 0 | I7: 0
B8: NI(Loss) | C8: =K41/10^6 -> 14451.16 | D8: =L41/10^6 -> 15249.106 | E8: =M41/10^6 -> 6137.3202 | F8: 유동성장기차입금 | G8: =C109 -> 576668 | H8: =E109 -> 534710 | I8: =G109 -> 423035
F9: 장기차입금 | G9: =D106 -> 35550 | H9: =F106 -> 1610 | I9: =H106 -> 48836
F10: 사채 | G10: =D107+D108 -> 99442 | H10: =F107+F108 -> 117486 | I10: =H107+H108 -> 114808
F11: NOA | G11: =SUM(G12:G17) -> 511292.84 | H11: =SUM(H12:H17) -> 479784.73 | I11: =SUM(I12:I17) -> 466652.94
F12: 장기금융상품 | G12: =SUM(C116:D120) -> 83335 | H12: =SUM(E116:F120) -> 109310 | I12: =SUM(C157,E157:F157) -> 90942
F13: 투자부동산 | G13: =C42/10^6 -> 290974.61 | H13: =D42/10^6 -> 242604.66 | I13: =E42/10^6 -> 236405.78
F14: 관계기업투자 | G14: =C44/10^6 -> 29588.225 | H14: =D44/10^6 -> 15934.063 | I14: =E44/10^6 -> 29532.164
F15: 당기손익-공정가치측정금융자산
F16: 기타포괄손익-공정가치측정금융자산
F17: 대여금 | G17: =C91+C92+C93+D91+D92+D93 -> 107395 | H17: =E91+E92+E93+F91+F92+F93 -> 111936 | I17: =G91+G92+G93+H91+H92+H93 -> 109773
F18: BV | G18: =C73/10^6 -> 446731.38 | H18: =D73/10^6 -> 465432.24 | I18: =E73/10^6 -> 436212.27
P19: 2018-10-01~2018-12-31 | Q19: =AVERAGE(Q87:Q148) -> 7020 | R19: =AVERAGE(Q331:Q387) -> 10163.684 | S19: =AVERAGE(Q574:Q636) -> 12285.714 | T19: 종가
P20: 2019-01-01~2019-03-31 | Q20: =AVERAGE(Q28:Q86) -> 8598.6441 | R20: =AVERAGE(Q270:Q330) -> 10254.262 | S20: =AVERAGE(Q512:Q573) -> 13125.806 | T20: 종가
P21: 2018-10-01~2019-03-31 | Q21: =AVERAGE(Q28:Q148) -> 7789.7521 | R21: =AVERAGE(Q270:Q390) -> 10192.893 | S21: =AVERAGE(Q512:Q636) -> 12702.4 | T21: 종가
P22: 2018.12.31 | Q22: =X87 -> 179750 | R22: =X331 -> 246558 | S22: =X574 -> 185585 | T22: 시가총액
B23: 연결 재무상태표 | J23: 연결 포괄손익계산서 | P23: 2019.03.31 | Q23: =X28 -> 254625 | R23: =X270 -> 250592 | S23: =X512 -> 238609 | T23: 시가총액
B24: 제 59 기 2018.12.31 현재 | J24: 제 59 기 2018.01.01 부터 2018.12.31 까지 | Q24: =Y28 -> 25210438 | R24: =Y270 -> 25210438 | S24: =Y512 -> 16570088 | T24: 상장주식수
B25: 제 58 기 2017.12.31 현재 | J25: 제 58 기 2017.01.01 부터 2017.12.31 까지 | P25: 3. 일자별시세 | AA25: 4. 제품군
B26: 제 57 기 2016.12.31 현재 | J26: 제 57 기 2016.01.01 부터 2016.12.31 까지
B27: (단위 : 원) | J27: (단위 : 원) | P27: 년/월/일 | Q27: 종가 | R27: 대비 | S27: 거래량(주) | T27: 거래대금(원) | U27: 시가 | V27: 고가 | W27: 저가 | X27: 시가총액(백만) | Y27: 상장주식수(주)
C28: 제 59 기 | D28: 제 58 기 | E28: 제 57 기 | K28: 제 59 기 | L28: 제 58 기 | M28: 제 57 기 | P28: 2019/03/29 | Q28: 10100 | R28: -400 | S28: 140392 | T28: 1429454550 | U28: 10550 | V28: 10600 | W28: 10000 | X28: 254625 | Y28: 25210438
B29: 자산 | J29: 매출액 | K29: 3358253405224 | L29: 3653606034371 | M29: 3185076053399 | P29: 2019/03/28 | Q29: 10500 | R29: -150 | S29: 32307 | T29: 339919800 | U29: 10650 | V29: 10700 | W29: 10450 | X29: 264710 | Y29: 25210438
B30: 유동자산 | C30: 948459990021 | D30: 1139103652565 | E30: 1000326734843 | J30: 매출원가 | K30: 3048862686870 | L30: 3322181716428 | M30: 2893269332884 | P30: 2019/03/27 | Q30: 10650 | R30: 0 | S30: 99572 | T30: 1058574050 | U30: 10500 | V30: 10900 | W30: 10400 | X30: 268491 | Y30: 25210438
B31: 현금및현금성자산 | C31: 82722733620 | D31: 95937083601 | E31: 66732084198 | J31: 매출총이익 | K31: 309390718354 | L31: 331424317943 | M31: 291806720515 | P31: 2019/03/26 | Q31: 10650 | R31: 200 | S31: 103694 | T31: 1094832500 | U31: 10600 | V31: 10800 | W31: 10350 | X31: 268491 | Y31: 25210438
B32: 매출채권 및 기타유동채권 | C32: 374078707879 | D32: 468890830444 | E32: 446751966633 | J32: 판매비와관리비 | K32: 232626704983 | L32: 258915149343 | M32: 231114801780 | P32: 2019/03/25 | Q32: 10450 | R32: -150 | S32: 227454 | T32: 2336336250 | U32: 10400 | V32: 10650 | W32: 10000 | X32: 263449 | Y32: 25210438
B33: 미청구공사 | C33: 262884984783 | D33: 276079241405 | E33: 187273369396 | J33: 영업이익(손실) | K33: 76764013371 | L33: 72509168600 | M33: 60691918735 | P33: 2019/03/22 | Q33: 10600 | R33: -200 | S33: 57962 | T33: 613718600 | U33: 10750 | V33: 10750 | W33: 10500 | X33: 267231 | Y33: 25210438
B34: 기타금융자산 | C34: 24593564362 | D34: 13816313855 | E34: 15831577098 | J34: 금융수익 | K34: 12291279013 | L34: 8805925158 | M34: 5413633219 | P34: 2019/03/21 | Q34: 10800 | R34: 100 | S34: 144898 | T34: 1567646450 | U34: 10700 | V34: 11150 | W34: 10500 | X34: 272273 | Y34: 25210438
B35: 재고자산 | C35: 131519713816 | D35: 206193548054 | E35: 180971510356 | J35: 금융비용 | K35: 35145153397 | L35: 33512651277 | M35: 27819559874 | P35: 2019/03/20 | Q35: 10700 | R35: -200 | S35: 236906 | T35: 2514457350 | U35: 10900 | V35: 11050 | W35: 10400 | X35: 269752 | Y35: 25210438
B36: 기타유동자산 | C36: 72647872981 | D36: 78183870106 | E36: 102764240532 | J36: 기타영업외수익 | K36: 40859237661 | L36: 52128403609 | M36: 59714068150 | P36: 2019/03/19 | Q36: 10900 | R36: -350 | S36: 225443 | T36: 2531004050 | U36: 11300 | V36: 11650 | W36: 10800 | X36: 274794 | Y36: 25210438
B37: 당기법인세자산 | C37: 12412580 | D37: 2765100 | E37: 1986630 | J37: 기타영업외비용 | K37: 60612105082 | L37: 73569559369 | M37: 91124085166 | P37: 2019/03/18 | Q37: 11250 | R37: 450 | S37: 393163 | T37: 4414229900 | U37: 11100 | V37: 11600 | W37: 10750 | X37: 283617 | Y37: 25210438
B38: 비유동자산 | C38: 1084949122134 | D38: 1124336999431 | E38: 1083373547672 | J38: 공동기업및관계기업투자손익 | K38: -1750785971 | L38: -9881761877 | M38: -1292961557 | P38: 2019/03/15 | Q38: 10800 | R38: 1080 | S38: 787731 | T38: 8254364740 | U38: 9940 | V38: 10850 | W38: 9800 | X38: 272273 | Y38: 25210438
B39: 장기기타금융자산 | C39: 131492695199 | D39: 138872932046 | E39: 137370572175 | J39: 법인세비용차감전순이익(손실) | K39: 32406485595 | L39: 16479524844 | M39: 5583013507 | P39: 2019/03/14 | Q39: 9720 | R39: 760 | S39: 495345 | T39: 4758831780 | U39: 9010 | V39: 10050 | W39: 8960 | X39: 245045 | Y39: 25210438
B40: 장기매출채권 및 기타비유동채권 | C40: 73074777502 | D40: 110039228020 | E40: 82446620603 | J40: 법인세비용 | K40: 17955325939 | L40: 1230418758 | M40: -554306716 | P40: 2019/03/13 | Q40: 8960 | R40: 410 | S40: 172572 | T40: 1519391110 | U40: 8550 | V40: 8980 | W40: 8470 | X40: 225886 | Y40: 25210438
B41: 유형자산 | C41: 376429671728 | D41: 415869547996 | E41: 391674393693 | J41: 당기순이익(손실) | K41: 14451159656 | L41: 15249106086 | M41: 6137320223 | P41: 2019/03/12 | Q41: 8550 | R41: 260 | S41: 73034 | T41: 620286140 | U41: 8430 | V41: 8580 | W41: 8370 | X41: 215549 | Y41: 25210438
... B43: 무형자산 | C43: 89230221700 | D43: 99105162398 | E43: 97271734257 | J43: 당기손익으로 재분류될 수 있는 항목(세후기타포괄손익) | K43: -5412701838 | L43: 16183489115 | M43: 4811925689 | P43: 2019/03/08 | Q43: 8290 | R43: 0 | S43: 22306 | T43: 183410180 | U43: 8200 | V43: 8340 | W43: 8140 | X43: 208995 | Y43: 25210438
B44: 공동기업 및 관계기업 투자자산 | C44: 29588225112 | D44: 15934063185 | E44: 29532164200 | J44: 매도가능금융자산평가손익 | L44: 21522462702 | M44: 3863813787 | P44: 2019/03/07 | Q44: 8290 | R44: -210 | S44: 45460 | T44: 383313800 | U44: 8500 | V44: 8600 | W44: 8240 | X44: 208995 | Y44: 25210438
B45: 기타비유동자산 | C45: 12895271599 | D45: 12810445631 | E45: 14570012806 | J45: 기타포괄손익-공정가치 측정 채무상품 평가손익 | K45: 24841762 | P45: 2019/03/06 | Q45: 8500 | R45: -40 | S45: 51062 | T45: 433290920 | U45: 8570 | V45: 8650 | W45: 8390 | X45: 214289 | Y45: 25210438
B46: 이연법인세자산 | C46: 81263649246 | D46: 89100957844 | E46: 94102273679 | J46: 지분법자본변동 | K46: -694460102 | L46: -3736237237 | M46: 383472366 | P46: 2019/03/05 | Q46: 8540 | R46: 350 | S46: 243100 | T46: 2078362370 | U46: 8120 | V46: 8860 | W46: 8070 | X46: 215297 | Y46: 25210438
B47: 자산총계 | C47: 2033409112155 | D47: 2263440651996 | E47: 2083700282515 | J47: 해외사업장환산외환차이 | K47: -4743083498 | L47: -1602736350 | M47: 564639536 | P47: 2019/03/04 | Q47: 8190 | R47: 70 | S47: 39153 | T47: 321089450 | U47: 8150 | V47: 8270 | W47: 8060 | X47: 206473 | Y47: 25210438
B48: 부채 | J48: 당기손익으로 재분류되지 않는항목(세후기타포괄손익) | K48: -8838402411 | L48: 380984543 | M48: -3463053690 | P48: 2019/02/28 | Q48: 8120 | R48: -140 | S48: 44150 | T48: 359116680 | U48: 8260 | V48: 8270 | W48: 7900 | X48: 204709 | Y48: 25210438
B49: 유동부채 | C49: 1257862450413 | D49: 1489672963279 | E49: 1304205444062 | J49: 기타포괄손익-공정가치측정지분상품평가손익 | K49: -2478229072 | P49: 2019/02/27 | Q49: 8260 | R49: -30 | S49: 20908 | T49: 172995970 | U49: 8370 | V49: 8370 | W49: 8230 | X49: 208238 | Y49: 25210438
B50: 매입채무 및 기타유동채무 | C50: 500919950741 | D50: 720276382069 | E50: 657981543120 | J50: 확정급여제도의 재측정손익 | K50: -6360173339 | L50: 380984543 | M50: -3463053690 | P50: 2019/02/26 | Q50: 8290 | R50: 260 | S50: 62543 | T50: 515398300 | U50: 8120 | V50: 8400 | W50: 8040 | X50: 208995 | Y50: 25210438
B51: 초과청구공사 | C51: 38647365893 | D51: 67027330731 | E51: 103466906566 | J51: 총포괄손익 | K51: 200055407 | L51: 31813579744 | M51: 7486192222 | P51: 2019/02/25 | Q51: 8030 | R51: 70 | S51: 12929 | T51: 103439130 | U51: 7900 | V51: 8070 | W51: 7900 | X51: 202440 | Y51: 25210438
B52: 차입금 및 사채 | C52: 576667877204 | D52: 534709729670 | E52: 423034643618 | J52: 당기순이익(손실)의 귀속 | P52: 2019/02/22 | Q52: 7960 | R52: -140 | S52: 18733 | T52: 149465320 | U52: 8110 | V52: 8140 | W52: 7880 | X52: 200675 | Y52: 25210438
B53: 기타금융부채 | C53: 11973905276 | D53: 19202271659 | E53: 10913466060 | J53: 지배기업의 소유주에게 귀속되는 당기순이익(손실) | K53: 16314019098 | L53: 15249106086 | M53: 6137320223 | P53: 2019/02/21 | Q53: 8100 | R53: 180 | S53: 53041 | T53: 429268400 | U53: 8000 | V53: 8230 | W53: 7870 | X53: 204205 | Y53: 25210438
B54: 당기법인세부채 | C54: 629058391 | D54: 839901752 | E54: 16186336 | J54: 비지배지분에 귀속되는 당기순이익(손실) | K54: -1862859442 | P54: 2019/02/20 | Q54: 7920 | R54: -90 | S54: 19395 | T54: 153657760 | U54: 8010 | V54: 8010 | W54: 7860 | X54: 199667 | Y54: 25210438
B55: 충당부채 | C55: 3617938958 | D55: 1555423352 | E55: 1555423352 | J55: 총 포괄손익의 귀속 | P55: 2019/02/19 | Q55: 8010 | R55: -50 | S55: 51167 | T55: 406088230 | U55: 8060 | V55: 8070 | W55: 7870 | X55: 201936 | Y55: 25210438
B56: 기타유동부채 | C56: 125406353950 | D56: 146061924046 | E56: 107237275010 | J56: 총 포괄손익, 지배기업의 소유주에게 귀속되는 지분 | K56: 2062914849 | L56: 31813579744 | M56: 7486192222 | P56: 2019/02/18 | Q56: 8060 | R56: -80 | S56: 37578 | T56: 304000190 | U56: 8090 | V56: 8190 | W56: 8030 | X56: 203196 | Y56: 25210438
B57: 비유동부채 | C57: 328815280724 | D57: 308335447379 | E57: 343282569369 | J57: 총 포괄손익, 비지배지분 | K57: -1862859442 | P57: 2019/02/15 | Q57: 8140 | R57: -140 | S57: 37311 | T57: 302379360 | U57: 8140 | V57: 8290 | W57: 8040 | X57: 205213 | Y57: 25210438
B58: 장기매입채무 및 기타채무 | C58: 77111938174 | D58: 67977002205 | E58: 68318601463 | J58: 주당이익 | P58: 2019/02/14 | Q58: 8280 | R58: 50 | S58: 12434 | T58: 101444910 | U58: 8290 | V58: 8290 | W58: 8100 | X58: 208742 | Y58: 25210438
B59: 장기차입금및사채 | C59: 134992081364 | D59: 119095697691 | E59: 163644387190 | J59: 기본주당이익 (단위 : 원) | K59: 569 | L59: 601 | M59: 367 | P59: 2019/02/13 | Q59: 8230 | R59: 0 | S59: 23799 | T59: 195031640 | U59: 8140 | V59: 8260 | W59: 8140 | X59: 207482 | Y59: 25210438
B60: 순확정급여부채 | C60: 53218914453 | D60: 55378311961 | E60: 54519023084 | J60: 구형우선주기본주당이익 (단위 : 원) | K60: 569 | L60: 601 | M60: 243 | P60: 2019/02/12 | Q60: 8230 | R60: 50 | S60: 9139 | T60: 75183490 | U60: 8180 | V60: 8250 | W60: 8180 | X60: 207482 | Y60: 25210438
B61: 장기기타금융부채 | C61: 11745909776 | D61: 11373250467 | E61: 15773884152 | P61: 2019/02/11 | Q61: 8180 | R61: -210 | S61: 29625 | T61: 242271260 | U61: 8250 | V61: 8320 | W61: 8080 | X61: 206221 | Y61: 25210438
B62: 기타비유동부채 | C62: 9924942181 | D62: 9665355767 | E62: 3893968505 | J62: 32. 비용의 성격별 분류 | P62: 2019/02/08 | Q62: 8390 | R62: -10 | S62: 37188 | T62: 313628000 | U62: 8350 | V62: 8570 | W62: 8300 | X62: 211516 | Y62: 25210438
B63: 장기충당부채 | C63: 41821494776 | D63: 44845829288 | E63: 37132704975 | J63: 당기 및 전기 비용의 성격별 분류내역은 다음과 같습니다. | P63: 2019/02/07 | Q63: 8400 | R63: 170 | S63: 35592 | T63: 296829000 | U63: 8400 | V63: 8400 | W63: 8270 | X63: 211768 | Y63: 25210438
B64: 부채총계 | C64: 1586677731137 | D64: 1798008410658 | E64: 1647488013431 | J64: (단위: 백만원) | P64: 2019/02/01 | Q64: 8230 | R64: -50 | S64: 19793 | T64: 163822850 | U64: 8330 | V64: 8330 | W64: 8200 | X64: 207482 | Y64: 25210438
B65: 자본 | J65: 구 분 | K65: 당기 | L65: 전기 | P65: 2019/01/31 | Q65: 8280 | R65: 150 | S65: 28296 | T65: 231981700 | U65: 8200 | V65: 8300 | W65: 8050 | X65: 208742 | Y65: 25210438
B66: 지배기업의 소유주에게 귀속되는 자본 | C66: 442633448113 | D66: 465432241338 | E66: 436212269084 | J66: 재고자산 변동 | K66: 1758986 | L66: 1932196 | P66: 2019/01/30 | Q66: 8130 | R66: 120 | S66: 28692 | T66: 232733300 | U66: 8010 | V66: 8200 | W66: 8010 | X66: 204961 | Y66: 25210438
B67: 자본금 | C67: 127682825000 | D67: 127682825000 | E67: 106081950000 | J67: 급여 | K67: 217016 | L67: 206516 | P67: 2019/01/29 | Q67: 8010 | R67: -170 | S67: 46705 | T67: 371514860 | U67: 8130 | V67: 8130 | W67: 7870 | X67: 201936 | Y67: 25210438
B68: 자본잉여금 | C68: 123759609293 | D68: 120184196846 | E68: 141924120786 | J68: 복리후생비 | K68: 14959 | L68: 17179 | P68: 2019/01/28 | Q68: 8180 | R68: -190 | S68: 30908 | T68: 255139010 | U68: 8370 | V68: 8400 | W68: 8120 | X68: 206221 | Y68: 25210438
B69: 이익잉여금(결손금) | C69: 189786659555 | D69: 194633856292 | E69: 181572988713 | J69: 운반비 | K69: 12124 | L69: 8787 | P69: 2019/01/25 | Q69: 8370 | R69: -10 | S69: 21854 | T69: 181891720 | U69: 8490 | V69: 8490 | W69: 8230 | X69: 211011 | Y69: 25210438
B70: 기타포괄손익누계액 | C70: 3559395364 | D70: 25086404299 | E70: 8902915184 | J70: 감가상각비 | K70: 15393 | L70: 12023 | P70: 2019/01/24 | Q70: 8380 | R70: -50 | S70: 19313 | T70: 161028650 | U70: 8500 | V70: 8500 | W70: 8270 | X70: 211263 | Y70: 25210438
B71: 기타자본 | C71: -2155041099 | D71: -2155041099 | E71: -2269705599 | J71: 무형자산상각비 | K71: 4066 | L71: 3350 | P71: 2019/01/23 | Q71: 8430 | R71: 200 | S71: 23776 | T71: 199021330 | U71: 8230 | V71: 8460 | W71: 8160 | X71: 212524 | Y71: 25210438
B72: 비지배지분 | C72: 4097932905 | J72: 광고선전비 | K72: 2690 | L72: 2945 | P72: 2019/01/22 | Q72: 8230 | R72: -160 | S72: 21554 | T72: 178977000 | U72: 8390 | V72: 8440 | W72: 8230 | X72: 207482 | Y72: 25210438
B73: 자본총계 | C73: 446731381018 | D73: 465432241338 | E73: 436212269084 | J73: 판매촉진비 | K73: 6310 | L73: 11372 | P73: 2019/01/21 | Q73: 8390 | R73: 210 | S73: 47386 | T73: 394450720 | U73: 8200 | V73: 8440 | W73: 8200 | X73: 211516 | Y73: 25210438
B74: 자본과부채총계 | C74: 2033409112155 | D74: 2263440651996 | E74: 2083700282515 | J74: 지급수수료 | K74: 104545 | L74: 142451 | P74: 2019/01/18 | Q74: 8180 | R74: 110 | S74: 26014 | T74: 211144300 | U74: 8040 | V74: 8180 | W74: 8040 | X74: 206221 | Y74: 25210438
J75: 외주비 | K75: 949808 | L75: 1014991 | P75: 2019/01/17 | Q75: 8070 | R75: -160 | S75: 30201 | T75: 244345230 | U75: 8310 | V75: 8310 | W75: 8010 | X75: 203448 | Y75: 25210438
J76: 기타비용 | K76: 195592 | L76: 229287 | P76: 2019/01/16 | Q76: 8230 | R76: 220 | S76: 83652 | T76: 697034510 | U76: 8170 | V76: 8770 | W76: 8150 | X76: 207482 | Y76: 25210438
B77: 8. 매출채권및기타채권과 미청구공사 | J77: 합 계(*) | K77: 3281489 | L77: 3581097 | P77: 2019/01/15 | Q77: 8010 | R77: 10 | S77: 25547 | T77: 204822010 | U77: 7930 | V77: 8070 | W77: 7930 | X77: 201936 | Y77: 25210438
B78: (1) 당기말과 전기말 현재 매출채권및기타채권의 상세 내역은 다음과 같습니다. | P78: 2019/01/14 | Q78: 8000 | R78: 220 | S78: 99153 | T78: 792320760 | U78: 8090 | V78: 8150 | W78: 7900 | X78: 201684 | Y78: 25210438
B79: (단위: 백만원) | G79: 전기말 | P79: 2019/01/11 | Q79: 7780 | R79: 290 | S79: 57136 | T79: 437437850 | U79: 7410 | V79: 7830 | W79: 7410 | X79: 196137 | Y79: 25210438
B80: 구 분 | C80: 당기말 | E80: 전기말 | G80: 유동 | H80: 비유동 | P80: 2019/01/10 | Q80: 7490 | R80: 0 | S80: 17701 | T80: 131761880 | U80: 7580 | V80: 7580 | W80: 7400 | X80: 188826 | Y80: 25210438
C81: 유동 | D81: 비유동 | E81: 유동 | F81: 비유동 | P81: 2019/01/09 | Q81: 7490 | R81: 120 | S81: 27130 | T81: 202996170 | U81: 7470 | V81: 7520 | W81: 7430 | X81: 188826 | Y81: 25210438
B82: 매출채권: | G82: 349826 | H82: - | J82: 연결 현금흐름표 | P82: 2019/01/08 | Q82: 7370 | R82: 120 | S82: 30775 | T82: 226449010 | U82: 7250 | V82: 7420 | W82: 7230 | X82: 185801 | Y82: 25210438
B83: 매출채권 | C83: 274761 | D83: - | E83: 344686 | F83: - | G83: -33907 | H83: - | J83: 제 59 기 2018.01.01 부터 2018.12.31 까지 | P83: 2019/01/07 | Q83: 7250 | R83: 130 | S83: 29372 | T83: 212624730 | U83: 7280 | V83: 7320 | W83: 7130 | X83: 182776 | Y83: 25210438
B84: 대손충당금 | C84: -25860 | D84: - | E84: -36711 | F84: - | G84: 315919 | H84: - | J84: 제 58 기 2017.01.01 부터 2017.12.31 까지 | P84: 2019/01/04 | Q84: 7120 | R84: -130 | S84: 10883 | T84: 77352910 | U84: 7160 | V84: 7170 | W84: 7070 | X84: 179498 | Y84: 25210438
B85: 소 계 | C85: 248901 | D85: - | E85: 307975 | F85: - | J85: 제 57 기 2016.01.01 부터 2016.12.31 까지 | P85: 2019/01/03 | Q85: 7250 | R85: 130 | S85: 34772 | T85: 247485830 | U85: 7070 | V85: 7290 | W85: 6940 | X85: 182776 | Y85: 25210438
B86: 기타채권: | G86: 100828 | H86: 40 | J86: (단위 : 원) | P86: 2019/01/02 | Q86: 7120 | R86: -10 | S86: 7821 | T86: 55175490 | U86: 7150 | V86: 7150 | W86: 6990 | X86: 179498 | Y86: 25210438
B87: 미수금 | C87: 88143 | D87: 37 | E87: 132402 | F87: 37 | G87: -21050 | H87: - | K87: 제 59 기 | L87: 제 58 기 | M87: 제 57 기 | P87: 2018/12/28 | Q87: 7130 | R87: 130 | S87: 5319 | T87: 37397660 | U87: 6980 | V87: 7130 | W87: 6980 | X87: 179750 | Y87: 25210438
B88: 대손충당금 | C88: -14390 | D88: - | E88: -19860 | F88: - | G88: 4852 | H88: - | J88: 영업활동현금흐름 | K88: 9024737988 | L88: 38513229540 | M88: 97891992759 | P88: 2018/12/27 | Q88: 7000 | R88: 60 | S88: 12426 | T88: 86804860 | U88: 6940 | V88: 7080 | W88: 6930 | X88: 176473 | Y88: 25210438
B89: 미수수익 | C89: 7517 | D89: - | E89: 8126 | G89: -4 | H89: - | J89: 당기순이익(손실) | K89: 14451159656 | L89: 15249106086 | M89: 6137320223 | P89: 2018/12/26 | Q89: 6940 | R89: -230 | S89: 30078 | T89: 209173880 | U89: 7170 | V89: 7170 | W89: 6840 | X89: 174960 | Y89: 25210438
B90: 대손충당금 | C90: - | D90: - | E90: -9 | F90: - | J90: 당기순이익조정을 위한 가감 | K90: 96773085156 | L90: 83627590730 | M90: 73771544685 | P90: 2018/12/24 | Q90: 7170 | R90: -110 | S90: 11508 | T90: 82179950 | U90: 7270 | V90: 7270 | W90: 7090 | X90: 180759 | Y90: 25210438
B91: 대여금 | C91: 35763 | D91: 96132 | E91: 33738 | F91: 105085 | G91: 40868 | H91: 92589 | J91: 퇴직급여 | K91: 15723581840 | L91: 14459985539 | M91: 14145036640 | P91: 2018/12/21 | Q91: 7280 | R91: 120 | S91: 25129 | T91: 179188310 | U91: 7190 | V91: 7330 | W91: 7000 | X91: 183532 | Y91: 25210438
B92: 대손충당금 | C92: -2341 | D92: -9967 | E92: -3089 | F92: -14446 | G92: -4570 | H92: -11678 | J92: 감가상각비 | K92: 12891905802 | L92: 12022504530 | M92: 10453762461 | P92: 2018/12/20 | Q92: 7160 | R92: -30 | S92: 11650 | T92: 83925230 | U92: 7230 | V92: 7270 | W92: 7120 | X92: 180507 | Y92: 25210438
B93: 현재가치할인차금 | C93: -598 | D93: -11594 | E93: -823 | F93: -8529 | G93: -798 | H93: -6638 | J93: 투자부동산 감가상각비 | K93: 2500833623 | L93: 1536112776 | M93: 1317330795 | P93: 2018/12/19 | Q93: 7190 | R93: -120 | S93: 23518 | T93: 170198330 | U93: 7370 | V93: 7370 | W93: 7190 | X93: 181263 | Y93: 25210438
B94: 보증금 | C94: 1296 | D94: 49708 | E94: 1296 | F94: 52684 | G94: 1296 | H94: 53215 | J94: 무형자산상각비 | K94: 4066154416 | L94: 3349863013 | M94: 2549639152 | P94: 2018/12/18 | Q94: 7310 | R94: -60 | S94: 23643 | T94: 172738240 | U94: 7230 | V94: 7400 | W94: 7210 | X94: 184288 | Y94: 25210438
B95: 현재가치할인차금 | C95: -39 | D95: -4269 | E95: -40 | F95: -5053 | G95: -39 | H95: -5785 | J95: 대손상각비 | K95: 7557148714 | L95: 4918938451 | M95: 3914937601 | P95: 2018/12/17 | Q95: 7370 | R95: -20 | S95: 11515 | T95: 84051980 | U95: 7390 | V95: 7410 | W95: 7230 | X95: 185801 | Y95: 25210438
B96: 금융보증자산 | C96: 9827 | D96: 11446 | E96: 9175 | F96: 9095 | G96: 9450 | H96: 15628 | J96: 기타의 대손상각비 | K96: 6014020392 | L96: 3178086120 | M96: 4194237571 | P96: 2018/12/14 | Q96: 7390 | R96: 0 | S96: 39577 | T96: 291853780 | U96: 7300 | V96: 7450 | W96: 7300 | X96: 186305 | Y96: 25210438
B97: 소 계 | C97: 125178 | D97: 131493 | E97: 160916 | F97: 138873 | G97: 130833 | H97: 137371 | J97: 매도가능금융자산처분손실 | L97: 137760942 | M97: 440153070 | P97: 2018/12/13 | Q97: 7390 | R97: 30 | S97: 29071 | T97: 213332150 | U97: 7370 | V97: 7450 | W97: 7270 | X97: 186305 | Y97: 25210438
B98: 합 계 | C98: 374079 | D98: 131493 | E98: 468891 | F98: 138873 | G98: 446752 | H98: 137371 | J98: 매도가능금융자산손상차손 | L98: 6367429040 | M98: 9882922256 | P98: 2018/12/12 | Q98: 7360 | R98: 80 | S98: 20196 | T98: 148229770 | U98: 7200 | V98: 7450 | W98: 7200 | X98: 185549 | Y98: 25210438
J99: 기타포괄손익-공정가치측정채무상품처분손실 | K99: 140442594 | P99: 2018/12/11 | Q99: 7280 | R99: -360 | S99: 74540 | T99: 546753430 | U99: 7610 | V99: 7620 | W99: 7200 | X99: 183532 | Y99: 25210438
J100: 당기손익-공정가치측정금융상품처분손실 | K100: 132884060 | P100: 2018/12/10 | Q100: 7640 | R100: -100 | S100: 60116 | T100: 457730650 | U100: 7540 | V100: 7780 | W100: 7500 | X100: 192608 | Y100: 25210438
B101: 19. 차입금및사채 | J101: 당기손익-공정가치측정금융상품평가손실 | K101: 572477405 | P101: 2018/12/07 | Q101: 7740 | R101: 410 | S101: 621293 | T101: 4870008600 | U101: 7460 | V101: 8110 | W101: 7460 | X101: 195129 | Y101: 25210438
B102: (1) 당기말과 전기말 현재 차입금및사채의 내역은 다음과 같습니다. | J102: 지분법손실 | K102: 5582098584 | L102: 15158306699 | M102: 2431729825 | P102: 2018/12/06 | Q102: 7330 | R102: -70 | S102: 28443 | T102: 208483330 | U102: 7350 | V102: 7430 | W102: 7210 | X102: 184793 | Y102: 25210438
...

Sheet 현대건설
B2: PL | C2: 2018 | D2: 2017 | E2: 2016 | F2: BS | G2: 2018.12.31 | H2: 2017.12.31 | I2: 2016.12.31
C3: 12mths | D3: 12mths | E3: 12mths | F3: Cash | G3: =G4+G5 -> 4066143 | H3: =H4+H5 -> 3463893 | I3: =I4+I5 -> 3595219
B4: Revenue | C4: =J33 -> 16730894 | D4: =K33 -> 16887090 | E4: =L33 -> 18825015 | F4: 현금및현금성자산 | G4: =C35 -> 2241188 | H4: =D35 -> 2107242 | I4: =E35 -> 2149984
B5: EBIT | C5: =J37 -> 839989 | D5: =K37 -> 986105 | E5: =L37 -> 1158959 | F5: 단기금융상품 | G5: =C36 -> 1824955 | H5: =D36 -> 1356651 | I5: =E36 -> 1445235
B6: Dep | C6: =SUM(J81:J84) -> 175573 | D6: =SUM(K81:K84) -> 194561 | E6: =SUM(L81:L84) -> 191201 | F6: Debt | G6: =SUM(G7:G10) -> 2400899 | H6: =SUM(H7:H10) -> 2209352 | I6: =SUM(I7:I10) -> 2510605
B7: EBITDA | C7: =C5+C6 -> 1015562 | D7: =D5+D6 -> 1180666 | E7: =E5+E6 -> 1350160 | F7: 단기차입금 | G7: =SUM(E108:E110) -> 266486 | H7: =SUM(F108:F110) -> 290166 | I7: =SUM(G108:G110) -> 114087
B8: NI(Loss) | C8: =J46 -> 535303 | D8: =K46 -> 371564 | E8: =L46 -> 731713 | F8: 유동성장기차입금 | G8: =-(E123+F147) -> 328612 | H8: =-(F123+G147) -> 223621 | I8: =-(G123+H147) -> 428436
F9: 장기차입금 | G9: =E124 -> 458363 | H9: =F124 -> 348102 | I9: =G124 -> 431693
F10: 사채 | G10: =F148 -> 1347438 | H10: =G148 -> 1347463 | I10: =H148 -> 1536389
F11: NOA | G11: =SUM(G12:G18) -> 1169462 | H11: =SUM(H12:H18) -> 1721209 | I11: =SUM(I12:I18) -> 1614507
F12: 장기금융상품 | G12: =C47 -> 7531 | H12: =D47 -> 611111 | I12: =E47 -> 249782
F13: 투자부동산 | G13: =C57 -> 371598 | H13: =D57 -> 394196 | I13: =E57 -> 390939
F14: 관계기업투자 | G14: =C55 -> 45891 | H14: =D55 -> 79319 | I14: =E55 -> 128145
F15: 당기손익-공정가치측정금융자산 | G15: =C53 -> 298346 | H15: =SUM(D50:D51) -> 292014 | I15: =SUM(E50:E51) -> 299806
F16: 기타포괄손익-공정가치측정금융자산 | G16: =C52 -> 83468 | H16: =D52 -> 0 | I16: =E52 -> 0
F17: 상각후원가측정유가증권 | G17: =C41+C54 -> 51998 | H17: =D40 -> 16668 | I17: =E40 -> 267135
F18: 장단기대여금 | G18: =D166+D167+D173+D174+D187+D188 -> 310630 | H18: =E166+E167+E173+E174+E187+E188 -> 327901 | I18: =G166+G167+G173+G187+G188 -> 278700
F19: BV | G19: =C95 -> 8291856 | H19: =D95 -> 8472938 | I19: =E95 -> 8124645 | N19: 2018-10-01~2018-12-31 | O19: =AVERAGE(O87:O148) -> 54182.258 | P19: =AVERAGE(O331:O387) -> 37092.105 | Q19: =AVERAGE(O574:O636) -> 42220.635 | R19: 종가
N20: 2019-01-01~2019-03-31 | O20: =AVERAGE(O28:O86) -> 57727.119 | P20: =AVERAGE(O270:O330) -> 40387.705 | Q20: =AVERAGE(O512:O573) -> 45703.226 | R20: 종가
N21: 2018-10-01~2019-03-31 | O21: =AVERAGE(O28:O148) -> 55910.744 | P21: =AVERAGE(O270:O390) -> 38779.752 | Q21: =AVERAGE(O512:O636) -> 43948 | R21: 종가
N22: 2018.12.31 | O22: =V87 -> 6080025 | P22: =V331 -> 4042214 | Q22: =V574 -> 4766027 | R22: 시가총액
N23: 2019.03.31 | O23: =V28 -> 5946398 | P23: =V270 -> 4866247 | Q23: =V512 -> 5512110 | R23: 시가총액
O24: =W28 -> 111355765 | P24: =W270 -> 111355765 | Q24: =W512 -> 111355765 | R24: 상장주식수
N25: 3. 일자별시세 | Y25: 4. 제품군
B27: 연결 재무상태표 | I27: 연결 포괄손익계산서 | N27: 년/월/일 | O27: 종가 | P27: 대비 | Q27: 거래량(주) | R27: 거래대금(원) | S27: 시가 | T27: 고가 | U27: 저가 | V27: 시가총액(백만) | W27: 상장주식수(주)
B28: 제 69 기 2018.12.31 현재 | I28: 제 69 기 2018.01.01 부터 2018.12.31 까지 | N28: 2019/03/29 | O28: 53400 | P28: 3000 | Q28: 1320678 | R28: 69400543400 | S28: 50500 | T28: 53500 | U28: 50300 | V28: 5946398 | W28: 111355765
B29: 제 68 기 2017.12.31 현재 | I29: 제 68 기 2017.01.01 부터 2017.12.31 까지 | N29: 2019/03/28 | O29: 50400 | P29: -100 | Q29: 385787 | R29: 19537069800 | S29: 50400 | T29: 51000 | U29: 50300 | V29: 5612331 | W29: 111355765
B30: 제 67 기 2016.12.31 현재 | I30: 제 67 기 2016.01.01 부터 2016.12.31 까지 | N30: 2019/03/27 | O30: 50500 | P30: -800 | Q30: 397721 | R30: 20212760600 | S30: 51200 | T30: 51400 | U30: 50400 | V30: 5623466 | W30: 111355765
B31: (단위 : 백만원) | I31: (단위 : 백만원) | N31: 2019/03/26 | O31: 51300 | P31: 100 | Q31: 395818 | R31: 20281138500 | S31: 51300 | T31: 51600 | U31: 50800 | V31: 5712551 | W31: 111355765
C32: 제 69 기 | D32: 제 68 기 | E32: 제 67 기 | J32: 제 69 기 | K32: 제 68 기 | L32: 제 67 기 | N32: 2019/03/25 | O32: 51200 | P32: -300 | Q32: 599622 | R32: 30569553700 | S32: 50600 | T32: 51500 | U32: 50300 | V32: 5701415 | W32: 111355765
B33: 자산 | I33: 매출액 | J33: 16730894 | K33: 16887090 | L33: 18825015 | N33: 2019/03/22 | O33: 51500 | P33: 1300 | Q33: 616205 | R33: 31487363400 | S33: 50200 | T33: 51600 | U33: 50200 | V33: 5734822 | W33: 111355765
B34: 유동자산 | C34: 13336768 | D34: 13249840 | E34: 14937924 | I34: 매출원가 | J34: 15069747 | K34: 15108126 | L34: 16895275 | N34: 2019/03/21 | O34: 50200 | P34: -900 | Q34: 606051 | R34: 30760140600 | S34: 51000 | T34: 51500 | U34: 50200 | V34: 5590059 | W34: 111355765
B35: 현금및현금성자산 | C35: 2241188 | D35: 2107242 | E35: 2149984 | I35: 매출총이익 | J35: 1661147 | K35: 1778964 | L35: 1929740 | N35: 2019/03/20 | O35: 51100 | P35: -500 | Q35: 329060 | R35: 16786742700 | S35: 51300 | T35: 51700 | U35: 50600 | V35: 5690280 | W35: 111355765
B36: 단기금융상품 | C36: 1824955 | D36: 1356651 | E36: 1445235 | I36: 판매비와관리비 | J36: 821158 | K36: 792859 | L36: 770781 | N36: 2019/03/19 | O36: 51600 | P36: 200 | Q36: 448860 | R36: 23145999800 | S36: 51800 | T36: 51900 | U36: 51100 | V36: 5745957 | W36: 111355765
B37: 매출채권 | C37: 2176726 | D37: 1966367 | E37: 2555190 | I37: 영업이익 | J37: 839989 | K37: 986105 | L37: 1158959 | N37: 2019/03/18 | O37: 51400 | P37: 700 | Q37: 572432 | R37: 29340203300 | S37: 51200 | T37: 51800 | U37: 50800 | V37: 5723686 | W37: 111355765
B38: 기타채권 | C38: 1322349 | D38: 1499381 | E38: 1795329 | I38: 지분법이익 | J38: 1856 | K38: 1249 | L38: 5669 | N38: 2019/03/15 | O38: 50700 | P38: 300 | Q38: 1686497 | R38: 85766680100 | S38: 50400 | T38: 52200 | U38: 49800 | V38: 5645737 | W38: 111355765
B39: 미청구공사 | C39: 2679723 | D39: 2896446 | E39: 3595809 | I39: 지분법손실 | J39: 18299 | K39: 16159 | L39: 11589 | N39: 2019/03/14 | O39: 50400 | P39: 400 | Q39: 700416 | R39: 35361385400 | S39: 50300 | T39: 51000 | U39: 50200 | V39: 5612331 | W39: 111355765
B40: 만기보유금융자산 | D40: 16668 | E40: 267135 | I40: 금융수익 | J40: 283085 | K40: 154925 | L40: 170649 | N40: 2019/03/13 | O40: 50000 | P40: -1100 | Q40: 622022 | R40: 31254899150 | S40: 51000 | T40: 51100 | U40: 49900 | V40: 5567788 | W40: 111355765
B41: 상각후원가 측정 금융자산 | C41: 14692 | I41: 금융비용 | J41: 172583 | K41: 300027 | L41: 200498 | N41: 2019/03/12 | O41: 51100 | P41: 0 | Q41: 690085 | R41: 35555085900 | S41: 51600 | T41: 52400 | U41: 51000 | V41: 5690280 | W41: 111355765
B42: 파생상품자산 | C42: 9 | I42: 기타수익 | J42: 257050 | K42: 360978 | L42: 317256 | N42: 2019/03/11 | O42: 51100 | P42: 0 | Q42: 727591 | R42: 36737964350 | S42: 51000 | T42: 51300 | U42: 49750 | V42: 5690280 | W42: 111355765
B43: 재고자산 | C43: 1947052 | D43: 2105517 | E43: 1199362 | I43: 기타비용 | J43: 293236 | K43: 632242 | L43: 458968 | N43: 2019/03/08 | O43: 51100 | P43: -1100 | Q43: 589480 | R43: 30348486000 | S43: 51700 | T43: 52400 | U43: 51000 | V43: 5690280 | W43: 111355765
B44: 법인세자산 | C44: 4898 | D44: 3749 | E44: 4307 | I44: 법인세비용차감전순이익 | J44: 897862 | K44: 554829 | L44: 981478 | N44: 2019/03/07 | O44: 52200 | P44: -500 | Q44: 784079 | R44: 41142504900 | S44: 52500 | T44: 53300 | U44: 51800 | V44: 5812771 | W44: 111355765
B45: 기타유동자산 | C45: 1125176 | D45: 1297819 | E45: 1925573 | I45: 법인세비용 | J45: 362559 | K45: 183265 | L45: 249765 | N45: 2019/03/06 | O45: 52700 | P45: -1400 | Q45: 1180569 | R45: 62505345900 | S45: 54100 | T45: 54200 | U45: 52500 | V45: 5868449 | W45: 111355765
B46: 비유동자산 | C46: 4717841 | D46: 5182062 | E46: 4935519 | I46: 당기순이익 | J46: 535303 | K46: 371564 | L46: 731713 | N46: 2019/03/05 | O46: 54100 | P46: -200 | Q46: 920458 | R46: 49837807100 | S46: 54300 | T46: 54700 | U46: 53600 | V46: 6024347 | W46: 111355765
B47: 장기금융상품 | C47: 7531 | D47: 611111 | E47: 249782 | I47: 법인세차감후 기타포괄이익(손실) | J47: -207137 | K47: 72581 | L47: 110703 | N47: 2019/03/04 | O47: 54300 | P47: -2900 | Q47: 2350983 | R47: 130185749600 | S47: 55000 | T47: 56800 | U47: 54100 | V47: 6046618 | W47: 111355765
B48: 장기미수채권 | C48: 379385 | D48: 364030 | E48: 409017 | I48: 후속적으로 당기손익으로 재분류되지 않는항목 | J48: -16008 | K48: 55242 | L48: 21567 | N48: 2019/02/28 | O48: 57200 | P48: -5000 | Q48: 1900149 | R48: 112709312100 | S48: 62400 | T48: 62700 | U48: 56200 | V48: 6369550 | W48: 111355765
B49: 장기성기타채권 | C49: 975213 | D49: 906373 | E49: 895090 | I49: 지분법자본변동 | J49: 1 | K49: 971 | L49: 2209 | N49: 2019/02/27 | O49: 62200 | P49: -100 | Q49: 449368 | R49: 27897191700 | S49: 62800 | T49: 62900 | U49: 61600 | V49: 6926329 | W49: 111355765
B50: 매도가능금융자산 | D50: 266255 | E50: 267404 | I50: 확정급여제도의 재측정요소 | J50: -18799 | K50: 54271 | L50: 19358 | N50: 2019/02/26 | O50: 62300 | P50: 900 | Q50: 613093 | R50: 38212773100 | S50: 61900 | T50: 63000 | U50: 61800 | V50: 6937464 | W50: 111355765
B51: 만기보유금융자산 | D51: 25759 | E51: 32402 | I51: 기타포괄손익-공정가치 측정 금융자산 평가손익 | J51: 2790 | N51: 2019/02/25 | O51: 61400 | P51: -2200 | Q51: 1033706 | R51: 64101600800 | S51: 63600 | T51: 64200 | U51: 61300 | V51: 6837244 | W51: 111355765
B52: 기타포괄손익-공정가치 측정 금융자산 | C52: 83468 | I52: 후속적으로 당기손익으로 재분류될 수 있는 항목 | J52: -191129 | K52: 17339 | L52: 89136 | N52: 2019/02/22 | O52: 63600 | P52: 800 | Q52: 520756 | R52: 32952589200 | S52: 62400 | T52: 63800 | U52: 62100 | V52: 7082227 | W52: 111355765
B53: 당기손익-공정가치 측정 지정 금융자산 | C53: 298346 | I53: 매도가능금융자산평가손익 | K53: 1029 | L53: 866 | N53: 2019/02/21 | O53: 62800 | P53: -700 | Q53: 812042 | R53: 50448016100 | S53: 63700 | T53: 63800 | U53: 61100 | V53: 6993142 | W53: 111355765
B54: 상각후원가 측정 금융자산 | C54: 37306 | I54: 해외사업환산손익 | J54: -191129 | K54: 16310 | L54: 88270 | N54: 2019/02/20 | O54: 63500 | P54: 200 | Q54: 506569 | R54: 32264507500 | S54: 64000 | T54: 64200 | U54: 63100 | V54: 7071091 | W54: 111355765
B55: 종속기업, 공동기업과 관계기업 투자자산 | C55: 45891 | D55: 79319 | E55: 128145 | I55: 총포괄손익 | J55: 328166 | K55: 444145 | L55: 842416 | N55: 2019/02/19 | O55: 63300 | P55: 500 | Q55: 519134 | R55: 33052119800 | S55: 62900 | T55: 64300 | U55: 62900 | V55: 7048820 | W55: 111355765
B56: 파생상품자산 | D56: 25 | I56: 당기순이익(손실)의 귀속 | N56: 2019/02/18 | O56: 62800 | P56: 300 | Q56: 324790 | R56: 20419324400 | S56: 63300 | T56: 63300 | U56: 62500 | V56: 6993142 | W56: 111355765
B57: 투자부동산 | C57: 371598 | D57: 394196 | E57: 390939 | I57: 지배기업소유주지분 | J57: 381606 | K57: 201697 | L57: 572112 | N57: 2019/02/15 | O57: 62500 | P57: 100 | Q57: 431320 | R57: 26907366100 | S57: 62000 | T57: 62900 | U57: 61700 | V57: 6959735 | W57: 111355765
B58: 유형자산 | C58: 1436574 | D58: 1398791 | E58: 1498089 | I58: 비지배주주지분 | J58: 153697 | K58: 169867 | L58: 159601 | N58: 2019/02/14 | O58: 62400 | P58: -500 | Q58: 921888 | R58: 56851787300 | S58: 62900 | T58: 63300 | U58: 60900 | V58: 6948600 | W58: 111355765
B59: 무형자산 | C59: 711198 | D59: 760228 | E59: 810336 | I59: 총 포괄손익의 귀속 | N59: 2019/02/13 | O59: 62900 | P59: -100 | Q59: 427807 | R59: 26999984000 | S59: 63500 | T59: 63800 | U59: 62600 | V59: 7004278 | W59: 111355765
B60: 이연법인세자산 | C60: 252549 | D60: 251650 | E60: 124633 | I60: 지배기업소유주지분 | J60: 225077 | K60: 201626 | L60: 664463 | N60: 2019/02/12 | O60: 63000 | P60: -1000 | Q60: 598606 | R60: 38033918900 | S60: 63500 | T60: 64800 | U60: 62800 | V60: 7015413 | W60: 111355765
B61: 기타비유동자산 | C61: 118782 | D61: 124325 | E61: 129682 | I61: 비지배주주지분 | J61: 103089 | K61: 242519 | L61: 177953 | N61: 2019/02/11 | O61: 64000 | P61: -300 | Q61: 481939 | R61: 31094496200 | S61: 65000 | T61: 65400 | U61: 64000 | V61: 7126769 | W61: 111355765
B62: 자산총계 | C62: 18054609 | D62: 18431902 | E62: 19873443 | I62: 지배기업소유주지분에 대한 주당이익 | N62: 2019/02/08 | O62: 64300 | P62: -700 | Q62: 534123 | R62: 34382379400 | S62: 64200 | T62: 65200 | U62: 64000 | V62: 7160176 | W62: 111355765
B63: 부채 | I63: 보통주 기본주당순이익 (단위 : 원) | J63: 3424 | K63: 1810 | L63: 5133 | N63: 2019/02/07 | O63: 65000 | P63: 500 | Q63: 875076 | R63: 57201918200 | S63: 66500 | T63: 67000 | U63: 64500 | V63: 7238125 | W63: 111355765
B64: 유동부채 | C64: 6860875 | D64: 7219038 | E64: 8749576 | I64: 구형우선주 기본주당순이익 (단위 : 원) | J64: 3474 | K64: 1860 | L64: 5229 | N64: 2019/02/01 | O64: 64500 | P64: 2300 | Q64: 1151133 | R64: 73705708900 | S64: 62500 | T64: 65000 | U64: 62400 | V64: 7182447 | W64: 111355765
B65: 매입채무 | C65: 2256754 | D65: 2347746 | E65: 2666981 | N65: 2019/01/31 | O65: 62200 | P65: 400 | Q65: 537369 | R65: 33356626800 | S65: 62500 | T65: 62700 | U65: 61400 | V65: 6926329 | W65: 111355765
B66: 기타채무 | C66: 1182054 | D66: 879357 | E66: 1350992 | N66: 2019/01/30 | O66: 61800 | P66: 2000 | Q66: 679357 | R66: 41719009600 | S66: 60600 | T66: 61900 | U66: 60200 | V66: 6881786 | W66: 111355765
B67: 공사 및 분양선수금 | C67: 1193947 | D67: 1388429 | E67: 1986132 | N67: 2019/01/29 | O67: 59800 | P67: -2300 | Q67: 848679 | R67: 51162723900 | S67: 61900 | T67: 62100 | U67: 59700 | V67: 6659075 | W67: 111355765
