Workbook
Name _CIR1: [2]VIVENDI단가산정!$EX$11
Name _CTW1: [2]VIVENDI단가산정!$GQ$11
Name _CTW2: [2]VIVENDI단가산정!$FM$11
Name _CTW3: [2]VIVENDI단가산정!$HF$11
Name _DEM1: [2]VIVENDI단가산정!$CP$11
Name _DEM2: [2]VIVENDI단가산정!$DE$11
Name _FXR3: [4]Control!$B$17
Name _FXR4: [4]Control!$B$18
Name _FXR5: [4]Control!$B$19
Name _LD1: '모델별 Mapping'!_LD1
Name _LD1: '모델별 Mapping'!_LD1
Name _POT1: [2]VIVENDI단가산정!$DT$11
Name _POT2: [2]VIVENDI단가산정!$EI$11
Name _pp11: '모델별 Mapping'!_pp11
Name _pp11: '모델별 Mapping'!_pp11
Name _PRE1: [2]VIVENDI단가산정!$AH$11
Name _PRE2: [2]VIVENDI단가산정!$AW$11
Name aaaa: '모델별 Mapping'!aaaa
Name aaaaa: '모델별 Mapping'!aaaaa
Name aaaaa: '모델별 Mapping'!aaaaa
Name aaaaaa: '모델별 Mapping'!aaaaaa
Name aaaaaa: '모델별 Mapping'!aaaaaa
Name aaabbbccc: '모델별 Mapping'!aaabbbccc
Name aaabbbccc: '모델별 Mapping'!aaabbbccc
Name as: '모델별 Mapping'!as
Name as: '모델별 Mapping'!as
Name asd: '모델별 Mapping'!asd
Name asd: '모델별 Mapping'!asd
Name asdf: '모델별 Mapping'!asdf
Name asdf: '모델별 Mapping'!asdf
Name asdfg: '모델별 Mapping'!asdfg
Name asdfg: '모델별 Mapping'!asdfg
Name asxz: '모델별 Mapping'!asxz
Name asxz: '모델별 Mapping'!asxz
Name BASE: [8]생산실적!$O$12
Name bbb: '모델별 Mapping'!bbb
Name bbb: '모델별 Mapping'!bbb
Name bbbbb: '모델별 Mapping'!bbbbb
Name bbbbb: '모델별 Mapping'!bbbbb
Name book: '모델별 Mapping'!book
Name book: '모델별 Mapping'!book
Name book2: '모델별 Mapping'!book2
Name book2: '모델별 Mapping'!book2
Name book3: '모델별 Mapping'!book3
Name book3: '모델별 Mapping'!book3
Name BW: [2]VIVENDI단가산정!$CA$11
Name BZ1_1: '모델별 Mapping'!BZ1_1
Name BZ1_1: '모델별 Mapping'!BZ1_1
Name CASE1: [9]MAIN!$V$16
Name ccc: '모델별 Mapping'!ccc
Name ccc: '모델별 Mapping'!ccc
Name cccccccccccccccccccccc: '모델별 Mapping'!cccccccccccccccccccccc
Name cccccccccccccccccccccc: '모델별 Mapping'!cccccccccccccccccccccc
Name chart2: '모델별 Mapping'!chart2
Name chart2: '모델별 Mapping'!chart2
Name CPG: [11]NCC!$B$144
Name CW: [12]수처리사업!$B$1:$Z$53
Name dd: [13]ECG!$B$34
Name ddd: '모델별 Mapping'!ddd
Name ddd: '모델별 Mapping'!ddd

Sheet Title
L5: Project
L6: =Des!C5 -> SVG1 | M6: =L6 -> SVG1
L10: Financial Model
L11: - Business Valuation

Sheet Des
B1: ="Project"&" "&Title!L6 -> Project SVG1 | C1: =$C$12 -> DRAFT - For Discussion Purposes Only
B2: Description
G4: DRAFT - For Discussion Purposes Only
B5: Project Name | C5: SVG1 | G5: FINAL
B6: Client | C6: 주식회사 동해기계항공
B7: Target Company | C7: 주식회사 동해기계항공 | G7: KPMG Color (신규)
B8: Valuation Date | C8: 43100 | G8: Primary | H8: R | I8: G | J8: B
B9: Year End after Valuation Date | C9: =IF(C8=DATE(YEAR(C8),12,31),DATE(YEAR(C8+1),12,31),DATE(YEAR(C8),12,31)) -> 43465 | G9: KPMG blue | H9: 0 | I9: 51 | J9: 141
B10: Partial Period Factor | C10: =(C9-C8)/365 -> 1 | G10: Medium blue | H10: 0 | I10: 94 | J10: 184
B11: Projection Period | C11: 2017/10/01 ~ 2021/12/31, 4년 3개월 | G11: Light blue | H11: 0 | I11: 145 | J11: 218
B12: Work-In-Progress Disclaimer | C12: DRAFT - For Discussion Purposes Only
B13: Currency & Unit | C13: KRW Million | G13: Secondary
B14: Terminal Growth rate | C14: 0.01 | G14: Violet | H14: 72 | I14: 54 | J14: 152
G15: Purple | H15: 71 | I15: 10 | J15: 104
G16: Light purple | H16: 109 | I16: 32 | J16: 119
G17: Green | H17: 0 | I17: 163 | J17: 161
G19: Tertiary
H20: 0 | I20: 154 | J20: 68
H21: 67 | I21: 176 | J21: 42
H22: 234 | I22: 170 | J22: 0
H23: 246 | I23: 141 | J23: 46
H24: 188 | I24: 32 | J24: 75
H25: 198 | I25: 0 | J25: 126

Sheet WGL
B1: ="Project"&" "&Title!L6 -> Project SVG1
B2: Working Group List
B4: 회사명 | C4: 업무 | D4: 이름 | E4: 부서 | F4: 직급 | G4: 이메일 | H4: 전화번호 | I4: 휴대전화
B5: KPMG 삼정회계법인 | C5: EP | D5: 김이동 | E5: DA5 | F5: 상무 | G5: yidongkim@kr.kpmg.com | H5: 02-2112-0343 | I5: 010-4048-5105
B6: KPMG 삼정회계법인 | C6: EM | D6: 박영걸 | E6: DA5 | F6: 이사 | G6: younggulpark@kr.kpmg.com | H6: 02-2112-0749 | I6: 010-6889-9548
B7: KPMG 삼정회계법인 | C7: ICA | D7: 김양태 | E7: DA5 | F7: 차장 | G7: ykim32@kr.kpmg.com | H7: 02-2112-7585 | I7: 010-5895-9114
B8: KPMG 삼정회계법인 | D8: 권기문 | E8: DA5 | F8: 과장' | G8: kimoonkwon@kr.kpmg.com | H8: 02-2112-6948 | I8: 010-2506-1320

Sheet DCF(KPMG)>>

Sheet _TM_Result(보고서)
A1: Left | B1: Top | C1: Right | D1: Bottom | E1: Ref
A2: 7 | B2: 5 | C2: 12 | D2: 7 | E2: $G$5:$L$7

Sheet _TM_Result
A1: Left | B1: Top | C1: Right | D1: Bottom | E1: Ref
A2: 14 | B2: 17 | C2: 17 | D2: 22 | E2: $N$17:$Q$22

Sheet Result
B1: ="Project"&" "&Title!L6 -> Project SVG1
B2: Result
B4: 평가방법 | C4: Low | E4: High | F4: 중간값
B5: GTM | D5: =E5-C5 -> 0
B6: GPCM | D6: =E6-C6 -> 0
B7: DCF | D7: =E7-C7 -> 0

Sheet DCF
B1: ="Project"&" "&Title!L6 -> Project SVG1 | N1: =Des!C12 -> DRAFT - For Discussion Purposes Only
B2: Discounted Cash Flow Results
B4: DCF Results | D4: Historical | H4: Forecasted
B5: =unit -> KRW Million | D5: ='Pro forma'!D$5 -> 2014 | E5: ='Pro forma'!E$5 -> 2015 | F5: ='Pro forma'!F$5 -> 2016 | G5: ='Pro forma'!G$5 -> 2017 | H5: ='Pro forma'!H$5 -> 2018 | I5: ='Pro forma'!I$5 -> 2019 | J5: ='Pro forma'!J$5 -> 2020 | K5: ='Pro forma'!K$5 -> 2021 | L5: 2022F | M5: Terminal | S5: 세율 | T5: 0.11
B6: Sales | D6: ='Pro forma'!D6 -> 41447.714 | E6: ='Pro forma'!E6 -> 61966.746 | F6: ='Pro forma'!F6 -> 81488.231 | G6: ='Pro forma'!G6 -> 92333.966 | H6: ='Pro forma'!H6 -> 138011.23 | I6: ='Pro forma'!I6 -> 182151.03 | J6: ='Pro forma'!J6 -> 203944.82 | K6: ='Pro forma'!K6 -> 261216.69 | L6: ='Pro forma'!L6 -> 300836.43 | M6: =L6*(1+$C$24) -> 303844.79 | S6: 최대 | T6: 200
B7: COGS | D7: ='Pro forma'!D9 -> 29094.554 | E7: ='Pro forma'!E9 -> 42664.217 | F7: ='Pro forma'!F9 -> 59896.716 | G7: ='Pro forma'!G9 -> 66253.175 | H7: ='Pro forma'!H9 -> 95072.958 | I7: ='Pro forma'!I9 -> 126580.95 | J7: ='Pro forma'!J9 -> 140774.16 | K7: ='Pro forma'!K9 -> 178212.96 | L7: ='Pro forma'!L9 -> 204547.06 | M7: =L7*(1+$C$24) -> 206592.53 | S7: Extra
B8: Gross Profit | D8: =D6-D7 -> 12353.16 | E8: =E6-E7 -> 19302.528 | F8: =F6-F7 -> 21591.515 | G8: =G6-G7 -> 26080.791 | H8: =H6-H7 -> 42938.268 | I8: =I6-I7 -> 55570.08 | J8: =J6-J7 -> 63170.662 | K8: =K6-K7 -> 83003.728 | ... M8: =M6-M7 -> 97252.258 | S8: 세율 | T8: 0.22
B9: SG&A | D9: ='Pro forma'!D17 -> 6260.3832 | E9: ='Pro forma'!E17 -> 7139.8918 | F9: ='Pro forma'!F17 -> 7407.697 | G9: ='Pro forma'!G17 -> 10368.971 | H9: ='Pro forma'!H17 -> 9842.4629 | I9: ='Pro forma'!I17 -> 11618.075 | J9: ='Pro forma'!J17 -> 13319.84 | K9: ='Pro forma'!K17 -> 15631.565 | L9: ='Pro forma'!L17 -> 17765.693 | M9: =L9*(1+$C$24) -> 17943.35 | S9: 최대 | T9: 20000
B10: EBIT | D10: =D8-D9 -> 6092.7769 | E10: =E8-E9 -> 12162.637 | F10: =F8-F9 -> 14183.818 | G10: =G8-G9 -> 15711.82 | H10: =H8-H9 -> 33095.805 | I10: =I8-I9 -> 43952.005 | J10: =J8-J9 -> 49850.822 | K10: =K8-K9 -> 67372.164 | ... M10: =M8-M9 -> 79308.908 | S10: Extra | T10: =200*11% -> 22
B11: Income Tax | H11: =IF(H10<=$T$6,H10*$T$5,IF(H10>$T$9,(H10-$T$9)*$T$11+$T$13,(H10-$T$6)*$T$8+$T$10)) -> 7547.1848 | I11: =IF(I10<=$T$6,I10*$T$5,IF(I10>$T$9,(I10-$T$9)*$T$11+$T$13,(I10-$T$6)*$T$8+$T$10)) -> 10174.385 | J11: =IF(J10<=$T$6,J10*$T$5,IF(J10>$T$9,(J10-$T$9)*$T$11+$T$13,(J10-$T$6)*$T$8+$T$10)) -> 11601.899 | K11: =IF(K10<=$T$6,K10*$T$5,IF(K10>$T$9,(K10-$T$9)*$T$11+$T$13,(K10-$T$6)*$T$8+$T$10)) -> 15842.064 | L11: =IF(L10<=$T$6,L10*$T$5,IF(L10>$T$9,(L10-$T$9)*$T$11+$T$13,(L10-$T$6)*$T$8+$T$10)) -> 18540.728 | M11: =IF(M10<=$T$6,M10*$T$5,IF(M10>$T$9,(M10-$T$9)*$T$11+$T$13,(M10-$T$6)*$T$8+$T$10)) -> 18730.756 | S11: 세율 | T11: 0.242
B12: NOPLAT | H12: =H10-H11 -> 25548.62 | I12: =I10-I11 -> 33777.62 | J12: =J10-J11 -> 38248.923 | K12: =K10-K11 -> 51530.1 | L12: =L10-L11 -> 59982.943 | M12: =M10-M11 -> 60578.152 | S12: 최대
B13: (+) Depreciation | H13: ='CapEx&Dep'!H8 -> 1099.3242 | I13: ='CapEx&Dep'!I8 -> 1174.6995 | J13: ='CapEx&Dep'!J8 -> 1432.5499 | K13: ='CapEx&Dep'!K8 -> 1899.2471 | L13: ='CapEx&Dep'!L8 -> 2179.9706 | M13: =CapEx | S13: Extra | T13: =39800*11% -> 4378
B14: (-) Increase in Net WC | H14: =WC!H23 -> 1658.4995 | I14: =WC!I23 -> 2899.6358 | J14: =WC!J23 -> 1329.8297 | K14: =WC!K23 -> 3505.1515 | L14: =WC!L23 -> 2457.262 | M14: =WC!M23 -> 190.0101
B15: (-) Capital Expenditure | H15: ='CapEx&Dep'!H6 -> 2804.3188 | I15: ='CapEx&Dep'!I6 -> 2263.5366 | J15: ='CapEx&Dep'!J6 -> 14548.685 | K15: ='CapEx&Dep'!K6 -> 5030.1011 | L15: ='CapEx&Dep'!L6 -> 3452.4351 | M15: =Dep
B16: Free Cash Flow to Firm (FCFF) | H16: =H12+H13-H14-H15 -> 22185.126 | I16: =I12+I13-I14-I15 -> 29789.147 | J16: =J12+J13-J14-J15 -> 23802.958 | K16: =K12+K13-K14-K15 -> 44894.095 | L16: =L12+L13-L14-L15 -> 56253.216 | M16: =M12-M14 -> 60388.142
B17: Discount Period | H17: 1 | I17: =H17+1 -> 2 | J17: =I17+1 -> 3 | K17: =J17+1 -> 4 | L17: =K17+1 -> 5 | M17: =L17+1 -> 6
B18: Discount Factor | H18: =1/(1+$C$25)^H17 -> 0.8984726 | I18: =1/(1+$C$25)^I17 -> 0.80725301 | J18: =1/(1+$C$25)^J17 -> 0.72529471 | K18: =1/(1+$C$25)^K17 -> 0.65165742 | L18: =1/(1+$C$25)^L17 -> 0.58549633 | M18: =1/(1+$C$25)^M17 -> 0.52605241
B19: Present Value of FCFF | H19: =H16*H18 -> 19932.728 | I19: =I16*I18 -> 24047.378 | J19: =J16*J18 -> 17264.16 | K19: =K16*K18 -> 29255.57 | L19: =L16*L18 -> 32936.052 | M19: =M16*M18 -> 31767.328
B20: Cumulative Present Value | H20: =SUM(H19:L19) -> 123435.89
B21: Present Value of Terminal Value | H21: =M19 -> 31767.328
B22: Operating Value | H22: =H20+H21 -> 155203.22
B24: Terminal Growth Rate | C24: =g -> 0.01
B25: WACC | C25: =wacc -> 0.113
B27: Stand-Alone Operating Value
F28: =unit -> KRW Million
B29: 항목 | D29: 평가결과 | J29: Terminal Growth Rate
D30: 최소값 | E30: 중앙값 | F30: 최대값 | I30: =H22 -> 155203.22 | J30: =K30-CHOOSE($Q$33,$R$32,$R$33) -> 0 | K30: =L30-CHOOSE($Q$33,$R$32,$R$33) -> 0.005 | L30: 0.01 | M30: =L30+CHOOSE($Q$33,$R$32,$R$33) -> 0.015 | N30: =M30+CHOOSE($Q$33,$R$32,$R$33) -> 0.02
B31: Operating Value | D31: =K34 -> 152423.71 | E31: =H22 -> 155203.22 | F31: =M32 -> 158057.74 | I31: =I32-CHOOSE($Q$33,$R$32,$R$33) -> 0.103 | J31: 160328.73 | K31: 160494 | L31: 160659.27 | M31: 160824.53 | N31: 160989.8
B32: Non-operating Asset | E32: ='NOA&IBD'!E11 -> 46315.428 | I32: =I33-CHOOSE($Q$33,$R$32,$R$33) -> 0.108 | J32: 157575.21 | K32: 157736.05 | L32: 157896.9 | M32: 158057.74 | N32: 158218.58 | Q32: 민감도 범위 선택 | R32: 0.005
B33: Enterprise Value | D33: =D31+$E$32 -> 198739.14 | E33: =E31+$E$32 -> 201518.64 | F33: =F31+$E$32 -> 204373.17 | I33: =wacc -> 0.113 | J33: 154890.1 | K33: 155046.66 | L33: 155203.22 | M33: 155359.77 | N33: 155516.33 | Q33: 1 | R33: 0.01
B34: Interest Bearing Debt | E34: ='NOA&IBD'!E18 -> 0 | I34: =I33+CHOOSE($Q$33,$R$32,$R$33) -> 0.118 | J34: 152271.31 | K34: 152423.71 | L34: 152576.11 | M34: 152728.51 | N34: 152880.92
B35: Stock Option | I35: =I34+CHOOSE($Q$33,$R$32,$R$33) -> 0.123 | J35: 149716.81 | K35: 149865.18 | L35: 150013.56 | M35: 150161.93 | N35: 150310.31
B36: Equity Value | D36: =D33-$E$34-$E$35 -> 198739.14 | E36: =E33-$E$34-$E$35 -> 201518.64 | F36: =F33-$E$34-$E$35 -> 204373.17

Sheet WACC
B1: Bloomberg Template | R1: <Tax Rate>
B2: Weighted Average Cost of Capital | R2: Unlevered | T2: 0.242
R3: Re-Levered, Kd | T3: 0.242 | U3: <= Terminal year 기준 EBIT규모에 따름 => 11%(~2억), 22%(~200억), 24.2%(200억~)
B4: Guideline Public Company | E4: Country | G4: Observed | H4: MKT Cap | I4: IBD | J4: Debt | L4: Debt | N4: Tax Rate | O4: Unlevered Beta | P4: Re-Levered Beta | Y4: =[28]Company!B5 -> 회계 데이터 기준일 | AA4: =TEXT([28]Company!D5,"YYYY년 M월 D일") -> 2017년 9월 29일
G5: Beta | J5: Equity | L5: TIC | Y5: =[28]Company!B6 -> Market Data 기준일 | AA5: =TEXT([28]Company!D6,"YYYY년 M월 D일") -> 2017년 9월 29일
A6: 1 | B6: =IF([28]Raw!AC9="","",[28]Raw!AC9) -> Hyundai Construction Equipment Co Ltd | E6: =IF([28]Raw!AF9="","",[28]Raw!AF9) -> SOUTH KOREA | G6: =IF(B6="","",CHOOSE($W$26,G65,H65,I65)) -> 1.281801 | H6: =IF(B6="","",CHOOSE($W$28,G82,H82,I82,J82,L82)) -> #DIV/0! | I6: =IF(B6="","",G100) -> 615793 | J6: =IF(B6="","",I6/H6) -> #DIV/0! | L6: =IF(B6="","",I6/(H6+I6)) -> #DIV/0! | N6: 0.242 | O6: =IF(B6="","",IF(G6="NA","NA",G6/(1+J6*(1-N6)))) -> #DIV/0! | P6: =IF(B6="","",O6*(1+($L$41/$L$42)*$E$41)) -> #DIV/0!
A7: =A6+1 -> 2 | B7: =IF([28]Raw!AC10="","",[28]Raw!AC10) -> Doosan Bobcat Inc | E7: =IF([28]Raw!AF10="","",[28]Raw!AF10) -> SOUTH KOREA | G7: =IF(B7="","",CHOOSE($W$26,G66,H66,I66)) -> 0.91189 | H7: =IF(B7="","",CHOOSE($W$28,G83,H83,I83,J83,L83)) -> 3664107 | I7: =IF(B7="","",G101) -> 103202.18 | J7: =IF(B7="","",I7/H7) -> 0.02816571 | L7: =IF(B7="","",I7/(H7+I7)) -> 0.027394135 | N7: 0.242 | O7: =IF(B7="","",IF(G7="NA","NA",G7/(1+J7*(1-N7)))) -> 0.89282846 | P7: =IF(B7="","",O7*(1+($L$41/$L$42)*$E$41)) -> 0.97444909 | AA7: =CHOOSE(W26,"5년 평균 Weekly adjusted Beta","5년 평균 Monthly adjusted Beta","2년 평균 Weekly adjusted Beta") -> 5년 평균 Weekly adjusted Beta
A8: =A7+1 -> 3 | B8: =IF([28]Raw!AC11="","",[28]Raw!AC11) -> DY POWER Corp | E8: =IF([28]Raw!AF11="","",[28]Raw!AF11) -> SOUTH KOREA | G8: =IF(B8="","",CHOOSE($W$26,G67,H67,I67)) -> 1.225582 | H8: =IF(B8="","",CHOOSE($W$28,G84,H84,I84,J84,L84)) -> 225802.93 | I8: =[28]디와이파워!D41/10^6 -> 26557.771 | J8: =IF(B8="","",I8/H8) -> 0.11761482 | L8: =IF(B8="","",I8/(H8+I8)) -> 0.10523735 | N8: 0.242 | O8: =IF(B8="","",IF(G8="NA","NA",G8/(1+J8*(1-N8)))) -> 1.1252626 | P8: =IF(B8="","",O8*(1+($L$41/$L$42)*$E$41)) -> 1.2281318
A9: =A8+1 -> 4 | B9: =IF([28]Raw!AC12="","",[28]Raw!AC12) -> Dongil Metal Co Ltd | E9: =IF([28]Raw!AF12="","",[28]Raw!AF12) -> SOUTH KOREA | G9: =IF(B9="","",CHOOSE($W$26,G68,H68,I68)) -> 0.7080026 | H9: =IF(B9="","",CHOOSE($W$28,G85,H85,I85,J85,L85)) -> 52920 | I9: =([28]동일금속!D34+[28]동일금속!D39)/10^6 -> 8234.0778 | J9: =IF(B9="","",I9/H9) -> 0.15559482 | L9: =IF(B9="","",I9/(H9+I9)) -> 0.13464479 | N9: 0.242 | O9: =IF(B9="","",IF(G9="NA","NA",G9/(1+J9*(1-N9)))) -> 0.63330952 | P9: =IF(B9="","",O9*(1+($L$41/$L$42)*$E$41)) -> 0.69120543 | AA9: =CHOOSE(W28,"","과거 1개월 평균 ","과거 3개월 평균 ","과거 6개월 평균 ","과거 12개월 평균 ")
A10: =A9+1 -> 5 | B10: =IF([28]Raw!AC13="","",[28]Raw!AC13) -> HEUNGKUK METALTECH Co Ltd | E10: =IF([28]Raw!AF13="","",[28]Raw!AF13) -> SOUTH KOREA | G10: =IF(B10="","",CHOOSE($W$26,G69,H69,I69)) -> 0.7862841 | H10: =IF(B10="","",CHOOSE($W$28,G86,H86,I86,J86,L86)) -> 43006.209 | I10: =IF(B10="","",G104) -> 8000 | J10: =IF(B10="","",I10/H10) -> 0.18601965 | L10: =IF(B10="","",I10/(H10+I10)) -> 0.15684365 | N10: 0.242 | O10: =IF(B10="","",IF(G10="NA","NA",G10/(1+J10*(1-N10)))) -> 0.68911666 | P10: =IF(B10="","",O10*(1+($L$41/$L$42)*$E$41)) -> 0.75211435
A11: =A10+1 -> 6 | B11: =IF([28]Raw!AC14="","",[28]Raw!AC14) -> Woorim Machinery Co Ltd | E11: =IF([28]Raw!AF14="","",[28]Raw!AF14) -> SOUTH KOREA | G11: =IF(B11="","",CHOOSE($W$26,G70,H70,I70)) -> 0.8332101 | H11: =IF(B11="","",CHOOSE($W$28,G87,H87,I87,J87,L87)) -> 52717.5 | I11: =IF(B11="","",G105) -> 3800 | J11: =IF(B11="","",I11/H11) -> 0.072082326 | L11: =IF(B11="","",I11/(H11+I11)) -> 0.067235812 | N11: 0.242 | O11: =IF(B11="","",IF(G11="NA","NA",G11/(1+J11*(1-N11)))) -> 0.79004339 | P11: =IF(B11="","",O11*(1+($L$41/$L$42)*$E$41)) -> 0.8622676 | AA11: =CHOOSE(W30,"","과거 1개월 평균 ","과거 3개월 평균 ","과거 6개월 평균 ","과거 12개월 평균 ","과거 24개월 평균 ")
A12: =A11+1 -> 7 | B12: =IF([28]Raw!AC15="","",[28]Raw!AC15) -> EVERDIGM Corp | E12: =IF([28]Raw!AF15="","",[28]Raw!AF15) -> SOUTH KOREA | G12: =IF(B12="","",CHOOSE($W$26,G71,H71,I71)) -> 0.8552536 | H12: =IF(B12="","",CHOOSE($W$28,G88,H88,I88,J88,L88)) -> 189909.01 | I12: =([28]애버다임!C38+[28]애버다임!C39+[28]애버다임!C45)/10^6 -> 36121.337 | J12: =IF(B12="","",I12/H12) -> 0.19020339 | L12: =IF(B12="","",I12/(H12+I12)) -> 0.15980747 | N12: 0.242 | O12: =IF(B12="","",IF(G12="NA","NA",G12/(1+J12*(1-N12)))) -> 0.7474855 | P12: =IF(B12="","",O12*(1+($L$41/$L$42)*$E$41)) -> 0.81581915
A13: =A12+1 -> 8 | B13: =IF([28]Raw!AC16="","",[28]Raw!AC16) -> Doosan Infracore Co Ltd | E13: =IF([28]Raw!AF16="","",[28]Raw!AF16) -> SOUTH KOREA | G13: =IF(B13="","",CHOOSE($W$26,G72,H72,I72)) -> 1.561469 | H13: =IF(B13="","",CHOOSE($W$28,G89,H89,I89,J89,L89)) -> 1703208.1 | I13: =IF(B13="","",G107) -> 2564617 | J13: =IF(B13="","",I13/H13) -> 1.5057567 | L13: =IF(B13="","",I13/(H13+I13)) -> 0.60091895 | N13: 0.242 | O13: =IF(B13="","",IF(G13="NA","NA",G13/(1+J13*(1-N13)))) -> 0.72919378 | P13: =IF(B13="","",O13*(1+($L$41/$L$42)*$E$41)) -> 0.79585525 | AA13: =CHOOSE(W32,"","과거 1개월 평균 ","과거 3개월 평균 ","과거 6개월 평균 ","과거 12개월 평균 ","과거 24개월 평균 ")
A14: =A13+1 -> 9 | B14: =IF([28]Raw!AC17="","",[28]Raw!AC17) -> Jinsung T.E.C. | E14: =IF([28]Raw!AF17="","",[28]Raw!AF17) -> SOUTH KOREA | G14: =IF(B14="","",CHOOSE($W$26,G73,H73,I73)) -> 1.013539 | H14: =IF(B14="","",CHOOSE($W$28,G90,H90,I90,J90,L90)) -> 230443.25 | I14: =IF(B14="","",G108) -> 19702.5 | J14: =IF(B14="","",I14/H14) -> 0.085498275 | L14: =IF(B14="","",I14/(H14+I14)) -> 0.078764081 | N14: 0.242 | O14: =IF(B14="","",IF(G14="NA","NA",G14/(1+J14*(1-N14)))) -> 0.95185169 | P14: =IF(B14="","",O14*(1+($L$41/$L$42)*$E$41)) -> 1.0388681
A15: =A14+1 -> 10 | B15: =IF([28]Raw!AC18="","",[28]Raw!AC18) -> Kanglim Co Ltd | E15: =IF([28]Raw!AF18="","",[28]Raw!AF18) -> SOUTH KOREA | G15: =IF(B15="","",CHOOSE($W$26,G74,H74,I74)) -> 1.122415 | H15: =IF(B15="","",CHOOSE($W$28,G91,H91,I91,J91,L91)) -> 193508.96 | I15: =IF(B15="","",G109) -> 35222.923 | J15: =IF(B15="","",I15/H15) -> 0.18202218 | L15: =IF(B15="","",I15/(H15+I15)) -> 0.15399219 | N15: 0.242 | O15: =IF(B15="","",IF(G15="NA","NA",G15/(1+J15*(1-N15)))) -> 0.98632848 | P15: =IF(B15="","",O15*(1+($L$41/$L$42)*$E$41)) -> 1.0764967
A16: =A15+1 -> 11 | B16: =IF([28]Raw!AC19="","",[28]Raw!AC19) -> Soosan Heavy Industries Co Ltd | E16: =IF([28]Raw!AF19="","",[28]Raw!AF19) -> SOUTH KOREA | G16: =IF(B16="","",CHOOSE($W$26,G75,H75,I75)) -> 0.9405083 | H16: =IF(B16="","",CHOOSE($W$28,G92,H92,I92,J92,L92)) -> 80977.745 | I16: =([28]수산중공업!C38+[28]수산중공업!C44)/10^6 -> 2574.0342 | J16: =IF(B16="","",I16/H16) -> 0.031786934 | L16: =IF(B16="","",I16/(H16+I16)) -> 0.030807653 | N16: 0.242 | O16: =IF(B16="","",IF(G16="NA","NA",G16/(1+J16*(1-N16)))) -> 0.91838039 | P16: =IF(B16="","",O16*(1+($L$41/$L$42)*$E$41)) -> 1.0023369
A17: =A16+1 -> 12 | B17: =IF([28]Raw!AC20="","",[28]Raw!AC20) -> Daechang Forging Co Ltd | E17: =IF([28]Raw!AF20="","",[28]Raw!AF20) -> SOUTH KOREA | G17: =IF(B17="","",CHOOSE($W$26,G76,H76,I76)) -> 0.7109918 | H17: =IF(B17="","",CHOOSE($W$28,G93,H93,I93,J93,L93)) -> 116000 | I17: =IF(B17="","",G111) -> 2214.5932 | J17: =IF(B17="","",I17/H17) -> 0.019091321 | L17: =IF(B17="","",I17/(H17+I17)) -> 0.01873367 | N17: 0.242 | O17: =IF(B17="","",IF(G17="NA","NA",G17/(1+J17*(1-N17)))) -> 0.70084965 | P17: =IF(B17="","",O17*(1+($L$41/$L$42)*$E$41)) -> 0.76491995
A18: =A17+1 -> 13 | B18: =IF([28]Raw!AC21="","",[28]Raw!AC21) -> DY Corp | E18: =IF([28]Raw!AF21="","",[28]Raw!AF21) -> SOUTH KOREA | G18: =IF(B18="","",CHOOSE($W$26,G77,H77,I77)) -> 1.187089 | H18: =IF(B18="","",CHOOSE($W$28,G94,H94,I94,J94,L94)) -> 190817.34 | I18: =IF(B18="","",G112) -> 2325 | J18: =IF(B18="","",I18/H18) -> 0.012184427 | L18: =IF(B18="","",I18/(H18+I18)) -> 0.012037754 | N18: 0.242 | O18: =IF(B18="","",IF(G18="NA","NA",G18/(1+J18*(1-N18)))) -> 1.1762256 | P18: =IF(B18="","",O18*(1+($L$41/$L$42)*$E$41)) -> 1.2837539
A19: =A18+1 -> 14 | B19: =IF([28]Raw!AC22="","",[28]Raw!AC22) -> Hae In Corp | E19: =IF([28]Raw!AF22="","",[28]Raw!AF22) -> SOUTH KOREA | G19: =IF(B19="","",CHOOSE($W$26,G78,H78,I78)) -> 0.4925056 | H19: =IF(B19="","",CHOOSE($W$28,G95,H95,I95,J95,L95)) -> 47100.728 | I19: =IF(B19="","",G113) -> 102869.93 | J19: =IF(B19="","",I19/H19) -> 2.1840411 | L19: =IF(B19="","",I19/(H19+I19)) -> 0.68593371 | N19: 0.242 | O19: =IF(B19="","",IF(G19="NA","NA",G19/(1+J19*(1-N19)))) -> 0.18546602 | P19: =IF(B19="","",O19*(1+($L$41/$L$42)*$E$41)) -> 0.20242096
A20: =A19+1 -> 15 | B20: =IF([28]Raw!AC23="","",[28]Raw!AC23) -> 0 | E20: =IF([28]Raw!AF23="","",[28]Raw!AF23) -> 0 | G20: =IF(B20="","",CHOOSE($W$26,#REF!,#REF!,#REF!)) -> #REF! | H20: =IF(B20="","",CHOOSE($W$28,#REF!,#REF!,#REF!,#REF!,#REF!)) -> #REF! | I20: =IF(B20="","",G114) -> 0 | J20: =IF(B20="","",I20/H20) -> #REF! | L20: =IF(B20="","",I20/(H20+I20)) -> #REF! | N20: #N/A | O20: =IF(B20="","",IF(G20="NA","NA",G20/(1+J20*(1-N20)))) -> #REF! | P20: =IF(B20="","",O20*(1+($L$41/$L$42)*$E$41)) -> #REF!
A21: =A20+1 -> 16 | B21: =IF([28]Raw!AC24="","",[28]Raw!AC24) -> 0 | E21: =IF([28]Raw!AF24="","",[28]Raw!AF24) -> 0 | G21: =IF(B21="","",CHOOSE($W$26,#REF!,#REF!,#REF!)) -> #REF! | H21: =IF(B21="","",CHOOSE($W$28,#REF!,#REF!,#REF!,#REF!,#REF!)) -> #REF! | I21: =IF(B21="","",G115) -> 0 | J21: =IF(B21="","",I21/H21) -> #REF! | L21: =IF(B21="","",I21/(H21+I21)) -> #REF! | N21: #N/A | O21: =IF(B21="","",IF(G21="NA","NA",G21/(1+J21*(1-N21)))) -> #REF! | P21: =IF(B21="","",O21*(1+($L$41/$L$42)*$E$41)) -> #REF!
A22: =A21+1 -> 17 | B22: =IF([28]Raw!AC25="","",[28]Raw!AC25) -> 0 | E22: =IF([28]Raw!AF25="","",[28]Raw!AF25) -> 0 | G22: =IF(B22="","",CHOOSE($W$26,#REF!,#REF!,#REF!)) -> #REF! | H22: =IF(B22="","",CHOOSE($W$28,#REF!,#REF!,#REF!,#REF!,#REF!)) -> #REF! | I22: =IF(B22="","",G116) -> 0 | J22: =IF(B22="","",I22/H22) -> #REF! | L22: =IF(B22="","",I22/(H22+I22)) -> #REF! | N22: #N/A | O22: =IF(B22="","",IF(G22="NA","NA",G22/(1+J22*(1-N22)))) -> #REF! | P22: =IF(B22="","",O22*(1+($L$41/$L$42)*$E$41)) -> #REF!
A23: =A22+1 -> 18 | B23: =IF([28]Raw!AC26="","",[28]Raw!AC26) -> 0 | E23: =IF([28]Raw!AF26="","",[28]Raw!AF26) -> 0 | G23: =IF(B23="","",CHOOSE($W$26,#REF!,#REF!,#REF!)) -> #REF! | H23: =IF(B23="","",CHOOSE($W$28,#REF!,#REF!,#REF!,#REF!,#REF!)) -> #REF! | I23: =IF(B23="","",G117) -> 0 | J23: =IF(B23="","",I23/H23) -> #REF! | L23: =IF(B23="","",I23/(H23+I23)) -> #REF! | N23: #N/A | O23: =IF(B23="","",IF(G23="NA","NA",G23/(1+J23*(1-N23)))) -> #REF! | P23: =IF(B23="","",O23*(1+($L$41/$L$42)*$E$41)) -> #REF!
A24: =A23+1 -> 19 | B24: =IF([28]Raw!AC27="","",[28]Raw!AC27) -> 0 | E24: =IF([28]Raw!AF27="","",[28]Raw!AF27) -> 0 | G24: =IF(B24="","",CHOOSE($W$26,#REF!,#REF!,#REF!)) -> #REF! | H24: =IF(B24="","",CHOOSE($W$28,#REF!,#REF!,#REF!,#REF!,#REF!)) -> #REF! | I24: =IF(B24="","",G118) -> 0 | J24: =IF(B24="","",I24/H24) -> #REF! | L24: =IF(B24="","",I24/(H24+I24)) -> #REF! | N24: #N/A | O24: =IF(B24="","",IF(G24="NA","NA",G24/(1+J24*(1-N24)))) -> #REF! | P24: =IF(B24="","",O24*(1+($L$41/$L$42)*$E$41)) -> #REF!
A25: =A24+1 -> 20 | B25: =IF([28]Raw!AC28="","",[28]Raw!AC28) -> 0 | E25: =IF([28]Raw!AF28="","",[28]Raw!AF28) -> 0 | G25: =IF(B25="","",CHOOSE($W$26,#REF!,#REF!,#REF!)) -> #REF! | H25: =IF(B25="","",CHOOSE($W$28,#REF!,#REF!,#REF!,#REF!,#REF!)) -> #REF! | I25: =IF(B25="","",G119) -> 0 | J25: =IF(B25="","",I25/H25) -> #REF! | L25: =IF(B25="","",I25/(H25+I25)) -> #REF! | N25: #N/A | O25: =IF(B25="","",IF(G25="NA","NA",G25/(1+J25*(1-N25)))) -> #REF! | P25: =IF(B25="","",O25*(1+($L$41/$L$42)*$E$41)) -> #REF!
B26: Maximum | G26: =MAX(G8,G9,G12,G16) -> 1.225582 | J26: =MAX(J8,J9,J12,J16) -> 0.19020339 | L26: =MAX(L8,L9,L12,L16) -> 0.15980747 | O26: =MAX(O8,O9,O12,O16) -> 1.1252626 | P26: =MAX(P8,P9,P12,P16) -> 1.2281318 | T26: : 'Beta' Option | W26: 1 | Y26: =CHOOSE(W26,L64,L65,L66) -> 5year, weekly
B27: Average | G27: =AVERAGE(G8,G9,G12,G16) -> 0.93233662 | J27: =AVERAGE(J8,J9,J12,J16) -> 0.12379999 | L27: =AVERAGE(L8,L9,L12,L16) -> 0.10762432 | O27: =AVERAGE(O8,O9,O12,O16) -> 0.85610949 | P27: =AVERAGE(P8,P9,P12,P16) -> 0.93437334
B28: Median | G28: =MEDIAN(G8,G9,G12,G16) -> 0.89788095 | J28: =MEDIAN(J8,J9,J12,J16) -> 0.13660482 | L28: =MEDIAN(L8,L9,L12,L16) -> 0.11994107 | O28: =MEDIAN(O8,O9,O12,O16) -> 0.83293294 | P28: =MEDIAN(P8,P9,P12,P16) -> 0.90907803 | T28: : 'Market Capitalization' Option | W28: 1 | Y28: =CHOOSE($W$28,N81,N82,N83,N84,N85) -> 43007
B29: Minimum | G29: =MIN(G8,G9,G12,G16) -> 0.7080026 | J29: =MIN(J8,J9,J12,J16) -> 0.031786934 | L29: =MIN(L8,L9,L12,L16) -> 0.030807653 | O29: =MIN(O8,O9,O12,O16) -> 0.63330952 | P29: =MIN(P8,P9,P12,P16) -> 0.69120543
T30: : 'Equity Risk Premium' Option | W30: 1 | Y30: =CHOOSE(W30,B123,B124,B125,B126,B127,B128) -> 43007
B31: Selected (Average) | L31: =L27 -> 0.10762432 | O31: =O27 -> 0.85610949 | P31: =O31*(1+($L$41/$L$42)*$E$41) -> 0.93437334
T32: : 'Risk-free Rate' Option | W32: 1 | Y32: =CHOOSE(W32,B123,B124,B125,B126,B127,B128) -> 43007
B33: Cost of Equity (KE)
B35: Risk Free Rate | D35: + | E35: Beta | F35: x | G35: Equity Risk Premium | H35: + | I35: Size Premium | J35: + | L35: Specific Premium | M35: + | N35: Country Risk Premium | O35: = | P35: Cost of Equity
B36: =CHOOSE($W$32,G123,G124,G125,G126,G127,G128) -> 0.0237 | E36: =P31 -> 0.93437334 | G36: =CHOOSE($W$32,I123,I124,I125,I126,I127,I128) -> 0.10614 | I36: 0 | L36: 0 | N36: 0 | P36: =SUM(B36,(E36*G36),I36,L36,N36) -> 0.12287439
B38: After-Tax Cost of Debt (KD) | L38: Weighted Average Cost of Capital
B40: Pre-Tax Cost of Debt | D40: x | E40: (1 - Tax Rate) | F40: = | G40: After-Tax Cost of Debt | L40: Captial Structure | M40: x | N40: Cost of Capital | O40: = | P40: Contribution
B41: =[28]Bond!M16/100 -> 0.0433 | E41: =1-T3 -> 0.758 | G41: =(B41*E41) -> 0.0328214 | J41: Debt | L41: =L31 -> 0.10762432 | N41: =G41 -> 0.0328214 | P41: =N41*L41 -> 0.0035323807
J42: Equity | L42: =(1-L41) -> 0.89237568 | N42: =P36 -> 0.12287439 | P42: =N42*L42 -> 0.10965011
N44: WACC | O44: = | P44: =ROUND(P41+P42,3) -> 0.113
B45: Notes:
B46: [1] | C46: 대상회사와 유사한 사업을 영위하고 있는 회사를 선정
B47: [2] | C47: 2017년 9월 30일 기준 과거 5년 평균 Weekly adjusted Beta 적용
B48: [3] | C48: 2017년 9월 30일 기준 시가총액 사용
B49: [4] | C49: 2017년 9월 30일 기준 이자발생부채 적용
B50: [5] | C50: 2017년 9월 30일 기준 10년 만기 국공채 이자율 적용 (Source: Bloomberg)
B51: [6] | C51: 2017년 9월 30일 기준 Market Risk Premium 적용 (Source: Bloomberg)
B52: [7] | C52: 2017년 9월 30일 기준 5년 만기 A0 등급 무보증 회사채 이자율 적용 (Source: www.KOFIAbond.or.kr)
B53: [8] | C53: 유사회사의 평균 자본구조 적용
B57: <비교대상 회사 선정 과정 및 기준>
B59: 선정 과정
B60: - 유사업체 선정기준 Tab 참조
B63: <Beta 선정> | L63: Option
G64: 5-year weekly | H64: 5-year monthly | I64: 2-year weekly | J64: Index | L64: 5year, weekly
A65: 1 | B65: =[28]Raw!AC36 -> Hyundai Construction Equipment Co Ltd | G65: =[28]Raw!AG36 -> 1.281801 | H65: =[28]Raw!AI36 -> 4.589204 | I65: =[28]Raw!AE36 -> 1.281801 | J65: =[28]Raw!AD9 -> KOSPI Index | L65: 5year, monthly
A66: =A65+1 -> 2 | B66: =[28]Raw!AC37 -> Doosan Bobcat Inc | G66: =[28]Raw!AG37 -> 0.91189 | H66: =[28]Raw!AI37 -> -0.4843347 | I66: =[28]Raw!AE37 -> 0.91189 | J66: =[28]Raw!AD10 -> KOSPI Index | L66: 2year, weekly
A67: =A66+1 -> 3 | B67: =[28]Raw!AC38 -> DY POWER Corp | G67: =[28]Raw!AG38 -> 1.225582 | H67: =[28]Raw!AI38 -> 2.535476 | I67: =[28]Raw!AE38 -> 1.344717 | J67: =[28]Raw!AD11 -> KOSPI Index
A68: =A67+1 -> 4 | B68: =[28]Raw!AC39 -> Dongil Metal Co Ltd | G68: =[28]Raw!AG39 -> 0.7080026 | H68: =[28]Raw!AI39 -> 0.828022 | I68: =[28]Raw!AE39 -> 0.5628106 | J68: =[28]Raw!AD12 -> KOSPI Index
A69: =A68+1 -> 5 | B69: =[28]Raw!AC40 -> HEUNGKUK METALTECH Co Ltd | G69: =[28]Raw!AG40 -> 0.7862841 | H69: =[28]Raw!AI40 -> 1.407036 | I69: =[28]Raw!AE40 -> 0.7036609 | J69: =[28]Raw!AD13 -> KOSPI Index
A70: =A69+1 -> 6 | B70: =[28]Raw!AC41 -> Woorim Machinery Co Ltd | G70: =[28]Raw!AG41 -> 0.8332101 | H70: =[28]Raw!AI41 -> 1.083192 | I70: =[28]Raw!AE41 -> 0.6419903 | J70: =[28]Raw!AD14 -> KOSPI Index
A71: =A70+1 -> 7 | B71: =[28]Raw!AC42 -> EVERDIGM Corp | G71: =[28]Raw!AG42 -> 0.8552536 | H71: =[28]Raw!AI42 -> 0.6295828 | I71: =[28]Raw!AE42 -> 0.9015758 | J71: =[28]Raw!AD15 -> KOSPI Index
A72: =A71+1 -> 8 | B72: =[28]Raw!AC43 -> Doosan Infracore Co Ltd | G72: =[28]Raw!AG43 -> 1.561469 | H72: =[28]Raw!AI43 -> 1.85068 | I72: =[28]Raw!AE43 -> 1.457915 | J72: =[28]Raw!AD16 -> KOSPI Index
A73: =A72+1 -> 9 | B73: =[28]Raw!AC44 -> Jinsung T.E.C. | G73: =[28]Raw!AG44 -> 1.013539 | H73: =[28]Raw!AI44 -> 1.079415 | I73: =[28]Raw!AE44 -> 0.873015 | J73: =[28]Raw!AD17 -> KOSPI Index
A74: =A73+1 -> 10 | B74: =[28]Raw!AC45 -> Kanglim Co Ltd | G74: =[28]Raw!AG45 -> 1.122415 | H74: =[28]Raw!AI45 -> 3.115253 | I74: =[28]Raw!AE45 -> 1.307705 | J74: =[28]Raw!AD18 -> KOSPI Index
A75: =A74+1 -> 11 | B75: =[28]Raw!AC46 -> Soosan Heavy Industries Co Ltd | G75: =[28]Raw!AG46 -> 0.9405083 | H75: =[28]Raw!AI46 -> 0.6347571 | I75: =[28]Raw!AE46 -> 1.560213 | J75: =[28]Raw!AD19 -> KOSPI Index
A76: =A75+1 -> 12 | B76: =[28]Raw!AC47 -> Daechang Forging Co Ltd | G76: =[28]Raw!AG47 -> 0.7109918 | H76: =[28]Raw!AI47 -> 1.132137 | I76: =[28]Raw!AE47 -> 0.7441038 | J76: =[28]Raw!AD20 -> KOSPI Index
A77: =A76+1 -> 13 | B77: =[28]Raw!AC48 -> DY Corp | G77: =[28]Raw!AG48 -> 1.187089 | H77: =[28]Raw!AI48 -> 1.790081 | I77: =[28]Raw!AE48 -> 1.089549 | J77: =[28]Raw!AD21 -> KOSPI Index
A78: =A77+1 -> 14 | B78: =[28]Raw!AC49 -> Hae In Corp | G78: =[28]Raw!AG49 -> 0.4925056 | H78: =[28]Raw!AI49 -> 0.8582942 | I78: =[28]Raw!AE49 -> 0.3309839 | J78: =[28]Raw!AD22 -> KOSPI Index
B80: <시가총액 선정> | N80: Option
G81: =[28]Company!D6 -> 43007 | H81: 1 month | I81: 3 month | J81: 6 month | L81: 12 month | N81: =G81 -> 43007
A82: 1 | B82: =[28]Raw!AC61 -> Hyundai Construction Equipment Co Ltd | G82: =[28]Raw!AD61 -> #DIV/0! | H82: =[28]Raw!AE61 -> 1268186.4 | I82: =[28]Raw!AF61 -> 1316784.4 | J82: =[28]Raw!AG61 -> 1241778.6 | L82: =[28]Raw!AH61 -> 1241778.6 | N82: 1 month avg.
A83: =A82+1 -> 2 | B83: =[28]Raw!AC62 -> Doosan Bobcat Inc | G83: =[28]Raw!AD62 -> 3664107 | H83: =[28]Raw!AE62 -> 3691466.7 | I83: =[28]Raw!AF62 -> 3629475.5 | J83: =[28]Raw!AG62 -> 3668567 | L83: =[28]Raw!AH62 -> 3645960.1 | N83: 3 month avg.
A84: =A83+1 -> 3 | B84: =[28]Raw!AC63 -> DY POWER Corp | G84: =[28]Raw!AD63 -> 225802.93 | H84: =[28]Raw!AE63 -> 246046.06 | I84: =[28]Raw!AF63 -> 223050.87 | J84: =[28]Raw!AG63 -> 186135.38 | L84: =[28]Raw!AH63 -> 141053.84 | N84: 6 month avg.
A85: =A84+1 -> 4 | B85: =[28]Raw!AC64 -> Dongil Metal Co Ltd | G85: =[28]Raw!AD64 -> 52920 | H85: =[28]Raw!AE64 -> 57067.5 | I85: =[28]Raw!AF64 -> 59722.727 | J85: =[28]Raw!AG64 -> 62036.535 | L85: =[28]Raw!AH64 -> 64869.28 | N85: 12 month avg.
A86: =A85+1 -> 5 | B86: =[28]Raw!AC65 -> HEUNGKUK METALTECH Co Ltd | G86: =[28]Raw!AD65 -> 43006.209 | H86: =[28]Raw!AE65 -> 45968.791 | I86: =[28]Raw!AF65 -> 51377.24 | J86: =[28]Raw!AG65 -> 48985.627 | L86: =[28]Raw!AH65 -> 48904.097
A87: =A86+1 -> 6 | B87: =[28]Raw!AC66 -> Woorim Machinery Co Ltd | G87: =[28]Raw!AD66 -> 52717.5 | H87: =[28]Raw!AE66 -> 57164.062 | I87: =[28]Raw!AF66 -> 65568.068 | J87: =[28]Raw!AG66 -> 69934.783 | L87: =[28]Raw!AH66 -> 86697.81
A88: =A87+1 -> 7 | B88: =[28]Raw!AC67 -> EVERDIGM Corp | G88: =[28]Raw!AD67 -> 189909.01 | H88: =[28]Raw!AE67 -> 204988.26 | I88: =[28]Raw!AF67 -> 217393.69 | J88: =[28]Raw!AG67 -> 206127.87 | L88: =[28]Raw!AH67 -> 193910.7
A89: =A88+1 -> 8 | B89: =[28]Raw!AC68 -> Doosan Infracore Co Ltd | G89: =[28]Raw!AD68 -> 1703208.1 | H89: =[28]Raw!AE68 -> 1728275.6 | I89: =[28]Raw!AF68 -> 1716849.9 | J89: =[28]Raw!AG68 -> 1791237.8 | L89: =[28]Raw!AH68 -> 1774680.6
A90: =A89+1 -> 9 | B90: =[28]Raw!AC69 -> Jinsung T.E.C. | G90: =[28]Raw!AD69 -> 230443.25 | H90: =[28]Raw!AE69 -> 218209.15 | I90: =[28]Raw!AF69 -> 209878.78 | J90: =[28]Raw!AG69 -> 196286.13 | L90: =[28]Raw!AH69 -> 183331.75
A91: =A90+1 -> 10 | B91: =[28]Raw!AC70 -> Kanglim Co Ltd | G91: =[28]Raw!AD70 -> 193508.96 | H91: =[28]Raw!AE70 -> 205724.52 | I91: =[28]Raw!AF70 -> 249491.64 | J91: =[28]Raw!AG70 -> 265615.13 | L91: =[28]Raw!AH70 -> 280760.64
A92: =A91+1 -> 11 | B92: =[28]Raw!AC71 -> Soosan Heavy Industries Co Ltd | G92: =[28]Raw!AD71 -> 80977.745 | H92: =[28]Raw!AE71 -> 82428.596 | I92: =[28]Raw!AF71 -> 82904.034 | J92: =[28]Raw!AG71 -> 88809.845 | L92: =[28]Raw!AH71 -> 97767.133
A93: =A92+1 -> 12 | B93: =[28]Raw!AC72 -> Daechang Forging Co Ltd | G93: =[28]Raw!AD72 -> 116000 | H93: =[28]Raw!AE72 -> 116741.67 | I93: =[28]Raw!AF72 -> 119921.21 | J93: =[28]Raw!AG72 -> 114894.49 | L93: =[28]Raw!AH72 -> 105316.8
A94: =A93+1 -> 13 | B94: =[28]Raw!AC73 -> DY Corp | G94: =[28]Raw!AD73 -> 190817.34 | H94: =[28]Raw!AE73 -> 199272.52 | I94: =[28]Raw!AF73 -> 194709.46 | J94: =[28]Raw!AG73 -> 192408.95 | L94: =[28]Raw!AH73 -> 189427.67
A95: =A94+1 -> 14 | B95: =[28]Raw!AC74 -> Hae In Corp | G95: =[28]Raw!AD74 -> 47100.728 | H95: =[28]Raw!AE74 -> 49598.253 | I95: =[28]Raw!AF74 -> 53609.269 | J95: =[28]Raw!AG74 -> 56243.394 | L95: =[28]Raw!AH74 -> 53693.811
B97: <이자부부채 선정>
G98: 이자부부채 | H98: 기준일
A100: 1 | B100: =[28]Raw!AB87 -> HYUNDAI CONSTRUCTION EQUIPME | G100: =[28]Raw!AG87 -> 615793 | H100: =[28]Raw!AE87 -> FQ2 2017
A101: =A100+1 -> 2 | B101: =[28]Raw!AB88 -> DOOSAN BOBCAT INC | G101: =[28]Raw!AG88 -> 103202.18 | H101: =[28]Raw!AE88 -> FQ2 2017
A102: =A101+1 -> 3 | B102: =[28]Raw!AB89 -> DY POWER CORP | G102: =[28]Raw!AG89 -> 21349 | H102: =[28]Raw!AE89 -> FQ2 2017
A103: =A102+1 -> 4 | B103: =[28]Raw!AB90 -> DONGIL METAL CO LTD | G103: =[28]Raw!AG90 -> 1692.306 | H103: =[28]Raw!AE90 -> FQ2 2017
A104: =A103+1 -> 5 | B104: =[28]Raw!AB91 -> HEUNGKUK METALTECH CO LTD | G104: =[28]Raw!AG91 -> 8000 | H104: =[28]Raw!AE91 -> FQ2 2017
A105: =A104+1 -> 6 | B105: =[28]Raw!AB92 -> WOORIM MACHINERY CO LTD | G105: =[28]Raw!AG92 -> 3800 | H105: =[28]Raw!AE92 -> FQ2 2017
A106: =A105+1 -> 7 | B106: =[28]Raw!AB93 -> EVERDIGM CORP | G106: =[28]Raw!AG93 -> 13342.976 | H106: =[28]Raw!AE93 -> FQ2 2017
A107: =A106+1 -> 8 | B107: =[28]Raw!AB94 -> DOOSAN INFRACORE CO LTD | G107: =[28]Raw!AG94 -> 2564617 | H107: =[28]Raw!AE94 -> FQ2 2017
A108: =A107+1 -> 9 | B108: =[28]Raw!AB95 -> JINSUNG T.E.C. | G108: =[28]Raw!AG95 -> 19702.5 | H108: =[28]Raw!AE95 -> FQ2 2017
A109: =A108+1 -> 10 | B109: =[28]Raw!AB96 -> KANGLIM CO LTD | G109: =[28]Raw!AG96 -> 35222.923 | H109: =[28]Raw!AE96 -> FQ2 2017
A110: =A109+1 -> 11 | B110: =[28]Raw!AB97 -> SOOSAN HEAVY INDUSTRIES CO | G110: =[28]Raw!AG97 -> 1490.966 | H110: =[28]Raw!AE97 -> FQ2 2017
A111: =A110+1 -> 12 | B111: =[28]Raw!AB98 -> DAECHANG FORGING CO LTD | G111: =[28]Raw!AG98 -> 2214.5932 | H111: =[28]Raw!AE98 -> FQ2 2017
A112: =A111+1 -> 13 | B112: =[28]Raw!AB99 -> DY CORP | G112: =[28]Raw!AG99 -> 2325 | H112: =[28]Raw!AE99 -> FQ2 2017
... A119: =A118+1 -> 20 | B119: =[28]Raw!AB106 -> #N/A Invalid Security | G119: =[28]Raw!AG106 -> 0 | H119: =[28]Raw!AE106 -> #N/A Invalid Security
...

Sheet _TM_GPCM_Tier1 (2)
A1: Left | B1: Top | C1: Right | D1: Bottom | E1: Ref
A2: 2 | B2: 101 | C2: 7 | D2: 292 | E2: $B$101:$G$292

Sheet _TM_매출액
A1: Left | B1: Top | C1: Right | D1: Bottom | E1: Ref
A2: 2 | B2: 24 | C2: 14 | D2: 24 | E2: $B$24:$N$24

Sheet Pro forma
B1: ="Project"&" "&Title!L6 -> Project SVG1 | K1: =Des!C12 -> DRAFT - For Discussion Purposes Only
B2: Pro Forma
B4: Pro Forma
B5: =unit -> KRW Million | D5: 2014 | E5: 2015 | F5: =G5-1 -> 2016 | G5: =YEAR(Des!C8) -> 2017 | H5: =G5+1 -> 2018 | I5: =H5+1 -> 2019 | J5: =I5+1 -> 2020 | K5: =J5+1 -> 2021 | L5: =K5+1 -> 2022
B6: Sales | D6: =IS!D5/10^6 -> 41447.714 | E6: =IS!E5/10^6 -> 61966.746 | F6: =IS!F5/10^6 -> 81488.231 | G6: =IS!G5/10^6 -> 92333.966 | H6: ='모델별 Mapping'!Q185/10^6 -> 138011.23 | I6: ='모델별 Mapping'!T185/10^6 -> 182151.03 | J6: ='모델별 Mapping'!W185/10^6 -> 203944.82 | K6: ='모델별 Mapping'!Z185/10^6 -> 261216.69 | L6: ='모델별 Mapping'!AC185/10^6 -> 300836.43 | M6: =RATE(5,0,-H6,L6) -> 0.16864661
B7: % of growth | F7: =F6/E6-1 -> 0.31503163 | G7: =G6/F6-1 -> 0.13309572 | H7: =H6/G6-1 -> 0.49469619 | I7: =I6/H6-1 -> 0.31982767 | J7: =J6/I6-1 -> 0.11964678 | K7: =K6/J6-1 -> 0.28082041 | L7: =L6/K6-1 -> 0.15167386 | O7: 61709.017 | P7: 81447.5 | Q7: 91483.174 | R7: 154181.35 | S7: 194357.52 | T7: 253491.11 | U7: 279502.71 | V7: 307288.73
B9: COGS | D9: =IS!D8/10^6 -> 29094.554 | E9: =IS!E8/10^6 -> 42664.217 | F9: =IS!F8/10^6 -> 59896.716 | G9: =IS!G8/10^6 -> 66253.175 | H9: =매출원가!H6 -> 95072.958 | I9: =매출원가!I6 -> 126580.95 | J9: =매출원가!J6 -> 140774.16 | K9: =매출원가!K6 -> 178212.96 | L9: =매출원가!L6 -> 204547.06
B10: % of growth | F10: =F9/E9-1 -> 0.40390988 | G10: =G9/F9-1 -> 0.10612365 | H10: =H9/G9-1 -> 0.43499476 | I10: =I9/H9-1 -> 0.3314086 | J10: =J9/I9-1 -> 0.11212747 | K10: =K9/J9-1 -> 0.26594938 | L10: =L9/K9-1 -> 0.14776763
B11: % of sales | D11: =D9/D$6 -> 0.70195799 | E11: =E9/E$6 -> 0.68850182 | F11: =F9/F$6 -> 0.73503518 | G11: =G9/G$6 -> 0.71753849 | H11: =H9/H$6 -> 0.68887844 | I11: =I9/I$6 -> 0.69492306 | J11: =J9/J$6 -> 0.69025611 | K11: =K9/K$6 -> 0.68224186 | L11: =L9/L$6 -> 0.67992784
B13: Gross Profit | D13: =D6-D9 -> 12353.16 | E13: =E6-E9 -> 19302.528 | F13: =F6-F9 -> 21591.515 | G13: =G6-G9 -> 26080.791 | H13: =H6-H9 -> 42938.268 | I13: =I6-I9 -> 55570.08 | J13: =J6-J9 -> 63170.662 | K13: =K6-K9 -> 83003.728 | L13: =L6-L9 -> 96289.365
B14: % of growth | F14: =F13/E13-1 -> 0.11858479 | G14: =G13/F13-1 -> 0.20791855 | H14: =H13/G13-1 -> 0.64635605 | I14: =I13/H13-1 -> 0.29418542 | J14: =J13/I13-1 -> 0.1367747 | K14: =K13/J13-1 -> 0.31396009 | L14: =L13/K13-1 -> 0.16006072
B15: % of sales | D15: =D13/D$6 -> 0.29804201 | E15: =E13/E$6 -> 0.31149818 | F15: =F13/F$6 -> 0.26496482 | G15: =G13/G$6 -> 0.28246151 | H15: =H13/H$6 -> 0.31112156 | I15: =I13/I$6 -> 0.30507694 | J15: =J13/J$6 -> 0.30974389 | K15: =K13/K$6 -> 0.31775814 | L15: =L13/L$6 -> 0.32007216
B17: SG&A | D17: =IS!D14/10^6 -> 6260.3832 | E17: =IS!E14/10^6 -> 7139.8918 | F17: =IS!F14/10^6 -> 7407.697 | G17: =IS!G14/10^6 -> 10368.971 | H17: ='SG&A'!H6 -> 9842.4629 | I17: ='SG&A'!I6 -> 11618.075 | J17: ='SG&A'!J6 -> 13319.84 | K17: ='SG&A'!K6 -> 15631.565 | L17: ='SG&A'!L6 -> 17765.693
B18: % of growth | D18: =D17/C17-1 -> #DIV/0! | E18: =E17/D17-1 -> 0.14048799 | F18: =F17/E17-1 -> 0.037508293 | G18: =G17/F17-1 -> 0.39975631 | H18: =H17/G17-1 -> -0.050777237 | I18: =I17/H17-1 -> 0.18040324 | J18: =J17/I17-1 -> 0.1464756 | K18: =K17/J17-1 -> 0.17355501 | L18: =L17/K17-1 -> 0.13652689
B19: % of sales | D19: =D17/D$6 -> 0.15104291 | E19: =E17/E$6 -> 0.11522135 | F19: =F17/F$6 -> 0.090905115 | G19: =G17/G$6 -> 0.11229855 | H19: =H17/H$6 -> 0.071316393 | I19: =I17/I$6 -> 0.063782647 | J19: =J17/J$6 -> 0.065310998 | K19: =K17/K$6 -> 0.059841371 | L19: =L17/L$6 -> 0.059054329
B21: EBIT | D21: =D13-D17 -> 6092.7769 | E21: =E13-E17 -> 12162.637 | F21: =F13-F17 -> 14183.818 | G21: =G13-G17 -> 15711.82 | H21: =H13-H17 -> 33095.805 | I21: =I13-I17 -> 43952.005 | J21: =J13-J17 -> 49850.822 | K21: =K13-K17 -> 67372.164 | L21: =L13-L17 -> 78523.671
B22: % of growth | F22: =F21/E21-1 -> 0.16617952 | G22: =G21/F21-1 -> 0.10772859 | H22: =H21/G21-1 -> 1.1064271 | I22: =I21/H21-1 -> 0.32802345 | J22: =J21/I21-1 -> 0.13421041 | K22: =K21/J21-1 -> 0.35147549 | L22: =L21/K21-1 -> 0.16552099
B23: % of sales | E23: =E21/E$6 -> 0.19627683 | F23: =F21/F$6 -> 0.17405971 | G23: =G21/G$6 -> 0.17016295 | H23: =H21/H$6 -> 0.23980517 | I23: =I21/I$6 -> 0.24129429 | J23: =J21/J$6 -> 0.24443289 | K23: =K21/K$6 -> 0.25791677 | L23: =L21/L$6 -> 0.26101783
B25: Depreciation | F25: ='CapEx&Dep'!F8 -> 1082.779 | G25: ='CapEx&Dep'!G8 -> 1159.6739 | H25: ='CapEx&Dep'!H8 -> 1099.3242 | I25: ='CapEx&Dep'!I8 -> 1174.6995 | J25: ='CapEx&Dep'!J8 -> 1432.5499 | K25: ='CapEx&Dep'!K8 -> 1899.2471 | L25: ='CapEx&Dep'!L8 -> 2179.9706
B26: % of growth | F26: =F25/E25-1 -> #DIV/0! | G26: =G25/F25-1 -> 0.071016235 | H26: =H25/G25-1 -> -0.052040242 | I26: =I25/H25-1 -> 0.068565149 | J26: =J25/I25-1 -> 0.21950326 | K26: =K25/J25-1 -> 0.32578081 | L26: =L25/K25-1 -> 0.14780774
B27: % of sales | F27: =F25/F$6 -> 0.013287551 | G27: =G25/G$6 -> 0.012559559 | H27: =H25/H$6 -> 0.0079654692 | I27: =I25/I$6 -> 0.0064490411 | J27: =J25/J$6 -> 0.0070242034 | K27: =K25/K$6 -> 0.0072707727 | L27: =L25/L$6 -> 0.007246365
B29: EBITDA | F29: =F21+F25 -> 15266.597 | G29: =G21+G25 -> 16871.494 | H29: =H21+H25 -> 34195.129 | I29: =I21+I25 -> 45126.705 | J29: =J21+J25 -> 51283.372 | K29: =K21+K25 -> 69271.411 | L29: =L21+L25 -> 80703.642 | M29: =RATE(5,0,-H29,L29) -> 0.18736919
B30: % of growth | F30: =F29/E29-1 -> #DIV/0! | G30: =G29/F29-1 -> 0.10512478 | H30: =H29/G29-1 -> 1.0267991 | I30: =I29/H29-1 -> 0.31968224 | J30: =J29/I29-1 -> 0.13643068 | K30: =K29/J29-1 -> 0.35075773 | L30: =L29/K29-1 -> 0.16503534
B31: % of sales | F31: =F29/F$6 -> 0.18734726 | G31: =G29/G$6 -> 0.18272251 | H31: =H29/H$6 -> 0.24777064 | I31: =I29/I$6 -> 0.24774333 | J31: =J29/J$6 -> 0.2514571 | K31: =K29/K$6 -> 0.26518754 | L31: =L29/L$6 -> 0.26826419

Sheet 매출액(보고서)
B1: ="Project"&" "&Title!L6 -> Project SVG1 | J1: =Des!C12 -> DRAFT - For Discussion Purposes Only
B2: Sales Forecast
G3: =G6='Pro forma'!H6 -> FALSE | H3: =H6='Pro forma'!I6 -> FALSE | I3: =I6='Pro forma'!J6 -> FALSE | J3: =J6='Pro forma'!K6 -> FALSE | K3: =K6='Pro forma'!L6 -> FALSE
B4: 국내 제품 매출액
B5: KRW, 대수 | D5: ='Pro forma'!E$5 -> 2015 | E5: ='Pro forma'!F$5 -> 2016 | F5: ='Pro forma'!G$5 -> 2017 | G5: ='Pro forma'!H$5 -> 2018 | H5: ='Pro forma'!I$5 -> 2019 | I5: ='Pro forma'!J$5 -> 2020 | J5: ='Pro forma'!K$5 -> 2021 | K5: 2022
B6: 총 매출액 | D6: =IS!E5/10^6 -> 61966.746 | E6: =IS!F5/10^6 -> 81488.231 | F6: =IS!G5/10^6 -> 92333.966 | G6: =G9+G158+G211+G221 -> 149515.7 | H6: =H9+H158+H211+H221 -> 191499.17 | I6: =I9+I158+I211+I221 -> 246627.59 | J6: =J9+J158+J211+J221 -> 273031.19 | K6: =K9+K158+K211+K221 -> 303958.33 | L6: 총 매출액은 국내 제품 매출 /해외제품매출/서비스매출/항공매출로 구성 | P6: 61966.746 | Q6: 81488.231 | R6: 92318.49 | S6: 153587.25 | T6: 193346.24 | U6: 252459.99 | V6: 278172.24 | W6: 306131.28
B7: % of growth | E7: =E6/D6-1 -> 0.31503163 | F7: =F6/E6-1 -> 0.13309572 | G7: =G6/F6-1 -> 0.6192925 | H7: =H6/G6-1 -> 0.28079645 | I7: =I6/H6-1 -> 0.28787806 | J7: =J6/I6-1 -> 0.10705859 | K7: =K6/J6-1 -> 0.1132733
B9: 국내 제품 매출액 | D9: =D11+D57+D98+D139+D141 -> 55129.323 | E9: =E11+E57+E98+E139+E141 -> 74962.145 | F9: =F11+F57+F98+F139+F141 -> 79031.856 | G9: =G11+G57+G98+G139+G141 -> 112042.8 | H9: =H11+H57+H98+H139+H141 -> 142930.2 | I9: =I11+I57+I98+I139+I141 -> 187956.7 | J9: =J11+J57+J98+J139+J141 -> 207998.6 | K9: =K11+K57+K98+K139+K141 -> 226353.9
B11: 고소작업차 | D11: =D15+D22+D29+D36+D43+D50 -> 34316.995 | E11: =E15+E22+E29+E36+E43+E50 -> 43593.833 | F11: =F15+F22+F29+F36+F43+F50 -> 48663.641 | G11: =G15+G22+G29+G36+G43+G50 -> 49040.8 | H11: =H15+H22+H29+H36+H43+H50 -> 62601.7 | I11: =I15+I22+I29+I36+I43+I50 -> 82093.2 | J11: =J15+J22+J29+J36+J43+J50 -> 89632.2 | K11: =K15+K22+K29+K36+K43+K50 -> 96991.9 | O11: 113263800000
B12: % of growth | E12: =E11/D11-1 -> 0.2703278 | F12: =F11/E11-1 -> 0.11629644 | G12: =G11/F11-1 -> 0.0077503272 | H12: =H11/G11-1 -> 0.27652281 | I12: =I11/H11-1 -> 0.31135736 | J12: =J11/I11-1 -> 0.091834646 | K12: =K11/J11-1 -> 0.082110001
B13: % of sales | D13: =D11/D$6 -> 0.55379696 | E13: =E11/E$6 -> 0.53497091 | F13: =F11/F$6 -> 0.52703943 | G13: =G11/G$6 -> 0.32799767 | H13: =H11/H$6 -> 0.32690324 | I13: =I11/I$6 -> 0.33286301 | J13: =J11/J$6 -> 0.32828557 | K13: =K11/K$6 -> 0.31909604
B15: 전기향 매출 | D15: =D18*D20/10^6 -> 5284.0229 | E15: =E18*E20/10^6 -> 13364.807 | F15: =F18*F20/10^6 -> 15325.141 | G15: =G18*G20/10^6 -> 23301.9 | H15: =H18*H20/10^6 -> 26056.9 | I15: =I18*I20/10^6 -> 34826.1 | J15: =J18*J20/10^6 -> 36651.1 | K15: =K18*K20/10^6 -> 38738.7 | L15: 2018년 한전향 단가 계약으로 인한 매출액 발생
B16: % of growth | E16: =E15/D15-1 -> 1.5292863 | F16: =F15/E15-1 -> 0.14667885 | G16: =G15/F15-1 -> 0.52050147 | H16: =H15/G15-1 -> 0.1182307 | I16: =I15/H15-1 -> 0.33654042 | J16: =J15/I15-1 -> 0.052403226 | K16: =K15/J15-1 -> 0.056958727 | L16: =RATE(5,0,-G15,K15) -> 0.10700795
B17: % of 국내 제품 매출 | D17: =D15/D$9 -> 0.095847775 | E17: =E15/E$9 -> 0.17828741 | F17: =F15/F$9 -> 0.19391094 | G17: =G15/G$9 -> 0.2079732 | H17: =H15/H$9 -> 0.18230507 | I17: =I15/I$9 -> 0.18528789 | J17: =J15/J$9 -> 0.1762084 | K17: =K15/K$9 -> 0.17114218 | L17: =G17+G24 -> 0.40296119 | M17: =H17+H24 -> 0.39785294 | N17: =I17+I24 -> 0.39384177 | O17: =J17+J24 -> 0.38305642 | P17: =K17+K24 -> 0.37814635
B18: 수량(Q) | D18: ='2015년 원장 (피벗) '!P10 -> 103 | E18: ='2016년 원장 (피벗)'!P10 -> 175 | F18: 228 | G18: ='사업계획(매출 확정본)'!AI14 -> 476 | H18: ='사업계획(매출 확정본)'!AJ14 -> 508 | I18: ='사업계획(매출 확정본)'!AK14 -> 571 | J18: ='사업계획(매출 확정본)'!AL14 -> 579 | K18: ='사업계획(매출 확정본)'!AM14 -> 584
B19: % of growth | D19: =D18/#REF!-1 -> #REF! | E19: =E18/D18-1 -> 0.69902913 | F19: =F18/E18-1 -> 0.30285714 | G19: =G18/F18-1 -> 1.0877193 | H19: =H18/G18-1 -> 0.067226891 | I19: =I18/H18-1 -> 0.12401575 | J19: =J18/I18-1 -> 0.014010508 | K19: =K18/J18-1 -> 0.0086355786
B20: 단가(P) | D20: ='2015년 원장 (피벗) '!W10 -> 51301193 | E20: ='2016년 원장 (피벗)'!W10 -> 76370325 | F20: 67215532 | G20: ='사업계획(매출 확정본)'!AI15 -> 48953571 | H20: ='사업계획(매출 확정본)'!AJ15 -> 51293110 | I20: ='사업계획(매출 확정본)'!AK15 -> 60991419 | J20: ='사업계획(매출 확정본)'!AL15 -> 63300691 | K20: ='사업계획(매출 확정본)'!AM15 -> 66333390
B21: % of growth | D21: =D20/#REF!-1 -> #REF! | E21: =E20/D20-1 -> 0.48866567 | F21: =F20/E20-1 -> -0.11987369 | G21: =G20/F20-1 -> -0.27169257 | H21: =H20/G20-1 -> 0.047790973 | I21: =I20/H20-1 -> 0.18907624 | J21: =J20/I20-1 -> 0.037862249 | K21: =K20/J20-1 -> 0.047909423
B22: 통신향 매출 | D22: =D25*D27/10^6 -> 24950.095 | E22: =E25*E27/10^6 -> 28258.785 | F22: =F25*F27/10^6 -> 30798.914 | G22: =G25*G27/10^6 -> 21847 | H22: =H25*H27/10^6 -> 30808.3 | I22: =I25*I27/10^6 -> 39199.1 | J22: =J25*J27/10^6 -> 43024.1 | K22: =K25*K27/10^6 -> 46856.2 | L22: KT 매출
B23: % of growth | E23: =E22/D22-1 -> 0.13261235 | F23: =F22/E22-1 -> 0.089888127 | G23: =G22/F22-1 -> -0.29065682 | H23: =H22/G22-1 -> 0.41018446 | I23: =I22/H22-1 -> 0.27235518 | J23: =J22/I22-1 -> 0.097578771 | K23: =K22/J22-1 -> 0.089068685
B24: % of 국내 제품 매출 | D24: =D22/D$9 -> 0.45257394 | E24: =E22/E$9 -> 0.37697407 | F24: =F22/F$9 -> 0.38970253 | G24: =G22/G$9 -> 0.19498799 | H24: =H22/H$9 -> 0.21554787 | I24: =I22/I$9 -> 0.20855389 | J24: =J22/J$9 -> 0.20684803 | K24: =K22/K$9 -> 0.20700416
B25: 수량(Q) | D25: ='2015년 원장 (피벗) '!P11 -> 642 | E25: ='2016년 원장 (피벗)'!P11 -> 780 | F25: 841 | G25: ='사업계획(매출 확정본)'!AI17 -> 606 | H25: ='사업계획(매출 확정본)'!AJ17 -> 782 | I25: ='사업계획(매출 확정본)'!AK17 -> 939 | J25: ='사업계획(매출 확정본)'!AL17 -> 981 | K25: ='사업계획(매출 확정본)'!AM17 -> 1018
B26: % of growth | D26: =D25/#REF!-1 -> #REF! | E26: =E25/D25-1 -> 0.21495327 | F26: =F25/E25-1 -> 0.078205128 | G26: =G25/F25-1 -> -0.27942925 | H26: =H25/G25-1 -> 0.29042904 | I26: =I25/H25-1 -> 0.20076726 | J26: =J25/I25-1 -> 0.044728435 | K26: =K25/J25-1 -> 0.037716616 | L26: =RATE(5,0,-G25,K25) -> 0.10931537
B27: 단가(P) | D27: ='2015년 원장 (피벗) '!W11 -> 38863076 | E27: ='2016년 원장 (피벗)'!W11 -> 36229212 | F27: 36621777 | G27: ='사업계획(매출 확정본)'!AI18 -> 36051155 | H27: ='사업계획(매출 확정본)'!AJ18 -> 39396803 | I27: ='사업계획(매출 확정본)'!AK18 -> 41745580 | J27: ='사업계획(매출 확정본)'!AL18 -> 43857390 | K27: ='사업계획(매출 확정본)'!AM18 -> 46027701
B28: % of growth | D28: =D27/#REF!-1 -> #REF! | E28: =E27/D27-1 -> -0.067772916 | F28: =F27/E27-1 -> 0.0108356 | G28: =G27/F27-1 -> -0.015581492 | H28: =H27/G27-1 -> 0.092802795 | I28: =I27/H27-1 -> 0.059618475 | J28: =J27/I27-1 -> 0.050587631 | K28: =K27/J27-1 -> 0.049485638
B29: 건설향 매출 | D29: =D32*D34/10^6 -> 646.66423 | E29: =E32*E34/10^6 -> 539.00345 | F29: =F32*F34/10^6 -> 373.79489 | G29: =G32*G34/10^6 -> 0 | H29: =H32*H34/10^6 -> 0 | I29: =I32*I34/10^6 -> 0 | J29: =J32*J34/10^6 -> 0 | K29: =K32*K34/10^6 -> 0
B30: % of growth | E30: =E29/D29-1 -> -0.16648636 | F30: =F29/E29-1 -> -0.30650743 | G30: =G29/F29-1 -> -1 | H30: =H29/G29-1 -> #DIV/0! | I30: =I29/H29-1 -> #DIV/0! | J30: =J29/I29-1 -> #DIV/0! | K30: =K29/J29-1 -> #DIV/0! | N30: 55129322651 | O30: 7.4962145e+10 | P30: 7.9031856e+10 | Q30: 113263800000 | R30: 149232200000 | S30: 193517700000 | T30: 215282100000 | U30: 225225800000
B31: % of 국내 제품 매출 | D31: =D29/D$9 -> 0.011729951 | E31: =E29/E$9 -> 0.0071903419 | F31: =F29/F$9 -> 0.0047296737 | G31: =G29/G$9 -> 0 | H31: =H29/H$9 -> 0 | I31: =I29/I$9 -> 0 | J31: =J29/J$9 -> 0 | K31: =K29/K$9 -> 0
B32: 수량(Q) | D32: ='2015년 원장 (피벗) '!P7 -> 32 | E32: ='2016년 원장 (피벗)'!P7 -> 20 | F32: 28 | G32: ='사업계획(매출 확정본)'!AI23 -> 0 | H32: ='사업계획(매출 확정본)'!AJ23 -> 0 | I32: ='사업계획(매출 확정본)'!AK23 -> 0 | J32: ='사업계획(매출 확정본)'!AL23 -> 0 | K32: ='사업계획(매출 확정본)'!AM23 -> 0
B33: % of growth | D33: =D32/#REF!-1 -> #REF! | E33: =E32/D32-1 -> -0.375 | F33: =F32/E32-1 -> 0.4 | G33: =G32/F32-1 -> -1 | H33: =H32/G32-1 -> #DIV/0! | I33: =I32/H32-1 -> #DIV/0! | J33: =J32/I32-1 -> #DIV/0! | K33: =K32/J32-1 -> #DIV/0!
B34: 단가(P) | D34: ='2015년 원장 (피벗) '!W7 -> 20208257 | E34: ='2016년 원장 (피벗)'!W7 -> 26950173 | F34: 13349818 | G34: =IFERROR('사업계획(매출 확정본)'!AI24,) -> 0 | H34: =IFERROR('사업계획(매출 확정본)'!AJ24,) -> 0 | I34: =IFERROR('사업계획(매출 확정본)'!AK24,) -> 0 | J34: =IFERROR('사업계획(매출 확정본)'!AL24,) -> 0 | K34: =IFERROR('사업계획(매출 확정본)'!AM24,) -> 0
B35: % of growth | D35: =D34/#REF!-1 -> #REF! | E35: =E34/D34-1 -> 0.33362182 | F35: =F34/E34-1 -> -0.50464816 | G35: =G34/F34-1 -> -1 | H35: =H34/G34-1 -> #DIV/0! | I35: =I34/H34-1 -> #DIV/0! | J35: =J34/I34-1 -> #DIV/0! | K35: =K34/J34-1 -> #DIV/0!
B36: 관공서향 매출 | D36: =D39*D41/10^6 -> 354.47763 | E36: =E39*E41/10^6 -> 195.69364 | F36: =F39*F41/10^6 -> 361.49866 | G36: =G39*G41/10^6 -> 554.4 | H36: =H39*H41/10^6 -> 970 | I36: =I39*I41/10^6 -> 1528.5 | J36: =J39*J41/10^6 -> 2140 | K36: =K39*K41/10^6 -> 2810
B37: % of growth | E37: =E36/D36-1 -> -0.44793797 | F37: =F36/E36-1 -> 0.84726836 | G37: =G36/F36-1 -> 0.53361563 | H37: =H36/G36-1 -> 0.74963925 | I37: =I36/H36-1 -> 0.5757732 | J37: =J36/I36-1 -> 0.40006542 | K37: =K36/J36-1 -> 0.31308411
B38: % of 국내 제품 매출 | D38: =D36/D$9 -> 0.0064299289 | E38: =E36/E$9 -> 0.0026105661 | F38: =F36/F$9 -> 0.004574088 | G38: =G36/G$9 -> 0.0049481091 | H38: =H36/H$9 -> 0.0067865294 | I38: =I36/I$9 -> 0.0081321921 | J38: =J36/J$9 -> 0.010288531 | K38: =K36/K$9 -> 0.012414189
B39: 수량(Q) | D39: ='2015년 원장 (피벗) '!P8 -> 7 | E39: ='2016년 원장 (피벗)'!P8 -> 2 | F39: 6 | G39: ='사업계획(매출 확정본)'!AI20 -> 6 | H39: ='사업계획(매출 확정본)'!AJ20 -> 10 | I39: ='사업계획(매출 확정본)'!AK20 -> 15 | J39: ='사업계획(매출 확정본)'!AL20 -> 20 | K39: ='사업계획(매출 확정본)'!AM20 -> 25
B40: % of growth | D40: =D39/#REF!-1 -> #REF! | E40: =E39/D39-1 -> -0.71428571 | F40: =F39/E39-1 -> 2 | G40: =G39/F39-1 -> 0 | H40: =H39/G39-1 -> 0.66666667 | I40: =I39/H39-1 -> 0.5 | J40: =J39/I39-1 -> 0.33333333 | K40: =K39/J39-1 -> 0.25
B41: 단가(P) | D41: ='2015년 원장 (피벗) '!W8 -> 50639661 | E41: ='2016년 원장 (피벗)'!W8 -> 97846818 | F41: 60249777 | G41: ='사업계획(매출 확정본)'!AI21 -> 92400000 | H41: ='사업계획(매출 확정본)'!AJ21 -> 97000000 | I41: ='사업계획(매출 확정본)'!AK21 -> 101900000 | J41: ='사업계획(매출 확정본)'!AL21 -> 107000000 | K41: ='사업계획(매출 확정본)'!AM21 -> 112400000
B42: % of growth | D42: =D41/#REF!-1 -> #REF! | E42: =E41/D41-1 -> 0.93221709 | F42: =F41/E41-1 -> -0.38424388 | G42: =G41/F41-1 -> 0.53361563 | H42: =H41/G41-1 -> 0.04978355 | I42: =I41/H41-1 -> 0.050515464 | J42: =J41/I41-1 -> 0.050049068 | K42: =K41/J41-1 -> 0.05046729 | T42: 확정적인건 아닌데, 경매물건이 나와서
B43: 항공향 매출 | D43: =D46*D48/10^6 -> 642.92875 | E43: =E46*E48/10^6 -> 5.572727 | F43: =F46*F48/10^6 -> 13.954545 | G43: =IFERROR(G46*G48/10^6,0) -> 0 | H43: =IFERROR(H46*H48/10^6,0) -> 0 | I43: =IFERROR(I46*I48/10^6,0) -> 0 | J43: =IFERROR(J46*J48/10^6,0) -> 0 | K43: =IFERROR(K46*K48/10^6,0) -> 0 | T43: 부지가 20억, 공장 증설 계획을 세우시는 것 같음
B44: % of growth | E44: =E43/D43-1 -> -0.99133228 | F44: =F43/E43-1 -> 1.5040783 | G44: =G43/F43-1 -> -1 | H44: =H43/G43-1 -> #DIV/0! | I44: =I43/H43-1 -> #DIV/0! | J44: =J43/I43-1 -> #DIV/0! | K44: =K43/J43-1 -> #DIV/0!
B45: % of 국내 제품 매출 | D45: =D43/D$9 -> 0.011662192 | E45: =E43/E$9 -> 7.4340548e-05 | F45: =F43/F$9 -> 0.00017656861 | G45: =G43/G$9 -> 0 | H45: =H43/H$9 -> 0 | I45: =I43/I$9 -> 0 | J45: =J43/J$9 -> 0 | K45: =K43/K$9 -> 0 | T45: 외주를 하려고 했는데, 좋은 경매 물건나와서 자체 생산 할 수 잇게
B46: 수량(Q) | D46: ='2015년 원장 (피벗) '!P12 -> 1 | E46: ='2016년 원장 (피벗)'!P12 -> 1 | F46: 1 | G46: ='사업계획(매출 확정본)'!AI26 -> 0 | H46: ='사업계획(매출 확정본)'!AJ26 -> 0 | I46: ='사업계획(매출 확정본)'!AK26 -> 0 | J46: ='사업계획(매출 확정본)'!AL26 -> 0 | K46: =IFERROR('사업계획(매출 확정본)'!AM27,0) -> 0 | T46: 14000평 정도될 것 같아서, 라인 구축 하는데 기계설비 등
B47: % of growth | D47: =D46/#REF!-1 -> #REF! | E47: =E46/D46-1 -> 0 | F47: =F46/E46-1 -> 0 | G47: =G46/F46-1 -> -1 | H47: =H46/G46-1 -> #DIV/0! | I47: =I46/H46-1 -> #DIV/0! | J47: =J46/I46-1 -> #DIV/0! | K47: =K46/J46-1 -> #DIV/0! | T47: 확정적인건 아니고, 부지를 경매참여 한다고 하면, Minimum 100-130억이다
B48: 단가(P) | D48: ='2015년 원장 (피벗) '!W12 -> 642928745 | E48: ='2016년 원장 (피벗)'!W12 -> 5572727 | F48: 13954545 | G48: ='사업계획(매출 확정본)'!AI27 -> #DIV/0! | H48: ='사업계획(매출 확정본)'!AJ27 -> #DIV/0! | I48: ='사업계획(매출 확정본)'!AK27 -> #DIV/0! | J48: ='사업계획(매출 확정본)'!AL27 -> #DIV/0! | T48: (부지 경매가 되면)
B49: % of growth | D49: =D48/#REF!-1 -> #REF! | E49: =E48/D48-1 -> -0.99133228 | F49: =F48/E48-1 -> 1.5040783 | G49: =G48/F48-1 -> #DIV/0! | H49: =H48/G48-1 -> #DIV/0! | I49: =I48/H48-1 -> #DIV/0! | J49: =J48/I48-1 -> #DIV/0! | K49: =K48/J48-1 -> #DIV/0! | T49: 신제품 - 증축 필요없고, 최초에는 외주 처리를 좀 하고(제관 쪽이니까 우리가 하는거랑 차이 많지 않음)
B50: 기타향 매출 | D50: =D53*D55/10^6 -> 2438.8073 | E50: =E53*E55/10^6 -> 1229.9713 | F50: =F53*F55/10^6 -> 1790.3369 | G50: =G53*G55/10^6 -> 3337.5 | H50: =H53*H55/10^6 -> 4766.5 | I50: =I53*I55/10^6 -> 6539.5 | J50: =J53*J55/10^6 -> 7817 | K50: =K53*K55/10^6 -> 8587 | L50: 모델의 범용성이 높은 모델들 | T50: 포트홀 판매를 60대로 추정했는데,
B51: % of growth | E51: =E50/D50-1 -> -0.49566689 | F51: =F50/E50-1 -> 0.45559248 | G51: =G50/F50-1 -> 0.86417427 | H51: =H50/G50-1 -> 0.42816479 | I51: =I50/H50-1 -> 0.37197105 | J51: =J50/I50-1 -> 0.19535133 | K51: =K50/J50-1 -> 0.098503262
B52: % of 국내 제품 매출 | D52: =D50/D$9 -> 0.044237933 | E52: =E50/E$9 -> 0.016407898 | F52: =F50/F$9 -> 0.022653358 | G52: =G50/G$9 -> 0.029787724 | H52: =H50/H$9 -> 0.033348446 | I52: =I50/I$9 -> 0.034792588 | J52: =J50/J$9 -> 0.037581984 | K52: =K50/K$9 -> 0.03793617 | T52: 6월달에 시제품이 나오면, 7-8월달이 되면 일정부분 홍보 형태로 관공서와 시험 운영을 하게 됨
B53: 수량(Q) | D53: ='2015년 원장 (피벗) '!P9 -> 22 | E53: ='2016년 원장 (피벗)'!P9 -> 23 | F53: 34 | G53: ='사업계획(매출 확정본)'!AI29 -> 53 | H53: ='사업계획(매출 확정본)'!AJ29 -> 70 | I53: ='사업계획(매출 확정본)'!AK29 -> 90 | J53: ='사업계획(매출 확정본)'!AL29 -> 105 | K53: ='사업계획(매출 확정본)'!AM29 -> 110 | T53: 인원계획 : 생산인력만. 판관비 인력은 증가할텐데.. 해외 쪽은
B54: % of growth | D54: =D53/#REF!-1 -> #REF! | E54: =E53/D53-1 -> 0.045454545 | F54: =F53/E53-1 -> 0.47826087 | G54: =G53/F53-1 -> 0.55882353 | H54: =H53/G53-1 -> 0.32075472 | I54: =I53/H53-1 -> 0.28571429 | J54: =J53/I53-1 -> 0.16666667 | K54: =K53/J53-1 -> 0.047619048 | T54: Aichi사 대비 기술적 우위 :
B55: 단가(P) | D55: ='2015년 원장 (피벗) '!W9 -> 1.1085488e+08 | E55: ='2016년 원장 (피벗)'!W9 -> 53477011 | F55: 52656968 | G55: ='사업계획(매출 확정본)'!AI30 -> 62971698 | H55: ='사업계획(매출 확정본)'!AJ30 -> 68092857 | I55: ='사업계획(매출 확정본)'!AK30 -> 72661111 | J55: ='사업계획(매출 확정본)'!AL30 -> 74447619 | K55: ='사업계획(매출 확정본)'!AM30 -> 78063636 | T55: 작업 속도가 1.4-2배 수준 차이가 남.
B57: 크레인 | D57: =D61+D67+D73+D79+D85+D91 -> 870.97955 | E57: =E61+E67+E73+E79+E85+E91 -> 10386.593 | F57: =F61+F67+F73+F79+F85+F91 -> 3467.3121 | G57: =G61+G67+G73+G79+G85+G91 -> 9332 | H57: =H61+H67+H73+H79+H85+H91 -> 13558 | I57: =I61+I67+I73+I79+I85+I91 -> 19319.5 | J57: =J61+J67+J73+J79+J85+J91 -> 22827.9 | K57: =K61+K67+K73+K79+K85+K91 -> 25928 | T57: 고소작업차/활선차 시장 규모 :
B58: % of growth | E58: =E57/D57-1 -> 10.925186 | F58: =F57/E57-1 -> -0.66617427 | G58: =G57/F57-1 -> 1.691422 | H58: =H57/G57-1 -> 0.45285041 | I58: =I57/H57-1 -> 0.42495206 | J58: =J57/I57-1 -> 0.1815989 | K58: =K57/J57-1 -> 0.13580312 | T58: 활선차도 고소작업차 안에 들어가는것임. 고소작업차는 특수자동차의 한 아이템
B59: % of 총 매출액 | D59: =D57/D$6 -> 0.014055596 | E59: =E57/E$6 -> 0.12746127 | F59: =F57/F$6 -> 0.037551859 | G59: =G57/G$6 -> 0.062414851 | H59: =H57/H$6 -> 0.070799261 | I59: =I57/I$6 -> 0.078334708 | J59: =J57/J$6 -> 0.08360913 | K59: =K57/K$6 -> 0.085301166 | T59: 고소작업차: 스카이/활선차 다 합해서 약
T60: 소형은 1000억 원/ 중대형은 6-7000억 수준 (스카이 포함해서) / 활선차는 700억 대 수준 (연도별 차이가 좀 있음0
B61: 전기향 매출 | D61: =D63*D65/10^6 -> 48 | E61: =E63*E65/10^6 -> 39 | F61: =F63*F65/10^6 -> 1091.4409 | G61: =G63*G65/10^6 -> 270 | H61: =H63*H65/10^6 -> 709 | I61: =I63*I65/10^6 -> 1489 | J61: =J63*J65/10^6 -> 2031.9 | K61: =K63*K65/10^6 -> 2461.5 | T61: 소형 고소작업차 시장에서는 우리 점유율이 80-90%
B62: % of growth | E62: =E61/D61-1 -> -0.1875 | F62: =F61/E61-1 -> 26.985665 | G62: =G61/F61-1 -> -0.7526206 | H62: =H61/G61-1 -> 1.6259259 | I62: =I61/H61-1 -> 1.100141 | J62: =J61/I61-1 -> 0.36460712 | K62: =K61/J61-1 -> 0.21142773
B63: 수량(Q) | D63: ='2015년 원장 (피벗) '!R10 -> 2 | E63: ='2016년 원장 (피벗)'!R10 -> 1 | F63: 11 | G63: ='사업계획(매출 확정본)'!AI32 -> 2 | H63: ='사업계획(매출 확정본)'!AJ32 -> 5 | I63: ='사업계획(매출 확정본)'!AK32 -> 10 | J63: ='사업계획(매출 확정본)'!AL32 -> 13 | K63: ='사업계획(매출 확정본)'!AM32 -> 15 | T63: 불법장비들이 사용 못하니까 고소작업차 사용하게됨
B64: % of growth | E64: =E63/D63-1 -> -0.5 | F64: =F63/E63-1 -> 10 | G64: =G63/F63-1 -> -0.81818182 | H64: =H63/G63-1 -> 1.5 | I64: =I63/H63-1 -> 1 | J64: =J63/I63-1 -> 0.3 | T64: 옛날에는 크레인에 버캣만 장착해서.. (카고 크레인 -> 고소작업차 시장으로 일부가 늘어남)
B65: 단가(P) | D65: ='2015년 원장 (피벗) '!Y10 -> 24000000 | E65: ='2016년 원장 (피벗)'!Y10 -> 39000000 | F65: 99221902 | G65: ='사업계획(매출 확정본)'!AI33 -> 135000000 | H65: ='사업계획(매출 확정본)'!AJ33 -> 141800000 | I65: ='사업계획(매출 확정본)'!AK33 -> 148900000 | J65: ='사업계획(매출 확정본)'!AL33 -> 156300000 | K65: ='사업계획(매출 확정본)'!AM33 -> 164100000
B66: % of growth | E66: =E65/D65-1 -> 0.625 | F66: =F65/E65-1 -> 1.5441513 | G66: =G65/F65-1 -> 0.3605867 | H66: =H65/G65-1 -> 0.05037037 | I66: =I65/H65-1 -> 0.050070522 | J66: =J65/I65-1 -> 0.049697784 | K66: =K65/J65-1 -> 0.049904031 | T66: 국내 시장 매출 성장
B67: 통신향 매출 | D67: =D69*D71/10^6 -> 207.6 | E67: =E69*E71/10^6 -> 9940.027 | F67: =F69*F71/10^6 -> 1646.3075 | G67: =G69*G71/10^6 -> 1944 | H67: =H69*H71/10^6 -> 2784.5 | I67: =I69*I71/10^6 -> 4140.5 | J67: =J69*J71/10^6 -> 3585 | K67: =K69*K71/10^6 -> 4035 | T67: 법률이 강화되면서 안정성 강화로 인해 / 건설현장 공사현장 등에서 우리 제품이 꼭 들어가야 함 (예전에는 무식하게 작업하는)
B68: % of growth | E68: =E67/D67-1 -> 46.88067 | F68: =F67/E67-1 -> -0.83437595 | G68: =G67/F67-1 -> 0.18082435 | H68: =H67/G67-1 -> 0.43235597 | I68: =I67/H67-1 -> 0.4869815 | J68: =J67/I67-1 -> -0.13416254 | K68: =K67/J67-1 -> 0.12552301 | T68: ->불법장비로 의심되는 장비들 아직도 많음
B69: 수량(Q) | D69: ='2015년 원장 (피벗) '!R11 -> 12 | E69: ='2016년 원장 (피벗)'!R11 -> 114 | F69: 60 | G69: ='사업계획(매출 확정본)'!AI35 -> 24 | H69: ='사업계획(매출 확정본)'!AJ35 -> 35 | I69: ='사업계획(매출 확정본)'!AK35 -> 50 | J69: ='사업계획(매출 확정본)'!AL35 -> 45 | K69: ='사업계획(매출 확정본)'!AM35 -> 50
B70: % of growth | E70: =E69/D69-1 -> 8.5 | F70: =F69/E69-1 -> -0.47368421 | G70: =G69/F69-1 -> -0.6 | H70: =H69/G69-1 -> 0.45833333 | I70: =I69/H69-1 -> 0.42857143 | J70: =J69/I69-1 -> -0.1 | K70: =K69/J69-1 -> 0.11111111 | T70: A/S
B71: 단가(P) | D71: ='2015년 원장 (피벗) '!Y11 -> 17300000 | E71: ='2016년 원장 (피벗)'!Y11 -> 87193219 | F71: 27438459 | G71: ='사업계획(매출 확정본)'!AI36 -> 81000000 | H71: ='사업계획(매출 확정본)'!AJ36 -> 79557143 | I71: ='사업계획(매출 확정본)'!AK36 -> 82810000 | J71: ='사업계획(매출 확정본)'!AL36 -> 79666667 | K71: ='사업계획(매출 확정본)'!AM36 -> 80700000 | T71: 한전, KT 등과의 유지보수 계약을 체결. 5년 씩.. 연 3억 수준은 서비스 매출로
B72: % of growth | E72: =E71/D71-1 -> 4.0400705 | F72: =F71/E71-1 -> -0.68531431 | G72: =G71/F71-1 -> 1.9520609 | H72: =H71/G71-1 -> -0.017813051 | I72: =I71/H71-1 -> 0.040887053 | J72: =J71/I71-1 -> -0.037958379 | K72: =K71/J71-1 -> 0.012970711
B73: 건설향 매출 | D73: =IFERROR(D75*D77,0)/10^6 -> 0 | E73: =IFERROR(E75*E77,0)/10^6 -> 0 | F73: =IFERROR(F75*F77,0)/10^6 -> 54.627273 | G73: =IFERROR(G75*G77,0)/10^6 -> 4590 | H73: =IFERROR(H75*H77,0)/10^6 -> 5769.5 | I73: =IFERROR(I75*I77,0)/10^6 -> 7538.5 | J73: =IFERROR(J75*J77,0)/10^6 -> 9027 | K73: =IFERROR(K75*K77,0)/10^6 -> 9977
B74: % of growth | E74: =E73/D73-1 -> #DIV/0! | F74: =F73/E73-1 -> #DIV/0! | G74: =G73/F73-1 -> 83.023964 | H74: =H73/G73-1 -> 0.25697168 | I74: =I73/H73-1 -> 0.30661236 | J74: =J73/I73-1 -> 0.19745307 | K74: =K73/J73-1 -> 0.10523984
B75: 수량(Q) | D75: ='2015년 원장 (피벗) '!R7 -> 0 | E75: ='2016년 원장 (피벗)'!R7 -> 0 | F75: 2 | G75: ='사업계획(매출 확정본)'!AI41 -> 289 | H75: ='사업계획(매출 확정본)'!AJ41 -> 335 | I75: ='사업계획(매출 확정본)'!AK41 -> 405 | J75: ='사업계획(매출 확정본)'!AL41 -> 465 | K75: ='사업계획(매출 확정본)'!AM41 -> 485
B76: % of growth | E76: =E75/D75-1 -> #DIV/0! | F76: =F75/E75-1 -> #DIV/0! | G76: =G75/F75-1 -> 143.5 | H76: =H75/G75-1 -> 0.15916955 | I76: =I75/H75-1 -> 0.20895522 | J76: =J75/I75-1 -> 0.14814815 | K76: =K75/J75-1 -> 0.043010753
B77: 단가(P) | D77: =IFERROR('2015년 원장 (피벗) '!Y7,0) -> 0 | E77: =IFERROR('2016년 원장 (피벗)'!Y7,0) -> 0 | F77: 27313636 | G77: ='사업계획(매출 확정본)'!AI42 -> 15882353 | H77: ='사업계획(매출 확정본)'!AJ42 -> 17222388 | I77: ='사업계획(매출 확정본)'!AK42 -> 18613580 | J77: ='사업계획(매출 확정본)'!AL42 -> 19412903 | K77: ='사업계획(매출 확정본)'!AM42 -> 20571134
B78: % of growth | D78: =D77/#REF!-1 -> #REF! | E78: =E77/D77-1 -> #DIV/0! | F78: =F77/E77-1 -> #DIV/0! | G78: =G77/F77-1 -> -0.41851928 | H78: =H77/G77-1 -> 0.084372582 | I78: =I77/H77-1 -> 0.080778123 | J78: =J77/I77-1 -> 0.042943 | K78: =K77/J77-1 -> 0.059662936
B79: 관공서향 매출 | D79: =D81*D83/10^6 -> 462.52618 | E79: =E81*E83/10^6 -> 407.56637 | F79: =F81*F83/10^6 -> 580.43637 | G79: =G81*G83/10^6 -> 2528 | H79: =H81*H83/10^6 -> 4295 | I79: =I81*I83/10^6 -> 6151.5 | J79: =J81*J83/10^6 -> 8184 | K79: =K81*K83/10^6 -> 9454.5
B80: % of growth | E80: =E79/D79-1 -> -0.11882531 | F80: =F79/E79-1 -> 0.42415178 | G80: =G79/F79-1 -> 3.3553439 | H80: =H79/G79-1 -> 0.69897152 | I80: =I79/H79-1 -> 0.4322468 | J80: =J79/I79-1 -> 0.33040722 | K80: =K79/J79-1 -> 0.15524194
B81: 수량(Q) | D81: ='2015년 원장 (피벗) '!R8 -> 7 | E81: ='2016년 원장 (피벗)'!R8 -> 4 | F81: 9 | G81: ='사업계획(매출 확정본)'!AI38 -> 24 | H81: ='사업계획(매출 확정본)'!AJ38 -> 40 | I81: ='사업계획(매출 확정본)'!AK38 -> 55 | J81: ='사업계획(매출 확정본)'!AL38 -> 70 | K81: ='사업계획(매출 확정본)'!AM38 -> 77
B82: % of growth | E82: =E81/D81-1 -> -0.42857143 | F82: =F81/E81-1 -> 1.25 | G82: =G81/F81-1 -> 1.6666667 | H82: =H81/G81-1 -> 0.66666667 | I82: =I81/H81-1 -> 0.375 | J82: =J81/I81-1 -> 0.27272727
B83: 단가(P) | D83: ='2015년 원장 (피벗) '!Y8 -> 66075169 | E83: ='2016년 원장 (피벗)'!Y8 -> 1.0189159e+08 | F83: 64492930 | G83: ='사업계획(매출 확정본)'!AI39 -> 1.0533333e+08 | H83: ='사업계획(매출 확정본)'!AJ39 -> 107375000 | I83: ='사업계획(매출 확정본)'!AK39 -> 1.1184545e+08 | J83: ='사업계획(매출 확정본)'!AL39 -> 1.1691429e+08 | K83: ='사업계획(매출 확정본)'!AM39 -> 1.2278571e+08
B84: % of growth | E84: =E83/D83-1 -> 0.54205571 | F84: =F83/E83-1 -> -0.36704365 | G84: =G83/F83-1 -> 0.63325397 | H84: =H83/G83-1 -> 0.019382911 | I84: =I83/H83-1 -> 0.041634035 | J84: =J83/I83-1 -> 0.045319957 | K84: =K83/J83-1 -> 0.050219941
B85: 항공향 매출 | D85: =IFERROR(D87*D89,0)/10^6 -> 0 | E85: =IFERROR(E87*E89,0)/10^6 -> 0 | F85: =IFERROR(F87*F89,0)/10^6 -> 0 | G85: =IFERROR(G87*G89,0)/10^6 -> 0 | H85: =IFERROR(H87*H89,0)/10^6 -> 0 | I85: =IFERROR(I87*I89,0)/10^6 -> 0 | J85: =IFERROR(J87*J89,0)/10^6 -> 0 | K85: =IFERROR(K87*K89,0)/10^6 -> 0
B86: % of growth | E86: =E85/D85-1 -> #DIV/0! | F86: =F85/E85-1 -> #DIV/0! | G86: =G85/F85-1 -> #DIV/0! | H86: =H85/G85-1 -> #DIV/0! | I86: =I85/H85-1 -> #DIV/0! | J86: =J85/I85-1 -> #DIV/0! | K86: =K85/J85-1 -> #DIV/0!
B87: 수량(Q) | D87: ='2015년 원장 (피벗) '!R12 -> 0 | E87: ='2016년 원장 (피벗)'!R12 -> 0 | F87: 0 | G87: ='사업계획(매출 확정본)'!AI44 -> 0 | H87: ='사업계획(매출 확정본)'!AJ44 -> 0 | I87: ='사업계획(매출 확정본)'!AK44 -> 0 | J87: ='사업계획(매출 확정본)'!AL44 -> 0 | K87: ='사업계획(매출 확정본)'!AM44 -> 0
B88: % of growth | E88: =E87/D87-1 -> #DIV/0! | F88: =F87/E87-1 -> #DIV/0! | G88: =G87/F87-1 -> #DIV/0! | H88: =H87/G87-1 -> #DIV/0! | I88: =I87/H87-1 -> #DIV/0! | J88: =J87/I87-1 -> #DIV/0! | K88: =K87/J87-1 -> #DIV/0!
B89: 단가(P) | D89: =IFERROR('2015년 원장 (피벗) '!Y12,0) -> 0 | E89: =IFERROR('2016년 원장 (피벗)'!Y12,0) -> 0 | F89: #DIV/0! | G89: ='사업계획(매출 확정본)'!AI45 -> #DIV/0! | H89: ='사업계획(매출 확정본)'!AJ45 -> #DIV/0! | I89: ='사업계획(매출 확정본)'!AK45 -> #DIV/0! | J89: ='사업계획(매출 확정본)'!AL45 -> #DIV/0!
B90: % of growth | D90: =D89/#REF!-1 -> #REF! | E90: =E89/D89-1 -> #DIV/0! | F90: =F89/E89-1 -> #DIV/0! | G90: =G89/F89-1 -> #DIV/0! | H90: =H89/G89-1 -> #DIV/0! | I90: =I89/H89-1 -> #DIV/0! | J90: =J89/I89-1 -> #DIV/0! | K90: =K89/J89-1 -> #DIV/0!
B91: 기타 매출 | D91: =D93*D95/10^6 -> 152.85336 | E91: =IFERROR(E93*E95/10^6,0) -> 0 | F91: =F93*F95/10^6 -> 94.5 | G91: =IFERROR(G93*G95/10^6,) -> 0 | H91: =IFERROR(H93*H95/10^6,) -> 0 | I91: =IFERROR(I93*I95/10^6,) -> 0 | J91: =IFERROR(J93*J95/10^6,) -> 0 | K91: =IFERROR(K93*K95/10^6,) -> 0
B92: % of growth | E92: =E91/D91-1 -> -1 | F92: =F91/E91-1 -> #DIV/0! | G92: =G91/F91-1 -> -1 | H92: =H91/G91-1 -> #DIV/0! | I92: =I91/H91-1 -> #DIV/0! | J92: =J91/I91-1 -> #DIV/0! | K92: =K91/J91-1 -> #DIV/0!
B93: 수량(Q) | D93: ='2015년 원장 (피벗) '!R9 -> 8 | E93: ='2016년 원장 (피벗)'!R9 -> 0 | F93: 4 | G93: ='사업계획(매출 확정본)'!AI47 -> 0 | H93: ='사업계획(매출 확정본)'!AJ47 -> 0 | I93: ='사업계획(매출 확정본)'!AK47 -> 0 | J93: ='사업계획(매출 확정본)'!AL47 -> 0 | K93: ='사업계획(매출 확정본)'!AM47 -> 0
B94: % of growth | E94: =E93/D93-1 -> -1 | F94: =F93/E93-1 -> #DIV/0! | G94: =G93/F93-1 -> -1 | H94: =H93/G93-1 -> #DIV/0! | I94: =I93/H93-1 -> #DIV/0! | J94: =J93/I93-1 -> #DIV/0! | K94: =K93/J93-1 -> #DIV/0!
B95: 단가(P) | D95: ='2015년 원장 (피벗) '!Y9 -> 19106670 | E95: =IFERROR('2016년 원장 (피벗)'!Y9,0) -> 0 | F95: 23625000 | G95: ='사업계획(매출 확정본)'!AI48 -> #DIV/0! | H95: ='사업계획(매출 확정본)'!AJ48 -> #DIV/0! | I95: ='사업계획(매출 확정본)'!AK48 -> #DIV/0! | J95: ='사업계획(매출 확정본)'!AL48 -> #DIV/0! | K95: =IFERROR('사업계획(매출 확정본)'!AM48,0) -> 0
B96: % of growth | E96: =E95/D95-1 -> -1 | F96: =F95/E95-1 -> #DIV/0! | G96: =G95/F95-1 -> #DIV/0! | H96: =H95/G95-1 -> #DIV/0! | I96: =I95/H95-1 -> #DIV/0! | J96: =J95/I95-1 -> #DIV/0! | K96: =K95/J95-1 -> #DIV/0!
B98: 활선차 | D98: =D102+D108+D114+D120+D126+D132 -> 18172.158 | E98: =E102+E108+E114+E120+E126+E132 -> 19174.655 | F98: =F102+F108+F114+F120+F126+F132 -> 26083.747 | G98: =G102+G108+G114+G120+G126+G132 -> 41420 | H98: =H102+H108+H114+H120+H126+H132 -> 50014.5 | I98: =I102+I108+I114+I120+I126+I132 -> 59321.5 | J98: =J102+J108+J114+J120+J126+J132 -> 65377.5 | K98: =K102+K108+K114+K120+K126+K132 -> 68774
B99: % of growth | E99: =E98/D98-1 -> 0.055166636 | F99: =F98/E98-1 -> 0.36032421 | G99: =G98/F98-1 -> 0.58796201 | H99: =H98/G98-1 -> 0.20749638 | I99: =I98/H98-1 -> 0.18608604 | J99: =J98/I98-1 -> 0.10208778 | K99: =K98/J98-1 -> 0.051952124
B100: % of 총 매출액 | D100: =D98/D$6 -> 0.29325661 | E100: =E98/E$6 -> 0.23530582 | F100: =F98/F$6 -> 0.28249352 | G100: =G98/G$6 -> 0.27702777 | H100: =H98/H$6 -> 0.26117345 | I100: =I98/I$6 -> 0.24053068 | J100: =J98/J$6 -> 0.23945067 | K100: =K98/K$6 -> 0.22626128
B102: 전기향 매출 | D102: =D104*D106/10^6 -> 15758.238 | E102: =E104*E106/10^6 -> 16127.709 | F102: =F104*F106/10^6 -> 24091.42 | G102: =G104*G106/10^6 -> 41420 | H102: =H104*H106/10^6 -> 50014.5 | I102: =I104*I106/10^6 -> 59321.5 | J102: =J104*J106/10^6 -> 65377.5 | K102: =K104*K106/10^6 -> 68774
B103: % of growth | E103: =E102/D102-1 -> 0.023446195 | F103: =F102/E102-1 -> 0.49379059 | G103: =G102/F102-1 -> 0.71928429 | H103: =H102/G102-1 -> 0.20749638 | I103: =I102/H102-1 -> 0.18608604 | J103: =J102/I102-1 -> 0.10208778 | K103: =K102/J102-1 -> 0.051952124
B104: 수량(Q) | D104: ='2015년 원장 (피벗) '!S10 -> 108 | E104: ='2016년 원장 (피벗)'!S10 -> 131 | F104: 155 | G104: ='사업계획(매출 확정본)'!AI50 -> 260 | H104: ='사업계획(매출 확정본)'!AJ50 -> 305 | I104: ='사업계획(매출 확정본)'!AK50 -> 345 | J104: ='사업계획(매출 확정본)'!AL50 -> 365 | K104: ='사업계획(매출 확정본)'!AM50 -> 370
B105: % of growth | E105: =E104/D104-1 -> 0.21296296 | F105: =F104/E104-1 -> 0.18320611 | G105: =G104/F104-1 -> 0.67741935 | H105: =H104/G104-1 -> 0.17307692 | I105: =I104/H104-1 -> 0.13114754 | J105: =J104/I104-1 -> 0.057971014
B106: 단가(P) | D106: ='2015년 원장 (피벗) '!Z10 -> 1.4590961e+08 | E106: ='2016년 원장 (피벗)'!Z10 -> 1.2311228e+08 | F106: 1.5542852e+08 | G106: ='사업계획(매출 확정본)'!AI51 -> 1.5930769e+08 | H106: ='사업계획(매출 확정본)'!AJ51 -> 1.6398197e+08 | I106: ='사업계획(매출 확정본)'!AK51 -> 1.7194638e+08 | J106: ='사업계획(매출 확정본)'!AL51 -> 1.7911644e+08 | K106: ='사업계획(매출 확정본)'!AM51 -> 1.8587568e+08
...

Sheet 매출액
B1: ="Project"&" "&Title!L6 -> Project SVG1 | J1: =Des!C12 -> DRAFT - For Discussion Purposes Only
B2: Sales Forecast
G3: ='사업계획(매출 확정본)'!AI114=G6 -> TRUE | H3: ='사업계획(매출 확정본)'!AJ114=H6 -> TRUE | I3: ='사업계획(매출 확정본)'!AK114=I6 -> TRUE | J3: ='사업계획(매출 확정본)'!AL114=J6 -> TRUE | K3: ='사업계획(매출 확정본)'!AM114=K6 -> TRUE
B4: Sales
B5: KRW, 대수 | D5: ='Pro forma'!E$5 -> 2015 | E5: ='Pro forma'!F$5 -> 2016 | F5: ='Pro forma'!G$5 -> 2017 | G5: ='Pro forma'!H$5 -> 2018 | H5: ='Pro forma'!I$5 -> 2019 | I5: ='Pro forma'!J$5 -> 2020 | J5: ='Pro forma'!K$5 -> 2021 | K5: 2022
B6: Sales | D6: =IS!E5 -> 61966745769 | E6: =IS!F5 -> 81488230867 | F6: =IS!G5 -> 92333965525 | G6: =G150+G204+G210+G220 -> 1.495157e+11 | H6: =H150+H204+H210+H220 -> 1.9132417e+11 | I6: =I150+I204+I210+I220 -> 2.4626959e+11 | J6: =J150+J204+J210+J220 -> 2.7248119e+11 | K6: =K150+K204+K210+K220 -> 3.0320433e+11 | L6: 총 매출액은 국내 제품 매출 /해외제품매출/서비스매출/항공매출로 구성
B7: % of growth | D7: =D6/#REF!-1 -> #REF! | E7: =E6/D6-1 -> 0.31503163 | F7: =F6/E6-1 -> 0.13309572 | G7: =G6/F6-1 -> 0.6192925 | H7: =H6/G6-1 -> 0.279626 | I7: =I6/H6-1 -> 0.28718488 | J7: =J6/I6-1 -> 0.10643459 | K7: =K6/J6-1 -> 0.11275327
M8: 61709.017 | N8: 81447.5 | O8: 91483.174 | P8: 154181.35 | Q8: 194357.52 | R8: 253491.11 | S8: 279502.71 | T8: 307288.73
M9: 61709.017 | N9: 81447.5 | O9: 91257.294 | P9: 153587.25 | Q9: 193346.24 | R9: 252459.99 | S9: 278172.24 | T9: 306131.28
B10: 고소작업차 부문 | D10: =D14+D21+D28+D35+D42+D49 -> 34316995394 | E10: =E14+E21+E28+E35+E42+E49 -> 40921440045 | F10: =F14+F21+F28+F35+F42+F49 -> 4.8663641e+10 | G10: =G14+G21+G28+G35+G42+G49 -> 49040800000 | H10: =H14+H21+H28+H35+H42+H49 -> 62601700000 | I10: =I14+I21+I28+I35+I42+I49 -> 82093200000 | J10: =J14+J21+J28+J35+J42+J49 -> 89632200000 | K10: =K14+K21+K28+K35+K42+K49 -> 96991900000 | M10: =M9=D6/10^6 -> FALSE
B11: % of growth | D11: =D10/#REF!-1 -> #REF! | E11: =E10/D10-1 -> 0.19245405 | F11: =F10/E10-1 -> 0.18919669 | G11: =G10/F10-1 -> 0.0077503272 | H11: =H10/G10-1 -> 0.27652281 | I11: =I10/H10-1 -> 0.31135736 | J11: =J10/I10-1 -> 0.091834646 | K11: =K10/J10-1 -> 0.082110001
B12: % of sales | D12: =D10/D$6 -> 0.55379696 | E12: =E10/E$6 -> 0.50217608 | F12: =F10/F$6 -> 0.52703943 | G12: =G10/G$6 -> 0.32799767 | H12: =H10/H$6 -> 0.32720225 | I12: =I10/I$6 -> 0.33334689 | J12: =J10/J$6 -> 0.32894822 | M12: 61966.746 | N12: 81488.231 | O12: 92318.49 | P12: 153587.25 | Q12: 193346.24 | R12: 252459.99 | S12: 278172.24 | T12: 306131.28
B14: 전기향 매출 | D14: =D17*D19 -> 5284022890 | E14: =E17*E19 -> 13364806884 | F14: =F17*F19 -> 1.5325141e+10 | G14: =G17*G19 -> 23301900000 | H14: =H17*H19 -> 26056900000 | I14: =I17*I19 -> 34826100000 | J14: =J17*J19 -> 36651100000 | K14: =K17*K19 -> 38738700000
B15: % of growth | D15: =D14/#REF!-1 -> #REF! | E15: =E14/D14-1 -> 1.5292863 | F15: =F14/E14-1 -> 0.14667885 | G15: =G14/F14-1 -> 0.52050147 | H15: =H14/G14-1 -> 0.1182307 | I15: =I14/H14-1 -> 0.33654042 | J15: =J14/I14-1 -> 0.052403226 | K15: =K14/J14-1 -> 0.056958727
B16: % of 국내 Sales | D16: =D14/D$6 -> 0.085271912 | E16: =E14/E$6 -> 0.16400904 | F16: =F14/F$6 -> 0.16597512 | G16: =G14/G$6 -> 0.15584919 | H16: =H14/H$6 -> 0.13619241 | I16: =I14/I$6 -> 0.14141454 | J16: =J14/J$6 -> 0.13450874
B17: 수량(Q) | D17: 103 | E17: 175 | F17: 228 | G17: ='사업계획(매출 확정본)'!AI14 -> 476 | H17: ='사업계획(매출 확정본)'!AJ14 -> 508 | I17: ='사업계획(매출 확정본)'!AK14 -> 571 | J17: ='사업계획(매출 확정본)'!AL14 -> 579 | K17: ='사업계획(매출 확정본)'!AM14 -> 584
B18: % of growth | D18: =D17/#REF!-1 -> #REF! | E18: =E17/D17-1 -> 0.69902913 | F18: =F17/E17-1 -> 0.30285714 | G18: =G17/F17-1 -> 1.0877193 | H18: =H17/G17-1 -> 0.067226891 | I18: =I17/H17-1 -> 0.12401575 | J18: =J17/I17-1 -> 0.014010508 | K18: =K17/J17-1 -> 0.0086355786
B19: 단가(P) | D19: 51301193 | E19: 76370325 | F19: 67215532 | G19: ='사업계획(매출 확정본)'!AI15 -> 48953571 | H19: ='사업계획(매출 확정본)'!AJ15 -> 51293110 | I19: ='사업계획(매출 확정본)'!AK15 -> 60991419 | J19: ='사업계획(매출 확정본)'!AL15 -> 63300691 | K19: ='사업계획(매출 확정본)'!AM15 -> 66333390
B20: % of growth | D20: =D19/#REF!-1 -> #REF! | E20: =E19/D19-1 -> 0.48866567 | F20: =F19/E19-1 -> -0.11987369 | G20: =G19/F19-1 -> -0.27169257 | H20: =H19/G19-1 -> 0.047790973 | I20: =I19/H19-1 -> 0.18907624 | J20: =J19/I19-1 -> 0.037862249 | K20: =K19/J19-1 -> 0.047909423
B21: 통신향 매출 | D21: =D24*D26 -> 24950094631 | E21: =E24*E26 -> 25586392091 | F21: =F24*F26 -> 3.0798914e+10 | G21: =G24*G26 -> 21847000000 | H21: =H24*H26 -> 30808300000 | I21: =I24*I26 -> 39199100000 | J21: =J24*J26 -> 43024100000 | K21: =K24*K26 -> 46856200000
B22: % of growth | D22: =D21/#REF!-1 -> #REF! | E22: =E21/D21-1 -> 0.025502807 | F22: =F21/E21-1 -> 0.20372245 | G22: =G21/F21-1 -> -0.29065682 | H22: =H21/G21-1 -> 0.41018446 | I22: =I21/H21-1 -> 0.27235518 | J22: =J21/I21-1 -> 0.097578771 | K22: =K21/J21-1 -> 0.089068685
B23: % of 국내 Sales | D23: =D21/D$6 -> 0.40263684 | E23: =E21/E$6 -> 0.3139888 | F23: =F21/F$6 -> 0.33355997 | G23: =G21/G$6 -> 0.14611844 | H23: =H21/H$6 -> 0.1610267 | I23: =I21/I$6 -> 0.1591715 | J23: =J21/J$6 -> 0.15789751
B24: 수량(Q) | D24: 642 | E24: 704 | F24: 841 | G24: ='사업계획(매출 확정본)'!AI17 -> 606 | H24: ='사업계획(매출 확정본)'!AJ17 -> 782 | I24: ='사업계획(매출 확정본)'!AK17 -> 939 | J24: ='사업계획(매출 확정본)'!AL17 -> 981 | K24: ='사업계획(매출 확정본)'!AM17 -> 1018
B25: % of growth | D25: =D24/#REF!-1 -> #REF! | E25: =E24/D24-1 -> 0.096573209 | F25: =F24/E24-1 -> 0.19460227 | G25: =G24/F24-1 -> -0.27942925 | H25: =H24/G24-1 -> 0.29042904 | I25: =I24/H24-1 -> 0.20076726 | J25: =J24/I24-1 -> 0.044728435 | K25: =K24/J24-1 -> 0.037716616
B26: 단가(P) | D26: 38863076 | E26: 36344307 | F26: 36621777 | G26: ='사업계획(매출 확정본)'!AI18 -> 36051155 | H26: ='사업계획(매출 확정본)'!AJ18 -> 39396803 | I26: ='사업계획(매출 확정본)'!AK18 -> 41745580 | J26: ='사업계획(매출 확정본)'!AL18 -> 43857390 | K26: ='사업계획(매출 확정본)'!AM18 -> 46027701
B27: % of growth | D27: =D26/#REF!-1 -> #REF! | E27: =E26/D26-1 -> -0.06481136 | F27: =F26/E26-1 -> 0.0076344854 | G27: =G26/F26-1 -> -0.015581492 | H27: =H26/G26-1 -> 0.092802795 | I27: =I26/H26-1 -> 0.059618475 | J27: =J26/I26-1 -> 0.050587631 | K27: =K26/J26-1 -> 0.049485638
B28: 건설향 매출 | D28: =D31*D33 -> 646664227 | E28: =E31*E33 -> 539003454 | F28: =F31*F33 -> 3.7379489e+08 | G28: =G31*G33 -> 0 | H28: =H31*H33 -> 0 | I28: =I31*I33 -> 0 | J28: =J31*J33 -> 0 | K28: =K31*K33 -> 0
B29: % of growth | D29: =D28/#REF!-1 -> #REF! | E29: =E28/D28-1 -> -0.16648636 | F29: =F28/E28-1 -> -0.30650743 | G29: =G28/F28-1 -> -1 | H29: =H28/G28-1 -> #DIV/0! | I29: =I28/H28-1 -> #DIV/0! | J29: =J28/I28-1 -> #DIV/0! | K29: =K28/J28-1 -> #DIV/0!
B30: % of 국내 Sales | D30: =D28/D$6 -> 0.010435665 | E30: =E28/E$6 -> 0.0066144945 | F30: =F28/F$6 -> 0.0040482924 | G30: =G28/G$6 -> 0 | H30: =H28/H$6 -> 0 | I30: =I28/I$6 -> 0 | J30: =J28/J$6 -> 0
B31: 수량(Q) | D31: 32 | E31: 20 | F31: 28 | G31: ='사업계획(매출 확정본)'!AI23 -> 0 | H31: ='사업계획(매출 확정본)'!AJ23 -> 0 | I31: ='사업계획(매출 확정본)'!AK23 -> 0 | J31: ='사업계획(매출 확정본)'!AL23 -> 0 | K31: ='사업계획(매출 확정본)'!AM23 -> 0
B32: % of growth | D32: =D31/#REF!-1 -> #REF! | E32: =E31/D31-1 -> -0.375 | F32: =F31/E31-1 -> 0.4 | G32: =G31/F31-1 -> -1 | H32: =H31/G31-1 -> #DIV/0! | I32: =I31/H31-1 -> #DIV/0! | J32: =J31/I31-1 -> #DIV/0! | K32: =K31/J31-1 -> #DIV/0!
B33: 단가(P) | D33: 20208257 | E33: 26950173 | F33: 13349818 | G33: =IFERROR('사업계획(매출 확정본)'!AI24,) -> 0 | H33: =IFERROR('사업계획(매출 확정본)'!AJ24,) -> 0 | I33: =IFERROR('사업계획(매출 확정본)'!AK24,) -> 0 | J33: =IFERROR('사업계획(매출 확정본)'!AL24,) -> 0 | K33: =IFERROR('사업계획(매출 확정본)'!AM24,) -> 0
B34: % of growth | D34: =D33/#REF!-1 -> #REF! | E34: =E33/D33-1 -> 0.33362182 | F34: =F33/E33-1 -> -0.50464816 | G34: =G33/F33-1 -> -1 | H34: =H33/G33-1 -> #DIV/0! | I34: =I33/H33-1 -> #DIV/0! | J34: =J33/I33-1 -> #DIV/0! | K34: =K33/J33-1 -> #DIV/0!
B35: 관공서향 매출 | D35: =D38*D40 -> 354477627 | E35: =E38*E40 -> 195693637 | F35: =F38*F40 -> 361498664 | G35: =G38*G40 -> 554400000 | H35: =H38*H40 -> 970000000 | I35: =I38*I40 -> 1528500000 | J35: =J38*J40 -> 2140000000 | K35: =K38*K40 -> 2810000000
B36: % of growth | D36: =D35/#REF!-1 -> #REF! | E36: =E35/D35-1 -> -0.44793797 | F36: =F35/E35-1 -> 0.84726836 | G36: =G35/F35-1 -> 0.53361563 | H36: =H35/G35-1 -> 0.74963925 | I36: =I35/H35-1 -> 0.5757732 | J36: =J35/I35-1 -> 0.40006542 | K36: =K35/J35-1 -> 0.31308411
B37: % of 국내 Sales | D37: =D35/D$6 -> 0.0057204493 | E37: =E35/E$6 -> 0.0024014957 | F37: =F35/F$6 -> 0.0039151212 | G37: =G35/G$6 -> 0.0037079719 | H37: =H35/H$6 -> 0.0050699291 | I37: =I35/I$6 -> 0.006206613 | J37: =J35/J$6 -> 0.0078537532
B38: 수량(Q) | D38: 7 | E38: 2 | F38: 6 | G38: ='사업계획(매출 확정본)'!AI20 -> 6 | H38: ='사업계획(매출 확정본)'!AJ20 -> 10 | I38: ='사업계획(매출 확정본)'!AK20 -> 15 | J38: ='사업계획(매출 확정본)'!AL20 -> 20 | K38: ='사업계획(매출 확정본)'!AM20 -> 25
B39: % of growth | D39: =D38/#REF!-1 -> #REF! | E39: =E38/D38-1 -> -0.71428571 | F39: =F38/E38-1 -> 2 | G39: =G38/F38-1 -> 0 | H39: =H38/G38-1 -> 0.66666667 | I39: =I38/H38-1 -> 0.5 | J39: =J38/I38-1 -> 0.33333333 | K39: =K38/J38-1 -> 0.25
B40: 단가(P) | D40: 50639661 | E40: 97846818 | F40: 60249777 | G40: ='사업계획(매출 확정본)'!AI21 -> 92400000 | H40: ='사업계획(매출 확정본)'!AJ21 -> 97000000 | I40: ='사업계획(매출 확정본)'!AK21 -> 101900000 | J40: ='사업계획(매출 확정본)'!AL21 -> 107000000 | K40: ='사업계획(매출 확정본)'!AM21 -> 112400000
B41: % of growth | D41: =D40/#REF!-1 -> #REF! | E41: =E40/D40-1 -> 0.93221709 | F41: =F40/E40-1 -> -0.38424388 | G41: =G40/F40-1 -> 0.53361563 | H41: =H40/G40-1 -> 0.04978355 | I41: =I40/H40-1 -> 0.050515464 | J41: =J40/I40-1 -> 0.050049068 | K41: =K40/J40-1 -> 0.05046729
B42: 항공향 매출 | D42: =D45*D47 -> 642928745 | E42: =E45*E47 -> 5572727 | F42: =F45*F47 -> 13954545 | G42: =IFERROR(G45*G47,0) -> 0 | H42: =IFERROR(H45*H47,0) -> 0 | I42: =IFERROR(I45*I47,0) -> 0 | J42: =IFERROR(J45*J47,0) -> 0 | K42: =K45*K47 -> 0
B43: % of growth | D43: =D42/#REF!-1 -> #REF! | E43: =E42/D42-1 -> -0.99133228 | F43: =F42/E42-1 -> 1.5040783 | G43: =G42/F42-1 -> -1 | H43: =H42/G42-1 -> #DIV/0! | I43: =I42/H42-1 -> #DIV/0! | J43: =J42/I42-1 -> #DIV/0! | K43: =K42/J42-1 -> #DIV/0!
B44: % of 국내 Sales | D44: =D42/D$6 -> 0.010375383 | E44: =E42/E$6 -> 6.8386894e-05 | F44: =F42/F$6 -> 0.00015113122 | G44: =G42/G$6 -> 0 | H44: =H42/H$6 -> 0 | I44: =I42/I$6 -> 0 | J44: =J42/J$6 -> 0
B45: 수량(Q) | D45: 1 | E45: 1 | F45: 1 | G45: ='사업계획(매출 확정본)'!AI26 -> 0 | H45: ='사업계획(매출 확정본)'!AJ26 -> 0 | I45: ='사업계획(매출 확정본)'!AK26 -> 0 | J45: ='사업계획(매출 확정본)'!AL26 -> 0 | K45: =IFERROR('사업계획(매출 확정본)'!AM27,0) -> 0
B46: % of growth | D46: =D45/#REF!-1 -> #REF! | E46: =E45/D45-1 -> 0 | F46: =F45/E45-1 -> 0 | G46: =G45/F45-1 -> -1 | H46: =H45/G45-1 -> #DIV/0! | I46: =I45/H45-1 -> #DIV/0! | J46: =J45/I45-1 -> #DIV/0! | K46: =K45/J45-1 -> #DIV/0!
B47: 단가(P) | D47: 642928745 | E47: 5572727 | F47: 13954545 | G47: ='사업계획(매출 확정본)'!AI27 -> #DIV/0! | H47: ='사업계획(매출 확정본)'!AJ27 -> #DIV/0! | I47: ='사업계획(매출 확정본)'!AK27 -> #DIV/0! | J47: ='사업계획(매출 확정본)'!AL27 -> #DIV/0!
B48: % of growth | D48: =D47/#REF!-1 -> #REF! | E48: =E47/D47-1 -> -0.99133228 | F48: =F47/E47-1 -> 1.5040783 | G48: =G47/F47-1 -> #DIV/0! | H48: =H47/G47-1 -> #DIV/0! | I48: =I47/H47-1 -> #DIV/0! | J48: =J47/I47-1 -> #DIV/0! | K48: =K47/J47-1 -> #DIV/0!
B49: 기타 매출 | D49: =D52*D54 -> 2438807274 | E49: =E52*E54 -> 1229971252 | F49: =F52*F54 -> 1790336910 | G49: =G52*G54 -> 3337500000 | H49: =H52*H54 -> 4766500000 | I49: =I52*I54 -> 6.5395e+09 | J49: =J52*J54 -> 7817000000 | K49: =K52*K54 -> 8587000000
B50: % of growth | D50: =D49/#REF!-1 -> #REF! | E50: =E49/D49-1 -> -0.49566689 | F50: =F49/E49-1 -> 0.45559248 | G50: =G49/F49-1 -> 0.86417427 | H50: =H49/G49-1 -> 0.42816479 | I50: =I49/H49-1 -> 0.37197105 | J50: =J49/I49-1 -> 0.19535133 | K50: =K49/J49-1 -> 0.098503262
B51: % of 국내 Sales | D51: =D49/D$6 -> 0.039356711 | E51: =E49/E$6 -> 0.015093851 | F51: =F49/F$6 -> 0.019389798 | G51: =G49/G$6 -> 0.022322071 | H51: =H49/H$6 -> 0.024913213 | I51: =I49/I$6 -> 0.026554233 | J51: =J49/J$6 -> 0.028688219
B52: 수량(Q) | D52: 22 | E52: 23 | F52: 34 | G52: ='사업계획(매출 확정본)'!AI29 -> 53 | H52: ='사업계획(매출 확정본)'!AJ29 -> 70 | I52: ='사업계획(매출 확정본)'!AK29 -> 90 | J52: ='사업계획(매출 확정본)'!AL29 -> 105 | K52: ='사업계획(매출 확정본)'!AM29 -> 110
B53: % of growth | D53: =D52/#REF!-1 -> #REF! | E53: =E52/D52-1 -> 0.045454545 | F53: =F52/E52-1 -> 0.47826087 | G53: =G52/F52-1 -> 0.55882353 | H53: =H52/G52-1 -> 0.32075472 | I53: =I52/H52-1 -> 0.28571429 | J53: =J52/I52-1 -> 0.16666667 | K53: =K52/J52-1 -> 0.047619048
B54: 단가(P) | D54: 1.1085488e+08 | E54: 53477011 | F54: 52656968 | G54: ='사업계획(매출 확정본)'!AI30 -> 62971698 | H54: ='사업계획(매출 확정본)'!AJ30 -> 68092857 | I54: ='사업계획(매출 확정본)'!AK30 -> 72661111 | J54: ='사업계획(매출 확정본)'!AL30 -> 74447619 | K54: ='사업계획(매출 확정본)'!AM30 -> 78063636
B56: 크레인 | D56: =D60+D66+D72+D78+D84+D90 -> 870979546 | E56: =E60+E66+E72+E78+E84+E90 -> 20781154581 | F56: =F60+F66+F72+F78+F84+F90 -> 3467312078 | G56: =G60+G66+G72+G78+G84+G90 -> 9332000000 | H56: =H60+H66+H72+H78+H84+H90 -> 13558000000 | I56: =I60+I66+I72+I78+I84+I90 -> 19319500000 | J56: =J60+J66+J72+J78+J84+J90 -> 22827900000 | K56: =K60+K66+K72+K78+K84+K90 -> 25928000000
B57: % of growth | D57: =D56/#REF!-1 -> #REF! | E57: =E56/D56-1 -> 22.859521 | F57: =F56/E56-1 -> -0.83315113 | G57: =G56/F56-1 -> 1.691422 | H57: =H56/G56-1 -> 0.45285041 | I57: =I56/H56-1 -> 0.42495206 | J57: =J56/I56-1 -> 0.1815989 | K57: =K56/J56-1 -> 0.13580312
B58: % of sales | D58: =D56/D$6 -> 0.014055596 | E58: =E56/E$6 -> 0.25502032 | F58: =F56/F$6 -> 0.037551859 | G58: =G56/G$6 -> 0.062414851 | H58: =H56/H$6 -> 0.070864019 | I58: =I56/I$6 -> 0.078448583 | J58: =J56/J$6 -> 0.083777894
B60: 전기향 매출 | D60: =D62*D64 -> 48000000 | E60: =E62*E64 -> 7761168100 | F60: =F62*F64 -> 1091440918 | G60: =G62*G64 -> 270000000 | H60: =H62*H64 -> 709000000 | I60: =I62*I64 -> 1489000000 | J60: =J62*J64 -> 2031900000 | K60: =K62*K64 -> 2461500000
B61: % of growth | D61: =D60/#REF!-1 -> #REF! | E61: =E60/D60-1 -> 160.691 | F61: =F60/E60-1 -> -0.85937157 | G61: =G60/F60-1 -> -0.7526206 | H61: =H60/G60-1 -> 1.6259259 | I61: =I60/H60-1 -> 1.100141 | J61: =J60/I60-1 -> 0.36460712 | K61: =K60/J60-1 -> 0.21142773
B62: 수량(Q) | D62: 2 | E62: 82 | F62: 11 | G62: ='사업계획(매출 확정본)'!AI32 -> 2 | H62: ='사업계획(매출 확정본)'!AJ32 -> 5 | I62: ='사업계획(매출 확정본)'!AK32 -> 10 | J62: ='사업계획(매출 확정본)'!AL32 -> 13 | K62: ='사업계획(매출 확정본)'!AM32 -> 15
B63: % of growth | D63: =D62/#REF!-1 -> #REF! | E63: =E62/D62-1 -> 40 | F63: =F62/E62-1 -> -0.86585366 | G63: =G62/F62-1 -> -0.81818182 | H63: =H62/G62-1 -> 1.5 | I63: =I62/H62-1 -> 1 | J63: =J62/I62-1 -> 0.3
B64: 단가(P) | D64: 24000000 | E64: 94648391 | F64: 99221902 | G64: ='사업계획(매출 확정본)'!AI33 -> 135000000 | H64: ='사업계획(매출 확정본)'!AJ33 -> 141800000 | I64: ='사업계획(매출 확정본)'!AK33 -> 148900000 | J64: ='사업계획(매출 확정본)'!AL33 -> 156300000 | K64: ='사업계획(매출 확정본)'!AM33 -> 164100000
B65: % of growth | D65: =D64/#REF!-1 -> #REF! | E65: =E64/D64-1 -> 2.943683 | F65: =F64/E64-1 -> 0.048321055 | G65: =G64/F64-1 -> 0.3605867 | H65: =H64/G64-1 -> 0.05037037 | I65: =I64/H64-1 -> 0.050070522 | J65: =J64/I64-1 -> 0.049697784 | K65: =K64/J64-1 -> 0.049904031
B66: 통신향 매출 | D66: =D68*D70 -> 207600000 | E66: =E68*E70 -> 12612420115 | F66: =F68*F70 -> 1646307520 | G66: =G68*G70 -> 1944000000 | H66: =H68*H70 -> 2784500000 | I66: =I68*I70 -> 4140500000 | J66: =J68*J70 -> 3585000000 | K66: =K68*K70 -> 4035000000
B67: % of growth | D67: =D66/#REF!-1 -> #REF! | E67: =E66/D66-1 -> 59.753469 | F67: =F66/E66-1 -> -0.86946934 | G67: =G66/F66-1 -> 0.18082435 | H67: =H66/G66-1 -> 0.43235597 | I67: =I66/H66-1 -> 0.4869815 | J67: =J66/I66-1 -> -0.13416254 | K67: =K66/J66-1 -> 0.12552301
B68: 수량(Q) | D68: 12 | E68: 190 | F68: 60 | G68: ='사업계획(매출 확정본)'!AI35 -> 24 | H68: ='사업계획(매출 확정본)'!AJ35 -> 35 | I68: ='사업계획(매출 확정본)'!AK35 -> 50 | J68: ='사업계획(매출 확정본)'!AL35 -> 45 | K68: ='사업계획(매출 확정본)'!AM35 -> 50
B69: % of growth | D69: =D68/#REF!-1 -> #REF! | E69: =E68/D68-1 -> 14.833333 | F69: =F68/E68-1 -> -0.68421053 | G69: =G68/F68-1 -> -0.6 | H69: =H68/G68-1 -> 0.45833333 | I69: =I68/H68-1 -> 0.42857143 | J69: =J68/I68-1 -> -0.1 | K69: =K68/J68-1 -> 0.11111111
B70: 단가(P) | D70: 17300000 | E70: 66381158 | F70: 27438459 | G70: ='사업계획(매출 확정본)'!AI36 -> 81000000 | H70: ='사업계획(매출 확정본)'!AJ36 -> 79557143 | I70: ='사업계획(매출 확정본)'!AK36 -> 82810000 | J70: ='사업계획(매출 확정본)'!AL36 -> 79666667 | K70: ='사업계획(매출 확정본)'!AM36 -> 80700000
B71: % of growth | D71: =D70/#REF!-1 -> #REF! | E71: =E70/D70-1 -> 2.8370612 | F71: =F70/E70-1 -> -0.58665291 | G71: =G70/F70-1 -> 1.9520609 | H71: =H70/G70-1 -> -0.017813051 | I71: =I70/H70-1 -> 0.040887053 | J71: =J70/I70-1 -> -0.037958379 | K71: =K70/J70-1 -> 0.012970711
B72: 건설향 매출 | D72: =IFERROR(D74*D76,0) -> 0 | E72: =IFERROR(E74*E76,0) -> 0 | F72: =IFERROR(F74*F76,0) -> 54627273 | G72: =IFERROR(G74*G76,0) -> 4590000000 | H72: =IFERROR(H74*H76,0) -> 5769500000 | I72: =IFERROR(I74*I76,0) -> 7.5385e+09 | J72: =IFERROR(J74*J76,0) -> 9027000000 | K72: =K74*K76 -> 9977000000
B73: % of growth | D73: =D72/#REF!-1 -> #REF! | E73: =E72/D72-1 -> #DIV/0! | F73: =F72/E72-1 -> #DIV/0! | G73: =G72/F72-1 -> 83.023964 | H73: =H72/G72-1 -> 0.25697168 | I73: =I72/H72-1 -> 0.30661236 | J73: =J72/I72-1 -> 0.19745307 | K73: =K72/J72-1 -> 0.10523984
B74: 수량(Q) | D74: 0 | E74: 0 | F74: 2 | G74: ='사업계획(매출 확정본)'!AI41 -> 289 | H74: ='사업계획(매출 확정본)'!AJ41 -> 335 | I74: ='사업계획(매출 확정본)'!AK41 -> 405 | J74: ='사업계획(매출 확정본)'!AL41 -> 465 | K74: ='사업계획(매출 확정본)'!AM41 -> 485
B75: % of growth | D75: =D74/#REF!-1 -> #REF! | E75: =E74/D74-1 -> #DIV/0! | F75: =F74/E74-1 -> #DIV/0! | G75: =G74/F74-1 -> 143.5 | H75: =H74/G74-1 -> 0.15916955 | I75: =I74/H74-1 -> 0.20895522 | J75: =J74/I74-1 -> 0.14814815 | K75: =K74/J74-1 -> 0.043010753
B76: 단가(P) | D76: #DIV/0! | E76: #DIV/0! | F76: 27313636 | G76: ='사업계획(매출 확정본)'!AI42 -> 15882353 | H76: ='사업계획(매출 확정본)'!AJ42 -> 17222388 | I76: ='사업계획(매출 확정본)'!AK42 -> 18613580 | J76: ='사업계획(매출 확정본)'!AL42 -> 19412903 | K76: ='사업계획(매출 확정본)'!AM42 -> 20571134
B77: % of growth | D77: =D76/#REF!-1 -> #DIV/0! | E77: =E76/D76-1 -> #DIV/0! | F77: =F76/E76-1 -> #DIV/0! | G77: =G76/F76-1 -> -0.41851928 | H77: =H76/G76-1 -> 0.084372582 | I77: =I76/H76-1 -> 0.080778123 | J77: =J76/I76-1 -> 0.042943 | K77: =K76/J76-1 -> 0.059662936
B78: 관공서향 매출 | D78: =D80*D82 -> 462526183 | E78: =E80*E82 -> 407566366 | F78: =F80*F82 -> 580436367 | G78: =G80*G82 -> 2528000000 | H78: =H80*H82 -> 4295000000 | I78: =I80*I82 -> 6151500000 | J78: =J80*J82 -> 8184000000 | K78: =K80*K82 -> 9454500000
B79: % of growth | D79: =D78/#REF!-1 -> #REF! | E79: =E78/D78-1 -> -0.11882531 | F79: =F78/E78-1 -> 0.42415178 | G79: =G78/F78-1 -> 3.3553439 | H79: =H78/G78-1 -> 0.69897152 | I79: =I78/H78-1 -> 0.4322468 | J79: =J78/I78-1 -> 0.33040722 | K79: =K78/J78-1 -> 0.15524194
B80: 수량(Q) | D80: 7 | E80: 4 | F80: 9 | G80: ='사업계획(매출 확정본)'!AI38 -> 24 | H80: ='사업계획(매출 확정본)'!AJ38 -> 40 | I80: ='사업계획(매출 확정본)'!AK38 -> 55 | J80: ='사업계획(매출 확정본)'!AL38 -> 70 | K80: ='사업계획(매출 확정본)'!AM38 -> 77
B81: % of growth | D81: =D80/#REF!-1 -> #REF! | E81: =E80/D80-1 -> -0.42857143 | F81: =F80/E80-1 -> 1.25 | G81: =G80/F80-1 -> 1.6666667 | H81: =H80/G80-1 -> 0.66666667 | I81: =I80/H80-1 -> 0.375 | J81: =J80/I80-1 -> 0.27272727
B82: 단가(P) | D82: 66075169 | E82: 1.0189159e+08 | F82: 64492930 | G82: ='사업계획(매출 확정본)'!AI39 -> 1.0533333e+08 | H82: ='사업계획(매출 확정본)'!AJ39 -> 107375000 | I82: ='사업계획(매출 확정본)'!AK39 -> 1.1184545e+08 | J82: ='사업계획(매출 확정본)'!AL39 -> 1.1691429e+08 | K82: ='사업계획(매출 확정본)'!AM39 -> 1.2278571e+08
B83: % of growth | D83: =D82/#REF!-1 -> #REF! | E83: =E82/D82-1 -> 0.54205571 | F83: =F82/E82-1 -> -0.36704365 | G83: =G82/F82-1 -> 0.63325397 | H83: =H82/G82-1 -> 0.019382911 | I83: =I82/H82-1 -> 0.041634035 | J83: =J82/I82-1 -> 0.045319957 | K83: =K82/J82-1 -> 0.050219941
B84: 항공향 매출 | D84: =IFERROR(D86*D88,0) -> 0 | E84: =IFERROR(E86*E88,0) -> 0 | F84: =IFERROR(F86*F88,0) -> 0 | G84: =IFERROR(G86*G88,0) -> 0 | H84: =IFERROR(H86*H88,0) -> 0 | I84: =IFERROR(I86*I88,0) -> 0 | J84: =IFERROR(J86*J88,0) -> 0 | K84: =K86*K88 -> 0
B85: % of growth | D85: =D84/#REF!-1 -> #REF! | E85: =E84/D84-1 -> #DIV/0! | F85: =F84/E84-1 -> #DIV/0! | G85: =G84/F84-1 -> #DIV/0! | H85: =H84/G84-1 -> #DIV/0! | I85: =I84/H84-1 -> #DIV/0! | J85: =J84/I84-1 -> #DIV/0! | K85: =K84/J84-1 -> #DIV/0!
B86: 수량(Q) | D86: 0 | E86: 0 | F86: 0 | G86: ='사업계획(매출 확정본)'!AI44 -> 0 | H86: ='사업계획(매출 확정본)'!AJ44 -> 0 | I86: ='사업계획(매출 확정본)'!AK44 -> 0 | J86: ='사업계획(매출 확정본)'!AL44 -> 0 | K86: ='사업계획(매출 확정본)'!AM44 -> 0
B87: % of growth | D87: =D86/#REF!-1 -> #REF! | E87: =E86/D86-1 -> #DIV/0! | F87: =F86/E86-1 -> #DIV/0! | G87: =G86/F86-1 -> #DIV/0! | H87: =H86/G86-1 -> #DIV/0! | I87: =I86/H86-1 -> #DIV/0! | J87: =J86/I86-1 -> #DIV/0! | K87: =K86/J86-1 -> #DIV/0!
B88: 단가(P) | D88: #DIV/0! | E88: #DIV/0! | F88: #DIV/0! | G88: ='사업계획(매출 확정본)'!AI45 -> #DIV/0! | H88: ='사업계획(매출 확정본)'!AJ45 -> #DIV/0! | I88: ='사업계획(매출 확정본)'!AK45 -> #DIV/0! | J88: ='사업계획(매출 확정본)'!AL45 -> #DIV/0!
B89: % of growth | D89: =D88/#REF!-1 -> #DIV/0! | E89: =E88/D88-1 -> #DIV/0! | F89: =F88/E88-1 -> #DIV/0! | G89: =G88/F88-1 -> #DIV/0! | H89: =H88/G88-1 -> #DIV/0! | I89: =I88/H88-1 -> #DIV/0! | J89: =J88/I88-1 -> #DIV/0! | K89: =K88/J88-1 -> #DIV/0!
B90: 기타 매출 | D90: =D92*D94 -> 152853363 | E90: =IFERROR(E92*E94,0) -> 0 | F90: =F92*F94 -> 94500000 | G90: =IFERROR(G92*G94,0) -> 0 | H90: =IFERROR(H92*H94,0) -> 0 | I90: =IFERROR(I92*I94,0) -> 0 | J90: =IFERROR(J92*J94,0) -> 0 | K90: =K92*K94 -> 0
B91: % of growth | D91: =D90/#REF!-1 -> #REF! | E91: =E90/D90-1 -> -1 | F91: =F90/E90-1 -> #DIV/0! | G91: =G90/F90-1 -> -1 | H91: =H90/G90-1 -> #DIV/0! | I91: =I90/H90-1 -> #DIV/0! | J91: =J90/I90-1 -> #DIV/0! | K91: =K90/J90-1 -> #DIV/0!
B92: 수량(Q) | D92: 8 | E92: 0 | F92: 4 | G92: ='사업계획(매출 확정본)'!AI47 -> 0 | H92: ='사업계획(매출 확정본)'!AJ47 -> 0 | I92: ='사업계획(매출 확정본)'!AK47 -> 0 | J92: ='사업계획(매출 확정본)'!AL47 -> 0 | K92: ='사업계획(매출 확정본)'!AM47 -> 0
B93: % of growth | D93: =D92/#REF!-1 -> #REF! | E93: =E92/D92-1 -> -1 | F93: =F92/E92-1 -> #DIV/0! | G93: =G92/F92-1 -> -1 | H93: =H92/G92-1 -> #DIV/0! | I93: =I92/H92-1 -> #DIV/0! | J93: =J92/I92-1 -> #DIV/0! | K93: =K92/J92-1 -> #DIV/0!
B94: 단가(P) | D94: 19106670 | E94: #DIV/0! | F94: 23625000 | G94: ='사업계획(매출 확정본)'!AI48 -> #DIV/0! | H94: ='사업계획(매출 확정본)'!AJ48 -> #DIV/0! | I94: ='사업계획(매출 확정본)'!AK48 -> #DIV/0! | J94: ='사업계획(매출 확정본)'!AL48 -> #DIV/0! | K94: =IFERROR('사업계획(매출 확정본)'!AM48,0) -> 0
B95: % of growth | D95: =D94/#REF!-1 -> #REF! | E95: =E94/D94-1 -> #DIV/0! | F95: =F94/E94-1 -> #DIV/0! | G95: =G94/F94-1 -> #DIV/0! | H95: =H94/G94-1 -> #DIV/0! | I95: =I94/H94-1 -> #DIV/0! | J95: =J94/I94-1 -> #DIV/0! | K95: =K94/J94-1 -> #DIV/0!
B97: 활선차 | D97: =D101+D107+D113+D119+D125+D131 -> 18172158093 | E97: =E101+E107+E113+E119+E125+E131 -> 1.1452487e+10 | F97: =F101+F107+F113+F119+F125+F131 -> 2.6083747e+10 | G97: =G101+G107+G113+G119+G125+G131 -> 41420000000 | H97: =H101+H107+H113+H119+H125+H131 -> 5.00145e+10 | I97: =I101+I107+I113+I119+I125+I131 -> 5.93215e+10 | J97: =J101+J107+J113+J119+J125+J131 -> 6.53775e+10 | K97: =K101+K107+K113+K119+K125+K131 -> 68774000000
B98: % of growth | D98: =D97/#REF!-1 -> #REF! | E98: =E97/D97-1 -> -0.36977839 | F98: =F97/E97-1 -> 1.2775619 | G98: =G97/F97-1 -> 0.58796201 | H98: =H97/G97-1 -> 0.20749638 | I98: =I97/H97-1 -> 0.18608604 | J98: =J97/I97-1 -> 0.10208778 | K98: =K97/J97-1 -> 0.051952124
B99: % of sales | D99: =D97/D$6 -> 0.29325661 | E99: =E97/E$6 -> 0.14054161 | F99: =F97/F$6 -> 0.28249352 | G99: =G97/G$6 -> 0.27702777 | H99: =H97/H$6 -> 0.26141234 | I99: =I97/I$6 -> 0.24088033 | J99: =J97/J$6 -> 0.239934
B101: 전기향 매출 | D101: =D103*D105 -> 1.5758238e+10 | E101: =E103*E105 -> 8405540909 | F101: =F103*F105 -> 24091419998 | G101: =G103*G105 -> 41420000000 | H101: =H103*H105 -> 5.00145e+10 | I101: =I103*I105 -> 5.93215e+10 | J101: =J103*J105 -> 6.53775e+10 | K101: =K103*K105 -> 68774000000
B102: % of growth | D102: =D101/#REF!-1 -> #REF! | E102: =E101/D101-1 -> -0.46659387 | F102: =F101/E101-1 -> 1.8661356 | G102: =G101/F101-1 -> 0.71928429 | H102: =H101/G101-1 -> 0.20749638 | I102: =I101/H101-1 -> 0.18608604 | J102: =J101/I101-1 -> 0.10208778 | K102: =K101/J101-1 -> 0.051952124
B103: 수량(Q) | D103: 108 | E103: 50 | F103: 155 | G103: ='사업계획(매출 확정본)'!AI50 -> 260 | H103: ='사업계획(매출 확정본)'!AJ50 -> 305 | I103: ='사업계획(매출 확정본)'!AK50 -> 345 | J103: ='사업계획(매출 확정본)'!AL50 -> 365 | K103: ='사업계획(매출 확정본)'!AM50 -> 370
B104: % of growth | D104: =D103/#REF!-1 -> #REF! | E104: =E103/D103-1 -> -0.53703704 | F104: =F103/E103-1 -> 2.1 | G104: =G103/F103-1 -> 0.67741935 | H104: =H103/G103-1 -> 0.17307692 | I104: =I103/H103-1 -> 0.13114754 | J104: =J103/I103-1 -> 0.057971014
B105: 단가(P) | D105: 1.4590961e+08 | E105: 1.6811082e+08 | F105: 1.5542852e+08 | G105: ='사업계획(매출 확정본)'!AI51 -> 1.5930769e+08 | H105: ='사업계획(매출 확정본)'!AJ51 -> 1.6398197e+08 | I105: ='사업계획(매출 확정본)'!AK51 -> 1.7194638e+08 | J105: ='사업계획(매출 확정본)'!AL51 -> 1.7911644e+08 | K105: ='사업계획(매출 확정본)'!AM51 -> 1.8587568e+08
...

Sheet Sheet4
A1: 전표번호 | B1: 적요 | C1: 거래처 | D1: 차변 | E1: 대변 | F1: 잔액
A2: 13 | B2: DHS 950L | C2: 선일정보통신 | E2: 36883000 | F2: 36883000
A3: 13 | B3: DHS 950L | C3: (주)애플파워 | E3: 38000000 | F3: 74883000
A4: 13 | B4: DHS 433L | C4: 부여군청 | E4: 12864000 | F4: 87747000
A5: 13 | B5: DHS 950L | C5: 제이에이치정보통신 | E5: 38500000 | F5: 126247000
A6: 13 | B6: DHS433L | C6: 대영 | E6: 13000000 | F6: 139247000
A7: 13 | B7: DHS 1200L | C7: (주)피닉스정보통신 | E7: 41870000 | F7: 181117000
A8: 13 | B8: DHS 433L | C8: (주)태진코리아 | E8: 12880000 | F8: 193997000
A9: 13 | B9: DHS 950L | C9: (유)나노정보통신 | E9: 41818189 | F9: 235815189
A10: 13 | B10: DHS 1200L | C10: (주)세인전력 | E10: 40300000 | F10: 1.5820759e+08
A11: 13 | B11: DHS 1200L | C11: (주)세인전력 | E11: 40300000 | F11: 1.5820759e+08
A12: 13 | B12: 탐헤드 턴 실린더 외 | C12: (주)한진디엔비 | E12: 51580000 | F12: 367995189
A13: 13 | B13: DHS 950L | C13: (유)나노정보통신 | E13: -41818182 | F13: 326177007
... A62: 13 | B62: DHS 1200L | C62: (주)뉴젠스 | E62: 41497000 | F62: 2473939812
A63: 13 | B63: DHS 433L | C63: (주)동해기계항공 | E63: 11603520
A64: 13 | B64: DHS 433L | C64: (주)동해기계항공 | E64: 11603520
A65: 13 | B65: DHS 1800 | C65: (주)동해기계항공 | E65: 36995264 | F65: 2534142116
A66: 13 | B66: DHS 433L | C66: 클린E＆T | E66: 15700000 | F66: 2549842116
A67: 13 | B67: DHS 950L | C67: 다성정보통신 | E67: 38454545 | F67: 2588296661
A68: 13 | B68: DHS 1200L | C68: 삼성디지컴(주) | E68: 41272727 | F68: 2629569388
A69: 13 | B69: DHS 950L | C69: (주)제주네트웍스 | E69: 42727273 | F69: 2672296661
A70: 13 | B70: DHS 950L | C70: 케이피정보통신 | E70: 37727273 | F70: 2710023934
A71: 13 | B71: DHS 950L | C71: (주)아미넷 | E71: 37220000 | F71: 2747243934
A72: 13 | B72: DHS 870 | C72: (주)아미넷 | E72: 35820000 | F72: 2783063934
A73: 13 | B73: DHS 1200L | C73: (주)아진전설 | E73: 44547000 | F73: 2827610934
A74: 13 | B74: DHS 433L | C74: 코오롱워터앤에너지(주) | E74: 13700000 | F74: 2841310934
A75: 13 | B75: DHS 950L | C75: (주)카이젠 | E75: 36483000 | F75: 2877793934
A76: 13 | B76: S3000 | C76: (주)한진디엔비 | E76: 19000000 | F76: 2896793934
... A882: 13 | B882: DHS 105AP | C882: 미래통신 | E882: 39000000 | F882: 32125375450
C884: 거래처 | D884: 차변 | E884: 대변
B885: DHS 950L | E885: 4865982374
B886: DHS 1200L | E886: 3364552525
B887: DHS 15AP | E887: 3352077865
B888: DHS 105AP | E888: 3254377266
B889: DHS 930 | E889: 1515999183
B890: DHS 433L | E890: 1383420902
B891: DHS 17AP | E891: 1303240910
B892: DHT 145S | E892: 1218887274
B893: DHS 185SKY | E893: 901290909
B894: DHS 433M | E894: 853998274
B895: 크레인대금 | E895: 820565302
B896: DHT 145AS | E896: 611000000
... B1010: DHT 45S | E1010: -133000000

Sheet Sheet5
A1: 전표번호 | B1: 적요 | C1: 거래처 | D1: 차변 | E1: 대변 | F1: 잔액
A2: 16 | B2: DHS 534 | C2: 전북마린 | E2: 13545455 | F2: 206288303394
A3: 16 | B3: DHS 433L | C3: 전북마린 | E3: -13545455 | F3: 206274757939
A4: 16 | B4: DHS 433L | C4: 전북마린 | E4: 13545455 | F4: 206288303394
A5: 16 | B5: DHT 170AS | C5: 대흥활선 | E5: 202000000 | F5: 206274757939
A6: 16 | B6: DHS 534MAP | C6: (주)에이스정보통신 | E6: 30909090 | F6: 206072757939
A7: 16 | B7: DHS 1200L | C7: 형제전기통신 | E7: 41000000 | F7: 206041848849
A8: 16 | B8: DHS 930 | C8: 원테크 | E8: 35500000 | F8: 206000848849
A9: 16 | B9: DHT 160AS | C9: 유진활선 | E9: 171950000 | F9: 205965348849
A10: 16 | B10: DHS 950L | C10: (주)하이네트웍 | E10: 18373000 | F10: 205793398849
A11: 16 | B11: DHS 1200L | C11: 오성전력(주) | E11: 40000000 | F11: 205775025849
A12: 16 | B12: DHS 950L | C12: NS정보통신 | E12: 37500000 | F12: 205735025849
A13: 16 | B13: DHS 130SKY | C13: (유)비츠 | E13: 42900000 | F13: 205697525849
... A1464: 16 | B1464: DHS 950L | C1464: 주식회사 수길정보통신 | E1464: 34000000 | F1464: 128197271378
C1466: 거래처 | D1466: 차변 | E1466: 대변
B1467: DHS 950L | E1467: 13249563649
B1468: DHT 105S | E1468: 7719099100
B1469: DHS 1200L | E1469: 6357136815
B1470: DHS 15AP | E1470: 5588614966
B1471: DH SUPER 3000A | E1471: 5584328840
B1472: DHT 160AS | E1472: 4800950000
B1473: DHS 930 | E1473: 4571621271
B1474: DHT 150S | E1474: 3934604545
B1475: DH S3000A | E1475: 3454999968
B1476: DHT 150AS | E1476: 3137409091
B1477: DHT 160S | E1477: 2810677273
B1478: DHS 433L | E1478: 2703566366
... B1554: Limit sensor for boom rest bracket외 | E1554: 605901

Sheet Sheet3
A1: 전표번호 | B1: 적요 | C1: 거래처 | D1: 차변 | E1: 대변 | F1: 잔액
A2: 17 | B2: DHS 1200L | C2: (주)윈투스시스템 | E2: 43500000 | F2: 294718098500
A3: 17 | B3: DHS 15AP | C3: (주)연성 | E3: 52727272 | F3: 294674598500
A4: 17 | B4: DHS 15AP | C4: 선우기업 | E4: 50909090 | F4: 294621871228
A5: 17 | B5: DHS 190SKY | C5: 신림전기 | E5: 61090909 | F5: 294570962138
A6: 17 | B6: DHS 950L | C6: 탑 에이치 정보통신 | E6: 36363637 | F6: 294509871229
A7: 17 | B7: DHS 930 | C7: 지성텔레콤 | E7: 19700000 | F7: 294473507592
A8: 17 | B8: DHS 1200L | C8: 주식회사 중부케이블 | E8: 39090909 | F8: 294453807592
A9: 17 | B9: DHS 1200L | C9: 주식회사 중부케이블 | E9: 39090909 | F9: 294414716683
A10: 17 | B10: DHS 1200L | C10: 주식회사 중부케이블 | E10: 39090909 | F10: 294375625774
A11: 17 | B11: DHS 1200L | C11: 주식회사 중부케이블 | E11: 39090909 | F11: 294336534865
A12: 17 | B12: DHS 15AP | C12: 태성전력 주식회사 | E12: 53000000 | F12: 294297443956
A13: 17 | B13: DHS 17AP | C13: 반도전기 | E13: 56900000 | F13: 294244443956
... A70: 17 | B70: DHT 150S | C70: WAIMEA TRUCK ＆ CRANE LTD | E70: 89306200 | F70: 289260536613
A71: 17 | B71: DHT 150AS | C71: WAIMEA TRUCK ＆ CRANE LTD | E71: 106830908
A72: 17 | B72: DHS 1200L | C72: 제이통신 | E72: 40909091 | F72: 289064399505
A73: 17 | B73: DHS 1200L | C73: 제CI통신 | E73: -40909091 | F73: 289023490414
A74: 17 | B74: DHS 303 | C74: 완도군청 | E74: 17727273 | F74: 289064399505
A75: 17 | B75: DHS 1200L | C75: 드림네트웍스(주) | E75: 42454545 | F75: 289046672232
A76: 17 | B76: DHS 1200L | C76: 드림네트웍스(주) | E76: 42454545 | F76: 289004217687
A77: 17 | B77: DHS 17AP | C77: 대운산전 | E77: 54500000 | F77: 288961763142
A78: 17 | B78: DHS 15AP | C78: (주)건보전기 | E78: 52000000 | F78: 288907263142
A79: 17 | B79: DHS 1200L | C79: 제CI통신 | E79: 40909091 | F79: 288855263142
A80: 17 | B80: DHS 534MAP | C80: 주식회사 바른네트워크 | E80: 31000000 | F80: 288814354051
A81: 17 | B81: DHS 1200L | C81: 코라인이엔티(주) | E81: 43700000 | F81: 288783354051
A82: 17 | B82: DHS 1200L | C82: 코라인이엔티(주) | E82: 43700000 | F82: 288739654051
A83: 17 | B83: DHS 1200L | C83: 코라인이엔티(주) | E83: 43700000 | F83: 288695954051
... A133: 17 | B133: DHS 14 | C133: WAIMEA TRUCK ＆ CRANE LTD | E133: 68487300 | F133: 285956141866
A134: 17 | B134: DHT 150S | C134: WAIMEA TRUCK ＆ CRANE LTD | E134: 91316400
A135: 17 | B135: DHS 950L | C135: 현정보통신 | E135: 38500000 | F135: 285796338166
A136: 17 | B136: DHS 1200L | C136: 한빛통신주식회사 | E136: 41000000 | F136: 285757838166
A137: 17 | B137: DHS 1200L | C137: 대신네트웍스 주식회사 | E137: 42181818 | F137: 285716838166
A138: 17 | B138: DHS 1200L | C138: 신우정보통신(주) | E138: 40000000 | F138: 285674656348
A139: 17 | B139: DHS 930 | C139: 하이눈정보통신 | E139: 36700000 | F139: 285634656348
A140: 17 | B140: DHS 190SKY | C140: 안정심 | E140: 59090910 | F140: 285597956348
A141: 17 | B141: DHS 1200L | C141: IK(아이케이) | E141: 42000000 | F141: 285538865438
A142: 17 | B142: DHT 160AS | C142: 신승전기주식회사 | E142: 177000000 | F142: 285496865438
A143: 17 | B143: DHS 920 | C143: 인천광역시연수구청 | E143: 44400000 | F143: 285319865438
A144: 17 | B144: DHS 1200L | C144: 주식회사 바른네트워크 | E144: 41818182 | F144: 285275465438
A145: 17 | B145: DHS 930 | C145: 은성통신 | E145: 36363637 | F145: 285233647256
A146: 17 | B146: DHS 950L | C146: 주식회사새빛넷 | E146: 37000000 | F146: 285197283619
... A285: 17 | B285: DHT 150AS-3unit | C285: MIESCOR CO. | E285: 502149915 | F285: 278065490971
A286: 17 | B286: DHS 280AP | C286: MIESCOR CO. | E286: 131898270
A287: 17 | B287: DHS 190SKY | C287: 최석원 | E287: 58218181 | F287: 277431442786
A288: 17 | B288: DHS 190SKY | C288: 현민써비스 | E288: 62000000 | F288: 277373224605
A289: 17 | B289: DHS 130SKY | C289: 주식회사 영도정보통신 | E289: 42000000 | F289: 277311224605
A290: 17 | B290: DHS 17AP | C290: 금강전력 | E290: 55000000 | F290: 277269224605
A291: 17 | B291: DHS 17AP | C291: 진우산전주식회사 | E291: 54500000 | F291: 277214224605
A292: 17 | B292: DHS 1200L | C292: 주식회사 에스디에스테크놀로지 | E292: 41818182 | F292: 277159724605
A293: 17 | B293: DHS 950L | C293: 심철현 | E293: 37000000 | F293: 277117906423
A294: 17 | B294: DHS 950L | C294: (주)정진건설 | E294: 37000000 | F294: 277080906423
A295: 17 | B295: DHT 160S | C295: 장원화물 | E295: 161000000 | F295: 277043906423
A296: 17 | B296: DHS 950L | C296: SH정보통신 | E296: 36500000 | F296: 276882906423
A297: 17 | B297: DHS 17AP | C297: 명성전기통신 | E297: 56000000 | F297: 276846406423
A298: 17 | B298: DHS 950L | C298: 한결미디어 | E298: 38400000 | F298: 276790406423
... A539: 17 | B539: DHT 180AS | C539: XIAMEN C＆DCOMMUNICATION LTD | E539: 89906684 | F539: 263886241223
A540: 17 | B540: DHAS 120AP | C540: XIAMEN C＆DCOMMUNICATION LTD | E540: 16097844
A541: 17 | B541: BKA-14,MA-1A 감시시스템 구축작업 | C541: 공군제20전투비행단 | E541: 8636363 | F541: 263780236695
A542: 17 | B542: DHS 17AP | C542: 청평전력공사 | E542: 53636363 | F542: 263771600332
A543: 17 | B543: DHS 15AP | C543: 주식회사 화승전력 | E543: 51818182 | F543: 263717963969
A544: 17 | B544: DHS 15AP | C544: 주식회사라인이엔지 | E544: 51818182 | F544: 263666145787
A545: 17 | B545: DHS 950L | C545: 세훈통신 | E545: 38000000 | F545: 263614327605
A546: 17 | B546: DHS 534MAP | C546: (주)대경기전 | E546: 30713000 | F546: 263576327605
A547: 17 | B547: DHS 930 | C547: 수윤통신 | E547: 35909091 | F547: 263545614605
A548: 17 | B548: DHS 534 | C548: (유)일도엔지니어링 | E548: 14000000 | F548: 263509705514
A549: 17 | B549: DHS 950L | C549: 동남전기통신(주) | E549: 37000000 | F549: 263495705514
A550: 17 | B550: DHS 950L | C550: 유진정보통신(주) | E550: 37000000 | F550: 263458705514
A551: 17 | B551: DHS 15AP | C551: 세명전기(주) | E551: 52500000 | F551: 263421705514
A552: 17 | B552: DHS 950L | C552: 다온통신 | E552: 38400000 | F552: 263369205514
... A957: 17 | B957: DHT 150S | C957: WAIMEA TRUCK ＆ CRANE LTD | E957: 91602200 | F957: 242321075846
A958: 17 | B958: DHT 160AS | C958: WAIMEA TRUCK ＆ CRANE LTD | E958: 118312061
A959: 17 | B959: DHS 15AP | C959: 효은기업 | E959: 51818182 | F959: 242111161585
A960: 17 | B960: DHS 950L | C960: 진텔콤 | E960: 38000000 | F960: 242059343403
A961: 17 | B961: DHS 950L | C961: 제이에스정보통신 | E961: 38181818 | F961: 242021343403
A962: 17 | B962: DHS 950L | C962: 제이엠제이정보 | E962: 38000000 | F962: 241983161585
A963: 17 | B963: DHS 534 | C963: 노화청해마린 | E963: 14000000 | F963: 241945161585
A964: 17 | B964: DHS 433L | C964: 동광크랑크공업 | E964: 14090909 | F964: 241931161585
A965: 17 | B965: DHS 534MAP | C965: 가가이지텍(주) | E965: 32727273 | F965: 241917070676
A966: 17 | B966: DHS 15AP | C966: 대한전기,조명판매장 | E966: 51000000 | F966: 241884343403
A967: 17 | B967: DHS 15AP | C967: 보광안전 | E967: 51818181 | F967: 241833343403
A968: 17 | B968: DHS 950L | C968: 너구리통신 | E968: 36363636 | F968: 241781525222
A969: 17 | B969: DHS 534 | C969: 무열농장 | E969: 15181818 | F969: 241745161586
A970: 17 | B970: DHS 950L | C970: 미진통신 | E970: 38500000 | F970: 241729979768
... A1232: 17 | B1232: DHS 17AP | C1232: RURAL ELECTRIFICATION TRADING CORPORATION | E1232: 50278285 | F1232: 225469720615
A1233: 17 | B1233: DHS 15AP | C1233: RURAL ELECTRIFICATION TRADING CORPORATION | E1233: 46378349
A1234: 17 | B1234: DHS 950L | C1234: NINOX S.A.S | E1234: 17084140 | F1234: 225373063981
A1235: 17 | B1235: DHT 160S | C1235: 화정중기 | E1235: 159000000 | F1235: 225355979841
A1236: 17 | B1236: DHS 930 | C1236: 최수암 | E1236: 35909091 | F1236: 225196979841
A1237: 17 | B1237: DHT 160AS | C1237: 동보(주) | E1237: 175000000 | F1237: 225161070750
A1238: 17 | B1238: DHS 130SKY | C1238: 경화EnC | E1238: 44818182 | F1238: 224986070750
A1239: 17 | B1239: DHAS 120AP | C1239: 문성네트웍스 | E1239: 47800000 | F1239: 224941252568
A1240: 17 | B1240: DHS 950L | C1240: 김유용 | E1240: 37272727 | F1240: 224893452568
A1241: 17 | B1241: DHAS 120AP | C1241: 효경 | E1241: 49090909 | F1241: 224856179841
A1242: 17 | B1242: DHS 433L | C1242: 삼성로또복권방슈퍼 | E1242: 14000000 | F1242: 224807088932
A1243: 17 | B1243: DHS 534MAP | C1243: 지호정보통신 | E1243: 30454546 | F1243: 224793088932
A1244: 17 | B1244: DHS 130SKY | C1244: 덕암 | E1244: 46370000 | F1244: 224762634386
A1245: 17 | B1245: DHS 15AP | C1245: 바른시스템 | E1245: 52000000 | F1245: 224716264386
... A1357: 17 | B1357: DHT 150AS | C1357: WAIMEA TRUCK ＆ CRANE LTD | E1357: 113334314 | F1357: 218163807368
A1358: 17 | B1358: DHT 160AS | C1358: WAIMEA TRUCK ＆ CRANE LTD | E1358: 119843868
A1359: 17 | B1359: DHS 190SKY | C1359: 이성구 | E1359: -61000000 | F1359: 217930629186
...

Sheet Sheet2
A3: 행 레이블 | B3: 합계 : 대변
A4: 13 | B4: 32125375450
A5: 14 | B5: 37735445080
A6: 15 | B6: 58302450848
A7: 16 | B7: 78125032016
A8: 17 | B8: 88429795106
A9: 총합계 | B9: 294718098500

Sheet SG&A
B1: ="Project"&" "&Title!L6 -> Project SVG1 | K1: =Des!C12 -> DRAFT - For Discussion Purposes Only
B2: 판매비와관리비
B4: 판매비와관리비
B5: =unit -> KRW Million | D5: ='Pro forma'!D$5 -> 2014 | E5: ='Pro forma'!E$5 -> 2015 | F5: ='Pro forma'!F$5 -> 2016 | G5: ='Pro forma'!G$5 -> 2017 | H5: ='Pro forma'!H$5 -> 2018 | I5: ='Pro forma'!I$5 -> 2019 | J5: ='Pro forma'!J$5 -> 2020 | K5: ='Pro forma'!K$5 -> 2021 | L5: ='Pro forma'!L$5 -> 2022 | P5: 평균비율' Option | Q5: 2014~2017E (과거 4개년) 평균 | T5: 2
B6: 판매비와관리비 | D6: =D10+D14+D18+D22 -> 6260.3832 | E6: =E10+E14+E18+E22 -> 7139.8918 | F6: =F10+F14+F18+F22 -> 7407.697 | G6: =G10+G14+G18+G22 -> 10368.971 | H6: =H10+H14+H18+H22 -> 9842.4629 | I6: =I10+I14+I18+I22 -> 11618.075 | J6: =J10+J14+J18+J22 -> 13319.84 | K6: =K10+K14+K18+K22 -> 15631.565 | L6: =L10+L14+L18+L22 -> 17765.693 | Q6: 2015~2017E (과거 3개년) 평균
B7: % of growth | E7: =E6/D6-1 -> 0.14048799 | F7: =F6/E6-1 -> 0.037508293 | G7: =G6/F6-1 -> 0.39975631 | H7: =H6/G6-1 -> -0.050777237 | I7: =I6/H6-1 -> 0.18040324 | J7: =J6/I6-1 -> 0.1464756 | K7: =K6/J6-1 -> 0.17355501 | Q7: 2016~2017E (과거 2개년) 평균
B8: % of sales | D8: =D6/D$33 -> 0.15104291 | E8: =E6/E$33 -> 0.11701978 | F8: =F6/F$33 -> 0.091168552 | G8: =G6/G$33 -> 0.11495027 | H8: =H6/H$33 -> 0.071316393 | I8: =I6/I$33 -> 0.063782647 | J8: =J6/J$33 -> 0.065310998 | K8: =K6/K$33 -> 0.059841371 | L8: =L6/L$33 -> 0.059054329
B10: 변동비성 경비 | D10: =D39 -> 893.82739 | E10: =E39 -> 1369.4276 | F10: =F39 -> 662.60552 | G10: =G39 -> 2756.3304 | H10: =H39 -> 1426.8345 | I10: =I39 -> 1887.7546 | J10: =J39 -> 2244.3241 | K10: =K39 -> 2806.0552 | L10: =L39 -> 3300.3064
B11: % of growth | E11: =E10/D10-1 -> 0.53209404 | F11: =F10/E10-1 -> -0.51614418 | G11: =G10/F10-1 -> 3.1598362 | H11: =H10/G10-1 -> -0.48234271 | I11: =I10/H10-1 -> 0.32303682 | J11: =J10/I10-1 -> 0.18888551 | K11: =K10/J10-1 -> 0.25028966 | L11: =L10/K10-1 -> 0.17613736
B12: % of sales | D12: =D10/D$33 -> 0.021565179 | E12: =E10/E$33 -> 0.022444335 | F12: =F10/F$33 -> 0.0081548673 | G12: =G10/G$33 -> 0.030556644 | H12: =H10/H$33 -> 0.01033854 | I12: =I10/I$33 -> 0.010363678 | J12: =J10/J$33 -> 0.011004565 | K12: =K10/K$33 -> 0.010742251 | L12: =L10/L$33 -> 0.010970435
B14: 인건비성 경비 | D14: =D72 -> 3661.7588 | E14: =E72 -> 4234.9548 | F14: =F72 -> 4672.4254 | G14: =G72 -> 5587.3654 | H14: =H72 -> 6394.7057 | I14: =I72 -> 7653.1618 | J14: =J72 -> 8856.8219 | K14: =K72 -> 10363.038 | L14: =L72 -> 11845.324
B15: % of growth | E15: =E14/D14-1 -> 0.15653569 | F15: =F14/E14-1 -> 0.10329994 | G15: =G14/F14-1 -> 0.19581693 | H15: =H14/G14-1 -> 0.14449392 | I15: =I14/H14-1 -> 0.19679657 | J15: =J14/I14-1 -> 0.15727617 | K15: =K14/J14-1 -> 0.17006287 | L15: =L14/K14-1 -> 0.14303579
B16: % of sales | D16: =D14/D$33 -> 0.088346461 | E16: =E14/E$33 -> 0.069409105 | F16: =F14/F$33 -> 0.057504817 | G16: =G14/G$33 -> 0.06194146 | H16: =H14/H$33 -> 0.046334678 | I16: =I14/I$33 -> 0.042015473 | J16: =J14/J$33 -> 0.04342754 | K16: =K14/K$33 -> 0.039672192 | L16: =L14/L$33 -> 0.039374632
B18: 고정비성 경비 | D18: =D106 -> 1498.1075 | E18: =E106 -> 1303.2363 | F18: =F106 -> 1627.506 | G18: =G106 -> 1485.0577 | H18: =H106 -> 1508.8186 | I18: =I106 -> 1529.9421 | J18: =J106 -> 1551.3613 | K18: =K106 -> 1577.7344 | L18: =L106 -> 1604.5559
B19: % of growth | E19: =E18/D18-1 -> -0.13007828 | F19: =F18/E18-1 -> 0.24881881 | G19: =G18/F18-1 -> -0.08752552 | H19: =H18/G18-1 -> 0.016 | I19: =I18/H18-1 -> 0.014 | J19: =J18/I18-1 -> 0.014 | K19: =K18/J18-1 -> 0.017 | L19: =L18/K18-1 -> 0.017
B20: % of sales | D20: =D18/D$33 -> 0.036144516 | E20: =E18/E$33 -> 0.021359487 | F20: =F18/F$33 -> 0.020030161 | G20: =G18/G$33 -> 0.01646333 | H20: =H18/H$33 -> 0.010932579 | I20: =I18/I$33 -> 0.0083993048 | J20: =J18/J$33 -> 0.0076067696 | K20: =K18/K$33 -> 0.0060399449 | L20: =L18/L$33 -> 0.0053336489
B22: 유무형 상각비 | D22: =D148 -> 206.68938 | E22: =E148 -> 232.27311 | F22: =F148 -> 445.16007 | G22: =G148 -> 540.21708 | H22: =H148 -> 512.10406 | I22: =I148 -> 547.21655 | J22: =J148 -> 667.33236 | K22: =K148 -> 884.73644 | L22: =L148 -> 1015.5073
B23: % of growth | E23: =E22/D22-1 -> 0.12377862 | F23: =F22/E22-1 -> 0.91653725 | G23: =G22/F22-1 -> 0.21353447 | H23: =H22/G22-1 -> -0.052040242 | I23: =I22/H22-1 -> 0.068565149 | J23: =J22/I22-1 -> 0.21950326 | K23: =K22/J22-1 -> 0.32578081 | L23: =L22/K22-1 -> 0.14780774
B24: % of sales | D24: =D22/D$33 -> 0.0049867499 | E24: =E22/E$33 -> 0.0038068573 | F24: =F22/F$33 -> 0.0054787067 | G24: =G22/G$33 -> 0.0059888396 | H24: =H22/H$33 -> 0.0037105971 | I24: =I22/I$33 -> 0.0030041913 | J24: =J22/J$33 -> 0.0032721222 | K24: =K22/K$33 -> 0.0033869829 | L24: =L22/L$33 -> 0.0033756129
D26: =D6=IS!D14/10^6 -> TRUE | E26: =E6=IS!E14/10^6 -> TRUE | F26: =F6=IS!F14/10^6 -> TRUE | G26: =G6=IS!G14/10^6 -> TRUE
B27: Macro Variables
B28: change of % | D28: =D$5 -> 2014 | E28: =E$5 -> 2015 | F28: =F$5 -> 2016 | G28: =G$5 -> 2017 | H28: =H$5 -> 2018 | I28: =I$5 -> 2019 | J28: =J$5 -> 2020 | K28: =K$5 -> 2021 | L28: =K28+1 -> 2022
B29: GDP (% real change pa) | D29: =Macro!D6/100 -> 0.03341 | E29: =Macro!E6/100 -> 0.0279 | F29: =Macro!F6/100 -> 0.02828 | G29: =Macro!G6/100 -> 0.03 | H29: =Macro!H6/100 -> 0.023 | I29: =Macro!I6/100 -> 0.025 | J29: =Macro!J6/100 -> 0.022 | K29: =Macro!K6/100 -> 0.028 | L29: =K29 -> 0.028
B30: Consumer prices (% change pa; av) | D30: =Macro!D7/100 -> 0.01275 | E30: =Macro!E7/100 -> 0.00708 | F30: =Macro!F7/100 -> 0.00972 | G30: =Macro!G7/100 -> 0.02 | H30: =Macro!H7/100 -> 0.016 | I30: =Macro!I7/100 -> 0.014 | J30: =Macro!J7/100 -> 0.014 | K30: =Macro!K7/100 -> 0.017 | L30: =K30 -> 0.017
B31: Average nominal wages (% change pa) | D31: =Macro!D8/100 -> 0.02554 | E31: =Macro!E8/100 -> 0.03414 | F31: =Macro!F8/100 -> 0.03807 | G31: =Macro!G8/100 -> 0.042 | H31: =Macro!H8/100 -> 0.036 | I31: =Macro!I8/100 -> 0.034 | J31: =Macro!J8/100 -> 0.036 | K31: =Macro!K8/100 -> 0.039 | L31: =K31 -> 0.039
B32: Producer prices (% change pa; av) - [YQM] | D32: =Macro!D9/100 -> 0.01263 | E32: =Macro!E9/100 -> 0.02687 | F32: =Macro!F9/100 -> 0.02808 | G32: =Macro!G9/100 -> 0.022 | H32: =Macro!H9/100 -> 0.019 | I32: =Macro!I9/100 -> 0.019 | J32: =Macro!J9/100 -> 0.022 | K32: =Macro!K9/100 -> 0.022 | L32: =K32 -> 0.022
B33: 매출액 | D33: ='Pro forma'!D6 -> 41447.714 | E33: ='Pro forma'!E6-매출원가!E48 -> 61014.399 | F33: ='Pro forma'!F6-매출원가!F48 -> 81252.766 | G33: ='Pro forma'!G6-매출원가!G48 -> 90203.966 | H33: ='Pro forma'!H6 -> 138011.23 | I33: ='Pro forma'!I6 -> 182151.03 | J33: ='Pro forma'!J6 -> 203944.82 | K33: ='Pro forma'!K6 -> 261216.69 | L33: ='Pro forma'!L6 -> 300836.43
B34: 국내매출액 | E34: =E33-E35 -> 59051.346 | F34: =F33-F35 -> 78328.201 | G34: =G33-G35 -> 84738.852 | H34: =H33-H35 -> 112544.83 | I34: =I33-I35 -> 148376.57 | J34: =J33-J35 -> 161470.57 | K34: =K33-K35 -> 209257.11 | L34: =L33-L35 -> 238549.18
B35: 수출매출액 | E35: ='매출액(보고서)'!D158-매출원가!E48 -> 1963.0526 | F35: ='매출액(보고서)'!E158-매출원가!F48 -> 2924.5644 | G35: ='매출액(보고서)'!F158-매출원가!G48 -> 5465.1138 | H35: ='모델별 Mapping'!Q163/10^6 -> 25466.395 | I35: ='모델별 Mapping'!T163/10^6 -> 33774.461 | J35: ='모델별 Mapping'!W163/10^6 -> 42474.245 | K35: ='모델별 Mapping'!Z163/10^6 -> 51959.572 | L35: ='모델별 Mapping'!AC163/10^6 -> 62287.246
B37: 변동비성 경비
B38: =unit -> KRW Million | D38: ='Pro forma'!D$5 -> 2014 | E38: ='Pro forma'!E$5 -> 2015 | F38: ='Pro forma'!F$5 -> 2016 | G38: ='Pro forma'!G$5 -> 2017 | H38: ='Pro forma'!H$5 -> 2018 | I38: ='Pro forma'!I$5 -> 2019 | J38: ='Pro forma'!J$5 -> 2020 | K38: ='Pro forma'!K$5 -> 2021 | L38: =K38+1 -> 2022
B39: 변동비성 경비 | D39: =D43+D47+D51+D55+D61+D65 -> 893.82739 | E39: =E43+E47+E51+E55+E61+E65 -> 1369.4276 | F39: =F43+F47+F51+F55+F61+F65 -> 662.60552 | G39: =G43+G47+G51+G55+G61+G65 -> 2756.3304 | H39: =H43+H47+H51+H55+H61+H65 -> 1426.8345 | I39: =I43+I47+I51+I55+I61+I65 -> 1887.7546 | J39: =J43+J47+J51+J55+J61+J65 -> 2244.3241 | K39: =K43+K47+K51+K55+K61+K65 -> 2806.0552 | L39: =L43+L47+L51+L55+L61+L65 -> 3300.3064
B40: % of growth | D40: =D39/C39-1 -> #DIV/0! | E40: =E39/D39-1 -> 0.53209404 | F40: =F39/E39-1 -> -0.51614418 | G40: =G39/F39-1 -> 3.1598362 | H40: =H39/G39-1 -> -0.48234271 | I40: =I39/H39-1 -> 0.32303682 | J40: =J39/I39-1 -> 0.18888551 | K40: =K39/J39-1 -> 0.25028966
B41: % of sales
B43: 운반비 | D43: =IS!D32/10^6 -> 112.39048 | E43: =IS!E32/10^6 -> 126.94999 | F43: =IS!F32/10^6 -> 166.87516 | G43: =IS!G32/10^6 -> 201.54673 | H43: =H45*H$33 -> 292.98767 | I43: =I45*I$33 -> 386.69323 | J43: =J45*J$33 -> 432.95982 | K43: =K45*K$33 -> 554.54378 | L43: =L45*L$33 -> 638.65357
B44: % of growth | D44: =D43/C43-1 -> #DIV/0! | E44: =E43/D43-1 -> 0.12954402 | F44: =F43/E43-1 -> 0.31449523 | G44: =G43/F43-1 -> 0.20776949 | H44: =H43/G43-1 -> 0.45369596 | I44: =I43/H43-1 -> 0.31982767 | J44: =J43/I43-1 -> 0.11964678 | K44: =K43/J43-1 -> 0.28082041 | L44: =L43/K43-1 -> 0.15167386
B45: % of sales | C45: =CHOOSE($T$5,AVERAGE(D45:G45),AVERAGE(E45:G45), AVERAGE(F45:G45)) -> 0.0021229263 | D45: =D43/D$33 -> 0.0027116207 | E45: =E43/E$33 -> 0.0020806563 | F45: =F43/F$33 -> 0.0020537782 | G45: =G43/G$33 -> 0.0022343444 | H45: =C45 -> 0.0021229263 | I45: =H45 -> 0.0021229263 | J45: =I45 -> 0.0021229263 | K45: =J45 -> 0.0021229263 | L45: =K45 -> 0.0021229263
B47: 지급수수료 | D47: =IS!D37/10^6 -> 120.2046 | E47: =IS!E37/10^6 -> 157.91327 | F47: =IS!F37/10^6 -> 160.33937 | G47: =IS!G37/10^6 -> 171.39398 | H47: =H49*H$33 -> 297.25517 | I47: =I49*I$33 -> 392.3256 | J47: =J49*J$33 -> 439.26609 | K47: =K49*K$33 -> 562.62097 | L47: =L49*L$33 -> 647.95587
B48: % of growth | D48: =D47/C47-1 -> #DIV/0! | E48: =E47/D47-1 -> 0.31370414 | F48: =F47/E47-1 -> 0.01536349 | G48: =G47/F47-1 -> 0.068945074 | H48: =H47/G47-1 -> 0.73433842 | I48: =I47/H47-1 -> 0.31982767 | J48: =J47/I47-1 -> 0.11964678 | K48: =K47/J47-1 -> 0.28082041 | L48: =L47/K47-1 -> 0.15167386
B49: % of sales | C49: =CHOOSE($T$5,AVERAGE(D49:G49),AVERAGE(E49:G49), AVERAGE(F49:G49)) -> 0.0021538478 | D49: =D47/D$33 -> 0.0029001502 | E49: =E47/E$33 -> 0.0025881313 | F49: =F47/F$33 -> 0.0019733405 | G49: =G47/G$33 -> 0.0019000715 | H49: =C49 -> 0.0021538478 | I49: =H49 -> 0.0021538478 | J49: =I49 -> 0.0021538478 | K49: =J49 -> 0.0021538478 | L49: =K49 -> 0.0021538478
B51: 광고선전비 | D51: =IS!D38/10^6 -> 68.590875 | E51: =IS!E38/10^6 -> 70.543764 | F51: =IS!F38/10^6 -> 30.088509 | G51: =IS!G38/10^6 -> 71.411271 | H51: =H53*H$33 -> 106.64377 | I51: =I53*I$33 -> 140.75139 | J51: =J53*J$33 -> 157.59184 | K51: =K53*K$33 -> 201.84685 | L51: =L53*L$33 -> 232.46174 | M51: 2016년 하락 사유 : 과거 지사 운영 전에는 DM/카탈로그 영업을 수행하였음. 최근에는 맨투맨 영업으로 해당 비용이 감소하여 광고선전비 하락
B52: % of growth | D52: =D51/C51-1 -> #DIV/0! | E52: =E51/D51-1 -> 0.028471557 | F52: =F51/E51-1 -> -0.57347741 | G52: =G51/F51-1 -> 1.3733735 | H52: =H51/G51-1 -> 0.49337444 | I52: =I51/H51-1 -> 0.31982767 | J52: =J51/I51-1 -> 0.11964678 | K52: =K51/J51-1 -> 0.28082041 | L52: =L51/K51-1 -> 0.15167386
B53: % of sales | C53: =CHOOSE($T$5,AVERAGE(D53:G53),AVERAGE(E53:G53), AVERAGE(F53:G53)) -> 0.00077271806 | D53: =D51/D$33 -> 0.0016548772 | E53: =E51/E$33 -> 0.0011561822 | F53: =F51/F$33 -> 0.00037030751 | G53: =G51/G$33 -> 0.00079166443 | H53: =C53 -> 0.00077271806 | I53: =H53 -> 0.00077271806 | J53: =I53 -> 0.00077271806 | K53: =J53 -> 0.00077271806 | L53: =K53 -> 0.00077271806
B55: 판매수수료 | D55: =IS!D41/10^6 -> 476.54705 | E55: =IS!E41/10^6 -> 956.96695 | F55: =IS!F41/10^6 -> 235.46536 | G55: =IS!G41/10^6 -> 2139.4974 | H55: =H59 -> 12.613821 | I55: =I59 -> 16.629778 | J55: =J59 -> 18.097329 | K55: =K59 -> 23.453158 | L55: =L59 -> 26.73616 | M55: 판매수수료는 Vietnam에 지급되는 수수료가 대부분임. 해당 금액은 매출액에 포함하여 받음. 추정시에는 매출액을 순액으로 추정하고, 해당부분은 수수료에서 제외함.
B56: % of growth | D56: =D55/C55-1 -> #DIV/0! | E56: =E55/D55-1 -> 1.0081269 | F56: =F55/E55-1 -> -0.75394619 | G56: =G55/F55-1 -> 8.0862509 | H56: =H55/G55-1 -> -0.99410431 | I56: =I55/H55-1 -> 0.31837751 | J56: =J55/I55-1 -> 0.088248428 | K56: =K55/J55-1 -> 0.29594581 | L56: =L55/K55-1 -> 0.13998124
B57: % of sales | C57: =CHOOSE($T$5,AVERAGE(D57:G57),AVERAGE(E57:G57), AVERAGE(F57:G57)) -> 0.014100219 | D57: =D55/D$33 -> 0.011497547 | E57: =E55/E$33 -> 0.01568428 | F57: =F55/F$33 -> 0.0028979366 | G57: =G55/G$33 -> 0.02371844 | H57: =C57 -> 0.014100219 | I57: =H57 -> 0.014100219 | J57: =I57 -> 0.014100219 | K57: =J57 -> 0.014100219 | L57: =K57 -> 0.014100219
B58: Vietnam | G58: 2130 | H58: ='모델별 Mapping'!Q16012^6 -> 0 | I58: ='사업계획(매출 확정본)'!T167/10^6 -> 4200 | J58: ='사업계획(매출 확정본)'!U167/10^6 -> 5292 | K58: ='사업계획(매출 확정본)'!V167/10^6 -> 6482 | L58: ='사업계획(매출 확정본)'!W167/10^6 -> 8019
B59: 기타 | G59: =G55-G58 -> 9.497377 | H59: =$G$59/$G$34*H34 -> 12.613821 | I59: =$G$59/$G$34*I34 -> 16.629778 | J59: =$G$59/$G$34*J34 -> 18.097329 | K59: =$G$59/$G$34*K34 -> 23.453158 | L59: =$G$59/$G$34*L34 -> 26.73616
B61: 해외시장개척비 | D61: =IS!D43/10^6 -> 0.4522 | E61: =IS!E43/10^6 -> 1.334238 | F61: =IS!F43/10^6 -> 6.403596 | G61: =IS!G43/10^6 -> 3.437222 | H61: =H63*H$35 -> 29.695545 | I61: =I63*I$35 -> 39.383314 | J61: =J63*J$35 -> 49.527853 | K61: =K63*K$35 -> 60.588388 | L61: =L63*L$35 -> 72.631156 | M61: 해외 영업부의 해외 딜러망 구축을 위한 출장 비용. 2018년부터 본격적인 수출향 매출 발생으로 인한 가산 효과 반영
B62: % of growth | D62: =D61/C61-1 -> #DIV/0! | E62: =E61/D61-1 -> 1.9505484 | F62: =F61/E61-1 -> 3.7994406 | G62: =G61/F61-1 -> -0.46323566 | H62: =H61/G61-1 -> 7.6394027 | I62: =I61/H61-1 -> 0.32623643 | J62: =J61/I61-1 -> 0.2575847 | K62: =K61/J61-1 -> 0.22331949 | L62: =L61/K61-1 -> 0.19876364
B63: % of sales | C63: =AVERAGE(E63:G63) -> 0.0011660679 | D63: =D61/D$33 -> 1.0910131e-05 | E63: =E61/E$35 -> 0.00067967511 | F63: =F61/F$35 -> 0.0021895897 | G63: =G61/G$35 -> 0.00062893878 | H63: =C63 -> 0.0011660679 | I63: =H63 -> 0.0011660679 | J63: =I63 -> 0.0011660679 | K63: =J63 -> 0.0011660679 | L63: =K63 -> 0.0011660679
B65: 수출제비용 | D65: =IS!D40/10^6 -> 115.64219 | E65: =IS!E40/10^6 -> 55.719403 | F65: =IS!F40/10^6 -> 63.43352 | G65: =IS!G40/10^6 -> 169.04385 | H65: =H67*H35 -> 687.63856 | I65: =I67*I35 -> 911.9713 | J65: =J67*J35 -> 1146.8812 | K65: =K67*K35 -> 1403.0021 | L65: =L67*L35 -> 1681.8679 | N65: =G55-G59 -> 2130
B66: % of growth | D66: =D65/C65-1 -> #DIV/0! | E66: =E65/D65-1 -> -0.51817409 | F66: =F65/E65-1 -> 0.13844579 | G66: =G65/F65-1 -> 1.6648978 | H66: =H65/G65-1 -> 3.0678118 | I66: =I65/H65-1 -> 0.32623643 | J66: =J65/I65-1 -> 0.2575847 | K66: =K65/J65-1 -> 0.22331949 | L66: =L65/K65-1 -> 0.19876364
B67: % of sales | C67: =AVERAGE(E67:G67) -> 0.027001802 | D67: =D65/D$33 -> 0.002790074 | E67: =E65/E$35 -> 0.02838406 | F67: =F65/F$35 -> 0.021689904 | G67: =G65/G$35 -> 0.030931442 | H67: =C67 -> 0.027001802 | I67: =H67 -> 0.027001802 | J67: =I67 -> 0.027001802 | K67: =J67 -> 0.027001802 | L67: =K67 -> 0.027001802
B70: 인건비성 경비
B71: =unit -> KRW Million | D71: ='Pro forma'!D$5 -> 2014 | E71: ='Pro forma'!E$5 -> 2015 | F71: ='Pro forma'!F$5 -> 2016 | G71: ='Pro forma'!G$5 -> 2017 | H71: ='Pro forma'!H$5 -> 2018 | I71: ='Pro forma'!I$5 -> 2019 | J71: ='Pro forma'!J$5 -> 2020 | K71: ='Pro forma'!K$5 -> 2021 | L71: 2022
B72: 인건비성 경비 | D72: =D76+D87+D91+D95+D99 -> 3661.7588 | E72: =E76+E87+E91+E95+E99 -> 4234.9548 | F72: =F76+F87+F91+F95+F99 -> 4672.4254 | G72: =G76+G87+G91+G95+G99 -> 5587.3654 | H72: =H76+H87+H91+H95+H99 -> 6394.7057 | I72: =I76+I87+I91+I95+I99 -> 7653.1618 | J72: =J76+J87+J91+J95+J99 -> 8856.8219 | K72: =K76+K87+K91+K95+K99 -> 10363.038 | L72: =L76+L87+L91+L95+L99 -> 11845.324
B73: % of growth | D73: =D72/C72-1 -> #DIV/0! | E73: =E72/D72-1 -> 0.15653569 | F73: =F72/E72-1 -> 0.10329994 | G73: =G72/F72-1 -> 0.19581693 | H73: =H72/G72-1 -> 0.14449392 | I73: =I72/H72-1 -> 0.19679657 | J73: =J72/I72-1 -> 0.15727617 | K73: =K72/J72-1 -> 0.17006287 | L73: =L72/K72-1 -> 0.14303579
B74: % of sales | D74: =D72/D$33 -> 0.088346461 | E74: =E72/E$33 -> 0.069409105 | F74: =F72/F$33 -> 0.057504817 | G74: =G72/G$33 -> 0.06194146 | H74: =H72/H$33 -> 0.046334678 | I74: =I72/I$33 -> 0.042015473 | J74: =J72/J$33 -> 0.04342754 | K74: =K72/K$33 -> 0.039672192 | L74: =L72/L$33 -> 0.039374632
B76: 급여 | D76: =D79+D82 -> 2667.369 | E76: =E79+E82 -> 2834.6871 | F76: =F79+F82 -> 3219.9568 | G76: =G79+G82 -> 3544.6454 | H76: =H79+H82 -> 4271.0266 | I76: =I79+I82 -> 5035.3739 | J76: =J79+J82 -> 5858.0685 | K76: =K79+K82 -> 6752.9697 | L76: =L79+L82 -> 7708.7631
B77: % of growth | D77: =D76/C76-1 -> #DIV/0! | E77: =E76/D76-1 -> 0.062727758 | F77: =F76/E76-1 -> 0.13591261 | G77: =G76/F76-1 -> 0.1008363 | H77: =H76/G76-1 -> 0.20492354 | I77: =I76/H76-1 -> 0.17896102 | J77: =J76/I76-1 -> 0.16338302 | K77: =K76/J76-1 -> 0.15276387 | L77: =L76/K76-1 -> 0.14153675
B78: % of sales | D78: =D76/D$33 -> 0.064355034 | E78: =E76/E$33 -> 0.046459314 | F78: =F76/F$33 -> 0.039628889 | G78: =G76/G$33 -> 0.039295893 | H78: =H76/H$33 -> 0.030946951 | I78: =I76/I$33 -> 0.027643949 | J78: =J76/J$33 -> 0.028723792 | K78: =K76/K$33 -> 0.025851985 | L78: =L76/L$33 -> 0.025624434
B79: 임원급여 | D79: =IS!D15/10^6 -> 463.2626 | E79: =IS!E15/10^6 -> 520.1528 | F79: =IS!F15/10^6 -> 578.5711 | G79: =IS!G15/10^6 -> 636.33662 | H79: =H80*H81 -> 732.49415 | I79: =I80*I81 -> 833.13885 | J79: =J80*J81 -> 941.59838 | K79: =K80*K81 -> 1059.8474 | L79: =L80*L81 -> 1185.8878
B80: 평균임원수 | D80: ='인건비 분석'!E75 -> 9 | E80: ='인건비 분석'!F75 -> 8 | F80: ='인건비 분석'!G75 -> 9 | G80: ='인건비 분석'!H75 -> 9 | H80: 10 | I80: 11 | J80: 12 | K80: 13 | L80: 14 | M80: 매년 1명씩은 임원 증가
B81: 임원당급여 | D81: =D79/D80 -> 51.473622 | E81: =E79/E80 -> 65.0191 | F81: =F79/F80 -> 64.285678 | G81: =G79/G80 -> 70.704069 | H81: =G81*(1+H$31) -> 73.249415 | I81: =H81*(1+I$31) -> 75.739895 | J81: =I81*(1+J$31) -> 78.466532 | K81: =J81*(1+K$31) -> 81.526726 | L81: =K81*(1+L$31) -> 84.706269
B82: 직원급여 | D82: =IS!D16/10^6 -> 2204.1064 | E82: =IS!E16/10^6 -> 2314.5343 | F82: =IS!F16/10^6 -> 2641.3857 | G82: =IS!G16/10^6 -> 2908.3087 | H82: =H83*H84 -> 3538.5325 | I82: =I83*I84 -> 4202.2351 | J82: =J83*J84 -> 4916.4701 | K82: =K83*K84 -> 5693.1223 | L82: =L83*L84 -> 6522.8753
B83: 평균직원수 | D83: ='인건비 분석'!E76 -> 74 | E83: ='인건비 분석'!F76 -> 79 | F83: ='인건비 분석'!G76 -> 80 | G83: ='인건비 분석'!H76 -> 86 | H83: =G83+15 -> 101 | I83: =H83+15 -> 116 | J83: =I83+15 -> 131 | K83: =J83+15 -> 146 | L83: =K83+15 -> 161 | M83: 영업파트 5명씩 증가/ 관리 파트 2~3명 증가
B84: 직원당급여 | D84: =D82/D83 -> 29.785222 | E84: =E82/E83 -> 29.297903 | F84: =F82/F83 -> 33.017322 | G84: =G82/G83 -> 33.817544 | H84: =G84*(1+H$31) -> 35.034975 | I84: =H84*(1+I$31) -> 36.226164 | J84: =I84*(1+J$31) -> 37.530306 | K84: =J84*(1+K$31) -> 38.993988 | L84: =K84*(1+L$31) -> 40.514754
E85: =E84/D84-1 -> -0.016361112 | F85: =F84/E84-1 -> 0.12695171 | G85: =G84/F84-1 -> 0.024236422
B87: 상여금 | D87: =IS!D17/10^6 -> 623.27835 | E87: =IS!E17/10^6 -> 998.62633 | F87: =IS!F17/10^6 -> 990.65333 | G87: =IS!G17/10^6 -> 1561.6346 | H87: =H89*H76 -> 1314.0259 | I87: =I89*I76 -> 1549.1853 | J87: =J89*J76 -> 1802.2959 | K87: =K89*K76 -> 2077.6216 | L87: =L89*L76 -> 2371.6814
B88: % of growth | D88: =D87/C87-1 -> #DIV/0! | E88: =E87/D87-1 -> 0.60221566 | F88: =F87/E87-1 -> -0.0079839673 | G88: =G87/F87-1 -> 0.57636836 | H88: =H87/G87-1 -> -0.15855735 | I88: =I87/H87-1 -> 0.17896102 | J88: =J87/I87-1 -> 0.16338302 | K88: =K87/J87-1 -> 0.15276387 | L88: =L87/K87-1 -> 0.14153675
B89: % of 급여 | C89: =F89 -> 0.30766044 | D89: =D87/D$76 -> 0.23366784 | E89: =E87/E$76 -> 0.35228803 | F89: =F87/F$76 -> 0.30766044 | G89: =G87/G$76 -> 0.44056158 | H89: =C89 -> 0.30766044 | I89: =H89 -> 0.30766044 | J89: =I89 -> 0.30766044 | K89: =J89 -> 0.30766044 | L89: =K89 -> 0.30766044
B91: 잡급 | D91: =IS!D18/10^6 -> 3.7 | E91: =IS!E18/10^6 -> 0.50778 | F91: =IS!F18/10^6 -> 11.89437 | G91: =IS!G18/10^6 -> 0.27192 | H91: =H93*H33 -> 7.2558971 | I91: =I93*I33 -> 9.5765338 | J91: =J93*J33 -> 10.722335 | K91: =K93*K33 -> 13.733386 | L91: =L93*L33 -> 15.816381 | M91: 환경 정비, 조경 등에 대한 발생 비용
B92: % of growth | D92: =D91/C91-1 -> #DIV/0! | E92: =E91/D91-1 -> -0.86276216 | F92: =F91/E91-1 -> 22.424259 | G92: =G91/F91-1 -> -0.97713876 | H92: =H91/G91-1 -> 25.683941 | I92: =I91/H91-1 -> 0.31982767 | J92: =J91/I91-1 -> 0.11964678 | K92: =K91/J91-1 -> 0.28082041 | L92: =L91/K91-1 -> 0.15167386
B93: % of sales | C93: =CHOOSE($T$5,AVERAGE(D93:G93),AVERAGE(E93:G93), AVERAGE(F93:G93)) -> 5.2574688e-05 | D93: =D91/D$33 -> 8.9269097e-05 | E93: =E91/E$33 -> 8.3222978e-06 | F93: =F91/F$33 -> 0.00014638726 | G93: =G91/G$33 -> 3.0145016e-06 | H93: =C93 -> 5.2574688e-05 | I93: =H93 -> 5.2574688e-05 | J93: =I93 -> 5.2574688e-05 | K93: =J93 -> 5.2574688e-05 | L93: =K93 -> 5.2574688e-05
B95: 퇴직급여 | D95: =IS!D19/10^6 -> 174.84353 | E95: =IS!E19/10^6 -> 196.85085 | F95: =IS!F19/10^6 -> 209.0551 | G95: =IS!G19/10^6 -> 237.35219 | H95: =H97*H33 -> 387.83377 | I95: =I97*I33 -> 511.87374 | J95: =J97*J33 -> 573.11779 | K95: =K97*K33 -> 734.06095 | L95: =L97*L33 -> 845.39881
B96: % of growth | D96: =D95/C95-1 -> #DIV/0! | E96: =E95/D95-1 -> 0.12586866 | F96: =F95/E95-1 -> 0.061997446 | G96: =G95/F95-1 -> 0.13535709 | H96: =H95/G95-1 -> 0.63400124 | I96: =I95/H95-1 -> 0.31982767 | J96: =J95/I95-1 -> 0.11964678 | K96: =K95/J95-1 -> 0.28082041 | L96: =L95/K95-1 -> 0.15167386
B97: % of sales | C97: =CHOOSE($T$5,AVERAGE(D97:G97),AVERAGE(E97:G97), AVERAGE(F97:G97)) -> 0.0028101611 | D97: =D95/D$33 -> 0.0042184119 | E97: =E95/E$33 -> 0.0032263016 | F97: =F95/F$33 -> 0.0025728983 | G97: =G95/G$33 -> 0.0026312833 | H97: =C97 -> 0.0028101611 | I97: =H97 -> 0.0028101611 | J97: =I97 -> 0.0028101611 | K97: =J97 -> 0.0028101611 | L97: =K97 -> 0.0028101611
B99: 복리후생비 | D99: =IS!D20/10^6 -> 192.56793 | E99: =IS!E20/10^6 -> 204.28271 | F99: =IS!F20/10^6 -> 240.86574 | G99: =IS!G20/10^6 -> 243.46131 | H99: =H101*H33 -> 414.56345 | I99: =I101*I33 -> 547.15232 | J99: =J101*J33 -> 612.61733 | K99: =K101*K33 -> 784.65277 | L99: =L101*L33 -> 903.66409
B100: % of growth | D100: =D99/C99-1 -> #DIV/0! | E100: =E99/D99-1 -> 0.060834544 | F100: =F99/E99-1 -> 0.17908041 | G100: =G99/F99-1 -> 0.010776003 | H100: =H99/G99-1 -> 0.7027899 | I100: =I99/H99-1 -> 0.31982767 | J100: =J99/I99-1 -> 0.11964678 | K100: =K99/J99-1 -> 0.28082041 | L100: =L99/K99-1 -> 0.15167386
B101: % of sales | C101: =CHOOSE($T$5,AVERAGE(D101:G101),AVERAGE(E101:G101), AVERAGE(F101:G101)) -> 0.0030038386 | D101: =D99/D$33 -> 0.0046460445 | E101: =E99/E$33 -> 0.0033481065 | F101: =F99/F$33 -> 0.0029644005 | G101: =G99/G$33 -> 0.0026990089 | H101: =C101 -> 0.0030038386 | I101: =H101 -> 0.0030038386 | J101: =I101 -> 0.0030038386 | K101: =J101 -> 0.0030038386 | L101: =K101 -> 0.0030038386
B104: 고정비성 경비
B105: =unit -> KRW Million | D105: ='Pro forma'!D$5 -> 2014 | E105: ='Pro forma'!E$5 -> 2015 | F105: ='Pro forma'!F$5 -> 2016 | G105: ='Pro forma'!G$5 -> 2017 | H105: ='Pro forma'!H$5 -> 2018 | I105: ='Pro forma'!I$5 -> 2019 | J105: ='Pro forma'!J$5 -> 2020 | K105: ='Pro forma'!K$5 -> 2021 | L105: =K105+1 -> 2022
B106: 고정비성 경비 | D106: =D110+D112+D114+D116+D118+D120+D122+D124+D126+D128+D130+D132+D134+D136+D138+D140+D142 -> 1498.1075 | E106: =E110+E112+E114+E116+E118+E120+E122+E124+E126+E128+E130+E132+E134+E136+E138+E140+E142 -> 1303.2363 | F106: =F110+F112+F114+F116+F118+F120+F122+F124+F126+F128+F130+F132+F134+F136+F138+F140+F142 -> 1627.506 | G106: =G110+G112+G114+G116+G118+G120+G122+G124+G126+G128+G130+G132+G134+G136+G138+G140+G142 -> 1485.0577 | H106: =H110+H112+H114+H116+H118+H120+H122+H124+H126+H128+H130+H132+H134+H136+H138+H140+H142 -> 1508.8186 | I106: =I110+I112+I114+I116+I118+I120+I122+I124+I126+I128+I130+I132+I134+I136+I138+I140+I142 -> 1529.9421 | J106: =J110+J112+J114+J116+J118+J120+J122+J124+J126+J128+J130+J132+J134+J136+J138+J140+J142 -> 1551.3613 | K106: =K110+K112+K114+K116+K118+K120+K122+K124+K126+K128+K130+K132+K134+K136+K138+K140+K142 -> 1577.7344 | L106: =L110+L112+L114+L116+L118+L120+L122+L124+L126+L128+L130+L132+L134+L136+L138+L140+L142 -> 1604.5559
B107: % of growth | D107: =D106/C106-1 -> #DIV/0! | E107: =E106/D106-1 -> -0.13007828 | F107: =F106/E106-1 -> 0.24881881 | G107: =G106/F106-1 -> -0.08752552 | H107: =H106/G106-1 -> 0.016 | I107: =I106/H106-1 -> 0.014 | J107: =J106/I106-1 -> 0.014 | K107: =K106/J106-1 -> 0.017
B108: % of sales | D108: =D106/D$33 -> 0.036144516 | E108: =E106/E$33 -> 0.021359487 | F108: =F106/F$33 -> 0.020030161 | G108: =G106/G$33 -> 0.01646333 | H108: =H106/H$33 -> 0.010932579 | I108: =I106/I$33 -> 0.0083993048 | J108: =J106/J$33 -> 0.0076067696 | K108: =K106/K$33 -> 0.0060399449
B110: 여비교통비 | D110: =IS!D21/10^6 -> 299.33286 | E110: =IS!E21/10^6 -> 226.30599 | F110: =IS!F21/10^6 -> 262.40722 | G110: =IS!G21/10^6 -> 318.16871 | H110: =G110*(1+H$30) -> 323.25941 | I110: =H110*(1+I$30) -> 327.78504 | J110: =I110*(1+J$30) -> 332.37403 | K110: =J110*(1+K$30) -> 338.02439 | L110: =K110*(1+L$30) -> 343.77081
B111: % of growth | D111: =D110/C110-1 -> #DIV/0! | E111: =E110/D110-1 -> -0.24396541 | F111: =F110/E110-1 -> 0.15952397 | G111: =G110/F110-1 -> 0.21249982 | H111: =H110/G110-1 -> 0.016 | I111: =I110/H110-1 -> 0.014 | J111: =J110/I110-1 -> 0.014 | K111: =K110/J110-1 -> 0.017
B112: 접대비 | D112: =IS!D22/10^6 -> 16.80968 | E112: =IS!E22/10^6 -> 17.736404 | F112: =IS!F22/10^6 -> 14.2083 | G112: =IS!G22/10^6 -> 14.69991 | H112: =G112*(1+H$30) -> 14.935109 | I112: =H112*(1+I$30) -> 15.1442 | J112: =I112*(1+J$30) -> 15.356219 | K112: =J112*(1+K$30) -> 15.617275 | L112: =K112*(1+L$30) -> 15.882768
B113: % of growth | D113: =D112/C112-1 -> #DIV/0! | E113: =E112/D112-1 -> 0.055130377 | F113: =F112/E112-1 -> -0.19891879 | G113: =G112/F112-1 -> 0.034600198 | H113: =H112/G112-1 -> 0.016 | I113: =I112/H112-1 -> 0.014 | J113: =J112/I112-1 -> 0.014 | K113: =K112/J112-1 -> 0.017
B114: 통신비 | D114: =IS!D23/10^6 -> 88.381894 | E114: =IS!E23/10^6 -> 79.730134 | F114: =IS!F23/10^6 -> 74.973654 | G114: =IS!G23/10^6 -> 78.848519 | H114: =G114*(1+H$30) -> 80.110095 | I114: =H114*(1+I$30) -> 81.231637 | J114: =I114*(1+J$30) -> 82.36888 | K114: =J114*(1+K$30) -> 83.769151 | L114: =K114*(1+L$30) -> 85.193226
B115: % of growth | D115: =D114/C114-1 -> #DIV/0! | E115: =E114/D114-1 -> -0.097890638 | F115: =F114/E114-1 -> -0.059657243 | G115: =G114/F114-1 -> 0.051683022 | H115: =H114/G114-1 -> 0.016 | I115: =I114/H114-1 -> 0.014 | J115: =J114/I114-1 -> 0.014 | K115: =K114/J114-1 -> 0.017
B116: 수도광열비 | D116: =IS!D24/10^6 -> 8.942602 | E116: =IS!E24/10^6 -> 5.456358 | F116: =IS!F24/10^6 -> 8.061839 | G116: =IS!G24/10^6 -> 7.837416 | H116: =G116*(1+H$30) -> 7.9628147 | I116: =H116*(1+I$30) -> 8.0742941 | J116: =I116*(1+J$30) -> 8.1873342 | K116: =J116*(1+K$30) -> 8.3265189 | L116: =K116*(1+L$30) -> 8.4680697
B117: % of growth | D117: =D116/C116-1 -> #DIV/0! | E117: =E116/D116-1 -> -0.38984671 | F117: =F116/E116-1 -> 0.47751284 | G117: =G116/F116-1 -> -0.027837693 | H117: =H116/G116-1 -> 0.016 | I117: =I116/H116-1 -> 0.014 | J117: =J116/I116-1 -> 0.014 | K117: =K116/J116-1 -> 0.017
B118: 전력비 | D118: =IS!D25/10^6 -> 92.963855 | E118: =IS!E25/10^6 -> 73.104813 | F118: =IS!F25/10^6 -> 89.962703 | G118: =IS!G25/10^6 -> 81.198489 | H118: =G118*(1+H$30) -> 82.497665 | I118: =H118*(1+I$30) -> 83.652632 | J118: =I118*(1+J$30) -> 84.823769 | K118: =J118*(1+K$30) -> 86.265773 | L118: =K118*(1+L$30) -> 87.732291
B119: % of growth | D119: =D118/C118-1 -> #DIV/0! | E119: =E118/D118-1 -> -0.21362111 | F119: =F118/E118-1 -> 0.23059891 | G119: =G118/F118-1 -> -0.097420528 | H119: =H118/G118-1 -> 0.016 | I119: =I118/H118-1 -> 0.014 | J119: =J118/I118-1 -> 0.014 | K119: =K118/J118-1 -> 0.017
B120: 세금과공과금 | D120: =IS!D26/10^6 -> 161.84231 | E120: =IS!E26/10^6 -> 186.1719 | F120: =IS!F26/10^6 -> 210.77678 | G120: =IS!G26/10^6 -> 231.43617 | H120: =G120*(1+H$30) -> 235.13914 | I120: =H120*(1+I$30) -> 238.43109 | J120: =I120*(1+J$30) -> 241.76913 | K120: =J120*(1+K$30) -> 245.8792 | L120: =K120*(1+L$30) -> 250.05915
B121: % of growth | D121: =D120/C120-1 -> #DIV/0! | E121: =E120/D120-1 -> 0.150329 | F121: =F120/E120-1 -> 0.13216212 | G121: =G120/F120-1 -> 0.098015495 | H121: =H120/G120-1 -> 0.016 | I121: =I120/H120-1 -> 0.014 | J121: =J120/I120-1 -> 0.014 | K121: =K120/J120-1 -> 0.017 | L121: =L120/K120-1 -> 0.017
B122: 지급임차료 | D122: =IS!D28/10^6 -> 63.220033 | E122: =IS!E28/10^6 -> 33.74549 | F122: =IS!F28/10^6 -> 23.566706 | G122: =IS!G28/10^6 -> 42.35686 | H122: =G122*(1+H$30) -> 43.03457 | I122: =H122*(1+I$30) -> 43.637054 | J122: =I122*(1+J$30) -> 44.247972 | K122: =J122*(1+K$30) -> 45.000188 | L122: =K122*(1+L$30) -> 45.765191 | M122: 대표이사 개인부지에 대한 임대료 및 연구소 임차료로 구성
B123: % of growth | D123: =D122/C122-1 -> #DIV/0! | E123: =E122/D122-1 -> -0.46622157 | F123: =F122/E122-1 -> -0.30163391 | G123: =G122/F122-1 -> 0.79731779 | H123: =H122/G122-1 -> 0.016 | I123: =I122/H122-1 -> 0.014 | J123: =J122/I122-1 -> 0.014 | K123: =K122/J122-1 -> 0.017
...

Sheet 사업계획(원재료)
K2: 2018년-2022년 모델별 매출 판매 대수 및 단가 계획
K4: *) 모델명은 2015-2018년 대상회사 원장 상 판매된 모델 취합본이며, 핑크색으로 표기된 부분을 기입해 주시면 감사하겠습니다.
K5: - 적용 산업 구분 : 윤이사님께서 1차적으로 구분해 주셨으며, 아직 구분 완료되지 않은 모델에 대한 산업 구분 부탁 드립니다 (전기, 건설, 통선, 관공서, 항공, 기타로 구분
K6: - 모델이 단종 예정이거나 판매 계획이 없는 경우 '없음'이라고 기입 부탁 드립니다. | U6: 원재료비 상승률 | V6: 0.046 | AE6: 윤이사님과 인터뷰 이후 수정 확정된 확정된 사업 계획 안
U7: 전기향 고소작업차 평균 원재료비 /매출 | X7: =AVERAGE(W67,W74,W103) -> 0.61501618
K8: 베트남/ 필리핀 /중국 쪽 납품 활선차 : DHT 160S, DHT 180S/ 고소작업차: DHS 17AP, DHS 15AP | U8: 통신향 크레인 비율 | X8: =W85 -> 0.83777778
U9: 통신향 고소작업차 평균 원재료비 /매출 | X9: =AVERAGE(W48,W52,W57,W101,W113,W124,W135) -> 0.6170769 | AH9: 회사 제시수치와 와꾸 맞음
U10: 기타향 고소작업차 평균 원재료비/매출 | X10: =AVERAGE(W37,W109) -> 0.57787904
K12: 국내 | Q12: =Q17/Q16 -> 0.63179857 | R12: =R17/R16 -> 0.62925734 | S12: =S17/S16 -> 0.62663083 | T12: =T17/T16 -> 0.62400209 | U12: =U17/U16 -> 0.6214417
B13: 2015 | C13: 2016 | D13: 2017 | E13: 산업구분 | H13: DHS 950L | I13: 고소작업차 | L13: 판매국가 | M13: 모델명 | N13: 모델 구분 | O13: 적용 산업구분 | P13: 2018 | R13: =P13+1 -> 2019 | S13: =R13+1 -> 2020 | T13: =S13+1 -> 2021 | U13: =T13+1 -> 2022 | AE13: 모델 | AF13: 산업 | AK13: =AK17/AJ17-1 -> 0.037862249 | AL13: =AL17/AK17-1 -> 0.047909423 | AN13: 국내 제품 매출금액 | AY13: DHT 150S | AZ13: 전기
B14: ALPHA 12000 | C14: ALPHA 12000 | D14: DHT 150S | E14: 전기 | G14: ALPHA 12000 | H14: DHS 534 | I14: 고소작업차 | L14: 국내 | M14: ALPHA 12000 | N14: 크레인 | O14: 관공서 | P14: 판대대수(개) | Q14: =SUMIFS('사업계획(매출 확정본)'!S$12:S$113,'사업계획(매출 확정본)'!$M$12:$M$113,'사업계획(원재료)'!$M14,'사업계획(매출 확정본)'!$Q$12:$Q$113,'사업계획(원재료)'!$P14) -> 20 | R14: =SUMIFS('사업계획(매출 확정본)'!T$12:T$113,'사업계획(매출 확정본)'!$M$12:$M$113,'사업계획(원재료)'!$M14,'사업계획(매출 확정본)'!$Q$12:$Q$113,'사업계획(원재료)'!$P14) -> 30 | S14: =SUMIFS('사업계획(매출 확정본)'!U$12:U$113,'사업계획(매출 확정본)'!$M$12:$M$113,'사업계획(원재료)'!$M14,'사업계획(매출 확정본)'!$Q$12:$Q$113,'사업계획(원재료)'!$P14) -> 40 | T14: =SUMIFS('사업계획(매출 확정본)'!V$12:V$113,'사업계획(매출 확정본)'!$M$12:$M$113,'사업계획(원재료)'!$M14,'사업계획(매출 확정본)'!$Q$12:$Q$113,'사업계획(원재료)'!$P14) -> 50 | U14: =SUMIFS('사업계획(매출 확정본)'!W$12:W$113,'사업계획(매출 확정본)'!$M$12:$M$113,'사업계획(원재료)'!$M14,'사업계획(매출 확정본)'!$Q$12:$Q$113,'사업계획(원재료)'!$P14) -> 55 | AE14: 고소작업차 | AH14: 2018 | AI14: 2019 | AJ14: 2020 | AK14: 2021 | AL14: 2022 | AY14: DHS 433L | AZ14: 건설
D15: DHS 433L | E15: 건설 | H15: DHT 150AS | I15: 활선차 | M15: ALPHA 12000 | N15: 크레인 | O15: 관공서 | P15: 판매 단가(원) | Q15: 111500000 | R15: =ROUND(Q15*1.05,-5) -> 117100000 | S15: =ROUND(R15*1.05,-5) -> 123000000 | T15: =ROUND(S15*1.05,-5) -> 129200000 | U15: =ROUND(T15*1.05,-5) -> 135700000 | AE15: 고소작업차 | AF15: 전기 | AG15: 매출액(원) | AH15: =SUMIFS($Q$14:$Q$148,$P$14:$P$148,AG15,$O$14:$O$148,AF15,$N$14:$N$148,AE15) -> 23301900000 | AI15: =SUMIFS($R$14:$R$148,$P$14:$P$148,AG15,$O$14:$O$148,AF15,$N$14:$N$148,AE15) -> 26056900000 | AJ15: =SUMIFS($S$14:$S$148,$P$14:$P$148,AG15,$O$14:$O$148,AF15,$N$14:$N$148,AE15) -> 34826100000 | AK15: =SUMIFS($T$14:$T$148,$P$14:$P$148,AG15,$O$14:$O$148,AF15,$N$14:$N$148,AE15) -> 36651100000 | AL15: =SUMIFS($U$14:$U$148,$P$14:$P$148,AG15,$O$14:$O$148,AF15,$N$14:$N$148,AE15) -> 38738700000 | AN15: 고소 | AO15: =AH15+AH19+AH23+AH27+AH31+AH35 -> 49040800000 | AP15: =AI15+AI19+AI23+AI27+AI31+AI35 -> 62601700000 | AQ15: =AJ15+AJ19+AJ23+AJ27+AJ31+AJ35 -> 82093200000 | AR15: =AK15+AK19+AK23+AK27+AK31+AK35 -> 89632200000 | AY15: DHS 930 | AZ15: 통신
M16: ALPHA 12000 | N16: 크레인 | O16: 관공서 | P16: 매출액(원) | Q16: =SUMIFS('사업계획(매출 확정본)'!S$12:S$113,'사업계획(매출 확정본)'!$M$12:$M$113,'사업계획(원재료)'!$M16,'사업계획(매출 확정본)'!$Q$12:$Q$113,'사업계획(원재료)'!$P16) -> 2230000000 | R16: =SUMIFS('사업계획(매출 확정본)'!T$12:T$113,'사업계획(매출 확정본)'!$M$12:$M$113,'사업계획(원재료)'!$M16,'사업계획(매출 확정본)'!$Q$12:$Q$113,'사업계획(원재료)'!$P16) -> 3513000000 | S16: =SUMIFS('사업계획(매출 확정본)'!U$12:U$113,'사업계획(매출 확정본)'!$M$12:$M$113,'사업계획(원재료)'!$M16,'사업계획(매출 확정본)'!$Q$12:$Q$113,'사업계획(원재료)'!$P16) -> 4920000000 | T16: =SUMIFS('사업계획(매출 확정본)'!V$12:V$113,'사업계획(매출 확정본)'!$M$12:$M$113,'사업계획(원재료)'!$M16,'사업계획(매출 확정본)'!$Q$12:$Q$113,'사업계획(원재료)'!$P16) -> 6460000000 | U16: =SUMIFS('사업계획(매출 확정본)'!W$12:W$113,'사업계획(매출 확정본)'!$M$12:$M$113,'사업계획(원재료)'!$M16,'사업계획(매출 확정본)'!$Q$12:$Q$113,'사업계획(원재료)'!$P16) -> 7463500000 | AE16: 고소작업차 | AF16: 전기 | AG16: 판대대수(개) | AH16: =SUMIFS($Q$14:$Q$148,$P$14:$P$148,AG16,$O$14:$O$148,AF16,$N$14:$N$148,AE16) -> 476 | AI16: =SUMIFS($R$14:$R$148,$P$14:$P$148,AG16,$O$14:$O$148,AF16,$N$14:$N$148,AE16) -> 508 | AJ16: =SUMIFS(S$14:S$148,$P$14:$P$148,$AG$16,$O$14:$O$148,$AF$16,$N$14:$N$148,$AE$16) -> 571 | AK16: =SUMIFS(T$14:T$148,$P$14:$P$148,$AG$16,$O$14:$O$148,$AF$16,$N$14:$N$148,$AE$16) -> 579 | AL16: =SUMIFS(U$14:U$148,$P$14:$P$148,$AG$16,$O$14:$O$148,$AF$16,$N$14:$N$148,$AE$16) -> 584 | AN16: 크레인 | AO16: =SUM(AH39,AH43,AH47,AH51,AH55,AH59) -> 9332000000 | AP16: =SUM(AI39,AI43,AI47,AI51,AI55,AI59) -> 13558000000 | AQ16: =SUM(AJ39,AJ43,AJ47,AJ51,AJ55,AJ59) -> 19319500000 | AR16: =SUM(AK39,AK43,AK47,AK51,AK55,AK59) -> 22827900000
M17: ALPHA 12000 | N17: 크레인 | O17: 관공서 | P17: 원재료비(원) | Q17: =VLOOKUP($M$14,'제품별 원재료비 '!$O$4:$S$48,5,FALSE)*Q14 -> 1408910800 | R17: =Q17*(1+$V$6)/Q14*R14 -> 2.210581e+09 | S17: =R17*(1+$V$6)/R14*S14 -> 3.0830237e+09 | T17: =S17*(1+$V$6)/S14*T14 -> 4.0310535e+09 | U17: =T17*(1+$V$6)/T14*U14 -> 4.6381301e+09 | AE17: 고소작업차 | AF17: 전기 | AG17: 판매 단가(원) | AH17: =AH15/AH16 -> 48953571 | AI17: =AI15/AI16 -> 51293110 | AJ17: =AJ15/AJ16 -> 60991419 | AK17: =AK15/AK16 -> 63300691 | AL17: =AL15/AL16 -> 66333390
B18: ALPHA 5000 | C18: AUGER CRANE(5TON) | D18: DHS 930 | E18: 통신 | G18: ALPHA 5000 | H18: DHS 950L | I18: 고소작업차 | L18: 국내 | M18: ALPHA 5000 | N18: 크레인 | O18: =VLOOKUP(M18,$AY$13:$AZ$131,2,FALSE) -> 관공서 | P18: 판대대수(개) | Q18: =SUMIFS('사업계획(매출 확정본)'!S$12:S$113,'사업계획(매출 확정본)'!$M$12:$M$113,'사업계획(원재료)'!$M18,'사업계획(매출 확정본)'!$Q$12:$Q$113,'사업계획(원재료)'!$P18) -> 4 | R18: =SUMIFS('사업계획(매출 확정본)'!T$12:T$113,'사업계획(매출 확정본)'!$M$12:$M$113,'사업계획(원재료)'!$M18,'사업계획(매출 확정본)'!$Q$12:$Q$113,'사업계획(원재료)'!$P18) -> 10 | S18: =SUMIFS('사업계획(매출 확정본)'!U$12:U$113,'사업계획(매출 확정본)'!$M$12:$M$113,'사업계획(원재료)'!$M18,'사업계획(매출 확정본)'!$Q$12:$Q$113,'사업계획(원재료)'!$P18) -> 15 | T18: =SUMIFS('사업계획(매출 확정본)'!V$12:V$113,'사업계획(매출 확정본)'!$M$12:$M$113,'사업계획(원재료)'!$M18,'사업계획(매출 확정본)'!$Q$12:$Q$113,'사업계획(원재료)'!$P18) -> 20 | U18: =SUMIFS('사업계획(매출 확정본)'!W$12:W$113,'사업계획(매출 확정본)'!$M$12:$M$113,'사업계획(원재료)'!$M18,'사업계획(매출 확정본)'!$Q$12:$Q$113,'사업계획(원재료)'!$P18) -> 22 | AD18: =AH18+AH22+AH26+AH30+AH34+AH38 -> 3.0274869e+10 | AE18: 고소작업차 | AF18: 전기 | AG18: 원재료비(원) | AH18: =SUMIFS(Q$14:Q$149,$N$14:$N$149,$AE18,$O$14:$O$149,$AF18,$P$14:$P$149,$AG18) -> 1.3979056e+10 | AI18: =SUMIFS(R$14:R$149,$N$14:$N$149,$AE18,$O$14:$O$149,$AF18,$P$14:$P$149,$AG18) -> 1.5562344e+10 | AJ18: =SUMIFS(S$14:S$149,$N$14:$N$149,$AE18,$O$14:$O$149,$AF18,$P$14:$P$149,$AG18) -> 2.0729476e+10 | AK18: =SUMIFS(T$14:T$149,$N$14:$N$149,$AE18,$O$14:$O$149,$AF18,$P$14:$P$149,$AG18) -> 2.1723504e+10 | AL18: =SUMIFS(U$14:U$149,$N$14:$N$149,$AE18,$O$14:$O$149,$AF18,$P$14:$P$149,$AG18) -> 2.2875552e+10 | AN18: 활선 | AO18: =SUM(AH63,AH67,AH71,AH75,AH79,AH83) -> 41420000000 | AP18: =SUM(AI63,AI67,AI71,AI75,AI79,AI83) -> 50014500000 | AQ18: =SUM(AJ63,AJ67,AJ71,AJ75,AJ79,AJ83) -> 59321500000 | AR18: =SUM(AK63,AK67,AK71,AK75,AK79,AK83) -> 65377500000 | AY18: DHS 950L | AZ18: 통신
D19: DHS 950L | E19: 통신 | H19: DHS 534 | I19: 고소작업차 | M19: ALPHA 5000 | N19: 크레인 | O19: =VLOOKUP(M19,$AY$13:$AZ$131,2,FALSE) -> 관공서 | P19: 판매 단가(원) | Q19: 74500000 | R19: =ROUND(Q19*1.05,-5) -> 78200000 | S19: =ROUND(R19*1.05,-5) -> 82100000 | T19: =ROUND(S19*1.05,-5) -> 86200000 | U19: =ROUND(T19*1.05,-5) -> 90500000 | AE19: 고소작업차 | AF19: 통신 | AG19: 매출액(원) | AH19: =SUMIFS(Q$14:Q$148,$P$14:$P$148,$AG$19,$O$14:$O$148,$AF$19,$N$14:$N$148,$AE$19) -> 21847000000 | AI19: =SUMIFS(R$14:R$148,$P$14:$P$148,$AG$19,$O$14:$O$148,$AF$19,$N$14:$N$148,$AE$19) -> 30808300000 | AJ19: =SUMIFS(S$14:S$148,$P$14:$P$148,$AG$19,$O$14:$O$148,$AF$19,$N$14:$N$148,$AE$19) -> 39199100000 | AK19: =SUMIFS(T$14:T$148,$P$14:$P$148,$AG$19,$O$14:$O$148,$AF$19,$N$14:$N$148,$AE$19) -> 43024100000 | AL19: =SUMIFS(U$14:U$148,$P$14:$P$148,$AG$19,$O$14:$O$148,$AF$19,$N$14:$N$148,$AE$19) -> 46856200000 | AN19: 인터뷰에 따르면 전기 고소작업차는 약 4천만원 원재료. 이를 반영 | AY19: DHS 1200L | AZ19: 통신
M20: ALPHA 5000 | N20: 크레인 | O20: 관공서 | P20: 매출액(원) | Q20: =SUMIFS('사업계획(매출 확정본)'!S$12:S$113,'사업계획(매출 확정본)'!$M$12:$M$113,'사업계획(원재료)'!$M20,'사업계획(매출 확정본)'!$Q$12:$Q$113,'사업계획(원재료)'!$P20) -> 298000000 | R20: =SUMIFS('사업계획(매출 확정본)'!T$12:T$113,'사업계획(매출 확정본)'!$M$12:$M$113,'사업계획(원재료)'!$M20,'사업계획(매출 확정본)'!$Q$12:$Q$113,'사업계획(원재료)'!$P20) -> 782000000 | S20: =SUMIFS('사업계획(매출 확정본)'!U$12:U$113,'사업계획(매출 확정본)'!$M$12:$M$113,'사업계획(원재료)'!$M20,'사업계획(매출 확정본)'!$Q$12:$Q$113,'사업계획(원재료)'!$P20) -> 1231500000 | T20: =SUMIFS('사업계획(매출 확정본)'!V$12:V$113,'사업계획(매출 확정본)'!$M$12:$M$113,'사업계획(원재료)'!$M20,'사업계획(매출 확정본)'!$Q$12:$Q$113,'사업계획(원재료)'!$P20) -> 1724000000 | U20: =SUMIFS('사업계획(매출 확정본)'!W$12:W$113,'사업계획(매출 확정본)'!$M$12:$M$113,'사업계획(원재료)'!$M20,'사업계획(매출 확정본)'!$Q$12:$Q$113,'사업계획(원재료)'!$P20) -> 1991000000 | AE20: 고소작업차 | AF20: 통신 | AG20: 판대대수(개) | AH20: =SUMIFS(Q$14:Q$148,$P$14:$P$148,$AG$20,$O$14:$O$148,$AF$20,$N$14:$N$148,$AE$20) -> 606 | AI20: =SUMIFS(R$14:R$148,$P$14:$P$148,$AG$20,$O$14:$O$148,$AF$20,$N$14:$N$148,$AE$20) -> 782 | AJ20: =SUMIFS(S$14:S$148,$P$14:$P$148,$AG$20,$O$14:$O$148,$AF$20,$N$14:$N$148,$AE$20) -> 939 | AK20: =SUMIFS(T$14:T$148,$P$14:$P$148,$AG$20,$O$14:$O$148,$AF$20,$N$14:$N$148,$AE$20) -> 981 | AL20: =SUMIFS(U$14:U$148,$P$14:$P$148,$AG$20,$O$14:$O$148,$AF$20,$N$14:$N$148,$AE$20) -> 1018
M21: ALPHA 5000 | N21: 크레인 | O21: 관공서 | P21: 원재료비(원) | Q21: =VLOOKUP(M19,'제품별 원재료비 '!$O$4:$S$48,5,FALSE)*Q18 -> 213778560 | R21: =Q21*(1+$V$6)/Q18*R18 -> 5.5903093e+08 | S21: =R21*(1+$V$6)/R18*S18 -> 8.7711954e+08 | T21: =S21*(1+$V$6)/S18*T18 -> 1.2232894e+09 | U21: =T21*(1+$V$6)/T18*U18 -> 1.4075168e+09 | AE21: 고소작업차 | AF21: 통신 | AG21: 판매 단가(원) | AH21: =AH19/AH20 -> 36051155 | AI21: =AI19/AI20 -> 39396803 | AJ21: =AJ19/AJ20 -> 41745580 | AK21: =AK19/AK20 -> 43857390 | AL21: =AL19/AL20 -> 46027701 | AM21: =AL21/AK21-1 -> 0.049485638
B22: DHS 15AP | C22: DHS 190SKY | D22: DHM 1300S2 | E22: 기타 | G22: DHS 15AP | H22: DHS 950L | I22: 고소작업차 | L22: 국내 | M22: DHS 15AP | N22: 고소작업차 | O22: 전기 | P22: 판대대수(개) | Q22: =SUMIFS('사업계획(매출 확정본)'!S$12:S$113,'사업계획(매출 확정본)'!$M$12:$M$113,'사업계획(원재료)'!$M22,'사업계획(매출 확정본)'!$Q$12:$Q$113,'사업계획(원재료)'!$P22) -> 169 | R22: =SUMIFS('사업계획(매출 확정본)'!T$12:T$113,'사업계획(매출 확정본)'!$M$12:$M$113,'사업계획(원재료)'!$M22,'사업계획(매출 확정본)'!$Q$12:$Q$113,'사업계획(원재료)'!$P22) -> 185 | S22: =SUMIFS('사업계획(매출 확정본)'!U$12:U$113,'사업계획(매출 확정본)'!$M$12:$M$113,'사업계획(원재료)'!$M22,'사업계획(매출 확정본)'!$Q$12:$Q$113,'사업계획(원재료)'!$P22) -> 210 | T22: =SUMIFS('사업계획(매출 확정본)'!V$12:V$113,'사업계획(매출 확정본)'!$M$12:$M$113,'사업계획(원재료)'!$M22,'사업계획(매출 확정본)'!$Q$12:$Q$113,'사업계획(원재료)'!$P22) -> 210 | U22: =SUMIFS('사업계획(매출 확정본)'!W$12:W$113,'사업계획(매출 확정본)'!$M$12:$M$113,'사업계획(원재료)'!$M22,'사업계획(매출 확정본)'!$Q$12:$Q$113,'사업계획(원재료)'!$P22) -> 210 | W22: 179 | X22: 200 | Y22: 230 | Z22: 235 | AA22: 240 | AE22: 고소작업차 | AF22: 통신 | AG22: 원재료비(원) | AH22: =SUMIFS(Q$14:Q$149,$N$14:$N$149,$AE22,$O$14:$O$149,$AF22,$P$14:$P$149,$AG22) -> 1.419651e+10 | AI22: =SUMIFS(R$14:R$149,$N$14:$N$149,$AE22,$O$14:$O$149,$AF22,$P$14:$P$149,$AG22) -> 1.97953e+10 | AJ22: =SUMIFS(S$14:S$149,$N$14:$N$149,$AE22,$O$14:$O$149,$AF22,$P$14:$P$149,$AG22) -> 2.5016964e+10 | AK22: =SUMIFS(T$14:T$149,$N$14:$N$149,$AE22,$O$14:$O$149,$AF22,$P$14:$P$149,$AG22) -> 2.7278645e+10 | AL22: =SUMIFS(U$14:U$149,$N$14:$N$149,$AE22,$O$14:$O$149,$AF22,$P$14:$P$149,$AG22) -> 2.9555014e+10 | AY22: DHS 15AP | AZ22: 전기
D23: 17-BAK-14 장비실 개선 공사 | E23: 항공 | H23: DHS 950L | I23: 고소작업차 | M23: DHS 15AP | N23: 고소작업차 | O23: 전기 | P23: 판매 단가(원) | Q23: 51500000 | R23: =ROUND(Q23*1.05,-5) -> 54100000 | S23: =ROUND(R23*1.05,-5) -> 56800000 | T23: =ROUND(S23*1.05,-5) -> 59600000 | U23: =ROUND(T23*1.05,-5) -> 62600000 | V23: =S23/R23-1 -> 0.049907579 | AE23: 고소작업차 | AF23: 관공서 | AG23: 매출액(원) | AH23: =SUMIFS(Q$14:Q$148,$P$14:$P$148,$AG$23,$O$14:$O$148,$AF$23,$N$14:$N$148,$AE$23) -> 554400000 | AI23: =SUMIFS(R$14:R$148,$P$14:$P$148,$AG$23,$O$14:$O$148,$AF$23,$N$14:$N$148,$AE$23) -> 970000000 | AJ23: =SUMIFS(S$14:S$148,$P$14:$P$148,$AG$23,$O$14:$O$148,$AF$23,$N$14:$N$148,$AE$23) -> 1528500000 | AK23: =SUMIFS(T$14:T$148,$P$14:$P$148,$AG$23,$O$14:$O$148,$AF$23,$N$14:$N$148,$AE$23) -> 2140000000 | AL23: =SUMIFS(U$14:U$148,$P$14:$P$148,$AG$23,$O$14:$O$148,$AF$23,$N$14:$N$148,$AE$23) -> 2810000000 | AY23: DHS 930(R) | AZ23: 통신
M24: DHS 15AP | N24: 고소작업차 | O24: 전기 | P24: 매출액(원) | Q24: =SUMIFS('사업계획(매출 확정본)'!S$12:S$113,'사업계획(매출 확정본)'!$M$12:$M$113,'사업계획(원재료)'!$M24,'사업계획(매출 확정본)'!$Q$12:$Q$113,'사업계획(원재료)'!$P24) -> 8703500000 | R24: =SUMIFS('사업계획(매출 확정본)'!T$12:T$113,'사업계획(매출 확정본)'!$M$12:$M$113,'사업계획(원재료)'!$M24,'사업계획(매출 확정본)'!$Q$12:$Q$113,'사업계획(원재료)'!$P24) -> 10008500000 | S24: =SUMIFS('사업계획(매출 확정본)'!U$12:U$113,'사업계획(매출 확정본)'!$M$12:$M$113,'사업계획(원재료)'!$M24,'사업계획(매출 확정본)'!$Q$12:$Q$113,'사업계획(원재료)'!$P24) -> 11928000000 | T24: =SUMIFS('사업계획(매출 확정본)'!V$12:V$113,'사업계획(매출 확정본)'!$M$12:$M$113,'사업계획(원재료)'!$M24,'사업계획(매출 확정본)'!$Q$12:$Q$113,'사업계획(원재료)'!$P24) -> 12516000000 | U24: =SUMIFS('사업계획(매출 확정본)'!W$12:W$113,'사업계획(매출 확정본)'!$M$12:$M$113,'사업계획(원재료)'!$M24,'사업계획(매출 확정본)'!$Q$12:$Q$113,'사업계획(원재료)'!$P24) -> 13146000000 | AE24: 고소작업차 | AF24: 관공서 | AG24: 판대대수(개) | AH24: =SUMIFS(Q$14:Q$148,$P$14:$P$148,$AG$24,$O$14:$O$148,$AF$24,$N$14:$N$148,$AE$24) -> 6 | AI24: =SUMIFS(R$14:R$148,$P$14:$P$148,$AG$24,$O$14:$O$148,$AF$24,$N$14:$N$148,$AE$24) -> 10 | AJ24: =SUMIFS(S$14:S$148,$P$14:$P$148,$AG$24,$O$14:$O$148,$AF$24,$N$14:$N$148,$AE$24) -> 15 | AK24: =SUMIFS(T$14:T$148,$P$14:$P$148,$AG$24,$O$14:$O$148,$AF$24,$N$14:$N$148,$AE$24) -> 20 | AL24: =SUMIFS(U$14:U$148,$P$14:$P$148,$AG$24,$O$14:$O$148,$AF$24,$N$14:$N$148,$AE$24) -> 25
M25: DHS 15AP | N25: 고소작업차 | O25: 전기 | P25: 원재료비(원) | Q25: =VLOOKUP(M22,'제품별 원재료비 '!$O$4:$S$48,5,FALSE)*Q22 -> 5118668620 | R25: =Q25*(1+$V$6)/Q22*R22 -> 5.861027e+09 | S25: =R25*(1+$V$6)/R22*S22 -> 6.9590983e+09 | T25: =S25*(1+$V$6)/S22*T22 -> 7.2792169e+09 | U25: =T25*(1+$V$6)/T22*U22 -> 7.6140608e+09 | AE25: 고소작업차 | AF25: 관공서 | AG25: 판매 단가(원) | AH25: =AH23/AH24 -> 92400000 | AI25: =AI23/AI24 -> 97000000 | AJ25: =AJ23/AJ24 -> 101900000 | AK25: =AK23/AK24 -> 107000000 | AL25: =AL23/AL24 -> 112400000
B26: DHS 17AP | C26: DHS 19AP | D26: AUGER CRANE(5TON) | E26: 통신 | G26: DHS 17AP | H26: DHS 15AP | I26: 고소작업차 | L26: 국내 | M26: DHS 17AP | N26: 고소작업차 | O26: 전기 | P26: 판대대수(개) | Q26: =SUMIFS('사업계획(매출 확정본)'!S$12:S$113,'사업계획(매출 확정본)'!$M$12:$M$113,'사업계획(원재료)'!$M26,'사업계획(매출 확정본)'!$Q$12:$Q$113,'사업계획(원재료)'!$P26) -> 39 | R26: =SUMIFS('사업계획(매출 확정본)'!T$12:T$113,'사업계획(매출 확정본)'!$M$12:$M$113,'사업계획(원재료)'!$M26,'사업계획(매출 확정본)'!$Q$12:$Q$113,'사업계획(원재료)'!$P26) -> 40 | S26: =SUMIFS('사업계획(매출 확정본)'!U$12:U$113,'사업계획(매출 확정본)'!$M$12:$M$113,'사업계획(원재료)'!$M26,'사업계획(매출 확정본)'!$Q$12:$Q$113,'사업계획(원재료)'!$P26) -> 50 | T26: =SUMIFS('사업계획(매출 확정본)'!V$12:V$113,'사업계획(매출 확정본)'!$M$12:$M$113,'사업계획(원재료)'!$M26,'사업계획(매출 확정본)'!$Q$12:$Q$113,'사업계획(원재료)'!$P26) -> 55 | U26: =SUMIFS('사업계획(매출 확정본)'!W$12:W$113,'사업계획(매출 확정본)'!$M$12:$M$113,'사업계획(원재료)'!$M26,'사업계획(매출 확정본)'!$Q$12:$Q$113,'사업계획(원재료)'!$P26) -> 55 | W26: 49 | X26: 55 | Y26: 70 | Z26: 80 | AA26: 85 | AE26: 고소작업차 | AF26: 관공서 | AG26: 원재료비(원) | AH26: =SUMIFS(Q$14:Q$149,$N$14:$N$149,$AE26,$O$14:$O$149,$AF26,$P$14:$P$149,$AG26) -> 291123360 | AI26: =SUMIFS(R$14:R$149,$N$14:$N$149,$AE26,$O$14:$O$149,$AF26,$P$14:$P$149,$AG26) -> 5.0752506e+08 | AJ26: =SUMIFS(S$14:S$149,$N$14:$N$149,$AE26,$O$14:$O$149,$AF26,$P$14:$P$149,$AG26) -> 7.9630682e+08 | AK26: =SUMIFS(T$14:T$149,$N$14:$N$149,$AE26,$O$14:$O$149,$AF26,$P$14:$P$149,$AG26) -> 1.1105826e+09 | AL26: =SUMIFS(U$14:U$149,$N$14:$N$149,$AE26,$O$14:$O$149,$AF26,$P$14:$P$149,$AG26) -> 1.4520867e+09 | AY26: DHT 150AS | AZ26: 전기
D27: DHT 110 | E27: 전기 | H27: DHS 930 | I27: 고소작업차 | M27: DHS 17AP | N27: 고소작업차 | O27: 전기 | P27: 판매 단가(원) | Q27: 55600000 | R27: =ROUND(Q27*1.05,-5) -> 58400000 | S27: =ROUND(R27*1.05,-5) -> 61300000 | T27: =ROUND(S27*1.05,-5) -> 64400000 | U27: =ROUND(T27*1.05,-5) -> 67600000 | V27: =S27/R27-1 -> 0.049657534 | W27: =Q29/Q28 -> 0.56558777 | AE27: 고소작업차 | AF27: 건설 | AG27: 매출액(원) | AH27: =SUMIFS(Q$14:Q$148,$P$14:$P$148,$AG$27,$O$14:$O$148,$AF$27,$N$14:$N$148,$AE$27) -> 0 | AI27: =SUMIFS(R$14:R$148,$P$14:$P$148,$AG$27,$O$14:$O$148,$AF$27,$N$14:$N$148,$AE$27) -> 0 | AJ27: =SUMIFS(S$14:S$148,$P$14:$P$148,$AG$27,$O$14:$O$148,$AF$27,$N$14:$N$148,$AE$27) -> 0 | AK27: =SUMIFS(T$14:T$148,$P$14:$P$148,$AG$27,$O$14:$O$148,$AF$27,$N$14:$N$148,$AE$27) -> 0 | AL27: =SUMIFS(U$14:U$148,$P$14:$P$148,$AG$27,$O$14:$O$148,$AF$27,$N$14:$N$148,$AE$27) -> 0 | AY27: DHT 160S | AZ27: 전기
M28: DHS 17AP | N28: 고소작업차 | O28: 전기 | P28: 매출액(원) | Q28: =SUMIFS('사업계획(매출 확정본)'!S$12:S$113,'사업계획(매출 확정본)'!$M$12:$M$113,'사업계획(원재료)'!$M28,'사업계획(매출 확정본)'!$Q$12:$Q$113,'사업계획(원재료)'!$P28) -> 2168400000 | R28: =SUMIFS('사업계획(매출 확정본)'!T$12:T$113,'사업계획(매출 확정본)'!$M$12:$M$113,'사업계획(원재료)'!$M28,'사업계획(매출 확정본)'!$Q$12:$Q$113,'사업계획(원재료)'!$P28) -> 2336000000 | S28: =SUMIFS('사업계획(매출 확정본)'!U$12:U$113,'사업계획(매출 확정본)'!$M$12:$M$113,'사업계획(원재료)'!$M28,'사업계획(매출 확정본)'!$Q$12:$Q$113,'사업계획(원재료)'!$P28) -> 3065000000 | T28: =SUMIFS('사업계획(매출 확정본)'!V$12:V$113,'사업계획(매출 확정본)'!$M$12:$M$113,'사업계획(원재료)'!$M28,'사업계획(매출 확정본)'!$Q$12:$Q$113,'사업계획(원재료)'!$P28) -> 3542000000 | U28: =SUMIFS('사업계획(매출 확정본)'!W$12:W$113,'사업계획(매출 확정본)'!$M$12:$M$113,'사업계획(원재료)'!$M28,'사업계획(매출 확정본)'!$Q$12:$Q$113,'사업계획(원재료)'!$P28) -> 3718000000 | AE28: 고소작업차 | AF28: 건설 | AG28: 판대대수(개) | AH28: =SUMIFS(Q$14:Q$148,$P$14:$P$148,$AG$28,$O$14:$O$148,$AF$27,$N$14:$N$148,$AE$27) -> 0 | AI28: =SUMIFS(R$14:R$148,$P$14:$P$148,$AG$28,$O$14:$O$148,$AF$27,$N$14:$N$148,$AE$27) -> 0 | AJ28: =SUMIFS(S$14:S$148,$P$14:$P$148,$AG$28,$O$14:$O$148,$AF$27,$N$14:$N$148,$AE$27) -> 0 | AK28: =SUMIFS(T$14:T$148,$P$14:$P$148,$AG$28,$O$14:$O$148,$AF$27,$N$14:$N$148,$AE$27) -> 0 | AL28: =SUMIFS(U$14:U$148,$P$14:$P$148,$AG$28,$O$14:$O$148,$AF$27,$N$14:$N$148,$AE$27) -> 0
M29: DHS 17AP | N29: 고소작업차 | O29: 전기 | P29: 원재료비(원) | Q29: =VLOOKUP(M26,'제품별 원재료비 '!$O$4:$S$48,5,FALSE)*Q26 -> 1226420520 | R29: =Q29*(1+$V$6)/Q26*R26 -> 1.3157291e+09 | S29: =R29*(1+$V$6)/R26*S26 -> 1.7203158e+09 | T29: =S29*(1+$V$6)/S26*T26 -> 1.9793953e+09 | U29: =T29*(1+$V$6)/T26*U26 -> 2.0704475e+09 | AE29: 고소작업차 | AF29: 건설 | AG29: 판매 단가(원) | AH29: =AH27/AH28 -> #DIV/0! | AI29: =AI27/AI28 -> #DIV/0! | AJ29: =AJ27/AJ28 -> #DIV/0! | AK29: =AK27/AK28 -> #DIV/0! | AL29: =AL27/AL28 -> #DIV/0!
B30: DHS 1800 | C30: DHS 280AP | D30: DHT 105S | E30: 전기 | G30: DHS 1800 | H30: DHS 950L | I30: 고소작업차 | L30: 국내 | M30: DHS 1800 | N30: 고소작업차 | O30: 관공서 | P30: 판대대수(개) | Q30: =SUMIFS('사업계획(매출 확정본)'!S$12:S$113,'사업계획(매출 확정본)'!$M$12:$M$113,'사업계획(원재료)'!$M30,'사업계획(매출 확정본)'!$Q$12:$Q$113,'사업계획(원재료)'!$P30) -> 6 | R30: =SUMIFS('사업계획(매출 확정본)'!T$12:T$113,'사업계획(매출 확정본)'!$M$12:$M$113,'사업계획(원재료)'!$M30,'사업계획(매출 확정본)'!$Q$12:$Q$113,'사업계획(원재료)'!$P30) -> 10 | S30: =SUMIFS('사업계획(매출 확정본)'!U$12:U$113,'사업계획(매출 확정본)'!$M$12:$M$113,'사업계획(원재료)'!$M30,'사업계획(매출 확정본)'!$Q$12:$Q$113,'사업계획(원재료)'!$P30) -> 15 | T30: =SUMIFS('사업계획(매출 확정본)'!V$12:V$113,'사업계획(매출 확정본)'!$M$12:$M$113,'사업계획(원재료)'!$M30,'사업계획(매출 확정본)'!$Q$12:$Q$113,'사업계획(원재료)'!$P30) -> 20 | U30: =SUMIFS('사업계획(매출 확정본)'!W$12:W$113,'사업계획(매출 확정본)'!$M$12:$M$113,'사업계획(원재료)'!$M30,'사업계획(매출 확정본)'!$Q$12:$Q$113,'사업계획(원재료)'!$P30) -> 25 | AE30: 고소작업차 | AF30: 건설 | AG30: 원재료비(원) | AH30: =SUMIFS(Q$14:Q$149,$N$14:$N$149,$AE30,$O$14:$O$149,$AF30,$P$14:$P$149,$AG30) -> 0 | AI30: =SUMIFS(R$14:R$149,$N$14:$N$149,$AE30,$O$14:$O$149,$AF30,$P$14:$P$149,$AG30) -> 0 | AJ30: =SUMIFS(S$14:S$149,$N$14:$N$149,$AE30,$O$14:$O$149,$AF30,$P$14:$P$149,$AG30) -> 0 | AK30: =SUMIFS(T$14:T$149,$N$14:$N$149,$AE30,$O$14:$O$149,$AF30,$P$14:$P$149,$AG30) -> 0 | AL30: =SUMIFS(U$14:U$149,$N$14:$N$149,$AE30,$O$14:$O$149,$AF30,$P$14:$P$149,$AG30) -> 0 | AY30: DHS 190SKY | AZ30: 기타
D31: DHT 180S | E31: 전기 | H31: DHS 1200L | I31: 고소작업차 | M31: DHS 1800 | N31: 고소작업차 | O31: 관공서 | P31: 판매 단가(원) | Q31: 92400000 | R31: =ROUND(Q31*1.05,-5) -> 97000000 | S31: =ROUND(R31*1.05,-5) -> 101900000 | T31: =ROUND(S31*1.05,-5) -> 107000000 | U31: =ROUND(T31*1.05,-5) -> 112400000 | AE31: 고소작업차 | AF31: 항공 | AG31: 매출액(원) | AH31: =SUMIFS(Q$14:Q$148,$P$14:$P$148,$AG$31,$O$14:$O$148,$AF$31,$N$14:$N$148,$AE$31) -> 0 | AI31: =SUMIFS(R$14:R$148,$P$14:$P$148,$AG$31,$O$14:$O$148,$AF$31,$N$14:$N$148,$AE$31) -> 0 | AJ31: =SUMIFS(S$14:S$148,$P$14:$P$148,$AG$31,$O$14:$O$148,$AF$31,$N$14:$N$148,$AE$31) -> 0 | AK31: =SUMIFS(T$14:T$148,$P$14:$P$148,$AG$31,$O$14:$O$148,$AF$31,$N$14:$N$148,$AE$31) -> 0 | AL31: =SUMIFS(U$14:U$148,$P$14:$P$148,$AG$31,$O$14:$O$148,$AF$31,$N$14:$N$148,$AE$31) -> 0 | AY31: DHS 950L(R) | AZ31: 통신
M32: DHS 1800 | N32: 고소작업차 | O32: 관공서 | P32: 매출액(원) | Q32: =SUMIFS('사업계획(매출 확정본)'!S$12:S$113,'사업계획(매출 확정본)'!$M$12:$M$113,'사업계획(원재료)'!$M32,'사업계획(매출 확정본)'!$Q$12:$Q$113,'사업계획(원재료)'!$P32) -> 554400000 | R32: =SUMIFS('사업계획(매출 확정본)'!T$12:T$113,'사업계획(매출 확정본)'!$M$12:$M$113,'사업계획(원재료)'!$M32,'사업계획(매출 확정본)'!$Q$12:$Q$113,'사업계획(원재료)'!$P32) -> 970000000 | S32: =SUMIFS('사업계획(매출 확정본)'!U$12:U$113,'사업계획(매출 확정본)'!$M$12:$M$113,'사업계획(원재료)'!$M32,'사업계획(매출 확정본)'!$Q$12:$Q$113,'사업계획(원재료)'!$P32) -> 1528500000 | T32: =SUMIFS('사업계획(매출 확정본)'!V$12:V$113,'사업계획(매출 확정본)'!$M$12:$M$113,'사업계획(원재료)'!$M32,'사업계획(매출 확정본)'!$Q$12:$Q$113,'사업계획(원재료)'!$P32) -> 2140000000 | U32: =SUMIFS('사업계획(매출 확정본)'!W$12:W$113,'사업계획(매출 확정본)'!$M$12:$M$113,'사업계획(원재료)'!$M32,'사업계획(매출 확정본)'!$Q$12:$Q$113,'사업계획(원재료)'!$P32) -> 2810000000 | AE32: 고소작업차 | AF32: 항공 | AG32: 판대대수(개) | AH32: =SUMIFS(Q$14:Q$148,$P$14:$P$148,$AG$32,$O$14:$O$148,$AF$31,$N$14:$N$148,$AE$31) -> 0 | AI32: =SUMIFS(R$14:R$148,$P$14:$P$148,$AG$32,$O$14:$O$148,$AF$31,$N$14:$N$148,$AE$31) -> 0 | AJ32: =SUMIFS(S$14:S$148,$P$14:$P$148,$AG$32,$O$14:$O$148,$AF$31,$N$14:$N$148,$AE$31) -> 0 | AK32: =SUMIFS(T$14:T$148,$P$14:$P$148,$AG$32,$O$14:$O$148,$AF$31,$N$14:$N$148,$AE$31) -> 0 | AL32: =SUMIFS(U$14:U$148,$P$14:$P$148,$AG$32,$O$14:$O$148,$AF$31,$N$14:$N$148,$AE$31) -> 0
M33: DHS 1800 | N33: 고소작업차 | O33: 관공서 | P33: 원재료비(원) | Q33: =VLOOKUP(M30,'제품별 원재료비 '!$O$4:$S$48,5,FALSE)*Q30 -> 291123360 | R33: =Q33*(1+$V$6)/Q30*R30 -> 5.0752506e+08 | S33: =R33*(1+$V$6)/R30*S30 -> 7.9630682e+08 | T33: =S33*(1+$V$6)/S30*T30 -> 1.1105826e+09 | U33: =T33*(1+$V$6)/T30*U30 -> 1.4520867e+09 | AE33: 고소작업차 | AF33: 항공 | AG33: 판매 단가(원) | AH33: =AH31/AH32 -> #DIV/0! | AI33: =AI31/AI32 -> #DIV/0! | AJ33: =AJ31/AJ32 -> #DIV/0! | AK33: =AK31/AK32 -> #DIV/0! | AL33: =AL31/AL32 -> #DIV/0!
B34: DHS 190SKY | C34: DHS 433L | D34: 방향지시등 | E34: 관공서 | G34: DHS 190SKY | H34: DHT 150AS | I34: 활선차 | L34: 국내 | M34: DHS 190SKY | N34: 고소작업차 | O34: 기타 | P34: 판대대수(개) | Q34: =SUMIFS('사업계획(매출 확정본)'!S$12:S$113,'사업계획(매출 확정본)'!$M$12:$M$113,'사업계획(원재료)'!$M34,'사업계획(매출 확정본)'!$Q$12:$Q$113,'사업계획(원재료)'!$P34) -> 38 | R34: =SUMIFS('사업계획(매출 확정본)'!T$12:T$113,'사업계획(매출 확정본)'!$M$12:$M$113,'사업계획(원재료)'!$M34,'사업계획(매출 확정본)'!$Q$12:$Q$113,'사업계획(원재료)'!$P34) -> 45 | S34: =SUMIFS('사업계획(매출 확정본)'!U$12:U$113,'사업계획(매출 확정본)'!$M$12:$M$113,'사업계획(원재료)'!$M34,'사업계획(매출 확정본)'!$Q$12:$Q$113,'사업계획(원재료)'!$P34) -> 55 | T34: =SUMIFS('사업계획(매출 확정본)'!V$12:V$113,'사업계획(매출 확정본)'!$M$12:$M$113,'사업계획(원재료)'!$M34,'사업계획(매출 확정본)'!$Q$12:$Q$113,'사업계획(원재료)'!$P34) -> 65 | U34: =SUMIFS('사업계획(매출 확정본)'!W$12:W$113,'사업계획(매출 확정본)'!$M$12:$M$113,'사업계획(원재료)'!$M34,'사업계획(매출 확정본)'!$Q$12:$Q$113,'사업계획(원재료)'!$P34) -> 70 | AE34: 고소작업차 | AF34: 항공 | AG34: 원재료비(원) | AH34: =SUMIFS(Q$14:Q$149,$N$14:$N$149,$AE34,$O$14:$O$149,$AF34,$P$14:$P$149,$AG34) -> 0 | AI34: =SUMIFS(R$14:R$149,$N$14:$N$149,$AE34,$O$14:$O$149,$AF34,$P$14:$P$149,$AG34) -> 0 | AJ34: =SUMIFS(S$14:S$149,$N$14:$N$149,$AE34,$O$14:$O$149,$AF34,$P$14:$P$149,$AG34) -> 0 | AK34: =SUMIFS(T$14:T$149,$N$14:$N$149,$AE34,$O$14:$O$149,$AF34,$P$14:$P$149,$AG34) -> 0 | AL34: =SUMIFS(U$14:U$149,$N$14:$N$149,$AE34,$O$14:$O$149,$AF34,$P$14:$P$149,$AG34) -> 0 | AY34: DHT 160AS | AZ34: 전기
D35: 밀폐형덮개설치 | E35: 관공서 | H35: DHS 433L | I35: 활선차 | M35: DHS 190SKY | N35: 고소작업차 | O35: 기타 | P35: 판매 단가(원) | Q35: 62500000 | R35: =ROUND(Q35*1.05,-5) -> 65600000 | S35: =ROUND(R35*1.05,-5) -> 68900000 | T35: =ROUND(S35*1.05,-5) -> 72300000 | U35: =ROUND(T35*1.05,-5) -> 75900000 | V35: =S35/R35-1 -> 0.050304878 | AE35: 고소작업차 | AF35: 기타 | AG35: 매출액(원) | AH35: =SUMIFS(Q$14:Q$148,$P$14:$P$148,$AG$35,$O$14:$O$148,$AF$35,$N$14:$N$148,$AE$35) -> 3337500000 | AI35: =SUMIFS(R$14:R$148,$P$14:$P$148,$AG$35,$O$14:$O$148,$AF$35,$N$14:$N$148,$AE$35) -> 4766500000 | AJ35: =SUMIFS(S$14:S$148,$P$14:$P$148,$AG$35,$O$14:$O$148,$AF$35,$N$14:$N$148,$AE$35) -> 6539500000 | AK35: =SUMIFS(T$14:T$148,$P$14:$P$148,$AG$35,$O$14:$O$148,$AF$35,$N$14:$N$148,$AE$35) -> 7817000000 | AL35: =SUMIFS(U$14:U$148,$P$14:$P$148,$AG$35,$O$14:$O$148,$AF$35,$N$14:$N$148,$AE$35) -> 8587000000 | AY35: 공군수리부속 | AZ35: 항공
M36: DHS 190SKY | N36: 고소작업차 | O36: 기타 | P36: 매출액(원) | Q36: =SUMIFS('사업계획(매출 확정본)'!S$12:S$113,'사업계획(매출 확정본)'!$M$12:$M$113,'사업계획(원재료)'!$M36,'사업계획(매출 확정본)'!$Q$12:$Q$113,'사업계획(원재료)'!$P36) -> 2375000000 | R36: =SUMIFS('사업계획(매출 확정본)'!T$12:T$113,'사업계획(매출 확정본)'!$M$12:$M$113,'사업계획(원재료)'!$M36,'사업계획(매출 확정본)'!$Q$12:$Q$113,'사업계획(원재료)'!$P36) -> 2952000000 | S36: =SUMIFS('사업계획(매출 확정본)'!U$12:U$113,'사업계획(매출 확정본)'!$M$12:$M$113,'사업계획(원재료)'!$M36,'사업계획(매출 확정본)'!$Q$12:$Q$113,'사업계획(원재료)'!$P36) -> 3789500000 | T36: =SUMIFS('사업계획(매출 확정본)'!V$12:V$113,'사업계획(매출 확정본)'!$M$12:$M$113,'사업계획(원재료)'!$M36,'사업계획(매출 확정본)'!$Q$12:$Q$113,'사업계획(원재료)'!$P36) -> 4699500000 | U36: =SUMIFS('사업계획(매출 확정본)'!W$12:W$113,'사업계획(매출 확정본)'!$M$12:$M$113,'사업계획(원재료)'!$M36,'사업계획(매출 확정본)'!$Q$12:$Q$113,'사업계획(원재료)'!$P36) -> 5313000000 | AE36: 고소작업차 | AF36: 기타 | AG36: 판대대수(개) | AH36: =SUMIFS(Q$14:Q$148,$P$14:$P$148,$AG$36,$O$14:$O$148,$AF$35,$N$14:$N$148,$AE$35) -> 53 | AI36: =SUMIFS(R$14:R$148,$P$14:$P$148,$AG$36,$O$14:$O$148,$AF$35,$N$14:$N$148,$AE$35) -> 70 | AJ36: =SUMIFS(S$14:S$148,$P$14:$P$148,$AG$36,$O$14:$O$148,$AF$35,$N$14:$N$148,$AE$35) -> 90 | AK36: =SUMIFS(T$14:T$148,$P$14:$P$148,$AG$36,$O$14:$O$148,$AF$35,$N$14:$N$148,$AE$35) -> 105 | AL36: =SUMIFS(U$14:U$148,$P$14:$P$148,$AG$36,$O$14:$O$148,$AF$35,$N$14:$N$148,$AE$35) -> 110
M37: DHS 190SKY | N37: 고소작업차 | O37: 기타 | P37: 원재료비(원) | Q37: =VLOOKUP(M34,'제품별 원재료비 '!$O$4:$S$48,5,FALSE)*Q34 -> 1214140660 | R37: =Q37*(1+$V$6)/Q34*R34 -> 1.5039369e+09 | S37: =R37*(1+$V$6)/R34*S34 -> 1.9226997e+09 | T37: =S37*(1+$V$6)/S34*T34 -> 2.3768064e+09 | U37: =T37*(1+$V$6)/T34*U34 -> 2.677381e+09 | W37: =Q37/Q36 -> 0.51121712 | AE37: 고소작업차 | AF37: 기타 | AG37: 판매 단가(원) | AH37: =AH35/AH36 -> 62971698 | AI37: =AI35/AI36 -> 68092857 | AJ37: =AJ35/AJ36 -> 72661111 | AK37: =AK35/AK36 -> 74447619 | AL37: =AL35/AL36 -> 78063636
B38: DHS 433L | C38: DHS 930(R) | G38: DHS 433L | H38: DHT 105S | I38: 크레인 | L38: 국내 | M38: DHS 433L | N38: 크레인 | O38: 건설 | P38: 판대대수(개) | Q38: =SUMIFS('사업계획(매출 확정본)'!S$12:S$113,'사업계획(매출 확정본)'!$M$12:$M$113,'사업계획(원재료)'!$M38,'사업계획(매출 확정본)'!$Q$12:$Q$113,'사업계획(원재료)'!$P38) -> 225 | R38: =SUMIFS('사업계획(매출 확정본)'!T$12:T$113,'사업계획(매출 확정본)'!$M$12:$M$113,'사업계획(원재료)'!$M38,'사업계획(매출 확정본)'!$Q$12:$Q$113,'사업계획(원재료)'!$P38) -> 250 | S38: =SUMIFS('사업계획(매출 확정본)'!U$12:U$113,'사업계획(매출 확정본)'!$M$12:$M$113,'사업계획(원재료)'!$M38,'사업계획(매출 확정본)'!$Q$12:$Q$113,'사업계획(원재료)'!$P38) -> 280 | T38: =SUMIFS('사업계획(매출 확정본)'!V$12:V$113,'사업계획(매출 확정본)'!$M$12:$M$113,'사업계획(원재료)'!$M38,'사업계획(매출 확정본)'!$Q$12:$Q$113,'사업계획(원재료)'!$P38) -> 310 | U38: =SUMIFS('사업계획(매출 확정본)'!W$12:W$113,'사업계획(매출 확정본)'!$M$12:$M$113,'사업계획(원재료)'!$M38,'사업계획(매출 확정본)'!$Q$12:$Q$113,'사업계획(원재료)'!$P38) -> 320 | AE38: 고소작업차 | AF38: 기타 | AG38: 원재료비(원) | AH38: =SUMIFS(Q$14:Q$149,$N$14:$N$149,$AE38,$O$14:$O$149,$AF38,$P$14:$P$149,$AG38) -> 1.8081799e+09 | AI38: =SUMIFS(R$14:R$149,$N$14:$N$149,$AE38,$O$14:$O$149,$AF38,$P$14:$P$149,$AG38) -> 2.6272858e+09 | AJ38: =SUMIFS(S$14:S$149,$N$14:$N$149,$AE38,$O$14:$O$149,$AF38,$P$14:$P$149,$AG38) -> 3.6227978e+09 | AK38: =SUMIFS(T$14:T$149,$N$14:$N$149,$AE38,$O$14:$O$149,$AF38,$P$14:$P$149,$AG38) -> 4.2857259e+09 | AL38: =SUMIFS(U$14:U$149,$N$14:$N$149,$AE38,$O$14:$O$149,$AF38,$P$14:$P$149,$AG38) -> 4.6741108e+09 | AY38: 수출부품
H39: DHT 105S | I39: 크레인 | M39: DHS 433L | N39: 크레인 | O39: 건설 | P39: 판매 단가(원) | Q39: 15000000 | R39: =ROUND(Q39*1.05,-5) -> 15800000 | S39: =ROUND(R39*1.05,-5) -> 16600000 | T39: =ROUND(S39*1.05,-5) -> 17400000 | U39: =ROUND(T39*1.05,-5) -> 18300000 | AE39: 크레인 | AF39: 전기 | AG39: 매출액(원) | AH39: =SUMIFS(Q$14:Q$148,$P$14:$P$148,$AG$39,$O$14:$O$148,$AF$39,$N$14:$N$148,$AE$39) -> 270000000 | AI39: =SUMIFS(R$14:R$148,$P$14:$P$148,$AG$39,$O$14:$O$148,$AF$39,$N$14:$N$148,$AE$39) -> 709000000 | AJ39: =SUMIFS(S$14:S$148,$P$14:$P$148,$AG$39,$O$14:$O$148,$AF$39,$N$14:$N$148,$AE$39) -> 1489000000 | AK39: =SUMIFS(T$14:T$148,$P$14:$P$148,$AG$39,$O$14:$O$148,$AF$39,$N$14:$N$148,$AE$39) -> 2031900000 | AL39: =SUMIFS(U$14:U$148,$P$14:$P$148,$AG$39,$O$14:$O$148,$AF$39,$N$14:$N$148,$AE$39) -> 2461500000 | AY39: DHS 108SKY | AZ39: 기타
M40: DHS 433L | N40: 크레인 | O40: 건설 | P40: 매출액(원) | Q40: =SUMIFS('사업계획(매출 확정본)'!S$12:S$113,'사업계획(매출 확정본)'!$M$12:$M$113,'사업계획(원재료)'!$M40,'사업계획(매출 확정본)'!$Q$12:$Q$113,'사업계획(원재료)'!$P40) -> 3375000000 | R40: =SUMIFS('사업계획(매출 확정본)'!T$12:T$113,'사업계획(매출 확정본)'!$M$12:$M$113,'사업계획(원재료)'!$M40,'사업계획(매출 확정본)'!$Q$12:$Q$113,'사업계획(원재료)'!$P40) -> 3950000000 | S40: =SUMIFS('사업계획(매출 확정본)'!U$12:U$113,'사업계획(매출 확정본)'!$M$12:$M$113,'사업계획(원재료)'!$M40,'사업계획(매출 확정본)'!$Q$12:$Q$113,'사업계획(원재료)'!$P40) -> 4648000000 | T40: =SUMIFS('사업계획(매출 확정본)'!V$12:V$113,'사업계획(매출 확정본)'!$M$12:$M$113,'사업계획(원재료)'!$M40,'사업계획(매출 확정본)'!$Q$12:$Q$113,'사업계획(원재료)'!$P40) -> 5394000000 | U40: =SUMIFS('사업계획(매출 확정본)'!W$12:W$113,'사업계획(매출 확정본)'!$M$12:$M$113,'사업계획(원재료)'!$M40,'사업계획(매출 확정본)'!$Q$12:$Q$113,'사업계획(원재료)'!$P40) -> 5856000000 | AE40: 크레인 | AF40: 전기 | AG40: 판대대수(개) | AH40: =SUMIFS(Q$14:Q$148,$P$14:$P$148,$AG$40,$O$14:$O$148,$AF$39,$N$14:$N$148,$AE$39) -> 2 | AI40: =SUMIFS(R$14:R$148,$P$14:$P$148,$AG$40,$O$14:$O$148,$AF$39,$N$14:$N$148,$AE$39) -> 5 | AJ40: =SUMIFS(S$14:S$148,$P$14:$P$148,$AG$40,$O$14:$O$148,$AF$39,$N$14:$N$148,$AE$39) -> 10 | AK40: =SUMIFS(T$14:T$148,$P$14:$P$148,$AG$40,$O$14:$O$148,$AF$39,$N$14:$N$148,$AE$39) -> 13 | AL40: =SUMIFS(U$14:U$148,$P$14:$P$148,$AG$40,$O$14:$O$148,$AF$39,$N$14:$N$148,$AE$39) -> 15
M41: DHS 433L | N41: 크레인 | O41: 건설 | P41: 원재료비(원) | Q41: =VLOOKUP(M38,'제품별 원재료비 '!$O$4:$S$48,5,FALSE)*Q38 -> 990812250 | R41: =Q41*(1+$V$6)/Q38*R38 -> 1151544015 | S41: =R41*(1+$V$6)/R38*S38 -> 1.3490568e+09 | T41: =S41*(1+$V$6)/S38*T38 -> 1.5623042e+09 | U41: =T41*(1+$V$6)/T38*U38 -> 1.6868853e+09 | AE41: 크레인 | AF41: 전기 | AG41: 판매 단가(원) | AH41: =AH39/AH40 -> 135000000 | AI41: =AI39/AI40 -> 141800000 | AJ41: =AJ39/AJ40 -> 148900000 | AK41: =AK39/AK40 -> 156300000 | AL41: =AL39/AL40 -> 164100000
B42: DHS 534 | C42: DHS 950L(R) | G42: DHS 534 | H42: DHT 105S | I42: 크레인 | L42: 국내 | M42: DHS 534 | N42: 크레인 | O42: 건설 | P42: 판대대수(개) | Q42: =SUMIFS('사업계획(매출 확정본)'!S$12:S$113,'사업계획(매출 확정본)'!$M$12:$M$113,'사업계획(원재료)'!$M42,'사업계획(매출 확정본)'!$Q$12:$Q$113,'사업계획(원재료)'!$P42) -> 49 | R42: =SUMIFS('사업계획(매출 확정본)'!T$12:T$113,'사업계획(매출 확정본)'!$M$12:$M$113,'사업계획(원재료)'!$M42,'사업계획(매출 확정본)'!$Q$12:$Q$113,'사업계획(원재료)'!$P42) -> 60 | S42: =SUMIFS('사업계획(매출 확정본)'!U$12:U$113,'사업계획(매출 확정본)'!$M$12:$M$113,'사업계획(원재료)'!$M42,'사업계획(매출 확정본)'!$Q$12:$Q$113,'사업계획(원재료)'!$P42) -> 85 | T42: =SUMIFS('사업계획(매출 확정본)'!V$12:V$113,'사업계획(매출 확정본)'!$M$12:$M$113,'사업계획(원재료)'!$M42,'사업계획(매출 확정본)'!$Q$12:$Q$113,'사업계획(원재료)'!$P42) -> 110 | U42: =SUMIFS('사업계획(매출 확정본)'!W$12:W$113,'사업계획(매출 확정본)'!$M$12:$M$113,'사업계획(원재료)'!$M42,'사업계획(매출 확정본)'!$Q$12:$Q$113,'사업계획(원재료)'!$P42) -> 115 | AE42: 크레인 | AF42: 전기 | AG42: 원재료비(원) | AH42: =SUMIFS(Q$14:Q$149,$N$14:$N$149,$AE42,$O$14:$O$149,$AF42,$P$14:$P$149,$AG42) -> 226200000 | AI42: =SUMIFS(R$14:R$149,$N$14:$N$149,$AE42,$O$14:$O$149,$AF42,$P$14:$P$149,$AG42) -> 591513000 | AJ42: =SUMIFS(S$14:S$149,$N$14:$N$149,$AE42,$O$14:$O$149,$AF42,$P$14:$P$149,$AG42) -> 1237445196 | AK42: =SUMIFS(T$14:T$149,$N$14:$N$149,$AE42,$O$14:$O$149,$AF42,$P$14:$P$149,$AG42) -> 1.682678e+09 | AL42: =SUMIFS(U$14:U$149,$N$14:$N$149,$AE42,$O$14:$O$149,$AF42,$P$14:$P$149,$AG42) -> 2.0308629e+09 | AY42: DHS 17AP | AZ42: 전기
H43: DHT 105S | I43: 크레인 | M43: DHS 534 | N43: 크레인 | O43: 건설 | P43: 판매 단가(원) | Q43: 13500000 | R43: =ROUND(Q43*1.05,-5) -> 14200000 | S43: =ROUND(R43*1.05,-5) -> 14900000 | T43: =ROUND(S43*1.05,-5) -> 15600000 | U43: =ROUND(T43*1.05,-5) -> 16400000 | V43: =S43/R43-1 -> 0.049295775 | AE43: 크레인 | AF43: 통신 | AG43: 매출액(원) | AH43: =SUMIFS(Q$14:Q$148,$P$14:$P$148,$AG$43,$O$14:$O$148,$AF$43,$N$14:$N$148,$AE$43) -> 1944000000 | AI43: =SUMIFS(R$14:R$148,$P$14:$P$148,$AG$43,$O$14:$O$148,$AF$43,$N$14:$N$148,$AE$39) -> 2784500000 | AJ43: =SUMIFS(S$14:S$148,$P$14:$P$148,$AG$43,$O$14:$O$148,$AF$43,$N$14:$N$148,$AE$39) -> 4140500000 | AK43: =SUMIFS(T$14:T$148,$P$14:$P$148,$AG$43,$O$14:$O$148,$AF$43,$N$14:$N$148,$AE$39) -> 3585000000 | AL43: =SUMIFS(U$14:U$148,$P$14:$P$148,$AG$43,$O$14:$O$148,$AF$43,$N$14:$N$148,$AE$39) -> 4035000000 | AY43: DHS 130SKY | AZ43: 통신
M44: DHS 534 | N44: 크레인 | O44: 건설 | P44: 매출액(원) | Q44: =SUMIFS('사업계획(매출 확정본)'!S$12:S$113,'사업계획(매출 확정본)'!$M$12:$M$113,'사업계획(원재료)'!$M44,'사업계획(매출 확정본)'!$Q$12:$Q$113,'사업계획(원재료)'!$P44) -> 661500000 | R44: =SUMIFS('사업계획(매출 확정본)'!T$12:T$113,'사업계획(매출 확정본)'!$M$12:$M$113,'사업계획(원재료)'!$M44,'사업계획(매출 확정본)'!$Q$12:$Q$113,'사업계획(원재료)'!$P44) -> 852000000 | S44: =SUMIFS('사업계획(매출 확정본)'!U$12:U$113,'사업계획(매출 확정본)'!$M$12:$M$113,'사업계획(원재료)'!$M44,'사업계획(매출 확정본)'!$Q$12:$Q$113,'사업계획(원재료)'!$P44) -> 1266500000 | T44: =SUMIFS('사업계획(매출 확정본)'!V$12:V$113,'사업계획(매출 확정본)'!$M$12:$M$113,'사업계획(원재료)'!$M44,'사업계획(매출 확정본)'!$Q$12:$Q$113,'사업계획(원재료)'!$P44) -> 1716000000 | U44: =SUMIFS('사업계획(매출 확정본)'!W$12:W$113,'사업계획(매출 확정본)'!$M$12:$M$113,'사업계획(원재료)'!$M44,'사업계획(매출 확정본)'!$Q$12:$Q$113,'사업계획(원재료)'!$P44) -> 1886000000 | AE44: 크레인 | AF44: 통신 | AG44: 판대대수(개) | AH44: =SUMIFS(Q$14:Q$148,$P$14:$P$148,$AG$44,$O$14:$O$148,$AF$43,$N$14:$N$148,$AE$39) -> 24 | AI44: =SUMIFS(R$14:R$148,$P$14:$P$148,$AG$44,$O$14:$O$148,$AF$43,$N$14:$N$148,$AE$39) -> 35 | AJ44: =SUMIFS(S$14:S$148,$P$14:$P$148,$AG$44,$O$14:$O$148,$AF$43,$N$14:$N$148,$AE$39) -> 50 | AK44: =SUMIFS(T$14:T$148,$P$14:$P$148,$AG$44,$O$14:$O$148,$AF$43,$N$14:$N$148,$AE$39) -> 45 | AL44: =SUMIFS(U$14:U$148,$P$14:$P$148,$AG$44,$O$14:$O$148,$AF$43,$N$14:$N$148,$AE$39) -> 50
M45: DHS 534 | N45: 크레인 | O45: 건설 | P45: 원재료비(원) | Q45: =VLOOKUP(M42,'제품별 원재료비 '!$O$4:$S$48,5,FALSE)*Q42 -> 314873020 | R45: =Q45*(1+$V$6)/Q42*R42 -> 4.032945e+08 | S45: =R45*(1+$V$6)/R42*S42 -> 5.9761524e+08 | T45: =S45*(1+$V$6)/S42*T42 -> 8.0896011e+08 | U45: =T45*(1+$V$6)/T42*U42 -> 8.8463465e+08 | AE45: 크레인 | AF45: 통신 | AG45: 판매 단가(원) | AH45: =AH43/AH44 -> 81000000 | AI45: =AI43/AI44 -> 79557143 | AJ45: =AJ43/AJ44 -> 82810000 | AK45: =AK43/AK44 -> 79666667 | AL45: =AL43/AL44 -> 80700000
B46: DHS 920 | C46: DHT 160AS | G46: DHS 920 | H46: DHT 150S | I46: 고소작업차 | L46: 국내 | M46: DHS 920 | N46: 고소작업차 | O46: 통신 | P46: 판대대수(개) | Q46: =SUMIFS('사업계획(매출 확정본)'!S$12:S$113,'사업계획(매출 확정본)'!$M$12:$M$113,'사업계획(원재료)'!$M46,'사업계획(매출 확정본)'!$Q$12:$Q$113,'사업계획(원재료)'!$P46) -> 16 | R46: =SUMIFS('사업계획(매출 확정본)'!T$12:T$113,'사업계획(매출 확정본)'!$M$12:$M$113,'사업계획(원재료)'!$M46,'사업계획(매출 확정본)'!$Q$12:$Q$113,'사업계획(원재료)'!$P46) -> 20 | S46: =SUMIFS('사업계획(매출 확정본)'!U$12:U$113,'사업계획(매출 확정본)'!$M$12:$M$113,'사업계획(원재료)'!$M46,'사업계획(매출 확정본)'!$Q$12:$Q$113,'사업계획(원재료)'!$P46) -> 30 | T46: =SUMIFS('사업계획(매출 확정본)'!V$12:V$113,'사업계획(매출 확정본)'!$M$12:$M$113,'사업계획(원재료)'!$M46,'사업계획(매출 확정본)'!$Q$12:$Q$113,'사업계획(원재료)'!$P46) -> 40 | U46: =SUMIFS('사업계획(매출 확정본)'!W$12:W$113,'사업계획(매출 확정본)'!$M$12:$M$113,'사업계획(원재료)'!$M46,'사업계획(매출 확정본)'!$Q$12:$Q$113,'사업계획(원재료)'!$P46) -> 45 | AE46: 크레인 | AF46: 통신 | AG46: 원재료비(원) | AH46: =SUMIFS(Q$14:Q$149,$N$14:$N$149,$AE46,$O$14:$O$149,$AF46,$P$14:$P$149,$AG46) -> 1.5754822e+09 | AI46: =SUMIFS(R$14:R$149,$N$14:$N$149,$AE46,$O$14:$O$149,$AF46,$P$14:$P$149,$AG46) -> 2.1854194e+09 | AJ46: =SUMIFS(S$14:S$149,$N$14:$N$149,$AE46,$O$14:$O$149,$AF46,$P$14:$P$149,$AG46) -> 3.2265778e+09 | AK46: =SUMIFS(T$14:T$149,$N$14:$N$149,$AE46,$O$14:$O$149,$AF46,$P$14:$P$149,$AG46) -> 2.6656737e+09 | AL46: =SUMIFS(U$14:U$149,$N$14:$N$149,$AE46,$O$14:$O$149,$AF46,$P$14:$P$149,$AG46) -> 2.9318956e+09 | AY46: DHS 534MAP | AZ46: 통신
H47: DHS 15AP | I47: 고소작업차 | M47: DHS 920 | N47: 고소작업차 | O47: 통신 | P47: 판매 단가(원) | Q47: 45500000 | R47: =ROUND(Q47*1.05,-5) -> 47800000 | S47: =ROUND(R47*1.05,-5) -> 50200000 | T47: =ROUND(S47*1.05,-5) -> 52700000 | U47: =ROUND(T47*1.05,-5) -> 55300000 | V47: =S47/R47-1 -> 0.050209205 | AE47: 크레인 | AF47: 관공서 | AG47: 매출액(원) | AH47: =SUMIFS(Q$14:Q$148,$P$14:$P$148,$AG$47,$O$14:$O$148,$AF$47,$N$14:$N$148,$AE$47) -> 2528000000 | AI47: =SUMIFS(R$14:R$148,$P$14:$P$148,$AG$47,$O$14:$O$148,$AF$47,$N$14:$N$148,$AE$47) -> 4295000000 | AJ47: =SUMIFS(S$14:S$148,$P$14:$P$148,$AG$47,$O$14:$O$148,$AF$47,$N$14:$N$148,$AE$47) -> 6151500000 | AK47: =SUMIFS(T$14:T$148,$P$14:$P$148,$AG$47,$O$14:$O$148,$AF$47,$N$14:$N$148,$AE$47) -> 8184000000 | AL47: =SUMIFS(U$14:U$148,$P$14:$P$148,$AG$47,$O$14:$O$148,$AF$47,$N$14:$N$148,$AE$47) -> 9454500000 | AY47: DHA 102AP | AZ47: 통신
M48: DHS 920 | N48: 고소작업차 | O48: 통신 | P48: 매출액(원) | Q48: =SUMIFS('사업계획(매출 확정본)'!S$12:S$113,'사업계획(매출 확정본)'!$M$12:$M$113,'사업계획(원재료)'!$M48,'사업계획(매출 확정본)'!$Q$12:$Q$113,'사업계획(원재료)'!$P48) -> 728000000 | R48: =SUMIFS('사업계획(매출 확정본)'!T$12:T$113,'사업계획(매출 확정본)'!$M$12:$M$113,'사업계획(원재료)'!$M48,'사업계획(매출 확정본)'!$Q$12:$Q$113,'사업계획(원재료)'!$P48) -> 956000000 | S48: =SUMIFS('사업계획(매출 확정본)'!U$12:U$113,'사업계획(매출 확정본)'!$M$12:$M$113,'사업계획(원재료)'!$M48,'사업계획(매출 확정본)'!$Q$12:$Q$113,'사업계획(원재료)'!$P48) -> 1506000000 | T48: =SUMIFS('사업계획(매출 확정본)'!V$12:V$113,'사업계획(매출 확정본)'!$M$12:$M$113,'사업계획(원재료)'!$M48,'사업계획(매출 확정본)'!$Q$12:$Q$113,'사업계획(원재료)'!$P48) -> 2108000000 | U48: =SUMIFS('사업계획(매출 확정본)'!W$12:W$113,'사업계획(매출 확정본)'!$M$12:$M$113,'사업계획(원재료)'!$M48,'사업계획(매출 확정본)'!$Q$12:$Q$113,'사업계획(원재료)'!$P48) -> 2488500000 | W48: =Q49/Q48 -> 0.48998154 | AE48: 크레인 | AF48: 관공서 | AG48: 판대대수(개) | AH48: =SUMIFS(Q$14:Q$148,$P$14:$P$148,$AG$48,$O$14:$O$148,$AF$47,$N$14:$N$148,$AE$47) -> 24 | AI48: =SUMIFS(R$14:R$148,$P$14:$P$148,$AG$48,$O$14:$O$148,$AF$47,$N$14:$N$148,$AE$47) -> 40 | AJ48: =SUMIFS(S$14:S$148,$P$14:$P$148,$AG$48,$O$14:$O$148,$AF$47,$N$14:$N$148,$AE$47) -> 55 | AK48: =SUMIFS(T$14:T$148,$P$14:$P$148,$AG$48,$O$14:$O$148,$AF$47,$N$14:$N$148,$AE$47) -> 70 | AL48: =SUMIFS(U$14:U$148,$P$14:$P$148,$AG$48,$O$14:$O$148,$AF$47,$N$14:$N$148,$AE$47) -> 77
M49: DHS 920 | N49: 고소작업차 | O49: 통신 | P49: 원재료비(원) | Q49: =VLOOKUP(M46,'제품별 원재료비 '!$O$4:$S$48,5,FALSE)*Q46 -> 356706560 | R49: =Q49*(1+$V$6)/Q46*R46 -> 4.6639383e+08 | S49: =R49*(1+$V$6)/R46*S46 -> 7.3177191e+08 | T49: =S49*(1+$V$6)/S46*T46 -> 1.0205779e+09 | U49: =T49*(1+$V$6)/T46*U46 -> 1.200965e+09 | AE49: 크레인 | AF49: 관공서 | AG49: 판매 단가(원) | AH49: =AH47/AH48 -> 1.0533333e+08 | AI49: =AI47/AI48 -> 107375000 | AJ49: =AJ47/AJ48 -> 1.1184545e+08 | AK49: =AK47/AK48 -> 1.1691429e+08 | AL49: =AL47/AL48 -> 1.2278571e+08
B50: DHS 930 | C50: DHT 160S | G50: DHS 930 | H50: DHS 15AP | I50: 고소작업차 | L50: 국내 | M50: DHS 930 | N50: 고소작업차 | O50: 통신 | P50: 판대대수(개) | Q50: =SUMIFS('사업계획(매출 확정본)'!S$12:S$113,'사업계획(매출 확정본)'!$M$12:$M$113,'사업계획(원재료)'!$M50,'사업계획(매출 확정본)'!$Q$12:$Q$113,'사업계획(원재료)'!$P50) -> 59 | R50: =SUMIFS('사업계획(매출 확정본)'!T$12:T$113,'사업계획(매출 확정본)'!$M$12:$M$113,'사업계획(원재료)'!$M50,'사업계획(매출 확정본)'!$Q$12:$Q$113,'사업계획(원재료)'!$P50) -> 65 | S50: =SUMIFS('사업계획(매출 확정본)'!U$12:U$113,'사업계획(매출 확정본)'!$M$12:$M$113,'사업계획(원재료)'!$M50,'사업계획(매출 확정본)'!$Q$12:$Q$113,'사업계획(원재료)'!$P50) -> 80 | T50: =SUMIFS('사업계획(매출 확정본)'!V$12:V$113,'사업계획(매출 확정본)'!$M$12:$M$113,'사업계획(원재료)'!$M50,'사업계획(매출 확정본)'!$Q$12:$Q$113,'사업계획(원재료)'!$P50) -> 100 | U50: =SUMIFS('사업계획(매출 확정본)'!W$12:W$113,'사업계획(매출 확정본)'!$M$12:$M$113,'사업계획(원재료)'!$M50,'사업계획(매출 확정본)'!$Q$12:$Q$113,'사업계획(원재료)'!$P50) -> 120 | AE50: 크레인 | AF50: 관공서 | AG50: 원재료비(원) | AH50: =SUMIFS(Q$14:Q$149,$N$14:$N$149,$AE50,$O$14:$O$149,$AF50,$P$14:$P$149,$AG50) -> 1622689360 | AI50: =SUMIFS(R$14:R$149,$N$14:$N$149,$AE50,$O$14:$O$149,$AF50,$P$14:$P$149,$AG50) -> 2.769612e+09 | AJ50: =SUMIFS(S$14:S$149,$N$14:$N$149,$AE50,$O$14:$O$149,$AF50,$P$14:$P$149,$AG50) -> 3.9601432e+09 | AK50: =SUMIFS(T$14:T$149,$N$14:$N$149,$AE50,$O$14:$O$149,$AF50,$P$14:$P$149,$AG50) -> 5.2543429e+09 | AL50: =SUMIFS(U$14:U$149,$N$14:$N$149,$AE50,$O$14:$O$149,$AF50,$P$14:$P$149,$AG50) -> 6.0456469e+09 | AY50: DHS 280AP | AZ50: 기타
H51: DHS 950L | I51: 고소작업차 | M51: DHS 930 | N51: 고소작업차 | O51: 통신 | P51: 판매 단가(원) | Q51: 35500000 | R51: =ROUND(Q51*1.05,-5) -> 37300000 | S51: =ROUND(R51*1.05,-5) -> 39200000 | T51: =ROUND(S51*1.05,-5) -> 41200000 | U51: =ROUND(T51*1.05,-5) -> 43300000 | V51: =S51/R51-1 -> 0.050938338 | AE51: 크레인 | AF51: 건설 | AG51: 매출액(원) | AH51: =SUMIFS(Q$14:Q$148,$P$14:$P$148,$AG$51,$O$14:$O$148,$AF$51,$N$14:$N$148,$AE$47) -> 4590000000 | AI51: =SUMIFS(R$14:R$148,$P$14:$P$148,$AG$51,$O$14:$O$148,$AF$51,$N$14:$N$148,$AE$47) -> 5769500000 | AJ51: =SUMIFS(S$14:S$148,$P$14:$P$148,$AG$51,$O$14:$O$148,$AF$51,$N$14:$N$148,$AE$47) -> 7538500000 | AK51: =SUMIFS(T$14:T$148,$P$14:$P$148,$AG$51,$O$14:$O$148,$AF$51,$N$14:$N$148,$AE$47) -> 9027000000 | AL51: =SUMIFS(U$14:U$148,$P$14:$P$148,$AG$51,$O$14:$O$148,$AF$51,$N$14:$N$148,$AE$47) -> 9977000000 | AY51: DHS 433MAP(R) | AZ51: 통신
M52: DHS 930 | N52: 고소작업차 | O52: 통신 | P52: 매출액(원) | Q52: =SUMIFS('사업계획(매출 확정본)'!S$12:S$113,'사업계획(매출 확정본)'!$M$12:$M$113,'사업계획(원재료)'!$M52,'사업계획(매출 확정본)'!$Q$12:$Q$113,'사업계획(원재료)'!$P52) -> 2094500000 | R52: =SUMIFS('사업계획(매출 확정본)'!T$12:T$113,'사업계획(매출 확정본)'!$M$12:$M$113,'사업계획(원재료)'!$M52,'사업계획(매출 확정본)'!$Q$12:$Q$113,'사업계획(원재료)'!$P52) -> 2424500000 | S52: =SUMIFS('사업계획(매출 확정본)'!U$12:U$113,'사업계획(매출 확정본)'!$M$12:$M$113,'사업계획(원재료)'!$M52,'사업계획(매출 확정본)'!$Q$12:$Q$113,'사업계획(원재료)'!$P52) -> 3136000000 | T52: =SUMIFS('사업계획(매출 확정본)'!V$12:V$113,'사업계획(매출 확정본)'!$M$12:$M$113,'사업계획(원재료)'!$M52,'사업계획(매출 확정본)'!$Q$12:$Q$113,'사업계획(원재료)'!$P52) -> 4120000000 | U52: =SUMIFS('사업계획(매출 확정본)'!W$12:W$113,'사업계획(매출 확정본)'!$M$12:$M$113,'사업계획(원재료)'!$M52,'사업계획(매출 확정본)'!$Q$12:$Q$113,'사업계획(원재료)'!$P52) -> 5196000000 | W52: =Q53/Q52 -> 0.63956 | AE52: 크레인 | AF52: 건설 | AG52: 판대대수(개) | AH52: =SUMIFS(Q$14:Q$148,$P$14:$P$148,$AG$52,$O$14:$O$148,$AF$51,$N$14:$N$148,$AE$47) -> 289 | AI52: =SUMIFS(R$14:R$148,$P$14:$P$148,$AG$52,$O$14:$O$148,$AF$51,$N$14:$N$148,$AE$47) -> 335 | AJ52: =SUMIFS(S$14:S$148,$P$14:$P$148,$AG$52,$O$14:$O$148,$AF$51,$N$14:$N$148,$AE$47) -> 405 | AK52: =SUMIFS(T$14:T$148,$P$14:$P$148,$AG$52,$O$14:$O$148,$AF$51,$N$14:$N$148,$AE$47) -> 465 | AL52: =SUMIFS(U$14:U$148,$P$14:$P$148,$AG$52,$O$14:$O$148,$AF$51,$N$14:$N$148,$AE$47) -> 485
M53: DHS 930 | N53: 고소작업차 | O53: 통신 | P53: 원재료비(원) | Q53: =VLOOKUP(M50,'제품별 원재료비 '!$O$4:$S$48,5,FALSE)*Q50 -> 1339558420 | R53: =Q53*(1+$V$6)/Q50*R50 -> 1.5436708e+09 | S53: =R53*(1+$V$6)/R50*S50 -> 1.987298e+09 | T53: =S53*(1+$V$6)/S50*T50 -> 2.5983922e+09 | U53: =T53*(1+$V$6)/T50*U50 -> 3.2615019e+09 | AE53: 크레인 | AF53: 건설 | AG53: 판매 단가(원) | AH53: =AH51/AH52 -> 15882353 | AI53: =AI51/AI52 -> 17222388 | AJ53: =AJ51/AJ52 -> 18613580 | AK53: =AK51/AK52 -> 19412903 | AL53: =AL51/AL52 -> 20571134
B54: DHS 950L | C54: DHT 180S | G54: DHS 950L | H54: DHS 950L | I54: 고소작업차 | L54: 국내 | M54: DHS 950L | N54: 고소작업차 | O54: 통신 | P54: 판대대수(개) | Q54: =SUMIFS('사업계획(매출 확정본)'!S$12:S$113,'사업계획(매출 확정본)'!$M$12:$M$113,'사업계획(원재료)'!$M54,'사업계획(매출 확정본)'!$Q$12:$Q$113,'사업계획(원재료)'!$P54) -> 315 | R54: =SUMIFS('사업계획(매출 확정본)'!T$12:T$113,'사업계획(매출 확정본)'!$M$12:$M$113,'사업계획(원재료)'!$M54,'사업계획(매출 확정본)'!$Q$12:$Q$113,'사업계획(원재료)'!$P54) -> 350 | S54: =SUMIFS('사업계획(매출 확정본)'!U$12:U$113,'사업계획(매출 확정본)'!$M$12:$M$113,'사업계획(원재료)'!$M54,'사업계획(매출 확정본)'!$Q$12:$Q$113,'사업계획(원재료)'!$P54) -> 380 | T54: =SUMIFS('사업계획(매출 확정본)'!V$12:V$113,'사업계획(매출 확정본)'!$M$12:$M$113,'사업계획(원재료)'!$M54,'사업계획(매출 확정본)'!$Q$12:$Q$113,'사업계획(원재료)'!$P54) -> 385 | U54: =SUMIFS('사업계획(매출 확정본)'!W$12:W$113,'사업계획(매출 확정본)'!$M$12:$M$113,'사업계획(원재료)'!$M54,'사업계획(매출 확정본)'!$Q$12:$Q$113,'사업계획(원재료)'!$P54) -> 390 | AE54: 크레인 | AF54: 건설 | AG54: 원재료비(원) | AH54: =SUMIFS(Q$14:Q$149,$N$14:$N$149,$AE54,$O$14:$O$149,$AF54,$P$14:$P$149,$AG54) -> 1678427770 | AI54: =SUMIFS(R$14:R$149,$N$14:$N$149,$AE54,$O$14:$O$149,$AF54,$P$14:$P$149,$AG54) -> 2.2046529e+09 | AJ54: =SUMIFS(S$14:S$149,$N$14:$N$149,$AE54,$O$14:$O$149,$AF54,$P$14:$P$149,$AG54) -> 3.0342015e+09 | AK54: =SUMIFS(T$14:T$149,$N$14:$N$149,$AE54,$O$14:$O$149,$AF54,$P$14:$P$149,$AG54) -> 3.6510145e+09 | AL54: =SUMIFS(U$14:U$149,$N$14:$N$149,$AE54,$O$14:$O$149,$AF54,$P$14:$P$149,$AG54) -> 4.0588742e+09 | AY54: DHS 534 | AZ54: 건설
H55: DHS 15AP | I55: 고소작업차 | M55: DHS 950L | N55: 고소작업차 | O55: 통신 | P55: 판매 단가(원) | Q55: 36500000 | R55: =ROUND(Q55*1.05,-5) -> 38300000 | S55: =ROUND(R55*1.05,-5) -> 40200000 | T55: =ROUND(S55*1.05,-5) -> 42200000 | U55: =ROUND(T55*1.05,-5) -> 44300000 | V55: =S55/R55-1 -> 0.049608355 | AE55: 크레인 | AF55: 항공 | AG55: 매출액(원) | AH55: =SUMIFS(Q$14:Q$148,$P$14:$P$148,$AG$55,$O$14:$O$148,$AF$55,$N$14:$N$148,$AE$47) -> 0 | AI55: =SUMIFS(R$14:R$148,$P$14:$P$148,$AG$55,$O$14:$O$148,$AF$55,$N$14:$N$148,$AE$47) -> 0 | AJ55: =SUMIFS(S$14:S$148,$P$14:$P$148,$AG$55,$O$14:$O$148,$AF$55,$N$14:$N$148,$AE$47) -> 0 | AK55: =SUMIFS(T$14:T$148,$P$14:$P$148,$AG$55,$O$14:$O$148,$AF$55,$N$14:$N$148,$AE$47) -> 0 | AL55: =SUMIFS(U$14:U$148,$P$14:$P$148,$AG$55,$O$14:$O$148,$AF$55,$N$14:$N$148,$AE$47) -> 0 | AY55: DHM 1500S2 | AZ55: 기타
M56: DHS 950L | N56: 고소작업차 | O56: 통신 | P56: 매출액(원) | Q56: =SUMIFS('사업계획(매출 확정본)'!S$12:S$113,'사업계획(매출 확정본)'!$M$12:$M$113,'사업계획(원재료)'!$M56,'사업계획(매출 확정본)'!$Q$12:$Q$113,'사업계획(원재료)'!$P56) -> 11497500000 | R56: =SUMIFS('사업계획(매출 확정본)'!T$12:T$113,'사업계획(매출 확정본)'!$M$12:$M$113,'사업계획(원재료)'!$M56,'사업계획(매출 확정본)'!$Q$12:$Q$113,'사업계획(원재료)'!$P56) -> 13405000000 | S56: =SUMIFS('사업계획(매출 확정본)'!U$12:U$113,'사업계획(매출 확정본)'!$M$12:$M$113,'사업계획(원재료)'!$M56,'사업계획(매출 확정본)'!$Q$12:$Q$113,'사업계획(원재료)'!$P56) -> 15276000000 | T56: =SUMIFS('사업계획(매출 확정본)'!V$12:V$113,'사업계획(매출 확정본)'!$M$12:$M$113,'사업계획(원재료)'!$M56,'사업계획(매출 확정본)'!$Q$12:$Q$113,'사업계획(원재료)'!$P56) -> 16247000000 | U56: =SUMIFS('사업계획(매출 확정본)'!W$12:W$113,'사업계획(매출 확정본)'!$M$12:$M$113,'사업계획(원재료)'!$M56,'사업계획(매출 확정본)'!$Q$12:$Q$113,'사업계획(원재료)'!$P56) -> 17277000000 | AE56: 크레인 | AF56: 항공 | AG56: 판대대수(개) | AH56: =SUMIFS(Q$14:Q$148,$P$14:$P$148,$AG$56,$O$14:$O$148,$AF$55,$N$14:$N$148,$AE$47) -> 0 | AI56: =SUMIFS(R$14:R$148,$P$14:$P$148,$AG$56,$O$14:$O$148,$AF$55,$N$14:$N$148,$AE$47) -> 0 | AJ56: =SUMIFS(S$14:S$148,$P$14:$P$148,$AG$56,$O$14:$O$148,$AF$55,$N$14:$N$148,$AE$47) -> 0 | AK56: =SUMIFS(T$14:T$148,$P$14:$P$148,$AG$56,$O$14:$O$148,$AF$55,$N$14:$N$148,$AE$47) -> 0 | AL56: =SUMIFS(U$14:U$148,$P$14:$P$148,$AG$56,$O$14:$O$148,$AF$55,$N$14:$N$148,$AE$47) -> 0
M57: DHS 950L | N57: 고소작업차 | O57: 통신 | P57: 원재료비(원) | Q57: =VLOOKUP(M54,'제품별 원재료비 '!$O$4:$S$48,5,FALSE)*Q54 -> 7517112750 | R57: =Q57*(1+$V$6)/Q54*R54 -> 8736555485 | S57: =R57*(1+$V$6)/R54*S54 -> 9.9217316e+09 | T57: =S57*(1+$V$6)/S54*T54 -> 1.0514686e+10 | U57: =T57*(1+$V$6)/T54*U54 -> 1.1141197e+10 | W57: =Q57/Q56 -> 0.65380411 | AE57: 크레인 | AF57: 항공 | AG57: 판매 단가(원) | AH57: =IFERROR(AH55/AH56,0) -> 0 | AI57: =IFERROR(AI55/AI56,0) -> 0 | AJ57: =IFERROR(AJ55/AJ56,0) -> 0 | AK57: =IFERROR(AK55/AK56,0) -> 0 | AL57: =IFERROR(AL55/AL56,0) -> 0
B58: DHT 105S | G58: DHT 105S | H58: DHS 433L | I58: 활선차 | L58: 국내 | M58: DHT 105S | N58: 활선차 | O58: 전기 | P58: 판대대수(개) | Q58: =SUMIFS('사업계획(매출 확정본)'!S$12:S$113,'사업계획(매출 확정본)'!$M$12:$M$113,'사업계획(원재료)'!$M58,'사업계획(매출 확정본)'!$Q$12:$Q$113,'사업계획(원재료)'!$P58) -> 11 | R58: =SUMIFS('사업계획(매출 확정본)'!T$12:T$113,'사업계획(매출 확정본)'!$M$12:$M$113,'사업계획(원재료)'!$M58,'사업계획(매출 확정본)'!$Q$12:$Q$113,'사업계획(원재료)'!$P58) -> 20 | S58: =SUMIFS('사업계획(매출 확정본)'!U$12:U$113,'사업계획(매출 확정본)'!$M$12:$M$113,'사업계획(원재료)'!$M58,'사업계획(매출 확정본)'!$Q$12:$Q$113,'사업계획(원재료)'!$P58) -> 25 | T58: =SUMIFS('사업계획(매출 확정본)'!V$12:V$113,'사업계획(매출 확정본)'!$M$12:$M$113,'사업계획(원재료)'!$M58,'사업계획(매출 확정본)'!$Q$12:$Q$113,'사업계획(원재료)'!$P58) -> 30 | U58: =SUMIFS('사업계획(매출 확정본)'!W$12:W$113,'사업계획(매출 확정본)'!$M$12:$M$113,'사업계획(원재료)'!$M58,'사업계획(매출 확정본)'!$Q$12:$Q$113,'사업계획(원재료)'!$P58) -> 40 | AE58: 크레인 | AF58: 항공 | AG58: 원재료비(원) | AH58: =SUMIFS(Q$14:Q$149,$N$14:$N$149,$AE58,$O$14:$O$149,$AF58,$P$14:$P$149,$AG58) -> 0 | AI58: =SUMIFS(R$14:R$149,$N$14:$N$149,$AE58,$O$14:$O$149,$AF58,$P$14:$P$149,$AG58) -> 0 | AJ58: =SUMIFS(S$14:S$149,$N$14:$N$149,$AE58,$O$14:$O$149,$AF58,$P$14:$P$149,$AG58) -> 0 | AK58: =SUMIFS(T$14:T$149,$N$14:$N$149,$AE58,$O$14:$O$149,$AF58,$P$14:$P$149,$AG58) -> 0 | AL58: =SUMIFS(U$14:U$149,$N$14:$N$149,$AE58,$O$14:$O$149,$AF58,$P$14:$P$149,$AG58) -> 0 | AY58: DHAS 120AP | AZ58: 통신
H59: DHS 433L | I59: 활선차 | M59: DHT 105S | N59: 활선차 | O59: 전기 | P59: 판매 단가(원) | Q59: 115000000 | R59: =ROUND(Q59*1.05,-5) -> 120800000 | S59: =ROUND(R59*1.05,-5) -> 126800000 | T59: =ROUND(S59*1.05,-5) -> 133100000 | U59: =ROUND(T59*1.05,-5) -> 139800000 | AE59: 크레인 | AF59: 기타 | AG59: 매출액(원) | AH59: =SUMIFS(Q$14:Q$148,$P$14:$P$148,$AG$59,$O$14:$O$148,$AF$59,$N$14:$N$148,$AE$47) -> 0 | AI59: =SUMIFS(R$14:R$148,$P$14:$P$148,$AG$59,$O$14:$O$148,$AF$59,$N$14:$N$148,$AE$47) -> 0 | AJ59: =SUMIFS(S$14:S$148,$P$14:$P$148,$AG$59,$O$14:$O$148,$AF$59,$N$14:$N$148,$AE$47) -> 0 | AK59: =SUMIFS(T$14:T$148,$P$14:$P$148,$AG$59,$O$14:$O$148,$AF$59,$N$14:$N$148,$AE$47) -> 0 | AL59: =SUMIFS(U$14:U$148,$P$14:$P$148,$AG$59,$O$14:$O$148,$AF$59,$N$14:$N$148,$AE$47) -> 0 | AY59: DHS 1200L(R) | AZ59: 통신
M60: DHT 105S | N60: 활선차 | O60: 전기 | P60: 매출액(원) | Q60: =SUMIFS('사업계획(매출 확정본)'!S$12:S$113,'사업계획(매출 확정본)'!$M$12:$M$113,'사업계획(원재료)'!$M60,'사업계획(매출 확정본)'!$Q$12:$Q$113,'사업계획(원재료)'!$P60) -> 1265000000 | R60: =SUMIFS('사업계획(매출 확정본)'!T$12:T$113,'사업계획(매출 확정본)'!$M$12:$M$113,'사업계획(원재료)'!$M60,'사업계획(매출 확정본)'!$Q$12:$Q$113,'사업계획(원재료)'!$P60) -> 2416000000 | S60: =SUMIFS('사업계획(매출 확정본)'!U$12:U$113,'사업계획(매출 확정본)'!$M$12:$M$113,'사업계획(원재료)'!$M60,'사업계획(매출 확정본)'!$Q$12:$Q$113,'사업계획(원재료)'!$P60) -> 3170000000 | T60: =SUMIFS('사업계획(매출 확정본)'!V$12:V$113,'사업계획(매출 확정본)'!$M$12:$M$113,'사업계획(원재료)'!$M60,'사업계획(매출 확정본)'!$Q$12:$Q$113,'사업계획(원재료)'!$P60) -> 3993000000 | U60: =SUMIFS('사업계획(매출 확정본)'!W$12:W$113,'사업계획(매출 확정본)'!$M$12:$M$113,'사업계획(원재료)'!$M60,'사업계획(매출 확정본)'!$Q$12:$Q$113,'사업계획(원재료)'!$P60) -> 5592000000 | AE60: 크레인 | AF60: 기타 | AG60: 판대대수(개) | AH60: =SUMIFS(Q$14:Q$148,$P$14:$P$148,$AG$60,$O$14:$O$148,$AF$59,$N$14:$N$148,$AE$47) -> 0 | AI60: =SUMIFS(R$14:R$148,$P$14:$P$148,$AG$60,$O$14:$O$148,$AF$59,$N$14:$N$148,$AE$47) -> 0 | AJ60: =SUMIFS(S$14:S$148,$P$14:$P$148,$AG$60,$O$14:$O$148,$AF$59,$N$14:$N$148,$AE$47) -> 0 | AK60: =SUMIFS(T$14:T$148,$P$14:$P$148,$AG$60,$O$14:$O$148,$AF$59,$N$14:$N$148,$AE$47) -> 0 | AL60: =SUMIFS(U$14:U$148,$P$14:$P$148,$AG$60,$O$14:$O$148,$AF$59,$N$14:$N$148,$AE$47) -> 0
M61: DHT 105S | N61: 활선차 | O61: 전기 | P61: 원재료비(원) | Q61: =VLOOKUP(M58,'제품별 원재료비 '!$O$4:$S$48,5,FALSE)*Q58 -> 815301080 | R61: =Q61*(1+$V$6)/Q58*R58 -> 1.5505544e+09 | S61: =R61*(1+$V$6)/R58*S58 -> 2.0273499e+09 | T61: =S61*(1+$V$6)/S58*T58 -> 2.5447296e+09 | U61: =T61*(1+$V$6)/T58*U58 -> 3.5490495e+09 | AE61: 크레인 | AF61: 기타 | AG61: 판매 단가(원) | AH61: =AH59/AH60 -> #DIV/0! | AI61: =AI59/AI60 -> #DIV/0! | AJ61: =AJ59/AJ60 -> #DIV/0! | AK61: =AK59/AK60 -> #DIV/0! | AL61: =AL59/AL60 -> #DIV/0!
B62: DHT 150AS | G62: DHT 150AS | H62: DHS 950L | I62: 고소작업차 | L62: 국내 | M62: DHT 150AS | N62: 활선차 | O62: 전기 | P62: 판대대수(개) | Q62: =SUMIFS('사업계획(매출 확정본)'!S$12:S$113,'사업계획(매출 확정본)'!$M$12:$M$113,'사업계획(원재료)'!$M62,'사업계획(매출 확정본)'!$Q$12:$Q$113,'사업계획(원재료)'!$P62) -> 38 | R62: =SUMIFS('사업계획(매출 확정본)'!T$12:T$113,'사업계획(매출 확정본)'!$M$12:$M$113,'사업계획(원재료)'!$M62,'사업계획(매출 확정본)'!$Q$12:$Q$113,'사업계획(원재료)'!$P62) -> 45 | S62: =SUMIFS('사업계획(매출 확정본)'!U$12:U$113,'사업계획(매출 확정본)'!$M$12:$M$113,'사업계획(원재료)'!$M62,'사업계획(매출 확정본)'!$Q$12:$Q$113,'사업계획(원재료)'!$P62) -> 55 | T62: =SUMIFS('사업계획(매출 확정본)'!V$12:V$113,'사업계획(매출 확정본)'!$M$12:$M$113,'사업계획(원재료)'!$M62,'사업계획(매출 확정본)'!$Q$12:$Q$113,'사업계획(원재료)'!$P62) -> 60 | U62: =SUMIFS('사업계획(매출 확정본)'!W$12:W$113,'사업계획(매출 확정본)'!$M$12:$M$113,'사업계획(원재료)'!$M62,'사업계획(매출 확정본)'!$Q$12:$Q$113,'사업계획(원재료)'!$P62) -> 60 | AE62: 크레인 | AF62: 기타 | AG62: 원재료비(원) | AH62: =SUMIFS(Q$14:Q$149,$N$14:$N$149,$AE62,$O$14:$O$149,$AF62,$P$14:$P$149,$AG62) -> 0 | AI62: =SUMIFS(R$14:R$149,$N$14:$N$149,$AE62,$O$14:$O$149,$AF62,$P$14:$P$149,$AG62) -> 0 | AJ62: =SUMIFS(S$14:S$149,$N$14:$N$149,$AE62,$O$14:$O$149,$AF62,$P$14:$P$149,$AG62) -> 0 | AK62: =SUMIFS(T$14:T$149,$N$14:$N$149,$AE62,$O$14:$O$149,$AF62,$P$14:$P$149,$AG62) -> 0 | AL62: =SUMIFS(U$14:U$149,$N$14:$N$149,$AE62,$O$14:$O$149,$AF62,$P$14:$P$149,$AG62) -> 0 | AY62: DHT 170AS | AZ62: 전기
H63: DHS 950L | I63: 고소작업차 | M63: DHT 150AS | N63: 활선차 | O63: 전기 | P63: 판매 단가(원) | Q63: 165000000 | R63: =ROUND(Q63*1.05,-5) -> 173300000 | S63: =ROUND(R63*1.05,-5) -> 182000000 | T63: =ROUND(S63*1.05,-5) -> 191100000 | U63: =ROUND(T63*1.05,-5) -> 200700000 | AE63: 활선차 | AF63: 전기 | AG63: 매출액(원) | AH63: =SUMIFS(Q$14:Q$148,$P$14:$P$148,$AG$63,$O$14:$O$148,$AF$63,$N$14:$N$148,$AE$63) -> 41420000000 | AI63: =SUMIFS(R$14:R$148,$P$14:$P$148,$AG$63,$O$14:$O$148,$AF$63,$N$14:$N$148,$AE$63) -> 50014500000 | AJ63: =SUMIFS(S$14:S$148,$P$14:$P$148,$AG$63,$O$14:$O$148,$AF$63,$N$14:$N$148,$AE$63) -> 59321500000 | AK63: =SUMIFS(T$14:T$148,$P$14:$P$148,$AG$63,$O$14:$O$148,$AF$63,$N$14:$N$148,$AE$63) -> 65377500000 | AL63: =SUMIFS(U$14:U$148,$P$14:$P$148,$AG$63,$O$14:$O$148,$AF$63,$N$14:$N$148,$AE$63) -> 68774000000 | AY63: DHS 1800 | AZ63: 관공서
M64: DHT 150AS | N64: 활선차 | O64: 전기 | P64: 매출액(원) | Q64: =SUMIFS('사업계획(매출 확정본)'!S$12:S$113,'사업계획(매출 확정본)'!$M$12:$M$113,'사업계획(원재료)'!$M64,'사업계획(매출 확정본)'!$Q$12:$Q$113,'사업계획(원재료)'!$P64) -> 6270000000 | R64: =SUMIFS('사업계획(매출 확정본)'!T$12:T$113,'사업계획(매출 확정본)'!$M$12:$M$113,'사업계획(원재료)'!$M64,'사업계획(매출 확정본)'!$Q$12:$Q$113,'사업계획(원재료)'!$P64) -> 7798500000 | S64: =SUMIFS('사업계획(매출 확정본)'!U$12:U$113,'사업계획(매출 확정본)'!$M$12:$M$113,'사업계획(원재료)'!$M64,'사업계획(매출 확정본)'!$Q$12:$Q$113,'사업계획(원재료)'!$P64) -> 10010000000 | T64: =SUMIFS('사업계획(매출 확정본)'!V$12:V$113,'사업계획(매출 확정본)'!$M$12:$M$113,'사업계획(원재료)'!$M64,'사업계획(매출 확정본)'!$Q$12:$Q$113,'사업계획(원재료)'!$P64) -> 11466000000 | U64: =SUMIFS('사업계획(매출 확정본)'!W$12:W$113,'사업계획(매출 확정본)'!$M$12:$M$113,'사업계획(원재료)'!$M64,'사업계획(매출 확정본)'!$Q$12:$Q$113,'사업계획(원재료)'!$P64) -> 12042000000 | AE64: 활선차 | AF64: 전기 | AG64: 판대대수(개) | AH64: =SUMIFS(Q$14:Q$148,$P$14:$P$148,$AG$64,$O$14:$O$148,$AF$63,$N$14:$N$148,$AE$63) -> 260 | AI64: =SUMIFS(R$14:R$148,$P$14:$P$148,$AG$64,$O$14:$O$148,$AF$63,$N$14:$N$148,$AE$63) -> 305 | AJ64: =SUMIFS(S$14:S$148,$P$14:$P$148,$AG$64,$O$14:$O$148,$AF$63,$N$14:$N$148,$AE$63) -> 345 | AK64: =SUMIFS(T$14:T$148,$P$14:$P$148,$AG$64,$O$14:$O$148,$AF$63,$N$14:$N$148,$AE$63) -> 365 | AL64: =SUMIFS(U$14:U$148,$P$14:$P$148,$AG$64,$O$14:$O$148,$AF$63,$N$14:$N$148,$AE$63) -> 370
M65: DHT 150AS | N65: 활선차 | O65: 전기 | P65: 원재료비(원) | Q65: =VLOOKUP(M62,'제품별 원재료비 '!$O$4:$S$48,5,FALSE)*Q62 -> 3692906500 | R65: =Q65*(1+$V$6)/Q62*R62 -> 4.574345e+09 | S65: =R65*(1+$V$6)/R62*S62 -> 5.8480459e+09 | T65: =S65*(1+$V$6)/S62*T62 -> 6.673152e+09 | U65: =T65*(1+$V$6)/T62*U62 -> 6.980117e+09 | AE65: 활선차 | AF65: 전기 | AG65: 판매 단가(원) | AH65: =AH63/AH64 -> 1.5930769e+08 | AI65: =AI63/AI64 -> 1.6398197e+08 | AJ65: =AJ63/AJ64 -> 1.7194638e+08 | AK65: =AK63/AK64 -> 1.7911644e+08 | AL65: =AL63/AL64 -> 1.8587568e+08
B66: DHT 150S | G66: DHT 150S | H66: DHS 950L | I66: 고소작업차 | L66: 국내 | M66: DHT 150S | N66: 활선차 | O66: 전기 | P66: 판대대수(개) | Q66: =SUMIFS('사업계획(매출 확정본)'!S$12:S$113,'사업계획(매출 확정본)'!$M$12:$M$113,'사업계획(원재료)'!$M66,'사업계획(매출 확정본)'!$Q$12:$Q$113,'사업계획(원재료)'!$P66) -> 35 | R66: =SUMIFS('사업계획(매출 확정본)'!T$12:T$113,'사업계획(매출 확정본)'!$M$12:$M$113,'사업계획(원재료)'!$M66,'사업계획(매출 확정본)'!$Q$12:$Q$113,'사업계획(원재료)'!$P66) -> 45 | S66: =SUMIFS('사업계획(매출 확정본)'!U$12:U$113,'사업계획(매출 확정본)'!$M$12:$M$113,'사업계획(원재료)'!$M66,'사업계획(매출 확정본)'!$Q$12:$Q$113,'사업계획(원재료)'!$P66) -> 45 | T66: =SUMIFS('사업계획(매출 확정본)'!V$12:V$113,'사업계획(매출 확정본)'!$M$12:$M$113,'사업계획(원재료)'!$M66,'사업계획(매출 확정본)'!$Q$12:$Q$113,'사업계획(원재료)'!$P66) -> 60 | U66: =SUMIFS('사업계획(매출 확정본)'!W$12:W$113,'사업계획(매출 확정본)'!$M$12:$M$113,'사업계획(원재료)'!$M66,'사업계획(매출 확정본)'!$Q$12:$Q$113,'사업계획(원재료)'!$P66) -> 60 | AE66: 활선차 | AF66: 전기 | AG66: 원재료비(원) | AH66: =SUMIFS(Q$14:Q$149,$N$14:$N$149,$AE66,$O$14:$O$149,$AF66,$P$14:$P$149,$AG66) -> 25005782935 | AI66: =SUMIFS(R$14:R$149,$N$14:$N$149,$AE66,$O$14:$O$149,$AF66,$P$14:$P$149,$AG66) -> 3.0243843e+10 | AJ66: =SUMIFS(S$14:S$149,$N$14:$N$149,$AE66,$O$14:$O$149,$AF66,$P$14:$P$149,$AG66) -> 3.5756593e+10 | AK66: =SUMIFS(T$14:T$149,$N$14:$N$149,$AE66,$O$14:$O$149,$AF66,$P$14:$P$149,$AG66) -> 3.9296022e+10 | AL66: =SUMIFS(U$14:U$149,$N$14:$N$149,$AE66,$O$14:$O$149,$AF66,$P$14:$P$149,$AG66) -> 4.1275937e+10 | AY66: DHS 920 | AZ66: 통신
H67: DHS 950L | I67: 고소작업차 | M67: DHT 150S | N67: 활선차 | O67: 전기 | P67: 판매 단가(원) | Q67: 148500000 | R67: =ROUND(Q67*1.05,-5) -> 155900000 | S67: =ROUND(R67*1.05,-5) -> 163700000 | T67: =ROUND(S67*1.05,-5) -> 171900000 | U67: =ROUND(T67*1.05,-5) -> 180500000 | V67: =S67/R67-1 -> 0.050032072 | W67: =Q69/Q68 -> 0.61940236 | AE67: 활선차 | AF67: 통신 | AG67: 매출액(원) | AH67: =SUMIFS(Q$14:Q$148,$P$14:$P$148,$AG$67,$O$14:$O$148,$AF$67,$N$14:$N$148,$AE$63) -> 0 | AI67: =SUMIFS(R$14:R$148,$P$14:$P$148,$AG$67,$O$14:$O$148,$AF$67,$N$14:$N$148,$AE$63) -> 0 | AJ67: =SUMIFS(S$14:S$148,$P$14:$P$148,$AG$67,$O$14:$O$148,$AF$67,$N$14:$N$148,$AE$63) -> 0 | AK67: =SUMIFS(T$14:T$148,$P$14:$P$148,$AG$67,$O$14:$O$148,$AF$67,$N$14:$N$148,$AE$63) -> 0 | AL67: =SUMIFS(U$14:U$148,$P$14:$P$148,$AG$67,$O$14:$O$148,$AF$67,$N$14:$N$148,$AE$63) -> 0 | AY67: DHAS 130AP | AZ67: 통신
M68: DHT 150S | N68: 활선차 | O68: 전기 | P68: 매출액(원) | Q68: =SUMIFS('사업계획(매출 확정본)'!S$12:S$113,'사업계획(매출 확정본)'!$M$12:$M$113,'사업계획(원재료)'!$M68,'사업계획(매출 확정본)'!$Q$12:$Q$113,'사업계획(원재료)'!$P68) -> 5197500000 | R68: =SUMIFS('사업계획(매출 확정본)'!T$12:T$113,'사업계획(매출 확정본)'!$M$12:$M$113,'사업계획(원재료)'!$M68,'사업계획(매출 확정본)'!$Q$12:$Q$113,'사업계획(원재료)'!$P68) -> 7015500000 | S68: =SUMIFS('사업계획(매출 확정본)'!U$12:U$113,'사업계획(매출 확정본)'!$M$12:$M$113,'사업계획(원재료)'!$M68,'사업계획(매출 확정본)'!$Q$12:$Q$113,'사업계획(원재료)'!$P68) -> 7366500000 | T68: =SUMIFS('사업계획(매출 확정본)'!V$12:V$113,'사업계획(매출 확정본)'!$M$12:$M$113,'사업계획(원재료)'!$M68,'사업계획(매출 확정본)'!$Q$12:$Q$113,'사업계획(원재료)'!$P68) -> 10314000000 | U68: =SUMIFS('사업계획(매출 확정본)'!W$12:W$113,'사업계획(매출 확정본)'!$M$12:$M$113,'사업계획(원재료)'!$M68,'사업계획(매출 확정본)'!$Q$12:$Q$113,'사업계획(원재료)'!$P68) -> 10830000000 | AE68: 활선차 | AF68: 통신 | AG68: 판대대수(개) | AH68: =SUMIFS(Q$14:Q$148,$P$14:$P$148,$AG$68,$O$14:$O$148,$AF$67,$N$14:$N$148,$AE$63) -> 0 | AI68: =SUMIFS(R$14:R$148,$P$14:$P$148,$AG$68,$O$14:$O$148,$AF$67,$N$14:$N$148,$AE$63) -> 0 | AJ68: =SUMIFS(S$14:S$148,$P$14:$P$148,$AG$68,$O$14:$O$148,$AF$67,$N$14:$N$148,$AE$63) -> 0 | AK68: =SUMIFS(T$14:T$148,$P$14:$P$148,$AG$68,$O$14:$O$148,$AF$67,$N$14:$N$148,$AE$63) -> 0 | AL68: =SUMIFS(U$14:U$148,$P$14:$P$148,$AG$68,$O$14:$O$148,$AF$67,$N$14:$N$148,$AE$63) -> 0
M69: DHT 150S | N69: 활선차 | O69: 전기 | P69: 원재료비(원) | Q69: =VLOOKUP(M66,'제품별 원재료비 '!$O$4:$S$48,5,FALSE)*Q66 -> 3219343750 | R69: =Q69*(1+$V$6)/Q66*R66 -> 4.3295574e+09 | S69: =R69*(1+$V$6)/R66*S66 -> 4.5287171e+09 | T69: =S69*(1+$V$6)/S66*T66 -> 6.3160508e+09 | U69: =T69*(1+$V$6)/T66*U66 -> 6.6065891e+09 | AE69: 활선차 | AF69: 통신 | AG69: 판매 단가(원) | AH69: =AH67/AH68 -> #DIV/0! | AI69: =AI67/AI68 -> #DIV/0! | AJ69: =AJ67/AJ68 -> #DIV/0! | AK69: =AK67/AK68 -> #DIV/0! | AL69: =AL67/AL68 -> #DIV/0!
B70: DHT 160AS | G70: DHT 160AS | H70: DHS 950L | I70: 고소작업차 | L70: 국내 | M70: DHT 160AS | N70: 활선차 | O70: 전기 | P70: 판대대수(개) | Q70: =SUMIFS('사업계획(매출 확정본)'!S$12:S$113,'사업계획(매출 확정본)'!$M$12:$M$113,'사업계획(원재료)'!$M70,'사업계획(매출 확정본)'!$Q$12:$Q$113,'사업계획(원재료)'!$P70) -> 65 | R70: =SUMIFS('사업계획(매출 확정본)'!T$12:T$113,'사업계획(매출 확정본)'!$M$12:$M$113,'사업계획(원재료)'!$M70,'사업계획(매출 확정본)'!$Q$12:$Q$113,'사업계획(원재료)'!$P70) -> 75 | S70: =SUMIFS('사업계획(매출 확정본)'!U$12:U$113,'사업계획(매출 확정본)'!$M$12:$M$113,'사업계획(원재료)'!$M70,'사업계획(매출 확정본)'!$Q$12:$Q$113,'사업계획(원재료)'!$P70) -> 80 | T70: =SUMIFS('사업계획(매출 확정본)'!V$12:V$113,'사업계획(매출 확정본)'!$M$12:$M$113,'사업계획(원재료)'!$M70,'사업계획(매출 확정본)'!$Q$12:$Q$113,'사업계획(원재료)'!$P70) -> 85 | U70: =SUMIFS('사업계획(매출 확정본)'!W$12:W$113,'사업계획(매출 확정본)'!$M$12:$M$113,'사업계획(원재료)'!$M70,'사업계획(매출 확정본)'!$Q$12:$Q$113,'사업계획(원재료)'!$P70) -> 85 | W70: 75 | X70: 85 | Y70: 90 | Z70: 95 | AA70: 85 | AE70: 활선차 | AF70: 통신 | AG70: 원재료비(원) | AH70: =SUMIFS(Q$14:Q$149,$N$14:$N$149,$AE70,$O$14:$O$149,$AF70,$P$14:$P$149,$AG70) -> 0 | AI70: =SUMIFS(R$14:R$149,$N$14:$N$149,$AE70,$O$14:$O$149,$AF70,$P$14:$P$149,$AG70) -> 0 | AJ70: =SUMIFS(S$14:S$149,$N$14:$N$149,$AE70,$O$14:$O$149,$AF70,$P$14:$P$149,$AG70) -> 0 | AK70: =SUMIFS(T$14:T$149,$N$14:$N$149,$AE70,$O$14:$O$149,$AF70,$P$14:$P$149,$AG70) -> 0 | AL70: =SUMIFS(U$14:U$149,$N$14:$N$149,$AE70,$O$14:$O$149,$AF70,$P$14:$P$149,$AG70) -> 0 | AY70: DHAS 140SS | AZ70: 기타
H71: DHS 950L | I71: 고소작업차 | M71: DHT 160AS | N71: 활선차 | O71: 전기 | P71: 판매 단가(원) | Q71: 175000000 | R71: =ROUND(Q71*1.05,-5) -> 183800000 | S71: =ROUND(R71*1.05,-5) -> 193000000 | T71: =ROUND(S71*1.05,-5) -> 202700000 | U71: =ROUND(T71*1.05,-5) -> 212800000 | V71: =S71/R71-1 -> 0.050054407 | AE71: 활선차 | AF71: 관공서 | AG71: 매출액(원) | AH71: =SUMIFS(Q$14:Q$148,$P$14:$P$148,$AG$71,$O$14:$O$148,$AF$71,$N$14:$N$148,$AE$63) -> 0 | AI71: =SUMIFS(R$14:R$148,$P$14:$P$148,$AG$71,$O$14:$O$148,$AF$71,$N$14:$N$148,$AE$63) -> 0 | AJ71: =SUMIFS(S$14:S$148,$P$14:$P$148,$AG$71,$O$14:$O$148,$AF$71,$N$14:$N$148,$AE$63) -> 0 | AK71: =SUMIFS(T$14:T$148,$P$14:$P$148,$AG$71,$O$14:$O$148,$AF$71,$N$14:$N$148,$AE$63) -> 0 | AL71: =SUMIFS(U$14:U$148,$P$14:$P$148,$AG$71,$O$14:$O$148,$AF$71,$N$14:$N$148,$AE$63) -> 0 | AY71: 이동정비탑차 | AZ71: 기타
M72: DHT 160AS | N72: 활선차 | O72: 전기 | P72: 매출액(원) | Q72: =SUMIFS('사업계획(매출 확정본)'!S$12:S$113,'사업계획(매출 확정본)'!$M$12:$M$113,'사업계획(원재료)'!$M72,'사업계획(매출 확정본)'!$Q$12:$Q$113,'사업계획(원재료)'!$P72) -> 11375000000 | R72: =SUMIFS('사업계획(매출 확정본)'!T$12:T$113,'사업계획(매출 확정본)'!$M$12:$M$113,'사업계획(원재료)'!$M72,'사업계획(매출 확정본)'!$Q$12:$Q$113,'사업계획(원재료)'!$P72) -> 13785000000 | S72: =SUMIFS('사업계획(매출 확정본)'!U$12:U$113,'사업계획(매출 확정본)'!$M$12:$M$113,'사업계획(원재료)'!$M72,'사업계획(매출 확정본)'!$Q$12:$Q$113,'사업계획(원재료)'!$P72) -> 15440000000 | T72: =SUMIFS('사업계획(매출 확정본)'!V$12:V$113,'사업계획(매출 확정본)'!$M$12:$M$113,'사업계획(원재료)'!$M72,'사업계획(매출 확정본)'!$Q$12:$Q$113,'사업계획(원재료)'!$P72) -> 17229500000 | U72: =SUMIFS('사업계획(매출 확정본)'!W$12:W$113,'사업계획(매출 확정본)'!$M$12:$M$113,'사업계획(원재료)'!$M72,'사업계획(매출 확정본)'!$Q$12:$Q$113,'사업계획(원재료)'!$P72) -> 18088000000 | AE72: 활선차 | AF72: 관공서 | AG72: 판대대수(개) | AH72: =SUMIFS(Q$14:Q$148,$P$14:$P$148,$AG$72,$O$14:$O$148,$AF$71,$N$14:$N$148,$AE$63) -> 0 | AI72: =SUMIFS(R$14:R$148,$P$14:$P$148,$AG$72,$O$14:$O$148,$AF$71,$N$14:$N$148,$AE$63) -> 0 | AJ72: =SUMIFS(S$14:S$148,$P$14:$P$148,$AG$72,$O$14:$O$148,$AF$71,$N$14:$N$148,$AE$63) -> 0 | AK72: =SUMIFS(T$14:T$148,$P$14:$P$148,$AG$72,$O$14:$O$148,$AF$71,$N$14:$N$148,$AE$63) -> 0 | AL72: =SUMIFS(U$14:U$148,$P$14:$P$148,$AG$72,$O$14:$O$148,$AF$71,$N$14:$N$148,$AE$63) -> 0
M73: DHT 160AS | N73: 활선차 | O73: 전기 | P73: 원재료비(원) | Q73: =VLOOKUP(M70,'제품별 원재료비 '!$O$4:$S$48,5,FALSE)*Q70 -> 6486066925 | R73: =Q73*(1+$V$6)/Q70*R70 -> 7.8281839e+09 | S73: =R73*(1+$V$6)/R70*S70 -> 8.7341657e+09 | T73: =S73*(1+$V$6)/S70*T70 -> 9.7069334e+09 | U73: =T73*(1+$V$6)/T70*U70 -> 1.0153452e+10 | AE73: 활선차 | AF73: 관공서 | AG73: 판매 단가(원) | AH73: =AH71/AH72 -> #DIV/0! | AI73: =AI71/AI72 -> #DIV/0! | AJ73: =AJ71/AJ72 -> #DIV/0! | AK73: =AK71/AK72 -> #DIV/0! | AL73: =AL71/AL72 -> #DIV/0!
B74: DHT 160S | G74: DHT 160S | H74: DHS 950L | I74: 고소작업차 | L74: 국내 | M74: DHT 160S | N74: 활선차 | O74: 전기 | P74: 판대대수(개) | Q74: =SUMIFS('사업계획(매출 확정본)'!S$12:S$113,'사업계획(매출 확정본)'!$M$12:$M$113,'사업계획(원재료)'!$M74,'사업계획(매출 확정본)'!$Q$12:$Q$113,'사업계획(원재료)'!$P74) -> 50 | R74: =SUMIFS('사업계획(매출 확정본)'!T$12:T$113,'사업계획(매출 확정본)'!$M$12:$M$113,'사업계획(원재료)'!$M74,'사업계획(매출 확정본)'!$Q$12:$Q$113,'사업계획(원재료)'!$P74) -> 60 | S74: =SUMIFS('사업계획(매출 확정본)'!U$12:U$113,'사업계획(매출 확정본)'!$M$12:$M$113,'사업계획(원재료)'!$M74,'사업계획(매출 확정본)'!$Q$12:$Q$113,'사업계획(원재료)'!$P74) -> 70 | T74: =SUMIFS('사업계획(매출 확정본)'!V$12:V$113,'사업계획(매출 확정본)'!$M$12:$M$113,'사업계획(원재료)'!$M74,'사업계획(매출 확정본)'!$Q$12:$Q$113,'사업계획(원재료)'!$P74) -> 70 | U74: =SUMIFS('사업계획(매출 확정본)'!W$12:W$113,'사업계획(매출 확정본)'!$M$12:$M$113,'사업계획(원재료)'!$M74,'사업계획(매출 확정본)'!$Q$12:$Q$113,'사업계획(원재료)'!$P74) -> 75 | W74: =Q77/Q76 -> 0.61063 | AE74: 활선차 | AF74: 관공서 | AG74: 원재료비(원) | AH74: =SUMIFS(Q$14:Q$149,$N$14:$N$149,$AE74,$O$14:$O$149,$AF74,$P$14:$P$149,$AG74) -> 0 | AI74: =SUMIFS(R$14:R$149,$N$14:$N$149,$AE74,$O$14:$O$149,$AF74,$P$14:$P$149,$AG74) -> 0 | AJ74: =SUMIFS(S$14:S$149,$N$14:$N$149,$AE74,$O$14:$O$149,$AF74,$P$14:$P$149,$AG74) -> 0 | AK74: =SUMIFS(T$14:T$149,$N$14:$N$149,$AE74,$O$14:$O$149,$AF74,$P$14:$P$149,$AG74) -> 0 | AL74: =SUMIFS(U$14:U$149,$N$14:$N$149,$AE74,$O$14:$O$149,$AF74,$P$14:$P$149,$AG74) -> 0 | AY74: DHS 1200HC | AZ74: 통신
H75: DHS 950L | I75: 고소작업차 | M75: DHT 160S | N75: 활선차 | O75: 전기 | P75: 판매 단가(원) | Q75: 158000000 | R75: =ROUND(Q75*1.05,-5) -> 165900000 | S75: =ROUND(R75*1.05,-5) -> 174200000 | T75: =ROUND(S75*1.05,-5) -> 182900000 | U75: =ROUND(T75*1.05,-5) -> 192000000 | V75: =S75/R75-1 -> 0.050030139 | AE75: 활선차 | AF75: 건설 | AG75: 매출액(원) | AH75: =SUMIFS(Q$14:Q$148,$P$14:$P$148,$AG$75,$O$14:$O$148,$AF$75,$N$14:$N$148,$AE$63) -> 0 | AI75: =SUMIFS(R$14:R$148,$P$14:$P$148,$AG$75,$O$14:$O$148,$AF$75,$N$14:$N$148,$AE$63) -> 0 | AJ75: =SUMIFS(S$14:S$148,$P$14:$P$148,$AG$75,$O$14:$O$148,$AF$75,$N$14:$N$148,$AE$63) -> 0 | AK75: =SUMIFS(T$14:T$148,$P$14:$P$148,$AG$75,$O$14:$O$148,$AF$75,$N$14:$N$148,$AE$63) -> 0 | AL75: =SUMIFS(U$14:U$148,$P$14:$P$148,$AG$75,$O$14:$O$148,$AF$75,$N$14:$N$148,$AE$63) -> 0 | AY75: DHM 1300S2 | AZ75: 기타
M76: DHT 160S | N76: 활선차 | O76: 전기 | P76: 매출액(원) | Q76: =SUMIFS('사업계획(매출 확정본)'!S$12:S$113,'사업계획(매출 확정본)'!$M$12:$M$113,'사업계획(원재료)'!$M76,'사업계획(매출 확정본)'!$Q$12:$Q$113,'사업계획(원재료)'!$P76) -> 7900000000 | R76: =SUMIFS('사업계획(매출 확정본)'!T$12:T$113,'사업계획(매출 확정본)'!$M$12:$M$113,'사업계획(원재료)'!$M76,'사업계획(매출 확정본)'!$Q$12:$Q$113,'사업계획(원재료)'!$P76) -> 9954000000 | S76: =SUMIFS('사업계획(매출 확정본)'!U$12:U$113,'사업계획(매출 확정본)'!$M$12:$M$113,'사업계획(원재료)'!$M76,'사업계획(매출 확정본)'!$Q$12:$Q$113,'사업계획(원재료)'!$P76) -> 12194000000 | T76: =SUMIFS('사업계획(매출 확정본)'!V$12:V$113,'사업계획(매출 확정본)'!$M$12:$M$113,'사업계획(원재료)'!$M76,'사업계획(매출 확정본)'!$Q$12:$Q$113,'사업계획(원재료)'!$P76) -> 12803000000 | U76: =SUMIFS('사업계획(매출 확정본)'!W$12:W$113,'사업계획(매출 확정본)'!$M$12:$M$113,'사업계획(원재료)'!$M76,'사업계획(매출 확정본)'!$Q$12:$Q$113,'사업계획(원재료)'!$P76) -> 14400000000 | AE76: 활선차 | AF76: 건설 | AG76: 판대대수(개) | AH76: =SUMIFS(Q$14:Q$148,$P$14:$P$148,$AG$76,$O$14:$O$148,$AF$75,$N$14:$N$148,$AE$63) -> 0 | AI76: =SUMIFS(R$14:R$148,$P$14:$P$148,$AG$76,$O$14:$O$148,$AF$75,$N$14:$N$148,$AE$63) -> 0 | AJ76: =SUMIFS(S$14:S$148,$P$14:$P$148,$AG$76,$O$14:$O$148,$AF$75,$N$14:$N$148,$AE$63) -> 0 | AK76: =SUMIFS(T$14:T$148,$P$14:$P$148,$AG$76,$O$14:$O$148,$AF$75,$N$14:$N$148,$AE$63) -> 0 | AL76: =SUMIFS(U$14:U$148,$P$14:$P$148,$AG$76,$O$14:$O$148,$AF$75,$N$14:$N$148,$AE$63) -> 0
M77: DHT 160S | N77: 활선차 | O77: 전기 | P77: 원재료비(원) | Q77: =VLOOKUP(M74,'제품별 원재료비 '!$O$4:$S$48,5,FALSE)*Q74 -> 4823977000 | R77: =Q77*(1+$V$6)/Q74*R74 -> 6.0550559e+09 | S77: =R77*(1+$V$6)/R74*S74 -> 7.3891866e+09 | T77: =S77*(1+$V$6)/S74*T74 -> 7.7290892e+09 | U77: =T77*(1+$V$6)/T74*U74 -> 8.6621006e+09 | AE77: 활선차 | AF77: 건설 | AG77: 판매 단가(원) | AH77: =AH75/AH76 -> #DIV/0! | AI77: =AI75/AI76 -> #DIV/0! | AJ77: =AJ75/AJ76 -> #DIV/0! | AK77: =AK75/AK76 -> #DIV/0! | AL77: =AL75/AL76 -> #DIV/0!
