Workbook
Name __10: #REF!
Name __11: #REF!
Name __6: #REF!
Name __7: #REF!
Name __8: #REF!
Name __9: #REF!
Name __DAT1: #REF!
Name __DAT10: #REF!
Name __DAT11: #REF!
Name __DAT12: #REF!
Name __DAT13: #REF!
Name __DAT14: #REF!
Name __DAT15: #REF!
Name __DAT16: #REF!
Name __DAT17: #REF!
Name __DAT18: #REF!
Name __DAT19: #REF!
Name __DAT2: #REF!
Name __DAT3: #REF!
Name __DAT4: #REF!
Name __DAT5: #REF!
Name __DAT6: #REF!
Name __DAT7: #REF!
Name __DAT8: #REF!
Name __DAT9: #REF!
Name _1: #N/A
Name _10: #REF!
Name _11: #REF!
Name _12: #REF!
Name _13: #REF!
Name _14: #REF!
Name _15: #REF!
Name _16: #REF!
Name _17: #REF!
Name _18: #REF!
Name _19: #REF!
Name _2: #N/A
Name _20: #REF!
Name _20020826기본: #REF!
Name _3: #N/A
Name _4: #REF!
Name _5: #REF!
Name _6: #REF!
Name _7: #N/A
Name _8: #REF!
Name _9: #REF!
Name _C: #REF!
Name _DAT1: #REF!
Name _DAT10: #REF!
Name _DAT11: #REF!
Name _DAT12: #REF!
Name _DAT13: #REF!
Name _DAT14: #REF!
Name _DAT15: #REF!
Name _DAT16: #REF!
Name _DAT17: #REF!
Name _DAT18: #REF!
Name _DAT19: #REF!
Name _DAT2: #REF!
Name _DAT3: #REF!

Sheet Title
L5: Project
L6: =Des!C5 -> IT | M6: =L6 -> IT
L10: Financial Model
L11: - Business Valuation

Sheet Des
B1: ="Project"&" "&Title!L6 -> Project IT | C1: =$C$12 -> DRAFT - For Discussion Purposes Only
B2: Description
G4: DRAFT - For Discussion Purposes Only
B5: Project Name | C5: IT | G5: FINAL
B6: Client | C6: GS ITM
B7: Target Company | C7: GS ITM
B8: Valuation Date | C8: 42369
B9: Year End after Valuation Date | C9: =IF(C8=DATE(YEAR(C8),12,31),DATE(YEAR(C8+1),12,31),DATE(YEAR(C8),12,31)) -> 42735
B10: Partial Period Factor | C10: =(C9-C8)/365 -> 1.0027397
B11: Projection Period | C11: 2016/01/01 ~ 2020/12/31, 5년
B12: Work-In-Progress Disclaimer | C12: DRAFT - For Discussion Purposes Only
B13: Currency & Unit | C13: KRW Millions
B15: KPMG Color(기존)
B22: KPMG Color(신규)

Sheet Terms
B2: A | C2: Actual | D2: GPCM | E2: Guideline Public Company Method
B3: AUD | C3: Australian Dollar | D3: IBD | E3: Interest Bearing Debt
B4: CAGR | C4: Compound Annual Growth Rate | D4: JPY | E4: Japanese Yen
B5: CapEx | C5: Capital Expenditure | D5: Kd / Ke | E5: Cost of Debt / Cost of Equity
B6: CNY | C6: Chinese Yuan | D6: KRW | E6: Korean Won
B7: COGS | C7: Cost of Goods Sold | D7: KRX | E7: Korea Exchange
B8: Cont’d | C8: Continued | D8: LTM | E8: Last Twelve Months
B9: DART | C9: Data Analysis, Retrieval and Transfer System | D9: MKT Cap | E9: Market Capitalization
B10: DCF | C10: Discounted Cash Flow | D10: n.a. | E10: Not Applicable
B11: Dep. | C11: Depreciation | D11: n.m | E11: Not Meaningful
B12: DKK | C12: Danish Krone | D12: NOA | E12: Non Operating Asset
B13: E | C13: Estimated | D13: PV | E13: Present Value
... B21: GICS | C21: Global Industry Classification Standard | D21: x | E21: Multiple

Sheet 가정
B1: ="Project"&" "&Title!L6 -> Project IT | H1: DRAFT - For Discussion Purposes Only
B2: Assumption
B4: 구분 | C4: 세부항목 | E4: 가정 | F4: 근거 | G4: Reference | H4: 비고
B5: 매출액
B16: COGS
B27: SG&A
B38: Working Capital
B49: CapEx & Depreciation
B60: Others | C60: Terminal Growth Rate | D60: (%) | E60: 0
C61: 2011년 까지의 법인세율 | D61: (%) | E61: 0.242
C62: 2012년 이후의 법인세율 | D62: 세율 | E62: 0.11 | F62: 과세표준 2억원 이하 | G62: 2011년 12월 28일 제304회 국회(임시회) 제3차 본회의에서 가결된 법인세법 개정내용
D63: 최대 | E63: 200
D64: Extra
D65: 세율 | E65: 0.22 | F65: 과세표준 2억원 초과 200억원 이하
D66: 최대 | E66: 20000
D67: Extra | E67: =200*11% -> 22
D68: 세율 | E68: 0.242 | F68: 과세표준 200억원 초과
D69: 최대
D70: Extra | E70: =39800*11% -> 4378
C71: Market Data 기준일 | E71: 42369

Sheet 인터뷰
B1: =가정!B1 -> Project IT | D1: DRAFT - For Discussion Purposes Only
B2: Questionaire
B4: 구분 | C4: 세부항목 | D4: 비고
B5: 매출액
B28: COGS
B39: SG&A
B50: Working Capital
B61: CapEx & Depreciation

Sheet DCF(KPMG)>>

Sheet _TM_Result(보고서)
A1: Left | B1: Top | C1: Right | D1: Bottom | E1: Ref
A2: 7 | B2: 5 | C2: 12 | D2: 7 | E2: $G$5:$L$7

Sheet _TM_Result
A1: Left | B1: Top | C1: Right | D1: Bottom | E1: Ref
A2: 14 | B2: 17 | C2: 17 | D2: 22 | E2: $N$17:$Q$22

Sheet Result
B1: =WACC!$B$1 -> Project IT
B2: Result
B4: 평가방법 | C4: Low | E4: High | F4: 중간값
B5: GTM | C5: =GTM!R35 -> 135079.2 | D5: =E5-C5 -> 2226.4228 | E5: =GTM!R36 -> 137305.62 | F5: n.a.
B6: GPCM | D6: =E6-C6 -> 0 | F6: n.a.
B7: DCF | C7: =DCF!D36 -> 103789.1 | D7: =E7-C7 -> 35104.219 | E7: =DCF!F36 -> 138893.32
N27: DCF Results
N28: WACC | Q28: =wacc -> 0.091
N29: Terminal Growth Rate | Q29: =g -> 0
N30: Operating Value (a) | O30: 1543.0476 | P30: ~ | Q30: 1724.4334
N31: NOA (b) | Q31: 590.36301
N32: IBD (c) | Q32: 59.320332
N33: 100% Equity Value (d) =(a)+(b)-(c) | O33: =O30+Q31-Q32 -> 2074.0902 | P33: ~ | Q33: =Q30+Q31-Q32 -> 2255.4761

Sheet WACC
B1: ="Project"&" "&Title!L6 -> Project IT | Q1: =Des!$C$12 -> DRAFT - For Discussion Purposes Only | S1: <Tax Rate>
B2: Weighted Average Cost of Capital | S2: Unlevered | U2: 0.242
S3: Re-Levered, Kd | U3: =U2 -> 0.242 | V3: <= Terminal year 기준 EBIT규모에 따름 => 11%(~2억), 22%(~200억), 24.2%(200억~)
B4: Guideline Public Company | E4: Country | G4: Observed | H4: Currency (Millions) | I4: MKT Cap | J4: IBD | K4: Debt | M4: Debt | O4: Tax Rate | P4: Unlevered Beta | Q4: Re-Levered Beta
G5: Beta | K5: Equity | M5: TIC
B6: SAMSUNG SDS CO LTD | E6: SOUTH KOREA | G6: =CHOOSE($X$34,G74,H74,I74) -> 1.245976 | H6: KRW | I6: =CHOOSE($X$47,G102,H102,I102,J102,K102)+J131 -> 20173498 | J6: =G131 -> 14363.157 | K6: =J6/I6 -> 0.00071198148 | M6: =J6/(I6+J6) -> 0.00071147493 | O6: 0.242 | P6: =IF(G6="NA","NA",G6/(1+K6*(1-O6))) -> 1.2453039 | Q6: =P6*(1+($M$47/$M$48)*$E$47) -> 1.2453039
B7: POSCO ICT CO LTD | E7: SOUTH KOREA | G7: =CHOOSE($X$34,G75,H75,I75) -> 0.612323 | H7: KRW | I7: =CHOOSE($X$47,G103,H103,I103,J103,K103)+J132 -> 749314.02 | J7: =G132 -> 40486.304 | K7: =J7/I7 -> 0.054031157 | M7: =J7/(I7+J7) -> 0.051261442 | O7: 0.242 | P7: =IF(G7="NA","NA",G7/(1+K7*(1-O7))) -> 0.58823161 | Q7: =P7*(1+($M$47/$M$48)*$E$47) -> 0.58823161
B8: DONGBU CO LTD | E8: SOUTH KOREA | G8: =CHOOSE($X$34,G76,H76,I76) -> 1.050498 | H8: KRW | I8: =CHOOSE($X$47,G104,H104,I104,J104,K104)+J133 -> 89137.821 | J8: =G133 -> 59995.438 | K8: =J8/I8 -> 0.67306377 | M8: =J8/(I8+J8) -> 0.40229415 | O8: 0.242 | P8: =IF(G8="NA","NA",G8/(1+K8*(1-O8))) -> 0.69561004 | Q8: =P8*(1+($M$47/$M$48)*$E$47) -> 0.69561004
B9: SHINSEGAE INFORMATION & COMM | E9: SOUTH KOREA | G9: =CHOOSE($X$34,G77,H77,I77) -> 0.8844239 | H9: KRW | I9: =CHOOSE($X$47,G105,H105,I105,J105,K105)+J134 -> 168289.72 | J9: =G134 -> 0 | K9: =J9/I9 -> 0 | M9: =J9/(I9+J9) -> 0 | O9: 0.242 | P9: =IF(G9="NA","NA",G9/(1+K9*(1-O9))) -> 0.8844239 | Q9: =P9*(1+($M$47/$M$48)*$E$47) -> 0.8844239
B10: HYUNDAI INFORMATION TECH | E10: SOUTH KOREA | G10: =CHOOSE($X$34,G78,H78,I78) -> 0.2608621 | H10: KRW | I10: =CHOOSE($X$47,G106,H106,I106,J106,K106)+J135 -> 116521.65 | J10: =G135 -> 71570.72 | K10: =J10/I10 -> 0.61422678 | M10: =J10/(I10+J10) -> 0.38050836 | O10: 0.242 | P10: =IF(G10="NA","NA",G10/(1+K10*(1-O10))) -> 0.17799193 | Q10: =P10*(1+($M$47/$M$48)*$E$47) -> 0.17799193
B11: HANIL NETWORKS CO LTD | E11: SOUTH KOREA | G11: =CHOOSE($X$34,G79,H79,I79) -> 0.7077572 | H11: KRW | I11: =CHOOSE($X$47,G107,H107,I107,J107,K107)+J136 -> 34610.335 | J11: =G136 -> 500 | K11: =J11/I11 -> 0.014446552 | M11: =J11/(I11+J11) -> 0.014240821 | O11: 0.242 | P11: =IF(G11="NA","NA",G11/(1+K11*(1-O11))) -> 0.70009086 | Q11: =P11*(1+($M$47/$M$48)*$E$47) -> 0.70009086
B32: Maximum | G32: =MAX(G6:G14) -> 1.245976 | K32: =MAX(K6:K14) -> 0.67306377 | M32: =MAX(M6:M14) -> 0.40229415 | P32: =MAX(P6:P14) -> 1.2453039 | Q32: =MAX(Q6:Q14) -> 1.2453039
B33: Average | G33: =AVERAGE(G6:G14) -> 0.79364003 | K33: =AVERAGE(K6:K14) -> 0.22608004 | M33: =AVERAGE(M6:M14) -> 0.14150271 | P33: =AVERAGE(P6:P14) -> 0.71527538 | Q33: =AVERAGE(Q6:Q14) -> 0.71527538
B34: Median | G34: =MEDIAN(G6:G14) -> 0.79609055 | K34: =MEDIAN(K6:K14) -> 0.034238855 | M34: =MEDIAN(M6:M14) -> 0.032751132 | P34: =MEDIAN(P6:P14) -> 0.69785045 | Q34: =MEDIAN(Q6:Q14) -> 0.69785045 | U34: : 'Beta' Option (기간) | X34: 3
B35: Minimum | G35: =MIN(G6:G14) -> 0.2608621 | K35: =MIN(K6:K14) -> 0 | M35: =MIN(M6:M14) -> 0 | P35: =MIN(P6:P14) -> 0.17799193 | Q35: =MIN(Q6:Q14) -> 0.17799193
B37: Selected | M37: =CHOOSE($X$53,M33,M34,0) -> 0 | P37: =CHOOSE($X$53,P33,P34,P33) -> 0.71527538 | Q37: =P37*(1+($M$47/$M$48)*$E$47) -> 0.71527538
X38: 3 | Z38: KPMG
B39: Cost of Equity (KE) | Z39: Damodaran
U40: : 'Equity Risk Premium' Option (시점) | X40: 2 | Z40: Bloomberg
B41: Risk Free Rate | D41: + | E41: Beta | F41: x | G41: Equity Risk Premium | I41: + | J41: Size Risk Premium | K41: + | M41: Specific Premium | P41: = | Q41: Cost of Equity
B42: =CHOOSE($X$42,G159,G160,G161,G162,G163) -> 0.02065 | E42: =Q37 -> 0.71527538 | G42: =CHOOSE($X$40,H159,H160,H161,H162,H163) -> 0.098446667 | J42: 0 | M42: 0 | Q42: =SUM(B42,(E42*G42),J42,M42,O42) -> 0.091066477 | U42: : 'Risk-free Rate' Option (시점) | X42: 1
B44: After-Tax Cost of Debt (KD) | M44: Weighted Average Cost of Capital | X44: 1 | Z44: 미적용 | AA44: 0
Z45: 3-등급 체계
B46: Pre-Tax Cost of Debt | D46: x | E46: (1 - Tax Rate) | F46: = | G46: After-Tax Cost of Debt | M46: Captial Structure | N46: x | O46: Cost of Capital | P46: = | Q46: Contribution | Z46: 10-등급 체계
B47: =CHOOSE($X$50,$G$180,,$G$182) -> 0.03921 | E47: =1-U3 -> 0.758 | G47: =(B47*E47) -> 0.02972118 | K47: Debt | M47: =M37 -> 0 | O47: =G47 -> 0.02972118 | Q47: =O47*M47 -> 0 | U47: : 'Market Capitalization' Option | X47: 2 | Y47: =X47 -> 2
K48: Equity | M48: =(1-M47) -> 1 | O48: =Q42 -> 0.091066477 | Q48: =O48*M48 -> 0.091066477
O50: WACC | P50: = | Q50: =ROUND(Q47+Q48,3) -> 0.091 | U50: : 'Cost of Debt' Option | X50: 3 | Z50: Kisline 기업평가등급
B51: Notes: | Z51: 회사제시 신용등급
B52: [1] | C52: 대상회사와 유사한 사업을 영위하고 있는 회사를 선정 | Z52: DART 공시 신용등급
B53: [2] | C53: ="2015년 12월 31일 기준, "&CHOOSE($X$34,"5년 Weekly adjusted Beta 적용","5년 Monthly adjusted Beta 적용","2년 Weekly adjusted Beta 적용") -> 2015년 12월 31일 기준, 2년 Weekly adjusted Beta 적용 | U53: : 'Capital Structure' Option | X53: 3 | Z53: Average
B54: [3] | C54: ="2015년 12월 31일 기준, "&CHOOSE($X$47,"사용","과거 1개월 평균 시가총액 적용","과거 3개월 평균 시가총액 적용","과거 6개월 평균 시가총액 적용","과거 12개월 평균 시가총액 적용") -> 2015년 12월 31일 기준, 과거 1개월 평균 시가총액 적용 | Z54: Median
B55: [4] | C55: 2015년 9월 30일 기준 이자발생부채 적용 | Z55: 무부채기업 가정
B56: [5] | C56: 2015년 12월 31일 기준, 과거 1개월 평균 10년 만기 국공채 이자율 적용 (Source: Bloomberg)
B57: [6] | C57: ="2015년 12월 31일 기준, "&CHOOSE($X$40,"사용","과거 1개월 평균 Equity Risk Premium 적용","과거 3개월 평균 Equity Risk Premium 적용","과거 6개월 평균 Equity Risk Premium 적용","과거 12개월 평균 Equity Risk Premium 적용") -> 2015년 12월 31일 기준, 과거 1개월 평균 Equity Risk Premium 적용
B58: [7] | C58: 2015년 12월 31일 기준, 대상회사의 신용등급 A+를 고려한 5년 만기 무보증 공모사채 이자율을 적용(Source: KOFIA BIS)
B59: [8] | C59: 대한민국의 한계 법인세율 24.2%를 적용
B60: [9] | C60: 유사상장회사의 시장가치기준 평균 자본구조 적용
B64: <비교대상 회사 선정 과정>
B66: 유사회사 선정 과정
B67: 1. 국내 IT 서비스업체 중 매출액 기준 상위 32개 사 중 System Integration (SI)를 주요 사업으로 하는 회사 선정 (20개사)
B68: 2. 상기 회사 중 다음 3가지 조건을 충족: a) 대기업 계열사 등 특수관계인 지분이 30% 이상, b) 특수관계인 매출이 20% 이상, c) SI 부문 (혹은 IT 부문)의 매출 기여도가 20% 이상
B69: 3. 최종 유사회사로 선정된 회사(6개사)
B72: <Beta 선정> | G72: =IF(X32=1,"Raw","Adjusted") -> Adjusted | M72: Option
G73: 5year weekly | H73: 5year monthly | I73: 2year weekly | M73: 5year, weekly
A74: 1 | B74: =$B6 -> SAMSUNG SDS CO LTD | G74: 1.245976 | H74: 0.6334106 | I74: 1.245976 | M74: 5year, monthly
A75: 2 | B75: =$B7 -> POSCO ICT CO LTD | G75: 0.8242348 | H75: 1.069606 | I75: 0.612323 | M75: 2year, weekly
A76: 3 | B76: =$B8 -> DONGBU CO LTD | G76: 0.884048 | H76: 1.185187 | I76: 1.050498
A77: 4 | B77: =$B9 -> SHINSEGAE INFORMATION & COMM | G77: 0.6309563 | H77: 0.7374672 | I77: 0.8844239
A78: 5 | B78: =$B10 -> HYUNDAI INFORMATION TECH | G78: 0.420551 | H78: 0.7556377 | I78: 0.2608621
A79: 6 | B79: =$B11 -> HANIL NETWORKS CO LTD | G79: 0.6607968 | H79: 1.56227 | I79: 0.7077572
A80: 7
A81: 8
A82: 9
A83: 10
A84: 11
A85: 12
A86: 13
A87: 14
A88: 15
A89: 16
A90: 17
A91: 18
... A98: 25
B100: <시가총액 선정>
G101: =M102 -> 42369 | H101: 1 month | I101: 3 months | J101: 6 months | K101: 12 months | M101: Option
A102: 1 | B102: =$B6 -> SAMSUNG SDS CO LTD | G102: 19653961 | H102: 20173498 | I102: 20771641 | J102: 20833051 | K102: 20807140 | M102: =Des!C8 -> 42369
A103: 2 | B103: =$B7 -> POSCO ICT CO LTD | G103: 770816.08 | H103: 749314.02 | I103: 761500.93 | J103: 779105.59 | K103: 807672.24 | M103: 1 month avg.
A104: 3 | B104: =$B8 -> DONGBU CO LTD | G104: 90243.588 | H104: 89137.821 | I104: 98524.553 | J104: 109180.39 | K104: 88413.512 | M104: 3 months avg.
A105: 4 | B105: =$B9 -> SHINSEGAE INFORMATION & COMM | G105: 169076 | H105: 168289.72 | I105: 196221.97 | J105: 234946.54 | K105: 223545.21 | M105: 6 months avg.
A106: 5 | B106: =$B10 -> HYUNDAI INFORMATION TECH | G106: 112243.32 | H106: 116521.65 | I106: 118263.35 | J106: 101034.17 | K106: 89829.769 | M106: 12 months avg.
A107: 6 | B107: =$B11 -> HANIL NETWORKS CO LTD | G107: 38731.697 | H107: 34610.335 | I107: 34499.331 | J107: 33664.433 | K107: 29612.26
A108: 7
A109: 8
A110: 9
A111: 10
A112: 11
A113: 12
A114: 13
A115: 14
A116: 15
A117: 16
A118: 17
A119: 18
... A126: 25
B128: <이자부부채 선정>
G129: 이자부부채 | H129: 기준일 | I129: NOA | J129: 비지배지분
A131: 1 | B131: =$B6 -> SAMSUNG SDS CO LTD | G131: 14363.157 | H131: 2015 3Q | I131: 1794921.4
A132: 2 | B132: =$B7 -> POSCO ICT CO LTD | G132: 40486.304 | H132: 2015 3Q | I132: 67864.481
A133: 3 | B133: =$B8 -> DONGBU CO LTD | G133: 59995.438 | H133: 2015 3Q | I133: 27856.767
A134: 4 | B134: =$B9 -> SHINSEGAE INFORMATION & COMM | G134: 0 | H134: 2015 3Q | I134: 94207.52
A135: 5 | B135: =$B10 -> HYUNDAI INFORMATION TECH | G135: 71570.72 | H135: 2015 3Q | I135: 3539.3462
A136: 6 | B136: =$B11 -> HANIL NETWORKS CO LTD | G136: 500 | H136: 2015 3Q | I136: 9287.8654
A137: 7
A138: 8
A139: 9
A140: 10
A141: 11
A142: 12
A143: 13
A144: 14
...

Sheet WACC(보고서)
B1: ="Project"&" "&Title!L6 -> Project IT | O1: =Des!$C$12 -> DRAFT - For Discussion Purposes Only | Q1: <Tax Rate>
B2: Weighted Average Cost of Capital | Q2: Unlevered | S2: 0.242
Q3: Re-Levered, Kd | S3: =S2 -> 0.242 | T3: <= Terminal year 기준 EBIT규모에 따름 => 11%(~2억), 22%(~200억), 24.2%(200억~)
B4: Guideline Public Company | D4: Country | F4: Observed | G4: Currency (Millions) | H4: MKT Cap | I4: IBD | J4: Debt | K4: Debt | M4: Tax Rate | N4: Unlevered Beta | O4: Re-Levered Beta
F5: Beta | J5: Equity | K5: TIC
B6: =WACC!B6 -> SAMSUNG SDS CO LTD | D6: =WACC!E6 -> SOUTH KOREA | F6: =WACC!G6 -> 1.245976 | G6: =WACC!H6 -> KRW | H6: =WACC!I6 -> 20173498 | I6: =WACC!J6 -> 14363.157 | J6: =WACC!K6 -> 0.00071198148 | K6: =WACC!M6 -> 0.00071147493 | M6: =WACC!O6 -> 0.242 | N6: =WACC!P6 -> 1.2453039 | O6: =WACC!Q6 -> 1.2453039
B7: =WACC!B7 -> POSCO ICT CO LTD | D7: =WACC!E7 -> SOUTH KOREA | F7: =WACC!G7 -> 0.612323 | G7: =WACC!H7 -> KRW | H7: =WACC!I7 -> 749314.02 | I7: =WACC!J7 -> 40486.304 | J7: =WACC!K7 -> 0.054031157 | K7: =WACC!M7 -> 0.051261442 | M7: =WACC!O7 -> 0.242 | N7: =WACC!P7 -> 0.58823161 | O7: =WACC!Q7 -> 0.58823161
B8: =WACC!B8 -> DONGBU CO LTD | D8: =WACC!E8 -> SOUTH KOREA | F8: =WACC!G8 -> 1.050498 | G8: =WACC!H8 -> KRW | H8: =WACC!I8 -> 89137.821 | I8: =WACC!J8 -> 59995.438 | J8: =WACC!K8 -> 0.67306377 | K8: =WACC!M8 -> 0.40229415 | M8: =WACC!O8 -> 0.242 | N8: =WACC!P8 -> 0.69561004 | O8: =WACC!Q8 -> 0.69561004
B9: =WACC!B9 -> SHINSEGAE INFORMATION & COMM | D9: =WACC!E9 -> SOUTH KOREA | F9: =WACC!G9 -> 0.8844239 | G9: =WACC!H9 -> KRW | H9: =WACC!I9 -> 168289.72 | I9: =WACC!J9 -> 0 | J9: =WACC!K9 -> 0 | K9: =WACC!M9 -> 0 | M9: =WACC!O9 -> 0.242 | N9: =WACC!P9 -> 0.8844239 | O9: =WACC!Q9 -> 0.8844239
B10: =WACC!B10 -> HYUNDAI INFORMATION TECH | D10: =WACC!E10 -> SOUTH KOREA | F10: =WACC!G10 -> 0.2608621 | G10: =WACC!H10 -> KRW | H10: =WACC!I10 -> 116521.65 | I10: =WACC!J10 -> 71570.72 | J10: =WACC!K10 -> 0.61422678 | K10: =WACC!M10 -> 0.38050836 | M10: =WACC!O10 -> 0.242 | N10: =WACC!P10 -> 0.17799193 | O10: =WACC!Q10 -> 0.17799193
B11: =WACC!B11 -> HANIL NETWORKS CO LTD | D11: =WACC!E11 -> SOUTH KOREA | F11: =WACC!G11 -> 0.7077572 | G11: =WACC!H11 -> KRW | H11: =WACC!I11 -> 34610.335 | I11: =WACC!J11 -> 500 | J11: =WACC!K11 -> 0.014446552 | K11: =WACC!M11 -> 0.014240821 | M11: =WACC!O11 -> 0.242 | N11: =WACC!P11 -> 0.70009086 | O11: =WACC!Q11 -> 0.70009086
B12: =WACC!B12 -> 0 | D12: =WACC!E12 -> 0 | F12: =WACC!G12 -> 0 | G12: =WACC!H12 -> 0 | H12: =WACC!I12 -> 0 | I12: =WACC!J12 -> 0 | J12: =WACC!K12 -> 0 | K12: =WACC!M12 -> 0 | M12: =WACC!O12 -> 0 | N12: =WACC!P12 -> 0 | O12: =WACC!Q12 -> 0
B13: =WACC!B13 -> 0 | D13: =WACC!E13 -> 0 | F13: =WACC!G13 -> 0 | G13: =WACC!H13 -> 0 | H13: =WACC!I13 -> 0 | I13: =WACC!J13 -> 0 | J13: =WACC!K13 -> 0 | K13: =WACC!M13 -> 0 | M13: =WACC!O13 -> 0 | N13: =WACC!P13 -> 0 | O13: =WACC!Q13 -> 0
B14: =WACC!B14 -> 0 | D14: =WACC!E14 -> 0 | F14: =WACC!G14 -> 0 | G14: =WACC!H14 -> 0 | H14: =WACC!I14 -> 0 | I14: =WACC!J14 -> 0 | J14: =WACC!K14 -> 0 | K14: =WACC!M14 -> 0 | M14: =WACC!O14 -> 0 | N14: =WACC!P14 -> 0 | O14: =WACC!Q14 -> 0
B15: =WACC!B15 -> 0 | D15: =WACC!E15 -> 0 | F15: =WACC!G15 -> 0 | G15: =WACC!H15 -> 0 | H15: =WACC!I15 -> 0 | I15: =WACC!J15 -> 0 | J15: =WACC!K15 -> 0 | K15: =WACC!M15 -> 0 | M15: =WACC!O15 -> 0 | N15: =WACC!P15 -> 0 | O15: =WACC!Q15 -> 0
B16: =WACC!B16 -> 0 | D16: =WACC!E16 -> 0 | F16: =WACC!G16 -> 0 | G16: =WACC!H16 -> 0 | H16: =WACC!I16 -> 0 | I16: =WACC!J16 -> 0 | J16: =WACC!K16 -> 0 | K16: =WACC!M16 -> 0 | M16: =WACC!O16 -> 0 | N16: =WACC!P16 -> 0 | O16: =WACC!Q16 -> 0
B17: =WACC!B17 -> 0 | D17: =WACC!E17 -> 0 | F17: =WACC!G17 -> 0 | G17: =WACC!H17 -> 0 | H17: =WACC!I17 -> 0 | I17: =WACC!J17 -> 0 | J17: =WACC!K17 -> 0 | K17: =WACC!M17 -> 0 | M17: =WACC!O17 -> 0 | N17: =WACC!P17 -> 0 | O17: =WACC!Q17 -> 0
... B30: =WACC!B30 -> 0 | D30: =WACC!E30 -> 0 | F30: =WACC!G30 -> 0 | G30: =WACC!H30 -> 0 | H30: =WACC!I30 -> 0 | I30: =WACC!J30 -> 0 | J30: =WACC!K30 -> 0 | K30: =WACC!M30 -> 0 | M30: =WACC!O30 -> 0 | N30: =WACC!P30 -> 0 | O30: =WACC!Q30 -> 0
B32: Maximum | F32: =MAX(F6:F14) -> 1.245976 | J32: =MAX(J6:J14) -> 0.67306377 | K32: =MAX(K6:K14) -> 0.40229415 | N32: =MAX(N6:N14) -> 1.2453039 | O32: =MAX(O6:O14) -> 1.2453039
B33: Average | F33: =AVERAGE(F6:F14) -> 0.52909336 | J33: =AVERAGE(J6:J14) -> 0.15072003 | K33: =AVERAGE(K6:K14) -> 0.094335138 | N33: =AVERAGE(N6:N14) -> 0.47685025 | O33: =AVERAGE(O6:O14) -> 0.47685025
B34: Median | F34: =MEDIAN(F6:F14) -> 0.612323 | J34: =MEDIAN(J6:J14) -> 0.00071198148 | K34: =MEDIAN(K6:K14) -> 0.00071147493 | N34: =MEDIAN(N6:N14) -> 0.58823161 | O34: =MEDIAN(O6:O14) -> 0.58823161 | S34: : 'Beta' Option (기간) | V34: 0
B35: Minimum | F35: =MIN(F6:F14) -> 0 | J35: =MIN(J6:J14) -> 0 | K35: =MIN(K6:K14) -> 0 | N35: =MIN(N6:N14) -> 0 | O35: =MIN(O6:O14) -> 0
B37: Selected (Median) | K37: =CHOOSE($V$54,K33,K34,0) -> 0.00071147493 | N37: =CHOOSE($V$54,N33,N34,0) -> 0.58823161 | O37: =N37*(1+($K$47/$K$48)*$D$47) -> 0.58823161
V38: 3 | X38: KPMG
B39: Cost of Equity (KE) | X39: Damodaran
S40: : 'Equity Risk Premium' Option (시점) | V40: 0 | X40: Bloomberg
B41: Risk Free Rate | D41: + | F41: Beta | H41: x | J41: Equity Risk Premium | N41: = | O41: Cost of Equity
B42: =WACC!$B$42 -> 0.02065 | F42: =WACC!$E$42 -> 0.71527538 | J42: =WACC!$G$42 -> 0.098446667 | O42: =WACC!$Q$42 -> 0.091066477 | S42: : 'Risk-free Rate' Option (시점) | V42: 0
B44: After-Tax Cost of Debt (KD) | K44: Weighted Average Cost of Capital | V44: 1 | X44: 미적용 | Y44: 0
X45: 3-등급 체계
B46: Pre-Tax Cost of Debt | C46: x | D46: (1 - Tax Rate) | E46: = | F46: After-Tax Cost of Debt | K46: Captial Structure | L46: x | M46: Cost of Capital | N46: = | O46: Contribution | X46: 10-등급 체계
B47: =WACC!$B$47 -> 0.03921 | D47: =WACC!$E$47 -> 0.758 | F47: =WACC!$G$47 -> 0.02972118 | J47: Debt | K47: =WACC!M47 -> 0 | M47: =WACC!O47 -> 0.02972118 | O47: =WACC!Q47 -> 0 | S47: : 'Market Capitalization' Option | V47: 0
J48: Equity | K48: =WACC!M48 -> 1 | M48: =WACC!O48 -> 0.091066477 | O48: =WACC!Q48 -> 0.091066477
M50: WACC | N50: = | O50: =wacc -> 0.091 | S50: : 'Cost of Debt' Option | V50: 1 | X50: Kisline 기업평가등급
B52: Notes: | X52: 회사제시 신용등급
B53: [1] | C53: =WACC!C52 -> 대상회사와 유사한 사업을 영위하고 있는 회사를 선정 | X53: DART 공시 신용등급
B54: [2] | C54: =WACC!C53 -> 2015년 12월 31일 기준, 2년 Weekly adjusted Beta 적용 | S54: : 'Capital Structure' Option | V54: 2 | X54: Average
B55: [3] | C55: =WACC!C54 -> 2015년 12월 31일 기준, 과거 1개월 평균 시가총액 적용 | X55: Median
B56: [4] | C56: =WACC!C55 -> 2015년 9월 30일 기준 이자발생부채 적용 | X56: 무부채기업 가정
B57: [5] | C57: =WACC!C56 -> 2015년 12월 31일 기준, 과거 1개월 평균 10년 만기 국공채 이자율 적용 (Source: Bloomberg)
B58: [6] | C58: =WACC!C57 -> 2015년 12월 31일 기준, 과거 1개월 평균 Equity Risk Premium 적용
B59: [7] | C59: =WACC!C58 -> 2015년 12월 31일 기준, 대상회사의 신용등급 A+를 고려한 5년 만기 무보증 공모사채 이자율을 적용(Source: KOFIA BIS)
B60: [8] | C60: =WACC!C59 -> 대한민국의 한계 법인세율 24.2%를 적용
B61: [9] | C61: =WACC!C60 -> 유사상장회사의 시장가치기준 평균 자본구조 적용

Sheet _TM_GPCM_Tier1 (2)
A1: Left | B1: Top | C1: Right | D1: Bottom | E1: Ref
A2: 2 | B2: 101 | C2: 7 | D2: 292 | E2: $B$101:$G$292

Sheet _TM_매출액
A1: Left | B1: Top | C1: Right | D1: Bottom | E1: Ref
A2: 2 | B2: 24 | C2: 14 | D2: 24 | E2: $B$24:$N$24

Sheet GTM
B1: ="Project"&" "&Title!L6 -> Project IT | M1: DRAFT - For Discussion Purposes Only
B2: Guideline Transaction Method
B4: Announce Date | C4: Target Company | D4: Bidder Company | E4: Seller Company | F4: Deal Price (KRW Mil) | G4: Acquisition Ratio | H4: Enterprise Value | I4: Equity Value | J4: NI | K4: EBITDA | L4: Multiples | M4: Multiples
G5: Ratio | H5: of Equity(MM) | I5: of Equity(MM) | J5: EV(MM) | K5: EV(MM) | L5: PER | M5: EV/EBITDA
B6: 10/30/2015 | C6: 아남정보기술 | D6: KESS | E6: 유한회사 아남 외 8인 | F6: 15000 | G6: 0.3812 | H6: 37885.917 | I6: 39349.423 | J6: 1237.5475 | K6: -389.07777 | L6: =I6/J6 -> 31.796293 | M6: =IF(OR(ISERROR(H6/K6),H6/K6<0),"n.a.",H6/K6) -> n.a.
B7: 09/30/2015 | C7: 코마스 | D7: 대우정보시스템 | F7: 4432.5366 | G7: 0.1027 | H7: 83274.661 | I7: 43160.045 | J7: 2371.6499 | K7: 7095.7919 | L7: =I7/J7 -> 18.198321 | M7: =IF(OR(ISERROR(H7/K7),H7/K7<0),"n.a.",H7/K7) -> 11.735781
B8: 05/15/2015 | C8: 코마스 | D8: 대우정보시스템 | F8: 20120 | G8: 0.5442 | H8: 77086.318 | I8: 36971.702 | J8: 2371.6499 | K8: 7095.7919 | L8: =I8/J8 -> 15.589022 | M8: =IF(OR(ISERROR(H8/K8),H8/K8<0),"n.a.",H8/K8) -> 10.863667
B9: 04/22/2015 | C9: 대림 I&S | D9: 대림코퍼레이션 | F9: 129866.84 | G9: 1 | H9: 229248.17 | I9: 129866.84 | J9: 15706.014 | K9: 22336.82 | L9: =I9/J9 -> 8.2686058 | M9: =IF(OR(ISERROR(H9/K9),H9/K9<0),"n.a.",H9/K9) -> 10.263241
B10: 09/28/2011 | C10: 코오롱아이넷 | D10: 코오롱건설 | F10: 113666.75 | G10: 1 | H10: 359674.81 | I10: 113666.75 | J10: 16261.359 | K10: 27272.191 | L10: =I10/J10 -> 6.9899907 | M10: =IF(OR(ISERROR(H10/K10),H10/K10<0),"n.a.",H10/K10) -> 13.188335
G12: Guideline Transaction Method
G13: Transaction Multiple | M13: EV/EBITDA
G14: Median | M14: =MEDIAN(M$6:M$10) -> 11.299724
G15: Mean | M15: =AVERAGE(M$6:M$10) -> 11.512756
G17: Comparable Transaction Method
G18: Multiple | M18: EV/EBITDA
G19: Minimum | M19: =MIN(M6:M10) -> 10.263241
G20: Maxamum | M20: =MAX(M6:M10) -> 13.188335
G22: Company Financials | M22: EBITDA
G23: 대상회사 | M23: ='GPCM '!S30 -> 10451.112
G25: Enterprise Value | O25: Enterprise Value
G26: =G19 -> Minimum | M26: =M19*M23 -> 107262.28 | O26: Median | R26: =M14*$M$23 -> 118094.67
G27: =G20 -> Maxamum | M27: =M23*M20 -> 137832.77 | O27: Mean | R27: =M15*$M$23 -> 120321.1
G31: Net Debt | M31: ='GPCM '!S40 -> -16984.526 | O31: Net Debt | R31: =M31 -> -16984.526
G34: 주식가치 | M34: KRW Millions | O34: 주식가치 | R34: KRW Millions
G35: =G26 -> Minimum | M35: =M26-$M$31 -> 124246.8 | O35: Median | R35: =R26-$M$31 -> 135079.2
G36: =G27 -> Maxamum | M36: =M27-$M$31 -> 154817.29 | O36: Mean | R36: =R27-$M$31 -> 137305.62
G41: Guideline Public Company Method | L41: Guideline Public Company Method
G42: Multiple | J42: PER | L42: Multiple | O42: PER
G43: Minimum | J43: =MIN(L6:L10) -> 6.9899907 | L43: Mean | O43: =AVERAGE(L6:L10) -> 16.168446
G44: Maxamum | J44: =MAX(L6:L10) -> 31.796293 | L44: Median | O44: =MEDIAN(L6:L10) -> 15.589022
G47: Company Financials | J47: NI | L47: Company Financials | O47: NI
G48: 대상회사 | J48: =7430802379/1000000 -> 7430.8024 | L48: 대상회사 | O48: =J48 -> 7430.8024
G50: 주식가치 | J50: KRW Millions | L50: 주식가치 | O50: KRW Millions
G51: =G43 -> Minimum | J51: =J43*J48 -> 51941.24 | L51: =L43 -> Mean | O51: =O43*O48 -> 120144.53
G52: =G44 -> Maxamum | J52: =J48*J44 -> 236271.97 | L52: =L44 -> Median | O52: =O48*O44 -> 115838.94

Sheet GPCM 
B1: ="Project"&" "&Title!L6 -> Project IT
B2: Guideline Public Company Method
B4: Guideline Public Company | C4: Ticker | D4: Country | E4: Currency (Millions) | F4: MKT Cap | G4: Minority Interest | H4: Net Debt | I4: Enterprise Value | J4: LTM | P4: Multiples | W4: 2016 Consensus | AA4: Multiples | AF4: 2017 Consensus | AJ4: Multiples
I5: of Equity(MM) | J5: BV | K5: Sales | L5: EBIT | M5: Dep. | N5: EBITDA | O5: Net Income | P5: PBR | Q5: EV/Sales | R5: EV/EBIT | S5: EV/EBITDA | T5: PER | W5: Sales | X5: EBIT | Y5: EBITDA | Z5: Net Income | AA5: EV/Sales | AB5: EV/EBIT | AC5: EV/EBITDA | AD5: PER | AF5: Sales | AG5: EBIT | AH5: EBITDA | AI5: Net Income | AJ5: EV/Sales | AK5: EV/EBIT | AL5: EV/EBITDA | AM5: PER
A6: 1 | B6: =WACC!B6 -> SAMSUNG SDS CO LTD | C6: 018260 KS Equity | D6: SOUTH KOREA | E6: KRW | F6: =IF(B6="","",WACC!I6) -> 20173498 | G6: =유사기업BS!C6 -> 170549.24 | H6: =유사기업BS!C4-유사기업BS!C3 -> -1780558.2 | I6: =F6+G6+H6 -> 18563489 | J6: =유사기업BS!C5 -> 4558746.8 | K6: =유사기업IS!C3 -> 7917776.1 | L6: =유사기업IS!C4 -> 601086.15 | M6: =유사기업IS!C5 -> 387759.73 | N6: =L6+M6 -> 988845.89 | O6: =유사기업IS!C6 -> 463627 | P6: =IF(OR(ISERROR(F6/J6),F6/J6<0),"n.a.",F6/J6) -> 4.4252289 | Q6: =IF(OR(ISERROR(I6/K6),I6/K6<0),"n.a.",I6/K6) -> 2.3445332 | R6: =IF(OR(ISERROR(I6/L6),I6/L6<0),"n.a.",I6/L6) -> 30.883242 | S6: =IF(OR(ISERROR(I6/N6),I6/N6<0),"n.a.",I6/N6) -> 18.772884 | T6: =IF(OR(ISERROR(F6/O6),F6/O6<0),"n.a.",F6/O6) -> 43.512345 | W6: =8674492550000/10^6 -> 8674492.6 | X6: =665470428571.429/10^6 -> 665470.43 | Y6: =1053360500000/10^6 -> 1053360.5 | Z6: =486456190476.19/10^6 -> 486456.19 | AA6: =IF(OR(ISERROR($I6/W6),$I6/W6<0),"n.a.",$I6/W6) -> 2.1400086 | AB6: =IF(OR(ISERROR($I6/X6),$I6/X6<0),"n.a.",$I6/X6) -> 27.895287 | AC6: =IF(OR(ISERROR($I6/Y6),$I6/Y6<0),"n.a.",$I6/Y6) -> 17.623111 | AD6: =IF(OR(ISERROR($F6/Z6),$F6/Z6<0),"n.a.",$F6/Z6) -> 41.470328 | AF6: =9637008578947.37/10^6 -> 9637008.6 | AG6: =740004571428.571/10^6 -> 740004.57 | AH6: =1141142789473.68/10^6 -> 1141142.8 | AI6: =545924900000/10^6 -> 545924.9 | AJ6: =IF(OR(ISERROR($I6/AF6),$I6/AF6<0),"n.a.",$I6/AF6) -> 1.9262709 | AK6: =IF(OR(ISERROR($I6/AG6),$I6/AG6<0),"n.a.",$I6/AG6) -> 25.085641 | AL6: =IF(OR(ISERROR($I6/AH6),$I6/AH6<0),"n.a.",$I6/AH6) -> 16.267455 | AM6: =IF(OR(ISERROR($F6/AI6),$F6/AI6<0),"n.a.",$F6/AI6) -> 36.952881
A7: =A6+1 -> 2 | B7: =WACC!B7 -> POSCO ICT CO LTD | C7: 022100 KS Equity | D7: SOUTH KOREA | E7: KRW | F7: =IF(B7="","",WACC!I7) -> 749314.02 | G7: =유사기업BS!K6 -> 1131.9434 | H7: =유사기업BS!K4-유사기업BS!K3 -> -27378.177 | I7: =F7+G7+H7 -> 723067.79 | J7: =유사기업BS!K5 -> 376233.16 | K7: =유사기업IS!O3 -> 951600.58 | L7: =유사기업IS!O4 -> 38347.109 | M7: =유사기업IS!O5 -> 38482.437 | N7: =L7+M7 -> 76829.546 | O7: =유사기업IS!O6 -> -2601.83 | P7: =IF(OR(ISERROR(F7/J7),F7/J7<0),"n.a.",F7/J7) -> 1.9916214 | Q7: =IF(OR(ISERROR(I7/K7),I7/K7<0),"n.a.",I7/K7) -> 0.75984378 | R7: =IF(OR(ISERROR(I7/L7),I7/L7<0),"n.a.",I7/L7) -> 18.855862 | S7: =IF(OR(ISERROR(I7/N7),I7/N7<0),"n.a.",I7/N7) -> 9.4113245 | T7: =IF(OR(ISERROR(F7/O7),F7/O7<0),"n.a.",F7/O7) -> n.a. | W7: =971000000000/10^6 -> 971000 | X7: n.a. | Y7: =85000000000/10^6 -> 85000 | Z7: =33000000000/10^6 -> 33000 | AA7: =IF(OR(ISERROR($I7/W7),$I7/W7<0),"n.a.",$I7/W7) -> 0.74466301 | AC7: =IF(OR(ISERROR($I7/Y7),$I7/Y7<0),"n.a.",$I7/Y7) -> 8.5066799 | AD7: =IF(OR(ISERROR($F7/Z7),$F7/Z7<0),"n.a.",$F7/Z7) -> 22.706486 | AF7: =1010000000000/10^6 -> 1010000 | AG7: n.a. | AH7: =88000000000/10^6 -> 88000 | AI7: =40000000000/10^6 -> 40000 | AJ7: =IF(OR(ISERROR($I7/AF7),$I7/AF7<0),"n.a.",$I7/AF7) -> 0.7159087 | AL7: =IF(OR(ISERROR($I7/AH7),$I7/AH7<0),"n.a.",$I7/AH7) -> 8.2166794 | AM7: =IF(OR(ISERROR($F7/AI7),$F7/AI7<0),"n.a.",$F7/AI7) -> 18.732851
A8: =A7+1 -> 3 | B8: =WACC!B8 -> DONGBU CO LTD | C8: 012030 KS Equity | D8: SOUTH KOREA | E8: KRW | F8: =IF(B8="","",WACC!I8) -> 89137.821 | G8: =유사기업BS!S6 -> 0 | H8: =유사기업BS!S4-유사기업BS!S3 -> 55162.137 | I8: =F8+G8+H8 -> 144299.96 | J8: =유사기업BS!S5 -> 188299.55 | K8: =유사기업IS!AA3 -> 228679.86 | L8: =유사기업IS!AA4 -> -6547.3502 | M8: =유사기업IS!AA5 -> 4496.6716 | N8: =L8+M8 -> -2050.6787 | O8: =유사기업IS!AA6 -> -30195.535 | P8: =IF(OR(ISERROR(F8/J8),F8/J8<0),"n.a.",F8/J8) -> 0.47338308 | Q8: =IF(OR(ISERROR(I8/K8),I8/K8<0),"n.a.",I8/K8) -> 0.63101296 | R8: =IF(OR(ISERROR(I8/L8),I8/L8<0),"n.a.",I8/L8) -> n.a. | S8: =IF(OR(ISERROR(I8/N8),I8/N8<0),"n.a.",I8/N8) -> n.a. | T8: =IF(OR(ISERROR(F8/O8),F8/O8<0),"n.a.",F8/O8) -> n.a. | W8: n.a. | X8: n.a. | Y8: n.a. | Z8: n.a. | AF8: n.a. | AG8: n.a. | AH8: n.a. | AI8: n.a.
A9: =A8+1 -> 4 | B9: =WACC!B9 -> SHINSEGAE INFORMATION & COMM | C9: 035510 KS Equity | D9: SOUTH KOREA | E9: KRW | F9: =IF(B9="","",WACC!I9) -> 168289.72 | G9: =유사기업BS!AA6 -> 0 | H9: =유사기업BS!AA4-유사기업BS!AA3 -> -94207.52 | I9: =F9+G9+H9 -> 74082.197 | J9: =유사기업BS!AA5 -> 168494.1 | K9: =유사기업IS!AM3 -> 256320 | L9: =유사기업IS!AM4 -> 15541.51 | M9: =유사기업IS!AM5 -> 5762.1324 | N9: =L9+M9 -> 21303.642 | O9: =유사기업IS!AM6 -> 10573.583 | P9: =IF(OR(ISERROR(F9/J9),F9/J9<0),"n.a.",F9/J9) -> 0.99878698 | Q9: =IF(OR(ISERROR(I9/K9),I9/K9<0),"n.a.",I9/K9) -> 0.2890223 | R9: =IF(OR(ISERROR(I9/L9),I9/L9<0),"n.a.",I9/L9) -> 4.766731 | S9: =IF(OR(ISERROR(I9/N9),I9/N9<0),"n.a.",I9/N9) -> 3.4774428 | T9: =IF(OR(ISERROR(F9/O9),F9/O9<0),"n.a.",F9/O9) -> 15.916053 | W9: =268000000000/10^6 -> 268000 | X9: =16100000000/10^6 -> 16100 | Y9: =22900000000/10^6 -> 22900 | Z9: =11600000000/10^6 -> 11600 | AA9: =IF(OR(ISERROR($I9/W9),$I9/W9<0),"n.a.",$I9/W9) -> 0.27642611 | AB9: =IF(OR(ISERROR($I9/X9),$I9/X9<0),"n.a.",$I9/X9) -> 4.6013787 | AC9: =IF(OR(ISERROR($I9/Y9),$I9/Y9<0),"n.a.",$I9/Y9) -> 3.2350304 | AD9: =IF(OR(ISERROR($F9/Z9),$F9/Z9<0),"n.a.",$F9/Z9) -> 14.507734 | AF9: =283000000000/10^6 -> 283000 | AG9: =22700000000/10^6 -> 22700 | AH9: =29600000000/10^6 -> 29600 | AI9: =15800000000/10^6 -> 15800 | AJ9: =IF(OR(ISERROR($I9/AF9),$I9/AF9<0),"n.a.",$I9/AF9) -> 0.26177455 | AK9: =IF(OR(ISERROR($I9/AG9),$I9/AG9<0),"n.a.",$I9/AG9) -> 3.2635329 | AL9: =IF(OR(ISERROR($I9/AH9),$I9/AH9<0),"n.a.",$I9/AH9) -> 2.5027769 | AM9: =IF(OR(ISERROR($F9/AI9),$F9/AI9<0),"n.a.",$F9/AI9) -> 10.651248
A10: =A9+1 -> 5 | B10: =WACC!B10 -> HYUNDAI INFORMATION TECH | C10: 026180 KS Equity | D10: SOUTH KOREA | E10: KRW | F10: =IF(B10="","",WACC!I10) -> 116521.65 | G10: =유사기업BS!AI6 -> 0 | H10: =유사기업BS!AI4-유사기업BS!AI3 -> 68031.374 | I10: =F10+G10+H10 -> 184553.03 | J10: =유사기업BS!AI5 -> 25725.035 | K10: =유사기업IS!AY3 -> 145026.31 | L10: =유사기업IS!AY4 -> -1078.9798 | M10: =유사기업IS!AY5 -> 8540.6252 | N10: =L10+M10 -> 7461.6454 | O10: =유사기업IS!AY6 -> -3956.2171 | P10: =IF(OR(ISERROR(F10/J10),F10/J10<0),"n.a.",F10/J10) -> 4.5295042 | Q10: =IF(OR(ISERROR(I10/K10),I10/K10<0),"n.a.",I10/K10) -> 1.2725487 | R10: =IF(OR(ISERROR(I10/L10),I10/L10<0),"n.a.",I10/L10) -> n.a. | S10: =IF(OR(ISERROR(I10/N10),I10/N10<0),"n.a.",I10/N10) -> 24.733557 | T10: =IF(OR(ISERROR(F10/O10),F10/O10<0),"n.a.",F10/O10) -> n.a. | W10: n.a. | X10: n.a. | Y10: n.a. | Z10: n.a. | AF10: n.a. | AG10: n.a. | AH10: n.a. | AI10: n.a.
A11: =A10+1 -> 6 | B11: =WACC!B11 -> HANIL NETWORKS CO LTD | C11: 046110 KS Equity | D11: SOUTH KOREA | E11: KRW | F11: =IF(B11="","",WACC!I11) -> 34610.335 | G11: =유사기업BS!AQ6 -> 26.040324 | H11: =유사기업BS!AQ4-유사기업BS!AQ3 -> -8787.8654 | I11: =F11+G11+H11 -> 25848.51 | J11: =유사기업BS!AQ5 -> 32002.201 | K11: =유사기업IS!BK3 -> 92527.773 | L11: =유사기업IS!BK4 -> 557.12668 | M11: =유사기업IS!BK5 -> 3634.339 | N11: =L11+M11 -> 4191.4657 | O11: =유사기업IS!BK6 -> 3115.3806 | P11: =IF(OR(ISERROR(F11/J11),F11/J11<0),"n.a.",F11/J11) -> 1.0814986 | Q11: =IF(OR(ISERROR(I11/K11),I11/K11<0),"n.a.",I11/K11) -> 0.27935947 | R11: =IF(OR(ISERROR(I11/L11),I11/L11<0),"n.a.",I11/L11) -> 46.396108 | S11: =IF(OR(ISERROR(I11/N11),I11/N11<0),"n.a.",I11/N11) -> 6.1669381 | T11: =IF(OR(ISERROR(F11/O11),F11/O11<0),"n.a.",F11/O11) -> 11.109505 | W11: n.a. | X11: n.a. | Y11: n.a. | Z11: n.a. | AF11: n.a. | AG11: n.a. | AH11: n.a. | AI11: n.a.
A12: =A11+1 -> 7
A13: =A12+1 -> 8
A14: =A13+1 -> 9
A15: =A14+1 -> 10
A16: =A15+1 -> 11
A17: =A16+1 -> 12
A18: =A17+1 -> 13
A19: =A18+1 -> 14
A20: =A19+1 -> 15
A21: =A20+1 -> 16
A22: =A21+1 -> 17
M24: 1 | N24: Guideline Public Company Method | Y24: Guideline Public Company Method | AH24: Guideline Public Company Method
N25: Multiples | P25: PBR | Q25: EV/Sales | R25: EV/EBIT | S25: EV/EBITDA | T25: PER | Y25: Multiples | AA25: EV/Sales | AB25: EV/EBIT | AC25: EV/EBITDA | AD25: PER | AH25: Multiples | AJ25: EV/Sales | AK25: EV/EBIT | AL25: EV/EBITDA | AM25: PER
N26: Median | P26: =MEDIAN(P6:P11) -> 1.53656 | Q26: =MEDIAN(Q6:Q11) -> 0.69542837 | R26: =MEDIAN(R6:R11) -> 24.869552 | S26: =MEDIAN(S6:S11) -> 9.4113245 | T26: =MEDIAN(T6:T11) -> 15.916053 | Y26: Median | AA26: =MEDIAN(AA6:AA11) -> 0.74466301 | AB26: =MEDIAN(AB6:AB11) -> 16.248333 | AC26: =MEDIAN(AC6:AC11) -> 8.5066799 | AD26: =MEDIAN(AD6:AD11) -> 22.706486 | AH26: Median | AJ26: =MEDIAN(AJ6:AJ11) -> 0.7159087 | AK26: =MEDIAN(AK6:AK11) -> 14.174587 | AL26: =MEDIAN(AL6:AL11) -> 8.2166794 | AM26: =MEDIAN(AM6:AM11) -> 18.732851
N27: Mean | P27: =AVERAGE(P6:P11) -> 2.2500039 | Q27: =AVERAGE(Q6:Q11) -> 0.92938673 | R27: =AVERAGE(R6:R11) -> 25.225486 | S27: =AVERAGE(S6:S11) -> 12.512429 | T27: =AVERAGE(T6:T11) -> 23.512634 | Y27: Mean | AA27: =AVERAGE(AA6:AA11) -> 1.0536992 | AB27: =AVERAGE(AB6:AB11) -> 16.248333 | AC27: =AVERAGE(AC6:AC11) -> 9.7882737 | AD27: =AVERAGE(AD6:AD11) -> 26.228183 | AH27: Mean | AJ27: =AVERAGE(AJ6:AJ11) -> 0.96798471 | AK27: =AVERAGE(AK6:AK11) -> 14.174587 | AL27: =AVERAGE(AL6:AL11) -> 8.9956371 | AM27: =AVERAGE(AM6:AM11) -> 22.112326
N29: Company Financials | P29: Book Value | Q29: Sales | R29: EBIT | S29: EBITDA | T29: Net Income | Y29: Company Financials | AA29: Sales | AB29: EBIT | AC29: EBITDA | AD29: Net Income | AH29: Company Financials | AJ29: Sales | AK29: EBIT | AL29: EBITDA | AM29: Net Income
N30: 대상회사 | P30: =BS!O77 -> 41343.829 | Q30: =IS!O7 -> 214888.12 | R30: =IS!O45 -> 9727.2909 | S30: =IS!O68 -> 10451.112 | T30: =IS!O66 -> 7612.9499 | Y30: 대상회사 | AH30: 대상회사
N32: Enterprise Value | P32: PBR | Q32: EV/Sales | R32: EV/EBIT | S32: EV/EBITDA | T32: PER | Y32: Enterprise Value | AA32: EV/Sales | AB32: EV/EBIT | AC32: EV/EBITDA | AD32: PER | AH32: Enterprise Value | AJ32: EV/Sales | AK32: EV/EBIT | AL32: EV/EBITDA | AM32: PER
N33: Median | P33: n.a. | Q33: =Q26*Q$30 -> 149439.3 | R33: =R26*R$30 -> 241913.37 | S33: =S26*S$30 -> 98358.803 | T33: n.a. | Y33: Median | AA33: =AA26*AA$30 -> 0 | AB33: =AB26*AB$30 -> 0 | AC33: =AC26*AC$30 -> 0 | AD33: n.a. | AH33: Median | AJ33: =AJ26*AJ$30 -> 0 | AK33: =AK26*AK$30 -> 0 | AL33: =AL26*AL$30 -> 0 | AM33: n.a.
N34: Mean | P34: n.a. | Q34: =Q27*Q$30 -> 199714.17 | R34: =R27*R$30 -> 245375.64 | S34: =S27*S$30 -> 130768.79 | T34: n.a. | Y34: Mean | AA34: =AA27*AA$30 -> 0 | AB34: =AB27*AB$30 -> 0 | AC34: =AC27*AC$30 -> 0 | AD34: n.a. | AH34: Mean | AJ34: =AJ27*AJ$30 -> 0 | AK34: =AK27*AK$30 -> 0 | AL34: =AL27*AL$30 -> 0 | AM34: n.a.
N36: NOA | S36: ='NOA&IBD'!E13 -> 16984.526 | Y36: NOA | AH36: NOA
N38: IBD | S38: ='NOA&IBD'!E20 -> 0 | Y38: IBD | AH38: IBD
N40: Net Debt | S40: =S38-S36 -> -16984.526 | Y40: Net Debt | AC40: =AC38-AC36 -> 0 | AH40: Net Debt | AL40: =AL38-AL36 -> 0
N42: Equity Value | P42: PBR | Q42: EV/Sales | R42: EV/EBIT | S42: EV/EBITDA | T42: PER | Y42: Equity Value | AA42: EV/Sales | AB42: EV/EBIT | AC42: EV/EBITDA | AD42: PER | AH42: Equity Value | AJ42: EV/Sales | AK42: EV/EBIT | AL42: EV/EBITDA | AM42: PER
N43: Median | P43: =P26*P$30 -> 63527.274 | Q43: =Q33-$S$40 -> 166423.82 | R43: =R33-$S$40 -> 258897.89 | S43: =S33-$S$40 -> 115343.33 | T43: =T26*T$30 -> 121168.12 | Y43: Median | AA43: =AA33-$S$40 -> 16984.526 | AB43: =AB33-$S$40 -> 16984.526 | AC43: =AC33-$S$40 -> 16984.526 | AD43: =AD26*AD$30 -> 0 | AH43: Median | AJ43: =AJ33-$S$40 -> 16984.526 | AK43: =AK33-$S$40 -> 16984.526 | AL43: =AL33-$S$40 -> 16984.526 | AM43: =AM26*AM$30 -> 0
N44: Mean | P44: =P27*P$30 -> 93023.775 | Q44: =Q34-$S$40 -> 216698.7 | R44: =R34-$S$40 -> 262360.16 | S44: =S34-$S$40 -> 147753.32 | T44: =T27*T$30 -> 179000.51 | Y44: Mean | AA44: =AA34-$S$40 -> 16984.526 | AB44: =AB34-$S$40 -> 16984.526 | AC44: =AC34-$S$40 -> 16984.526 | AD44: =AD27*AD$30 -> 0 | AH44: Mean | AJ44: =AJ34-$S$40 -> 16984.526 | AK44: =AK34-$S$40 -> 16984.526 | AL44: =AL34-$S$40 -> 16984.526 | AM44: =AM27*AM$30 -> 0

Sheet DCF
B1: ="Project"&" "&Title!L6 -> Project IT | N1: =Des!C12 -> DRAFT - For Discussion Purposes Only
B2: Discounted Cash Flow Results
B4: DCF Results | D4: Historical | H4: Forecasted
B5: =unit -> KRW Millions | D5: ='Pro forma'!E5 -> 2012 | E5: ='Pro forma'!F5 -> 2013 | F5: ='Pro forma'!G5 -> 2014 | G5: ='Pro forma'!H5 -> 2015/12A | H5: ='Pro forma'!I5 -> 2015/0E | I5: ='Pro forma'!K5 -> 2016 | J5: ='Pro forma'!L5 -> 2017 | K5: ='Pro forma'!M5 -> 2018 | L5: ='Pro forma'!N5 -> 2019 | M5: ='Pro forma'!O5 -> 2020 | N5: Terminal
B6: 매출액 | D6: ='Pro forma'!E6 -> 182279.27 | E6: ='Pro forma'!F6 -> 211683.37 | F6: ='Pro forma'!G6 -> 251810.75 | G6: ='Pro forma'!H6 -> 214888.12 | I6: ='Pro forma'!K6 -> 247657.65 | J6: ='Pro forma'!L6 -> 256222.03 | K6: ='Pro forma'!M6 -> 265319.19 | L6: ='Pro forma'!N6 -> 274730.7 | M6: ='Pro forma'!O6 -> 284669.53 | N6: =M6*(1+$C$24) -> 284669.53
B7: 매출원가 | D7: ='Pro forma'!E9 -> 165640.96 | E7: ='Pro forma'!F9 -> 194029.19 | F7: ='Pro forma'!G9 -> 233681.98 | G7: ='Pro forma'!H9 -> 193423.41 | I7: ='Pro forma'!K9 -> 225185.42 | J7: ='Pro forma'!L9 -> 233133.63 | K7: ='Pro forma'!M9 -> 241478.05 | L7: ='Pro forma'!N9 -> 250207.65 | M7: ='Pro forma'!O9 -> 259472.68 | N7: =M7*(1+$C$24) -> 259472.68
B8: 매출총이익 | D8: =D6-D7 -> 16638.31 | E8: =E6-E7 -> 17654.178 | F8: =F6-F7 -> 18128.765 | G8: =G6-G7 -> 21464.712 | I8: =I6-I7 -> 22472.232 | J8: =J6-J7 -> 23088.4 | K8: =K6-K7 -> 23841.136 | L8: =L6-L7 -> 24523.055 | M8: =M6-M7 -> 25196.85 | N8: =N6-N7 -> 25196.85
B9: 판매비와관리비 | D9: ='Pro forma'!E17 -> 7996.3669 | E9: ='Pro forma'!F17 -> 8441.2134 | F9: ='Pro forma'!G17 -> 8664.1025 | G9: ='Pro forma'!H17 -> 11711.818 | I9: ='Pro forma'!K17 -> 11720.924 | J9: ='Pro forma'!L17 -> 12255.522 | K9: ='Pro forma'!M17 -> 12744.482 | L9: ='Pro forma'!N17 -> 13187.062 | M9: ='Pro forma'!O17 -> 13753.785 | N9: =M9*(1+$C$24) -> 13753.785
B10: 영업이익 | D10: =D8-D9 -> 8641.9429 | E10: =E8-E9 -> 9212.9645 | F10: =F8-F9 -> 9464.6625 | G10: =G8-G9 -> 9752.8942 | I10: =I8-I9 -> 10751.308 | J10: =J8-J9 -> 10832.877 | K10: =K8-K9 -> 11096.654 | L10: =L8-L9 -> 11335.993 | M10: =M8-M9 -> 11443.066 | N10: =N8-N9 -> 11443.066
B11: 법인세비용 | I11: =IF(I10>200,IF(I10>20000,200*가정!$E$62+(20000-200)*가정!$E$65+(I10-20000)*가정!$E$68,200*가정!$E$62+(I10-200)*가정!$E$65),IF(I10<0,0,I10*가정!$E$62)) -> 2343.2877 | J11: =IF(J10>200,IF(J10>20000,200*가정!$E$62+(20000-200)*가정!$E$65+(J10-20000)*가정!$E$68,200*가정!$E$62+(J10-200)*가정!$E$65),IF(J10<0,0,J10*가정!$E$62)) -> 2361.233 | K11: =IF(K10>200,IF(K10>20000,200*가정!$E$62+(20000-200)*가정!$E$65+(K10-20000)*가정!$E$68,200*가정!$E$62+(K10-200)*가정!$E$65),IF(K10<0,0,K10*가정!$E$62)) -> 2419.264 | L11: =IF(L10>200,IF(L10>20000,200*가정!$E$62+(20000-200)*가정!$E$65+(L10-20000)*가정!$E$68,200*가정!$E$62+(L10-200)*가정!$E$65),IF(L10<0,0,L10*가정!$E$62)) -> 2471.9185 | M11: =IF(M10>200,IF(M10>20000,200*가정!$E$62+(20000-200)*가정!$E$65+(M10-20000)*가정!$E$68,200*가정!$E$62+(M10-200)*가정!$E$65),IF(M10<0,0,M10*가정!$E$62)) -> 2495.4744 | N11: =IF(N10>200,IF(N10>20000,200*가정!$E$62+(20000-200)*가정!$E$65+(N10-20000)*가정!$E$68,200*가정!$E$62+(N10-200)*가정!$E$65),IF(N10<0,0,N10*가정!$E$62)) -> 2495.4744
B12: 세후영업이익 | I12: =I10-I11 -> 8408.0199 | J12: =J10-J11 -> 8471.6443 | K12: =K10-K11 -> 8677.3904 | L12: =L10-L11 -> 8864.0748 | M12: =M10-M11 -> 8947.5911 | N12: =N10-N11 -> 8947.5911
B13: 가산: 감가상각비 | I13: ='CapEx&Dep'!K7 -> 945.31832 | J13: ='CapEx&Dep'!L7 -> 1265.9716 | K13: ='CapEx&Dep'!M7 -> 1562.7974 | L13: ='CapEx&Dep'!N7 -> 1823.8785 | M13: ='CapEx&Dep'!O7 -> 2179.7868 | N13: =CapEx
B14: 차감: 순운전자본의 변동 | I14: =WC!K19 -> -6765.6418 | J14: =WC!L19 -> 388.93767 | K14: =WC!M19 -> 416.56031 | L14: =WC!N19 -> 409.05387 | M14: =WC!O19 -> 421.45988 | N14: =WC!P19 -> 421.45988
B15: 차감: 자본적지출 | I15: ='CapEx&Dep'!K6 -> 1048.6801 | J15: ='CapEx&Dep'!L6 -> 1084.945 | K15: ='CapEx&Dep'!M6 -> 1123.466 | L15: ='CapEx&Dep'!N6 -> 1163.3181 | M15: ='CapEx&Dep'!O6 -> 1205.403 | N15: =Dep
B16: 추정영업현금흐름 (FCFF) | I16: =I12+I13-I14-I15 -> 15070.3 | J16: =J12+J13-J14-J15 -> 8263.7332 | K16: =K12+K13-K14-K15 -> 8700.1614 | L16: =L12+L13-L14-L15 -> 9115.5814 | M16: =M12+M13-M14-M15 -> 9500.515 | N16: =N12-N14 -> 8526.1312
B17: 할인기간 | I17: =ppf -> 1.0027397 | J17: =I17+1 -> 2.0027397 | K17: =J17+1 -> 3.0027397 | L17: =K17+1 -> 4.0027397 | M17: =L17+1 -> 5.0027397 | N17: =M17 -> 5.0027397
B18: 할인계수 | I18: =1/(1+$C$25)^I17 -> 0.9163716 | J18: =1/(1+$C$25)^J17 -> 0.8399373 | K18: =1/(1+$C$25)^K17 -> 0.76987837 | L18: =1/(1+$C$25)^L17 -> 0.70566303 | M18: =1/(1+$C$25)^M17 -> 0.64680388 | N18: =1/(1+$C$25)^N17 -> 0.64680388
B19: FCFF의 현재가치 | I19: =I16*I18 -> 13809.995 | J19: =J16*J18 -> 6941.0177 | K19: =K16*K18 -> 6698.0661 | L19: =L16*L18 -> 6432.5288 | M19: =M16*M18 -> 6144.97 | N19: =N18*N16/(C25-C24) -> 60601.481
B20: 누적현재가치 | I20: =SUM(I19:M19) -> 40026.577
B21: Terminal Value의 현재가치 | I21: =N19 -> 60601.481
B22: Operating Value | I22: =I20+I21 -> 100628.06
B24: Terminal Growth Rate | C24: =g -> 0
B25: WACC | C25: =wacc -> 0.091
B27: Stand-Alone Operating Value
F28: =unit -> KRW Millions
B29: 항목 | D29: 평가결과 | I29: Terminal Growth Rate
D30: 최소값 | E30: 중앙값 | F30: 최대값 | H30: =I22 -> 100628.06 | I30: =J30-CHOOSE($O$33,$P$32,$P$33) -> -0.02 | J30: =K30-CHOOSE($O$33,$P$32,$P$33) -> -0.01 | K30: =g -> 0 | L30: =K30+CHOOSE($O$33,$P$32,$P$33) -> 0.01 | M30: =L30+CHOOSE($O$33,$P$32,$P$33) -> 0.02
B31: 영업가치 (Operating Value) | D31: =J34 -> 86804.575 | E31: =K33 -> 100628.06 | F31: =L32 -> 121908.79 | H31: =H32-CHOOSE($O$33,$P$32,$P$33) -> 0.071 | I31: 109198.71 | J31: 117099.2 | K31: 127225.18 | L31: 140671.15 | M31: 159390.05
B32: 비영업용자산 (Non-operating Asset) | E32: ='NOA&IBD'!E13 -> 16984.526 | H32: =H33-CHOOSE($O$33,$P$32,$P$33) -> 0.081 | I32: 98780.247 | J32: 104795.36 | K32: 112295.69 | L32: 121908.79 | M32: 134673.73 | O32: 민감도 범위 선택 | P32: 0.005
B33: 기업가치 (Enterprise Value) | D33: =D31+$E$32 -> 103789.1 | E33: =E31+$E$32 -> 117612.58 | F33: =F31+$E$32 -> 138893.32 | H33: =wacc -> 0.091 | I33: 90231.93 | J33: 94915.334 | K33: 100628.06 | L33: 107751.33 | M33: 116881.16 | O33: 2 | P33: 0.01
B34: 이자발생부부채 (Interest Bearing Debt) | E34: ='NOA&IBD'!E20 -> 0 | H34: =H33+CHOOSE($O$33,$P$32,$P$33) -> 0.101 | I34: 83090.367 | J34: 86804.575 | K34: 91254.269 | L34: 96681.917 | M34: 103449.73
B35: 비지배지분 | H35: =H34+CHOOSE($O$33,$P$32,$P$33) -> 0.111 | I35: 77033.645 | J35: 80024.891 | K35: 83555.1 | L35: 87784.361 | M35: 92943.129
B36: 주식가치 (Equity Value)_100% 기준 | D36: =D33-$E$34-$E$35 -> 103789.1 | E36: =E33-$E$34-$E$35 -> 117612.58 | F36: =F33-$E$34-$E$35 -> 138893.32
B38: 순자산 BV

Sheet Pro forma
B1: ="Project"&" "&Title!L6 -> Project IT | O1: =Des!C12 -> DRAFT - For Discussion Purposes Only
B2: 추정손익계산서
B4: 추정손익계산서
B5: =unit -> KRW Millions | C5: =D5-1 -> 2010 | D5: =E5-1 -> 2011 | E5: =F5-1 -> 2012 | F5: =G5-1 -> 2013 | G5: =J5-1 -> 2014 | H5: =YEAR(Des!$C$8)&"/"&MONTH(Des!$C$8)&"A" -> 2015/12A | I5: =YEAR(Des!$C$8)&"/"&12-MONTH(Des!$C$8)&"E" -> 2015/0E | J5: =YEAR(Des!C8) -> 2015 | K5: =J5+1 -> 2016 | L5: =K5+1 -> 2017 | M5: =L5+1 -> 2018 | N5: =M5+1 -> 2019 | O5: =N5+1 -> 2020
B6: 매출액 | C6: =매출액!C6 -> 101202.83 | D6: =매출액!D6 -> 120090.95 | E6: =매출액!E6 -> 182279.27 | F6: =매출액!F6 -> 211683.37 | G6: =매출액!G6 -> 251810.75 | H6: =매출액!H6 -> 214888.12 | I6: =매출액!I6 -> 0 | J6: =매출액!J6 -> 214888.12 | ... O6: =매출액!O6 -> 284669.53
B7: % of growth | D7: =D6/C6-1 -> 0.18663626 | F7: =F6/E6-1 -> 0.16131348 | G7: =G6/F6-1 -> 0.18956321 | H7: n.a. | I7: n.a. | J7: =J6/G6-1 -> -0.14662847 | K7: =K6/J6-1 -> 0.15249576 | L7: =L6/K6-1 -> 0.034581504 | M7: =M6/L6-1 -> 0.035505009 | N7: =N6/M6-1 -> 0.035472419 | O7: =O6/N6-1 -> 0.036176613
B9: 매출원가 | C9: =매출원가!C6 -> 86101.883 | D9: =매출원가!D6 -> 106369.5 | E9: =매출원가!E6 -> 165640.96 | F9: =매출원가!F6 -> 194029.19 | G9: =매출원가!G6 -> 233681.98 | H9: =매출원가!H6 -> 193423.41 | I9: =매출원가!I6 -> 0 | J9: =매출원가!J6 -> 193443.28 | ... O9: =매출원가!O6 -> 259472.68
B10: % of growth | D10: =D9/C9-1 -> 0.23539109 | F10: =F9/E9-1 -> 0.17138415 | G10: =G9/F9-1 -> 0.20436508 | H10: n.a. | I10: n.a. | J10: =J9/G9-1 -> -0.1721943 | K10: =K9/J9-1 -> 0.16409019 | L10: =L9/K9-1 -> 0.035296275 | M10: =M9/L9-1 -> 0.035792471 | N10: =N9/M9-1 -> 0.036150675 | O10: =O9/N9-1 -> 0.037029368
B11: % of sales | C11: =C9/C$6 -> 0.85078534 | D11: =D9/D$6 -> 0.88574121 | E11: =E9/E$6 -> 0.90872078 | F11: =F9/F$6 -> 0.91660102 | G11: =G9/G$6 -> 0.92800639 | H11: =H9/H$6 -> 0.90011215 | I11: =I9/I$6 -> #DIV/0! | J11: =J9/J$6 -> 0.90020459 | ... O11: =O9/O$6 -> 0.91148736
B13: 매출총이익 | C13: =C6-C9 -> 15100.945 | D13: =D6-D9 -> 13721.446 | E13: =E6-E9 -> 16638.31 | F13: =F6-F9 -> 17654.178 | G13: =G6-G9 -> 18128.765 | H13: =H6-H9 -> 21464.712 | I13: =I6-I9 -> 0 | J13: =J6-J9 -> 21444.848 | ... O13: =O6-O9 -> 25196.85
B14: % of growth | D14: =D13/C13-1 -> -0.09135184 | F14: =F13/E13-1 -> 0.061055967 | G14: =G13/F13-1 -> 0.026882423 | H14: n.a. | I14: n.a. | J14: =J13/G13-1 -> 0.18291829 | K14: =K13/J13-1 -> 0.047908219 | L14: =L13/K13-1 -> 0.027419064 | M14: =M13/L13-1 -> 0.032602381 | N14: =N13/M13-1 -> 0.028602612 | O14: =O13/N13-1 -> 0.027475993
B15: % of sales | C15: =C13/C$6 -> 0.14921466 | D15: =D13/D$6 -> 0.11425879 | E15: =E13/E$6 -> 0.091279223 | F15: =F13/F$6 -> 0.083398984 | G15: =G13/G$6 -> 0.071993611 | H15: =H13/H$6 -> 0.099887849 | I15: =I13/I$6 -> #DIV/0! | J15: =J13/J$6 -> 0.099795406 | ... O15: =O13/O$6 -> 0.088512636
B17: 판매비와관리비 | C17: ='SG&A'!C6 -> 8937.6962 | D17: ='SG&A'!D6 -> 7198.3637 | E17: ='SG&A'!E6 -> 7996.3669 | F17: ='SG&A'!F6 -> 8441.2134 | G17: ='SG&A'!G6 -> 8664.1025 | H17: ='SG&A'!H6 -> 11711.818 | I17: ='SG&A'!I6 -> 44.614312 | J17: ='SG&A'!J6 -> 11722.521 | ... O17: ='SG&A'!O6 -> 13753.785
B18: % of growth | D18: =D17/C17-1 -> -0.19460636 | F18: =F17/E17-1 -> 0.055631083 | G18: =G17/F17-1 -> 0.026404859 | H18: n.a. | I18: n.a. | J18: =J17/G17-1 -> 0.35299886 | K18: =K17/J17-1 -> -0.00013617951 | L18: =L17/K17-1 -> 0.045610557 | M18: =M17/L17-1 -> 0.039897093 | N18: =N17/M17-1 -> 0.034727172 | O18: =O17/N17-1 -> 0.042975693
B19: % of sales | C19: n.a. | D19: n.a. | E19: =E17/E$6 -> 0.043868768 | F19: =F17/F$6 -> 0.039876602 | G19: =G17/G$6 -> 0.034407199 | H19: =H17/H$6 -> 0.054501933 | I19: =I17/I$6 -> #DIV/0! | J19: =J17/J$6 -> 0.054551739 | K19: =K17/K$6 -> 0.047327124 | L19: =L17/L$6 -> 0.04783165 | ... O19: =O17/O$6 -> 0.048314918
B21: 영업이익 | C21: =C13-C17 -> 6163.2491 | D21: =D13-D17 -> 6523.0825 | E21: =E13-E17 -> 8641.9429 | F21: =F13-F17 -> 9212.9645 | G21: =G13-G17 -> 9464.6625 | H21: =H13-H17 -> 9752.8942 | I21: =I13-I17 -> -44.614312 | J21: =J13-J17 -> 9722.3268 | ... O21: =O13-O17 -> 11443.066
B22: % of growth | D22: =D21/C21-1 -> 0.05838371 | F22: =F21/E21-1 -> 0.066075598 | G22: =G21/F21-1 -> 0.027319982 | H22: n.a. | I22: n.a. | J22: =J21/G21-1 -> 0.027223822 | K22: =K21/J21-1 -> 0.10583689 | L22: =L21/K21-1 -> 0.007586954 | M22: =M21/L21-1 -> 0.02434968 | N22: =N21/M21-1 -> 0.02156857 | O22: =O21/N21-1 -> 0.009445327
B23: % of sales | C23: =C21/C$6 -> 0.06089997 | D23: =D21/D$6 -> 0.054317855 | E23: =E21/E$6 -> 0.047410455 | F23: =F21/F$6 -> 0.043522382 | G23: =G21/G$6 -> 0.037586412 | H23: =H21/H$6 -> 0.045385915 | I23: =I21/I$6 -> #DIV/0! | J23: =J21/J$6 -> 0.045243667 | ... O23: =O21/O$6 -> 0.040197718
B25: 감가상각비 | C25: ='CapEx&Dep'!C7 -> 677.542 | D25: ='CapEx&Dep'!D7 -> 599.583 | E25: ='CapEx&Dep'!E7 -> 554.964 | F25: ='CapEx&Dep'!F7 -> 711.792 | G25: ='CapEx&Dep'!G7 -> 741.121 | H25: ='CapEx&Dep'!H7 -> 712.84854 | I25: ='CapEx&Dep'!I7 -> 64.479145 | J25: ='CapEx&Dep'!J7 -> 775.38114 | ... O25: ='CapEx&Dep'!O7 -> 2179.7868
B26: % of growth | F26: =F25/E25-1 -> 0.2825913 | G26: =G25/F25-1 -> 0.041204453 | H26: n.a. | I26: n.a. | J26: =J25/G25-1 -> 0.046227457 | K26: =K25/J25-1 -> 0.219166 | L26: =L25/K25-1 -> 0.33920139 | M26: =M25/L25-1 -> 0.23446478 | N26: =N25/M25-1 -> 0.16706014 | O26: =O25/N25-1 -> 0.19513814
B27: % of sales | C27: =C25/C$6 -> 0.006694892 | D27: =D25/D$6 -> 0.0049927411 | E27: =E25/E$6 -> 0.003044581 | F27: =F25/F$6 -> 0.0033625315 | G27: =G25/G$6 -> 0.0029431667 | H27: =H25/H$6 -> 0.0033173008 | I27: =I25/I$6 -> #DIV/0! | J27: =J25/J$6 -> 0.0036083015 | ... O27: =O25/O$6 -> 0.0076572536
B29: EBITDA | C29: =C21+C25 -> 6840.7911 | D29: =D21+D25 -> 7122.6655 | E29: =E21+E25 -> 9196.9069 | F29: =F21+F25 -> 9924.7565 | G29: =G21+G25 -> 10205.783 | H29: =H21+H25 -> 10465.743 | I29: =I21+I25 -> 19.864833 | J29: =J21+J25 -> 10497.708 | ... O29: =O21+O25 -> 13622.852
B30: % of growth | D30: =D29/C29-1 -> 0.041204935 | F30: =F29/E29-1 -> 0.079140688 | G30: =G29/F29-1 -> 0.02831576 | H30: n.a. | I30: n.a. | J30: =J29/G29-1 -> 0.028603824 | K30: =K29/J29-1 -> 0.1142076 | L30: =L29/K29-1 -> 0.034387948 | M30: =M29/L29-1 -> 0.046335222 | N30: =N29/M29-1 -> 0.039529367 | O30: =O29/N29-1 -> 0.035181227
B31: % of sales | C31: =C29/C$6 -> 0.067594861 | D31: =D29/D$6 -> 0.059310596 | E31: =E29/E$6 -> 0.050455036 | F31: =F29/F$6 -> 0.046884914 | G31: =G29/G$6 -> 0.040529579 | H31: =H29/H$6 -> 0.048703216 | I31: =I29/I$6 -> #DIV/0! | J31: =J29/J$6 -> 0.048851969 | ... O31: =O29/O$6 -> 0.047854972

Sheet 매출액
B1: ="Project"&" "&Title!L6 -> Project IT | O1: =Des!C12 -> DRAFT - For Discussion Purposes Only
B2: 매출액
B4: 매출액
B5: =unit -> KRW Millions | C5: ='Pro forma'!C$5 -> 2010 | D5: ='Pro forma'!D$5 -> 2011 | E5: ='Pro forma'!E$5 -> 2012 | F5: ='Pro forma'!F$5 -> 2013 | G5: ='Pro forma'!G$5 -> 2014 | H5: ='Pro forma'!H$5 -> 2015/12A | I5: ='Pro forma'!I$5 -> 2015/0E | J5: ='Pro forma'!J$5 -> 2015 | ... O5: ='Pro forma'!O$5 -> 2020
B6: 매출액 | C6: =C9+C13+C17 -> 101202.83 | D6: =D9+D13+D17 -> 120090.95 | E6: =E9+E13+E17 -> 182279.27 | F6: =F9+F13+F17 -> 211683.37 | G6: =G9+G13+G17 -> 251810.75 | H6: =H9+H13+H17 -> 214888.12 | J6: =J9+J13+J17 -> 214888.12 | K6: =K9+K13+K17 -> 247657.65 | L6: =L9+L13+L17 -> 256222.03 | M6: =M9+M13+M17 -> 265319.19 | N6: =N9+N13+N17 -> 274730.7 | O6: =O9+O13+O17 -> 284669.53
B7: % of growth | D7: =D6/C6-1 -> 0.18663626 | E7: =E6/D6-1 -> 0.51784355 | F7: =F6/E6-1 -> 0.16131348 | G7: =G6/F6-1 -> 0.18956321 | J7: =J6/G6-1 -> -0.14662847 | K7: =K6/J6-1 -> 0.15249576 | L7: =L6/K6-1 -> 0.034581504 | M7: =M6/L6-1 -> 0.035505009 | N7: =N6/M6-1 -> 0.035472419 | O7: =O6/N6-1 -> 0.036176613
B9: 상품 | C9: =C71 -> 28667.765 | D9: =D71 -> 33818.96 | E9: =E71 -> 72895.968 | F9: =F71 -> 71774.78 | G9: =G71 -> 69236.769 | H9: =H71 -> 43311.995 | J9: =J71 -> 43311.995 | K9: =K71 -> 52024.746 | L9: =L71 -> 54263.917 | M9: =M71 -> 56179.287 | N9: =N71 -> 58153.964 | O9: =O71 -> 60235.145
B10: % of growth | D10: =D9/C9-1 -> 0.17968598 | E10: =E9/D9-1 -> 1.1554763 | F10: =F9/E9-1 -> -0.015380654 | G10: =G9/F9-1 -> -0.035360773 | J10: =J9/G9-1 -> -0.37443651 | K10: =K9/J9-1 -> 0.20116256 | L10: =L9/K9-1 -> 0.043040493 | M10: =M9/L9-1 -> 0.035297296 | N10: =N9/M9-1 -> 0.035149564 | O10: =O9/N9-1 -> 0.035787434
B11: % of sales | C11: =C9/(C$13+C$17) -> 0.3952263 | D11: =D9/(D$13+D$17) -> 0.39200397 | E11: =E9/(E$13+E$17) -> 0.66642686 | F11: =F9/(F$13+F$17) -> 0.51301197 | G11: =G9/(G$13+G$17) -> 0.37922583 | H11: =H9/(H$13+H$17) -> 0.25243602 | J11: =J9/(J$13+J$17) -> 0.25243602 | K11: =K9/K$6 -> 0.21006719 | L11: =L9/L$6 -> 0.21178475 | M11: =M9/M$6 -> 0.21174227 | N11: =N9/N$6 -> 0.21167625 | O11: =O9/O$6 -> 0.21159674
B13: SI | C13: =C109 -> 32345.633 | D13: =D109 -> 31656.879 | E13: =E109 -> 52687.669 | F13: =F109 -> 60245.229 | G13: =G109 -> 90980.18 | H13: =H109 -> 76214.068 | J13: =J109 -> 76214.068 | K13: =K109 -> 96372.275 | L13: =L109 -> 98768.886 | M13: =M109 -> 102065.25 | N13: =N109 -> 105326.77 | O13: =O109 -> 108650.36
B14: % of growth | D14: =D13/C13-1 -> -0.02129358 | E14: =E13/D13-1 -> 0.66433555 | F14: =F13/E13-1 -> 0.14344077 | G14: =G13/F13-1 -> 0.51016407 | J14: =J13/G13-1 -> -0.16230031 | K14: =K13/J13-1 -> 0.26449456 | L14: =L13/K13-1 -> 0.024868265 | M14: =M13/L13-1 -> 0.033374468 | N14: =N13/M13-1 -> 0.0319553 | O14: =O13/N13-1 -> 0.031554991
B15: % of 매출액 | C15: =C13/C$6 -> 0.31961195 | D15: =D13/D$6 -> 0.26360754 | E15: =E13/E$6 -> 0.28904916 | F15: =F13/F$6 -> 0.28460067 | G15: =G13/G$6 -> 0.3613038 | H15: =H13/H$6 -> 0.35466859 | J15: =J13/J$6 -> 0.35466859 | K15: =K13/K$6 -> 0.38913506 | L15: =L13/L$6 -> 0.38548164 | M15: =M13/M$6 -> 0.38468851 | N15: =N13/N$6 -> 0.38338187 | O15: =O13/O$6 -> 0.38167188
B17: SM | C17: =C170 -> 40189.43 | D17: =D170 -> 54615.106 | E17: =E170 -> 56695.63 | F17: =F170 -> 79663.359 | G17: =G170 -> 91593.798 | H17: =H170 -> 95362.06 | J17: =J170 -> 95362.06 | K17: =K170 -> 99260.63 | L17: =L170 -> 103189.22 | M17: =M170 -> 107074.66 | N17: =N170 -> 111249.97 | O17: =O170 -> 115784.03
B18: % of growth | D18: =D17/C17-1 -> 0.35894204 | E18: =E17/D17-1 -> 0.038094289 | F18: =F17/E17-1 -> 0.40510582 | G18: =G17/F17-1 -> 0.14976068 | J18: =J17/G17-1 -> 0.041141019 | K18: =K17/J17-1 -> 0.040881765 | L18: =L17/K17-1 -> 0.039578552 | M18: =M17/L17-1 -> 0.037653513 | N18: =N17/M17-1 -> 0.038994386 | O18: =O17/N17-1 -> 0.040755606
B19: % of 매출액 | C19: =C17/C$6 -> 0.39711766 | D19: =D17/D$6 -> 0.45478122 | E19: =E17/E$6 -> 0.31103718 | F19: =F17/F$6 -> 0.37633263 | G19: =G17/G$6 -> 0.36374062 | H19: =H17/H$6 -> 0.44377539 | J19: =J17/J$6 -> 0.44377539 | K19: =K17/K$6 -> 0.40079775 | L19: =L17/L$6 -> 0.40273361 | M19: =M17/M$6 -> 0.40356922 | N19: =N17/N$6 -> 0.40494188 | O19: =O17/O$6 -> 0.40673137
B23: change of % | C23: =C$5 -> 2010 | D23: =D$5 -> 2011 | E23: =E$5 -> 2012 | F23: =F$5 -> 2013 | G23: =G$5 -> 2014 | H23: =H$5 -> 2015/12A | I23: =I$5 -> 2015/0E | J23: =J$5 -> 2015 | ... O23: =O$5 -> 2020
B24: Nominal GDP Growth | C24: =Macro!H27/Macro!G27-1 -> 0.098636217 | D24: =Macro!I27/Macro!H27-1 -> 0.053246407 | E24: =Macro!J27/Macro!I27-1 -> 0.033598138 | F24: =Macro!K27/Macro!J27-1 -> 0.037742605 | G24: =Macro!L27/Macro!K27-1 -> 0.03891901 | J24: =Macro!M27/Macro!L27-1 -> 0.023003842 | K24: =Macro!N27/Macro!M27-1 -> 0.037334115 | L24: =Macro!O27/Macro!N27-1 -> 0.028565319 | M24: =Macro!P27/Macro!O27-1 -> 0.039323857 | N24: =Macro!Q27/Macro!P27-1 -> 0.040235567 | O24: =Macro!R27/Macro!Q27-1 -> 0.037923737
B25: Real GDP Growth | C25: =Macro!H7/Macro!G7-1 -> 0.064967852 | D25: =Macro!I7/Macro!H7-1 -> 0.036816889 | E25: =Macro!J7/Macro!I7-1 -> 0.022924056 | F25: =Macro!K7/Macro!J7-1 -> 0.028962124 | G25: =Macro!L7/Macro!K7-1 -> 0.033101476 | J25: =Macro!M7/Macro!L7-1 -> 0.025270579 | K25: =Macro!N7/Macro!M7-1 -> 0.028600364 | L25: =Macro!O7/Macro!N7-1 -> 0.027601128 | M25: =Macro!P7/Macro!O7-1 -> 0.030071592 | N25: =Macro!Q7/Macro!P7-1 -> 0.029194884 | O25: =Macro!R7/Macro!Q7-1 -> 0.030382129
B26: Consumer prices (%) | C26: =Macro!H87/100 -> 0.02938 | D26: =Macro!I87/100 -> 0.04025 | E26: =Macro!J87/100 -> 0.02183 | F26: =Macro!K87/100 -> 0.01301 | G26: =Macro!L87/100 -> 0.01275 | J26: =Macro!M87/100 -> 0.006 | K26: =Macro!N87/100 -> 0.013 | L26: =Macro!O87/100 -> 0.015 | M26: =Macro!P87/100 -> 0.018 | N26: =Macro!Q87/100 -> 0.02 | O26: =Macro!R87/100 -> 0.022
B27: Growth in average wages | C27: =Macro!H90/100 -> 0.06844 | D27: =Macro!I90/100 -> 0.00923 | E27: =Macro!J90/100 -> 0.05371 | F27: =Macro!K90/100 -> 0.03856 | G27: =Macro!L90/100 -> 0.02554 | J27: =Macro!M90/100 -> 0.042 | K27: =Macro!N90/100 -> 0.043 | L27: =Macro!O90/100 -> 0.042 | M27: =Macro!P90/100 -> 0.04 | N27: =Macro!Q90/100 -> 0.042 | O27: =Macro!R90/100 -> 0.044
B28: Growth in real wages | C28: =Macro!H91/100 -> 0.03794 | D28: =Macro!I91/100 -> -0.02982 | E28: =Macro!J91/100 -> 0.0312 | F28: =Macro!K91/100 -> 0.02521 | G28: =Macro!L91/100 -> 0.01263 | J28: =Macro!M91/100 -> 0.035 | K28: =Macro!N91/100 -> 0.03 | L28: =Macro!O91/100 -> 0.027 | M28: =Macro!P91/100 -> 0.022 | N28: =Macro!Q91/100 -> 0.022 | O28: =Macro!R91/100 -> 0.022
B29: 국내 SI 성장률 | G29: 0.036997886 | J29: 0.046551138 | K29: 0.051948052 | L29: 0.018518519 | M29: 0.022727273 | N29: 0.022727273 | O29: 0.022727273 | Q29: source: IDC(2014), http://www.etnews.com/20141023000161
B30: 국내 IT서비스 성장률 | J30: 0.026 | K30: 0.02912779 | L30: 0.025960943 | M30: 0.024251171 | N30: 0.021563373 | O30: 0.021563373 | Q30: source: 한국 IDC, Korea IT Services 2014 Review and 2015-2019 Forecast
B31: 상품/SI+SM매출 | C31: =C71/(C109+C170) -> 0.3952263 | D31: =D71/(D109+D170) -> 0.39200397 | E31: =E71/(E109+E170) -> 0.66642686 | F31: =F71/(F109+F170) -> 0.51301197 | G31: =G71/(G109+G170) -> 0.37922583 | H31: =H71/(H109+H170) -> 0.25243602 | J31: =J71/(J109+J170) -> 0.25243602 | K31: =K71/(K109+K170) -> 0.26593045 | L31: =K31 -> 0.26593045 | M31: =L31 -> 0.26593045 | N31: =M31 -> 0.26593045 | O31: =N31 -> 0.26593045
B32: 대내상품/SI+SM매출 | F32: =F75/(F113+F174) -> 0.30276709 | G32: =G75/(G113+G174) -> 0.22708067 | H32: =H75/(H113+H174) -> 0.22312067
B33: 대외상품/SI+SM매출 | F33: =F96/(F133+F194) -> 1.0435365 | G33: =G96/(G133+G194) -> 0.5733462 | H33: =H96/(H133+H194) -> 0.29244934
B36: 대내외 매출구분
B37: =Des!$C$13 -> KRW Millions | C37: ='Pro forma'!C$5 -> 2010 | D37: ='Pro forma'!D$5 -> 2011 | E37: ='Pro forma'!E$5 -> 2012 | F37: ='Pro forma'!F$5 -> 2013 | G37: ='Pro forma'!G$5 -> 2014 | H37: ='Pro forma'!H$5 -> 2015/12A | I37: ='Pro forma'!I$5 -> 2015/0E | J37: ='Pro forma'!J$5 -> 2015 | ... O37: ='Pro forma'!O$5 -> 2020
B38: 대내 | F38: =F41+F44+F47 -> 130536.98 | G38: =G41+G44+G47 -> 125595.43 | H38: =H41+H44+H47 -> 121120.58 | J38: =J41+J44+J47 -> 121120.58 | K38: =K41+K44+K47 -> 132545.53 | L38: =L41+L44+L47 -> 138547.69 | M38: =M41+M44+M47 -> 143887.43 | N38: =N41+N44+N47 -> 149668.3 | O38: =O41+O44+O47 -> 155927.35
B39: % of growth | D39: =D38/C38-1 -> #DIV/0! | E39: =E38/D38-1 -> #DIV/0! | F39: =F38/E38-1 -> #DIV/0! | G39: =G38/F38-1 -> -0.037855574 | J39: =J38/G38-1 -> -0.035629076 | K39: =K38/J38-1 -> 0.094327033 | L39: =L38/K38-1 -> 0.045283783 | M39: =M38/L38-1 -> 0.038540809 | N39: =N38/M38-1 -> 0.040176337 | O39: =O38/N38-1 -> 0.041819445
B40: % of sales | D40: =D38/D$6 -> 0 | E40: =E38/E$6 -> 0 | F40: =F38/F$6 -> 0.6166615 | G40: =G38/G$6 -> 0.49876915 | H40: =H38/H$6 -> 0.56364484 | J40: =J38/J$6 -> 0.56364484 | K40: =K38/K$6 -> 0.53519658 | L40: =L38/L$6 -> 0.54073295 | M40: =M38/M$6 -> 0.54231822 | N40: =N38/N$6 -> 0.54478185 | O40: =O38/O$6 -> 0.54774863
B41: 상품 | F41: =F75 -> 30337.198 | G41: =G75 -> 23242.396 | H41: =H75 -> 22094.718 | J41: =J75 -> 22094.718 | K41: =K75 -> 25977.718 | L41: =L75 -> 27637.124 | M41: =M75 -> 28702.281 | N41: =N75 -> 29855.433 | O41: =O75 -> 31103.971
B42: % of growth | D42: =D41/C41-1 -> #DIV/0! | E42: =E41/D41-1 -> #DIV/0! | F42: =F41/E41-1 -> #DIV/0! | G42: =G41/F41-1 -> -0.23386478 | J42: =J41/G41-1 -> -0.049378647 | K42: =K41/J41-1 -> 0.17574337 | L42: =L41/K41-1 -> 0.06387804 | M42: =M41/L41-1 -> 0.038540809 | N42: =N41/M41-1 -> 0.040176337 | O42: =O41/N41-1 -> 0.041819445
B43: % of 대내매출 | D43: =D41/D$38 -> #DIV/0! | E43: =E41/E$38 -> #DIV/0! | F43: =F41/F$38 -> 0.23240309 | G43: =G41/G$38 -> 0.18505765 | H43: =H41/H$38 -> 0.18241918 | J43: =J41/J$38 -> 0.18241918 | K43: =K41/K$38 -> 0.19599091 | L43: =L41/L$38 -> 0.19947733 | M43: =M41/M$38 -> 0.19947733 | N43: =N41/N$38 -> 0.19947733 | O43: =O41/O$38 -> 0.19947733
B44: SI | F44: =F113 -> 32703.735 | G44: =G113 -> 26138.877 | H44: =H113 -> 18225.235 | J44: =J113 -> 18225.235 | K44: =K113 -> 22292.753 | L44: =L113 -> 23095.958 | M44: =M113 -> 23857.957 | N44: =N113 -> 24649.932 | O44: =O113 -> 25473.271
B45: % of growth | D45: =D44/C44-1 -> #DIV/0! | E45: =E44/D44-1 -> #DIV/0! | F45: =F44/E44-1 -> #DIV/0! | G45: =G44/F44-1 -> -0.20073727 | J45: =J44/G44-1 -> -0.30275368 | K45: =K44/J44-1 -> 0.22318054 | L45: =L44/K44-1 -> 0.036029862 | M45: =M44/L44-1 -> 0.032992725 | N45: =N44/M44-1 -> 0.033195437 | O45: =O44/N44-1 -> 0.033401249
B46: % of 대내매출 | D46: =D44/D$38 -> #DIV/0! | E46: =E44/E$38 -> #DIV/0! | F46: =F44/F$38 -> 0.25053233 | G46: =G44/G$38 -> 0.20811964 | H46: =H44/H$38 -> 0.15047183 | J46: =J44/J$38 -> 0.15047183 | K46: =K44/K$38 -> 0.1681894 | L46: =L44/L$38 -> 0.16670042 | M46: =M44/M$38 -> 0.16580987 | N46: =N44/N$38 -> 0.16469708 | O46: =O44/O$38 -> 0.16336628
B47: SM | F47: =F174 -> 67496.051 | G47: =G174 -> 76214.159 | H47: =H174 -> 80800.629 | J47: =J174 -> 80800.629 | K47: =K174 -> 84275.056 | L47: =L174 -> 87814.609 | M47: =M174 -> 91327.193 | N47: =N174 -> 95162.935 | O47: =O174 -> 99350.104
B48: % of growth | D48: =D47/C47-1 -> #DIV/0! | E48: =E47/D47-1 -> #DIV/0! | F48: =F47/E47-1 -> #DIV/0! | G48: =G47/F47-1 -> 0.12916471 | J48: =J47/G47-1 -> 0.060178712 | K48: =K47/J47-1 -> 0.043 | L48: =L47/K47-1 -> 0.042 | M48: =M47/L47-1 -> 0.04 | N48: =N47/M47-1 -> 0.042 | O48: =O47/N47-1 -> 0.044
B49: % of 대내매출 | D49: =D47/D$6 -> 0 | E49: =E47/E$6 -> 0 | F49: =F47/F$6 -> 0.31885382 | G49: =G47/G$6 -> 0.30266444 | H49: =H47/H$6 -> 0.37601254 | J49: =J47/J$6 -> 0.37601254 | K49: =K47/K$6 -> 0.34028852 | L49: =L47/L$6 -> 0.34272857 | M49: =M47/M$6 -> 0.34421631 | N49: =N47/N$6 -> 0.34638624 | O49: =O47/O$6 -> 0.34900154
B50: 대외 | F50: =F53+F56+F59 -> 81146.384 | G50: =G53+G56+G59 -> 126215.32 | H50: =H53+H56+H59 -> 93767.541 | J50: =J53+J56+J59 -> 93767.541 | K50: =K53+K56+K59 -> 115112.12 | L50: =L53+L56+L59 -> 117674.33 | M50: =M53+M56+M59 -> 121431.76 | N50: =N53+N56+N59 -> 125062.4 | O50: =O53+O56+O59 -> 128742.18
B51: % of growth | D51: =D50/C50-1 -> #DIV/0! | E51: =E50/D50-1 -> #DIV/0! | F51: =F50/E50-1 -> #DIV/0! | G51: =G50/F50-1 -> 0.55540282 | J51: =J50/G50-1 -> -0.2570827 | K51: =K50/J50-1 -> 0.22763295 | L51: =L50/K50-1 -> 0.022258395 | M51: =M50/L50-1 -> 0.031930712 | N51: =N50/M50-1 -> 0.029898632 | O51: =O50/N50-1 -> 0.029423559
B52: % of sales | D52: =D50/D$6 -> 0 | E52: =E50/E$6 -> 0 | F52: =F50/F$6 -> 0.3833385 | G52: =G50/G$6 -> 0.50123085 | H52: =H50/H$6 -> 0.43635516 | J52: =J50/J$6 -> 0.43635516 | K52: =K50/K$6 -> 0.46480342 | L52: =L50/L$6 -> 0.45926705 | M52: =M50/M$6 -> 0.45768178 | N52: =N50/N$6 -> 0.45521815 | O52: =O50/O$6 -> 0.45225137
B53: 상품 | F53: =F96 -> 41437.582 | G53: =G96 -> 45994.373 | H53: =H96 -> 21217.277 | J53: =J96 -> 21217.277 | K53: =K96 -> 26047.028 | L53: =L96 -> 26626.793 | M53: =M96 -> 27477.006 | N53: =N96 -> 28298.531 | O53: =O96 -> 29131.174
B54: % of growth | D54: =D53/C53-1 -> #DIV/0! | E54: =E53/D53-1 -> #DIV/0! | F54: =F53/E53-1 -> #DIV/0! | G54: =G53/F53-1 -> 0.10996757 | J54: =J53/G53-1 -> -0.53869842 | K54: =K53/J53-1 -> 0.22763295 | L54: =L53/K53-1 -> 0.022258395 | M54: =M53/L53-1 -> 0.031930712 | N54: =N53/M53-1 -> 0.029898632 | O54: =O53/N53-1 -> 0.029423559
B55: % of 대외매출 | D55: =D53/D$50 -> #DIV/0! | E55: =E53/E$50 -> #DIV/0! | F55: =F53/F$50 -> 0.51065223 | G55: =G53/G$50 -> 0.36441198 | H55: =H53/H$50 -> 0.22627528 | J55: =J53/J$50 -> 0.22627528 | K55: =K53/K$50 -> 0.22627528 | L55: =L53/L$50 -> 0.22627528 | M55: =M53/M$50 -> 0.22627528 | N55: =N53/N$50 -> 0.22627528 | O55: =O53/O$50 -> 0.22627528
B56: SI(공사포함) | F56: =F133 -> 27541.494 | G56: =G133 -> 64841.304 | H56: =H133 -> 57988.833 | J56: =J133 -> 57988.833 | K56: =K133 -> 74079.522 | L56: =L133 -> 75672.928 | M56: =M133 -> 78207.288 | N56: =N133 -> 80676.839 | O56: =O133 -> 83177.085
B57: % of growth | D57: =D56/C56-1 -> #DIV/0! | E57: =E56/D56-1 -> #DIV/0! | F57: =F56/E56-1 -> #DIV/0! | G57: =G56/F56-1 -> 1.3543132 | J57: =J56/G56-1 -> -0.10568065 | K57: =K56/J56-1 -> 0.27747909 | L57: =L56/K56-1 -> 0.021509405 | M57: =M56/L56-1 -> 0.033490979 | N57: =N56/M56-1 -> 0.031576982 | O57: =O56/N56-1 -> 0.030990887
B58: % of 대외매출 | D58: =D56/D$50 -> #DIV/0! | E58: =E56/E$50 -> #DIV/0! | F58: =F56/F$50 -> 0.33940507 | G58: =G56/G$50 -> 0.51373562 | H58: =H56/H$50 -> 0.61843184 | J58: =J56/J$50 -> 0.61843184 | K58: =K56/K$50 -> 0.64354231 | L58: =L56/L$50 -> 0.6430708 | M58: =M56/M$50 -> 0.64404311 | N58: =N56/N$50 -> 0.64509266 | O58: =O56/O$50 -> 0.64607483
B59: SM | F59: =F194 -> 12167.308 | G59: =G194 -> 15379.639 | H59: =H194 -> 14561.431 | J59: =J194 -> 14561.431 | K59: =K194 -> 14985.573 | L59: =L194 -> 15374.613 | M59: =M194 -> 15747.465 | N59: =N194 -> 16087.034 | O59: =O194 -> 16433.925
B60: % of growth | D60: =D59/C59-1 -> #DIV/0! | E60: =E59/D59-1 -> #DIV/0! | F60: =F59/E59-1 -> #DIV/0! | G60: =G59/F59-1 -> 0.26401328 | J60: =J59/G59-1 -> -0.053200714 | K60: =K59/J59-1 -> 0.02912779 | L60: =L59/K59-1 -> 0.025960943 | M60: =M59/L59-1 -> 0.024251171 | N60: =N59/M59-1 -> 0.021563373 | O60: =O59/N59-1 -> 0.021563373
B61: % of 대외매출 | D61: =D59/D$50 -> #DIV/0! | E61: =E59/E$50 -> #DIV/0! | F61: =F59/F$50 -> 0.1499427 | G61: =G59/G$50 -> 0.1218524 | H61: =H59/H$50 -> 0.15529288 | J61: =J59/J$50 -> 0.15529288 | K61: =K59/K$50 -> 0.13018241 | L61: =L59/L$50 -> 0.13065392 | M61: =M59/M$50 -> 0.1296816 | N61: =N59/N$50 -> 0.12863205 | O61: =O59/O$50 -> 0.12764988
B64: 1. 상품매출 추정
B66: Step1. 대내 매출은 지속가능한 상품매출 확정. ->FY 2015&2016 계획 동시검토
B67: Step2. 대외 매출은 총액 기준으로 SM+SI 기준 검토
B69: 상품매출
B70: =Des!$C$13 -> KRW Millions | C70: ='Pro forma'!C$5 -> 2010 | D70: ='Pro forma'!D$5 -> 2011 | E70: ='Pro forma'!E$5 -> 2012 | F70: ='Pro forma'!F$5 -> 2013 | G70: ='Pro forma'!G$5 -> 2014 | H70: ='Pro forma'!H$5 -> 2015/12A | I70: ='Pro forma'!I$5 -> 2015/0E | J70: ='Pro forma'!J$5 -> 2015 | ... O70: ='Pro forma'!O$5 -> 2020
B71: 상품매출 | C71: =IS!J8 -> 28667.765 | D71: =IS!K8 -> 33818.96 | E71: =IS!L8 -> 72895.968 | F71: =IS!M8 -> 71774.78 | G71: =IS!N8 -> 69236.769 | H71: =H75+H96 -> 43311.995 | J71: =J75+J96 -> 43311.995 | K71: =K75+K96 -> 52024.746 | L71: =L75+L96 -> 54263.917 | M71: =M75+M96 -> 56179.287 | N71: =N75+N96 -> 58153.964 | O71: =O75+O96 -> 60235.145
B72: % of growth | D72: =D71/C71-1 -> 0.17968598 | E72: =E71/D71-1 -> 1.1554763 | F72: =F71/E71-1 -> -0.015380654 | G72: =G71/F71-1 -> -0.035360773 | J72: =J71/G71-1 -> -0.37443651 | K72: =K71/J71-1 -> 0.20116256 | L72: =L71/K71-1 -> 0.043040493 | M72: =M71/L71-1 -> 0.035297296 | N72: =N71/M71-1 -> 0.035149564 | O72: =O71/N71-1 -> 0.035787434
B73: % of sales | D73: =D71/D$6 -> 0.28161124 | E73: =E71/E$6 -> 0.39991366 | F73: =F71/F$6 -> 0.3390667 | G73: =G71/G$6 -> 0.27495557 | H73: =H71/H$6 -> 0.20155602 | J73: =J71/J$6 -> 0.20155602 | K73: =K71/K$6 -> 0.21006719 | L73: =L71/L$6 -> 0.21178475 | M73: =M71/M$6 -> 0.21174227 | N73: =N71/N$6 -> 0.21167625 | O73: =O71/O$6 -> 0.21159674
B75: 그룹내 | D75: =SUM(D80,D83,D86,D89,D92) -> 0 | E75: =SUM(E80,E83,E86,E89,E92) -> 0 | F75: =SUM(F80,F83,F86,F89,F92) -> 30337.198 | G75: =SUM(G80,G83,G86,G89,G92) -> 23242.396 | H75: =SUM(H80,H83,H86,H89,H92) -> 22094.718 | J75: =SUM(J80,J83,J86,J89,J92) -> 22094.718 | K75: =SUM(K80,K83,K86,K89,K92) -> 25977.718 | L75: =(L113+L174)*L78 -> 27637.124 | M75: =(M113+M174)*M78 -> 28702.281 | N75: =(N113+N174)*N78 -> 29855.433 | O75: =(O113+O174)*O78 -> 31103.971
B76: % of growth | E76: =E75/D75-1 -> #DIV/0! | F76: =F75/E75-1 -> #DIV/0! | G76: =G75/F75-1 -> -0.23386478 | J76: =J75/G75-1 -> -0.049378647 | K76: =K75/J75-1 -> 0.17574337 | L76: =L75/K75-1 -> 0.06387804 | M76: =M75/L75-1 -> 0.038540809 | N76: =N75/M75-1 -> 0.040176337 | O76: =O75/N75-1 -> 0.041819445
B77: % of 상품매출 | D77: =D75/D$71 -> 0 | E77: =E75/E$71 -> 0 | F77: =F75/F$71 -> 0.42267211 | G77: =G75/G$71 -> 0.3356944 | H77: =H75/H$71 -> 0.5101293 | J77: =J75/J$71 -> 0.5101293 | K77: =K75/K$71 -> 0.49933387 | L77: =K77 -> 0.49933387 | M77: =L77 -> 0.49933387 | N77: =M77 -> 0.49933387 | O77: =N77 -> 0.49933387
B78: % of 대내매출 | D78: =D75/(D113+D174) -> #DIV/0! | E78: =E75/(E113+E174) -> #DIV/0! | F78: =F75/(F113+F174) -> 0.30276709 | G78: =G75/(G113+G174) -> 0.22708067 | H78: =H75/(H113+H174) -> 0.22312067 | J78: =J75/(J113+J174) -> 0.22312067 | K78: =K75/(K113+K174) -> 0.24376703 | L78: =AVERAGE(F78:H78,K78) -> 0.24918386 | M78: =L78 -> 0.24918386 | N78: =M78 -> 0.24918386 | O78: =N78 -> 0.24918386
B80: GS Caltex | F80: 3655.8841 | G80: 2880.6398 | H80: 1321.9662 | J80: =H80+I80 -> 1321.9662 | K80: =사업계획!N30/10^3 -> 188.639 | L80: =L$75*$K82 -> 200.68889 | M80: =M$75*$K82 -> 208.4236 | N80: =N$75*$K82 -> 216.7973 | O80: =O$75*$K82 -> 225.86364
B81: % of growth | D81: =D80/C80-1 -> #DIV/0! | E81: =E80/D80-1 -> #DIV/0! | F81: =F80/E80-1 -> #DIV/0! | G81: =G80/F80-1 -> -0.21205385 | J81: =J80/G80-1 -> -0.54108589 | K81: =K80/J80-1 -> -0.85730422 | L81: =L80/K80-1 -> 0.06387804 | M81: =M80/L80-1 -> 0.038540809 | N81: =N80/M80-1 -> 0.040176337 | O81: =O80/N80-1 -> 0.041819445
B82: % of 대내상품매출 | D82: =D80/D$75 -> #DIV/0! | E82: =E80/E$75 -> #DIV/0! | F82: =F80/F$75 -> 0.1205083 | G82: =G80/G$75 -> 0.12393902 | H82: =H80/H$75 -> 0.059831778 | J82: =J80/J$75 -> 0.059831778 | K82: =K80/K$75 -> 0.0072615693 | L82: =L80/L$75 -> 0.0072615693 | M82: =M80/M$75 -> 0.0072615693 | N82: =N80/N$75 -> 0.0072615693 | O82: =O80/O$75 -> 0.0072615693
B83: GS HS | F83: 406.56273 | G83: 37.425 | H83: 303.009 | J83: =H83+I83 -> 303.009 | K83: =사업계획!N31/10^3 -> 3000 | L83: =L$75*$K85 -> 3191.6341 | M83: =M$75*$K85 -> 3314.6423 | N83: =N$75*$K85 -> 3447.8125 | O83: =O$75*$K85 -> 3591.9981
B84: % of growth | D84: =D83/C83-1 -> #DIV/0! | E84: =E83/D83-1 -> #DIV/0! | F84: =F83/E83-1 -> #DIV/0! | G84: =G83/F83-1 -> -0.90794778 | J84: =J83/G83-1 -> 7.0964329 | K84: =K83/J83-1 -> 8.900696 | L84: =L83/K83-1 -> 0.06387804 | M84: =M83/L83-1 -> 0.038540809 | N84: =N83/M83-1 -> 0.040176337 | O84: =O83/N83-1 -> 0.041819445
B85: % of 대내상품매출 | D85: =D83/D$75 -> #DIV/0! | E85: =E83/E$75 -> #DIV/0! | F85: =F83/F$75 -> 0.013401459 | G85: =G83/G$75 -> 0.0016102041 | H85: =H83/H$75 -> 0.013714092 | J85: =J83/J$75 -> 0.013714092 | K85: =K83/K$75 -> 0.11548358 | L85: =L83/L$75 -> 0.11548358 | M85: =M83/M$75 -> 0.11548358 | N85: =N83/N$75 -> 0.11548358 | O85: =O83/O$75 -> 0.11548358
B86: GS R | F86: 22462.903 | G86: 17203.564 | H86: 17062.686 | J86: =H86+I86 -> 17062.686 | K86: =사업계획!N32/10^3 -> 21906 | L86: =L$75*$K88 -> 23305.312 | M86: =M$75*$K88 -> 24203.518 | N86: =N$75*$K88 -> 25175.927 | O86: =O$75*$K88 -> 26228.77
B87: % of growth | D87: =D86/C86-1 -> #DIV/0! | E87: =E86/D86-1 -> #DIV/0! | F87: =F86/E86-1 -> #DIV/0! | G87: =G86/F86-1 -> -0.23413442 | J87: =J86/G86-1 -> -0.0081888986 | K87: =K86/J86-1 -> 0.28385414 | L87: =L86/K86-1 -> 0.06387804 | M87: =M86/L86-1 -> 0.038540809 | N87: =N86/M86-1 -> 0.040176337 | O87: =O86/N86-1 -> 0.041819445
B88: % of 대내상품매출 | D88: =D86/D$75 -> #DIV/0! | E88: =E86/E$75 -> #DIV/0! | F88: =F86/F$75 -> 0.74044093 | G88: =G86/G$75 -> 0.74018033 | H88: =H86/H$75 -> 0.77225182 | J88: =J86/J$75 -> 0.77225182 | K88: =K86/K$75 -> 0.84326114 | L88: =L86/L$75 -> 0.84326114 | M88: =M86/M$75 -> 0.84326114 | N88: =N86/N$75 -> 0.84326114 | O88: =O86/O$75 -> 0.84326114
B89: GS E&C | F89: 3059.8395 | G89: 1388.1278 | H89: 922.0215 | J89: =H89+I89 -> 922.0215 | K89: =사업계획!N33/10^3 -> 719.4 | L89: =L$75*$K91 -> 765.35386 | M89: =M$75*$K91 -> 794.85122 | N89: =N$75*$K91 -> 826.78543 | O89: =O$75*$K91 -> 861.36114
B90: % of growth | D90: =D89/C89-1 -> #DIV/0! | E90: =E89/D89-1 -> #DIV/0! | F90: =F89/E89-1 -> #DIV/0! | G90: =G89/F89-1 -> -0.54633968 | J90: =J89/G89-1 -> -0.33578052 | K90: =K89/J89-1 -> -0.21975789 | L90: =L89/K89-1 -> 0.06387804 | M90: =M89/L89-1 -> 0.038540809 | N90: =N89/M89-1 -> 0.040176337 | O90: =O89/N89-1 -> 0.041819445
B91: % of 대내상품매출 | D91: =D89/D$75 -> #DIV/0! | E91: =E89/E$75 -> #DIV/0! | F91: =F89/F$75 -> 0.10086098 | G91: =G89/G$75 -> 0.059723953 | H91: =H89/H$75 -> 0.041730404 | J91: =J89/J$75 -> 0.041730404 | K91: =K89/K$75 -> 0.027692964 | L91: =L89/L$75 -> 0.027692964 | M91: =M89/M$75 -> 0.027692964 | N91: =N89/N$75 -> 0.027692964 | O91: =O89/O$75 -> 0.027692964
B92: GS 기타 | F92: 752.00849 | G92: 1732.639 | H92: 2485.035 | J92: =H92+I92 -> 2485.035 | K92: =사업계획!N34/10^3 -> 163.679 | L92: =L$75*$K94 -> 174.13449 | M92: =M$75*$K94 -> 180.84578 | N92: =N$75*$K94 -> 188.1115 | O92: =O$75*$K94 -> 195.97822
B93: % of growth | D93: =D92/C92-1 -> #DIV/0! | E93: =E92/D92-1 -> #DIV/0! | F93: =F92/E92-1 -> #DIV/0! | G93: =G92/F92-1 -> 1.3040152 | J93: =J92/G92-1 -> 0.43424857 | K93: =K92/J92-1 -> -0.93413413 | L93: =L92/K92-1 -> 0.06387804 | M93: =M92/L92-1 -> 0.038540809 | N93: =N92/M92-1 -> 0.040176337 | O93: =O92/N92-1 -> 0.041819445
B94: % of 대내상품매출 | D94: =D92/D$75 -> #DIV/0! | E94: =E92/E$75 -> #DIV/0! | F94: =F92/F$75 -> 0.024788331 | G94: =G92/G$75 -> 0.074546489 | H94: =H92/H$75 -> 0.11247191 | J94: =J92/J$75 -> 0.11247191 | K94: =K92/K$75 -> 0.0063007459 | L94: =L92/L$75 -> 0.0063007459 | M94: =M92/M$75 -> 0.0063007459 | N94: =N92/N$75 -> 0.0063007459 | O94: =O92/O$75 -> 0.0063007459
B96: 대외 | F96: 41437.582 | G96: 45994.373 | H96: 21217.277 | J96: =H96+I96 -> 21217.277 | K96: =(K133+K194)*K99 -> 26047.028 | L96: =(L133+L194)*L99 -> 26626.793 | M96: =(M133+M194)*M99 -> 27477.006 | N96: =(N133+N194)*N99 -> 28298.531 | O96: =(O133+O194)*O99 -> 29131.174
B97: % of growth | E97: =E96/D96-1 -> #DIV/0! | F97: =F96/E96-1 -> #DIV/0! | G97: =G96/F96-1 -> 0.10996757 | J97: =J96/G96-1 -> -0.53869842 | K97: =K96/J96-1 -> 0.22763295 | L97: =L96/K96-1 -> 0.022258395 | M97: =M96/L96-1 -> 0.031930712 | N97: =N96/M96-1 -> 0.029898632 | O97: =O96/N96-1 -> 0.029423559
B98: % of 상품매출 | D98: =D96/D$71 -> 0 | E98: =E96/E$71 -> 0 | F98: =F96/F$71 -> 0.57732789 | G98: =G96/G$71 -> 0.6643056 | H98: =H96/H$71 -> 0.4898707 | J98: =J96/J$71 -> 0.4898707 | K98: =K96/K$71 -> 0.50066613 | L98: =L96/L$71 -> 0.49069059 | M98: =M96/M$71 -> 0.48909496 | N98: =N96/N$71 -> 0.48661396 | O98: =O96/O$71 -> 0.48362421
B99: % of 대외매출 | D99: =D96/(D133+D194) -> #DIV/0! | E99: =E96/(E133+E194) -> #DIV/0! | F99: =F96/(F133+F194) -> 1.0435365 | G99: =G96/(G133+G194) -> 0.5733462 | H99: =H96/(H133+H194) -> 0.29244934 | J99: =J96/(J133+J194) -> 0.29244934 | K99: =J99 -> 0.29244934 | L99: =K99 -> 0.29244934 | M99: =L99 -> 0.29244934 | N99: =M99 -> 0.29244934 | O99: =N99 -> 0.29244934
B102: 2. SI 매출
B104: Step1. 대내 각 부분별 매출추정: 회사 계획을 근거로 각 부분별 매출 추정-> 거래처별 비교 검토
B105: Step2. 대외 각 부분별 매출추정: 회사 계획을 근거로 각 부분별 매출 추정-> 거래처별 비교 검토
B107: SI- 거래처별
B108: =Des!$C$13 -> KRW Millions | C108: ='Pro forma'!C$5 -> 2010 | D108: ='Pro forma'!D$5 -> 2011 | E108: ='Pro forma'!E$5 -> 2012 | F108: ='Pro forma'!F$5 -> 2013 | G108: ='Pro forma'!G$5 -> 2014 | H108: ='Pro forma'!H$5 -> 2015/12A | I108: ='Pro forma'!I$5 -> 2015/0E | J108: ='Pro forma'!J$5 -> 2015 | ... O108: ='Pro forma'!O$5 -> 2020
B109: 매출(SI)- 거래처별 | C109: =IS!J9 -> 32345.633 | D109: =IS!K9 -> 31656.879 | E109: =IS!L9 -> 52687.669 | F109: =IS!M9 -> 60245.229 | G109: =IS!N9 -> 90980.18 | H109: =H113+H133 -> 76214.068 | J109: =J113+J133 -> 76214.068 | K109: =K113+K133 -> 96372.275 | L109: =L113+L133 -> 98768.886 | M109: =M113+M133 -> 102065.25 | N109: =N113+N133 -> 105326.77 | O109: =O113+O133 -> 108650.36
B110: % of growth | D110: =D109/C109-1 -> -0.02129358 | E110: =E109/D109-1 -> 0.66433555 | F110: =F109/E109-1 -> 0.14344077 | G110: =G109/F109-1 -> 0.51016407 | J110: =J109/G109-1 -> -0.16230031 | K110: =K109/J109-1 -> 0.26449456 | L110: =L109/K109-1 -> 0.024868265 | M110: =M109/L109-1 -> 0.033374468 | N110: =N109/M109-1 -> 0.0319553 | O110: =O109/N109-1 -> 0.031554991
B111: % of sales | D111: =D109/D$6 -> 0.26360754 | E111: =E109/E$6 -> 0.28904916 | F111: =F109/F$6 -> 0.28460067 | G111: =G109/G$6 -> 0.3613038 | H111: =H109/H$6 -> 0.35466859 | J111: =J109/J$6 -> 0.35466859 | K111: =K109/K$6 -> 0.38913506 | L111: =L109/L$6 -> 0.38548164 | M111: =M109/M$6 -> 0.38468851 | N111: =N109/N$6 -> 0.38338187 | O111: =O109/O$6 -> 0.38167188
B113: 그룹내 | D113: =SUM(D117,D120,D123,D126,D129) -> 0 | E113: =SUM(E117,E120,E123,E126,E129) -> 0 | F113: =SUM(F117,F120,F123,F126,F129) -> 32703.735 | G113: =SUM(G117,G120,G123,G126,G129) -> 26138.877 | H113: =SUM(H117,H120,H123,H126,H129) -> 18225.235 | J113: =SUM(J117,J120,J123,J126,J129) -> 18225.235 | K113: =SUM(K117,K120,K123,K126,K129) -> 22292.753 | L113: =SUM(L117,L120,L123,L126,L129) -> 23095.958 | M113: =SUM(M117,M120,M123,M126,M129) -> 23857.957 | N113: =SUM(N117,N120,N123,N126,N129) -> 24649.932 | O113: =SUM(O117,O120,O123,O126,O129) -> 25473.271
B114: % of growth | D114: =D113/C113-1 -> #DIV/0! | E114: =E113/D113-1 -> #DIV/0! | F114: =F113/E113-1 -> #DIV/0! | G114: =G113/F113-1 -> -0.20073727 | J114: =J113/G113-1 -> -0.30275368 | K114: =K113/J113-1 -> 0.22318054 | L114: =L113/K113-1 -> 0.036029862 | M114: =M113/L113-1 -> 0.032992725 | N114: =N113/M113-1 -> 0.033195437 | O114: =O113/N113-1 -> 0.033401249
B115: % of SI매출 | D115: =D113/D$109 -> 0 | E115: =E113/E$109 -> 0 | F115: =F113/F$109 -> 0.54284357 | G115: =G113/G$109 -> 0.28730298 | H115: =H113/H$109 -> 0.23913217 | J115: =J113/J$109 -> 0.23913217 | K115: =K113/K$109 -> 0.23131916 | L115: =L113/L$109 -> 0.2338384 | M115: =M113/M$109 -> 0.23375202 | N115: =N113/N$109 -> 0.23403292 | O115: =O113/O$109 -> 0.23445179
B117: GS Caltex | F117: 22369.63 | G117: 7282.1321 | H117: 3396.949 | J117: =H117+I117 -> 3396.949 | K117: =사업계획!S6 -> 5319.9752 | L117: =K117*(1+L118) -> 5418.4933 | M117: =L117*(1+M118) -> 5541.6408 | N117: =M117*(1+N118) -> 5667.5872 | O117: =N117*(1+O118) -> 5796.396
B118: % of growth | D118: =D117/C117-1 -> #DIV/0! | E118: =E117/D117-1 -> #DIV/0! | F118: =F117/E117-1 -> #DIV/0! | G118: =G117/F117-1 -> -0.67446346 | J118: =J117/G117-1 -> -0.53352274 | K118: =K117/J117-1 -> 0.56610392 | L118: =L$29 -> 0.018518519 | M118: =M$29 -> 0.022727273 | N118: =N$29 -> 0.022727273 | O118: =O$29 -> 0.022727273
B119: % of sales | D119: =D117/D$6 -> 0 | E119: =E117/E$6 -> 0 | F119: =F117/F$6 -> 0.10567495 | G119: =G117/G$6 -> 0.028919068 | H119: =H117/H$6 -> 0.015807989 | J119: =J117/J$6 -> 0.015807989 | K119: =K117/K$6 -> 0.021481166 | L119: =L117/L$6 -> 0.021147648 | M119: =M117/M$6 -> 0.020886694 | N119: =N117/N$6 -> 0.02062961 | O119: =O117/O$6 -> 0.020361842
B120: GS HS | F120: 3868.4099 | G120: 6346.4436 | H120: 3302.546 | J120: =H120+I120 -> 3302.546 | K120: =사업계획!S7 -> 5153.659 | L120: =K120*(1+L121) -> 5395.3158 | M120: =L120*(1+M121) -> 5568.2626 | N120: =M120*(1+N121) -> 5746.7532 | O120: =N120*(1+O121) -> 5930.9654
B121: % of growth | D121: =D120/C120-1 -> #DIV/0! | E121: =E120/D120-1 -> #DIV/0! | F121: =F120/E120-1 -> #DIV/0! | G121: =G120/F120-1 -> 0.64058199 | J121: =J120/G120-1 -> -0.47962257 | K121: =K120/J120-1 -> 0.56051089 | L121: =그룹사EE!L7 -> 0.046890328 | M121: =그룹사EE!M7 -> 0.032054995 | N121: =M121 -> 0.032054995 | O121: =N121 -> 0.032054995 | Q121: 매출액 Consensus 비례증가/2019년 이후 2018년 성장률
B122: % of sales | D122: =D120/D$6 -> 0 | E122: =E120/E$6 -> 0 | F122: =F120/F$6 -> 0.01827451 | G122: =G120/G$6 -> 0.025203228 | H122: =H120/H$6 -> 0.015368676 | J122: =J120/J$6 -> 0.015368676 | K122: =K120/K$6 -> 0.020809609 | L122: =L120/L$6 -> 0.02105719 | M122: =M120/M$6 -> 0.020987033 | N122: =N120/N$6 -> 0.020917768 | O122: =O120/O$6 -> 0.020834563
...

Sheet 매출원가
B1: ="Project"&" "&Title!L6 -> Project IT | O1: =Des!C12 -> DRAFT - For Discussion Purposes Only
B2: 매출원가
B4: 매출원가
B5: =unit -> KRW Millions | C5: ='Pro forma'!C$5 -> 2010 | D5: ='Pro forma'!D$5 -> 2011 | E5: ='Pro forma'!E$5 -> 2012 | F5: ='Pro forma'!F$5 -> 2013 | G5: ='Pro forma'!G$5 -> 2014 | H5: ='Pro forma'!H$5 -> 2015/12A | I5: ='Pro forma'!I$5 -> 2015/0E | J5: ='Pro forma'!J$5 -> 2015 | ... O5: ='Pro forma'!O$5 -> 2020
B6: 매출원가 | C6: =SUM(C9,C13,C17) -> 86101.883 | D6: =SUM(D9,D13,D17) -> 106369.5 | E6: =SUM(E9,E13,E17) -> 165640.96 | F6: =SUM(F9,F13,F17) -> 194029.19 | G6: =SUM(G9,G13,G17) -> 233681.98 | H6: =SUM(H9,H13,H17) -> 193423.41 | J6: =SUM(J9,J13,J17) -> 193443.28 | K6: =SUM(K9,K13,K17) -> 225185.42 | L6: =SUM(L9,L13,L17) -> 233133.63 | M6: =SUM(M9,M13,M17) -> 241478.05 | N6: =SUM(N9,N13,N17) -> 250207.65 | O6: =SUM(O9,O13,O17) -> 259472.68
B7: % of growth | D7: =D6/C6-1 -> 0.23539109 | E7: =E6/D6-1 -> 0.55722231 | F7: =F6/E6-1 -> 0.17138415 | G7: =G6/F6-1 -> 0.20436508 | J7: =J6/G6-1 -> -0.1721943 | K7: =K6/J6-1 -> 0.16409019 | L7: =L6/K6-1 -> 0.035296275 | M7: =M6/L6-1 -> 0.035792471 | N7: =N6/M6-1 -> 0.036150675 | O7: =O6/N6-1 -> 0.037029368
B9: 상품 | C9: =C74 -> 27235.239 | D9: =D74 -> 32097.45 | E9: =E74 -> 69801.338 | F9: =F74 -> 69822.706 | G9: =G74 -> 67182.469 | H9: =H74 -> 41356.112 | J9: =J74 -> 41356.112 | K9: =K74 -> 49675.413 | L9: =L74 -> 51813.467 | M9: =M74 -> 53642.342 | N9: =N74 -> 55527.847 | O9: =O74 -> 57515.047
B10: % of growth | D10: =D9/C9-1 -> 0.17852645 | E10: =E9/D9-1 -> 1.1746693 | F10: =F9/E9-1 -> 0.00030612811 | G10: =G9/F9-1 -> -0.037813449 | J10: =J9/G9-1 -> -0.38442108 | K10: =K9/J9-1 -> 0.20116256 | L10: =L9/K9-1 -> 0.043040493 | M10: =M9/L9-1 -> 0.035297296 | N10: =N9/M9-1 -> 0.035149564 | O10: =O9/N9-1 -> 0.035787434
B11: % of COGS | C11: =C9/C$6 -> 0.3163141 | D11: =D9/D$6 -> 0.30175426 | E11: =E9/E$6 -> 0.42140144 | F11: =F9/F$6 -> 0.35985671 | G11: =G9/G$6 -> 0.28749529 | H11: =H9/H$6 -> 0.2138113 | J11: =J9/J$6 -> 0.21378935 | K11: =K9/K$6 -> 0.22059782 | L11: =L9/L$6 -> 0.22224794 | M11: =M9/M$6 -> 0.22214169 | N11: =N9/N$6 -> 0.22192706 | O11: =O9/O$6 -> 0.22166128
B13: SI | C13: =C81 -> 29500.793 | D13: =D81 -> 29493.783 | E13: =E81 -> 49020.706 | F13: =F81 -> 56234.131 | G13: =G81 -> 86626.579 | H13: =H81 -> 71978.983 | J13: =J81 -> 71978.983 | K13: =K81 -> 88058.883 | L13: =L81 -> 90412.235 | M13: =M81 -> 93482.625 | N13: =N81 -> 96566.989 | O13: =O81 -> 99746.059
B14: % of growth | D14: =D13/C13-1 -> -0.00023761368 | E14: =E13/D13-1 -> 0.66206909 | F14: =F13/E13-1 -> 0.14715057 | G14: =G13/F13-1 -> 0.54046266 | J14: =J13/G13-1 -> -0.16908894 | K14: =K13/J13-1 -> 0.22339716 | L14: =L13/K13-1 -> 0.02672475 | M14: =M13/L13-1 -> 0.033959897 | N14: =N13/M13-1 -> 0.032993979 | O14: =O13/N13-1 -> 0.032920876
B15: % of COGS | C15: =C13/C$6 -> 0.34262658 | D15: =D13/D$6 -> 0.2772767 | E15: =E13/E$6 -> 0.29594556 | F15: =F13/F$6 -> 0.28982305 | G15: =G13/G$6 -> 0.37070286 | H15: =H13/H$6 -> 0.3721317 | J15: =J13/J$6 -> 0.37209348 | K15: =K13/K$6 -> 0.39105056 | L15: =L13/L$6 -> 0.38781293 | M15: =M13/M$6 -> 0.38712679 | N15: =N13/N$6 -> 0.38594739 | O15: =O13/O$6 -> 0.38441835
B17: SM | C17: =C195 -> 29365.85 | D17: =D195 -> 44778.266 | E17: =E195 -> 46818.913 | F17: =F195 -> 67972.354 | G17: =G195 -> 79872.934 | H17: =H195 -> 80088.317 | J17: =J195 -> 80108.182 | K17: =K195 -> 87451.123 | L17: =L195 -> 90907.924 | M17: =M195 -> 94353.087 | N17: =N195 -> 98112.813 | O17: =O195 -> 102211.57
B18: % of growth | D18: =D17/C17-1 -> 0.52484145 | E18: =E17/D17-1 -> 0.045572268 | F18: =F17/E17-1 -> 0.45181401 | G18: =G17/F17-1 -> 0.17507972 | J18: =J17/G17-1 -> 0.0029452723 | K18: =K17/J17-1 -> 0.091662813 | L18: =L17/K17-1 -> 0.039528372 | M18: =M17/L17-1 -> 0.03789728 | N18: =N17/M17-1 -> 0.039847409 | O18: =O17/N17-1 -> 0.041776012
B19: % of COGS | C19: =C17/C$6 -> 0.34105933 | D19: =D17/D$6 -> 0.42096904 | E19: =E17/E$6 -> 0.282653 | F19: =F17/F$6 -> 0.35032024 | G19: =G17/G$6 -> 0.34180185 | H19: =H17/H$6 -> 0.414057 | J19: =J17/J$6 -> 0.41411717 | K19: =K17/K$6 -> 0.38835162 | L19: =L17/L$6 -> 0.38993913 | M19: =M17/M$6 -> 0.39073152 | N19: =N17/N$6 -> 0.39212555 | O19: =O17/O$6 -> 0.39392037
C22: =C6-IS!J11 -> 0 | D22: =D6-IS!K11 -> 0 | E22: =E6-IS!L11 -> 0 | F22: =F6-IS!M11 -> 0 | G22: =G6-IS!N11 -> 0 | H22: =H6-IS!O11 -> -25.603271
B24: 매출원가
B25: =unit -> KRW Millions | C25: ='Pro forma'!C$5 -> 2010 | D25: ='Pro forma'!D$5 -> 2011 | E25: ='Pro forma'!E$5 -> 2012 | F25: ='Pro forma'!F$5 -> 2013 | G25: ='Pro forma'!G$5 -> 2014 | H25: ='Pro forma'!H$5 -> 2015/12A | I25: ='Pro forma'!I$5 -> 2015/0E | J25: ='Pro forma'!J$5 -> 2015 | ... O25: ='Pro forma'!O$5 -> 2020
B26: 매출원가 | C26: =SUM(C29,C33,C37,C41,C45,C49) -> 86101.883 | D26: =SUM(D29,D33,D37,D41,D45,D49) -> 106369.5 | E26: =SUM(E29,E33,E37,E41,E45,E49) -> 165640.96 | F26: =SUM(F29,F33,F37,F41,F45,F49) -> 194029.19 | G26: =SUM(G29,G33,G37,G41,G45,G49) -> 233681.98 | H26: =SUM(H29,H33,H37,H41,H45,H49) -> 193423.41 | J26: =SUM(J29,J33,J37,J41,J45,J49) -> 193443.28 | K26: =SUM(K29,K33,K37,K41,K45,K49) -> 225185.42 | L26: =SUM(L29,L33,L37,L41,L45,L49) -> 233133.63 | M26: =SUM(M29,M33,M37,M41,M45,M49) -> 241478.05 | N26: =SUM(N29,N33,N37,N41,N45,N49) -> 250207.65 | O26: =SUM(O29,O33,O37,O41,O45,O49) -> 259472.68
B27: % of growth | D27: =D26/C26-1 -> 0.23539109 | E27: =E26/D26-1 -> 0.55722231 | F27: =F26/E26-1 -> 0.17138415 | G27: =G26/F26-1 -> 0.20436508 | H27: =H26/G26-1 -> -0.17227931 | J27: =J26/G26-1 -> -0.1721943 | K27: =K26/J26-1 -> 0.16409019 | L27: =L26/K26-1 -> 0.035296275 | M27: =M26/L26-1 -> 0.035792471 | N27: =N26/M26-1 -> 0.036150675 | O27: =O26/N26-1 -> 0.037029368
B29: 상품 재료비 | C29: =C74 -> 27235.239 | D29: =D74 -> 32097.45 | E29: =E74 -> 69801.338 | F29: =F74 -> 69822.706 | G29: =G74 -> 67182.469 | H29: =H74 -> 41356.112 | J29: =J74 -> 41356.112 | K29: =K74 -> 49675.413 | L29: =L74 -> 51813.467 | M29: =M74 -> 53642.342 | N29: =N74 -> 55527.847 | O29: =O74 -> 57515.047
B30: % of growth | D30: =D29/C29-1 -> 0.17852645 | E30: =E29/D29-1 -> 1.1746693 | F30: =F29/E29-1 -> 0.00030612811 | G30: =G29/F29-1 -> -0.037813449 | H30: =H29/G29-1 -> -0.38442108 | J30: =J29/G29-1 -> -0.38442108 | K30: =K29/J29-1 -> 0.20116256 | L30: =L29/K29-1 -> 0.043040493 | M30: =M29/L29-1 -> 0.035297296 | N30: =N29/M29-1 -> 0.035149564 | O30: =O29/N29-1 -> 0.035787434
B31: % of COGS | C31: =C29/C$26 -> 0.3163141 | D31: =D29/D$26 -> 0.30175426 | E31: =E29/E$26 -> 0.42140144 | F31: =F29/F$26 -> 0.35985671 | G31: =G29/G$26 -> 0.28749529 | H31: =H29/H$26 -> 0.2138113 | J31: =J29/J$26 -> 0.21378935 | K31: =K29/K$26 -> 0.22059782 | L31: =L29/L$26 -> 0.22224794 | M31: =M29/M$26 -> 0.22214169 | N31: =N29/N$26 -> 0.22192706 | O31: =O29/O$26 -> 0.22166128
B33: 직접 변동비 | C33: =C86+C200 -> 46281.226 | D33: =D86+D200 -> 56836.968 | E33: =E86+E200 -> 71014.951 | F33: =F86+F200 -> 94637.465 | G33: =G86+G200 -> 135546.49 | H33: =H86+H200 -> 124020.14 | J33: =J86+J200 -> 124020.14 | K33: =K86+K200 -> 140571.79 | L33: =L86+L200 -> 145009.07 | M33: =M86+M200 -> 150133.39 | N33: =N86+N200 -> 155416.93 | O33: =O86+O200 -> 160981.11 | R33: 재료비+외주비
B34: % of growth | D34: =D33/C33-1 -> 0.22807826 | E34: =E33/D33-1 -> 0.24945003 | F34: =F33/E33-1 -> 0.33264142 | G34: =G33/F33-1 -> 0.43227092 | H34: =H33/G33-1 -> -0.085036116 | J34: =J33/G33-1 -> -0.085036116 | K34: =K33/J33-1 -> 0.13345934 | L34: =L33/K33-1 -> 0.031565959 | M34: =M33/L33-1 -> 0.035337879 | N34: =N33/M33-1 -> 0.035192362 | O34: =O33/N33-1 -> 0.035801614
B35: % of COGS | C35: =C33/C$26 -> 0.53751701 | D35: =D33/D$26 -> 0.5343352 | E35: =E33/E$26 -> 0.42872821 | F35: =F33/F$26 -> 0.48774859 | G35: =G33/G$26 -> 0.58004681 | H35: =H33/H$26 -> 0.64118475 | J35: =J33/J$26 -> 0.64111891 | K35: =K33/K$26 -> 0.62424907 | L35: =L33/L$26 -> 0.62199982 | M35: =M33/M$26 -> 0.62172683 | N35: =N33/N$26 -> 0.62115181 | O35: =O33/O$26 -> 0.62041642
B37: 인건비성 경비 | C37: =C92+C206 -> 11251.56 | D37: =D92+D206 -> 16073.507 | E37: =E92+E206 -> 22926.02 | F37: =F92+F206 -> 27053.053 | G37: =G92+G206 -> 28287.174 | H37: =H92+H206 -> 25541.977 | J37: =J92+J206 -> 25541.977 | K37: =K92+K206 -> 32254.035 | L37: =L92+L206 -> 33608.705 | M37: =M92+M206 -> 34953.053 | N37: =N92+N206 -> 36421.081 | O37: =O92+O206 -> 38023.609
B38: % of growth | D38: =D37/C37-1 -> 0.42855805 | E38: =E37/D37-1 -> 0.42632349 | F38: =F37/E37-1 -> 0.18001525 | G38: =G37/F37-1 -> 0.045618527 | H38: =H37/G37-1 -> -0.097047424 | J38: =J37/G37-1 -> -0.097047424 | K38: =K37/J37-1 -> 0.2627854 | L38: =L37/K37-1 -> 0.042 | M38: =M37/L37-1 -> 0.04 | N38: =N37/M37-1 -> 0.042 | O38: =O37/N37-1 -> 0.044
B39: % of COGS | C39: =C37/C$26 -> 0.13067728 | D39: =D37/D$26 -> 0.15111011 | E39: =E37/E$26 -> 0.13840792 | F39: =F37/F$26 -> 0.13942775 | G39: =G37/G$26 -> 0.12104987 | H39: =H37/H$26 -> 0.13205215 | J39: =J37/J$26 -> 0.13203859 | K39: =K37/K$26 -> 0.14323323 | L39: =L37/L$26 -> 0.14416069 | M39: =M37/M$26 -> 0.14474629 | N39: =N37/N$26 -> 0.14556342 | O39: =O37/O$26 -> 0.14654186
B41: 변동비성 경비 | C41: =C110 -> 35.700155 | D41: =D110 -> 0 | E41: =E110 -> 63.09237 | F41: =F110 -> 22.67268 | G41: =G110 -> 112.17493 | H41: =H110 -> 6.823425 | J41: =J110 -> 6.823425 | K41: =K110 -> 192.74455 | L41: =L110 -> 197.53777 | M41: =M110 -> 204.13049 | N41: =N110 -> 210.65354 | O41: =O110 -> 217.30071
B42: % of growth | D42: =D41/C41-1 -> -1 | E42: =E41/D41-1 -> #DIV/0! | F42: =F41/E41-1 -> -0.64064308 | G42: =G41/F41-1 -> 3.9475816 | H42: =H41/G41-1 -> -0.93917157 | J42: =J41/G41-1 -> -0.93917157 | K42: =K41/J41-1 -> 27.247478 | L42: =L41/K41-1 -> 0.024868265 | M42: =M41/L41-1 -> 0.033374468 | N42: =N41/M41-1 -> 0.0319553 | O42: =O41/N41-1 -> 0.031554991
B43: % of COGS | C43: =C41/C$26 -> 0.00041462688 | D43: =D41/D$26 -> 0 | E43: =E41/E$26 -> 0.00038089837 | F43: =F41/F$26 -> 0.0001168519 | G43: =G41/G$26 -> 0.00048003245 | H43: =H41/H$26 -> 3.5277141e-05 | J43: =J41/J$26 -> 3.5273519e-05 | K43: =K41/K$26 -> 0.00085593708 | L43: =L41/L$26 -> 0.00084731566 | M43: =M41/M$26 -> 0.00084533765 | N43: =N41/N$26 -> 0.00084191488 | O43: =O41/O$26 -> 0.00083747049
B45: 고정비성 경비 | C45: =C122+C224 -> 1298.157 | D45: =D122+D224 -> 1304.5384 | E45: =E122+E224 -> 1636.4161 | F45: =F122+F224 -> 2264.1418 | G45: =G122+G224 -> 2299.0054 | H45: =H122+H224 -> 2269.1618 | J45: =J122+J224 -> 2269.1618 | K45: =K122+K224 -> 2298.6609 | L45: =L122+L224 -> 2333.1408 | M45: =M122+M224 -> 2375.1373 | N45: =N122+N224 -> 2422.6401 | O45: =O122+O224 -> 2475.9382
B46: % of growth | D46: =D45/C45-1 -> 0.0049157446 | E46: =E45/D45-1 -> 0.25440244 | F46: =F45/E45-1 -> 0.38359783 | G46: =G45/F45-1 -> 0.015398165 | H46: =H45/G45-1 -> -0.012981095 | J46: =J45/G45-1 -> -0.012981095 | K46: =K45/J45-1 -> 0.013 | L46: =L45/K45-1 -> 0.015 | M46: =M45/L45-1 -> 0.018 | N46: =N45/M45-1 -> 0.02 | O46: =O45/N45-1 -> 0.022
B47: % of COGS | C47: =C45/C$26 -> 0.015076987 | D47: =D45/D$26 -> 0.012264215 | E47: =E45/E$26 -> 0.0098792964 | F47: =F45/F$26 -> 0.011669078 | G47: =G45/G$26 -> 0.00983818 | H47: =H45/H$26 -> 0.011731578 | J47: =J45/J$26 -> 0.011730373 | K47: =K45/K$26 -> 0.010207859 | L47: =L45/L$26 -> 0.01000774 | M47: =M45/M$26 -> 0.0098358311 | N47: =N45/N$26 -> 0.0096825181 | O47: =O45/O$26 -> 0.0095421922
B49: 유무형 상각비 | C49: =C303+C307 -> 0 | D49: =D303+D307 -> 57.036222 | E49: =E303+E307 -> 199.13919 | F49: =F303+F307 -> 229.15173 | G49: =G303+G307 -> 254.66976 | H49: =H303+H307 -> 229.19532 | J49: =J303+J307 -> 249.06016 | K49: =K303+K307 -> 192.77696 | L49: =L303+L307 -> 171.70323 | M49: =M303+M307 -> 170.00589 | N49: =N303+N307 -> 208.49328 | O49: =O303+O307 -> 259.67531
B50: % of growth | D50: =D49/C49-1 -> #DIV/0! | E50: =E49/D49-1 -> 2.4914513 | F50: =F49/E49-1 -> 0.15071136 | G50: =G49/F49-1 -> 0.11135864 | H50: =H49/G49-1 -> -0.10002928 | J50: =J49/G49-1 -> -0.022026957 | K50: =K49/J49-1 -> -0.22598235 | L50: =L49/K49-1 -> -0.10931664 | M50: =M49/L49-1 -> -0.0098852941 | N50: =N49/M49-1 -> 0.22638856 | O50: =O49/N49-1 -> 0.24548525
B51: % of COGS | C51: =C49/C$26 -> 0 | D51: =D49/D$26 -> 0.00053620843 | E51: =E49/E$26 -> 0.001202234 | F51: =F49/F$26 -> 0.0011810168 | G51: =G49/G$26 -> 0.0010898134 | H51: =H49/H$26 -> 0.001184941 | J51: =J49/J$26 -> 0.00128751 | K51: =K49/K$26 -> 0.00085608099 | L51: =L49/L$26 -> 0.00073650134 | M51: =M49/M$26 -> 0.00070402212 | N51: =N49/N$26 -> 0.000833281 | O51: =O49/O$26 -> 0.0010007809
B55: KRW Millions | C55: =C5 -> 2010 | D55: =D5 -> 2011 | E55: =E5 -> 2012 | F55: =F5 -> 2013 | G55: =G5 -> 2014 | H55: =H5 -> 2015/12A | I55: =I5 -> 2015/0E | J55: =J5 -> 2015 | ... O55: =O5 -> 2020
B56: Nominal GDP Growth | C56: =Macro!H27/Macro!G27-1 -> 0.098636217 | D56: =Macro!I27/Macro!H27-1 -> 0.053246407 | E56: =Macro!J27/Macro!I27-1 -> 0.033598138 | F56: =Macro!K27/Macro!J27-1 -> 0.037742605 | G56: =Macro!L27/Macro!K27-1 -> 0.03891901 | J56: =Macro!M27/Macro!L27-1 -> 0.023003842 | K56: =Macro!N27/Macro!M27-1 -> 0.037334115 | L56: =Macro!O27/Macro!N27-1 -> 0.028565319 | M56: =Macro!P27/Macro!O27-1 -> 0.039323857 | N56: =Macro!Q27/Macro!P27-1 -> 0.040235567 | O56: =Macro!R27/Macro!Q27-1 -> 0.037923737
B57: Consumer prices (%) | C57: =Macro!H87/100 -> 0.02938 | D57: =Macro!I87/100 -> 0.04025 | E57: =Macro!J87/100 -> 0.02183 | F57: =Macro!K87/100 -> 0.01301 | G57: =Macro!L87/100 -> 0.01275 | J57: =Macro!M87/100 -> 0.006 | K57: =Macro!N87/100 -> 0.013 | L57: =Macro!O87/100 -> 0.015 | M57: =Macro!P87/100 -> 0.018 | N57: =Macro!Q87/100 -> 0.02 | O57: =Macro!R87/100 -> 0.022
B58: Growth in average wages | C58: =Macro!H90/100 -> 0.06844 | D58: =Macro!I90/100 -> 0.00923 | E58: =Macro!J90/100 -> 0.05371 | F58: =Macro!K90/100 -> 0.03856 | G58: =Macro!L90/100 -> 0.02554 | J58: =Macro!M90/100 -> 0.042 | K58: =Macro!N90/100 -> 0.043 | L58: =Macro!O90/100 -> 0.042 | M58: =Macro!P90/100 -> 0.04 | N58: =Macro!Q90/100 -> 0.042 | O58: =Macro!R90/100 -> 0.044
B61: 매출액 | C61: =매출액!C6 -> 101202.83 | D61: =매출액!D6 -> 120090.95 | E61: =매출액!E6 -> 182279.27 | F61: =매출액!F6 -> 211683.37 | G61: =매출액!G6 -> 251810.75 | H61: =매출액!H6 -> 214888.12 | J61: =매출액!J6 -> 214888.12 | K61: =매출액!K6 -> 247657.65 | L61: =매출액!L6 -> 256222.03 | M61: =매출액!M6 -> 265319.19 | N61: =매출액!N6 -> 274730.7 | O61: =매출액!O6 -> 284669.53
B62: 상품 | C62: =매출액!C9 -> 28667.765 | D62: =매출액!D9 -> 33818.96 | E62: =매출액!E9 -> 72895.968 | F62: =매출액!F9 -> 71774.78 | G62: =매출액!G9 -> 69236.769 | H62: =매출액!H9 -> 43311.995 | J62: =매출액!J9 -> 43311.995 | K62: =매출액!K9 -> 52024.746 | L62: =매출액!L9 -> 54263.917 | M62: =매출액!M9 -> 56179.287 | N62: =매출액!N9 -> 58153.964 | O62: =매출액!O9 -> 60235.145
B63: SI | C63: =매출액!C13 -> 32345.633 | D63: =매출액!D13 -> 31656.879 | E63: =매출액!E13 -> 52687.669 | F63: =매출액!F13 -> 60245.229 | G63: =매출액!G13 -> 90980.18 | H63: =매출액!H13 -> 76214.068 | J63: =매출액!J13 -> 76214.068 | K63: =매출액!K13 -> 96372.275 | L63: =매출액!L13 -> 98768.886 | M63: =매출액!M13 -> 102065.25 | N63: =매출액!N13 -> 105326.77 | O63: =매출액!O13 -> 108650.36
B64: SM | C64: =매출액!C17 -> 40189.43 | D64: =매출액!D17 -> 54615.106 | E64: =매출액!E17 -> 56695.63 | F64: =매출액!F17 -> 79663.359 | G64: =매출액!G17 -> 91593.798 | H64: =매출액!H17 -> 95362.06 | J64: =매출액!J17 -> 95362.06 | K64: =매출액!K17 -> 99260.63 | L64: =매출액!L17 -> 103189.22 | M64: =매출액!M17 -> 107074.66 | N64: =매출액!N17 -> 111249.97 | O64: =매출액!O17 -> 115784.03
B67: 1. 상품매출원가 추정
B69: Step1. 대내 매출은 지속가능한 상품매출 확정. ->FY 2015&2016 계획 동시검토
B70: Step2. 대외 매출은 총액 기준으로 SM+SI 기준 검토
B72: 상품매출원가(재료비)
B73: =Des!$C$13 -> KRW Millions | C73: ='Pro forma'!C$5 -> 2010 | D73: ='Pro forma'!D$5 -> 2011 | E73: ='Pro forma'!E$5 -> 2012 | F73: ='Pro forma'!F$5 -> 2013 | G73: ='Pro forma'!G$5 -> 2014 | H73: ='Pro forma'!H$5 -> 2015/12A | I73: ='Pro forma'!I$5 -> 2015/0E | J73: ='Pro forma'!J$5 -> 2015 | ... O73: ='Pro forma'!O$5 -> 2020
B74: 상품매출원가 | C74: =IS!J12-'CapEx&Dep'!C59 -> 27235.239 | D74: =IS!K12-'CapEx&Dep'!D59 -> 32097.45 | E74: =IS!L12-'CapEx&Dep'!E59 -> 69801.338 | F74: =IS!M12-'CapEx&Dep'!F59 -> 69822.706 | G74: =IS!N12-'CapEx&Dep'!G59 -> 67182.469 | H74: =IS!O12-'CapEx&Dep'!J59 -> 41356.112 | J74: =H74+I74 -> 41356.112 | K74: =K62*K76 -> 49675.413 | L74: =L62*L76 -> 51813.467 | M74: =M62*M76 -> 53642.342 | N74: =N62*N76 -> 55527.847 | O74: =O62*O76 -> 57515.047 | R74: 감사보고서상 상품매출원가서 기존 녹아져 있는 운용리스감가상각비 제거
B75: % of growth | D75: =D74/C74-1 -> 0.17852645 | E75: =E74/D74-1 -> 1.1746693 | F75: =F74/E74-1 -> 0.00030612811 | G75: =G74/F74-1 -> -0.037813449 | H75: =H74/G74-1 -> -0.38442108 | J75: =J74/G74-1 -> -0.38442108 | K75: =K74/J74-1 -> 0.20116256 | L75: =L74/K74-1 -> 0.043040493 | M75: =M74/L74-1 -> 0.035297296 | N75: =N74/M74-1 -> 0.035149564 | O75: =O74/N74-1 -> 0.035787434
B76: % of sales | C76: =C74/C$62 -> 0.9500301 | D76: =D74/D$62 -> 0.9490963 | E76: =E74/E$62 -> 0.95754731 | F76: =F74/F$62 -> 0.97280278 | G76: =G74/G$62 -> 0.97032935 | H76: =H74/H$62 -> 0.954842 | J76: =J74/J$62 -> 0.954842 | K76: =J76 -> 0.954842 | L76: =K76 -> 0.954842 | M76: =L76 -> 0.954842 | N76: =M76 -> 0.954842 | O76: =N76 -> 0.954842 | R76: 협력매출 사라진 2015년 매출원가율 유지 가정
B79: SI매출원가
B80: =Des!$C$13 -> KRW Millions | C80: ='Pro forma'!C$5 -> 2010 | D80: ='Pro forma'!D$5 -> 2011 | E80: ='Pro forma'!E$5 -> 2012 | F80: ='Pro forma'!F$5 -> 2013 | G80: ='Pro forma'!G$5 -> 2014 | H80: ='Pro forma'!H$5 -> 2015/12A | I80: ='Pro forma'!I$5 -> 2015/0E | J80: ='Pro forma'!J$5 -> 2015 | ... O80: ='Pro forma'!O$5 -> 2020
B81: SI매출원가 | C81: =C86+C92+C97+C102 -> 29500.793 | D81: =D86+D92+D97+D102 -> 29493.783 | E81: =E86+E92+E97+E102 -> 49020.706 | F81: =F86+F92+F97+F102 -> 56234.131 | G81: =G86+G92+G97+G102 -> 86626.579 | H81: =H86+H92+H97+H102 -> 71978.983 | J81: =J86+J92+J97+J102 -> 71978.983 | K81: =K86+K92+K97+K102 -> 88058.883 | L81: =L86+L92+L97+L102 -> 90412.235 | M81: =M86+M92+M97+M102 -> 93482.625 | N81: =N86+N92+N97+N102 -> 96566.989 | O81: =O86+O92+O97+O102 -> 99746.059
B82: % of growth | D82: =D81/C81-1 -> -0.00023761368 | E82: =E81/D81-1 -> 0.66206909 | F82: =F81/E81-1 -> 0.14715057 | G82: =G81/F81-1 -> 0.54046266 | J82: =J81/G81-1 -> -0.16908894 | K82: =K81/J81-1 -> 0.22339716 | L82: =L81/K81-1 -> 0.02672475 | M82: =M81/L81-1 -> 0.033959897 | N82: =N81/M81-1 -> 0.032993979 | O82: =O81/N81-1 -> 0.032920876
B83: % of sales | D83: =D81/D$63 -> 0.9316706 | E83: =E81/E$63 -> 0.93040188 | F83: =F81/F$63 -> 0.93342049 | G83: =G81/G$63 -> 0.95214781 | H83: =H81/H$63 -> 0.9444317 | J83: =J81/J$63 -> 0.9444317 | K83: =K81/K$63 -> 0.91373669 | L83: =L81/L$63 -> 0.91539186 | M83: =M81/M$63 -> 0.91591045 | N83: =N81/N$63 -> 0.91683233 | O83: =O81/O$63 -> 0.91804631
B84: % of COGS | D84: =D81/D$6 -> 0.2772767 | E84: =E81/E$6 -> 0.29594556 | F84: =F81/F$6 -> 0.28982305 | G84: =G81/G$6 -> 0.37070286 | H84: =H81/H$6 -> 0.3721317 | J84: =J81/J$6 -> 0.37209348 | K84: =K81/K$6 -> 0.39105056 | L84: =L81/L$6 -> 0.38781293 | M84: =M81/M$6 -> 0.38712679 | N84: =N81/N$6 -> 0.38594739 | O84: =O81/O$6 -> 0.38441835
B86: 직접 변동비 | C86: =원가구분!U7+원가구분!U8 -> 24990.995 | D86: =원가구분!V7+원가구분!V8 -> 23680.118 | E86: =원가구분!W7+원가구분!W8 -> 38805.207 | F86: =원가구분!X7+원가구분!X8 -> 44305.388 | G86: =원가구분!Y7+원가구분!Y8 -> 75287.26 | H86: =원가구분!Z7+원가구분!Z8 -> 62540.686 | J86: =H86+I86 -> 62540.686 | K86: =K63*K88 -> 76568.497 | L86: =L63*L88 -> 78472.623 | M86: =M63*M88 -> 81091.605 | N86: =N63*N88 -> 83682.911 | O86: =O63*O88 -> 86323.525 | R86: 재료비+외주비
B87: % of growth | D87: =D86/C86-1 -> -0.052453957 | E87: =E86/D86-1 -> 0.63872522 | F87: =F86/E86-1 -> 0.14173824 | G87: =G86/F86-1 -> 0.69928 | J87: =J86/G86-1 -> -0.16930586 | K87: =K86/J86-1 -> 0.22429896 | L87: =L86/K86-1 -> 0.024868265 | M87: =M86/L86-1 -> 0.033374468 | N87: =N86/M86-1 -> 0.0319553 | O87: =O86/N86-1 -> 0.031554991
B88: % of sales | C88: =C86/C$63 -> 0.77262344 | D88: =D86/D$63 -> 0.7480244 | E88: =E86/E$63 -> 0.73651401 | F88: =F86/F$63 -> 0.73541738 | G88: =G86/G$63 -> 0.82751276 | H88: =H86/H$63 -> 0.82059241 | J88: =J86/J$63 -> 0.82059241 | K88: =AVERAGE(F88:H88) -> 0.79450752 | L88: =K88 -> 0.79450752 | M88: =L88 -> 0.79450752 | N88: =M88 -> 0.79450752 | O88: =N88 -> 0.79450752
B89: % of COGS | C89: =C86/C$6 -> 0.29024911 | D89: =D86/D$6 -> 0.22262132 | E89: =E86/E$6 -> 0.23427302 | F89: =F86/F$6 -> 0.22834393 | G89: =G86/G$6 -> 0.32217829 | H89: =H86/H$6 -> 0.32333566 | J89: =J86/J$6 -> 0.32330246 | K89: =K86/K$6 -> 0.34002422 | L89: =L86/L$6 -> 0.33659933 | M89: =M86/M$6 -> 0.33581356 | N89: =N86/N$6 -> 0.33445385 | O89: =O86/O$6 -> 0.3326883
B90: % of SI COGS | C90: =C86/C$81 -> 0.84712958 | D90: =D86/D$81 -> 0.80288506 | E90: =E86/E$81 -> 0.79160848 | F90: =F86/F$81 -> 0.78787362 | G90: =G86/G$81 -> 0.86910116 | H90: =H86/H$81 -> 0.86887427 | J90: =J86/J$81 -> 0.86887427 | K90: =K86/K$81 -> 0.86951474 | L90: =L86/L$81 -> 0.86794252 | M90: =M86/M$81 -> 0.86745109 | N90: =N86/N$81 -> 0.86657886 | O90: =O86/O$81 -> 0.86543294
B92: 인건비성 경비 | C92: =노무비!C76 -> 3953.9628 | D92: =노무비!D76 -> 5141.6747 | E92: =노무비!E76 -> 9363.1906 | F92: =노무비!F76 -> 10962.727 | G92: =노무비!G76 -> 10189.763 | H92: =노무비!H76 -> 8332.1261 | J92: =노무비!J76 -> 8332.1261 | K92: =노무비!K76 -> 10184.003 | L92: =노무비!L76 -> 10611.731 | M92: =노무비!M76 -> 11036.201 | N92: =노무비!N76 -> 11499.721 | O92: =노무비!O76 -> 12005.709
B93: % of growth | D93: =D92/C92-1 -> 0.3003852 | E93: =E92/D92-1 -> 0.82103908 | F93: =F92/E92-1 -> 0.17083241 | G93: =G92/F92-1 -> -0.070508338 | J93: =J92/G92-1 -> -0.18230426 | K93: =K92/J92-1 -> 0.22225746 | L93: =L92/K92-1 -> 0.042 | M93: =M92/L92-1 -> 0.04 | N93: =N92/M92-1 -> 0.042 | O93: =O92/N92-1 -> 0.044
B94: % of sales | C94: =C92/C$63 -> 0.12224101 | D94: =D92/D$63 -> 0.16241888 | E94: =E92/E$63 -> 0.17771123 | F94: =F92/F$63 -> 0.18196839 | G94: =G92/G$63 -> 0.11199982 | H94: =H92/H$63 -> 0.1093253 | J94: =J92/J$63 -> 0.1093253 | K94: =K92/K$63 -> 0.10567358 | L94: =L92/L$63 -> 0.10744002 | M94: =M92/M$63 -> 0.10812888 | N94: =N92/N$63 -> 0.10918137 | O94: =O92/O$63 -> 0.11049857
B95: % of COGS | C95: =C92/C$6 -> 0.045921909 | D95: =D92/D$6 -> 0.048337867 | E95: =E92/E$6 -> 0.056527026 | F95: =F92/F$6 -> 0.056500401 | G95: =G92/G$6 -> 0.043605259 | H95: =H92/H$6 -> 0.043077133 | J95: =J92/J$6 -> 0.04307271 | K95: =K92/K$6 -> 0.045224968 | L95: =L92/L$6 -> 0.045517807 | M95: =M92/M$6 -> 0.045702707 | N95: =N92/N$6 -> 0.04596071 | O95: =O92/O$6 -> 0.046269645
B97: 변동비성 경비 | C97: =C110 -> 35.700155 | D97: =D110 -> 0 | E97: =E110 -> 63.09237 | F97: =F110 -> 22.67268 | G97: =G110 -> 112.17493 | H97: =H110 -> 6.823425 | J97: =J110 -> 6.823425 | K97: =K110 -> 192.74455 | L97: =L110 -> 197.53777 | M97: =M110 -> 204.13049 | N97: =N110 -> 210.65354 | O97: =O110 -> 217.30071
B98: % of growth | D98: =D97/C97-1 -> -1 | E98: =E97/D97-1 -> #DIV/0! | F98: =F97/E97-1 -> -0.64064308 | G98: =G97/F97-1 -> 3.9475816 | J98: =J97/G97-1 -> -0.93917157 | K98: =K97/J97-1 -> 27.247478 | L98: =L97/K97-1 -> 0.024868265 | M98: =M97/L97-1 -> 0.033374468 | N98: =N97/M97-1 -> 0.0319553 | O98: =O97/N97-1 -> 0.031554991
B99: % of sales | C99: =C97/C$63 -> 0.0011037086 | D99: =D97/D$63 -> 0 | E99: =E97/E$63 -> 0.0011974789 | F99: =F97/F$63 -> 0.00037633984 | G99: =G97/G$63 -> 0.0012329601 | H99: =H97/H$63 -> 8.952973e-05 | J99: =J97/J$63 -> 8.952973e-05 | K99: =K97/K$63 -> 0.002 | L99: =L97/L$63 -> 0.002 | M99: =M97/M$63 -> 0.002 | N99: =N97/N$63 -> 0.002 | O99: =O97/O$63 -> 0.002
B100: % of COGS | C100: =C97/C$6 -> 0.00041462688 | D100: =D97/D$6 -> 0 | E100: =E97/E$6 -> 0.00038089837 | F100: =F97/F$6 -> 0.0001168519 | G100: =G97/G$6 -> 0.00048003245 | H100: =H97/H$6 -> 3.5277141e-05 | J100: =J97/J$6 -> 3.5273519e-05 | K100: =K97/K$6 -> 0.00085593708 | L100: =L97/L$6 -> 0.00084731566 | M100: =M97/M$6 -> 0.00084533765 | N100: =N97/N$6 -> 0.00084191488 | O100: =O97/O$6 -> 0.00083747049
B102: 고정비성 경비 | C102: =C122 -> 520.1357 | D102: =D122 -> 671.9907 | E102: =E122 -> 789.21643 | F102: =F122 -> 943.34294 | G102: =G122 -> 1037.3805 | H102: =H122 -> 1099.347 | J102: =J122 -> 1099.347 | K102: =K122 -> 1113.6385 | L102: =L122 -> 1130.3431 | M102: =M122 -> 1150.6892 | N102: =N122 -> 1173.703 | O102: =O122 -> 1199.5245
B103: % of growth | D103: =D102/C102-1 -> 0.29195266 | E103: =E102/D102-1 -> 0.17444547 | F103: =F102/E102-1 -> 0.19529055 | G103: =G102/F102-1 -> 0.099685406 | J103: =J102/G102-1 -> 0.059733632 | K103: =K102/J102-1 -> 0.013 | L103: =L102/K102-1 -> 0.015 | M103: =M102/L102-1 -> 0.018 | N103: =N102/M102-1 -> 0.02 | O103: =O102/N102-1 -> 0.022
B104: % of sales | C104: =C102/C$63 -> 0.016080554 | D104: =D102/D$63 -> 0.02122732 | E104: =E102/E$63 -> 0.014979149 | F104: =F102/F$63 -> 0.015658384 | G104: =G102/G$63 -> 0.011402269 | H104: =H102/H$63 -> 0.014424462 | J104: =J102/J$63 -> 0.014424462 | K104: =K102/K$63 -> 0.01155559 | L104: =L102/L$63 -> 0.011444323 | M104: =M102/M$63 -> 0.011274055 | N104: =N102/N$63 -> 0.011143444 | O104: =O102/O$63 -> 0.011040226
B105: % of COGS | C105: =C102/C$6 -> 0.0060409329 | D105: =D102/D$6 -> 0.006317513 | E105: =E102/E$6 -> 0.0047646213 | F105: =F102/F$6 -> 0.0048618609 | G105: =G102/G$6 -> 0.0044392831 | H105: =H102/H$6 -> 0.0056836293 | J105: =J102/J$6 -> 0.0056830457 | K105: =K102/K$6 -> 0.0049454289 | L105: =L102/L$6 -> 0.0048484771 | M105: =M102/M$6 -> 0.0047651918 | N105: =N102/N$6 -> 0.0046909158 | O105: =O102/O$6 -> 0.0046229317
C107: =C81-원가명세서!K40/10^6 -> 0 | D107: =D81-원가명세서!L40/10^6 -> 0 | E107: =E81-원가명세서!M40/10^6 -> 0 | F107: =F81-원가명세서!N40/10^6 -> 0 | G107: =G81-원가명세서!O40/10^6 -> 0
B108: SI 변동비성 경비 | R108: 가정 | T108: 확정 | U108: 비고
B109: =unit -> KRW Millions | C109: ='Pro forma'!C$5 -> 2010 | D109: ='Pro forma'!D$5 -> 2011 | E109: ='Pro forma'!E$5 -> 2012 | F109: ='Pro forma'!F$5 -> 2013 | G109: ='Pro forma'!G$5 -> 2014 | H109: ='Pro forma'!H$5 -> 2015/12A | I109: ='Pro forma'!I$5 -> 2015/0E | J109: ='Pro forma'!J$5 -> 2015 | ... O109: ='Pro forma'!O$5 -> 2020 | R109: 최초적용 | S109: 추세 및 인터뷰 등 | T109: 적용사항
B110: SI 변동비성 경비 | C110: =C115 -> 35.700155 | D110: =D115 -> 0 | E110: =E115 -> 63.09237 | F110: =F115 -> 22.67268 | G110: =G115 -> 112.17493 | H110: =H115 -> 6.823425 | J110: =J115 -> 6.823425 | K110: =K115 -> 192.74455 | L110: =L115 -> 197.53777 | M110: =M115 -> 204.13049 | N110: =N115 -> 210.65354 | O110: =O115 -> 217.30071
B111: % of growth | D111: =D110/C110-1 -> -1 | E111: =E110/D110-1 -> #DIV/0! | F111: =F110/E110-1 -> -0.64064308 | G111: =G110/F110-1 -> 3.9475816 | H111: =H110/G110-1 -> -0.93917157 | J111: =J110/G110-1 -> -0.93917157 | K111: =K110/J110-1 -> 27.247478 | L111: =L110/K110-1 -> 0.024868265 | M111: =M110/L110-1 -> 0.033374468 | N111: =N110/M110-1 -> 0.0319553 | O111: =O110/N110-1 -> 0.031554991
B112: % of SI 매출액 | C112: =C110/C$63 -> 0.0011037086 | D112: =D110/D$63 -> 0 | E112: =E110/E$63 -> 0.0011974789 | F112: =F110/F$63 -> 0.00037633984 | G112: =G110/G$63 -> 0.0012329601 | H112: =H110/H$63 -> 8.952973e-05 | J112: =J110/J$63 -> 8.952973e-05 | K112: =K110/K$63 -> 0.002 | L112: =L110/L$63 -> 0.002 | M112: =M110/M$63 -> 0.002 | N112: =N110/N$63 -> 0.002 | O112: =O110/O$63 -> 0.002
B113: % of SI COGS | D113: =D110/D$13 -> 0 | E113: =E110/E$13 -> 0.0012870555 | F113: =F110/F$13 -> 0.00040318361 | G113: =G110/G$13 -> 0.0012949251 | H113: =H110/H$13 -> 9.4797464e-05 | J113: =J110/J$13 -> 9.4797464e-05 | K113: =K110/K$13 -> 0.0021888144 | L113: =L110/L$13 -> 0.0021848566 | M113: =M110/M$13 -> 0.0021836196 | N113: =N110/N$13 -> 0.0021814239 | O113: =O110/O$13 -> 0.0021785393
B115: 하자보수비 | C115: =원가명세서!K35/1000000 -> 35.700155 | D115: =원가명세서!L35/1000000 -> 0 | E115: =원가명세서!M35/1000000 -> 63.09237 | F115: =원가명세서!N35/1000000 -> 22.67268 | G115: =원가명세서!O35/1000000 -> 112.17493 | H115: =원가명세서!P35/1000000 -> 6.823425 | J115: =H115+I115 -> 6.823425 | K115: =K116*K$63 -> 192.74455 | L115: =L116*L$63 -> 197.53777 | M115: =M116*M$63 -> 204.13049 | N115: =N116*N$63 -> 210.65354 | O115: =O116*O$63 -> 217.30071 | R115: 변동비 | S115: SI 매출의 0.2% | T115: 변동비
B116: % of SI 매출액 | C116: =C115/C$63 -> 0.0011037086 | D116: =D115/D$63 -> 0 | E116: =E115/E$63 -> 0.0011974789 | F116: =F115/F$63 -> 0.00037633984 | G116: =G115/G$63 -> 0.0012329601 | H116: =H115/H$63 -> 8.952973e-05 | J116: =J115/J$63 -> 8.952973e-05 | K116: 0.002 | L116: =K116 -> 0.002 | M116: =L116 -> 0.002 | N116: =M116 -> 0.002 | O116: =N116 -> 0.002
B120: SI 고정비성 경비 | R120: 가정 | T120: 확정 | U120: 비고
B121: =Des!$C$13 -> KRW Millions | C121: ='Pro forma'!C$5 -> 2010 | D121: ='Pro forma'!D$5 -> 2011 | E121: ='Pro forma'!E$5 -> 2012 | F121: ='Pro forma'!F$5 -> 2013 | G121: ='Pro forma'!G$5 -> 2014 | H121: ='Pro forma'!H$5 -> 2015/12A | I121: ='Pro forma'!I$5 -> 2015/0E | J121: ='Pro forma'!J$5 -> 2015 | ... O121: ='Pro forma'!O$5 -> 2020 | R121: 최초적용 | S121: 추세 및 인터뷰 등 | T121: 적용사항
B122: SI 고정비성 경비 | C122: =C127+C131+C135+C139+C143+C147+C151+C155+C159+C163+C167+C171+C175+C179+C183+C187 -> 520.1357 | D122: =D127+D131+D135+D139+D143+D147+D151+D155+D159+D163+D167+D171+D175+D179+D183+D187 -> 671.9907 | E122: =E127+E131+E135+E139+E143+E147+E151+E155+E159+E163+E167+E171+E175+E179+E183+E187 -> 789.21643 | F122: =F127+F131+F135+F139+F143+F147+F151+F155+F159+F163+F167+F171+F175+F179+F183+F187 -> 943.34294 | G122: =G127+G131+G135+G139+G143+G147+G151+G155+G159+G163+G167+G171+G175+G179+G183+G187 -> 1037.3805 | H122: =H127+H131+H135+H139+H143+H147+H151+H155+H159+H163+H167+H171+H175+H179+H183+H187 -> 1099.347 | J122: =J127+J131+J135+J139+J143+J147+J151+J155+J159+J163+J167+J171+J175+J179+J183+J187 -> 1099.347 | K122: =K127+K131+K135+K139+K143+K147+K151+K155+K159+K163+K167+K171+K175+K179+K183+K187 -> 1113.6385 | L122: =L127+L131+L135+L139+L143+L147+L151+L155+L159+L163+L167+L171+L175+L179+L183+L187 -> 1130.3431 | M122: =M127+M131+M135+M139+M143+M147+M151+M155+M159+M163+M167+M171+M175+M179+M183+M187 -> 1150.6892 | N122: =N127+N131+N135+N139+N143+N147+N151+N155+N159+N163+N167+N171+N175+N179+N183+N187 -> 1173.703 | O122: =O127+O131+O135+O139+O143+O147+O151+O155+O159+O163+O167+O171+O175+O179+O183+O187 -> 1199.5245
B123: % of growth | D123: =D122/C122-1 -> 0.29195266 | E123: =E122/D122-1 -> 0.17444547 | F123: =F122/E122-1 -> 0.19529055 | G123: =G122/F122-1 -> 0.099685406 | H123: =H122/G122-1 -> 0.059733632 | J123: =J122/G122-1 -> 0.059733632 | K123: =K122/J122-1 -> 0.013 | L123: =L122/K122-1 -> 0.015 | M123: =M122/L122-1 -> 0.018 | N123: =N122/M122-1 -> 0.02 | O123: =O122/N122-1 -> 0.022
B124: % of SI 매출액 | D124: =D122/D$63 -> 0.02122732 | E124: =E122/E$63 -> 0.014979149 | F124: =F122/F$63 -> 0.015658384 | G124: =G122/G$63 -> 0.011402269 | H124: =H122/H$63 -> 0.014424462 | J124: =J122/J$63 -> 0.014424462 | K124: =K122/K$63 -> 0.01155559 | L124: =L122/L$63 -> 0.011444323 | M124: =M122/M$63 -> 0.011274055 | N124: =N122/N$63 -> 0.011143444 | O124: =O122/O$63 -> 0.011040226
B125: % of SI COGS | D125: =D122/D$6 -> 0.006317513 | E125: =E122/E$6 -> 0.0047646213 | F125: =F122/F$6 -> 0.0048618609 | G125: =G122/G$6 -> 0.0044392831 | H125: =H122/H$6 -> 0.0056836293 | J125: =J122/J$6 -> 0.0056830457 | K125: =K122/K$6 -> 0.0049454289 | L125: =L122/L$6 -> 0.0048484771 | M125: =M122/M$6 -> 0.0047651918 | N125: =N122/N$6 -> 0.0046909158 | O125: =O122/O$6 -> 0.0046229317
B127: 임차료 | C127: =원가명세서!K19/1000000 -> 8.635 | D127: =원가명세서!L19/1000000 -> 31.13245 | E127: =원가명세서!M19/1000000 -> 69.358 | F127: =원가명세서!N19/1000000 -> 74.260741 | G127: =원가명세서!O19/1000000 -> 104.85935 | H127: =원가명세서!P19/1000000 -> 178.06021 | J127: =H127+I127 -> 178.06021 | K127: =J127*(1+K$57) -> 180.37499 | L127: =K127*(1+L$57) -> 183.08062 | M127: =L127*(1+M$57) -> 186.37607 | N127: =M127*(1+N$57) -> 190.10359 | O127: =N127*(1+O$57) -> 194.28587 | R127: 고정비 | S127: 프로젝트 Site 숙소 임차; 매출비례 X | T127: 고정비
B128: % of growth | D128: =D127/C127-1 -> 2.6053793 | E128: =E127/D127-1 -> 1.2278362 | F128: =F127/E127-1 -> 0.070687462 | G128: =G127/F127-1 -> 0.41204293 | H128: =H127/G127-1 -> 0.6980861 | J128: =J127/G127-1 -> 0.6980861 | K128: =K127/J127-1 -> 0.013 | L128: =L127/K127-1 -> 0.015 | M128: =M127/L127-1 -> 0.018 | N128: =N127/M127-1 -> 0.02 | O128: =O127/N127-1 -> 0.022
B129: % of sales | D129: =D127/D$63 -> 0.00098343396 | E129: =E127/E$63 -> 0.0013163991 | F129: =F127/F$63 -> 0.001232641 | G129: =G127/G$63 -> 0.0011525516 | H129: =H127/H$63 -> 0.0023363168 | J129: =J127/J$63 -> 0.0023363168 | K129: =K127/K$63 -> 0.0018716482 | L129: =L127/L$63 -> 0.0018536264 | M129: =M127/M$63 -> 0.0018260483 | N129: =N127/N$63 -> 0.0018048934 | O129: =O127/O$63 -> 0.0017881752
B130: % of SI COGS | C130: =C127/C$13 -> 0.00029270399 | D130: =D127/D$13 -> 0.0010555597 | E130: =E127/E$13 -> 0.0014148715 | F130: =F127/F$13 -> 0.0013205635 | G130: =G127/G$13 -> 0.0012104755 | H130: =H127/H$13 -> 0.0024737806 | J130: =J127/J$13 -> 0.0024737806 | K130: =K127/K$13 -> 0.0020483452 | L130: =L127/L$13 -> 0.002024954 | M130: =M127/M$13 -> 0.0019936974 | N130: =N127/N$13 -> 0.0019686188 | O130: =O127/O$13 -> 0.001947805
B131: 접대비 | C131: =원가명세서!K20/1000000 -> 4.00554 | D131: =원가명세서!L20/1000000 -> 24.91095 | E131: =원가명세서!M20/1000000 -> 94.36149 | F131: =원가명세서!N20/1000000 -> 70.25195 | G131: =원가명세서!O20/1000000 -> 34.55703 | H131: =원가명세서!P20/1000000 -> 7.591824 | J131: =H131+I131 -> 7.591824 | K131: =J131*(1+K$57) -> 7.6905177 | L131: =K131*(1+L$57) -> 7.8058755 | M131: =L131*(1+M$57) -> 7.9463812 | N131: =M131*(1+N$57) -> 8.1053089 | O131: =N131*(1+O$57) -> 8.2836257 | R131: 고정비 | S131: 매출연동 접대성격으로 보기 어려움 | T131: 고정비
B132: % of growth | D132: =D131/C131-1 -> 5.219124 | E132: =E131/D131-1 -> 2.7879523 | F132: =F131/E131-1 -> -0.2555019 | G132: =G131/F131-1 -> -0.50809864 | H132: =H131/G131-1 -> -0.78031029 | J132: =J131/G131-1 -> -0.78031029 | K132: =K131/J131-1 -> 0.013 | L132: =L131/K131-1 -> 0.015 | M132: =M131/L131-1 -> 0.018 | N132: =N131/M131-1 -> 0.02 | O132: =O131/N131-1 -> 0.022
B133: % of sales | D133: =D131/D$63 -> 0.0007869048 | E133: =E131/E$63 -> 0.0017909597 | F133: =F131/F$63 -> 0.0011660998 | G133: =G131/G$63 -> 0.00037983031 | H133: =H131/H$63 -> 9.9611845e-05 | J133: =J131/J$63 -> 9.9611845e-05 | K133: =K131/K$63 -> 7.9800106e-05 | L133: =L131/L$63 -> 7.9031725e-05 | M133: =M131/M$63 -> 7.7855897e-05 | N133: =N131/N$63 -> 7.6953929e-05 | O133: =O131/O$63 -> 7.6241128e-05
B134: % of SI COGS | C134: =C131/C$13 -> 0.00013577737 | D134: =D131/D$13 -> 0.00084461697 | E134: =E131/E$13 -> 0.0019249313 | F134: =F131/F$13 -> 0.001249276 | G134: =G131/G$13 -> 0.00039891948 | H134: =H131/H$13 -> 0.00010547279 | J134: =J131/J$13 -> 0.00010547279 | K134: =K131/K$13 -> 8.7333809e-05 | L134: =L131/L$13 -> 8.6336495e-05 | M134: =M131/M$13 -> 8.5003831e-05 | N134: =N131/N$13 -> 8.3934572e-05 | O134: =O131/O$13 -> 8.3047148e-05
...

Sheet SG&A
B1: ="Project"&" "&Title!L6 -> Project IT | O1: =Des!C12 -> DRAFT - For Discussion Purposes Only
B2: 판매비와관리비
B4: 판매비와관리비
B5: =unit -> KRW Millions | C5: ='Pro forma'!C$5 -> 2010 | D5: ='Pro forma'!D$5 -> 2011 | E5: ='Pro forma'!E$5 -> 2012 | F5: ='Pro forma'!F$5 -> 2013 | G5: ='Pro forma'!G$5 -> 2014 | H5: ='Pro forma'!H$5 -> 2015/12A | I5: ='Pro forma'!I$5 -> 2015/0E | J5: ='Pro forma'!J$5 -> 2015 | ... O5: ='Pro forma'!O$5 -> 2020
B6: 판매비와관리비 | C6: =C10+C14+C18+C22 -> 8937.6962 | D6: =D10+D14+D18+D22 -> 7198.3637 | E6: =E10+E14+E18+E22 -> 7996.3669 | F6: =F10+F14+F18+F22 -> 8441.2134 | G6: =G10+G14+G18+G22 -> 8664.1025 | H6: =H10+H14+H18+H22 -> 11711.818 | I6: =I10+I14+I18+I22 -> 44.614312 | J6: =J10+J14+J18+J22 -> 11722.521 | ... O6: =O10+O14+O18+O22 -> 13753.785
B7: % of growth | C7: n.a. | D7: =D6/C6-1 -> -0.19460636 | F7: =F6/E6-1 -> 0.055631083 | G7: =G6/F6-1 -> 0.026404859 | H7: n.a. | I7: n.a. | J7: =J6/G6-1 -> 0.35299886 | K7: =K6/J6-1 -> -0.00013617951 | L7: =L6/K6-1 -> 0.045610557 | M7: =M6/L6-1 -> 0.039897093 | N7: =N6/M6-1 -> 0.034727172 | O7: =O6/N6-1 -> 0.042975693
B8: % of sales | C8: =C6/C$34 -> 0.088314688 | D8: =D6/D$34 -> 0.059940936 | E8: =E6/E$34 -> 0.043868768 | F8: =F6/F$34 -> 0.039876602 | G8: =G6/G$34 -> 0.034407199 | H8: =H6/H$34 -> 0.054501933 | I8: =I6/I$34 -> #DIV/0! | J8: =J6/J$34 -> 0.054551739 | ... O8: =O6/O$34 -> 0.048314918
B10: 변동비성 경비 | C10: =C42 -> 143.95466 | D10: =D42 -> 279.43271 | E10: =E42 -> 765.96359 | F10: =F42 -> 714.09608 | G10: =G42 -> 958.52658 | H10: =H42 -> 2974.8705 | I10: =I42 -> 0 | J10: =J42 -> 2974.8705 | ... O10: =O42 -> 1060.2124
B11: % of growth | D11: =D10/C10-1 -> 0.94111615 | E11: =E10/D10-1 -> 1.7411379 | F11: =F10/E10-1 -> -0.06771537 | G11: =G10/F10-1 -> 0.34229357 | H11: n.a. | I11: n.a. | J11: =J10/G10-1 -> 2.1035868 | K11: =K10/J10-1 -> -0.68994726 | L11: =L10/K10-1 -> 0.034581504 | M11: =M10/L10-1 -> 0.035505009 | N11: =N10/M10-1 -> 0.035472419 | O11: =O10/N10-1 -> 0.036176613
B12: % of sales | C12: =C10/C$34 -> 0.0014224371 | D12: =D10/D$34 -> 0.0023268424 | E12: =E10/E$34 -> 0.0042021432 | F12: =F10/F$34 -> 0.0033734161 | G12: =G10/G$34 -> 0.0038065356 | H12: =H10/H$34 -> 0.013843811 | I12: =I10/I$34 -> #DIV/0! | J12: =J10/J$34 -> 0.013843811 | ... O12: =O10/O$34 -> 0.003724362
B14: 인건비성 경비 | C14: =노무비!C53 -> 6344.9109 | D14: =노무비!D53 -> 4899.5275 | E14: =노무비!E53 -> 5478.0373 | F14: =노무비!F53 -> 5596.7852 | G14: =노무비!G53 -> 5560.1474 | H14: =노무비!H53 -> 6451.2332 | I14: =노무비!I53 -> 0 | J14: =노무비!J53 -> 6451.2332 | ... O14: =노무비!O53 -> 9854.9307
B15: % of growth | D15: =D14/C14-1 -> -0.227802 | E15: =E14/D14-1 -> 0.11807462 | F15: =F14/E14-1 -> 0.021677092 | G15: =G14/F14-1 -> -0.0065462367 | H15: n.a. | I15: n.a. | J15: =J14/G14-1 -> 0.16026299 | K15: =K14/J14-1 -> 0.29581069 | L15: =L14/K14-1 -> 0.042 | M15: =M14/L14-1 -> 0.04 | N15: =N14/M14-1 -> 0.042 | O15: =O14/N14-1 -> 0.044
B16: % of sales | C16: =C14/C$34 -> 0.062694996 | D16: =D14/D$34 -> 0.040798475 | E16: =E14/E$34 -> 0.030052992 | F16: =F14/F$34 -> 0.026439419 | G16: =G14/G$34 -> 0.022080659 | H16: =H14/H$34 -> 0.030021358 | I16: =I14/I$34 -> #DIV/0! | J16: =J14/J$34 -> 0.030021358 | ... O16: =O14/O$34 -> 0.034618846
B18: 고정비성 경비 | C18: =C55 -> 1838.1416 | D18: =D55 -> 1476.8578 | E18: =E55 -> 1396.3467 | F18: =F55 -> 1647.6908 | G18: =G55 -> 1658.9767 | H18: =H55 -> 1770.0961 | I18: =I55 -> 0 | J18: =J55 -> 1770.0961 | ... O18: =O55 -> 1931.3954
B19: % of growth | D19: =D18/C18-1 -> -0.19654842 | E19: =E18/D18-1 -> -0.054515147 | F19: =F18/E18-1 -> 0.18000122 | G19: =G18/F18-1 -> 0.0068495547 | H19: n.a. | I19: n.a. | J19: =J18/G18-1 -> 0.06698071 | K19: =K18/J18-1 -> 0.013 | L19: =L18/K18-1 -> 0.015 | M19: =M18/L18-1 -> 0.018 | N19: =N18/M18-1 -> 0.02 | O19: =O18/N18-1 -> 0.022
B20: % of sales | C20: =C18/C$34 -> 0.018162947 | D20: =D18/D$34 -> 0.012297828 | E20: =E18/E$34 -> 0.0076604799 | F20: =F18/F$34 -> 0.0077837516 | G20: =G18/G$34 -> 0.0065881887 | H20: =H18/H$34 -> 0.0082372917 | I20: =I18/I$34 -> #DIV/0! | J20: =J18/J$34 -> 0.0082372917 | ... O20: =O18/O$34 -> 0.0067846931
B22: 유무형 상각비 | C22: =C110 -> 610.68905 | D22: =D110 -> 542.54574 | E22: =E110 -> 356.01931 | F22: =F110 -> 482.64134 | G22: =G110 -> 486.45183 | H22: =H110 -> 515.61839 | I22: =I110 -> 44.614312 | J22: =J110 -> 526.32098 | ... O22: =O110 -> 907.24648
B23: % of growth | D23: =D22/C22-1 -> -0.1115843 | E23: =E22/D22-1 -> -0.34379854 | F23: =F22/E22-1 -> 0.35566059 | G23: =G22/F22-1 -> 0.0078950717 | H23: n.a. | I23: n.a. | J23: =J22/G22-1 -> 0.081959094 | K23: =K22/J22-1 -> 0.22714723 | L23: =L22/K22-1 -> 0.19307535 | M23: =M22/L22-1 -> 0.095891102 | N23: =N22/M22-1 -> -0.011853413 | O23: =O22/N22-1 -> 0.087229648
B24: % of sales | C24: =C22/C$34 -> 0.0060343082 | D24: =D22/D$34 -> 0.0045177906 | E24: =E22/E$34 -> 0.0019531531 | F24: =F22/F$34 -> 0.0022800154 | G24: =G22/G$34 -> 0.0019318152 | H24: =H22/H$34 -> 0.0023994737 | I24: =I22/I$34 -> #DIV/0! | J24: =J22/J$34 -> 0.0024492791 | ... O24: =O22/O$34 -> 0.0031870165
C26: =C6-IS!J19 -> 0 | D26: =D6-IS!K19 -> 0 | E26: =E6-IS!L19 -> 0 | F26: =F6-IS!M19 -> 0 | G26: =G6-IS!N19 -> 0 | H26: =H6-IS!O19 -> 0
B27: Macro Variables
C28: ='Pro forma'!C5 -> 2010 | D28: ='Pro forma'!D5 -> 2011 | E28: ='Pro forma'!E5 -> 2012 | F28: ='Pro forma'!F5 -> 2013 | G28: ='Pro forma'!G5 -> 2014 | H28: ='Pro forma'!H5 -> 2015/12A | I28: ='Pro forma'!I5 -> 2015/0E | J28: ='Pro forma'!J5 -> 2015 | ... O28: ='Pro forma'!O5 -> 2020
B29: Consumer prices (%) | C29: =Macro!H87/100 -> 0.02938 | D29: =Macro!I87/100 -> 0.04025 | E29: =Macro!J87/100 -> 0.02183 | F29: =Macro!K87/100 -> 0.01301 | G29: =Macro!L87/100 -> 0.01275 | J29: =Macro!M87/100 -> 0.006 | K29: =Macro!N87/100 -> 0.013 | L29: =Macro!O87/100 -> 0.015 | M29: =Macro!P87/100 -> 0.018 | N29: =Macro!Q87/100 -> 0.02 | O29: =Macro!R87/100 -> 0.022
B30: Growth in average wages | C30: =Macro!H90/100 -> 0.06844 | D30: =Macro!I90/100 -> 0.00923 | E30: =Macro!J90/100 -> 0.05371 | F30: =Macro!K90/100 -> 0.03856 | G30: =Macro!L90/100 -> 0.02554 | J30: =Macro!M90/100 -> 0.042 | K30: =Macro!N90/100 -> 0.043 | L30: =Macro!O90/100 -> 0.042 | M30: =Macro!P90/100 -> 0.04 | N30: =Macro!Q90/100 -> 0.042 | O30: =Macro!R90/100 -> 0.044
B32: Major Variables
C33: ='Pro forma'!C5 -> 2010 | D33: ='Pro forma'!D5 -> 2011 | E33: ='Pro forma'!E5 -> 2012 | F33: ='Pro forma'!F5 -> 2013 | G33: ='Pro forma'!G5 -> 2014 | H33: ='Pro forma'!H5 -> 2015/12A | I33: ='Pro forma'!I5 -> 2015/0E | J33: ='Pro forma'!J5 -> 2015 | ... O33: ='Pro forma'!O5 -> 2020
B34: 매출액 | C34: =매출액!C6 -> 101202.83 | D34: =매출액!D6 -> 120090.95 | E34: =매출액!E6 -> 182279.27 | F34: =매출액!F6 -> 211683.37 | G34: =매출액!G6 -> 251810.75 | H34: =매출액!H6 -> 214888.12 | I34: =매출액!I6 -> 0 | J34: =매출액!J6 -> 214888.12 | ... O34: =매출액!O6 -> 284669.53
B35: 상품매출 | C35: =매출액!C9 -> 28667.765 | D35: =매출액!D9 -> 33818.96 | E35: =매출액!E9 -> 72895.968 | F35: =매출액!F9 -> 71774.78 | G35: =매출액!G9 -> 69236.769 | H35: =매출액!H9 -> 43311.995 | I35: =매출액!I9 -> 0 | J35: =매출액!J9 -> 43311.995 | ... O35: =매출액!O9 -> 60235.145
B36: 용역매출 | C36: =매출액!C13 -> 32345.633 | D36: =매출액!D13 -> 31656.879 | E36: =매출액!E13 -> 52687.669 | F36: =매출액!F13 -> 60245.229 | G36: =매출액!G13 -> 90980.18 | H36: =매출액!H13 -> 76214.068 | I36: =매출액!I13 -> 0 | J36: =매출액!J13 -> 76214.068 | ... O36: =매출액!O13 -> 108650.36
B37: 용역수수료매출 | C37: =매출액!C17 -> 40189.43 | D37: =매출액!D17 -> 54615.106 | E37: =매출액!E17 -> 56695.63 | F37: =매출액!F17 -> 79663.359 | G37: =매출액!G17 -> 91593.798 | H37: =매출액!H17 -> 95362.06 | I37: =매출액!I17 -> 0 | J37: =매출액!J17 -> 95362.06 | ... O37: =매출액!O17 -> 115784.03
B40: 변동비성 경비 | R40: 가정 | T40: 확정 | U40: 비고
B41: =unit -> KRW Millions | C41: ='Pro forma'!C$5 -> 2010 | D41: ='Pro forma'!D$5 -> 2011 | E41: ='Pro forma'!E$5 -> 2012 | F41: ='Pro forma'!F$5 -> 2013 | G41: ='Pro forma'!G$5 -> 2014 | H41: ='Pro forma'!H$5 -> 2015/12A | I41: ='Pro forma'!I$5 -> 2015/0E | J41: ='Pro forma'!J$5 -> 2015 | ... O41: ='Pro forma'!O$5 -> 2020 | R41: 최초적용 | S41: 추세 및 인터뷰 등 | T41: 적용사항
B42: 변동비성 경비 | C42: =C46+C48 -> 143.95466 | D42: =D46+D48 -> 279.43271 | E42: =E46+E48 -> 765.96359 | F42: =F46+F48 -> 714.09608 | G42: =G46+G48 -> 958.52658 | H42: =H46+H48 -> 2974.8705 | I42: =I46+I48 -> 0 | J42: =J46+J48 -> 2974.8705 | ... O42: =O46+O48 -> 1060.2124
B43: % of growth | D43: =D42/C42-1 -> 0.94111615 | E43: =E42/D42-1 -> 1.7411379 | F43: =F42/E42-1 -> -0.06771537 | G43: =G42/F42-1 -> 0.34229357 | H43: n.a. | I43: n.a. | J43: =J42/G42-1 -> 2.1035868 | K43: =K42/J42-1 -> -0.68994726 | L43: =L42/K42-1 -> 0.034581504 | M43: =M42/L42-1 -> 0.035505009 | N43: =N42/M42-1 -> 0.035472419 | O43: =O42/N42-1 -> 0.036176613
B44: % of sales | C44: =C42/C$34 -> 0.0014224371 | D44: =D42/D$34 -> 0.0023268424 | E44: =E42/E$34 -> 0.0042021432 | F44: =F42/F$34 -> 0.0033734161 | G44: =G42/G$34 -> 0.0038065356 | H44: =H42/H$34 -> 0.013843811 | I44: =I42/I$34 -> #DIV/0! | J44: =J42/J$34 -> 0.013843811 | ... O44: =O42/O$34 -> 0.003724362
B46: 광고선전비 | C46: =IS!J29 -> 65.597645 | D46: =IS!K29 -> 257.3843 | E46: =IS!L29 -> 371.55853 | F46: =IS!M29 -> 454.3607 | G46: =IS!N29 -> 509.71276 | H46: =IS!O29 -> 437.297 | J46: =H46+I46 -> 437.297 | K46: =K34*K$47 -> 495.3153 | L46: =L34*L$47 -> 512.44405 | M46: =M34*M$47 -> 530.63838 | N46: =N34*N$47 -> 549.46141 | O46: =O34*O$47 -> 569.33906 | R46: 변동비 | S46: 매출의 0.2% | T46: 변동비
B47: % of 매출액 | C47: =C46/C$34 -> 0.00064817996 | D47: =D46/D$34 -> 0.0021432449 | E47: =E46/E$34 -> 0.0020384026 | F47: =F46/F$34 -> 0.0021464166 | G47: =G46/G$34 -> 0.0020241898 | H47: =H46/H$34 -> 0.0020349985 | I47: =I46/I$34 -> #DIV/0! | J47: =J46/J$34 -> 0.0020349985 | K47: 0.002 | L47: =K47 -> 0.002 | M47: =L47 -> 0.002 | N47: =M47 -> 0.002 | O47: =N47 -> 0.002
B48: 대손상각비 | C48: =IS!J30 -> 78.357011 | D48: =IS!K30 -> 22.048408 | E48: =IS!L30 -> 394.40506 | F48: =IS!M30 -> 259.73538 | G48: =IS!N30 -> 448.81382 | H48: =IS!O30 -> 2537.5735 | J48: =H48+I48 -> 2537.5735 | K48: =K34*K$49 -> 427.05143 | L48: =L34*L$49 -> 441.81951 | M48: =M34*M$49 -> 457.50632 | N48: =N34*N$49 -> 473.73517 | O48: =O34*O$49 -> 490.87331 | R48: 변동비 | U48: 2015년 무안태양광 24억 대손설정
B49: % of 매출액 | C49: =C48/C$34 -> 0.00077425713 | D49: =D48/D$34 -> 0.00018359759 | E49: =E48/E$34 -> 0.0021637406 | F49: =F48/F$34 -> 0.0012269994 | G49: =G48/G$34 -> 0.0017823458 | H49: =H48/H$34 -> 0.011808812 | I49: =I48/I$34 -> #DIV/0! | J49: =J48/J$34 -> 0.011808812 | K49: =AVERAGE(E49:G49) -> 0.001724362 | L49: =K49 -> 0.001724362 | M49: =L49 -> 0.001724362 | N49: =M49 -> 0.001724362 | O49: =N49 -> 0.001724362
B53: 고정비성 경비 | R53: 가정 | T53: 확정 | U53: 비고
B54: =unit -> KRW Millions | C54: ='Pro forma'!C$5 -> 2010 | D54: ='Pro forma'!D$5 -> 2011 | E54: ='Pro forma'!E$5 -> 2012 | F54: ='Pro forma'!F$5 -> 2013 | G54: ='Pro forma'!G$5 -> 2014 | H54: ='Pro forma'!H$5 -> 2015/12A | I54: ='Pro forma'!I$5 -> 2015/0E | J54: ='Pro forma'!J$5 -> 2015 | ... O54: ='Pro forma'!O$5 -> 2020 | R54: 최초적용 | S54: 추세 및 인터뷰 등 | T54: 적용사항
B55: 고정비성 경비 | C55: =C59+C62+C68+C71+C74+C77+C80+C83+C86+C89+C94+C97+C100+C103 -> 1838.1416 | D55: =D59+D62+D68+D71+D74+D77+D80+D83+D86+D89+D94+D97+D100+D103 -> 1476.8578 | E55: =E59+E62+E68+E71+E74+E77+E80+E83+E86+E89+E94+E97+E100+E103 -> 1396.3467 | F55: =F59+F62+F68+F71+F74+F77+F80+F83+F86+F89+F94+F97+F100+F103 -> 1647.6908 | G55: =G59+G62+G68+G71+G74+G77+G80+G83+G86+G89+G94+G97+G100+G103 -> 1658.9767 | H55: =H59+H62+H68+H71+H74+H77+H80+H83+H86+H89+H94+H97+H100+H103 -> 1770.0961 | I55: =I59+I62+I68+I71+I74+I77+I80+I83+I86+I89+I94+I97+I100+I103 -> 0 | J55: =J59+J62+J68+J71+J74+J77+J80+J83+J86+J89+J94+J97+J100+J103 -> 1770.0961 | ... O55: =O59+O62+O68+O71+O74+O77+O80+O83+O86+O89+O94+O97+O100+O103 -> 1931.3954
B56: % of growth | D56: =D55/C55-1 -> -0.19654842 | E56: =E55/D55-1 -> -0.054515147 | F56: =F55/E55-1 -> 0.18000122 | G56: =G55/F55-1 -> 0.0068495547 | J56: =J55/G55-1 -> 0.06698071 | K56: =K55/J55-1 -> 0.013 | L56: =L55/K55-1 -> 0.015 | M56: =M55/L55-1 -> 0.018 | N56: =N55/M55-1 -> 0.02 | O56: =O55/N55-1 -> 0.022
B57: % of sales | C57: =C55/C$34 -> 0.018162947 | D57: =D55/D$34 -> 0.012297828 | E57: =E55/E$34 -> 0.0076604799 | F57: =F55/F$34 -> 0.0077837516 | G57: =G55/G$34 -> 0.0065881887 | H57: =H55/H$34 -> 0.0082372917 | I57: =I55/I$34 -> #DIV/0! | J57: =J55/J$34 -> 0.0082372917 | ... O57: =O55/O$34 -> 0.0067846931
B59: 임차료 | C59: =IS!J25 -> 550.74759 | D59: =IS!K25 -> 571.45627 | E59: =IS!L25 -> 598.6898 | F59: =IS!M25 -> 692.17782 | G59: =IS!N25 -> 677.70822 | H59: =IS!O25 -> 672.10346 | J59: =H59+I59 -> 672.10346 | K59: =J59*(1+K$29) -> 680.84081 | L59: =K59*(1+L$29) -> 691.05342 | M59: =L59*(1+M$29) -> 703.49238 | N59: =M59*(1+N$29) -> 717.56223 | O59: =N59*(1+O$29) -> 733.3486 | R59: 고정비 | S59: 울산영업소, 동일빌딩 14년 철수로 15년 값이 가장 근접할 것으로 예상됨 | T59: 고정비
B60: % of growth | D60: =D59/C59-1 -> 0.037601042 | E60: =E59/D59-1 -> 0.047656362 | F60: =F59/E59-1 -> 0.15615435 | G60: =G59/F59-1 -> -0.020904446 | J60: =J59/G59-1 -> -0.0082701667 | K60: =K59/J59-1 -> 0.013 | L60: =L59/K59-1 -> 0.015 | M60: =M59/L59-1 -> 0.018 | N60: =N59/M59-1 -> 0.02 | O60: =O59/N59-1 -> 0.022
B61: % of sales | C61: =C59/C$34 -> 0.0054420178 | D61: =D59/D$34 -> 0.0047585292 | E61: =E59/E$34 -> 0.0032844646 | F61: =F59/F$34 -> 0.0032698734 | G61: =G59/G$34 -> 0.0026913396 | H61: =H59/H$34 -> 0.0031276901 | I61: =I59/I$34 -> #DIV/0! | J61: =J59/J$34 -> 0.0031276901 | ... O61: =O59/O$34 -> 0.0025761401
B62: 접대비 | C62: =IS!J26 -> 73.78339 | D62: =IS!K26 -> 76.838882 | E62: =IS!L26 -> 42.847974 | F62: =IS!M26 -> 65.240137 | G62: =IS!N26 -> 70.333851 | H62: =IS!O26 -> 71.079569 | J62: =H62+I62 -> 71.079569 | K62: =J62*(1+K$29) -> 72.003603 | L62: =K62*(1+L$29) -> 73.083657 | M62: =L62*(1+M$29) -> 74.399163 | N62: =M62*(1+N$29) -> 75.887147 | O62: =N62*(1+O$29) -> 77.556664 | R62: 고정비 | S62: 매출연동 접대성격으로 보기 어려움 | T62: 고정비
B63: % of growth | D63: =D62/C62-1 -> 0.041411651 | E63: =E62/D62-1 -> -0.44236599 | F63: =F62/E62-1 -> 0.52259561 | G63: =G62/F62-1 -> 0.078076384 | J63: =J62/G62-1 -> 0.010602548 | K63: =K62/J62-1 -> 0.013 | L63: =L62/K62-1 -> 0.015 | M63: =M62/L62-1 -> 0.018 | N63: =N62/M62-1 -> 0.02 | O63: =O62/N62-1 -> 0.022
B64: % of sales | C64: =C62/C$34 -> 0.00072906451 | D64: =D62/D$34 -> 0.0006398391 | E64: =E62/E$34 -> 0.00023506773 | F64: =F62/F$34 -> 0.0003081968 | G64: =G62/G$34 -> 0.00027931235 | H64: =H62/H$34 -> 0.00033077477 | I64: =I62/I$34 -> #DIV/0! | J64: =J62/J$34 -> 0.00033077477 | ... O64: =O62/O$34 -> 0.00027244456
B65: 세금과공과 | R65: 고정비 | S65: 4대보험 회사부담분 | T65: 노무비 연계
B66: % of growth | D66: =D65/C65-1 -> #DIV/0! | E66: =E65/D65-1 -> #DIV/0! | F66: =F65/E65-1 -> #DIV/0! | G66: =G65/F65-1 -> #DIV/0! | J66: =J65/G65-1 -> #DIV/0! | K66: =K65/J65-1 -> #DIV/0! | L66: =L65/K65-1 -> #DIV/0! | M66: =M65/L65-1 -> #DIV/0! | N66: =N65/M65-1 -> #DIV/0! | O66: =O65/N65-1 -> #DIV/0!
B67: % of 인건비성경비 | C67: =C65/노무비!C$152 -> 0 | D67: =D65/노무비!D$152 -> 0 | E67: =E65/노무비!E$152 -> 0 | F67: =F65/노무비!F$152 -> 0 | G67: =G65/노무비!G$152 -> 0 | H67: =H65/노무비!H$152 -> 0 | I67: =I65/노무비!I$152 -> #DIV/0! | J67: =J65/노무비!J$152 -> 0 | ... O67: =O65/노무비!O$152 -> 0
B68: 차량유지비 | C68: =IS!J31 -> 41.243308 | D68: =IS!K31 -> 66.029359 | E68: =IS!L31 -> 101.43927 | F68: =IS!M31 -> 122.52879 | G68: =IS!N31 -> 113.1702 | H68: =IS!O31 -> 124.76102 | J68: =H68+I68 -> 124.76102 | K68: =J68*(1+K$29) -> 126.38291 | L68: =K68*(1+L$29) -> 128.27865 | M68: =L68*(1+M$29) -> 130.58767 | N68: =M68*(1+N$29) -> 133.19942 | O68: =N68*(1+O$29) -> 136.12981 | R68: 고정비 | S68: 차량 관련 활동은 현상태 유지 | T68: 고정비
B69: % of growth | D69: =D68/C68-1 -> 0.60097146 | E69: =E68/D68-1 -> 0.53627528 | F69: =F68/E68-1 -> 0.20790287 | G69: =G68/F68-1 -> -0.076378647 | J69: =J68/G68-1 -> 0.10241929 | K69: =K68/J68-1 -> 0.013 | L69: =L68/K68-1 -> 0.015 | M69: =M68/L68-1 -> 0.018 | N69: =N68/M68-1 -> 0.02 | O69: =O68/N68-1 -> 0.022
B70: % of sales | C70: =C68/C$34 -> 0.00040753118 | D70: =D68/D$34 -> 0.00054982796 | E70: =E68/E$34 -> 0.00055650472 | F70: =F68/F$34 -> 0.00057883049 | G70: =G68/G$34 -> 0.00044942564 | H70: =H68/H$34 -> 0.00058058591 | I70: =I68/I$34 -> #DIV/0! | J70: =J68/J$34 -> 0.00058058591 | ... O70: =O68/O$34 -> 0.00047820295
B71: 교육훈련비 | C71: =IS!J32 -> 264.57651 | D71: =IS!K32 -> 294.69729 | E71: =IS!L32 -> 148.49386 | F71: =IS!M32 -> 157.74476 | G71: =IS!N32 -> 83.142655 | H71: =IS!O32 -> 52.484068 | J71: =H71+I71 -> 52.484068 | K71: =J71*(1+K$29) -> 53.166361 | L71: =K71*(1+L$29) -> 53.963856 | M71: =L71*(1+M$29) -> 54.935206 | N71: =M71*(1+N$29) -> 56.03391 | O71: =N71*(1+O$29) -> 57.266656 | R71: 고정비 | S71: 15년 규모 축소지만 향후 적정수준 유지 전망됨 | T71: 고정비
B72: % of growth | D72: =D71/C71-1 -> 0.11384526 | E72: =E71/D71-1 -> -0.49611392 | F72: =F71/E71-1 -> 0.062298198 | G72: =G71/F71-1 -> -0.47292922 | J72: =J71/G71-1 -> -0.36874679 | K72: =K71/J71-1 -> 0.013 | L72: =L71/K71-1 -> 0.015 | M72: =M71/L71-1 -> 0.018 | N72: =N71/M71-1 -> 0.02 | O72: =O71/N71-1 -> 0.022
B73: % of sales | C73: =C71/C$34 -> 0.0026143193 | D73: =D71/D$34 -> 0.0024539509 | E73: =E71/E$34 -> 0.00081465032 | F73: =F71/F$34 -> 0.00074519204 | G73: =G71/G$34 -> 0.00033017914 | H73: =H71/H$34 -> 0.00024423904 | I73: =I71/I$34 -> #DIV/0! | J73: =J71/J$34 -> 0.00024423904 | ... O73: =O71/O$34 -> 0.0002011689
B74: 여비교통비 | C74: =IS!J33 -> 101.96901 | D74: =IS!K33 -> 68.909326 | E74: =IS!L33 -> 61.012652 | F74: =IS!M33 -> 51.392932 | G74: =IS!N33 -> 68.484012 | H74: =IS!O33 -> 104.1085 | J74: =H74+I74 -> 104.1085 | K74: =J74*(1+K$29) -> 105.46191 | L74: =K74*(1+L$29) -> 107.04384 | M74: =L74*(1+M$29) -> 108.97062 | N74: =M74*(1+N$29) -> 111.15004 | O74: =N74*(1+O$29) -> 113.59534 | R74: 고정비 | S74: 항공, 택시 등 교통비 | T74: 고정비
B75: % of growth | D75: =D74/C74-1 -> -0.32421309 | E75: =E74/D74-1 -> -0.11459514 | F75: =F74/E74-1 -> -0.15766763 | G75: =G74/F74-1 -> 0.33255701 | J75: =J74/G74-1 -> 0.52018687 | K75: =K74/J74-1 -> 0.013 | L75: =L74/K74-1 -> 0.015 | M75: =M74/L74-1 -> 0.018 | N75: =N74/M74-1 -> 0.02 | O75: =O74/N74-1 -> 0.022
B76: % of sales | C76: =C74/C$34 -> 0.0010075708 | D76: =D74/D$34 -> 0.00057380951 | E76: =E74/E$34 -> 0.00033472075 | F76: =F74/F$34 -> 0.0002427821 | G76: =G74/G$34 -> 0.0002719662 | H76: =H74/H$34 -> 0.00048447766 | I76: =I74/I$34 -> #DIV/0! | J76: =J74/J$34 -> 0.00048447766 | ... O76: =O74/O$34 -> 0.00039904284
B77: 운반비 | C77: =IS!J34 -> 4.86974 | D77: =IS!K34 -> 5.27691 | E77: =IS!L34 -> 7.838358 | F77: =IS!M34 -> 6.97875 | G77: =IS!N34 -> 8.91129 | H77: =IS!O34 -> 7.48971 | J77: =H77+I77 -> 7.48971 | K77: =J77*(1+K$29) -> 7.5870762 | L77: =K77*(1+L$29) -> 7.7008824 | M77: =L77*(1+M$29) -> 7.8394983 | N77: =M77*(1+N$29) -> 7.9962882 | O77: =N77*(1+O$29) -> 8.1722066 | R77: 고정비 | S77: 택배 등 | T77: 고정비
B78: % of growth | D78: =D77/C77-1 -> 0.083612267 | E78: =E77/D77-1 -> 0.4854068 | F78: =F77/E77-1 -> -0.10966685 | G78: =G77/F77-1 -> 0.27691779 | J78: =J77/G77-1 -> -0.15952573 | K78: =K77/J77-1 -> 0.013 | L78: =L77/K77-1 -> 0.015 | M78: =M77/L77-1 -> 0.018 | N78: =N77/M77-1 -> 0.02 | O78: =O77/N77-1 -> 0.022
B79: % of sales | C79: =C77/C$34 -> 4.8118616e-05 | D79: =D77/D$34 -> 4.3940948e-05 | E79: =E77/E$34 -> 4.3001918e-05 | F79: =F77/F$34 -> 3.2967871e-05 | G79: =G77/G$34 -> 3.5388839e-05 | H79: =H77/H$34 -> 3.4853997e-05 | I79: =I77/I$34 -> #DIV/0! | J79: =J77/J$34 -> 3.4853997e-05 | ... O79: =O77/O$34 -> 2.8707697e-05
B80: 통신비 | C80: =IS!J36 -> 77.461589 | D80: =IS!K36 -> 119.2956 | E80: =IS!L36 -> 54.966967 | F80: =IS!M36 -> 40.220957 | G80: =IS!N36 -> 52.089794 | H80: =IS!O36 -> 93.845882 | J80: =H80+I80 -> 93.845882 | K80: =J80*(1+K$29) -> 95.065878 | L80: =K80*(1+L$29) -> 96.491867 | M80: =L80*(1+M$29) -> 98.22872 | N80: =M80*(1+N$29) -> 100.19329 | O80: =N80*(1+O$29) -> 102.39755 | R80: 고정비 | S80: 원가배분 아직 (2014년 ) | T80: 고정비
B81: % of growth | D81: =D80/C80-1 -> 0.54006132 | E81: =E80/D80-1 -> -0.53923725 | F81: =F80/E80-1 -> -0.2682704 | G81: =G80/F80-1 -> 0.29509087 | J81: =J80/G80-1 -> 0.80161745 | K81: =K80/J80-1 -> 0.013 | L81: =L80/K80-1 -> 0.015 | M81: =M80/L80-1 -> 0.018 | N81: =N80/M80-1 -> 0.02 | O81: =O80/N80-1 -> 0.022
B82: % of sales | C82: =C80/C$34 -> 0.00076540933 | D82: =D80/D$34 -> 0.00099337712 | E82: =E80/E$34 -> 0.00030155359 | F82: =F80/F$34 -> 0.00019000528 | G82: =G80/G$34 -> 0.00020686089 | H82: =H80/H$34 -> 0.00043671972 | I82: =I80/I$34 -> #DIV/0! | J82: =J80/J$34 -> 0.00043671972 | ... O82: =O80/O$34 -> 0.00035970673
B83: 수도광열비 | C83: =IS!J37 -> 66.57373 | D83: =IS!K37 -> 40.95318 | E83: =IS!L37 -> 2.70649 | F83: =IS!M37 -> 2.692576 | G83: =IS!N37 -> 4.7505 | H83: =IS!O37 -> 5.09476 | J83: =H83+I83 -> 5.09476 | K83: =J83*(1+K$29) -> 5.1609919 | L83: =K83*(1+L$29) -> 5.2384068 | M83: =L83*(1+M$29) -> 5.3326981 | N83: =M83*(1+N$29) -> 5.439352 | O83: =N83*(1+O$29) -> 5.5590178 | R83: 고정비 | S83: 빌딩 가스료, 전기료 | T83: 고정비
B84: % of growth | D84: =D83/C83-1 -> -0.38484474 | E84: =E83/D83-1 -> -0.93391258 | F84: =F83/E83-1 -> -0.005140976 | G84: =G83/F83-1 -> 0.7642956 | J84: =J83/G83-1 -> 0.072468161 | K84: =K83/J83-1 -> 0.013 | L84: =L83/K83-1 -> 0.015 | M84: =M83/L83-1 -> 0.018 | N84: =N83/M83-1 -> 0.02 | O84: =O83/N83-1 -> 0.022
B85: % of sales | C85: =C83/C$34 -> 0.0006578248 | D85: =D83/D$34 -> 0.00034101805 | E85: =E83/E$34 -> 1.4848041e-05 | F85: =F83/F$34 -> 1.2719828e-05 | G85: =G83/G$34 -> 1.8865358e-05 | H85: =H83/H$34 -> 2.3708895e-05 | I85: =I83/I$34 -> #DIV/0! | J85: =J83/J$34 -> 2.3708895e-05 | ... O85: =O83/O$34 -> 1.9527969e-05
B86: 소모품비 | C86: =IS!J38 -> 51.723712 | D86: =IS!K38 -> 70.063489 | E86: =IS!L38 -> 90.152744 | F86: =IS!M38 -> 112.40739 | G86: =IS!N38 -> 177.45285 | H86: =IS!O38 -> 333.77764 | J86: =H86+I86 -> 333.77764 | K86: =J86*(1+K$29) -> 338.11675 | L86: =K86*(1+L$29) -> 343.1885 | M86: =L86*(1+M$29) -> 349.36589 | N86: =M86*(1+N$29) -> 356.35321 | O86: =N86*(1+O$29) -> 364.19298 | R86: 고정비 | S86: 사무용품비 | T86: 고정비
B87: % of growth | D87: =D86/C86-1 -> 0.35457194 | E87: =E86/D86-1 -> 0.2867293 | F87: =F86/E86-1 -> 0.2468549 | G87: =G86/F86-1 -> 0.57865823 | J87: =J86/G86-1 -> 0.88093702 | K87: =K86/J86-1 -> 0.013 | L87: =L86/K86-1 -> 0.015 | M87: =M86/L86-1 -> 0.018 | N87: =N86/M86-1 -> 0.02 | O87: =O86/N86-1 -> 0.022
B88: % of sales | C88: =C86/C$34 -> 0.00051108959 | D88: =D86/D$34 -> 0.00058342025 | E88: =E86/E$34 -> 0.00049458584 | F88: =F86/F$34 -> 0.00053101664 | G88: =G86/G$34 -> 0.00070470723 | H88: =H86/H$34 -> 0.0015532624 | I88: =I86/I$34 -> #DIV/0! | J88: =J86/J$34 -> 0.0015532624 | ... O88: =O86/O$34 -> 0.0012793536
B89: 지급수수료 | C89: =IS!J40 -> 583.36496 | D89: =IS!K40 -> 139.95263 | E89: =IS!L40 -> 236.48546 | F89: =IS!M40 -> 368.81184 | G89: =IS!N40 -> 357.97965 | H89: =IS!O40 -> 253.0396 | J89: =H89+I89 -> 253.0396 | K89: =J89*(1+K$29) -> 256.32912 | L89: =K89*(1+L$29) -> 260.17405 | M89: =L89*(1+M$29) -> 264.85719 | N89: =M89*(1+N$29) -> 270.15433 | O89: =N89*(1+O$29) -> 276.09773 | R89: 고정비 | S89: 경상비용 - 업무용역비가 대부분 | T89: 고정비
B90: % of growth | D90: =D89/C89-1 -> -0.7600942 | E90: =E89/D89-1 -> 0.68975358 | F90: =F89/E89-1 -> 0.55955396 | G90: =G89/F89-1 -> -0.029370494 | J90: =J89/G89-1 -> -0.2931453 | K90: =K89/J89-1 -> 0.013 | L90: =L89/K89-1 -> 0.015 | M90: =M89/L89-1 -> 0.018 | N90: =N89/M89-1 -> 0.02 | O90: =O89/N89-1 -> 0.022
B91: % of sales | C91: =C89/C$34 -> 0.0057643148 | D91: =D89/D$34 -> 0.0011653887 | E91: =E89/E$34 -> 0.0012973799 | F91: =F89/F$34 -> 0.0017422807 | G91: =G89/G$34 -> 0.0014216218 | H91: =H89/H$34 -> 0.0011775411 | I91: =I89/I$34 -> #DIV/0! | J91: =J89/J$34 -> 0.0011775411 | ... O91: =O89/O$34 -> 0.00096988858
B92: 지급수수료 | C92: =IS!J40 -> 583.36496 | D92: =IS!K40 -> 139.95263 | E92: =IS!L40 -> 236.48546 | F92: =IS!M40 -> 368.81184 | G92: =IS!N40 -> 357.97965 | H92: =IS!O40 -> 253.0396 | J92: =H92+I92 -> 253.0396 | K92: =J92*(1+K$29) -> 256.32912 | L92: =K92*(1+L$29) -> 260.17405 | M92: =L92*(1+M$29) -> 264.85719 | N92: =M92*(1+N$29) -> 270.15433 | O92: =N92*(1+O$29) -> 276.09773
B93: 비경상적비용 | C93: 314.343 | D93: 74.666686 | E93: 90 | F93: 0 | G93: 125 | H93: 172
B94: 사무용품비 | C94: =IS!J41 -> 7.779917 | D94: =IS!K41 -> 7.439045 | E94: =IS!L41 -> 8.92603 | F94: =IS!M41 -> 7.443288 | G94: =IS!N41 -> 4.537964 | H94: =IS!O41 -> 7.234877 | J94: =H94+I94 -> 7.234877 | K94: =J94*(1+K$29) -> 7.3289304 | L94: =K94*(1+L$29) -> 7.4388644 | M94: =L94*(1+M$29) -> 7.5727639 | N94: =M94*(1+N$29) -> 7.7242192 | O94: =N94*(1+O$29) -> 7.894152
B95: % of growth | D95: =D94/C94-1 -> -0.043814349 | E95: =E94/D94-1 -> 0.19988923 | F95: =F94/E94-1 -> -0.16611439 | G95: =G94/F94-1 -> -0.39032804 | J95: =J94/G94-1 -> 0.59430022 | K95: =K94/J94-1 -> 0.013 | L95: =L94/K94-1 -> 0.015 | M95: =M94/L94-1 -> 0.018 | N95: =N94/M94-1 -> 0.02 | O95: =O94/N94-1 -> 0.022
B96: % of sales | C96: =C94/C$34 -> 7.6874502e-05 | D96: =D94/D$34 -> 6.1945095e-05 | E96: =E94/E$34 -> 4.8968981e-05 | F96: =F94/F$34 -> 3.5162366e-05 | G96: =G94/G$34 -> 1.8021328e-05 | H96: =H94/H$34 -> 3.366811e-05 | I96: =I94/I$34 -> #DIV/0! | J96: =J94/J$34 -> 3.366811e-05 | ... O96: =O94/O$34 -> 2.7730934e-05
B97: 도서인쇄비 | C97: =IS!J42 -> 12.636178 | D97: =IS!K42 -> 10.646129 | E97: =IS!L42 -> 8.566626 | F97: =IS!M42 -> 8.810588 | G97: =IS!N42 -> 9.254214 | H97: =IS!O42 -> 9.637994 | J97: =H97+I97 -> 9.637994 | K97: =J97*(1+K$29) -> 9.7632879 | L97: =K97*(1+L$29) -> 9.9097372 | M97: =L97*(1+M$29) -> 10.088113 | N97: =M97*(1+N$29) -> 10.289875 | O97: =N97*(1+O$29) -> 10.516252
B98: % of growth | D98: =D97/C97-1 -> -0.15748821 | E98: =E97/D97-1 -> -0.19532949 | F98: =F97/E97-1 -> 0.02847819 | G98: =G97/F97-1 -> 0.050351463 | J98: =J97/G97-1 -> 0.041470837 | K98: =K97/J97-1 -> 0.013 | L98: =L97/K97-1 -> 0.015 | M98: =M97/L97-1 -> 0.018 | N98: =N97/M97-1 -> 0.02 | O98: =O97/N97-1 -> 0.022
B99: % of sales | C99: =C97/C$34 -> 0.00012485993 | D99: =D97/D$34 -> 8.8650555e-05 | E99: =E97/E$34 -> 4.699726e-05 | F99: =F97/F$34 -> 4.1621541e-05 | G99: =G97/G$34 -> 3.6750671e-05 | H99: =H97/H$34 -> 4.4851218e-05 | I99: =I97/I$34 -> #DIV/0! | J99: =J97/J$34 -> 4.4851218e-05 | ... O99: =O97/O$34 -> 3.6941966e-05
B100: 판촉비 | C100: =IS!J43 -> 0 | D100: =IS!K43 -> 1.85 | E100: =IS!L43 -> 23.57898 | F100: =IS!M43 -> 5.22784 | G100: =IS!N43 -> 0 | H100: =IS!O43 -> 0 | J100: =H100+I100 -> 0 | K100: =J100*(1+K$29) -> 0 | L100: =K100*(1+L$29) -> 0 | M100: =L100*(1+M$29) -> 0 | N100: =M100*(1+N$29) -> 0 | O100: =N100*(1+O$29) -> 0
B101: % of growth | D101: =D100/C100-1 -> #DIV/0! | E101: =E100/D100-1 -> 11.745395 | F101: =F100/E100-1 -> -0.77828388 | G101: =G100/F100-1 -> -1 | J101: =J100/G100-1 -> #DIV/0! | K101: =K100/J100-1 -> #DIV/0! | L101: =L100/K100-1 -> #DIV/0! | M101: =M100/L100-1 -> #DIV/0! | N101: =N100/M100-1 -> #DIV/0! | O101: =O100/N100-1 -> #DIV/0!
B102: % of sales | C102: =C100/C$34 -> 0 | D102: =D100/D$34 -> 1.5404992e-05 | E102: =E100/E$34 -> 0.00012935635 | F102: =F100/F$34 -> 2.4696508e-05 | G102: =G100/G$34 -> 0 | H102: =H100/H$34 -> 0 | I102: =I100/I$34 -> #DIV/0! | J102: =J100/J$34 -> 0 | ... O102: =O100/O$34 -> 0
B103: 회의비 | C103: =IS!J44 -> 1.41197 | D103: =IS!K44 -> 3.44967 | E103: =IS!L44 -> 10.641443 | F103: =IS!M44 -> 6.013092 | G103: =IS!N44 -> 31.161491 | H103: =IS!O44 -> 35.439065 | J103: =H103+I103 -> 35.439065 | K103: =J103*(1+K$29) -> 35.899773 | L103: =K103*(1+L$29) -> 36.438269 | M103: =L103*(1+M$29) -> 37.094158 | N103: =M103*(1+N$29) -> 37.836041 | O103: =N103*(1+O$29) -> 38.668434
B104: % of growth | D104: =D103/C103-1 -> 1.443161 | E104: =E103/D103-1 -> 2.0847713 | F104: =F103/E103-1 -> -0.43493641 | G104: =G103/F103-1 -> 4.1822741 | J104: =J103/G103-1 -> 0.13727116 | K104: =K103/J103-1 -> 0.013 | L104: =L103/K103-1 -> 0.015 | M104: =M103/L103-1 -> 0.018 | N104: =N103/M103-1 -> 0.02 | O104: =O103/N103-1 -> 0.022
B105: % of sales | C105: =C103/C$34 -> 1.3951883e-05 | D105: =D103/D$34 -> 2.872548e-05 | E105: =E103/E$34 -> 5.8379887e-05 | F105: =F103/F$34 -> 2.8406067e-05 | G105: =G103/G$34 -> 0.00012374965 | H105: =H103/H$34 -> 0.00016491868 | I105: =I103/I$34 -> #DIV/0! | J105: =J103/J$34 -> 0.00016491868 | ... O105: =O103/O$34 -> 0.00013583623
B108: 유무형자산 상각비 | R108: 가정 | T108: 확정 | U108: 비고
B109: =unit -> KRW Millions | C109: ='Pro forma'!C$5 -> 2010 | D109: ='Pro forma'!D$5 -> 2011 | E109: ='Pro forma'!E$5 -> 2012 | F109: ='Pro forma'!F$5 -> 2013 | G109: ='Pro forma'!G$5 -> 2014 | H109: ='Pro forma'!H$5 -> 2015/12A | I109: ='Pro forma'!I$5 -> 2015/0E | J109: ='Pro forma'!J$5 -> 2015 | ... O109: ='Pro forma'!O$5 -> 2020 | R109: 최초적용 | S109: 추세 및 인터뷰 등 | T109: 적용사항
B110: 유무형자산 상각비 | C110: =C115+C119 -> 610.68905 | D110: =D115+D119 -> 542.54574 | E110: =E115+E119 -> 356.01931 | F110: =F115+F119 -> 482.64134 | G110: =G115+G119 -> 486.45183 | H110: =H115+H119 -> 515.61839 | I110: =I115+I119 -> 44.614312 | J110: =J115+J119 -> 526.32098 | ... O110: =O115+O119 -> 907.24648
B111: % of growth | D111: =D110/C110-1 -> -0.1115843 | E111: =E110/D110-1 -> -0.34379854 | F111: =F110/E110-1 -> 0.35566059 | G111: =G110/F110-1 -> 0.0078950717 | J111: =J110/G110-1 -> 0.081959094 | K111: =K110/J110-1 -> 0.22714723 | L111: =L110/K110-1 -> 0.19307535 | M111: =M110/L110-1 -> 0.095891102 | N111: =N110/M110-1 -> -0.011853413 | O111: =O110/N110-1 -> 0.087229648
B112: % of sales | C112: =C110/C$34 -> 0.0060343082 | D112: =D110/D$34 -> 0.0045177906 | E112: =E110/E$34 -> 0.0019531531 | F112: =F110/F$34 -> 0.0022800154 | G112: =G110/G$34 -> 0.0019318152 | H112: =H110/H$34 -> 0.0023994737 | I112: =I110/I$34 -> #DIV/0! | J112: =J110/J$34 -> 0.0024492791 | ... O112: =O110/O$34 -> 0.0031870165
B113: % of 총 상각비 | C113: =C110/'CapEx&Dep'!C7 -> 0.90133018 | D113: =D110/'CapEx&Dep'!D7 -> 0.90487178 | E113: =E110/'CapEx&Dep'!E7 -> 0.64151784 | F113: =F110/'CapEx&Dep'!F7 -> 0.67806514 | G113: =G110/'CapEx&Dep'!G7 -> 0.65637302 | H113: =H110/'CapEx&Dep'!H7 -> 0.7233211 | I113: =I110/'CapEx&Dep'!I7 -> 0.69191847 | J113: =J110/'CapEx&Dep'!J7 -> 0.67879003 | ... O113: =O110/'CapEx&Dep'!O7 -> 0.41620882
B115: 유형감가상각비 | C115: =IS!J27 -> 174.63043 | D115: =IS!K27 -> 271.8179 | E115: =IS!L27 -> 262.10296 | F115: =IS!M27 -> 384.81117 | G115: =IS!N27 -> 391.2159 | H115: =IS!O27 -> 456.47531 | I115: ='CapEx&Dep'!I154 -> 40.601021 | J115: ='CapEx&Dep'!J154 -> 468.22237 | K115: ='CapEx&Dep'!K154 -> 624.48187 | L115: ='CapEx&Dep'!L154 -> 744.78738 | M115: ='CapEx&Dep'!M154 -> 804.39659 | N115: ='CapEx&Dep'!N154 -> 778.77959 | O115: ='CapEx&Dep'!O154 -> 841.99685 | R115: 과거 5개년평균 판관비 배부 상각비비율
B116: 총 유형감가상각비 | C116: ='CapEx&Dep'!C53 -> 230.157 | D116: ='CapEx&Dep'!D53 -> 321.594 | E116: ='CapEx&Dep'!E53 -> 455.79 | F116: ='CapEx&Dep'!F53 -> 612.66 | G116: ='CapEx&Dep'!G53 -> 645.885 | H116: ='CapEx&Dep'!H53 -> 650.35451 | I116: ='CapEx&Dep'!I53 -> 59.795354 | J116: ='CapEx&Dep'!J53 -> 710.14986 | ... O116: ='CapEx&Dep'!O53 -> 1089.7033
B117: 판매관리비 배부율 | C117: =C115/C116 -> 0.75874483 | D117: =D115/D116 -> 0.84522067 | E117: =E115/E116 -> 0.57505202 | F117: =F115/F116 -> 0.62809906 | G117: =G115/G116 -> 0.6057052 | H117: =H115/H116 -> 0.7018869 | I117: =I115/I116 -> 0.67899959 | J117: =J115/J116 -> 0.65932896 | ... O117: =O115/O116 -> 0.77268448
...

Sheet 노무비
B1: ="Project"&" "&Title!L6 -> Project IT | O1: =Des!C12 -> DRAFT - For Discussion Purposes Only
B2: 노무비
B4: 노무비
B5: =unit -> KRW Millions | C5: ='Pro forma'!C$5 -> 2010 | D5: ='Pro forma'!D$5 -> 2011 | E5: ='Pro forma'!E$5 -> 2012 | F5: ='Pro forma'!F$5 -> 2013 | G5: ='Pro forma'!G$5 -> 2014 | H5: ='Pro forma'!H$5 -> 2015/12A | I5: ='Pro forma'!I$5 -> 2015/0E | J5: ='Pro forma'!J$5 -> 2015 | ... O5: ='Pro forma'!O$5 -> 2020
B6: 노무비 | C6: =C10+C14+C18+C22 -> 16648.581 | D6: =D10+D14+D18+D22 -> 19493.081 | E6: =E10+E14+E18+E22 -> 26547.784 | F6: =F10+F14+F18+F22 -> 30230.851 | G6: =G10+G14+G18+G22 -> 30990.735 | H6: =H10+H14+H18+H22 -> 29018.682 | J6: =J10+J14+J18+J22 -> 29018.682 | K6: =K10+K14+K18+K22 -> 37055.599 | L6: =L10+L14+L18+L22 -> 38611.934 | M6: =M10+M14+M18+M22 -> 40156.412 | N6: =N10+N14+N18+N22 -> 41842.981 | O6: =O10+O14+O18+O22 -> 43684.072
B7: % of growth | C7: n.a. | D7: =D6/C6-1 -> 0.17085536 | F7: =F6/E6-1 -> 0.13873354 | G7: =G6/F6-1 -> 0.025136032 | H7: =H6/G6-1 -> -0.063633641 | J7: =J6/G6-1 -> -0.063633641 | K7: =K6/J6-1 -> 0.27695666 | L7: =L6/K6-1 -> 0.042 | M7: =M6/L6-1 -> 0.04 | N7: =N6/M6-1 -> 0.042 | O7: =O6/N6-1 -> 0.044
B8: % of sales | C8: =C6/C$44 -> 0.16450708 | D8: =D6/D$44 -> 0.16231932 | E8: =E6/E$44 -> 0.14564346 | F8: =F6/F$44 -> 0.14281165 | G8: =G6/G$44 -> 0.12307153 | H8: =H6/H$44 -> 0.13504088 | J8: =J6/J$44 -> 0.13504088 | K8: =K6/K$44 -> 0.14962429 | L8: =L6/L$44 -> 0.15069717 | M8: =M6/M$44 -> 0.15135133 | N8: =N6/N$44 -> 0.15230544 | O8: =O6/O$44 -> 0.15345538
B10: 급여 | C10: =C80+C117+C156 -> 11266.167 | D10: =D80+D117+D156 -> 10894.268 | E10: =E80+E117+E156 -> 13195.42 | F10: =F80+F117+F156 -> 16205.225 | G10: =G80+G117+G156 -> 18864.429 | H10: =H80+H117+H156 -> 24011.683 | J10: =J80+J117+J156 -> 24011.683 | K10: =K80+K117+K156 -> 24011.683 | L10: =L80+L117+L156 -> 25020.173 | M10: =M80+M117+M156 -> 26020.98 | N10: =N80+N117+N156 -> 27113.862 | O10: =O80+O117+O156 -> 28306.871
B11: % of growth | D11: =D10/C10-1 -> -0.033010305 | E11: =E10/D10-1 -> 0.21122592 | F11: =F10/E10-1 -> 0.22809474 | G11: =G10/F10-1 -> 0.16409545 | H11: =H10/G10-1 -> 0.27285499 | J11: =J10/G10-1 -> 0.27285499 | K11: =K10/J10-1 -> 0 | L11: =L10/K10-1 -> 0.042 | M11: =M10/L10-1 -> 0.04 | N11: =N10/M10-1 -> 0.042 | O11: =O10/N10-1 -> 0.044
B12: % of sales | C12: =C10/C$44 -> 0.11132265 | D12: =D10/D$44 -> 0.090716813 | E12: =E10/E$44 -> 0.072391226 | F12: =F10/F$44 -> 0.076554079 | G12: =G10/G$44 -> 0.074915107 | H12: =H10/H$44 -> 0.11174039 | J12: =J10/J$44 -> 0.11174039 | K12: =K10/K$44 -> 0.096955142 | L12: =L10/L$44 -> 0.097650362 | M12: =M10/M$44 -> 0.098074249 | N12: =N10/N$44 -> 0.098692506 | O12: =O10/O$44 -> 0.099437658
B14: 상여 | C14: =C88+C125+C164 -> 3266.4126 | D14: =D88+D125+D164 -> 5821.6886 | E14: =E88+E125+E164 -> 10059.997 | F14: =F88+F125+F164 -> 10099.981 | G14: =G88+G125+G164 -> 7853.304 | H14: =H88+H125+H164 -> 501.9046 | J14: =J88+J125+J164 -> 501.9046 | K14: =K88+K125+K164 -> 7673.5422 | L14: =L88+L125+L164 -> 7995.831 | M14: =M88+M125+M164 -> 8315.6642 | N14: =N88+N125+N164 -> 8664.9221 | O14: =O88+O125+O164 -> 9046.1787
B15: % of growth | D15: =D14/C14-1 -> 0.78228823 | E15: =E14/D14-1 -> 0.72802041 | F15: =F14/E14-1 -> 0.0039746111 | G15: =G14/F14-1 -> -0.22244372 | H15: =H14/G14-1 -> -0.93609001 | J15: =J14/G14-1 -> -0.93609001 | K15: =K14/J14-1 -> 14.288846 | L15: =L14/K14-1 -> 0.042 | M15: =M14/L14-1 -> 0.04 | N15: =N14/M14-1 -> 0.042 | O15: =O14/N14-1 -> 0.044
B16: % of sales | C16: =C14/C$44 -> 0.032275902 | D16: =D14/D$44 -> 0.048477332 | E16: =E14/E$44 -> 0.055190022 | F16: =F14/F$44 -> 0.047712682 | G16: =G14/G$44 -> 0.031187326 | H16: =H14/H$44 -> 0.0023356554 | J16: =J14/J$44 -> 0.0023356554 | K16: =K14/K$44 -> 0.030984475 | L16: =L14/L$44 -> 0.03120665 | M16: =M14/M$44 -> 0.031342114 | N16: =N14/N$44 -> 0.031539693 | O16: =O14/O$44 -> 0.031777826
B18: 퇴직급여 | C18: =C94+C133+C172 -> 1112.4414 | D18: =D94+D133+D172 -> 1475.7958 | E18: =E94+E133+E172 -> 1836.1896 | F18: =F94+F133+F172 -> 2321.0452 | G18: =G94+G133+G172 -> 2611.3034 | H18: =H94+H133+H172 -> 2861.6776 | J18: =J94+J133+J172 -> 2861.6776 | K18: =K94+K133+K172 -> 3250.7647 | L18: =L94+L133+L172 -> 3387.2968 | M18: =M94+M133+M172 -> 3522.7887 | N18: =N94+N133+N172 -> 3670.7458 | O18: =O94+O133+O172 -> 3832.2586
B19: % of growth | D19: =D18/C18-1 -> 0.32662795 | E19: =E18/D18-1 -> 0.244203 | F19: =F18/E18-1 -> 0.26405531 | G19: =G18/F18-1 -> 0.12505496 | H19: =H18/G18-1 -> 0.095880929 | J19: =J18/G18-1 -> 0.095880929 | K19: =K18/J18-1 -> 0.1359647 | L19: =L18/K18-1 -> 0.042 | M19: =M18/L18-1 -> 0.04 | N19: =N18/M18-1 -> 0.042 | O19: =O18/N18-1 -> 0.044
B20: % of sales | C20: =C18/C$44 -> 0.010992196 | D20: =D18/D$44 -> 0.012288985 | E20: =E18/E$44 -> 0.010073497 | F20: =F18/F$44 -> 0.010964702 | G20: =G18/G$44 -> 0.010370103 | H20: =H18/H$44 -> 0.013317058 | J20: =J18/J$44 -> 0.013317058 | K20: =K18/K$44 -> 0.013126042 | L20: =L18/L$44 -> 0.013220162 | M20: =M18/M$44 -> 0.013277549 | N20: =N18/N$44 -> 0.013361251 | O20: =O18/O$44 -> 0.013462131
B22: 복리후생비 | C22: =C98+C137+C176 -> 1003.56 | D22: =D98+D137+D176 -> 1301.3285 | E22: =E98+E137+E176 -> 1456.1777 | F22: =F98+F137+F176 -> 1604.5996 | G22: =G98+G137+G176 -> 1661.6987 | H22: =H98+H137+H176 -> 1643.4169 | J22: =J98+J137+J176 -> 1643.4169 | K22: =K98+K137+K176 -> 2119.6093 | L22: =L98+L137+L176 -> 2208.6329 | M22: =M98+M137+M176 -> 2296.9782 | N22: =N98+N137+N176 -> 2393.4513 | O22: =O98+O137+O176 -> 2498.7632
B23: % of growth | D23: =D22/C22-1 -> 0.29671218 | E23: =E22/D22-1 -> 0.11899313 | F23: =F22/E22-1 -> 0.10192571 | G23: =G22/F22-1 -> 0.035584626 | H23: =H22/G22-1 -> -0.011001881 | J23: =J22/G22-1 -> -0.011001881 | K23: =K22/J22-1 -> 0.28975756 | L23: =L22/K22-1 -> 0.042 | M23: =M22/L22-1 -> 0.04 | N23: =N22/M22-1 -> 0.042 | O23: =O22/N22-1 -> 0.044
B24: % of sales | C24: =C22/C$44 -> 0.009916324 | D24: =D22/D$44 -> 0.010836192 | E24: =E22/E$44 -> 0.007988718 | F24: =F22/F$44 -> 0.0075801874 | G24: =G22/G$44 -> 0.0065989983 | H24: =H22/H$44 -> 0.007647779 | J24: =J22/J$44 -> 0.007647779 | K24: =K22/K$44 -> 0.0085586265 | L24: =L22/L$44 -> 0.0086199964 | M24: =M22/M$44 -> 0.0086574147 | N24: =N22/N$44 -> 0.0087119907 | O24: =O22/O$44 -> 0.0087777683
B26: 보험료 | C26: =C102+C141+C180 -> 414.95967 | D26: =D102+D141+D180 -> 840.91452 | E26: =E102+E141+E180 -> 1040.4417 | F26: =F102+F141+F180 -> 1426.9934 | G26: =G102+G141+G180 -> 1767.5193 | H26: =H102+H141+H180 -> 1732.2978 | J26: =J102+J141+J180 -> 1732.2978 | K26: =K102+K141+K180 -> 2161.5044 | L26: =L102+L141+L180 -> 2252.2875 | M26: =M102+M141+M180 -> 2342.379 | N26: =N102+N141+N180 -> 2440.759 | O26: =O102+O141+O180 -> 2548.1524
B27: % of growth | D27: =D26/C26-1 -> 1.026497 | E27: =E26/D26-1 -> 0.23727403 | F27: =F26/E26-1 -> 0.37152658 | G27: =G26/F26-1 -> 0.23863168 | H27: =H26/G26-1 -> -0.019927092 | J27: =J26/G26-1 -> -0.019927092 | K27: =K26/J26-1 -> 0.24776723 | L27: =L26/K26-1 -> 0.042 | M27: =M26/L26-1 -> 0.04 | N27: =N26/M26-1 -> 0.042 | O27: =O26/N26-1 -> 0.044
B28: % of sales | C28: =C26/C$44 -> 0.0041002775 | D28: =D26/D$44 -> 0.0070023141 | E28: =E26/E$44 -> 0.0057079541 | F28: =F26/F$44 -> 0.0067411693 | G28: =G26/G$44 -> 0.0070192368 | H28: =H26/H$44 -> 0.0080613936 | J28: =J26/J$44 -> 0.0080613936 | K28: =K26/K$44 -> 0.0087277916 | L28: =L26/L$44 -> 0.0087903745 | M28: =M26/M$44 -> 0.0088285323 | N28: =N26/N$44 -> 0.0088841871 | O28: =O26/O$44 -> 0.0089512649
B30: 세금과공과 | C30: =C106+C145+C184 -> 532.92992 | D30: =D106+D145+D184 -> 639.0389 | E30: =E106+E145+E184 -> 815.83221 | F30: =F106+F145+F184 -> 991.99376 | G30: =G106+G145+G184 -> 1089.0668 | H30: =H106+H145+H184 -> 1242.2302 | J30: =J106+J145+J184 -> 1242.2302 | K30: =K106+K145+K184 -> 1396.5087 | L30: =L106+L145+L184 -> 1455.1621 | M30: =M106+M145+M184 -> 1513.3686 | N30: =N106+N145+N184 -> 1576.9301 | O30: =O106+O145+O184 -> 1646.315
B31: % of growth | D31: =D30/C30-1 -> 0.19910494 | E31: =E30/D30-1 -> 0.27665501 | F31: =F30/E30-1 -> 0.21592865 | G31: =G30/F30-1 -> 0.097856551 | H31: =H30/G30-1 -> 0.1406372 | J31: =J30/G30-1 -> 0.1406372 | K31: =K30/J30-1 -> 0.12419484 | L31: =L30/K30-1 -> 0.042 | M31: =M30/L30-1 -> 0.04 | N31: =N30/M30-1 -> 0.042 | O31: =O30/N30-1 -> 0.044
B32: % of sales | C32: =C30/C$44 -> 0.0052659588 | D32: =D30/D$44 -> 0.0053212913 | E32: =E30/E$44 -> 0.0044757269 | F32: =F30/F$44 -> 0.0046862149 | G32: =G30/G$44 -> 0.0043249419 | H32: =H30/H$44 -> 0.0057808228 | J32: =J30/J$44 -> 0.0057808228 | K32: =K30/K$44 -> 0.0056388677 | L32: =L30/L$44 -> 0.0056793014 | M32: =M30/M$44 -> 0.0057039545 | N32: =N30/N$44 -> 0.005739912 | O32: =O30/O$44 -> 0.0057832498
B35: Macro Variables
C36: ='Pro forma'!C5 -> 2010 | D36: ='Pro forma'!D5 -> 2011 | E36: ='Pro forma'!E5 -> 2012 | F36: ='Pro forma'!F5 -> 2013 | G36: ='Pro forma'!G5 -> 2014 | H36: ='Pro forma'!H5 -> 2015/12A | I36: ='Pro forma'!I5 -> 2015/0E | J36: ='Pro forma'!J5 -> 2015 | ... O36: ='Pro forma'!O5 -> 2020
B37: Consumer prices (%) | C37: =Macro!H87/100 -> 0.02938 | D37: =Macro!I87/100 -> 0.04025 | E37: =Macro!J87/100 -> 0.02183 | F37: =Macro!K87/100 -> 0.01301 | G37: =Macro!L87/100 -> 0.01275 | J37: =Macro!M87/100 -> 0.006 | K37: =Macro!N87/100 -> 0.013 | L37: =Macro!O87/100 -> 0.015 | M37: =Macro!P87/100 -> 0.018 | N37: =Macro!Q87/100 -> 0.02 | O37: =Macro!R87/100 -> 0.022
B38: Growth in average wages | C38: =Macro!H90/100 -> 0.06844 | D38: =Macro!I90/100 -> 0.00923 | E38: =Macro!J90/100 -> 0.05371 | F38: =Macro!K90/100 -> 0.03856 | G38: =Macro!L90/100 -> 0.02554 | J38: =Macro!M90/100 -> 0.042 | K38: =Macro!N90/100 -> 0.043 | L38: =Macro!O90/100 -> 0.042 | M38: =Macro!P90/100 -> 0.04 | N38: =Macro!Q90/100 -> 0.042 | O38: =Macro!R90/100 -> 0.044
B39: Labour productivity growth (%) | C39: =Macro!H67/100 -> 0.051 | D39: =Macro!I67/100 -> 0.019 | E39: =Macro!J67/100 -> 0.005 | F39: =Macro!K67/100 -> 0.013 | G39: =Macro!L67/100 -> 0.012 | J39: =Macro!M67/100 -> 0.012 | K39: =Macro!N67/100 -> 0.015 | L39: =Macro!O67/100 -> 0.015 | M39: =Macro!P67/100 -> 0.019 | N39: =Macro!Q67/100 -> 0.019 | O39: =Macro!R67/100 -> 0.02
B42: Major Variables
C43: ='Pro forma'!C5 -> 2010 | D43: ='Pro forma'!D5 -> 2011 | E43: ='Pro forma'!E5 -> 2012 | F43: ='Pro forma'!F5 -> 2013 | G43: ='Pro forma'!G5 -> 2014 | H43: ='Pro forma'!H5 -> 2015/12A | I43: ='Pro forma'!I5 -> 2015/0E | J43: ='Pro forma'!J5 -> 2015 | ... O43: ='Pro forma'!O5 -> 2020
B44: 매출액 | C44: =매출액!C6 -> 101202.83 | D44: =매출액!D6 -> 120090.95 | E44: =매출액!E6 -> 182279.27 | F44: =매출액!F6 -> 211683.37 | G44: =매출액!G6 -> 251810.75 | H44: =매출액!H6 -> 214888.12 | J44: =매출액!J6 -> 214888.12 | K44: =매출액!K6 -> 247657.65 | L44: =매출액!L6 -> 256222.03 | M44: =매출액!M6 -> 265319.19 | N44: =매출액!N6 -> 274730.7 | O44: =매출액!O6 -> 284669.53
B45: 상품매출 | C45: =매출액!C9 -> 28667.765 | D45: =매출액!D9 -> 33818.96 | E45: =매출액!E9 -> 72895.968 | F45: =매출액!F9 -> 71774.78 | G45: =매출액!G9 -> 69236.769 | H45: =매출액!H9 -> 43311.995 | J45: =매출액!J9 -> 43311.995 | K45: =매출액!K9 -> 52024.746 | L45: =매출액!L9 -> 54263.917 | M45: =매출액!M9 -> 56179.287 | N45: =매출액!N9 -> 58153.964 | O45: =매출액!O9 -> 60235.145
B46: SI 매출 | C46: =매출액!C13 -> 32345.633 | D46: =매출액!D13 -> 31656.879 | E46: =매출액!E13 -> 52687.669 | F46: =매출액!F13 -> 60245.229 | G46: =매출액!G13 -> 90980.18 | H46: =매출액!H13 -> 76214.068 | J46: =매출액!J13 -> 76214.068 | K46: =매출액!K13 -> 96372.275 | L46: =매출액!L13 -> 98768.886 | M46: =매출액!M13 -> 102065.25 | N46: =매출액!N13 -> 105326.77 | O46: =매출액!O13 -> 108650.36
B47: SM 매출 | C47: =매출액!C17 -> 40189.43 | D47: =매출액!D17 -> 54615.106 | E47: =매출액!E17 -> 56695.63 | F47: =매출액!F17 -> 79663.359 | G47: =매출액!G17 -> 91593.798 | H47: =매출액!H17 -> 95362.06 | J47: =매출액!J17 -> 95362.06 | K47: =매출액!K17 -> 99260.63 | L47: =매출액!L17 -> 103189.22 | M47: =매출액!M17 -> 107074.66 | N47: =매출액!N17 -> 111249.97 | O47: =매출액!O17 -> 115784.03
B49: 인건비 집계
B50: =unit -> KRW Millions | C50: ='Pro forma'!C5 -> 2010 | D50: ='Pro forma'!D5 -> 2011 | E50: ='Pro forma'!E5 -> 2012 | F50: ='Pro forma'!F5 -> 2013 | G50: ='Pro forma'!G$5 -> 2014 | H50: ='Pro forma'!H5 -> 2015/12A | I50: ='Pro forma'!I5 -> 2015/0E | J50: ='Pro forma'!J5 -> 2015 | K50: ='Pro forma'!K5 -> 2016 | L50: ='Pro forma'!L5 -> 2017 | M50: ='Pro forma'!M5 -> 2018 | N50: ='Pro forma'!N5 -> 2019 | O50: ='Pro forma'!O5 -> 2020
B51: 인건비 합계 | D51: =SUM(D52:D53) -> 20973.034 | E51: =SUM(E52:E53) -> 28404.057 | F51: =SUM(F52:F53) -> 32649.839 | G51: =SUM(G52:G53) -> 33847.321 | H51: =SUM(H52:H53) -> 31993.21 | J51: =SUM(J52:J53) -> 31993.21 | K51: =SUM(K52:K53) -> 40613.612 | L51: =SUM(L52:L53) -> 42319.384 | M51: =SUM(M52:M53) -> 44012.159 | N51: =SUM(N52:N53) -> 45860.67 | O51: =SUM(O52:O53) -> 47878.539
B52: 매출원가 | C52: =C76+C113 -> 11251.56 | D52: =D76+D113 -> 16073.507 | E52: =E76+E113 -> 22926.02 | F52: =F76+F113 -> 27053.053 | G52: =G76+G113 -> 28287.174 | H52: =H76+H113 -> 25541.977 | J52: =J76+J113 -> 25541.977 | K52: =K76+K113 -> 32254.035 | L52: =L76+L113 -> 33608.705 | M52: =M76+M113 -> 34953.053 | N52: =N76+N113 -> 36421.081 | O52: =O76+O113 -> 38023.609
B53: 판관비 | C53: =C152 -> 6344.9109 | D53: =D152 -> 4899.5275 | E53: =E152 -> 5478.0373 | F53: =F152 -> 5596.7852 | G53: =G152 -> 5560.1474 | H53: =H152 -> 6451.2332 | J53: =J152 -> 6451.2332 | K53: =K152 -> 8359.577 | L53: =L152 -> 8710.6792 | M53: =M152 -> 9059.1064 | N53: =N152 -> 9439.5888 | O53: =O152 -> 9854.9307
B55: 인원수
B56: 명수 | C56: ='Pro forma'!C$5 -> 2010 | D56: ='Pro forma'!D$5 -> 2011 | E56: ='Pro forma'!E$5 -> 2012 | F56: ='Pro forma'!F$5 -> 2013 | G56: ='Pro forma'!G$5 -> 2014 | H56: ='Pro forma'!H$5 -> 2015/12A | I56: ='Pro forma'!I$5 -> 2015/0E | J56: ='Pro forma'!J$5 -> 2015 | ... O56: ='Pro forma'!O$5 -> 2020
B57: 인원수 | C57: =C61+C71 -> 0 | D57: =D61+D71 -> 352 | E57: =E61+E71 -> 422 | F57: =F61+F71 -> 470 | G57: =G61+G71 -> 483 | H57: =H61+H71 -> 466 | J57: =J61+J71 -> 466 | K57: =K61+K71 -> 466 | L57: =L61+L71 -> 466 | M57: =M61+M71 -> 466 | N57: =N61+N71 -> 466 | O57: =O61+O71 -> 466
B58: % of growth | D58: =D57/C57-1 -> #DIV/0! | E58: =E57/D57-1 -> 0.19886364 | F58: =F57/E57-1 -> 0.11374408 | G58: =G57/F57-1 -> 0.027659574 | H58: n.a. | J58: =J57/G57-1 -> -0.035196687 | K58: =K57/J57-1 -> 0 | L58: =L57/K57-1 -> 0 | M58: =M57/L57-1 -> 0 | N58: =N57/M57-1 -> 0 | O58: =O57/N57-1 -> 0
B59: % of sales | C59: =C57/C$44 -> 0 | D59: =D57/D$44 -> 0.0029311119 | E59: =E57/E$44 -> 0.0023151289 | F59: =F57/F$44 -> 0.0022202972 | G59: =G57/G$44 -> 0.0019181072 | H59: =H57/H$44 -> 0.0021685703
B61: 매출원가부분 | C61: =C64+C67 -> 0 | D61: =D64+D67 -> 312 | E61: =E64+E67 -> 380 | F61: =F64+F67 -> 433 | G61: =G64+G67 -> 432 | H61: =H64+H67 -> 399 | J61: =J64+J67 -> 399 | K61: =K64+K67 -> 399 | L61: =L64+L67 -> 399 | M61: =M64+M67 -> 399 | N61: =N64+N67 -> 399 | O61: =O64+O67 -> 399
B62: % of growth | D62: =D61/C61-1 -> #DIV/0! | E62: =E61/D61-1 -> 0.21794872 | F62: =F61/E61-1 -> 0.13947368 | G62: =G61/F61-1 -> -0.0023094688 | H62: n.a. | J62: =J61/G61-1 -> -0.076388889 | K62: =K61/J61-1 -> 0 | L62: =L61/K61-1 -> 0 | M62: =M61/L61-1 -> 0 | N62: =N61/M61-1 -> 0 | O62: =O61/N61-1 -> 0
B63: % of sales | C63: =C61/C$44 -> 0 | D63: =D61/D$44 -> 0.002598031 | E63: =E61/E$44 -> 0.0020847132 | F63: =F61/F$44 -> 0.0020455079 | G63: =G61/G$44 -> 0.0017155741 | H63: =H61/H$44 -> 0.0018567801
B64: SI | D64: 110 | E64: 137 | F64: 175 | G64: 143 | H64: 100 | J64: =H64+I64 -> 100 | K64: =K83 -> 100 | L64: =L83 -> 100 | M64: =M83 -> 100 | N64: =N83 -> 100 | O64: =O83 -> 100
B65: % of growth | D65: =D64/C64-1 -> #DIV/0! | E65: =E64/D64-1 -> 0.24545455 | F65: =F64/E64-1 -> 0.27737226 | G65: =G64/F64-1 -> -0.18285714 | H65: n.a. | J65: =J64/G64-1 -> -0.3006993 | K65: =K64/J64-1 -> 0 | L65: =L64/K64-1 -> 0 | M65: =M64/L64-1 -> 0 | N65: =N64/M64-1 -> 0 | O65: =O64/N64-1 -> 0
B66: % of sales | C66: =C64/C$46 -> 0 | D66: =D64/D$46 -> 0.0034747582 | E66: =E64/E$46 -> 0.0026002289 | F66: =F64/F$46 -> 0.0029047943 | G66: =G64/G$46 -> 0.0015717709 | H66: =H64/H$46 -> 0.0013120937
B67: SM | D67: 202 | E67: 243 | F67: 258 | G67: 289 | H67: 299 | J67: =H67+I67 -> 299 | K67: =K120 -> 299 | L67: =L120 -> 299 | M67: =M120 -> 299 | N67: =N120 -> 299 | O67: =O120 -> 299
B68: % of growth | D68: =D67/C67-1 -> #DIV/0! | E68: =E67/D67-1 -> 0.2029703 | F68: =F67/E67-1 -> 0.061728395 | G68: =G67/F67-1 -> 0.12015504 | H68: n.a. | J68: =J67/G67-1 -> 0.034602076 | K68: =K67/J67-1 -> 0 | L68: =L67/K67-1 -> 0 | M68: =M67/L67-1 -> 0 | N68: =N67/M67-1 -> 0 | O68: =O67/N67-1 -> 0
B69: % of sales | C69: =C67/C$47 -> 0 | D69: =D67/D$47 -> 0.0036986104 | E69: =E67/E$47 -> 0.0042860446 | F69: =F67/F$47 -> 0.0032386282 | G69: =G67/G$47 -> 0.0031552355 | H69: =H67/H$47 -> 0.0031354188
B71: 판관비부분 | D71: 40 | E71: 42 | F71: 37 | G71: 51 | H71: 67 | J71: =H71+I71 -> 67 | K71: =K159 -> 67 | L71: =L159 -> 67 | M71: =M159 -> 67 | N71: =N159 -> 67 | O71: =O159 -> 67
B72: % of growth | D72: =D71/C71-1 -> #DIV/0! | E72: =E71/D71-1 -> 0.05 | F72: =F71/E71-1 -> -0.11904762 | G72: =G71/F71-1 -> 0.37837838 | H72: n.a. | J72: =J71/G71-1 -> 0.31372549 | K72: =K71/J71-1 -> 0 | L72: =L71/K71-1 -> 0 | M72: =M71/L71-1 -> 0 | N72: =N71/M71-1 -> 0 | O72: =O71/N71-1 -> 0
B74: 인건비 - 매출원가 (SI)
B75: =unit -> KRW Millions | C75: ='Pro forma'!C$5 -> 2010 | D75: ='Pro forma'!D$5 -> 2011 | E75: ='Pro forma'!E$5 -> 2012 | F75: ='Pro forma'!F$5 -> 2013 | G75: ='Pro forma'!G$5 -> 2014 | H75: ='Pro forma'!H$5 -> 2015/12A | I75: ='Pro forma'!I$5 -> 2015/0E | J75: ='Pro forma'!J$5 -> 2015 | ... O75: ='Pro forma'!O$5 -> 2020
B76: 인건비성경비 | C76: =C80+C88+C94+C98+C102+C106 -> 3953.9628 | D76: =D80+D88+D94+D98+D102+D106 -> 5141.6747 | E76: =E80+E88+E94+E98+E102+E106 -> 9363.1906 | F76: =F80+F88+F94+F98+F102+F106 -> 10962.727 | G76: =G80+G88+G94+G98+G102+G106 -> 10189.763 | H76: =H80+H88+H94+H98+H102+H106 -> 8332.1261 | J76: =J80+J88+J94+J98+J102+J106 -> 8332.1261 | K76: =K80+K88+K94+K98+K102+K106 -> 10184.003 | L76: =L80+L88+L94+L98+L102+L106 -> 10611.731 | M76: =M80+M88+M94+M98+M102+M106 -> 11036.201 | N76: =N80+N88+N94+N98+N102+N106 -> 11499.721 | O76: =O80+O88+O94+O98+O102+O106 -> 12005.709
B77: % of growth | D77: =D76/C76-1 -> 0.3003852 | E77: =E76/D76-1 -> 0.82103908 | F77: =F76/E76-1 -> 0.17083241 | G77: =G76/F76-1 -> -0.070508338 | H77: =H76/G76-1 -> -0.18230426 | J77: =J76/G76-1 -> -0.18230426 | K77: =K76/J76-1 -> 0.22225746 | L77: =L76/K76-1 -> 0.042 | M77: =M76/L76-1 -> 0.04 | N77: =N76/M76-1 -> 0.042 | O77: =O76/N76-1 -> 0.044
B78: % of sales | C78: =C76/C$44 -> 0.039069687 | D78: =D76/D$44 -> 0.042814841 | E78: =E76/E$44 -> 0.051367283 | F78: =F76/F$44 -> 0.051788325 | G78: =G76/G$44 -> 0.040465959 | H78: =H76/H$44 -> 0.038774251 | J78: =J76/J$44 -> 0.038774251 | K78: =K76/K$44 -> 0.041121295 | L78: =L76/L$44 -> 0.041416156 | M78: =M76/M$44 -> 0.041595938 | N78: =N76/N$44 -> 0.041858158 | O78: =O76/O$44 -> 0.042174197
B80: 급여 | C80: =(원가명세서!K9+원가명세서!K11)/10^6 -> 3177.3945 | D80: =(원가명세서!L9+원가명세서!L11)/10^6 -> 2549.6291 | E80: =(원가명세서!M9+원가명세서!M11)/10^6 -> 4532.2275 | F80: =(원가명세서!N9+원가명세서!N11)/10^6 -> 5704.7892 | G80: =(원가명세서!O9+원가명세서!O11)/10^6 -> 5921.981 | H80: =(원가명세서!P9+원가명세서!P11)/10^6 -> 6509.771 | J80: =H80+I80 -> 6509.771 | K80: =K83*K86 -> 6509.771 | L80: =L83*L86 -> 6783.1814 | M80: =M83*M86 -> 7054.5087 | N80: =N83*N86 -> 7350.7981 | O80: =O83*O86 -> 7674.2332
B81: % of growth | D81: =D80/C80-1 -> -0.19757239 | E81: =E80/D80-1 -> 0.77760272 | F81: =F80/E80-1 -> 0.25871641 | G81: =G80/F80-1 -> 0.038071841 | H81: =H80/G80-1 -> 0.099255643 | J81: =J80/G80-1 -> 0.099255643 | K81: =K80/J80-1 -> 0 | L81: =L80/K80-1 -> 0.042 | M81: =M80/L80-1 -> 0.04 | N81: =N80/M80-1 -> 0.042 | O81: =O80/N80-1 -> 0.044
B82: % of sales | C82: =C80/C$46 -> 0.098232564 | D82: =D80/D$46 -> 0.080539495 | E82: =E80/E$46 -> 0.08602065 | F82: =F80/F$46 -> 0.094692796 | G82: =G80/G$46 -> 0.065090891 | H82: =H80/H$46 -> 0.085414297 | J82: =J80/J$46 -> 0.085414297 | K82: =K80/K$46 -> 0.067548172 | L82: =L80/L$46 -> 0.06867731 | M82: =M80/M$46 -> 0.069117638 | N82: =N80/N$46 -> 0.069790406 | O82: =O80/O$46 -> 0.070632379
B83: 인원수 | D83: =D$64 -> 110 | E83: =E$64 -> 137 | F83: =F$64 -> 175 | G83: =G$64 -> 143 | H83: =H$64 -> 100 | J83: =J$64 -> 100 | K83: =J83 -> 100 | L83: =K83 -> 100 | M83: =L83 -> 100 | N83: =M83 -> 100 | O83: =N83 -> 100 | R83: =MAX(ROUNDUP(K46/K84,0),J83)
B84: 1인당매출 | D84: =D$46/D$83 -> 287.78981 | E84: =E$46/E$83 -> 384.58153 | F84: =F$46/F$83 -> 344.25845 | G84: =G$46/G$83 -> 636.22504 | H84: =H$46/H$83 -> 762.14068 | J84: =J$46/J$83 -> 762.14068 | K84: =J84*(1+K85) -> 773.57279 | L84: =K84*(1+L85) -> 785.17639 | M84: =L84*(1+M85) -> 800.09474 | N84: =M84*(1+N85) -> 815.29654 | O84: =N84*(1+O85) -> 831.60247
B85: % of growth | E85: =E84/D84-1 -> 0.33632781 | F85: =F84/E84-1 -> -0.10484922 | G85: =G84/F84-1 -> 0.84810288 | H85: =H84/G84-1 -> 0.19791055 | J85: =J84/G84-1 -> 0.19791055 | K85: =K$39 -> 0.015 | L85: =L$39 -> 0.015 | M85: =M$39 -> 0.019 | N85: =N$39 -> 0.019 | O85: =O$39 -> 0.02
B86: 1인당급여 | D86: =D$80/D83 -> 23.178446 | E86: =E$80/E83 -> 33.081953 | F86: =F$80/F83 -> 32.598795 | G86: =G$80/G83 -> 41.412455 | H86: =H$80/H83 -> 65.09771 | J86: =J$80/J83 -> 65.09771 | K86: =J86 -> 65.09771 | L86: =K86*(1+L$38) -> 67.831814 | M86: =L86*(1+M$38) -> 70.545087 | N86: =M86*(1+N$38) -> 73.507981 | O86: =N86*(1+O$38) -> 76.742332 | R86: 2016년 급여동결
B88: 상여 | C88: =원가명세서!K10/10^6 -> 0 | D88: =원가명세서!L10/10^6 -> 1641.1464 | E88: =원가명세서!M10/10^6 -> 3310.1726 | F88: =원가명세서!N10/10^6 -> 3335.1465 | G88: =원가명세서!O10/10^6 -> 2399.6123 | H88: =원가명세서!P10/10^6 -> 81.515874 | J88: =H88+I88 -> 81.515874 | K88: =K91*K92 -> 1678.0505 | L88: =L91*L92 -> 1748.5287 | M88: =M91*M92 -> 1818.4698 | N88: =N91*N92 -> 1894.8455 | O88: =O91*O92 -> 1978.2188
B89: % of growth | D89: =D88/C88-1 -> #DIV/0! | E89: =E88/D88-1 -> 1.0169879 | F89: =F88/E88-1 -> 0.0075445955 | G89: =G88/F88-1 -> -0.28050768 | H89: =H88/G88-1 -> -0.96602956 | J89: =J88/G88-1 -> -0.96602956 | K89: =K88/J88-1 -> 19.585568 | L89: =L88/K88-1 -> 0.042 | M89: =M88/L88-1 -> 0.04 | N89: =N88/M88-1 -> 0.042 | O89: =O88/N88-1 -> 0.044
B90: % of sales | C90: =C88/C$46 -> 0 | D90: =D88/D$46 -> 0.051841701 | E90: =E88/E$46 -> 0.062826324 | F90: =F88/F$46 -> 0.055359512 | G90: =G88/G$46 -> 0.02637511 | H90: =H88/H$46 -> 0.0010695647 | J90: =J88/J$46 -> 0.0010695647 | K90: =K88/K$46 -> 0.017412171 | L90: =L88/L$46 -> 0.017703234 | M90: =M88/M$46 -> 0.017816739 | N90: =N88/N$46 -> 0.017990161 | O90: =O88/O$46 -> 0.0182072
B91: 인원수 | D91: =D$64 -> 110 | E91: =E$64 -> 137 | F91: =F$64 -> 175 | G91: =G$64 -> 143 | H91: =H$64 -> 100 | J91: =J$64 -> 100 | K91: =J91 -> 100 | L91: =K91 -> 100 | M91: =L91 -> 100 | N91: =M91 -> 100 | O91: =N91 -> 100
B92: 1인당상여 | D92: =D88/D91 -> 14.919513 | E92: =E88/E91 -> 24.161844 | F92: =F88/F91 -> 19.05798 | G92: =G88/G91 -> 16.780505 | H92: =H88/H91 -> 0.81515874 | J92: =J88/J91 -> 0.81515874 | K92: =G92 -> 16.780505 | L92: =K92*(1+L$38) -> 17.485287 | M92: =L92*(1+M$38) -> 18.184698 | N92: =M92*(1+N$38) -> 18.948455 | O92: =N92*(1+O$38) -> 19.782188
B94: 퇴직급여 | C94: =원가명세서!K12/10^6 -> 285.92705 | D94: =원가명세서!L12/10^6 -> 369.54627 | E94: =원가명세서!M12/10^6 -> 571.71005 | F94: =원가명세서!N12/10^6 -> 705.30156 | G94: =원가명세서!O12/10^6 -> 730.5592 | H94: =원가명세서!P12/10^6 -> 652.20677 | J94: =H94+I94 -> 652.20677 | K94: =K$80*K96 -> 753.36739 | L94: =L$80*L96 -> 785.00882 | M94: =M$80*M96 -> 816.40917 | N94: =N$80*N96 -> 850.69836 | O94: =O$80*O96 -> 888.12908
B95: % of growth | D95: =D94/C94-1 -> 0.29244947 | E95: =E94/D94-1 -> 0.54705946 | F95: =F94/E94-1 -> 0.23367005 | G95: =G94/F94-1 -> 0.035811119 | H95: =H94/G94-1 -> -0.10724993 | J95: =J94/G94-1 -> -0.10724993 | K95: =K94/J94-1 -> 0.15510513 | L95: =L94/K94-1 -> 0.042 | M95: =M94/L94-1 -> 0.04 | N95: =N94/M94-1 -> 0.042 | O95: =O94/N94-1 -> 0.044
B96: % of 급여 | C96: =C94/C$80 -> 0.089987898 | D96: =D94/D$80 -> 0.14494119 | E96: =E94/E$80 -> 0.12614328 | F96: =F94/F$80 -> 0.12363324 | G96: =G94/G$80 -> 0.12336399 | H96: =H94/H$80 -> 0.1001889 | J96: =J94/J$80 -> 0.1001889 | K96: =AVERAGE(F96:H96) -> 0.11572871 | L96: =K96 -> 0.11572871 | M96: =L96 -> 0.11572871 | N96: =M96 -> 0.11572871 | O96: =N96 -> 0.11572871
B98: 복리후생비 | C98: =원가명세서!K18/10^6 -> 221.58944 | D98: =원가명세서!L18/10^6 -> 295.27387 | E98: =원가명세서!M18/10^6 -> 463.09062 | F98: =원가명세서!N18/10^6 -> 555.60256 | G98: =원가명세서!O18/10^6 -> 489.20777 | H98: =원가명세서!P18/10^6 -> 431.72478 | J98: =H98+I98 -> 431.72478 | K98: =K$80*K100 -> 534.49693 | L98: =L$80*L100 -> 556.9458 | M98: =M$80*M100 -> 579.22363 | N98: =N$80*N100 -> 603.55102 | O98: =O$80*O100 -> 630.10727
B99: % of growth | D99: =D98/C98-1 -> 0.33252683 | E99: =E98/D98-1 -> 0.56834271 | F99: =F98/E98-1 -> 0.1997707 | G99: =G98/F98-1 -> -0.11950051 | H99: =H98/G98-1 -> -0.11750221 | J99: =J98/G98-1 -> -0.11750221 | K99: =K98/J98-1 -> 0.23805015 | L99: =L98/K98-1 -> 0.042 | M99: =M98/L98-1 -> 0.04 | N99: =N98/M98-1 -> 0.042 | O99: =O98/N98-1 -> 0.044
B100: % of 급여 | C100: =C98/C$80 -> 0.069739353 | D100: =D98/D$80 -> 0.11581052 | E100: =E98/E$80 -> 0.10217727 | F100: =F98/F$80 -> 0.097392303 | G100: =G98/G$80 -> 0.082608805 | H100: =H98/H$80 -> 0.066319502 | J100: =J98/J$80 -> 0.066319502 | K100: =AVERAGE(F100:H100) -> 0.08210687 | L100: =K100 -> 0.08210687 | M100: =L100 -> 0.08210687 | N100: =M100 -> 0.08210687 | O100: =N100 -> 0.08210687
B102: 보험료 | C102: =원가명세서!K27/10^6 -> 150.06023 | D102: =원가명세서!L27/10^6 -> 146.41247 | E102: =원가명세서!M27/10^6 -> 246.5386 | F102: =원가명세서!N27/10^6 -> 354.56853 | G102: =원가명세서!O27/10^6 -> 364.42479 | H102: =원가명세서!P27/10^6 -> 344.00934 | J102: =H102+I102 -> 344.00934 | K102: =K$80*K104 -> 383.06858 | L102: =L$80*L104 -> 399.15746 | M102: =M$80*M104 -> 415.12376 | N102: =N$80*N104 -> 432.55896 | O102: =O$80*O104 -> 451.59155
B103: % of growth | D103: =D102/C102-1 -> -0.024308646 | E103: =E102/D102-1 -> 0.68386341 | F103: =F102/E102-1 -> 0.43818669 | G103: =G102/F102-1 -> 0.027797887 | H103: =H102/G102-1 -> -0.056021016 | J103: =J102/G102-1 -> -0.056021016 | K103: =K102/J102-1 -> 0.11354122 | L103: =L102/K102-1 -> 0.042 | M103: =M102/L102-1 -> 0.04 | N103: =N102/M102-1 -> 0.042 | O103: =O102/N102-1 -> 0.044
B104: % of 급여 | C104: =C102/C$80 -> 0.047227447 | D104: =D102/D$80 -> 0.057425008 | E104: =E102/E$80 -> 0.054396784 | F104: =F102/F$80 -> 0.062152784 | G104: =G102/G$80 -> 0.061537649 | H104: =H102/H$80 -> 0.052845075 | J104: =J102/J$80 -> 0.052845075 | K104: =AVERAGE(F104:H104) -> 0.058845169 | L104: =K104 -> 0.058845169 | M104: =L104 -> 0.058845169 | N104: =M104 -> 0.058845169 | O104: =N104 -> 0.058845169
B106: 세금과공과 | C106: =원가명세서!K21/1000000 -> 118.99164 | D106: =원가명세서!L21/1000000 -> 139.66665 | E106: =원가명세서!M21/1000000 -> 239.45128 | F106: =원가명세서!N21/1000000 -> 307.31874 | G106: =원가명세서!O21/1000000 -> 283.97834 | H106: =원가명세서!P21/1000000 -> 312.89827 | J106: =H106+I106 -> 312.89827 | K106: =K$80*K108 -> 325.2488 | L106: =L$80*L108 -> 338.90925 | M106: =M$80*M108 -> 352.46562 | N106: =N$80*N108 -> 367.26918 | O106: =O$80*O108 -> 383.42902
B107: % of growth | D107: =D106/C106-1 -> 0.17375179 | E107: =E106/D106-1 -> 0.7144485 | F107: =F106/E106-1 -> 0.28342908 | G107: =G106/F106-1 -> -0.07594851 | H107: =H106/G106-1 -> 0.10183852 | J107: =J106/G106-1 -> 0.10183852 | K107: =K106/J106-1 -> 0.039471405 | L107: =L106/K106-1 -> 0.042 | M107: =M106/L106-1 -> 0.04 | N107: =N106/M106-1 -> 0.042 | O107: =O106/N106-1 -> 0.044
B108: % of 급여 | C108: =C106/C$80 -> 0.037449439 | D108: =D106/D$80 -> 0.054779204 | E108: =E106/E$80 -> 0.052833022 | F108: =F106/F$80 -> 0.053870305 | G108: =G106/G$80 -> 0.047953267 | H108: =H106/H$80 -> 0.048065941 | J108: =J106/J$80 -> 0.048065941 | K108: =AVERAGE(F108:H108) -> 0.049963171 | L108: =K108 -> 0.049963171 | M108: =L108 -> 0.049963171 | N108: =M108 -> 0.049963171 | O108: =N108 -> 0.049963171
B111: 인건비 - 매출원가 (SM)
B112: =unit -> KRW Millions | C112: ='Pro forma'!C$5 -> 2010 | D112: ='Pro forma'!D$5 -> 2011 | E112: ='Pro forma'!E$5 -> 2012 | F112: ='Pro forma'!F$5 -> 2013 | G112: ='Pro forma'!G$5 -> 2014 | H112: ='Pro forma'!H$5 -> 2015/12A | I112: ='Pro forma'!I$5 -> 2015/0E | J112: ='Pro forma'!J$5 -> 2015 | ... O112: ='Pro forma'!O$5 -> 2020
B113: 인건비성경비 | C113: =C117+C125+C133+C137+C141+C145 -> 7297.5973 | D113: =D117+D125+D133+D137+D141+D145 -> 10931.832 | E113: =E117+E125+E133+E137+E141+E145 -> 13562.83 | F113: =F117+F125+F133+F137+F141+F145 -> 16090.326 | G113: =G117+G125+G133+G137+G141+G145 -> 18097.41 | H113: =H117+H125+H133+H137+H141+H145 -> 17209.85 | J113: =J117+J125+J133+J137+J141+J145 -> 17209.85 | K113: =K117+K125+K133+K137+K141+K145 -> 22070.032 | L113: =L117+L125+L133+L137+L141+L145 -> 22996.973 | M113: =M117+M125+M133+M137+M141+M145 -> 23916.852 | N113: =N117+N125+N133+N137+N141+N145 -> 24921.36 | O113: =O117+O125+O133+O137+O141+O145 -> 26017.9
B114: % of growth | D114: =D113/C113-1 -> 0.49800429 | E114: =E113/D113-1 -> 0.24067307 | F114: =F113/E113-1 -> 0.18635469 | G114: =G113/F113-1 -> 0.12473856 | H114: =H113/G113-1 -> -0.049043483 | J114: =J113/G113-1 -> -0.049043483 | K114: =K113/J113-1 -> 0.28240695 | L114: =L113/K113-1 -> 0.042 | M114: =M113/L113-1 -> 0.04 | N114: =N113/M113-1 -> 0.042 | O114: =O113/N113-1 -> 0.044
B115: % of sales | C115: =C113/C$44 -> 0.07210863 | D115: =D113/D$44 -> 0.09102961 | E115: =E113/E$44 -> 0.074406869 | F115: =F113/F$44 -> 0.076011292 | G115: =G113/G$44 -> 0.071869095 | H115: =H113/H$44 -> 0.08008749 | J115: =J113/J$44 -> 0.08008749 | K115: =K113/K$44 -> 0.089115082 | L115: =L113/L$44 -> 0.089754084 | M115: =M113/M$44 -> 0.090143695 | N115: =N113/N$44 -> 0.090711957 | O115: =O113/O$44 -> 0.091396855
B117: 급여 | C117: =(원가명세서!C9+원가명세서!C11)/10^6 -> 6232.396 | D117: =(원가명세서!D9+원가명세서!D11)/10^6 -> 5773.9036 | E117: =(원가명세서!E9+원가명세서!E11)/10^6 -> 6811.4096 | F117: =(원가명세서!F9+원가명세서!F11)/10^6 -> 8439.7856 | G117: =(원가명세서!G9+원가명세서!G11)/10^6 -> 10779.54 | H117: =(원가명세서!H9+원가명세서!H11)/10^6 -> 13891.937 | J117: =H117+I117 -> 13891.937 | K117: =K120*K123 -> 13891.937 | L117: =L120*L123 -> 14475.399 | M117: =M120*M123 -> 15054.414 | N117: =N120*N123 -> 15686.7 | O117: =O120*O123 -> 16376.915
B118: % of growth | D118: =D117/C117-1 -> -0.073566007 | E118: =E117/D117-1 -> 0.17968884 | F118: =F117/E117-1 -> 0.23906593 | G118: =G117/F117-1 -> 0.27722914 | H118: =H117/G117-1 -> 0.2887319 | J118: =J117/G117-1 -> 0.2887319 | K118: =K117/J117-1 -> 0 | L118: =L117/K117-1 -> 0.042 | M118: =M117/L117-1 -> 0.04 | N118: =N117/M117-1 -> 0.042 | O118: =O117/N117-1 -> 0.044
B119: % of sales | C119: =C117/C$47 -> 0.1550755 | D119: =D117/D$47 -> 0.1057199 | E119: =E117/E$47 -> 0.12013994 | F119: =F117/F$47 -> 0.10594313 | G119: =G117/G$47 -> 0.11768854 | H119: =H117/H$47 -> 0.14567572 | J119: =J117/J$47 -> 0.14567572 | K119: =K117/K$47 -> 0.13995415 | L119: =L117/L$47 -> 0.14028014 | M119: =M117/M$47 -> 0.14059736 | N119: =N117/N$47 -> 0.14100408 | O119: =O117/O$47 -> 0.14144364
B120: 인원수 | D120: =D$67 -> 202 | E120: =E$67 -> 243 | F120: =F$67 -> 258 | G120: =G$67 -> 289 | H120: =H$67 -> 299 | J120: =J$67 -> 299 | K120: =J120 -> 299 | L120: =K120 -> 299 | M120: =L120 -> 299 | N120: =M120 -> 299 | O120: =N120 -> 299 | R120: =MAX(ROUNDUP(K47/K118,0),J117)
B121: 1인당매출 | D121: =D47/D120 -> 270.37181 | E121: =E47/E120 -> 233.31535 | F121: =F47/F120 -> 308.77271 | G121: =G47/G120 -> 316.93356 | H121: =H47/H120 -> 318.93666 | J121: =J47/J120 -> 318.93666 | K121: =J121*(1+K122) -> 323.72071 | L121: =K121*(1+L122) -> 328.57652 | M121: =L121*(1+M122) -> 334.81947 | N121: =M121*(1+N122) -> 341.18104 | O121: =N121*(1+O122) -> 348.00466
B122: % of growth | E122: =E121/D121-1 -> -0.13705742 | F122: =F121/E121-1 -> 0.32341362 | G122: =G121/F121-1 -> 0.02642995 | H122: =H121/G121-1 -> 0.0063202489 | J122: =J121/G121-1 -> 0.0063202489 | K122: =K$39 -> 0.015 | L122: =L$39 -> 0.015 | M122: =M$39 -> 0.019 | N122: =N$39 -> 0.019 | O122: =O$39 -> 0.02
B123: 1인당급여 | D123: =D117/D120 -> 28.583681 | E123: =E117/E120 -> 28.030492 | F123: =F117/F120 -> 32.712347 | G123: =G117/G120 -> 37.299447 | H123: =H117/H120 -> 46.461328 | J123: =J117/J120 -> 46.461328 | K123: =J123 -> 46.461328 | L123: =K123*(1+L$38) -> 48.412704 | M123: =L123*(1+M$38) -> 50.349212 | N123: =M123*(1+N$38) -> 52.463879 | O123: =N123*(1+O$38) -> 54.77229 | R123: 2016년 급여동결
B125: 상여 | C125: =원가명세서!C10/10^6 -> 0 | D125: =원가명세서!D10/10^6 -> 3348.9999 | E125: =원가명세서!E10/10^6 -> 4825.2008 | F125: =원가명세서!F10/10^6 -> 5004.6762 | G125: =원가명세서!G10/10^6 -> 4188.6924 | H125: =원가명세서!H10/10^6 -> 172.29925 | J125: =H125+I125 -> 172.29925 | K125: =K128*K131 -> 4333.6299 | L125: =L128*L131 -> 4515.6424 | M125: =M128*M131 -> 4696.268 | N125: =N128*N131 -> 4893.5113 | O125: =O128*O131 -> 5108.8258
B126: % of growth | D126: =D125/C125-1 -> #DIV/0! | E126: =E125/D125-1 -> 0.44078861 | F126: =F125/E125-1 -> 0.037195421 | G126: =G125/F125-1 -> -0.16304427 | H126: =H125/G125-1 -> -0.95886562 | J126: =J125/G125-1 -> -0.95886562 | K126: =K125/J125-1 -> 24.151763 | L126: =L125/K125-1 -> 0.042 | M126: =M125/L125-1 -> 0.04 | N126: =N125/M125-1 -> 0.042 | O126: =O125/N125-1 -> 0.044
...

Sheet CapEx&Dep
B1: ="Project"&" "&Title!L6 -> Project IT | O1: =Des!C12 -> DRAFT - For Discussion Purposes Only
B2: 자본적 지출 및 감가상각비
B4: 자본적 지출, 감가상각비 및 무형자산상각비
B5: =unit -> KRW Millions | C5: ='SG&A'!C5 -> 2010 | D5: ='SG&A'!D5 -> 2011 | E5: ='SG&A'!E5 -> 2012 | F5: ='SG&A'!F5 -> 2013 | G5: ='SG&A'!G5 -> 2014 | H5: ='SG&A'!H5 -> 2015/12A | I5: ='SG&A'!I5 -> 2015/0E | J5: ='SG&A'!J5 -> 2015 | ... O5: ='SG&A'!O5 -> 2020
B6: 자본적 지출 | C6: =C19 -> 740.09 | D6: =D19 -> 1200.436 | E6: =E19 -> 598.167 | F6: =F19 -> 7756.671 | G6: =G19 -> 1132.61 | H6: =H19 -> 762.43818 | I6: =I19 -> 0 | J6: =J19 -> 762.43818 | ... O6: =O19 -> 1205.403
B7: 유무형자산 상각비 | C7: =C51 -> 677.542 | D7: =D51 -> 599.583 | E7: =E51 -> 554.964 | F7: =F51 -> 711.792 | G7: =G51 -> 741.121 | H7: =H51 -> 712.84854 | I7: =I51 -> 64.479145 | J7: =J51 -> 775.38114 | ... O7: =O51 -> 2179.7868
B8: Spread | C8: =C6-C7 -> 62.548 | D8: =D6-D7 -> 600.853 | E8: =E6-E7 -> 43.203 | F8: =F6-F7 -> 7044.879 | G8: =G6-G7 -> 391.489 | H8: =H6-H7 -> 49.589638 | I8: =I6-I7 -> -64.479145 | J8: =J6-J7 -> -12.942957 | ... O8: =O6-O7 -> -974.38378
B10: =unit -> KRW Millions | C10: =C$5 -> 2010 | D10: =D$5 -> 2011 | E10: =E$5 -> 2012 | F10: =F$5 -> 2013 | G10: =G$5 -> 2014 | H10: =H$5 -> 2015/12A | I10: =I$5 -> 2015/0E | J10: =J$5 -> 2015 | ... O10: =O$5 -> 2020
B15: 매출액 | C15: =매출액!C6 -> 101202.83 | D15: =매출액!D6 -> 120090.95 | E15: =매출액!E6 -> 182279.27 | F15: =매출액!F6 -> 211683.37 | G15: =매출액!G6 -> 251810.75 | H15: =매출액!H6 -> 214888.12 | I15: =매출액!I6 -> 0 | J15: =매출액!J6 -> 214888.12 | ... O15: =매출액!O6 -> 284669.53
B17: Capital Expenditure | R17: 가정 | T17: 확정 | U17: 비고
B18: =unit -> KRW Millions | C18: =C$5 -> 2010 | D18: =D$5 -> 2011 | E18: =E$5 -> 2012 | F18: =F$5 -> 2013 | G18: =G$5 -> 2014 | H18: =H$5 -> 2015/12A | I18: =I$5 -> 2015/0E | J18: =J$5 -> 2015 | ... O18: =O$5 -> 2020 | R18: 최초적용 | S18: 추세 및 인터뷰 등 | T18: 적용사항
B19: 유무형자산 Capex | C19: =C21+C39 -> 740.09 | D19: =D21+D39 -> 1200.436 | E19: =E21+E39 -> 598.167 | F19: =F21+F39 -> 7756.671 | G19: =G21+G39 -> 1132.61 | H19: =H21+H39 -> 762.43818 | I19: =I21+I39 -> 0 | J19: =J21+J39 -> 762.43818 | ... O19: =O21+O39 -> 1205.403
B20: % of sales | C20: =C19/C$15 -> 0.0073129379 | D20: =D19/D$15 -> 0.0099960576 | E20: =E19/E$15 -> 0.0032815965 | F20: =F19/F$15 -> 0.036642798 | G20: =G19/G$15 -> 0.004497862
B21: 유형자산 | C21: =C23+C25+C27+C29+C31+C33+C35+C37 -> 722.686 | D21: =D23+D25+D27+D29+D31+D33+D35+D37 -> 1166.036 | E21: =E23+E25+E27+E29+E31+E33+E35+E37 -> 450.257 | F21: =F23+F25+F27+F29+F31+F33+F35+F37 -> 7719.281 | G21: =G23+G25+G27+G29+G31+G33+G35+G37 -> 1125.224 | H21: =H23+H25+H27+H29+H31+H33+H35+H37 -> 730.25418 | I21: =I23+I25+I27+I29+I31+I33+I35+I37 -> 0 | J21: =J23+J25+J27+J29+J31+J33+J35+J37 -> 730.25418 | ... O21: =O23+O25+O27+O29+O31+O33+O35+O37 -> 1122.6421
B22: % of sales | C22: =C21/C$15 -> 0.0071409664 | D22: =D21/D$15 -> 0.009709608 | E22: =E21/E$15 -> 0.0024701493 | F22: =F21/F$15 -> 0.036466167 | G22: =G21/G$15 -> 0.0044685305 | H22: =H21/H$15 -> 0.0033982994
B23: 토지 | C23: =CAPEX_주석사항!AL23/1000 -> 0 | D23: =CAPEX_주석사항!AD23/1000 -> 0 | E23: =CAPEX_주석사항!V23/1000 -> 0 | F23: =CAPEX_주석사항!N23/1000 -> 6695.647 | G23: =CAPEX_주석사항!E23/1000 -> 310.939 | H23: 0 | I23: 0 | J23: =H23+I23 -> 0 | K23: 0 | L23: 0 | M23: 0 | N23: 0 | O23: 0 | R23: 발생 없음
B24: % of sales | C24: =C23/C$15 -> 0 | D24: =D23/D$15 -> 0 | E24: =E23/E$15 -> 0 | F24: =F23/F$15 -> 0.031630482 | G24: =G23/G$15 -> 0.0012348123 | H24: =H23/H$15 -> 0 | I24: =I23/I$15 -> #DIV/0! | J24: =J23/J$15 -> 0
B25: 기계장치 | C25: =CAPEX_주석사항!AL24/1000 -> 49.67 | D25: =CAPEX_주석사항!AD24/1000 -> 556.22 | E25: =CAPEX_주석사항!V24/1000 -> 123 | F25: =CAPEX_주석사항!N24/1000 -> 19.7 | G25: =CAPEX_주석사항!E24/1000 -> 34.057 | H25: =SUM('기존(정액)'!J77:J81)/1000000 -> 25.14 | I25: 0 | J25: =H25+I25 -> 25.14 | K25: =K$15*K26 -> 279.93974 | L25: =L$15*L26 -> 289.62048 | M25: =M$15*M26 -> 299.90345 | N25: =N$15*N26 -> 310.54175 | O25: =O$15*O26 -> 321.7761 | R25: 과거 5개년 평균 매출액대비 비율
B26: % of sales | C26: =C25/C$15 -> 0.00049079656 | D26: =D25/D$15 -> 0.0046316564 | E26: =E25/E$15 -> 0.00067478876 | F26: =F25/F$15 -> 9.3063523e-05 | G26: =G25/G$15 -> 0.0001352484 | H26: =H25/H$15 -> 0.00011699111 | I26: =I25/I$15 -> #DIV/0! | J26: =J25/J$15 -> 0.00011699111 | K26: =AVERAGE(D26:H26) -> 0.0011303496 | L26: =K26 -> 0.0011303496 | M26: =L26 -> 0.0011303496 | N26: =M26 -> 0.0011303496 | O26: =N26 -> 0.0011303496
B27: 차량운반구 | C27: =CAPEX_주석사항!AL25/1000 -> 184.293 | D27: =CAPEX_주석사항!AD25/1000 -> 0 | E27: =CAPEX_주석사항!V25/1000 -> 0 | F27: =CAPEX_주석사항!N25/1000 -> 231.118 | G27: =CAPEX_주석사항!E25/1000 -> 70.14 | H27: ='기존(정액)'!N89/1000000 -> 75.690033 | I27: 0 | J27: =H27+I27 -> 75.690033 | K27: =K$15*K28 -> 85.322141 | L27: =L$15*L28 -> 88.272709 | M27: =M$15*M28 -> 91.406833 | N27: =N$15*N28 -> 94.649254 | O27: =O$15*O28 -> 98.073343 | R27: 과거 5개년 평균 매출액대비 비율
B28: % of sales | C28: =C27/C$15 -> 0.0018210262 | D28: =D27/D$15 -> 0 | E28: =E27/E$15 -> 0 | F28: =F27/F$15 -> 0.0010918099 | G28: =G27/G$15 -> 0.00027854252 | H28: =H27/H$15 -> 0.00035222995 | I28: =I27/I$15 -> #DIV/0! | J28: =J27/J$15 -> 0.00035222995 | K28: =AVERAGE(D28:H28) -> 0.00034451648 | L28: =K28 -> 0.00034451648 | M28: =L28 -> 0.00034451648 | N28: =M28 -> 0.00034451648 | O28: =N28 -> 0.00034451648
B29: 집기비품 | C29: =CAPEX_주석사항!AL26/1000 -> 118.482 | D29: =CAPEX_주석사항!AD26/1000 -> 366.842 | E29: =CAPEX_주석사항!V26/1000 -> 173.267 | F29: =CAPEX_주석사항!N26/1000 -> 211.332 | G29: =CAPEX_주석사항!E26/1000 -> 142.773 | H29: =SUM('기존(정액)'!J369:J417)/1000000 -> 243.92215 | I29: 0 | J29: =H29+I29 -> 243.92215 | K29: =K$15*K30 -> 332.14345 | L29: =L$15*L30 -> 343.62946 | M29: =M$15*M30 -> 355.83003 | N29: =N$15*N30 -> 368.45218 | O29: =O$15*O30 -> 381.78154 | R29: 과거 5개년 평균 매출액대비 비율
B30: % of sales | C30: =C29/C$15 -> 0.001170738 | D30: =D29/D$15 -> 0.0030547016 | E30: =E29/E$15 -> 0.00095055792 | F30: =F29/F$15 -> 0.00099834012 | G30: =G29/G$15 -> 0.00056698533 | H30: =H29/H$15 -> 0.0011351123 | I30: =I29/I$15 -> #DIV/0! | J30: =J29/J$15 -> 0.0011351123 | K30: =AVERAGE(D30:H30) -> 0.0013411394 | L30: =K30 -> 0.0013411394 | M30: =L30 -> 0.0013411394 | N30: =M30 -> 0.0013411394 | O30: =N30 -> 0.0013411394
B31: 시설장치 | C31: =CAPEX_주석사항!AL27/1000 -> 1.5 | D31: =CAPEX_주석사항!AD27/1000 -> 24.212 | E31: =CAPEX_주석사항!V27/1000 -> 24.893 | F31: =CAPEX_주석사항!N27/1000 -> 418.801 | G31: =CAPEX_주석사항!E27/1000 -> 23.874 | H31: =SUM('기존(정액)'!J447:J458)/1000000 -> 373.532 | I31: 0 | J31: =H31+I31 -> 373.532 | K31: =K$15*K32 -> 205.54011 | L31: =L$15*L32 -> 212.648 | M31: =M$15*M32 -> 220.19807 | N31: =N$15*N32 -> 228.00903 | O31: =O$15*O32 -> 236.25762 | R31: 과거 5개년 평균 매출액대비 비율 | S31: 삼환빌딩 공사 건으로 과다발생 | T31: 2010-2014년 적용
B32: % of sales | C32: =C31/C$15 -> 1.482172e-05 | D32: =D31/D$15 -> 0.00020161387 | E32: =E31/E$15 -> 0.00013656518 | F32: =F31/F$15 -> 0.0019784313 | G32: =G31/G$15 -> 9.4809297e-05 | H32: =H31/H$15 -> 0.0017382627 | I32: =I31/I$15 -> #DIV/0! | J32: =J31/J$15 -> 0.0017382627 | K32: =AVERAGE(D32:H32) -> 0.00082993646 | L32: =K32 -> 0.00082993646 | M32: =L32 -> 0.00082993646 | N32: =M32 -> 0.00082993646 | O32: =N32 -> 0.00082993646
B33: 운용리스자산 | C33: =CAPEX_주석사항!AL28/1000 -> 0 | D33: =CAPEX_주석사항!AD28/1000 -> 0 | E33: =CAPEX_주석사항!V28/1000 -> 129.097 | F33: =CAPEX_주석사항!N28/1000 -> 142.683 | G33: =CAPEX_주석사항!E28/1000 -> 12.754 | H33: =SUM('기존(정액)'!O525)/1000000 -> 11.97 | I33: 0 | J33: =H33+I33 -> 11.97 | K33: =K$15*K34 -> 73.734108 | L33: =L$15*L34 -> 76.283944 | M33: =M$15*M34 -> 78.992406 | N33: =N$15*N34 -> 81.794458 | O33: =O$15*O34 -> 84.753504
B34: % of sales | C34: =C33/C$15 -> 0 | D34: =D33/D$15 -> 0 | E34: =E33/E$15 -> 0.00070823743 | F34: =F33/F$15 -> 0.00067403973 | G34: =G33/G$15 -> 5.0649149e-05 | H34: =H33/H$15 -> 5.5703404e-05 | I34: =I33/I$15 -> #DIV/0! | J34: =J33/J$15 -> 5.5703404e-05 | K34: =AVERAGE(D34:H34) -> 0.00029772594 | L34: =K34 -> 0.00029772594 | M34: =L34 -> 0.00029772594 | N34: =M34 -> 0.00029772594 | O34: =N34 -> 0.00029772594
B35: 조형물 | C35: =CAPEX_주석사항!AL29/1000 -> 0 | D35: =CAPEX_주석사항!AD29/1000 -> 0 | E35: =CAPEX_주석사항!V29/1000 -> 0 | F35: =CAPEX_주석사항!N29/1000 -> 0 | G35: =CAPEX_주석사항!E29/1000 -> 0 | H35: 0 | I35: 0 | J35: =H35+I35 -> 0
B36: % of sales | C36: =C35/C$15 -> 0 | D36: =D35/D$15 -> 0 | E36: =E35/E$15 -> 0 | F36: =F35/F$15 -> 0 | G36: =G35/G$15 -> 0 | H36: =H35/H$15 -> 0 | I36: =I35/I$15 -> #DIV/0! | J36: =J35/J$15 -> 0
B37: 건설중인자산 | C37: =CAPEX_주석사항!AL30/1000 -> 368.741 | D37: =CAPEX_주석사항!AD30/1000 -> 218.762 | E37: =CAPEX_주석사항!V30/1000 -> 0 | F37: =CAPEX_주석사항!N30/1000 -> 0 | G37: =CAPEX_주석사항!E30/1000 -> 530.687 | H37: 0 | I37: 0 | J37: =H37+I37 -> 0
B38: % of sales | C38: =C37/C$15 -> 0.0036435839 | D38: =D37/D$15 -> 0.0018216361 | E38: =E37/E$15 -> 0 | F38: =F37/F$15 -> 0 | G38: =G37/G$15 -> 0.0021074835 | H38: =H37/H$15 -> 0 | I38: =I37/I$15 -> #DIV/0! | J38: =J37/J$15 -> 0
B39: 무형자산 | C39: =C41+C43+C45 -> 17.404 | D39: =D41+D43+D45 -> 34.4 | E39: =E41+E43+E45 -> 147.91 | F39: =F41+F43+F45 -> 37.39 | G39: =G41+G43+G45 -> 7.386 | H39: =H41+H43+H45 -> 32.184 | I39: =I41+I43+I45 -> 0 | J39: =J41+J43+J45 -> 32.184 | ... O39: =O41+O43+O45 -> 82.760891
B40: % of sales | C40: =C39/C$15 -> 0.00017197148 | D40: =D39/D$15 -> 0.00028644957 | E40: =E39/E$15 -> 0.0008114472 | F40: =F39/F$15 -> 0.00017663173 | G40: =G39/G$15 -> 2.9331552e-05
B41: 영업권 | C41: =CAPEX_주석사항!AL36/1000 -> 0 | D41: =CAPEX_주석사항!AD36/1000 -> 0 | E41: 0 | F41: 0 | G41: 0 | H41: 0 | I41: 0 | J41: 0 | K41: 0 | L41: 0 | M41: 0 | N41: 0 | O41: 0 | R41: 발생 없음
B42: % of sales | C42: =C41/C$15 -> 0 | D42: =D41/D$15 -> 0 | E42: =E41/E$15 -> 0 | F42: =F41/F$15 -> 0 | G42: =G41/G$15 -> 0
B43: 산업재산권 | C43: =CAPEX_주석사항!AL37/1000 -> 0 | D43: =CAPEX_주석사항!AD37/1000 -> 0 | E43: =CAPEX_주석사항!V36/1000 -> 0 | F43: =CAPEX_주석사항!N36/1000 -> 0 | G43: =CAPEX_주석사항!E36/1000 -> 0 | H43: 0 | R43: 발생 없음
B44: % of sales | C44: =C43/C$15 -> 0 | D44: =D43/D$15 -> 0 | E44: =E43/E$15 -> 0 | F44: =F43/F$15 -> 0 | G44: =G43/G$15 -> 0
B45: 소프트웨어 | C45: =CAPEX_주석사항!AL38/1000 -> 17.404 | D45: =CAPEX_주석사항!AD38/1000 -> 34.4 | E45: =CAPEX_주석사항!V37/1000 -> 147.91 | F45: =CAPEX_주석사항!N37/1000 -> 37.39 | G45: =CAPEX_주석사항!E37/1000 -> 7.386 | H45: =SUM('기존(정액)'!J516:J519)/1000000 -> 32.184 | I45: 0 | J45: =H45+I45 -> 32.184 | K45: =K$15*K46 -> 72.000568 | L45: =L$15*L46 -> 74.490456 | M45: =M$15*M46 -> 77.135241 | N45: =N$15*N46 -> 79.871414 | O45: =O$15*O46 -> 82.760891 | R45: 과거 5개년 평균 매출액대비 비율
B46: % of sales | C46: =C45/C$15 -> 0.00017197148 | D46: =D45/D$15 -> 0.00028644957 | E46: =E45/E$15 -> 0.0008114472 | F46: =F45/F$15 -> 0.00017663173 | G46: =G45/G$15 -> 2.9331552e-05 | H46: =H45/H$15 -> 0.00014977096 | J46: =J45/J$15 -> 0.00014977096 | K46: =AVERAGE(D46:H46) -> 0.0002907262 | L46: =K46 -> 0.0002907262 | M46: =L46 -> 0.0002907262 | N46: =M46 -> 0.0002907262 | O46: =N46 -> 0.0002907262
B49: Depreciation & Amortization
B50: =unit -> KRW Millions | C50: =C$5 -> 2010 | D50: =D$5 -> 2011 | E50: =E$5 -> 2012 | F50: =F$5 -> 2013 | G50: =G$5 -> 2014 | H50: =H$5 -> 2015/12A | I50: =I$5 -> 2015/0E | J50: =J$5 -> 2015 | ... O50: =O$5 -> 2020
B51: 유무형자산 상각비 | C51: =C53+C62+C99+C104 -> 677.542 | D51: =D53+D62+D99+D104 -> 599.583 | E51: =E53+E62+E99+E104 -> 554.964 | F51: =F53+F62+F99+F104 -> 711.792 | G51: =G53+G62+G99+G104 -> 741.121 | H51: =H53+H62+H99+H104 -> 712.84854 | I51: =I53+I62+I99+I104 -> 64.479145 | J51: =J53+J62+J99+J104 -> 775.38114 | ... O51: =O53+O62+O99+O104 -> 2179.7868
B52: % of sales | C52: =C51/C$15 -> 0.006694892 | D52: =D51/D$15 -> 0.0049927411 | E52: =E51/E$15 -> 0.003044581 | F52: =F51/F$15 -> 0.0033625315 | G52: =G51/G$15 -> 0.0029431667 | H52: =H51/H$15 -> 0.0033173008 | I52: =I51/I$15 -> #DIV/0! | J52: =J51/J$15 -> 0.0036083015 | ... O52: =O51/O$15 -> 0.0076572536
B53: 감가상각비 | C53: =C54+C62 -> 230.157 | D53: =D54+D62 -> 321.594 | E53: =E54+E62 -> 455.79 | F53: =F54+F62 -> 612.66 | G53: =G54+G62 -> 645.885 | H53: =H54+H62 -> 650.35451 | I53: =I54+I62 -> 59.795354 | J53: =J54+J62 -> 710.14986 | ... O53: =O54+O62 -> 1089.7033
B54: 감가상각비(기존 유형자산) | C54: =SUM(C55:C61) -> 230.157 | D54: =SUM(D55:D61) -> 321.594 | E54: =SUM(E55:E61) -> 455.79 | F54: =SUM(F55:F61) -> 612.66 | G54: =SUM(G55:G61) -> 645.885 | H54: =SUM(H55:H61) -> 650.35451 | I54: =SUM(I55:I61) -> 59.795354 | J54: =SUM(J55:J61) -> 710.14986 | ... O54: =SUM(O55:O61) -> 154.05679
B55: 기계장치 | C55: =-CAPEX_주석사항!AN24/1000 -> 91.107 | D55: =-CAPEX_주석사항!AF24/1000 -> 161.966 | E55: =-CAPEX_주석사항!X24/1000 -> 215.664 | F55: =-CAPEX_주석사항!P24/1000 -> 230.532 | G55: =-CAPEX_주석사항!G24/1000 -> 225.129 | H55: ='기존(정액)'!Q2/1000000 -> 177.75298 | I55: ='기존(정액)'!U2/1000000 -> 14.242933 | J55: =H55+I55 -> 191.99591 | K55: ='기존(정액)'!V2/1000000 -> 191.99591 | L55: ='기존(정액)'!W2/1000000 -> 97.329535 | M55: ='기존(정액)'!X2/1000000 -> 33.8272 | N55: ='기존(정액)'!Y2/1000000 -> 13.177866 | O55: ='기존(정액)'!Z2/1000000 -> 9.5619333
B56: 차량운반구 | C56: =-CAPEX_주석사항!AN25/1000 -> 38.313 | D56: =-CAPEX_주석사항!AF25/1000 -> 36.859 | E56: =-CAPEX_주석사항!X25/1000 -> 36.859 | F56: =-CAPEX_주석사항!P25/1000 -> 61.231 | G56: =-CAPEX_주석사항!G25/1000 -> 62.618 | H56: ='기존(정액)'!Q3/1000000 -> 71.25035 | I56: ='기존(정액)'!U3/1000000 -> 6.4773045 | J56: =H56+I56 -> 77.727654 | K56: ='기존(정액)'!V3/1000000 -> 77.727654 | L56: ='기존(정액)'!W3/1000000 -> 77.727654 | M56: ='기존(정액)'!X3/1000000 -> 77.725654 | N56: ='기존(정액)'!Y3/1000000 -> 53.352256 | O56: ='기존(정액)'!Z3/1000000 -> 8.122026
B57: 집기비품 | C57: =-CAPEX_주석사항!AN26/1000 -> 76.598 | D57: =-CAPEX_주석사항!AF26/1000 -> 103.117 | E57: =-CAPEX_주석사항!X26/1000 -> 160.069 | F57: =-CAPEX_주석사항!P26/1000 -> 182.274 | G57: =-CAPEX_주석사항!G26/1000 -> 198.285 | H57: ='기존(정액)'!Q4/1000000 -> 206.34112 | I57: ='기존(정액)'!U4/1000000 -> 19.283281 | J57: =H57+I57 -> 225.6244 | K57: ='기존(정액)'!V4/1000000 -> 225.6244 | L57: ='기존(정액)'!W4/1000000 -> 204.08098 | M57: ='기존(정액)'!X4/1000000 -> 133.13819 | N57: ='기존(정액)'!Y4/1000000 -> 87.451349 | O57: ='기존(정액)'!Z4/1000000 -> 60.24136
B58: 시설장치 | C58: =-CAPEX_주석사항!AN27/1000 -> 24.139 | D58: =-CAPEX_주석사항!AF27/1000 -> 19.652 | E58: =-CAPEX_주석사항!X27/1000 -> 31.92 | F58: =-CAPEX_주석사항!P27/1000 -> 93.815 | G58: =-CAPEX_주석사항!G27/1000 -> 114.778 | H58: ='기존(정액)'!Q5/1000000 -> 152.39295 | I58: ='기존(정액)'!U5/1000000 -> 15.812602 | J58: =H58+I58 -> 168.20555 | K58: ='기존(정액)'!V5/1000000 -> 168.20555 | L58: ='기존(정액)'!W5/1000000 -> 180.94101 | M58: ='기존(정액)'!X5/1000000 -> 164.68472 | N58: ='기존(정액)'!Y5/1000000 -> 97.386795 | O58: ='기존(정액)'!Z5/1000000 -> 76.131475
B59: 운용리스자산 | C59: =-CAPEX_주석사항!AN28/1000 -> 0 | D59: =-CAPEX_주석사항!AF28/1000 -> 0 | E59: =-CAPEX_주석사항!X28/1000 -> 11.278 | F59: =-CAPEX_주석사항!P28/1000 -> 44.808 | G59: =-CAPEX_주석사항!G28/1000 -> 45.075 | H59: ='기존(정액)'!Q8/1000000 -> 42.617113 | I59: ='기존(정액)'!U8/1000000 -> 3.9792333 | J59: =H59+I59 -> 46.596346 | K59: ='기존(정액)'!V8/1000000 -> 46.596346 | L59: ='기존(정액)'!W8/1000000 -> 47.7508 | M59: ='기존(정액)'!X8/1000000 -> 47.7508 | N59: ='기존(정액)'!Y8/1000000 -> 9.7436177 | O59: ='기존(정액)'!Z8/1000000 -> 0
B60: 조형물 | C60: =-CAPEX_주석사항!AN29/1000 -> 0 | D60: =-CAPEX_주석사항!AF29/1000 -> 0 | E60: =-CAPEX_주석사항!X29/1000 -> 0 | F60: =-CAPEX_주석사항!P29/1000 -> 0 | G60: =-CAPEX_주석사항!G29/1000 -> 0 | H60: 0 | I60: 0 | J60: =H60+I60 -> 0 | K60: 0 | L60: 0 | M60: 0 | N60: 0 | O60: 0
B61: 건설중인자산 | C61: =-CAPEX_주석사항!AN30/1000 -> 0 | D61: =-CAPEX_주석사항!AF30/1000 -> 0 | E61: =-CAPEX_주석사항!X30/1000 -> 0 | F61: =-CAPEX_주석사항!P30/1000 -> 0 | G61: =-CAPEX_주석사항!G30/1000 -> 0 | H61: 0 | I61: 0 | J61: =H61+I61 -> 0 | K61: 0 | L61: 0 | M61: 0 | N61: 0 | O61: 0
B62: 감가상각비(신규 유형자산) | C62: =SUM(C63,C69,C75,C81,C87,C93) -> 0 | D62: =SUM(D63,D69,D75,D81,D87,D93) -> 0 | E62: =SUM(E63,E69,E75,E81,E87,E93) -> 0 | F62: =SUM(F63,F69,F75,F81,F87,F93) -> 0 | G62: =SUM(G63,G69,G75,G81,G87,G93) -> 0 | H62: =SUM(H63,H69,H75,H81,H87,H93) -> 0 | I62: =SUM(I63,I69,I75,I81,I87,I93) -> 0 | J62: =SUM(J63,J69,J75,J81,J87,J93) -> 0 | ... O62: =SUM(O63,O69,O75,O81,O87,O93) -> 935.64653
B63: 기계장치 | K63: =SUM(K64:K68) -> 27.993974 | L63: =SUM(L64:L68) -> 84.949995 | M63: =SUM(M64:M68) -> 143.90239 | N63: =SUM(N64:N68) -> 204.94691 | O63: =SUM(O64:O68) -> 268.17869
B64: 2016년 취득 | K64: =$K$25/5/2 -> 27.993974 | L64: =$K$25/5 -> 55.987948 | M64: =$K$25/5 -> 55.987948 | N64: =$K$25/5 -> 55.987948 | O64: =$K$25/5 -> 55.987948
B65: 2017년 취득 | L65: =$L$25/5/2 -> 28.962048 | M65: =$L$25/5 -> 57.924095 | N65: =$L$25/5 -> 57.924095 | O65: =$L$25/5 -> 57.924095
B66: 2018년 취득 | M66: =$M$25/5/2 -> 29.990345 | N66: =$M$25/5 -> 59.980691 | O66: =$M$25/5 -> 59.980691
B67: 2019년 취득 | N67: =$N$25/5/2 -> 31.054175 | O67: =$N$25/5 -> 62.108351
B68: 2020년 취득 | O68: =$O$25/5/2 -> 32.17761
B69: =B56 -> 차량운반구 | K69: =SUM(K70:K74) -> 8.5322141 | L69: =SUM(L70:L74) -> 25.891699 | M69: =SUM(M70:M74) -> 43.859653 | N69: =SUM(N70:N74) -> 62.465262 | O69: =SUM(O70:O74) -> 81.737522
B70: 2016년 취득 | K70: =$K$27/5/2 -> 8.5322141 | L70: =$K$27/5 -> 17.064428 | M70: =$K$27/5 -> 17.064428 | N70: =$K$27/5 -> 17.064428 | O70: =$K$27/5 -> 17.064428
B71: 2017년 취득 | L71: =$L$27/5/2 -> 8.8272709 | M71: =$L$27/5 -> 17.654542 | N71: =$L$27/5 -> 17.654542 | O71: =$L$27/5 -> 17.654542
B72: 2018년 취득 | M72: =$M$27/5/2 -> 9.1406833 | N72: =$M$27/5 -> 18.281367 | O72: =$M$27/5 -> 18.281367
B73: 2019년 취득 | N73: =$N$27/5/2 -> 9.4649254 | O73: =$N$27/5 -> 18.929851
B74: 2020년 취득 | O74: =$O$27/5/2 -> 9.8073343
B75: =B57 -> 집기비품 | K75: =SUM(K76:K80) -> 33.214345 | L75: =SUM(L76:L80) -> 100.79164 | M75: =SUM(M76:M80) -> 170.73759 | N75: =SUM(N76:N80) -> 243.16581 | O75: =SUM(O76:O80) -> 318.18918
B76: 2016년 취득 | K76: =$K$29/5/2 -> 33.214345 | L76: =$K$29/5 -> 66.428689 | M76: =$K$29/5 -> 66.428689 | N76: =$K$29/5 -> 66.428689 | O76: =$K$29/5 -> 66.428689
B77: 2017년 취득 | L77: =$L$29/5/2 -> 34.362946 | M77: =$L$29/5 -> 68.725893 | N77: =$L$29/5 -> 68.725893 | O77: =$L$29/5 -> 68.725893
B78: 2018년 취득 | M78: =$M$29/5/2 -> 35.583003 | N78: =$M$29/5 -> 71.166006 | O78: =$M$29/5 -> 71.166006
B79: 2019년 취득 | N79: =$N$29/5/2 -> 36.845218 | O79: =$N$29/5 -> 73.690437
B80: 2020년 취득 | O80: =$O$29/5/2 -> 38.178154
B81: =B58 -> 시설장치 | K81: =SUM(K82:K86) -> 20.554011 | L81: =SUM(L82:L86) -> 62.372823 | M81: =SUM(M82:M86) -> 105.65743 | N81: =SUM(N82:N86) -> 150.47814 | O81: =SUM(O82:O86) -> 196.9048
B82: 2016년 취득 | K82: =$K$31/5/2 -> 20.554011 | L82: =$K$31/5 -> 41.108023 | M82: =$K$31/5 -> 41.108023 | N82: =$K$31/5 -> 41.108023 | O82: =$K$31/5 -> 41.108023
B83: 2017년 취득 | L83: =$L$31/5/2 -> 21.2648 | M83: =$L$31/5 -> 42.5296 | N83: =$L$31/5 -> 42.5296 | O83: =$L$31/5 -> 42.5296
B84: 2018년 취득 | M84: =$M$31/5/2 -> 22.019807 | N84: =$M$31/5 -> 44.039614 | O84: =$M$31/5 -> 44.039614
B85: 2019년 취득 | N85: =$N$31/5/2 -> 22.800903 | O85: =$N$31/5 -> 45.601805
B86: 2020년 취득 | O86: =$O$31/5/2 -> 23.625762
B87: =B59 -> 운용리스자산 | K87: =SUM(K88:K92) -> 7.3734108 | L87: =SUM(L88:L92) -> 22.375216 | M87: =SUM(M88:M92) -> 37.902851 | N87: =SUM(N88:N92) -> 53.981537 | O87: =SUM(O88:O92) -> 70.636334
B88: 2016년 취득 | K88: =$K$33/5/2 -> 7.3734108 | L88: =$K$33/5 -> 14.746822 | M88: =$K$33/5 -> 14.746822 | N88: =$K$33/5 -> 14.746822 | O88: =$K$33/5 -> 14.746822
B89: 2017년 취득 | L89: =$L$33/5/2 -> 7.6283944 | M89: =$L$33/5 -> 15.256789 | N89: =$L$33/5 -> 15.256789 | O89: =$L$33/5 -> 15.256789
B90: 2018년 취득 | M90: =$M$33/5/2 -> 7.8992406 | N90: =$M$33/5 -> 15.798481 | O90: =$M$33/5 -> 15.798481
B91: 2019년 취득 | N91: =$N$33/5/2 -> 8.1794458 | O91: =$N$33/5 -> 16.358892
B92: 2020년 취득 | O92: =$O$33/5/2 -> 8.4753504
B93: =B60 -> 조형물 | K93: =SUM(K94:K98) -> 0 | L93: =SUM(L94:L98) -> 0 | M93: =SUM(M94:M98) -> 0 | N93: =SUM(N94:N98) -> 0 | O93: =SUM(O94:O98) -> 0
B94: 2016년 취득 | K94: =$K$35/5/2 -> 0 | L94: =$K$35/5 -> 0 | M94: =$K$35/5 -> 0 | N94: =$K$35/5 -> 0 | O94: =$K$35/5 -> 0
B95: 2017년 취득 | L95: =$L$35/5/2 -> 0 | M95: =$L$35/5 -> 0 | N95: =$L$35/5 -> 0 | O95: =$L$35/5 -> 0
B96: 2018년 취득 | M96: =$M$35/5/2 -> 0 | N96: =$M$35/5 -> 0 | O96: =$M$35/5 -> 0
B97: 2019년 취득 | N97: =$N$35/5/2 -> 0 | O97: =$N$35/5 -> 0
B98: 2020년 취득 | O98: =$O$35/5/2 -> 0
B99: 무형자산상각비 | C99: =C100+C104 -> 447.385 | D99: =D100+D104 -> 277.989 | E99: =E100+E104 -> 99.174 | F99: =F100+F104 -> 99.132 | G99: =G100+G104 -> 95.236 | H99: =H100+H104 -> 62.494038 | I99: =I100+I104 -> 4.6837907 | J99: =J100+J104 -> 65.231279 | ... O99: =O100+O104 -> 77.21846
B100: 무형자산상각비(기존 무형자산) | C100: =SUM(C101:C103) -> 447.385 | D100: =SUM(D101:D103) -> 277.989 | E100: =SUM(E101:E103) -> 99.174 | F100: =SUM(F101:F103) -> 99.132 | G100: =SUM(G101:G103) -> 95.236 | H100: =SUM(H101:H103) -> 62.494038 | I100: =SUM(I101:I103) -> 4.6837907 | J100: =SUM(J101:J103) -> 65.231279 | ... O100: =SUM(O101:O103) -> 0
B101: 영업권 | C101: =-CAPEX_주석사항!AM36/1000 -> 402.304 | D101: =-CAPEX_주석사항!AE36/1000 -> 201.153
B102: 산업재산권 | C102: =-CAPEX_주석사항!AM37/1000 -> 0.166 | D102: =-CAPEX_주석사항!AE37/1000 -> 0.508 | E102: =-CAPEX_주석사항!W36/1000 -> 0.507 | F102: =-CAPEX_주석사항!O36/1000 -> 0.409 | G102: =-CAPEX_주석사항!F36/1000 -> 0.41 | H102: ='기존(정액)'!Q6/1000000 -> 1.94655
B103: 소프트웨어 | C103: =-CAPEX_주석사항!AM38/1000 -> 44.915 | D103: =-CAPEX_주석사항!AE38/1000 -> 76.328 | E103: =-CAPEX_주석사항!W37/1000 -> 98.667 | F103: =-CAPEX_주석사항!O37/1000 -> 98.723 | G103: =-CAPEX_주석사항!F37/1000 -> 94.826 | H103: ='기존(정액)'!Q7/1000000 -> 60.547488 | I103: ='기존(정액)'!U7/10^6 -> 4.6837907 | J103: =H103+I103 -> 65.231279 | K103: ='기존(정액)'!W7/10^6 -> 21.832407 | L103: ='기존(정액)'!X7/10^6 -> 10.75599 | M103: ='기존(정액)'!Y7/10^6 -> 9.0216501 | N103: ='기존(정액)'!Z7/10^6 -> 0.91033367 | O103: ='기존(정액)'!AA7/10^6 -> 0
B104: 무형자산상각비(신규 무형자산) | C104: =SUM(C105,C111,C117) -> 0 | D104: =SUM(D105,D111,D117) -> 0 | E104: =SUM(E105,E111,E117) -> 0 | F104: =SUM(F105,F111,F117) -> 0 | G104: =SUM(G105,G111,G117) -> 0 | H104: =SUM(H105,H111,H117) -> 0 | I104: =SUM(I105,I111,I117) -> 0 | J104: =SUM(J105,J111,J117) -> 0 | ... O104: =SUM(O105,O111,O117) -> 77.21846
B105: =B101 -> 영업권 | K105: =SUM(K106:K110) -> 0 | L105: =SUM(L106:L110) -> 0 | M105: =SUM(M106:M110) -> 0 | N105: =SUM(N106:N110) -> 0 | O105: =SUM(O106:O110) -> 0
B106: 2016년 취득 | K106: =$K$41/5/2 -> 0 | L106: =$K$41/5 -> 0 | M106: =$K$41/5 -> 0 | N106: =$K$41/5 -> 0 | O106: =$K$41/5 -> 0
B107: 2017년 취득 | L107: =$L$41/5/2 -> 0 | M107: =$L$41/5 -> 0 | N107: =$L$41/5 -> 0 | O107: =$L$41/5 -> 0
B108: 2018년 취득 | M108: =$M$41/5/2 -> 0 | N108: =$M$41/5 -> 0 | O108: =$M$41/5 -> 0
B109: 2019년 취득 | N109: =$N$41/5/2 -> 0 | O109: =$N$41/5 -> 0
...

Sheet WC
B1: ="Project"&" "&Title!L6 -> Project IT | P1: =Des!C12 -> DRAFT - For Discussion Purposes Only
B2: 운전자본
B4: 운전자본
B5: KRW Millions | C5: ='Pro forma'!C$5 -> 2010 | D5: ='Pro forma'!D$5 -> 2011 | E5: ='Pro forma'!E$5 -> 2012 | F5: ='Pro forma'!F$5 -> 2013 | G5: ='Pro forma'!G$5 -> 2014 | H5: ='Pro forma'!H$5 -> 2015/12A | I5: ='Pro forma'!I$5 -> 2015/0E | J5: ='Pro forma'!J$5 -> 2015 | ... O5: ='Pro forma'!O$5 -> 2020 | P5: Terminal
