Workbook

Sheet Summary
A1: =MID(CELL("filename",A1),FIND("]",CELL("filename",A1))+1,255) -> Summary
B3: 1. Proforma
L5: 2021(A) | M5: 2022(A) | N5: 2023(A) | O5: 24.3m(A) | P5: 24.9m(E) | Q5: 2024(F) | R5: 2025(F) | S5: 2026(F) | T5: 2027(F) | U5: 2028(F)
B6: 매출액 | O6: ='Proforma PL'!O6 -> 89716.379 | P6: ='Proforma PL'!P6 -> 312170.78 | Q6: ='Proforma PL'!Q6 -> 401887.16 | R6: ='Proforma PL'!R6 -> 384025.11 | S6: ='Proforma PL'!S6 -> 433849.88 | T6: ='Proforma PL'!T6 -> 483807.54 | U6: ='Proforma PL'!U6 -> 535532.09
C7: 국내 | O7: ='Proforma PL'!O7 -> 32117.625 | P7: ='Proforma PL'!P7 -> 134103.49 | Q7: ='Proforma PL'!Q7 -> 166221.11 | R7: ='Proforma PL'!R7 -> 162076.51 | S7: ='Proforma PL'!S7 -> 186135.91 | T7: ='Proforma PL'!T7 -> 207378.78 | U7: ='Proforma PL'!U7 -> 232356.82
C8: 미주 | O8: ='Proforma PL'!O8 -> 13939.073 | P8: ='Proforma PL'!P8 -> 52334.224 | Q8: ='Proforma PL'!Q8 -> 66273.296 | R8: ='Proforma PL'!R8 -> 59731.026 | S8: ='Proforma PL'!S8 -> 64926.093 | T8: ='Proforma PL'!T8 -> 69442.616 | U8: ='Proforma PL'!U8 -> 76922.963
C9: 유럽 | O9: ='Proforma PL'!O9 -> 13488.451 | P9: ='Proforma PL'!P9 -> 48793.04 | Q9: ='Proforma PL'!Q9 -> 62281.491 | R9: ='Proforma PL'!R9 -> 59615.67 | S9: ='Proforma PL'!S9 -> 66472.55 | T9: ='Proforma PL'!T9 -> 72281.457 | U9: ='Proforma PL'!U9 -> 78126.589
C10: 중국 | O10: ='Proforma PL'!O10 -> 14020.191 | P10: ='Proforma PL'!P10 -> 36602.449 | Q10: ='Proforma PL'!Q10 -> 50622.64 | R10: ='Proforma PL'!R10 -> 53388.54 | S10: ='Proforma PL'!S10 -> 63265.924 | T10: ='Proforma PL'!T10 -> 76460.228 | U10: ='Proforma PL'!U10 -> 83020.2
C11: 직수출 | O11: ='Proforma PL'!O11 -> 16151.039 | P11: ='Proforma PL'!P11 -> 40337.577 | Q11: ='Proforma PL'!Q11 -> 56488.616 | R11: ='Proforma PL'!R11 -> 49213.365 | S11: ='Proforma PL'!S11 -> 53049.402 | T11: ='Proforma PL'!T11 -> 58244.454 | U11: ='Proforma PL'!U11 -> 65105.515
B12: 매출원가 | O12: ='Proforma PL'!O12 -> 68482.371 | P12: ='Proforma PL'!P12 -> 231123.95 | Q12: ='Proforma PL'!Q12 -> 299606.7 | R12: ='Proforma PL'!R12 -> 279432.09 | S12: ='Proforma PL'!S12 -> 317959.05 | T12: ='Proforma PL'!T12 -> 356180.13 | U12: ='Proforma PL'!U12 -> 393810.57
B13: 매출총이익 | O13: ='Proforma PL'!O13 -> 21234.008 | P13: ='Proforma PL'!P13 -> 81046.822 | Q13: ='Proforma PL'!Q13 -> 102280.45 | R13: ='Proforma PL'!R13 -> 104593.02 | S13: ='Proforma PL'!S13 -> 115890.83 | T13: ='Proforma PL'!T13 -> 127627.4 | U13: ='Proforma PL'!U13 -> 141721.52
B14: % GP | O14: ='Proforma PL'!O14 -> 0.23667928 | P14: ='Proforma PL'!P14 -> 0.25962335 | Q14: ='Proforma PL'!Q14 -> 0.25450042 | R14: ='Proforma PL'!R14 -> 0.27235985 | S14: ='Proforma PL'!S14 -> 0.26712197 | T14: ='Proforma PL'!T14 -> 0.26379788 | U14: ='Proforma PL'!U14 -> 0.26463683
B15: 판매관리비 | O15: ='Proforma PL'!O15 -> 18313.221 | P15: ='Proforma PL'!P15 -> 60236.142 | Q15: ='Proforma PL'!Q15 -> 78549.363 | R15: ='Proforma PL'!R15 -> 79066.553 | S15: ='Proforma PL'!S15 -> 83876.936 | T15: ='Proforma PL'!T15 -> 88454.287 | U15: ='Proforma PL'!U15 -> 93105.563
B16: 영업이익 | O16: ='Proforma PL'!O16 -> 2920.7872 | P16: ='Proforma PL'!P16 -> 20810.68 | Q16: ='Proforma PL'!Q16 -> 23731.088 | R16: ='Proforma PL'!R16 -> 25526.466 | S16: ='Proforma PL'!S16 -> 32013.897 | T16: ='Proforma PL'!T16 -> 39173.116 | U16: ='Proforma PL'!U16 -> 48615.952
B17: % EBIT | O17: ='Proforma PL'!O17 -> 0.032555786 | P17: ='Proforma PL'!P17 -> 0.066664407 | Q17: ='Proforma PL'!Q17 -> 0.059049134 | R17: ='Proforma PL'!R17 -> 0.066470827 | S17: ='Proforma PL'!S17 -> 0.073790263 | T17: ='Proforma PL'!T17 -> 0.080968387 | U17: ='Proforma PL'!U17 -> 0.090780653
B18: D&A | O18: ='Proforma PL'!O26 -> 1114.4191 | P18: ='Proforma PL'!P26 -> 4387.6363 | Q18: ='Proforma PL'!Q26 -> 5502.0555 | R18: ='Proforma PL'!R26 -> 4388.9114 | S18: ='Proforma PL'!S26 -> 4406.3455 | T18: ='Proforma PL'!T26 -> 4431.8656 | U18: ='Proforma PL'!U26 -> 4510.3795
B19: EBITDA | O19: ='Proforma PL'!O27 -> 4035.2064 | P19: ='Proforma PL'!P27 -> 25198.316 | Q19: ='Proforma PL'!Q27 -> 29233.144 | R19: ='Proforma PL'!R27 -> 29915.378 | S19: ='Proforma PL'!S27 -> 36420.242 | T19: ='Proforma PL'!T27 -> 43604.981 | U19: ='Proforma PL'!U27 -> 53126.332
B20: % EBITDA | O20: ='Proforma PL'!O28 -> 0.044977366 | P20: ='Proforma PL'!P28 -> 0.080719651 | Q20: ='Proforma PL'!Q28 -> 0.072739682 | R20: ='Proforma PL'!R28 -> 0.077899536 | S20: ='Proforma PL'!S28 -> 0.083946646 | T20: ='Proforma PL'!T28 -> 0.090128776 | U20: ='Proforma PL'!U28 -> 0.099202892
B22: 2. DCF
L24: 2021(A) | M24: 2022(A) | N24: 2023(A) | O24: 24.3m(A) | P24: 24.9m(E) | Q24: 2024(F) | R24: 2025(F) | S24: 2026(F) | T24: 2027(F) | U24: 2028(F) | V24: Terminal
B25: Revenue | P25: =P6 -> 312170.78 | Q25: =Q6 -> 401887.16 | R25: =R6 -> 384025.11 | S25: =S6 -> 433849.88 | T25: =T6 -> 483807.54 | U25: =U6 -> 535532.09 | V25: =U25*(1+$I$45) -> 538209.75
B26: COGS | P26: =P12 -> 231123.95 | Q26: =Q12 -> 299606.7 | R26: =R12 -> 279432.09 | S26: =S12 -> 317959.05 | T26: =T12 -> 356180.13 | U26: =U12 -> 393810.57 | V26: =U26*(1+$I$45) -> 395779.62
B27: Gross Profit | P27: =P25-P26 -> 81046.822 | Q27: =Q25-Q26 -> 102280.45 | R27: =R25-R26 -> 104593.02 | S27: =S25-S26 -> 115890.83 | T27: =T25-T26 -> 127627.4 | U27: =U25-U26 -> 141721.52 | V27: =V25-V26 -> 142430.12
B28: % of Revenue | P28: =P27/P$25 -> 0.25962335 | Q28: =Q27/Q$25 -> 0.25450042 | R28: =R27/R$25 -> 0.27235985 | S28: =S27/S$25 -> 0.26712197 | T28: =T27/T$25 -> 0.26379788 | U28: =U27/U$25 -> 0.26463683 | V28: =V27/V$25 -> 0.26463683
B29: SG&A | P29: =P15 -> 60236.142 | Q29: =Q15 -> 78549.363 | R29: =R15 -> 79066.553 | S29: =S15 -> 83876.936 | T29: =T15 -> 88454.287 | U29: =U15 -> 93105.563 | V29: =U29*(1+$I$45) -> 93571.091
B30: EBIT | P30: =P27-P29 -> 20810.68 | Q30: =Q27-Q29 -> 23731.088 | R30: =R27-R29 -> 25526.466 | S30: =S27-S29 -> 32013.897 | T30: =T27-T29 -> 39173.116 | U30: =U27-U29 -> 48615.952 | V30: =V27-V29 -> 48859.032
B31: % of Revenue | P31: =P30/P$25 -> 0.066664407 | Q31: =Q30/Q$25 -> 0.059049134 | R31: =R30/R$25 -> 0.066470827 | S31: =S30/S$25 -> 0.073790263 | T31: =T30/T$25 -> 0.080968387 | U31: =U30/U$25 -> 0.090780653 | V31: =V30/V$25 -> 0.090780653
B32: Income Tax | P32: 4303.9005 | R32: 5729.469 | S32: 7118.5538 | T32: 9031.9654 | U32: 11315.372 | V32: 11374.258
B33: EBIT after Tax | P33: =P30-P32 -> 16506.779 | R33: =R30-R32 -> 19796.997 | S33: =S30-S32 -> 24895.343 | T33: =T30-T32 -> 30141.15 | U33: =U30-U32 -> 37300.581 | V33: =V30-V32 -> 37484.774
B34: (+) D&A | P34: =P18 -> 4387.6363 | R34: =R18 -> 4388.9114 | S34: =S18 -> 4406.3455 | T34: =T18 -> 4431.8656 | U34: =U18 -> 4510.3795
B35: (-) CAPEX | P35: =CAPEX_HW!Y6+CAPEX_강소!Y6+Projection_미국!Y274+Projection_중국!Y272+Projection_유럽!Y166 -> 4294.9396 | R35: =CAPEX_HW!AA6+CAPEX_강소!AA6+Projection_미국!AA274+Projection_중국!AA272+Projection_유럽!AA166 -> 4357.0404 | S35: =CAPEX_HW!AB6+CAPEX_강소!AB6+Projection_미국!AB274+Projection_중국!AB272+Projection_유럽!AB166 -> 4375.1867 | T35: =CAPEX_HW!AC6+CAPEX_강소!AC6+Projection_미국!AC274+Projection_중국!AC272+Projection_유럽!AC166 -> 4403.4354 | U35: =CAPEX_HW!AD6+CAPEX_강소!AD6+Projection_미국!AD274+Projection_중국!AD272+Projection_유럽!AD166 -> 4480.7549
B36: (+/-) NWC | P36: =NWC_연결!P6 -> -16257.034 | R36: =NWC_연결!R6 -> -9574.7874 | S36: =NWC_연결!S6 -> 20834.399 | T36: =NWC_연결!T6 -> 20951.381 | U36: =NWC_연결!U6 -> 20590.111 | V36: =NWC_연결!V6 -> 1079.4051
B37: FCFF | P37: =P33+P34-P35-P36 -> 32856.509 | R37: =R33+R34-R35-R36 -> 29403.656 | S37: =S33+S34-S35-S36 -> 4092.1031 | T37: =T33+T34-T35-T36 -> 9218.1993 | U37: =U33+U34-U35-U36 -> 16740.094 | V37: =V33+V34-V35-V36 -> 36405.369
B38: 할인기간 | P38: ='Key Assumption'!$I$9/2 -> 0.37671233 | R38: ='Key Assumption'!$I$9+0.5 -> 1.2534247 | S38: =R38+1 -> 2.2534247 | T38: =S38+1 -> 3.2534247 | U38: =T38+1 -> 4.2534247 | V38: =U38 -> 4.2534247
B39: 할인계수 | P39: =1/(1+$I$46)^P38 -> 0.96144905 | R39: =1/(1+$I$46)^R38 -> 0.87738673 | S39: =1/(1+$I$46)^S38 -> 0.79043849 | T39: =1/(1+$I$46)^T38 -> 0.71210675 | U39: =1/(1+$I$46)^U38 -> 0.64153761 | V39: =U39 -> 0.64153761
B40: PV of FCFF | P40: =P37*P39 -> 31589.86 | R40: =R37*R39 -> 25798.377 | S40: =S37*S39 -> 3234.5558 | T40: =T37*T39 -> 6564.342 | U40: =U37*U39 -> 10739.4 | V40: =V37*V39/(I46-I45) -> 222432.51
B41: 대상기간 누적 현재가치 | P41: =SUM(P40:U40) -> 77926.535
B42: Terminal Value의 현재가치 | P42: =V40 -> 222432.51
B43: 영업가치 | P43: =P42+P41 -> 300359.04
B45: 영구성장률 | I45: 0.005
B46: WACC | I46: =DCF!I27 -> 0.11 | T46: 영구성장률
Q47: =$I$53 -> 303168.4 | R47: 0 | S47: 0.0025 | T47: 0.005 | U47: 0.0075 | V47: 0.01
B48: DCF Results | Q48: 0.1 | R48: =DCF!R29 -> 330117.76 | S48: =DCF!S29 -> 333624.88 | T48: =DCF!T29 -> 337316.58 | U48: =DCF!U29 -> 341207.83 | V48: =DCF!V29 -> 345315.27
B49: 영업가치 | I49: =P43 -> 300359.04 | Q49: 0.105 | R49: =DCF!R30 -> 313228.53 | S49: =DCF!S30 -> 316217.97 | T49: =DCF!T30 -> 319356.87 | U49: =DCF!U30 -> 322656.74 | V49: =DCF!V30 -> 326130.29
B50: NOA | I50: =DCF!I31 -> 38139.886 | P50: WACC | Q50: 0.11 | R50: =DCF!R31 -> 297935.42 | S50: =DCF!S31 -> 300491.06 | T50: =DCF!T31 -> 303168.4 | U50: =DCF!U31 -> 305976.35 | V50: =DCF!V31 -> 308924.69
B51: 기업가치 | I51: =I49+I50 -> 338498.93 | Q51: 0.115 | R51: =DCF!R32 -> 284028.51 | S51: =DCF!S32 -> 286218.45 | T51: =DCF!T32 -> 288507.93 | U51: =DCF!U32 -> 290903.9 | V51: =DCF!V32 -> 293413.96
B52: IBD | I52: =DCF!I33 -> 35330.527 | Q52: 0.12 | R52: =DCF!R33 -> 271332.94 | S52: =DCF!S33 -> 273212.88 | T52: =DCF!T33 -> 275174.55 | U52: =DCF!U33 -> 277223.41 | V52: =DCF!V33 -> 279365.4
B53: 지분가치 | I53: =I51-I52 -> 303168.4
B55: 3. 상대가치평가
H57: GPCM | I57: GTM | J57: 1.3 | K57: 1.2 | L57: 1.1 | M57: 1 | N57: 0.9 | O57: 0.8 | P57: 0.7 | Q57: 0.6 | R57: 0.5
B58: 2024 EBITDA | H58: =Q19 -> 29233.144 | I58: =H58 -> 29233.144 | J58: =$I$58*J57 -> 38003.087 | K58: =$I$58*K57 -> 35079.773 | L58: =$I$58*L57 -> 32156.458 | M58: =$I$58*M57 -> 29233.144 | N58: =$I$58*N57 -> 26309.83 | O58: =$I$58*O57 -> 23386.515 | P58: =$I$58*P57 -> 20463.201 | Q58: =$I$58*Q57 -> 17539.886 | R58: =$I$58*R57 -> 14616.572
B59: Multiple
C60: Min | H60: 4 | I60: 8 | J60: =I60 -> 8 | K60: =J60 -> 8 | L60: =K60 -> 8 | M60: =L60 -> 8 | N60: =M60 -> 8 | O60: =N60 -> 8 | P60: =O60 -> 8 | Q60: =P60 -> 8 | R60: =Q60 -> 8
C61: Max | H61: 6 | I61: 10 | J61: =I61 -> 10 | K61: =J61 -> 10 | L61: =K61 -> 10 | M61: =L61 -> 10 | N61: =M61 -> 10 | O61: =N61 -> 10 | P61: =O61 -> 10 | Q61: =P61 -> 10 | R61: =Q61 -> 10
B62: EV
C63: Min | H63: =H$58*H60 -> 116932.58 | I63: =I$58*I60 -> 233865.15 | J63: =J$58*J60 -> 304024.7 | K63: =K$58*K60 -> 280638.18 | L63: =L$58*L60 -> 257251.67 | M63: =M$58*M60 -> 233865.15 | N63: =N$58*N60 -> 210478.64 | O63: =O$58*O60 -> 187092.12 | ... R63: =R$58*R60 -> 116932.58
C64: Max | H64: =H$58*H61 -> 175398.86 | I64: =I$58*I61 -> 292331.44 | J64: =J$58*J61 -> 380030.87 | K64: =K$58*K61 -> 350797.73 | L64: =L$58*L61 -> 321564.58 | M64: =M$58*M61 -> 292331.44 | N64: =N$58*N61 -> 263098.3 | O64: =O$58*O61 -> 233865.15 | ... R64: =R$58*R61 -> 146165.72
B65: Net Debt | H65: =I52-I50 -> -2809.3584 | I65: =H65 -> -2809.3584 | J65: =I65 -> -2809.3584 | K65: =J65 -> -2809.3584 | L65: =K65 -> -2809.3584 | M65: =L65 -> -2809.3584 | N65: =M65 -> -2809.3584 | O65: =N65 -> -2809.3584 | P65: =O65 -> -2809.3584 | ... R65: =Q65 -> -2809.3584
B66: Equtiy Value
C67: Min | H67: =H63-H$65 -> 119741.93 | I67: =I63-I$65 -> 236674.51 | J67: =J63-J$65 -> 306834.06 | K67: =K63-K$65 -> 283447.54 | L67: =L63-L$65 -> 260061.03 | M67: =M63-M$65 -> 236674.51 | N67: =N63-N$65 -> 213287.99 | O67: =O63-O$65 -> 189901.48 | ... R67: =R63-R$65 -> 119741.93
C68: Max | H68: =H64-H$65 -> 178208.22 | I68: =I64-I$65 -> 295140.8 | J68: =J64-J$65 -> 382840.23 | K68: =K64-K$65 -> 353607.09 | L68: =L64-L$65 -> 324373.94 | M68: =M64-M$65 -> 295140.8 | N68: =N64-N$65 -> 265907.65 | O68: =O64-O$65 -> 236674.51 | ... R68: =R64-R$65 -> 148975.08
B70: 4. Valuation Results
M73: Equtiy Value | P73: Equtiy Value
P74: Min | Q74: Range | R74: Max
M75: Trading | P75: =H67/100 -> 1197.4193 | Q75: =R75-P75 -> 584.66288 | R75: =H68/100 -> 1782.0822
M76: Transaction | P76: =I67/100 -> 2366.7451 | Q76: =R76-P76 -> 584.66288 | R76: =I68/100 -> 2951.408
M77: DCF | P77: =S51/100 -> 2862.1845 | Q77: =R77-P77 -> 364.38296 | R77: =U49/100 -> 3226.5674

Sheet Proforma BS
A1: =MID(CELL("filename",A1),FIND("]",CELL("filename",A1))+1,255) -> Proforma BS
B3: 1. Consolidated
L5: 2021(A) | M5: 2022(A) | N5: 2023(A) | O5: 24.3m(A) | P5: 24.9m(E) | Q5: 2024(F) | R5: 2025(F) | S5: 2026(F) | T5: 2027(F) | U5: 2028(F)
B6: 유동자산 | L6: 348659.32 | M6: 326604.66 | N6: 261417.96 | O6: 261289.84 | P6: =SUM(P7:P9) -> 290129.7 | Q6: =SUM(Q7:Q9) -> 290129.32 | R6: =SUM(R7:R9) -> 306079.43 | S6: =SUM(S7:S9) -> 338454.86 | T6: =SUM(T7:T9) -> 376176.48 | U6: =SUM(U7:U9) -> 421085.34
C7: 현금및현금성자산 | L7: 49615.27 | M7: 47352.205 | N7: 33949.401 | O7: 32054.35 | P7: ='Proforma CF'!P28 -> 63667.583 | Q7: ='Proforma CF'!Q28 -> 63667.205 | R7: ='Proforma CF'!R28 -> 92904.807 | S7: ='Proforma CF'!S28 -> 96863.437 | T7: ='Proforma CF'!T28 -> 106081.64 | U7: ='Proforma CF'!U28 -> 122821.73
C8: 운전자산 | L8: =NWC_연결!L8 -> 296182.39 | M8: =NWC_연결!M8 -> 275437.12 | N8: =NWC_연결!N8 -> 224805.55 | O8: =NWC_연결!O8 -> 225839.03 | P8: =NWC_연결!P8 -> 223065.66 | Q8: =NWC_연결!Q8 -> 223065.66 | R8: =NWC_연결!R8 -> 209778.16 | S8: =NWC_연결!S8 -> 238194.97 | ... U8: =NWC_연결!U8 -> 294867.15
C9: 기타유동자산 | L9: =L6-SUM(L7:L8) -> 2861.6639 | M9: =M6-SUM(M7:M8) -> 3815.3399 | N9: =N6-SUM(N7:N8) -> 2663.0124 | O9: =O6-SUM(O7:O8) -> 3396.4569 | P9: =O9 -> 3396.4569 | Q9: =P9 -> 3396.4569 | R9: =Q9 -> 3396.4569 | S9: =R9 -> 3396.4569 | T9: =S9 -> 3396.4569 | U9: =T9 -> 3396.4569
B10: 비유동자산 | L10: 48763.271 | M10: 55075.956 | N10: 49991.27 | O10: 49896.044 | P10: =SUM(P11:P12) -> 49803.347 | Q10: =SUM(Q11:Q12) -> 49803.347 | R10: =SUM(R11:R12) -> 49771.476 | S10: =SUM(S11:S12) -> 49740.317 | T10: =SUM(T11:T12) -> 49711.887 | U10: =SUM(U11:U12) -> 49682.262
C11: 유무형자산 | L11: 45847.265 | M11: 44335.772 | N11: 41352.385 | O11: 40759.559 | P11: =O11-'Proforma CF'!P21-'Proforma CF'!P10 -> 40666.862 | Q11: =P11 -> 40666.862 | R11: =Q11-'Proforma CF'!R21-'Proforma CF'!R10 -> 40634.991 | S11: =R11-'Proforma CF'!S21-'Proforma CF'!S10 -> 40603.832 | T11: =S11-'Proforma CF'!T21-'Proforma CF'!T10 -> 40575.402 | U11: =T11-'Proforma CF'!U21-'Proforma CF'!U10 -> 40545.778
C12: 기타비유동자산 | L12: =L10-L11 -> 2916.0068 | M12: =M10-M11 -> 10740.185 | N12: =N10-N11 -> 8638.8845 | O12: =O10-O11 -> 9136.4849 | P12: =O12 -> 9136.4849 | Q12: =P12 -> 9136.4849 | R12: =Q12 -> 9136.4849 | S12: =R12 -> 9136.4849 | T12: =S12 -> 9136.4849 | U12: =T12 -> 9136.4849
B13: 자산총계 | L13: =L6+L10 -> 397422.6 | M13: =M6+M10 -> 381680.62 | N13: =N6+N10 -> 311409.23 | O13: =O6+O10 -> 311185.88 | P13: =P6+P10 -> 339933.05 | Q13: =Q6+Q10 -> 339932.67 | R13: =R6+R10 -> 355850.9 | S13: =S6+S10 -> 388195.18 | ... U13: =U6+U10 -> 470767.6
B14: 유동부채 | L14: 133932.14 | M14: 142933.39 | N14: 76739.878 | O14: 77804.858 | P14: =SUM(P15:P17) -> 91288.523 | Q14: =SUM(Q15:Q17) -> 91288.523 | R14: =SUM(R15:R17) -> 87575.813 | S14: =SUM(S15:S17) -> 95158.221 | T14: =SUM(T15:T17) -> 102710.26 | U14: =SUM(U15:U17) -> 110288.91
C15: 운전부채 | L15: =NWC_연결!L36 -> 78564.102 | M15: =NWC_연결!M36 -> 87002.549 | N15: =NWC_연결!N36 -> 49260.644 | O15: =NWC_연결!O36 -> 46502.089 | P15: =NWC_연결!P36 -> 59985.753 | Q15: =NWC_연결!Q36 -> 59985.753 | R15: =NWC_연결!R36 -> 56273.043 | S15: =NWC_연결!S36 -> 63855.451 | ... U15: =NWC_연결!U36 -> 78986.143
C16: 단기차입금 | L16: 43377.942 | M16: 44481.344 | N16: 15294.991 | O16: 18319.887 | P16: =O16 -> 18319.887 | Q16: =P16 -> 18319.887 | R16: =Q16 -> 18319.887 | S16: =R16 -> 18319.887 | T16: =S16 -> 18319.887 | U16: =T16 -> 18319.887
C17: 기타유동부채 | L17: =L14-SUM(L15:L16) -> 11990.098 | M17: =M14-SUM(M15:M16) -> 11449.502 | N17: =N14-SUM(N15:N16) -> 12184.243 | O17: =O14-SUM(O15:O16) -> 12982.882 | P17: =O17 -> 12982.882 | Q17: =P17 -> 12982.882 | R17: =Q17 -> 12982.882 | S17: =R17 -> 12982.882 | T17: =S17 -> 12982.882 | U17: =T17 -> 12982.882
B18: 비유동부채 | L18: 48887.947 | M18: 13028.576 | N18: 26775.73 | O18: 22430.027 | P18: =SUM(P19:P20) -> 22430.027 | Q18: =SUM(Q19:Q20) -> 22430.027 | R18: =SUM(R19:R20) -> 22430.027 | S18: =SUM(S19:S20) -> 22430.027 | T18: =SUM(T19:T20) -> 22430.027 | U18: =SUM(U19:U20) -> 22430.027
C19: 장기차입금 | L19: 41160.42 | M19: 6756 | N19: 21727.92 | O19: 17010.64 | P19: =O19 -> 17010.64 | Q19: =P19 -> 17010.64 | R19: =Q19 -> 17010.64 | S19: =R19 -> 17010.64 | T19: =S19 -> 17010.64 | U19: =T19 -> 17010.64
C20: 기타비유동부채 | L20: =L18-L19 -> 7727.5269 | M20: =M18-M19 -> 6272.5756 | N20: =N18-N19 -> 5047.8099 | O20: =O18-O19 -> 5419.3869 | P20: =O20 -> 5419.3869 | Q20: =P20 -> 5419.3869 | R20: =Q20 -> 5419.3869 | S20: =R20 -> 5419.3869 | T20: =S20 -> 5419.3869 | U20: =T20 -> 5419.3869
B21: 부채총계 | L21: =L14+L18 -> 182820.09 | M21: =M14+M18 -> 155961.97 | N21: =N14+N18 -> 103515.61 | O21: =O14+O18 -> 100234.89 | P21: =P14+P18 -> 113718.55 | Q21: =Q14+Q18 -> 113718.55 | R21: =R14+R18 -> 110005.84 | S21: =S14+S18 -> 117588.25 | ... U21: =U14+U18 -> 132718.94
B22: 자본총계 | L22: =L13-L21 -> 214602.51 | M22: =M13-M21 -> 225718.65 | N22: =N13-N21 -> 207893.63 | O22: =O13-O21 -> 210950.99 | P22: =P13-P21 -> 226214.5 | Q22: =Q13-Q21 -> 226214.12 | R22: =R13-R21 -> 245845.06 | S22: =S13-S21 -> 270606.93 | ... U22: =U13-U21 -> 338048.66

Sheet Proforma CF
A1: =MID(CELL("filename",A1),FIND("]",CELL("filename",A1))+1,255) -> Proforma CF
B3: 1. Consolidated
L5: 2021(A) | M5: 2022(A) | N5: 2023(A) | O5: 24.3m(A) | P5: 24.9m(E) | Q5: 2024(F) | R5: 2025(F) | S5: 2026(F) | T5: 2027(F) | U5: 2028(F)
B6: 영업활동 현금흐름 | M6: =M7+M8+M17+M18+M19 -> 29526.46 | N6: =N7+N8+N17+N18+N19 -> -2171.758 | O6: =O7+O8+O17+O18+O19 -> 318.92586 | P6: =P7+P8+P17+P18+P19 -> 35908.173 | Q6: =Q7+Q8+Q17+Q18+Q19 -> 36226.72 | R6: =R7+R8+R17+R18+R19 -> 33594.642 | S6: =S7+S8+S17+S18+S19 -> 8333.8172 | T6: =T7+T8+T17+T18+T19 -> 13621.635 | U6: =U7+U8+U17+U18+U19 -> 21220.849
C7: 당기순이익 | M7: ='Proforma PL'!M24 -> -17269.009 | N7: ='Proforma PL'!N24 -> -5710.2659 | O7: ='Proforma PL'!O24 -> 1784.2967 | P7: ='Proforma PL'!P24 -> 15263.503 | Q7: ='Proforma PL'!Q24 -> 17047.421 | R7: ='Proforma PL'!R24 -> 19630.943 | S7: ='Proforma PL'!S24 -> 24761.87 | T7: ='Proforma PL'!T24 -> 30141.15 | U7: ='Proforma PL'!U24 -> 37300.581
C8: 조정 | M8: =SUM(M9:M16) -> 46418.571 | N8: =SUM(N9:N16) -> 3618.9728 | O8: =SUM(O9:O16) -> -1753.8767 | P8: =SUM(P9:P16) -> 26191.846 | Q8: =SUM(Q9:Q16) -> 24437.97 | R8: =SUM(R9:R16) -> 19859.222 | S8: =SUM(S9:S16) -> -9176.0267 | T8: =SUM(T9:T16) -> -7487.55 | U8: =SUM(U9:U16) -> -4764.3605
D9: NWC변동 | M9: =-NWC_연결!M6 -> 29183.721 | N9: =-NWC_연결!N6 -> 12889.66 | O9: =-NWC_연결!O6 -> -3792.0324 | P9: =-NWC_연결!P6 -> 16257.034 | Q9: =-NWC_연결!Q6 -> 12465.001 | R9: =-NWC_연결!R6 -> 9574.7874 | S9: =-NWC_연결!S6 -> -20834.399 | T9: =-NWC_연결!T6 -> -20951.381 | U9: =-NWC_연결!U6 -> -20590.111
D10: D&A | M10: ='Proforma PL'!M26 -> 0 | N10: ='Proforma PL'!N26 -> 0 | O10: ='Proforma PL'!O26 -> 1114.4191 | P10: ='Proforma PL'!P26 -> 4387.6363 | Q10: ='Proforma PL'!Q26 -> 5502.0555 | R10: ='Proforma PL'!R26 -> 4388.9114 | S10: ='Proforma PL'!S26 -> 4406.3455 | T10: ='Proforma PL'!T26 -> 4431.8656 | U10: ='Proforma PL'!U26 -> 4510.3795
D11: 이자수익 | M11: ='Proforma PL'!M19 -> 2387.6219 | N11: ='Proforma PL'!N19 -> 2951.2325 | O11: ='Proforma PL'!O19 -> 605.2542 | P11: 0 | Q11: =O11+P11 -> 605.2542 | R11: 0 | S11: 0 | T11: 0 | U11: 0
D12: 이자비용 | M12: ='Proforma PL'!M20 -> -3903.9999 | N12: ='Proforma PL'!N20 -> -3906.604 | O12: ='Proforma PL'!O20 -> -893.76005 | P12: 0 | Q12: =O12+P12 -> -893.76005 | R12: 0 | S12: 0 | T12: 0 | U12: 0
D13: 법인세비용 | M13: ='Proforma PL'!M23 -> 1139.4799 | N13: ='Proforma PL'!N23 -> 1035.8364 | O13: ='Proforma PL'!O23 -> 0 | P13: ='Proforma PL'!P23 -> 5547.1766 | Q13: ='Proforma PL'!Q23 -> 5547.1766 | R13: ='Proforma PL'!R23 -> 5895.5228 | S13: ='Proforma PL'!S23 -> 7252.0264 | T13: ='Proforma PL'!T23 -> 9031.9654 | U13: ='Proforma PL'!U23 -> 11315.372
D14: 기타부채의 증감 | M14: ='Proforma BS'!M17+'Proforma BS'!M20-'Proforma BS'!L17-'Proforma BS'!L20 -> -1995.5477 | N14: ='Proforma BS'!N17+'Proforma BS'!N20-'Proforma BS'!M17-'Proforma BS'!M20 -> -490.02447 | O14: ='Proforma BS'!O17+'Proforma BS'!O20-'Proforma BS'!N17-'Proforma BS'!N20 -> 1170.216 | P14: ='Proforma BS'!P17+'Proforma BS'!P20-'Proforma BS'!O17-'Proforma BS'!O20 -> 0 | Q14: ='Proforma BS'!Q17+'Proforma BS'!Q20-'Proforma BS'!N17-'Proforma BS'!N20 -> 1170.216 | R14: ='Proforma BS'!R17+'Proforma BS'!R20-'Proforma BS'!Q17-'Proforma BS'!Q20 -> 0 | S14: ='Proforma BS'!S17+'Proforma BS'!S20-'Proforma BS'!R17-'Proforma BS'!R20 -> 0 | T14: ='Proforma BS'!T17+'Proforma BS'!T20-'Proforma BS'!S17-'Proforma BS'!S20 -> 0 | U14: ='Proforma BS'!U17+'Proforma BS'!U20-'Proforma BS'!T17-'Proforma BS'!T20 -> 0
D15: 기타자산의 증감 | M15: =-('Proforma BS'!M9+'Proforma BS'!M12-'Proforma BS'!L9-'Proforma BS'!L12) -> -8777.8538 | N15: =-('Proforma BS'!N9+'Proforma BS'!N12-'Proforma BS'!M9-'Proforma BS'!M12) -> 3253.6276 | O15: =-('Proforma BS'!O9+'Proforma BS'!O12-'Proforma BS'!N9-'Proforma BS'!N12) -> -1231.0449 | P15: =-('Proforma BS'!P9+'Proforma BS'!P12-'Proforma BS'!O9-'Proforma BS'!O12) -> 0 | Q15: =-('Proforma BS'!Q9+'Proforma BS'!Q12-'Proforma BS'!N9-'Proforma BS'!N12) -> -1231.0449 | R15: =-('Proforma BS'!R9+'Proforma BS'!R12-'Proforma BS'!Q9-'Proforma BS'!Q12) -> 0 | S15: =-('Proforma BS'!S9+'Proforma BS'!S12-'Proforma BS'!R9-'Proforma BS'!R12) -> 0 | T15: =-('Proforma BS'!T9+'Proforma BS'!T12-'Proforma BS'!S9-'Proforma BS'!S12) -> 0 | U15: =-('Proforma BS'!U9+'Proforma BS'!U12-'Proforma BS'!T9-'Proforma BS'!T12) -> 0
D16: 기타조정 | M16: ='Proforma CE'!M9 -> 28385.15 | N16: ='Proforma CE'!N9 -> -12114.755 | O16: ='Proforma CE'!O9 -> 1273.0714 | P16: 0 | Q16: =O16+P16 -> 1273.0714 | R16: 0 | S16: 0 | T16: 0 | U16: 0
C17: 이자수취 | M17: =-M11 -> -2387.6219 | N17: =-N11 -> -2951.2325 | O17: =-O11 -> -605.2542 | P17: =-P11 -> 0 | Q17: =-Q11 -> -605.2542 | R17: =-R11 -> 0 | S17: =-S11 -> 0 | T17: =-T11 -> 0 | U17: =-U11 -> 0
C18: 이자지급 | M18: =-M12 -> 3903.9999 | N18: =-N12 -> 3906.604 | O18: =-O12 -> 893.76005 | P18: =-P12 -> 0 | Q18: =-Q12 -> 893.76005 | R18: =-R12 -> 0 | S18: =-S12 -> 0 | T18: =-T12 -> 0 | U18: =-U12 -> 0
C19: 법인세납부 | M19: =-M13 -> -1139.4799 | N19: =-N13 -> -1035.8364 | O19: =-O13 -> 0 | P19: =-P13 -> -5547.1766 | Q19: =-Q13 -> -5547.1766 | R19: =-R13 -> -5895.5228 | S19: =-S13 -> -7252.0264 | T19: =-T13 -> -9031.9654 | U19: =-U13 -> -11315.372
B20: 투자활동 현금흐름 | M20: =SUM(M21:M22) -> 1511.4929 | N20: =SUM(N21:N22) -> 2983.3867 | O20: =SUM(O21:O22) -> -521.59306 | P20: =SUM(P21:P22) -> -4294.9396 | Q20: =SUM(Q21:Q22) -> -4816.5326 | R20: =SUM(R21:R22) -> -4357.0404 | S20: =SUM(S21:S22) -> -4375.1867 | T20: =SUM(T21:T22) -> -4403.4354 | U20: =SUM(U21:U22) -> -4480.7549
C21: CAPEX | M21: =-('Proforma BS'!M11-'Proforma BS'!L11+M10) -> 1511.4929 | N21: =-('Proforma BS'!N11-'Proforma BS'!M11+N10) -> 2983.3867 | O21: =-('Proforma BS'!O11-'Proforma BS'!N11+O10) -> -521.59306 | P21: =-(CAPEX_HW!Y6+CAPEX_강소!Y6+Projection_미국!Y274+Projection_중국!Y272+Projection_유럽!Y166) -> -4294.9396 | Q21: =O21+P21 -> -4816.5326 | R21: =-(CAPEX_HW!AA6+CAPEX_강소!AA6+Projection_미국!AA274+Projection_중국!AA272+Projection_유럽!AA166) -> -4357.0404 | S21: =-(CAPEX_HW!AB6+CAPEX_강소!AB6+Projection_미국!AB274+Projection_중국!AB272+Projection_유럽!AB166) -> -4375.1867 | T21: =-(CAPEX_HW!AC6+CAPEX_강소!AC6+Projection_미국!AC274+Projection_중국!AC272+Projection_유럽!AC166) -> -4403.4354 | U21: =-(CAPEX_HW!AD6+CAPEX_강소!AD6+Projection_미국!AD274+Projection_중국!AD272+Projection_유럽!AD166) -> -4480.7549
C22: 기타 | M22: 0 | N22: 0 | O22: 0 | P22: 0 | Q22: =O22+P22 -> 0 | R22: 0 | S22: 0 | T22: 0 | U22: 0
B23: 재무활동 현금흐름 | M23: =SUM(M24:M25) -> -33301.018 | N23: =SUM(N24:N25) -> -14214.433 | O23: =SUM(O24:O25) -> -1692.3837 | P23: =SUM(P24:P25) -> 0 | Q23: =SUM(Q24:Q25) -> -1692.3837 | R23: =SUM(R24:R25) -> 0 | S23: =SUM(S24:S25) -> 0 | T23: =SUM(T24:T25) -> 0 | U23: =SUM(U24:U25) -> 0
C24: 차입금변동 | M24: =('Proforma BS'!M16+'Proforma BS'!M19)-('Proforma BS'!L16+'Proforma BS'!L19) -> -33301.018 | N24: =('Proforma BS'!N16+'Proforma BS'!N19)-('Proforma BS'!M16+'Proforma BS'!M19) -> -14214.433 | O24: =('Proforma BS'!O16+'Proforma BS'!O19)-('Proforma BS'!N16+'Proforma BS'!N19) -> -1692.3837 | P24: 0 | Q24: =O24+P24 -> -1692.3837 | R24: =('Proforma BS'!R16+'Proforma BS'!R19)-('Proforma BS'!Q16+'Proforma BS'!Q19) -> 0 | S24: =('Proforma BS'!S16+'Proforma BS'!S19)-('Proforma BS'!R16+'Proforma BS'!R19) -> 0 | T24: =('Proforma BS'!T16+'Proforma BS'!T19)-('Proforma BS'!S16+'Proforma BS'!S19) -> 0 | U24: =('Proforma BS'!U16+'Proforma BS'!U19)-('Proforma BS'!T16+'Proforma BS'!T19) -> 0
C25: 기타 | M25: 0 | N25: 0 | O25: 0 | P25: 0 | Q25: =O25+P25 -> 0 | R25: 0 | S25: 0 | T25: 0 | U25: 0
B26: 현금의 증감 | M26: =M6+M20+M23 -> -2263.0651 | N26: =N6+N20+N23 -> -13402.804 | O26: =O6+O20+O23 -> -1895.0509 | P26: =P6+P20+P23 -> 31613.233 | Q26: =Q6+Q20+Q23 -> 29717.804 | R26: =R6+R20+R23 -> 29237.602 | S26: =S6+S20+S23 -> 3958.6305 | T26: =T6+T20+T23 -> 9218.1993 | U26: =U6+U20+U23 -> 16740.094
B27: 기초 현금 | M27: ='Proforma BS'!L7 -> 49615.27 | N27: ='Proforma BS'!M7 -> 47352.205 | O27: ='Proforma BS'!N7 -> 33949.401 | P27: =O28 -> 32054.35 | Q27: ='Proforma BS'!N7 -> 33949.401 | R27: =Q28 -> 63667.205 | S27: =R28 -> 92904.807 | T27: =S28 -> 96863.437 | U27: =T28 -> 106081.64
B28: 기말 현금 | M28: =SUM(M26:M27) -> 47352.205 | N28: =SUM(N26:N27) -> 33949.401 | O28: =SUM(O26:O27) -> 32054.35 | P28: =SUM(P26:P27) -> 63667.583 | Q28: =SUM(Q26:Q27) -> 63667.205 | R28: =SUM(R26:R27) -> 92904.807 | S28: =SUM(S26:S27) -> 96863.437 | T28: =SUM(T26:T27) -> 106081.64 | U28: =SUM(U26:U27) -> 122821.73

Sheet Proforma CE
A1: =MID(CELL("filename",A1),FIND("]",CELL("filename",A1))+1,255) -> Proforma CE
B3: 1. Consolidated
L5: 2021(A) | M5: 2022(A) | N5: 2023(A) | O5: 24.3m(A) | P5: 24.9m(E) | Q5: 2024(F) | R5: 2025(F) | S5: 2026(F) | T5: 2027(F) | U5: 2028(F)
B6: 기초 | M6: 214602.51 | N6: 225718.65 | O6: 207893.63 | P6: =O10 -> 210950.99 | Q6: =O6 -> 207893.63 | R6: =Q10 -> 226214.12 | S6: =R10 -> 245845.06 | T6: =S10 -> 270606.93 | U6: =T10 -> 300748.08
B7: 당기순이익 | M7: ='Proforma PL'!M24 -> -17269.009 | N7: ='Proforma PL'!N24 -> -5710.2659 | O7: ='Proforma PL'!O24 -> 1784.2967 | P7: ='Proforma PL'!P24 -> 15263.503 | Q7: ='Proforma PL'!Q24 -> 17047.421 | R7: ='Proforma PL'!R24 -> 19630.943 | S7: ='Proforma PL'!S24 -> 24761.87 | T7: ='Proforma PL'!T24 -> 30141.15 | U7: ='Proforma PL'!U24 -> 37300.581
B8: 배당 | M8: 0 | N8: 0 | O8: 0 | P8: 0 | Q8: =O8+P8 -> 0 | R8: 0 | S8: 0 | T8: 0 | U8: 0
B9: 해외사업장환산손익 | M9: =-(M6+M7-M10) -> 28385.15 | N9: =-(N6+N7-N10) -> -12114.755 | O9: =-(O6+O7-O10) -> 1273.0714 | P9: =-'Proforma PL'!$X$26 -> 0 | Q9: =O9+P9 -> 1273.0714 | R9: 0 | S9: 0 | T9: 0 | U9: 0
B10: 기말 | M10: 225718.65 | N10: 207893.63 | O10: 210950.99 | P10: =SUM(P6:P9) -> 226214.5 | Q10: =SUM(Q6:Q9) -> 226214.12 | R10: =SUM(R6:R9) -> 245845.06 | S10: =SUM(S6:S9) -> 270606.93 | T10: =SUM(T6:T9) -> 300748.08 | U10: =SUM(U6:U9) -> 338048.66

Sheet Proforma PL
A1: =MID(CELL("filename",A1),FIND("]",CELL("filename",A1))+1,255) -> Proforma PL
B3: 1. Consolidated
L5: 2021(A) | M5: 2022(A) | N5: 2023(A) | O5: 24.3m(A) | P5: 24.9m(E) | Q5: 2024(F) | R5: 2025(F) | S5: 2026(F) | T5: 2027(F) | U5: 2028(F)
B6: 매출액 | L6: 452648.37 | M6: 440670.04 | N6: 424735.38 | O6: =SUM(O34,O59,O81,O103,O125,O147) -> 89716.379 | P6: =SUM(P34,P59,P81,P103,P125,P147) -> 312170.78 | Q6: =SUM(Q34,Q59,Q81,Q103,Q125,Q147) -> 401887.16 | R6: =SUM(R34,R59,R81,R103,R125,R147) -> 384025.11 | S6: =SUM(S34,S59,S81,S103,S125,S147) -> 433849.88 | T6: =SUM(T34,T59,T81,T103,T125,T147) -> 483807.54 | U6: =SUM(U34,U59,U81,U103,U125,U147) -> 535532.09
C7: 국내 | O7: =O35 -> 32117.625 | P7: =P35 -> 134103.49 | Q7: =Q35 -> 166221.11 | R7: =R35 -> 162076.51 | S7: =S35 -> 186135.91 | T7: =T35 -> 207378.78 | U7: =U35 -> 232356.82
C8: 미주 | O8: 13939.073 | P8: =P59 -> 52334.224 | Q8: 66273.296 | R8: =R59 -> 59731.026 | S8: =S59 -> 64926.093 | T8: =T59 -> 69442.616 | U8: =U59 -> 76922.963
C9: 유럽 | O9: 13488.451 | P9: =P81 -> 48793.04 | Q9: 62281.491 | R9: =R81 -> 59615.67 | S9: =S81 -> 66472.55 | T9: =T81 -> 72281.457 | U9: =U81 -> 78126.589
C10: 중국 | O10: 14020.191 | P10: =P103 -> 36602.449 | Q10: 50622.64 | R10: =R103 -> 53388.54 | S10: =S103 -> 63265.924 | T10: =T103 -> 76460.228 | U10: =U103 -> 83020.2
C11: 직수출 | O11: =O36 -> 16151.039 | P11: =P36 -> 40337.577 | Q11: =Q36 -> 56488.616 | R11: =R36 -> 49213.365 | S11: =S36 -> 53049.402 | T11: =T36 -> 58244.454 | U11: =U36 -> 65105.515
B12: 매출원가 | L12: 409694.77 | M12: 360581.46 | N12: 345731 | O12: =SUM(O38,O60,O82,O104,O126,O148) -> 68482.371 | P12: =SUM(P38,P60,P82,P104,P126,P148) -> 231123.95 | Q12: =SUM(Q38,Q60,Q82,Q104,Q126,Q148)+0.378440499999897 -> 299606.7 | R12: =SUM(R38,R60,R82,R104,R126,R148) -> 279432.09 | S12: =SUM(S38,S60,S82,S104,S126,S148) -> 317959.05 | T12: =SUM(T38,T60,T82,T104,T126,T148) -> 356180.13 | U12: =SUM(U38,U60,U82,U104,U126,U148) -> 393810.57
B13: 매출총이익 | L13: =L6-L12 -> 42953.6 | M13: =M6-M12 -> 80088.587 | N13: =N6-N12 -> 79004.376 | O13: =O6-O12 -> 21234.008 | P13: =P6-P12 -> 81046.822 | Q13: =Q6-Q12 -> 102280.45 | R13: =R6-R12 -> 104593.02 | S13: =S6-S12 -> 115890.83 | ... U13: =U6-U12 -> 141721.52
B14: % GP | L14: =L13/L6 -> 0.09489397 | M14: =M13/M6 -> 0.18174275 | N14: =N13/N6 -> 0.18600846 | O14: =O13/O6 -> 0.23667928 | P14: =P13/P6 -> 0.25962335 | Q14: =Q13/Q6 -> 0.25450042 | R14: =R13/R6 -> 0.27235985 | S14: =S13/S6 -> 0.26712197 | ... U14: =U13/U6 -> 0.26463683
B15: 판매관리비 | L15: 100840.94 | M15: 96440.798 | N15: 80346.348 | O15: =SUM(O41,O63,O85,O107,O129,O151) -> 18313.221 | P15: =SUM(P41,P63,P85,P107,P129,P151) -> 60236.142 | Q15: =SUM(Q41,Q63,Q85,Q107,Q129,Q151) -> 78549.363 | R15: =SUM(R41,R63,R85,R107,R129,R151) -> 79066.553 | S15: =SUM(S41,S63,S85,S107,S129,S151) -> 83876.936 | T15: =SUM(T41,T63,T85,T107,T129,T151) -> 88454.287 | U15: =SUM(U41,U63,U85,U107,U129,U151) -> 93105.563
B16: 영업이익 | L16: =L13-L15 -> -57887.344 | M16: =M13-M15 -> -16352.211 | N16: =N13-N15 -> -1341.9724 | O16: =O13-O15 -> 2920.7872 | P16: =P13-P15 -> 20810.68 | Q16: =Q13-Q15 -> 23731.088 | R16: =R13-R15 -> 25526.466 | S16: =S13-S15 -> 32013.897 | ... U16: =U13-U15 -> 48615.952
B17: % EBIT | L17: =L16/L$6 -> -0.1278859 | M17: =M16/M$6 -> -0.037107608 | N17: =N16/N$6 -> -0.0031595493 | O17: =O16/O$6 -> 0.032555786 | P17: =P16/P$6 -> 0.066664407 | Q17: =Q16/Q$6 -> 0.059049134 | R17: =R16/R$6 -> 0.066470827 | S17: =S16/S$6 -> 0.073790263 | ... U17: =U16/U$6 -> 0.090780653
B18: 영업외손익 | L18: -1319.7445 | M18: 222.68274 | N18: -3332.4572 | O18: -1136.4906 | P18: =SUM(P19:P21) -> 0 | Q18: =SUM(Q19:Q21) -> -1136.4906 | R18: =SUM(R19:R21) -> 0 | S18: =SUM(S19:S21) -> 0 | T18: =SUM(T19:T21) -> 0 | U18: =SUM(U19:U21) -> 0
C19: 이자수익 | L19: 2286.8084 | M19: 2387.6219 | N19: 2951.2325 | O19: 605.2542 | P19: 0 | Q19: =O19+P19 -> 605.2542 | R19: =SUM(R45,R67,R89,R111,R133,R155) -> 0 | S19: =SUM(S45,S67,S89,S111,S133,S155) -> 0 | T19: =SUM(T45,T67,T89,T111,T133,T155) -> 0 | U19: =SUM(U45,U67,U89,U111,U133,U155) -> 0
C20: 이자비용 | L20: -4213.3726 | M20: -3903.9999 | N20: -3906.604 | O20: -893.76005 | P20: 0 | Q20: =O20+P20 -> -893.76005 | R20: =SUM(R46,R68,R90,R112,R134,R156) -> 0 | S20: =SUM(S46,S68,S90,S112,S134,S156) -> 0 | T20: =SUM(T46,T68,T90,T112,T134,T156) -> 0 | U20: =SUM(U46,U68,U90,U112,U134,U156) -> 0
C21: 기타영업외손익 | L21: =L18-SUM(L19:L20) -> 606.81979 | M21: =M18-SUM(M19:M20) -> 1739.0608 | N21: =N18-SUM(N19:N20) -> -2377.0857 | O21: =O18-SUM(O19:O20) -> -847.98471 | P21: 0 | Q21: =O21+P21 -> -847.98471 | R21: =SUM(R47,R69,R91,R113,R135,R157) -> 0 | S21: =SUM(S47,S69,S91,S113,S135,S157) -> 0 | T21: =SUM(T47,T69,T91,T113,T135,T157) -> 0 | U21: =SUM(U47,U69,U91,U113,U135,U157) -> 0
B22: 법인세차감전순손익 | L22: =L16+L18 -> -59207.088 | M22: =M16+M18 -> -16129.529 | N22: =N16+N18 -> -4674.4295 | O22: =O16+O18 -> 1784.2967 | P22: =P16+P18 -> 20810.68 | Q22: =Q16+Q18 -> 22594.598 | R22: =R16+R18 -> 25526.466 | S22: =S16+S18 -> 32013.897 | ... U22: =U16+U18 -> 48615.952
B23: 법인세비용 | L23: 309.5015 | M23: 1139.4799 | N23: 1035.8364 | O23: 0 | P23: =Q23-O23 -> 5547.1766 | Q23: =SUM(Q49,Q71,Q93,Q115,Q137,Q159) -> 5547.1766 | R23: =SUM(R49,R71,R93,R115,R137,R159) -> 5895.5228 | S23: =SUM(S49,S71,S93,S115,S137,S159) -> 7252.0264 | T23: =SUM(T49,T71,T93,T115,T137,T159) -> 9031.9654 | U23: =SUM(U49,U71,U93,U115,U137,U159) -> 11315.372
B24: 당기순이익 | L24: =L22-L23 -> -59516.59 | M24: =M22-M23 -> -17269.009 | N24: =N22-N23 -> -5710.2659 | O24: =O22 -> 1784.2967 | P24: =P22-P23 -> 15263.503 | Q24: =Q22-Q23 -> 17047.421 | R24: =R22-R23 -> 19630.943 | S24: =S22-S23 -> 24761.87 | T24: =T22-T23 -> 30141.15 | U24: =U22-U23 -> 37300.581
B25: NI% | L25: =L24/L$6 -> -0.13148526 | M25: =M24/M$6 -> -0.03918807 | N25: =N24/N$6 -> -0.013444291 | O25: =O24/O$6 -> 0.019888193 | P25: =P24/P$6 -> 0.048894721 | Q25: =Q24/Q$6 -> 0.042418428 | R25: =R24/R$6 -> 0.051118906 | S25: =S24/S$6 -> 0.057074743 | ... U25: =U24/U$6 -> 0.06965144
B26: D&A | O26: =SUM(O52,O74,O96,O118,O140)+-0.378440499999897 -> 1114.4191 | P26: =SUM(P52,P74,P96,P118,P140) -> 4387.6363 | Q26: =SUM(Q52,Q74,Q96,Q118,Q140)+-0.378440499999897 -> 5502.0555 | R26: =SUM(R52,R74,R96,R118,R140) -> 4388.9114 | S26: =SUM(S52,S74,S96,S118,S140) -> 4406.3455 | T26: =SUM(T52,T74,T96,T118,T140) -> 4431.8656 | U26: =SUM(U52,U74,U96,U118,U140) -> 4510.3795
B27: EBITDA | O27: =O16+O26 -> 4035.2064 | P27: =P16+P26 -> 25198.316 | Q27: =Q16+Q26 -> 29233.144 | R27: =R16+R26 -> 29915.378 | S27: =S16+S26 -> 36420.242 | T27: =T16+T26 -> 43604.981 | U27: =U16+U26 -> 53126.332
B28: % EBITDA | O28: =O27/O$6 -> 0.044977366 | P28: =P27/P$6 -> 0.080719651 | Q28: =Q27/Q$6 -> 0.072739682 | R28: =R27/R$6 -> 0.077899536 | S28: =S27/S$6 -> 0.083946646 | T28: =T27/T$6 -> 0.090128776 | U28: =U27/U$6 -> 0.099202892
B31: 2. 국내법인
L33: 2021(A) | M33: 2022(A) | N33: 2023(A) | O33: 24.3m(A) | P33: 24.9m(E) | Q33: 2024(F) | R33: 2025(F) | S33: 2026(F) | T33: 2027(F) | U33: 2028(F)
B34: 매출액 | O34: =O35+O36+O37 -> 75922.089 | P34: =P35+P36+P37 -> 256926.5 | Q34: =Q35+Q36+Q37 -> 332848.59 | R34: =R35+R36+R37 -> 313819.47 | S34: =S35+S36+S37 -> 352044.14 | T34: =T35+T36+T37 -> 388249.09 | U34: =U35+U36+U37 -> 431347.15
C35: 국내 | O35: =Revenue_HW!O7 -> 32117.625 | P35: =Revenue_HW!Y7 -> 134103.49 | Q35: =Revenue_HW!Z7 -> 166221.11 | R35: =Revenue_HW!AA7 -> 162076.51 | S35: =Revenue_HW!AB7 -> 186135.91 | T35: =Revenue_HW!AC7 -> 207378.78 | U35: =Revenue_HW!AD7 -> 232356.82
C36: 직수출 | O36: =Revenue_HW!O10 -> 16151.039 | P36: =Revenue_HW!Y10 -> 40337.577 | Q36: =Revenue_HW!Z10 -> 56488.616 | R36: =Revenue_HW!AA10 -> 49213.365 | S36: =Revenue_HW!AB10 -> 53049.402 | T36: =Revenue_HW!AC10 -> 58244.454 | U36: =Revenue_HW!AD10 -> 65105.515
C37: 해외법인 | O37: =Revenue_HW!O11 -> 27653.424 | P37: =Revenue_HW!Y11 -> 82485.436 | Q37: =Revenue_HW!Z11 -> 110138.86 | R37: =Revenue_HW!AA11 -> 102529.6 | S37: =Revenue_HW!AB11 -> 112858.83 | T37: =Revenue_HW!AC11 -> 122625.85 | U37: =Revenue_HW!AD11 -> 133884.82
B38: 매출원가 | O38: =COGS_HW!O6 -> 60294.782 | P38: =COGS_HW!Y6 -> 201130.51 | Q38: =COGS_HW!Z6 -> 261425.29 | R38: =COGS_HW!AA6 -> 238001.56 | S38: =COGS_HW!AB6 -> 269199.45 | T38: =COGS_HW!AC6 -> 298232.32 | U38: =COGS_HW!AD6 -> 331122.8
B39: 매출총이익 | O39: =O34-O38 -> 15627.307 | P39: =P34-P38 -> 55795.987 | Q39: =Q34-Q38 -> 71423.294 | R39: =R34-R38 -> 75817.914 | S39: =S34-S38 -> 82844.691 | T39: =T34-T38 -> 90016.764 | U39: =U34-U38 -> 100224.36
B40: % GP | O40: =IFERROR(O39/O$34,) -> 0.20583347 | P40: =IFERROR(P39/P$34,) -> 0.21716712 | Q40: =IFERROR(Q39/Q$34,) -> 0.21458193 | R40: =IFERROR(R39/R$34,) -> 0.24159722 | S40: =IFERROR(S39/S$34,) -> 0.23532473 | T40: =IFERROR(T39/T$34,) -> 0.23185313 | U40: =IFERROR(U39/U$34,) -> 0.23235196
B41: 판매관리비 | O41: ='SG&A_HW'!O6 -> 11854.107 | P41: ='SG&A_HW'!Y6 -> 39349.784 | Q41: ='SG&A_HW'!Z6 -> 51203.891 | R41: ='SG&A_HW'!AA6 -> 51425.31 | S41: ='SG&A_HW'!AB6 -> 54986.493 | T41: ='SG&A_HW'!AC6 -> 58307.097 | U41: ='SG&A_HW'!AD6 -> 61720.693
B42: 영업이익 | O42: =O39-O41 -> 3773.1998 | P42: =P39-P41 -> 16446.203 | Q42: =Q39-Q41 -> 20219.403 | R42: =R39-R41 -> 24392.604 | S42: =S39-S41 -> 27858.198 | T42: =T39-T41 -> 31709.668 | U42: =U39-U41 -> 38503.663
B43: % EBIT | O43: =IFERROR(O42/O$34,) -> 0.049698315 | P43: =IFERROR(P42/P$34,) -> 0.064011315 | Q43: =IFERROR(Q42/Q$34,) -> 0.060746548 | R43: =IFERROR(R42/R$34,) -> 0.07772814 | S43: =IFERROR(S42/S$34,) -> 0.079132684 | T43: =IFERROR(T42/T$34,) -> 0.081673515 | U43: =IFERROR(U42/U$34,) -> 0.089263747
B44: 영업외손익 | P44: =SUM(P45:P47) -> 0 | Q44: =SUM(Q45:Q47) -> 0 | R44: =SUM(R45:R47) -> 0 | S44: =SUM(S45:S47) -> 0 | T44: =SUM(T45:T47) -> 0 | U44: =SUM(U45:U47) -> 0
C45: 이자수익
C46: 이자비용
C47: 기타영업외손익
B48: 법인세차감전순손익 | P48: =P42+P44 -> 16446.203 | Q48: =Q42+Q44 -> 20219.403 | R48: =R42+R44 -> 24392.604 | S48: =S42+S44 -> 27858.198 | T48: =T42+T44 -> 31709.668 | U48: =U42+U44 -> 38503.663
B49: 법인세비용 | P49: =Q49-O49 -> 4208.682 | Q49: =IF(Q48<0,0,IF(Q48<200,Q48*9%*1.1,IF(Q48<20000,(200*9%*1.1+(Q48-200)*19%*1.1),(200*9%*1.1+(20000-200)*19%*1.1+(Q48-20000)*21%*1.1)))) -> 4208.682 | R49: =IF(R48<0,0,IF(R48<200,R48*9%*1.1,IF(R48<20000,(200*9%*1.1+(R48-200)*19%*1.1),(200*9%*1.1+(20000-200)*19%*1.1+(R48-20000)*21%*1.1)))) -> 5172.6915 | S49: =IF(S48<0,0,IF(S48<200,S48*9%*1.1,IF(S48<20000,(200*9%*1.1+(S48-200)*19%*1.1),(200*9%*1.1+(20000-200)*19%*1.1+(S48-20000)*21%*1.1)))) -> 5973.2437 | T49: =IF(T48<0,0,IF(T48<200,T48*9%*1.1,IF(T48<20000,(200*9%*1.1+(T48-200)*19%*1.1),(200*9%*1.1+(20000-200)*19%*1.1+(T48-20000)*21%*1.1)))) -> 6862.9332 | U49: =IF(U48<0,0,IF(U48<200,U48*9%*1.1,IF(U48<20000,(200*9%*1.1+(U48-200)*19%*1.1),(200*9%*1.1+(20000-200)*19%*1.1+(U48-20000)*21%*1.1)))) -> 8432.3462
B50: 당기순이익 | P50: =P48-P49 -> 12237.521 | Q50: =Q48-Q49 -> 16010.721 | R50: =R48-R49 -> 19219.912 | S50: =S48-S49 -> 21884.954 | T50: =T48-T49 -> 24846.734 | U50: =U48-U49 -> 30071.317
B51: NI% | P51: =P50/P34 -> 0.047630435 | Q51: =Q50/Q34 -> 0.048102114 | R51: =R50/R34 -> 0.061245123 | S51: =S50/S34 -> 0.06216537 | T51: =T50/T34 -> 0.063996891 | U51: =U50/U34 -> 0.069714885
B52: D&A | O52: =CAPEX_HW!O13 -> 457.46185 | P52: =CAPEX_HW!Y13 -> 1372.3855 | Q52: =CAPEX_HW!Z13 -> 1829.8474 | R52: =CAPEX_HW!AA13 -> 1859.125 | S52: =CAPEX_HW!AB13 -> 1896.3075 | T52: =CAPEX_HW!AC13 -> 1928.5447 | U52: =CAPEX_HW!AD13 -> 1963.2585
B53: EBITDA | O53: =O42+O52 -> 4230.6617 | P53: =P42+P52 -> 17818.588 | Q53: =Q42+Q52 -> 22049.25 | R53: =R42+R52 -> 26251.729 | S53: =S42+S52 -> 29754.505 | T53: =T42+T52 -> 33638.212 | U53: =U42+U52 -> 40466.922
B54: % EBITDA | O54: =IFERROR(O53/O$34,) -> 0.055723726 | P54: =IFERROR(P53/P$34,) -> 0.069352864 | Q54: =IFERROR(Q53/Q$34,) -> 0.066244085 | R54: =IFERROR(R53/R$34,) -> 0.083652326 | S54: =IFERROR(S53/S$34,) -> 0.084519246 | T54: =IFERROR(T53/T$34,) -> 0.086640802 | U54: =IFERROR(U53/U$34,) -> 0.093815205
B56: 3. 미국법인
L58: 2021(A) | M58: 2022(A) | N58: 2023(A) | O58: 24.3m(A) | P58: 24.9m(E) | Q58: 2024(F) | R58: 2025(F) | S58: 2026(F) | T58: 2027(F) | U58: 2028(F)
B59: 매출액 | O59: =Projection_미국!O6 -> 13953.787 | P59: =Projection_미국!Y6 -> 52334.224 | Q59: =Projection_미국!Z6 -> 66288.01 | R59: =Projection_미국!AA6 -> 59731.026 | S59: =Projection_미국!AB6 -> 64926.093 | T59: =Projection_미국!AC6 -> 69442.616 | U59: =Projection_미국!AD6 -> 76922.963
B60: 매출원가 | O60: =Projection_미국!O7 -> 10605.123 | P60: =Projection_미국!Y7 -> 41905.984 | Q60: =Projection_미국!Z7 -> 52511.107 | R60: =Projection_미국!AA7 -> 48000.829 | S60: =Projection_미국!AB7 -> 52173.483 | T60: =Projection_미국!AC7 -> 55812.69 | U60: =Projection_미국!AD7 -> 61789.765
B61: 매출총이익 | O61: =O59-O60 -> 3348.664 | P61: =P59-P60 -> 10428.239 | Q61: =Q59-Q60 -> 13776.903 | R61: =R59-R60 -> 11730.197 | S61: =S59-S60 -> 12752.61 | T61: =T59-T60 -> 13629.926 | U61: =U59-U60 -> 15133.198
B62: % GP | O62: =IFERROR(O61/O$59,) -> 0.23998245 | P62: =IFERROR(P61/P$59,) -> 0.19926233 | Q62: =IFERROR(Q61/Q$59,) -> 0.20783401 | R62: =IFERROR(R61/R$59,) -> 0.19638365 | S62: =IFERROR(S61/S$59,) -> 0.19641733 | T62: =IFERROR(T61/T$59,) -> 0.1962761 | U62: =IFERROR(U61/U$59,) -> 0.19673186
B63: 판매관리비 | O63: =Projection_미국!O10 -> 2235.3253 | P63: =Projection_미국!Y10 -> 7490.7322 | Q63: =Projection_미국!Z10 -> 9726.0575 | R63: =Projection_미국!AA10 -> 9896.5172 | S63: =Projection_미국!AB10 -> 10285.702 | T63: =Projection_미국!AC10 -> 10692.28 | U63: =Projection_미국!AD10 -> 11166.186
B64: 영업이익 | O64: =O61-O63 -> 1113.3387 | P64: =P61-P63 -> 2937.507 | Q64: =Q61-Q63 -> 4050.8457 | R64: =R61-R63 -> 1833.6799 | S64: =S61-S63 -> 2466.9079 | T64: =T61-T63 -> 2937.6461 | U64: =U61-U63 -> 3967.0114
B65: % EBIT | O65: =IFERROR(O64/O$59,) -> 0.079787566 | P65: =IFERROR(P64/P$59,) -> 0.056129753 | Q65: =IFERROR(Q64/Q$59,) -> 0.06110978 | R65: =IFERROR(R64/R$59,) -> 0.030698952 | S65: =IFERROR(S64/S$59,) -> 0.037995632 | T65: =IFERROR(T64/T$59,) -> 0.042303218 | U65: =IFERROR(U64/U$59,) -> 0.051571224
B66: 영업외손익 | P66: =SUM(P67:P69) -> 0 | Q66: =SUM(Q67:Q69) -> 0 | R66: =SUM(R67:R69) -> 0 | S66: =SUM(S67:S69) -> 0 | T66: =SUM(T67:T69) -> 0 | U66: =SUM(U67:U69) -> 0
C67: 이자수익
C68: 이자비용
C69: 기타영업외손익
B70: 법인세차감전순손익 | P70: =P64+P66 -> 2937.507 | Q70: =Q64+Q66 -> 4050.8457 | R70: =R64+R66 -> 1833.6799 | S70: =S64+S66 -> 2466.9079 | T70: =T64+T66 -> 2937.6461 | U70: =U64+U66 -> 3967.0114
B71: 법인세비용 | P71: =Q71-O71 -> 1138.2876 | Q71: 1138.2876 | R71: 515.26406 | S71: 693.20113 | T71: 825.47856 | U71: 1114.7302
B72: 당기순이익 | P72: =P70-P71 -> 1799.2194 | Q72: =Q70-Q71 -> 2912.5581 | R72: =R70-R71 -> 1318.4159 | S72: =S70-S71 -> 1773.7068 | T72: =T70-T71 -> 2112.1676 | U72: =U70-U71 -> 2852.2812
B73: NI% | P73: =IFERROR(P72/P$59,) -> 0.034379404 | Q73: =IFERROR(Q72/Q$59,) -> 0.043937932 | R73: =IFERROR(R72/R$59,) -> 0.022072547 | S73: =IFERROR(S72/S$59,) -> 0.027318859 | T73: =IFERROR(T72/T$59,) -> 0.030416014 | U73: =IFERROR(U72/U$59,) -> 0.03707971
B74: D&A | O74: =Projection_미국!O13 -> 282.80612 | P74: =Projection_미국!Y13 -> 895.23221 | Q74: =Projection_미국!Z13 -> 1178.0383 | R74: =Projection_미국!AA13 -> 1189.5052 | S74: =Projection_미국!AB13 -> 1172.4709 | T74: =Projection_미국!AC13 -> 1181.3922 | U74: =Projection_미국!AD13 -> 1201.6201
B75: EBITDA | O75: =O64+O74 -> 1396.1448 | P75: =P64+P74 -> 3832.7393 | Q75: =Q64+Q74 -> 5228.884 | R75: =R64+R74 -> 3023.1851 | S75: =S64+S74 -> 3639.3788 | T75: =T64+T74 -> 4119.0383 | U75: =U64+U74 -> 5168.6315
B76: % EBITDA | O76: =IFERROR(O75/O$59,) -> 0.1000549 | P76: =IFERROR(P75/P$59,) -> 0.07323581 | Q76: =IFERROR(Q75/Q$59,) -> 0.078881294 | R76: =IFERROR(R75/R$59,) -> 0.050613312 | S76: =IFERROR(S75/S$59,) -> 0.056054179 | T76: =IFERROR(T75/T$59,) -> 0.059315714 | U76: =IFERROR(U75/U$59,) -> 0.067192309
B78: 4. 유럽법인
L80: 2021(A) | M80: 2022(A) | N80: 2023(A) | O80: 24.3m(A) | P80: 24.9m(E) | Q80: 2024(F) | R80: 2025(F) | S80: 2026(F) | T80: 2027(F) | U80: 2028(F)
B81: 매출액 | O81: =Projection_유럽!O6 -> 13509.221 | P81: =Projection_유럽!Y6 -> 48793.04 | Q81: =Projection_유럽!Z6 -> 62302.261 | R81: =Projection_유럽!AA6 -> 59615.67 | S81: =Projection_유럽!AB6 -> 66472.55 | T81: =Projection_유럽!AC6 -> 72281.457 | U81: =Projection_유럽!AD6 -> 78126.589
B82: 매출원가 | O82: =Projection_유럽!O7 -> 11220.6 | P82: =Projection_유럽!Y7 -> 42356.998 | Q82: =Projection_유럽!Z7 -> 53577.598 | R82: =Projection_유럽!AA7 -> 52494.471 | S82: =Projection_유럽!AB7 -> 58529.709 | T82: =Projection_유럽!AC7 -> 63638.299 | U82: =Projection_유럽!AD7 -> 68777.065
B83: 매출총이익 | O83: =O81-O82 -> 2288.621 | P83: =P81-P82 -> 6436.0418 | Q83: =Q81-Q82 -> 8724.6628 | R83: =R81-R82 -> 7121.1988 | S83: =S81-S82 -> 7942.8406 | T83: =T81-T82 -> 8643.1578 | U83: =U81-U82 -> 9349.5245
B84: % GP | O84: =IFERROR(O83/O$81,) -> 0.16941177 | P84: =IFERROR(P83/P$81,) -> 0.13190491 | Q84: =IFERROR(Q83/Q$81,) -> 0.14003766 | R84: =IFERROR(R83/R$81,) -> 0.11945179 | S84: =IFERROR(S83/S$81,) -> 0.11949054 | T84: =IFERROR(T83/T$81,) -> 0.11957642 | U84: =IFERROR(U83/U$81,) -> 0.11967148
B85: 판매관리비 | O85: =Projection_유럽!O10 -> 1831.9466 | P85: =Projection_유럽!Y10 -> 6225.3598 | Q85: =Projection_유럽!Z10 -> 8057.3064 | R85: =Projection_유럽!AA10 -> 7748.0762 | S85: =Projection_유럽!AB10 -> 8040.5478 | T85: =Projection_유럽!AC10 -> 8326.3219 | U85: =Projection_유럽!AD10 -> 8600.7688
B86: 영업이익 | O86: =O83-O85 -> 456.67444 | P86: =P83-P85 -> 210.68196 | Q86: =Q83-Q85 -> 667.35639 | R86: =R83-R85 -> -626.87747 | S86: =S83-S85 -> -97.707171 | T86: =T83-T85 -> 316.83592 | U86: =U83-U85 -> 748.75565
B87: % EBIT | O87: =IFERROR(O86/O$81,) -> 0.033804646 | P87: =IFERROR(P86/P$81,) -> 0.004317869 | Q87: =IFERROR(Q86/Q$81,) -> 0.010711592 | R87: =IFERROR(R86/R$81,) -> -0.010515314 | S87: =IFERROR(S86/S$81,) -> -0.0014698875 | T87: =IFERROR(T86/T$81,) -> 0.0043833637 | U87: =IFERROR(U86/U$81,) -> 0.0095838774
B88: 영업외손익 | P88: =SUM(P89:P91) -> 0 | Q88: =SUM(Q89:Q91) -> 0 | R88: =SUM(R89:R91) -> 0 | S88: =SUM(S89:S91) -> 0 | T88: =SUM(T89:T91) -> 0 | U88: =SUM(U89:U91) -> 0
C89: 이자수익
C90: 이자비용
C91: 기타영업외손익
B92: 법인세차감전순손익 | P92: =P86+P88 -> 210.68196 | Q92: =Q86+Q88 -> 667.35639 | R92: =R86+R88 -> -626.87747 | S92: =S86+S88 -> -97.707171 | T92: =T86+T88 -> 316.83592 | U92: =U86+U88 -> 748.75565
B93: 법인세비용 | P93: =Q93-O93 -> 200.20692 | Q93: 200.20692 | R93: 0 | S93: 0 | T93: 95.050775 | U93: 224.62669
B94: 당기순이익 | P94: =P92-P93 -> 10.475039 | Q94: =Q92-Q93 -> 467.14948 | R94: =R92-R93 -> -626.87747 | S94: =S92-S93 -> -97.707171 | T94: =T92-T93 -> 221.78514 | U94: =U92-U93 -> 524.12895
B95: NI% | P95: =IFERROR(P94/P$81,) -> 0.00021468305 | Q95: =IFERROR(Q94/Q$81,) -> 0.0074981143 | R95: =IFERROR(R94/R$81,) -> -0.010515314 | S95: =IFERROR(S94/S$81,) -> -0.0014698875 | T95: =IFERROR(T94/T$81,) -> 0.0030683546 | U95: =IFERROR(U94/U$81,) -> 0.0067087142
B96: D&A | O96: =Projection_유럽!O13 -> 205.40436 | P96: =Projection_유럽!Y13 -> 723.6019 | Q96: =Projection_유럽!Z13 -> 929.00626 | R96: =Projection_유럽!AA13 -> 641.75066 | S96: =Projection_유럽!AB13 -> 643.80317 | T96: =Projection_유럽!AC13 -> 646.54457 | U96: =Projection_유럽!AD13 -> 650.3506
B97: EBITDA | O97: =O86+O96 -> 662.0788 | P97: =P86+P96 -> 934.28386 | Q97: =Q86+Q96 -> 1596.3627 | R97: =R86+R96 -> 14.873191 | S97: =S86+S96 -> 546.096 | T97: =T86+T96 -> 963.38049 | U97: =U86+U96 -> 1399.1062
B98: % EBITDA | O98: =IFERROR(O97/O$81,) -> 0.049009399 | P98: =IFERROR(P97/P$81,) -> 0.019147892 | Q98: =IFERROR(Q97/Q$81,) -> 0.025622869 | R98: =IFERROR(R97/R$81,) -> 0.00024948459 | S98: =IFERROR(S97/S$81,) -> 0.0082153611 | T98: =IFERROR(T97/T$81,) -> 0.013328183 | U98: =IFERROR(U97/U$81,) -> 0.017908196
B100: 5. 중국법인
L102: 2021(A) | M102: 2022(A) | N102: 2023(A) | O102: 24.3m(A) | P102: 24.9m(E) | Q102: 2024(F) | R102: 2025(F) | S102: 2026(F) | T102: 2027(F) | U102: 2028(F)
B103: 매출액 | O103: =Projection_중국!O6 -> 14141.97 | P103: =Projection_중국!Y6 -> 36602.449 | Q103: =Projection_중국!Z6 -> 50744.419 | R103: =Projection_중국!AA6 -> 53388.54 | S103: =Projection_중국!AB6 -> 63265.924 | T103: =Projection_중국!AC6 -> 76460.228 | U103: =Projection_중국!AD6 -> 83020.2
B104: 매출원가 | O104: =Projection_중국!O7 -> 12472.529 | P104: =Projection_중국!Y7 -> 32333.407 | Q104: =Projection_중국!Z7 -> 44805.936 | R104: =Projection_중국!AA7 -> 45839.185 | S104: =Projection_중국!AB7 -> 54442.29 | T104: =Projection_중국!AC7 -> 65789.152 | U104: =Projection_중국!AD7 -> 71372.57
B105: 매출총이익 | O105: =O103-O104 -> 1669.4411 | P105: =P103-P104 -> 4269.0425 | Q105: =Q103-Q104 -> 5938.4836 | R105: =R103-R104 -> 7549.3549 | S105: =S103-S104 -> 8823.6341 | T105: =T103-T104 -> 10671.076 | U105: =U103-U104 -> 11647.631
B106: % GP | O106: =IFERROR(O105/O$103,) -> 0.1180487 | P106: =IFERROR(P105/P$103,) -> 0.1166327 | Q106: =IFERROR(Q105/Q$103,) -> 0.11702733 | R106: =IFERROR(R105/R$103,) -> 0.14140403 | S106: =IFERROR(S105/S$103,) -> 0.13946898 | T106: =IFERROR(T105/T$103,) -> 0.13956374 | U106: =IFERROR(U105/U$103,) -> 0.14029876
B107: 판매관리비 | O107: =Projection_중국!O10 -> 1653.3205 | P107: =Projection_중국!Y10 -> 4816.373 | Q107: =Projection_중국!Z10 -> 6469.6934 | R107: =Projection_중국!AA10 -> 6719.0856 | S107: =Projection_중국!AB10 -> 7148.6706 | T107: =Projection_중국!AC10 -> 7578.0618 | U107: =Projection_중국!AD10 -> 7934.7163
B108: 영업이익 | O108: =O105-O107 -> 16.120663 | P108: =P105-P107 -> -547.33046 | Q108: =Q105-Q107 -> -531.2098 | R108: =R105-R107 -> 830.26927 | S108: =S105-S107 -> 1674.9635 | T108: =T105-T107 -> 3093.0138 | U108: =U105-U107 -> 3712.9145
B109: % EBIT | O109: =IFERROR(O108/O$103,) -> 0.0011399163 | P109: =IFERROR(P108/P$103,) -> -0.014953384 | Q109: =IFERROR(Q108/Q$103,) -> -0.010468339 | R109: =IFERROR(R108/R$103,) -> 0.015551451 | S109: =IFERROR(S108/S$103,) -> 0.026474971 | T109: =IFERROR(T108/T$103,) -> 0.040452584 | U109: =IFERROR(U108/U$103,) -> 0.044723025
B110: 영업외손익 | P110: =SUM(P111:P113) -> 0 | Q110: =SUM(Q111:Q113) -> 0 | R110: =SUM(R111:R113) -> 0 | S110: =SUM(S111:S113) -> 0 | T110: =SUM(T111:T113) -> 0 | U110: =SUM(U111:U113) -> 0
C111: 이자수익
...

Sheet DCF
A1: =MID(CELL("filename",A1),FIND("]",CELL("filename",A1))+1,255) -> DCF
B3: 1. Consolidated
L5: 2021(A) | M5: 2022(A) | N5: 2023(A) | O5: 24.3m(A) | P5: 24.9m(E) | Q5: 2024(F) | R5: 2025(F) | S5: 2026(F) | T5: 2027(F) | U5: 2028(F) | V5: Terminal
B6: Revenue | P6: ='Proforma PL'!P6 -> 312170.78 | Q6: ='Proforma PL'!Q6 -> 401887.16 | R6: ='Proforma PL'!R6 -> 384025.11 | S6: ='Proforma PL'!S6 -> 433849.88 | T6: ='Proforma PL'!T6 -> 483807.54 | U6: ='Proforma PL'!U6 -> 535532.09 | V6: =U6*(1+$I$26) -> 538209.75
B7: COGS | P7: ='Proforma PL'!P12 -> 231123.95 | Q7: ='Proforma PL'!Q12 -> 299606.7 | R7: ='Proforma PL'!R12 -> 279432.09 | S7: ='Proforma PL'!S12 -> 317959.05 | T7: ='Proforma PL'!T12 -> 356180.13 | U7: ='Proforma PL'!U12 -> 393810.57 | V7: =U7*(1+$I$26) -> 395779.62
B8: Gross Profit | P8: =P6-P7 -> 81046.822 | Q8: =Q6-Q7 -> 102280.45 | R8: =R6-R7 -> 104593.02 | S8: =S6-S7 -> 115890.83 | T8: =T6-T7 -> 127627.4 | U8: =U6-U7 -> 141721.52 | V8: =V6-V7 -> 142430.12
B9: % of Revenue | P9: =P8/P$6 -> 0.25962335 | Q9: =Q8/Q$6 -> 0.25450042 | R9: =R8/R$6 -> 0.27235985 | S9: =S8/S$6 -> 0.26712197 | T9: =T8/T$6 -> 0.26379788 | U9: =U8/U$6 -> 0.26463683 | V9: =V8/V$6 -> 0.26463683
B10: SG&A | P10: ='Proforma PL'!P15 -> 60236.142 | Q10: ='Proforma PL'!Q15 -> 78549.363 | R10: ='Proforma PL'!R15 -> 79066.553 | S10: ='Proforma PL'!S15 -> 83876.936 | T10: ='Proforma PL'!T15 -> 88454.287 | U10: ='Proforma PL'!U15 -> 93105.563 | V10: =U10*(1+$I$26) -> 93571.091
B11: EBIT | P11: =P8-P10 -> 20810.68 | Q11: =Q8-Q10 -> 23731.088 | R11: =R8-R10 -> 25526.466 | S11: =S8-S10 -> 32013.897 | T11: =T8-T10 -> 39173.116 | U11: =U8-U10 -> 48615.952 | V11: =V8-V10 -> 48859.032
B12: % of Revenue | P12: =P11/P$6 -> 0.066664407 | Q12: =Q11/Q$6 -> 0.059049134 | R12: =R11/R$6 -> 0.066470827 | S12: =S11/S$6 -> 0.073790263 | T12: =T11/T$6 -> 0.080968387 | U12: =U11/U$6 -> 0.090780653 | V12: =V11/V$6 -> 0.090780653
B13: Income Tax | P13: 4303.9005 | R13: 5729.469 | S13: 7118.5538 | T13: 9031.9654 | U13: 11315.372 | V13: 11374.258
B14: EBIT after Tax | P14: =P11-P13 -> 16506.779 | R14: =R11-R13 -> 19796.997 | S14: =S11-S13 -> 24895.343 | T14: =T11-T13 -> 30141.15 | U14: =U11-U13 -> 37300.581 | V14: =V11-V13 -> 37484.774
B15: (+) D&A | P15: ='Proforma PL'!P26 -> 4387.6363 | R15: ='Proforma PL'!R26 -> 4388.9114 | S15: ='Proforma PL'!S26 -> 4406.3455 | T15: ='Proforma PL'!T26 -> 4431.8656 | U15: ='Proforma PL'!U26 -> 4510.3795
B16: (-) CAPEX | P16: =CAPEX_HW!Y6+CAPEX_강소!Y6+Projection_미국!Y274+Projection_중국!Y272+Projection_유럽!Y166 -> 4294.9396 | R16: =CAPEX_HW!AA6+CAPEX_강소!AA6+Projection_미국!AA274+Projection_중국!AA272+Projection_유럽!AA166 -> 4357.0404 | S16: =CAPEX_HW!AB6+CAPEX_강소!AB6+Projection_미국!AB274+Projection_중국!AB272+Projection_유럽!AB166 -> 4375.1867 | T16: =CAPEX_HW!AC6+CAPEX_강소!AC6+Projection_미국!AC274+Projection_중국!AC272+Projection_유럽!AC166 -> 4403.4354 | U16: =CAPEX_HW!AD6+CAPEX_강소!AD6+Projection_미국!AD274+Projection_중국!AD272+Projection_유럽!AD166 -> 4480.7549
B17: (+/-) NWC | P17: =NWC_연결!P6 -> -16257.034 | R17: =NWC_연결!R6 -> -9574.7874 | S17: =NWC_연결!S6 -> 20834.399 | T17: =NWC_연결!T6 -> 20951.381 | U17: =NWC_연결!U6 -> 20590.111 | V17: =NWC_연결!V6 -> 1079.4051
B18: FCFF | P18: =P14+P15-P16-P17 -> 32856.509 | R18: =R14+R15-R16-R17 -> 29403.656 | S18: =S14+S15-S16-S17 -> 4092.1031 | T18: =T14+T15-T16-T17 -> 9218.1993 | U18: =U14+U15-U16-U17 -> 16740.094 | V18: =V14+V15-V16-V17 -> 36405.369
B19: 할인기간 | P19: ='Key Assumption'!$I$9/2 -> 0.37671233 | R19: ='Key Assumption'!$I$9+0.5 -> 1.2534247 | S19: =R19+1 -> 2.2534247 | T19: =S19+1 -> 3.2534247 | U19: =T19+1 -> 4.2534247 | V19: =U19 -> 4.2534247
B20: 할인계수 | P20: =1/(1+$I$27)^P19 -> 0.96144905 | R20: =1/(1+$I$27)^R19 -> 0.87738673 | S20: =1/(1+$I$27)^S19 -> 0.79043849 | T20: =1/(1+$I$27)^T19 -> 0.71210675 | U20: =1/(1+$I$27)^U19 -> 0.64153761 | V20: =U20 -> 0.64153761
B21: PV of FCFF | P21: =P18*P20 -> 31589.86 | R21: =R18*R20 -> 25798.377 | S21: =S18*S20 -> 3234.5558 | T21: =T18*T20 -> 6564.342 | U21: =U18*U20 -> 10739.4 | V21: =V18*V20/(I27-I26) -> 222432.51
B22: 대상기간 누적 현재가치 | P22: =SUM(P21:U21) -> 77926.535
B23: Terminal Value의 현재가치 | P23: =V21 -> 222432.51
B24: 영업가치 | P24: =P23+P22 -> 300359.04
B26: 영구성장률 | I26: 0.005
B27: WACC | I27: 0.11 | T27: 영구성장률
Q28: =$I$34 -> 303168.4 | R28: 0 | S28: 0.0025 | T28: 0.005 | U28: 0.0075 | V28: 0.01
B29: DCF Results | Q29: =Q30-0.5% -> 0.1 | R29: 330117.76 | S29: 333624.88 | T29: 337316.58 | U29: 341207.83 | V29: 345315.27
B30: 영업가치 | I30: =P24 -> 300359.04 | Q30: =Q31-0.5% -> 0.105 | R30: 313228.53 | S30: 316217.97 | T30: 319356.87 | U30: 322656.74 | V30: 326130.29
B31: NOA | I31: 38139.886 | P31: WACC | Q31: 0.11 | R31: 297935.42 | S31: 300491.06 | T31: 303168.4 | U31: 305976.35 | V31: 308924.69
B32: 기업가치 | I32: =I30+I31 -> 338498.93 | Q32: =Q31+0.5% -> 0.115 | R32: 284028.51 | S32: 286218.45 | T32: 288507.93 | U32: 290903.9 | V32: 293413.96
B33: IBD | I33: 35330.527 | Q33: =Q32+0.5% -> 0.12 | R33: 271332.94 | S33: 273212.88 | T33: 275174.55 | U33: 277223.41 | V33: 279365.4
B34: 지분가치 | I34: =I32-I33 -> 303168.4
I36: GPCM | J36: GTM
B37: 2024 EBITDA | I37: ='Proforma PL'!Q27 -> 29233.144 | J37: =I37 -> 29233.144
B38: Multiple
C39: Min | I39: 4 | J39: 8
C40: Max | I40: 6 | J40: 10
B41: EV
C42: Min | I42: =I$37*I39 -> 116932.58 | J42: =J$37*J39 -> 233865.15
C43: Max | I43: =I$37*I40 -> 175398.86 | J43: =J$37*J40 -> 292331.44
B44: Net Debt | I44: =I33-I31 -> -2809.3584 | J44: =I44 -> -2809.3584
B45: Equtiy Value
C46: Min | I46: =I42-I$44 -> 119741.93 | J46: =J42-J$44 -> 236674.51
C47: Max | I47: =I43-I$44 -> 178208.22 | J47: =J43-J$44 -> 295140.8
B49: 2. 민감도 분석
B51: 사업계획 달성률 | H51: 0.9
I53: 1 | J53: =I53-5% -> 0.95 | K53: =J53-5% -> 0.9 | L53: =K53-5% -> 0.85 | M53: =L53-5% -> 0.8 | N53: =M53-5% -> 0.75 | O53: =N53-5% -> 0.7
B54: 2024년 매출액(연결) | H54: {=TRANSPOSE('Proforma PL'!Q6:U6)} -> 401887.16 | I54: 429596.24 | J54: 418892.62 | K54: 401887.16 | L54: 387819.46 | M54: 371567.72 | N54: 358874.83 | O54: 336856.79
B55: 2025년 매출액(연결) | H55: 384025.11 | I55: 412815.17 | J55: 401605.72 | K55: 384025.11 | L55: 369386.54 | M55: 352431.8 | N55: 338770.28 | O55: 315421.19
B56: 2026년 매출액(연결) | H56: 433849.88 | I56: 466937.23 | J56: 454145.66 | K56: 433849.88 | L56: 417241.84 | M56: 397510.69 | N56: 382561.82 | O56: 357209.34
B57: 2027년 매출액(연결) | H57: 483807.54 | I57: 520332.65 | J57: 506217.81 | K57: 483807.54 | L57: 465540.13 | M57: 443364.93 | N57: 426843.58 | O57: 397183.98
B58: 2028년 매출액(연결) | H58: 535532.09 | I58: 575302.71 | J58: 559816.82 | K58: 535532.09 | L58: 515057.81 | M58: 490560.4 | N58: 472507.5 | O58: 439289.11
I60: 1 | J60: =I60-5% -> 0.95 | K60: =J60-5% -> 0.9 | L60: =K60-5% -> 0.85 | M60: =L60-5% -> 0.8 | N60: =M60-5% -> 0.75 | O60: =N60-5% -> 0.7
B61: 2024년 영업이익(연결) | H61: ='Proforma PL'!Q16 -> 23731.088 | I61: 37017.004 | J61: 31910.756 | K61: 23731.088 | L61: 16309.19 | M61: 8174.831 | N61: 2320.2844 | O61: -9535.7356
I63: 1 | J63: =I63-5% -> 0.95 | K63: =J63-5% -> 0.9 | L63: =K63-5% -> 0.85 | M63: =L63-5% -> 0.8 | N63: =M63-5% -> 0.75 | O63: =N63-5% -> 0.7
B64: 2024년 영업이익률 | H64: ='Proforma PL'!Q17 -> 0.059049134 | I64: 0.086166965 | J64: 0.076178846 | K64: 0.059049134 | L64: 0.042053562 | M64: 0.022000918 | N64: 0.0064654419 | O64: -0.028307981
I66: 1 | J66: =I66-5% -> 0.95 | K66: =J66-5% -> 0.9 | L66: =K66-5% -> 0.85 | M66: =L66-5% -> 0.8 | N66: =M66-5% -> 0.75 | O66: =N66-5% -> 0.7
B67: 2024년 EBITDA(연결) | H67: {=TRANSPOSE('Proforma PL'!Q27:U27)} -> 29233.144 | I67: 42519.06 | J67: 37412.812 | K67: 29233.144 | L67: 21811.245 | M67: 13676.886 | N67: 7822.3398 | O67: -4033.6801
B68: 2025년 EBITDA(연결) | H68: 29915.378 | I68: 38516.306 | J68: 35163.951 | K68: 29915.378 | L68: 25169.139 | M68: 19843.555 | N68: 15893.177 | O68: 8359.6009
B69: 2026년 EBITDA(연결) | H69: 36420.242 | I69: 45830.155 | J69: 42190.965 | K69: 36420.242 | L69: 31206.114 | M69: 25112.346 | N69: 20948.552 | O69: 13147.801
B70: 2027년 EBITDA(연결) | H70: 43604.981 | I70: 53808.495 | J70: 49872.912 | K70: 43604.981 | L70: 38081.975 | M70: 31437.741 | N70: 26966.876 | O70: 18074.646
B71: 2028년 EBITDA(연결) | H71: 53126.332 | I71: 64063.034 | J71: 59860.734 | K71: 53126.332 | L71: 47033.954 | M71: 39655.252 | N71: 34846.124 | O71: 24938.056
I73: 1 | J73: =I73-5% -> 0.95 | K73: =J73-5% -> 0.9 | L73: =K73-5% -> 0.85 | M73: =L73-5% -> 0.8 | N73: =M73-5% -> 0.75 | O73: =N73-5% -> 0.7
B74: DCF 지분가치 | H74: =I34 -> 303168.4 | I74: 398443.2 | J74: 361897.46 | K74: 303168.4 | L74: 249433.29 | M74: 185647.37 | N74: 143896.74 | O74: 57278.089
I76: 1 | J76: =I76-5% -> 0.95 | K76: =J76-5% -> 0.9 | L76: =K76-5% -> 0.85 | M76: =L76-5% -> 0.8 | N76: =M76-5% -> 0.75 | O76: =N76-5% -> 0.7
B77: GPCM 지분가치-Min | I77: =I$67*$I$39-$I$44 -> 172885.6 | J77: =J$67*$I$39-$I$44 -> 152460.61 | K77: =K$67*$I$39-$I$44 -> 119741.93 | L77: =L$67*$I$39-$I$44 -> 90054.339 | M77: =M$67*$I$39-$I$44 -> 57516.904 | N77: =N$67*$I$39-$I$44 -> 34098.718 | O77: =O$67*$I$39-$I$44 -> -13325.362
B78: GPCM 지분가치-Max | I78: =I$67*$I$40-$I$44 -> 257923.72 | J78: =J$67*$I$40-$I$44 -> 227286.23 | K78: =K$67*$I$40-$I$44 -> 178208.22 | L78: =L$67*$I$40-$I$44 -> 133676.83 | M78: =M$67*$I$40-$I$44 -> 84870.677 | N78: =N$67*$I$40-$I$44 -> 49743.397 | O78: =O$67*$I$40-$I$44 -> -21392.722
I80: 1 | J80: =I80-5% -> 0.95 | K80: =J80-5% -> 0.9 | L80: =K80-5% -> 0.85 | M80: =L80-5% -> 0.8 | N80: =M80-5% -> 0.75 | O80: =N80-5% -> 0.7
B81: GTM 지분가치 - Min | I81: =I$67*$J$39-$J$44 -> 342961.83 | J81: =J$67*$J$39-$J$44 -> 302111.85 | K81: =K$67*$J$39-$J$44 -> 236674.51 | L81: =L$67*$J$39-$J$44 -> 177299.32 | M81: =M$67*$J$39-$J$44 -> 112224.45 | N81: =N$67*$J$39-$J$44 -> 65388.077 | O81: =O$67*$J$39-$J$44 -> -29460.082
B82: GTM 지분가치 - Max | I82: =I$67*$J$40-$J$44 -> 427999.95 | J82: =J$67*$J$40-$J$44 -> 376937.48 | K82: =K$67*$J$40-$J$44 -> 295140.8 | L82: =L$67*$J$40-$J$44 -> 220921.81 | M82: =M$67*$J$40-$J$44 -> 139578.22 | N82: =N$67*$J$40-$J$44 -> 81032.757 | O82: =O$67*$J$40-$J$44 -> -37527.442
B84: Variable
B85: (1) 시장성장률 초과달성률
B86: (2) 재료비율
H88: =I34/100 -> 3031.684 | I88: =J88-10% -> -0.3 | J88: =K88-10% -> -0.2 | K88: =L88-10% -> -0.1 | L88: 0 | M88: =L88+10% -> 0.1 | N88: =M88+10% -> 0.2 | O88: =N88+10% -> 0.3
B89: =B90-0.5% -> -0.025 | H89: =B89 -> -0.025 | I89: 5045.499 | J89: 5045.499 | K89: 5045.499 | L89: 5045.499 | M89: 5045.499 | N89: 5045.499 | O89: 5045.499
B90: =B91-0.5% -> -0.02 | H90: =B90 -> -0.02 | I90: 4654.0704 | J90: 4654.0704 | K90: 4654.0704 | L90: 4654.0704 | M90: 4654.0704 | N90: 4654.0704 | O90: 4654.0704
B91: =B92-0.5% -> -0.015 | H91: =B91 -> -0.015 | I91: 4257.03 | J91: 4257.03 | K91: 4257.03 | L91: 4257.03 | M91: 4257.03 | N91: 4257.03 | O91: 4257.03
B92: =B93-0.5% -> -0.01 | H92: =B92 -> -0.01 | I92: 3854.3225 | J92: 3854.3225 | K92: 3854.3225 | L92: 3854.3225 | M92: 3854.3225 | N92: 3854.3225 | O92: 3854.3225
B93: =B94-0.5% -> -0.005 | H93: =B93 -> -0.005 | I93: 3445.8925 | J93: 3445.8925 | K93: 3445.8925 | L93: 3445.8925 | M93: 3445.8925 | N93: 3445.8925 | O93: 3445.8925
B94: 0 | H94: =B94 -> 0 | I94: 3031.684 | J94: 3031.684 | K94: 3031.684 | L94: 3031.684 | M94: 3031.684 | N94: 3031.684 | O94: 3031.684
B95: =B94+0.5% -> 0.005 | H95: =B95 -> 0.005 | I95: 2611.6411 | J95: 2611.6411 | K95: 2611.6411 | L95: 2611.6411 | M95: 2611.6411 | N95: 2611.6411 | O95: 2611.6411
B96: =B95+0.5% -> 0.01 | H96: =B96 -> 0.01 | I96: 2185.7075 | J96: 2185.7075 | K96: 2185.7075 | L96: 2185.7075 | M96: 2185.7075 | N96: 2185.7075 | O96: 2185.7075
B97: =B96+0.5% -> 0.015 | H97: =B97 -> 0.015 | I97: 1753.8264 | J97: 1753.8264 | K97: 1753.8264 | L97: 1753.8264 | M97: 1753.8264 | N97: 1753.8264 | O97: 1753.8264
B98: =B97+0.5% -> 0.02 | H98: =B98 -> 0.02 | I98: 1315.941 | J98: 1315.941 | K98: 1315.941 | L98: 1315.941 | M98: 1315.941 | N98: 1315.941 | O98: 1315.941
B99: =B98+0.5% -> 0.025 | H99: =B99 -> 0.025 | I99: 871.99415 | J99: 871.99415 | K99: 871.99415 | L99: 871.99415 | M99: 871.99415 | N99: 871.99415 | O99: 871.99415

Sheet Key Assumption
A1: =MID(CELL("filename",A1),FIND("]",CELL("filename",A1))+1,255) -> Key Assumption
B3: 0. General
B5: Key Base Factors
B6: Valuation Date | I6: 45382
B7: Market Data Date | I7: =I6 -> 45382
B8: Year End after Valuation Date | I8: 45657
B9: Partial Period Factor | I9: =(I8-I7)/365 -> 0.75342466
B11: Macro Indicators(from EIU) | L11: 2021A | M11: 2022A | N11: 2023A | O11: 1월 | P11: 2월 | Q11: 3월 | R11: 4월 | S11: 5월 | T11: 6월 | U11: 7월 | V11: 8월 | W11: 9월 | X11: 10월 | Y11: 11월 | Z11: 12월 | AA11: 2024F | AB11: 2025F | AC11: 2026F | AD11: 2027F | AE11: 2028F
B12: 한국
C13: 소비자물가지수 (avg.) | L13: 0.025 | M13: 0.05089 | N13: 0.03591 | AA13: 0.021 | AB13: 0.016 | AC13: 0.02 | AD13: 0.017 | AE13: 0.018
C14: 생산자물가지수 (avg.) | L14: 0.06379 | M14: 0.08376 | N14: 0.01609 | AA14: 0.022 | AB14: 0.019 | AC14: 0.016 | AD14: 0.02 | AE14: 0.018
C15: 평균명목임금상승률 | L15: 0.05024 | M15: 0.04897 | N15: 0.025 | AA15: 0.032 | AB15: 0.028 | AC15: 0.041 | AD15: 0.034 | AE15: 0.035
B16: 일본
C17: 소비자물가지수 (avg.) | L17: -0.00233 | M17: 0.02498 | N17: 0.03268 | AA17: 0.023 | AB17: 0.014 | AC17: 0.013 | AD17: 0.014 | AE17: 0.012
C18: 생산자물가지수 (avg.) | L18: 0.04608 | M18: 0.09814 | N18: 0.04178 | AA18: 0.016 | AB18: 0.011 | AC18: 0.013 | AD18: 0.012 | AE18: 0.014
C19: 평균명목임금상승률 | L19: 0.00901 | M19: 0.02999 | N19: 0.01883 | AA19: 0.03 | AB19: 0.018 | AC19: 0.017 | AD19: 0.017 | AE19: 0.016
B20: 미국
C21: 소비자물가지수 (avg.) | L21: 0.04682 | M21: 0.07992 | N21: 0.04128 | AA21: 0.025 | AB21: 0.021 | AC21: 0.023 | AD21: 0.023 | AE21: 0.024
C22: 생산자물가지수 (avg.) | L22: 0.06979 | M22: 0.09479 | N22: 0.02024 | AA22: 0.015 | AB22: 0.019 | AC22: 0.022 | AD22: 0.02 | AE22: 0.02
C23: 평균명목임금상승률 | L23: 0.04955 | M23: 0.06391 | N23: 0.04964 | AA23: 0.029 | AB23: 0.025 | AC23: 0.029 | AD23: 0.029 | AE23: 0.031
B24: 중국
C25: 소비자물가지수 (avg.) | L25: 0.00851 | M25: 0.01878 | N25: 0.00333 | AA25: 0.01 | AB25: 0.013 | AC25: 0.015 | AD25: 0.016 | AE25: 0.018
C26: 생산자물가지수 (avg.) | L26: 0.08126 | M26: 0.03955 | N26: -0.03009 | AA26: 0.02 | AB26: 0.016 | AC26: 0.01 | AD26: 0.015 | AE26: 0.007
C27: 평균명목임금상승률 | L27: 0.09713 | M27: 0.06732 | N27: 0.073 | AA27: 0.064 | AB27: 0.06 | AC27: 0.055 | AD27: 0.05 | AE27: 0.047
B28: 유럽
C29: 소비자물가지수 (avg.) | L29: 0.03212 | M29: 0.08658 | N29: 0.06016 | AA29: 0.021 | AB29: 0.019 | AC29: 0.019 | AD29: 0.02 | AE29: 0.02
C30: 생산자물가지수 (avg.) | L30: 0.09693 | M30: 0.33282 | N30: -0.02044 | AA30: -0.002 | AB30: 0.015 | AC30: 0.011 | AD30: 0.01 | AE30: 0.009
C31: 평균명목임금상승률 | L31: 0.01518 | M31: 0.02642 | N31: 0.04 | AA31: 0.024 | AB31: 0.029 | AC31: 0.026 | AD31: 0.027 | AE31: 0.027
H33: 1. 블룸버그 / 2. EIU / 3. 평균치
I34: 2018A | J34: 2019A | K34: 2020A | L34: 2021A | M34: 2022A | N34: 2023A | O34: 1월 | P34: 2월 | Q34: 3월 | R34: 4월 | S34: 5월 | T34: 6월 | U34: 7월 | V34: 8월 | W34: 9월 | X34: 10월 | Y34: 11월 | Z34: 12월 | AA34: 2024F | AB34: 2025F | AC34: 2026F | AD34: 2027F | AE34: 2028F
B35: KRW/USD | H35: 2 | I35: =CHOOSE($H$35,I36,I37) -> 1100.1633 | J35: =CHOOSE($H$35,J36,J37) -> 1165.3575 | K35: =CHOOSE($H$35,K36,K37) -> 1180.2658 | L35: =CHOOSE($H$35,L36,L37) -> 1143.9583 | M35: =CHOOSE($H$35,M36,M37) -> 1291.4467 | N35: =CHOOSE($H$35,N36,N37) -> 1305.6625 | O35: =CHOOSE($H35,O36,O37,AVERAGE(O36:O37)) -> 1330.6 | P35: =CHOOSE($H35,P36,P37,AVERAGE(P36:P37)) -> 1330.6 | Q35: =CHOOSE($H35,Q36,Q37,AVERAGE(Q36:Q37)) -> 1330.6 | R35: =CHOOSE($H35,R36,R37,AVERAGE(R36:R37)) -> 1308.6 | S35: =CHOOSE($H35,S36,S37,AVERAGE(S36:S37)) -> 1308.6 | T35: =CHOOSE($H35,T36,T37,AVERAGE(T36:T37)) -> 1308.6 | U35: =CHOOSE($H35,U36,U37,AVERAGE(U36:U37)) -> 1289.8 | V35: =CHOOSE($H35,V36,V37,AVERAGE(V36:V37)) -> 1289.8 | ... AE35: =CHOOSE($H35,AE36,AE37,AVERAGE(AE36:AE37)) -> 1212
C36: 블룸버그 | I36: 1100.1633 | J36: 1165.3575 | K36: 1180.2658 | L36: 1143.9583 | M36: 1291.4467 | N36: 1305.6625 | O36: 1270 | P36: 1270 | Q36: 1270 | R36: 1369.863 | S36: =R36 -> 1369.863 | T36: =S36 -> 1369.863 | U36: 1351.3514 | V36: =U36 -> 1351.3514 | W36: =V36 -> 1351.3514 | X36: 1333.3333 | Y36: =X36 -> 1333.3333 | Z36: =Y36 -> 1333.3333 | AA36: =Z36 -> 1333.3333 | AB36: 1265.8228 | AC36: 1234.5679 | AD36: 1282.0513 | AE36: =AD36 -> 1282.0513
C37: EIU | I37: =I36 -> 1100.1633 | J37: =J36 -> 1165.3575 | K37: =K36 -> 1180.2658 | L37: =L36 -> 1143.9583 | M37: =M36 -> 1291.4467 | N37: =N36 -> 1305.6625 | O37: =P37 -> 1330.6 | P37: =Q37 -> 1330.6 | Q37: 1330.6 | R37: =S37 -> 1308.6 | S37: =T37 -> 1308.6 | T37: 1308.6 | U37: =V37 -> 1289.8 | V37: =W37 -> 1289.8 | W37: 1289.8 | X37: =Y37 -> 1259.9 | Y37: =Z37 -> 1259.9 | Z37: 1259.9 | AA37: 1289.2 | AB37: 1214.2 | AC37: 1201.8 | AD37: 1199.3 | AE37: 1212
B38: KRW/JPY | H38: 2 | I38: =CHOOSE($H$35,I39,I40) -> 9.96239 | J38: =CHOOSE($H$35,J39,J40) -> 10.688575 | K38: =CHOOSE($H$35,K39,K40) -> 11.054715 | L38: =CHOOSE($H$35,L39,L40) -> 10.421174 | M38: =CHOOSE($H$35,M39,M40) -> 9.8236886 | N38: =CHOOSE($H$35,N39,N40) -> 9.2937433 | O38: =CHOOSE($H38,O39,O40,AVERAGE(O39:O40)) -> 8.9422043 | P38: =CHOOSE($H38,P39,P40,AVERAGE(P39:P40)) -> 8.9422043 | Q38: =CHOOSE($H38,Q39,Q40,AVERAGE(Q39:Q40)) -> 8.9422043 | R38: =CHOOSE($H38,R39,R40,AVERAGE(R39:R40)) -> 9.2025316 | S38: =CHOOSE($H38,S39,S40,AVERAGE(S39:S40)) -> 9.2025316 | T38: =CHOOSE($H38,T39,T40,AVERAGE(T39:T40)) -> 9.2025316 | U38: =CHOOSE($H38,U39,U40,AVERAGE(U39:U40)) -> 9.6110283 | V38: =CHOOSE($H38,V39,V40,AVERAGE(V39:V40)) -> 9.6110283 | ... AE38: =CHOOSE($H38,AE39,AE40,AVERAGE(AE39:AE40)) -> 11.564885
C39: 블룸버그 | I39: 9.96239 | J39: 10.688575 | K39: 11.054715 | L39: 10.421174 | M39: 9.8236886 | N39: 9.2937433 | O39: 9.538 | P39: 9.538 | Q39: 9.538 | R39: 11.1 | S39: 11.1 | T39: 11.1 | U39: 11 | V39: 11 | W39: 11 | X39: 11 | Y39: 11 | Z39: 11 | AA39: =Z39 -> 11 | AB39: 11 | AC39: 10.6 | AD39: 9.6 | AE39: =AD39 -> 9.6
C40: EIU | I40: =I39 -> 9.96239 | J40: =J39 -> 10.688575 | K40: =K39 -> 11.054715 | L40: =L39 -> 10.421174 | M40: =M39 -> 9.8236886 | N40: =N39 -> 9.2937433 | O40: =P40 -> 8.9422043 | P40: =Q40 -> 8.9422043 | Q40: 8.9422043 | R40: =S40 -> 9.2025316 | S40: =T40 -> 9.2025316 | T40: 9.2025316 | U40: =V40 -> 9.6110283 | V40: =W40 -> 9.6110283 | W40: 9.6110283 | X40: =Y40 -> 9.6470138 | Y40: =Z40 -> 9.6470138 | Z40: 9.6470138 | AA40: 9.2748201 | AB40: 10.413379 | AC40: 11.148423 | AD40: 11.389364 | AE40: 11.564885
B41: KRW/EUR | H41: 2 | I41: =CHOOSE($H$35,I42,I43) -> 1299.8318 | J41: =CHOOSE($H$35,J42,J43) -> 1304.7315 | K41: =CHOOSE($H$35,K42,K43) -> 1347.0156 | L41: =CHOOSE($H$35,L42,L43) -> 1353.9058 | M41: =CHOOSE($H$35,M42,M43) -> 1361.0264 | N41: =CHOOSE($H$35,N42,N43) -> 1413.3789 | O41: =CHOOSE($H41,O42,O43,AVERAGE(O42:O43)) -> 1444.734 | P41: =CHOOSE($H41,P42,P43,AVERAGE(P42:P43)) -> 1444.734 | Q41: =CHOOSE($H41,Q42,Q43,AVERAGE(Q42:Q43)) -> 1444.734 | R41: =CHOOSE($H41,R42,R43,AVERAGE(R42:R43)) -> 1426.4225 | S41: =CHOOSE($H41,S42,S43,AVERAGE(S42:S43)) -> 1426.4225 | T41: =CHOOSE($H41,T42,T43,AVERAGE(T42:T43)) -> 1426.4225 | U41: =CHOOSE($H41,U42,U43,AVERAGE(U42:U43)) -> 1431.6794 | V41: =CHOOSE($H41,V42,V43,AVERAGE(V42:V43)) -> 1431.6794 | ... AE41: =CHOOSE($H41,AE42,AE43,AVERAGE(AE42:AE43)) -> 1418.0414
C42: 블룸버그 | I42: 1299.8318 | J42: 1304.7315 | K42: 1347.0156 | L42: 1353.9058 | M42: 1361.0264 | N42: 1413.3789 | O42: 1401 | P42: 1401 | Q42: 1401 | R42: 1466.2757 | S42: 1466.2757 | T42: 1466.2757 | U42: 1445.0867 | V42: 1445.0867 | W42: 1445.0867 | X42: 1449.2754 | Y42: 1449.2754 | Z42: 1449.2754 | AA42: 1401 | AB42: 1422.4751 | AC42: 1390.8206 | AD42: 1466.2757 | AE42: =AD42 -> 1466.2757
C43: EIU | I43: =I42 -> 1299.8318 | J43: =J42 -> 1304.7315 | K43: =K42 -> 1347.0156 | L43: =L42 -> 1353.9058 | M43: =M42 -> 1361.0264 | N43: =N42 -> 1413.3789 | O43: =P43 -> 1444.734 | P43: =Q43 -> 1444.734 | Q43: 1444.734 | R43: =S43 -> 1426.4225 | S43: =T43 -> 1426.4225 | T43: 1426.4225 | U43: =V43 -> 1431.6794 | V43: =W43 -> 1431.6794 | W43: 1431.6794 | X43: =Y43 -> 1398.4904 | Y43: =Z43 -> 1398.4904 | Z43: 1398.4904 | AA43: 1418.1058 | AB43: 1381.1853 | AC43: 1388.0804 | AD43: 1397.1342 | AE43: 1418.0414
B44: KRW/CNY | H44: 2 | I44: =CHOOSE($H$35,I45,I46) -> 166.28829 | J44: =CHOOSE($H$35,J45,J46) -> 168.68662 | K44: =CHOOSE($H$35,K45,K46) -> 171.03443 | L44: =CHOOSE($H$35,L45,L46) -> 177.38767 | M44: =CHOOSE($H$35,M45,M46) -> 191.69226 | N44: =CHOOSE($H$35,N45,N46) -> 184.31148 | O44: =CHOOSE($H44,O45,O46,AVERAGE(O45:O46)) -> 185.26873 | P44: =CHOOSE($H44,P45,P46,AVERAGE(P45:P46)) -> 185.26873 | Q44: =CHOOSE($H44,Q45,Q46,AVERAGE(Q45:Q46)) -> 185.26873 | R44: =CHOOSE($H44,R45,R46,AVERAGE(R45:R46)) -> 182.15479 | S44: =CHOOSE($H44,S45,S46,AVERAGE(S45:S46)) -> 182.15479 | T44: =CHOOSE($H44,T45,T46,AVERAGE(T45:T46)) -> 182.15479 | U44: =CHOOSE($H44,U45,U46,AVERAGE(U45:U46)) -> 180.89762 | V44: =CHOOSE($H44,V45,V46,AVERAGE(V45:V46)) -> 180.89762 | ... AE44: =CHOOSE($H44,AE45,AE46,AVERAGE(AE45:AE46)) -> 178.682
C45: 블룸버그 | I45: 166.28829 | J45: 168.68662 | K45: 171.03443 | L45: 177.38767 | M45: 191.69226 | N45: 184.31148 | O45: 185.1 | P45: 185.1 | Q45: 185.1 | R45: 188.86811 | S45: 188.86811 | T45: 188.86811 | U45: 187.44142 | V45: 187.44142 | W45: 187.44142 | X45: 184.39978 | Y45: 184.39978 | Z45: 184.39978 | AA45: 185.1 | AB45: 180.73378 | AC45: 179.69452 | AD45: 187.35012 | AE45: =AD45 -> 187.35012
C46: EIU | I46: =I45 -> 166.28829 | J46: =J45 -> 168.68662 | K46: =K45 -> 171.03443 | L46: =L45 -> 177.38767 | M46: =M45 -> 191.69226 | N46: =N45 -> 184.31148 | O46: =P46 -> 185.26873 | P46: =Q46 -> 185.26873 | Q46: 185.26873 | R46: =S46 -> 182.15479 | S46: =T46 -> 182.15479 | T46: 182.15479 | U46: =V46 -> 180.89762 | V46: =W46 -> 180.89762 | W46: 180.89762 | X46: =Y46 -> 177.57576 | Y46: =Z46 -> 177.57576 | Z46: 177.57576 | AA46: 182.27061 | AB46: 174.00401 | AC46: 175.70175 | AD46: 177.80578 | AE46: 178.682
A48: 1. Key Assumption
B49: 1.1. Revenue
B51: 1.1.1 판매 기종 수
L52: 2021A | M52: 2022A | N52: 2023E | O52: 1월 | P52: 2월 | Q52: 3월 | R52: 4월 | S52: 5월 | T52: 6월 | U52: 7월 | V52: 8월 | W52: 9월 | X52: 10월 | Y52: 11월 | Z52: 12월 | AA52: 2024F | AB52: 2025F | AC52: 2026F | AD52: 2027F | AE52: 2028F
B53: 국내 | AA53: =SUM(AA54:AA57) -> 94 | AB53: =SUM(AB54:AB57) -> 95 | AC53: =SUM(AC54:AC57) -> 101 | AD53: =SUM(AD54:AD57) -> 104 | AE53: =SUM(AE54:AE57) -> 107
C54: 5축 | I54: =AA54/$AA$122 -> 1 | AA54: 5 | AB54: =INT($I54*AB$122) -> 6 | AC54: =INT($I54*AC$122) -> 7 | AD54: =INT($I54*AD$122) -> 7 | AE54: =INT($I54*AE$122) -> 8
C55: 선반 | I55: =AA55/$AA$123 -> 0.424 | AA55: 53 | AB55: =INT($I55*AB$123) -> 53 | AC55: =INT($I55*AC$123) -> 55 | AD55: =INT($I55*AD$123) -> 56 | AE55: =INT($I55*AE$123) -> 56
C56: VMC | I56: =AA56/$AA$124 -> 1 | AA56: 24 | AB56: =INT($I56*AB$124) -> 24 | AC56: =INT($I56*AC$124) -> 27 | AD56: =INT($I56*AD$124) -> 29 | AE56: =INT($I56*AE$124) -> 31
C57: HMC | I57: =AA57/$AA$125 -> 1 | AA57: 12 | AB57: =INT($I57*AB$125) -> 12 | AC57: =INT($I57*AC$125) -> 12 | AD57: =INT($I57*AD$125) -> 12 | AE57: =INT($I57*AE$125) -> 12
C58: 단종 | I58: =AA58/$AA$126 -> 0.7037037 | AA58: 19 | AB58: =INT($I58*AB$126) -> 0 | AC58: =INT($I58*AC$126) -> 0 | AD58: =INT($I58*AD$126) -> 0 | AE58: =INT($I58*AE$126) -> 0
B59: 인도 | AA59: =SUM(AA60:AA63) -> 43 | AB59: =SUM(AB60:AB63) -> 43 | AC59: =SUM(AC60:AC63) -> 44 | AD59: =SUM(AD60:AD63) -> 45 | AE59: =SUM(AE60:AE63) -> 47
C60: 5축 | I60: =AA60/$AA$122 -> 0.4 | AA60: 2 | AB60: =INT($I60*AB$122) -> 2 | AC60: =INT($I60*AC$122) -> 2 | AD60: =INT($I60*AD$122) -> 2 | AE60: =INT($I60*AE$122) -> 3
C61: 선반 | I61: =AA61/$AA$123 -> 0.272 | AA61: 34 | AB61: =INT($I61*AB$123) -> 34 | AC61: =INT($I61*AC$123) -> 35 | AD61: =INT($I61*AD$123) -> 36 | AE61: =INT($I61*AE$123) -> 36
C62: VMC | I62: =AA62/$AA$124 -> 0.16666667 | AA62: 4 | AB62: =INT($I62*AB$124) -> 4 | AC62: =INT($I62*AC$124) -> 4 | AD62: =INT($I62*AD$124) -> 4 | AE62: =INT($I62*AE$124) -> 5
C63: HMC | I63: =AA63/$AA$125 -> 0.25 | AA63: 3 | AB63: =INT($I63*AB$125) -> 3 | AC63: =INT($I63*AC$125) -> 3 | AD63: =INT($I63*AD$125) -> 3 | AE63: =INT($I63*AE$125) -> 3
C64: 단종 | I64: =AA64/$AA$126 -> 0.22222222 | AA64: 6 | AB64: =INT($I64*AB$126) -> 0 | AC64: =INT($I64*AC$126) -> 0 | AD64: =INT($I64*AD$126) -> 0 | AE64: =INT($I64*AE$126) -> 0
B65: CIS | AA65: =SUM(AA66:AA69) -> 45 | AB65: =SUM(AB66:AB69) -> 45 | AC65: =SUM(AC66:AC69) -> 47 | AD65: =SUM(AD66:AD69) -> 48 | AE65: =SUM(AE66:AE69) -> 48
C66: 5축 | I66: =AA66/$AA$122 -> 0.6 | AA66: 3 | AB66: =INT($I66*AB$122) -> 3 | AC66: =INT($I66*AC$122) -> 4 | AD66: =INT($I66*AD$122) -> 4 | AE66: =INT($I66*AE$122) -> 4
C67: 선반 | I67: =AA67/$AA$123 -> 0.232 | AA67: 29 | AB67: =INT($I67*AB$123) -> 29 | AC67: =INT($I67*AC$123) -> 30 | AD67: =INT($I67*AD$123) -> 30 | AE67: =INT($I67*AE$123) -> 30
C68: VMC | I68: =AA68/$AA$124 -> 0.20833333 | AA68: 5 | AB68: =INT($I68*AB$124) -> 5 | AC68: =INT($I68*AC$124) -> 5 | AD68: =INT($I68*AD$124) -> 6 | AE68: =INT($I68*AE$124) -> 6
C69: HMC | I69: =AA69/$AA$125 -> 0.66666667 | AA69: 8 | AB69: =INT($I69*AB$125) -> 8 | AC69: =INT($I69*AC$125) -> 8 | AD69: =INT($I69*AD$125) -> 8 | AE69: =INT($I69*AE$125) -> 8
C70: 단종 | I70: =AA70/$AA$126 -> 0.14814815 | AA70: 4 | AB70: =INT($I70*AB$126) -> 0 | AC70: =INT($I70*AC$126) -> 0 | AD70: =INT($I70*AD$126) -> 0 | AE70: =INT($I70*AE$126) -> 0
B71: 동남아 | AA71: =SUM(AA72:AA75) -> 17 | AB71: =SUM(AB72:AB75) -> 17 | AC71: =SUM(AC72:AC75) -> 17 | AD71: =SUM(AD72:AD75) -> 17 | AE71: =SUM(AE72:AE75) -> 18
C72: 5축 | I72: =AA72/$AA$122 -> 0.2 | AA72: 1 | AB72: =INT($I72*AB$122) -> 1 | AC72: =INT($I72*AC$122) -> 1 | AD72: =INT($I72*AD$122) -> 1 | AE72: =INT($I72*AE$122) -> 1
C73: 선반 | I73: =AA73/$AA$123 -> 0.088 | AA73: 11 | AB73: =INT($I73*AB$123) -> 11 | AC73: =INT($I73*AC$123) -> 11 | AD73: =INT($I73*AD$123) -> 11 | AE73: =INT($I73*AE$123) -> 11
C74: VMC | I74: =AA74/$AA$124 -> 0.16666667 | AA74: 4 | AB74: =INT($I74*AB$124) -> 4 | AC74: =INT($I74*AC$124) -> 4 | AD74: =INT($I74*AD$124) -> 4 | AE74: =INT($I74*AE$124) -> 5
C75: HMC | I75: =AA75/$AA$125 -> 0.083333333 | AA75: 1 | AB75: =INT($I75*AB$125) -> 1 | AC75: =INT($I75*AC$125) -> 1 | AD75: =INT($I75*AD$125) -> 1 | AE75: =INT($I75*AE$125) -> 1
C76: 단종 | I76: =AA76/$AA$126 -> 0.11111111 | AA76: 3 | AB76: =INT($I76*AB$126) -> 0 | AC76: =INT($I76*AC$126) -> 0 | AD76: =INT($I76*AD$126) -> 0 | AE76: =INT($I76*AE$126) -> 0
B77: 중동 | AA77: =SUM(AA78:AA81) -> 13 | AB77: =SUM(AB78:AB81) -> 13 | AC77: =SUM(AC78:AC81) -> 13 | AD77: =SUM(AD78:AD81) -> 13 | AE77: =SUM(AE78:AE81) -> 14
C78: 5축 | I78: =AA78/$AA$122 -> 0.4 | AA78: 2 | AB78: =INT($I78*AB$122) -> 2 | AC78: =INT($I78*AC$122) -> 2 | AD78: =INT($I78*AD$122) -> 2 | AE78: =INT($I78*AE$122) -> 3
C79: 선반 | I79: =AA79/$AA$123 -> 0.04 | AA79: 5 | AB79: =INT($I79*AB$123) -> 5 | AC79: =INT($I79*AC$123) -> 5 | AD79: =INT($I79*AD$123) -> 5 | AE79: =INT($I79*AE$123) -> 5
C80: VMC | I80: =AA80/$AA$124 -> 0.125 | AA80: 3 | AB80: =INT($I80*AB$124) -> 3 | AC80: =INT($I80*AC$124) -> 3 | AD80: =INT($I80*AD$124) -> 3 | AE80: =INT($I80*AE$124) -> 3
C81: HMC | I81: =AA81/$AA$125 -> 0.25 | AA81: 3 | AB81: =INT($I81*AB$125) -> 3 | AC81: =INT($I81*AC$125) -> 3 | AD81: =INT($I81*AD$125) -> 3 | AE81: =INT($I81*AE$125) -> 3
C82: 단종 | I82: =AA82/$AA$126 -> 0.037037037 | AA82: 1 | AB82: =INT($I82*AB$126) -> 0 | AC82: =INT($I82*AC$126) -> 0 | AD82: =INT($I82*AD$126) -> 0 | AE82: =INT($I82*AE$126) -> 0
B83: 기타 | AA83: =SUM(AA84:AA87) -> 10 | AB83: =SUM(AB84:AB87) -> 10 | AC83: =SUM(AC84:AC87) -> 10 | AD83: =SUM(AD84:AD87) -> 10 | AE83: =SUM(AE84:AE87) -> 11
C84: 5축 | I84: =AA84/$AA$122 -> 0.2 | AA84: 1 | AB84: =INT($I84*AB$122) -> 1 | AC84: =INT($I84*AC$122) -> 1 | AD84: =INT($I84*AD$122) -> 1 | AE84: =INT($I84*AE$122) -> 1
C85: 선반 | I85: =AA85/$AA$123 -> 0.032 | AA85: 4 | AB85: =INT($I85*AB$123) -> 4 | AC85: =INT($I85*AC$123) -> 4 | AD85: =INT($I85*AD$123) -> 4 | AE85: =INT($I85*AE$123) -> 4
C86: VMC | I86: =AA86/$AA$124 -> 0.16666667 | AA86: 4 | AB86: =INT($I86*AB$124) -> 4 | AC86: =INT($I86*AC$124) -> 4 | AD86: =INT($I86*AD$124) -> 4 | AE86: =INT($I86*AE$124) -> 5
C87: HMC | I87: =AA87/$AA$125 -> 0.083333333 | AA87: 1 | AB87: =INT($I87*AB$125) -> 1 | AC87: =INT($I87*AC$125) -> 1 | AD87: =INT($I87*AD$125) -> 1 | AE87: =INT($I87*AE$125) -> 1
C88: 단종 | I88: =AA88/$AA$126 -> 0.037037037 | AA88: 1 | AB88: =INT($I88*AB$126) -> 0 | AC88: =INT($I88*AC$126) -> 0 | AD88: =INT($I88*AD$126) -> 0 | AE88: =INT($I88*AE$126) -> 0
B89: 북미 | AA89: =SUM(AA90:AA93) -> 84 | AB89: =SUM(AB90:AB93) -> 84 | AC89: =SUM(AC90:AC93) -> 88 | AD89: =SUM(AD90:AD93) -> 90 | AE89: =SUM(AE90:AE93) -> 93
C90: 5축 | I90: =AA90/$AA$122 -> 0.4 | AA90: 2 | AB90: =INT($I90*AB$122) -> 2 | AC90: =INT($I90*AC$122) -> 2 | AD90: =INT($I90*AD$122) -> 2 | AE90: =INT($I90*AE$122) -> 3
C91: 선반 | I91: =AA91/$AA$123 -> 0.504 | AA91: 63 | AB91: =INT($I91*AB$123) -> 63 | AC91: =INT($I91*AC$123) -> 66 | AD91: =INT($I91*AD$123) -> 67 | AE91: =INT($I91*AE$123) -> 67
C92: VMC | I92: =AA92/$AA$124 -> 0.58333333 | AA92: 14 | AB92: =INT($I92*AB$124) -> 14 | AC92: =INT($I92*AC$124) -> 15 | AD92: =INT($I92*AD$124) -> 16 | AE92: =INT($I92*AE$124) -> 18
C93: HMC | I93: =AA93/$AA$125 -> 0.41666667 | AA93: 5 | AB93: =INT($I93*AB$125) -> 5 | AC93: =INT($I93*AC$125) -> 5 | AD93: =INT($I93*AD$125) -> 5 | AE93: =INT($I93*AE$125) -> 5
C94: 단종 | I94: =AA94/$AA$126 -> 0.25925926 | AA94: 7 | AB94: =INT($I94*AB$126) -> 0 | AC94: =INT($I94*AC$126) -> 0 | AD94: =INT($I94*AD$126) -> 0 | AE94: =INT($I94*AE$126) -> 0
B95: 남미 | AA95: =SUM(AA96:AA99) -> 37 | AB95: =SUM(AB96:AB99) -> 37 | AC95: =SUM(AC96:AC99) -> 38 | AD95: =SUM(AD96:AD99) -> 39 | AE95: =SUM(AE96:AE99) -> 40
C96: 5축 | I96: =AA96/$AA$122 -> 0.4 | AA96: 2 | AB96: =INT($I96*AB$122) -> 2 | AC96: =INT($I96*AC$122) -> 2 | AD96: =INT($I96*AD$122) -> 2 | AE96: =INT($I96*AE$122) -> 3
C97: 선반 | I97: =AA97/$AA$123 -> 0.24 | AA97: 30 | AB97: =INT($I97*AB$123) -> 30 | AC97: =INT($I97*AC$123) -> 31 | AD97: =INT($I97*AD$123) -> 31 | AE97: =INT($I97*AE$123) -> 31
C98: VMC | I98: =AA98/$AA$124 -> 0.20833333 | AA98: 5 | AB98: =INT($I98*AB$124) -> 5 | AC98: =INT($I98*AC$124) -> 5 | AD98: =INT($I98*AD$124) -> 6 | AE98: =INT($I98*AE$124) -> 6
C99: HMC | I99: =AA99/$AA$125 -> 0 | AA99: 0 | AB99: =INT($I99*AB$125) -> 0 | AC99: =INT($I99*AC$125) -> 0 | AD99: =INT($I99*AD$125) -> 0 | AE99: =INT($I99*AE$125) -> 0
C100: 단종 | I100: =AA100/$AA$126 -> 0.037037037 | AA100: 1 | AB100: =INT($I100*AB$126) -> 0 | AC100: =INT($I100*AC$126) -> 0 | AD100: =INT($I100*AD$126) -> 0 | AE100: =INT($I100*AE$126) -> 0
B101: 유럽 | AA101: =SUM(AA102:AA105) -> 139 | AB101: =SUM(AB102:AB105) -> 139 | AC101: =SUM(AC102:AC105) -> 146 | AD101: =SUM(AD102:AD105) -> 150 | AE101: =SUM(AE102:AE105) -> 151
C102: 5축 | I102: =AA102/$AA$122 -> 0.2 | AA102: 1 | AB102: =INT($I102*AB$122) -> 1 | AC102: =INT($I102*AC$122) -> 1 | AD102: =INT($I102*AD$122) -> 1 | AE102: =INT($I102*AE$122) -> 1
C103: 선반 | I103: =AA103/$AA$123 -> 0.904 | AA103: 113 | AB103: =INT($I103*AB$123) -> 113 | AC103: =INT($I103*AC$123) -> 118 | AD103: =INT($I103*AD$123) -> 120 | AE103: =INT($I103*AE$123) -> 120
C104: VMC | I104: =AA104/$AA$124 -> 0.83333333 | AA104: 20 | AB104: =INT($I104*AB$124) -> 20 | AC104: =INT($I104*AC$124) -> 22 | AD104: =INT($I104*AD$124) -> 24 | AE104: =INT($I104*AE$124) -> 25
C105: HMC | I105: =AA105/$AA$125 -> 0.41666667 | AA105: 5 | AB105: =INT($I105*AB$125) -> 5 | AC105: =INT($I105*AC$125) -> 5 | AD105: =INT($I105*AD$125) -> 5 | AE105: =INT($I105*AE$125) -> 5
C106: 단종 | I106: =AA106/$AA$126 -> 0.25925926 | AA106: 7 | AB106: =INT($I106*AB$126) -> 0 | AC106: =INT($I106*AC$126) -> 0 | AD106: =INT($I106*AD$126) -> 0 | AE106: =INT($I106*AE$126) -> 0
...

Sheet Revenue_HW
A1: =MID(CELL("filename",A1),FIND("]",CELL("filename",A1))+1,255) -> Revenue_HW
B3: 1. Summary
L5: 2021A | M5: 2022A | N5: 2023A | O5: 24.3m(A) | P5: 4월 | Q5: 5월 | R5: 6월 | S5: 7월 | T5: 8월 | U5: 9월 | V5: 10월 | W5: 11월 | X5: 12월 | Y5: 24.9m(E) | Z5: 2024F | AA5: 2025F | AB5: 2026F | AC5: 2027F | AD5: 2028F
B6: Revenue | O6: =SUM(O7,O10:O11) -> 75922.089 | P6: =SUM(P7,P10:P11) -> 31185.781 | Q6: =SUM(Q7,Q10:Q11) -> 28388.615 | R6: =SUM(R7,R10:R11) -> 30236.481 | S6: =SUM(S7,S10:S11) -> 27502.329 | T6: =SUM(T7,T10:T11) -> 29479.607 | U6: =SUM(U7,U10:U11) -> 28030.159 | V6: =SUM(V7,V10:V11) -> 27965.981 | ... AD6: =SUM(AD7,AD10:AD11) -> 431347.15
C7: 국내 | O7: =O8+O9 -> 32117.625 | P7: =P8+P9 -> 16095.789 | Q7: =Q8+Q9 -> 16190.455 | R7: =R8+R9 -> 16128.559 | S7: =S8+S9 -> 13851.138 | T7: =T8+T9 -> 15176.667 | U7: =U8+U9 -> 14644.102 | V7: =V8+V9 -> 14837.581 | ... AD7: =AD8+AD9 -> 232356.82
D8: Captive | O8: =O32 -> 2474.7736 | P8: =P32 -> 8168.4689 | Q8: =Q32 -> 8227.6115 | R8: =R32 -> 8150.1619 | S8: =S32 -> 7159.766 | T8: =T32 -> 7813.6521 | U8: =U32 -> 7407.2577 | V8: =V32 -> 7550.3174 | ... AD8: =AD32 -> 102379.18
D9: Non-Captive | O9: =O39 -> 29642.852 | P9: =P39 -> 7927.3197 | Q9: =Q39 -> 7962.8439 | R9: =R39 -> 7978.3976 | S9: =S39 -> 6691.3716 | T9: =T39 -> 7363.0147 | U9: =U39 -> 7236.8438 | V9: =V39 -> 7287.2639 | ... AD9: =AD39 -> 129977.64
C10: 직수출 | O10: =O167 -> 16151.039 | P10: =P167 -> 4029.1142 | Q10: =Q167 -> 3985.546 | R10: =R167 -> 5271.1354 | S10: =S167 -> 4023.8946 | T10: =T167 -> 3887.8392 | U10: =U167 -> 4352.3323 | V10: =V167 -> 3853.2827 | ... AD10: =AD167 -> 65105.515
C11: 이전 | O11: =O395 -> 27653.424 | P11: =P395 -> 11060.878 | Q11: =Q395 -> 8212.613 | R11: =R395 -> 8836.7858 | S11: =S395 -> 9627.2965 | T11: =T395 -> 10415.101 | U11: =U395 -> 9033.7251 | V11: =V395 -> 9275.117 | ... AD11: =AD395 -> 133884.82
L13: 2021A | M13: 2022A | N13: 2023A | O13: 24.3m(A) | P13: 4월 | Q13: 5월 | R13: 6월 | S13: 7월 | T13: 8월 | U13: 9월 | V13: 10월 | W13: 11월 | X13: 12월 | Y13: 24.9m(E) | Z13: 2024F | AA13: 2025F | AB13: 2026F | AC13: 2027F | AD13: 2028F
B14: 판매수량 | O14: =SUM(O15:O19) -> 642 | P14: =SUM(P15:P19) -> 272 | Q14: =SUM(Q15:Q19) -> 254 | R14: =SUM(R15:R19) -> 257 | S14: =SUM(S15:S19) -> 251 | T14: =SUM(T15:T19) -> 257 | U14: =SUM(U15:U19) -> 239 | V14: =SUM(V15:V19) -> 251 | ... AD14: =SUM(AD15:AD19) -> 3822
C15: 5축 | O15: =SUM(Revenue_HW!O51,Revenue_HW!O178,Revenue_HW!O221,Revenue_HW!O264,Revenue_HW!O307,Revenue_HW!O350,Revenue_HW!O399,Revenue_HW!O437,Revenue_HW!O475,Revenue_HW!O513) -> 4 | P15: =SUM(Revenue_HW!P51,Revenue_HW!P178,Revenue_HW!P221,Revenue_HW!P264,Revenue_HW!P307,Revenue_HW!P350,Revenue_HW!P399,Revenue_HW!P437,Revenue_HW!P475,Revenue_HW!P513) -> 3 | Q15: =SUM(Revenue_HW!Q51,Revenue_HW!Q178,Revenue_HW!Q221,Revenue_HW!Q264,Revenue_HW!Q307,Revenue_HW!Q350,Revenue_HW!Q399,Revenue_HW!Q437,Revenue_HW!Q475,Revenue_HW!Q513) -> 7 | R15: =SUM(Revenue_HW!R51,Revenue_HW!R178,Revenue_HW!R221,Revenue_HW!R264,Revenue_HW!R307,Revenue_HW!R350,Revenue_HW!R399,Revenue_HW!R437,Revenue_HW!R475,Revenue_HW!R513) -> 7 | S15: =SUM(Revenue_HW!S51,Revenue_HW!S178,Revenue_HW!S221,Revenue_HW!S264,Revenue_HW!S307,Revenue_HW!S350,Revenue_HW!S399,Revenue_HW!S437,Revenue_HW!S475,Revenue_HW!S513) -> 5 | T15: =SUM(Revenue_HW!T51,Revenue_HW!T178,Revenue_HW!T221,Revenue_HW!T264,Revenue_HW!T307,Revenue_HW!T350,Revenue_HW!T399,Revenue_HW!T437,Revenue_HW!T475,Revenue_HW!T513) -> 3 | U15: =SUM(Revenue_HW!U51,Revenue_HW!U178,Revenue_HW!U221,Revenue_HW!U264,Revenue_HW!U307,Revenue_HW!U350,Revenue_HW!U399,Revenue_HW!U437,Revenue_HW!U475,Revenue_HW!U513) -> 6 | V15: =SUM(Revenue_HW!V51,Revenue_HW!V178,Revenue_HW!V221,Revenue_HW!V264,Revenue_HW!V307,Revenue_HW!V350,Revenue_HW!V399,Revenue_HW!V437,Revenue_HW!V475,Revenue_HW!V513) -> 5 | ... AD15: =SUM(Revenue_HW!AD51,Revenue_HW!AD178,Revenue_HW!AD221,Revenue_HW!AD264,Revenue_HW!AD307,Revenue_HW!AD350,Revenue_HW!AD399,Revenue_HW!AD437,Revenue_HW!AD475,Revenue_HW!AD513) -> 103
C16: 선반 | O16: =SUM(O56,O184,O227,O270,O313,O356,O404,O442,O480,O518) -> 387 | P16: =SUM(P56,P184,P227,P270,P313,P356,P404,P442,P480,P518) -> 167 | Q16: =SUM(Q56,Q184,Q227,Q270,Q313,Q356,Q404,Q442,Q480,Q518) -> 144 | R16: =SUM(R56,R184,R227,R270,R313,R356,R404,R442,R480,R518) -> 149 | S16: =SUM(S56,S184,S227,S270,S313,S356,S404,S442,S480,S518) -> 152 | T16: =SUM(T56,T184,T227,T270,T313,T356,T404,T442,T480,T518) -> 149 | U16: =SUM(U56,U184,U227,U270,U313,U356,U404,U442,U480,U518) -> 141 | V16: =SUM(V56,V184,V227,V270,V313,V356,V404,V442,V480,V518) -> 154 | ... AD16: =SUM(AD56,AD184,AD227,AD270,AD313,AD356,AD404,AD442,AD480,AD518) -> 2184
C17: VMC | O17: =SUM(O61,O190,O233,O276,O319,O362,O409,O447,O485,O523) -> 209 | P17: =SUM(P61,P190,P233,P276,P319,P362,P409,P447,P485,P523) -> 77 | Q17: =SUM(Q61,Q190,Q233,Q276,Q319,Q362,Q409,Q447,Q485,Q523) -> 81 | R17: =SUM(R61,R190,R233,R276,R319,R362,R409,R447,R485,R523) -> 80 | S17: =SUM(S61,S190,S233,S276,S319,S362,S409,S447,S485,S523) -> 82 | T17: =SUM(T61,T190,T233,T276,T319,T362,T409,T447,T485,T523) -> 80 | U17: =SUM(U61,U190,U233,U276,U319,U362,U409,U447,U485,U523) -> 67 | V17: =SUM(V61,V190,V233,V276,V319,V362,V409,V447,V485,V523) -> 69 | ... AD17: =SUM(AD61,AD190,AD233,AD276,AD319,AD362,AD409,AD447,AD485,AD523) -> 1412
C18: HMC | O18: =SUM(O66,O196,O239,O282,O325,O368,O414,O452,O490,O528) -> 9 | P18: =SUM(P66,P196,P239,P282,P325,P368,P414,P452,P490,P528) -> 10 | Q18: =SUM(Q66,Q196,Q239,Q282,Q325,Q368,Q414,Q452,Q490,Q528) -> 8 | R18: =SUM(R66,R196,R239,R282,R325,R368,R414,R452,R490,R528) -> 11 | S18: =SUM(S66,S196,S239,S282,S325,S368,S414,S452,S490,S528) -> 6 | T18: =SUM(T66,T196,T239,T282,T325,T368,T414,T452,T490,T528) -> 12 | U18: =SUM(U66,U196,U239,U282,U325,U368,U414,U452,U490,U528) -> 9 | V18: =SUM(V66,V196,V239,V282,V325,V368,V414,V452,V490,V528) -> 8 | ... AD18: =SUM(AD66,AD196,AD239,AD282,AD325,AD368,AD414,AD452,AD490,AD528) -> 123
C19: 단종 | O19: =SUM(O71,O202,O245,O288,O331,O374,O419,O457,O495,O533) -> 33 | P19: =SUM(P71,P202,P245,P288,P331,P374,P419,P457,P495,P533) -> 15 | Q19: =SUM(Q71,Q202,Q245,Q288,Q331,Q374,Q419,Q457,Q495,Q533) -> 14 | R19: =SUM(R71,R202,R245,R288,R331,R374,R419,R457,R495,R533) -> 10 | S19: =SUM(S71,S202,S245,S288,S331,S374,S419,S457,S495,S533) -> 6 | T19: =SUM(T71,T202,T245,T288,T331,T374,T419,T457,T495,T533) -> 13 | U19: =SUM(U71,U202,U245,U288,U331,U374,U419,U457,U495,U533) -> 16 | V19: =SUM(V71,V202,V245,V288,V331,V374,V419,V457,V495,V533) -> 15 | ... AD19: =SUM(AD71,AD202,AD245,AD288,AD331,AD374,AD419,AD457,AD495,AD533) -> 0
B21: 2. 국내
AA22: =AA24/Z24-1 -> -0.024934293 | AB22: =AB24/AA24-1 -> 0.14844475 | AC22: =AC24/AB24-1 -> 0.11412558 | AD22: =AD24/AC24-1 -> 0.12044644
L23: 2021A | M23: 2022A | N23: 2023A | O23: 24.3m(A) | P23: 4월 | Q23: 5월 | R23: 6월 | S23: 7월 | T23: 8월 | U23: 9월 | V23: 10월 | W23: 11월 | X23: 12월 | Y23: 24.9m(E) | Z23: 2024F | AA23: 2025F | AB23: 2026F | AC23: 2027F | AD23: 2028F
B24: 국내매출 | O24: =O25 -> 32117.625 | P24: =P25 -> 16095.789 | Q24: =Q25 -> 16190.455 | R24: =R25 -> 16128.559 | S24: =S25 -> 13851.138 | T24: =T25 -> 15176.667 | U24: =U25 -> 14644.102 | V24: =V25 -> 14837.581 | ... AD24: =AD25 -> 232356.82
C25: 전체 | O25: =O26+O27+O28+O29+O30+O31 -> 32117.625 | P25: =P26+P27+P28+P29+P30+P31 -> 16095.789 | Q25: =Q26+Q27+Q28+Q29+Q30+Q31 -> 16190.455 | R25: =R26+R27+R28+R29+R30+R31 -> 16128.559 | S25: =S26+S27+S28+S29+S30+S31 -> 13851.138 | T25: =T26+T27+T28+T29+T30+T31 -> 15176.667 | U25: =U26+U27+U28+U29+U30+U31 -> 14644.102 | V25: =V26+V27+V28+V29+V30+V31 -> 14837.581 | ... AD25: =AD26+AD27+AD28+AD29+AD30+AD31 -> 232356.82
D26: 5축 | O26: =O50 -> 643 | P26: =P50 -> 905.21086 | Q26: =Q50 -> 905.21086 | R26: =R50 -> 1206.9478 | S26: =S50 -> 603.4739 | T26: =T50 -> 603.4739 | U26: =U50 -> 905.21086 | V26: =V50 -> 905.21086 | ... X26: =X50 -> 301.73695 | Y26: =SUM(P26:X26) -> 7241.6869 | Z26: =Z50 -> 7884.6869 | AA26: =AA50 -> 9989.4504 | AB26: =AB50 -> 12683.212 | AC26: =AC50 -> 13646.676 | AD26: =AD50 -> 17051.241
D27: 선반 | O27: =O55 -> 10464.138 | P27: =P55 -> 4927.9832 | Q27: =Q55 -> 5042.5875 | R27: =R55 -> 4927.9832 | S27: =S55 -> 4756.0768 | T27: =T55 -> 4756.0768 | U27: =U55 -> 4469.5662 | V27: =V55 -> 4756.0768 | ... X27: =X55 -> 4297.6598 | Y27: =SUM(P27:X27) -> 42518.181 | Z27: =Z55 -> 52982.318 | AA27: =AA55 -> 56254.374 | AB27: =AB55 -> 61988.76 | AC27: =AC55 -> 67506.077 | AD27: =AD55 -> 72226.305
D28: VMC | O28: =O60 -> 9894.2026 | P28: =P60 -> 4793.1204 | Q28: =Q60 -> 4874.3597 | R28: =R60 -> 4955.599 | S28: =S60 -> 4793.1204 | T28: =T60 -> 4955.599 | U28: =U60 -> 4143.2057 | V28: =V60 -> 4224.4451 | ... X28: =X60 -> 3980.7271 | Y28: =SUM(P28:X28) -> 40863.382 | Z28: =Z60 -> 50757.585 | AA28: =AA60 -> 54340.235 | AB28: =AB60 -> 65297.874 | AC28: =AC60 -> 75555.377 | AD28: =AD60 -> 87028.299
D29: HMC | O29: =O65 -> 963.45 | P29: =P65 -> 1556.6361 | Q29: =Q65 -> 1556.6361 | R29: =R65 -> 1816.0754 | S29: =S65 -> 1297.1967 | T29: =T65 -> 1556.6361 | U29: =U65 -> 1556.6361 | V29: =V65 -> 1816.0754 | ... X29: =X65 -> 1297.1967 | Y29: =SUM(P29:X29) -> 14009.725 | Z29: =Z65 -> 14973.175 | AA29: =AA65 -> 16109.204 | AB29: =AB65 -> 17014.816 | AC29: =AC65 -> 18192.498 | AD29: =AD65 -> 19660.94
D30: 단종 | O30: =O70 -> 2416.508 | P30: =P70 -> 1392.0329 | Q30: =Q70 -> 1276.0302 | R30: =R70 -> 696.01645 | S30: =S70 -> 232.00548 | T30: =T70 -> 928.02193 | U30: =U70 -> 1276.0302 | V30: =V70 -> 812.01919 | ... X30: =X70 -> 928.02193 | Y30: =SUM(P30:X30) -> 8468.2001 | Z30: =Z70 -> 10884.708 | AA30: =AA70 -> 0 | AB30: =AB70 -> 0 | AC30: =AC70 -> 0 | AD30: =AD70 -> 0
D31: 기타 | O31: =O75 -> 7736.3271 | P31: =P75 -> 2520.8052 | Q31: =Q75 -> 2535.6312 | R31: =R75 -> 2525.9375 | S31: =S75 -> 2169.2643 | T31: =T75 -> 2376.859 | U31: =U75 -> 2293.4525 | V31: =V75 -> 2323.7539 | ... X31: =X75 -> 2006.497 | Y31: =SUM(P31:X31) -> 21002.311 | Z31: =Z75 -> 28738.639 | AA31: =AA75 -> 25383.242 | AB31: =AB75 -> 29151.251 | AC31: =AC75 -> 32478.155 | AD31: =AD75 -> 36390.033
C32: Captive | O32: =SUM(O33:O38) -> 2474.7736 | P32: =SUM(P33:P38) -> 8168.4689 | Q32: =SUM(Q33:Q38) -> 8227.6115 | R32: =SUM(R33:R38) -> 8150.1619 | S32: =SUM(S33:S38) -> 7159.766 | T32: =SUM(T33:T38) -> 7813.6521 | U32: =SUM(U33:U38) -> 7407.2577 | V32: =SUM(V33:V38) -> 7550.3174 | ... AD32: =SUM(AD33:AD38) -> 102379.18
D33: 5축 | O33: =O88 -> 0 | P33: =P88 -> 238.73789 | Q33: =Q88 -> 238.73789 | R33: =R88 -> 318.31719 | S33: =S88 -> 159.15859 | T33: =T88 -> 159.15859 | U33: =U88 -> 238.73789 | V33: =V88 -> 238.73789 | ... X33: =X88 -> 79.579297 | Y33: =SUM(P33:X33) -> 1909.9031 | Z33: =Z88 -> 1909.9031 | AA33: =AA88 -> 2401.3468 | AB33: =AB88 -> 3139.3732 | AC33: =AC88 -> 3401.4385 | AD33: =AD88 -> 4150.8203
D34: 선반 | O34: =O93 -> 641.644 | P34: =P93 -> 2600.6302 | Q34: =Q93 -> 2661.11 | R34: =R93 -> 2600.6302 | S34: =S93 -> 2509.9106 | T34: =T93 -> 2509.9106 | U34: =U93 -> 2358.7111 | V34: =V93 -> 2509.9106 | ... X34: =X93 -> 2267.9915 | Y34: =SUM(P34:X34) -> 22437.996 | Z34: =Z93 -> 23079.64 | AA34: =AA93 -> 24470.901 | AB34: =AB93 -> 27312.228 | AC34: =AC93 -> 29957.899 | AD34: =AD93 -> 32136.794
D35: VMC | O35: =O98 -> 923.456 | P35: =P98 -> 2553.239 | Q35: =Q98 -> 2596.5142 | R35: =R98 -> 2639.7895 | S35: =S98 -> 2553.239 | T35: =T98 -> 2639.7895 | U35: =U98 -> 2207.0371 | V35: =V98 -> 2250.3123 | ... X35: =X98 -> 2120.4866 | Y35: =SUM(P35:X35) -> 21767.444 | Z35: =Z98 -> 22690.9 | AA35: =AA98 -> 24282.373 | AB35: =AB98 -> 29498.343 | AC35: =AC98 -> 34380.41 | AD35: =AD98 -> 39752.259
D36: HMC | O36: =O103 -> 0 | P36: =P103 -> 850.07721 | Q36: =Q103 -> 850.07721 | R36: =R103 -> 991.75674 | S36: =S103 -> 708.39767 | T36: =T103 -> 850.07721 | U36: =U103 -> 850.07721 | V36: =V103 -> 991.75674 | ... X36: =X103 -> 708.39767 | Y36: =SUM(P36:X36) -> 7650.6949 | Z36: =Z103 -> 7650.6949 | AA36: =AA103 -> 8237.3594 | AB36: =AB103 -> 8820.1543 | AC36: =AC103 -> 9423.8049 | AD36: =AD103 -> 10305.428
D37: 단종 | O37: =O108 -> 96.65 | P37: =P108 -> 646.4985 | Q37: =Q108 -> 592.62362 | R37: =R108 -> 323.24925 | S37: =S108 -> 107.74975 | T37: =T108 -> 430.999 | U37: =U108 -> 592.62362 | V37: =V108 -> 377.12412 | ... X37: =X108 -> 430.999 | Y37: =SUM(P37:X37) -> 3932.8658 | Z37: =Z108 -> 4029.5158 | AA37: =AA108 -> 0 | AB37: =AB108 -> 0 | AC37: =AC108 -> 0 | AD37: =AD108 -> 0
D38: 기타 | O38: =O113 -> 813.0236 | P38: =P113 -> 1279.2861 | Q38: =Q113 -> 1288.5486 | R38: =R113 -> 1276.419 | S38: =S113 -> 1121.3104 | T38: =T113 -> 1223.7173 | U38: =U113 -> 1160.0708 | V38: =V113 -> 1182.4757 | ... X38: =X113 -> 1041.2756 | Y38: =SUM(P38:X38) -> 10714.392 | Z38: =Z113 -> 11527.416 | AA38: =AA113 -> 11028.788 | AB38: =AB113 -> 12770.257 | AC38: =AC113 -> 14328.878 | AD38: =AD113 -> 16033.882
C39: Non-Captive | O39: =SUM(O40:O45) -> 29642.852 | P39: =SUM(P40:P45) -> 7927.3197 | Q39: =SUM(Q40:Q45) -> 7962.8439 | R39: =SUM(R40:R45) -> 7978.3976 | S39: =SUM(S40:S45) -> 6691.3716 | T39: =SUM(T40:T45) -> 7363.0147 | U39: =SUM(U40:U45) -> 7236.8438 | V39: =SUM(V40:V45) -> 7287.2639 | ... AD39: =SUM(AD40:AD45) -> 129977.64
D40: 5축 | O40: =O126 -> 643 | P40: =P126 -> 666.47297 | Q40: =Q126 -> 666.47297 | R40: =R126 -> 888.63062 | S40: =S126 -> 444.31531 | T40: =T126 -> 444.31531 | U40: =U126 -> 666.47297 | V40: =V126 -> 666.47297 | ... X40: =X126 -> 222.15766 | Y40: =SUM(P40:X40) -> 5331.7837 | Z40: =Z126 -> 5974.7837 | AA40: =AA126 -> 7588.1037 | AB40: =AB126 -> 9543.8385 | AC40: =AC126 -> 10245.237 | AD40: =AD126 -> 12900.421
D41: 선반 | O41: =O131 -> 9822.4936 | P41: =P131 -> 2327.353 | Q41: =Q131 -> 2381.4775 | R41: =R131 -> 2327.353 | S41: =S131 -> 2246.1663 | T41: =T131 -> 2246.1663 | U41: =U131 -> 2110.8551 | V41: =V131 -> 2246.1663 | ... X41: =X131 -> 2029.6683 | Y41: =SUM(P41:X41) -> 20080.185 | Z41: =Z131 -> 29902.679 | AA41: =AA131 -> 31783.472 | AB41: =AB131 -> 34676.532 | AC41: =AC131 -> 37548.178 | AD41: =AD131 -> 40089.511
D42: VMC | O42: =O136 -> 8970.7466 | P42: =P136 -> 2239.8814 | Q42: =Q136 -> 2277.8454 | R42: =R136 -> 2315.8095 | S42: =S136 -> 2239.8814 | T42: =T136 -> 2315.8095 | U42: =U136 -> 1936.1686 | V42: =V136 -> 1974.1327 | ... X42: =X136 -> 1860.2404 | Y42: =SUM(P42:X42) -> 19095.938 | Z42: =Z136 -> 28066.684 | AA42: =AA136 -> 30057.863 | AB42: =AB136 -> 35799.531 | AC42: =AC136 -> 41174.967 | AD42: =AD136 -> 47276.041
D43: HMC | O43: =O141 -> 963.45 | P43: =P141 -> 706.55887 | Q43: =Q141 -> 706.55887 | R43: =R141 -> 824.31868 | S43: =S141 -> 588.79906 | T43: =T141 -> 706.55887 | U43: =U141 -> 706.55887 | V43: =V141 -> 824.31868 | ... X43: =X141 -> 588.79906 | Y43: =SUM(P43:X43) -> 6359.0298 | Z43: =Z141 -> 7322.4798 | AA43: =AA141 -> 7871.8445 | AB43: =AB141 -> 8194.6613 | AC43: =AC141 -> 8768.6926 | AD43: =AD141 -> 9355.5122
D44: 단종 | O44: =O146 -> 2319.858 | P44: =P146 -> 745.5344 | Q44: =Q146 -> 683.40653 | R44: =R146 -> 372.7672 | S44: =S146 -> 124.25573 | T44: =T146 -> 497.02293 | U44: =U146 -> 683.40653 | V44: =V146 -> 434.89507 | ... X44: =X146 -> 497.02293 | Y44: =SUM(P44:X44) -> 4535.3343 | Z44: =Z146 -> 6855.1923 | AA44: =AA146 -> 0 | AB44: =AB146 -> 0 | AC44: =AC146 -> 0 | AD44: =AD146 -> 0
D45: 기타 | O45: =O151 -> 6923.3035 | P45: =P151 -> 1241.5191 | Q45: =Q151 -> 1247.0826 | R45: =R151 -> 1249.5185 | S45: =S151 -> 1047.9539 | T45: =T151 -> 1153.1417 | U45: =U151 -> 1133.3818 | V45: =V151 -> 1141.2782 | ... X45: =X151 -> 965.22138 | Y45: =SUM(P45:X45) -> 10287.919 | Z45: =Z151 -> 17211.223 | AA45: =AA151 -> 14354.454 | AB45: =AB151 -> 16380.995 | AC45: =AC151 -> 18149.276 | AD45: =AD151 -> 20356.151
L47: 2021A | M47: 2022A | N47: 2023A | O47: 24.3m(A) | P47: 4월 | Q47: 5월 | R47: 6월 | S47: 7월 | T47: 8월 | U47: 9월 | V47: 10월 | W47: 11월 | X47: 12월 | Y47: 24.9m(E) | Z47: 2024F | AA47: 2025F | AB47: 2026F | AC47: 2027F | AD47: 2028F
A48: 국내 | B48: 국내매출 | O48: =O49 -> 32117.625 | P48: =P49 -> 16095.789 | Q48: =Q49 -> 16190.455 | R48: =R49 -> 16128.559 | S48: =S49 -> 13851.138 | T48: =T49 -> 15176.667 | U48: =U49 -> 14644.102 | V48: =V49 -> 14837.581 | ... AD48: =AD49 -> 232356.82
A49: 국내 | C49: 전체 | O49: =O50+O55+O60+O65+O75+O70 -> 32117.625 | P49: =P50+P55+P60+P65+P75+P70 -> 16095.789 | Q49: =Q50+Q55+Q60+Q65+Q75+Q70 -> 16190.455 | R49: =R50+R55+R60+R65+R75+R70 -> 16128.559 | S49: =S50+S55+S60+S65+S75+S70 -> 13851.138 | T49: =T50+T55+T60+T65+T75+T70 -> 15176.667 | U49: =U50+U55+U60+U65+U75+U70 -> 14644.102 | V49: =V50+V55+V60+V65+V75+V70 -> 14837.581 | ... AD49: =AD50+AD55+AD60+AD65+AD75+AD70 -> 232356.82
A50: 국내 | D50: 5축 | O50: =O88+O126 -> 643 | P50: =P51*P54 -> 905.21086 | Q50: =Q51*Q54 -> 905.21086 | R50: =R51*R54 -> 1206.9478 | S50: =S51*S54 -> 603.4739 | T50: =T51*T54 -> 603.4739 | U50: =U51*U54 -> 905.21086 | V50: =V51*V54 -> 905.21086 | W50: =W51*W54 -> 905.21086 | X50: =X51*X54 -> 301.73695 | Y50: =SUM(P50:X50) -> 7241.6869 | Z50: =Y50+O50 -> 7884.6869 | AA50: =AA88+AA126 -> 9989.4504 | AB50: =AB88+AB126 -> 12683.212 | AC50: =AC88+AC126 -> 13646.676 | AD50: =AD88+AD126 -> 17051.241
A51: 국내 | E51: 판매수량 | O51: =O89+O127 -> 3 | P51: =SUMIFS(INDEX(판매수량!$N$2:$V$82,0,MATCH(Revenue_HW!P$47,판매수량!$N$2:$V$2,0)),판매수량!$A$2:$A$82,Revenue_HW!$A51,판매수량!$B$2:$B$82,Revenue_HW!$AG51) -> 3 | Q51: =SUMIFS(INDEX(판매수량!$N$2:$V$82,0,MATCH(Revenue_HW!Q$47,판매수량!$N$2:$V$2,0)),판매수량!$A$2:$A$82,Revenue_HW!$A51,판매수량!$B$2:$B$82,Revenue_HW!$AG51) -> 3 | R51: =SUMIFS(INDEX(판매수량!$N$2:$V$82,0,MATCH(Revenue_HW!R$47,판매수량!$N$2:$V$2,0)),판매수량!$A$2:$A$82,Revenue_HW!$A51,판매수량!$B$2:$B$82,Revenue_HW!$AG51) -> 4 | S51: =SUMIFS(INDEX(판매수량!$N$2:$V$82,0,MATCH(Revenue_HW!S$47,판매수량!$N$2:$V$2,0)),판매수량!$A$2:$A$82,Revenue_HW!$A51,판매수량!$B$2:$B$82,Revenue_HW!$AG51) -> 2 | T51: =SUMIFS(INDEX(판매수량!$N$2:$V$82,0,MATCH(Revenue_HW!T$47,판매수량!$N$2:$V$2,0)),판매수량!$A$2:$A$82,Revenue_HW!$A51,판매수량!$B$2:$B$82,Revenue_HW!$AG51) -> 2 | U51: =SUMIFS(INDEX(판매수량!$N$2:$V$82,0,MATCH(Revenue_HW!U$47,판매수량!$N$2:$V$2,0)),판매수량!$A$2:$A$82,Revenue_HW!$A51,판매수량!$B$2:$B$82,Revenue_HW!$AG51) -> 3 | V51: =SUMIFS(INDEX(판매수량!$N$2:$V$82,0,MATCH(Revenue_HW!V$47,판매수량!$N$2:$V$2,0)),판매수량!$A$2:$A$82,Revenue_HW!$A51,판매수량!$B$2:$B$82,Revenue_HW!$AG51) -> 3 | W51: =SUMIFS(INDEX(판매수량!$N$2:$V$82,0,MATCH(Revenue_HW!W$47,판매수량!$N$2:$V$2,0)),판매수량!$A$2:$A$82,Revenue_HW!$A51,판매수량!$B$2:$B$82,Revenue_HW!$AG51) -> 3 | X51: =SUMIFS(INDEX(판매수량!$N$2:$V$82,0,MATCH(Revenue_HW!X$47,판매수량!$N$2:$V$2,0)),판매수량!$A$2:$A$82,Revenue_HW!$A51,판매수량!$B$2:$B$82,Revenue_HW!$AG51) -> 1 | Y51: =SUM(P51:X51) -> 24 | Z51: =Y51+O51 -> 27 | AA51: =AA89+AA127 -> 34 | AB51: =AB89+AB127 -> 43 | AC51: =AC89+AC127 -> 46 | AD51: =AD89+AD127 -> 57 | AG51: =IF($E51="판매수량",$D50,) -> 5축
A52: 국내 | F52: 기종 수 | Z52: ='Key Assumption'!AA54 -> 5 | AA52: ='Key Assumption'!AB54 -> 6 | AB52: ='Key Assumption'!AC54 -> 7 | AC52: ='Key Assumption'!AD54 -> 7 | AD52: ='Key Assumption'!AE54 -> 8
A53: 국내 | F53: 기종당 판매량 | Z53: =Z51/Z52 -> 5.4 | AA53: =AA51/AA52 -> 5.6666667 | AB53: =AB51/AB52 -> 6.1428571 | AC53: =AC51/AC52 -> 6.5714286 | AD53: =AD51/AD52 -> 7.125
A54: 국내 | E54: 판매단가 | O54: =O50/O51 -> 214.33333 | P54: ='Key Assumption'!R291 -> 301.73695 | Q54: ='Key Assumption'!S291 -> 301.73695 | R54: ='Key Assumption'!T291 -> 301.73695 | S54: ='Key Assumption'!U291 -> 301.73695 | T54: ='Key Assumption'!V291 -> 301.73695 | U54: ='Key Assumption'!W291 -> 301.73695 | V54: ='Key Assumption'!X291 -> 301.73695 | W54: ='Key Assumption'!Y291 -> 301.73695 | X54: ='Key Assumption'!Z291 -> 301.73695 | Y54: =Y50/Y51 -> 301.73695 | Z54: =Z50/Z51 -> 292.02544 | AA54: =AA50/AA51 -> 293.80737 | AB54: =AB50/AB51 -> 294.95841 | AC54: =AC50/AC51 -> 296.66686 | AD54: =AD50/AD51 -> 299.14458
A55: 국내 | D55: 선반 | O55: =O93+O131 -> 10464.138 | P55: =P56*P59 -> 4927.9832 | Q55: =Q56*Q59 -> 5042.5875 | R55: =R56*R59 -> 4927.9832 | S55: =S56*S59 -> 4756.0768 | T55: =T56*T59 -> 4756.0768 | U55: =U56*U59 -> 4469.5662 | V55: =V56*V59 -> 4756.0768 | W55: =W56*W59 -> 4584.1704 | X55: =X56*X59 -> 4297.6598 | Y55: =SUM(P55:X55) -> 42518.181 | Z55: =Y55+O55 -> 52982.318 | AA55: =AA93+AA131 -> 56254.374 | AB55: =AB93+AB131 -> 61988.76 | AC55: =AC93+AC131 -> 67506.077 | AD55: =AD93+AD131 -> 72226.305
A56: 국내 | E56: 판매수량 | O56: =O94+O132 -> 182 | P56: =SUMIFS(INDEX(판매수량!$N$2:$V$82,0,MATCH(Revenue_HW!P$47,판매수량!$N$2:$V$2,0)),판매수량!$A$2:$A$82,Revenue_HW!$A56,판매수량!$B$2:$B$82,Revenue_HW!$AG56) -> 86 | Q56: =SUMIFS(INDEX(판매수량!$N$2:$V$82,0,MATCH(Revenue_HW!Q$47,판매수량!$N$2:$V$2,0)),판매수량!$A$2:$A$82,Revenue_HW!$A56,판매수량!$B$2:$B$82,Revenue_HW!$AG56) -> 88 | R56: =SUMIFS(INDEX(판매수량!$N$2:$V$82,0,MATCH(Revenue_HW!R$47,판매수량!$N$2:$V$2,0)),판매수량!$A$2:$A$82,Revenue_HW!$A56,판매수량!$B$2:$B$82,Revenue_HW!$AG56) -> 86 | S56: =SUMIFS(INDEX(판매수량!$N$2:$V$82,0,MATCH(Revenue_HW!S$47,판매수량!$N$2:$V$2,0)),판매수량!$A$2:$A$82,Revenue_HW!$A56,판매수량!$B$2:$B$82,Revenue_HW!$AG56) -> 83 | T56: =SUMIFS(INDEX(판매수량!$N$2:$V$82,0,MATCH(Revenue_HW!T$47,판매수량!$N$2:$V$2,0)),판매수량!$A$2:$A$82,Revenue_HW!$A56,판매수량!$B$2:$B$82,Revenue_HW!$AG56) -> 83 | U56: =SUMIFS(INDEX(판매수량!$N$2:$V$82,0,MATCH(Revenue_HW!U$47,판매수량!$N$2:$V$2,0)),판매수량!$A$2:$A$82,Revenue_HW!$A56,판매수량!$B$2:$B$82,Revenue_HW!$AG56) -> 78 | V56: =SUMIFS(INDEX(판매수량!$N$2:$V$82,0,MATCH(Revenue_HW!V$47,판매수량!$N$2:$V$2,0)),판매수량!$A$2:$A$82,Revenue_HW!$A56,판매수량!$B$2:$B$82,Revenue_HW!$AG56) -> 83 | W56: =SUMIFS(INDEX(판매수량!$N$2:$V$82,0,MATCH(Revenue_HW!W$47,판매수량!$N$2:$V$2,0)),판매수량!$A$2:$A$82,Revenue_HW!$A56,판매수량!$B$2:$B$82,Revenue_HW!$AG56) -> 80 | X56: =SUMIFS(INDEX(판매수량!$N$2:$V$82,0,MATCH(Revenue_HW!X$47,판매수량!$N$2:$V$2,0)),판매수량!$A$2:$A$82,Revenue_HW!$A56,판매수량!$B$2:$B$82,Revenue_HW!$AG56) -> 75 | Y56: =SUM(P56:X56) -> 742 | Z56: =Y56+O56 -> 924 | AA56: =AA94+AA132 -> 976 | AB56: =AB94+AB132 -> 1068 | AC56: =AC94+AC132 -> 1155 | AD56: =AD94+AD132 -> 1227 | AG56: =IF($E56="판매수량",$D55,) -> 선반
A57: 국내 | F57: 기종 수 | Z57: ='Key Assumption'!AA55 -> 53 | AA57: ='Key Assumption'!AB55 -> 53 | AB57: ='Key Assumption'!AC55 -> 55 | AC57: ='Key Assumption'!AD55 -> 56 | AD57: ='Key Assumption'!AE55 -> 56 | AG57: =IF($E57="판매수량",$D56,) -> 0
A58: 국내 | F58: 기종당 판매량 | Z58: =Z56/Z57 -> 17.433962 | AA58: =AA56/AA57 -> 18.415094 | AB58: =AB56/AB57 -> 19.418182 | AC58: =AC56/AC57 -> 20.625 | AD58: =AD56/AD57 -> 21.910714 | AG58: =IF($E58="판매수량",$D57,) -> 0
A59: 국내 | E59: 판매단가 | O59: =O55/O56 -> 57.495261 | P59: ='Key Assumption'!R292 -> 57.302131 | Q59: ='Key Assumption'!S292 -> 57.302131 | R59: ='Key Assumption'!T292 -> 57.302131 | S59: ='Key Assumption'!U292 -> 57.302131 | T59: ='Key Assumption'!V292 -> 57.302131 | U59: ='Key Assumption'!W292 -> 57.302131 | V59: ='Key Assumption'!X292 -> 57.302131 | W59: ='Key Assumption'!Y292 -> 57.302131 | X59: ='Key Assumption'!Z292 -> 57.302131 | Y59: =Y55/Y56 -> 57.302131 | Z59: =Z55/Z56 -> 57.340171 | AA59: =AA55/AA56 -> 57.637678 | AB59: =AB55/AB56 -> 58.04191 | AC59: =AC55/AC56 -> 58.44682 | AD59: =AD55/AD56 -> 58.864144 | AG59: =IF($E59="판매수량",$D58,) -> 0
A60: 국내 | D60: VMC | O60: =O98+O136 -> 9894.2026 | P60: =P61*P64 -> 4793.1204 | Q60: =Q61*Q64 -> 4874.3597 | R60: =R61*R64 -> 4955.599 | S60: =S61*S64 -> 4793.1204 | T60: =T61*T64 -> 4955.599 | U60: =U61*U64 -> 4143.2057 | V60: =V61*V64 -> 4224.4451 | W60: =W61*W64 -> 4143.2057 | X60: =X61*X64 -> 3980.7271 | Y60: =SUM(P60:X60) -> 40863.382 | Z60: =Y60+O60 -> 50757.585 | AA60: =AA98+AA136 -> 54340.235 | AB60: =AB98+AB136 -> 65297.874 | AC60: =AC98+AC136 -> 75555.377 | AD60: =AD98+AD136 -> 87028.299 | AG60: =IF($E60="판매수량",$D59,) -> 0
A61: 국내 | E61: 판매수량 | O61: =O99+O137 -> 128 | P61: =SUMIFS(INDEX(판매수량!$N$2:$V$82,0,MATCH(Revenue_HW!P$47,판매수량!$N$2:$V$2,0)),판매수량!$A$2:$A$82,Revenue_HW!$A61,판매수량!$B$2:$B$82,Revenue_HW!$AG61) -> 59 | Q61: =SUMIFS(INDEX(판매수량!$N$2:$V$82,0,MATCH(Revenue_HW!Q$47,판매수량!$N$2:$V$2,0)),판매수량!$A$2:$A$82,Revenue_HW!$A61,판매수량!$B$2:$B$82,Revenue_HW!$AG61) -> 60 | R61: =SUMIFS(INDEX(판매수량!$N$2:$V$82,0,MATCH(Revenue_HW!R$47,판매수량!$N$2:$V$2,0)),판매수량!$A$2:$A$82,Revenue_HW!$A61,판매수량!$B$2:$B$82,Revenue_HW!$AG61) -> 61 | S61: =SUMIFS(INDEX(판매수량!$N$2:$V$82,0,MATCH(Revenue_HW!S$47,판매수량!$N$2:$V$2,0)),판매수량!$A$2:$A$82,Revenue_HW!$A61,판매수량!$B$2:$B$82,Revenue_HW!$AG61) -> 59 | T61: =SUMIFS(INDEX(판매수량!$N$2:$V$82,0,MATCH(Revenue_HW!T$47,판매수량!$N$2:$V$2,0)),판매수량!$A$2:$A$82,Revenue_HW!$A61,판매수량!$B$2:$B$82,Revenue_HW!$AG61) -> 61 | U61: =SUMIFS(INDEX(판매수량!$N$2:$V$82,0,MATCH(Revenue_HW!U$47,판매수량!$N$2:$V$2,0)),판매수량!$A$2:$A$82,Revenue_HW!$A61,판매수량!$B$2:$B$82,Revenue_HW!$AG61) -> 51 | V61: =SUMIFS(INDEX(판매수량!$N$2:$V$82,0,MATCH(Revenue_HW!V$47,판매수량!$N$2:$V$2,0)),판매수량!$A$2:$A$82,Revenue_HW!$A61,판매수량!$B$2:$B$82,Revenue_HW!$AG61) -> 52 | W61: =SUMIFS(INDEX(판매수량!$N$2:$V$82,0,MATCH(Revenue_HW!W$47,판매수량!$N$2:$V$2,0)),판매수량!$A$2:$A$82,Revenue_HW!$A61,판매수량!$B$2:$B$82,Revenue_HW!$AG61) -> 51 | X61: =SUMIFS(INDEX(판매수량!$N$2:$V$82,0,MATCH(Revenue_HW!X$47,판매수량!$N$2:$V$2,0)),판매수량!$A$2:$A$82,Revenue_HW!$A61,판매수량!$B$2:$B$82,Revenue_HW!$AG61) -> 49 | Y61: =SUM(P61:X61) -> 503 | Z61: =Y61+O61 -> 631 | AA61: =AA99+AA137 -> 671 | AB61: =AB99+AB137 -> 800 | AC61: =AC99+AC137 -> 918 | AD61: =AD99+AD137 -> 1049 | AG61: =IF($E61="판매수량",$D60,) -> VMC
A62: 국내 | F62: 기종 수 | Z62: ='Key Assumption'!AA56 -> 24 | AA62: ='Key Assumption'!AB56 -> 24 | AB62: ='Key Assumption'!AC56 -> 27 | AC62: ='Key Assumption'!AD56 -> 29 | AD62: ='Key Assumption'!AE56 -> 31 | AG62: =IF($E62="판매수량",$D61,) -> 0
A63: 국내 | F63: 기종당 판매량 | Z63: =Z61/Z62 -> 26.291667 | AA63: =AA61/AA62 -> 27.958333 | AB63: =AB61/AB62 -> 29.62963 | AC63: =AC61/AC62 -> 31.655172 | AD63: =AD61/AD62 -> 33.83871 | AG63: =IF($E63="판매수량",$D62,) -> 0
A64: 국내 | E64: 판매단가 | O64: =O60/O61 -> 77.298457 | P64: ='Key Assumption'!R293 -> 81.239328 | Q64: ='Key Assumption'!S293 -> 81.239328 | R64: ='Key Assumption'!T293 -> 81.239328 | S64: ='Key Assumption'!U293 -> 81.239328 | T64: ='Key Assumption'!V293 -> 81.239328 | U64: ='Key Assumption'!W293 -> 81.239328 | V64: ='Key Assumption'!X293 -> 81.239328 | W64: ='Key Assumption'!Y293 -> 81.239328 | X64: ='Key Assumption'!Z293 -> 81.239328 | Y64: =Y60/Y61 -> 81.239328 | Z64: =Z60/Z61 -> 80.439912 | AA64: =AA60/AA61 -> 80.983957 | AB64: =AB60/AB61 -> 81.622342 | AC64: =AC60/AC61 -> 82.304332 | AD64: =AD60/AD61 -> 82.963107 | AG64: =IF($E64="판매수량",$D63,) -> 0
A65: 국내 | D65: HMC | O65: =O103+O141 -> 963.45 | P65: =P66*P69 -> 1556.6361 | Q65: =Q66*Q69 -> 1556.6361 | R65: =R66*R69 -> 1816.0754 | S65: =S66*S69 -> 1297.1967 | T65: =T66*T69 -> 1556.6361 | U65: =U66*U69 -> 1556.6361 | V65: =V66*V69 -> 1816.0754 | W65: =W66*W69 -> 1556.6361 | X65: =X66*X69 -> 1297.1967 | Y65: =SUM(P65:X65) -> 14009.725 | Z65: =Y65+O65 -> 14973.175 | AA65: =AA103+AA141 -> 16109.204 | AB65: =AB103+AB141 -> 17014.816 | AC65: =AC103+AC141 -> 18192.498 | AD65: =AD103+AD141 -> 19660.94 | AG65: =IF($E65="판매수량",$D64,) -> 0
A66: 국내 | E66: 판매수량 | O66: =O104+O142 -> 4 | P66: =SUMIFS(INDEX(판매수량!$N$2:$V$82,0,MATCH(Revenue_HW!P$47,판매수량!$N$2:$V$2,0)),판매수량!$A$2:$A$82,Revenue_HW!$A66,판매수량!$B$2:$B$82,Revenue_HW!$AG66) -> 6 | Q66: =SUMIFS(INDEX(판매수량!$N$2:$V$82,0,MATCH(Revenue_HW!Q$47,판매수량!$N$2:$V$2,0)),판매수량!$A$2:$A$82,Revenue_HW!$A66,판매수량!$B$2:$B$82,Revenue_HW!$AG66) -> 6 | R66: =SUMIFS(INDEX(판매수량!$N$2:$V$82,0,MATCH(Revenue_HW!R$47,판매수량!$N$2:$V$2,0)),판매수량!$A$2:$A$82,Revenue_HW!$A66,판매수량!$B$2:$B$82,Revenue_HW!$AG66) -> 7 | S66: =SUMIFS(INDEX(판매수량!$N$2:$V$82,0,MATCH(Revenue_HW!S$47,판매수량!$N$2:$V$2,0)),판매수량!$A$2:$A$82,Revenue_HW!$A66,판매수량!$B$2:$B$82,Revenue_HW!$AG66) -> 5 | T66: =SUMIFS(INDEX(판매수량!$N$2:$V$82,0,MATCH(Revenue_HW!T$47,판매수량!$N$2:$V$2,0)),판매수량!$A$2:$A$82,Revenue_HW!$A66,판매수량!$B$2:$B$82,Revenue_HW!$AG66) -> 6 | U66: =SUMIFS(INDEX(판매수량!$N$2:$V$82,0,MATCH(Revenue_HW!U$47,판매수량!$N$2:$V$2,0)),판매수량!$A$2:$A$82,Revenue_HW!$A66,판매수량!$B$2:$B$82,Revenue_HW!$AG66) -> 6 | V66: =SUMIFS(INDEX(판매수량!$N$2:$V$82,0,MATCH(Revenue_HW!V$47,판매수량!$N$2:$V$2,0)),판매수량!$A$2:$A$82,Revenue_HW!$A66,판매수량!$B$2:$B$82,Revenue_HW!$AG66) -> 7 | W66: =SUMIFS(INDEX(판매수량!$N$2:$V$82,0,MATCH(Revenue_HW!W$47,판매수량!$N$2:$V$2,0)),판매수량!$A$2:$A$82,Revenue_HW!$A66,판매수량!$B$2:$B$82,Revenue_HW!$AG66) -> 6 | X66: =SUMIFS(INDEX(판매수량!$N$2:$V$82,0,MATCH(Revenue_HW!X$47,판매수량!$N$2:$V$2,0)),판매수량!$A$2:$A$82,Revenue_HW!$A66,판매수량!$B$2:$B$82,Revenue_HW!$AG66) -> 5 | Y66: =SUM(P66:X66) -> 54 | Z66: =Y66+O66 -> 58 | AA66: =AA104+AA142 -> 62 | AB66: =AB104+AB142 -> 65 | AC66: =AC104+AC142 -> 69 | AD66: =AD104+AD142 -> 74 | AG66: =IF($E66="판매수량",$D65,) -> HMC
A67: 국내 | F67: 기종 수 | Z67: ='Key Assumption'!AA57 -> 12 | AA67: ='Key Assumption'!AB57 -> 12 | AB67: ='Key Assumption'!AC57 -> 12 | AC67: ='Key Assumption'!AD57 -> 12 | AD67: ='Key Assumption'!AE57 -> 12 | AG67: =IF($E67="판매수량",$D66,) -> 0
A68: 국내 | F68: 기종당 판매량 | Z68: =Z66/Z67 -> 4.8333333 | AA68: =AA66/AA67 -> 5.1666667 | AB68: =AB66/AB67 -> 5.4166667 | AC68: =AC66/AC67 -> 5.75 | AD68: =AD66/AD67 -> 6.1666667 | AG68: =IF($E68="판매수량",$D67,) -> 0
A69: 국내 | E69: 판매단가 | O69: =O65/O66 -> 240.8625 | P69: ='Key Assumption'!R294 -> 259.43935 | Q69: ='Key Assumption'!S294 -> 259.43935 | R69: ='Key Assumption'!T294 -> 259.43935 | S69: ='Key Assumption'!U294 -> 259.43935 | T69: ='Key Assumption'!V294 -> 259.43935 | U69: ='Key Assumption'!W294 -> 259.43935 | V69: ='Key Assumption'!X294 -> 259.43935 | W69: ='Key Assumption'!Y294 -> 259.43935 | X69: ='Key Assumption'!Z294 -> 259.43935 | Y69: =Y65/Y66 -> 259.43935 | Z69: =Z65/Z66 -> 258.15818 | AA69: =AA65/AA66 -> 259.82587 | AB69: =AB65/AB66 -> 261.76639 | AC69: =AC65/AC66 -> 263.65939 | AD69: =AD65/AD66 -> 265.68837 | AG69: =IF($E69="판매수량",$D68,) -> 0
A70: 국내 | D70: 단종 | O70: =O108+O146 -> 2416.508 | P70: =P71*P74 -> 1392.0329 | Q70: =Q71*Q74 -> 1276.0302 | R70: =R71*R74 -> 696.01645 | S70: =S71*S74 -> 232.00548 | T70: =T71*T74 -> 928.02193 | U70: =U71*U74 -> 1276.0302 | V70: =V71*V74 -> 812.01919 | W70: =W71*W74 -> 928.02193 | X70: =X71*X74 -> 928.02193 | Y70: =SUM(P70:X70) -> 8468.2001 | Z70: =Y70+O70 -> 10884.708 | AG70: =IF($E70="판매수량",$D69,) -> 0
A71: 국내 | E71: 판매수량 | O71: =O109+O147 -> 19 | P71: =SUMIFS(INDEX(판매수량!$N$2:$V$82,0,MATCH(Revenue_HW!P$47,판매수량!$N$2:$V$2,0)),판매수량!$A$2:$A$82,Revenue_HW!$A71,판매수량!$B$2:$B$82,Revenue_HW!$AG71) -> 12 | Q71: =SUMIFS(INDEX(판매수량!$N$2:$V$82,0,MATCH(Revenue_HW!Q$47,판매수량!$N$2:$V$2,0)),판매수량!$A$2:$A$82,Revenue_HW!$A71,판매수량!$B$2:$B$82,Revenue_HW!$AG71) -> 11 | R71: =SUMIFS(INDEX(판매수량!$N$2:$V$82,0,MATCH(Revenue_HW!R$47,판매수량!$N$2:$V$2,0)),판매수량!$A$2:$A$82,Revenue_HW!$A71,판매수량!$B$2:$B$82,Revenue_HW!$AG71) -> 6 | S71: =SUMIFS(INDEX(판매수량!$N$2:$V$82,0,MATCH(Revenue_HW!S$47,판매수량!$N$2:$V$2,0)),판매수량!$A$2:$A$82,Revenue_HW!$A71,판매수량!$B$2:$B$82,Revenue_HW!$AG71) -> 2 | T71: =SUMIFS(INDEX(판매수량!$N$2:$V$82,0,MATCH(Revenue_HW!T$47,판매수량!$N$2:$V$2,0)),판매수량!$A$2:$A$82,Revenue_HW!$A71,판매수량!$B$2:$B$82,Revenue_HW!$AG71) -> 8 | U71: =SUMIFS(INDEX(판매수량!$N$2:$V$82,0,MATCH(Revenue_HW!U$47,판매수량!$N$2:$V$2,0)),판매수량!$A$2:$A$82,Revenue_HW!$A71,판매수량!$B$2:$B$82,Revenue_HW!$AG71) -> 11 | V71: =SUMIFS(INDEX(판매수량!$N$2:$V$82,0,MATCH(Revenue_HW!V$47,판매수량!$N$2:$V$2,0)),판매수량!$A$2:$A$82,Revenue_HW!$A71,판매수량!$B$2:$B$82,Revenue_HW!$AG71) -> 7 | W71: =SUMIFS(INDEX(판매수량!$N$2:$V$82,0,MATCH(Revenue_HW!W$47,판매수량!$N$2:$V$2,0)),판매수량!$A$2:$A$82,Revenue_HW!$A71,판매수량!$B$2:$B$82,Revenue_HW!$AG71) -> 8 | X71: =SUMIFS(INDEX(판매수량!$N$2:$V$82,0,MATCH(Revenue_HW!X$47,판매수량!$N$2:$V$2,0)),판매수량!$A$2:$A$82,Revenue_HW!$A71,판매수량!$B$2:$B$82,Revenue_HW!$AG71) -> 8 | Y71: =SUM(P71:X71) -> 73 | Z71: =Y71+O71 -> 92 | AG71: =IF($E71="판매수량",$D70,) -> 단종
A72: 국내 | F72: 기종 수 | Z72: 19 | AG72: =IF($E72="판매수량",$D71,) -> 0
A73: 국내 | F73: 기종당 판매량 | Z73: =Z71/Z72 -> 4.8421053 | AG73: =IF($E73="판매수량",$D72,) -> 0
A74: 국내 | E74: 판매단가 | O74: =O70/O71 -> 127.18463 | P74: ='Key Assumption'!R295 -> 116.00274 | Q74: ='Key Assumption'!S295 -> 116.00274 | R74: ='Key Assumption'!T295 -> 116.00274 | S74: ='Key Assumption'!U295 -> 116.00274 | T74: ='Key Assumption'!V295 -> 116.00274 | U74: ='Key Assumption'!W295 -> 116.00274 | V74: ='Key Assumption'!X295 -> 116.00274 | W74: ='Key Assumption'!Y295 -> 116.00274 | X74: ='Key Assumption'!Z295 -> 116.00274 | Y74: =Y70/Y71 -> 116.00274 | Z74: =Z70/Z71 -> 118.31205 | AG74: =IF($E74="판매수량",$D73,) -> 0
A75: 국내 | D75: 기타 | O75: =O76+O78+O80+O82+O85+O86 -> 7736.3271 | P75: =P76+P78+P80+P82+P85+P86 -> 2520.8052 | Q75: =Q76+Q78+Q80+Q82+Q85+Q86 -> 2535.6312 | R75: =R76+R78+R80+R82+R85+R86 -> 2525.9375 | S75: =S76+S78+S80+S82+S85+S86 -> 2169.2643 | T75: =T76+T78+T80+T82+T85+T86 -> 2376.859 | U75: =U76+U78+U80+U82+U85+U86 -> 2293.4525 | V75: =V76+V78+V80+V82+V85+V86 -> 2323.7539 | ... Y75: =Y76+Y78+Y80+Y82+Y85+Y86 -> 21002.311 | Z75: =Y75+O75 -> 28738.639 | AA75: =AA76+AA78+AA80+AA82+AA85+AA86 -> 25383.242 | AB75: =AB76+AB78+AB80+AB82+AB85+AB86 -> 29151.251 | AC75: =AC76+AC78+AC80+AC82+AC85+AC86 -> 32478.155 | AD75: =AD76+AD78+AD80+AD82+AD85+AD86 -> 36390.033 | AG75: =IF($E75="판매수량",$D74,) -> 0
A76: 국내 | E76: 옵션 | O76: =O114+O152 -> 3645.8334 | P76: =SUM(P$50,P$55,P$60,P$65,P$70)*P77 -> 1390.2816 | Q76: =SUM(Q$50,Q$55,Q$60,Q$65,Q$70)*Q77 -> 1398.4585 | R76: =SUM(R$50,R$55,R$60,R$65,R$70)*R77 -> 1393.1122 | S76: =SUM(S$50,S$55,S$60,S$65,S$70)*S77 -> 1196.3988 | T76: =SUM(T$50,T$55,T$60,T$65,T$70)*T77 -> 1310.892 | U76: =SUM(U$50,U$55,U$60,U$65,U$70)*U77 -> 1264.8914 | V76: =SUM(V$50,V$55,V$60,V$65,V$70)*V77 -> 1281.6033 | W76: =SUM(W$50,W$55,W$60,W$65,W$70)*W77 -> 1240.9873 | X76: =SUM(X$50,X$55,X$60,X$65,X$70)*X77 -> 1106.6289 | Y76: =SUM(P76:X76) -> 11583.254 | Z76: =Y76+O76 -> 15229.087 | AA76: =AA114+AA152 -> 13999.437 | AB76: =AB114+AB152 -> 16077.58 | AC76: =AC114+AC152 -> 17912.443 | AD76: =AD114+AD152 -> 20069.933 | AG76: =IF($E76="판매수량",$D75,) -> 0
A77: 국내 | F77: % 본기매출 | I77: 0.10241497 | O77: =O76/SUM(O$50,O$55,O$60,O$65,O$70) -> 0.14953402 | P77: =$I77 -> 0.10241497 | Q77: =$I77 -> 0.10241497 | R77: =$I77 -> 0.10241497 | S77: =$I77 -> 0.10241497 | T77: =$I77 -> 0.10241497 | U77: =$I77 -> 0.10241497 | V77: =$I77 -> 0.10241497 | W77: =$I77 -> 0.10241497 | X77: =$I77 -> 0.10241497 | Y77: =IFERROR(Y76/SUM(Y$21,Y$27,Y$33,Y$39,Y$45),) -> 0.096201479 | Z77: =IFERROR(Z76/SUM(Z$21,Z$27,Z$33,Z$39,Z$45),) -> 0.090954413 | AA77: =AA76/SUM(AA$50,AA$55,AA$60,AA$65,AA$70) -> 0.10241497 | AB77: =AB76/SUM(AB$50,AB$55,AB$60,AB$65,AB$70) -> 0.10241497 | AC77: =AC76/SUM(AC$50,AC$55,AC$60,AC$65,AC$70) -> 0.10241497 | AD77: =AD76/SUM(AD$50,AD$55,AD$60,AD$65,AD$70) -> 0.10241497 | AG77: =IF($E77="판매수량",$D76,) -> 0
A78: 국내 | E78: A/S | O78: =O116+O154 -> 2355.9423 | P78: =SUM(P$50,P$55,P$60,P$65,P$70)*P79 -> 622.23554 | Q78: =SUM(Q$50,Q$55,Q$60,Q$65,Q$70)*Q79 -> 625.8952 | R78: =SUM(R$50,R$55,R$60,R$65,R$70)*R79 -> 623.5024 | S78: =SUM(S$50,S$55,S$60,S$65,S$70)*S79 -> 535.46119 | T78: =SUM(T$50,T$55,T$60,T$65,T$70)*T79 -> 586.70387 | U78: =SUM(U$50,U$55,U$60,U$65,U$70)*U79 -> 566.11581 | V78: =SUM(V$50,V$55,V$60,V$65,V$70)*V79 -> 573.59541 | W78: =SUM(W$50,W$55,W$60,W$65,W$70)*W79 -> 555.41729 | X78: =SUM(X$50,X$55,X$60,X$65,X$70)*X79 -> 495.28371 | Y78: =SUM(P78:X78) -> 5184.2104 | Z78: =Y78+O78 -> 7540.1527 | AA78: =AA116+AA154 -> 6265.5993 | AB78: =AB116+AB154 -> 7195.6946 | AC78: =AC116+AC154 -> 8016.9075 | AD78: =AD116+AD154 -> 8982.5154 | AG78: =IF($E78="판매수량",$D77,) -> 0
A79: 국내 | F79: % 본기매출 | I79: 0.045836928 | O79: =O78/SUM(O$50,O$55,O$60,O$65,O$70) -> 0.096629075 | P79: =$I79 -> 0.045836928 | Q79: =$I79 -> 0.045836928 | R79: =$I79 -> 0.045836928 | S79: =$I79 -> 0.045836928 | T79: =$I79 -> 0.045836928 | U79: =$I79 -> 0.045836928 | V79: =$I79 -> 0.045836928 | W79: =$I79 -> 0.045836928 | X79: =$I79 -> 0.045836928 | Y79: =IFERROR(Y78/SUM(Y$21,Y$27,Y$33,Y$39,Y$45),) -> 0.043056011 | Z79: =IFERROR(Z78/SUM(Z$21,Z$27,Z$33,Z$39,Z$45),) -> 0.045032913 | AA79: =AA78/SUM(AA$50,AA$55,AA$60,AA$65,AA$70) -> 0.045836928 | AB79: =AB78/SUM(AB$50,AB$55,AB$60,AB$65,AB$70) -> 0.045836928 | AC79: =AC78/SUM(AC$50,AC$55,AC$60,AC$65,AC$70) -> 0.045836928 | AD79: =AD78/SUM(AD$50,AD$55,AD$60,AD$65,AD$70) -> 0.045836928 | AG79: =IF($E79="판매수량",$D78,) -> 0
A80: 국내 | E80: 판매촉진비 | O80: =O118+O156 -> 1734.5514 | P80: =SUM(P$50,P$55,P$60,P$65,P$70)*P81 -> 508.28808 | Q80: =SUM(Q$50,Q$55,Q$60,Q$65,Q$70)*Q81 -> 511.27756 | R80: =SUM(R$50,R$55,R$60,R$65,R$70)*R81 -> 509.32295 | S80: =SUM(S$50,S$55,S$60,S$65,S$70)*S81 -> 437.40436 | T80: =SUM(T$50,T$55,T$60,T$65,T$70)*T81 -> 479.26318 | U80: =SUM(U$50,U$55,U$60,U$65,U$70)*U81 -> 462.44533 | V80: =SUM(V$50,V$55,V$60,V$65,V$70)*V81 -> 468.55522 | W80: =SUM(W$50,W$55,W$60,W$65,W$70)*W81 -> 453.70599 | X80: =SUM(X$50,X$55,X$60,X$65,X$70)*X81 -> 404.58442 | Y80: =SUM(P80:X80) -> 4234.8471 | Z80: =Y80+O80 -> 5969.3985 | AA80: =AA118+AA156 -> 5118.2056 | AB80: =AB118+AB156 -> 5877.9764 | AC80: =AC118+AC156 -> 6548.8039 | AD80: =AD118+AD156 -> 7337.584 | AG80: =IF($E80="판매수량",$D79,) -> 0
A81: 국내 | F81: % 본기매출 | I81: 0.037442998 | O81: =O80/SUM(O$50,O$55,O$60,O$65,O$70) -> 0.0711427 | P81: =$I81 -> 0.037442998 | Q81: =$I81 -> 0.037442998 | R81: =$I81 -> 0.037442998 | S81: =$I81 -> 0.037442998 | T81: =$I81 -> 0.037442998 | U81: =$I81 -> 0.037442998 | V81: =$I81 -> 0.037442998 | W81: =$I81 -> 0.037442998 | X81: =$I81 -> 0.037442998 | Y81: =IFERROR(Y80/SUM(Y$21,Y$27,Y$33,Y$39,Y$45),) -> 0.03517134 | Z81: =IFERROR(Z80/SUM(Z$21,Z$27,Z$33,Z$39,Z$45),) -> 0.035651719 | AA81: =AA80/SUM(AA$50,AA$55,AA$60,AA$65,AA$70) -> 0.037442998 | AB81: =AB80/SUM(AB$50,AB$55,AB$60,AB$65,AB$70) -> 0.037442998 | AC81: =AC80/SUM(AC$50,AC$55,AC$60,AC$65,AC$70) -> 0.037442998 | AD81: =AD80/SUM(AD$50,AD$55,AD$60,AD$65,AD$70) -> 0.037442998 | AG81: =IF($E81="판매수량",$D80,) -> 0
A82: 국내 | E82: 운송비 | P82: 0 | Q82: 0 | R82: 0 | S82: 0 | T82: 0 | U82: 0 | V82: 0 | W82: 0 | X82: 0 | Y82: =SUM(P82:X82) -> 0 | Z82: =Y82+O82 -> 0 | AG82: =IF($E82="판매수량",$D81,) -> 0
A83: 국내 | F83: 판매대수 | P83: 0 | Q83: 0 | R83: 0 | S83: 0 | T83: 0 | U83: 0 | V83: 0 | W83: 0 | X83: 0 | Y83: =SUM(P83:X83) -> 0 | Z83: =SUM(O83:X83) -> 0 | AG83: =IF($E83="판매수량",$D82,) -> 0
A84: 국내 | F84: 대당운송비 | I84: 0 | P84: 0 | Q84: 0 | R84: 0 | S84: 0 | T84: 0 | U84: 0 | V84: 0 | W84: 0 | X84: 0 | Y84: 0 | Z84: 0 | AG84: =IF($E84="판매수량",$D83,) -> 0
A85: 국내 | E85: 환차 | P85: 0 | Q85: 0 | R85: 0 | S85: 0 | T85: 0 | U85: 0 | V85: 0 | W85: 0 | X85: 0 | Y85: =SUM(P85:X85) -> 0 | Z85: =SUM(O85:X85) -> 0 | AG85: =IF($E85="판매수량",$D84,) -> 0
A86: 국내 | E86: 기타 | P86: 0 | Q86: 0 | R86: 0 | S86: 0 | T86: 0 | U86: 0 | V86: 0 | W86: 0 | X86: 0 | Y86: =SUM(P86:X86) -> 0 | Z86: =SUM(O86:X86) -> 0 | AG86: =IF($E86="판매수량",$D85,) -> 0
C87: Captive | I87: 0.51283073 | O87: =SUM(O88,O93,O98,O103,O108,O113) -> 2474.7736 | P87: =SUM(P88,P93,P98,P103,P108,P113) -> 8168.4689 | Q87: =SUM(Q88,Q93,Q98,Q103,Q108,Q113) -> 8227.6115 | R87: =SUM(R88,R93,R98,R103,R108,R113) -> 8150.1619 | S87: =SUM(S88,S93,S98,S103,S108,S113) -> 7159.766 | T87: =SUM(T88,T93,T98,T103,T108,T113) -> 7813.6521 | U87: =SUM(U88,U93,U98,U103,U108,U113) -> 7407.2577 | V87: =SUM(V88,V93,V98,V103,V108,V113) -> 7550.3174 | ... AD87: =SUM(AD88,AD93,AD98,AD103,AD108,AD113) -> 102379.18 | AG87: =IF($E87="판매수량",$D86,) -> 0
D88: 5축 | I88: 0.26373733 | O88: 0 | P88: =P50*$I88 -> 238.73789 | Q88: =Q50*$I88 -> 238.73789 | R88: =R50*$I88 -> 318.31719 | S88: =S50*$I88 -> 159.15859 | T88: =T50*$I88 -> 159.15859 | U88: =U50*$I88 -> 238.73789 | V88: =V50*$I88 -> 238.73789 | W88: =W50*$I88 -> 238.73789 | X88: =X50*$I88 -> 79.579297 | Y88: =SUM(P88:X88) -> 1909.9031 | Z88: =Y88+O88 -> 1909.9031 | AA88: =AA89*AA92 -> 2401.3468 | AB88: =AB89*AB92 -> 3139.3732 | AC88: =AC89*AC92 -> 3401.4385 | AD88: =AD89*AD92 -> 4150.8203 | AG88: =IF($E88="판매수량",$D87,) -> 0
E89: 판매수량 | I89: 0.28571429 | O89: 0 | P89: =ROUND(P51*$I89,) -> 1 | Q89: =ROUND(Q51*$I89,) -> 1 | R89: =ROUND(R51*$I89,) -> 1 | S89: =ROUND(S51*$I89,) -> 1 | T89: =ROUND(T51*$I89,) -> 1 | U89: =ROUND(U51*$I89,) -> 1 | V89: =ROUND(V51*$I89,) -> 1 | W89: =ROUND(W51*$I89,) -> 1 | X89: =ROUND(X51*$I89,) -> 0 | Y89: =SUM(P89:X89) -> 8 | Z89: =Y89+O89 -> 8 | AA89: =ROUND(AA90*AA91,) -> 10 | AB89: =ROUND(AB90*AB91,) -> 13 | AC89: =ROUND(AC90*AC91,) -> 14 | AD89: =ROUND(AD90*AD91,) -> 17 | AG89: =IF($E89="판매수량",$D88,) -> 5축
F90: 기종 수 | Z90: =Z52 -> 5 | AA90: ='Key Assumption'!AB54 -> 6 | AB90: ='Key Assumption'!AC54 -> 7 | AC90: ='Key Assumption'!AD54 -> 7 | AD90: ='Key Assumption'!AE54 -> 8 | AG90: =IF($E90="판매수량",$D89,) -> 0
F91: 기종당 판매량 | Z91: =Z89/Z90 -> 1.6 | AA91: ='Key Assumption'!AB160 -> 1.7093069 | AB91: ='Key Assumption'!AC160 -> 1.8534653 | AC91: ='Key Assumption'!AD160 -> 2.0055446 | AD91: ='Key Assumption'!AE160 -> 2.1560396 | AG91: =IF($E91="판매수량",$D90,) -> 0
E92: 판매단가 | O92: 0 | P92: =P88/P89 -> 238.73789 | Q92: =Q88/Q89 -> 238.73789 | R92: =R88/R89 -> 318.31719 | S92: =S88/S89 -> 159.15859 | T92: =T88/T89 -> 159.15859 | U92: =U88/U89 -> 238.73789 | V92: =V88/V89 -> 238.73789 | W92: =W88/W89 -> 238.73789 | X92: =IFERROR(X88/X89,) -> 0 | Y92: =Y88/Y89 -> 238.73789 | Z92: =Z88/Z89 -> 238.73789 | AA92: ='Key Assumption'!AB297 -> 240.13468 | AB92: ='Key Assumption'!AC297 -> 241.49025 | AC92: ='Key Assumption'!AD297 -> 242.9599 | AD92: ='Key Assumption'!AE297 -> 244.1659 | AG92: =IF($E92="판매수량",$D91,) -> 0
D93: 선반 | I93: 0.52772708 | O93: 641.644 | P93: =P55*$I93 -> 2600.6302 | Q93: =Q55*$I93 -> 2661.11 | R93: =R55*$I93 -> 2600.6302 | S93: =S55*$I93 -> 2509.9106 | T93: =T55*$I93 -> 2509.9106 | U93: =U55*$I93 -> 2358.7111 | V93: =V55*$I93 -> 2509.9106 | W93: =W55*$I93 -> 2419.1909 | X93: =X55*$I93 -> 2267.9915 | Y93: =SUM(P93:X93) -> 22437.996 | Z93: =Y93+O93 -> 23079.64 | AA93: =AA94*AA97 -> 24470.901 | AB93: =AB94*AB97 -> 27312.228 | AC93: =AC94*AC97 -> 29957.899 | AD93: =AD94*AD97 -> 32136.794 | AG93: =IF($E93="판매수량",$D92,) -> 0
E94: 판매수량 | I94: 0.48565966 | O94: 10 | P94: =ROUND(P56*$I94,) -> 42 | Q94: =ROUND(Q56*$I94,) -> 43 | R94: =ROUND(R56*$I94,) -> 42 | S94: =ROUND(S56*$I94,) -> 40 | T94: =ROUND(T56*$I94,) -> 40 | U94: =ROUND(U56*$I94,) -> 38 | V94: =ROUND(V56*$I94,) -> 40 | W94: =ROUND(W56*$I94,) -> 39 | X94: =ROUND(X56*$I94,) -> 36 | Y94: =SUM(P94:X94) -> 360 | Z94: =Y94+O94 -> 370 | AA94: =ROUND(AA95*AA96,) -> 390 | AB94: =ROUND(AB95*AB96,) -> 433 | AC94: =ROUND(AC95*AC96,) -> 472 | AD94: =ROUND(AD95*AD96,) -> 503 | AG94: =IF($E94="판매수량",$D93,) -> 선반
F95: 기종 수 | Z95: =Z57 -> 53 | AA95: ='Key Assumption'!AB55 -> 53 | AB95: ='Key Assumption'!AC55 -> 55 | AC95: ='Key Assumption'!AD55 -> 56 | AD95: ='Key Assumption'!AE55 -> 56 | AG95: =IF($E95="판매수량",$D94,) -> 0
F96: 기종당 판매량 | Z96: =Z94/Z95 -> 6.9811321 | AA96: ='Key Assumption'!AB161 -> 7.3644804 | AB96: ='Key Assumption'!AC161 -> 7.8796047 | AC96: ='Key Assumption'!AD161 -> 8.4216831 | AD96: ='Key Assumption'!AE161 -> 8.9757412 | AG96: =IF($E96="판매수량",$D95,) -> 0
E97: 판매단가 | O97: =O93/O94 -> 64.1644 | P97: =P93/P94 -> 61.919767 | Q97: =Q93/Q94 -> 61.886279 | R97: =R93/R94 -> 61.919767 | S97: =S93/S94 -> 62.747764 | T97: =T93/T94 -> 62.747764 | U97: =U93/U94 -> 62.071345 | V97: =V93/V94 -> 62.747764 | ... Z97: =Z93/Z94 -> 62.377404 | AA97: ='Key Assumption'!AB298 -> 62.745901 | AB97: ='Key Assumption'!AC298 -> 63.076739 | AC97: ='Key Assumption'!AD298 -> 63.470126 | AD97: ='Key Assumption'!AE298 -> 63.890247 | AG97: =IF($E97="판매수량",$D96,) -> 0
D98: VMC | I98: 0.53268827 | O98: 923.456 | P98: =P60*$I98 -> 2553.239 | Q98: =Q60*$I98 -> 2596.5142 | R98: =R60*$I98 -> 2639.7895 | S98: =S60*$I98 -> 2553.239 | T98: =T60*$I98 -> 2639.7895 | U98: =U60*$I98 -> 2207.0371 | V98: =V60*$I98 -> 2250.3123 | W98: =W60*$I98 -> 2207.0371 | X98: =X60*$I98 -> 2120.4866 | Y98: =SUM(P98:X98) -> 21767.444 | Z98: =Y98+O98 -> 22690.9 | AA98: =AA99*AA102 -> 24282.373 | AB98: =AB99*AB102 -> 29498.343 | AC98: =AC99*AC102 -> 34380.41 | AD98: =AD99*AD102 -> 39752.259 | AG98: =IF($E98="판매수량",$D97,) -> 0
E99: 판매수량 | I99: 0.50899281 | O99: 13 | P99: =ROUND(P61*$I99,) -> 30 | Q99: =ROUND(Q61*$I99,) -> 31 | R99: =ROUND(R61*$I99,) -> 31 | S99: =ROUND(S61*$I99,) -> 30 | T99: =ROUND(T61*$I99,) -> 31 | U99: =ROUND(U61*$I99,) -> 26 | V99: =ROUND(V61*$I99,) -> 26 | W99: =ROUND(W61*$I99,) -> 26 | X99: =ROUND(X61*$I99,) -> 25 | Y99: =SUM(P99:X99) -> 256 | Z99: =Y99+O99 -> 269 | AA99: =ROUND(AA100*AA101,) -> 286 | AB99: =ROUND(AB100*AB101,) -> 345 | AC99: =ROUND(AC100*AC101,) -> 399 | AD99: =ROUND(AD100*AD101,) -> 458 | AG99: =IF($E99="판매수량",$D98,) -> VMC
F100: 기종 수 | Z100: =Z62 -> 24 | AA100: ='Key Assumption'!AB56 -> 24 | AB100: ='Key Assumption'!AC56 -> 27 | AC100: ='Key Assumption'!AD56 -> 29 | AD100: ='Key Assumption'!AE56 -> 31 | AG100: =IF($E100="판매수량",$D99,) -> 0
F101: 기종당 판매량 | Z101: =Z99/Z100 -> 11.208333 | AA101: ='Key Assumption'!AB162 -> 11.900481 | AB101: ='Key Assumption'!AC162 -> 12.793576 | AC101: ='Key Assumption'!AD162 -> 13.753652 | AD101: ='Key Assumption'!AE162 -> 14.776245 | AG101: =IF($E101="판매수량",$D100,) -> 0
E102: 판매단가 | O102: =O98/O99 -> 71.035077 | P102: =P98/P99 -> 85.107966 | Q102: =Q98/Q99 -> 83.758524 | R102: =R98/R99 -> 85.154499 | S102: =S98/S99 -> 85.107966 | T102: =T98/T99 -> 85.154499 | U102: =U98/U99 -> 84.886042 | V102: =V98/V99 -> 86.550474 | ... Z102: =Z98/Z99 -> 84.352789 | AA102: ='Key Assumption'!AB299 -> 84.903401 | AB102: ='Key Assumption'!AC299 -> 85.502443 | AC102: ='Key Assumption'!AD299 -> 86.16644 | AD102: ='Key Assumption'!AE299 -> 86.795324 | AG102: =IF($E102="판매수량",$D101,) -> 0
D103: HMC | I103: 0.54609887 | O103: 0 | P103: =P65*$I103 -> 850.07721 | Q103: =Q65*$I103 -> 850.07721 | R103: =R65*$I103 -> 991.75674 | S103: =S65*$I103 -> 708.39767 | T103: =T65*$I103 -> 850.07721 | U103: =U65*$I103 -> 850.07721 | V103: =V65*$I103 -> 991.75674 | W103: =W65*$I103 -> 850.07721 | X103: =X65*$I103 -> 708.39767 | Y103: =SUM(P103:X103) -> 7650.6949 | Z103: =Y103+O103 -> 7650.6949 | AA103: =AA104*AA107 -> 8237.3594 | AB103: =AB104*AB107 -> 8820.1543 | AC103: =AC104*AC107 -> 9423.8049 | AD103: =AD104*AD107 -> 10305.428 | AG103: =IF($E103="판매수량",$D102,) -> 0
E104: 판매수량 | I104: 0.5 | O104: 0 | P104: =ROUND(P66*$I104,) -> 3 | Q104: =ROUND(Q66*$I104,) -> 3 | R104: =ROUND(R66*$I104,) -> 4 | S104: =ROUND(S66*$I104,) -> 3 | T104: =ROUND(T66*$I104,) -> 3 | U104: =ROUND(U66*$I104,) -> 3 | V104: =ROUND(V66*$I104,) -> 4 | W104: =ROUND(W66*$I104,) -> 3 | X104: =ROUND(X66*$I104,) -> 3 | Y104: =SUM(P104:X104) -> 29 | Z104: =Y104+O104 -> 29 | AA104: =ROUND(AA105*AA106,) -> 31 | AB104: =ROUND(AB105*AB106,) -> 33 | AC104: =ROUND(AC105*AC106,) -> 35 | AD104: =ROUND(AD105*AD106,) -> 38 | AG104: =IF($E104="판매수량",$D103,) -> HMC
F105: 기종 수 | Z105: =Z67 -> 12 | AA105: ='Key Assumption'!AB57 -> 12 | AB105: ='Key Assumption'!AC57 -> 12 | AC105: ='Key Assumption'!AD57 -> 12 | AD105: ='Key Assumption'!AE57 -> 12 | AG105: =IF($E105="판매수량",$D104,) -> 0
...

Sheet COGS_HW
A1: =MID(CELL("filename",A1),FIND("]",CELL("filename",A1))+1,255) -> COGS_HW
B3: 1. Summary
L5: 2021A | M5: 2022A | N5: 2023A | O5: 24.3m(A) | P5: 4월 | Q5: 5월 | R5: 6월 | S5: 7월 | T5: 8월 | U5: 9월 | V5: 10월 | W5: 11월 | X5: 12월 | Y5: 24.9m(E) | Z5: 2024F | AA5: 2025F | AB5: 2026F | AC5: 2027F | AD5: 2028F
B6: COGS | O6: =O8+O9+O10+O11+O12 -> 60294.782 | P6: =P8+P9+P10+P11+P12 -> 24038.464 | Q6: =Q8+Q9+Q10+Q11+Q12 -> 22896.864 | R6: =R8+R9+R10+R11+R12 -> 23421.162 | S6: =S8+S9+S10+S11+S12 -> 21593.167 | T6: =T8+T9+T10+T11+T12 -> 22839.145 | U6: =U8+U9+U10+U11+U12 -> 22032.922 | V6: =V8+V9+V10+V11+V12 -> 22056.431 | ... Y6: =Y8+Y9+Y10+Y11+Y12 -> 201130.51 | Z6: =O6+Y6 -> 261425.29 | AA6: =AA8+AA9+AA10+AA11+AA12 -> 238001.56 | AB6: =AB8+AB9+AB10+AB11+AB12 -> 269199.45 | AC6: =AC8+AC9+AC10+AC11+AC12 -> 298232.32 | AD6: =AD8+AD9+AD10+AD11+AD12 -> 331122.8
C7: % COGS | O7: =O6/Revenue_HW!O$6 -> 0.79416653 | P7: =P6/Revenue_HW!P$6 -> 0.77081488 | Q7: =Q6/Revenue_HW!Q$6 -> 0.80655095 | R7: =R6/Revenue_HW!R$6 -> 0.77459948 | S7: =S6/Revenue_HW!S$6 -> 0.7851396 | T7: =T6/Revenue_HW!T$6 -> 0.77474387 | U7: =U6/Revenue_HW!U$6 -> 0.78604342 | V7: =V6/Revenue_HW!V$6 -> 0.78868792 | ... AD7: =AD6/Revenue_HW!AD$6 -> 0.76764804
C8: 원재료비 | O8: =O32 -> 47973.788 | P8: =P32 -> 20140.172 | Q8: =Q32 -> 19108.709 | R8: =R32 -> 19633.007 | S8: =S32 -> 17923.314 | T8: =T32 -> 19427.089 | U8: =U32 -> 18552.651 | V8: =V32 -> 18560.157 | ... X8: =X32 -> 17186.067 | Y8: =SUM(P8:X8) -> 169035.66 | Z8: =Z32 -> 217009.45 | AA8: =AA32 -> 209141.79 | AB8: =AB32 -> 239286.03 | AC8: =AC32 -> 267408.86 | AD8: =AD32 -> 299329.34
C9: 노무비 | O9: =O138 -> 9180.6027 | P9: =P138 -> 2801.3941 | Q9: =Q138 -> 2603.4191 | R9: =R138 -> 2603.4191 | S9: =S138 -> 2543.6761 | T9: =T138 -> 2285.8781 | U9: =U138 -> 2266.2561 | V9: =V138 -> 2252.9801 | ... X9: =X138 -> 2149.4421 | Y9: =SUM(P9:X9) -> 21695.736 | Z9: =Z138 -> 30876.338 | AA9: =AA138 -> 22688.296 | AB9: =AB138 -> 23618.517 | AC9: =AC138 -> 24421.546 | AD9: =AD138 -> 25276.3
C10: 변동경비 | O10: =O150 -> 778.53829 | P10: =P150 -> 132.63645 | Q10: =Q150 -> 220.4739 | R10: =R150 -> 220.4739 | S10: =S150 -> 161.9156 | T10: =T150 -> 161.9156 | U10: =U150 -> 249.75305 | V10: =V150 -> 279.03219 | ... X10: =X150 -> 161.9156 | Y10: =SUM(P10:X10) -> 1720.7527 | Z10: =Z150 -> 2499.291 | AA10: =AA150 -> 189.21811 | AB10: =AB150 -> 193.00247 | AC10: =AC150 -> 196.28352 | AD10: =AD150 -> 199.81662
C11: 고정경비 | O11: =O167 -> 2361.853 | P11: =P167 -> 964.26214 | Q11: =Q167 -> 964.26214 | R11: =R167 -> 964.26214 | S11: =S167 -> 964.26214 | T11: =T167 -> 964.26214 | U11: =U167 -> 964.26214 | V11: =V167 -> 964.26214 | ... X11: =X167 -> 964.26214 | Y11: =SUM(P11:X11) -> 8678.3592 | Z11: =Z167 -> 11040.212 | AA11: =AA167 -> 5982.2582 | AB11: =AB167 -> 6101.9034 | AC11: =AC167 -> 6205.6357 | AD11: =AD167 -> 6317.3372
C12: 재고차이 | O12: 0 | P12: 0 | Q12: 0 | R12: 0 | S12: 0 | T12: 0 | U12: 0 | V12: 0 | W12: 0 | X12: 0 | Y12: =SUM(P12:X12) -> 0 | Z12: =Y12+O12 -> 0
B14: 2. 원재료비
L16: 2021A | M16: 2022A | N16: 2023A | O16: 24.3m(A) | P16: 4월 | Q16: 5월 | R16: 6월 | S16: 7월 | T16: 8월 | U16: 9월 | V16: 10월 | W16: 11월 | X16: 12월 | Y16: 24.9m(E) | Z16: 2024F | AA16: 2025F | AB16: 2026F | AC16: 2027F | AD16: 2028F
B17: 원재료비_기종군별 | O17: =SUM(O19:O24) -> 47973.788 | P17: =SUM(P19:P24) -> 20140.172 | Q17: =SUM(Q19:Q24) -> 19108.709 | R17: =SUM(R19:R24) -> 19633.007 | S17: =SUM(S19:S24) -> 17923.314 | T17: =SUM(T19:T24) -> 19427.089 | U17: =SUM(U19:U24) -> 18552.651 | V17: =SUM(V19:V24) -> 18560.157 | ... AD17: =SUM(AD19:AD24) -> 299329.34
C18: % 원재료비 | O18: =O17/Revenue_HW!O6 -> 0.63188182 | P18: =P17/Revenue_HW!P6 -> 0.64581264 | Q18: =Q17/Revenue_HW!Q6 -> 0.67311171 | R18: =R17/Revenue_HW!R6 -> 0.64931522 | S18: =S17/Revenue_HW!S6 -> 0.65170167 | T18: =T17/Revenue_HW!T6 -> 0.65900095 | U18: =U17/Revenue_HW!U6 -> 0.66188175 | V18: =V17/Revenue_HW!V6 -> 0.66366909 | ... AD18: =AD17/Revenue_HW!AD6 -> 0.69394069
C19: 5축 | O19: =O34 -> 888.44947 | P19: =P34 -> 758.69594 | Q19: =Q34 -> 1574.1859 | R19: =R34 -> 1510.8505 | S19: =S34 -> 1096.4795 | T19: =T34 -> 687.11476 | U19: =U34 -> 1593.4323 | V19: =V34 -> 1094.6293 | ... AD19: =AD34 -> 20703.163
C20: 선반 | O20: =O53 -> 20987.111 | P20: =P53 -> 8558.3552 | Q20: =Q53 -> 7379.6596 | R20: =R53 -> 7635.8977 | S20: =S53 -> 7867.5948 | T20: =T53 -> 7712.3134 | U20: =U53 -> 7298.2294 | V20: =V53 -> 7978.0734 | ... AD20: =AD53 -> 123940.28
C21: VMC | O21: =O72 -> 12334.679 | P21: =P72 -> 4410.9624 | Q21: =Q72 -> 4639.9544 | R21: =R72 -> 4582.8242 | S21: =S72 -> 4739.6509 | T21: =T72 -> 4623.4601 | U21: =U72 -> 3872.998 | V21: =V72 -> 3991.5095 | ... AD21: =AD72 -> 88541.024
C22: HMC | O22: =O91 -> 1903.4061 | P22: =P91 -> 2103.6771 | Q22: =Q91 -> 1679.0003 | R22: =R91 -> 2335.7227 | S22: =S91 -> 1282.0226 | T22: =T91 -> 2544.338 | U22: =U91 -> 1883.6196 | V22: =V91 -> 1670.8879 | ... AD22: =AD91 -> 28573.832
C23: 단종 | O23: =O110 -> 3220.1244 | P23: =P110 -> 1397.2488 | Q23: =Q110 -> 1242.327 | R23: =R110 -> 865.86087 | S23: =S110 -> 484.66595 | T23: =T110 -> 1150.3066 | U23: =U110 -> 1398.3125 | V23: =V110 -> 1293.3053 | ... AD23: =AD110 -> 0
C24: 기타 | O24: =O129 -> 8640.0173 | P24: =P129 -> 2911.2321 | Q24: =Q129 -> 2593.5818 | R24: =R129 -> 2701.8511 | S24: =S129 -> 2452.8997 | T24: =T129 -> 2709.5564 | U24: =U129 -> 2506.0587 | V24: =V129 -> 2531.7516 | ... AD24: =AD129 -> 37571.039
B25: 원재료비_성격별 | O25: =O26+O29 -> 47973.788 | P25: =P26+P29 -> 20140.172 | Q25: =Q26+Q29 -> 19108.709 | R25: =R26+R29 -> 19633.007 | S25: =S26+S29 -> 17923.314 | T25: =T26+T29 -> 19427.089 | U25: =U26+U29 -> 18552.651 | V25: =V26+V29 -> 18560.157 | ... AD25: =AD26+AD29 -> 299329.34
C26: 재료비 | O26: =SUM(O27:O28) -> 30369.069 | P26: =SUM(P27:P28) -> 12747.454 | Q26: =SUM(Q27:Q28) -> 12154.693 | R26: =SUM(R27:R28) -> 12641.559 | S26: =SUM(S27:S28) -> 11059.286 | T26: =SUM(T27:T28) -> 12550.294 | U26: =SUM(U27:U28) -> 12080.619 | V26: =SUM(V27:V28) -> 11769.255 | ... AD26: =SUM(AD27:AD28) -> 177027.14
D27: NC재료비 | O27: =SUM(O36,O55,O74,O93,O112) -> 7810.7323 | P27: =SUM(P36,P55,P74,P93,P112) -> 3644.0423 | Q27: =SUM(Q36,Q55,Q74,Q93,Q112) -> 3410.5198 | R27: =SUM(R36,R55,R74,R93,R112) -> 3476.4936 | S27: =SUM(S36,S55,S74,S93,S112) -> 3331.7852 | T27: =SUM(T36,T55,T74,T93,T112) -> 3549.6451 | U27: =SUM(U36,U55,U74,U93,U112) -> 3616.9129 | V27: =SUM(V36,V55,V74,V93,V112) -> 3436.4264 | ... AD27: =SUM(AD36,AD55,AD74,AD93,AD112) -> 65197.825
D28: 기타재료비 | O28: =SUM(O47,O66,O85,O104,O123,O129) -> 22558.336 | P28: =SUM(P47,P66,P85,P104,P123,P129) -> 9103.412 | Q28: =SUM(Q47,Q66,Q85,Q104,Q123,Q129) -> 8744.1736 | R28: =SUM(R47,R66,R85,R104,R123,R129) -> 9165.065 | S28: =SUM(S47,S66,S85,S104,S123,S129) -> 7727.5008 | T28: =SUM(T47,T66,T85,T104,T123,T129) -> 9000.6488 | U28: =SUM(U47,U66,U85,U104,U123,U129) -> 8463.7062 | V28: =SUM(V47,V66,V85,V104,V123,V129) -> 8332.829 | ... AD28: =SUM(AD47,AD66,AD85,AD104,AD123,AD129) -> 111829.31
C29: 도급비 | O29: =SUM(O50,O69,O88,O107,O126) -> 17604.719 | P29: =SUM(P50,P69,P88,P107,P126) -> 7392.7172 | Q29: =SUM(Q50,Q69,Q88,Q107,Q126) -> 6954.0155 | R29: =SUM(R50,R69,R88,R107,R126) -> 6991.4485 | S29: =SUM(S50,S69,S88,S107,S126) -> 6864.0276 | T29: =SUM(T50,T69,T88,T107,T126) -> 6876.7952 | U29: =SUM(U50,U69,U88,U107,U126) -> 6472.0315 | V29: =SUM(V50,V69,V88,V107,V126) -> 6790.9017 | ... AD29: =SUM(AD50,AD69,AD88,AD107,AD126) -> 122302.21
L31: 2021A | M31: 2022A | N31: 2023A | O31: 24.3m(A) | P31: 4월 | Q31: 5월 | R31: 6월 | S31: 7월 | T31: 8월 | U31: 9월 | V31: 10월 | W31: 11월 | X31: 12월 | Y31: 24.9m(E) | Z31: 2024F | AA31: 2025F | AB31: 2026F | AC31: 2027F | AD31: 2028F
B32: 원재료비 | O32: =O34+O53+O72+O91+O110+O129 -> 47973.788 | P32: =P34+P53+P72+P91+P110+P129 -> 20140.172 | Q32: =Q34+Q53+Q72+Q91+Q110+Q129 -> 19108.709 | R32: =R34+R53+R72+R91+R110+R129 -> 19633.007 | S32: =S34+S53+S72+S91+S110+S129 -> 17923.314 | T32: =T34+T53+T72+T91+T110+T129 -> 19427.089 | U32: =U34+U53+U72+U91+U110+U129 -> 18552.651 | V32: =V34+V53+V72+V91+V110+V129 -> 18560.157 | ... AD32: =AD34+AD53+AD72+AD91+AD110+AD129 -> 299329.34
B33: % 원재료비 | O33: =O32/Revenue_HW!O$6 -> 0.63188182 | P33: =P32/Revenue_HW!P$6 -> 0.64581264 | Q33: =Q32/Revenue_HW!Q$6 -> 0.67311171 | R33: =R32/Revenue_HW!R$6 -> 0.64931522 | S33: =S32/Revenue_HW!S$6 -> 0.65170167 | T33: =T32/Revenue_HW!T$6 -> 0.65900095 | U33: =U32/Revenue_HW!U$6 -> 0.66188175 | V33: =V32/Revenue_HW!V$6 -> 0.66366909 | ... AD33: =AD32/Revenue_HW!AD$6 -> 0.69394069
A34: 5축 | C34: 5축 | O34: =O35+O50 -> 888.44947 | P34: =P35+P50 -> 758.69594 | Q34: =Q35+Q50 -> 1574.1859 | R34: =R35+R50 -> 1510.8505 | S34: =S35+S50 -> 1096.4795 | T34: =T35+T50 -> 687.11476 | U34: =U35+U50 -> 1593.4323 | V34: =V35+V50 -> 1094.6293 | ... AD34: =AD35+AD50 -> 20703.163
A35: 5축 | D35: 재료비 | O35: 635.10759 | P35: =P36+P47 -> 568.68953 | Q35: =Q36+Q47 -> 1130.8376 | R35: =R36+R47 -> 1130.8376 | S35: =S36+S47 -> 779.80218 | T35: =T36+T47 -> 497.10834 | U35: =U36+U47 -> 1213.4195 | V35: =V36+V47 -> 777.95198 | W35: =W36+W47 -> 1343.9281 | ... AD35: =AD36+AD47 -> 12206.781
A36: 5축 | E36: NC재료비 | O36: =O37+O42 -> 145.93955 | P36: =P37+P42 -> 201.8135 | Q36: =Q37+Q42 -> 274.79357 | R36: =R37+R42 -> 274.79357 | S36: =S37+S42 -> 168.34213 | T36: =T37+T42 -> 130.23231 | U36: =U37+U42 -> 479.66741 | V36: =V37+V42 -> 166.49193 | ... AD36: =AD37+AD42 -> 5049.5916
A37: 5축 | F37: 화낙 | O37: =O38*O41/10^6 -> 53.18667 | P37: =P38*P41/10^6 -> 18.245017 | Q37: =Q38*Q41/10^6 -> 91.225086 | R37: =R38*R41/10^6 -> 91.225086 | S37: =S38*S41/10^6 -> 76.219625 | T37: =T38*T41/10^6 -> 38.109812 | U37: =U38*U41/10^6 -> 19.054906 | V37: =V38*V41/10^6 -> 76.505005 | ... X37: =X38*X41/10^6 -> 57.378754 | Y37: =SUM(P37:X37) -> 563.59455 | Z37: =Y37+O37 -> 616.78122 | AA37: =AA38*AA41/10^6 -> 814.03747 | AB37: =AB38*AB41/10^6 -> 1086.5563 | AC37: =AC38*AC41/10^6 -> 1216.9728 | AD37: =AD38*AD41/10^6 -> 1614.4781
G38: 매입금액(JPY) | O38: =O39*O40 -> 5947825.4 | P38: =P39*P40 -> 1982608.5 | Q38: =Q39*Q40 -> 9913042.4 | R38: =R39*R40 -> 9913042.4 | S38: =S39*S40 -> 7930433.9 | T38: =T39*T40 -> 3965216.9 | U38: =U39*U40 -> 1982608.5 | V38: =V39*V40 -> 7930433.9 | ... X38: =X39*X40 -> 5947825.4 | Y38: =SUM(P38:X38) -> 59478254 | Z38: =Y38+O38 -> 65426080 | AA38: =AA39*AA40 -> 78172269 | AB38: =AB39*AB40 -> 97462780 | AC38: =AC39*AC40 -> 1.0685169e+08 | AD38: =AD39*AD40 -> 1.3960174e+08
A39: 5축 | G39: 생산수량 | I39: =1-I44 -> 0.64705882 | O39: =Revenue_HW!O15-COGS_HW!O44 -> 3 | P39: =Revenue_HW!P15-P44 -> 1 | Q39: =Revenue_HW!Q15-Q44 -> 5 | R39: =Revenue_HW!R15-R44 -> 5 | S39: =Revenue_HW!S15-S44 -> 4 | T39: =Revenue_HW!T15-T44 -> 2 | U39: =Revenue_HW!U15-U44 -> 1 | V39: =Revenue_HW!V15-V44 -> 4 | W39: =Revenue_HW!W15-W44 -> 5 | X39: =Revenue_HW!X15-X44 -> 3 | Y39: =SUM(P39:X39) -> 30 | Z39: =Y39+O39 -> 33 | AA39: =ROUND($I39*Revenue_HW!AA$15,) -> 39 | AB39: =ROUND($I39*Revenue_HW!AB$15,) -> 48 | AC39: =ROUND($I39*Revenue_HW!AC$15,) -> 52 | AD39: =ROUND($I39*Revenue_HW!AD$15,) -> 67
A40: 5축 | G40: 매입단가(JPY) | O40: =P40 -> 1982608.5 | P40: ='Key Assumption'!R434 -> 1982608.5 | Q40: ='Key Assumption'!S434 -> 1982608.5 | R40: ='Key Assumption'!T434 -> 1982608.5 | S40: ='Key Assumption'!U434 -> 1982608.5 | T40: ='Key Assumption'!V434 -> 1982608.5 | U40: ='Key Assumption'!W434 -> 1982608.5 | V40: ='Key Assumption'!X434 -> 1982608.5 | W40: ='Key Assumption'!Y434 -> 1982608.5 | X40: ='Key Assumption'!Z434 -> 1982608.5 | Y40: =Y38/Y39 -> 1982608.5 | Z40: =Z38/Z39 -> 1982608.5 | AA40: ='Key Assumption'!AB434 -> 2004417.2 | AB40: ='Key Assumption'!AC434 -> 2030474.6 | AC40: ='Key Assumption'!AD434 -> 2054840.3 | AD40: ='Key Assumption'!AE434 -> 2083608
A41: 5축 | G41: 환율 | O41: =O$187 -> 8.9422043 | P41: =P$187 -> 9.2025316 | Q41: =Q$187 -> 9.2025316 | R41: =R$187 -> 9.2025316 | S41: =S$187 -> 9.6110283 | T41: =T$187 -> 9.6110283 | U41: =U$187 -> 9.6110283 | V41: =V$187 -> 9.6470138 | ... X41: =X$187 -> 9.6470138 | Y41: =Y37/Y38*10^6 -> 9.4756404 | Z41: =Z37/Z38*10^6 -> 9.4271462 | AA41: =AA$187 -> 10.413379 | AB41: =AB$187 -> 11.148423 | AC41: =AC$187 -> 11.389364 | AD41: =AD$187 -> 11.564885
A42: 5축 | F42: 지멘스 | O42: =O43*O46/10^6 -> 92.752878 | P42: =P43*P46/10^6 -> 183.56848 | Q42: =Q43*Q46/10^6 -> 183.56848 | R42: =R43*R46/10^6 -> 183.56848 | S42: =S43*S46/10^6 -> 92.122501 | T42: =T43*T46/10^6 -> 92.122501 | U42: =U43*U46/10^6 -> 460.61251 | V42: =V43*V46/10^6 -> 89.986928 | ... X42: =X43*X46/10^6 -> 0 | Y42: =SUM(P42:X42) -> 1555.5107 | Z42: =Y42+O42 -> 1648.2635 | AA42: =AA43*AA46/10^6 -> 1984.5434 | AB42: =AB43*AB46/10^6 -> 2383.0058 | AC42: =AC43*AC46/10^6 -> 2702.0578 | AD42: =AD43*AD46/10^6 -> 3435.1135
G43: 매입금액(EUR) | O43: =O44*O45 -> 64345.76 | P43: =P44*P45 -> 128691.52 | Q43: =Q44*Q45 -> 128691.52 | R43: =R44*R45 -> 128691.52 | S43: =S44*S45 -> 64345.76 | T43: =T44*T45 -> 64345.76 | U43: =U44*U45 -> 321728.8 | V43: =V44*V45 -> 64345.76 | ... X43: =X44*X45 -> 0 | Y43: =SUM(P43:X43) -> 1093877.9 | Z43: =Y43+O43 -> 1158223.7 | AA43: =AA44*AA45 -> 1436840.8 | AB43: =AB44*AB45 -> 1716763.5 | AC43: =AC44*AC45 -> 1934000.2 | AD43: =AD44*AD45 -> 2422435.2
A44: 5축 | G44: 생산수량 | I44: =COGS_HW!Z44/Revenue_HW!Z15 -> 0.35294118 | O44: 1 | P44: 2 | Q44: 2 | R44: 2 | S44: 1 | T44: 1 | U44: 5 | V44: 1 | W44: 3 | X44: 0 | Y44: =SUM(P44:X44) -> 17 | Z44: =Y44+O44 -> 18 | AA44: =Revenue_HW!AA15-COGS_HW!AA39 -> 22 | AB44: =Revenue_HW!AB15-COGS_HW!AB39 -> 26 | AC44: =Revenue_HW!AC15-COGS_HW!AC39 -> 29 | AD44: =Revenue_HW!AD15-COGS_HW!AD39 -> 36
A45: 5축 | G45: 매입단가(EUR) | O45: =P45 -> 64345.76 | P45: ='Key Assumption'!R440 -> 64345.76 | Q45: ='Key Assumption'!S440 -> 64345.76 | R45: ='Key Assumption'!T440 -> 64345.76 | S45: ='Key Assumption'!U440 -> 64345.76 | T45: ='Key Assumption'!V440 -> 64345.76 | U45: ='Key Assumption'!W440 -> 64345.76 | V45: ='Key Assumption'!X440 -> 64345.76 | W45: ='Key Assumption'!Y440 -> 64345.76 | X45: ='Key Assumption'!Z440 -> 64345.76 | Y45: =Y43/Y44 -> 64345.76 | Z45: =Z43/Z44 -> 64345.76 | AA45: ='Key Assumption'!AB440 -> 65310.946 | AB45: ='Key Assumption'!AC440 -> 66029.367 | AC45: ='Key Assumption'!AD440 -> 66689.66 | AD45: ='Key Assumption'!AE440 -> 67289.867
A46: 5축 | G46: 환율 | O46: =Revenue_HW!$O$482 -> 1441.4761 | P46: =P$188 -> 1426.4225 | Q46: =Q$188 -> 1426.4225 | R46: =R$188 -> 1426.4225 | S46: =S$188 -> 1431.6794 | T46: =T$188 -> 1431.6794 | U46: =U$188 -> 1431.6794 | V46: =V$188 -> 1398.4904 | W46: =W$188 -> 1398.4904 | X46: =X$188 -> 1398.4904 | Y46: =Y42/Y43*10^6 -> 1422.0149 | Z46: =Z42/Z43*10^6 -> 1423.096 | AA46: =AA$188 -> 1381.1853 | AB46: =AB$188 -> 1388.0804 | AC46: =AC$188 -> 1397.1342 | AD46: =AD$188 -> 1418.0414
A47: 5축 | E47: 기타재료비 | O47: =O35-O36 -> 489.16804 | P47: =P48*P49 -> 366.87603 | Q47: =Q48*Q49 -> 856.04407 | R47: =R48*R49 -> 856.04407 | S47: =S48*S49 -> 611.46005 | T47: =T48*T49 -> 366.87603 | U47: =U48*U49 -> 733.75206 | V47: =V48*V49 -> 611.46005 | W47: =W48*W49 -> 978.33608 | X47: =X48*X49 -> 366.87603 | Y47: =SUM(P47:X47) -> 5747.7245 | Z47: =Y47+O47 -> 6236.8925 | AA47: =AA48*AA49 -> 4140.94 | AB47: =AB48*AB49 -> 5027.2532 | AC47: =AC48*AC49 -> 5556.7317 | AD47: =AD48*AD49 -> 7157.1891
A48: 5축 | F48: 생산수량 | O48: =Revenue_HW!O15 -> 4 | P48: =Revenue_HW!P15 -> 3 | Q48: =Revenue_HW!Q15 -> 7 | R48: =Revenue_HW!R15 -> 7 | S48: =Revenue_HW!S15 -> 5 | T48: =Revenue_HW!T15 -> 3 | U48: =Revenue_HW!U15 -> 6 | V48: =Revenue_HW!V15 -> 5 | ... X48: =Revenue_HW!X15 -> 3 | Y48: =SUM(P48:X48) -> 47 | Z48: =Y48+O48 -> 51 | AA48: =Revenue_HW!AA15 -> 61 | AB48: =Revenue_HW!AB15 -> 74 | AC48: =Revenue_HW!AC15 -> 81 | AD48: =Revenue_HW!AD15 -> 103
A49: 5축 | F49: 매입단가 | O49: =O47/O48 -> 122.29201 | P49: ='Key Assumption'!R446 -> 122.29201 | Q49: ='Key Assumption'!S446 -> 122.29201 | R49: ='Key Assumption'!T446 -> 122.29201 | S49: ='Key Assumption'!U446 -> 122.29201 | T49: ='Key Assumption'!V446 -> 122.29201 | U49: ='Key Assumption'!W446 -> 122.29201 | V49: ='Key Assumption'!X446 -> 122.29201 | W49: ='Key Assumption'!Y446 -> 122.29201 | X49: ='Key Assumption'!Z446 -> 122.29201 | Y49: =Y47/Y48 -> 122.29201 | Z49: =Z47/Z48 -> 122.29201 | AA49: ='Key Assumption'!AB446 -> 67.884262 | AB49: ='Key Assumption'!AC446 -> 67.935854 | AC49: ='Key Assumption'!AD446 -> 68.601625 | AD49: ='Key Assumption'!AE446 -> 69.487272
A50: 5축 | D50: 도급비 | O50: 253.34188 | P50: =P51*P52 -> 190.00641 | Q50: =Q51*Q52 -> 443.3483 | R50: =R51*R52 -> 380.01282 | S50: =S51*S52 -> 316.67735 | T50: =T51*T52 -> 190.00641 | U50: =U51*U52 -> 380.01282 | V50: =V51*V52 -> 316.67735 | W50: =W51*W52 -> 506.68377 | X50: =X51*X52 -> 190.00641 | Y50: =SUM(P50:X50) -> 2913.4317 | Z50: =Y50+O50 -> 3166.7735 | AA50: =AA51*AA52 -> 4769.6332 | AB50: =AB51*AB52 -> 5878.6902 | AC50: =AC51*AC52 -> 6563.4782 | AD50: =AD51*AD52 -> 8496.382
A51: 5축 | E51: 생산수량 | O51: =O48 -> 4 | P51: 3 | Q51: 7 | R51: 6 | S51: 5 | T51: 3 | U51: 6 | V51: 5 | W51: 8 | X51: 3 | Y51: =SUM(P51:X51) -> 46 | Z51: =Y51+O51 -> 50 | AA51: =AA48 -> 61 | AB51: =AB48 -> 74 | AC51: =AC48 -> 81 | AD51: =AD48 -> 103
A52: 5축 | E52: 단가 | O52: =O50/O51 -> 63.335471 | P52: ='Key Assumption'!R452 -> 63.335471 | Q52: ='Key Assumption'!S452 -> 63.335471 | R52: ='Key Assumption'!T452 -> 63.335471 | S52: ='Key Assumption'!U452 -> 63.335471 | T52: ='Key Assumption'!V452 -> 63.335471 | U52: ='Key Assumption'!W452 -> 63.335471 | V52: ='Key Assumption'!X452 -> 63.335471 | W52: ='Key Assumption'!Y452 -> 63.335471 | X52: ='Key Assumption'!Z452 -> 63.335471 | Y52: =Y50/Y51 -> 63.335471 | Z52: =Z50/Z51 -> 63.335471 | AA52: ='Key Assumption'!AB452 -> 78.190708 | AB52: ='Key Assumption'!AC452 -> 79.44176 | AC52: ='Key Assumption'!AD452 -> 81.030595 | AD52: ='Key Assumption'!AE452 -> 82.489146
C53: 선반 | O53: =O54+O69 -> 20987.111 | P53: =P54+P69 -> 8558.3552 | Q53: =Q54+Q69 -> 7379.6596 | R53: =R54+R69 -> 7635.8977 | S53: =S54+S69 -> 7867.5948 | T53: =T54+T69 -> 7712.3134 | U53: =U54+U69 -> 7298.2294 | V53: =V54+V69 -> 7978.0734 | ... AD53: =AD54+AD69 -> 123940.28
A54: 선반 | D54: 재료비 | O54: 9435.4813 | P54: =P55+P66 -> 3680.1246 | Q54: =Q55+Q66 -> 3173.2811 | R54: =R55+R66 -> 3283.4644 | S54: =S55+S66 -> 3427.5287 | T54: =T55+T66 -> 3359.8801 | U54: =U55+U66 -> 3179.4838 | V54: =V55+V66 -> 3479.5852 | W54: =W55+W66 -> 3231.0434 | ... AD54: =AD55+AD66 -> 56729.277
A55: 선반 | E55: NC재료비 | O55: =O56+O61 -> 4344.7316 | P55: =P56+P61 -> 1929.4396 | Q55: =Q56+Q61 -> 1663.7084 | R55: =R56+R61 -> 1721.4761 | S55: =S56+S61 -> 1834.0909 | T55: =T56+T61 -> 1797.8917 | U55: =U56+U61 -> 1701.3606 | V55: =V56+V61 -> 1865.1812 | ... AD55: =AD56+AD61 -> 33325.789
A56: 선반 | F56: 화낙 | O56: =O57*O60/10^6 -> 4344.7316 | P56: =P57*P60/10^6 -> 1929.4396 | Q56: =Q57*Q60/10^6 -> 1663.7084 | R56: =R57*R60/10^6 -> 1721.4761 | S56: =S57*S60/10^6 -> 1834.0909 | T56: =T57*T60/10^6 -> 1797.8917 | U56: =U57*U60/10^6 -> 1701.3606 | V56: =V57*V60/10^6 -> 1865.1812 | ... X56: =X57*X60/10^6 -> 1695.6192 | Y56: =SUM(P56:X56) -> 15940.722 | Z56: =Y56+O56 -> 20285.453 | AA56: =AA57*AA60/10^6 -> 23381.807 | AB56: =AB57*AB60/10^6 -> 27694.183 | AC56: =AC57*AC60/10^6 -> 30662.564 | AD56: =AD57*AD60/10^6 -> 33325.789
G57: 매입금액(JPY) | O57: =O58*O59 -> 4.8586808e+08 | P57: =P58*P59 -> 2.09664e+08 | Q57: =Q58*Q59 -> 1.8078812e+08 | R57: =R58*R59 -> 1.8706549e+08 | S57: =S58*S59 -> 1.9083191e+08 | T57: =T58*T59 -> 1.8706549e+08 | U57: =U58*U59 -> 1.770217e+08 | V57: =V58*V59 -> 1.9334285e+08 | ... X57: =X58*X59 -> 1.7576623e+08 | Y57: =SUM(P57:X57) -> 1.6810784e+09 | Z57: =Y57+O57 -> 2.1669465e+09 | AA57: =AA58*AA59 -> 2.2453621e+09 | AB57: =AB58*AB59 -> 2.4841346e+09 | AC57: =AC58*AC59 -> 2.6922104e+09 | AD57: =AD58*AD59 -> 2.8816359e+09
A58: 선반 | G58: 생산수량 | O58: =Revenue_HW!O16 -> 387 | P58: =Revenue_HW!P16 -> 167 | Q58: =Revenue_HW!Q16 -> 144 | R58: =Revenue_HW!R16 -> 149 | S58: =Revenue_HW!S16 -> 152 | T58: =Revenue_HW!T16 -> 149 | U58: =Revenue_HW!U16 -> 141 | V58: =Revenue_HW!V16 -> 154 | ... X58: =Revenue_HW!X16 -> 140 | Y58: =SUM(P58:X58) -> 1339 | Z58: =Y58+O58 -> 1726 | AA58: =Revenue_HW!AA16 -> 1769 | AB58: =Revenue_HW!AB16 -> 1932 | AC58: =Revenue_HW!AC16 -> 2069 | AD58: =Revenue_HW!AD16 -> 2184
A59: 선반 | G59: 매입단가(JPY) | O59: =P59 -> 1255473.1 | P59: ='Key Assumption'!R435 -> 1255473.1 | Q59: ='Key Assumption'!S435 -> 1255473.1 | R59: ='Key Assumption'!T435 -> 1255473.1 | S59: ='Key Assumption'!U435 -> 1255473.1 | T59: ='Key Assumption'!V435 -> 1255473.1 | U59: ='Key Assumption'!W435 -> 1255473.1 | V59: ='Key Assumption'!X435 -> 1255473.1 | W59: ='Key Assumption'!Y435 -> 1255473.1 | X59: ='Key Assumption'!Z435 -> 1255473.1 | Y59: =Y57/Y58 -> 1255473.1 | Z59: =Z57/Z58 -> 1255473.1 | AA59: ='Key Assumption'!AB435 -> 1269283.3 | AB59: ='Key Assumption'!AC435 -> 1285784 | AC59: ='Key Assumption'!AD435 -> 1301213.4 | AD59: ='Key Assumption'!AE435 -> 1319430.3
A60: 선반 | G60: 환율 | O60: =O$187 -> 8.9422043 | P60: =P$187 -> 9.2025316 | Q60: =Q$187 -> 9.2025316 | R60: =R$187 -> 9.2025316 | S60: =S$187 -> 9.6110283 | T60: =T$187 -> 9.6110283 | U60: =U$187 -> 9.6110283 | V60: =V$187 -> 9.6470138 | ... X60: =X$187 -> 9.6470138 | Y60: =Y56/Y57*10^6 -> 9.4824377 | Z60: =Z56/Z57*10^6 -> 9.3613077 | AA60: =AA$187 -> 10.413379 | AB60: =AB$187 -> 11.148423 | AC60: =AC$187 -> 11.389364 | AD60: =AD$187 -> 11.564885
A61: 선반 | F61: 지멘스
G62: 매입금액(EUR)
A63: 선반 | G63: 생산수량
A64: 선반 | G64: 매입단가(EUR)
A65: 선반 | G65: 환율
A66: 선반 | E66: 기타재료비 | O66: =O54-O55 -> 5090.7497 | P66: =P67*P68 -> 1750.685 | Q66: =Q67*Q68 -> 1509.5727 | R66: =R67*R68 -> 1561.9884 | S66: =S67*S68 -> 1593.4378 | T66: =T67*T68 -> 1561.9884 | U66: =U67*U68 -> 1478.1232 | V66: =V67*V68 -> 1614.4041 | W66: =W67*W68 -> 1499.0895 | X66: =X67*X68 -> 1467.6401 | Y66: =SUM(P66:X66) -> 14036.929 | Z66: =Y66+O66 -> 19127.679 | AA66: =AA67*AA68 -> 18519.089 | AB66: =AB67*AB68 -> 20240.855 | AC66: =AC67*AC68 -> 21888.58 | AD66: =AD67*AD68 -> 23403.488
A67: 선반 | F67: 생산수량 | O67: =O58 -> 387 | P67: =P58 -> 167 | Q67: =Q58 -> 144 | R67: =R58 -> 149 | S67: =S58 -> 152 | T67: =T58 -> 149 | U67: =U58 -> 141 | V67: =V58 -> 154 | ... X67: =X58 -> 140 | Y67: =SUM(P67:X67) -> 1339 | Z67: =Y67+O67 -> 1726 | AA67: =AA58 -> 1769 | AB67: =AB58 -> 1932 | AC67: =AC58 -> 2069 | AD67: =AD58 -> 2184
A68: 선반 | F68: 매입단가 | O68: =O66/O67 -> 13.154392 | P68: ='Key Assumption'!R447 -> 10.483143 | Q68: ='Key Assumption'!S447 -> 10.483143 | R68: ='Key Assumption'!T447 -> 10.483143 | S68: ='Key Assumption'!U447 -> 10.483143 | T68: ='Key Assumption'!V447 -> 10.483143 | U68: ='Key Assumption'!W447 -> 10.483143 | V68: ='Key Assumption'!X447 -> 10.483143 | W68: ='Key Assumption'!Y447 -> 10.483143 | X68: ='Key Assumption'!Z447 -> 10.483143 | Y68: =Y66/Y67 -> 10.483143 | Z68: =Z66/Z67 -> 11.082085 | AA68: ='Key Assumption'!AB447 -> 10.468677 | AB68: ='Key Assumption'!AC447 -> 10.476633 | AC68: ='Key Assumption'!AD447 -> 10.579304 | AD68: ='Key Assumption'!AE447 -> 10.715883
A69: 선반 | D69: 도급비 | O69: 11551.63 | P69: =P70*P71 -> 4878.2306 | Q69: =Q70*Q71 -> 4206.3785 | R69: =R70*R71 -> 4352.4333 | S69: =S70*S71 -> 4440.0662 | T69: =T70*T71 -> 4352.4333 | U69: =U70*U71 -> 4118.7456 | V69: =V70*V71 -> 4498.4881 | W69: =W70*W71 -> 4177.1675 | X69: =X70*X71 -> 4089.5346 | Y69: =SUM(P69:X69) -> 39113.478 | Z69: =Y69+O69 -> 50665.108 | AA69: =AA70*AA71 -> 51602.881 | AB69: =AB70*AB71 -> 57259.42 | AC69: =AC70*AC71 -> 62546.136 | AD69: =AD70*AD71 -> 67211.008
A70: 선반 | E70: 생산수량 | O70: =O58 -> 387 | P70: =P58 -> 167 | Q70: =Q58 -> 144 | R70: =R58 -> 149 | S70: =S58 -> 152 | T70: =T58 -> 149 | U70: =U58 -> 141 | V70: =V58 -> 154 | ... X70: =X58 -> 140 | Y70: =SUM(P70:X70) -> 1339 | Z70: =Y70+O70 -> 1726 | AA70: =AA58 -> 1769 | AB70: =AB58 -> 1932 | AC70: =AC58 -> 2069 | AD70: =AD58 -> 2184
A71: 선반 | E71: 단가 | O71: =O69/O70 -> 29.849173 | P71: ='Key Assumption'!R453 -> 29.210962 | Q71: ='Key Assumption'!S453 -> 29.210962 | R71: ='Key Assumption'!T453 -> 29.210962 | S71: ='Key Assumption'!U453 -> 29.210962 | T71: ='Key Assumption'!V453 -> 29.210962 | U71: ='Key Assumption'!W453 -> 29.210962 | V71: ='Key Assumption'!X453 -> 29.210962 | W71: ='Key Assumption'!Y453 -> 29.210962 | X71: ='Key Assumption'!Z453 -> 29.210962 | Y71: =Y69/Y70 -> 29.210962 | Z71: =Z69/Z70 -> 29.35406 | AA71: ='Key Assumption'!AB453 -> 29.170651 | AB71: ='Key Assumption'!AC453 -> 29.637381 | AC71: ='Key Assumption'!AD453 -> 30.230129 | AD71: ='Key Assumption'!AE453 -> 30.774271
C72: VMC | O72: =O73+O88 -> 12334.679 | P72: =P73+P88 -> 4410.9624 | Q72: =Q73+Q88 -> 4639.9544 | R72: =R73+R88 -> 4582.8242 | S72: =S73+S88 -> 4739.6509 | T72: =T73+T88 -> 4623.4601 | U72: =U73+U88 -> 3872.998 | V72: =V73+V88 -> 3991.5095 | ... AD72: =AD73+AD88 -> 88541.024
A73: VMC | D73: 재료비 | O73: 7345.6162 | P73: =P74+P85 -> 2590.3763 | Q73: =Q74+Q85 -> 2724.7924 | R73: =R74+R85 -> 2691.3062 | S73: =S74+S85 -> 2800.8449 | T73: =T74+T85 -> 2731.9421 | U73: =U74+U85 -> 2288.8517 | V73: =V74+V85 -> 2360.0752 | W73: =W74+W85 -> 2222.3251 | ... AD73: =AD74+AD85 -> 53369.02
A74: VMC | E74: NC재료비 | O74: =O75+O80 -> 2417.495 | P74: =P75+P80 -> 914.11159 | Q74: =Q75+Q80 -> 961.44901 | R74: =R75+R80 -> 949.73245 | S74: =S75+S80 -> 1015.7318 | T74: =T75+T80 -> 990.36835 | U74: =U75+U80 -> 830.28371 | V74: =V75+V80 -> 857.9679 | ... AD74: =AD75+AD80 -> 21947.803
A75: VMC | F75: 화낙 | O75: =O76*O79/10^6 -> 2226.7819 | P75: =P76*P79/10^6 -> 890.52142 | Q75: =Q76*Q79/10^6 -> 914.26866 | R75: =R76*R79/10^6 -> 926.14228 | S75: =S76*S79/10^6 -> 992.05473 | T75: =T76*T79/10^6 -> 954.85267 | U75: =U76*U79/10^6 -> 818.44515 | V75: =V76*V79/10^6 -> 846.40379 | ... X75: =X76*X79/10^6 -> 771.7211 | Y75: =SUM(P75:X75) -> 7898.578 | Z75: =Y75+O75 -> 10125.36 | AA75: =AA76*AA79/10^6 -> 11994.422 | AB75: =AB76*AB79/10^6 -> 15232.471 | AC75: =AC76*AC79/10^6 -> 18139.617 | AD75: =AD76*AD79/10^6 -> 21248.853
G76: 매입금액(JPY) | O76: =O77*O78 -> 2.4901935e+08 | P76: =P77*P78 -> 96769178 | Q76: =Q77*Q78 -> 99349689 | R76: =R77*R78 -> 1.0063994e+08 | S76: =S77*S78 -> 1.0322046e+08 | T76: =T77*T78 -> 99349689 | U76: =U77*U78 -> 85156876 | V76: =V77*V78 -> 87737388 | ... X76: =X77*X78 -> 79995853 | Y76: =SUM(P76:X76) -> 8.3350518e+08 | Z76: =Y76+O76 -> 1.0825245e+09 | AA76: =AA77*AA78 -> 1.151828e+09 | AB76: =AB77*AB78 -> 1.3663342e+09 | AC76: =AC77*AC78 -> 1.5926805e+09 | AD76: =AD77*AD78 -> 1.8373595e+09
A77: VMC | G77: 생산수량 | I77: =1-I82 -> 0.95995423 | O77: =Revenue_HW!O17-COGS_HW!O82 -> 193 | P77: =Revenue_HW!P17-P82 -> 75 | Q77: =Revenue_HW!Q17-Q82 -> 77 | R77: =Revenue_HW!R17-R82 -> 78 | S77: =Revenue_HW!S17-S82 -> 80 | T77: =Revenue_HW!T17-T82 -> 77 | U77: =Revenue_HW!U17-U82 -> 66 | V77: =Revenue_HW!V17-V82 -> 68 | W77: =Revenue_HW!W17-W82 -> 63 | X77: =Revenue_HW!X17-X82 -> 62 | Y77: =SUM(P77:X77) -> 646 | Z77: =Y77+O77 -> 839 | AA77: =ROUND(Revenue_HW!AA$17*$I77,) -> 883 | AB77: =ROUND(Revenue_HW!AB$17*$I77,) -> 1034 | AC77: =ROUND(Revenue_HW!AC$17*$I77,) -> 1191 | AD77: =ROUND(Revenue_HW!AD$17*$I77,) -> 1355
A78: VMC | G78: 매입단가(JPY) | O78: =P78 -> 1290255.7 | P78: ='Key Assumption'!R436 -> 1290255.7 | Q78: ='Key Assumption'!S436 -> 1290255.7 | R78: ='Key Assumption'!T436 -> 1290255.7 | S78: ='Key Assumption'!U436 -> 1290255.7 | T78: ='Key Assumption'!V436 -> 1290255.7 | U78: ='Key Assumption'!W436 -> 1290255.7 | V78: ='Key Assumption'!X436 -> 1290255.7 | W78: ='Key Assumption'!Y436 -> 1290255.7 | X78: ='Key Assumption'!Z436 -> 1290255.7 | Y78: =Y76/Y77 -> 1290255.7 | Z78: =Z76/Z77 -> 1290255.7 | AA78: ='Key Assumption'!AB436 -> 1304448.5 | AB78: ='Key Assumption'!AC436 -> 1321406.3 | AC78: ='Key Assumption'!AD436 -> 1337263.2 | AD78: ='Key Assumption'!AE436 -> 1355984.9
A79: VMC | G79: 환율 | O79: =O$187 -> 8.9422043 | P79: =P$187 -> 9.2025316 | Q79: =Q$187 -> 9.2025316 | R79: =R$187 -> 9.2025316 | S79: =S$187 -> 9.6110283 | T79: =T$187 -> 9.6110283 | U79: =U$187 -> 9.6110283 | V79: =V$187 -> 9.6470138 | ... X79: =X$187 -> 9.6470138 | Y79: =Y75/Y76*10^6 -> 9.4763394 | Z79: =Z75/Z76*10^6 -> 9.3534692 | AA79: =AA$187 -> 10.413379 | AB79: =AB$187 -> 11.148423 | AC79: =AC$187 -> 11.389364 | AD79: =AD$187 -> 11.564885
A80: VMC | F80: 지멘스 | O80: =O81*O84/10^6 -> 190.71306 | P80: =P81*P84/10^6 -> 23.590175 | Q80: =Q81*Q84/10^6 -> 47.180351 | R80: =R81*R84/10^6 -> 23.590175 | S80: =S81*S84/10^6 -> 23.677114 | T80: =T81*T84/10^6 -> 35.515672 | U80: =U81*U84/10^6 -> 11.838557 | V80: =V81*V84/10^6 -> 11.564117 | ... X80: =X81*X84/10^6 -> 23.128234 | Y80: =SUM(P80:X80) -> 223.21263 | Z80: =Y80+O80 -> 413.92569 | AA80: =AA81*AA84/10^6 -> 428.91645 | AB80: =AB81*AB84/10^6 -> 506.46946 | AC80: =AC81*AC84/10^6 -> 598.68681 | AD80: =AD81*AD84/10^6 -> 698.95063
G81: 매입금액(EUR) | O81: =O82*O83 -> 132304 | P81: =P82*P83 -> 16538 | Q81: =Q82*Q83 -> 33076 | R81: =R82*R83 -> 16538 | S81: =S82*S83 -> 16538 | T81: =T82*T83 -> 24807 | U81: =U82*U83 -> 8269 | V81: =V82*V83 -> 8269 | ... X81: =X82*X83 -> 16538 | Y81: =SUM(P81:X81) -> 157111 | Z81: =Y81+O81 -> 289415 | AA81: =AA82*AA83 -> 310542.3 | AB81: =AB82*AB83 -> 364870.41 | AC81: =AC82*AC83 -> 428510.6 | AD81: =AD82*AD83 -> 492898.6
A82: VMC | G82: 생산수량 | I82: =Z82/Revenue_HW!Z17 -> 0.040045767 | O82: 16 | P82: 2 | Q82: 4 | R82: 2 | S82: 2 | T82: 3 | U82: 1 | V82: 1 | W82: 2 | X82: 2 | Y82: =SUM(P82:X82) -> 19 | Z82: =Y82+O82 -> 35 | AA82: =Revenue_HW!AA17-COGS_HW!AA77 -> 37 | AB82: =Revenue_HW!AB17-COGS_HW!AB77 -> 43 | AC82: =Revenue_HW!AC17-COGS_HW!AC77 -> 50 | AD82: =Revenue_HW!AD17-COGS_HW!AD77 -> 57
A83: VMC | G83: 매입단가(EUR) | O83: =P83 -> 8269 | P83: ='Key Assumption'!R442 -> 8269 | Q83: ='Key Assumption'!S442 -> 8269 | R83: ='Key Assumption'!T442 -> 8269 | S83: ='Key Assumption'!U442 -> 8269 | T83: ='Key Assumption'!V442 -> 8269 | U83: ='Key Assumption'!W442 -> 8269 | V83: ='Key Assumption'!X442 -> 8269 | W83: ='Key Assumption'!Y442 -> 8269 | X83: ='Key Assumption'!Z442 -> 8269 | Y83: =Y81/Y82 -> 8269 | Z83: =Z81/Z82 -> 8269 | AA83: ='Key Assumption'!AB442 -> 8393.035 | AB83: ='Key Assumption'!AC442 -> 8485.3584 | AC83: ='Key Assumption'!AD442 -> 8570.212 | AD83: ='Key Assumption'!AE442 -> 8647.3439
A84: VMC | G84: 환율 | O84: =Revenue_HW!$O$482 -> 1441.4761 | P84: =P$188 -> 1426.4225 | Q84: =Q$188 -> 1426.4225 | R84: =R$188 -> 1426.4225 | S84: =S$188 -> 1431.6794 | T84: =T$188 -> 1431.6794 | U84: =U$188 -> 1431.6794 | V84: =V$188 -> 1398.4904 | W84: =W$188 -> 1398.4904 | X84: =X$188 -> 1398.4904 | Y84: =Y80/Y81*10^6 -> 1420.732 | Z84: =Z80/Z81*10^6 -> 1430.2151 | AA84: =AA$188 -> 1381.1853 | AB84: =AB$188 -> 1388.0804 | AC84: =AC$188 -> 1397.1342 | AD84: =AD$188 -> 1418.0414
A85: VMC | E85: 기타재료비 | O85: =O73-O74 -> 4928.1213 | P85: =P86*P87 -> 1676.2647 | Q85: =Q86*Q87 -> 1763.3434 | R85: =R86*R87 -> 1741.5737 | S85: =S86*S87 -> 1785.1131 | T85: =T86*T87 -> 1741.5737 | U85: =U86*U87 -> 1458.568 | V85: =V86*V87 -> 1502.1073 | W85: =W86*W87 -> 1415.0286 | X85: =X86*X87 -> 1393.259 | Y85: =SUM(P85:X85) -> 14476.832 | Z85: =Y85+O85 -> 19404.953 | AA85: =AA86*AA87 -> 20000.459 | AB85: =AB86*AB87 -> 23431.375 | AC85: =AC86*AC87 -> 27263.978 | AD85: =AD86*AD87 -> 31421.216
A86: VMC | F86: 생산수량 | O86: =+O82+O77 -> 209 | P86: =+P82+P77 -> 77 | Q86: =+Q82+Q77 -> 81 | R86: =+R82+R77 -> 80 | S86: =+S82+S77 -> 82 | T86: =+T82+T77 -> 80 | U86: =+U82+U77 -> 67 | V86: =+V82+V77 -> 69 | ... Y86: =+Y82+Y77 -> 665 | Z86: =Y86+O86 -> 874 | AA86: =+AA82+AA77 -> 920 | AB86: =+AB82+AB77 -> 1077 | AC86: =+AC82+AC77 -> 1241 | AD86: =+AD82+AD77 -> 1412
A87: VMC | F87: 매입단가 | O87: =O85/O86 -> 23.579528 | P87: ='Key Assumption'!R448 -> 21.769671 | Q87: ='Key Assumption'!S448 -> 21.769671 | R87: ='Key Assumption'!T448 -> 21.769671 | S87: ='Key Assumption'!U448 -> 21.769671 | T87: ='Key Assumption'!V448 -> 21.769671 | U87: ='Key Assumption'!W448 -> 21.769671 | V87: ='Key Assumption'!X448 -> 21.769671 | W87: ='Key Assumption'!Y448 -> 21.769671 | X87: ='Key Assumption'!Z448 -> 21.769671 | Y87: =Y85/Y86 -> 21.769671 | Z87: =Z85/Z86 -> 22.202463 | AA87: ='Key Assumption'!AB448 -> 21.739629 | AB87: ='Key Assumption'!AC448 -> 21.756151 | AC87: ='Key Assumption'!AD448 -> 21.969362 | AD87: ='Key Assumption'!AE448 -> 22.252986
A88: VMC | D88: 도급비 | O88: 4989.0627 | P88: =P89*P90 -> 1820.5861 | Q88: =Q89*Q90 -> 1915.162 | R88: =R89*R90 -> 1891.518 | S88: =S89*S90 -> 1938.806 | T88: =T89*T90 -> 1891.518 | U88: =U89*U90 -> 1584.1464 | V88: =V89*V90 -> 1631.4343 | W88: =W89*W90 -> 1536.8584 | X88: =X89*X90 -> 1513.2144 | Y88: =SUM(P88:X88) -> 15723.244 | Z88: =Y88+O88 -> 20712.306 | AA88: =AA89*AA90 -> 21722.439 | AB88: =AB89*AB90 -> 25836.291 | AC88: =AC89*AC90 -> 30365.918 | AD88: =AD89*AD90 -> 35172.004
A89: VMC | E89: 생산수량 | O89: =O86 -> 209 | P89: =P86 -> 77 | Q89: =Q86 -> 81 | R89: =R86 -> 80 | S89: =S86 -> 82 | T89: =T86 -> 80 | U89: =U86 -> 67 | V89: =V86 -> 69 | ... X89: =X86 -> 64 | Y89: =SUM(P89:X89) -> 665 | Z89: =Y89+O89 -> 874 | AA89: =AA86 -> 920 | AB89: =AB86 -> 1077 | AC89: =AC86 -> 1241 | AD89: =AD86 -> 1412
A90: VMC | E90: 단가 | O90: =O88/O89 -> 23.871113 | P90: ='Key Assumption'!R454 -> 23.643975 | Q90: ='Key Assumption'!S454 -> 23.643975 | R90: ='Key Assumption'!T454 -> 23.643975 | S90: ='Key Assumption'!U454 -> 23.643975 | T90: ='Key Assumption'!V454 -> 23.643975 | U90: ='Key Assumption'!W454 -> 23.643975 | V90: ='Key Assumption'!X454 -> 23.643975 | W90: ='Key Assumption'!Y454 -> 23.643975 | X90: ='Key Assumption'!Z454 -> 23.643975 | Y90: =Y88/Y89 -> 23.643975 | Z90: =Z88/Z89 -> 23.698291 | AA90: ='Key Assumption'!AB454 -> 23.611347 | AB90: ='Key Assumption'!AC454 -> 23.989128 | AC90: ='Key Assumption'!AD454 -> 24.468911 | AD90: ='Key Assumption'!AE454 -> 24.909351
C91: HMC | O91: =O92+O107 -> 1903.4061 | P91: =P92+P107 -> 2103.6771 | Q91: =Q92+Q107 -> 1679.0003 | R91: =R92+R107 -> 2335.7227 | S91: =S92+S107 -> 1282.0226 | T91: =T92+T107 -> 2544.338 | U91: =U92+U107 -> 1883.6196 | V91: =V92+V107 -> 1670.8879 | ... AD91: =AD92+AD107 -> 28573.832
A92: HMC | D92: 재료비 | O92: 1726.0421 | P92: =P93+P104 -> 1926.3132 | Q92: =Q93+Q104 -> 1541.0506 | R92: =R93+R104 -> 2118.9445 | S92: =S93+S104 -> 1163.7799 | T92: =T93+T104 -> 2327.5599 | U92: =U93+U104 -> 1745.6699 | V92: =V93+V104 -> 1552.6453 | W92: =W93+W104 -> 1746.726 | ... AD92: =AD93+AD104 -> 17151.019
A93: HMC | E93: NC재료비 | O93: =O94+O99 -> 262.42442 | P93: =P94+P99 -> 300.07131 | Q93: =Q94+Q99 -> 240.05705 | R93: =R94+R99 -> 330.07844 | S93: =S94+S99 -> 188.03481 | T93: =T94+T99 -> 376.06962 | U93: =U94+U99 -> 282.05222 | V93: =V94+V99 -> 251.6518 | ... AD93: =AD94+AD99 -> 4874.6414
A94: HMC | F94: 화낙 | O94: =O95*O98/10^6 -> 262.42442 | P94: =P95*P98/10^6 -> 300.07131 | Q94: =Q95*Q98/10^6 -> 240.05705 | R94: =R95*R98/10^6 -> 330.07844 | S94: =S95*S98/10^6 -> 188.03481 | T94: =T95*T98/10^6 -> 376.06962 | U94: =U95*U98/10^6 -> 282.05222 | V94: =V95*V98/10^6 -> 251.6518 | ... X94: =X95*X98/10^6 -> 314.56475 | Y94: =SUM(P94:X94) -> 2565.6883 | Z94: =Y94+O94 -> 2828.1127 | AA94: =AA95*AA98/10^6 -> 3535.8775 | AB94: =AB95*AB98/10^6 -> 4020.8229 | AC94: =AC95*AC98/10^6 -> 4387.9592 | AD94: =AD95*AD98/10^6 -> 4874.6414
G95: 매입금액(JPY) | O95: =O96*O97 -> 29346726 | P95: =P96*P97 -> 32607474 | Q95: =Q96*Q97 -> 26085979 | R95: =R96*R97 -> 35868221 | S95: =S96*S97 -> 19564484 | T95: =T96*T97 -> 39128968 | U95: =U96*U97 -> 29346726 | V95: =V96*V97 -> 26085979 | ... X95: =X96*X97 -> 32607474 | Y95: =SUM(P95:X95) -> 2.7064203e+08 | Z95: =Y95+O95 -> 2.9998876e+08 | AA95: =AA96*AA97 -> 3.3955141e+08 | AB95: =AB96*AB97 -> 3.6066293e+08 | AC95: =AC96*AC97 -> 3.8526816e+08 | AD95: =AD96*AD97 -> 4.2150364e+08
A96: HMC | G96: 생산수량 | O96: =Revenue_HW!O18 -> 9 | P96: =Revenue_HW!P18 -> 10 | Q96: =Revenue_HW!Q18 -> 8 | R96: =Revenue_HW!R18 -> 11 | S96: =Revenue_HW!S18 -> 6 | T96: =Revenue_HW!T18 -> 12 | U96: =Revenue_HW!U18 -> 9 | V96: =Revenue_HW!V18 -> 8 | ... X96: =Revenue_HW!X18 -> 10 | Y96: =SUM(P96:X96) -> 83 | Z96: =Y96+O96 -> 92 | AA96: =Revenue_HW!AA18 -> 103 | AB96: =Revenue_HW!AB18 -> 108 | AC96: =Revenue_HW!AC18 -> 114 | AD96: =Revenue_HW!AD18 -> 123
A97: HMC | G97: 매입단가(JPY) | O97: =P97 -> 3260747.4 | P97: ='Key Assumption'!R437 -> 3260747.4 | Q97: ='Key Assumption'!S437 -> 3260747.4 | R97: ='Key Assumption'!T437 -> 3260747.4 | S97: ='Key Assumption'!U437 -> 3260747.4 | T97: ='Key Assumption'!V437 -> 3260747.4 | U97: ='Key Assumption'!W437 -> 3260747.4 | V97: ='Key Assumption'!X437 -> 3260747.4 | W97: ='Key Assumption'!Y437 -> 3260747.4 | X97: ='Key Assumption'!Z437 -> 3260747.4 | Y97: =Y95/Y96 -> 3260747.4 | Z97: =Z95/Z96 -> 3260747.4 | AA97: ='Key Assumption'!AB437 -> 3296615.6 | AB97: ='Key Assumption'!AC437 -> 3339471.6 | AC97: ='Key Assumption'!AD437 -> 3379545.3 | AD97: ='Key Assumption'!AE437 -> 3426858.9
A98: HMC | G98: 환율 | O98: =O$187 -> 8.9422043 | P98: =P$187 -> 9.2025316 | Q98: =Q$187 -> 9.2025316 | R98: =R$187 -> 9.2025316 | S98: =S$187 -> 9.6110283 | T98: =T$187 -> 9.6110283 | U98: =U$187 -> 9.6110283 | V98: =V$187 -> 9.6470138 | ... X98: =X$187 -> 9.6470138 | Y98: =Y94/Y95*10^6 -> 9.4800067 | Z98: =Z94/Z95*10^6 -> 9.4273956 | AA98: =AA$187 -> 10.413379 | AB98: =AB$187 -> 11.148423 | AC98: =AC$187 -> 11.389364 | AD98: =AD$187 -> 11.564885
A99: HMC | F99: 지멘스
G100: 매입금액(EUR)
A101: HMC | G101: 생산수량
A102: HMC | G102: 매입단가(EUR)
A103: HMC | G103: 환율
A104: HMC | E104: 기타재료비 | O104: =O92-O93 -> 1463.6177 | P104: =P105*P106 -> 1626.2419 | Q104: =Q105*Q106 -> 1300.9935 | R104: =R105*R106 -> 1788.8661 | S104: =S105*S106 -> 975.74513 | T104: =T105*T106 -> 1951.4903 | U104: =U105*U106 -> 1463.6177 | V104: =V105*V106 -> 1300.9935 | W104: =W105*W106 -> 1463.6177 | X104: =X105*X106 -> 1626.2419 | Y104: =SUM(P104:X104) -> 13497.808 | Z104: =Y104+O104 -> 14961.425 | AA104: =AA105*AA106 -> 10043.063 | AB104: =AB105*AB106 -> 10538.594 | AC104: =AC105*AC106 -> 11233.087 | AD104: =AD105*AD106 -> 12276.378
A105: HMC | F105: 생산수량 | O105: =O96 -> 9 | P105: =P96 -> 10 | Q105: =Q96 -> 8 | R105: =R96 -> 11 | S105: =S96 -> 6 | T105: =T96 -> 12 | U105: =U96 -> 9 | V105: =V96 -> 8 | ... X105: =X96 -> 10 | Y105: =SUM(P105:X105) -> 83 | Z105: =Y105+O105 -> 92 | AA105: =AA96 -> 103 | AB105: =AB96 -> 108 | AC105: =AC96 -> 114 | AD105: =AD96 -> 123
...

Sheet SG&A_HW
A1: =MID(CELL("filename",A1),FIND("]",CELL("filename",A1))+1,255) -> SG&A_HW
B3: 1. Summary
L5: 2021A | M5: 2022A | N5: 2023A | O5: 24.3m(A) | P5: 4월 | Q5: 5월 | R5: 6월 | S5: 7월 | T5: 8월 | U5: 9월 | V5: 10월 | W5: 11월 | X5: 12월 | Y5: 24.9m(E) | Z5: 2024F | AA5: 2025F | AB5: 2026F | AC5: 2027F | AD5: 2028F
B6: SG&A | L6: =SUM(L8:L10) -> 69399.84 | M6: =SUM(M8:M10) -> 65678.894 | N6: =SUM(N8:N10) -> 53377.339 | O6: =SUM(O8:O10) -> 11854.107 | P6: =SUM(P8:P10) -> 4489.7001 | Q6: =SUM(Q8:Q10) -> 4289.9002 | R6: =SUM(R8:R10) -> 4548.8281 | S6: =SUM(S8:S10) -> 4360.5625 | ... AD6: =SUM(AD8:AD10) -> 61720.693
C7: % of revenue | L7: =IFERROR(L6/Revenue_HW!L$6,"-") -> - | M7: =IFERROR(M6/Revenue_HW!M$6,"-") -> - | N7: =IFERROR(N6/Revenue_HW!N$6,"-") -> - | O7: =IFERROR(O6/Revenue_HW!O$6,"-") -> 0.15613516 | P7: =IFERROR(P6/Revenue_HW!P$6,"-") -> 0.14396626 | Q7: =IFERROR(Q6/Revenue_HW!Q$6,"-") -> 0.15111341 | R7: =IFERROR(R6/Revenue_HW!R$6,"-") -> 0.15044172 | S7: =IFERROR(S6/Revenue_HW!S$6,"-") -> 0.15855248 | ... AD7: =IFERROR(AD6/Revenue_HW!AD$6,"-") -> 0.14308821
C8: 인건비 | L8: =L15 -> 22708.769 | M8: =M15 -> 17280.514 | N8: =N15 -> 17207.635 | O8: =O15 -> 4194.6848 | P8: =P15 -> 1398.2283 | Q8: =Q15 -> 1398.2283 | R8: =R15 -> 1398.2283 | S8: =S15 -> 1398.2283 | ... AD8: =AD15 -> 19216.047
C9: 변동비 | L9: =L26 -> 32987.956 | M9: =M26 -> 32265.465 | N9: =N26 -> 24404.934 | O9: =O26 -> 5301.976 | P9: =P26 -> 2059.4535 | Q9: =Q26 -> 1859.6536 | R9: =R26 -> 2118.5815 | S9: =S26 -> 1930.3158 | ... AD9: =AD26 -> 29809.003
C10: 고정비 | L10: =L49 -> 13703.115 | M10: =M49 -> 16132.914 | N10: =N49 -> 11764.77 | O10: =O49 -> 2357.4464 | P10: =P49 -> 1032.0184 | Q10: =Q49 -> 1032.0184 | R10: =R49 -> 1032.0184 | S10: =S49 -> 1032.0184 | ... AD10: =AD49 -> 12695.643
B12: 2. 인건비
L14: 2021A | M14: 2022A | N14: 2023A | O14: 24.3m(A) | P14: 4월 | Q14: 5월 | R14: 6월 | S14: 7월 | T14: 8월 | U14: 9월 | V14: 10월 | W14: 11월 | X14: 12월 | Y14: 24.9m(E) | Z14: 2024F | AA14: 2025F | AB14: 2026F | AC14: 2027F | AD14: 2028F
B15: 인건비 | L15: =L17+L20 -> 22708.769 | M15: =M17+M20 -> 17280.514 | N15: =N17+N20 -> 17207.635 | O15: =O17+O21 -> 4194.6848 | P15: =P17+P21 -> 1398.2283 | Q15: =Q17+Q21 -> 1398.2283 | R15: =R17+R21 -> 1398.2283 | S15: =S17+S21 -> 1398.2283 | T15: =T17+T21 -> 1398.2283 | U15: =U17+U21 -> 1398.2283 | V15: =V17+V21 -> 1398.2283 | ... AD15: =AD17+AD21 -> 19216.047
B16: % of revenue | L16: =IFERROR(L15/Revenue_HW!L$6,"-") -> - | M16: =IFERROR(M15/Revenue_HW!M$6,"-") -> - | N16: =IFERROR(N15/Revenue_HW!N$6,"-") -> - | O16: =IFERROR(O15/Revenue_HW!O$6,"-") -> 0.055249861 | P16: =IFERROR(P15/Revenue_HW!P$6,"-") -> 0.044835442 | Q16: =IFERROR(Q15/Revenue_HW!Q$6,"-") -> 0.049253135 | R16: =IFERROR(R15/Revenue_HW!R$6,"-") -> 0.046243089 | S16: =IFERROR(S15/Revenue_HW!S$6,"-") -> 0.050840359 | ... AD16: =IFERROR(AD15/Revenue_HW!AD$6,"-") -> 0.044548914
C17: 인건비 | L17: 20857.481 | M17: 15164.068 | N17: 15016.109 | O17: 3199.5407 | P17: =P18*P19/12 -> 1066.5136 | Q17: =Q18*Q19/12 -> 1066.5136 | R17: =R18*R19/12 -> 1066.5136 | S17: =S18*S19/12 -> 1066.5136 | T17: =T18*T19/12 -> 1066.5136 | U17: =U18*U19/12 -> 1066.5136 | V17: =V18*V19/12 -> 1066.5136 | W17: =W18*W19/12 -> 1066.5136 | X17: =X18*X19/12 -> 1066.5136 | Y17: =SUM(P17:X17) -> 9598.6222 | Z17: =SUM(O17,Y17) -> 12798.163 | AA17: =AA18*AA19 -> 13156.511 | AB17: =AB18*AB19 -> 13695.928 | AC17: =AC18*AC19 -> 14161.59 | AD17: =AD18*AD19 -> 14657.246
D18: 평균인원수 | O18: =$Z18 -> 85 | P18: =$Z18 -> 85 | Q18: =$Z18 -> 85 | R18: =$Z18 -> 85 | S18: =$Z18 -> 85 | T18: =$Z18 -> 85 | U18: =$Z18 -> 85 | V18: =$Z18 -> 85 | ... Y18: =$Z18 -> 85 | Z18: 85 | AA18: =Z18 -> 85 | AB18: =AA18 -> 85 | AC18: =AB18 -> 85 | AD18: =AC18 -> 85
D19: 평균급여 | O19: =O17/O18*4 -> 150.56662 | P19: =$O19 -> 150.56662 | Q19: =$O19 -> 150.56662 | R19: =$O19 -> 150.56662 | S19: =$O19 -> 150.56662 | T19: =$O19 -> 150.56662 | U19: =$O19 -> 150.56662 | V19: =$O19 -> 150.56662 | W19: =$O19 -> 150.56662 | X19: =$O19 -> 150.56662 | Y19: =Y17/Y18/3*4 -> 150.56662 | Z19: =Z17/Z18 -> 150.56662 | AA19: =Z19*(1+'Key Assumption'!AB$15) -> 154.78249 | AB19: =AA19*(1+'Key Assumption'!AC$15) -> 161.12857 | AC19: =AB19*(1+'Key Assumption'!AD$15) -> 166.60694 | AD19: =AC19*(1+'Key Assumption'!AE$15) -> 172.43818
C20: 간접비배부액 | L20: 1851.2873 | M20: 2116.4461 | N20: 2191.5264 | O20: 541.83248
C21: Stand-alone Cost | O21: 995.14409 | P21: =O21/3 -> 331.7147 | Q21: =P21 -> 331.7147 | R21: =Q21 -> 331.7147 | S21: =R21 -> 331.7147 | T21: =S21 -> 331.7147 | U21: =T21 -> 331.7147 | V21: =U21 -> 331.7147 | W21: =V21 -> 331.7147 | X21: =W21 -> 331.7147 | Y21: =SUM(P21:X21) -> 2985.4323 | Z21: =Y21+O21 -> 3980.5764 | AA21: =Z21*(1+'Key Assumption'!AB$15) -> 4092.0325 | AB21: =AA21*(1+'Key Assumption'!AC$15) -> 4259.8058 | AC21: =AB21*(1+'Key Assumption'!AD$15) -> 4404.6392 | AD21: =AC21*(1+'Key Assumption'!AE$15) -> 4558.8016
B23: 3. 변동비
L25: 2021A | M25: 2022A | N25: 2023A | O25: 24.3m(A) | P25: 4월 | Q25: 5월 | R25: 6월 | S25: 7월 | T25: 8월 | U25: 9월 | V25: 10월 | W25: 11월 | X25: 12월 | Y25: 24.9m(E) | Z25: 2024F | AA25: 2025F | AB25: 2026F | AC25: 2027F | AD25: 2028F
B26: 변동비 | L26: =SUM(L28,L31,L34,L36,L39,L41,L43) -> 32987.956 | M26: =SUM(M28,M31,M34,M36,M39,M41,M43) -> 32265.465 | N26: =SUM(N28,N31,N34,N36,N39,N41,N43) -> 24404.934 | O26: =SUM(O28,O31,O34,O36,O39,O41,O44) -> 5301.976 | P26: =SUM(P28,P31,P34,P36,P39,P41,P44) -> 2059.4535 | Q26: =SUM(Q28,Q31,Q34,Q36,Q39,Q41,Q44) -> 1859.6536 | R26: =SUM(R28,R31,R34,R36,R39,R41,R44) -> 2118.5815 | S26: =SUM(S28,S31,S34,S36,S39,S41,S44) -> 1930.3158 | T26: =SUM(T28,T31,T34,T36,T39,T41,T44) -> 1865.6143 | U26: =SUM(U28,U31,U34,U36,U39,U41,U44) -> 1899.0628 | V26: =SUM(V28,V31,V34,V36,V39,V41,V44) -> 1830.8611 | ... AD26: =SUM(AD28,AD31,AD34,AD36,AD39,AD41,AD44) -> 29809.003
B27: % of revenue | L27: =IFERROR(L26/Revenue_HW!L$6,"-") -> - | M27: =IFERROR(M26/Revenue_HW!M$6,"-") -> - | N27: =IFERROR(N26/Revenue_HW!N$6,"-") -> - | O27: =IFERROR(O26/Revenue_HW!O$6,"-") -> 0.069834433 | P27: =IFERROR(P26/Revenue_HW!P$6,"-") -> 0.06603822 | Q27: =IFERROR(Q26/Revenue_HW!Q$6,"-") -> 0.065507021 | R27: =IFERROR(R26/Revenue_HW!R$6,"-") -> 0.070067066 | S27: =IFERROR(S26/Revenue_HW!S$6,"-") -> 0.07018736 | ... AD27: =IFERROR(AD26/Revenue_HW!AD$6,"-") -> 0.069106758
C28: 운반비 | L28: 1293.7876 | M28: 1415.6139 | N28: 1524.0458 | O28: 304.68709 | P28: =P29*P30 -> 129.08861 | Q28: =Q29*Q30 -> 120.54598 | R28: =R29*R30 -> 121.96975 | S28: =S29*S30 -> 119.12221 | T28: =T29*T30 -> 121.96975 | U28: =U29*U30 -> 113.42712 | V28: =V29*V30 -> 119.12221 | W28: =W29*W30 -> 112.47794 | X28: =X29*X30 -> 109.15581 | Y28: =SUM(P28:X28) -> 1066.8794 | Z28: =SUM(O28,Y28) -> 1371.5665 | AA28: =AA29*AA30 -> 1375.6707 | AB28: =AB29*AB30 -> 1569.4219 | AC28: =AC29*AC30 -> 1753.1613 | AD28: =AD29*AD30 -> 1946.1321
D29: 판매수량 | O29: =Revenue_HW!O$14 -> 642 | P29: =Revenue_HW!P$14 -> 272 | Q29: =Revenue_HW!Q$14 -> 254 | R29: =Revenue_HW!R$14 -> 257 | S29: =Revenue_HW!S$14 -> 251 | T29: =Revenue_HW!T$14 -> 257 | U29: =Revenue_HW!U$14 -> 239 | V29: =Revenue_HW!V$14 -> 251 | ... AD29: =Revenue_HW!AD$14 -> 3822
D30: 단위당 운반보관비 | O30: =O28/O29 -> 0.47459048 | P30: =$O30 -> 0.47459048 | Q30: =$O30 -> 0.47459048 | R30: =$O30 -> 0.47459048 | S30: =$O30 -> 0.47459048 | T30: =$O30 -> 0.47459048 | U30: =$O30 -> 0.47459048 | V30: =$O30 -> 0.47459048 | W30: =$O30 -> 0.47459048 | X30: =$O30 -> 0.47459048 | Y30: =Y28/Y29 -> 0.47459048 | Z30: =Z28/Z29 -> 0.47459048 | AA30: =Z30*(1+'Key Assumption'!AB$13) -> 0.48218392 | AB30: =AA30*(1+'Key Assumption'!AC$13) -> 0.4918276 | AC30: =AB30*(1+'Key Assumption'!AD$13) -> 0.50018867 | AD30: =AC30*(1+'Key Assumption'!AE$13) -> 0.50919207
C31: 판매보증비 | L31: 3670.941 | M31: 3042.4288 | N31: 2893.9612 | O31: 424.22818 | P31: =P32*P33 -> 179.73531 | Q31: =Q32*Q33 -> 167.84106 | R31: =R32*R33 -> 169.82343 | S31: =S32*S33 -> 165.85868 | T31: =T32*T33 -> 169.82343 | U31: =U32*U33 -> 157.92918 | V31: =V32*V33 -> 165.85868 | W31: =W32*W33 -> 156.6076 | X31: =X32*X33 -> 151.98206 | Y31: =SUM(P31:X31) -> 1485.4594 | Z31: =SUM(O31,Y31) -> 1909.6876 | AA31: =AA32*AA33 -> 1915.4021 | AB31: =AB32*AB33 -> 2185.1697 | AC31: =AC32*AC33 -> 2440.9976 | AD31: =AD32*AD33 -> 2709.6786
D32: 판매수량 | O32: =Revenue_HW!O$14 -> 642 | P32: =Revenue_HW!P$14 -> 272 | Q32: =Revenue_HW!Q$14 -> 254 | R32: =Revenue_HW!R$14 -> 257 | S32: =Revenue_HW!S$14 -> 251 | T32: =Revenue_HW!T$14 -> 257 | U32: =Revenue_HW!U$14 -> 239 | V32: =Revenue_HW!V$14 -> 251 | ... AD32: =Revenue_HW!AD$14 -> 3822
D33: 단위당 판매보증비 | O33: =O31/O32 -> 0.66079157 | P33: =$O33 -> 0.66079157 | Q33: =$O33 -> 0.66079157 | R33: =$O33 -> 0.66079157 | S33: =$O33 -> 0.66079157 | T33: =$O33 -> 0.66079157 | U33: =$O33 -> 0.66079157 | V33: =$O33 -> 0.66079157 | W33: =$O33 -> 0.66079157 | X33: =$O33 -> 0.66079157 | Y33: =Y31/Y32 -> 0.66079157 | Z33: =Z31/Z32 -> 0.66079157 | AA33: =Z33*(1+'Key Assumption'!AB$13) -> 0.67136423 | AB33: =AA33*(1+'Key Assumption'!AC$13) -> 0.68479152 | AC33: =AB33*(1+'Key Assumption'!AD$13) -> 0.69643297 | AD33: =AC33*(1+'Key Assumption'!AE$13) -> 0.70896876
C34: 판매촉진비 | L34: 7477.9963 | M34: 8260.8329 | N34: 11978.741 | O34: 2859.6925 | P34: =P35 -> 934.02431 | Q34: =Q35 -> 908.05534 | R34: =R35 -> 1109.8892 | S34: =S35 -> 874.74794 | T34: =T35 -> 826.24318 | U34: =U35 -> 933.81645 | V34: =V35 -> 782.96292 | W34: =W35 -> 1029.4091 | X34: =X35 -> 958.93923 | Y34: =SUM(P34:X34) -> 8358.0877 | Z34: =SUM(O34,Y34) -> 11217.78 | AA34: =AA35 -> 10174.924 | AB34: =AB35 -> 11316.615 | AC34: =AC35 -> 12598.08 | AD34: =AD35 -> 13887.333
D35: 매출 연동 | O35: =Revenue_HW!O80+SUM(Revenue_HW!O212,Revenue_HW!O255,Revenue_HW!O298,Revenue_HW!O341,Revenue_HW!O384) -> 2859.6925 | P35: =Revenue_HW!P80+SUM(Revenue_HW!P212,Revenue_HW!P255,Revenue_HW!P298,Revenue_HW!P341,Revenue_HW!P384) -> 934.02431 | Q35: =Revenue_HW!Q80+SUM(Revenue_HW!Q212,Revenue_HW!Q255,Revenue_HW!Q298,Revenue_HW!Q341,Revenue_HW!Q384) -> 908.05534 | R35: =Revenue_HW!R80+SUM(Revenue_HW!R212,Revenue_HW!R255,Revenue_HW!R298,Revenue_HW!R341,Revenue_HW!R384) -> 1109.8892 | S35: =Revenue_HW!S80+SUM(Revenue_HW!S212,Revenue_HW!S255,Revenue_HW!S298,Revenue_HW!S341,Revenue_HW!S384) -> 874.74794 | T35: =Revenue_HW!T80+SUM(Revenue_HW!T212,Revenue_HW!T255,Revenue_HW!T298,Revenue_HW!T341,Revenue_HW!T384) -> 826.24318 | U35: =Revenue_HW!U80+SUM(Revenue_HW!U212,Revenue_HW!U255,Revenue_HW!U298,Revenue_HW!U341,Revenue_HW!U384) -> 933.81645 | V35: =Revenue_HW!V80+SUM(Revenue_HW!V212,Revenue_HW!V255,Revenue_HW!V298,Revenue_HW!V341,Revenue_HW!V384) -> 782.96292 | ... X35: =Revenue_HW!X80+SUM(Revenue_HW!X212,Revenue_HW!X255,Revenue_HW!X298,Revenue_HW!X341,Revenue_HW!X384) -> 958.93923 | Y35: =SUM(P35:X35) -> 8358.0877 | Z35: =Y35+O35 -> 11217.78 | AA35: =Revenue_HW!AA80+SUM(Revenue_HW!AA212,Revenue_HW!AA255,Revenue_HW!AA298,Revenue_HW!AA341,Revenue_HW!AA384) -> 10174.924 | AB35: =Revenue_HW!AB80+SUM(Revenue_HW!AB212,Revenue_HW!AB255,Revenue_HW!AB298,Revenue_HW!AB341,Revenue_HW!AB384) -> 11316.615 | AC35: =Revenue_HW!AC80+SUM(Revenue_HW!AC212,Revenue_HW!AC255,Revenue_HW!AC298,Revenue_HW!AC341,Revenue_HW!AC384) -> 12598.08 | AD35: =Revenue_HW!AD80+SUM(Revenue_HW!AD212,Revenue_HW!AD255,Revenue_HW!AD298,Revenue_HW!AD341,Revenue_HW!AD384) -> 13887.333
C36: 수출비 | L36: 20559.643 | M36: 19521.278 | N36: 7893.0955 | O36: 1698.229 | P36: =P37*P38 -> 812.98847 | Q36: =Q37*Q38 -> 659.59442 | R36: =R37*R38 -> 713.28234 | S36: =S37*S38 -> 766.97026 | T36: =T37*T38 -> 743.96115 | U36: =U37*U38 -> 690.27323 | V36: =V37*V38 -> 759.30056 | W36: =W37*W38 -> 682.60353 | X36: =X37*X38 -> 705.61264 | Y36: =SUM(P36:X36) -> 6534.5866 | Z36: =SUM(O36,Y36) -> 8232.8156 | AA36: =AA37*AA38 -> 8649.5838 | AB36: =AB37*AB38 -> 9657.1434 | AC36: =AC37*AC38 -> 10437.079 | AD36: =AD37*AD38 -> 11224.744
D37: 수출물량 | O37: =Revenue_HW!O$14-SUM(Revenue_HW!O51,Revenue_HW!O56,Revenue_HW!O61,Revenue_HW!O66,Revenue_HW!O71) -> 306 | P37: =Revenue_HW!P$14-SUM(Revenue_HW!P51,Revenue_HW!P56,Revenue_HW!P61,Revenue_HW!P66,Revenue_HW!P71) -> 106 | Q37: =Revenue_HW!Q$14-SUM(Revenue_HW!Q51,Revenue_HW!Q56,Revenue_HW!Q61,Revenue_HW!Q66,Revenue_HW!Q71) -> 86 | R37: =Revenue_HW!R$14-SUM(Revenue_HW!R51,Revenue_HW!R56,Revenue_HW!R61,Revenue_HW!R66,Revenue_HW!R71) -> 93 | S37: =Revenue_HW!S$14-SUM(Revenue_HW!S51,Revenue_HW!S56,Revenue_HW!S61,Revenue_HW!S66,Revenue_HW!S71) -> 100 | T37: =Revenue_HW!T$14-SUM(Revenue_HW!T51,Revenue_HW!T56,Revenue_HW!T61,Revenue_HW!T66,Revenue_HW!T71) -> 97 | U37: =Revenue_HW!U$14-SUM(Revenue_HW!U51,Revenue_HW!U56,Revenue_HW!U61,Revenue_HW!U66,Revenue_HW!U71) -> 90 | V37: =Revenue_HW!V$14-SUM(Revenue_HW!V51,Revenue_HW!V56,Revenue_HW!V61,Revenue_HW!V66,Revenue_HW!V71) -> 99 | ... AD37: =Revenue_HW!AD$14-SUM(Revenue_HW!AD51,Revenue_HW!AD56,Revenue_HW!AD61,Revenue_HW!AD66,Revenue_HW!AD71) -> 1415
D38: 단위당 수출비 | I38: =P38 -> 7.6697026 | O38: =O36/O37 -> 5.5497679 | P38: 7.6697026 | Q38: 7.6697026 | R38: 7.6697026 | S38: 7.6697026 | T38: 7.6697026 | U38: 7.6697026 | V38: 7.6697026 | W38: 7.6697026 | X38: 7.6697026 | Y38: =Y36/Y37 -> 7.6697026 | Z38: =Z36/Z37 -> 7.1095126 | AA38: =$I38*(1+'Key Assumption'!AB$13) -> 7.7924178 | AB38: =$AA38*(1+'Key Assumption'!AC$13) -> 7.9482662 | AC38: =$AA38*(1+'Key Assumption'!AD$13) -> 7.9248889 | AD38: =$AA38*(1+'Key Assumption'!AE$13) -> 7.9326813
C39: 소모품비 | L39: 7.080267 | M39: 9.242727 | N39: 5.830809 | O39: 5.558981 | P39: 0.423333 | Q39: 0.423333 | R39: 0.423333 | S39: 0.423333 | T39: 0.423333 | U39: 0.423333 | V39: 0.423333 | W39: 0.423333 | X39: 0.423333 | Y39: =SUM(P39:X39) -> 3.809997 | Z39: =SUM(O39,Y39) -> 9.368978
D40: % of Revenue | O40: =O39/Revenue_HW!O$6 -> 7.3219548e-05 | P40: =P39/Revenue_HW!P$6 -> 1.3574552e-05 | Q40: =Q39/Revenue_HW!Q$6 -> 1.491207e-05 | R40: =R39/Revenue_HW!R$6 -> 1.4000737e-05 | S40: =S39/Revenue_HW!S$6 -> 1.5392624e-05 | T40: =T39/Revenue_HW!T$6 -> 1.4360198e-05 | U40: =U39/Revenue_HW!U$6 -> 1.5102768e-05 | V40: =V39/Revenue_HW!V$6 -> 1.5137427e-05 | ... Z40: =Z39/Revenue_HW!Z$6 -> 2.8147868e-05
C41: 수선비 | L41: 0 | M41: 0 | N41: 0 | O41: 0 | P41: 0 | Q41: 0 | R41: 0 | S41: 0 | T41: 0 | U41: 0 | V41: 0 | W41: 0 | X41: 0 | Y41: =SUM(P41:X41) -> 0 | Z41: =SUM(O41,Y41) -> 0 | AA41: =Revenue_HW!AA$6*AA42 -> 0 | AB41: =Revenue_HW!AB$6*AB42 -> 0 | AC41: =Revenue_HW!AC$6*AC42 -> 0 | AD41: =Revenue_HW!AD$6*AD42 -> 0
D42: % of Revenue | O42: =O41/Revenue_HW!O$6 -> 0 | P42: =P41/Revenue_HW!P$6 -> 0 | Q42: =Q41/Revenue_HW!Q$6 -> 0 | R42: =R41/Revenue_HW!R$6 -> 0 | S42: =S41/Revenue_HW!S$6 -> 0 | T42: =T41/Revenue_HW!T$6 -> 0 | U42: =U41/Revenue_HW!U$6 -> 0 | V42: =V41/Revenue_HW!V$6 -> 0 | ... Z42: =Z41/Revenue_HW!Z$6 -> 0 | AA42: =Z42 -> 0 | AB42: =AA42 -> 0 | AC42: =AB42 -> 0 | AD42: =AC42 -> 0
C43: 간접비배부액 | L43: -21.492759 | M43: 16.068537 | N43: 109.25957 | O43: -29.104887
C44: Stand-alone Cost | O44: 9.5802783 | P44: =O44/3 -> 3.1934261 | Q44: =P44 -> 3.1934261 | R44: =Q44 -> 3.1934261 | S44: =R44 -> 3.1934261 | T44: =S44 -> 3.1934261 | U44: =T44 -> 3.1934261 | V44: =U44 -> 3.1934261 | W44: =V44 -> 3.1934261 | X44: =W44 -> 3.1934261 | Y44: =SUM(P44:X44) -> 28.740835 | Z44: =Y44+O44 -> 38.321113 | AA44: =Z44*(1+'Key Assumption'!AB$13) -> 38.934251 | AB44: =AA44*(1+'Key Assumption'!AC$13) -> 39.712936 | AC44: =AB44*(1+'Key Assumption'!AD$13) -> 40.388056 | AD44: =AC44*(1+'Key Assumption'!AE$13) -> 41.115041
B46: 4. 고정비
L48: 2021A | M48: 2022A | N48: 2023A | O48: 24.3m(A) | P48: 4월 | Q48: 5월 | R48: 6월 | S48: 7월 | T48: 8월 | U48: 9월 | V48: 10월 | W48: 11월 | X48: 12월 | Y48: 24.9m(E) | Z48: 2024F | AA48: 2025F | AB48: 2026F | AC48: 2027F | AD48: 2028F
B49: 고정비 | L49: =SUM(L51,L52,L53,L54,L55,L56,L57,L58) -> 13703.115 | M49: =SUM(M51,M52,M53,M54,M55,M56,M57,M58) -> 16132.914 | N49: =SUM(N51,N52,N53,N54,N55,N56,N57,N58) -> 11764.77 | O49: =SUM(O51,O52,O53,O54,O55,O56,O57,O59) -> 2357.4464 | P49: =SUM(P51,P52,P53,P54,P55,P56,P57,P59) -> 1032.0184 | Q49: =SUM(Q51,Q52,Q53,Q54,Q55,Q56,Q57,Q59) -> 1032.0184 | R49: =SUM(R51,R52,R53,R54,R55,R56,R57,R59) -> 1032.0184 | S49: =SUM(S51,S52,S53,S54,S55,S56,S57,S59) -> 1032.0184 | T49: =SUM(T51,T52,T53,T54,T55,T56,T57,T59) -> 1032.0184 | U49: =SUM(U51,U52,U53,U54,U55,U56,U57,U59) -> 1032.0184 | V49: =SUM(V51,V52,V53,V54,V55,V56,V57,V59) -> 1032.0184 | ... AD49: =SUM(AD51,AD52,AD53,AD54,AD55,AD56,AD57,AD59) -> 12695.643
B50: % of revenue | L50: =IFERROR(L49/Revenue_HW!L$6,"-") -> - | M50: =IFERROR(M49/Revenue_HW!M$6,"-") -> - | N50: =IFERROR(N49/Revenue_HW!N$6,"-") -> - | O50: =IFERROR(O49/Revenue_HW!O$6,"-") -> 0.031050864 | P50: =IFERROR(P49/Revenue_HW!P$6,"-") -> 0.033092594 | Q50: =IFERROR(Q49/Revenue_HW!Q$6,"-") -> 0.03635325 | R50: =IFERROR(R49/Revenue_HW!R$6,"-") -> 0.034131565 | S50: =IFERROR(S49/Revenue_HW!S$6,"-") -> 0.037524764 | ... AD50: =IFERROR(AD49/Revenue_HW!AD$6,"-") -> 0.029432541
C51: 유형자산 감가상각비 | L51: 216.70209 | M51: 253.27451 | N51: 193.03391 | O51: 0 | P51: =CAPEX_HW!P16 -> 0 | Q51: =CAPEX_HW!Q16 -> 0 | R51: =CAPEX_HW!R16 -> 0 | S51: =CAPEX_HW!S16 -> 0 | T51: =CAPEX_HW!T16 -> 0 | U51: =CAPEX_HW!U16 -> 0 | V51: =CAPEX_HW!V16 -> 0 | W51: =CAPEX_HW!W16 -> 0 | ... AD51: =CAPEX_HW!AD16 -> 0
C52: 무형자산상각비 | L52: 303.38451 | M52: 244.16943 | N52: 250.27192 | O52: 457.46185 | P52: =CAPEX_HW!P19 -> 152.48728 | Q52: =CAPEX_HW!Q19 -> 152.48728 | R52: =CAPEX_HW!R19 -> 152.48728 | S52: =CAPEX_HW!S19 -> 152.48728 | T52: =CAPEX_HW!T19 -> 152.48728 | U52: =CAPEX_HW!U19 -> 152.48728 | V52: =CAPEX_HW!V19 -> 152.48728 | W52: =CAPEX_HW!W19 -> 152.48728 | ... AD52: =CAPEX_HW!AD19 -> 1963.2585
C53: 기술개발비 | L53: 8376.3394 | M53: 8262.5162 | N53: 5639.7999 | O53: 920.38761 | P53: 345.36825 | Q53: 345.36825 | R53: 345.36825 | S53: 345.36825 | T53: 345.36825 | U53: 345.36825 | V53: 345.36825 | W53: 345.36825 | X53: 345.36825 | Y53: =SUM(P53:X53) -> 3108.3142 | Z53: =SUM(O53,Y53) -> 4028.7018 | AA53: =Z53*(1+'Key Assumption'!AB$13) -> 4093.1611 | AB53: =AA53*(1+'Key Assumption'!AC$13) -> 4175.0243 | AC53: =AB53*(1+'Key Assumption'!AD$13) -> 4245.9997 | AD53: =AC53*(1+'Key Assumption'!AE$13) -> 4322.4277
C54: 광고선전비 | L54: 1031.0789 | M54: 1615.2616 | N54: 64.808279 | O54: 78.95391 | P54: 135.04167 | Q54: 135.04167 | R54: 135.04167 | S54: 135.04167 | T54: 135.04167 | U54: 135.04167 | V54: 135.04167 | W54: 135.04167 | X54: 135.04167 | Y54: =SUM(P54:X54) -> 1215.375 | Z54: =SUM(O54,Y54) -> 1294.3289 | AA54: =Z54*(1+'Key Assumption'!AB$13) -> 1315.0382 | AB54: =AA54*(1+'Key Assumption'!AC$13) -> 1341.3389 | AC54: =AB54*(1+'Key Assumption'!AD$13) -> 1364.1417 | AD54: =AC54*(1+'Key Assumption'!AE$13) -> 1388.6962
C55: 지급수수료 | L55: 1735.2413 | M55: 1845.7453 | N55: 1343.8865 | O55: 291.66618 | P55: 127.88751 | Q55: 127.88751 | R55: 127.88751 | S55: 127.88751 | T55: 127.88751 | U55: 127.88751 | V55: 127.88751 | W55: 127.88751 | X55: 127.88751 | Y55: =SUM(P55:X55) -> 1150.9876 | Z55: =SUM(O55,Y55) -> 1442.6538 | AA55: =Z55*(1+'Key Assumption'!AB$13) -> 1465.7363 | AB55: =AA55*(1+'Key Assumption'!AC$13) -> 1495.051 | AC55: =AB55*(1+'Key Assumption'!AD$13) -> 1520.4669 | AD55: =AC55*(1+'Key Assumption'!AE$13) -> 1547.8353
C56: 대손상각비(환입) | L56: -260.4869 | M56: 1059.4279 | N56: 1165.3208 | O56: -187.31215 | P56: 0 | Q56: 0 | R56: 0 | S56: 0 | T56: 0 | U56: 0 | V56: 0 | W56: 0 | X56: 0 | Y56: =SUM(P56:X56) -> 0 | Z56: =SUM(O56,Y56) -> -187.31215 | AA56: 0 | AB56: 0 | AC56: 0 | AD56: 0
C57: 기타판관비 | L57: 1323.738 | M57: 1928.9888 | N57: 2154.2561 | O57: 595.01217 | P57: 204.14141 | Q57: =P57 -> 204.14141 | R57: =Q57 -> 204.14141 | S57: =R57 -> 204.14141 | T57: =S57 -> 204.14141 | U57: =T57 -> 204.14141 | V57: =U57 -> 204.14141 | W57: =V57 -> 204.14141 | X57: =W57 -> 204.14141 | Y57: =SUM(P57:X57) -> 1837.2727 | Z57: =SUM(O57,Y57) -> 2432.2848 | AA57: =Z57*(1+'Key Assumption'!AB$13) -> 2471.2014 | AB57: =AA57*(1+'Key Assumption'!AC$13) -> 2520.6254 | AC57: =AB57*(1+'Key Assumption'!AD$13) -> 2563.476 | AD57: =AC57*(1+'Key Assumption'!AE$13) -> 2609.6186
C58: 간접비배부액 | L58: 977.11796 | M58: 923.53045 | N58: 953.39243 | O58: 320.39729
C59: Stand-alone Cost | O59: 201.27684 | P59: =O59/3 -> 67.092281 | Q59: =P59 -> 67.092281 | R59: =Q59 -> 67.092281 | S59: =R59 -> 67.092281 | T59: =S59 -> 67.092281 | U59: =T59 -> 67.092281 | V59: =U59 -> 67.092281 | W59: =V59 -> 67.092281 | X59: =W59 -> 67.092281 | Y59: =SUM(P59:X59) -> 603.83053 | Z59: =Y59+O59 -> 805.10737 | AA59: =Z59*(1+'Key Assumption'!AB$13) -> 817.98909 | AB59: =AA59*(1+'Key Assumption'!AC$13) -> 834.34887 | AC59: =AB59*(1+'Key Assumption'!AD$13) -> 848.5328 | AD59: =AC59*(1+'Key Assumption'!AE$13) -> 863.80639
P161: =O161/3 -> 0 | Q161: =P161 -> 0 | R161: =Q161 -> 0 | S161: =R161 -> 0 | T161: =S161 -> 0 | U161: =T161 -> 0 | V161: =U161 -> 0 | W161: =V161 -> 0 | X161: =W161 -> 0

Sheet CAPEX_HW
A1: =MID(CELL("filename",A1),FIND("]",CELL("filename",A1))+1,255) -> CAPEX_HW
B3: 1. Summary
L5: 2021A | M5: 2022A | N5: 2023A | O5: 24.3m(A) | P5: 4월 | Q5: 5월 | R5: 6월 | S5: 7월 | T5: 8월 | U5: 9월 | V5: 10월 | W5: 11월 | X5: 12월 | Y5: 24.9m(E) | Z5: 2024F | AA5: 2025F | AB5: 2026F | AC5: 2027F | AD5: 2028F
B6: CAPEX | Y6: =Y7+Y9 -> 1372.3855 | AA6: =AA7+AA9 -> 1859.125 | AB6: =AB7+AB9 -> 1896.3075 | AC6: =AC7+AC9 -> 1928.5447 | AD6: =AD7+AD9 -> 1963.2585
C7: 유형자산 | Y7: =Y8 -> 0 | AA7: =AA8 -> 0 | AB7: =AB8 -> 0 | AC7: =AC8 -> 0 | AD7: =AD8 -> 0
D8: 판관비 | Y8: =Y16 -> 0 | AA8: =AA16 -> 0 | AB8: =AB16 -> 0 | AC8: =AC16 -> 0 | AD8: =AD16 -> 0
C9: 무형자산 | Y9: =Y10 -> 1372.3855 | AA9: =AA10 -> 1859.125 | AB9: =AB10 -> 1896.3075 | AC9: =AC10 -> 1928.5447 | AD9: =AD10 -> 1963.2585
D10: 판관비 | Y10: =Y19 -> 1372.3855 | AA10: =AA19 -> 1859.125 | AB10: =AB19 -> 1896.3075 | AC10: =AC19 -> 1928.5447 | AD10: =AD19 -> 1963.2585
L12: 2021A | M12: 2022A | N12: 2023A | O12: 24.3m(A) | P12: 4월 | Q12: 5월 | R12: 6월 | S12: 7월 | T12: 8월 | U12: 9월 | V12: 10월 | W12: 11월 | X12: 12월 | Y12: 24.9m(E) | Z12: 2024F | AA12: 2025F | AB12: 2026F | AC12: 2027F | AD12: 2028F
B13: D&A | O13: =O14+O17 -> 457.46185 | P13: =P14+P17 -> 152.48728 | Q13: =Q14+Q17 -> 152.48728 | R13: =R14+R17 -> 152.48728 | S13: =S14+S17 -> 152.48728 | T13: =T14+T17 -> 152.48728 | U13: =U14+U17 -> 152.48728 | V13: =V14+V17 -> 152.48728 | ... AD13: =AD14+AD17 -> 1963.2585
C14: 유형자산 | O14: =O15+O16 -> 0 | P14: =P15+P16 -> 0 | Q14: =Q15+Q16 -> 0 | R14: =R15+R16 -> 0 | S14: =S15+S16 -> 0 | T14: =T15+T16 -> 0 | U14: =U15+U16 -> 0 | V14: =V15+V16 -> 0 | ... AD14: =AD15+AD16 -> 0
D15: 제조원가 | O15: 0 | P15: =$O15/3 -> 0 | Q15: =$O15/3 -> 0 | R15: =$O15/3 -> 0 | S15: =$O15/3 -> 0 | T15: =$O15/3 -> 0 | U15: =$O15/3 -> 0 | V15: =$O15/3 -> 0 | W15: =$O15/3 -> 0 | X15: =$O15/3 -> 0 | Y15: =SUM(P15:X15) -> 0 | Z15: =O15+Y15 -> 0
D16: 판관비 | O16: 0 | P16: =$O16/3 -> 0 | Q16: =$O16/3 -> 0 | R16: =$O16/3 -> 0 | S16: =$O16/3 -> 0 | T16: =$O16/3 -> 0 | U16: =$O16/3 -> 0 | V16: =$O16/3 -> 0 | W16: =$O16/3 -> 0 | X16: =$O16/3 -> 0 | Y16: =SUM(P16:X16) -> 0 | Z16: =O16+Y16 -> 0
C17: 무형자산 | O17: =O18+O19 -> 457.46185 | P17: =P18+P19 -> 152.48728 | Q17: =Q18+Q19 -> 152.48728 | R17: =R18+R19 -> 152.48728 | S17: =S18+S19 -> 152.48728 | T17: =T18+T19 -> 152.48728 | U17: =U18+U19 -> 152.48728 | V17: =V18+V19 -> 152.48728 | ... AD17: =AD18+AD19 -> 1963.2585
D18: 제조원가 | O18: 0 | P18: =$O18/3 -> 0 | Q18: =$O18/3 -> 0 | R18: =$O18/3 -> 0 | S18: =$O18/3 -> 0 | T18: =$O18/3 -> 0 | U18: =$O18/3 -> 0 | V18: =$O18/3 -> 0 | W18: =$O18/3 -> 0 | X18: =$O18/3 -> 0 | Y18: =SUM(P18:X18) -> 0 | Z18: =O18+Y18 -> 0
D19: 판관비 | O19: ='SG&A_HW'!O52 -> 457.46185 | P19: =$O19/3 -> 152.48728 | Q19: =$O19/3 -> 152.48728 | R19: =$O19/3 -> 152.48728 | S19: =$O19/3 -> 152.48728 | T19: =$O19/3 -> 152.48728 | U19: =$O19/3 -> 152.48728 | V19: =$O19/3 -> 152.48728 | W19: =$O19/3 -> 152.48728 | X19: =$O19/3 -> 152.48728 | Y19: =SUM(P19:X19) -> 1372.3855 | Z19: =O19+Y19 -> 1829.8474 | AA19: =Z19*(1+'Key Assumption'!AB$13) -> 1859.125 | AB19: =AA19*(1+'Key Assumption'!AC$13) -> 1896.3075 | AC19: =AB19*(1+'Key Assumption'!AD$13) -> 1928.5447 | AD19: =AC19*(1+'Key Assumption'!AE$13) -> 1963.2585

Sheet NWC_연결
A1: =MID(CELL("filename",A1),FIND("]",CELL("filename",A1))+1,255) -> NWC_연결
B3: 1. Summary
K5: 2020A | L5: 2021A | M5: 2022A | N5: 2023A | O5: 24.3m(A) | P5: 24.9m(E) | Q5: 2024F | R5: 2025F | S5: 2026F | T5: 2027F | U5: 2028F | V5: Terminal
B6: NWC변동 | L6: =L7-K7 -> -47572.091 | M6: =M7-L7 -> -29183.721 | N6: =N7-M7 -> -12889.66 | O6: =O7-N7 -> 3792.0324 | P6: =P7-O7 -> -16257.034 | Q6: =Q7-N7 -> -12465.001 | R6: =R7-Q7 -> -9574.7874 | S6: =S7-R7 -> 20834.399 | T6: =T7-S7 -> 20951.381 | U6: =U7-T7 -> 20590.111 | V6: =V7-U7 -> 1079.4051
B7: NWC | K7: =K8-K36 -> 265190.38 | L7: =L8-L36 -> 217618.29 | M7: =M8-M36 -> 188434.57 | N7: =N8-N36 -> 175544.91 | O7: =O8-O36 -> 179336.94 | P7: =P8-P36 -> 163079.91 | Q7: =Q8-Q36 -> 163079.91 | R7: =R8-R36 -> 153505.12 | ... V7: =V8-V36 -> 216960.42
B8: 운전자산 | K8: =K9+K12+K21+K27+K33+K24+K18+K30+K15 -> 310760.74 | L8: =L9+L12+L21+L27+L33+L24+L18+L30+L15 -> 296182.39 | M8: =M9+M12+M21+M27+M33+M24+M18+M30+M15 -> 275437.12 | N8: =N9+N12+N21+N27+N33+N24+N18+N30+N15 -> 224805.55 | O8: =O9+O12+O21+O27+O33+O24+O18+O30+O15 -> 225839.03 | P8: =P9+P12+P21+P27+P33+P24+P18+P30+P15 -> 223065.66 | Q8: =Q9+Q12+Q21+Q27+Q33+Q24+Q18+Q30+Q15 -> 223065.66 | R8: =R9+R12+R21+R27+R33+R24+R18+R30+R15 -> 209778.16 | ... V8: =V9+V12+V21+V27+V33+V24+V18+V30+V15 -> 296341.49
C9: 매출채권 | K9: 105441.93 | L9: 101196.2 | M9: 84333.457 | N9: 76242.913 | O9: 82165.751 | P9: =Q9 -> 84100.814 | Q9: =Q46/Q10 -> 84100.814 | R9: =R46/R10 -> 80362.917 | S9: =S46/S10 -> 90789.486 | T9: =T46/T10 -> 101243.86 | U9: =U46/U10 -> 112067.99 | V9: =V46/V10 -> 112628.33
D10: 회전율 | L10: =L46/AVERAGE(K9:L9) -> 4.3810731 | M10: =M46/AVERAGE(L9:M9) -> 4.7504 | N10: =N46/AVERAGE(M9:N9) -> 5.2901355 | O10: =O46/AVERAGE(N9:O9)*4 -> 4.5308824 | Q10: =365/Q11 -> 4.7786357 | R10: =365/R11 -> 4.7786357 | S10: =365/S11 -> 4.7786357 | T10: =365/T11 -> 4.7786357 | U10: =365/U11 -> 4.7786357 | V10: =365/V11 -> 4.7786357
D11: 회전기일 | H11: =AVERAGE(L11:N11) -> 76.381633 | L11: =365/L10 -> 83.312922 | M11: =365/M10 -> 76.835635 | N11: =365/N10 -> 68.996342 | O11: =365/O10 -> 80.558259 | Q11: =$H11 -> 76.381633 | R11: =$H11 -> 76.381633 | S11: =$H11 -> 76.381633 | T11: =$H11 -> 76.381633 | U11: =$H11 -> 76.381633 | V11: =$H11 -> 76.381633
C12: 원재료 | K12: 52516.678 | L12: 68062.259 | M12: 64500.431 | N12: 40453.078 | O12: 40726.626 | P12: =Q12 -> 48003.937 | Q12: =Q47/Q13 -> 48003.937 | R12: =R47/R13 -> 44523.417 | S12: =S47/S13 -> 50662.124 | T12: =T47/T13 -> 56752.095 | U12: =U47/U13 -> 62747.955 | V12: =V47/V13 -> 63061.695
D13: 회전율 | L13: =L47/AVERAGE(K12:L12) -> 6.8601768 | M13: =M47/AVERAGE(L12:M12) -> 5.4931822 | N13: =N47/AVERAGE(M12:N12) -> 6.6580802 | O13: =O47/AVERAGE(N12:O12)*4 -> 6.9132672 | Q13: =365/Q14 -> 6.2760702 | R13: =365/R14 -> 6.2760702 | S13: =365/S14 -> 6.2760702 | T13: =365/T14 -> 6.2760702 | U13: =365/U14 -> 6.2760702 | V13: =365/V14 -> 6.2760702
D14: 회전기일 | H14: =AVERAGE(L14:N14) -> 58.157412 | L14: =365/L13 -> 53.205626 | M14: =365/M13 -> 66.446003 | N14: =365/N13 -> 54.820607 | O14: =365/O13 -> 52.797034 | Q14: =$H14 -> 58.157412 | R14: =$H14 -> 58.157412 | S14: =$H14 -> 58.157412 | T14: =$H14 -> 58.157412 | U14: =$H14 -> 58.157412 | V14: =$H14 -> 58.157412
C15: 부재료 | K15: 96.095434 | L15: 141.62016 | M15: 171.84097 | N15: 484.84449 | O15: 215.06552 | P15: =Q15 -> 166.46405 | Q15: =Q47/Q16 -> 166.46405 | R15: =R47/R16 -> 154.39459 | S15: =S47/S16 -> 175.68189 | T15: =T47/T16 -> 196.80019 | U15: =U47/U16 -> 217.59213 | V15: =V47/V16 -> 218.68009
D16: 회전율 | L16: =L47/AVERAGE(K15:L15) -> 3479.7583 | M16: =M47/AVERAGE(L15:M15) -> 2323.0664 | N16: =N47/AVERAGE(M15:N15) -> 1064.115 | O16: =O47/AVERAGE(N15:O15)*4 -> 801.84162 | Q16: =365/Q17 -> 1809.8567 | R16: =365/R17 -> 1809.8567 | S16: =365/S17 -> 1809.8567 | T16: =365/T17 -> 1809.8567 | U16: =365/U17 -> 1809.8567 | V16: =365/V17 -> 1809.8567
D17: 회전기일 | H17: =AVERAGE(L17:N17) -> 0.20167343 | L17: =365/L16 -> 0.10489234 | M17: =365/M16 -> 0.15711992 | N17: =365/N16 -> 0.34300802 | O17: =365/O16 -> 0.45520211 | Q17: =$H$17 -> 0.20167343 | R17: =$H$17 -> 0.20167343 | S17: =$H$17 -> 0.20167343 | T17: =$H$17 -> 0.20167343 | U17: =$H$17 -> 0.20167343 | V17: =$H$17 -> 0.20167343
C18: 미착품 | K18: 3737.3757 | L18: 11678.957 | M18: 3744.5044 | N18: 3017.3541 | O18: 9552.1099 | P18: =Q18 -> 4970.4511 | Q18: =Q47/Q19 -> 4970.4511 | R18: =R47/R19 -> 4610.069 | S18: =S47/S19 -> 5245.6866 | T18: =T47/T19 -> 5876.2579 | U18: =U47/U19 -> 6497.0846 | V18: =V47/V19 -> 6529.57
D19: 회전율 | L19: =L47/AVERAGE(K18:L18) -> 53.656913 | M19: =M47/AVERAGE(L18:M18) -> 47.213203 | N19: =N47/AVERAGE(M18:N18) -> 103.34272 | O19: =O47/AVERAGE(N18:O18)*4 -> 44.649237 | Q19: =365/Q20 -> 60.613428 | R19: =365/R20 -> 60.613428 | S19: =365/S20 -> 60.613428 | T19: =365/T20 -> 60.613428 | U19: =365/U20 -> 60.613428 | V19: =365/V20 -> 60.613428
D20: 회전기일 | H20: =AVERAGE(L20:N20) -> 6.021768 | L20: =365/L19 -> 6.8024785 | M20: =365/M19 -> 7.7308884 | N20: =365/N19 -> 3.5319371 | O20: =365/O19 -> 8.1748317 | Q20: =$H20 -> 6.021768 | R20: =$H20 -> 6.021768 | S20: =$H20 -> 6.021768 | T20: =$H20 -> 6.021768 | U20: =$H20 -> 6.021768 | V20: =$H20 -> 6.021768
C21: 재공품(국내) | K21: 17540.897 | L21: 19044.333 | M21: 15176.007 | N21: 12580.186 | O21: 7742.0806
D22: 회전율 | L22: =L51/AVERAGE(K21:L21) -> 18.458449 | M22: =M51/AVERAGE(L21:M21) -> 18.223202 | N22: =N51/AVERAGE(M21:N21) -> 22.881 | O22: =O51/AVERAGE(N21:O21)*4 -> 24.392914 | Q22: =365/Q23 -> 19.639264 | R22: =365/R23 -> 19.639264 | S22: =365/S23 -> 19.639264 | T22: =365/T23 -> 19.639264 | U22: =365/U23 -> 19.639264 | V22: =365/V23 -> 19.639264
D23: 회전기일 | H23: =AVERAGE(L23:N23) -> 18.585218 | L23: =365/L22 -> 19.774142 | M23: =365/M22 -> 20.029411 | N23: =365/N22 -> 15.9521 | O23: =365/O22 -> 14.963362 | Q23: =$H23 -> 18.585218 | R23: =$H23 -> 18.585218 | S23: =$H23 -> 18.585218 | T23: =$H23 -> 18.585218 | U23: =$H23 -> 18.585218 | V23: =$H23 -> 18.585218
C24: 재공품(중국-강소) | K24: 1566.3394 | L24: 1674.0061 | M24: 4865.4949 | N24: 6270.0368 | O24: 4419.4443 | P24: =Q24 -> 4020.1699 | Q24: =Q52/Q25 -> 4020.1699 | R24: =R52/R25 -> 4179.8511 | S24: =S52/S25 -> 4923.8768 | T24: =T52/T25 -> 5860.1216 | U24: =U52/U25 -> 6339.5568 | V24: =V52/V25 -> 6371.2546
D25: 회전율 | L25: =L52/AVERAGE(K24:L24) -> 29.558277 | M25: =M52/AVERAGE(L24:M24) -> 11.868242 | N25: =N52/AVERAGE(M24:N24) -> 5.2641654 | O25: =O52/AVERAGE(N24:O24)*4 -> 7.2909477 | Q25: =365/Q26 -> 9.7385654 | R25: =365/R26 -> 9.7385654 | S25: =365/S26 -> 9.7385654 | T25: =365/T26 -> 9.7385654 | U25: =365/U26 -> 9.7385654 | V25: =365/V26 -> 9.7385654
D26: 회전기일 | H26: =AVERAGE(L26:N26) -> 37.479853 | L26: =365/L25 -> 12.348487 | M26: =365/M25 -> 30.754345 | N26: =365/N25 -> 69.336727 | O26: =365/O25 -> 50.062079 | Q26: =$H26 -> 37.479853 | R26: =$H26 -> 37.479853 | S26: =$H26 -> 37.479853 | T26: =$H26 -> 37.479853 | U26: =$H26 -> 37.479853 | V26: =$H26 -> 37.479853
C27: 반제품 | K27: 63884.109 | L27: 65151.578 | M27: 72333.673 | N27: 54689.815 | O27: 57389.977 | P27: =Q27 -> 52881.256 | Q27: =Q47/Q28 -> 52881.256 | R27: =R47/R28 -> 49047.106 | S27: =S47/S28 -> 55809.521 | T27: =T47/T28 -> 62518.249 | U27: =U47/U28 -> 69123.302 | V27: =V47/V28 -> 69468.919
D28: 회전율 | L28: =L47/AVERAGE(K27:L27) -> 6.410574 | M28: =M47/AVERAGE(L27:M27) -> 5.2965027 | N28: =N47/AVERAGE(M27:N27) -> 5.5012573 | O28: =O47/AVERAGE(N27:O27)*4 -> 5.0072986 | Q28: =365/Q29 -> 5.6972187 | R28: =365/R29 -> 5.6972187 | S28: =365/S29 -> 5.6972187 | T28: =365/T29 -> 5.6972187 | U28: =365/U29 -> 5.6972187 | V28: =365/V29 -> 5.6972187
D29: 회전기일 | H29: =AVERAGE(L29:N29) -> 64.066349 | L29: =365/L28 -> 56.937179 | M29: =365/M28 -> 68.913398 | N29: =365/N28 -> 66.34847 | O29: =365/O28 -> 72.893596 | Q29: =$H29 -> 64.066349 | R29: =$H29 -> 64.066349 | S29: =$H29 -> 64.066349 | T29: =$H29 -> 64.066349 | U29: =$H29 -> 64.066349 | V29: =$H29 -> 64.066349
C30: 제품 | K30: 61956.738 | L30: 26513.722 | M30: 27572.659 | N30: 28473.157 | O30: 22502.016 | P30: =Q30 -> 26254.388 | Q30: =Q47/Q31 -> 26254.388 | R30: =R47/R31 -> 24350.816 | S30: =S47/S31 -> 27708.208 | T30: =T47/T31 -> 31038.944 | U30: =U47/U31 -> 34318.209 | V30: =V47/V31 -> 34489.8
D31: 회전율 | L31: =L47/AVERAGE(K30:L30) -> 9.3499324 | M31: =M47/AVERAGE(L30:M30) -> 13.463482 | N31: =N47/AVERAGE(M30:N30) -> 12.468172 | O31: =O47/AVERAGE(N30:O30)*4 -> 11.009614 | Q31: =365/Q32 -> 11.475266 | R31: =365/R32 -> 11.475266 | S31: =365/S32 -> 11.475266 | T31: =365/T32 -> 11.475266 | U31: =365/U32 -> 11.475266 | V31: =365/V32 -> 11.475266
D32: 회전기일 | H32: =AVERAGE(L32:N32) -> 31.807542 | L32: =365/L31 -> 39.037715 | M32: =365/M31 -> 27.110372 | N32: =365/N31 -> 29.27454 | O32: =365/O31 -> 33.152842 | Q32: =$H32 -> 31.807542 | R32: =$H32 -> 31.807542 | S32: =$H32 -> 31.807542 | T32: =$H32 -> 31.807542 | U32: =$H32 -> 31.807542 | V32: =$H32 -> 31.807542
C33: 미수금 | K33: 4020.5785 | L33: 2719.7137 | M33: 2739.049 | N33: 2594.1682 | O33: 1125.9602 | P33: =Q33 -> 2668.1804 | Q33: =Q46/Q34 -> 2668.1804 | R33: =R46/R34 -> 2549.592 | S33: =S46/S34 -> 2880.385 | T33: =T46/T34 -> 3212.0603 | U33: =U46/U34 -> 3555.4663 | V33: =V46/V34 -> 3573.2436
D34: 회전율 | L34: =L46/AVERAGE(K33:L33) -> 134.3112 | M34: =M46/AVERAGE(L33:M33) -> 161.45419 | N34: =N46/AVERAGE(M33:N33) -> 159.27924 | O34: =O46/AVERAGE(N33:O33)*4 -> 192.93179 | Q34: =365/Q35 -> 150.62218 | R34: =365/R35 -> 150.62218 | S34: =365/S35 -> 150.62218 | T34: =365/T35 -> 150.62218 | U34: =365/U35 -> 150.62218 | V34: =365/V35 -> 150.62218
D35: 회전기일 | H35: =AVERAGE(L35:N35) -> 2.4232819 | L35: =365/L34 -> 2.7175693 | M35: =365/M34 -> 2.2607032 | N35: =365/N34 -> 2.291573 | O35: =365/O34 -> 1.8918603 | Q35: =$H35 -> 2.4232819 | R35: =$H35 -> 2.4232819 | S35: =$H35 -> 2.4232819 | T35: =$H35 -> 2.4232819 | U35: =$H35 -> 2.4232819 | V35: =$H35 -> 2.4232819
B36: 운전부채 | K36: =K37+K40+K43 -> 45570.358 | L36: =L37+L40+L43 -> 78564.102 | M36: =M37+M40+M43 -> 87002.549 | N36: =N37+N40+N43 -> 49260.644 | O36: =O37+O40+O43 -> 46502.089 | P36: =P37+P40+P43 -> 59985.753 | Q36: =Q37+Q40+Q43 -> 59985.753 | R36: =R37+R40+R43 -> 56273.043 | ... V36: =V37+V40+V43 -> 79381.074
C37: 매입채무 | K37: 22456.106 | L37: 38940.428 | M37: 27509.431 | N37: 22185.138 | O37: 20759.996 | P37: =Q37 -> 23759.774 | Q37: =Q47/Q38 -> 23759.774 | R37: =R47/R38 -> 22037.074 | S37: =S47/S38 -> 25075.456 | T37: =T47/T38 -> 28089.716 | U37: =U47/U38 -> 31057.395 | V37: =V47/V38 -> 31212.682
D38: 회전율 | L38: =L47/AVERAGE(K37:L37) -> 13.472956 | M38: =M47/AVERAGE(L37:M37) -> 10.958504 | N38: =N47/AVERAGE(M37:N37) -> 14.061675 | O38: =O47/AVERAGE(N37:O37)*4 -> 13.068232 | Q38: =365/Q39 -> 12.68009 | R38: =365/R39 -> 12.68009 | S38: =365/S39 -> 12.68009 | T38: =365/T39 -> 12.68009 | U38: =365/U39 -> 12.68009 | V38: =365/V39 -> 12.68009
D39: 회전기일 | H39: =AVERAGE(L39:N39) -> 28.785284 | L39: =365/L38 -> 27.091307 | M39: =365/M38 -> 33.307467 | N39: =365/N38 -> 25.957078 | O39: =365/O38 -> 27.930327 | Q39: =$H39 -> 28.785284 | R39: =$H39 -> 28.785284 | S39: =$H39 -> 28.785284 | T39: =$H39 -> 28.785284 | U39: =$H39 -> 28.785284 | V39: =$H39 -> 28.785284
C40: 미지급금 | K40: 12699.359 | L40: 16395.281 | M40: 25943.583 | N40: 3065.4381 | O40: 2470.414 | P40: =Q40 -> 13540.206 | Q40: =Q47/Q41 -> 13540.206 | R40: =R47/R41 -> 12558.475 | S40: =S47/S41 -> 14289.986 | T40: =T47/T41 -> 16007.75 | U40: =U47/U41 -> 17698.97 | V40: =V47/V41 -> 17787.464
D41: 회전율 | L41: =L47/AVERAGE(K40:L40) -> 28.431107 | M41: =M47/AVERAGE(L40:M40) -> 17.199115 | N41: =N47/AVERAGE(M40:N40) -> 24.088675 | O41: =O47/AVERAGE(N40:O40)*4 -> 101.37861 | Q41: =365/Q42 -> 22.25048 | R41: =365/R42 -> 22.25048 | S41: =365/S42 -> 22.25048 | T41: =365/T42 -> 22.25048 | U41: =365/U42 -> 22.25048 | V41: =365/V42 -> 22.25048
