Workbook

Sheet Report
B2: 적용환율 : | D2: 1 USD k = | E2: =1131.6/10^3 -> 1.1316
B3: Multiples based on available LTM financials; EV/EBIT over 40x, EV/EBITDA over 30x, P/E over 30x are classified as outliers and excluded from calculation of mean and median
B5: 1. 하이엔텍
B7: (USD m) | G7: Implied EV | H7: Implied Equity Value | J7: Historic
B8: Date | C8: Target | D8: Bidder | E8: Deal Value | F8: % Stake | J8: EV/EBITDA | K8: P/E | L8: P/B
B9: Korea
B10: =Transaction!D7 -> 2016.05 | C10: =Transaction!C7 -> 코오롱워터앤에너지 | D10: =Transaction!G7 -> SC PE | E10: =Transaction!M7/$E$2 -> 124361.27 | F10: =Transaction!L7 -> 0.6298 | G10: =Transaction!P7/$E$2 -> 72238.236 | H10: =Transaction!M7/$E$2 -> 124361.27 | J10: =Transaction!AA7 -> 6.6280923 | K10: =Transaction!AE7 -> 18.828503 | L10: =Transaction!AF7 -> 1.606883
B11: =Transaction!D8 -> 2018.06 | C11: =Transaction!C8 -> TSK워터 | D11: =Transaction!G8 -> 태영건설 | E11: =Transaction!M8/$E$2 -> 441852.24 | F11: =Transaction!L8 -> 0.24999876 | G11: =Transaction!P8/$E$2 -> 515981.19 | H11: =Transaction!M8/$E$2 -> 441852.24 | J11: =Transaction!AA8 -> 7.1405148 | K11: =Transaction!AE8 -> 14.443424 | L11: =Transaction!AF8 -> 2.7755315
B12: =Transaction!D15 -> 2018.12 | C12: =Transaction!C15 -> WIK그린 | D12: =Transaction!G15 -> SC PE | E12: =Transaction!M15/$E$2 -> 66277.837 | F12: =Transaction!L15 -> 1 | G12: =Transaction!P15/$E$2 -> 63880.4 | H12: =Transaction!M15/$E$2 -> 66277.837 | J12: =Transaction!AA15 -> 13.273734 | K12: =Transaction!AE15 -> 19.627495 | L12: =Transaction!AF15 -> 2.0439125
B13: =Transaction!D16 -> 2019.05 | C13: =Transaction!C16 -> 인선이엔티 | D13: =Transaction!G16 -> IS 동서 | E13: =Transaction!M16/$E$2 -> 370825.9 | F13: =Transaction!L16 -> 0.2383 | G13: =Transaction!P16/$E$2 -> 408401.99 | H13: =Transaction!M16/$E$2 -> 370825.9 | J13: =Transaction!AA16 -> 15.245795 | K13: =Transaction!AE16 -> 21.018255 | L13: =Transaction!AF16 -> 2.2447119
B14: =Transaction!D17 -> 2019.04 | C14: =Transaction!C17 -> 창원에너텍 | D14: =Transaction!G17 -> SK증권 PE | E14: =Transaction!M17/$E$2 -> 60091.905 | F14: =Transaction!L17 -> 1 | G14: =Transaction!P17/$E$2 -> 91267.19 | H14: =Transaction!M17/$E$2 -> 60091.905 | J14: =Transaction!AA17 -> 16.918537 | K14: NA | L14: =Transaction!AF17 -> 6.1887813
B15: =Transaction!D18 -> 2017.11 | C15: =Transaction!C18 -> 삼우그린 | D15: =Transaction!G18 -> 앵커 PE | E15: =Transaction!M18/$E$2 -> 50371.156 | F15: =Transaction!L18 -> 1 | G15: =Transaction!P18/$E$2 -> 35622.234 | H15: =Transaction!M18/$E$2 -> 50371.156 | J15: =Transaction!AA18 -> 11.17719 | K15: =Transaction!AE18 -> 22.239133 | L15: =Transaction!AF18 -> 2.9686205
B16: Mean | J16: =AVERAGE(J10:J15) -> 11.730644 | K16: =AVERAGE(K10:K15) -> 19.231362 | L16: =AVERAGE(L10:L15) -> 2.9714068
B17: Median | J17: =MEDIAN(J10:J15) -> 12.225462 | K17: =MEDIAN(K10:K15) -> 19.627495 | L17: =MEDIAN(L10:L15) -> 2.5101217
B18: Global
B19: =Transaction!D10 -> 2018.03 | C19: =Transaction!C10 -> FCC Aqualia | D19: =Transaction!G10 -> IFM Investors | E19: =Transaction!M10/$E$2 -> 2272.383 | F19: =Transaction!L10 -> 0.49 | G19: =Transaction!P10 -> 3156.8947 | H19: =Transaction!M10 -> 2571.4286 | J19: =Transaction!AA10 -> 10.905504 | K19: =Transaction!AE10 -> 0 | L19: =Transaction!AF10 -> 0
B20: =Transaction!D11 -> 2017.12 | C20: =Transaction!C11 -> Anglian Water Group | D20: =Transaction!G11 -> Dalmore Capital | E20: =Transaction!M11/$E$2 -> 3116.5312 | F20: =Transaction!L11 -> 0.15 | G20: =Transaction!P11 -> 13016.432 | H20: =Transaction!M11 -> 3526.6667 | J20: =Transaction!AA11 -> 15.521123 | K20: =Transaction!AE11 -> 0 | L20: =Transaction!AF11 -> 0
B21: =Transaction!D12 -> 2017.05 | C21: =Transaction!C12 -> Affinity Water | D21: =Transaction!G12 -> Allianz Capital Partners | E21: =Transaction!M12/$E$2 -> 886350.84 | F21: =Transaction!L12 -> 1 | G21: =Transaction!P12/$E$2 -> 1995169.4 | H21: =Transaction!M12/$E$2 -> 886350.84 | J21: =Transaction!AA12 -> 12.285164 | K21: =Transaction!AE12 -> 23.184433 | L21: =Transaction!AF12 -> 3.3057958
B22: =Transaction!D13 -> 2012.06 | C22: =Transaction!C13 -> Veolia Water Central | D22: =Transaction!G13 -> Morgan Stanley | E22: =Transaction!M13/$E$2 -> 2180714 | F22: =Transaction!L13 -> 0.9 | G22: =Transaction!P13/$E$2 -> 2923051.2 | H22: =Transaction!M13/$E$2 -> 2180714 | J22: =Transaction!AA13 -> 13.105763 | K22: NA | L22: =Transaction!AF13 -> 3.8815522
B23: Mean | J23: =AVERAGE(J19:J22) -> 12.954388 | K23: =AVERAGE(K19:K22) -> 7.7281443 | L23: =AVERAGE(L19:L22) -> 1.796837
B24: Median | J24: =MEDIAN(J19:J22) -> 12.695463 | K24: =MEDIAN(K19:K22) -> 0 | L24: =MEDIAN(L19:L22) -> 1.6528979
B26: Mean | J26: =AVERAGE(J19:J22,J10:J15) -> 12.220142 | K26: =AVERAGE(K19:K22,K10:K15) -> 14.917655 | L26: =AVERAGE(L19:L22,L10:L15) -> 2.5015789
B27: Median | J27: =MEDIAN(J19:J22,J10:J15) -> 12.695463 | K27: =MEDIAN(K19:K22,K10:K15) -> 19.227999 | L27: =MEDIAN(L19:L22,L10:L15) -> 2.5101217
B29: Merger Market에서“Industrial products and services ” 산업분류內 최근5개년간(2014.01.01 ~ 현재) 국내외 거래사례 중 수처리장 운영회사(또는 유관회사) 내에서, 재무정보가 공개되지 않은 사례, 영업이익 및 EBITDA가 (-)인 사례를 제외함.
B31: 2. 히타치
B33: (USD m) | G33: Implied EV | H33: Implied Equity Value | J33: Historic
B34: Date | C34: Target | D34: Bidder | E34: Deal Value | F34: % Stake | J34: EV/EBITDA | K34: P/E | L34: P/B
B35: Korea
B36: =Transaction!D26 -> 2017.09 | C36: =Transaction!C26 -> 한국종합기술 | D36: =Transaction!G26 -> 한국종합기술홀딩스 | E36: =Transaction!M26/$E$2 -> 86082.715 | F36: =Transaction!L26 -> 0.5201 | G36: =Transaction!P26/$E$2 -> 46230.297 | H36: =Transaction!M26/$E$2 -> 86082.715 | J36: =Transaction!AA26 -> 8.2963934 | K36: =Transaction!AE26 -> NA | L36: =Transaction!AF26 -> 0.85162015
B37: =Transaction!D27 -> 2014.10 | C37: =Transaction!C27 -> 휴비스워터 | D37: =Transaction!G27 -> 휴비스 | E37: =Transaction!M27/$E$2 -> 122253.36 | F37: =Transaction!L27 -> 0.9527 | G37: =Transaction!P27/$E$2 -> 101596.36 | H37: =Transaction!M27/$E$2 -> 122253.36 | J37: =Transaction!AA27 -> 9.2611499 | K37: NA | L37: =Transaction!AF27 -> 2.0536668
B38: Mean | J38: =AVERAGE(J36:J37) -> 8.7787717 | K38: NA | L38: =AVERAGE(L36:L37) -> 1.4526435
B39: Median | J39: =MEDIAN(J36:J37) -> 8.7787717 | K39: NA | L39: =MEDIAN(L36:L37) -> 1.4526435
B40: Global
B41: =Transaction!D29 -> 2017.09 | C41: =Transaction!C29 -> Trility | D41: =Transaction!G29 -> Beijing Enterprises Water | E41: =Transaction!M29 -> 200 | F41: =Transaction!L29 -> 1 | G41: =Transaction!P29 -> 200 | H41: =Transaction!M29 -> 200 | J41: =Transaction!AA29 -> 9.371193
B42: =Transaction!D30 -> 2017.03 | C42: =Transaction!C30 -> Suez Water Technologies & Solutions | D42: =Transaction!G30 -> Suez | E42: =Transaction!M30 -> 3379 | F42: =Transaction!L30 -> 1 | G42: =Transaction!P30 -> 3379 | H42: =Transaction!M30 -> 3379 | J42: =Transaction!AA30 -> 9.9337447
B43: Mean | J43: =AVERAGE(J41:J42) -> 9.6524688 | K43: NA | L43: =AVERAGE(L41:L42) -> #DIV/0!
B44: Median | J44: =MEDIAN(J41:J42) -> 9.6524688 | K44: NA | L44: =MEDIAN(L41:L42) -> #NUM!
B46: Mean | J46: =AVERAGE(J41:J42,J36:J37) -> 9.2156202 | K46: =AVERAGE(K41:K42,K36:K37) -> #DIV/0! | L46: =AVERAGE(L41:L42,L36:L37) -> 1.4526435
B47: Median | J47: =MEDIAN(J41:J42,J36:J37) -> 9.3161714 | K47: =MEDIAN(K41:K42,K36:K37) -> #NUM! | L47: =MEDIAN(L41:L42,L36:L37) -> 1.4526435
B49: Merger Market에서“Utillities(others) ” 산업분류內 최근5개년간(2014.01.01 ~ 현재) 국내외 거래사례 중 수처리장 EPC 회사(또는 유관회사) 내에서, 재무정보가 공개되지 않은 사례, 영업이익 및 EBITDA가 (-)인 사례를 제외함.

Sheet Transaction
B2: Transaction Multiple_하이엔텍
K3: 거래정보 | Q3: 재무정보 | Z3: Multiple
D4: Announce | K4: 거래 | L4: 취득 | M4: Equity | N4: Net | P4: Enterprise | Q4: Fiscal | Z4: EV/ | AA4: EV/ | AB4: EV/ | AE4: PER | AF4: PBR
B5: Target | D5: Date | F5: 산업 | G5: Major Bidder | H5: Seller | I5: 국가 | J5: 단위 | K5: 가격 | L5: 지분율 | M5: Value | N5: Debt (*1) | O5: NOA (*2) | P5: Vaule | Q5: Year (*3) | R5: BV | S5: Sales | T5: EBITDA | U5: EBIT | V5: NI | W5: PBR | X5: Net margin | Y5: BV | Z5: Sales | AA5: EBITDA | AB5: EBIT | AC5: PER | AD5: Source
B6: Tier 1 / 수처리 국내
C7: 코오롱워터앤에너지 | D7: 2016.05 | E7: -2000년 민영화 이후 2007년 코오롱 건설이 100% 취득 -2009년 SCPE 40% 취득 -2016년 5월 SCPE 62.98% 추가 취득(거래 전 지분율 35%) | F7: 수처리 운영관리업 | G7: SC PE | H7: 코오롱 인더스트리 | I7: 한국 | J7: KRW m | K7: 88630 | L7: 0.6298 | M7: =K7/L7 -> 140727.21 | N7: =환경관리!B4 -> -8095.1262 | O7: =환경관리!C4 -> 50887.301 | P7: =M7+N7-O7 -> 81744.788 | Q7: FY2015 | R7: =환경관리!F4 -> 87577.76 | S7: =환경관리!G4 -> 226423.01 | T7: =환경관리!H4 -> 12333.079 | U7: =환경관리!I4 -> 8938.5028 | V7: =환경관리!J4 -> 7474.1583 | W7: =IFERROR(IF(P7/R7<0,"NA",P7/R7),"NA") -> 0.93339665 | X7: =환경관리!J4 -> 7474.1583 | Y7: =환경관리!F4 -> 87577.76 | Z7: =IFERROR(IF(P7/S7<0,"NA",P7/S7),"NA") -> 0.36102686 | AA7: =IFERROR(IF(P7/T7<0,"NA",P7/T7),"NA") -> 6.6280923 | AB7: =IFERROR(IF(P7/U7<0,"NA",P7/U7),"NA") -> 9.1452439 | AC7: =IFERROR(IF(P7/V7<0,"NA",P7/V7),"NA") -> 10.936989 | AD7: http://www.investchosun.com/2016/05/23/3194607 | AE7: =IFERROR(IF(M7/X7<0,"NA",M7/X7),"NA") -> 18.828503 | AF7: =IFERROR(IF(M7/Y7<0,"NA",M7/Y7),"NA") -> 1.606883 | AG7: Majority 추가취득
C8: TSK워터 | D8: 2018.06 | E8: -2004년 태영건설 100% 설립 -2010년 SK계열사로부터 합작사업약정계약 (지분율 50대50) -2018년 6월 SK계열사 지분 25% 인수(Implied EquityValue 5천억) -2018년 10월 TSK워터 물적분할(존속법인 TSK코퍼레이션, 신설법인 TSK워터) -2019년 1월 휴비스워터 100% 자회사 편입 완료(주식교환, Implied EquityValue 6천억) - 태영건설 윤석민 회장과 SK디스커버리 최창원 회장은 절친한 사이, 기타 특수관계는 확인되지 않음. | F8: 수처리 운영관리업 | G8: 태영건설 | H8: SK디스커버리, SK건설 | I8: 한국 | J8: KRW m | K8: 124999.38 | L8: 0.24999876 | M8: =K8/L8 -> 500000 | N8: =티에스케이코퍼레이션!B4 -> 117925.29 | O8: =티에스케이코퍼레이션!C4 -> 34040.969 | P8: =M8+N8-O8 -> 583884.32 | Q8: FY2017 | R8: =티에스케이코퍼레이션!F4 -> 180145.67 | S8: =티에스케이코퍼레이션!G4 -> 421868.93 | T8: =티에스케이코퍼레이션!H4 -> 81770.619 | U8: =티에스케이코퍼레이션!I4 -> 51166.931 | V8: =티에스케이코퍼레이션!J4 -> 34617.831 | W8: =IFERROR(IF(P8/R8<0,"NA",P8/R8),"NA") -> 3.2411787 | X8: =티에스케이코퍼레이션!J4 -> 34617.831 | Y8: =티에스케이코퍼레이션!F4 -> 180145.67 | Z8: =IFERROR(IF(P8/S8<0,"NA",P8/S8),"NA") -> 1.384042 | AA8: =IFERROR(IF(P8/T8<0,"NA",P8/T8),"NA") -> 7.1405148 | AB8: =IFERROR(IF(P8/U8<0,"NA",P8/U8),"NA") -> 11.411361 | AC8: =IFERROR(IF(P8/V8<0,"NA",P8/V8),"NA") -> 16.866577 | AD8: https://www.thebell.co.kr/free/content/ArticleView.asp?key=201806290100048700002980&lcode=00 | AE8: =IFERROR(IF(M8/X8<0,"NA",M8/X8),"NA") -> 14.443424 | AF8: =IFERROR(IF(M8/Y8<0,"NA",M8/Y8),"NA") -> 2.7755315
B9: Tier 2 / 수처리 해외
C10: FCC Aqualia | D10: 2018.03 | F10: 수자원 공급업무 및 수처리업 | G10: IFM Investors | H10: Fomento de Construcciones | I10: 스페인 | J10: USD m | K10: =MergerMarket!S8 -> 1260 | L10: 0.49 | M10: =K10/L10 -> 2571.4286 | N10: =MergerMarket!L8 -> 585.4661 | O10: 0 | P10: =M10+N10-O10 -> 3156.8947 | Q10: FY2017 | R10: 439.3 | S10: =MergerMarket!O8 -> 1242.252 | T10: =MergerMarket!P8 -> 289.4772 | U10: =MergerMarket!Q8 -> 178.5612 | V10: 88.9 | W10: =IFERROR(IF(P10/R10<0,"NA",P10/R10),"NA") -> 7.1861932 | Z10: =IFERROR(IF(P10/S10<0,"NA",P10/S10),"NA") -> 2.5412675 | AA10: =IFERROR(IF(P10/T10<0,"NA",P10/T10),"NA") -> 10.905504 | AB10: =IFERROR(IF(P10/U10<0,"NA",P10/U10),"NA") -> 17.679623 | AC10: =IFERROR(IF(P10/V10<0,"NA",P10/V10),"NA") -> 35.510626 | AD10: https://www.ifminvestors.com/about-us/media-centre/!news/2018/03/18/ifm-investors-to-invest-in-fcc-aqualia-with-49-stake
C11: Anglian Water Group | D11: 2017.12 | F11: 수자원 공급업무 및 수처리업 | G11: Dalmore Capital | H11: 3i Infrastructure | I11: 영국 | J11: USD m | K11: =MergerMarket!S9 -> 529 | L11: 0.15 | M11: =K11/L11 -> 3526.6667 | N11: =MergerMarket!L9 -> 9489.765 | O11: 0 | P11: =M11+N11-O11 -> 13016.432 | Q11: FY2016 | R11: 1121.3 | S11: =MergerMarket!O9 -> 1682.6232 | T11: =MergerMarket!P9 -> 838.6269 | U11: =MergerMarket!Q9 -> 446.7849 | V11: -16.8 | W11: =IFERROR(IF(P11/R11<0,"NA",P11/R11),"NA") -> 11.60834 | Z11: =IFERROR(IF(P11/S11<0,"NA",P11/S11),"NA") -> 7.7357971 | AA11: =IFERROR(IF(P11/T11<0,"NA",P11/T11),"NA") -> 15.521123 | AB11: =IFERROR(IF(P11/U11<0,"NA",P11/U11),"NA") -> 29.133553 | AC11: =IFERROR(IF(P11/V11<0,"NA",P11/V11),"NA") -> NA | AD11: https://www.3i-infrastructure.com/newsroom/press-releases/2017/3i-infrastructure-plc-sells-its-stake-in-anglian-water-group/
C12: Affinity Water | D12: 2017.05 | F12: 수자원 공급업무 및 수처리업 | G12: Allianz Capital Partners | H12: Veolia Water, Morgan Stanley | I12: 영국 | J12: KRW m | K12: 1002994.6 | L12: 1 | M12: =K12/L12 -> 1002994.6 | N12: =Affinity!M6-Affinity!M3 -> 1254823.1 | O12: =Affinity!M10 -> 84.000301 | P12: =M12+N12-O12 -> 2257733.7 | Q12: FY2016 | R12: =Affinity!M16 -> 303404.89 | S12: =Affinity!C3 -> 432128.35 | T12: =Affinity!D3 -> 183777.26 | U12: =Affinity!E3 -> 112764.8 | V12: =Affinity!F3 -> 43261.555 | W12: =IFERROR(IF(P12/R12<0,"NA",P12/R12),"NA") -> 7.4413228 | X12: =Affinity!F3 -> 43261.555 | Y12: =Affinity!M16 -> 303404.89 | Z12: =IFERROR(IF(P12/S12<0,"NA",P12/S12),"NA") -> 5.2246832 | AA12: =IFERROR(IF(P12/T12<0,"NA",P12/T12),"NA") -> 12.285164 | AB12: =IFERROR(IF(P12/U12<0,"NA",P12/U12),"NA") -> 20.021617 | AC12: =IFERROR(IF(P12/V12<0,"NA",P12/V12),"NA") -> 52.187993 | AD12: https://www.allianz.com/en/press/news/financials/stakes_investments/170502-allianz-invests-in-affinity-water-in-uk.html | AE12: =IFERROR(IF(M12/X12<0,"NA",M12/X12),"NA") -> 23.184433 | AF12: =IFERROR(IF(M12/Y12<0,"NA",M12/Y12),"NA") -> 3.3057958
C13: Veolia Water Central | D13: 2012.06 | F13: 수자원 공급업무 및 수처리업 | G13: Morgan Stanley | H13: Veolia Environnement | I13: 영국 | J13: KRW m | K13: 2220926.4 | L13: 0.9 | M13: =K13/L13 -> 2467696 | N13: =Affinity!L6-Affinity!L3 -> 840119.35 | O13: =Affinity!L10 -> 90.57168 | P13: =M13+N13-O13 -> 3307724.8 | Q13: FY2011 | R13: =Affinity!L16 -> 635749.79 | S13: =Affinity!C4 -> 458365.16 | T13: =Affinity!D4 -> 252387.04 | U13: =Affinity!E4 -> 116757.76 | V13: =Affinity!F4 -> 65010.54 | W13: =IFERROR(IF(P13/R13<0,"NA",P13/R13),"NA") -> 5.202872 | X13: =Affinity!F4 -> 65010.54 | Y13: =Affinity!L16 -> 635749.79 | Z13: =IFERROR(IF(P13/S13<0,"NA",P13/S13),"NA") -> 7.216353 | AA13: =IFERROR(IF(P13/T13<0,"NA",P13/T13),"NA") -> 13.105763 | AB13: =IFERROR(IF(P13/U13<0,"NA",P13/U13),"NA") -> 28.329806 | AC13: =IFERROR(IF(P13/V13<0,"NA",P13/V13),"NA") -> 50.879823 | AD13: https://www.bbc.com/news/business-18621952 | AE13: =IFERROR(IF(M13/X13<0,"NA",M13/X13),"NA") -> 37.958399 | AF13: =IFERROR(IF(M13/Y13<0,"NA",M13/Y13),"NA") -> 3.8815522
B14: Tier 3 / 폐기물처리
C15: WIK그린 | D15: 2018.12 | F15: 폐기물 처리업 | G15: SC PE | H15: 맥쿼리 | I15: 한국 | J15: KRW m | K15: 75000 | L15: 1 | M15: =K15/L15 -> 75000 | N15: =WIK그린!B4 -> -2654.192 | O15: =WIK그린!C4 -> 58.747546 | P15: =M15+N15-O15 -> 72287.06 | Q15: FY2017 | R15: =WIK그린!F4 -> 36694.33 | S15: =WIK그린!G4 -> 12535.804 | T15: =WIK그린!H4 -> 5445.8721 | U15: =WIK그린!I4 -> 3709.3191 | V15: =WIK그린!J4 -> 3821.1703 | W15: =IFERROR(IF(P15/R15<0,"NA",P15/R15),"NA") -> 1.969979 | X15: =WIK그린!J4 -> 3821.1703 | Y15: =WIK그린!F4 -> 36694.33 | Z15: =IFERROR(IF(P15/S15<0,"NA",P15/S15),"NA") -> 5.7664477 | AA15: =IFERROR(IF(P15/T15<0,"NA",P15/T15),"NA") -> 13.273734 | AB15: =IFERROR(IF(P15/U15<0,"NA",P15/U15),"NA") -> 19.487959 | AC15: =IFERROR(IF(P15/V15<0,"NA",P15/V15),"NA") -> 18.917519 | AD15: https://www.thebell.co.kr/free/Content/ArticleView.asp?key=201903150100028040001799&svccode=01 | AE15: =IFERROR(IF(M15/X15<0,"NA",M15/X15),"NA") -> 19.627495 | AF15: =IFERROR(IF(M15/Y15<0,"NA",M15/Y15),"NA") -> 2.0439125
C16: 인선이엔티 | D16: 2019.05 | F16: 폐기물 처리업 | G16: IS 동서 | H16: E&F PE | I16: 한국 | J16: KRW m | K16: 99997.015 | L16: 0.2383 | M16: =K16/L16 -> 419626.58 | N16: =인선이엔티!C6-인선이엔티!C3 -> 45306.328 | O16: =인선이엔티!C10 -> 2785.2241 | P16: =M16+N16-O16 -> 462147.69 | Q16: FY2018 | R16: =인선이엔티!C16 -> 186940.06 | S16: =인선이엔티!H4 -> 175954.97 | T16: =인선이엔티!H7 -> 30313.125 | U16: =인선이엔티!H5 -> 23853.49 | V16: =인선이엔티!H8 -> 19964.863 | W16: =IFERROR(IF(P16/R16<0,"NA",P16/R16),"NA") -> 2.4721704 | X16: =인선이엔티!H8 -> 19964.863 | Y16: =인선이엔티!C16 -> 186940.06 | Z16: =IFERROR(IF(P16/S16<0,"NA",P16/S16),"NA") -> 2.6265112 | AA16: =IFERROR(IF(P16/T16<0,"NA",P16/T16),"NA") -> 15.245795 | AB16: =IFERROR(IF(P16/U16<0,"NA",P16/U16),"NA") -> 19.374426 | AC16: =IFERROR(IF(P16/V16<0,"NA",P16/V16),"NA") -> 23.148052 | AD16: http://dart.fss.or.kr/dsaf001/main.do?rcpNo=20190503900734 | AE16: =IFERROR(IF(M16/X16<0,"NA",M16/X16),"NA") -> 21.018255 | AF16: =IFERROR(IF(M16/Y16<0,"NA",M16/Y16),"NA") -> 2.2447119
C17: 창원에너텍 | D17: 2019.04 | F17: 폐기물 처리업 | G17: SK증권 PE | H17: KC환경서비스 | I17: 한국 | J17: KRW m | K17: 68000 | L17: 1 | M17: =K17/L17 -> 68000 | N17: =창원에너텍!B5 -> 35786.697 | O17: =창원에너텍!C5 -> 508.74475 | P17: =M17+N17-O17 -> 103277.95 | Q17: FY2018 | R17: =창원에너텍!F5 -> 10987.624 | S17: =창원에너텍!G5 -> 14685.915 | T17: =창원에너텍!H5 -> 6104.4256 | U17: =창원에너텍!I5 -> 2059.2282 | V17: =창원에너텍!J5 -> 767.8966 | W17: =IFERROR(IF(P17/R17<0,"NA",P17/R17),"NA") -> 9.3994804 | X17: =창원에너텍!J5 -> 767.8966 | Y17: =창원에너텍!F5 -> 10987.624 | Z17: =IFERROR(IF(P17/S17<0,"NA",P17/S17),"NA") -> 7.0324492 | AA17: =IFERROR(IF(P17/T17<0,"NA",P17/T17),"NA") -> 16.918537 | AB17: =IFERROR(IF(P17/U17<0,"NA",P17/U17),"NA") -> 50.15372 | AC17: =IFERROR(IF(P17/V17<0,"NA",P17/V17),"NA") -> 134.49461 | AD17: https://www.thebell.co.kr/free/Content/ArticleView.asp?key=201904300100057530003569&svccode=01 | AE17: =IFERROR(IF(M17/X17<0,"NA",M17/X17),"NA") -> 88.553589 | AF17: =IFERROR(IF(M17/Y17<0,"NA",M17/Y17),"NA") -> 6.1887813
C18: 삼우그린 | D18: 2017.11 | F18: 폐기물 처리업 | G18: 앵커 PE | H18: - | I18: 한국 | J18: KRW m | K18: 57000 | L18: 1 | M18: =K18/L18 -> 57000 | N18: =삼우그린!B5 -> 152.01951 | O18: =삼우그린!C5 -> 16841.9 | P18: =M18+N18-O18 -> 40310.12 | Q18: FY2016 | R18: =삼우그린!F5 -> 22114.32 | S18: =삼우그린!G5 -> 8007.8196 | T18: =삼우그린!H5 -> 3606.4627 | U18: =삼우그린!I5 -> 3110.421 | V18: =삼우그린!J5 -> 2913.4828 | W18: =IFERROR(IF(P18/R18<0,"NA",P18/R18),"NA") -> 1.8228062 | X18: =삼우그린!J4 -> 2563.0496 | Y18: =삼우그린!F4 -> 19200.838 | Z18: =IFERROR(IF(P18/S18<0,"NA",P18/S18),"NA") -> 5.0338446 | AA18: =IFERROR(IF(P18/T18<0,"NA",P18/T18),"NA") -> 11.17719 | AB18: =IFERROR(IF(P18/U18<0,"NA",P18/U18),"NA") -> 12.959699 | AC18: =IFERROR(IF(P18/V18<0,"NA",P18/V18),"NA") -> 13.835716 | AD18: https://www.thebell.co.kr/free/content/ArticleView.asp?key=201711160100031120001918&lcode=00 | AE18: =IFERROR(IF(M18/X18<0,"NA",M18/X18),"NA") -> 22.239133 | AF18: =IFERROR(IF(M18/Y18<0,"NA",M18/Y18),"NA") -> 2.9686205
C19: 코엔텍 | D19: 2017.04 | F19: 폐기물 처리업 | G19: 맥쿼리 | H19: 후성HDS 외 | I19: 한국 | J19: KRW m | K19: 79500 | L19: 0.3363 | M19: =K19/L19 -> 236396.07 | N19: =코엔텍!B4 -> -13359.281 | O19: =코엔텍!C4 -> 3123.8873 | P19: =M19+N19-O19 -> 219912.91 | Q19: FY2016 | R19: =코엔텍!F4 -> 110624.03 | S19: =코엔텍!G4 -> 55095.779 | T19: =코엔텍!H4 -> 22232.954 | U19: =코엔텍!I4 -> 15475.622 | V19: =코엔텍!J4 -> 14719.206 | W19: =IFERROR(IF(P19/R19<0,"NA",P19/R19),"NA") -> 1.9879306 | X19: =코엔텍!J4 -> 14719.206 | Y19: =코엔텍!F4 -> 110624.03 | Z19: =IFERROR(IF(P19/S19<0,"NA",P19/S19),"NA") -> 3.9914656 | AA19: =IFERROR(IF(P19/T19<0,"NA",P19/T19),"NA") -> 9.8913042 | AB19: =IFERROR(IF(P19/U19<0,"NA",P19/U19),"NA") -> 14.210279 | AC19: =IFERROR(IF(P19/V19<0,"NA",P19/V19),"NA") -> 14.940542 | AD19: https://www.mk.co.kr/news/stock/view/2017/11/740560/ | AE19: =IFERROR(IF(M19/X19<0,"NA",M19/X19),"NA") -> 16.060382 | AF19: =IFERROR(IF(M19/Y19<0,"NA",M19/Y19),"NA") -> 2.1369323
B21: Transaction Multiple_엘지히타치워터솔루션
K22: 거래정보 | Q22: 재무정보 | W22: Multiple | Z22: Multiple
D23: Announce | K23: 거래 | L23: 취득 | M23: Equity | N23: Net | P23: Enterprise | Q23: Fiscal | Z23: EV/ | AA23: EV/ | AB23: EV/
B24: Target | D24: Date | F24: 산업 | G24: Major Bidder | H24: Seller | I24: 국가 | J24: 단위 | K24: 가격 | L24: 지분율 | M24: Value | N24: Debt (*1) | O24: NOA (*2) | P24: Vaule | Q24: Year (*3) | R24: BV | S24: Sales | T24: EBITDA | U24: EBIT | V24: NI | W24: PBR | Z24: Sales | AA24: EBITDA | AB24: EBIT | AC24: PER | AD24: Source
B25: Tier 1 / EPC 국내
C26: 한국종합기술 | D26: 2017.09 | F26: 환경 및 플랜트 EPC | G26: 한국종합기술홀딩스 | H26: 한진중공업 홀딩스 | I26: 한국 | J26: KRW m | K26: 50663.565 | L26: 0.5201 | M26: =K26/L26 -> 97411.2 | N26: =한국종합기술!C6-한국종합기술!C3 -> 18639.086 | O26: =한국종합기술!C10 -> 63736.082 | P26: =M26+N26-O26 -> 52314.204 | Q26: FY2016 | R26: =한국종합기술!C17 -> 122403.97 | S26: =한국종합기술!G4 -> 199370.93 | T26: =한국종합기술!H4 -> 6305.6561 | U26: =한국종합기술!I4 -> 4236.7241 | V26: =한국종합기술!J4 -> 3063.3867 | W26: =IFERROR(IF(P26/R26<0,"NA",P26/R26),"NA") -> 0.42738977 | X26: =한국종합기술!J3 -> -7815.611 | Y26: =한국종합기술!D17 -> 114383.39 | Z26: =IFERROR(IF(P26/S26<0,"NA",P26/S26),"NA") -> 0.26239635 | AA26: =IFERROR(IF(P26/T26<0,"NA",P26/T26),"NA") -> 8.2963934 | AB26: =IFERROR(IF(P26/U26<0,"NA",P26/U26),"NA") -> 12.347796 | AC26: =IFERROR(IF(P26/V26<0,"NA",P26/V26),"NA") -> 17.077245 | AD26: http://dart.fss.or.kr/dsaf001/main.do?rcpNo=20171212800646 | AE26: =IFERROR(IF(M26/X26<0,"NA",M26/X26),"NA") -> NA | AF26: =IFERROR(IF(M26/Y26<0,"NA",M26/Y26),"NA") -> 0.85162015 | AG26: Majority, 우리사주조합
C27: 휴비스워터 | D27: 2014.10 | E27: -2014년 10월 KDB-JKL로부터 95.3% 지분인수(4.7% 우리사주조합, Implied EquityValue 1383억) -2019년 1월 TSK코퍼레이션 100% 자회사편입(Implied EquityValue 1188억) | F27: 수처리설비 제조 및 EPC | G27: 휴비스 | H27: JKL, KDB캐피탈 | I27: 한국 | J27: KRW m | K27: 131798.33 | L27: 0.9527 | M27: =K27/L27 -> 138341.91 | N27: ='휴비스워터_''14'!C6-'휴비스워터_''14'!C3 -> -22440.338 | O27: ='휴비스워터_''14'!C10 -> 935.12711 | P27: =M27+N27-O27 -> 114966.44 | Q27: FY2013 | R27: ='휴비스워터_''14'!C16 -> 65687.151 | S27: ='휴비스워터_''14'!G4 -> 105760.54 | T27: ='휴비스워터_''14'!H4 -> 12413.841 | U27: ='휴비스워터_''14'!I4 -> 10841.688 | V27: ='휴비스워터_''14'!J4 -> 8364.5223 | W27: =IFERROR(IF(P27/R27<0,"NA",P27/R27),"NA") -> 1.750212 | X27: ='휴비스워터_''18'!J5 -> 959.72901 | Y27: ='휴비스워터_''18'!C17 -> 67363.364 | Z27: =IFERROR(IF(P27/S27<0,"NA",P27/S27),"NA") -> 1.0870447 | AA27: =IFERROR(IF(P27/T27<0,"NA",P27/T27),"NA") -> 9.2611499 | AB27: =IFERROR(IF(P27/U27<0,"NA",P27/U27),"NA") -> 10.604109 | AC27: =IFERROR(IF(P27/V27<0,"NA",P27/V27),"NA") -> 13.744532 | AD27: http://dart.fss.or.kr/dsaf001/main.do?rcpNo=20141124000274 | AE27: =IFERROR(IF(M27/X27<0,"NA",M27/X27),"NA") -> 144.14684 | AF27: =IFERROR(IF(M27/Y27<0,"NA",M27/Y27),"NA") -> 2.0536668 | AG27: Majority
B28: Tier 2 / EPC 해외
C29: Trility | D29: 2017.09 | F29: 수처리설비 제조 및 EPC | G29: Beijing Enterprises Water | H29: Mitsubishi, JGC | I29: 호주 | J29: USD m | K29: =MergerMarket!S10 -> 200 | L29: 1 | M29: =K29/L29 -> 200 | N29: 0 | O29: 0 | P29: =M29+N29-O29 -> 200 | Q29: FY2017 | S29: =MergerMarket!O10 -> 63.1394 | T29: =MergerMarket!P10 -> 21.342 | U29: =MergerMarket!Q10 -> 12.9031 | W29: =IFERROR(IF(P29/R29<0,"NA",P29/R29),"NA") -> NA | Z29: =IFERROR(IF(P29/S29<0,"NA",P29/S29),"NA") -> 3.1675942 | AA29: =IFERROR(IF(P29/T29<0,"NA",P29/T29),"NA") -> 9.371193 | AB29: =IFERROR(IF(P29/U29<0,"NA",P29/U29),"NA") -> 15.500151 | AC29: =IFERROR(IF(P29/V29<0,"NA",P29/V29),"NA") -> NA | AD29: https://www.afr.com/street-talk/beijing-enterprises-water-buys-trility-group-20170913-gygb36 | AG29: Majority
C30: Suez Water Technologies & Solutions | D30: 2017.03 | F30: 수처리설비 제조 및 EPC | G30: Suez | H30: General Electric | I30: 미국 | J30: USD m | K30: =MergerMarket!S5 -> 3379 | L30: 1 | M30: =K30/L30 -> 3379 | N30: 0 | O30: 0 | P30: =M30+N30-O30 -> 3379 | Q30: FY2016 | S30: =MergerMarket!O5 -> 2091.7226 | T30: =MergerMarket!P5 -> 340.1537 | U30: =MergerMarket!Q5 -> 0 | W30: =IFERROR(IF(P30/R30<0,"NA",P30/R30),"NA") -> NA | Z30: =IFERROR(IF(P30/S30<0,"NA",P30/S30),"NA") -> 1.615415 | AA30: =IFERROR(IF(P30/T30<0,"NA",P30/T30),"NA") -> 9.9337447 | AB30: =IFERROR(IF(P30/U30<0,"NA",P30/U30),"NA") -> NA | AC30: =IFERROR(IF(P30/V30<0,"NA",P30/V30),"NA") -> NA | AD30: https://www.suez.com/en/news/press-releases/suez-finalizes-the-acquisition-of-ge-water-and-process-technologies | AG30: Spin-off
B32: Note | T32: 하이엔텍 평균값
B33: (*1) Net Debt = 현금및현금성자산 + 단기금융상품 - 장단기차입금 및 사채 | T33: 구분 | Z33: EV/Sales | AA33: EV/EBITDA | AB33: EV/EBIT
B34: (*2) NOA = 투자부동산 + 장기금융상품 + 대여금 + 매도/만기보유증권 + 관계기업투자주식 | T34: Tier 1 only | Z34: =AVERAGE(Z7:Z8) -> 0.87253443 | AA34: =AVERAGE(AA7:AA8) -> 6.8843036 | AB34: =AVERAGE(AB7:AB8) -> 10.278302
B35: (*3) Fiscal Year는 Announce date 기준의 직전 회계연도임. | T35: Tier 2 only | Z35: =AVERAGE(Z10:Z13) -> 5.6795252 | AA35: =AVERAGE(AA10:AA13) -> 12.954388 | AB35: =AVERAGE(AB10:AB13) -> 23.79115
T36: Tier 1/2 | Z36: =AVERAGE(Z7:Z8,Z10:Z13) -> 4.0771949 | AA36: =AVERAGE(AA7:AA8,AA10:AA13) -> 10.931027 | AB36: =AVERAGE(AB7:AB8,AB10:AB13) -> 19.286867
T37: Tier 1/3 | Z37: =AVERAGE(Z7:Z8,Z15:Z19) -> 3.7422553 | AA37: =AVERAGE(AA7:AA8,AA15:AA19) -> 11.467881 | AB37: =AVERAGE(AB7:AB8,AB15:AB19) -> 19.53467
T38: Tier 1/2/3 | Z38: =AVERAGE(Z7:Z8,Z10:Z13,Z15:Z19) -> 4.4467171 | AA38: =AVERAGE(AA7:AA8,AA10:AA13,AA15:AA19) -> 12.008429 | AB38: =AVERAGE(AB7:AB8,AB10:AB13,AB15:AB19) -> 21.082481
T40: 엘지히타치워터솔루션 평균값
T41: 구분 | Z41: EV/Sales | AA41: EV/EBITDA | AB41: EV/EBIT
T42: Tier 1 only | Z42: =AVERAGE(Z26:Z27) -> 0.67472053 | AA42: =AVERAGE(AA26:AA27) -> 8.7787717 | AB42: =AVERAGE(AB26:AB27) -> 11.475952
T43: Tier 2 only | Z43: =AVERAGE(Z29:Z30) -> 2.3915046 | AA43: =AVERAGE(AA29:AA30) -> 9.6524688 | AB43: =AVERAGE(AB29:AB30) -> 15.500151
T44: Tier 1/2 | Z44: =AVERAGE(Z26:Z27,Z29:Z30) -> 1.5331126 | AA44: =AVERAGE(AA26:AA27,AA29:AA30) -> 9.2156202 | AB44: =AVERAGE(AB26:AB27,AB29:AB30) -> 12.817352

Sheet Affinity
B2: 구분 | C2: Sales | D2: EBITDA | E2: EBIT | F2: NI | G2: D&A | K2: BS | L2: FY2011 | M2: FY2016
B3: FY2016 | C3: =I24 -> 432128.35 | D3: =I81 -> 183777.26 | E3: =I83 -> 112764.8 | F3: =I54 -> 43261.555 | G3: =D3-E3 -> 71012.454 | K3: Cash | L3: =SUM(L4:L5) -> 1291.5522 | M3: =SUM(M4:M5) -> 63180.826
B4: FY2011 | C4: =D24 -> 458365.16 | D4: =D81 -> 252387.04 | E4: =D83 -> 116757.76 | F4: =D54 -> 65010.54 | G4: =D4-E4 -> 135629.28 | K4: 현금및현금성자산 | L4: =M24 -> 1291.5522 | M4: =R24 -> 63180.826
K5: 단기금융상품
K6: Debt | L6: =SUM(L7:L9) -> 841410.91 | M6: =SUM(M7:M9) -> 1318003.9
K7: 단기차입금 | L7: =M48+M49 -> 84876.533 | M7: 0
K8: 장기차입금 | L8: =M56 -> 756534.37 | M8: =R56 -> 1318003.9
K9: 사채
K10: NOA | L10: =SUM(L11:L15) -> 90.57168 | M10: =SUM(M11:M15) -> 84.000301
K11: 장기금융상품 | L11: =M41 -> 90.57168 | M11: =R41 -> 84.000301
K12: 투자부동산
K13: 관계기업투자
K14: 매도가능증권
K15: 장단기대여금
K16: BV | L16: =M71 -> 635749.79 | M16: =R71 -> 303404.89
B18: Source : Capital IQ
B20: Income Statement | K20: Balance Sheet
B21: For the Fiscal Period Ending | C21: 12 months Mar-31-2011 | D21: 12 months Mar-31-2012 | E21: 12 months Mar-31-2013 | F21: 12 months Mar-31-2014 | G21: Restated 12 months Mar-31-2015 | H21: 12 months Mar-31-2016 | I21: 12 months Mar-31-2017 | K21: Balance Sheet as of: | L21: 40633 | M21: 40999 | N21: 41364 | O21: Restated Mar-31-2014 | P21: Restated Mar-31-2015 | Q21: 42460 | R21: 42825
B22: Currency | C22: KRW | D22: KRW | E22: KRW | F22: KRW | G22: KRW | H22: KRW | I22: KRW | K22: Currency | L22: KRW | M22: KRW | N22: KRW | O22: KRW | P22: KRW | Q22: KRW | R22: KRW
K23: ASSETS
B24: Revenue | C24: 421379.47 | D24: 458365.16 | E24: 472141.56 | F24: 516015.62 | G24: 487466.67 | H24: 495449.27 | I24: 432128.35 | K24: Cash And Equivalents | L24: 2530.2426 | M24: 1291.5522 | N24: 60445.892 | O24: 29797.684 | P24: 97000.823 | Q24: 152985.45 | R24: 63180.826
B25: Other Revenue | C25: - | D25: - | E25: - | F25: - | G25: - | H25: - | I25: -
B26: Total Revenue | C26: 421379.47 | D26: 458365.16 | E26: 472141.56 | F26: 516015.62 | G26: 487466.67 | H26: 495449.27 | I26: 432128.35 | K26: Accounts Receivable | L26: 80016.505 | M26: 92294.353 | N26: 115490.7 | O26: 127820.48 | P26: 117377.78 | Q26: 115598.61 | R26: 102009.96
K27: Other Receivables | L27: 10968.488 | M27: 12154.719 | N27: 11244.804 | O27: 6212.4256 | P27: 6212.3457 | Q27: 5694.1417 | R27: 14736.453
B28: Fuel & Purchased Power | C28: - | D28: - | E28: - | F28: - | G28: - | H28: - | I28: - | K28: Accounts Receivable, Total | L28: 90984.993 | M28: 104449.07 | N28: 126735.5 | O28: 134032.91 | P28: 123590.12 | Q28: 121292.75 | R28: 116746.42
B29: Ops. and Maintenance | C29: - | D29: - | E29: - | F29: - | G29: - | H29: - | I29: -
B30: Selling General & Admin Exp. | C30: 70700.852 | D30: 74015.177 | E30: 65566.535 | F30: 69346.113 | G30: 75206.584 | H30: 86708.779 | I30: 76115.472 | K30: Inventory | L30: 1496.3422 | M30: 1724.4848 | N30: 2662.5318 | O30: 2500.5544 | P30: 2077.3663 | Q30: 2000.6444 | R30: 2002.0072
B31: Depreciation & Amort. | C31: - | D31: - | E31: - | F31: - | G31: - | H31: - | I31: - | K31: Prepaid Exp. | L31: 4038.8932 | M31: 4436.2009 | N31: 4547.9287 | O31: 9773.7677 | P31: 9040.3292 | Q31: 9520.2513 | R31: 8808.8315
B32: Other Operating Exp. | C32: 260783.79 | D32: 267592.22 | E32: 275950.47 | F32: 296014.64 | G32: 251122.63 | H32: 271344.35 | I32: 243248.07 | K32: Other Current Assets | L32: - | M32: 3798.5763 | N32: - | O32: - | P32: - | Q32: - | R32: -
B33: Total Operating Exp. | C33: 331484.64 | D33: 341607.39 | E33: 341517.01 | F33: 365360.76 | G33: 326329.22 | H33: 358053.13 | I33: 319363.54 | K33: Total Current Assets | L33: 99050.471 | M33: 115699.89 | N33: 194391.85 | O33: 176104.91 | P33: 231708.64 | Q33: 285799.09 | R33: 190738.08
B35: Operating Income | C35: 89894.826 | D35: 116757.76 | E35: 130624.55 | F35: 150654.86 | G35: 161137.45 | H35: 137396.14 | I35: 112764.8 | K35: Gross Property, Plant & Equipment | L35: 2993101.2 | M35: 3191887.3 | N35: 3579633.8 | O35: 3937811.9 | P35: 2842538.3 | Q35: 2942510.8 | R35: 2672198
K36: Accumulated Depreciation | L36: -1386252.9 | M36: -1549743 | N36: -1572905.9 | O36: -1791509.1 | P36: -809769.5 | Q36: -880427.6 | R36: -823082.5
B37: Interest Expense, Total | C37: -33633.4 | D37: -34618.3 | E37: -40015.7 | F37: -71019.6 | G37: -62223.9 | H37: -63328.1 | I37: -62471 | K37: Net Property, Plant & Equipment | L37: 1606848.3 | M37: 1642144.3 | N37: 2006727.9 | O37: 2146302.7 | P37: 2032768.7 | Q37: 2062083.2 | R37: 1849115.4
B38: Interest and Invest. Income | C38: 226.82509 | D38: 219.18347 | E38: 20.273085 | F38: 610.97116 | G38: 274.89712 | H38: 638.50353 | I38: 410.20147
B39: Net Interest Exp. | C39: -33406.6 | D39: -34399.1 | E39: -39995.4 | F39: -70408.7 | G39: -61949 | H39: -62689.6 | I39: -62060.8 | K39: Goodwill | L39: 11742.154 | M39: 12096.754 | N39: 26055.982 | O39: 26494.897 | P39: 24627.16 | Q39: 24493.978 | R39: 20945.475
K40: Other Intangibles | L40: - | M40: - | N40: - | O40: - | P40: 37190.123 | Q40: 46943.107 | R40: 51419.384
B41: Other Non-Operating Inc. (Exp.) | C41: -1306.4 | D41: -1686.4 | E41: -1623.5 | F41: -1926.8 | G41: - | H41: - | I41: - | K41: Long-term Investments | L41: 87.9167 | M41: 90.57168 | N41: 103.05485 | O41: 108.02679 | P41: 98.765432 | Q41: 98.231312 | R41: 84.000301
B42: EBT Excl. Unusual Items | C42: 55181.796 | D42: 80672.195 | E42: 89005.6 | F42: 78319.42 | G42: 99188.477 | H42: 74706.55 | I42: 50703.981 | K42: Other Long-Term Assets | L42: - | M42: - | N42: - | O42: - | P42: 74235.391 | Q42: 118840.24 | R42: 102196.17
K43: Total Assets | L43: 1717728.8 | M43: 1770031.5 | N43: 2227278.8 | O43: 2349010.6 | P43: 2400628.8 | Q43: 2538257.8 | R43: 2214498.5
B44: Impairment of Goodwill | C44: - | D44: - | E44: - | F44: - | G44: - | H44: - | I44: -
B45: Gain (Loss) On Sale Of Assets | C45: -1716.1 | D45: 8104.3539 | E45: 6338.7178 | F45: 2620.9777 | G45: - | H45: - | I45: - | K45: LIABILITIES
B46: Other Unusual Items | C46: - | D46: - | E46: - | F46: - | G46: - | H46: - | I46: -13231.4 | K46: Accounts Payable | L46: 14770.006 | M46: 7234.8658 | N46: 13917.473 | O46: 19173.869 | P46: 23400.823 | Q46: 13293.971 | R46: 26068.093
B47: EBT Incl. Unusual Items | C47: 53465.662 | D47: 88776.549 | E47: 95344.318 | F47: 80940.397 | G47: 99188.477 | H47: 74706.55 | I47: 37472.534 | K47: Accrued Exp. | L47: 39256.565 | M47: 36007.677 | N47: 66284.54 | O47: 67258.185 | P47: 71733.333 | Q47: 80030.687 | R47: 76819.675
K48: Short-term Borrowings | L48: 56862.763 | M48: 83325.945 | N48: - | O48: 30460.012 | P48: - | Q48: - | R48: -
B49: Income Tax Expense | C49: 16097.548 | D49: 23766.009 | E49: 21862.833 | F49: 2289.8137 | G49: 18650.206 | H49: -23086 | I49: -5789 | K49: Curr. Port. of LT Debt | L49: 2317.4842 | M49: 1550.5872 | N49: 1846.5401 | O49: 1779.7856 | P49: - | Q49: - | R49: -
B50: Earnings from Cont. Ops. | C50: 37368.114 | D50: 65010.54 | E50: 73481.485 | F50: 78650.584 | G50: 80538.272 | H50: 97792.546 | I50: 43261.555 | K50: Curr. Port. of Cap. Leases | L50: 2609.3677 | M50: 2881.9909 | N50: - | O50: - | P50: - | Q50: - | R50: -
K51: Curr. Income Taxes Payable | L51: 9604.0203 | M51: 7600.7754 | N51: 8364.3369 | O51: 6045.9581 | P51: 9254.321 | Q51: 3295.6605 | R51: 11530.441
B52: Earnings of Discontinued Ops. | C52: - | D52: - | E52: - | F52: - | G52: - | H52: - | I52: - | K52: Unearned Revenue, Current | L52: 59349.048 | M52: 69955.754 | N52: 66041.263 | O52: 57698.7 | P52: 70974.486 | Q52: 79745.816 | R52: 69511.649
B53: Extraord. Item & Account. Change | C53: - | D53: - | E53: - | F53: - | G53: - | H53: - | I53: - | K53: Other Current Liabilities | L53: 67527.059 | M53: 49283.674 | N53: 50353.274 | O53: 52382.365 | P53: 48849.383 | Q53: 41651.714 | R53: 32015.315
B54: Net Income to Company | C54: 37368.114 | D54: 65010.54 | E54: 73481.485 | F54: 78650.584 | G54: 80538.272 | H54: 97792.546 | I54: 43261.555 | K54: Total Current Liabilities | L54: 252296.31 | M54: 257841.27 | N54: 206807.43 | O54: 234798.87 | P54: 224212.35 | Q54: 218017.85 | R54: 215945.17
B56: Minority Int. in Earnings | C56: - | D56: - | E56: - | F56: - | G56: - | H56: - | I56: - | K56: Long-Term Debt | L56: 737995.64 | M56: 756534.37 | N56: 1322033.2 | O56: 1402499.4 | P56: 1374610.7 | Q56: 1477141.9 | R56: 1318003.9
B57: Net Income | C57: 37368.114 | D57: 65010.54 | E57: 73481.485 | F57: 78650.584 | G57: 80538.272 | H57: 97792.546 | I57: 43261.555 | K57: Capital Leases | L57: 2797.5094 | M57: - | N57: - | O57: - | P57: - | Q57: - | R57: -
K58: Unearned Revenue, Non-Current | L58: - | M58: - | N58: - | O58: - | P58: 139848.56 | Q58: 144034.94 | R58: 131866.47
B59: Pref. Dividends and Other Adj. | C59: - | D59: - | E59: - | F59: - | G59: - | H59: - | I59: - | K59: Pension & Other Post-Retire. Benefits | L59: 37609.006 | M59: 26754.874 | N59: 21992.918 | O59: -4407.8 | P59: 1102.8807 | Q59: 1096.9163 | R59: 938.00336
B60: NI to Common Incl Extra Items | C60: 37368.114 | D60: 65010.54 | E60: 73481.485 | F60: 78650.584 | G60: 80538.272 | H60: 97792.546 | I60: 43261.555 | K60: Def. Tax Liability, Non-Curr. | L60: 71351.435 | M60: 80474.749 | N60: 85939.296 | O60: 79617.512 | P60: 323649.38 | Q60: 302310.14 | R60: 241831.27
B61: NI to Common Excl. Extra Items | C61: 37368.114 | D61: 65010.54 | E61: 73481.485 | F61: 78650.584 | G61: 80538.272 | H61: 97792.546 | I61: 43261.555 | K61: Other Non-Current Liab., Total | L61: 10715.287 | M61: 12676.412 | N61: 13157.232 | O61: 12573.609 | P61: 3420.5761 | Q61: 3626.3726 | R61: 2508.809
K62: Total Liabilities | L62: 1112765.2 | M62: 1134281.7 | N62: 1649930.1 | O62: 1725081.5 | P62: 2066844.4 | Q62: 2146228.1 | R62: 1911093.6
B63: Per Share Items
B64: Basic EPS | C64: 2830.9177 | D64: 4637.27 | E64: 277.22768 | F64: 296.72833 | G64: 303.85021 | H64: 368.94699 | I64: 163.21538 | K64: Common Stock | L64: 46606.401 | M64: 48013.859 | N64: 44779.865 | O64: 46940.295 | P64: 43631.276 | Q64: 43395.319 | R64: 37108.533
B65: Basic EPS Excl. Extra Items | C65: 2830.9177 | D65: 4637.27 | E65: 277.22768 | F65: 296.72833 | G65: 303.85021 | H65: 368.94699 | I65: 163.21538 | K65: Additional Paid In Capital | L65: - | M65: - | N65: 53301.319 | O65: 55872.87 | P65: 51934.156 | Q65: 51653.298 | R65: 44170.158
B66: Weighted Avg. Basic Shares Out. | C66: 13.2 | D66: 14.01914 | E66: 265.05782 | F66: 265.05782 | G66: 265.058 | H66: 265.058 | I66: 265.058 | K66: Retained Earnings | L66: 335117.36 | M66: 361002.41 | N66: 127879.24 | O66: 151187.91 | P66: 238218.93 | Q66: 296981.09 | R66: 222126.19
K67: Treasury Stock | L67: - | M67: - | N67: - | O67: - | P67: - | Q67: - | R67: -
B68: Diluted EPS | C68: 2830.9177 | D68: 4637.27 | E68: 277.22768 | F68: 296.72833 | G68: 303.85021 | H68: 368.94699 | I68: 163.21538 | K68: Comprehensive Inc. and Other | L68: 223239.84 | M68: 226733.52 | N68: 351388.31 | O68: 369927.99 | P68: - | Q68: - | R68: -
B69: Diluted EPS Excl. Extra Items | C69: 2830.9177 | D69: 4637.27 | E69: 277.22768 | F69: 296.72833 | G69: 303.85021 | H69: 368.94699 | I69: 163.21538 | K69: Total Common Equity | L69: 604963.61 | M69: 635749.79 | N69: 577348.74 | O69: 623929.07 | P69: 333784.36 | Q69: 392029.71 | R69: 303404.89
B70: Weighted Avg. Diluted Shares Out. | C70: 13.2 | D70: 14.01914 | E70: 265.05782 | F70: 265.05782 | G70: 265.058 | H70: 265.058 | I70: 265.058
K71: Total Equity | L71: 604963.61 | M71: 635749.79 | N71: 577348.74 | O71: 623929.07 | P71: 333784.36 | Q71: 392029.71 | R71: 303404.89
B72: Normalized Basic EPS | C72: 2612.7736 | D72: 3596.5199 | E72: 209.87204 | F72: 184.67445 | G72: 233.88313 | H72: 176.15494 | I72: 119.55763
B73: Normalized Diluted EPS | C73: 2612.7736 | D73: 3596.5199 | E73: 209.87204 | F73: 184.67445 | G73: 233.88313 | H73: 176.15494 | I73: 119.55763 | K73: Total Liabilities And Equity | L73: 1717728.8 | M73: 1770031.5 | N73: 2227278.8 | O73: 2349010.6 | P73: 2400628.8 | Q73: 2538257.8 | R73: 2214498.5
B75: Dividends per Share | C75: 231.39675 | D75: 222.62519 | E75: 978.17634 | F75: 306.19395 | G75: 191.11111 | H75: 247.21547 | I75: 266.70095 | K75: Supplemental Items
B76: Payout Ratio % | C76: 1.641351 | D76: 0.907854 | E76: 3.528106 | F76: 1.032198 | G76: 0.629509 | H76: 0.669657 | I76: 1.634251 | K76: Total Shares Out. on Filing Date | L76: 265.05782 | M76: 265.05782 | N76: 265.05782 | O76: 265.05782 | P76: 265.058 | Q76: 265.058 | R76: 265.058
K77: Total Shares Out. on Balance Sheet Date | L77: 265.05782 | M77: 265.05782 | N77: 265.05782 | O77: 265.05782 | P77: 265.058 | Q77: 265.058 | R77: 265.058
B78: Supplemental Items | K78: Book Value/Share | L78: 2282.3826 | M78: 2398.5319 | N78: 2178.1977 | O78: 2353.9355 | P78: 1259.2872 | Q78: 1479.0328 | R78: 1144.6735
B79: Utility Revenue | C79: 421379.47 | D79: 458365.16 | E79: 472141.56 | F79: 516015.62 | G79: 487466.67 | H79: 495449.27 | I79: 432128.35 | K79: Tangible Book Value | L79: 593221.45 | M79: 623653.04 | N79: 551292.75 | O79: 597434.17 | P79: 271967.08 | Q79: 320592.62 | R79: 231040.03
B80: Non-Utility Revenue | C80: NA | D80: NA | E80: NA | F80: NA | G80: NA | H80: NA | I80: NA | K80: Tangible Book Value/Share | L80: 2238.0831 | M80: 2352.8928 | N80: 2079.8952 | O80: 2253.9753 | P80: 1026.0658 | Q80: 1209.5172 | R80: 871.65712
B81: EBITDA | C81: 214209.04 | D81: 252387.04 | E81: 258986.97 | F81: 294695.3 | G81: 234424.69 | H81: 213425.53 | I81: 183777.26 | K81: Total Debt | L81: 802582.76 | M81: 844292.9 | N81: 1323879.7 | O81: 1434739.2 | P81: 1374610.7 | Q81: 1477141.9 | R81: 1318003.9
B82: EBITA | C82: 89894.826 | D82: 116757.76 | E82: 131126.31 | F82: 151473.03 | G82: 161137.45 | H82: 137396.14 | I82: 112764.8 | K82: Net Debt | L82: 800052.52 | M82: 843001.34 | N82: 1263433.9 | O82: 1404941.5 | P82: 1277609.9 | Q82: 1324156.5 | R82: 1254823.1
B83: EBIT | C83: 89894.826 | D83: 116757.76 | E83: 130624.55 | F83: 150654.86 | G83: 161137.45 | H83: 137396.14 | I83: 112764.8 | K83: Debt Equiv. of Unfunded Proj. Benefit Obligation | L83: 50822.886 | M83: 35205.212 | N83: 27605.184 | O83: -11707.6 | P83: -74235.4 | Q83: -118840.2 | R83: -102196.2
B84: EBITDAR | C84: 218473 | D84: 256734.48 | E84: 262923.33 | F84: 300688.13 | G84: 240586.01 | H84: 219082.02 | I84: 188960.08 | K84: Debt Equivalent Oper. Leases | L84: 34111.68 | M84: 34779.525 | N84: 31490.858 | O84: 47942.642 | P84: 49290.535 | Q84: 45251.891 | R84: 41462.548
B85: Effective Tax Rate % | C85: 0.301081 | D85: 0.267705 | E85: 0.229303 | F85: 0.02829 | G85: 0.188027 | H85: NM | I85: NM | K85: Inventory Method | L85: NA | M85: NA | N85: NA | O85: NA | P85: NA | Q85: NA | R85: NA
B86: Current Domestic Taxes | C86: 13634.122 | D86: 13694.438 | E86: 13324.485 | F86: 9766.684 | G86: 14362.14 | H86: 2593.3066 | I86: 9993.2358 | K86: Raw Materials Inventory | L86: 1496.3422 | M86: 1724.4848 | N86: 2662.5318 | O86: 2500.5544 | P86: 2928.3951 | Q86: 2987.8691 | R86: 2717.4097
B87: Total Current Taxes | C87: 13634.122 | D87: 13694.438 | E87: 13324.485 | F87: 9766.684 | G87: 14362.14 | H87: 2593.3066 | I87: 9993.2358 | K87: Land | L87: 400435.95 | M87: 396260.16 | N87: 450260.15 | O87: 480138.33 | P87: 451865.02 | Q87: 462825.01 | R87: 400521.83
B88: Deferred Domestic Taxes | C88: 2463.4259 | D88: 10071.571 | E88: 8538.3476 | F88: -7476.9 | G88: 4288.0658 | H88: -25679.3 | I88: -15782.3 | K88: Machinery | L88: 2380313 | M88: 2553061.7 | N88: 2826833.3 | O88: 3090483.4 | P88: 2176727.6 | Q88: 2254470.8 | R88: 1996894.3
B89: Total Deferred Taxes | C89: 2463.4259 | D89: 10071.571 | E89: 8538.3476 | F89: -7476.9 | G89: 4288.0658 | H89: -25679.3 | I89: -15782.3 | K89: Construction in Progress | L89: 36005.405 | M89: 60893.152 | N89: 133104.63 | O89: 189579.92 | P89: 182915.23 | Q89: 194358.84 | R89: 248834.09
K90: Full Time Employees | L90: 748 | M90: 719 | N90: 1024 | O90: 920 | P90: 1095 | Q90: 1138 | R90: 1282
B91: Normalized Net Income | C91: 34488.622 | D91: 50420.122 | E91: 55628.5 | F91: 48949.637 | G91: 61992.798 | H91: 46691.594 | I91: 31689.988 | K91: Assets under Cap. Lease, Gross | L91: 176346.83 | M91: 181672.3 | N91: 169435.69 | O91: 177610.2 | P91: NA | Q91: NA | R91: NA
B92: Interest on Long Term Debt | C92: 34125.746 | D92: 22003.484 | E92: 25606.596 | F92: 70791.192 | G92: 60488.889 | H92: 62381.795 | I92: 62471.024 | K92: Assets under Cap. Lease, Accum. Depr. | L92: -149326.5 | M92: -156044.1 | N92: -146777.1 | O92: -154915.7 | P92: NA | Q92: NA | R92: NA
B93: Non-Cash Pension Expense | C93: 2839.7094 | D93: 1047.0086 | E93: -2638.9 | F93: -1158.2 | G93: -758.8 | H93: -2599.9 | I93: -3859.8 | K93: Accum. Allowance for Doubtful Accts | L93: NA | M93: NA | N93: 40137.329 | O93: 43077.894 | P93: 40567.901 | Q93: 43079.342 | R93: 39030.74
B94: Filing Date | C94: 41073 | D94: 41494 | E94: 41817 | F94: 42193 | G94: 42566 | H94: 42920 | I94: 43273 | K94: Filing Date | L94: 41073 | M94: 41494 | N94: 41817 | O94: 42193 | P94: 42566 | Q94: 42920 | R94: 43273
B95: Restatement Type | C95: NC | D95: NC | E95: NC | F95: NC | G95: RS | H95: NC | I95: NC | K95: Restatement Type | L95: NC | M95: NC | N95: NC | O95: RS | P95: RS | Q95: NC | R95: NC
B96: Calculation Type | C96: REP | D96: REP | E96: REP | F96: REP | G96: REP | H96: REP | I96: REP | K96: Calculation Type | L96: REP | M96: REP | N96: REP | O96: REP | P96: REP | Q96: REP | R96: REP
B98: Supplemental Operating Expense Items
B99: General and Administrative Exp. | C99: NA | D99: NA | E99: 65566.535 | F99: 69346.113 | G99: 75206.584 | H99: 86708.779 | I99: 76115.472 | K99: Currency | L99: KRW | M99: KRW | N99: KRW | O99: KRW | P99: KRW | Q99: KRW | R99: KRW
B100: R&D Exp. | C100: 390.35015 | D100: 458.2927 | E100: 375.05207 | F100: 375.43735 | G100: 8116.8724 | H100: 8686.9224 | I100: 8607.2308 | K100: Exchange Rate | L100: 1758.334 | M100: 1811.4336 | N100: 1689.4237 | O100: 1770.9309 | P100: 1646.0905 | Q100: 1637.1885 | R100: 1400.005
B101: Net Rental Exp. | C101: 4263.96 | D101: 4347.4406 | E101: 3936.3573 | F101: 5992.8302 | G101: 6161.3169 | H101: 5656.4864 | I101: 5182.8185 | K101: Conversion Method | L101: H | M101: H | N101: H | O101: H | P101: H | Q101: H | R101: H
B102: Imputed Oper. Lease Interest Exp. | C102: 1416.2484 | D102: 1440.9501 | E102: 1193.6927 | F102: 2412.6649 | G102: 2264.9992 | H102: 2015.0222 | I102: 2006.994
B103: Imputed Oper. Lease Depreciation | C103: 2847.7116 | D103: 2906.4905 | E103: 2742.6646 | F103: 3580.1653 | G103: 3896.3177 | H103: 3641.4642 | I103: 3175.8246
B106: Currency | C106: KRW | D106: KRW | E106: KRW | F106: KRW | G106: KRW | H106: KRW | I106: KRW
B107: Exchange Rate | C107: 1758.334 | D107: 1811.4336 | E107: 1689.4237 | F107: 1770.9309 | G107: 1646.0905 | H107: 1637.1885 | I107: 1400.005
B108: Conversion Method | C108: H | D108: H | E108: H | F108: H | G108: H | H108: H | I108: H

Sheet 휴비스워터-TSK
B3: TSK코퍼레이션-휴비스워터 주식교환 | G3: 과거 거래
B4: 주, 백만원 | C4: 주식수 | D4: Implied Equity Value | I4: 거래 | J4: 취득 | K4: Equity
B5: 거래전 지분가치 | I5: 가격 | J5: 지분율 | K5: Value
B6: TSK코퍼레이션 | C6: 800000 | D6: =K17 -> 500000 | G6: (1)TSK코퍼레이션 | H6: 2018.06 | I6: =Transaction!K8 -> 124999.38 | J6: =Transaction!L8 -> 0.24999876 | K6: =Transaction!M8 -> 500000
B7: 휴비스워터 | C7: 8775440 | D7: 98973 | E7: >>역산 | G7: (2)휴비스워터 | H7: 2014.10 | I7: =Transaction!K27 -> 131798.33 | J7: =Transaction!L27 -> 0.9527 | K7: =Transaction!M27 -> 138341.91
B8: 합병시너지 | D8: =K22-D6-D7 -> 119794.44 | G8: (3)TSK-휴비스워터 주식교환 | H8: 2018.11 | I8: =118767698990/10^6 -> 118767.7 | J8: 1 | K8: =J8*I8 -> 118767.7
B9: TSK코퍼레이션 | D9: =$D$8*D6/($D$6+$D$7) -> 99999.868
B10: 휴비스워터 | D10: =$D$8*D7/($D$6+$D$7) -> 19794.574
B11: 시너지 배분 후 가격 | D11: =SUM(D12:D13) -> 718767.44
B12: TSK코퍼레이션 | D12: =D6+D9 -> 599999.87
B13: 휴비스워터 | D13: =D7+D10 -> 118767.57
G16: (1)주식교환 이후 | I16: 주식수 | J16: 지분율 | K16: 지분가치
G17: TSK코퍼레이션 | I17: 800000 | J17: =I17/$I$17 -> 1 | K17: =K6 -> 500000
G18: 태영건설 | I18: =I23 -> 600000 | J18: =I18/$I$17 -> 0.75 | K18: =$K$6*J18 -> 375000
G19: SK디스커버리 | I19: =I24 -> 159999 | J19: =I19/$I$17 -> 0.19999875 | K19: =$K$6*J19 -> 99999.375
G20: SK건설 | I20: =I25 -> 40001 | J20: =I20/$I$17 -> 0.05000125 | K20: =$K$6*J20 -> 25000.625
G21: (3)주식교환 이후
G22: TSK코퍼레이션 | I22: 958357 | J22: =I22/$I$22 -> 1 | K22: =I8*I22/158357 -> 718767.44
D23: =I8-D13 -> 0.12521427 | G23: 태영건설 | I23: 600000 | J23: =I23/$I$22 -> 0.6260715 | K23: =K22*I23/$I$22 -> 449999.81
G24: SK디스커버리 | I24: 159999 | J24: =I24/$I$22 -> 0.16695136 | K24: =K23*I24/$I$22 -> 75128.078
G25: SK건설 | I25: 40001 | J25: =I25/$I$22 -> 0.041739143 | K25: =K24*I25/$I$22 -> 3135.7816
G26: 휴비스 | I26: 158357 | J26: =I26/$I$22 -> 0.16523801 | K26: =K25*I26/$I$22 -> 518.1503

Sheet 유사거래 FS>

Sheet 환경관리
B2: Net | D2: Enterprise | E2: Fiscal | N2: Source : Dart
B3: Debt | C3: NOA | D3: Vaule | E3: Year | F3: BV | G3: Salse | H3: EBITDA | I3: EBIT | J3: NI
B4: =C14 -> -8095.1262 | C4: =C17 -> 50887.301 | E4: 2015 | F4: =O48/10^6 -> 87577.76 | G4: =C30 -> 226423.01 | H4: =C34 -> 12333.079 | I4: =C33 -> 8938.5028 | J4: =O79/10^6 -> 7474.1583 | N4: 연 결 재 무 상 태 표 | R4: 연 결 현 금 흐 름 표 | V4: 7. 사용이 제한된 예금
B5: =D14 -> -19879.392 | C5: =D17 -> 40757.898 | E5: 2016 | F5: =P48/10^6 -> 94568.671 | G5: =D30 -> 210609.73 | H5: =D34 -> 10217.156 | I5: =D33 -> 7766.0377 | J5: =P79/10^6 -> 7090.1836 | N5: 환경관리주식회사와 그 종속기업(구, 코오롱워터앤에너지 주식회사와 그 종속기업) | P5: (단위 : 원) | R5: 환경관리주식회사와 그 종속기업(구, 코오롱워터앤에너지 주식회사와 그 종속기업) | T5: (단위 : 원) | V5: 당기말과 전기말 현재 사용이 제한된 예금은 다음과 같습니다.
N6: 과 목 | O6: 2015 | P6: 2016 | R6: 과 목 | S6: 2015 | T6: 2016 | V6: (단위:천원)
N7: 자 산 | R7: Ⅰ. 영업활동으로 인한 순현금흐름 | S7: 1923153634 | T7: 1069370482 | V7: 계정과목 | W7: 전기말 | X7: 당기말 | Y7: 사용제한내용
N8: Ⅰ. 유동자산 | O8: 65534271872 | P8: 62715628803 | R8: (1) 당기순이익 | S8: 7474158340 | T8: 7090183637 | V8: 현금및현금성자산 | W8: 318991 | X8: - | Y8: 프로젝트금융 질권설정
C9: 2015년 | D9: 2016년 | N9: 현금및현금성자산(주6,7,17,31,38) | O9: 21240657688 | P9: 25561149435 | R9: (2) 조정 | S9: 14506139728 | T9: 8938936726 | V9: 단기금융상품 | W9: 4884358 | X9: 5631078 | Y9: 대수선비적립금
B10: 백만원 | C10: 12월31일 | D10: 12월31일 | N10: 매출채권(주8,31,33,38) | O10: 19544584936 | P10: 15364315189 | R10: 외화환산손실 | S10: 88304682 | T10: 26885568 | W10: 576916 | X10: 1031264 | Y10: 프로젝트금융 질권설정
B11: 차입금 | C11: =(O30+O35)/10^6 -> 18606.806 | D11: =(P30+P35)/10^6 -> 12344.1 | N11: 기타수취채권(주9,32,34,34,38) | O11: 10646061132 | P11: 4574905199 | R11: 대손상각비(환입) | S11: -130298185 | T11: 30992391 | V11: 장기금융상품 | W11: 2000 | X11: 2000 | Y11: 당좌개설보증금
B12: 현금및현금성자산 | C12: =O9/10^6 -> 21240.658 | D12: =P9/10^6 -> 25561.149 | N12: 기타유동자산(주10) | O12: 7281040412 | P12: 9642337741 | R12: 기타의대손상각비 | S12: 1065778356 | T12: 4224442 | V12: 합 계 | W12: 5782265 | X12: 6664342
B13: 단기금융상품 | C13: =O13/10^6 -> 5461.2745 | D13: =P13/10^6 -> 6662.3422 | N13: 단기금융자산(주7,11,31,38) | O13: 5461274468 | P13: 6662342199 | R13: 감가상각비 | S13: 1726835306 | T13: 1056027008
B14: Net Debt | C14: =-SUM(C12:C13)+C11+C15 -> -8095.1262 | D14: =-SUM(D12:D13)+D11+D15 -> -19879.392 | N14: 재고자산(주12) | O14: 1360653236 | P14: 910579040 | R14: 운휴자산상각비 | S14: 29362895 | T14: 23003312
N15: Ⅱ. 비유동자산 | O15: 85830871652 | P15: 74304106502 | R15: 유형자산처분손실 | S15: 32439929 | T15: 17507637
N16: 매출채권(주8,31,33,38) | O16: - | P16: 66168923 | R16: 투자부동산감가상각비 | S16: 45446037 | T16: 32213070 | V16: 9. 기타수취채권
B17: NOA | C17: =SUM(C18:C22) -> 50887.301 | D17: =SUM(D18:D22) -> 40757.898 | N17: 장기금융자산(주7,13,31,38) | O17: 15175561796 | P17: 13645537600 | R17: 매도가능금융자산처분손실 | S17: 16514114 | T17: - | V17: 당기말과 전기말 현재 기타수취채권의 내역은 다음과 같습니다.
B18: 장기금융상품 | C18: =W48/10^3 -> 2 | D18: =X48/10^3 -> 2 | N18: 관계기업투자(주14) | O18: 20011786352 | P18: 21492107897 | R18: 무형자산상각비 | S18: 1667741160 | T18: 1395091290 | V18: (단위:천원)
B19: 투자부동산 | C19: =O19/10^6 -> 5655.4686 | D19: =P19/10^6 -> 5600.2522 | N19: 투자부동산(주15) | O19: 5655468629 | P19: 5600252247 | R19: 무형자산손상차손 | S19: - | T19: 1162338997 | V19: 구 분 | W19: 전기말 | Y19: 당기말
B20: 관계기업투자 | C20: =O18/10^6 -> 20011.786 | D20: =P18/10^6 -> 21492.108 | N20: 유형자산(주16,17) | O20: 9035480404 | P20: 2628029379 | R20: 무형자산처분손실 | S20: - | T20: 439866526 | W20: 유동 | X20: 비유동 | Y20: 유동 | Z20: 비유동
B21: 매도가능증권 | C21: =O17/10^6-C18 -> 15173.562 | D21: =P17/10^6-D18 -> 13643.538 | N21: 영업권및무형자산(주17,18) | O21: 18795663701 | P21: 24993868951 | R21: 영업권손상차손 | S21: 446578757 | T21: - | V21: 미수금 | W21: 9978385 | X21: - | Y21: 3627563 | Z21: 1830920
B22: 장단기대여금 | C22: =SUM(W25,X29)/10^3 -> 10044.484 | D22: =SUM(Y25,Z29)/10^3 -> 20 | N22: 기타수취채권(주9,31,38) | O22: 15522770350 | P22: 5780403724 | R22: 법인세비용 | S22: 4259215432 | T22: 1987442857 | V22: 대손충당금 | W22: -933323 | X22: - | Y22: -49040 | Z22: -728433
N23: 이연법인세자산(주36) | O23: 1634140420 | P23: 97737781 | R23: 퇴직급여 | S23: 7657508463 | T23: 5106958599 | V23: 현재가치할인차금 | W23: - | X23: - | Y23: - | Z23: -123719
N24: 자 산 총 계 | O24: 151365143524 | P24: 137019735305 | R24: 이자비용 | S24: 1389476004 | T24: 539571253 | V24: 미수수익 | W24: 189583 | X24: - | Y24: 73601 | Z24: -
N25: 부 채 | R25: 하자보수충당부채전입액 | S25: 176718651 | T25: 123985063 | V25: 단기대여금 | W25: 44500 | X25: - | Y25: 20000 | Z25: -
N26: Ⅰ. 유동부채 | O26: 46220512180 | P26: 23575921173 | R26: 공사손실충당부채전입액 | S26: 1235508429 | T26: 231013621 | V26: 미청구공사 | W26: 1364715 | X26: - | Y26: 769739 | Z26: -
N27: 매입채무(주31,33,38) | O27: 8745162202 | P27: 6132163585 | R27: 외화환산이익 | S27: -115653664 | T27: -11711851 | V27: 미수법인세환급액 | W27: 2201 | X27: - | Y27: 133042 | Z27: -
C28: 2015년 | D28: 2016년 | N28: 기타지급채무(주20,31,33,38) | O28: 16900634711 | P28: 10545482601 | R28: 이자수익 | S28: -416108154 | T28: -836120505 | V28: 보증금 | W28: - | X28: 5522786 | Y28: - | Z28: 4801636
B29: 백만원 | C29: 12개월 | D29: 12개월 | N29: 기타부채(주21,34) | O29: 10312009349 | P29: 6201344987 | R29: 유형자산처분이익 | S29: -105113805 | T29: -121262530 | V29: 장기대여금 | W29: - | X29: 9999984 | Y29: - | Z29: -
B30: 매출액 | C30: =O56/10^6 -> 226423.01 | D30: =P56/10^6 -> 210609.73 | N30: 단기금융부채(주22,31,35,38) | O30: 10262705918 | P30: 696930000 | R30: 투자부동산처분이익 | S30: -249281209 | T30: - | V30: 합 계 | W30: 10646061 | X30: 15522770 | Y30: 4574905 | Z30: 5780404
B31: 매출총이익 | C31: =O66/10^6 -> 25824.019 | D31: =P66/10^6 -> 24618.764 | N31: Ⅱ. 비유동부채 | O31: 17566871442 | P31: 18875143107 | R31: 지분법이익 | S31: -2917064288 | T31: -2214167874
B32: 판관비 | C32: =O67/10^6 -> 16885.516 | D32: =P67/10^6 -> 16852.727 | N32: 매입채무(주31,33,38) | O32: - | P32: 2149062956 | R32: 매도가능금융자산처분이익 | S32: -488861255 | T32: -
B33: 영업이익 | C33: =O68/10^6 -> 8938.5028 | D33: =P68/10^6 -> 7766.0377 | N33: 순확정급여부채(주23) | O33: 3626954249 | P33: 387725644 | R33: 염가매수차익 | S33: -205363520 | T33: - | V33: 11. 단기금융자산
B34: EBITDA | C34: =C33+C36 -> 12333.079 | D34: =D33+D36 -> 10217.156 | N34: 기타지급채무(주20,31,33,38) | O34: 1721878935 | P34: 2338596097 | R34: 하자보수충당부채환입 | S34: -298437407 | T34: - | V34: 당기말과 전기말 현재 단기금융자산의 내역은 다음과 같습니다.
N35: 장기금융부채(주22,31,35,38) | O35: 8344100000 | P35: 11647170000 | R35: 배당금수익 | S35: -405107000 | T35: -54922148 | V35: (단위:천원)
B36: D&A | C36: =SUM(S13,S18)/10^6 -> 3394.5765 | D36: =SUM(T13,T18)/10^6 -> 2451.1183 | N36: 기타부채(주21,35) | O36: 1786051947 | P36: 1019498028 | R36: (3) 운전자본의 변동 | S36: -15350335333 | T36: -12474744155 | V36: 구 분 | W36: 내역 | X36: 전기말 | Y36: 당기말
N37: 충당부채(주24,35) | O37: 633935886 | P37: 702531158 | R37: 정부보조금의 증가(감소) | S37: -326104439 | T37: -595233454 | V37: 단기금융상품 | W37: 정기적금 | X37: 742000 | Y37: 213600
N38: 이연법인세부채(주36) | O38: 1453950425 | P38: 630559224 | R38: 매출채권의 감소(증가) | S38: 14033249866 | T38: 4922959334 | W38: 정기예금 | X38: 4719274 | Y38: 6448742
N39: 부 채 총 계 | O39: 63787383622 | P39: 42451064280 | R39: 미수금의 감소(증가) | S39: 2394949075 | T39: 4730379154 | V39: 합 계 | X39: 5461274 | Y39: 6662342
N40: 자 본 | R40: 미청구공사의 감소(증가) | S40: -9472925632 | T40: 594975144
N41: Ⅰ. 지배기업소유주지분 | O41: 86093788786 | P41: 93091855726 | R41: 선급금의 감소(증가) | S41: -632589878 | T41: -1658201187
N42: 자본금(주1,25) | O42: 4344465000 | P42: 4344465000 | R42: 선급공사비의 감소(증가) | S42: -646899652 | T42: -1789782971
N43: 자본잉여금(주25) | O43: 8818644451 | P43: 8818644451 | R43: 선급비용의 감소(증가) | S43: 352803551 | T43: 284509994
N44: 자본조정(주26) | O44: -43867620972 | P44: -43886774022 | R44: 미수법인세환급액의 감소(증가) | S44: -34020 | T44: - | V44: 13. 장기금융자산
N45: 기타포괄손익누계액(주26) | O45: 315656260 | P45: 569578087 | R45: 부가세대급금의 감소(증가) | S45: 32145 | T45: -34572268 | V45: (1) 당기말과 전기말 현재 장기금융자산의 내역은 다음과 같습니다.
N46: 이익잉여금(주27) | O46: 116482644047 | P46: 123245942210 | R46: 재고자산의 감소(증가) | S46: -360143328 | T46: 450074196 | V46: (단위:천원)
N47: Ⅱ. 비지배지분(주1) | O47: 1483971116 | P47: 1476815299 | R47: 기타의당좌자산의 감소(증가) | S47: 1244608121 | T47: - | V47: 구 분 | W47: 전기말 | X47: 당기말
N48: 자 본 총 계 | O48: 87577759902 | P48: 94568671025 | R48: 매입채무의 증가(감소) | S48: -11015099142 | T48: -1313310738 | V48: 장기금융상품 | W48: 2000 | X48: 2000
N49: 부 채 및 자 본 총 계 | O49: 151365143524 | P49: 137019735305 | R49: 미지급금의 증가(감소) | S49: -5569059330 | T49: -4924414277 | V49: 매도가능금융자산 | W49: 15173562 | X49: 13643538
R50: 선수금의 증가(감소) | S50: -1284966407 | T50: 527718564 | V50: 합 계 | W50: 15175562 | X50: 13645538
N51: "첨부된 주석은 본 연결재무제표의 일부입니다." | R51: 초과청구공사의 증가(감소) | S51: 3046892720 | T51: -3170812446
R52: 예수금의 증가(감소) | S52: 443138228 | T52: -142171008
N53: 연 결 포 괄 손 익 계 산 서 | R53: 부가세예수금의 증가(감소) | S53: 912192762 | T53: -1571248240
N54: 환경관리주식회사와 그 종속기업(구, 코오롱워터앤에너지 주식회사와 그 종속기업) | P54: (단위 : 원) | R54: 기타부채의 증가(감소) | S54: 3245804832 | T54: -
N55: 과 목 | O55: 2015 | P55: 2016 | R55: 퇴직금의 지급 | S55: -404763933 | T55: -215570300
N56: Ⅰ. 매출액(주5,33,34,39) | O56: 226423006985 | P56: 210609731794 | R56: 사외적립자산의 감소(증가) | S56: -10548184037 | T56: -8310000000
N57: 운영관리수익 | O57: 209079571818 | P57: 197705863861 | R57: 퇴직금의관계사전출입액 | S57: 739828247 | T57: -248874970
N58: 건설공사수익 | O58: 15887292168 | P58: 12439483407 | R58: 하자보수충당부채의 증가(감소) | S58: -572098356 | T58: -55389791
N59: 임대수익 | O59: 294250945 | P59: 267793997 | R59: 공사손실충당부채의 증가(감소) | S59: -256642135 | T59: -
N60: 용역수익 | O60: 1161892054 | P60: 196590529 | R60: 미지급비용의 증가(감소) | S60: -674324591 | T60: 44221109
N61: Ⅱ. 매출원가(주32,33,34,39) | O61: 200598988036 | P61: 185990967391 | R61: (4) 법인세의 납부 | S61: -4706809101 | T61: -2485005726
N62: 운영관리원가 | O62: 183246041157 | P62: 174817438840 | R62: Ⅱ. 투자활동으로 인한 순현금흐름 | S62: -12525507380 | T62: 10043102479
N63: 건설공사원가 | O63: 15837757028 | P63: 10369490585 | R63: 정부보조금의 수령 | S63: 8151622142 | T63: 6006663056
N64: 임대원가 | O64: 364239445 | P64: 220963106 | R64: 이자의 수취 | S64: 652886039 | T64: 947136746
N65: 용역원가 | O65: 1150950406 | P65: 583074860 | R65: 단기금융상품의 감소 | S65: 9376995056 | T65: 5106380994
N66: Ⅲ. 매출총이익 | O66: 25824018949 | P66: 24618764403 | R66: 장기금융상품의 감소 | S66: 918000000 | T66: -
N67: Ⅳ. 판매비와일반관리비(주28,32,39) | O67: 16885516165 | P67: 16852726684 | R67: 매도가능금융자산의 처분 | S67: 2647888970 | T67: 1893280000
N68: Ⅴ. 영업이익 | O68: 8938502784 | P68: 7766037719 | R68: 투자부동산의 처분 | S68: 2750000000 | T68: -
N69: Ⅵ. 기타수익(주29,33,39) | O69: 1268865012 | P69: 524055325 | R69: 유형자산의 처분 | S69: 187862091 | T69: 258456142
N70: Ⅶ. 기타비용(주29,33,39) | O70: 1214236023 | P70: 1778105824 | R70: 무형자산의 처분 | S70: - | T70: 254545454
N71: Ⅷ. 금융수익(주30) | O71: 1585418456 | P71: 891042653 | R71: 보증금의 감소 | S71: 3678562899 | T71: 2446799408
N72: Ⅸ. 금융비용(주30) | O72: 778570762 | P72: 539571253 | R72: 단기대여금의 감소 | S72: 42500000 | T72: 24500000
N73: Ⅹ. 관계기업등투자손익(주14) | O73: 2499439547 | P73: 2214167874 | R73: 장기대여금의 감소 | S73: - | T73: 9999984000
N74: 지분법이익 | O74: 2499439547 | P74: 2214167874 | R74: 배당금의 수령 | S74: 866757172 | T74: 788768477
N75: XI. 법인세비용차감전순이익 | O75: 12299419014 | P75: 9077626494 | R75: 임대보증금의 증가 | S75: -27516190 | T75: -
N76: XII. 법인세비용(주36) | O76: 4128592910 | P76: 1987442857 | R76: 단기금융상품의 증가 | S76: -9636485577 | T76: -6307448725
N77: XIII. 계속사업손익 | O77: 8170826104 | P77: 7090183637 | R77: 장기금융상품의 증가 | S77: -519000000 | T77: -
N78: XIV. 중단사업손익 | O78: -696667764 | P78: - | R78: 매도가능금융자산의 취득 | S78: -1688596850 | T78: -37715000
N79: XV. 당기순이익 | O79: 7474158340 | P79: 7090183637 | R79: 투자부동산의 취득 | S79: -2055771000 | T79: -
N80: 지배지분순이익 | O80: 7891912471 | P80: 7097339454 | R80: 유형자산의 취득 | S80: -14452466580 | T80: -9146822782
N81: 비지배지분순손실 | O81: -417754131 | P81: -7155817 | R81: 정부보조금의 반납 | S81: -593971414 | T81: -5729549
N82: XVI. 기타포괄손익 | O82: 3320090063 | P82: -80119464 | R82: 무형자산의 취득 | S82: -1928088514 | T82: -460046552
N83: 후속적으로 당기손익으로 재분류되지 않는 포괄손익: | R83: 보증금의 증가 | S83: -1896185624 | T83: -1725649190
N84: 확정급여제도의 재측정요소 | O84: 2463787790 | P84: -334041291 | R84: 단기대여금의 증가 | S84: -500000 | T84: -
N85: 후속적으로 당기손익으로 재분류되는 포괄손익: | R85: 장기대여금의 증가 | S85: -9000000000 | T85: -
N86: 매도가능금융자산평가손익 | O86: 664053310 | P86: 253921827 | R86: Ⅲ. 재무활동으로 인한 순현금흐름 | S86: 9833118280 | T86: -6820260569
N87: 지분법자본변동 | O87: 192248963 | P87: - | R87: 단기차입금의 증가 | S87: 11078335065 | T87: -
N88: XVII. 총포괄이익 | O88: 10794248403 | P88: 7010064173 | R88: 장기차입금의 차입 | S88: 14099984000 | T88: 4000000000
N89: 지배지분포괄이익 | O89: 11091074078 | P89: 7017219990 | R89: 종속기업의 유상증자 | S89: 375412560 | T89: -
N90: 비지배지분포괄손실 | O90: -296825675 | P90: -7155817 | R90: 단기차입금의 상환 | S90: -10577683601 | T90: -
N91: XVIII. 주당손익(주37) | R91: 유동성장기부채의 상환 | S91: -279799996 | T91: -652200000
N92: 기본주당계속영업이익 | O92: 5920 | P92: 8247 | R92: 전환상환우선주의 상환 | S92: -298200000 | T92: -9802777375
N93: 기본주당중단영업손실 | O93: -226 | P93: - | R93: 이자의 지급 | S93: -916095156 | T93: -346130144
N94: 희석주당계속영업이익 | O94: 5806 | P94: 8247 | R94: 자기주식의 취득 | S94: - | T94: -19153050
N95: 희석주당중단영업손실 | O95: -226 | P95: - | R95: 배당금의 지급 | S95: -214400000 | T95: -
R96: 동일지배하의 인적분할로 인한 순현금유출 | S96: -3434434592 | T96: -
N97: "첨부된 주석은 본 연결재무제표의 일부입니다." | R97: Ⅳ. 현금및현금성자산의 순증감(Ⅰ+Ⅱ+Ⅲ) | S97: -769235466 | T97: 4292212392
R98: Ⅴ. 기초 현금및현금성자산 | S98: 22178809252 | T98: 21428433385
R99: Ⅵ. 외화표시 현금및현금성자산의 환율변동효과 | S99: 18859599 | T99: -
R100: VII. 기말 현금및현금성자산(Ⅳ+Ⅴ+Ⅵ) | S100: 21428433385 | T100: 25720645777
R102: "첨부된 주석은 본 연결재무제표의 일부입니다."

Sheet 티에스케이코퍼레이션
B2: Net | D2: Enterprise | E2: Fiscal | N2: Source : Dart
B3: Debt | C3: NOA | D3: Vaule | E3: Year | F3: BV | G3: Salse | H3: EBITDA | I3: EBIT | J3: NI
B4: =C13 -> 117925.29 | C4: =SUM(C17:C21) -> 34040.969 | E4: FY2017 | F4: =P55/10^6 -> 180145.67 | G4: =C29 -> 421868.93 | H4: =C33 -> 81770.619 | I4: =C32 -> 51166.931 | J4: =U20/10^6 -> 34617.831 | N4: 연결 재무상태표 | S4: 연 결 포 괄 손 익 계 산 서 | X4: 6. 사용이 제한되어 있거나 담보로 제공된 금융자산
B5: =D13 -> 48381.328 | C5: =SUM(D17:D21) -> 22468.547 | E5: FY2018 | F5: =Q55/10^6 -> 209037.43 | G5: =D29 -> 504407.15 | H5: =D33 -> 113382.4 | I5: =D32 -> 83868.907 | J5: =V20/10^6 -> 31015.337 | N5: 주식회사 티에스케이코퍼레이션과 그외 종속기업 | S5: 주식회사 티에스케이코퍼레이션과 그외 종속기업
O6: (단위: 원) | T6: (단위: 원) | X6: 당기말 및 전기말 현재 사용이 제한되어 있거나 부채나 우발부채에 대한 담보로 제공된 금융자산의 내역은 다음과 같습니다. | AG6: 1) 당기말 및 전기말 현재 매출채권 및 기타채권의 내역은 다음과 같습니다.
N7: 과 목 | O7: 주석 | P7: 2017 | Q7: 2018 | S7: 과 목 | T7: 주석 | U7: 2017 | V7: 2018 | X7: (단위 : 천원) | AG7: (단위 : 천원)
C8: 2017년 | D8: 2018년 | N8: 자 산 | S8: I. 매출액 | T8: 4,27,37 | U8: 421868931793 | V8: 504407145313 | X8: 구 분 | Y8: 거래처 | Z8: 2017 | AA8: 2018 | AB8: 제한내용 | AG8: 구 분 | AH8: 당기말 | AJ8: 전기말
B9: 백만원 | C9: 12월31일 | D9: 12월31일 | N9: I. 유동자산 | P9: 124194152060 | Q9: 169099918165 | S9: II. 매출원가 | T9: 28 | U9: -344104363460 | V9: -389532097445 | X9: 보통예금 | Y9: 산업은행 | Z9: 5018198 | AA9: 5209987 | AB9: 질권설정 | AH9: 유동 | AI9: 비유동 | AJ9: 유동 | AK9: 비유동
B10: 차입금 | C10: =(P37+P38+P43)/1000000 -> 178156.23 | D10: =(Q37+Q38+Q43)/1000000 -> 129223.68 | N10: 현금및현금성자산 | O10: 5,6,36,37 | P10: 47409986738 | Q10: 49901946228 | S10: III. 매출총이익 | U10: 77764568333 | V10: 114875047868 | Y10: 기업은행 | Z10: - | AA10: 108621 | AB10: 질권설정 | AG10: 매출채권 | AH10: 58178470 | AI10: 3162924 | AJ10: 45385177 | AK10: 3528510
B11: 현금및현금성자산 | C11: =(P10)/1000000 -> 47409.987 | D11: =(Q10)/1000000 -> 49901.946 | N11: 기타유동금융자산 | O11: 6,11,36 | P11: 12820957644 | Q11: 30940409433 | S11: 판매비와관리비 | T11: 28 | U11: -26597637227 | V11: -31006140620 | Y11: KEB하나은행 | Z11: 6299793 | AA11: - | AB11: 질권설정 | AG11: (현재가치할인차금) | AH11: - | AI11: -533859 | AJ11: -6745 | AK11: -649463
B12: 단기금융상품 | C12: =P11/10^6 -> 12820.958 | D12: =Q11/10^6 -> 30940.409 | N12: 매출채권및기타채권 | O12: 7,36 | P12: 54846834052 | Q12: 72802261449 | S12: IV. 영업이익 | U12: 51166931106 | V12: 83868907248 | Z12: 188804 | AA12: - | AB12: Escrow | AG12: (대손충당금) | AH12: -1616449 | AI12: - | AJ12: -2832043 | AK12: -
B13: Net Debt | C13: =C10-C11-C12+C14 -> 117925.29 | D13: =D10-D11-D12+D14 -> 48381.328 | N13: 유동성만기보유금융자산 | O13: 10,36 | P13: 1328145000 | Q13: - | S13: 금융수익 | T13: 29 | U13: 1201367544 | V13: 1516428042 | X13: 단기금융상품 | Y13: 우리은행 | Z13: 859017 | AA13: - | AB13: 김포BTO 대수선비 적립 공동명의 계좌 | AG13: 미수금 | AH13: 17004457 | AI13: - | AJ13: 12127149 | AK13: -
N14: 유동상각후원가측정금융자산 | O14: 10,36 | P14: - | Q14: 1366675000 | S14: 금융비용 | T14: 30 | U14: -7162028646 | V14: -6465775563 | Y14: KEB하나은행 | Z14: 967743 | AA14: - | AB14: KEB하나은행 장기차입금관련 질권설정 | AG14: (대손충당금) | AH14: -1191408 | AI14: - | AJ14: -244984 | AK14: -
N15: 재고자산 | O15: 12 | P15: 692026605 | Q15: 232030401 | S15: 기타영업외수익 | T15: 31 | U15: 2132416279 | V15: 477803891 | Z15: 6012623 | AA15: 6076782 | AB15: 동대문 대수선비 적립 계좌 | AG15: 미수수익 | AH15: 427191 | AI15: - | AJ15: 418280 | AK15: -
B16: NOA | N16: 미청구공사 | P16: 3126114439 | Q16: 6526338135 | S16: 기타영업외비용 | T16: 32 | U16: -3847275491 | V16: -10260149259 | Z16: 547678 | AA16: 596376 | AB16: 대천 대수선비 공동명의 계좌 | AG16: 대여금 | AH16: - | AI16: 2174054 | AJ16: - | AK16: 2373000
B17: 장기금융상품 | C17: =SUM(P25:P26)/10^6+P21/10^6+SUM(P13:P14)/10^6 -> 7203.725 | D17: =SUM(Q25:Q26)/10^6+Q21/10^6+SUM(Q13:Q14)/10^6 -> 7580.33 | N17: 기타유동자산 | O17: 13 | P17: 3953771794 | Q17: 7319153429 | S17: 관계기업투자손실 | T17: 33 | U17: -164220085 | V17: -14198394162 | Z17: 4697 | AA17: - | AB17: 선수금 질권설정 | AG17: 보증금 | AH17: - | AI17: 12971699 | AJ17: - | AK17: 8814485
B18: 투자부동산 | C18: 0 | D18: 0 | N18: 당기법인세자산 | P18: 16315788 | Q18: 11104090 | S18: V. 법인세차감전순이익 | U18: 43327190707 | V18: 54938820197 | Z18: 726330 | AA18: 762264 | AB18: 울산BTL1단계 대수선비 적립계좌 | AG18: 합 계 | AH18: 72802261 | AI18: 17774818 | AJ18: 54846834 | AK18: 14066532
B19: 관계기업투자 | C19: =P28/10^6 -> 17279.739 | D19: =Q28/10^6 -> 3083.1213 | N19: II. 비유동자산 | P19: 339040848740 | Q19: 306558237579 | S19: VI. 법인세비용 | T19: 34 | U19: -8709359988 | V19: -23923483476 | Z19: 291214 | AA19: 278613 | AB19: 울산BTL2단계 대수선비 적립계좌
B20: 매도가능증권 | C20: =SUM(P22:P24)/10^6 -> 7184.5053 | D20: =SUM(Q22:Q24)/10^6 -> 9631.0414 | N20: 매출채권및기타채권 | O20: 7,36,37 | P20: 14066532717 | Q20: 17774817980 | S20: VII. 연결당기순이익 | U20: 34617830719 | V20: 31015336721 | Y20: 신한은행 | Z20: 1907262 | AA20: - | AB20: 질권설정
B21: 장기대여금 | C21: =AK16/10^3 -> 2373 | D21: =AI16/10^3 -> 2174.054 | N21: 기타비유동금융자산 | O21: 11 | P21: 3900000 | Q21: 0 | S21: 지배기업소유지분 | U21: 33807014813 | V21: 27970498704 | Z21: - | AA21: 61619 | AB21: 선수금 질권설정
N22: 매도가능금융자산 | O22: 6,8,9,36 | P22: 7184505310 | Q22: - | S22: 비지배지분 | U22: 810815906 | V22: 3044838017 | Y22: 기업은행 | Z22: 1023805 | AA22: 1255444 | AB22: PF질권설정
N23: 비유동당기손익인식공정가치측정금융자산 | O23: 6,8,36 | P23: - | Q23: 9355382798 | S23: VIII. 기타포괄손익 | U23: -1572592158 | V23: -1814960120 | X23: 장기금융상품 | Y23: 산업은행 | Z23: 2000 | AA23: - | AB23: 당좌개설보증금
N24: 비유동기타포괄손익인식공정가치측정금융자산 | O24: 9,36 | P24: - | Q24: 275658580 | S24: 후속적으로 당기손익으로 재분류되지 않는 항목 | U24: -1572953173 | V24: -1814960120 | Y24: 부산은행 | Z24: 1900 | AA24: - | AB24: 당좌개설보증금
N25: 만기보유금융자산 | O25: 10,36 | P25: 5871680000 | Q25: - | S25: 확정급여제도의 재측정요소 | U25: -2016606632 | V25: -2327001588 | X25: 매도가능증권 | Y25: 전문건설공제조합 | Z25: 676712 | AA25: - | AB25: 융자약정한도 담보제공
N26: 비유동상각후원가측정금융자산 | O26: 10,36 | P26: - | Q26: 6213655000 | S26: 공정가치측정금융자산의 평가 | U26: - | V26: 101119 | X26: 당기손익인식공정가치측정금융자산 | Y26: 전문건설공제조합 | Z26: - | AA26: 678926 | AB26: 융자약정한도 담보제공
C27: 2017년 | D27: 2018년 | N27: 이연법인세자산 | O27: 34 | P27: 13494599063 | Q27: 11021338563 | S27: 법인세효과 | U27: 443653459 | V27: 511940349 | Y27: 엔지니어링공제조합 | Z27: - | AA27: 1767073 | AB27: 이행보증
B28: 백만원 | C28: 12개월 | D28: 12개월 | N28: 관계기업투자 | O28: 14 | P28: 17279739170 | Q28: 3083121254 | S28: 후속적으로 당기손익으로 재분류되는 항목 | U28: 361015 | V28: -
B29: 매출액 | C29: =(U8)/1000000 -> 421868.93 | D29: =(V8)/1000000 -> 504407.15 | N29: 유형자산 | O29: 15 | P29: 233264266819 | Q29: 221617025256 | S29: 매도가능증권평가이익 | U29: 361015 | V29: -
B30: 매출총이익 | C30: =(U10)/1000000 -> 77764.568 | D30: =(V10)/1000000 -> 114875.05 | N30: 무형자산 | O30: 16 | P30: 40487045676 | Q30: 30363441292 | S30: IX. 총포괄이익 | U30: 33045238561 | V30: 29200376601
B31: 판관비 | C31: =-(U11)/1000000 -> 26597.637 | D31: =-(V11)/1000000 -> 31006.141 | N31: 기타비유동자산 | O31: 13 | P31: 7388579985 | Q31: 6853796856 | S31: X. 연결총포괄이익의 귀속
B32: 영업이익 | C32: =(U12)/1000000 -> 51166.931 | D32: =(V12)/1000000 -> 83868.907 | N32: 자 산 총 계 | P32: 463235000800 | Q32: 475658155744 | S32: 지배기업 소유주지분 | U32: 32234422655 | V32: 26164613915
B33: EBITDA | C33: =C32+C35 -> 81770.619 | D33: =D32+D35 -> 113382.4 | N33: 부 채 | S33: 비지배지분 | U33: 810815906 | V33: 3035762686 | X33: 10. 상각후원가측정유가증권 및 만기보유금융자산
N34: I. 유동부채 | P34: 97750350959 | Q34: 133896828143 | S34: XI. 지배기업 소유주지분에 대한 주당이익 | AG34: 8. 당기손익-공정가치측정금융자산
B35: D&A | C35: =SUM(U48:U49)/10^3 -> 30603.688 | D35: =SUM(V48:V49)/10^3 -> 29513.492 | N35: 매입채무및기타채무 | O35: 17,36,37 | P35: 53321744101 | Q35: 68736228532 | S35: 기본 주당순이익 | T35: 35 | U35: 42259 | V35: 34963 | X35: (1) 당기말 현재 상각후원가측정유가증권 및 전기말 현재 만기보유금융자산의 내역은 다음과 같습니다.
N36: 초과청구공사 | P36: 2967927793 | Q36: 1986152544 | S36: 주석 참조 | X36: (단위: 천원) | AG36: 당기말 현재 당기손익-공정가치측정 금융자산의 내역은 다음과 같습니다.
N37: 단기차입금 | O37: 18,36,39 | P37: 10110000000 | Q37: 28326005004 | X37: 구 분 | Y37: 2017 | Z37: 2018 | AG37: (단위: 천원)
N38: 유동성장기차입금 | O38: 18,36,39 | P38: 24633464210 | Q38: 19030499646 | Y38: 유동 | Z38: 유동 | AG38: 구 분 | AH38: 2017 | AI38: 2018
N39: 당기법인세부채 | O39: 34 | P39: 6247408549 | Q39: 15371263894 | X39: 국공채 | Y39: 1328145 | Z39: 1366675 | AG39: 당기손익-공정가치측정항목 | AH39: - | AI39: 9355383
N40: 기타유동부채 | O40: 19,22 | P40: 469806306 | Q40: 446678523 | Y40: 비유동 | Z40: 비유동 | AG40: 비상장주식 등 (주1) | AH40: - | AI40: -
N41: II. 비유동부채 | P41: 185338975083 | Q41: 132723897337 | Y41: 5871680 | Z41: 6213655 | AG41: 합 계 | AH41: 0 | AI41: 9355383
N42: 매입채무및기타채무 | O42: 17,36,39 | P42: 345543783 | Q42: 423194433 | S42: 38. 현금흐름표 | AG42: (주1) | AH42: 전기말 매도가능금융자산 중 일부 항목을 기업회계기준서 제 1109호 '금융상품'의 적용에따라 최초적용일에 당기손익-공정가치 측정항목으로 분류하였습니다.
N43: 장기차입금 | O43: 18,36,39 | P43: 143412767353 | Q43: 81867178913 | X43: (2) 당기말 현재 상각후원가측정유가증권 및 전기말 현재 만기보유금융자산의 만기내역은 다음과 같습니다.
N44: 퇴직급여충당부채 | O44: 20 | P44: 3339753308 | Q44: 3285418086 | S44: (1) 당기 및 전기의 영업활동으로 인한 현금흐름 중 수익ㆍ비용의 조정 내역은 다음과 같습니다. | X44: (단위: 천원)
N45: 충당부채 | O45: 21 | P45: 37687159494 | Q45: 46924743966 | S45: (단위: 천원) | X45: 구 분 | Y45: 전 기 말 | Z45: 당 기 말 | AG45: 9. 기타포괄손익-공정가치측정금융자산 및 매도가능금융자산
N46: 기타비유동금융부채 | O46: 19 | P46: 553751145 | Q46: 223361939 | S46: 구 분 | U46: 전 기 | V46: 당 기 | X46: 1년 이내 | Y46: 1328145 | Z46: 1366675
N47: 부 채 총 계 | P47: 283089326042 | Q47: 266620725480 | S47: 퇴직급여 | U47: 6020315 | V47: 6697807 | X47: 5년 이내 | Y47: 5871680 | Z47: 6213655 | AG47: 당기말 현재 기타포괄손익-공정가치측정금융자산 및 전기말 현재 매도가능금융자산의 내역은 다음과 같습니다.
N48: 자 본 | S48: 감가상각비 | U48: 24291802 | V48: 24260076 | X48: 계 | Y48: 7199825 | Z48: 7580330
N49: I. 지배기업 소유주지분 | P49: 178500981945 | Q49: 204665522319 | S49: 무형자산상각비 | U49: 6311886 | V49: 5253416
N50: 자본금 | O50: 23 | P50: 4000000000 | Q50: 4000000000 | S50: 대손상각비 | U50: 105814 | V50: -1214747 | AG50: (단위: 천원)
N51: 기타불입자본 | O51: 24 | P51: 72550931334 | Q51: 72549355089 | S51: 기타의대손상각비 | U51: 112219 | V51: 1143941 | X51: 11. 기타금융자산 | AG51: 구 분 | AH51: 2017 | AI51: 2018
N52: 이익잉여금 | O52: 25 | P52: 101977443030 | Q52: 128143458530 | S52: 지분법손실 | U52: 313093 | V52: 14212384 | AH52: 유동 | AI52: 유동
N53: 기타자본구성요소 | O53: 25 | P53: -27392419 | Q53: -27291300 | S53: 하자보수충당부채전입액 | U53: 87526 | V53: 99750 | X53: 당기말 및 전기말 현재 기타금융자산의 내역은 다음과 같습니다. | AG53: 지분상품:
N54: II. 비지배지분 | O54: 26 | P54: 1644692813 | Q54: 4371907945 | S54: 기타충당부채전입액 | U54: 5716374 | V54: 6420676 | X54: (단위: 천원) | AG54: 비상장주식 | AH54: - | AI54: -
N55: 자 본 총 계 | P55: 180145674758 | Q55: 209037430264 | S55: 복구충당부채전입액 | U55: 921402 | V55: 1185372 | X55: 구 분 | Y55: 전기말 | Z55: 당기말 | AG55: 합 계 | AH55: - | AI55: -
N56: 부 채 및 자 본 총 계 | P56: 463235000800 | Q56: 475658155744 | S56: 당기손익-공정가치측정금융자산평가손실 | U56: - | V56: 439640 | X56: 단기금융상품 | Y56: 12820958 | Z56: 30940409 | AH56: 비유동 | AI56: 비유동
N57: 주석 참조 | S57: 지급보증비용 | U57: 1603887 | V57: 55317 | X57: 장기금융상품 | Y57: 3900 | Z57: 0 | AG57: 지분상품:
S58: 유형자산처분손실 | U58: 565071 | V58: 531136 | X58: 총 계 | Y58: 12824858 | Z58: 30940409 | AG58: 비상장주식 | AH58: 7184505 | AI58: 275659
S59: 유형자산손상차손 | U59: - | V59: 505139 | AG59: 합 계 | AH59: 7184505 | AI59: 275659
S60: 무형자산손상차손 | U60: 404000 | V60: 4340585
S61: 이자비용 | U61: 7162029 | V61: 6465776
S62: 법인세비용 | U62: 8709360 | V62: 23923483
S63: 기타 현금유출이 없는 비용 등 | U63: 1397408 | V63: - | X63: 18. 차입금
S64: 비용가산 소계 | U64: 63722186 | V64: 94319751
X65: (1) 당기말 및 전기말 현재 차입금의 구성내역은 다음과 같습니다.
X66: (단위: 천원)
X67: 구 분 | Y67: 당기말 | AA67: 전기말
Y68: 유동 | Z68: 비유동 | AA68: 유동 | AB68: 비유동
X69: 단기차입금 | Y69: 28326005 | Z69: - | AA69: 10110000 | AB69: -
X70: 장기차입금 | Y70: 19030500 | Z70: 81867179 | AA70: 24633464 | AB70: 143412767
X71: 합 계 | Y71: 47356505 | Z71: 81867179 | AA71: 34743464 | AB71: 143412767
X74: 18. 차입금
X76: (1) 당기말 및 전기말 현재 차입금의 구성내역은 다음과 같습니다.
X77: (단위: 천원)
X78: 구 분 | Y78: 당기말 | AA78: 전기말
Y79: 유동 | Z79: 비유동 | AA79: 유동 | AB79: 비유동
X80: 단기차입금 | Y80: 28326005 | Z80: - | AA80: 10110000 | AB80: -
X81: 장기차입금 | Y81: 19030500 | Z81: 81867179 | AA81: 24633464 | AB81: 143412767
X82: 합 계 | Y82: 47356505 | Z82: 81867179 | AA82: 34743464 | AB82: 143412767
X84: (2) 당기말 및 전기말 현재 단기차입금의 내역은 다음과 같습니다
X85: (단위: 천원)
X86: 차입처 | Y86: 이자율 | Z86: 당기말 | AA86: 전기말
X87: 산업은행 | Y87: 2.89~3.06% | Z87: 5000000 | AA87: 5000000
X88: 우리은행 | Y88: CD+0.74% | Z88: 16000000 | AA88: 3610000
X89: 신한은행 | Y89: 0.0335 | Z89: 2326005 | AA89: 1500000
X90: 하나은행 | Y90: 0.0323 | Z90: 5000000 | AA90: -
X91: 합계 | Z91: 28326005 | AA91: 10110000
X93: (3) 당기말 및 전기말 현재 장기차입금의 내역은 다음과 같습니다.
X94: (단위: 천원)
X95: 차입처 | Y95: 차입금 종류 | Z95: 이자율 | AA95: 만기 | AB95: 당기말 | AD95: 전기말
AB96: 유동 | AC96: 비유동 | AD96: 유동 | AE96: 비유동
X97: KEB하나은행 | Y97: 일반자금대출 | Z97: - | AA97: - | AB97: - | AC97: - | AD97: 6520000 | AE97: -
Y98: 일반자금대출 | Z98: - | AA98: - | AB98: - | AC98: - | AD98: 2936000 | AE98: 9333334
Y99: PF대출 | Z99: 0.035 | AA99: 43697 | AB99: 7000000 | AC99: - | AD99: - | AE99: 7000000
Y100: 시설자금대출 | Z100: - | AA100: - | AB100: - | AC100: - | AD100: 4532861 | AE100: 27967139
X101: 산업은행 | Y101: 일반자금대출 | Z101: 0.0263 | AA101: 44851 | AB101: - | AC101: 9970000 | AD101: - | AE101: -
Y102: PF대출 | Z102: 0.052 | AA102: 46727 | AB102: 1734971 | AC102: 15413470 | AD102: 1580958 | AE102: 17148441
Y103: 환경개선자금대출 | Z103: - | AA103: - | AB103: - | AC103: - | AD103: 506100 | AE103: 499900
X104: 신한은행 | Y104: 시설자금대출 | Z104: - | AA104: - | AB104: - | AC104: - | AD104: 1040859 | AE104: 4633047
X105: 교보생명보험 | Y105: 시설자금대출 | Z105: - | AA105: - | AB105: - | AC105: - | AD105: 1040859 | AE105: 4633047
X106: 교보생명보험 | Y106: PF대출 | Z106: 0.052 | AA106: 46727 | AB106: 2478059 | AC106: 22015060 | AD106: 2258084 | AE106: 24493117
...

Sheet WIK그린
B2: Net | D2: Enterprise | E2: Fiscal | N2: Source : Dart
B3: Debt | C3: NOA | D3: Vaule | E3: Year | F3: BV | G3: Salse | H3: EBITDA | I3: EBIT | J3: NI | N3: 재무상태표 | S3: (3) 당기말 및 전기말 현재 금융자산과 금융부채의 범주별 장부금액은 다음과 같습니다.
B4: =C14 -> -2654.192 | C4: =C17 -> 58.747546 | E4: FY2017 | F4: =P33/10^6 -> 36694.33 | G4: =C30 -> 12535.804 | H4: =C34 -> 5445.8721 | I4: =C33 -> 3709.3191 | J4: =P52/10^6 -> 3821.1703 | S4: (단위: 천원)
B5: =D14 -> -1909.4167 | C5: =D17 -> 37933.968 | E5: FY2018 | F5: =Q33/10^6 -> 36191.307 | G5: =D30 -> 12556.757 | H5: =D34 -> 5887.3167 | I5: =D33 -> 4393.2167 | J5: =Q52/10^6 -> 4490.7528 | N5: 더블유아이케이그린 주식회사 | O5: (단위: 원) | S5: 구 분 | T5: 당기말 | V5: 전기말
N6: 과 목 | O6: 주석 | P6: 2017 | Q6: 2018 | T6: 상각후원가 | U6: 상각후원가 | V6: 대여금및수취채권 | W6: 상각후원
N7: 자 산 | T7: 측정 금융자산 | U7: 측정 금융부채 | W7: 측정 금융부채
N8: I. 유 동 자 산 | P8: 3976612716 | Q8: 2822801833 | S8: (금융자산)
C9: 2017년 | D9: 2018년 | N9: 현금및현금성자산 | O9: 26 | P9: 1654192012 | Q9: 1909416695 | S9: 현금및현금성자산 | T9: 1909417 | U9: - | V9: 1654192 | W9: -
B10: 백만원 | C10: 12월31일 | D10: 12월31일 | N10: 단기금융상품 | O10: 26 | P10: 1000000000 | Q10: 0 | S10: 매출채권 | T10: 852526 | U10: - | V10: 1035029 | W10: -
B11: 차입금 | C11: 0 | D11: 0 | N11: 매출채권 | O11: 5,26 | P11: 1035029359 | Q11: 852525828 | S11: 단기금융상품 | T11: - | U11: - | V11: 1000000 | W11: -
B12: 현금및현금성자산 | C12: =P9/10^6 -> 1654.192 | D12: =Q9/10^6 -> 1909.4167 | N12: 기타유동금융자산 | O12: 6, 26 | P12: 35628823 | Q12: 550000 | S12: 기타유동금융자산 | T12: 550 | U12: - | V12: 35629 | W12: -
B13: 단기금융상품 | C13: =P10/10^6 -> 1000 | D13: =Q10/10^6 -> 0 | N13: 기타유동자산 | O13: 11 | P13: 67939022 | Q13: 58618360 | S13: 기타비유동금융자산 | T13: 58548 | U13: - | V13: 58748 | W13: -
B14: Net Debt | C14: =-SUM(C12:C13)+C11 -> -2654.192 | D14: =-SUM(D12:D13)+D11 -> -1909.4167 | N14: 당기법인세자산 | P14: 183823500 | Q14: 1690950 | S14: 합계 | T14: 2821041 | U14: - | V14: 3783598 | W14: -
N15: II. 비 유 동 자 산 | P15: 33957354995 | Q15: 34345704163 | S15: (금융부채)
N16: 유형자산 | O16: 7 | P16: 22716548172 | Q16: 23005878522 | S16: 매입채무및기타채무 | T16: - | U16: 630186 | V16: - | W16: 787280
B17: NOA | C17: =SUM(C18:C22) -> 58.747546 | D17: =SUM(D18:D22) -> 37933.968 | N17: 무형자산 | O17: 8,9 | P17: 11022480969 | Q17: 11022480969
B18: 장기금융상품 | C18: =P18/10^6 -> 58.747546 | D18: =P20/10^6 -> 37933.968 | N18: 기타비유동금융자산 | O18: 6, 26 | P18: 58747546 | Q18: 58547977
B19: 투자부동산 | C19: 0 | D19: 0 | N19: 이연법인세자산 | O19: 20 | P19: 159578308 | Q19: 258796695
B20: 관계기업투자 | C20: 0 | D20: 0 | N20: 자 산 총 계 | P20: 37933967711 | Q20: 37168505996
B21: 매도가능증권 | C21: 0 | D21: =P21/10^6 -> 0 | N21: 부 채 | S21: (1) 당기 및 전기의 영업활동 현금흐름 중 조정 및 순운전자본의 변동은 다음과 같습니다
B22: 장단기대여금 | C22: 0 | D22: =SUM(W25,X29)/10^3 -> 0 | N22: I. 유 동 부 채 | P22: 917647084 | Q22: 966377871 | S22: (단위: 천원)
N23: 매입채무및기타채무 | O23: 10, 27 | P23: 787279948 | Q23: 630186091 | S23: 구 분 | T23: 금 액
N24: 기타유동부채 | O24: 11 | P24: 130367136 | Q24: 336191780 | T24: 2017 | U24: 2018
N25: II. 비 유 동 부 채 | P25: 321990162 | Q25: 10821405 | S25: 조정: | T25: 1752290 | U25: 1670321
N26: 기타비유동부채 | O26: 11 | P26: 299893266 | Q26: - | S26: 퇴직급여 | T26: 80937 | U26: 68759
N27: 순확정급여부채 | O27: 12 | P27: 22096896 | Q27: 10821405 | S27: 대손상각비환입 | T27: - | U27: -7061
C28: 2017년 | D28: 2018년 | N28: 부 채 총 계 | P28: 1239637246 | Q28: 977199276 | S28: 감가상각비 | T28: 1735959 | U28: 1494100
B29: 백만원 | C29: 12개월 | D29: 12개월 | N29: 자 본 | S29: 무형자산상각비 | T29: 594 | U29: -
B30: 매출액 | C30: =P42/10^6 -> 12535.804 | D30: =Q42/10^6 -> 12556.757 | N30: I. 자본금 | O30: 13 | P30: 632000000 | Q30: 632000000 | S30: 유형자산처분손실 | T30: 1922 | U30: -
B31: 매출총이익 | N31: II. 기타불입자본 | O31: 14 | P31: 28108000000 | Q31: 28108000000 | S31: 기타충당부채전입액 | T31: - | U31: 209357
B32: 판관비 | N32: III. 이익잉여금 | O32: 15 | P32: 7954330465 | Q32: 7451306720 | S32: 이자수익 | T32: -17433 | U32: -10981
B33: 영업이익 | C33: =P46/10^6 -> 3709.3191 | D33: =Q46/10^6 -> 4393.2167 | N33: 자 본 총 계 | P33: 36694330465 | Q33: 36191306720 | S33: 유형자산처분이익 | T33: -9931 | U33: -
B34: EBITDA | C34: =C33+C36 -> 5445.8721 | D34: =D33+D36 -> 5887.3167 | N34: 부 채 및 자 본 총 계 | P34: 37933967711 | Q34: 37168505996 | S34: 법인세비용(수익) | T34: -39758 | U34: -83853
S35: 순운전자본의 변동: | T35: 424081 | U35: -376233
B36: D&A | C36: =SUM(T28:T29)/10^3 -> 1736.553 | D36: =SUM(U28:U29)/10^3 -> 1494.1 | N36: 주석 참조 | S36: 매출채권의 감소 | T36: 505768 | U36: 189564
S37: 선급비용의 감소 | T37: 5930 | U37: 2083
N38: 포괄손익계산서 | S38: 선급금의 감소(증가) | T38: -10566 | U38: 7237
S39: 미수금의 감소(증가) | T39: -35629 | U39: 35079
N40: 더블유아이케이그린 주식회사 | O40: (단위: 원) | S40: 보증금의 감소 | T40: - | U40: 200
N41: 과 목 | O41: 주석 | P41: 2017 | Q41: 2018 | S41: 외상매입금의 증가(감소) | T41: 92164 | U41: -196564
N42: I. 매출액 | O42: 16 | P42: 12535804436 | Q42: 12556756994 | S42: 기타충당부채의 증가(감소) | T42: - | U42: -299893
N43: II. 매출원가 | O43: 21 | P43: 7805237067 | Q43: 7368183743 | S43: 미지급금의 증가 | T43: 51847 | U43: 187924
N44: III. 매출총이익 | P44: 4730567369 | Q44: 5188573251 | S44: 부가세예수금의 감소 | T44: -126606 | U44: -1581
N45: 판매비와관리비 | O45: 17, 21 | P45: 1021248226 | Q45: 795356521 | S45: 예수금의 증가(감소) | T45: 645 | U45: -1951
N46: IV. 영업이익 | P46: 3709319143 | Q46: 4393216730 | S46: 미지급비용의 증가(감소) | T46: 53823 | U46: -148454
N47: 금융수익 | O47: 18 | P47: 17433349 | Q47: 10980858 | S47: 선수금의 감소 | T47: -33841 | U47: -
N48: 기타영업외수익 | O48: 19 | P48: 70464761 | Q48: 3149649 | S48: 확정급여채무의 감소 | T48: -23824 | U48: -77599
N49: 기타영업외비용 | O49: 19 | P49: 15805072 | Q49: 447525 | S49: 사외적립자산의 증가 | T49: -55630 | U49: -72278
N50: V. 법인세비용차감전순이익 | P50: 3781412181 | Q50: 4406899712
N51: VI. 법인세수익 | O51: 20 | P51: -39758085 | Q51: -83853041
N52: VII. 당기순이익 | P52: 3821170266 | Q52: 4490752753
N53: VIII. 기타포괄손익 | P53: 26260575 | Q53: -54477134
N54: 후속적으로 당기손익으로 재분류되지 않는 항목 | P54: 26260575 | Q54: -54477134
N55: 확정급여제도의 재측정요소 | O55: 12 | P55: 33667404 | Q55: -69842480
N56: 당기손익으로 재분류되지 않는 항목의 법인세 | O56: 20 | P56: -7406829 | Q56: 15365346
N57: IX. 총포괄이익 | P57: 3847430841 | Q57: 4436275619
N58: X. 주당순이익 | O58: 22
N59: 기본주당순이익 | P59: 30231 | Q59: 35528
N60: 희석주당순이익 | P60: 30231 | Q60: 14606
N62: 주석 참조
N65: 현 금 흐 름 표
N67: 더블유아이케이그린 주식회사 | O67: (단위: 원)
N68: 과 목 | O68: 주석 | P68: 2017 | Q68: 2018
N69: I. 영업활동으로 인한 현금흐름 | P69: 5660549246 | Q69: 5977954047
N70: 1. 영업활동으로부터 창출된 현금 | P70: 5997541378 | Q70: 5784840639
N71: 당기순이익 | P71: 3821170266 | Q71: 4490752753
N72: 조정 | O72: 25 | P72: 1752289639 | Q72: 1670320849
N73: 순운전자본의 변동 | O73: 25 | P73: 424081473 | Q73: -376232963
N74: 2. 이자의 수취 | P74: 17433349 | Q74: 10980858
N75: 3. 법인세의 납부 | P75: -354425481 | Q75: 182132550
N76: II. 투자활동으로 인한 현금흐름 | P76: -520630900 | Q76: -783430000
N77: 1. 투자활동으로 인한 현금유입액 | P77: 125390910 | Q77: 1000000000
N78: 단기금융상품의 감소 | P78: - | Q78: 1000000000
N79: 유형자산의 처분 | P79: 125390910 | Q79: -
N80: 2. 투자활동으로 인한 현금유출액 | P80: -646021810 | Q80: -1783430000
N81: 유형자산의 취득 | P81: 646021810 | Q81: 1783430000
N82: III. 재무활동으로 인한 현금흐름 | P82: -5534910356 | Q82: -4939299364
N83: 1. 재무활동으로 인한 현금유입액 | P83: - | Q83: -
N84: 2. 재무활동으로 인한 현금유출액 | P84: -5534910356 | Q84: -4939299364
N85: 배당금의 지급 | P85: 5534910356 | Q85: 4939299364
N86: IV. 현금및현금성자산의 증가(감소)(Ⅰ+Ⅱ+Ⅲ) | P86: -394992010 | Q86: 255224683
N87: V. 기초의 현금및현금성자산 | P87: 2049184022 | Q87: 1654192012
N88: VI. 기말의 현금및현금성자산 | P88: 1654192012 | Q88: 1909416695
N90: 주석 참조

Sheet 인선이엔티
B2: BS | C2: 2018.12.31 | G2: PL | H2: 2018
B3: Cash | C3: =C4+C5 -> 26968.662 | H3: 12mths
B4: 현금및현금성자산 | C4: =C41/10^6 -> 24061.062 | G4: Revenue | H4: =I26/10^6 -> 175954.97
B5: 단기금융상품 | C5: =N27/10^3 -> 2907.6 | G5: EBIT | H5: =I30/10^6 -> 23853.49
B6: Debt | C6: =SUM(C7:C8) -> 72274.99 | G6: Dep | H6: =SUM(I65:I66)/10^3 -> 6459.635
B7: 단기차입금 | C7: =SUM(C61:C62)/10^6 -> 72274.99 | G7: EBITDA | H7: =(H5+H6) -> 30313.125
B8: 장기차입금 | C8: 0 | G8: NI(Loss) | H8: =I36/10^6 -> 19964.863
B9: 사채 | C9: =C63/10^6 -> 18328.878
B10: NOA | C10: =SUM(C11:C15) -> 2785.2241
B11: 장기금융상품 | C11: =O28/10^3 -> 662.857
B12: 매도가능금융자산 | C12: =O29/10^3 -> 1421.074
B13: 투자부동산 | C13: 0
B14: 관계기업투자 | C14: =C31/10^6 -> 217.32705
B15: 장단기대여금 | C15: =SUM(N30:O31)/10^3 -> 483.966
B16: BV | C16: =C50/10^6 -> 186940.06
B18: Source : Dart
B20: 연결 재무상태표 | G20: 연결 포괄손익계산서
B21: 제 22 기 2018.12.31 현재 | G21: 제 22 기 2018.01.01 부터 2018.12.31 까지
B22: 제 21 기 2017.12.31 현재 | G22: 제 21 기 2017.01.01 부터 2017.12.31 까지
B23: 제 20 기 2016.12.31 현재 | G23: 제 20 기 2016.01.01 부터 2016.12.31 까지
B24: (단위 : 원) | G24: (단위 : 원)
C25: 제 22 기 | D25: 제 21 기 | E25: 제 20 기 | I25: 제 22 기 | J25: 제 21 기 | K25: 제 20 기 | M25: 구 분 | N25: 당 기 말 | P25: 전 기 말
B26: 자산 | G26: 매출액 | I26: 175954965244 | J26: 160280182183 | K26: 135518950239 | N26: 유 동 | O26: 비 유 동 | P26: 유 동 | Q26: 비 유 동
B27: 비유동자산 | C27: 246540218177 | D27: 244197069564 | E27: 245154928672 | G27: 매출원가 | I27: 135494696794 | J27: 121392406280 | K27: 101462555546 | M27: 단기금융상품 (*1) | N27: 2907600 | O27: - | P27: 2607600 | Q27: -
B28: 유형자산 | C28: 229775553893 | D28: 220172721125 | E28: 208912572083 | G28: 매출총이익 | I28: 40460268450 | J28: 38887775903 | K28: 34056394693 | M28: 장기금융상품 (*2) | N28: - | O28: 662857 | P28: - | Q28: 7920317
B29: 영업권 | C29: 2019841407 | D29: 2019841407 | E29: 2019841407 | G29: 판매비와관리비 | I29: 16606777982 | J29: 16973112972 | K29: 15992451697 | M29: 매도가능금융자산 | N29: - | O29: 1421074 | P29: - | Q29: 507473
B30: 무형자산 | C30: 115612498 | D30: 423315836 | E30: 713753670 | G30: 영업이익(손실) | I30: 23853490468 | J30: 21914662931 | K30: 18063942996 | M30: 대여금 | N30: 1167863 | O30: 471103 | P30: 1824863 | Q30: 437956
B31: 관계기업투자 | C31: 217327052 | D31: 556166223 | E31: 6526768408 | G31: 기타이익 | I31: 341074920 | J31: 1255730117 | K31: 352110868 | M31: (대손충당금) | N31: -1115000 | O31: -40000 | P31: -1185000 | Q31: -180000
B32: 장기매출채권 및 기타채권 | C32: 10195896412 | D32: 10626643520 | E32: 22199645869 | G32: 기타비용 | I32: 1567814262 | J32: 9802594236 | K32: 6191340311 | M32: 합 계 | N32: 2960463 | O32: 2515034 | P32: 3247463 | Q32: 8685746
B33: 기타비유동금융자산 | C33: 2515034246 | D33: 8685745901 | E33: 2453960193 | G33: 금융수익 | I33: 1598390513 | J33: 141953494 | K33: 1816252101
B34: 이연법인세자산 | C34: 1700952669 | D34: 1712635552 | E34: 2328387042 | G34: 금융원가 | I34: 3921438989 | J34: 5193370975 | K34: 7135913606
B35: 유동자산 | C35: 69081354677 | D35: 54148067907 | E35: 55892016899 | G35: 투자손익 | I35: -338839171 | J35: -5615695985 | K35: 578306614
B36: 재고자산 | C36: 11722277279 | D36: 13231722336 | E36: 15958428488 | G36: 법인세비용차감전순이익(손실) | I36: 19964863479 | J36: 2700685346 | K36: 7483358662
B37: 매출채권 및 기타유동채권 | C37: 27274253842 | D37: 27724131942 | E37: 28330035580 | G37: 법인세비용 | I37: 4489603960 | J37: -450506666 | K37: 6122292143
B38: 기타유동금융자산 | C38: 2960463410 | D38: 3247463410 | E38: 4219216410 | G38: 계속영업이익(손실) | I38: 15475259519 | J38: 3151192012 | K38: 1361066519
B39: 당기법인세자산 | C39: 64515 | D39: 318838324 | E39: 347870 | G39: 중단영업이익(손실) | K39: -888599696
B40: 기타유동자산 | C40: 3063233781 | D40: 3966785287 | E40: 3502342995 | G40: 당기순이익(손실) | I40: 15475259519 | J40: 3151192012 | K40: 472466823
B41: 현금및현금성자산 | C41: 24061061850 | D41: 5659126608 | E41: 3881645556 | G41: 기타포괄손익 | I41: -832658382 | J41: 157599567 | K41: 722521040
B42: 자산총계 | C42: 315621572854 | D42: 298345137471 | E42: 301046945571 | G42: 당기손익으로 재분류될 수 있는 항목(세후기타포괄손익)
B43: 자본 | G43: 해외사업장환산외환차이(세후기타포괄손익) | I43: -649411462 | J43: 292174939 | K43: 692479246
B44: 지배기업의 소유주에게 귀속되는 자본 | C44: 182359225884 | D44: 164314240001 | E44: 144902928961 | G44: 당기손익으로 재분류되지 않는항목(세후기타포괄손익)
B45: 자본금 | C45: 18299694000 | D45: 17889866500 | E45: 17092099000 | G45: 매도가능금융자산평가손익 | I45: -215407112
B46: 자본잉여금 | C46: 53913460842 | D46: 50881395194 | E46: 35374690366 | G46: 확정급여제도의 재측정손익(세후기타포괄손익) | I46: 32160192 | J46: -134575372 | K46: 30041794
B47: 기타포괄손익누계액 | C47: 456699860 | D47: 1177022284 | E47: 884847345 | G47: 총포괄손익 | I47: 14642601137 | J47: 3308791579 | K47: 1194987863
B48: 이익잉여금(결손금) | C48: 109689371182 | D48: 94365956023 | E48: 91551292250 | G48: 당기순이익(손실)의 귀속
B49: 비지배지분 | C49: 4580835419 | D49: 5434327409 | E49: 778077364 | G49: 지배기업의 소유주에게 귀속되는 당기순이익(손실) | I49: 15297281954 | J49: 2948361170 | K49: 444848042
B50: 자본총계 | C50: 186940061303 | D50: 169748567410 | E50: 145681006325 | G50: 계속영업이익 | I50: 15297281954 | J50: 2948361170 | K50: 1333447738
B51: 부채 | G51: 중단영업이익 | K51: -888599696
B52: 비유동부채 | C52: 16568369727 | D52: 52059218015 | E52: 43876942225 | G52: 비지배지분에 귀속되는 당기순이익(손실) | I52: 177977565 | J52: 202830842 | K52: 27618781
B53: 장기매입채무 및 기타비유동채무 | C53: 765000000 | D53: 755000000 | E53: 725000000 | G53: 계속영업이익 | I53: 177977565 | J53: 202830842 | K53: 27618781
B54: 장기차입금 | D54: 36874830000 | E54: 10708150000 | G54: 총 포괄손익의 귀속
B55: 전환사채 | E55: 13435650833 | G55: 지배기업의 소유주에게 귀속되는 지분 | I55: 14458596585 | J55: 3106838712 | K55: 1162916766
B56: 이연법인세부채 | C56: 7023014036 | D56: 5959841266 | E56: 7675689848 | G56: 비지배지분 | I56: 184004552 | J56: 201952867 | K56: 32071097
B57: 순확정급여부채 | C57: 929319771 | D57: 1479384336 | E57: 2143272677 | G57: 주당이익
B58: 비유동충당부채 | C58: 7851035920 | D58: 6990162413 | E58: 9189178867 | G58: 계속영업기본주당이익(손실) (단위 : 원) | I58: 421 | J58: 84 | K58: 39
B59: 유동부채 | C59: 112113141824 | D59: 76537352046 | E59: 111488997021 | G59: 중단영업기본주당이익(손실) (단위 : 원) | K59: -26
B60: 매입채무 및 기타유동채무 | C60: 11659598671 | D60: 7757345245 | E60: 9483355069 | G60: 기본주당이익(손실) (단위 : 원) | I60: 421 | J60: 84 | K60: 13
B61: 단기차입금 | C61: 40900000000 | D61: 34900000000 | E61: 55762241927 | G61: 희석주당이익(손실) (단위 : 원) | I61: 378 | J61: 84 | K61: 13
B62: 유동성장기차입금 | C62: 31374990000 | D62: 3833480000 | E62: 3833480000
B63: 유동성전환사채 | C63: 18328878453 | D63: 21916404412 | E63: 31534424054 | G63: 영업으로부터 창출된 현금 | J63: (단위 : 천원)
B64: 기타유동금융부채 | C64: 1125741230 | D64: 3577110655 | E64: 4302472250 | G64: 구 분 | I64: 제 22 기 | J64: 제 21 기
B65: 당기법인세부채 | C65: 3400546038 | D65: 351297675 | E65: 2526473913 | G65: 감가상각비 | I65: 6143983 | J65: 5984958
B66: 유동충당부채 | C66: 2742975210 | D66: 2009995308 | E66: 1840777134 | G66: 무형자산상각비 | I66: 315652 | J66: 310906
B67: 기타유동부채 | C67: 2580412222 | D67: 2191718751 | E67: 2205772674
B68: 부채총계 | C68: 128681511551 | D68: 128596570061 | E68: 155365939246
B69: 자본과부채총계 | C69: 315621572854 | D69: 298345137471 | E69: 301046945571

Sheet 창원에너텍
B2: Net | D2: Enterprise | E2: Fiscal | N2: Source : Dart
B3: Debt | C3: NOA | D3: Vaule | E3: Year | F3: BV | G3: Salse | H3: EBITDA | I3: EBIT | J3: NI
B4: =C14 -> 40797.741 | C4: =C17 -> 411.16225 | E4: FY2017 | F4: =O66/10^6 -> 10223.491 | G4: =C30 -> 11812.948 | H4: =C34 -> 4549.2593 | I4: =C33 -> 941.82406 | J4: =O120/10^6 -> -17.681055 | N4: 재 무 상 태 표 | R4: 현 금 흐 름 표
B5: =D14 -> 35786.697 | C5: =D17 -> 508.74475 | E5: FY2018 | F5: =P66/10^6 -> 10987.624 | G5: =D30 -> 14685.915 | H5: =D34 -> 6104.4256 | I5: =D33 -> 2059.2282 | J5: =P120/10^6 -> 767.8966 | N5: 주식회사 창원에너텍 | P5: (단위 : 원) | R5: 주식회사 창원에너텍 | T5: (단위 : 원)
N6: 과 목 | O6: 제 4(전) 기 | P6: 제 5(당) 기 | R6: 과 목 | S6: 제 4(전) 기 | T6: 제 5(당) 기
N7: 자산 | R7: Ⅰ.영업활동으로 인한 현금흐름 | S7: 3769956298 | T7: 5170081145 | V7: 계정과목 | W7: 예금종류 | X7: 예입처 | Y7: 금액 | AA7: 사용제한내용
N8: Ⅰ.유동자산 | O8: 5280052361 | P8: 8050684741 | R8: 1.당기순이익(손실) | S8: -17681055 | T8: 767896604 | Y8: 당기 | Z8: 전기
C9: 2017년 | D9: 2018년 | N9: (1)당좌자산 | O9: 5280052361 | P9: 8050684741 | R9: 2.현금의 유출이 없는 비용등의 가산 | S9: 4033685146 | T9: 4386718315 | V9: 현금및현금성자산 | W9: 보통예금 | X9: KEB하나은행 | Y9: 5047297 | Z9: 2339630 | AA9: 질권설정
B10: 백만원 | C10: 12월31일 | D10: 12월31일 | N10: 1.현금및현금성자산(주석3,7) | O10: 3202259192 | P10: 6213303093 | R10: (1)퇴직급여 | S10: 189345110 | T10: 313605630
B11: 차입금 | C11: =(O49+O51)/10^6 -> 44000 | D11: =(P49+P51)/10^6 -> 42000 | N11: 2.매출채권 | O11: 1869941391 | P11: 1495077325 | R11: (2)감가상각비 | S11: 3607408472 | T11: 4044876289
B12: 현금및현금성자산 | C12: =O10/10^6 -> 3202.2592 | D12: =P10/10^6 -> 6213.3031 | N12: 대손충당금 | O12: -64317561 | P12: -17277505 | R12: (3)무형자산상각비 | S12: 26766 | T12: 321200
B13: 단기금융상품 | C13: 0 | D13: 0 | N13: 3.미수금 | O13: 177488854 | P13: 286330633 | R13: (4)유형자산처분손실 | S13: 258760360 | T13: -
B14: Net Debt | C14: =-SUM(C12:C13)+C11+C15 -> 40797.741 | D14: =-SUM(D12:D13)+D11+D15 -> 35786.697 | N14: 4.선급금 | O14: 18395000 | P14: - | R14: (5)대손상각비 | S14: -21855562 | T14: 1726230
N15: 5.선급비용 | O15: 75852855 | P15: 72430565 | R15: (6)이자비용 | S15: - | T15: 26188966
N16: 6.당기법인세자산 | O16: 432630 | P16: 820630 | R16: 3.현금의 유입이 없는 수익등의 차감 | S16: -4148095 | T16: -3272596
B17: NOA | C17: =SUM(C18:C22) -> 411.16225 | D17: =SUM(D18:D22) -> 508.74475 | N17: (2)재고자산 | O17: - | P17: - | R17: (1)유형자산처분이익 | S17: -4148095 | T17: -
B18: 장기금융상품 | C18: =O20/10^6 -> 379.3982 | D18: =P20/10^6 -> 508.74475 | N18: Ⅱ.비유동자산 | O18: 52527311246 | P18: 52377292084 | R18: (2)매도가능증권처분이익 | S18: - | T18: 3272596
B19: 투자부동산 | C19: 0 | D19: 0 | N19: (1)투자자산 | O19: 411162251 | P19: 508744748 | R19: 4.영업활동으로 인한 자산부채의 변동 | S19: -241899698 | T19: 18738822
B20: 관계기업투자 | C20: 0 | D20: 0 | N20: 1.장기금융상품 | O20: 379398200 | P20: 508744748 | R20: (1)매출채권의 감소(증가) | S20: -676875045 | T20: 326097780
B21: 매도가능증권 | C21: =O21/10^6 -> 31.764051 | D21: =P21/10^6 -> 0 | N21: 2.매도가능증권(주석4) | O21: 31764051 | P21: 0 | R21: (2)미수금의 감소(증가) | S21: -155847745 | T21: -108841779
B22: 장단기대여금 | C22: 0 | D22: 0 | N22: (2)유형자산(주석5) | O22: 52055583779 | P22: 51822803320 | R22: (3)선급금의 감소(증가) | S22: 73425000 | T22: 18395000
N23: 1.토지 | O23: 6910803678 | P23: 6910803678 | R23: (4)선급비용의 감소(증가) | S23: -40678583 | T23: 3422290
N24: 2.건물 | O24: 6006958551 | P24: 6475297230 | R24: (5)부가세대급금의 감소(증가) | S24: 233061226 | T24: -
N25: 감가상각누계액 | O25: -313909527 | P25: -616208863 | R25: (6)당기법인세자산의 감소(증가) | S25: 301620 | T25: -388000
N26: 3.구축물 | O26: 15195635032 | P26: 15239744621 | R26: (7)매입채무의 증가(감소) | S26: 95115763 | T26: 70679096
N27: 감가상각누계액 | O27: -632838958 | P27: -1392804497 | R27: (8)예수금의 증가(감소) | S27: 6417579 | T27: 5563248
C28: 2017년 | D28: 2018년 | N28: 4.기계장치 | O28: 27942759163 | P28: 31199642725 | R28: (9)선수금의 증가(감소) | S28: 30081201 | T28: 22244476
B29: 백만원 | C29: 12개월 | D29: 12개월 | N29: 감가상각누계액 | O29: -3497645699 | P29: -6323353974 | R29: (10)미지급비용의 증가(감소) | S29: 42540511 | T29: 4141209
B30: 매출액 | C30: =O75/10^6 -> 11812.948 | D30: =P75/10^6 -> 14685.915 | N30: 정부보조금 | O30: -41666666 | P30: -36666666 | R30: (11)미지급금의 증가(감소) | S30: 167987848 | T30: -229787928
B31: 매출총이익 | N31: 5.차량운반구 | O31: 560379838 | P31: 592843838 | R31: (12)퇴직금의 지급 | S31: -17429073 | T31: -92786570
B32: 판관비 | N32: 감가상각누계액 | O32: -223172860 | P32: -340118427 | R32: Ⅱ.투자활동으로 인한 현금흐름 | S32: -17055953691 | T32: -3895669782
B33: 영업이익 | C33: =O106/10^6 -> 941.82406 | D33: =P106/10^6 -> 2059.2282 | N33: 6.공구와기구 | O33: 63371273 | P33: 73671273 | R33: 1.투자활동으로 인한 현금 유입액 | S33: 250775217 | T33: 45772596
B34: EBITDA | C34: =C33+C36 -> 4549.2593 | D34: =D33+D36 -> 6104.4256 | N34: 감가상각누계액 | O34: -28957437 | P34: -42423357 | R34: (1)보증금의 감소 | S34: 50000000 | T34: 14500000
N35: 7.비품 | O35: 157472992 | P35: 157472992 | R35: (2)기계장치의 처분 | S35: 188314884 | T35: -
B36: D&A | C36: =SUM(S11:S12)/10^6 -> 3607.4352 | D36: =SUM(T11:T12)/10^6 -> 4045.1975 | N36: 감가상각누계액 | O36: -43605601 | P36: -75097253 | R36: (3)차량운반구의 처분 | S36: 12460333 | T36: -
N37: (3)무형자산 | O37: 1579234 | P37: 1258034 | R37: (4)매도가능증권의 처분 | S37: - | T37: 31272596
N38: 1.기타의무형자산 | O38: 1579234 | P38: 1258034 | R38: 2.투자활동으로 인한 현금 유출액 | S38: -17306728908 | T38: -3941442378
N39: (4)기타비유동자산 | O39: 58985982 | P39: 44485982 | R39: (1)장기금융상품의 증가 | S39: 113819460 | T39: 129346548
N40: 1.기타보증금 | O40: 58985982 | P40: 44485982 | R40: (2)매도가능증권의 취득 | S40: 9600000 | T40: -
N41: 자산총계 | O41: 57807363607 | P41: 60427976825 | R41: (3)토지의취득 | S41: 40258360 | T41: -
N42: 부채 | R42: (4)건물의 취득 | S42: 2079301963 | T42: 468338679
N43: Ⅰ.유동부채 | O43: 5157718531 | P43: 6816423760 | R43: (5)구축물의취득 | S43: 5137637293 | T43: 44109589
N44: 1.매입채무 | O44: 581146563 | P44: 651825659 | R44: (6)기계장치의 취득 | S44: 9757889614 | T44: 3256883562
N45: 2.미지급금 | O45: 2456508416 | P45: 2012585616 | R45: (7)차량운반구의 취득 | S45: 60758590 | T45: 32464000
N46: 3.예수금 | O46: 23990022 | P46: 29553270 | R46: (8)공구와기구의 취득 | S46: 5071273 | T46: 10300000
N47: 4.선수금 | O47: 30081201 | P47: 52325677 | R47: (9)비품의 취득 | S47: 99986355 | T47: -
N48: 5.미지급비용 | O48: 65992329 | P48: 70133538 | R48: (10)무형자산의 취득 | S48: 1606000 | T48: -
N49: 6.유동성장기차입금(주석6,7) | O49: 2000000000 | P49: 4000000000 | R49: (11)보증금의증가 | S49: 800000 | T49: -
N50: Ⅱ.비유동부채 | O50: 42426154028 | P50: 42623929464 | R50: Ⅲ. 재무활동으로 인한 현금흐름 | S50: 14874168940 | T50: 1736632538
N51: 1.장기차입금(주석6,7) | O51: 42000000000 | P51: 38000000000 | R51: 1.재무활동으로 인한 현금 유입액 | S51: 55137860417 | T51: 4068395742
N52: 2.퇴직급여충당부채(주석8) | O52: 409133498 | P52: 629952558 | R52: (1)미지급금의 증가 | S52: 2100860417 | T52: -
N53: 3.장기미지급금(주석9) | O53: 17020530 | P53: 4433635025 | R53: (2)장기차입금의 증가 | S53: 53037000000 | T53: -
N54: 현재가치할인차금 | O54: - | P54: -439658119 | R54: (3)장기미지급금의 증가 | S54: - | T54: 4068395742
N55: 부채총계 | O55: 47583872559 | P55: 49440353224 | R55: 2.재무활동으로 인한 현금 유출액 | S55: -40263691477 | T55: -2331763204
N56: 자본 | R56: (1)장기차입금의 상환 | S56: 37000000000 | T56: -
N57: Ⅰ.자본금 | O57: 8396940000 | P57: 8396940000 | R57: (2)유동성장기차입금의 상환 | S57: - | T57: 2000000000
N58: 1.보통주자본금(주석10) | O58: 6000000000 | P58: 6000000000 | R58: (3)미지급금의상환 | S58: 3263691477 | T58: 331763204
N59: 2.우선주자본금(주석10) | O59: 2396940000 | P59: 2396940000 | R59: Ⅳ. 현금의 증가(감소) | S59: 1588171547 | T59: 3011043901
N60: Ⅱ.자본잉여금 | O60: 5559113354 | P60: 5559113354 | R60: Ⅴ. 기초의 현금 | S60: 1614087645 | T60: 3202259192
N61: 1.주식발행초과금(주석10) | O61: 5559113354 | P61: 5559113354 | R61: Ⅵ. 기말의 현금 | S61: 3202259192 | T61: 6213303093
N62: Ⅲ.기타포괄손익누계액 | O62: 3764051 | P62: - | R62: 별첨 주석은 본 재무제표의 일부분입니다.
N63: 1.매도가능증권평가손익(주석4) | O63: 3764051 | P63: -
N64: Ⅳ.결손금 | O64: 3736326357 | P64: 2968429753
N65: 1.미처리결손금 | O65: -3736326357 | P65: -2968429753
N66: 자본총계 | O66: 10223491048 | P66: 10987623601
N67: 부채및자본총계 | O67: 57807363607 | P67: 60427976825
N68: 별첨 주석은 본 재무제표의 일부분입니다.
N72: 손 익 계 산 서
N73: 주식회사 창원에너텍 | P73: (단위 : 원)
N74: 과 목 | O74: 제 4(전) 기 | P74: 제 5(당) 기
N75: Ⅰ.매출액 | O75: 11812948218 | P75: 14685915041
N76: 1.제품매출 | O76: 5593118274 | P76: 8151103510
N77: 2.운반매출 | O77: 82127997 | P77: 98644372
N78: 3.스팀매출 | O78: 6137701947 | P78: 6427857549
N79: 4.전기발전매출 | O79: - | P79: 8309610
N80: Ⅱ.매출원가 | O80: 9179821964 | P80: 11354139410
N81: Ⅲ.매출총이익 | O81: 2633126254 | P81: 3331775631
N82: Ⅳ.판매비와관리비 | O82: 1691302191 | P82: 1272547480
N83: 1.임원급여 | O83: 240930580 | P83: 304445320
N84: 2.직원급여 | O84: 202216816 | P84: 263507820
N85: 3.상여금 | O85: 53282230 | P85: 36888270
N86: 4.제수당 | O86: 142684 | P86: 2059616
N87: 5.퇴직급여 | O87: 73669718 | P87: 186541007
N88: 6.복리후생비 | O88: 81140899 | P88: 88600299
N89: 7.여비교통비 | O89: 15060043 | P89: 6359923
N90: 8.접대비 | O90: 1068000 | P90: 9425708
N91: 9.통신비 | O91: 6750062 | P91: 7125303
... N94: 12.지급임차료 | O94: 1552728 | P94: 1440000
N95: 13.수선비 | O95: 2275000 | P95: -
N96: 14.보험료 | O96: 11193155 | P96: 26198954
N97: 15.차량유지비 | O97: 19721452 | P97: 26474000
N98: 16.운반비 | O98: 56600 | P98: 32100
N99: 17.교육훈련비 | O99: 613000 | P99: 23020
N100: 18.도서인쇄비 | O100: 200000 | P100: 634800
N101: 19.사무용품비 | O101: 2145038 | P101: 850495
N102: 20.소모품비 | O102: 9045071 | P102: 3008454
N103: 21.지급수수료 | O103: 841123795 | P103: 127231752
N104: 22.대손상각비 | O104: -21855562 | P104: 1726230
N105: 23.무형자산상각비 | O105: 26766 | P105: 321200
N106: Ⅴ.영업이익 | O106: 941824063 | P106: 2059228151
...

Sheet 삼우그린
B2: Net | D2: Enterprise | E2: Fiscal | N2: Source : Dart
B3: Debt | C3: NOA | D3: Vaule | E3: Year | F3: BV | G3: Salse | H3: EBITDA | I3: EBIT | J3: NI
B4: =C14 -> -2133.5236 | C4: =C17 -> 15479.426 | E4: FY2016 | F4: =O68/10^6 -> 19200.838 | G4: =C30 -> 7431.4802 | H4: =C34 -> 3291.6417 | I4: =C33 -> 2615.5111 | J4: =S53/10^6 -> 2563.0496 | N4: 재 무 상 태 표 | R4: 손 익 계 산 서 | V4: 현 금 흐 름 표
B5: =D14 -> 152.01951 | C5: =D17 -> 16841.9 | E5: FY2017 | F5: =P68/10^6 -> 22114.32 | G5: =D30 -> 8007.8196 | H5: =D34 -> 3606.4627 | I5: =D33 -> 3110.421 | J5: =T53/10^6 -> 2913.4828 | N5: 제 24 기 2017년 12월 31일 현재 | R5: 제 24 기 2017년 01월 01일부터 2017년 12월 31일까지 | V5: 제 24기 2017년 01월 01일부터 2017년 12월 31일까지
N6: 제 23 기 2016년 12월 31일 현재 | R6: 제 23 기 2016년 01월 01일부터 2016년 12월 31일까지 | V6: 제 23기 2016년 01월 01일부터 2016년 12월 31일까지
N7: 회사명 : (주)삼우그린 | P7: (단위 : 원) | R7: 회사명 : (주)삼우그린 | T7: (단위 : 원) | V7: 회사명 : (주)삼우그린 | X7: (단위 : 원)
N8: 과 목 | O8: 2016 | P8: 2017 | R8: 과 목 | S8: 2016 | T8: 2017 | V8: 과 목 | W8: 2016 | X8: 2017
C9: 2016년 | D9: 2017년 | N9: 자 산 | R9: Ⅰ.매 출 액(주2) | S9: 7431480177 | T9: 8007819574 | V9: I. 영 업 활 동 으 로 인 한 현 금 흐 름 | W9: 2863438760 | X9: 10623555
B10: 백만원 | C10: 12월31일 | D10: 12월31일 | N10: I. 유 동 자 산 | O10: 15895871332 | P10: 18909098823 | R10: 1.폐 기 물 처 분 수 입 | S10: 7431480177 | T10: 8007819574 | V10: 1. 당 기 순 이 익 | W10: 2563049577 | X10: 2913482762
B11: 차입금 | C11: =(O55+O57)/10^6 -> 0 | D11: =(P55+P57)/10^6 -> 3000 | N11: (1) 당 좌 자 산 | O11: 15895871332 | P11: 18909098823 | R11: Ⅱ.매 출 원 가 | S11: 3339567144 | T11: 3760312223 | V11: 2. 현금의 유출이없는 비용 등의 가산 | W11: 679655512 | X11: 596041691
B12: 현금및현금성자산 | C12: =O12/10^6 -> 433.52362 | D12: =P12/10^6 -> 2847.9805 | N12: 1.현 금 및 현 금 등 가 물 | O12: 433523621 | P12: 2847980486 | R12: 1.폐 기 물 처 분 원 가 | S12: 3339567144 | T12: 3760312223 | V12: 가.유 형 자 산 감 가 상 각 비 | W12: 676130570 | X12: 495355292
B13: 단기금융상품 | C13: =O13/10^6 -> 1700 | D13: =P13/10^6 -> 0 | N13: 2.단 기 금 융 상 품(주3) | O13: 1700000000 | P13: 0 | R13: Ⅲ.매 출 총 이 익 | S13: 4091913033 | T13: 4247507351 | V13: 나.대 손 상 각 | W13: 3524942 | X13: 0
B14: Net Debt | C14: =-SUM(C12:C13)+C11 -> -2133.5236 | D14: =-SUM(D12:D13)+D11 -> 152.01951 | N14: 3.매 출 채 권 (주2) | O14: 2083346544 | P14: 1982912595 | R14: Ⅳ.판 매 비 와 관 리 비 | S14: 1476401910 | T14: 1137086367 | V14: 다.무 형 자 산 상 각 비 | W14: 0 | X14: 686399
N15: 대 손 충 당 금 | O15: 20833465 | P15: 19829125 | R15: 1.급 여 | S15: 774647310 | T15: 765522690 | V15: 라.지 분 법 손 실 | W15: 0 | X15: 100000000
N16: 4.단 기 대 여 금 | O16: 1093826300 | P16: 701926300 | R16: 2.퇴 직 급 여 | S16: 447268206 | T16: 134511507 | V16: 3. 현금의 유입이없는 수익등의 차감 | W16: 25796 | X16: 8431067
B17: NOA | C17: =SUM(C18:C22) -> 15479.426 | D17: =SUM(D18:D22) -> 16841.9 | N17: 대 손 충 당 금 | O17: 0 | P17: 680026300 | R17: 3.복 리 후 생 비 | S17: 30814100 | T17: 44863630 | V17: 가.유 형 자 산 처 분 이 익 | W17: 25796 | X17: 7426727
B18: 장기금융상품 | C18: =O25/10^6 -> 320.6 | D18: =P25/10^6 -> 0 | N18: 5.미 수 수 익(주13) | O18: 619926874 | P18: 1044337534 | R18: 4.여 비 교 통 비 | S18: 1005200 | T18: 1023800 | V18: 나.대 손 충 당 금 환 입 | W18: 0 | X18: 1004340
B19: 투자부동산 | C19: 0 | D19: 0 | N19: 6.관 계 회 사 대 여 금(주13) | O19: 7965000000 | P19: 12820000000 | R19: 5.접 대 비 | S19: 13643500 | T19: 2633900 | V19: 4. 영 업 활 동으로인한자산부채의변동 | W19: 379240533 | X19: 3511716941
B20: 관계기업투자 | C20: 0 | D20: 0 | N20: 7.선 납 법 인 세(주10) | O20: 0 | P20: 208018060 | R20: 6.통 신 비 | S20: 2597615 | T20: 2609378 | V20: 가.매 출 채 권 의 감 소(증 가) | W20: 352494173 | X20: 100433949
B21: 매도가능증권 | C21: =O26/10^6 -> 4100 | D21: =P26/10^6 -> 4000 | N21: 8.선 급 비 용 | O21: 21081458 | P21: 3779273 | R21: 7.수 도 광 열 비 | S21: 1590645 | T21: 1749684 | V21: 나.미 수 수 익 의 감 소(증 가) | W21: 601447372 | X21: 424410660
B22: 장단기대여금 | C22: =(O19+O16+O22-O17)/10^6 -> 11058.826 | D22: =(P19+P16+P22-P17)/10^6 -> 12841.9 | E22: >>특수관계자 대여금 포함 | N22: 9.주 주.임 원 단기채 권(주13) | O22: 2000000000 | P22: 0 | R22: 8.전 력 비 | S22: 15827861 | T22: 15538654 | V22: 다.선 급 금 의 감 소(증 가) | W22: 0 | X22: 0
N23: II.비 유 동 자 산 | O23: 7367103591 | P23: 7260334507 | R23: 9.세 금 과 공 과 금 | S23: 31741280 | T23: 40023750 | V23: 라.선 급 비 용 의 감 소(증 가) | W23: 17654919 | X23: 17302185
N24: (1) 투 자 자 산 | O24: 4420600000 | P24: 4000000000 | R24: 10.감 가 상 각 비 | S24: 27190998 | T24: 16955812 | V24: 마.선 납 법 인 세 의 감 소(증 가) | W24: 0 | X24: 208018060
N25: 1.장 기 금 융 상 품(주3) | O25: 320600000 | P25: 0 | R25: 11.수 선 비 | S25: 191000 | T25: 1337000 | V25: 바.예 수 금 의 증 가(감 소) | W25: 4179690 | X25: 626699750
N26: 2.매 도 가 능 증 권(주8) | O26: 4100000000 | P26: 4000000000 | R26: 12.보 험 료 | S26: 9245191 | T26: 7710145 | V26: 사.미 지 급 금 의 증 가(감 소) | W26: 122844906 | X26: 854770239
N27: (2) 유 형 자 산(주2,4,5,7) | O27: 2870560591 | P27: 3078342906 | R27: 13.차 량 유 지 비 | S27: 16533258 | T27: 24337872 | V27: 아.미 지 급 법 인 세 의 증 가(감 소) | W27: 473690715 | X27: 576326468
C28: 2016년 | D28: 2017년 | N28: 1.토 지 | O28: 456444690 | P28: 1000968790 | R28: 14.운 반 비 | S28: 220500 | T28: 0 | V28: 자.미 지 급 비 용 의 증 가(감소) | W28: 0 | X28: 7372602
B29: 백만원 | C29: 12개월 | D29: 12개월 | N29: 2.건 물 | O29: 1948021188 | P29: 1950630968 | R29: 15.교 육 훈 련 비 | S29: 356700 | T29: 788500 | V29: 차.퇴 직 금 의 지 급 | W29: 0 | X29: 2200000000
B30: 매출액 | C30: =S9/10^6 -> 7431.4802 | D30: =T9/10^6 -> 8007.8196 | N30: 감 가 상 각 누 계 액 | O30: 496750058 | P30: 545515827 | R30: 16.도 서 인 쇄 비 | S30: 665300 | T30: 824500 | V30: II.투 자 활 동 으 로 인 한 현 금 흐 름 | W30: 226154000 | X30: 897554120
B31: 매출총이익 | N31: 3.구 축 물 | O31: 91300000 | P31: 91300000 | R31: 17.사 무 용 품 비 | S31: 1033450 | T31: 387300 | V31: 1.투 자 활 동 으 로 인 한 현 금 유 입 액 | W31: 167820000 | X31: 1711000000
B32: 판관비 | N32: 감 가 상 각 누 계 액 | O32: 20618125 | P32: 22900625 | R32: 18.소 모 품 비 | S32: 6012790 | T32: 5482090 | V32: 가.단 기 금 융 상 품 의 감 소 | W32: 50000000 | X32: 1700000000
B33: 영업이익 | C33: =S39/10^6 -> 2615.5111 | D33: =T39/10^6 -> 3110.421 | N33: 4.기 계 장 치 | O33: 9640897886 | P33: 9800474886 | R33: 19.지 급 수 수 료 | S33: 37076859 | T33: 49058930 | V33: 나.차 량 의 처 분 | W33: 9200000 | X33: 11000000
B34: EBITDA | C34: =C33+C36 -> 3291.6417 | D34: =D33+D36 -> 3606.4627 | N34: 감 가 상 각 누 계 액 | O34: 8777995808 | P34: 9210696201 | R34: 20.광 고 선 전 비 | S34: 1386000 | T34: 396000 | V34: 다.건 설 중 인 자 산 의 감 소 | W34: 108620000 | X34: 0
N35: 5.차 량 운 반 구 | O35: 271488907 | P35: 195801267 | R35: 21.대 손 상 각 비 | S35: 20833465 | T35: 19829125 | V35: 2.투 자 활 동 으 로 인 한 현 금 유 출 액 | W35: 393974000 | X35: 813445880
B36: D&A | C36: =SUM(W12,W14)/10^6 -> 676.13057 | D36: =SUM(X12,X14)/10^6 -> 496.04169 | N36: 감 가 상 각 누 계 액 | O36: 257582401 | P36: 190126518 | R36: 22.무 형 자 산 상 각 비 | S36: 0 | T36: 686399 | V36: 가.보 증 금 의 증 가 | W36: 0 | X36: 66959000
N37: 6.공 구 와 기 구 | O37: 5679933 | P37: 5679933 | R37: 22.잡 비 | S37: 520682 | T37: 815701 | V37: 나.소 프 트 웨 어 의 취 득 | W37: 0 | X37: 39776000
N38: 감 가 상 각 누 계 액 | O38: 5677933 | P38: 5677933 | R38: 23.협 회 비 | S38: 36000000 | T38: 0 | V38: 다.토 지 의 취 득 | W38: 0 | X38: 544524100
N39: 7.비 품 | O39: 96897080 | P39: 96897080 | R39: Ⅴ.영 업 이 익 | S39: 2615511123 | T39: 3110420984 | V39: 라.건 물 의 증 가 | W39: 64920000 | X39: 2609780
N40: 감 가 상 각 누 계 액 | O40: 83641528 | P40: 89650801 | R40: Ⅵ.영 업 외 수 익 | S40: 657408459 | T40: 716006320 | V40: 마.건 설 중 인 자 산 의 증 가 | W40: 71460000 | X40: 0
N41: 8.시 설 비 | O41: 656536865 | P41: 656536865 | R41: 1.이 자 수 익(주13) | S41: 633429438 | T41: 677219944 | V41: 바.기 계 장 치 의 취 득 | W41: 253935000 | X41: 159577000
N42: 감 가 상 각 누 계 액 | O42: 654440105 | P42: 655378978 | R42: 2.대 손 충 당 금 환 입 | S42: 17308523 | T42: 20833465 | V42: 사.비 품 의 취 득 | W42: 3659000 | X42: 0
N43: (3)무 형 자 산 | O43: 0 | P43: 39089601 | R43: 3.유 형 자 산 처 분 이 익 | S43: 25796 | T43: 7426727 | V43: Ⅲ.재 무 활 동 으 로 인 한 현 금 흐 름 | W43: 2484316300 | X43: 1527526300
N44: 1.소 프 트 웨 어 | O44: 0 | P44: 39089601 | R44: 4.잡 이 익 | S44: 6644702 | T44: 10526184 | V44: 1.재 무 활 동 으 로 인 한 현 금 유 입 액 | W44: 224773700 | X44: 6392526300
N45: (4)기 타 비 유 동 자 산 | O45: 75943000 | P45: 142902000 | R45: Ⅶ.영 업 외 비 용 | S45: 3545177 | T45: 791472342 | V45: 가.단 기 대 여 금 의 감 소 | W45: 224773700 | X45: 1071926300
N46: 1.기 타 보 증 금 | O46: 75873000 | P46: 142832000 | R46: 1.이 자 비 용 | S46: 0 | T46: 7372602 | V46: 나.주 주 임 원 단 기 채 권 의 감 소 | W46: 0 | X46: 2000000000
N47: 2.전 신 전 화 가 입 권 | O47: 70000 | P47: 70000 | R47: 2.기 부 금 | S47: 600000 | T47: 3200000 | V47: 다.장 기 금 융 상 품 의 감 소 | W47: 0 | X47: 320600000
N48: 자 산 총 계 | O48: 23262974923 | P48: 26169433330 | R48: 3.전 기 오 류 수 정 손 실 | S48: 0 | T48: 100000000 | V48: 라.유 동 성 장 기 부 채 의 증 가 | W48: 0 | X48: 1000000000
N49: 부 채 | R49: 4.잡 손 실 | S49: 2945177 | T49: 873440 | V49: 마.장 기 차 입 금 의 증 가 | W49: 0 | X49: 2000000000
N50: I. 유 동 부 채 | O50: 1852137380 | P50: 2055113025 | R50: 5.기 타 대 손 상 각 비 | S50: 0 | T50: 680026300 | V50: 2.재 무 활 동 으 로 인 한 현 금 유 출 액 | W50: 2709090000 | X50: 4865000000
N51: 1.미 지 급 금 | O51: 1253358632 | P51: 398588393 | R51: Ⅷ.법 인 세 차 감 전 순 이 익 | S51: 3269374405 | T51: 3034954962 | V51: 가.관 계 회 사 대 여 금 의 증 가 | W51: 580000000 | X51: 4855000000
N52: 2.예 수 금 | O52: 22452280 | P52: 649152030 | R52: Ⅸ.법 인 세 등(주10) | S52: 706324828 | T52: 121472200 | V52: 나.주 주 임 원 단 기 채 권 의 증 가 | W52: 2000000000 | X52: 0
N53: 3.미 지 급 법 인 세 (주10) | O53: 576326468 | P53: 0 | R53: Ⅹ.당 기 순 이 익 | S53: 2563049577 | T53: 2913482762 | V53: 다.장 기 금 융 상 품 의 증 가 | W53: 129090000 | X53: 0
N54: 4.미 지 급 비 용 | O54: 0 | P54: 7372602 | R54: 별첨 주석은 본 재무제표의 일부입니다. | V54: 라.장 기 계 약 보 증 금 의 감 소 | W54: 0 | X54: 10000000
N55: 5.유 동 성 장 기 부 채(주9) | O55: 0 | P55: 1000000000 | V55: Ⅳ.현 금 의 증 가 (감 소) | W55: 152968460 | X55: 2414456865
N56: II. 비 유 동 부 채 | O56: 2210000000 | P56: 2000000000 | V56: Ⅴ.기 초 의 현 금 | W56: 280555161 | X56: 433523621
N57: 1.장 기 차 입 금(주9) | O57: 0 | P57: 2000000000 | V57: Ⅵ.기 말 의 현 금 | W57: 433523621 | X57: 2847980486
N58: 2.퇴 직 급 여 충 당 부 채(주2) | O58: 2200000000 | P58: 0 | V58: 별첨 주석은 본 재무제표의 일부입니다.
N59: 3.장 기 계 약 보 증 금 | O59: 10000000 | P59: 0
N60: 부 채 총 계 | O60: 4062137380 | P60: 4055113025
N61: 자 본
N62: I. 자 본 금 | O62: 750000000 | P62: 750000000
N63: 1.보 통 주 자 본 금(주11) | O63: 750000000 | P63: 750000000
N64: Ⅱ. 이 익 잉 여 금 | O64: 18450837543 | P64: 21364320305
N65: 1.이 익 준 비 금 | O65: 119500000 | P65: 119500000
N66: 2.기 업 합 리 화 적 립 금 | O66: 254599 | P66: 254599
N67: 3.미 처 분 이 익 잉 여 금 | O67: 18331082944 | P67: 21244565706
N68: 자 본 총 계 | O68: 19200837543 | P68: 22114320305
N69: 부 채 및 자 본 총 계 | O69: 23262974923 | P69: 26169433330
N70: 별첨 주석은 본 재무제표의 일부입니다.

Sheet 코엔텍
B2: Net | D2: Enterprise | E2: Fiscal | N2: Source : Dart
B3: Debt | C3: NOA | D3: Vaule | E3: Year | F3: BV | G3: Salse | H3: EBITDA | I3: EBIT | J3: NI | N3: 연결 재무상태표 | R3: 6. 범주별 금융상품
B4: =C14 -> -13359.281 | C4: =C17 -> 3123.8873 | E4: FY2016 | F4: =O51/10^6 -> 110624.03 | G4: =C30 -> 55095.779 | H4: =C34 -> 22232.954 | I4: =C33 -> 15475.622 | J4: =O73/10^6 -> 14719.206 | N4: 제 25 기 2017.12.31 현재
B5: =D14 -> -38048.585 | C5: =D17 -> 260.54229 | E5: FY2017 | F5: =P51/10^6 -> 125556.41 | G5: =D30 -> 61255.105 | H5: =D34 -> 29371.594 | I5: =D33 -> 18586.515 | J5: =P73/10^6 -> 16059.145 | N5: 제 24 기 2016.12.31 현재 | R5: 6.1 금융상품 범주별 장부금액
N6: 제 23 기 2015.12.31 현재
N7: (단위 : 원) | R7: (1) 당기말
O8: 2016 | P8: 2017 | R8: (단위: 천원)
C9: 2016년 | D9: 2017년 | N9: 자산 | R9: 구 분 | S9: 대여금및수취채권 | T9: 매도가능금융자산 | U9: 만기보유금융자산 | V9: 상각후원가로 측정하는 금융부채
B10: 백만원 | C10: 12월31일 | D10: 12월31일 | N10: 유동자산 | O10: 51114217201 | P10: 74921431201 | R10: 현금및현금성자산 | S10: 46925585 | T10: - | U10: - | V10: -
B11: 차입금 | C11: =(O33+O39)/10^6 -> 26877 | D11: =(P33+P39)/10^6 -> 26877 | N11: 현금및현금성자산 | O11: 28886280777 | P11: 46925585127 | R11: 단기금융상품 | S11: 18000000 | T11: - | U11: - | V11: -
B12: 현금및현금성자산 | C12: =O11/10^6 -> 28886.281 | D12: =P11/10^6 -> 46925.585 | N12: 단기금융상품 | O12: 11350000000 | P12: 18000000000 | R12: 매출채권 | S12: 9145365 | T12: - | U12: - | V12: -
B13: 단기금융상품 | C13: =O12/10^6 -> 11350 | D13: =P12/10^6 -> 18000 | N13: 매출채권 | O13: 9082969784 | P13: 9145364918 | R13: 기타유동금융자산 | S13: 245824 | T13: - | U13: - | V13: -
B14: Net Debt | C14: =-SUM(C12:C13)+C11 -> -13359.281 | D14: =-SUM(D12:D13)+D11 -> -38048.585 | N14: 매도가능금융자산 | O14: 55055000 | P14: 36665000 | R14: 장기금융상품 | S14: 4500 | T14: - | U14: - | V14: -
N15: 만기보유금융자산 | O15: 25240000 | P15: 21690000 | R15: 매도가능금융자산 | S15: - | T15: 143772 | U15: - | V15: -
N16: 기타유동금융자산 | O16: 245127692 | P16: 245823917 | R16: 만기보유금융자산 | S16: - | T16: - | U16: 112270 | V16: -
B17: NOA | C17: =SUM(C18:C22) -> 3123.8873 | D17: =SUM(D18:D22) -> 260.54229 | N17: 기타유동자산 | O17: 1419381360 | P17: 508066325 | R17: 기타비유동금융자산 | S17: 2109727 | T17: - | U17: - | V17: -
B18: 장기금융상품 | C18: =SUM(O15,O21,O23)/10^6 -> 1118.9755 | D18: =SUM(P15,P21,P23)/10^6 -> 116.77 | N18: 당기법인세자산 | R18: 매입채무 | S18: - | T18: - | U18: - | V18: 987844
B19: 투자부동산 | C19: 0 | D19: 0 | N19: 재고자산 | O19: 50162588 | P19: 38235914 | R19: 기타유동금융부채 | S19: - | T19: - | U19: - | V19: 4555734
B20: 관계기업투자 | C20: 0 | D20: 0 | N20: 비유동자산 | O20: 102803197359 | P20: 97824811089 | R20: 장기차입금 | S20: - | T20: - | U20: - | V20: 26877000
B21: 매도가능증권 | C21: =(O14+O22)/10^6 -> 2003.4118 | D21: =(P14+P22)/10^6 -> 143.77229 | N21: 장기금융상품 | O21: 1012315500 | P21: 4500000 | R21: 합 계 | S21: 76431001 | T21: 143772 | U21: 112270 | V21: 32420578
B22: 장단기대여금 | C22: =U52/10^3 -> 1.5 | D22: 0 | E22: >>특수관계자 대여금 포함 | N22: 매도가능금융자산 | O22: 1948356765 | P22: 107107294
N23: 만기보유금융자산 | O23: 81420000 | P23: 90580000 | R23: (2) 전기말
N24: 유형자산 | O24: 91109007387 | P24: 85408356850
N25: 무형자산 | O25: 5461073518 | P25: 7247343318 | R25: (단위: 천원)
N26: 기타비유동금융자산 | O26: 1715454725 | P26: 2109726596 | R26: 구 분 | S26: 대여금및수취채권 | T26: 매도가능금융자산 | U26: 만기보유금융자산 | V26: 상각후원가로 측정하는 금융부채
N27: 기타비유동자산 | O27: 0 | P27: 995530810 | R27: 단기금융상품 | S27: 11350000 | T27: - | U27: - | V27: -
C28: 2016년 | D28: 2017년 | N28: 이연법인세자산 | O28: 1475569464 | P28: 1861666221 | R28: 매출채권 | S28: 9082970 | T28: - | U28: - | V28: -
B29: 백만원 | C29: 12개월 | D29: 12개월 | N29: 자산총계 | O29: 153917414560 | P29: 172746242290 | R29: 기타유동금융자산 | S29: 245128 | T29: - | U29: - | V29: -
B30: 매출액 | C30: =O62/10^6 -> 55095.779 | D30: =P62/10^6 -> 61255.105 | N30: 부채 | R30: 장기금융상품 | S30: 1012316 | T30: - | U30: - | V30: -
B31: 매출총이익 | N31: 유동부채 | O31: 10635544794 | P31: 14284279261 | R31: 매도가능금융자산 | S31: - | T31: 2003412 | U31: - | V31: -
B32: 판관비 | N32: 매입채무 | O32: 1220761374 | P32: 987844296 | R32: 만기보유금융자산 | S32: - | T32: - | U32: 106660 | V32: -
B33: 영업이익 | C33: =O66/10^6 -> 15475.622 | D33: =P66/10^6 -> 18586.515 | N33: 유동성장기차입금 | O33: 0 | P33: 1071800000 | R33: 기타비유동금융자산 | S33: 1715455 | T33: - | U33: - | V33: -
B34: EBITDA | C34: =C33+C36 -> 22232.954 | D34: =D33+D36 -> 29371.594 | N34: 당기법인세부채 | O34: 1293721312 | P34: 3403177240 | R34: 매입채무 | S34: - | T34: - | U34: - | V34: 1220761
N35: 기타유동금융부채 | O35: 6326514015 | P35: 4555734318 | R35: 기타유동금융부채 | S35: - | T35: - | U35: - | V35: 6326514
B36: D&A | C36: =S118/10^3 -> 6757.332 | D36: =T118/10^3 -> 10785.079 | N36: 기타유동부채 | O36: 1794548093 | P36: 1902383407 | R36: 장기차입금 | S36: - | T36: - | U36: - | V36: 26877000
N37: 충당부채 | O37: 0 | P37: 2363340000 | R37: 합 계 | S37: 23405869 | T37: 2003412 | U37: 106660 | V37: 34424275
N38: 비유동부채 | O38: 32657835623 | P38: 32905549752
N39: 장기차입금 | O39: 26877000000 | P39: 25805200000
N40: 순확정급여부채 | O40: 589204506 | P40: 6716807
N41: 기타비유동부채 | O41: 0 | P41: 129577209 | R41: 7. 사용제한예금
N42: 충당부채 | O42: 5191631117 | P42: 6964055736 | R42: (단위: 천원)
N43: 부채총계 | O43: 43293380417 | P43: 47189829013 | R43: 구 분 | S43: 당기말 | T43: 전기말
N44: 자본 | R44: 장기금융상품
N45: 지배기업의 소유주에게 귀속되는 자본 | O45: 110615623733 | P45: 125548416965 | R45: 당좌개설보증금 | S45: 4500 | T45: 2500
N46: 자본금 | O46: 25000000000 | P46: 25000000000
N47: 주식발행초과금 | O47: 1385970000 | P47: 1385970000
N48: 이익잉여금(결손금) | O48: 84336793733 | P48: 99260317942 | R48: 9. 기타금융자산
N49: 기타자본구성요소 | O49: -107140000 | P49: -97870977 | R49: (단위: 천원)
N50: 비지배지분 | O50: 8410410 | P50: 7996312 | R50: 구 분 | S50: 당기말 | U50: 전기말
N51: 자본총계 | O51: 110624034143 | P51: 125556413277 | S51: 유동 | T51: 비유동 | U51: 유동 | V51: 비유동
N52: 자본과부채총계 | O52: 153917414560 | P52: 172746242290 | R52: 대여금 | S52: - | T52: - | U52: 1500
R53: 미수금 | S53: 61919 | T53: - | U53: 107890 | V53: -
R54: 미수수익 | S54: 183905 | T54: - | U54: 135738 | V54: -
R55: 보증금 | S55: - | T55: 2109727 | U55: - | V55: 1715455
N56: 연결 포괄손익계산서 | R56: 합 계 | S56: 245824 | T56: 2109727 | U56: 245128 | V56: 1715455
N57: 제 25 기 2017.01.01 부터 2017.12.31 까지
N58: 제 24 기 2016.01.01 부터 2016.12.31 까지
N59: 제 23 기 2015.01.01 부터 2015.12.31 까지 | R59: 11. 매도가능금융자산
N60: (단위 : 원)
O61: 2016 | P61: 2017 | R61: (1) 매도가능금융자산의 내역
N62: 매출액 | O62: 55095779281 | P62: 61255104519
N63: 매출원가 | O63: 34338313483 | P63: 37331138174 | R63: (단위: 천원)
N64: 매출총이익 | O64: 20757465798 | P64: 23923966345 | R64: 구 분 | S64: 장부가액
N65: 판매비와관리비 | O65: 5281844158 | P65: 5337451797 | S65: 당기말 | T65: 전기말
N66: 영업이익(손실) | O66: 15475621640 | P66: 18586514548 | R66: 국채 및 공채
N67: 금융이익 | O67: 415891521 | P67: 711143379 | R67: 1년 이내 만기 도래분 | S67: 36665 | T67: 55055
N68: 금융비용 | O68: 579484907 | P68: 434218906 | R68: 1년 초과 5년 내 만기 도래분 | S68: 30025 | T68: 56665
N69: 기타영업외이익 | O69: 1152076524 | P69: 1241499399 | R69: 시장성 없는 지분증권
N70: 기타영업외비용 | O70: 28054165 | P70: 132347364 | R70: (주)한텍 | S70: - | T70: 1726637
N71: 법인세비용차감전순이익(손실) | O71: 16436050613 | P71: 19972591056 | R71: 한국엔지니어링공제조합 | S71: - | T71: 99856
N72: 법인세비용 | O72: 1716844754 | P72: 3913445884 | R72: 전문건설공제조합 | S72: 52055 | T72: 15000
N73: 당기순이익(손실) | O73: 14719205859 | P73: 16059145172 | R73: 한국건설자원공제조합 | S73: 25027 | T73: 50199
N74: 기타포괄손익 | O74: -73403476 | P74: 117876962 | R74: 합 계 | S74: 143772 | T74: 2003412
N75: 당기손익으로 재분류되지 않는항목(세후기타포괄손익)
N76: 확정급여제도의 재측정손익(세후기타포괄손익) | O76: -73403476 | P76: 108607939
N77: 당기손익으로 재분류될 수 있는 항목(세후기타포괄손익) | R77: 12. 만기보유금융자산
N78: 매도가능금융자산평가손익(세후기타포괄손익) | P78: 9269023 | R78: (단위: 천원)
N79: 총포괄손익 | O79: 14645802383 | P79: 16177022134 | R79: 구 분 | S79: 장부가액
N80: 당기순이익(손실)의 귀속 | S80: 당기말 | T80: 전기말
N81: 지배기업의 소유주에게 귀속되는 당기순이익(손실) | O81: 14719205859 | P81: 16059559270 | R81: 국채 및 공채
N82: 비지배지분에 귀속되는 당기순이익(손실) | O82: -384157 | P82: -414098 | R82: 1년 이내 만기 도래분 | S82: 21690 | T82: 25240
N83: 총 포괄손익의 귀속 | R83: 1년 초과 5년 내 만기 도래분 | S83: 90580 | T83: 81420
N84: 총 포괄손익, 지배기업의 소유주에게 귀속되는 지분 | O84: 14646186540 | P84: 16177436232 | R84: 합 계 | S84: 112270 | T84: 106660
N85: 총 포괄손익, 비지배지분 | O85: -384157 | P85: -414098
N86: 주당이익
N87: 기본주당이익(손실) (단위 : 원) | O87: 296 | P87: 323
N88: 희석주당이익(손실) (단위 : 원) | O88: 296 | P88: 323
R90: (3) 감가상각비가 포함되어 있는 계정과목별 금액
R91: (단위: 천원)
N92: 연결 현금흐름표 | R92: 구 분 | S92: 당기 | T92: 전기
N93: 제 25 기 2017.01.01 부터 2017.12.31 까지 | R93: 매출원가 | S93: 10688588 | T93: 6654651
N94: 제 24 기 2016.01.01 부터 2016.12.31 까지 | R94: 판매비와관리비 | S94: 96278 | T94: 100125
N95: 제 23 기 2015.01.01 부터 2015.12.31 까지 | R95: 합 계 | S95: 10784866 | T95: 6754776
N96: (단위 : 원)
O97: 2016 | P97: 2017
N98: 영업활동현금흐름 | O98: 21771596783 | P98: 29406676829 | R98: (2) 무형자산의 변동 내역
N99: 당기순이익(손실) | O99: 14719205859 | P99: 16059145172
N100: 당기순이익조정을 위한 가감 | O100: 7701531464 | P100: 15370439377 | R100: 1) 당기
N101: 배당금수취(영업) | O101: 1000000 | P101: 0 | R101: (단위: 천원)
N102: 이자지급(영업) | O102: -351100052 | P102: -446169713 | R102: 계정과목 | S102: 기초 순장부금액 | T102: 취득 | U102: 처분 | V102: 상각비 | W102: 기말 순장부금액
...

Sheet 한국종합기술
B2: BS | C2: FY2016 | D2: FY2017 | F2: 구분 | G2: Sales | H2: EBITDA | I2: EBIT | J2: NI | K2: D&A
B3: Cash | C3: =SUM(C4:C5) -> 17610.914 | D3: =SUM(D4:D5) -> 12861.999 | F3: FY2017 | G3: =SUMIFS($H$21:$H$94,$E$21:$E$94,G$2)/10^6 -> 199604.54 | H3: =SUMIFS($H$21:$H$94,$E$21:$E$94,H$2)/10^6 -> -5169.9129 | I3: =SUMIFS($H$21:$H$94,$E$21:$E$94,I$2)/10^6 -> -7252.9299 | J3: =SUMIFS($H$21:$H$94,$E$21:$E$94,J$2)/10^6 -> -7815.611 | K3: =H3-I3 -> 2083.017
B4: 현금및현금성자산 | C4: =SUMIFS(C$21:C$65,$A$21:$A$65,$B4)/10^6 -> 12410.914 | D4: =SUMIFS(D$21:D$65,$A$21:$A$65,$B4)/10^6 -> 7661.9988 | F4: FY2016 | G4: =SUMIFS($G$21:$G$94,$E$21:$E$94,G$2)/10^6 -> 199370.93 | H4: =SUMIFS($G$21:$G$94,$E$21:$E$94,H$2)/10^6 -> 6305.6561 | I4: =SUMIFS($G$21:$G$94,$E$21:$E$94,I$2)/10^6 -> 4236.7241 | J4: =SUMIFS($G$21:$G$94,$E$21:$E$94,J$2)/10^6 -> 3063.3867 | K4: =H4-I4 -> 2068.932
B5: 단기금융상품 | C5: =SUMIFS(C$21:C$65,$A$21:$A$65,$B5)/10^6 -> 5200 | D5: =SUMIFS(D$21:D$65,$A$21:$A$65,$B5)/10^6 -> 5200
B6: Debt | C6: =SUM(C7:C9) -> 36250 | D6: =SUM(D7:D9) -> 44250
B7: 단기차입금 | C7: =SUMIFS(C$21:C$65,$A$21:$A$65,$B7)/10^6 -> 13000 | D7: =SUMIFS(D$21:D$65,$A$21:$A$65,$B7)/10^6 -> 24000
B8: 장기차입금 | C8: =SUMIFS(C$21:C$65,$A$21:$A$65,$B8)/10^6 -> 23250 | D8: =SUMIFS(D$21:D$65,$A$21:$A$65,$B8)/10^6 -> 20250
B9: 사채 | C9: =SUMIFS(C$21:C$65,$A$21:$A$65,$B9)/10^6 -> 0 | D9: =SUMIFS(D$21:D$65,$A$21:$A$65,$B9)/10^6 -> 0
B10: NOA | C10: =SUM(C11:C16) -> 63736.082 | D10: =SUM(D11:D16) -> 63868.008
B11: 장기금융상품 | C11: =SUMIFS(C$21:C$65,$A$21:$A$65,$B11)/10^6 -> 2.5 | D11: =SUMIFS(D$21:D$65,$A$21:$A$65,$B11)/10^6 -> 2.5
B12: 투자부동산 | C12: =SUMIFS(C$21:C$65,$A$21:$A$65,$B12)/10^6 -> 48008.369 | D12: =SUMIFS(D$21:D$65,$A$21:$A$65,$B12)/10^6 -> 47607.643
B13: 관계기업투자 | C13: =SUMIFS(C$21:C$65,$A$21:$A$65,$B13)/10^6 -> 0 | D13: =SUMIFS(D$21:D$65,$A$21:$A$65,$B13)/10^6 -> 0
B14: 매도가능증권 | C14: =SUMIFS(C$21:C$65,$A$21:$A$65,$B14)/10^6 -> 9523.9083 | D14: =SUMIFS(D$21:D$65,$A$21:$A$65,$B14)/10^6 -> 10008.25
B15: 만기보유금융자산 | C15: =SUMIFS(C$21:C$65,$A$21:$A$65,$B15)/10^6 -> 6201.305 | D15: =SUMIFS(D$21:D$65,$A$21:$A$65,$B15)/10^6 -> 6249.615
B16: 장단기대여금 | C16: =SUMIFS(C$21:C$65,$A$21:$A$65,$B16)/10^6 -> 0 | D16: =SUMIFS(D$21:D$65,$A$21:$A$65,$B16)/10^6 -> 0
B17: BV | C17: =SUMIFS(C$21:C$65,$A$21:$A$65,$B17)/10^6 -> 122403.97 | D17: =SUMIFS(D$21:D$65,$A$21:$A$65,$B17)/10^6 -> 114383.39
B19: Source : Dart
B20: 자산 | C20: FY2016 | D20: FY2017 | G20: FY2016 | H20: FY2017 | J20: 구 분 | K20: 보 유 목 적 | L20: 구 분 | M20: FY2016 | N20: FY2017
B21: 유동자산 | C21: 104206214972 | D21: 93977947500 | E21: Sales | F21: 수익(매출액) | G21: 199370927856 | H21: 199604541858 | J21: 단 기 | K21: 매도가능금융자산 | L21: 시장성 있는 투자주식 | M21: 235526 | N21: 259332
A22: 현금및현금성자산 | B22: 현금및현금성자산 | C22: 12410914241 | D22: 7661998807 | F22: 매출원가 | G22: 176829616884 | H22: 185005056228 | K22: 만기보유금융자산 | L22: 채무증권 | M22: 1214760 | N22: 1526600
A23: 단기금융상품 | B23: 단기금융상품 | C23: 5200000000 | D23: 5200000000 | F23: 매출총이익 | G23: 22541310972 | H23: 14599485630 | K23: 소 계 | M23: 1450286 | N23: 1785932
A24: 매도가능증권 | B24: 유동매도가능금융자산 | C24: 235526140 | D24: 259332260 | F24: 판매비와관리비 | G24: 18304586884 | H24: 21852415482 | J24: 장 기 | K24: 매도가능금융자산 | L24: 시장성 없는 투자주식 | M24: 10000 | N24: 10000
A25: 만기보유금융자산 | B25: 유동만기보유금융자산 | C25: 1214760000 | D25: 1526600000 | E25: ebit | F25: 영업이익 | G25: 4236724088 | H25: -7252929852 | K25: 매도가능금융자산 | L25: 출자금 | M25: 9278382 | N25: 9738918
B26: 매출채권 | C26: 16354891457 | D26: 26233350749 | F26: 기타수익 | G26: 1407105917 | H26: 542870506 | K26: 만기보유금융자산 | L26: 채무증권 | M26: 4986545 | N26: 4723015
B27: 미청구공사 | C27: 48406302000 | D27: 41557190477 | F27: 기타비용 | G27: 478478031 | H27: 1540894285 | K27: 소 계 | M27: 14274927 | N27: 14471933
B28: 미수금 | C28: 111046526 | D28: 776639116 | F28: 금융수익 | G28: 480373018 | H28: 279210396 | J28: 합 계 | M28: 15725213 | N28: 16257865
B29: 미수수익 | C29: 405053050 | D29: 395307538 | F29: 금융원가 | G29: 1614574637 | H29: 1700884177
B30: 기타유동자산 | C30: 19867721558 | D30: 10367528553 | F30: 법인세비용차감전순이익 | G30: 4031150355 | H30: -9672627412
B31: 비유동자산 | C31: 138237621956 | D31: 136820743192 | F31: 법인세비용 | G31: 967763690 | H31: -1857016399
A32: 장기금융상품 | B32: 장기금융상품 | C32: 2500000 | D32: 2500000 | E32: ni | F32: 당기순이익 | G32: 3063386665 | H32: -7815611013
A33: 매도가능증권 | B33: 매도가능금융자산 | C33: 9288382186 | D33: 9748917566 | F33: 주당이익
A34: 만기보유금융자산 | B34: 만기보유금융자산 | C34: 4986545000 | D34: 4723015000 | F34: 기본주당이익(손실) (단위 : 원) | G34: 280 | H34: -714
A35: 투자부동산 | B35: 투자부동산 | C35: 48008368765 | D35: 47607643472 | F35: 희석주당이익(손실) (단위 : 원) | G35: 280 | H35: -714
B36: 유형자산 | C36: 71715393358 | D36: 70707472996
B37: 무형자산 | C37: 3324752550 | D37: 2984516387 | F37: 감가상각비 | G37: 2009955 | H37: 2015270
B38: 보증금 | C38: 911680097 | D38: 1046677771 | F38: 무형자산상각비 | G38: 58977 | H38: 67747
B39: 자산총계 | C39: 242443836928 | D39: 230798690692 | F39: D&a | G39: =SUM(G37:G38) -> 2068932 | H39: =SUM(H37:H38) -> 2083017
B40: 부채
B41: 유동부채 | C41: 73439396702 | D41: 76077411069 | E41: ebitda | F41: EBITDA | G41: =G25+G39*10^3 -> 6305656088 | H41: =H25+H39*10^3 -> -5169912852
A42: 단기차입금 | B42: 단기차입금 | C42: 10000000000 | D42: 21000000000
A43: 단기차입금 | B43: 유동성장기차입금 | C43: 3000000000 | D43: 3000000000
B44: 매입채무 | C44: 12017033055 | D44: 14811468765
B45: 초과청구공사 | C45: 37783723841 | D45: 23719941271
B46: 미지급금 | C46: 7937728416 | D46: 10193322989
B47: 미지급비용 | C47: 205282612 | D47: 203177764
B48: 예수금 | C48: 1101549935 | D48: 1766109778
B49: 미지급법인세 | C49: 503529323 | D49: 0
B50: 선수수익 | C50: 797125739 | D50: 651325852
B51: 공사손실충당부채 | C51: 93423781 | D51: 58142746
B52: 소송충당부채 | C52: 0 | D52: 673921904
B53: 비유동부채 | C53: 46600473691 | D53: 40337889907
A54: 장기차입금 | B54: 장기차입금 | C54: 23250000000 | D54: 20250000000
B55: 임대보증금 | C55: 3029415000 | D55: 1794615000
B56: 퇴직급여부채 | C56: 15956952709 | D56: 15537921666
B57: 이연법인세부채 | C57: 4364105982 | D57: 2755353241
B58: 부채총계 | C58: 120039870393 | D58: 116415300976
B59: 자본
B60: 자본금 | C60: 5475000000 | D60: 5475000000
B61: 주식발행초과금 | C61: 6717349930 | D61: 6717349930
B62: 이익잉여금 | C62: 107088966482 | D62: 98405007759
B63: 기타자본항목 | C63: 3122650123 | D63: 3786032027
A64: BV | B64: 자본총계 | C64: 122403966535 | D64: 114383389716
B65: 자본과부채총계 | C65: 242443836928 | D65: 230798690692

Sheet 휴비스워터_'18
B3: BS | C3: FY2017 | D3: FY2018 | F3: 구분 | G3: Sales | H3: EBITDA | I3: EBIT | J3: NI | K3: D&A
B4: Cash | C4: =SUM(C5:C6) -> 16931.649 | D4: =SUM(D5:D6) -> 8767.511 | F4: FY2018 | G4: =SUMIFS($H$21:$H$44,$E$21:$E$44,G$3)/10^6 -> 81813.008 | H4: =SUMIFS($H$21:$H$44,$E$21:$E$44,H$3)/10^6 -> -2588.5417 | I4: =SUMIFS($H$21:$H$44,$E$21:$E$44,I$3)/10^6 -> -3815.8077 | J4: =SUMIFS($H$21:$H$44,$E$21:$E$44,J$3)/10^6 -> -1293.7663 | K4: =H4-I4 -> 1227.266
B5: 현금및현금성자산 | C5: =L23/10^3 -> 13931.649 | D5: =N23/10^3 -> 7767.511 | F5: FY2017 | G5: =SUMIFS($G$21:$G$44,$E$21:$E$44,G$3)/10^6 -> 82896.239 | H5: =SUMIFS($G$21:$G$44,$E$21:$E$44,H$3)/10^6 -> 3381.1181 | I5: =SUMIFS($G$21:$G$44,$E$21:$E$44,I$3)/10^6 -> 1819.3271 | J5: =SUMIFS($G$21:$G$44,$E$21:$E$44,J$3)/10^6 -> 959.72901 | K5: =H5-I5 -> 1561.791
B6: 단기금융상품 | C6: =L24/10^3 -> 3000 | D6: =N24/10^3 -> 1000
B7: Debt | C7: =SUM(C8:C10) -> 0 | D7: =SUM(D8:D10) -> 2250
B8: 단기차입금 | C8: =C40/10^6 -> 0 | D8: =D40/10^6 -> 2250
B9: 장기차입금
B10: 사채
B11: NOA | C11: =SUM(C12:C16) -> 1140.255 | D11: =SUM(D12:D16) -> 485.329
B12: 장기금융상품 | C12: =K43/10^3 -> 16.585 | D12: =L43/10^3 -> 17.22
B13: 투자부동산 | C13: =L54/10^3 -> 107.16 | D13: =M54/10^3 -> 105.139
B14: 관계기업투자 | C14: =C34/10^6 -> 362.97 | D14: =D34/10^6 -> 362.97
B15: 매도가능증권 | C15: =K44/10^3 -> 653.54 | D15: =L44/10^3 -> 0
B16: 장단기대여금
B17: BV | C17: =C54/10^6 -> 67363.364 | D17: =D54/10^6 -> 60455.183
B19: Source : Dart
B20: 과 목 | C20: FY2017 | D20: FY2018 | F20: 과 목 | G20: FY2017 | H20: FY2018 | J20: 구 분 | K20: FY2017 | L20: FY2017 | M20: FY2018 | N20: FY2018
B21: 자 산 | E21: Sales | F21: Ⅰ. 매출액 | G21: 82896238677 | H21: 81813008383 | K21: 장부금액 | L21: 공정가치 | M21: 장부금액 | N21: 공정가치
B22: Ⅰ. 유동자산 | C22: 51951864521 | D22: 51112737675 | F22: Ⅱ. 매출원가 | G22: 70307717300 | H22: 73478030466 | J22: 금융자산
B23: 1. 현금및현금성자산 | C23: 13931649440 | D23: 7767511155 | F23: Ⅲ. 매출총이익 | G23: 12588521377 | H23: 8334977917 | J23: 현금및현금성자산 | K23: 13931649 | L23: 13931649 | M23: 7767511 | N23: 7767511
B24: 2. 매출채권및기타채권 | C24: 32979496553 | D24: 38734034186 | F24: Ⅳ. 판매비와관리비 | G24: 10769194295 | H24: 12150785617 | J24: 단기금융상품 | K24: 3000000 | L24: 3000000 | M24: 1000000 | N24: 1000000
B25: 3. 재고자산 | C25: 1561857545 | D25: 1558692942 | E25: EBIT | F25: Ⅴ. 영업이익 | G25: 1819327082 | H25: -3815807700 | J25: 당기손익-공정가치 | K25: - | L25: - | M25: 737156 | N25: 737156
B26: 4. 유동금융자산 | C26: 3000000000 | D26: 1737156340 | F26: Ⅵ. 기타수익 | G26: 513011024 | H26: 1100847478 | J26: 금융자산
B27: 6. 파생상품금융자산 | C27: - | D27: 345324265 | F27: Ⅶ. 기타비용 | G27: 622961217 | H27: 172291665 | J27: 매출채권(*1) | K27: 16182028 | L27: 16182028 | M27: 18020449 | N27: 18020449
B28: 7. 기타유동자산 | C28: 478860983 | D28: 970018787 | F28: Ⅷ. 금융수익 | G28: 626754902 | H28: 1715913631 | J28: 파생금융자산 | K28: - | L28: - | M28: 345324 | N28: 345324
B29: Ⅱ. 비유동자산 | C29: 33604670571 | D29: 31460369422 | F29: Ⅸ. 금융원가 | G29: 1025634740 | H29: 394581682 | J29: 기타채권 | K29: 184437 | L29: 184437 | M29: 100028 | N29: 100028
B30: 1. 유형자산 | C30: 28828059343 | D30: 27547210509 | F30: Ⅹ. 법인세비용차감전순이익 | G30: 1310497051 | H30: -1565919938 | J30: 기타포괄손익-공정가치 금융자산 | K30: - | L30: - | M30: 126170 | N30: 126170
B31: 2. 무형자산 | C31: 2631290054 | D31: 2006111560 | F31: ⅩI. 법인세비용 | G31: 350768045 | H31: -272153599 | J31: 매도가능금융자산 | K31: 653540 | L31: 653540 | M31: - | N31: -
B32: 3. 투자부동산 | C32: 107159659 | D32: 105139400 | E32: NI | F32: ⅩII. 당기순이익 | G32: 959729006 | H32: -1293766339 | J32: 기타금융자산 | K32: 810629 | L32: 810629 | M32: 1172879 | N32: 1172879
B33: 6. 비유동금융자산 | C33: 1464168956 | D33: 1299048753 | F33: ⅩIII. 기타포괄손익 | G33: -165135960 | H33: 5648486 | J33: 합 계 | K33: 34762283 | L33: 34762283 | M33: 29269517 | N33: 29269517
B34: 7. 종속기업투자주식 | C34: 362970000 | D34: 362970000 | F34: 1. 후속적으로 당기손익으로 재분류되지않는 항목 | J34: 금융부채
B35: 8. 기타비유동자산 | C35: 211022559 | D35: 139889200 | F35: (1) 해외사업환산손익 | G35: -165135960 | H35: 5648486 | J35: 매입채무 | K35: 11191624 | L35: 11191624 | M35: 13827798 | N35: 13827798
B36: 자 산 총 계 | C36: 85556535092 | D36: 82573107097 | F36: ⅩⅣ. 당기총포괄이익 | G36: 794593046 | H36: -1288117853 | J36: 기타채무 | K36: 2651088 | L36: 2651088 | M36: 2889742 | N36: 2889742
B37: 부 채 | F37: ⅩⅤ. 주당순이익 | J37: 차입금 | K37: - | L37: - | M37: 2250000 | N37: 2250000
B38: Ⅰ. 유동부채 | C38: 14539659054 | D38: 19548475703 | F38: 1. 기본주당순이익 | G38: 109 | H38: -147 | J38: 기타금융부채 | K38: 733914 | L38: 733914 | M38: - | N38: -
B39: 1. 매입채무및기타채무 | C39: 13842712342 | D39: 16717539812 | J39: 합 계 | K39: 14576626 | L39: 14576626 | M39: 18967540 | N39: 18967540
B40: 2. 단기차입금 | C40: 0 | D40: 2250000000 | F40: 감가상각비 | G40: 1352436 | H40: 1225246
B41: 3. 당기법인세부채 | C41: 146590216 | D41: - | F41: 무형자산상각비 | G41: 209355 | H41: 2020
B42: 4. 유동충당부채 | C42: - | D42: 161171433 | E42: D&A | F42: D&A | G42: =SUM(G40:G41) -> 1561791 | H42: =SUM(H40:H41) -> 1227266 | J42: 구 분 | K42: FY2017 | L42: FY2018
B43: 5. 기타유동부채 | C43: 550356496 | D43: 419764458 | J43: 장기금융상품 | K43: 16585 | L43: 17220
B44: Ⅱ. 비유동부채 | C44: 3653511583 | D44: 2569448132 | E44: EBITDA | G44: =G25+G42*10^3 -> 3381118082 | H44: =H25+H42*10^3 -> -2588541700 | J44: 매도가능증권 | K44: 653540 | L44: 0
B45: 1. 장기매입채무및기타채무 | C45: 548914249 | D45: - | J45: 보증금 | K45: 794044 | L45: 1155659
B46: 2. 비유동충당부채 | C46: 698875509 | D46: 307787250 | J46: 기타포괄손익-공정가치 | K46: - | L46: 126170
B47: 3. 이연법인세부채 | C47: 2220721825 | D47: 2261660882 | J47: 금융자산
B48: 4. 기타비유동부채 | C48: 185000000 | D48: - | J48: 합 계 | K48: 1464169 | L48: 1299049
B49: 부 채 총 계 | C49: 18193170637 | D49: 22117923835
B50: 자 본 | J50: 구 분 | K50: FY2017 | L50: FY2017 | M50: FY2018 | N50: FY2018
B51: 1. 자본금 | C51: 4387720000 | D51: 4387720000 | K51: 장부금액 | L51: 공정가치 | M51: 장부금액 | N51: 공정가치
B52: 2. 기타자본 | C52: -229711090 | D52: -1469062604 | J52: 토 지 | K52: 44700 | L52: 44700 | M52: 44700 | N52: 44700
B53: 3. 이익잉여금 | C53: 63205355545 | D53: 57536525866 | J53: 건 물 | K53: 62460 | L53: 62460 | M53: 60439 | N53: 60439
B54: 자 본 총 계 | C54: 67363364455 | D54: 60455183262 | J54: 합 계 | K54: 107160 | L54: 107160 | M54: 105139 | N54: 105139
B55: 부채와 자본총계 | C55: 85556535092 | D55: 82573107097

Sheet 휴비스워터_'14
B2: BS | C2: FY2013 | D2: FY2014 | F2: 구분 | G2: Sales | H2: EBITDA | I2: EBIT | J2: NI | K2: D&A
B3: Cash | C3: =SUM(C4:C5) -> 22440.338 | D3: =SUM(D4:D5) -> 43964.045 | F3: FY2014 | G3: =SUMIFS($G$21:$G$45,$E$21:$E$45,G$2)/10^6 -> 109990.68 | H3: =SUMIFS($G$21:$G$45,$E$21:$E$45,H$2)/10^6 -> 15984.153 | I3: =SUMIFS($G$21:$G$45,$E$21:$E$45,I$2)/10^6 -> 14518.296 | J3: =SUMIFS($G$21:$G$45,$E$21:$E$45,J$2)/10^6 -> 12465.956 | K3: =H3-I3 -> 1465.857
B4: 현금및현금성자산 | C4: =SUMIFS(C$21:C$52,$A$21:$A$52,$B4)/10^6 -> 456.50584 | D4: =SUMIFS(D$21:D$52,$A$21:$A$52,$B4)/10^6 -> 1998.5169 | F4: FY2013 | G4: =SUMIFS($H$21:$H$45,$E$21:$E$45,G$2)/10^6 -> 105760.54 | H4: =SUMIFS($H$21:$H$45,$E$21:$E$45,H$2)/10^6 -> 12413.841 | I4: =SUMIFS($H$21:$H$45,$E$21:$E$45,I$2)/10^6 -> 10841.688 | J4: =SUMIFS($H$21:$H$45,$E$21:$E$45,J$2)/10^6 -> 8364.5223 | K4: =H4-I4 -> 1572.153
B5: 단기금융상품 | C5: =SUMIFS(C$21:C$52,$A$21:$A$52,$B5)/10^6 -> 21983.832 | D5: =SUMIFS(D$21:D$52,$A$21:$A$52,$B5)/10^6 -> 41965.528
B6: Debt | C6: =SUM(C7:C9) -> 0 | D6: =SUM(D7:D9) -> 0
B7: 단기차입금 | C7: =SUMIFS(C$21:C$52,$A$21:$A$52,$B7)/10^6 -> 0 | D7: =SUMIFS(D$21:D$52,$A$21:$A$52,$B7)/10^6 -> 0
B8: 장기차입금 | C8: =SUMIFS(C$21:C$52,$A$21:$A$52,$B8)/10^6 -> 0 | D8: =SUMIFS(D$21:D$52,$A$21:$A$52,$B8)/10^6 -> 0
B9: 사채 | C9: =SUMIFS(C$21:C$52,$A$21:$A$52,$B9)/10^6 -> 0 | D9: =SUMIFS(D$21:D$52,$A$21:$A$52,$B9)/10^6 -> 0
B10: NOA | C10: =SUM(C11:C15) -> 935.12711 | D10: =SUM(D11:D15) -> 1065.6679
B11: 장기금융상품 | C11: =SUMIFS(C$21:C$52,$A$21:$A$52,$B11)/10^6 -> 935.12711 | D11: =SUMIFS(D$21:D$52,$A$21:$A$52,$B11)/10^6 -> 701.28967
B12: 투자부동산 | C12: =SUMIFS(C$21:C$52,$A$21:$A$52,$B12)/10^6 -> 0 | D12: =SUMIFS(D$21:D$52,$A$21:$A$52,$B12)/10^6 -> 364.37821
B13: 관계기업투자 | C13: =SUMIFS(C$21:C$52,$A$21:$A$52,$B13)/10^6 -> 0 | D13: =SUMIFS(D$21:D$52,$A$21:$A$52,$B13)/10^6 -> 0
B14: 매도가능증권 | C14: =SUMIFS(C$21:C$52,$A$21:$A$52,$B14)/10^6 -> 0 | D14: =SUMIFS(D$21:D$52,$A$21:$A$52,$B14)/10^6 -> 0
B15: 장단기대여금 | C15: =SUMIFS(C$21:C$52,$A$21:$A$52,$B15)/10^6 -> 0 | D15: =SUMIFS(D$21:D$52,$A$21:$A$52,$B15)/10^6 -> 0
B16: BV | C16: =C51/10^6 -> 65687.151 | D16: =D51/10^6 -> 74045.964
B18: Source : Dart
B20: 자 산 | C20: FY2013 | D20: FY2014 | F20: 과 목 | G20: FY2013 | H20: FY2014
B21: Ⅰ. 유동자산 | C21: 51020611204 | D21: 71248505248 | E21: Sales | F21: Ⅰ. 매출액 | G21: 109990679550 | H21: 105760544030
A22: 현금및현금성자산 | B22: 1. 현금및현금성자산 | C22: 456505842 | D22: 1998516902 | F22: 1. 공사매출 | G22: 109990043550 | H22: 105760544030
B23: 2. 매출채권및기타채권 | C23: 26974586924 | D23: 26074289725 | F23: 2. 상품매출 | G23: 636000 | H23: -
B24: 3. 재고자산 | C24: 291052824 | D24: 389163648 | F24: Ⅱ. 매출원가 | G24: 88396368546 | H24: 86911708652
A25: 단기금융상품 | B25: 4. 단기금융자산 | C25: 21983831824 | D25: 41965527856 | F25: 1. 공사매출원가 | G25: 88395808546 | H25: 86911708652
B26: 5. 기타유동자산 | C26: 1314633790 | D26: 821007117 | F26: 2. 상품매출원가 | G26: 560000 | H26: -
B27: Ⅱ. 비유동자산 | C27: 34293410964 | D27: 35040266787 | F27: Ⅲ. 매출총이익 | G27: 21594311004 | H27: 18848835378
B28: 1. 유형자산 | C28: 30438174974 | D28: 30864952128 | F28: Ⅳ. 판매비와관리비 | G28: 7076015241 | H28: 8007147537
B29: 2. 무형자산 | C29: 1875153834 | D29: 2063228018 | E29: EBIT | F29: Ⅴ. 영업이익 | G29: 14518295763 | H29: 10841687841
A30: 투자부동산 | B30: 3. 투자부동산 | C30: - | D30: 364378210 | F30: Ⅵ. 기타수익 | G30: 979857420 | H30: 1151166747
A31: 장기금융상품 | B31: 4. 장기금융자산 | C31: 935127106 | D31: 701289665 | F31: Ⅶ. 기타비용 | G31: 250450800 | H31: 1517323984
B32: 5. 기타비유동자산 | C32: 1044955050 | D32: 1046418766 | F32: Ⅷ. 금융수익 | G32: 465979890 | H32: 703735392
B33: 자 산 총 계 | C33: 85314022168 | D33: 106288772035 | F33: Ⅸ. 금융원가 | G33: 1473403 | H33: -
B34: 부 채 | F34: Ⅹ. 법인세비용차감전 순이익 | G34: 15712208870 | H34: 11179265996
B35: Ⅰ. 유동부채 | C35: 15979883720 | D35: 29538136205 | F35: ⅩI. 법인세비용 | G35: 3246252676 | H35: 2814743741
B36: 1. 매입채무및기타채무 | C36: 12142187755 | D36: 26367383401 | E36: NI | F36: ⅩII. 당기순이익 | G36: 12465956194 | H36: 8364522255
B37: 2. 단기금융부채 | C37: - | D37: - | F37: ⅩIII. 당기총포괄이익 | G37: 12465956194 | H37: 8364522255
B38: 3. 법인세부채 | C38: 2971788803 | D38: 1611678080 | F38: ⅩⅣ. 주당순이익
B39: 4. 기타유동부채 | C39: 865907162 | D39: 1559074724 | F39: 1. 기본주당순이익 | G39: 1421 | H39: 953
B40: Ⅱ. 비유동부채 | C40: 3646987305 | D40: 2704671662
B41: 1. 장기매입채무및기타채무 | C41: 225676962 | D41: 320550544 | F41: 감가상각비 | G41: 1383133 | H41: 1436448
B42: 2. 순확정급여부채 | C42: - | D42: - | F42: 무형자산상각비 | G42: 82724 | H42: 135705
B43: 3. 비유동충당부채 | C43: 878966652 | D43: 326303669 | F43: D&A | G43: =SUM(G41:G42) -> 1465857 | H43: =SUM(H41:H42) -> 1572153
B44: 4. 이연법인세부채 | C44: 2152343691 | D44: 1582817449
B45: 5. 기타비유동부채 | C45: 390000000 | D45: 475000000 | E45: EBITDA | F45: EBITDA | G45: =G29+G43*10^3 -> 15984152763 | H45: =H29+H43*10^3 -> 12413840841
B46: 부 채 총 계 | C46: 19626871025 | D46: 32242807867
B47: 자 본
B48: 1. 자본금 | C48: 2193860000 | D48: 4387720000
B49: 2. 기타자본 | C49: -4734243600 | D49: -4739952830
B50: 3. 이익잉여금 | C50: 68227534743 | D50: 74398196998
B51: 자 본 총 계 | C51: 65687151143 | D51: 74045964168
B52: 부채와 자본총계 | C52: 85314022168 | D52: 106288772035

Sheet MergerMarket
B2: Source : Mergermarket
B4: Announced Date | C4: Completed Date | D4: Target Company | E4: Target Description | F4: Target Country | G4: Bidder Company | H4: Bidder Description | I4: Seller Company | J4: Seller Description | K4: Implied Equity Value (m) | L4: Net Debt (m) | M4: Enterprise Value (m) | N4: Reported Y1 Date | O4: Reported Revenue (m) Y1 | P4: Reported EBITDA (m) Y1 | Q4: Reported EBIT (m) Y1 | R4: Deal Description | S4: Deal Value USD(m)
B5: 03/08/2017 | C5: 10/02/2017 | D5: Suez Water Technologies & Solutions | E5: US-based supplier of water and provider of waste water and process systems solutions | F5: USA | G5: Caisse de Depot et Placement du Quebec; Suez | H5: Canada-based institutional fund manager investing in financial markets, private equity, infrastructure, real estate and private debt. It's private equity investment constitute minority equity stakes of range between CAD 125 million and 1 billion; France-based company engaged in the drinking water distribution, wastewater treatment and waste management activities through its subsidiaries | I5: General Electric Company | J5: US-based diversified technology and financial services company | M5: 3378.56 | N5: 12/31/2016 | O5: 2091.7226 | P5: 340.1537 | R5: Suez and Caisse de Depot et Placement du Quebec have entered into a binding agreement to acquire GE Water & Process Technologies, from General Electric Company. Suez is a listed France-based company engaged in the drinking water distribution, waste water treatment and waste management activities through its subsidiaries, headquartered in Paris. Caisse de Depot et Placement du Quebec (CDPQ) is a Canada-based privately owned investment manager, headquartered in Quebec. GE Water & Process Technologies is the US-based supplier of water and provider of waste water and process systems solutions, headquartered in Trevose, Pennsylvania. General Electric Company is the listed US-based diversified technology and financial services company, headquartered in Fairfield, Connecticut. Terms: The enterprise value of the transaction is EUR 3.2bn which will be paid in cash. The transaction is structured as a 70/30 joint venturebetween Suez and CDPQ, wherein CDPQ will invest EUR 0.7bn for its 30% stake , and Suez will invest the remaining EUR 2.5bn. The consideration represents 10.0x 2016 EBITDA of GE Water including cost synergies, and 12.8x 2016 operating cash flow, including synergies. Financing: Suez plans to finance the transaction with a fully underwritten bridge financing , which will later be refinanced via: A capital increase of approximately EUR 0.75bn. Suez main shareholders Engie, CriteriaCaixa and Caltagirone Group already confirmed their intent to participate in the capital increase for their pro rata share. ENGIE, a major shareholder of Suez who owns 32.6% stake has announced that it will invest around EUR 240 min the capital increase. A long-term senior bond of approximately EUR 1.1bn. Hybrid bonds for approximately EUR 0.6bn. Rationale: The transaction will combine the systems and service offerings of Suez and GE, covering the entire value chain making Suez, a leader in waterresource management. It enhances Suez’s long term profitable growth, and offers strong value to its shareholders and also broadens access of Suez to the industrial clients The deal strengthens the global footprint of Suez in key geographies, especially in the US and the emerging markets. It will increases the innovation capabilities of Suez to deliver performing solutions, with an worldwide network of R&D centres, a huge portfolio of patents and a cutting-edge digital platform, InSight. The acquisition is expected to generate significant cost and revenue synergies for Suez alongwith positive free cash flow from year one. The deal is fully aligned with the Suez’sfinancial discipline, to maintain strong investment grade rating profile. It is in line with CDPQ’s longterm vision and strategy of increasing its emphasis on stable assets, anchored in the real economy. The deal enables CDPQ to increase its exposure in the water segment and is expected to generate long-term value. It will provide Suez with cross selling opportunities as they have complementary customer base, industry verticals and value chain and geographies. The contribution of GE Water to the Industrial Solutions business of Suez will enable the company to further optimize its operations in manufacturing supply chain, engineering and services deliveries. It also creates business opportunities for Suez and its other businesses, especially in the recycling and resources, and the energy recovery sector. Below are benefits of cost and revenue synergies from the transaction, which are expected to be realized by the end of year 5: EUR 65m impact on EBITDA from identified annual run]rate cost synergies, of which 80% are expected to be achieved in year 3 Implementation costs, spread over 2017]19, are expected to be equal to one year of cost synergies Revenue synergies of EUR 200mare expected per year. Post Deal Details: Pursuant to the acquisition, SUEZ will contribute its existing industrial water activities to the newly dedicated Industrial Water business unit. The employees of GE Water will join the team of Suez to form an unparalleled industrial water platform. Expected Completion Date: The transaction is expected to complete by mid-2017. Conditions: Receipt of required regulatory approvals from merger control authorities, in the European Union and the US Other customary closing conditions. Background: GE Water operates across 130 countries, generated annual revenue of approximately USD 2.1bn in 2016 and has a workforce of 7,500 employees. The transaction has been approved by the Board of Suez. It was previously submitted to the opinion of the European WorksCouncil. Earlier in October 2016, GE planned to sell GE Water. The transaction was conducted via an auction in which GE Water has received a bid from Suez and CDPQ. Blackstone Group, Warburg Pincus, CD&R and Bain Capital were the competitors against the bid. UPDATE 02 October 2017: Suez has completed the acquisition of GE Water & Process Technologies. Source Links: Suez press release, 08 March 2017 Suez press release, 08 March 2017 (French) Caisse de Depot et Placement du Quebec press release, 08 March 2017 Caisse de Depot et Placement du Quebec press release, 08 March 2017 (French) Engie SA press release, 08 March 2017 Engie SA press release, 08 March 2017 (French) Davis Polk & Wardwell LLP press release, 08 March 2017 Suez press release, 02 October 2017 (French) Suez press release, 02 October 2017 | S5: 3379
B6: 05/02/2017 | C6: 05/22/2017 | D6: Affinity Water Limited | E6: UK-based water supply company | F6: United Kingdom | G6: Allianz Capital Partners GmbH; Infrastructure Central Limited ; DIF Management B.V. | H6: Germany-based private equity firm. It has three business divisions, private equity, infrastructure and renewables. Its private equity business focuses on fund investments, in the volume of EUR 40-200m per transaction. It specializes in primary and secondary market and co-investment transactions in North/South America, Europe, Asia and Africa. It has EUR 9.7bn assets under management. Its infrastructure business focuses on long-term investments and seeks returns through cash yields, not exits. It primarily focuses on brownfield assets in Europe and US with an operational track record, but can also consider greenfield project. It seeks significant minority or joint control equity stakes of up to 50%, and typically partners with co-investors to acquire controlling equity stakes of up to 100%. It has EUR 5.3bn assets under management. Its renewables division invests in wind farms and solar parks, with a long-term buy-and-hold strategy. In Europe it usually acquires 100% stakes, but can consider joint ventures with industrial partners. In the US it focuses on tax equity and invests alongside a cash equity partner every time. Preferred investment size for the renewables is EUR 50mn to 250mn. It has EUR 3.8bn assets under management. ; Netherlands-based fund management and investment company specialized in infrastructure investments; UK-based Channel Islands-incorporated infrastructure investment company | I6: Veolia Water UK Limited; Infracapital Partners LP; Morgan Stanley Infrastructure Inc. | J6: UK-based private equity firm and infrastructure arm of M&G Investment Management Limited. It invests in utilities, transport, communication, renewables and social infrastructure sectors; UK-based provider of waste, water and energy management services; US-based private equity firm and infrastructure investment arm of Morgan Stanley | K6: 948.5175 | L6: 1126.6194 | M6: 2075.1369 | N6: 03/31/2017 | O6: 385.4262 | P6: 167.9289 | Q6: 97.1351 | R6: Allianz Capital Partners GmbH, HICL Infrastructure Company Limited and Dutch Infrastructure Fund B.V. have signed a definitive agreement to acquire Affinity Water Limited from Infracapital Partners LP, Morgan Stanley Infrastructure Inc., Partners Group Holding AG, Veolia Water UK Limited and Gingko Tree Investments Limited. Allianz Capital Partners GmbH (Allianz Capital), the Germany-based company, headquartered in Munich, is an investment arm of Allianz SE. Allianz SE, the listed Germany-based company, headquartered in Munich, is a provider of insurance, banking and asset management services. HICL Infrastructure Company Limited (HICL), the listed UK-based company, headquartered in London, is an infrastructure investment firm. Dutch Infrastructure Fund B.V. Netherlands-based company, headquartered in Schiphol, is a principal investment firm specializing in investing public private partnership projects. Affinity Water Limited, the UK-based company, headquartered in Hatfield, is a water supply company. Infracapital Partners II LP, the UK-based infrastructure fund of Infracapital Partners LP. Infracapital Partners LP, the UK-based company, headquartered in London, is an infrastructure arm of M&G Investments. M&G Investments, the UK-based company, headquartered in London, is an asset management firm. North Haven Infrastructure Partners LP, the US-based infrastructure fund of Morgan Stanley Infrastructure Inc. Morgan Stanley Infrastructure Inc., the US-based company, headquartered in New York, is an infrastructure investment arm of Morgan Stanley. Terms: Allianz, DIF and HICL have agreed to acquire 100% stake in Affinity Water Acquisitions (Investments) Limited, a holding company and an indirect owner of 90% of Affinity Water, from Infracapital and Morgan Stanley, for a consideration of GBP 687m. As part of the transaction, Allianz, DIF and HICL will also acquire Veolia Water UK Limited’s 10% indirect stake in Affinity Water. HICL will pay GBP 269m for the acquisition of 36.6% stake in Affinity Water. The equity value of Affinity Water is GBP 735m. Affinity Water had unaudited net debt of GBP 873.01m as of 30 September 2016, thereby valuing the transaction at GBP 1.608bn. Financing: HICL will finance the transaction utilizing its cash resources and revolving credit facility. Rationale: The acquisition will enable Allianz to expand its product portfolio of high-quality core infrastructure assets. The investment will deliver inflation-linked, stable and predictable cash-flows, which are perfect for matching long-term payment obligations to the customers in Allianz’s core business of insurance. The transaction is in line with HICL's strategy of investing in assets that are positioned at the lower end of the risk spectrum in three market segments: PPP projects, regulated assets and demand-based assets. The acquisition will provide long-term returns for the shareholders of HICL. The transaction will be accretive to HICL’s existing portfolio in terms of total return, weighted average asset life and inflation correlation. The acquisition will enhance Affinity Water to provide high quality services to its customers. Post Deal Details: Pursuant to the transaction, Allianz, DIF and HICL will own 36.6%, 26.9% and 36.6% stakes respectively in Affinity Water. HICL will have a net funding requirement of around GBP 230m, following completion of the acquisition. Affinity Water will continue to operate in the ordinary course of business. The acquisition will not change the operational level of Affinity Water. Expected Completion: The transaction is expected to be completed by the end of May 2017. Background: Affinity Water serves 1.5m customers across an area of approximately 4,515 sq.km in the south east of England. Affinity Water supplies on an average 900m litres of water a day to over 3.6m people. Affinity Water reported revenues of GBP 302.62m for the year ended 31 March 2016. Prior to the acquisition, Morgan Stanley, Infracapital, Veolia Water UK Limited, Gingko Tree Investments Limited and Partners Group held 40%, 35%, 10%, 10% and 5% stakes respectively in Affinity Water. In October 2012, Infracapital, Gingko Tree and Morgan Stanley had completed the acquisition of UK-based water supply operations of Veolia Water UK Limited, a subsidiary of Veolia Environnement S.A., for a consideration of USD 1.92bn. The three separate water-branded businesses of Veolia, namely Veolia Water Central, Veolia Water Southeast and Veolia Water East were brought together to form Affinity Water Limited. UPDATE 22 May 2017: The consortium has completed the acquistion of Affinity Water Limited. Source Links: HICL Infrastructure Company Limited press release, 22 May 2017 HICL Infrastructure Company Limited stock exchange announcement, 02 May 2017 HICL Infrastructure Company Limited press release, 02 May 2017 Allianz Capital Partners GmbH press release, 02 May 2017 Allianz SE press release, 02 May 2017 Allianz SE press release, 02 May 2017 (German) Affinity Water Limited press release, 02 May 2017 Dutch Infrastructure Fund B.V. press release, 02 May 2017 Infracapital Partners LP press release, 02 May 2017 Affinity Water Limited interim report | S6: 2075
B7: 12/03/2018 | C7: 12/03/2018 | D7: Saur Group | E7: France-based company engaged in providing water management services | F7: France | G7: EQT Partners AB | H7: Sweden-based private equity firm investing in the Healthcare, TMT, Industrial Technology, Consumer and Services sectors. The EQT Equity team typically makes investments in medium to large-sized companies in Northern, Central Europe and the US between EUR 100m and EUR 1000m. As of March 2019, it manages two active funds: EQT VII and EQT VIII. Its latest fund, EQT VIII was launched with target size of around EUR 8bn and closed in February 2018, hitting its hard-cap of EUR 10.75bn. In the middle market segment it typically invests between EUR 50m and EUR 150m in the US, EUR 100m - 300m in Northern Europe, DACH and Benelux and between USD 30m - 250m in Greater China and Southeast Asia. The EQT Mid Market team manages three active funds as of March 2019: EQT Mid Market US, EQT Mid Market Europe and EQT Mid Market Asia III. Its latest fund, EQT Mid Market Asia III closed in May 2018 at USD 800m. The EQT Real Assets team focuses on medium-sized infrastructure businesses in the Nordic region, Continental Europe and North America. It also seeks real estate investment opportunities across selected markets in Europe. Its latest fund, EQT Infrastructure IV fund held a final close in March 2019 at the hard cap of EUR 9bn. The EQT Credit investment platform spans the full risk-reward spectrum and is currently investing three strategies: senior debt, direct lending and credit opportunities. As of March 2019, EQT has raised 29 funds with approximately EUR 61bn in capital and has approximately EUR 40bn assets under management. It has offices in 14 countries across Europe, Asia and North America. EQT was founded in 1994 and is based in Stockholm, Sweden. Its second largest office is in Munich, which was set up in the early 2000s. It has 540 employees, of whom 330 are within the Investment Advisory teams. | M7: 1702.35 | N7: 12/31/2017 | O7: 1548 | P7: 157.2 | R7: EQT Partners AB, a Sweden-based private equity firm through its EQT Infrastructure III, has agreed to acquire Saur Group, a France-based company engaged in providing water management services, for a consideration of EUR 1.5bn. The acquisition will expand EQT’s geographical reach in France as well as other nations. The transaction will accelerate Saur Group’s growth and enhance its geographical reach. Saur Group will benefit from through the synergies generated from EQT’s water infrastructure management, digitalization and sustainable development. The transaction is subject to the required Works Councils consultations, required trade unions consultations and standard regulatory endorsements. The transaction is expected to complete by end of 2018. Saur Group reported revenues of EUR 1.29bn (excluding waste management) and has a workforce of 9000 employees. Source Links: Saur Group press release, 23 July 2018 EQT Partners AB press release, 23 July 2018 Saur Group press release, 23 July 2018 (French) EQT Partners AB press release, 03 December 2018 Saur Group press release, 03 December 2018 Saur Group press release, 23 July 2018 (French) | S7: 1702
B8: 03/17/2018 | C8: 09/28/2018 | D8: FCC Aqualia, S.A. (49% Stake) | E8: Spain-based water management company | F8: Spain | G8: IFM Investors | H8: Australia-based privately owned investment manager. The firm provides its services to pooled investment vehicles, pension and profit sharing plans, insurance companies, and non-U.S. government entities. It manages separate client focused equity and fixed income portfolios. The firm also manages superannuation funds, infrastructure funds, private equity funds, and equity mutual funds. It invests in the public equity and fixed income markets across the globe. For the equity portion of its portfolio, the firm invests in small cap equities of the firm. It also invests in private equity markets including infrastructure and private assets. It typically invests in infrastructure sector and also makes responsible investing. IFM investors was founded in 2004 and is based in Melbourne, Victoria with additional offices in Berlin, Germany, London, United Kingdom, New York City, Sydney, Australia, and Japan, Tokyo. | I8: Fomento de Construcciones y Contratas SA | J8: Spain-based construction company engaged in general construction, environmental services and renewable energy | K8: 2569.6789 | L8: 585.4661 | M8: 3155.145 | N8: 12/31/2017 | O8: 1242.252 | P8: 289.4772 | Q8: 178.5612 | R8: IFM Investors, an Australia-based fund management and private equity firm, through IFM Global Infrastructure Fund, an Australia-based infrastructure fund, has agreed to acquire a 49% stake in FCC Aqualia, S.A., a Spain-based water management company, from Fomento de Construcciones y Contratas SA (FCC), a listed Spain-based construction company engaged in general construction, environmental services and renewable energy, for a consideration of EUR 1.024bn. The transaction values Aqualia’s implied equity at EUR 2.09bn. The sale proceeds will enable FCC to reduce their debt and for other corporate needs. The acquisition will enable Aqualia to strengthen their position and develop in new markets with active involvement of IFM. It will also allow Aqualia to tap into market opportunities further reinforce its commitment to partnering administrations to deliver a public service. Post transaction, FCC will continue to control Aqualia. Aqualia plans to maintain its current strategy, operations and commercial relations. The transaction is expected to close by end of August 2018, subject to relevant merger control approvals, consent of FCC's senior lenders and customary closing conditions. Aqualia reported revenues of EUR 1.03bn and EBITDA of EUR 241m in 2017 and has a workforce of over 7,500 employees. Currently, Aqualia provides services to 23.6m people in 1,100 municipalities in 22 countries. UPDATE 28 September 2018: IFM Investors completed the acquisition of FCC Aqualia, S.A. from Fomento de Construcciones y Contratas SA. Source Links: Fomento de Construcciones y Contratas SA press release, 20 February 2018 Fomento de Construcciones y Contratas SA stock exchange announcement, 17 March 2018 Fomento de Construcciones y Contratas SA stock exchange announcement, 17 March 2018 (Spanish) Fomento de Construcciones y Contratas SA press release, 19 March 2018 Fomento de Construcciones y Contratas SA press release, 19 March 2018 (Spanish) IFM Investors press release, 19 March 2018 Fomento de Construcciones y Contratas SA press release, 28 September 2018 | S8: 1260
B9: 12/15/2017 | C9: 02/21/2018 | D9: Anglian Water Group Ltd (15% Stake) | E9: UK-based company providing drinking water and wastewater services | F9: United Kingdom | G9: Dalmore Capital Limited; GLIL Infrastructure LLP | H9: UK-based fund management company that focuses on lower risk opportunities for institutional investors in infrastructure sector; UK-based infrastructure investment company | I9: 3i Infrastructure plc | J9: Channel Islands-based, UK listed private equity firm investing in infrastructure businesses and assets around the globe with a primary focus on European, North American, and Asian markets | K9: 3523.3955 | L9: 9489.765 | M9: 13013.16 | N9: 03/31/2017 | O9: 1682.6232 | P9: 838.6269 | Q9: 446.7849 | R9: Dalmore Capital, the UK-based fund management company, and GLIL Infrastructure LLP, the UK-based infrastructure investment company, have together agreed to acquire a 15% stake in Anglian Dalmore Capital, the UK-based fund management company, and GLIL Infrastructure LLP, the UK-based infrastructure investment company, have agreed to acquire a 15% stake in Anglian Water Group (AWG), the UK-based company providing drinking water and wastewater services, from 3i Infrastructure plc, a Channel Islands-based UK listed private equity firm, for a consideration of GBP 395m. The transaction is in line with Dalmore and GLIL’s shared investment philosophy and strategy to invest in UK infrastructure resources. The acquisition is expected to close in early 2018 and is subject to certain third party consents. AWG reported revenues of GBP 1.35bn and net loss of GBP 13.40m for the year ended 31 March 2017. It has a workforce of 4,500 employees. Earlier in 2007, 3i Infrastructure had acquired a 15% stake in AWG, following its take-private in 2006 by a consortium of investors. UPDATE 21/02/2018: Dalmore Capital Limited and GLIL Infrastructure LLP completed the acquisition of Anglian Water Group Ltd from 3i Infrastructure plc. Source Links: 3i Infrastructure plc press release, 27 June 2017 3i Infrastructure plc press release, 15 December 2017 3i Infrastructure plc stock exchange announcement, 18 December 2017 3i Infrastructure plc press release, 21 February 2018 Anglian Water Group annual report Income Statement Balance Sheet | S9: 529
B10: 09/13/2017 | C10: 04/24/2018 | D10: TRILITY Pty Ltd | E10: Australia-based company engaged in providing water utility services | F10: Australia | G10: Beijing Enterprises Water Group Limited | H10: Hong Kong-based HKEx-listed company headquartered in Hong Kong, is engaged in the construction of sewage and water treatment plants and provision of integrated water system solutions | I10: Mitsubishi Corporation; JGC Corporation; INCJ, Ltd. | J10: Japan-based government-sponsored private equity and venture capital firm headquartered in Tokyo. INCJ, Ltd. was established in September 2018 via company split from Innovation Network Corporation of Japan (INCJ) which has changed its name to Japan Investment Corporation (JIC) and begun new activities. INCJ, Ltd. will continue the activities of INCJ, engaging in Value Up activities such as overseeing additional investments, milestone investments and exits from investments in portfolio companies until March 2025. INCJ was established in 2009 with the aim of lasting for 15 years. INCJ has invested in a sectors including energy, TMT, consumer, healthcare, automobiles, chemicals, and others. INCJ is capitalized at JPY 300bn, of which JPY 286bn is from the Japanese government and JPY 14bn from investors in the private sector. INCJ has the capacity to invest up to JPY2 trillion(approx. US$20 billion). ; Listed Japan-based company engaged in providing engineering designing service and building industrial plants and refineries, and developing oil, gas and other natural resources ; Listed Japan-based conglomerate engaged in chemical and steel plants, shipbuilding, automobiles, construction equipment, industrial machinery, real estate, iron and steel industries, non-ferrous metals, basic and specialty chemicals, novel synthetic fiber materials, petrochemicals, non-organic chemicals and fertilizers, textiles and clothing, lumber and paper, food and distribution, information and logistics technology | M10: 200.275 | N10: 03/31/2017 | O10: 63.1394 | P10: 21.342 | Q10: 12.9031 | R10: Beijing Enterprises Water Group Limited, the HKEx-listed Hong Kong-based company engaged in the construction of sewage and water treatment plants and provision of integrated water system solutions, has agreed to acquire TRILITY Pty Ltd, an Australia-based company engaged in providing water utility services, from Mitsubishi Corporation, the listed Japan-based conglomerate, JGC Corporation, the listed Japan-based engineering designers and builders of industrial plants and refineries and Innovation Network Corporation of Japan, the Japan based investment company engaged in supporting the development of new and existing industries, for an estimated consideration of approximately AUD 250m (USD 200.27m). Beijing Enterprises is funding the transaction via internal funding. The transaction has already got necessary regulatory approvals from the State Water Authorities and the Foreign Investment Review Board. Prior to this transaction, Mitsubishi, Innovation Network and JGC held 60%, 30% and 10% stake, respectively, in TRILITY. In May 2010, Mitsubishi along with JGC, Manila Water Company and Innovation Network, had acquired TRILITY, from United Utilities Group Plc, for a net consideration of AUD 225m (USD 199.84m). TRILITY owners started seeking for potential buyers since November 2016. The bidders who participated in the auction process were China Everbright Water, Colonial First State, H.R.L. Morrison, Downer EDI, CIMIC and AMP Capital Pty Ltd. UPDATE 24 April 2018: Beijing Enterprises Water Group Limited has completed the acquistion of TRILITY Pty Ltd. Source link: Beijing Enterprises Water Group Limited press release, 24 April 2018 | S10: 200
