Workbook

Sheet for IM
B2: FCF Conversion
C4: 구분 | D4: 25H1 | E4: 억환산 | H4: CAPEX | I4: 25H1
C5: 매출액 | D5: =E81 -> 33392.893 | E5: =D5/100 -> 333.92893 | H5: Titan | I5: =TITAN!M103 -> 42.7038
C6: 영업비용 | D6: =-E85 -> -24315.748 | E6: =D6/100 -> -243.15748 | H6: Class | I6: =CLASS!M103 -> 115.6239
C7: D&A | D7: =E93 -> 57.174702 | E7: =D7/100 -> 0.57174702 | H7: Nova | I7: =NOVA!M79 -> 28.309429
C8: EBITDA | D8: =E94 -> 9134.3195 | E8: =D8/100 -> 91.343195 | F8: =E8/E5 -> 0.27354082 | H8: TTA | I8: =TTA!M87 -> 10.438546
C9: CAPEX | D9: =-SUM(I5:I8) -> -197.07568 | E9: =D9/100 -> -1.9707568
C10: △NWC | D10: =-'Pro forma BS'!M58 -> -2408.5126 | E10: =D10/100 -> -24.085126
C11: FCF | D11: =D8+D9+D10 -> 6528.7312 | E11: =D11/100 -> 65.287312 | F11: =E11/E8 -> 0.71474741
B13: Business Plan Overview
J14: >> 값복사
C15: Year | D15: 강의매출 | E15: 솔루션매출 | F15: 기타매출 | G15: 합계 | H15: EBITDA율 | J15: Year | K15: 강의매출 | L15: 솔루션매출 | M15: 기타매출 | N15: 합계 | O15: EBITDA율
C16: 2024A | D16: =D82/100 -> 111.92304 | F16: =D84 -> 31.054544 | G16: =D81/100 -> 112.23359 | H16: =D95 -> 0.19212933 | J16: 2024A | K16: 111.92304 | M16: 31.054544 | N16: 112.23359 | O16: 0.19212933
C17: 2025E | D17: {=TRANSPOSE(F82:K83)/100} -> 747.53703 | E17: 25.707433 | G17: {=TRANSPOSE(F81:K81)/100} -> 773.24447 | H17: {=TRANSPOSE(F95:K95)} -> 0.29740087 | J17: 2025E | K17: 747.53703 | L17: 25.707433 | N17: 773.24447 | O17: 0.29740087
C18: 2026F | D18: 860.73301 | E18: 71.962766 | G18: 932.69577 | H18: 0.37983296 | J18: 2026F | K18: 860.73301 | L18: 71.962766 | N18: 932.69577 | O18: 0.37983296
C19: 2027F | D19: 941.09021 | E19: 94.261391 | G19: 1035.3516 | H19: 0.42053463 | J19: 2027F | K19: 941.09021 | L19: 94.261391 | N19: 1035.3516 | O19: 0.42053463
C20: 2028F | D20: 1027.0793 | E20: 119.24423 | G20: 1146.3235 | H20: 0.42991681 | J20: 2028F | K20: 1027.0793 | L20: 119.24423 | N20: 1146.3235 | O20: 0.42991681
C21: 2029F | D21: 1114.0782 | E21: 146.53889 | G21: 1260.6171 | H21: 0.43864079 | J21: 2029F | K21: 1114.0782 | L21: 146.53889 | N21: 1260.6171 | O21: 0.43864079
C22: 2030F | D22: 1204.6789 | E22: 176.54417 | G22: 1381.2231 | H22: 0.44670162 | J22: 2030F | K22: 1204.6789 | L22: 176.54417 | N22: 1381.2231 | O22: 0.44670162
B24: KPI
H25: >> 값복사
C26: Year | D26: 부업 강의 | E26: 투자 강의 | F26: 합계 | H26: Year | I26: 부업 강의 | J26: 투자 강의 | K26: 합계
C27: 2024A | D27: =SUM(D36:F36) -> 65 | F27: =D27+E27 -> 65 | H27: 2024A | I27: 65 | K27: 65
C28: 2025E | D28: =SUM(D37:F37) -> 235.1 | E28: {=TRANSPOSE('Key Assumption'!O32:T32)} -> 11 | F28: =D28+E28 -> 246.1 | H28: 2025E | I28: 235.1 | J28: 11 | K28: 246.1
C29: 2026F | D29: =SUM(D38:F38) -> 256.08 | E29: 11 | F29: =D29+E29 -> 267.08 | H29: 2026F | I29: 256.08 | J29: 11 | K29: 267.08
C30: 2027F | D30: =SUM(D39:F39) -> 277.06 | E30: 11 | F30: =D30+E30 -> 288.06 | H30: 2027F | I30: 277.06 | J30: 11 | K30: 288.06
C31: 2028F | D31: =SUM(D40:F40) -> 298.04 | E31: 11 | F31: =D31+E31 -> 309.04 | H31: 2028F | I31: 298.04 | J31: 11 | K31: 309.04
C32: 2029F | D32: =SUM(D41:F41) -> 319.02 | E32: 11 | F32: =D32+E32 -> 330.02 | H32: 2029F | I32: 319.02 | J32: 11 | K32: 330.02
C33: 2030F | D33: =SUM(D42:F42) -> 340 | E33: 11 | F33: =D33+E33 -> 351 | H33: 2030F | I33: 340 | J33: 11 | K33: 351
D35: 부업-Titan | E35: 부업-Class | F35: 부업-TTA
C36: 2024A | D36: ='Key Assumption'!L23 -> 65
C37: 2025E | D37: {=TRANSPOSE('Key Assumption'!O23:T23)} -> 92.2 | E37: {=TRANSPOSE('Key Assumption'!O28:T28)} -> 93.4 | F37: {=TRANSPOSE('Key Assumption'!O37:T37)} -> 49.5
C38: 2026F | D38: 97.76 | E38: 98.72 | F38: 59.6
C39: 2027F | D39: 103.32 | E39: 104.04 | F39: 69.7
C40: 2028F | D40: 108.88 | E40: 109.36 | F40: 79.8
C41: 2029F | D41: 114.44 | E41: 114.68 | F41: 89.9
C42: 2030F | D42: 120 | E42: 120 | F42: 100
H44: >> 값복사
C45: Year | D45: 구축관리형 플랫폼 | E45: 구축형 플랫폼 | F45: 합계 | H45: Year | I45: 부업 강의 | J45: 투자 강의 | K45: 합계
C46: 2024A | H46: 2024A
C47: 2025E | D47: {=TRANSPOSE('Key Assumption'!O44:T44)} -> 5.25 | F47: =D47+E47 -> 5.25 | H47: 2025E | I47: 5.25 | K47: 5.25
C48: 2026F | D48: 8 | E48: {=TRANSPOSE('Key Assumption'!P48:T48)} -> 3 | F48: =D48+E48 -> 11 | H48: 2026F | I48: 8 | J48: 3 | K48: 11
C49: 2027F | D49: 9 | E49: 4.75 | F49: =D49+E49 -> 13.75 | H49: 2027F | I49: 9 | J49: 4.75 | K49: 13.75
C50: 2028F | D50: 10 | E50: 6.5 | F50: =D50+E50 -> 16.5 | H50: 2028F | I50: 10 | J50: 6.5 | K50: 16.5
C51: 2029F | D51: 11 | E51: 8.25 | F51: =D51+E51 -> 19.25 | H51: 2029F | I51: 11 | J51: 8.25 | K51: 19.25
C52: 2030F | D52: 12 | E52: 10 | F52: =D52+E52 -> 22 | H52: 2030F | I52: 12 | J52: 10 | K52: 22
B55: Pro-Forma BS
C57: (단위: 백만원) | D57: 2024A | E57: 2025 H1 | F57: 2025E | G57: 2026F | H57: 2027F | I57: 2028F | J57: 2029F | K57: 2030F
C58: 유동자산 | D58: ='Pro forma BS'!L32 -> 3393.8404 | E58: ='Pro forma BS'!M32 -> 15473.031 | F58: ='Pro forma BS'!O32 -> 23214.434 | G58: ='Pro forma BS'!P32 -> 42605.176 | H58: ='Pro forma BS'!Q32 -> 59586.579 | I58: ='Pro forma BS'!R32 -> 77108.596 | J58: ='Pro forma BS'!S32 -> 95870.9 | K58: ='Pro forma BS'!T32 -> 115971.17
C59: 현금및현금성자산 | D59: ='Pro forma BS'!L33 -> 1161.7762 | E59: ='Pro forma BS'!M33 -> 3776.9549 | F59: ='Pro forma BS'!O33 -> 12536.878 | G59: ='Pro forma BS'!P33 -> 30525.74 | H59: ='Pro forma BS'!Q33 -> 46754.786 | I59: ='Pro forma BS'!R33 -> 63289.258 | J59: ='Pro forma BS'!S33 -> 81036.882 | K59: ='Pro forma BS'!T33 -> 100068.75
C60: 운전자산 | D60: ='Pro forma BS'!L35 -> 1641.1379 | E60: ='Pro forma BS'!M35 -> 8174.6202 | F60: ='Pro forma BS'!O35 -> 7156.1012 | G60: ='Pro forma BS'!P35 -> 8557.9806 | H60: ='Pro forma BS'!Q35 -> 9310.3382 | I60: ='Pro forma BS'!R35 -> 10297.883 | J60: ='Pro forma BS'!S35 -> 11312.562 | K60: ='Pro forma BS'!T35 -> 12380.965
C61: 기타유동자산 | D61: =D58-D59-D60 -> 590.92622 | E61: =E58-E59-E60 -> 3521.4555 | F61: =F58-F59-F60 -> 3521.4555 | G61: =G58-G59-G60 -> 3521.4555 | H61: =H58-H59-H60 -> 3521.4555 | I61: =I58-I59-I60 -> 3521.4555 | J61: =J58-J59-J60 -> 3521.4555 | K61: =K58-K59-K60 -> 3521.4555
C62: 비유동자산 | D62: ='Pro forma BS'!L38 -> 1137.2261 | E62: ='Pro forma BS'!M38 -> 1856.4592 | F62: ='Pro forma BS'!O38 -> 1849.4094 | G62: ='Pro forma BS'!P38 -> 1827.5494 | H62: ='Pro forma BS'!Q38 -> 1810.156 | I62: ='Pro forma BS'!R38 -> 1797.3912 | J62: ='Pro forma BS'!S38 -> 1789.524 | K62: ='Pro forma BS'!T38 -> 1780.2847
C63: 유무형자산 | D63: ='Pro forma BS'!L40 -> 987.43582 | E63: ='Pro forma BS'!M40 -> 1080.9109 | F63: ='Pro forma BS'!O40 -> 1073.8611 | G63: ='Pro forma BS'!P40 -> 1052.001 | H63: ='Pro forma BS'!Q40 -> 1034.6076 | I63: ='Pro forma BS'!R40 -> 1021.8429 | J63: ='Pro forma BS'!S40 -> 1013.9757 | K63: ='Pro forma BS'!T40 -> 1004.7364
C64: 기타비유동자산 | D64: =D62-D63 -> 149.79032 | E64: =E62-E63 -> 775.54832 | F64: =F62-F63 -> 775.54832 | G64: =G62-G63 -> 775.54832 | H64: =H62-H63 -> 775.54832 | I64: =I62-I63 -> 775.54832 | J64: =J62-J63 -> 775.54832 | K64: =K62-K63 -> 775.54832
C65: 자산총계 | D65: =D62+D58 -> 4531.0665 | E65: =E62+E58 -> 17329.49 | F65: =F62+F58 -> 25063.844 | G65: =G62+G58 -> 44432.726 | H65: =H62+H58 -> 61396.735 | I65: =I62+I58 -> 78905.987 | J65: =J62+J58 -> 97660.424 | K65: =K62+K58 -> 117751.46
C66: 유동부채 | D66: ='Pro forma BS'!L43 -> 1203.7292 | E66: ='Pro forma BS'!M43 -> 6466.7597 | F66: ='Pro forma BS'!O43 -> 7266.716 | G66: ='Pro forma BS'!P43 -> 7841.884 | H66: ='Pro forma BS'!Q43 -> 8226.6176 | I66: ='Pro forma BS'!R43 -> 9012.9826 | J66: ='Pro forma BS'!S43 -> 9811.4643 | K66: ='Pro forma BS'!T43 -> 10643.901
C67: 단기차입금 | D67: ='Pro forma BS'!L44 -> 100 | E67: ='Pro forma BS'!M44 -> 100 | F67: ='Pro forma BS'!O44 -> 100 | G67: ='Pro forma BS'!P44 -> 100 | H67: ='Pro forma BS'!Q44 -> 100 | I67: ='Pro forma BS'!R44 -> 100 | J67: ='Pro forma BS'!S44 -> 100 | K67: ='Pro forma BS'!T44 -> 100
C68: 운전부채 | D68: ='Pro forma BS'!L45 -> 437.91273 | E68: ='Pro forma BS'!M45 -> 5875.5802 | F68: ='Pro forma BS'!O45 -> 6675.4256 | G68: ='Pro forma BS'!P45 -> 7250.3618 | H68: ='Pro forma BS'!Q45 -> 7634.8318 | I68: ='Pro forma BS'!R45 -> 8420.9316 | J68: ='Pro forma BS'!S45 -> 9219.1464 | K68: ='Pro forma BS'!T45 -> 10051.315
C69: 미지급법인세 | D69: ='Pro forma BS'!L46 -> 596.78793 | E69: ='Pro forma BS'!M46 -> 336.46338 | F69: ='Pro forma BS'!O46 -> 336.57424 | G69: ='Pro forma BS'!P46 -> 336.8061 | H69: ='Pro forma BS'!Q46 -> 337.06961 | I69: ='Pro forma BS'!R46 -> 337.33486 | J69: ='Pro forma BS'!S46 -> 337.60172 | K69: ='Pro forma BS'!T46 -> 337.87004
C70: 기타유동부채 | D70: =D66-D67-D68-D69 -> 69.028535 | E70: =E66-E67-E68-E69 -> 154.71614 | F70: =F66-F67-F68-F69 -> 154.71614 | G70: =G66-G67-G68-G69 -> 154.71614 | H70: =H66-H67-H68-H69 -> 154.71614 | I70: =I66-I67-I68-I69 -> 154.71614 | J70: =J66-J67-J68-J69 -> 154.71614 | K70: =K66-K67-K68-K69 -> 154.71614
C71: 비유동부채 | D71: ='Pro forma BS'!L48 -> 575.19028 | E71: ='Pro forma BS'!M48 -> 611.75831 | F71: ='Pro forma BS'!O48 -> 773.11313 | G71: ='Pro forma BS'!P48 -> 1183.8449 | H71: ='Pro forma BS'!Q48 -> 1632.4845 | I71: ='Pro forma BS'!R48 -> 2121.524 | J71: ='Pro forma BS'!S48 -> 2650.5397 | K71: ='Pro forma BS'!T48 -> 3221.396
C72: 장기차입금 | D72: ='Pro forma BS'!L49 -> 542 | E72: ='Pro forma BS'!M49 -> 542 | F72: ='Pro forma BS'!O49 -> 542 | G72: ='Pro forma BS'!P49 -> 542 | H72: ='Pro forma BS'!Q49 -> 542 | I72: ='Pro forma BS'!R49 -> 542 | J72: ='Pro forma BS'!S49 -> 542 | K72: ='Pro forma BS'!T49 -> 542
C73: 기타비유동부채 | D73: ='Pro forma BS'!L50 -> 33.190278 | E73: ='Pro forma BS'!M50 -> 69.75831 | F73: ='Pro forma BS'!O50 -> 231.11313 | G73: ='Pro forma BS'!P50 -> 641.84495 | H73: ='Pro forma BS'!Q50 -> 1090.4845 | I73: ='Pro forma BS'!R50 -> 1579.524 | J73: ='Pro forma BS'!S50 -> 2108.5397 | K73: ='Pro forma BS'!T50 -> 2679.396
C74: 부채총계 | D74: =D71+D66 -> 1778.9195 | E74: =E71+E66 -> 7078.518 | F74: =F71+F66 -> 8039.8291 | G74: =G71+G66 -> 9025.729 | H74: =H71+H66 -> 9859.1021 | I74: =I71+I66 -> 11134.507 | J74: =J71+J66 -> 12462.004 | K74: =K71+K66 -> 13865.297
C75: 자본총계 | D75: =D65-D74 -> 2752.1471 | E75: =E65-E74 -> 10250.972 | F75: =F65-F74 -> 17024.015 | G75: =G65-G74 -> 35406.997 | H75: =H65-H74 -> 51537.633 | I75: =I65-I74 -> 67771.481 | J75: =J65-J74 -> 85198.42 | K75: =K65-K74 -> 103886.16
D76: ='Pro forma BS'!L52=D75 -> TRUE | E76: ='Pro forma BS'!M52=E75 -> TRUE | F76: ='Pro forma BS'!N52=F75 -> TRUE | G76: ='Pro forma BS'!P52=G75 -> TRUE | H76: ='Pro forma BS'!Q52=H75 -> TRUE | I76: ='Pro forma BS'!R52=I75 -> TRUE | J76: ='Pro forma BS'!S52=J75 -> TRUE | K76: ='Pro forma BS'!T52=K75 -> TRUE
B78: Pro-Forma PL
C80: (단위: 백만원) | D80: 2024A | E80: 2025 H1 | F80: 2025E | G80: 2026F | H80: 2027F | I80: 2028F | J80: 2029F | K80: 2030F
C81: 매출액 | D81: =SUM(D82:D84) -> 11223.359 | E81: =SUM(E82:E84) -> 33392.893 | F81: =SUM(F82:F84) -> 77324.447 | G81: =SUM(G82:G84) -> 93269.577 | H81: =SUM(H82:H84) -> 103535.16 | I81: =SUM(I82:I84) -> 114632.35 | J81: =SUM(J82:J84) -> 126061.71 | K81: =SUM(K82:K84) -> 138122.31
C82: 강의매출 | D82: =D102+D106+D113 -> 11192.304 | E82: =E102+E106+E113 -> 33173.573 | F82: =F102+F106+F113 -> 74753.703 | G82: =G102+G106+G113 -> 86073.301 | H82: =H102+H106+H113 -> 94109.021 | I82: =I102+I106+I113 -> 102707.93 | J82: =J102+J106+J113 -> 111407.82 | K82: =K102+K106+K113 -> 120467.89
C83: 솔루션매출 | D83: =D108-D111 -> 0 | E83: =E108-E111 -> 219.32018 | F83: =F108-F111 -> 2570.7433 | G83: =G108-G111 -> 7196.2766 | H83: =H108-H111 -> 9426.1391 | I83: =I108-I111 -> 11924.423 | J83: =J108-J111 -> 14653.889 | K83: =K108-K111 -> 17654.417
C84: 기타매출 | D84: =D103+D107 -> 31.054544 | E84: =E103+E107 -> 0 | F84: =F103+F107 -> 0 | G84: =G103+G107 -> 0 | H84: =H103+H107 -> 0 | I84: =I103+I107 -> 0 | J84: =J103+J107 -> 0 | K84: =K103+K107 -> 0
C85: 영업비용 | D85: =SUM(D86:D88) -> 9194.9006 | E85: =SUM(E86:E88) -> 24315.748 | F85: =SUM(F86:F88) -> 54467.237 | G85: =SUM(G86:G88) -> 57986.595 | H85: =SUM(H86:H88) -> 60124.892 | I85: =SUM(I86:I88) -> 65467.261 | J85: =SUM(J86:J88) -> 70872.351 | K85: =SUM(K86:K88) -> 76518.723
C86: 인건비 | D86: ='Pro forma PL'!L8 -> 664.89449 | E86: ='Pro forma PL'!M8 -> 988.67775 | F86: ='Pro forma PL'!O8 -> 2794.906 | G86: ='Pro forma PL'!P8 -> 5597.9335 | H86: ='Pro forma PL'!Q8 -> 6113.6151 | I86: ='Pro forma PL'!R8 -> 6662.5778 | J86: ='Pro forma PL'!S8 -> 7205.6801 | K86: ='Pro forma PL'!T8 -> 7774.0943
C87: 변동비 | D87: =D115+D116 -> 7603.4827 | E87: =E115+E116 -> 21864.136 | F87: =F115+F116 -> 48716.112 | G87: =G115+G116 -> 49380.844 | H87: =H115+H116 -> 50965.933 | I87: =I115+I116 -> 55710.68 | J87: =J115+J116 -> 60526.946 | K87: =K115+K116 -> 65556.135
C88: 고정비 | D88: ='Pro forma PL'!L10 -> 926.52339 | E88: ='Pro forma PL'!M10 -> 1462.9347 | F88: ='Pro forma PL'!O10 -> 2956.2189 | G88: ='Pro forma PL'!P10 -> 3007.8182 | H88: ='Pro forma PL'!Q10 -> 3045.3445 | I88: ='Pro forma PL'!R10 -> 3094.0035 | J88: ='Pro forma PL'!S10 -> 3139.7249 | K88: ='Pro forma PL'!T10 -> 3188.4931
C89: 영업이익 | D89: =D81-D85 -> 2028.4584 | E89: =E81-E85 -> 9077.1448 | F89: =F81-F85 -> 22857.21 | G89: =G81-G85 -> 35282.982 | H89: =H81-H85 -> 43410.268 | I89: =I81-I85 -> 49165.087 | J89: =J81-J85 -> 55189.358 | K89: =K81-K85 -> 61603.584
C90: 영업이익률 | D90: =D89/D$81 -> 0.18073541 | E90: =E89/E$81 -> 0.27182864 | F90: =F89/F$81 -> 0.29560134 | G90: =G89/G$81 -> 0.37829036 | H90: =H89/H$81 -> 0.41928044 | I90: =I89/I$81 -> 0.42889366 | J90: =J89/J$81 -> 0.43779636 | K90: =K89/K$81 -> 0.44600749
C91: 당기순이익 | D91: =D89+D118-D119 -> 1063.1242 | E91: =E89+E118-E119 -> 8805.794 | F91: =F89+F118-F119 -> 15404.996 | G91: =G89+G118-G119 -> 25971.241 | H91: =H89+H118-H119 -> 31953.516 | I91: =I89+I118-I119 -> 36189.775 | J91: =J89+J118-J119 -> 40624.493 | K91: =K89+K118-K119 -> 45344.454
C92: 당기순이익률 | D92: =D91/D$81 -> 0.094724247 | E92: =E91/E$81 -> 0.26370264 | F92: =F91/F$81 -> 0.19922543 | G92: =G91/G$81 -> 0.27845351 | H92: =H91/H$81 -> 0.30862478 | I92: =I91/I$81 -> 0.31570299 | J92: =J91/J$81 -> 0.32225878 | K92: =K91/K$81 -> 0.32829204
C93: 감가상각비 | D93: ='Pro forma PL'!L21 -> 127.87806 | E93: ='Pro forma PL'!M21 -> 57.174702 | F93: ='Pro forma PL'!O21 -> 139.14745 | G93: ='Pro forma PL'!P21 -> 143.8773 | H93: ='Pro forma PL'!Q21 -> 129.85259 | I93: ='Pro forma PL'!R21 -> 117.28632 | J93: ='Pro forma PL'!S21 -> 106.45002 | K93: ='Pro forma PL'!T21 -> 95.874855
C94: EBITDA | D94: =D89+D93 -> 2156.3364 | E94: =E89+E93 -> 9134.3195 | F94: =F89+F93 -> 22996.357 | G94: =G89+G93 -> 35426.859 | H94: =H89+H93 -> 43540.12 | I94: =I89+I93 -> 49282.373 | J94: =J89+J93 -> 55295.808 | K94: =K89+K93 -> 61699.458
C95: EBITDA율 | D95: =D94/D$81 -> 0.19212933 | E95: =E94/E$81 -> 0.27354082 | F95: =F94/F$81 -> 0.29740087 | G95: =G94/G$81 -> 0.37983296 | H95: =H94/H$81 -> 0.42053463 | I95: =I94/I$81 -> 0.42991681 | J95: =J94/J$81 -> 0.43864079 | K95: =K94/K$81 -> 0.44670162
C97: 매출 | D97: =D81='Pro forma PL'!L6 -> TRUE | E97: =E81='Pro forma PL'!M6 -> TRUE | F97: =F81='Pro forma PL'!O6 -> TRUE | G97: =G81='Pro forma PL'!P6 -> TRUE | H97: =H81='Pro forma PL'!Q6 -> TRUE | I97: =I81='Pro forma PL'!R6 -> TRUE | J97: =J81='Pro forma PL'!S6 -> TRUE | K97: =K81='Pro forma PL'!T6 -> TRUE
C98: 조정EBITDA | D98: =D94='Pro forma PL'!L24 -> TRUE | E98: =E94='Pro forma PL'!M24 -> TRUE | F98: =F94='Pro forma PL'!O24 -> TRUE | G98: =G94='Pro forma PL'!P24 -> TRUE | H98: =H94='Pro forma PL'!Q24 -> TRUE | I98: =I94='Pro forma PL'!R24 -> FALSE | J98: =J94='Pro forma PL'!S24 -> TRUE | K98: =K94='Pro forma PL'!T24 -> TRUE
C101: Titan | D101: =SUM(D102:D104) -> 11203.459 | E101: =SUM(E102:E104) -> 17504.878 | F101: =SUM(F102:F104) -> 35082.076 | G101: =SUM(G102:G104) -> 37812.47 | H101: =SUM(H102:H104) -> 40682.35 | I101: =SUM(I102:I104) -> 43771.909 | J101: =SUM(J102:J104) -> 46881.275 | K101: =SUM(K102:K104) -> 50120.726 | N101: 25H1 내부거래
C102: 강의매출 | D102: =TITAN!L20 -> 11192.304 | E102: =TITAN!M20 -> 17501.106 | F102: =TITAN!O20 -> 35078.303 | G102: =TITAN!P20 -> 37812.47 | H102: =TITAN!Q20 -> 40682.35 | I102: =TITAN!R20 -> 43771.909 | J102: =TITAN!S20 -> 46881.275 | K102: =TITAN!T20 -> 50120.726
C103: 상품매출 | D103: =TITAN!L34 -> 11.154544 | E103: =TITAN!M34 -> 0 | F103: =TITAN!O34 -> 0 | G103: =TITAN!P34 -> 0 | H103: =TITAN!Q34 -> 0 | I103: =TITAN!R34 -> 0 | J103: =TITAN!S34 -> 0 | K103: =TITAN!T34 -> 0 | N103: =조정!$J$19 -> 22275000
C104: 임대료매출 | D104: =TITAN!L35 -> 0 | E104: =TITAN!M35 -> 3.772728 | F104: =TITAN!O35 -> 3.772728 | G104: =TITAN!P35 -> 0 | H104: =TITAN!Q35 -> 0 | I104: =TITAN!R35 -> 0 | J104: =TITAN!S35 -> 0 | K104: =TITAN!T35 -> 0 | L104: >>내부거래 | N104: =조정!$J$42 -> 20250000
C105: Class | D105: =SUM(D106:D107) -> 19.9 | E105: =SUM(E106:E107) -> 10266.381 | F105: =SUM(F106:F107) -> 26835.388 | G105: =SUM(G106:G107) -> 32543.72 | H105: =SUM(H106:H107) -> 34715.24 | I105: =SUM(I106:I107) -> 37063.293 | J105: =SUM(J106:J107) -> 39417.29 | K105: =SUM(K106:K107) -> 41870.527
C106: 강의매출 | D106: =CLASS!L21 -> 0 | E106: =CLASS!M21 -> 10266.381 | F106: =CLASS!O21 -> 26835.388 | G106: =CLASS!P21 -> 32543.72 | H106: =CLASS!Q21 -> 34715.24 | I106: =CLASS!R21 -> 37063.293 | J106: =CLASS!S21 -> 39417.29 | K106: =CLASS!T21 -> 41870.527
C107: 기타매출 | D107: =CLASS!L36 -> 19.9 | E107: =CLASS!M36 -> 0 | F107: =CLASS!O36 -> 0 | G107: =CLASS!P36 -> 0 | H107: =CLASS!Q36 -> 0 | I107: =CLASS!R36 -> 0 | J107: =CLASS!S36 -> 0 | K107: =CLASS!T36 -> 0
C108: Nova | D108: =SUM(D109:D110) -> 0 | E108: =SUM(E109:E110) -> 261.84518 | F108: =SUM(F109:F110) -> 2613.2683 | G108: =SUM(G109:G110) -> 7196.2766 | H108: =SUM(H109:H110) -> 9426.1391 | I108: =SUM(I109:I110) -> 11924.423 | J108: =SUM(J109:J110) -> 14653.889 | K108: =SUM(K109:K110) -> 17654.417
C109: 솔루션매출 | D109: =NOVA!L19 -> 0 | E109: =NOVA!M19 -> 221.34518 | F109: =NOVA!O19 -> 2572.7683 | G109: =NOVA!P19 -> 7196.2766 | H109: =NOVA!Q19 -> 9426.1391 | I109: =NOVA!R19 -> 11924.423 | J109: =NOVA!S19 -> 14653.889 | K109: =NOVA!T19 -> 17654.417
C110: 기타매출 | D110: =NOVA!L34 -> 0 | E110: =NOVA!M34 -> 40.5 | F110: =NOVA!O34 -> 40.5 | G110: =NOVA!P34 -> 0 | H110: =NOVA!Q34 -> 0 | I110: =NOVA!R34 -> 0 | J110: =NOVA!S34 -> 0 | K110: =NOVA!T34 -> 0
C111: 내부거래 | E111: =(조정!$J$19+조정!$J$42)/10^6 -> 42.525 | F111: =E111 -> 42.525 | L111: >>내부거래
C112: TTA | D112: =SUM(D113) -> 0 | E112: =SUM(E113) -> 5406.0864 | F112: =SUM(F113) -> 12840.012 | G112: =SUM(G113) -> 15717.11 | H112: =SUM(H113) -> 18711.43 | I112: =SUM(I113) -> 21872.723 | J112: =SUM(J113) -> 25109.255 | K112: =SUM(K113) -> 28476.636
C113: 강의매출 | D113: =TTA!L20 -> 0 | E113: =TTA!M20 -> 5406.0864 | F113: =TTA!O20 -> 12840.012 | G113: =TTA!P20 -> 15717.11 | H113: =TTA!Q20 -> 18711.43 | I113: =TTA!R20 -> 21872.723 | J113: =TTA!S20 -> 25109.255 | K113: =TTA!T20 -> 28476.636
C115: 변동비 | D115: ='Pro forma PL'!L9 -> 6290.7849 | E115: ='Pro forma PL'!M9 -> 17029.245 | F115: ='Pro forma PL'!O9 -> 43881.221 | G115: ='Pro forma PL'!P9 -> 49380.844 | H115: ='Pro forma PL'!Q9 -> 50965.933 | I115: ='Pro forma PL'!R9 -> 55710.68 | J115: ='Pro forma PL'!S9 -> 60526.946 | K115: ='Pro forma PL'!T9 -> 65556.135
...

Sheet DCF
A1: DCF
A3: 1. Consolidated
O4: =O6/L6 -> 6.8895993
L5: 2024A | M5: 2025 1H | N5: 2025 2H | O5: 2025E | P5: 2026F | Q5: 2027F | R5: 2028F | S5: 2029F | T5: 2030F
B6: Revenue | L6: ='Pro forma PL'!L6 -> 11223.359 | M6: ='Pro forma PL'!M6 -> 33392.893 | N6: ='Pro forma PL'!N6 -> 43931.553 | O6: ='Pro forma PL'!O6 -> 77324.447 | P6: ='Pro forma PL'!P6 -> 93269.577 | Q6: ='Pro forma PL'!Q6 -> 103535.16 | R6: ='Pro forma PL'!R6 -> 114632.35 | S6: ='Pro forma PL'!S6 -> 126061.71 | T6: ='Pro forma PL'!T6 -> 138122.31
B7: Operating Expense | L7: ='Pro forma PL'!L7 -> 7882.2028 | M7: ='Pro forma PL'!M7 -> 19480.857 | N7: ='Pro forma PL'!N7 -> 30151.488 | O7: ='Pro forma PL'!O7 -> 49632.346 | P7: ='Pro forma PL'!P7 -> 57986.595 | Q7: ='Pro forma PL'!Q7 -> 60124.892 | R7: ='Pro forma PL'!R7 -> 65467.261 | S7: ='Pro forma PL'!S7 -> 70872.351 | T7: ='Pro forma PL'!T7 -> 76518.723
B8: EBIT | L8: =L6-L7 -> 3341.1562 | M8: =M6-M7 -> 13912.036 | N8: =N6-N7 -> 13780.065 | O8: =O6-O7 -> 27692.101 | P8: =P6-P7 -> 35282.982 | Q8: =Q6-Q7 -> 43410.268 | R8: =R6-R7 -> 49165.087 | S8: =S6-S7 -> 55189.358 | T8: =T6-T7 -> 61603.584
B9: margin % | L9: =L8/L$6 -> 0.29769663 | M9: =M8/M$6 -> 0.41661666 | N9: =N8/N$6 -> 0.31367125 | O9: =O8/O$6 -> 0.35812867 | P9: =P8/P$6 -> 0.37829036 | Q9: =Q8/Q$6 -> 0.41928044 | R9: =R8/R$6 -> 0.42889366 | S9: =S8/S$6 -> 0.43779636 | T9: =T8/T$6 -> 0.44600749
B10: Income Tax | N10: =SUM(N48,N93,N128,N161) -> 3485.8775 | P10: =SUM(P48,P93,P128,P161) -> 9311.7412 | Q10: =SUM(Q48,Q93,Q128,Q161) -> 11456.751 | R10: =SUM(R48,R93,R128,R161) -> 12975.312 | S10: =SUM(S48,S93,S128,S161) -> 14564.865 | T10: =SUM(T48,T93,T128,T161) -> 16259.129
B11: EBIT after Tax | N11: =N8-N10 -> 10294.188 | P11: =P8-P10 -> 25971.241 | Q11: =Q8-Q10 -> 31953.516 | R11: =R8-R10 -> 36189.775 | S11: =S8-S10 -> 40624.493 | T11: =T8-T10 -> 45344.454
B12: (+) D&A | N12: ='Pro forma PL'!N21 -> 81.972752 | P12: ='Pro forma PL'!P21 -> 143.8773 | Q12: ='Pro forma PL'!Q21 -> 129.85259 | R12: ='Pro forma PL'!R21 -> 117.28632 | S12: ='Pro forma PL'!S21 -> 106.45002 | T12: ='Pro forma PL'!T21 -> 95.874855
B13: (-) CAPEX | N13: =SUM(N51,N96,N131,N164) -> -74.922948 | P13: =SUM(P51,P96,P131,P164) -> -122.01725 | Q13: =SUM(Q51,Q96,Q131,Q164) -> -112.45919 | R13: =SUM(R51,R96,R131,R164) -> -104.52159 | S13: =SUM(S51,S96,S131,S164) -> -98.582786 | T13: =SUM(T51,T96,T131,T164) -> -86.635555
B14: (+/-) NWC | N14: =SUM(N52,N97,N132,N165) -> 1487.6571 | P14: =SUM(P52,P97,P132,P165) -> -1004.2223 | Q14: =SUM(Q52,Q97,Q132,Q165) -> -620.98453 | R14: =SUM(R52,R97,R132,R165) -> -760.89675 | S14: =SUM(S52,S97,S132,S165) -> -782.99139 | T14: =SUM(T52,T97,T132,T165) -> -825.58487
B15: FCFF | N15: =SUM(N11:N14) -> 11788.895 | P15: =SUM(P11:P14) -> 24988.878 | Q15: =SUM(Q11:Q14) -> 31349.925 | R15: =SUM(R11:R14) -> 35441.643 | S15: =SUM(S11:S14) -> 39849.369 | T15: =SUM(T11:T14) -> 44528.109
B16: 할인기간 | N16: =N54 -> 0.25205479 | P16: =P54 -> 1 | Q16: =Q54 -> 2 | R16: =R54 -> 3 | S16: =S54 -> 4 | T16: =T54 -> 5
B17: 할인계수 | N17: =1/(1+$J$24)^N16 -> 0.9653856 | P17: =1/(1+$J$24)^P16 -> 0.86956522 | Q17: =1/(1+$J$24)^Q16 -> 0.75614367 | R17: =1/(1+$J$24)^R16 -> 0.65751623 | S17: =1/(1+$J$24)^S16 -> 0.57175325 | T17: =1/(1+$J$24)^T16 -> 0.49717674
B18: PV of FCFF | N18: =N17*N15 -> 11380.829 | P18: =P17*P15 -> 21729.46 | Q18: =Q17*Q15 -> 23705.047 | R18: =R17*R15 -> 23303.456 | S18: =S17*S15 -> 22784.006 | T18: =T17*T15 -> 22138.34
B19: 대상기간 누적 현재가치 | N19: =SUM(N18:T18) -> 125041.14
B20: Terminal Value의 현재가치 | N20: =SUM(N58,N103,N138,N171) -> 162240.69
B21: 영업가치 | N21: =SUM(N19:N20) -> 287281.83
B23: 영구성장률 | J23: 0.01
B24: WACC | J24: 0.15
B27: 영업가치 | J27: =N21 -> 287281.83
B28: 비영업용자산 | J28: =SUM(J29:J31) -> 7516.3069
C29: 현금및현금성자산등 | J29: =SUM(J67,J68,J69,J112,J147,J180) -> 6556.3069
C30: 투자부동산 | J30: =J113 -> 650
C31: 투자주식 | J31: =J114+J74 -> 310
B32: 기업가치 | J32: =J28+J27 -> 294798.14
B33: 비지배지분 | J33: =SUM(J34:J36) -> 9435.2177
C34: 클래스어라운드 | J34: =J118*(1-I81) -> 0
C35: 시스템노바 | J35: =J151*(1-I82) -> 9435.2177
C36: 티티에이컴퍼니 | J36: =J184*(1-I83) -> 0
B37: IBD | J37: =SUM(J77,J117,J150,J183) -> 692.297
B38: 지분가치 | J38: =J32-J33-J37 -> 284670.62 | K38: =ROUND(J38,)=ROUND(J78,) -> TRUE
A41: 2. TITAN
L43: 2024A | M43: 2025 1H | N43: 2025 2H | O43: 2025E | P43: 2026F | Q43: 2027F | R43: 2028F | S43: 2029F | T43: 2030F | U43: Terminal
B44: Revenue | L44: =TITAN!L6 -> 11203.459 | M44: =TITAN!M6 -> 17504.878 | N44: =TITAN!N6 -> 17577.197 | O44: =TITAN!O6 -> 35082.076 | P44: =TITAN!P6 -> 37812.47 | Q44: =TITAN!Q6 -> 40682.35 | R44: =TITAN!R6 -> 43771.909 | S44: =TITAN!S6 -> 46881.275 | T44: =TITAN!T6 -> 50120.726 | U44: =T44*(1+$J$61) -> 50621.934
B45: Operating Expense | L45: =TITAN!L7 -> 7805.3692 | M45: =TITAN!M7 -> 10871.796 | N45: =TITAN!N7 -> 12636.466 | O45: =TITAN!O7 -> 23508.262 | P45: =TITAN!P7 -> 25900.887 | Q45: =TITAN!Q7 -> 26116.725 | R45: =TITAN!R7 -> 27996.971 | S45: =TITAN!S7 -> 29882.534 | T45: =TITAN!T7 -> 31848.718 | U45: =T45*(1+$J$61) -> 32167.205
B46: EBIT | L46: =L44-L45 -> 3398.0897 | M46: =M44-M45 -> 6633.0824 | N46: =N44-N45 -> 4940.7319 | O46: =O44-O45 -> 11573.814 | P46: =P44-P45 -> 11911.583 | Q46: =Q44-Q45 -> 14565.625 | R46: =R44-R45 -> 15774.938 | S46: =S44-S45 -> 16998.741 | ... U46: =U44-U45 -> 18454.728
B47: margin % | L47: =L46/L44 -> 0.3033072 | M47: =M46/M44 -> 0.37892765 | N47: =N46/N44 -> 0.28108758 | O47: =O46/O44 -> 0.32990677 | P47: =P46/P44 -> 0.31501732 | Q47: =Q46/Q44 -> 0.35803303 | R47: =R46/R44 -> 0.36038954 | S47: =S46/S44 -> 0.36259127 | ... U47: =U46/U44 -> 0.36455992
B48: Income Tax | N48: =IF(N46<0,0,IF(N46<2,N46*9%*1.1,IF(N46<200,N46*19%*1.1,IF(N46<3000,N46*21%*1.1,N46*24%*1.1)))) -> 1304.3532 | P48: =IF(P46<0,0,IF(P46<2,P46*9%*1.1,IF(P46<200,P46*19%*1.1,IF(P46<3000,P46*21%*1.1,P46*24%*1.1)))) -> 3144.6579 | Q48: =IF(Q46<0,0,IF(Q46<2,Q46*9%*1.1,IF(Q46<200,Q46*19%*1.1,IF(Q46<3000,Q46*21%*1.1,Q46*24%*1.1)))) -> 3845.325 | R48: =IF(R46<0,0,IF(R46<2,R46*9%*1.1,IF(R46<200,R46*19%*1.1,IF(R46<3000,R46*21%*1.1,R46*24%*1.1)))) -> 4164.5837 | S48: =IF(S46<0,0,IF(S46<2,S46*9%*1.1,IF(S46<200,S46*19%*1.1,IF(S46<3000,S46*21%*1.1,S46*24%*1.1)))) -> 4487.6676 | T48: =IF(T46<0,0,IF(T46<2,T46*9%*1.1,IF(T46<200,T46*19%*1.1,IF(T46<3000,T46*21%*1.1,T46*24%*1.1)))) -> 4823.8101 | U48: =IF(U46<0,0,IF(U46<2,U46*9%*1.1,IF(U46<200,U46*19%*1.1,IF(U46<3000,U46*21%*1.1,U46*24%*1.1)))) -> 4872.0482
B49: EBIT after Tax | N49: =N46-N48 -> 3636.3787 | P49: =P46-P48 -> 8766.9251 | Q49: =Q46-Q48 -> 10720.3 | R49: =R46-R48 -> 11610.354 | S49: =S46-S48 -> 12511.073 | T49: =T46-T48 -> 13448.198 | U49: =U46-U48 -> 13582.68
B50: (+) D&A | N50: =TITAN!N10 -> 50.626289 | P50: =TITAN!P10 -> 84.973118 | Q50: =TITAN!Q10 -> 77.169324 | R50: =TITAN!R10 -> 70.15918 | S50: =TITAN!S10 -> 63.861971 | T50: =TITAN!T10 -> 58.205191
B51: (-) CAPEX | N51: =-TITAN!N103 -> -41.794002 | P51: =-TITAN!P103 -> -62.613702 | Q51: =-TITAN!Q103 -> -56.245857 | R51: =-TITAN!R103 -> -50.525625 | S51: =-TITAN!S103 -> -45.387144 | T51: =-TITAN!T103 -> -40.771249
B52: (+/-) NWC | N52: =-TITAN!N146 -> -127.23848 | P52: =-TITAN!P146 -> -241.88511 | Q52: =-TITAN!Q146 -> -140.6542 | R52: =-TITAN!R146 -> -271.03893 | S52: =-TITAN!S146 -> -272.64897 | T52: =-TITAN!T146 -> -284.13505 | U52: =-TITAN!U146 -> -45.036442
B53: FCFF | N53: =N52+N51+N50+N49 -> 3517.9725 | P53: =P52+P51+P50+P49 -> 8547.3995 | Q53: =Q52+Q51+Q50+Q49 -> 10600.569 | R53: =R52+R51+R50+R49 -> 11358.949 | S53: =S52+S51+S50+S49 -> 12256.899 | T53: =T52+T51+T50+T49 -> 13181.497 | U53: =U52+U51+U50+U49 -> 13537.644
B54: 할인기간 | N54: ='Key Assumption'!L9/2 -> 0.25205479 | P54: 1 | Q54: =P54+1 -> 2 | R54: =Q54+1 -> 3 | S54: =R54+1 -> 4 | T54: =S54+1 -> 5 | U54: =T54 -> 5
B55: 할인계수 | N55: =1/(1+$J$62)^N54 -> 0.9653856 | P55: =1/(1+$J$62)^P54 -> 0.86956522 | Q55: =1/(1+$J$62)^Q54 -> 0.75614367 | R55: =1/(1+$J$62)^R54 -> 0.65751623 | S55: =1/(1+$J$62)^S54 -> 0.57175325 | T55: =1/(1+$J$62)^T54 -> 0.49717674 | U55: =1/(1+$J$62)^U54 -> 0.49717674
B56: PV of FCFF | N56: =N55*N53 -> 3396.2 | P56: =P55*P53 -> 7432.5213 | Q56: =Q55*Q53 -> 8015.5533 | R56: =R55*R53 -> 7468.6934 | S56: =S55*S53 -> 7007.9219 | T56: =T55*T53 -> 6553.5336 | U56: =U55*U53/(J62-J61) -> 48075.724
B57: 대상기간 누적 현재가치 | N57: =SUM(N56:T56) -> 39874.424
B58: Terminal Value의 현재가치 | N58: =U56 -> 48075.724
B59: 영업가치 | N59: =N58+N57 -> 87950.148
B61: 영구성장률 | J61: =J23 -> 0.01
B62: WACC | J62: =J24 -> 0.15
B65: 영업가치 | J65: =N59 -> 87950.148
B66: 비영업용자산 | J66: =J69+J70+J67+J68 -> 197362.47
C67: 현금및현금성자산 | J67: =연결정산표!U8/10^6+연결정산표!U9/10^6 -> 3359.0177
C68: 단기매매증권 | J68: =연결정산표!U10/10^6 -> 216.65419
C69: 장단기대여금 | J69: =연결정산표!U17/10^6 -> 1250 | K69: 우모건 대여금
C70: 투자주식 | J70: =J71+J72+J73+J74 -> 192536.8
D71: 클래스어라운드 | J71: =J81 -> 80913.234
D72: 시스템노바 | J72: =J82 -> 53466.234
D73: 티티에이컴퍼니 | J73: =J83 -> 58007.333
D74: 우모건(클레스어라운드 50%, 타이탄 50%) | J74: =연결정산표!U27/10^6 -> 150 | K74: 타이탄 50%, 클래스 50%
B75: 기업가치 | J75: =J65+J66 -> 285312.62
B76: IBD | J76: =J77 -> 642
C77: 차입금 | J77: =연결정산표!U66/10^6+연결정산표!U62/10^6 -> 642
B78: 지분가치 | J78: =J75-J76 -> 284670.62
H80: BV | I80: 실질지분율 | J80: FV
B81: 클래스어라운드 | H81: =연결정산표!U24/10^6 -> 39 | I81: 1 | J81: =J118*I81 -> 80913.234 | K81: 박세영 40%, 타이탄 39%, 오윤록 11%
B82: 시스템노바 | H82: =연결정산표!U25/10^6 -> 5.1 | I82: 0.85 | J82: =J151*I82 -> 53466.234 | K82: 타이탄 51%, 박세영 25%, 오윤록 9%, 박창욱(임직원) 15% | P82: >>> 박창욱 보유 지분 매각 대상 여부 확인 필요
B83: 티티에이 | H83: =연결정산표!U26/10^6 -> 30.6 | I83: 1 | J83: =J184*I83 -> 58007.333 | K83: 타이탄 51%, 어베러라이프 49%
A86: 3. CLASS
L88: 2024A | M88: 2025 1H | N88: 2025 2H | O88: 2025E | P88: 2026F | Q88: 2027F | R88: 2028F | S88: 2029F | T88: 2030F | U88: Terminal
B89: Revenue | L89: =CLASS!L6 -> 19.9 | M89: =CLASS!M6 -> 10266.381 | N89: =CLASS!N6 -> 16569.007 | O89: =CLASS!O6 -> 26835.388 | P89: =CLASS!P6 -> 32543.72 | Q89: =CLASS!Q6 -> 34715.24 | R89: =CLASS!R6 -> 37063.293 | S89: =CLASS!S6 -> 39417.29 | T89: =CLASS!T6 -> 41870.527 | U89: =T89*(1+$J$106) -> 42289.232
B90: Operating Expense | L90: =CLASS!L7 -> 76.833572 | M90: =CLASS!M7 -> 6468.495 | N90: =CLASS!N7 -> 12303.422 | O90: =CLASS!O7 -> 18771.917 | P90: =CLASS!P7 -> 20780.481 | Q90: =CLASS!Q7 -> 21363.142 | R90: =CLASS!R7 -> 22769.727 | S90: =CLASS!S7 -> 24174.58 | T90: =CLASS!T7 -> 25632.359 | U90: =T90*(1+$J$106) -> 25888.683
B91: EBIT | L91: =L89-L90 -> -56.933572 | M91: =M89-M90 -> 3797.886 | N91: =N89-N90 -> 4265.5856 | O91: =O89-O90 -> 8063.4716 | P91: =P89-P90 -> 11763.24 | Q91: =Q89-Q90 -> 13352.098 | R91: =R89-R90 -> 14293.566 | S91: =S89-S90 -> 15242.711 | ... U91: =U89-U90 -> 16400.55
B92: margin % | L92: =L91/L89 -> -2.8609835 | M92: =M91/M89 -> 0.36993425 | N92: =N91/N89 -> 0.25744365 | O92: =O91/O89 -> 0.30047904 | P92: =P91/P89 -> 0.36145959 | Q92: =Q91/Q89 -> 0.38461777 | R92: =R91/R89 -> 0.38565289 | S92: =S91/S89 -> 0.38670113 | ... U92: =U91/U89 -> 0.38781857
B93: Income Tax | N93: =IF(N91<0,0,IF(N91<2,N91*9%*1.1,IF(N91<200,N91*19%*1.1,IF(N91<3000,N91*21%*1.1,N91*24%*1.1)))) -> 1126.1146 | P93: =IF(P91<0,0,IF(P91<2,P91*9%*1.1,IF(P91<200,P91*19%*1.1,IF(P91<3000,P91*21%*1.1,P91*24%*1.1)))) -> 3105.4953 | Q93: =IF(Q91<0,0,IF(Q91<2,Q91*9%*1.1,IF(Q91<200,Q91*19%*1.1,IF(Q91<3000,Q91*21%*1.1,Q91*24%*1.1)))) -> 3524.9539 | R93: =IF(R91<0,0,IF(R91<2,R91*9%*1.1,IF(R91<200,R91*19%*1.1,IF(R91<3000,R91*21%*1.1,R91*24%*1.1)))) -> 3773.5015 | S93: =IF(S91<0,0,IF(S91<2,S91*9%*1.1,IF(S91<200,S91*19%*1.1,IF(S91<3000,S91*21%*1.1,S91*24%*1.1)))) -> 4024.0756 | T93: =IF(T91<0,0,IF(T91<2,T91*9%*1.1,IF(T91<200,T91*19%*1.1,IF(T91<3000,T91*21%*1.1,T91*24%*1.1)))) -> 4286.8763 | U93: =IF(U91<0,0,IF(U91<2,U91*9%*1.1,IF(U91<200,U91*19%*1.1,IF(U91<3000,U91*21%*1.1,U91*24%*1.1)))) -> 4329.7451
B94: EBIT after Tax | N94: =N91-N93 -> 3139.471 | P94: =P91-P93 -> 8657.7446 | Q94: =Q91-Q93 -> 9827.1442 | R94: =R91-R93 -> 10520.065 | S94: =S91-S93 -> 11218.635 | T94: =T91-T93 -> 11951.292 | U94: =U91-U93 -> 12070.805
B95: (+) D&A | N95: =CLASS!N10 -> 22.238234 | P95: =CLASS!P10 -> 43.978483 | Q95: =CLASS!Q10 -> 42.895476 | R95: =CLASS!R10 -> 42.600536 | S95: =CLASS!S10 -> 43.149102 | T95: =CLASS!T10 -> 37.29325
B96: (-) CAPEX | N96: =-CLASS!N103 -> -20.246737 | P96: =-CLASS!P103 -> -36.932111 | Q96: =-CLASS!Q103 -> -36.257576 | R96: =-CLASS!R103 -> -36.267936 | S96: =-CLASS!S103 -> -37.016798 | T96: =-CLASS!T103 -> -31.918019
B97: (+/-) NWC | N97: =-CLASS!N153 -> -260.33142 | P97: =-CLASS!P153 -> -354.5899 | Q97: =-CLASS!Q153 -> -142.52162 | R97: =-CLASS!R153 -> -125.42567 | S97: =-CLASS!S153 -> -125.96142 | T97: =-CLASS!T153 -> -131.50375 | U97: =-CLASS!U153 -> -22.158284
B98: FCFF | N98: =N97+N96+N95+N94 -> 2881.1311 | P98: =P97+P96+P95+P94 -> 8310.201 | Q98: =Q97+Q96+Q95+Q94 -> 9691.2605 | R98: =R97+R96+R95+R94 -> 10400.972 | S98: =S97+S96+S95+S94 -> 11098.806 | T98: =T97+T96+T95+T94 -> 11825.163 | U98: =U97+U96+U95+U94 -> 12048.646
B99: 할인기간 | N99: ='Key Assumption'!$L$9/2 -> 0.25205479 | P99: 1 | Q99: =P99+1 -> 2 | R99: =Q99+1 -> 3 | S99: =R99+1 -> 4 | T99: =S99+1 -> 5 | U99: =T99 -> 5
B100: 할인계수 | N100: =1/(1+$J$107)^N99 -> 0.9653856 | P100: =1/(1+$J$107)^P99 -> 0.86956522 | Q100: =1/(1+$J$107)^Q99 -> 0.75614367 | R100: =1/(1+$J$107)^R99 -> 0.65751623 | S100: =1/(1+$J$107)^S99 -> 0.57175325 | T100: =1/(1+$J$107)^T99 -> 0.49717674 | U100: =1/(1+$J$107)^U99 -> 0.49717674
B101: PV of FCFF | N101: =N100*N98 -> 2781.4025 | P101: =P100*P98 -> 7226.2618 | Q101: =Q100*Q98 -> 7327.9852 | R101: =R100*R98 -> 6838.8077 | S101: =S100*S98 -> 6345.7783 | T101: =T100*T98 -> 5879.196 | U101: =U100*U98/(J107-J106) -> 42787.904
B102: 대상기간 누적 현재가치 | N102: =SUM(N101:T101) -> 36399.431
B103: Terminal Value의 현재가치 | N103: =U101 -> 42787.904
B104: 영업가치 | N104: =N103+N102 -> 79187.336
B106: 영구성장률 | J106: =J23 -> 0.01
B107: WACC | J107: =J24 -> 0.15
B110: 영업가치 | J110: =N104 -> 79187.336
B111: 비영업용자산 | J111: =J113+J114+J112 -> 1725.8985
C112: 현금및현금성자산 | J112: =연결정산표!T8/10^6 -> 915.8985
C113: 투자부동산 | J113: =연결정산표!T44/10^6 -> 650 | K113: 우모건 대여금
C114: 투자주식 | J114: =연결정산표!T27/10^6+연결정산표!T29/10^6+연결정산표!T30/10^6 -> 160
B115: 기업가치 | J115: =J110+J111 -> 80913.234
B116: IBD | J116: =J117 -> 0
C117: 차입금 | J117: 0
...

Sheet Pro forma BS
A1: Pro forma BS
A3: 1. Consolidated
L5: 2024A | M5: 2025 1H | N5: 2025 2H | O5: 2025E | P5: 2026F | Q5: 2027F | R5: 2028F | S5: 2029F | T5: 2030F
B6: 유동자산 | L6: =연결정산표!G5/10^6 -> 3393.8404 | M6: =연결정산표_우모건제외!M7/10^6 -> 16785.728 | N6: =SUM(N7:N11) -> 31203.336 | O6: =SUM(O7:O11) -> 31203.336 | P6: =SUM(P7:P11) -> 60135.704 | Q6: =SUM(Q7:Q11) -> 94831.636 | R6: =SUM(R7:R11) -> 133268.42 | S6: =SUM(S7:S11) -> 176251.04 | T6: =SUM(T7:T11) -> 224112.67
C7: 현금및현금성자산 | L7: =SUM(연결정산표!G7:G9)/10^6 -> 1161.7762 | M7: =SUM(연결정산표_우모건제외!M9:M11)/10^6 -> 5089.6527 | N7: ='Pro forma CF'!N25 -> 20525.78 | O7: ='Pro forma CF'!O25 -> 20525.78 | P7: ='Pro forma CF'!P25 -> 48056.268 | Q7: ='Pro forma CF'!Q25 -> 81999.842 | R7: ='Pro forma CF'!R25 -> 119449.09 | S7: ='Pro forma CF'!S25 -> 161417.02 | T7: ='Pro forma CF'!T25 -> 208210.25
C8: 단기대여금 | L8: =연결정산표!G17/10^6 -> 0 | M8: =연결정산표_우모건제외!M19/10^6 -> 1200 | N8: =M8 -> 1200 | O8: =N8 -> 1200 | P8: =O8 -> 1200 | Q8: =P8 -> 1200 | R8: =Q8 -> 1200 | S8: =R8 -> 1200 | T8: =S8 -> 1200
C9: 운전자산 | L9: =SUM(연결정산표!G11,연결정산표!G13)/10^6 -> 1641.1379 | M9: =연결정산표_우모건제외!M13/10^6+연결정산표_우모건제외!M15/10^6-연결정산표_우모건제외!G15/10^6 -> 8174.6202 | N9: =SUM(TITAN!N148,CLASS!N155,NOVA!N109,TTA!N117) -> 7156.1012 | O9: =SUM(TITAN!O148,CLASS!O155,NOVA!O109,TTA!O117) -> 7156.1012 | P9: =SUM(TITAN!P148,CLASS!P155,NOVA!P109,TTA!P117) -> 8557.9806 | Q9: =SUM(TITAN!Q148,CLASS!Q155,NOVA!Q109,TTA!Q117) -> 9310.3382 | R9: =SUM(TITAN!R148,CLASS!R155,NOVA!R109,TTA!R117) -> 10297.883 | S9: =SUM(TITAN!S148,CLASS!S155,NOVA!S109,TTA!S117) -> 11312.562 | T9: =SUM(TITAN!T148,CLASS!T155,NOVA!T109,TTA!T117) -> 12380.965
C10: 주임종단기채권 | L10: =연결정산표!J18/10^6 -> 369.18887 | M10: =연결정산표_우모건제외!M20/10^6 -> 1991.9156 | N10: =M10 -> 1991.9156 | O10: =N10 -> 1991.9156 | P10: =O10 -> 1991.9156 | Q10: =P10 -> 1991.9156 | R10: =Q10 -> 1991.9156 | S10: =R10 -> 1991.9156 | T10: =S10 -> 1991.9156
C11: 기타유동자산 | L11: =L6-L7-L8-L9-L10 -> 221.73735 | M11: =M6-M7-M8-M9-M10 -> 329.53993 | N11: =M11 -> 329.53993 | O11: =N11 -> 329.53993 | P11: =O11 -> 329.53993 | Q11: =P11 -> 329.53993 | R11: =Q11 -> 329.53993 | S11: =R11 -> 329.53993 | T11: =S11 -> 329.53993
B12: 비유동자산 | L12: =연결정산표!J21/10^6 -> 1137.2261 | M12: =연결정산표_우모건제외!M23/10^6 -> 1856.4592 | N12: =SUM(N13:N15) -> 1849.4094 | O12: =SUM(O13:O15) -> 1849.4094 | P12: =SUM(P13:P15) -> 1827.5494 | Q12: =SUM(Q13:Q15) -> 1810.156 | R12: =SUM(R13:R15) -> 1797.3912 | S12: =SUM(S13:S15) -> 1789.524 | T12: =SUM(T13:T15) -> 1780.2847
C13: 투자주식 | L13: 0 | M13: =연결정산표_우모건제외!M24/10^6 -> 310 | N13: =M13 -> 310 | O13: =N13 -> 310 | P13: =O13 -> 310 | Q13: =P13 -> 310 | R13: =Q13 -> 310 | S13: =R13 -> 310 | T13: =S13 -> 310
C14: 유무형자산 | L14: =연결정산표!J31/10^6 -> 987.43582 | M14: =연결정산표_우모건제외!M33/10^6 -> 1080.9109 | N14: =M14-'Pro forma PL'!N21-DCF!N13 -> 1073.8611 | O14: =N14 -> 1073.8611 | P14: =O14-'Pro forma PL'!P21-DCF!P13 -> 1052.001 | Q14: =P14-'Pro forma PL'!Q21-DCF!Q13 -> 1034.6076 | R14: =Q14-'Pro forma PL'!R21-DCF!R13 -> 1021.8429 | S14: =R14-'Pro forma PL'!S21-DCF!S13 -> 1013.9757 | T14: =S14-'Pro forma PL'!T21-DCF!T13 -> 1004.7364
C15: 기타비유동자산 | L15: =L12-L13-L14 -> 149.79032 | M15: =M12-M13-M14 -> 465.54832 | N15: =M15 -> 465.54832 | O15: =N15 -> 465.54832 | P15: =O15 -> 465.54832 | Q15: =P15 -> 465.54832 | R15: =Q15 -> 465.54832 | S15: =R15 -> 465.54832 | T15: =S15 -> 465.54832
B16: 자산총계 | L16: =L12+L6 -> 4531.0665 | M16: =M12+M6 -> 18642.188 | N16: =N12+N6 -> 33052.746 | O16: =O12+O6 -> 33052.746 | P16: =P12+P6 -> 61963.253 | Q16: =Q12+Q6 -> 96641.792 | R16: =R12+R6 -> 135065.82 | S16: =S12+S6 -> 178040.56 | T16: =T12+T6 -> 225892.96
B17: 유동부채 | L17: =연결정산표!J52/10^6 -> 1203.7292 | M17: =연결정산표_우모건제외!M54/10^6 -> 1631.8687 | N17: =SUM(N18:N21) -> 9281.87 | O17: =SUM(O18:O21) -> 9281.87 | P17: =SUM(P18:P21) -> 11810.405 | Q17: =SUM(Q18:Q21) -> 14086.788 | R17: =SUM(R18:R21) -> 15831.997 | S17: =SUM(S18:S21) -> 17653.238 | T17: =SUM(T18:T21) -> 19590.32
C18: 단기차입금 | L18: =연결정산표!J62/10^6 -> 100 | M18: =연결정산표_우모건제외!M64/10^6 -> 100 | N18: =M18 -> 100 | O18: =N18 -> 100 | P18: =O18 -> 100 | Q18: =P18 -> 100 | R18: =Q18 -> 100 | S18: =R18 -> 100 | T18: =S18 -> 100
C19: 운전부채 | L19: =연결정산표!J53/10^6 -> 437.91273 | M19: =연결정산표_우모건제외!M55/10^6 -> 1040.6891 | N19: =SUM(TITAN!N155,CLASS!N162,NOVA!N113,TTA!N124) -> 1509.8272 | O19: =SUM(TITAN!O155,CLASS!O162,NOVA!O113,TTA!O124) -> 1509.8272 | P19: =SUM(TITAN!P155,CLASS!P162,NOVA!P113,TTA!P124) -> 1907.4843 | Q19: =SUM(TITAN!Q155,CLASS!Q162,NOVA!Q113,TTA!Q124) -> 2038.8573 | R19: =SUM(TITAN!R155,CLASS!R162,NOVA!R113,TTA!R124) -> 2265.5051 | S19: =SUM(TITAN!S155,CLASS!S162,NOVA!S113,TTA!S124) -> 2497.1929 | T19: =SUM(TITAN!T155,CLASS!T162,NOVA!T113,TTA!T124) -> 2740.0109
C20: 미지급법인세 | L20: =연결정산표!G60/10^6 -> 596.78793 | M20: =연결정산표_우모건제외!M62/10^6 -> 336.46338 | N20: =M20+'Pro forma PL'!N18+'Pro forma CF'!N15 -> 7517.3267 | O20: =N20 -> 7517.3267 | P20: =O20+'Pro forma PL'!P18+'Pro forma CF'!P15 -> 9648.2045 | Q20: =P20+'Pro forma PL'!Q18+'Pro forma CF'!Q15 -> 11793.215 | R20: =Q20+'Pro forma PL'!R18+'Pro forma CF'!R15 -> 13311.775 | S20: =R20+'Pro forma PL'!S18+'Pro forma CF'!S15 -> 14901.329 | T20: =S20+'Pro forma PL'!T18+'Pro forma CF'!T15 -> 16595.593
C21: 기타유동부채 | L21: =L17-L18-L19-L20 -> 69.028535 | M21: =M17-M18-M19-M20 -> 154.71614 | N21: =M21 -> 154.71614 | O21: =N21 -> 154.71614 | P21: =O21 -> 154.71614 | Q21: =P21 -> 154.71614 | R21: =Q21 -> 154.71614 | S21: =R21 -> 154.71614 | T21: =S21 -> 154.71614
B22: 비유동부채 | L22: =연결정산표!J63/10^6 -> 575.19028 | M22: =연결정산표_우모건제외!M65/10^6 -> 611.75831 | N22: =N23+N24 -> 773.11313 | O22: =O23+O24 -> 773.11313 | P22: =P23+P24 -> 1183.8449 | Q22: =Q23+Q24 -> 1632.4845 | R22: =R23+R24 -> 2121.524 | S22: =S23+S24 -> 2650.5397 | T22: =T23+T24 -> 3221.396
C23: 장기차입금 | L23: =연결정산표!J66/10^6 -> 542 | M23: =연결정산표_우모건제외!M68/10^6 -> 542 | N23: =M23 -> 542 | O23: =N23 -> 542 | P23: =O23 -> 542 | Q23: =P23 -> 542 | R23: =Q23 -> 542 | S23: =R23 -> 542 | T23: =S23 -> 542
C24: 기타비유동부채 | L24: =L22-L23 -> 33.190278 | M24: =M22-M23 -> 69.75831 | N24: =M24+'Pro forma CF'!N11 -> 231.11313 | O24: =N24 -> 231.11313 | P24: =O24+'Pro forma CF'!P11 -> 641.84495 | Q24: =P24+'Pro forma CF'!Q11 -> 1090.4845 | R24: =Q24+'Pro forma CF'!R11 -> 1579.524 | S24: =R24+'Pro forma CF'!S11 -> 2108.5397 | T24: =S24+'Pro forma CF'!T11 -> 2679.396
B25: 부채총계 | L25: =L22+L17 -> 1778.9195 | M25: =M22+M17 -> 2243.627 | N25: =N22+N17 -> 10054.983 | O25: =O22+O17 -> 10054.983 | P25: =P22+P17 -> 12994.25 | Q25: =Q22+Q17 -> 15719.273 | R25: =R22+R17 -> 17953.521 | S25: =S22+S17 -> 20303.777 | T25: =T22+T17 -> 22811.716
B26: 자본총계 | L26: =L16-L25 -> 2752.1471 | M26: =M16-M25 -> 16398.561 | N26: =N16-N25 -> 22997.762 | O26: =O16-O25 -> 22997.762 | P26: =P16-P25 -> 48969.003 | Q26: =Q16-Q25 -> 80922.519 | R26: =R16-R25 -> 117112.29 | S26: =S16-S25 -> 157736.79 | T26: =T16-T25 -> 203081.24
L27: =연결정산표!J89/10^6=L26 -> TRUE | M27: ='Pro forma CE'!M11=M26 -> TRUE | N27: =ROUND('Pro forma CE'!N11,)=ROUND(N26,) -> TRUE | O27: =ROUND('Pro forma CE'!O11,)=ROUND(O26,) -> TRUE | P27: =ROUND('Pro forma CE'!P11,)=ROUND(P26,) -> TRUE | Q27: =ROUND('Pro forma CE'!Q11,)=ROUND(Q26,) -> TRUE | R27: =ROUND('Pro forma CE'!R11,)=ROUND(R26,) -> TRUE | S27: =ROUND('Pro forma CE'!S11,)=ROUND(S26,) -> TRUE | T27: =ROUND('Pro forma CE'!T11,)=ROUND(T26,) -> TRUE
A29: 2. Normalization 기준 BS
L31: 2024A | M31: 2025 1H | N31: 2025 2H | O31: 2025E | P31: 2026F | Q31: 2027F | R31: 2028F | S31: 2029F | T31: 2030F
B32: 유동자산 | L32: =SUM(L33:L37) -> 3393.8404 | M32: =SUM(M33:M37) -> 15473.031 | N32: =SUM(N33:N37) -> 23214.434 | O32: =SUM(O33:O37) -> 23214.434 | P32: =SUM(P33:P37) -> 42605.176 | Q32: =SUM(Q33:Q37) -> 59586.579 | R32: =SUM(R33:R37) -> 77108.596 | S32: =SUM(S33:S37) -> 95870.9 | T32: =SUM(T33:T37) -> 115971.17
C33: 현금및현금성자산 | L33: =L7 -> 1161.7762 | M33: ='Pro forma CF'!M50 -> 3776.9549 | N33: ='Pro forma CF'!N50 -> 12536.878 | O33: ='Pro forma CF'!O50 -> 12536.878 | P33: ='Pro forma CF'!P50 -> 30525.74 | Q33: ='Pro forma CF'!Q50 -> 46754.786 | R33: ='Pro forma CF'!R50 -> 63289.258 | S33: ='Pro forma CF'!S50 -> 81036.882 | T33: ='Pro forma CF'!T50 -> 100068.75
C34: 단기대여금 | L34: =L8 -> 0 | M34: =M8 -> 1200 | N34: =M34 -> 1200 | O34: =N34 -> 1200 | P34: =O34 -> 1200 | Q34: =P34 -> 1200 | R34: =Q34 -> 1200 | S34: =R34 -> 1200 | T34: =S34 -> 1200
C35: 운전자산 | L35: =L9 -> 1641.1379 | M35: =M9 -> 8174.6202 | N35: =N9 -> 7156.1012 | O35: =O9 -> 7156.1012 | P35: =P9 -> 8557.9806 | Q35: =Q9 -> 9310.3382 | R35: =R9 -> 10297.883 | S35: =S9 -> 11312.562 | T35: =T9 -> 12380.965
C36: 주임종단기채권 | L36: =L10 -> 369.18887 | M36: =M10 -> 1991.9156 | N36: =M36 -> 1991.9156 | O36: =N36 -> 1991.9156 | P36: =O36 -> 1991.9156 | Q36: =P36 -> 1991.9156 | R36: =Q36 -> 1991.9156 | S36: =R36 -> 1991.9156 | T36: =S36 -> 1991.9156
C37: 기타유동자산 | L37: =L11 -> 221.73735 | M37: =M11 -> 329.53993 | N37: =M37 -> 329.53993 | O37: =N37 -> 329.53993 | P37: =O37 -> 329.53993 | Q37: =P37 -> 329.53993 | R37: =Q37 -> 329.53993 | S37: =R37 -> 329.53993 | T37: =S37 -> 329.53993
B38: 비유동자산 | L38: =SUM(L39:L41) -> 1137.2261 | M38: =SUM(M39:M41) -> 1856.4592 | N38: =SUM(N39:N41) -> 1849.4094 | O38: =SUM(O39:O41) -> 1849.4094 | P38: =SUM(P39:P41) -> 1827.5494 | Q38: =SUM(Q39:Q41) -> 1810.156 | R38: =SUM(R39:R41) -> 1797.3912 | S38: =SUM(S39:S41) -> 1789.524 | T38: =SUM(T39:T41) -> 1780.2847
C39: 투자주식 | L39: =L13 -> 0 | M39: =M13 -> 310 | N39: =M39 -> 310 | O39: =N39 -> 310 | P39: =O39 -> 310 | Q39: =P39 -> 310 | R39: =Q39 -> 310 | S39: =R39 -> 310 | T39: =S39 -> 310
C40: 유무형자산 | L40: =L14 -> 987.43582 | M40: =M14 -> 1080.9109 | N40: =N14 -> 1073.8611 | O40: =O14 -> 1073.8611 | P40: =P14 -> 1052.001 | Q40: =Q14 -> 1034.6076 | R40: =R14 -> 1021.8429 | S40: =S14 -> 1013.9757 | T40: =T14 -> 1004.7364
C41: 기타비유동자산 | L41: =L15 -> 149.79032 | M41: =M15 -> 465.54832 | N41: =M41 -> 465.54832 | O41: =N41 -> 465.54832 | P41: =O41 -> 465.54832 | Q41: =P41 -> 465.54832 | R41: =Q41 -> 465.54832 | S41: =R41 -> 465.54832 | T41: =S41 -> 465.54832
B42: 자산총계 | L42: =L38+L32 -> 4531.0665 | M42: =M38+M32 -> 17329.49 | N42: =N38+N32 -> 25063.844 | O42: =O38+O32 -> 25063.844 | P42: =P38+P32 -> 44432.726 | Q42: =Q38+Q32 -> 61396.735 | R42: =R38+R32 -> 78905.987 | S42: =S38+S32 -> 97660.424 | T42: =T38+T32 -> 117751.46
B43: 유동부채 | L43: =L44+L45+L46+L47 -> 1203.7292 | M43: =M44+M45+M46+M47 -> 6466.7597 | N43: =SUM(N44:N47) -> 7266.716 | O43: =SUM(O44:O47) -> 7266.716 | P43: =SUM(P44:P47) -> 7841.884 | Q43: =SUM(Q44:Q47) -> 8226.6176 | R43: =SUM(R44:R47) -> 9012.9826 | S43: =SUM(S44:S47) -> 9811.4643 | T43: =SUM(T44:T47) -> 10643.901
C44: 단기차입금 | L44: =L18 -> 100 | M44: =M18 -> 100 | N44: =M44 -> 100 | O44: =N44 -> 100 | P44: =O44 -> 100 | Q44: =P44 -> 100 | R44: =Q44 -> 100 | S44: =R44 -> 100 | T44: =S44 -> 100
C45: 운전부채 | L45: =L19 -> 437.91273 | M45: =M63 -> 5875.5802 | N45: =N63 -> 6675.4256 | O45: =O63 -> 6675.4256 | P45: =P63 -> 7250.3618 | Q45: =Q63 -> 7634.8318 | R45: =R63 -> 8420.9316 | S45: =S63 -> 9219.1464 | T45: =T63 -> 10051.315
C46: 미지급법인세 | L46: =L20 -> 596.78793 | M46: =M20 -> 336.46338 | N46: =M46+'Pro forma PL'!N44+'Pro forma CF'!N41 -> 336.57424 | O46: =N46 -> 336.57424 | P46: =O46+'Pro forma PL'!P44+'Pro forma CF'!P41 -> 336.8061 | Q46: =P46+'Pro forma PL'!Q44+'Pro forma CF'!Q41 -> 337.06961 | R46: =Q46+'Pro forma PL'!R44+'Pro forma CF'!R41 -> 337.33486 | S46: =R46+'Pro forma PL'!S44+'Pro forma CF'!S41 -> 337.60172 | T46: =S46+'Pro forma PL'!T44+'Pro forma CF'!T41 -> 337.87004
C47: 기타유동부채 | L47: =L21 -> 69.028535 | M47: =M21 -> 154.71614 | N47: =M47 -> 154.71614 | O47: =N47 -> 154.71614 | P47: =O47 -> 154.71614 | Q47: =P47 -> 154.71614 | R47: =Q47 -> 154.71614 | S47: =R47 -> 154.71614 | T47: =S47 -> 154.71614
B48: 비유동부채 | L48: =SUM(L49:L50) -> 575.19028 | M48: =SUM(M49:M50) -> 611.75831 | N48: =N49+N50 -> 773.11313 | O48: =O49+O50 -> 773.11313 | P48: =P49+P50 -> 1183.8449 | Q48: =Q49+Q50 -> 1632.4845 | R48: =R49+R50 -> 2121.524 | S48: =S49+S50 -> 2650.5397 | T48: =T49+T50 -> 3221.396
C49: 장기차입금 | L49: =L23 -> 542 | M49: =M23 -> 542 | N49: =M49 -> 542 | O49: =N49 -> 542 | P49: =O49 -> 542 | Q49: =P49 -> 542 | R49: =Q49 -> 542 | S49: =R49 -> 542 | T49: =S49 -> 542
C50: 기타비유동부채 | L50: =L24 -> 33.190278 | M50: =M24 -> 69.75831 | N50: =N24 -> 231.11313 | O50: =O24 -> 231.11313 | P50: =P24 -> 641.84495 | Q50: =Q24 -> 1090.4845 | R50: =R24 -> 1579.524 | S50: =S24 -> 2108.5397 | T50: =T24 -> 2679.396
B51: 부채총계 | L51: =L48+L43 -> 1778.9195 | M51: =M48+M43 -> 7078.518 | N51: =N48+N43 -> 8039.8291 | O51: =O48+O43 -> 8039.8291 | P51: =P48+P43 -> 9025.729 | Q51: =Q48+Q43 -> 9859.1021 | R51: =R48+R43 -> 11134.507 | S51: =S48+S43 -> 12462.004 | T51: =T48+T43 -> 13865.297
B52: 자본총계 | L52: =L42-L51 -> 2752.1471 | M52: =M42-M51 -> 10250.972 | N52: =N42-N51 -> 17024.015 | O52: =O42-O51 -> 17024.015 | P52: =P42-P51 -> 35406.997 | Q52: =Q42-Q51 -> 51537.633 | R52: =R42-R51 -> 67771.481 | S52: =S42-S51 -> 85198.42 | T52: =T42-T51 -> 103886.16
A55: 3. Normalization 기준 NWC
L57: 2024A | M57: 2025 1H | N57: 2025 2H | O57: 2025E | P57: 2026F | Q57: 2027F | R57: 2028F | S57: 2029F | T57: 2030F
B58: NWC 변동 | M58: =M59-L59 -> 2408.5126 | N58: =N59-M59 -> -1818.3644 | O58: =O59-L59 -> 590.14821 | P58: =P59-O59 -> 826.94325 | Q58: =Q59-P59 -> 367.88749 | R58: =R59-Q59 -> 201.44474 | S58: =S59-R59 -> 216.46442 | T58: =T59-S59 -> 236.23396
B59: NWC | L59: =L60-L63 -> -109.47259 | M59: =M60-M63 -> 2299.04 | N59: =N60-N63 -> 480.67562 | O59: =O60-O63 -> 480.67562 | P59: =P60-P63 -> 1307.6189 | Q59: =Q60-Q63 -> 1675.5064 | R59: =R60-R63 -> 1876.9511 | S59: =S60-S63 -> 2093.4155 | T59: =T60-T63 -> 2329.6495
B60: 운전자산 | L60: =L61+L62 -> 1641.1379 | M60: =M61+M62 -> 8174.6202 | N60: =N61+N62 -> 7156.1012 | O60: =O61+O62 -> 7156.1012 | P60: =P61+P62 -> 8557.9806 | Q60: =Q61+Q62 -> 9310.3382 | R60: =R61+R62 -> 10297.883 | S60: =S61+S62 -> 11312.562 | T60: =T61+T62 -> 12380.965
C61: Reported | L61: =SUM(TITAN!L148,CLASS!L155,NOVA!L109,TTA!L117) -> 1641.1379 | M61: =SUM(TITAN!M148,CLASS!M155,NOVA!M109,TTA!M117) -> 8174.6202 | N61: =SUM(TITAN!N148,CLASS!N155,NOVA!N109,TTA!N117) -> 7156.1012 | O61: =SUM(TITAN!O148,CLASS!O155,NOVA!O109,TTA!O117) -> 7156.1012 | P61: =SUM(TITAN!P148,CLASS!P155,NOVA!P109,TTA!P117) -> 8557.9806 | Q61: =SUM(TITAN!Q148,CLASS!Q155,NOVA!Q109,TTA!Q117) -> 9310.3382 | R61: =SUM(TITAN!R148,CLASS!R155,NOVA!R109,TTA!R117) -> 10297.883 | S61: =SUM(TITAN!S148,CLASS!S155,NOVA!S109,TTA!S117) -> 11312.562 | T61: =SUM(TITAN!T148,CLASS!T155,NOVA!T109,TTA!T117) -> 12380.965
C62: Normalization | L62: 0 | M62: 0 | N62: 0 | O62: 0 | P62: 0 | Q62: 0 | R62: 0 | S62: 0 | T62: 0
B63: 운전부채 | L63: =SUM(TITAN!L160,CLASS!L167,NOVA!L114,TTA!L129) -> 1750.6105 | M63: =SUM(TITAN!M160,CLASS!M167,NOVA!M114,TTA!M129) -> 5875.5802 | N63: =SUM(TITAN!N160,CLASS!N167,NOVA!N114,TTA!N129) -> 6675.4256 | O63: =SUM(TITAN!O160,CLASS!O167,NOVA!O114,TTA!O129) -> 6675.4256 | P63: =SUM(TITAN!P160,CLASS!P167,NOVA!P114,TTA!P129) -> 7250.3618 | Q63: =SUM(TITAN!Q160,CLASS!Q167,NOVA!Q114,TTA!Q129) -> 7634.8318 | R63: =SUM(TITAN!R160,CLASS!R167,NOVA!R114,TTA!R129) -> 8420.9316 | S63: =SUM(TITAN!S160,CLASS!S167,NOVA!S114,TTA!S129) -> 9219.1464 | T63: =SUM(TITAN!T160,CLASS!T167,NOVA!T114,TTA!T129) -> 10051.315
C64: Reported | L64: =SUM(TITAN!L155,CLASS!L162,NOVA!L113,TTA!L124) -> 437.91273 | M64: =SUM(TITAN!M155,CLASS!M162,NOVA!M113,TTA!M124) -> 1040.6891 | N64: =SUM(TITAN!N155,CLASS!N162,NOVA!N113,TTA!N124) -> 1509.8272 | O64: =SUM(TITAN!O155,CLASS!O162,NOVA!O113,TTA!O124) -> 1509.8272 | P64: =SUM(TITAN!P155,CLASS!P162,NOVA!P113,TTA!P124) -> 1907.4843 | Q64: =SUM(TITAN!Q155,CLASS!Q162,NOVA!Q113,TTA!Q124) -> 2038.8573 | R64: =SUM(TITAN!R155,CLASS!R162,NOVA!R113,TTA!R124) -> 2265.5051 | S64: =SUM(TITAN!S155,CLASS!S162,NOVA!S113,TTA!S124) -> 2497.1929 | T64: =SUM(TITAN!T155,CLASS!T162,NOVA!T113,TTA!T124) -> 2740.0109
C65: Normalization | L65: =SUM(TITAN!L82,CLASS!L86,TTA!L70) -> 1312.6978 | M65: =M63-M64 -> 4834.891 | N65: =N63-N64 -> 5165.5984 | O65: =O63-O64 -> 5165.5984 | P65: =P63-P64 -> 5342.8775 | Q65: =Q63-Q64 -> 5595.9745 | R65: =R63-R64 -> 6155.4265 | S65: =S63-S64 -> 6721.9535 | T65: =T63-T64 -> 7311.3044

Sheet Pro forma CF
A1: Pro forma CF
A3: 1. Consolidated
L5: 2024A | M5: 2025 1H | N5: 2025 2H | O5: 2025E | P5: 2026F | Q5: 2027F | R5: 2028F | S5: 2029F | T5: 2030F
B6: 영업활동현금흐름 | M6: =SUM(M7:M15) -> 7596.7369 | N6: =SUM(N7:N15) -> 15511.05 | O6: =SUM(O7:O15) -> 23107.787 | P6: =SUM(P7:P15) -> 27652.505 | Q6: =SUM(Q7:Q15) -> 34056.034 | R6: =SUM(R7:R15) -> 37553.765 | S6: =SUM(S7:S15) -> 42066.52 | T6: =SUM(T7:T15) -> 46879.865
C7: 당기순이익 | M7: ='Pro forma PL'!M19 -> 13640.685 | N7: ='Pro forma PL'!N19 -> 6599.2018 | O7: =N7+M7 -> 20239.887 | P7: ='Pro forma PL'!P19 -> 25971.241 | Q7: ='Pro forma PL'!Q19 -> 31953.516 | R7: ='Pro forma PL'!R19 -> 36189.775 | S7: ='Pro forma PL'!S19 -> 40624.493 | T7: ='Pro forma PL'!T19 -> 45344.454
C8: 법인세비용 | M8: ='Pro forma PL'!M18 -> 0 | N8: ='Pro forma PL'!N18 -> 7180.8633 | O8: =N8+M8 -> 7180.8633 | P8: ='Pro forma PL'!P18 -> 9311.7412 | Q8: ='Pro forma PL'!Q18 -> 11456.751 | R8: ='Pro forma PL'!R18 -> 12975.312 | S8: ='Pro forma PL'!S18 -> 14564.865 | T8: ='Pro forma PL'!T18 -> 16259.129
C9: 단기매매증권평가이익 | M9: =연결정산표_우모건제외!AF102/10^6 -> -29.554816 | N9: 0 | O9: =N9+M9 -> -29.554816 | P9: 0 | Q9: 0 | R9: 0 | S9: 0 | T9: 0
C10: 무형자산처분이익 | M10: =연결정산표_우모건제외!AF103/10^6 -> -4.545455 | N10: 0 | O10: =N10+M10 -> -4.545455 | P10: 0 | Q10: 0 | R10: 0 | S10: 0 | T10: 0
C11: 퇴직급여 | M11: =연결정산표_우모건제외!AF98/10^6 -> 36.568032 | N11: =SUM(TITAN!N56,CLASS!N56,NOVA!N53,TTA!N47) -> 161.35482 | O11: =N11+M11 -> 197.92286 | P11: =SUM(TITAN!P56,CLASS!P56,NOVA!P53,TTA!P47) -> 410.73182 | Q11: =SUM(TITAN!Q56,CLASS!Q56,NOVA!Q53,TTA!Q47) -> 448.63958 | R11: =SUM(TITAN!R56,CLASS!R56,NOVA!R53,TTA!R47) -> 489.03945 | S11: =SUM(TITAN!S56,CLASS!S56,NOVA!S53,TTA!S47) -> 529.01573 | T11: =SUM(TITAN!T56,CLASS!T56,NOVA!T53,TTA!T47) -> 570.85625
C12: 감가상각비 | M12: ='Pro forma PL'!M21 -> 57.174702 | N12: ='Pro forma PL'!N21 -> 81.972752 | O12: =N12+M12 -> 139.14745 | P12: ='Pro forma PL'!P21 -> 143.8773 | Q12: ='Pro forma PL'!Q21 -> 129.85259 | R12: ='Pro forma PL'!R21 -> 117.28632 | S12: ='Pro forma PL'!S21 -> 106.45002 | T12: ='Pro forma PL'!T21 -> 95.874855
C13: 운전자본변동 | M13: =SUM(연결정산표_우모건제외!AF106,연결정산표_우모건제외!AF108,연결정산표_우모건제외!AF112)/10^6 -> -5930.7586 | N13: =DCF!N14 -> 1487.6571 | O13: =N13+M13 -> -4443.1015 | P13: =DCF!P14 -> -1004.2223 | Q13: =DCF!Q14 -> -620.98453 | R13: =DCF!R14 -> -760.89675 | S13: =DCF!S14 -> -782.99139 | T13: =DCF!T14 -> -825.58487
C14: 기타자산부채증감 | M14: =SUM(연결정산표_우모건제외!AF118:AF119,연결정산표_우모건제외!AF114:AF116,연결정산표_우모건제외!AF113,연결정산표_우모건제외!AF109:AF111,연결정산표_우모건제외!AF107)/10^6 -> 87.492542 | N14: 0 | O14: =N14+M14 -> 87.492542 | P14: 0 | Q14: 0 | R14: 0 | S14: 0 | T14: 0
C15: 법인세납부 | M15: =연결정산표_우모건제외!AF117/10^6 -> -260.32455 | N15: 0 | O15: =N15+M15 -> -260.32455 | P15: =-O8 -> -7180.8633 | Q15: =-P8 -> -9311.7412 | R15: =-Q8 -> -11456.751 | S15: =-R8 -> -12975.312 | T15: =-S8 -> -14564.865
B16: 투자활동현금흐름 | M16: =연결정산표_우모건제외!AG120/10^6 -> -3640.289 | N16: =N17+N18+N19 -> -74.922948 | O16: =O17+O18+O19 -> -3715.212 | P16: =P17+P18+P19 -> -122.01725 | Q16: =Q17+Q18+Q19 -> -112.45919 | R16: =R17+R18+R19 -> -104.52159 | S16: =S17+S18+S19 -> -98.582786 | T16: =T17+T18+T19 -> -86.635555
C17: 유무형자산취득처분 | M17: =(연결정산표_우모건제외!AF124+연결정산표_우모건제외!AF130+연결정산표_우모건제외!AF131+연결정산표_우모건제외!AF132+연결정산표_우모건제외!AF135)/10^6 -> -146.10431 | N17: =DCF!N13 -> -74.922948 | O17: =N17+M17 -> -221.02726 | P17: =DCF!P13 -> -122.01725 | Q17: =DCF!Q13 -> -112.45919 | R17: =DCF!R13 -> -104.52159 | S17: =DCF!S13 -> -98.582786 | T17: =DCF!T13 -> -86.635555
C18: 대여금증감 | M18: =연결정산표_우모건제외!AF122/10^6+연결정산표_우모건제외!AF128/10^6 -> -2822.7267 | N18: 0 | O18: =N18+M18 -> -2822.7267 | P18: 0 | Q18: 0 | R18: 0 | S18: 0 | T18: 0
C19: 기타 | M19: =M16-M17-M18 -> -671.458 | N19: 0 | O19: =N19+M19 -> -671.458 | P19: 0 | Q19: 0 | R19: 0 | S19: 0 | T19: 0
B20: 재무활동현금흐름 | M20: =M21+M22 -> -28.571429 | N20: =N21+N22 -> 0 | O20: =O21+O22 -> -28.571429 | P20: =P21+P22 -> 0 | Q20: =Q21+Q22 -> 0 | R20: =R21+R22 -> 0 | S20: =S21+S22 -> 0 | T20: =T21+T22 -> 0
C21: 차입금변동 | M21: 0 | N21: 0 | O21: =N21+M21 -> 0 | P21: 0 | Q21: 0 | R21: 0 | S21: 0 | T21: 0
C22: 배당금지급 | M22: =연결정산표_우모건제외!AF142/10^6 -> -28.571429 | N22: 0 | O22: =N22+M22 -> -28.571429 | P22: 0 | Q22: 0 | R22: 0 | S22: 0 | T22: 0
B23: 현금증감 | M23: =M20+M16+M6 -> 3927.8765 | N23: =N20+N16+N6 -> 15436.127 | O23: =N23+M23 -> 19364.003 | P23: =P20+P16+P6 -> 27530.488 | Q23: =Q20+Q16+Q6 -> 33943.575 | R23: =R20+R16+R6 -> 37449.243 | S23: =S20+S16+S6 -> 41967.938 | T23: =T20+T16+T6 -> 46793.229
B24: 기초현금 | M24: ='Pro forma BS'!L7 -> 1161.7762 | N24: =M25 -> 5089.6527 | O24: =M24 -> 1161.7762 | P24: =O25 -> 20525.78 | Q24: =P25 -> 48056.268 | R24: =Q25 -> 81999.842 | S24: =R25 -> 119449.09 | T24: =S25 -> 161417.02
B25: 기말현금 | M25: =M24+M23 -> 5089.6527 | N25: =N24+N23 -> 20525.78 | O25: =O24+O23 -> 20525.78 | P25: =P24+P23 -> 48056.268 | Q25: =Q24+Q23 -> 81999.842 | R25: =R24+R23 -> 119449.09 | S25: =S24+S23 -> 161417.02 | T25: =T24+T23 -> 208210.25
A28: 2. Nomalization 기준
L30: 2024A | M30: 2025 1H | N30: 2025 2H | O30: 2025E | P30: 2026F | Q30: 2027F | R30: 2028F | S30: 2029F | T30: 2030F
B31: 영업활동현금흐름 | M31: =SUM(M32:M40) -> 6284.0391 | N31: =SUM(N32:N40) -> 8759.9227 | O31: =SUM(O32:O40) -> 15043.962 | P31: =SUM(P32:P40) -> 17988.863 | Q31: =SUM(Q32:Q40) -> 16229.045 | R31: =SUM(R32:R40) -> 16534.472 | S31: =SUM(S32:S40) -> 17747.624 | T31: =SUM(T32:T40) -> 19031.872
C32: 당기순이익 | M32: =M7-'Pro forma BS'!M65 -> 8805.794 | N32: ='Pro forma PL'!N44 -> 0.11086279 | O32: =N32+M32 -> 8805.9049 | P32: ='Pro forma PL'!P44 -> 0.23185275 | Q32: ='Pro forma PL'!Q44 -> 0.26351231 | R32: ='Pro forma PL'!R44 -> 0.2652467 | S32: ='Pro forma PL'!S44 -> 0.26686718 | T32: ='Pro forma PL'!T44 -> 0.2683161
C33: 법인세비용 | M33: =M8 -> 0 | N33: ='Pro forma PL'!N43 -> 1948.6572 | O33: =N33+M33 -> 1948.6572 | P33: ='Pro forma PL'!P43 -> 8766.9251 | Q33: ='Pro forma PL'!Q43 -> 10720.3 | R33: ='Pro forma PL'!R43 -> 11610.354 | S33: ='Pro forma PL'!S43 -> 12511.073 | T33: ='Pro forma PL'!T43 -> 13448.198
C34: 단기매매증권평가이익 | M34: =M9 -> -29.554816 | N34: 0 | O34: =N34+M34 -> -29.554816 | P34: 0 | Q34: 0 | R34: 0 | S34: 0 | T34: 0
C35: 무형자산처분이익 | M35: =M10 -> -4.545455 | N35: 0 | O35: =N35+M35 -> -4.545455 | P35: 0 | Q35: 0 | R35: 0 | S35: 0 | T35: 0
C36: 퇴직급여 | M36: =M11 -> 36.568032 | N36: =SUM(TITAN!N81,CLASS!N81,NOVA!N78,TTA!N72) -> 1.4319605 | O36: =N36+M36 -> 37.999992 | P36: =SUM(TITAN!P81,CLASS!P81,NOVA!P78,TTA!P72) -> 0.75 | Q36: =SUM(TITAN!Q81,CLASS!Q81,NOVA!Q78,TTA!Q72) -> 0.5 | R36: =SUM(TITAN!R81,CLASS!R81,NOVA!R78,TTA!R72) -> 0.5 | S36: =SUM(TITAN!S81,CLASS!S81,NOVA!S78,TTA!S72) -> 0.5 | T36: =SUM(TITAN!T81,CLASS!T81,NOVA!T78,TTA!T72) -> 0.5
C37: 감가상각비 | M37: =M12 -> 57.174702 | N37: ='Pro forma PL'!N46 -> 4991.3582 | O37: =N37+M37 -> 5048.5329 | P37: ='Pro forma PL'!P46 -> 11996.556 | Q37: ='Pro forma PL'!Q46 -> 14642.794 | R37: ='Pro forma PL'!R46 -> 15845.097 | S37: ='Pro forma PL'!S46 -> 17062.603 | T37: ='Pro forma PL'!T46 -> 18330.213
C38: 운전자본변동 | M38: =M13+'Pro forma BS'!M65-'Pro forma BS'!L65 -> -2408.5653 | N38: =N13+'Pro forma BS'!N65-'Pro forma BS'!M65 -> 1818.3644 | O38: =N38+M38 -> -590.20091 | P38: =P13+'Pro forma BS'!P65-'Pro forma BS'!O65 -> -826.94325 | Q38: =Q13+'Pro forma BS'!Q65-'Pro forma BS'!P65 -> -367.88749 | R38: =R13+'Pro forma BS'!R65-'Pro forma BS'!Q65 -> -201.44474 | S38: =S13+'Pro forma BS'!S65-'Pro forma BS'!R65 -> -216.46442 | T38: =T13+'Pro forma BS'!T65-'Pro forma BS'!S65 -> -236.23396
C39: 기타자산부채증감 | M39: =M14 -> 87.492542 | N39: 0 | O39: =N39+M39 -> 87.492542 | P39: 0 | Q39: 0 | R39: 0 | S39: 0 | T39: 0
C40: 법인세납부 | M40: =M15 -> -260.32455 | N40: 0 | O40: =N40+M40 -> -260.32455 | P40: =-O33 -> -1948.6572 | Q40: =-P33 -> -8766.9251 | R40: =-Q33 -> -10720.3 | S40: =-R33 -> -11610.354 | T40: =-S33 -> -12511.073
B41: 투자활동현금흐름 | M41: =M16 -> -3640.289 | N41: =N42+N43+N44 -> 0 | O41: =O42+O43+O44 -> -3640.289 | P41: =P42+P43+P44 -> 0 | Q41: =Q42+Q43+Q44 -> 0 | R41: =R42+R43+R44 -> 0 | S41: =S42+S43+S44 -> 0 | T41: =T42+T43+T44 -> 0
C42: 유무형자산취득처분 | M42: =M17 -> -146.10431 | N42: =DCF!N38 -> 0 | O42: =N42+M42 -> -146.10431 | P42: =DCF!P38 -> 0 | Q42: =DCF!Q38 -> 0 | R42: =DCF!R38 -> 0 | S42: =DCF!S38 -> 0 | T42: =DCF!T38 -> 0
C43: 대여금증감 | M43: =M18 -> -2822.7267 | N43: 0 | O43: =N43+M43 -> -2822.7267 | P43: 0 | Q43: 0 | R43: 0 | S43: 0 | T43: 0
C44: 기타 | M44: =M19 -> -671.458 | N44: 0 | O44: =N44+M44 -> -671.458 | P44: 0 | Q44: 0 | R44: 0 | S44: 0 | T44: 0
B45: 재무활동현금흐름 | M45: =M20 -> -28.571429 | N45: =N46+N47 -> 0 | O45: =O46+O47 -> -28.571429 | P45: =P46+P47 -> 0 | Q45: =Q46+Q47 -> 0 | R45: =R46+R47 -> 0 | S45: =S46+S47 -> 0 | T45: =T46+T47 -> 0
C46: 차입금변동 | M46: =M21 -> 0 | N46: 0 | O46: =N46+M46 -> 0 | P46: 0 | Q46: 0 | R46: 0 | S46: 0 | T46: 0
C47: 배당금지급 | M47: =M22 -> -28.571429 | N47: 0 | O47: =N47+M47 -> -28.571429 | P47: 0 | Q47: 0 | R47: 0 | S47: 0 | T47: 0
B48: 현금증감 | M48: =M45+M41+M31 -> 2615.1787 | N48: =N45+N41+N31 -> 8759.9227 | O48: =N48+M48 -> 11375.101 | P48: =P45+P41+P31 -> 17988.863 | Q48: =Q45+Q41+Q31 -> 16229.045 | R48: =R45+R41+R31 -> 16534.472 | S48: =S45+S41+S31 -> 17747.624 | T48: =T45+T41+T31 -> 19031.872
B49: 기초현금 | M49: =M24 -> 1161.7762 | N49: =M50 -> 3776.9549 | O49: =M49 -> 1161.7762 | P49: =O50 -> 12536.878 | Q49: =P50 -> 30525.74 | R49: =Q50 -> 46754.786 | S49: =R50 -> 63289.258 | T49: =S50 -> 81036.882
B50: 기말현금 | M50: =M49+M48 -> 3776.9549 | N50: =N49+N48 -> 12536.878 | O50: =O49+O48 -> 12536.878 | P50: =P49+P48 -> 30525.74 | Q50: =Q49+Q48 -> 46754.786 | R50: =R49+R48 -> 63289.258 | S50: =S49+S48 -> 81036.882 | T50: =T49+T48 -> 100068.75

Sheet Pro forma CE
A1: Pro forma CE
A3: 1. Consolidated
L5: 2024A | M5: 2025 1H | N5: 2025 2H | O5: 2025E | P5: 2026F | Q5: 2027F | R5: 2028F | S5: 2029F | T5: 2030F
B6: 기초 | L6: =L11-L7 -> 376.32503 | M6: =L11 -> 2752.1471 | N6: =M11 -> 16398.561 | O6: =L11 -> 2752.1471 | P6: =O11 -> 22997.762 | Q6: =P11 -> 48969.003 | R6: =Q11 -> 80922.519 | S6: =R11 -> 117112.29 | T6: =S11 -> 157736.79
C7: 당기순이익 | L7: ='Pro forma PL'!L19 -> 2375.822 | M7: ='Pro forma PL'!M19 -> 13640.685 | N7: ='Pro forma PL'!N19 -> 6599.2018 | O7: ='Pro forma PL'!O19 -> 20239.887 | P7: ='Pro forma PL'!P19 -> 25971.241 | Q7: ='Pro forma PL'!Q19 -> 31953.516 | R7: ='Pro forma PL'!R19 -> 36189.775 | S7: ='Pro forma PL'!S19 -> 40624.493 | T7: ='Pro forma PL'!T19 -> 45344.454
C8: 배당 | M8: =연결정산표_우모건제외!J87/10^6 -> -31.428572 | N8: 0 | O8: =SUM(M8:N8) -> -31.428572 | P8: 0 | Q8: 0 | R8: 0 | S8: 0 | T8: 0
C9: 전기오류수정 | M9: =연결정산표_우모건제외!J88/10^6 -> -56.931671 | N9: 0 | O9: =SUM(M9:N9) -> -56.931671 | P9: 0 | Q9: 0 | R9: 0 | S9: 0 | T9: 0
C10: 기타 | M10: =M11-M9-M8-M7-M6 -> 94.088814 | N10: 0 | O10: =SUM(M10:N10) -> 94.088814 | P10: 0 | Q10: 0 | R10: 0 | S10: 0 | T10: 0
B11: 기말 | L11: =연결정산표_우모건제외!P91/10^6 -> 2752.1471 | M11: =연결정산표_우모건제외!M91/10^6 -> 16398.561 | N11: =SUM(N6:N10) -> 22997.762 | O11: =SUM(O6:O10) -> 22997.762 | P11: =SUM(P6:P10) -> 48969.003 | Q11: =SUM(Q6:Q10) -> 80922.519 | R11: =SUM(R6:R10) -> 117112.29 | S11: =SUM(S6:S10) -> 157736.79 | T11: =SUM(T6:T10) -> 203081.24

Sheet Pro forma PL
A1: Pro forma PL
A3: 1. Consolidated
L5: 2024A | M5: 2025 1H | N5: 2025 2H | O5: 2025E | P5: 2026F | Q5: 2027F | R5: 2028F | S5: 2029F | T5: 2030F
B6: 매출액 | L6: =SUM(L30,L54,L78,L102,L126) -> 11223.359 | M6: =SUM(M30,M54,M78,M102,M126) -> 33392.893 | N6: =SUM(N30,N54,N78,N102,N126) -> 43931.553 | O6: =SUM(O30,O54,O78,O102,O126) -> 77324.447 | P6: =SUM(P30,P54,P78,P102,P126) -> 93269.577 | Q6: =SUM(Q30,Q54,Q78,Q102,Q126) -> 103535.16 | R6: =SUM(R30,R54,R78,R102,R126) -> 114632.35 | S6: =SUM(S30,S54,S78,S102,S126) -> 126061.71 | T6: =SUM(T30,T54,T78,T102,T126) -> 138122.31
B7: 영업비용 | L7: =SUM(L8:L10) -> 7882.2028 | M7: =SUM(M8:M10) -> 19480.857 | N7: =SUM(N8:N10) -> 30151.488 | O7: =SUM(O8:O10) -> 49632.346 | P7: =SUM(P8:P10) -> 57986.595 | Q7: =SUM(Q8:Q10) -> 60124.892 | R7: =SUM(R8:R10) -> 65467.261 | S7: =SUM(S8:S10) -> 70872.351 | T7: =SUM(T8:T10) -> 76518.723
C8: 인건비 | L8: =SUM(L32,L56,L80,L104,L128) -> 664.89449 | M8: =SUM(M32,M56,M80,M104,M128) -> 988.67775 | N8: =SUM(N32,N56,N80,N104,N128) -> 1806.2283 | O8: =SUM(O32,O56,O80,O104,O128) -> 2794.906 | P8: =SUM(P32,P56,P80,P104,P128) -> 5597.9335 | Q8: =SUM(Q32,Q56,Q80,Q104,Q128) -> 6113.6151 | R8: =SUM(R32,R56,R80,R104,R128) -> 6662.5778 | S8: =SUM(S32,S56,S80,S104,S128) -> 7205.6801 | T8: =SUM(T32,T56,T80,T104,T128) -> 7774.0943
C9: 변동비 | L9: =SUM(L33,L57,L81,L105,L129) -> 6290.7849 | M9: =SUM(M33,M57,M81,M105,M129) -> 17029.245 | N9: =SUM(N33,N57,N81,N105,N129) -> 26851.976 | O9: =SUM(O33,O57,O81,O105,O129) -> 43881.221 | P9: =SUM(P33,P57,P81,P105,P129) -> 49380.844 | Q9: =SUM(Q33,Q57,Q81,Q105,Q129) -> 50965.933 | R9: =SUM(R33,R57,R81,R105,R129) -> 55710.68 | S9: =SUM(S33,S57,S81,S105,S129) -> 60526.946 | T9: =SUM(T33,T57,T81,T105,T129) -> 65556.135
C10: 고정비 | L10: =SUM(L34,L58,L82,L106,L130) -> 926.52339 | M10: =SUM(M34,M58,M82,M106,M130) -> 1462.9347 | N10: =SUM(N34,N58,N82,N106,N130) -> 1493.2841 | O10: =SUM(O34,O58,O82,O106,O130) -> 2956.2189 | P10: =SUM(P34,P58,P82,P106,P130) -> 3007.8182 | Q10: =SUM(Q34,Q58,Q82,Q106,Q130) -> 3045.3445 | R10: =SUM(R34,R58,R82,R106,R130) -> 3094.0035 | S10: =SUM(S34,S58,S82,S106,S130) -> 3139.7249 | T10: =SUM(T34,T58,T82,T106,T130) -> 3188.4931
B11: 영업이익 | L11: =L6-L7 -> 3341.1562 | M11: =M6-M7 -> 13912.036 | N11: =N6-N7 -> 13780.065 | O11: =O6-O7 -> 27692.101 | P11: =P6-P7 -> 35282.982 | Q11: =Q6-Q7 -> 43410.268 | R11: =R6-R7 -> 49165.087 | S11: =S6-S7 -> 55189.358 | T11: =T6-T7 -> 61603.584
B12: 영업이익률% | L12: =L11/L6 -> 0.29769663 | M12: =M11/M6 -> 0.41661666 | N12: =N11/N6 -> 0.31367125 | O12: =O11/O6 -> 0.35812867 | P12: =P11/P6 -> 0.37829036 | Q12: =Q11/Q6 -> 0.41928044 | R12: =R11/R6 -> 0.42889366 | S12: =S11/S6 -> 0.43779636 | T12: =T11/T6 -> 0.44600749
B13: 영업외손익 | L13: =SUM(L14:L16) -> -159.16174 | M13: =SUM(M14:M16) -> -271.35077 | N13: =SUM(N14:N16) -> 0 | O13: =SUM(O14:O16) -> -271.35077 | P13: =SUM(P14:P16) -> 0 | Q13: =SUM(Q14:Q16) -> 0 | R13: =SUM(R14:R16) -> 0 | S13: =SUM(S14:S16) -> 0 | T13: =SUM(T14:T16) -> 0
C14: 이자수익 | L14: =SUM(L38,L62,L86,L110,L134) -> 0.154836 | M14: =SUM(M38,M62,M86,M110,M134) -> 0.407191 | N14: =SUM(N38,N62,N86,N110,N134) -> 0 | O14: =SUM(O38,O62,O86,O110,O134) -> 0.407191 | P14: =SUM(P38,P62,P86,P110,P134) -> 0 | Q14: =SUM(Q38,Q62,Q86,Q110,Q134) -> 0 | R14: =SUM(R38,R62,R86,R110,R134) -> 0 | S14: =SUM(S38,S62,S86,S110,S134) -> 0 | T14: =SUM(T38,T62,T86,T110,T134) -> 0
C15: 이자비용 | L15: =SUM(L39,L63,L87,L111,L135) -> -36.830795 | M15: =SUM(M39,M63,M87,M111,M135) -> -15.001928 | N15: =SUM(N39,N63,N87,N111,N135) -> 0 | O15: =SUM(O39,O63,O87,O111,O135) -> -15.001928 | P15: =SUM(P39,P63,P87,P111,P135) -> 0 | Q15: =SUM(Q39,Q63,Q87,Q111,Q135) -> 0 | R15: =SUM(R39,R63,R87,R111,R135) -> 0 | S15: =SUM(S39,S63,S87,S111,S135) -> 0 | T15: =SUM(T39,T63,T87,T111,T135) -> 0
C16: 기타 | L16: =SUM(L40,L64,L88,L112,L136) -> -122.48578 | M16: =SUM(M40,M64,M88,M112,M136) -> -256.75603 | N16: =SUM(N40,N64,N88,N112,N136) -> 0 | O16: =SUM(O40,O64,O88,O112,O136) -> -256.75603 | P16: =SUM(P40,P64,P88,P112,P136) -> 0 | Q16: =SUM(Q40,Q64,Q88,Q112,Q136) -> 0 | R16: =SUM(R40,R64,R88,R112,R136) -> 0 | S16: =SUM(S40,S64,S88,S112,S136) -> 0 | T16: =SUM(T40,T64,T88,T112,T136) -> 0
B17: 법인세차감전순이익 | L17: =L11+L13 -> 3181.9944 | M17: =M11+M13 -> 13640.685 | N17: =N11+N13 -> 13780.065 | O17: =O11+O13 -> 27420.75 | P17: =P11+P13 -> 35282.982 | Q17: =Q11+Q13 -> 43410.268 | R17: =R11+R13 -> 49165.087 | S17: =S11+S13 -> 55189.358 | T17: =T11+T13 -> 61603.584
B18: 법인세비용 | L18: =SUM(L42,L66,L90,L114,L138) -> 806.1724 | M18: =SUM(M42,M66,M90,M114,M138) -> 0 | N18: =SUM(N42,N66,N90,N114,N138) -> 7180.8633 | O18: =SUM(O42,O66,O90,O114,O138) -> 7180.8633 | P18: =SUM(P42,P66,P90,P114,P138) -> 9311.7412 | Q18: =SUM(Q42,Q66,Q90,Q114,Q138) -> 11456.751 | R18: =SUM(R42,R66,R90,R114,R138) -> 12975.312 | S18: =SUM(S42,S66,S90,S114,S138) -> 14564.865 | T18: =SUM(T42,T66,T90,T114,T138) -> 16259.129
B19: 당기순이익 | L19: =L17-L18 -> 2375.822 | M19: =M17-M18 -> 13640.685 | N19: =N17-N18 -> 6599.2018 | O19: =O17-O18 -> 20239.887 | P19: =P17-P18 -> 25971.241 | Q19: =Q17-Q18 -> 31953.516 | R19: =R17-R18 -> 36189.775 | S19: =S17-S18 -> 40624.493 | T19: =T17-T18 -> 45344.454
B20: 당기순이익률% | L20: =L19/L$6 -> 0.21168547 | M20: =M19/M$6 -> 0.40849066 | N20: =N19/N$6 -> 0.15021554 | O20: =O19/O$6 -> 0.26175275 | P20: =P19/P$6 -> 0.27845351 | Q20: =Q19/Q$6 -> 0.30862478 | R20: =R19/R$6 -> 0.31570299 | S20: =S19/S$6 -> 0.32225878 | T20: =T19/T$6 -> 0.32829204
B21: D&A | L21: =SUM(L45,L69,L93,L117,L141) -> 127.87806 | M21: =SUM(M45,M69,M93,M117,M141) -> 57.174702 | N21: =SUM(N45,N69,N93,N117,N141) -> 81.972752 | O21: =SUM(O45,O69,O93,O117,O141) -> 139.14745 | P21: =SUM(P45,P69,P93,P117,P141) -> 143.8773 | Q21: =SUM(Q45,Q69,Q93,Q117,Q141) -> 129.85259 | R21: =SUM(R45,R69,R93,R117,R141) -> 117.28632 | S21: =SUM(S45,S69,S93,S117,S141) -> 106.45002 | T21: =SUM(T45,T69,T93,T117,T141) -> 95.874855
B22: EBITDA | L22: =L21+L11 -> 3469.0342 | M22: =M21+M11 -> 13969.211 | N22: =N21+N11 -> 13862.038 | O22: =O21+O11 -> 27831.248 | P22: =P21+P11 -> 35426.859 | Q22: =Q21+Q11 -> 43540.12 | R22: =R21+R11 -> 49282.373 | S22: =S21+S11 -> 55295.808 | T22: =T21+T11 -> 61699.458
B23: EBITDA% | L23: =L22/L$6 -> 0.30909055 | M23: =M22/M$6 -> 0.41832885 | N23: =N22/N$6 -> 0.31553717 | O23: =O22/O$6 -> 0.35992819 | P23: =P22/P$6 -> 0.37983296 | Q23: =Q22/Q$6 -> 0.42053463 | R23: =R22/R$6 -> 0.42991681 | S23: =S22/S$6 -> 0.43864079 | T23: =T22/T$6 -> 0.44670162
B24: Normalized EBITDA | L24: =SUM(L48,L72,L96,L120,L142) -> 2156.3364 | M24: =SUM(M48,M72,M96,M120,M142) -> 9134.3195 | N24: =SUM(N48,N72,N96,N120,N142) -> 13862.038 | O24: =SUM(O48,O72,O96,O120,O142) -> 22996.357 | P24: =SUM(P48,P72,P96,P120,P142) -> 35426.859 | Q24: =SUM(Q48,Q72,Q96,Q120,Q142) -> 43540.12 | R24: =SUM(R48,R72,R96,R120,R142) -> 49282.373 | S24: =SUM(S48,S72,S96,S120,S142) -> 55295.808 | T24: =SUM(T48,T72,T96,T120,T142) -> 61699.458
B25: Norm. EBITDA% | L25: =L24/L6 -> 0.19212933 | M25: =M24/M6 -> 0.27354082 | N25: =N24/N6 -> 0.31553717 | O25: =O24/O6 -> 0.29740087 | P25: =P24/P6 -> 0.37983296 | Q25: =Q24/Q6 -> 0.42053463 | R25: =R24/R6 -> 0.42991681 | S25: =S24/S6 -> 0.43864079 | T25: =T24/T6 -> 0.44670162
A27: 2. TITAN
L29: 2024A | M29: 2025 1H | N29: 2025 2H | O29: 2025E | P29: 2026F | Q29: 2027F | R29: 2028F | S29: 2029F | T29: 2030F
B30: 매출액 | L30: =TITAN!L6 -> 11203.459 | M30: =TITAN!M6 -> 17504.878 | N30: =TITAN!N6 -> 17577.197 | O30: =TITAN!O6 -> 35082.076 | P30: =TITAN!P6 -> 37812.47 | Q30: =TITAN!Q6 -> 40682.35 | R30: =TITAN!R6 -> 43771.909 | S30: =TITAN!S6 -> 46881.275 | T30: =TITAN!T6 -> 50120.726
B31: 영업비용 | L31: =TITAN!L7 -> 7805.3692 | M31: =TITAN!M7 -> 10871.796 | N31: =TITAN!N7 -> 12636.466 | O31: =TITAN!O7 -> 23508.262 | P31: =TITAN!P7 -> 25900.887 | Q31: =TITAN!Q7 -> 26116.725 | R31: =TITAN!R7 -> 27996.971 | S31: =TITAN!S7 -> 29882.534 | T31: =TITAN!T7 -> 31848.718
C32: 인건비 | L32: =TITAN!L43 -> 646.27145 | M32: =TITAN!M43 -> 581.34672 | N32: =TITAN!N43 -> 643.12573 | O32: =TITAN!O43 -> 1224.4724 | P32: =TITAN!P43 -> 1995.7352 | Q32: =TITAN!Q43 -> 2143.1634 | R32: =TITAN!R43 -> 2312.8469 | S32: =TITAN!S43 -> 2479.1937 | T32: =TITAN!T43 -> 2653.0773
C33: 변동비 | L33: =TITAN!L44 -> 6247.7291 | M33: =TITAN!M44 -> 9389.8284 | N33: =TITAN!N44 -> 11088.007 | O33: =TITAN!O44 -> 20477.835 | P33: =TITAN!P44 -> 22082.324 | Q33: =TITAN!Q44 -> 22127.256 | R33: =TITAN!R44 -> 23807.677 | S33: =TITAN!S44 -> 25498.871 | T33: =TITAN!T44 -> 27260.819
C34: 고정비 | L34: =L31-L32-L33 -> 911.36869 | M34: =M31-M32-M33 -> 900.62095 | N34: =N31-N32-N33 -> 905.33322 | O34: =O31-O32-O33 -> 1805.9542 | P34: =P31-P32-P33 -> 1822.8277 | Q34: =Q31-Q32-Q33 -> 1846.3053 | R34: =R31-R32-R33 -> 1876.447 | S34: =S31-S32-S33 -> 1904.4692 | T34: =T31-T32-T33 -> 1934.8223
B35: 영업이익 | L35: =L30-L31 -> 3398.0897 | M35: =M30-M31 -> 6633.0824 | N35: =N30-N31 -> 4940.7319 | O35: =O30-O31 -> 11573.814 | P35: =P30-P31 -> 11911.583 | Q35: =Q30-Q31 -> 14565.625 | R35: =R30-R31 -> 15774.938 | S35: =S30-S31 -> 16998.741 | T35: =T30-T31 -> 18272.008
B36: 영업이익률% | L36: =L35/L30 -> 0.3033072 | M36: =M35/M30 -> 0.37892765 | N36: =N35/N30 -> 0.28108758 | O36: =O35/O30 -> 0.32990677 | P36: =P35/P30 -> 0.31501732 | Q36: =Q35/Q30 -> 0.35803303 | R36: =R35/R30 -> 0.36038954 | S36: =S35/S30 -> 0.36259127 | T36: =T35/T30 -> 0.36455992
B37: 영업외손익 | L37: =연결정산표!F139/10^6-연결정산표!F146/10^6 -> -159.16364 | M37: =연결정산표!U139/10^6-연결정산표!U146/10^6+연결정산표!W140/10^6 -> -240.19787 | N37: =SUM(N38:N40) -> 0 | O37: =SUM(O38:O40) -> -240.19787 | P37: =SUM(P38:P40) -> 0 | Q37: =SUM(Q38:Q40) -> 0 | R37: =SUM(R38:R40) -> 0 | S37: =SUM(S38:S40) -> 0 | T37: =SUM(T38:T40) -> 0
C38: 이자수익 | L38: =연결정산표!G140/10^6 -> 0.152929 | M38: =연결정산표!U140/10^6-연결정산표!W140/10^6 -> 0.308253 | N38: 0 | O38: =N38+M38 -> 0.308253 | P38: 0 | Q38: 0 | R38: 0 | S38: 0 | T38: 0
C39: 이자비용 | L39: =-연결정산표!F147/10^6 -> -36.830795 | M39: =-연결정산표!U147/10^6 -> -14.810261 | N39: 0 | O39: =N39+M39 -> -14.810261 | P39: 0 | Q39: 0 | R39: 0 | S39: 0 | T39: 0
C40: 기타 | L40: =L37-L38-L39 -> -122.48577 | M40: =M37-M38-M39 -> -225.69587 | N40: 0 | O40: =N40+M40 -> -225.69587 | P40: 0 | Q40: 0 | R40: 0 | S40: 0 | T40: 0
B41: 법인세차감전순이익 | L41: =L35+L37 -> 3238.9261 | M41: =M35+M37 -> 6392.8845 | N41: =N35+N37 -> 4940.7319 | O41: =O35+O37 -> 11333.616 | P41: =P35+P37 -> 11911.583 | Q41: =Q35+Q37 -> 14565.625 | R41: =R35+R37 -> 15774.938 | S41: =S35+S37 -> 16998.741 | T41: =T35+T37 -> 18272.008
B42: 법인세비용 | L42: =연결정산표!F154/10^6 -> 806.1724 | M42: 0 | N42: =O42 -> 2992.0747 | O42: =IF(O41<0,0,IF(O41<2,O41*9%*1.1,IF(O41<200,O41*19%*1.1,IF(O41<3000,O41*21%*1.1,O41*24%*1.1)))) -> 2992.0747 | P42: =IF(P41<0,0,IF(P41<2,P41*9%*1.1,IF(P41<200,P41*19%*1.1,IF(P41<3000,P41*21%*1.1,P41*24%*1.1)))) -> 3144.6579 | Q42: =IF(Q41<0,0,IF(Q41<2,Q41*9%*1.1,IF(Q41<200,Q41*19%*1.1,IF(Q41<3000,Q41*21%*1.1,Q41*24%*1.1)))) -> 3845.325 | R42: =IF(R41<0,0,IF(R41<2,R41*9%*1.1,IF(R41<200,R41*19%*1.1,IF(R41<3000,R41*21%*1.1,R41*24%*1.1)))) -> 4164.5837 | S42: =IF(S41<0,0,IF(S41<2,S41*9%*1.1,IF(S41<200,S41*19%*1.1,IF(S41<3000,S41*21%*1.1,S41*24%*1.1)))) -> 4487.6676 | T42: =IF(T41<0,0,IF(T41<2,T41*9%*1.1,IF(T41<200,T41*19%*1.1,IF(T41<3000,T41*21%*1.1,T41*24%*1.1)))) -> 4823.8101
B43: 당기순이익 | L43: =L41-L42 -> 2432.7537 | M43: =M41-M42 -> 6392.8845 | N43: =N41-N42 -> 1948.6572 | O43: =O41-O42 -> 8341.5417 | P43: =P41-P42 -> 8766.9251 | Q43: =Q41-Q42 -> 10720.3 | R43: =R41-R42 -> 11610.354 | S43: =S41-S42 -> 12511.073 | T43: =T41-T42 -> 13448.198
B44: 당기순이익률% | L44: =L43/L$30 -> 0.21714309 | M44: =M43/M$30 -> 0.36520588 | N44: =N43/N$30 -> 0.11086279 | O44: =O43/O$30 -> 0.23777218 | P44: =P43/P$30 -> 0.23185275 | Q44: =Q43/Q$30 -> 0.26351231 | R44: =R43/R$30 -> 0.2652467 | S44: =S43/S$30 -> 0.26686718 | T44: =T43/T$30 -> 0.2683161
B45: D&A | L45: =TITAN!L10 -> 127.87806 | M45: =TITAN!M10 -> 45.914015 | N45: =TITAN!N10 -> 50.626289 | O45: =TITAN!O10 -> 96.540304 | P45: =TITAN!P10 -> 84.973118 | Q45: =TITAN!Q10 -> 77.169324 | R45: =TITAN!R10 -> 70.15918 | S45: =TITAN!S10 -> 63.861971 | T45: =TITAN!T10 -> 58.205191
B46: EBITDA | L46: =L35+L45 -> 3525.9678 | M46: =M35+M45 -> 6678.9964 | N46: =N35+N45 -> 4991.3582 | O46: =O35+O45 -> 11670.355 | P46: =P35+P45 -> 11996.556 | Q46: =Q35+Q45 -> 14642.794 | R46: =R35+R45 -> 15845.097 | S46: =S35+S45 -> 17062.603 | T46: =T35+T45 -> 18330.213
B47: EBITDA% | L47: =L46/L$30 -> 0.31472136 | M47: =M46/M$30 -> 0.38155057 | N47: =N46/N$30 -> 0.28396781 | O47: =O46/O$30 -> 0.33265861 | P47: =P46/P$30 -> 0.31726454 | Q47: =Q46/Q$30 -> 0.3599299 | R47: =R46/R$30 -> 0.36199237 | S47: =S46/S$30 -> 0.36395348 | T47: =T46/T$30 -> 0.36572122
B48: Normalized EBITDA | L48: =TITAN!L13 -> 2213.27 | M48: =TITAN!M13 -> 5264.701 | N48: =TITAN!N13 -> 4991.3582 | O48: =TITAN!O13 -> 10256.059 | P48: =TITAN!P13 -> 11996.556 | Q48: =TITAN!Q13 -> 14642.794 | R48: =TITAN!R13 -> 15845.097 | S48: =TITAN!S13 -> 17062.603 | T48: =TITAN!T13 -> 18330.213
B49: Norm. EBITDA% | L49: =L48/L30 -> 0.19755238 | M49: =M48/M30 -> 0.30075622 | N49: =N48/N30 -> 0.28396781 | O49: =O48/O30 -> 0.29234471 | P49: =P48/P30 -> 0.31726454 | Q49: =Q48/Q30 -> 0.3599299 | R49: =R48/R30 -> 0.36199237 | S49: =S48/S30 -> 0.36395348 | T49: =T48/T30 -> 0.36572122
A51: 3. CLASS
L53: 2024A | M53: 2025 1H | N53: 2025 2H | O53: 2025E | P53: 2026F | Q53: 2027F | R53: 2028F | S53: 2029F | T53: 2030F
B54: 매출액 | L54: =CLASS!L6 -> 19.9 | M54: =CLASS!M6 -> 10266.381 | N54: =CLASS!N6 -> 16569.007 | O54: =CLASS!O6 -> 26835.388 | P54: =CLASS!P6 -> 32543.72 | Q54: =CLASS!Q6 -> 34715.24 | R54: =CLASS!R6 -> 37063.293 | S54: =CLASS!S6 -> 39417.29 | T54: =CLASS!T6 -> 41870.527
B55: 영업비용 | L55: =CLASS!L7 -> 76.833572 | M55: =CLASS!M7 -> 6468.495 | N55: =CLASS!N7 -> 12303.422 | O55: =CLASS!O7 -> 18771.917 | P55: =CLASS!P7 -> 20780.481 | Q55: =CLASS!Q7 -> 21363.142 | R55: =CLASS!R7 -> 22769.727 | S55: =CLASS!S7 -> 24174.58 | T55: =CLASS!T7 -> 25632.359
C56: 인건비 | L56: =CLASS!L44 -> 18.623039 | M56: =CLASS!M44 -> 309.49833 | N56: =CLASS!N44 -> 738.17506 | O56: =CLASS!O44 -> 1047.6734 | P56: =CLASS!P44 -> 1886.7181 | Q56: =CLASS!Q44 -> 1994.7124 | R56: =CLASS!R44 -> 2121.6594 | S56: =CLASS!S44 -> 2243.7552 | T56: =CLASS!T44 -> 2371.0464
C57: 변동비 | L57: =CLASS!L45 -> 43.055839 | M57: =CLASS!M45 -> 5821.6407 | N57: =CLASS!N45 -> 11215.632 | O57: =CLASS!O45 -> 17037.273 | P57: =CLASS!P45 -> 18184.139 | Q57: =CLASS!Q45 -> 18647.907 | R57: =CLASS!R45 -> 19913.61 | S57: =CLASS!S45 -> 21182.673 | T57: =CLASS!T45 -> 22505.224
C58: 고정비 | L58: =CLASS!L46 -> 15.154694 | M58: =CLASS!M46 -> 337.35601 | N58: =CLASS!N46 -> 349.61399 | O58: =CLASS!O46 -> 686.97 | P58: =CLASS!P46 -> 709.62355 | Q58: =CLASS!Q46 -> 720.52215 | R58: =CLASS!R46 -> 734.45737 | S58: =CLASS!S46 -> 748.15122 | T58: =CLASS!T46 -> 756.08812
B59: 영업이익 | L59: =L54-L55 -> -56.933572 | M59: =M54-M55 -> 3797.886 | N59: =N54-N55 -> 4265.5856 | O59: =O54-O55 -> 8063.4716 | P59: =P54-P55 -> 11763.24 | Q59: =Q54-Q55 -> 13352.098 | R59: =R54-R55 -> 14293.566 | S59: =S54-S55 -> 15242.711 | T59: =T54-T55 -> 16238.168
B60: 영업이익률% | L60: =L59/L54 -> -2.8609835 | M60: =M59/M54 -> 0.36993425 | N60: =N59/N54 -> 0.25744365 | O60: =O59/O54 -> 0.30047904 | P60: =P59/P54 -> 0.36145959 | Q60: =Q59/Q54 -> 0.38461777 | R60: =R59/R54 -> 0.38565289 | S60: =S59/S54 -> 0.38670113 | T60: =T59/T54 -> 0.38781857
B61: 영업외손익 | L61: =연결정산표!E139/10^6-연결정산표!E146/10^6 -> 0.001901 | M61: =연결정산표!T139/10^6-연결정산표!T146/10^6-조정!J54/10^6 -> -31.149629 | N61: =SUM(N62:N64) -> 0 | O61: =SUM(O62:O64) -> -31.149629 | P61: =SUM(P62:P64) -> 0 | Q61: =SUM(Q62:Q64) -> 0 | R61: =SUM(R62:R64) -> 0 | S61: =SUM(S62:S64) -> 0 | T61: =SUM(T62:T64) -> 0
C62: 이자수익 | L62: =연결정산표!E140/10^6 -> 0.001907 | M62: =연결정산표!T140/10^6 -> 0.219176 | N62: 0 | O62: =N62+M62 -> 0.219176 | P62: 0 | Q62: 0 | R62: 0 | S62: 0 | T62: 0
C63: 이자비용 | L63: 0 | M63: 0 | N63: 0 | O63: =N63+M63 -> 0 | P63: 0 | Q63: 0 | R63: 0 | S63: 0 | T63: 0
C64: 기타 | L64: =L61-L62-L63 -> -6e-06 | M64: =M61-M62-M63 -> -31.368805 | N64: 0 | O64: =N64+M64 -> -31.368805 | P64: 0 | Q64: 0 | R64: 0 | S64: 0 | T64: 0
B65: 법인세차감전순이익 | L65: =L59+L61 -> -56.931671 | M65: =M59+M61 -> 3766.7364 | N65: =N59+N61 -> 4265.5856 | O65: =O59+O61 -> 8032.322 | P65: =P59+P61 -> 11763.24 | Q65: =Q59+Q61 -> 13352.098 | R65: =R59+R61 -> 14293.566 | S65: =S59+S61 -> 15242.711 | T65: =T59+T61 -> 16238.168
B66: 법인세비용 | L66: =연결정산표!F177/10^6 -> 0 | M66: 0 | N66: =O66 -> 2120.533 | O66: =IF(O65<0,0,IF(O65<2,O65*9%*1.1,IF(O65<200,O65*19%*1.1,IF(O65<3000,O65*21%*1.1,O65*24%*1.1)))) -> 2120.533 | P66: =IF(P65<0,0,IF(P65<2,P65*9%*1.1,IF(P65<200,P65*19%*1.1,IF(P65<3000,P65*21%*1.1,P65*24%*1.1)))) -> 3105.4953 | Q66: =IF(Q65<0,0,IF(Q65<2,Q65*9%*1.1,IF(Q65<200,Q65*19%*1.1,IF(Q65<3000,Q65*21%*1.1,Q65*24%*1.1)))) -> 3524.9539 | R66: =IF(R65<0,0,IF(R65<2,R65*9%*1.1,IF(R65<200,R65*19%*1.1,IF(R65<3000,R65*21%*1.1,R65*24%*1.1)))) -> 3773.5015 | S66: =IF(S65<0,0,IF(S65<2,S65*9%*1.1,IF(S65<200,S65*19%*1.1,IF(S65<3000,S65*21%*1.1,S65*24%*1.1)))) -> 4024.0756 | T66: =IF(T65<0,0,IF(T65<2,T65*9%*1.1,IF(T65<200,T65*19%*1.1,IF(T65<3000,T65*21%*1.1,T65*24%*1.1)))) -> 4286.8763
B67: 당기순이익 | L67: =L65-L66 -> -56.931671 | M67: =M65-M66 -> 3766.7364 | N67: =N65-N66 -> 2145.0526 | O67: =O65-O66 -> 5911.789 | P67: =P65-P66 -> 8657.7446 | Q67: =Q65-Q66 -> 9827.1442 | R67: =R65-R66 -> 10520.065 | S67: =S65-S66 -> 11218.635 | T67: =T65-T66 -> 11951.292
B68: 당기순이익률% | L68: =L67/L$54 -> -2.860888 | M68: =M67/M$54 -> 0.36690012 | N68: =N67/N$54 -> 0.12946175 | O68: =O67/O$54 -> 0.22029825 | P68: =P67/P$54 -> 0.26603426 | Q68: =Q67/Q$54 -> 0.28307868 | R68: =R67/R$54 -> 0.28384053 | S68: =S67/S$54 -> 0.28461203 | T68: =T67/T$54 -> 0.28543447
B69: D&A | L69: =CLASS!L10 -> 0 | M69: =CLASS!M10 -> 9.980253 | N69: =CLASS!N10 -> 22.238234 | O69: =CLASS!O10 -> 32.218487 | P69: =CLASS!P10 -> 43.978483 | Q69: =CLASS!Q10 -> 42.895476 | R69: =CLASS!R10 -> 42.600536 | S69: =CLASS!S10 -> 43.149102 | T69: =CLASS!T10 -> 37.29325
B70: EBITDA | L70: =L69+L59 -> -56.933572 | M70: =M69+M59 -> 3807.8663 | N70: =N69+N59 -> 4287.8239 | O70: =O69+O59 -> 8095.6901 | P70: =P69+P59 -> 11807.218 | Q70: =Q69+Q59 -> 13394.994 | R70: =R69+R59 -> 14336.167 | S70: =S69+S59 -> 15285.86 | T70: =T69+T59 -> 16275.461
B71: EBITDA% | L71: =L70/L$54 -> -2.8609835 | M71: =M70/M$54 -> 0.37090638 | N71: =N70/N$54 -> 0.25878581 | O71: =O70/O$54 -> 0.30167964 | P71: =P70/P$54 -> 0.36281096 | Q71: =Q70/Q$54 -> 0.38585341 | R71: =R70/R$54 -> 0.38680229 | S71: =S70/S$54 -> 0.3877958 | T71: =T70/T$54 -> 0.38870925
B72: Normalized EBITDA | L72: =CLASS!L13 -> -56.933572 | M72: =CLASS!M13 -> 1987.2706 | N72: =CLASS!N13 -> 4287.8239 | O72: =CLASS!O13 -> 6275.0945 | P72: =CLASS!P13 -> 11807.218 | Q72: =CLASS!Q13 -> 13394.994 | R72: =CLASS!R13 -> 14336.167 | S72: =CLASS!S13 -> 15285.86 | T72: =CLASS!T13 -> 16275.461
B73: Norm. EBITDA% | L73: =L72/L54 -> -2.8609835 | M73: =M72/M54 -> 0.19357071 | N73: =N72/N54 -> 0.25878581 | O73: =O72/O54 -> 0.23383655 | P73: =P72/P54 -> 0.36281096 | Q73: =Q72/Q54 -> 0.38585341 | R73: =R72/R54 -> 0.38680229 | S73: =S72/S54 -> 0.3877958 | T73: =T72/T54 -> 0.38870925
A75: 4. NOVA
L77: 2024A | M77: 2025 1H | N77: 2025 2H | O77: 2025E | P77: 2026F | Q77: 2027F | R77: 2028F | S77: 2029F | T77: 2030F
B78: 매출액 | M78: =NOVA!M6 -> 261.84518 | N78: =NOVA!N6 -> 2351.4231 | O78: =NOVA!O6 -> 2613.2683 | P78: =NOVA!P6 -> 7196.2766 | Q78: =NOVA!Q6 -> 9426.1391 | R78: =NOVA!R6 -> 11924.423 | S78: =NOVA!S6 -> 14653.889 | T78: =NOVA!T6 -> 17654.417
B79: 영업비용 | M79: =NOVA!M7 -> 247.98681 | N79: =NOVA!N7 -> 489.71621 | O79: =NOVA!O7 -> 737.70302 | P79: =NOVA!P7 -> 1450.3768 | Q79: =NOVA!Q7 -> 1786.275 | R79: =NOVA!R7 -> 2124.0661 | S79: =NOVA!S7 -> 2483.1611 | T79: =NOVA!T7 -> 2871.8628
C80: 인건비 | M80: =NOVA!M41 -> 48.135155 | N80: =NOVA!N41 -> 256.8716 | O80: =NOVA!O41 -> 305.00675 | P80: =NOVA!P41 -> 779.57835 | Q80: =NOVA!Q41 -> 927.48945 | R80: =NOVA!R41 -> 1054.1634 | S80: =NOVA!S41 -> 1182.3929 | T80: =NOVA!T41 -> 1317.0106
C81: 변동비 | M81: =NOVA!M42 -> 180.91932 | N81: =NOVA!N42 -> 199.62994 | O81: =NOVA!O42 -> 380.54925 | P81: =NOVA!P42 -> 610.94587 | Q81: =NOVA!Q42 -> 800.25561 | R81: =NOVA!R42 -> 1012.3537 | S81: =NOVA!S42 -> 1244.0785 | T81: =NOVA!T42 -> 1498.8158
C82: 고정비 | M82: =NOVA!M43 -> 18.93234 | N82: =NOVA!N43 -> 33.214679 | O82: =NOVA!O43 -> 52.147019 | P82: =NOVA!P43 -> 59.85256 | Q82: =NOVA!Q43 -> 58.529912 | R82: =NOVA!R43 -> 57.549093 | S82: =NOVA!S43 -> 56.689691 | T82: =NOVA!T43 -> 56.036345
B83: 영업이익 | M83: =M78-M79 -> 13.858365 | N83: =N78-N79 -> 1861.7069 | O83: =O78-O79 -> 1875.5653 | P83: =P78-P79 -> 5745.8998 | Q83: =Q78-Q79 -> 7639.8641 | R83: =R78-R79 -> 9800.3568 | S83: =S78-S79 -> 12170.728 | T83: =T78-T79 -> 14782.554
B84: 영업이익률% | M84: =M83/M78 -> 0.052925798 | N84: =N83/N78 -> 0.79173624 | O84: =O83/O78 -> 0.71770866 | P84: =P83/P78 -> 0.79845455 | Q84: =Q83/Q78 -> 0.81049771 | R84: =R83/R78 -> 0.82187263 | S84: =S83/S78 -> 0.83054593 | T84: =T83/T78 -> 0.83732894
B85: 영업외손익 | M85: =연결정산표!S139/10^6-연결정산표!S146/10^6+연결정산표_우모건제외!G149/10^6+연결정산표_우모건제외!L145/10^6 -> 0.312619 | N85: =SUM(N86:N88) -> 0 | O85: =SUM(O86:O88) -> 0.312619 | P85: =SUM(P86:P88) -> 0 | Q85: =SUM(Q86:Q88) -> 0 | R85: =SUM(R86:R88) -> 0 | S85: =SUM(S86:S88) -> 0 | T85: =SUM(T86:T88) -> 0
C86: 이자수익 | M86: =연결정산표!S140/10^6 -> 0.009165 | N86: 0 | O86: =N86+M86 -> 0.009165 | P86: 0 | Q86: 0 | R86: 0 | S86: 0 | T86: 0
C87: 이자비용 | M87: 0 | N87: 0 | O87: =N87+M87 -> 0 | P87: 0 | Q87: 0 | R87: 0 | S87: 0 | T87: 0
C88: 기타 | M88: =M85-M86-M87 -> 0.303454 | N88: 0 | O88: =N88+M88 -> 0.303454 | P88: 0 | Q88: 0 | R88: 0 | S88: 0 | T88: 0
B89: 법인세차감전순이익 | M89: =M83+M85 -> 14.170984 | N89: =N83+N85 -> 1861.7069 | O89: =O83+O85 -> 1875.8779 | P89: =P83+P85 -> 5745.8998 | Q89: =Q83+Q85 -> 7639.8641 | R89: =R83+R85 -> 9800.3568 | S89: =S83+S85 -> 12170.728 | T89: =T83+T85 -> 14782.554
B90: 법인세비용 | M90: 0 | N90: =O90 -> 433.32779 | O90: =IF(O89<0,0,IF(O89<2,O89*9%*1.1,IF(O89<200,O89*19%*1.1,IF(O89<3000,O89*21%*1.1,O89*24%*1.1)))) -> 433.32779 | P90: =IF(P89<0,0,IF(P89<2,P89*9%*1.1,IF(P89<200,P89*19%*1.1,IF(P89<3000,P89*21%*1.1,P89*24%*1.1)))) -> 1516.9175 | Q90: =IF(Q89<0,0,IF(Q89<2,Q89*9%*1.1,IF(Q89<200,Q89*19%*1.1,IF(Q89<3000,Q89*21%*1.1,Q89*24%*1.1)))) -> 2016.9241 | R90: =IF(R89<0,0,IF(R89<2,R89*9%*1.1,IF(R89<200,R89*19%*1.1,IF(R89<3000,R89*21%*1.1,R89*24%*1.1)))) -> 2587.2942 | S90: =IF(S89<0,0,IF(S89<2,S89*9%*1.1,IF(S89<200,S89*19%*1.1,IF(S89<3000,S89*21%*1.1,S89*24%*1.1)))) -> 3213.0721 | T90: =IF(T89<0,0,IF(T89<2,T89*9%*1.1,IF(T89<200,T89*19%*1.1,IF(T89<3000,T89*21%*1.1,T89*24%*1.1)))) -> 3902.5943
B91: 당기순이익 | M91: =M89-M90 -> 14.170984 | N91: =N89-N90 -> 1428.3791 | O91: =O89-O90 -> 1442.5501 | P91: =P89-P90 -> 4228.9822 | Q91: =Q89-Q90 -> 5622.94 | R91: =R89-R90 -> 7213.0626 | S91: =S89-S90 -> 8957.6556 | T91: =T89-T90 -> 10879.96
B92: 당기순이익률% | M92: =M91/M$78 -> 0.054119706 | N92: =N91/N$78 -> 0.60745304 | O92: =O91/O$78 -> 0.55200995 | P92: =P91/P$78 -> 0.58766255 | Q92: =Q91/Q$78 -> 0.59652631 | R92: =R91/R$78 -> 0.60489825 | S92: =S91/S$78 -> 0.6112818 | T92: =T91/T$78 -> 0.6162741
B93: D&A | M93: =NOVA!M10 -> 2.132428 | N93: =NOVA!N10 -> 10.863412 | O93: =NOVA!O10 -> 12.99584 | P93: =NOVA!P10 -> 20.049996 | Q93: =NOVA!Q10 -> 18.010901 | R93: =NOVA!R10 -> 16.179184 | S93: =NOVA!S10 -> 14.533753 | T93: =NOVA!T10 -> 13.055663
B94: EBITDA | M94: =M83+M93 -> 15.990793 | N94: =N83+N93 -> 1872.5703 | O94: =O83+O93 -> 1888.5611 | P94: =P83+P93 -> 5765.9498 | Q94: =Q83+Q93 -> 7657.875 | R94: =R83+R93 -> 9816.536 | S94: =S83+S93 -> 12185.262 | T94: =T83+T93 -> 14795.61
B95: EBITDA% | M95: =M94/M$78 -> 0.061069649 | N95: =N94/N$78 -> 0.79635617 | O95: =O94/O$78 -> 0.72268168 | P95: =P94/P$78 -> 0.80124072 | Q95: =Q94/Q$78 -> 0.81240845 | R95: =R94/R$78 -> 0.82322944 | S95: =S94/S$78 -> 0.83153773 | T95: =T94/T$78 -> 0.83806845
B96: Normalized EBITDA | M96: =M94 -> 15.990793 | N96: =N94 -> 1872.5703 | O96: =O94 -> 1888.5611 | P96: =P94 -> 5765.9498 | Q96: =Q94 -> 7657.875 | R96: =R94 -> 9816.536 | S96: =S94 -> 12185.262 | T96: =T94 -> 14795.61
B97: Norm. EBITDA% | M97: =M95 -> 0.061069649 | N97: =N95 -> 0.79635617 | O97: =O95 -> 0.72268168 | P97: =P95 -> 0.80124072 | Q97: =Q95 -> 0.81240845 | R97: =R95 -> 0.82322944 | S97: =S95 -> 0.83153773 | T97: =T95 -> 0.83806845
A99: 5. TTA
L101: 2024A | M101: 2025 1H | N101: 2025 2H | O101: 2025E | P101: 2026F | Q101: 2027F | R101: 2028F | S101: 2029F | T101: 2030F
B102: 매출액 | M102: =TTA!M6 -> 5406.0864 | N102: =TTA!N6 -> 7433.9257 | O102: =TTA!O6 -> 12840.012 | P102: =TTA!P6 -> 15717.11 | Q102: =TTA!Q6 -> 18711.43 | R102: =TTA!R6 -> 21872.723 | S102: =TTA!S6 -> 25109.255 | T102: =TTA!T6 -> 28476.636
B103: 영업비용 | M103: =TTA!M7 -> 1920.4115 | N103: =TTA!N7 -> 4726.7598 | O103: =TTA!O7 -> 6647.1713 | P103: =TTA!P7 -> 9866.086 | Q103: =TTA!Q7 -> 10872.232 | R103: =TTA!R7 -> 12592.675 | S103: =TTA!S7 -> 14351.491 | T103: =TTA!T7 -> 16181.755
C104: 인건비 | M104: =TTA!M35 -> 49.697537 | N104: =TTA!N35 -> 168.05591 | O104: =TTA!O35 -> 217.75345 | P104: =TTA!P35 -> 935.90182 | Q104: =TTA!Q35 -> 1048.2498 | R104: =TTA!R35 -> 1173.9081 | S104: =TTA!S35 -> 1300.3382 | T104: =TTA!T35 -> 1432.96
C105: 변동비 | M105: =TTA!M36 -> 1662.9043 | N105: =TTA!N36 -> 4348.7069 | O105: =TTA!O36 -> 6011.6112 | P105: =TTA!P36 -> 8503.4346 | Q105: =TTA!Q36 -> 9390.5132 | R105: =TTA!R36 -> 10977.038 | S105: =TTA!S36 -> 12601.324 | T105: =TTA!T36 -> 14291.277
C106: 고정비 | M106: =TTA!M37 -> 207.80966 | N106: =TTA!N37 -> 209.99697 | O106: =TTA!O37 -> 417.80663 | P106: =TTA!P37 -> 426.74955 | Q106: =TTA!Q37 -> 433.46925 | R106: =TTA!R37 -> 441.72861 | S106: =TTA!S37 -> 449.82894 | T106: =TTA!T37 -> 457.5185
B107: 영업이익 | M107: =M102-M103 -> 3485.6748 | N107: =N102-N103 -> 2707.1659 | O107: =O102-O103 -> 6192.8407 | P107: =P102-P103 -> 5851.0241 | Q107: =Q102-Q103 -> 7839.1982 | R107: =R102-R103 -> 9280.0475 | S107: =S102-S103 -> 10757.764 | T107: =T102-T103 -> 12294.881
B108: 영업이익률% | M108: =M107/M102 -> 0.64476861 | N108: =N107/N102 -> 0.3641637 | O108: =O107/O102 -> 0.48230801 | P108: =P107/P102 -> 0.37227099 | Q108: =Q107/Q102 -> 0.41895237 | R108: =R107/R102 -> 0.42427491 | S108: =S107/S102 -> 0.42843821 | T108: =T107/T102 -> 0.43175328
B109: 영업외손익 | M109: =연결정산표!R139/10^6-연결정산표!R146/10^6 -> 0.06745 | N109: =SUM(N110:N112) -> 0 | O109: =SUM(O110:O112) -> 0.06745 | P109: =SUM(P110:P112) -> 0 | Q109: =SUM(Q110:Q112) -> 0 | R109: =SUM(R110:R112) -> 0 | S109: =SUM(S110:S112) -> 0 | T109: =SUM(T110:T112) -> 0
C110: 이자수익 | M110: =연결정산표!R140/10^6 -> 0.062264 | N110: 0 | O110: =N110+M110 -> 0.062264 | P110: 0 | Q110: 0 | R110: 0 | S110: 0 | T110: 0
...

Sheet Key Assumption
A1: Key Assumption
A3: 1. General
B5: Key Base Factors
B6: Valuation Date | L6: 45838
B7: Market Data Date | L7: 45838
B8: Year End after Valuation Date | L8: 46022
B9: Partial Period Factor | L9: 0.50410959
B11: Macro Indicators(from EIU) | O11: 2025E | P11: 2026F | Q11: 2027F | R11: 2028F | S11: 2029F | T11: 2030F
B12: 소비자물가지수 (avg.) | O12: =EIU!R11/100 -> 0.01913561 | P12: =EIU!S11/100 -> 0.016637681 | Q12: =EIU!T11/100 -> 0.018 | R12: =EIU!U11/100 -> 0.021 | S12: =EIU!V11/100 -> 0.019 | T12: =EIU!W11/100 -> 0.019564128
B13: 생산자물가지수 (avg.) | O13: =EIU!R12/100 -> 0.010711003 | P13: =EIU!S12/100 -> 0.013083958 | Q13: =EIU!T12/100 -> 0.017 | R13: =EIU!U12/100 -> 0.019 | S13: =EIU!V12/100 -> 0.022 | T13: =S13 -> 0.022
B14: 평균명목임금상승률 | O14: =EIU!R10/100 -> 0.016078204 | P14: =EIU!S10/100 -> 0.018670956 | Q14: =EIU!T10/100 -> 0.026144 | R14: =EIU!U10/100 -> 0.033252 | S14: =EIU!V10/100 -> 0.028171 | T14: =S14 -> 0.028171
A17: 2. Key Assumption
B19: 1. .강의 수 / 결제 건수
L20: 2024A | M20: 2025 1H | N20: 2025 2H | O20: 2025E | P20: 2026F | Q20: 2027F | R20: 2028F | S20: 2029F | T20: 2030F
B21: TITAN
C22: 부업
D23: 강의수 | I23: 120 | L23: =TITAN!L23 -> 65 | M23: =TITAN!M23 -> 46 | N23: =COUNTA(타이탄_하반기!B244:B584)/5*6-3 -> 46.2 | O23: =N23+M23 -> 92.2 | P23: =O23+($T23-$O23)/5 -> 97.76 | Q23: =P23+($T23-$O23)/5 -> 103.32 | R23: =Q23+($T23-$O23)/5 -> 108.88 | S23: =R23+($T23-$O23)/5 -> 114.44 | T23: =I23 -> 120 | U23: 플랫폼 추가 및 확장하며 2030년까지 강의 120개 오픈 | AA23: =COUNTIFS(클래스매출!$C$70:$C$117,"부업")/(("2025-11-11"-"2025-07-01")/(31+31+30+31+30+31)) -> 65.022556
D24: 강의당 유입 인원 수(톡방) | I24: =M24 -> 4473.8696 | L24: =TITAN!L25 -> 2085.0067 | M24: =TITAN!M25 -> 4473.8696 | N24: =M24 -> 4473.8696 | O24: =N24 -> 4473.8696 | P24: =$I24 -> 4473.8696 | Q24: =$I24 -> 4473.8696 | R24: =$I24 -> 4473.8696 | S24: =$I24 -> 4473.8696 | T24: =$I24 -> 4473.8696
D25: 유료전환율 | I25: =M25 -> 0.032721406 | L25: =TITAN!L27 -> 0.029529513 | M25: =TITAN!M27 -> 0.032721406 | N25: =M25 -> 0.032721406 | O25: =N25 -> 0.032721406 | P25: =$I25 -> 0.032721406 | Q25: =$I25 -> 0.032721406 | R25: =$I25 -> 0.032721406 | S25: =$I25 -> 0.032721406 | T25: =$I25 -> 0.032721406
B26: CLASS
C27: 부업
D28: 강의수 | I28: 120 | M28: =CLASS!M24 -> 37 | N28: =COUNTIFS(클래스매출!$C$70:$C$117,"부업")/5*6 -> 56.4 | O28: =N28+M28 -> 93.4 | P28: =O28+($T28-$O28)/5 -> 98.72 | Q28: =P28+($T28-$O28)/5 -> 104.04 | R28: =Q28+($T28-$O28)/5 -> 109.36 | S28: =R28+($T28-$O28)/5 -> 114.68 | T28: =I28 -> 120 | U28: 플랫폼 추가 및 확장하며 2030년까지 강의 120개 오픈
D29: 강의당 유입 인원 수(톡방) | I29: =I24 -> 4473.8696 | M29: =CLASS!M26 -> 2944.1892 | N29: =I29 -> 4473.8696 | O29: =CLASS!O26 -> 3867.8934 | P29: =$I29 -> 4473.8696 | Q29: =$I29 -> 4473.8696 | R29: =$I29 -> 4473.8696 | S29: =$I29 -> 4473.8696 | T29: =$I29 -> 4473.8696
D30: 유료전환율 | I30: =M30 -> 0.02703447 | J30: =I30 -> 0.02703447 | M30: =CLASS!M27 -> 0.02703447 | N30: =$I30 -> 0.02703447 | O30: =$I30 -> 0.02703447 | P30: =O30+($T30-$O30)/5 -> 0.02703447 | Q30: =P30+($T30-$O30)/5 -> 0.02703447 | R30: =Q30+($T30-$O30)/5 -> 0.02703447 | S30: =R30+($T30-$O30)/5 -> 0.02703447 | T30: =J30 -> 0.02703447
C31: 투자
D32: 강의수 | I32: =O32 -> 11 | L32: =CLASS!L31 -> 0 | M32: =CLASS!M31 -> 10 | N32: 1 | O32: =N32+M32 -> 11 | P32: =O32+($T32-$O32)/5 -> 11 | Q32: =P32+($T32-$O32)/5 -> 11 | R32: =Q32+($T32-$O32)/5 -> 11 | S32: =R32+($T32-$O32)/5 -> 11 | T32: =I32 -> 11 | U32: 현수준 유지 가정(부업 주력)
D33: 강의당 유입 인원 수(톡방) | I33: =M33 -> 3237.7 | M33: =CLASS!M33 -> 3237.7 | N33: =I33 -> 3237.7 | O33: =CLASS!O33 -> 3237.7 | P33: =$I33 -> 3237.7 | Q33: =$I33 -> 3237.7 | R33: =$I33 -> 3237.7 | S33: =$I33 -> 3237.7 | T33: =$I33 -> 3237.7
D34: 유료전환율 | I34: =M34 -> 0.031009667 | M34: =CLASS!M34 -> 0.031009667 | N34: =$I34 -> 0.031009667 | O34: =$I34 -> 0.031009667 | P34: =$I34 -> 0.031009667 | Q34: =$I34 -> 0.031009667 | R34: =$I34 -> 0.031009667 | S34: =$I34 -> 0.031009667 | T34: =$I34 -> 0.031009667
B35: TTA
C36: 부업
D37: 강의수 | I37: 100 | M37: =TTA!M23 -> 15 | N37: =(COUNTA(티티에이매출v2!$F$18:$F$43)-3)/4*6 -> 34.5 | O37: =N37+M37 -> 49.5 | P37: =O37+($T37-$O37)/5 -> 59.6 | Q37: =P37+($T37-$O37)/5 -> 69.7 | R37: =Q37+($T37-$O37)/5 -> 79.8 | S37: =R37+($T37-$O37)/5 -> 89.9 | T37: =I37 -> 100
D38: 강의당 유입 인원 수(톡방) | I38: =$O38 -> 3742.5866 | M38: =TTA!M25 -> 5200 | N38: =SUM(티티에이매출v2!$K$19:$K$46)/COUNTA(티티에이매출v2!$K$19:$K$46) -> 3108.9286 | O38: =TTA!O25 -> 3742.5866 | P38: =$I38 -> 3742.5866 | Q38: =$I38 -> 3742.5866 | R38: =$I38 -> 3742.5866 | S38: =$I38 -> 3742.5866 | T38: =$I38 -> 3742.5866
D39: 유료전환율 | I39: =M39 -> 0.028846154 | M39: =TTA!M26 -> 0.028846154 | N39: =$I39 -> 0.028846154 | O39: =$I39 -> 0.028846154 | P39: =$I39 -> 0.028846154 | Q39: =$I39 -> 0.028846154 | R39: =$I39 -> 0.028846154 | S39: =$I39 -> 0.028846154 | T39: =$I39 -> 0.028846154
B41: 2. NOVA - 관리 플랫폼 수 / 플랫폼당 월 매출액 / 수수료율
L42: 2024A | M42: 2025 1H | N42: 2025 2H | O42: 2025E | P42: 2026F | Q42: 2027F | R42: 2028F | S42: 2029F | T42: 2030F
B43: 구축관리형
C44: 평균 플랫폼 수 | I44: =시스템노바매출!N21 -> 8 | J44: 12 | M44: =NOVA!M22 -> 1 | N44: =AVERAGE(시스템노바매출!I21:N21) -> 6.6666667 | O44: =NOVA!O22 -> 5.25 | P44: =I44 -> 8 | Q44: =P44+($T44-$P44)/4 -> 9 | R44: =Q44+($T44-$P44)/4 -> 10 | S44: =R44+($T44-$P44)/4 -> 11 | T44: =J44 -> 12
C45: 플랫폼당 월매출액 | M45: =NOVA!M23 -> 1217.3985 | N45: =NOVA!N23 -> 653.50932 | O45: =NOVA!O23 -> 629.90363 | P45: =O45*(1+P$12) -> 640.38377 | Q45: =P45*(1+Q$12) -> 651.91068 | R45: =Q45*(1+R$12) -> 665.6008 | S45: =R45*(1+S$12) -> 678.24722 | T45: =S45*(1+T$12) -> 691.51653 | U45: 물가상승률 수준 상승 가정
C46: 수수료율 | I46: 0.15 | M46: =NOVA!M26 -> 0.097247237 | N46: =M46 -> 0.097247237 | O46: =N46 -> 0.097247237 | P46: =O46+($T46-$O46)/5 -> 0.10779779 | Q46: =P46+($T46-$O46)/5 -> 0.11834834 | R46: =Q46+($T46-$O46)/5 -> 0.12889889 | S46: =R46+($T46-$O46)/5 -> 0.13944945 | T46: =I46 -> 0.15
B47: 구축형
C48: 평균 플랫폼 수 | I48: 3 | J48: 10 | M48: 0 | N48: 0 | O48: 0 | P48: =I48 -> 3 | Q48: =P48+($T48-$P48)/4 -> 4.75 | R48: =Q48+($T48-$P48)/4 -> 6.5 | S48: =R48+($T48-$P48)/4 -> 8.25 | T48: =J48 -> 10
C49: 플랫폼당 월매출액 | M49: 0 | N49: 0 | O49: 0 | P49: =P45 -> 640.38377 | Q49: =Q45 -> 651.91068 | R49: =R45 -> 665.6008 | S49: =S45 -> 678.24722 | T49: =T45 -> 691.51653 | U49: 구축관리형 수준 준용 / 물가상승률 수준 상승 가정
C50: 수수료율 | I50: 0.05 | M50: 0 | N50: 0 | O50: 0 | P50: =$I50 -> 0.05 | Q50: =$I50 -> 0.05 | R50: =$I50 -> 0.05 | S50: =$I50 -> 0.05 | T50: =$I50 -> 0.05

Sheet TITAN
A1: TITAN
A3: 1. Summary
L5: 2024A | M5: 2025 1H | N5: 2025 2H | O5: 2025E | P5: 2026F | Q5: 2027F | R5: 2028F | S5: 2029F | T5: 2030F
B6: Revenue | L6: =L19 -> 11203.459 | M6: =M19 -> 17504.878 | N6: =N19 -> 17577.197 | O6: =O19 -> 35082.076 | P6: =P19 -> 37812.47 | Q6: =Q19 -> 40682.35 | R6: =R19 -> 43771.909 | S6: =S19 -> 46881.275 | T6: =T19 -> 50120.726
B7: Operating Expense | L7: =L41 -> 7805.3692 | M7: =M41 -> 10871.796 | N7: =N41 -> 12636.466 | O7: =O41 -> 23508.262 | P7: =P41 -> 25900.887 | Q7: =Q41 -> 26116.725 | R7: =R41 -> 27996.971 | S7: =S41 -> 29882.534 | T7: =T41 -> 31848.718
B8: EBIT | L8: =L6-L7 -> 3398.0897 | M8: =M6-M7 -> 6633.0824 | N8: =N6-N7 -> 4940.7319 | O8: =O6-O7 -> 11573.814 | P8: =P6-P7 -> 11911.583 | Q8: =Q6-Q7 -> 14565.625 | R8: =R6-R7 -> 15774.938 | S8: =S6-S7 -> 16998.741 | T8: =T6-T7 -> 18272.008
B9: EBIT % | L9: =L8/L6 -> 0.3033072 | M9: =M8/M6 -> 0.37892765 | N9: =N8/N6 -> 0.28108758 | O9: =O8/O6 -> 0.32990677 | P9: =P8/P6 -> 0.31501732 | Q9: =Q8/Q6 -> 0.35803303 | R9: =R8/R6 -> 0.36038954 | S9: =S8/S6 -> 0.36259127 | T9: =T8/T6 -> 0.36455992
B10: D&A | L10: =L109 -> 127.87806 | M10: =M109 -> 45.914015 | N10: =N109 -> 50.626289 | O10: =O109 -> 96.540304 | P10: =P109 -> 84.973118 | Q10: =Q109 -> 77.169324 | R10: =R109 -> 70.15918 | S10: =S109 -> 63.861971 | T10: =T109 -> 58.205191
B11: EBITDA | L11: =L10+L8 -> 3525.9678 | M11: =M10+M8 -> 6678.9964 | N11: =N10+N8 -> 4991.3582 | O11: =O10+O8 -> 11670.355 | P11: =P10+P8 -> 11996.556 | Q11: =Q10+Q8 -> 14642.794 | R11: =R10+R8 -> 15845.097 | S11: =S10+S8 -> 17062.603 | T11: =T10+T8 -> 18330.213
B12: EBITDA % | L12: =L11/L6 -> 0.31472136 | M12: =M11/M6 -> 0.38155057 | N12: =N11/N6 -> 0.28396781 | O12: =O11/O6 -> 0.33265861 | P12: =P11/P6 -> 0.31726454 | Q12: =Q11/Q6 -> 0.3599299 | R12: =R11/R6 -> 0.36199237 | S12: =S11/S6 -> 0.36395348 | T12: =T11/T6 -> 0.36572122
B13: Normalized EBITDA | L13: =L11-L82 -> 2213.27 | M13: =M11-M82 -> 5264.701 | N13: =N11-N82 -> 4991.3582 | O13: =O11-O82 -> 10256.059 | P13: =P11-P82 -> 11996.556 | Q13: =Q11-Q82 -> 14642.794 | R13: =R11-R82 -> 15845.097 | S13: =S11-S82 -> 17062.603 | T13: =T11-T82 -> 18330.213
B14: Norm EBITDA % | L14: =L13/L6 -> 0.19755238 | M14: =M13/M6 -> 0.30075622 | N14: =N13/N6 -> 0.28396781 | O14: =O13/O6 -> 0.29234471 | P14: =P13/P6 -> 0.31726454 | Q14: =Q13/Q6 -> 0.3599299 | R14: =R13/R6 -> 0.36199237 | S14: =S13/S6 -> 0.36395348 | T14: =T13/T6 -> 0.36572122
M15: =M8=연결정산표_우모건제외!I140/10^6 -> TRUE | V15: =(연결정산표!F98/10^6-(SUMIFS(타이탄매출!$N:$N,타이탄매출!$B:$B,TITAN!L$18,타이탄매출!$C:$C,TITAN!$D21)/10^6+SUMIFS(클래스매출!$J:$J,클래스매출!$A:$A,TITAN!L$18,클래스매출!$C:$C,TITAN!$D21)/10^6)-(SUMIFS(타이탄매출!$N:$N,타이탄매출!$B:$B,TITAN!L$18,타이탄매출!$C:$C,TITAN!$D29)/10^6+SUMIFS(클래스매출!$J:$J,클래스매출!$A:$A,TITAN!L$18,클래스매출!$C:$C,TITAN!$D29)/10^6))*(SUMIFS(타이탄매출!$N:$N,타이탄매출!$B:$B,TITAN!L$18,타이탄매출!$C:$C,TITAN!$D21)/10^6+SUMIFS(클래스매출!$J:$J,클래스매출!$A:$A,TITAN!L$18,클래스매출!$C:$C,TITAN!$D21)/10^6)/((SUMIFS(타이탄매출!$N:$N,타이탄매출!$B:$B,TITAN!L$18,타이탄매출!$C:$C,TITAN!$D21)/10^6+SUMIFS(클래스매출!$J:$J,클래스매출!$A:$A,TITAN!L$18,클래스매출!$C:$C,TITAN!$D21)/10^6)+(SUMIFS(타이탄매출!$N:$N,타이탄매출!$B:$B,TITAN!L$18,타이탄매출!$C:$C,TITAN!$D29)/10^6+SUMIFS(클래스매출!$J:$J,클래스매출!$A:$A,TITAN!L$18,클래스매출!$C:$C,TITAN!$D29)/10^6)) -> -359.22244
A16: 2. Revenue | V16: =(연결정산표!F98/10^6-(SUMIFS(타이탄매출!$N:$N,타이탄매출!$B:$B,TITAN!L$18,타이탄매출!$C:$C,TITAN!$D21)/10^6+SUMIFS(클래스매출!$J:$J,클래스매출!$A:$A,TITAN!L$18,클래스매출!$C:$C,TITAN!$D21)/10^6)-(SUMIFS(타이탄매출!$N:$N,타이탄매출!$B:$B,TITAN!L$18,타이탄매출!$C:$C,TITAN!$D29)/10^6+SUMIFS(클래스매출!$J:$J,클래스매출!$A:$A,TITAN!L$18,클래스매출!$C:$C,TITAN!$D29)/10^6))*(SUMIFS(타이탄매출!$N:$N,타이탄매출!$B:$B,TITAN!L$18,타이탄매출!$C:$C,TITAN!$D29)/10^6+SUMIFS(클래스매출!$J:$J,클래스매출!$A:$A,TITAN!L$18,클래스매출!$C:$C,TITAN!$D29)/10^6)/((SUMIFS(타이탄매출!$N:$N,타이탄매출!$B:$B,TITAN!L$18,타이탄매출!$C:$C,TITAN!$D21)/10^6+SUMIFS(클래스매출!$J:$J,클래스매출!$A:$A,TITAN!L$18,클래스매출!$C:$C,TITAN!$D21)/10^6)+(SUMIFS(타이탄매출!$N:$N,타이탄매출!$B:$B,TITAN!L$18,타이탄매출!$C:$C,TITAN!$D29)/10^6+SUMIFS(클래스매출!$J:$J,클래스매출!$A:$A,TITAN!L$18,클래스매출!$C:$C,TITAN!$D29)/10^6)) -> -106.17016
L17: =L20-L21-L29 -> 0
L18: 2024A | M18: 2025 1H | N18: 2025 2H | O18: 2025E | P18: 2026F | Q18: 2027F | R18: 2028F | S18: 2029F | T18: 2030F
B19: Revenue | L19: =L20+L34+L35 -> 11203.459 | M19: =M20+M34+M35 -> 17504.878 | N19: =N20+N34+N35 -> 17577.197 | O19: =O20+O34+O35 -> 35082.076 | P19: =P20+P34+P35 -> 37812.47 | Q19: =Q20+Q34+Q35 -> 40682.35 | R19: =R20+R34+R35 -> 43771.909 | S19: =S20+S34+S35 -> 46881.275 | T19: =T20+T34+T35 -> 50120.726
C20: 용역매출(강의매출) | L20: =연결정산표!F98/10^6 -> 11192.304 | M20: =M21+M29 -> 17501.106 | N20: =N21+N29 -> 17577.197 | O20: =O21+O29 -> 35078.303 | P20: =P21+P29 -> 37812.47 | Q20: =Q21+Q29 -> 40682.35 | R20: =R21+R29 -> 43771.909 | S20: =S21+S29 -> 46881.275 | T20: =T21+T29 -> 50120.726
D21: 부업 | L21: =SUMIFS(타이탄매출!$N:$N,타이탄매출!$B:$B,TITAN!L$18,타이탄매출!$C:$C,TITAN!$D21)/10^6+SUMIFS(클래스매출!$K:$K,클래스매출!$A:$A,TITAN!L$18,클래스매출!$C:$C,TITAN!$D21)/10^6+(연결정산표!F98/10^6-(SUMIFS(타이탄매출!$N:$N,타이탄매출!$B:$B,TITAN!L$18,타이탄매출!$C:$C,TITAN!$D21)/10^6+SUMIFS(클래스매출!$K:$K,클래스매출!$A:$A,TITAN!L$18,클래스매출!$C:$C,TITAN!$D21)/10^6)-(SUMIFS(타이탄매출!$N:$N,타이탄매출!$B:$B,TITAN!L$18,타이탄매출!$C:$C,TITAN!$D29)/10^6+SUMIFS(클래스매출!$K:$K,클래스매출!$A:$A,TITAN!L$18,클래스매출!$C:$C,TITAN!$D29)/10^6))*(SUMIFS(타이탄매출!$N:$N,타이탄매출!$B:$B,TITAN!L$18,타이탄매출!$C:$C,TITAN!$D21)/10^6+SUMIFS(클래스매출!$K:$K,클래스매출!$A:$A,TITAN!L$18,클래스매출!$C:$C,TITAN!$D21)/10^6)/((SUMIFS(타이탄매출!$N:$N,타이탄매출!$B:$B,TITAN!L$18,타이탄매출!$C:$C,TITAN!$D21)/10^6+SUMIFS(클래스매출!$K:$K,클래스매출!$A:$A,TITAN!L$18,클래스매출!$C:$C,TITAN!$D21)/10^6)+(SUMIFS(타이탄매출!$N:$N,타이탄매출!$B:$B,TITAN!L$18,타이탄매출!$C:$C,TITAN!$D29)/10^6+SUMIFS(클래스매출!$K:$K,클래스매출!$A:$A,TITAN!L$18,클래스매출!$C:$C,TITAN!$D29)/10^6)) -> 8654.2413 | M21: =연결정산표!U98/10^6 -> 17501.106 | N21: =N22*N28 -> 17577.197 | O21: =O22*O28 -> 35078.303 | P21: =P22*P28 -> 37812.47 | Q21: =Q22*Q28 -> 40682.35 | R21: =R22*R28 -> 43771.909 | S21: =S22*S28 -> 46881.275 | T21: =T22*T28 -> 50120.726
E22: 결제 건수 | L22: =SUMIFS(타이탄매출!$L$4:$L$131,타이탄매출!$B$4:$B$131,TITAN!L$18,타이탄매출!$C$4:$C$131,TITAN!$D21)+SUMIFS(클래스매출!$T:$T,클래스매출!$A:$A,TITAN!L$18,클래스매출!$C:$C,TITAN!$D21) -> 4002 | M22: =SUMIFS(타이탄매출!$L$4:$L$131,타이탄매출!$B$4:$B$131,TITAN!M$18,타이탄매출!$C$4:$C$131,TITAN!$D21) -> 6734 | N22: =N23*N24 -> 6763.2783 | O22: =N22+M22 -> 13497.278 | P22: =P23*P24 -> 14311.214 | Q22: =Q23*Q24 -> 15125.15 | R22: =R23*R24 -> 15939.085 | S22: =S23*S24 -> 16753.021 | T22: =T23*T24 -> 17566.957
F23: 강의 수 | L23: =COUNTIFS(타이탄매출!$B$4:$B$131,L$18,타이탄매출!$C$4:$C$131,$D21)+COUNTIFS(클래스매출!$A:$A,TITAN!L$18,클래스매출!$C:$C,TITAN!$D21) -> 65 | M23: =COUNTIFS(타이탄매출!$B$4:$B$131,M$18,타이탄매출!$C$4:$C$131,$D21) -> 46 | N23: ='Key Assumption'!N23 -> 46.2 | O23: =N23+M23 -> 92.2 | P23: ='Key Assumption'!P23 -> 97.76 | Q23: ='Key Assumption'!Q23 -> 103.32 | R23: ='Key Assumption'!R23 -> 108.88 | S23: ='Key Assumption'!S23 -> 114.44 | T23: ='Key Assumption'!T23 -> 120
F24: 강의당 결제건수 | L24: =L22/L23 -> 61.569231 | M24: =M22/M23 -> 146.3913 | N24: =N25*N27 -> 146.3913 | O24: =O22/O23 -> 146.3913 | P24: =P25*P27 -> 146.3913 | Q24: =Q25*Q27 -> 146.3913 | R24: =R25*R27 -> 146.3913 | S24: =S25*S27 -> 146.3913 | T24: =T25*T27 -> 146.3913
G25: 강의당 신규 유입 수(톡방) | L25: =SUMIFS(타이탄매출!$J:$J,타이탄매출!$B:$B,TITAN!L$18,타이탄매출!$C:$C,TITAN!$D21)/COUNTIFS(타이탄매출!$B:$B,TITAN!L$18,타이탄매출!$C:$C,TITAN!D$21,타이탄매출!$J:$J,">0")+SUMIFS(클래스매출!$R:$R,클래스매출!$A:$A,TITAN!L$18,클래스매출!$C:$C,TITAN!$D21)/COUNTIFS(클래스매출!$A:$A,TITAN!L$18,클래스매출!$C:$C,TITAN!$D21,클래스매출!$R:$R,">0") -> 2085.0067 | M25: =SUMIFS(타이탄매출!$J:$J,타이탄매출!$B:$B,TITAN!M$18,타이탄매출!$C:$C,TITAN!$D21)/COUNTIFS(타이탄매출!$B:$B,TITAN!M$18,타이탄매출!$J:$J,">0",타이탄매출!$C:$C,TITAN!$D21) -> 4473.8696 | N25: ='Key Assumption'!N24 -> 4473.8696 | O25: ='Key Assumption'!O24 -> 4473.8696 | P25: ='Key Assumption'!P24 -> 4473.8696 | Q25: ='Key Assumption'!Q24 -> 4473.8696 | R25: ='Key Assumption'!R24 -> 4473.8696 | S25: ='Key Assumption'!S24 -> 4473.8696 | T25: ='Key Assumption'!T24 -> 4473.8696
G26: CPM | L26: =L75 -> 8.2386225 | M26: =M75 -> 10.364051 | N26: =N75 -> 10.364051 | O26: =O75 -> 10.364051 | P26: =P75 -> 10.536485 | Q26: =Q75 -> 10.726142 | R26: =R75 -> 10.951391 | S26: =S75 -> 11.159467 | T26: =T75 -> 11.377792
G27: 유료 전환율 | L27: =L24/(L25) -> 0.029529513 | M27: =M24/(M25) -> 0.032721406 | N27: ='Key Assumption'!N25 -> 0.032721406 | O27: ='Key Assumption'!O25 -> 0.032721406 | P27: ='Key Assumption'!P25 -> 0.032721406 | Q27: ='Key Assumption'!Q25 -> 0.032721406 | R27: ='Key Assumption'!R25 -> 0.032721406 | S27: ='Key Assumption'!S25 -> 0.032721406 | T27: ='Key Assumption'!T25 -> 0.032721406
E28: 건당결제액 | L28: =L21/L22 -> 2.1624791 | M28: =M21/M22 -> 2.5989168 | N28: =M28 -> 2.5989168 | O28: =N28 -> 2.5989168 | P28: =O28*(1+'Key Assumption'!P$12) -> 2.6421567 | Q28: =P28*(1+'Key Assumption'!Q$12) -> 2.6897156 | R28: =Q28*(1+'Key Assumption'!R$12) -> 2.7461996 | S28: =R28*(1+'Key Assumption'!S$12) -> 2.7983774 | T28: =S28*(1+'Key Assumption'!T$12) -> 2.8531252
D29: 투자 | L29: =SUMIFS(타이탄매출!$N:$N,타이탄매출!$B:$B,TITAN!L$18,타이탄매출!$C:$C,TITAN!$D29)/10^6+SUMIFS(클래스매출!$K:$K,클래스매출!$A:$A,TITAN!L$18,클래스매출!$C:$C,TITAN!$D29)/10^6+(연결정산표!F98/10^6-(SUMIFS(타이탄매출!$N:$N,타이탄매출!$B:$B,TITAN!L$18,타이탄매출!$C:$C,TITAN!$D21)/10^6+SUMIFS(클래스매출!$K:$K,클래스매출!$A:$A,TITAN!L$18,클래스매출!$C:$C,TITAN!$D21)/10^6)-(SUMIFS(타이탄매출!$N:$N,타이탄매출!$B:$B,TITAN!L$18,타이탄매출!$C:$C,TITAN!$D29)/10^6+SUMIFS(클래스매출!$K:$K,클래스매출!$A:$A,TITAN!L$18,클래스매출!$C:$C,TITAN!$D29)/10^6))*(SUMIFS(타이탄매출!$N:$N,타이탄매출!$B:$B,TITAN!L$18,타이탄매출!$C:$C,TITAN!$D29)/10^6+SUMIFS(클래스매출!$K:$K,클래스매출!$A:$A,TITAN!L$18,클래스매출!$C:$C,TITAN!$D29)/10^6)/((SUMIFS(타이탄매출!$N:$N,타이탄매출!$B:$B,TITAN!L$18,타이탄매출!$C:$C,TITAN!$D21)/10^6+SUMIFS(클래스매출!$K:$K,클래스매출!$A:$A,TITAN!L$18,클래스매출!$C:$C,TITAN!$D21)/10^6)+(SUMIFS(타이탄매출!$N:$N,타이탄매출!$B:$B,TITAN!L$18,타이탄매출!$C:$C,TITAN!$D29)/10^6+SUMIFS(클래스매출!$K:$K,클래스매출!$A:$A,TITAN!L$18,클래스매출!$C:$C,TITAN!$D29)/10^6)) -> 2538.0631 | U29: 클래스 일부 타이탄 인식
E30: 결제 건수 | L30: =SUMIFS(클래스매출!$T:$T,클래스매출!$A:$A,TITAN!L$18,클래스매출!$C:$C,TITAN!$D29) -> 911
F31: 강의 수 | L31: =COUNTIFS(클래스매출!$A:$A,TITAN!L$18,클래스매출!$C:$C,TITAN!$D29) -> 10
F32: 강의당 결제건수 | L32: =L30/L31 -> 91.1
E33: 건당결제액 | L33: =L29/L30 -> 2.7860188
C34: 상품매출 | L34: =연결정산표!F97/10^6 -> 11.154544 | M34: 0 | N34: 0 | O34: =N34+M34 -> 0 | P34: 0 | Q34: 0 | R34: 0 | S34: 0 | T34: 0
C35: 임대료매출 | L35: 0 | M35: =연결정산표!U100/10^6 -> 3.772728 | N35: 0 | O35: =N35+M35 -> 3.772728 | P35: 0 | Q35: 0 | R35: 0 | S35: 0 | T35: 0 | U35: 향후 미발생
A38: 3. Operating Expense
L40: 2024A | M40: 2025 1H | N40: 2025 2H | O40: 2025E | P40: 2026F | Q40: 2027F | R40: 2028F | S40: 2029F | T40: 2030F
B41: Operating Expense | L41: =L43+L44+L45+L46 -> 7805.3692 | M41: =M43+M44+M45+M46 -> 10871.796 | N41: =N43+N44+N45+N46 -> 12636.466 | O41: =O43+O44+O45+O46 -> 23508.262 | P41: =P43+P44+P45+P46 -> 25900.887 | Q41: =Q43+Q44+Q45+Q46 -> 26116.725 | R41: =R43+R44+R45+R46 -> 27996.971 | S41: =S43+S44+S45+S46 -> 29882.534 | T41: =T43+T44+T45+T46 -> 31848.718
B42: % of Revenue | L42: =L41/L$19 -> 0.6966928 | M42: =M41/M$19 -> 0.62107235 | N42: =N41/N$19 -> 0.71891242 | O42: =O41/O$19 -> 0.67009323 | P42: =P41/P$19 -> 0.68498268 | Q42: =Q41/Q$19 -> 0.64196697 | R42: =R41/R$19 -> 0.63961046 | S42: =S41/S$19 -> 0.63740873 | T42: =T41/T$19 -> 0.63544008
C43: 인건비 | L43: =L49 -> 646.27145 | M43: =M49 -> 581.34672 | N43: =N49 -> 643.12573 | O43: =O49 -> 1224.4724 | P43: =P49 -> 1995.7352 | Q43: =Q49 -> 2143.1634 | R43: =R49 -> 2312.8469 | S43: =S49 -> 2479.1937 | T43: =T49 -> 2653.0773
C44: 변동비 | L44: =L62 -> 6247.7291 | M44: =M62 -> 9389.8284 | N44: =N62 -> 11088.007 | O44: =O62 -> 20477.835 | P44: =P62 -> 22082.324 | Q44: =Q62 -> 22127.256 | R44: =R62 -> 23807.677 | S44: =S62 -> 25498.871 | T44: =T62 -> 27260.819
C45: 고정비 | L45: =L86 -> 902.64485 | M45: =M86 -> 900.62095 | N45: =N86 -> 905.33322 | O45: =O86 -> 1805.9542 | P45: =P86 -> 1822.8277 | Q45: =Q86 -> 1846.3053 | R45: =R86 -> 1876.447 | S45: =S86 -> 1904.4692 | T45: =T86 -> 1934.8223
C46: 기타 | L46: =연결정산표!F101/10^6 -> 8.723845 | M46: 0 | N46: 0 | O46: 0 | P46: 0 | Q46: 0 | R46: 0 | S46: 0 | T46: 0
L48: 2024A | M48: 2025 1H | N48: 2025 2H | O48: 2025E | P48: 2026F | Q48: 2027F | R48: 2028F | S48: 2029F | T48: 2030F
B49: 인건비 | L49: =L51+L54+L56+L58 -> 646.27145 | M49: =M51+M54+M56+M58 -> 581.34672 | N49: =N51+N54+N56+N58 -> 643.12573 | O49: =O51+O54+O56+O58 -> 1224.4724 | P49: =P51+P54+P56+P58 -> 1995.7352 | Q49: =Q51+Q54+Q56+Q58 -> 2143.1634 | R49: =R51+R54+R56+R58 -> 2312.8469 | S49: =S51+S54+S56+S58 -> 2479.1937 | T49: =T51+T54+T56+T58 -> 2653.0773
B50: % of Revenue | L50: =L49/L$19 -> 0.057684993 | M50: =M49/M$19 -> 0.033210555 | N50: =N49/N$19 -> 0.036588639 | O50: =O49/O$19 -> 0.034903078 | P50: =P49/P$19 -> 0.052779816 | Q50: =Q49/Q$19 -> 0.052680424 | R50: =R49/R$19 -> 0.052838612 | S50: =S49/S$19 -> 0.052882387 | T50: =T49/T$19 -> 0.052933737 | U50: 3% 타겟
C51: 급여 | L51: =연결정산표!F109/10^6 -> 501.06186 | M51: =연결정산표!U109/10^6 -> 412.75305 | N51: =N52*N53/2 -> 511.64181 | O51: =N51+M51 -> 924.39486 | P51: =P52*P53 -> 1506.6467 | Q51: =Q52*Q53 -> 1617.9452 | R51: =R52*R53 -> 1746.0449 | S51: =S52*S53 -> 1871.6256 | T51: =T52*T53 -> 2002.8961
D52: 인원 수 | L52: =L51/L53 -> 14.567409 | M52: =HR!C8 -> 24 | N52: =AVERAGE(HR!B11:G11) -> 29.75 | O52: =O51/O53 -> 26.875 | P52: =41+2 -> 43 | Q52: =P52+2 -> 45 | R52: =Q52+2 -> 47 | S52: =R52+2 -> 49 | T52: =S52+2 -> 51 | U52: 2026년초까지 41명까지 채용
D53: 평균급여 | L53: =M53 -> 34.396088 | M53: =M51/M52*2 -> 34.396088 | N53: =M53 -> 34.396088 | O53: =M53 -> 34.396088 | P53: =O53*(1+'Key Assumption'!P$14) -> 35.038296 | Q53: =P53*(1+'Key Assumption'!Q$14) -> 35.954337 | R53: =Q53*(1+'Key Assumption'!R$14) -> 37.14989 | S53: =R53*(1+'Key Assumption'!S$14) -> 38.19644 | T53: =S53*(1+'Key Assumption'!T$14) -> 39.272472
C54: 상여 | L54: =연결정산표!F110/10^6 -> 32.267745 | M54: =연결정산표!U110/10^6 -> 62.522608 | N54: 0 | O54: =N54+M54 -> 62.522608 | P54: =P55*P$51 -> 101.90394 | Q54: =Q55*Q$51 -> 109.43175 | R54: =R55*R$51 -> 118.09594 | S54: =S55*S$51 -> 126.58975 | T54: =T55*T$51 -> 135.46839
D55: % of 급여 | I55: =O55 -> 0.067636257 | L55: =L54/L$51 -> 0.064398725 | M55: =M54/M$51 -> 0.15147703 | N55: =N54/N$51 -> 0 | O55: =O54/O$51 -> 0.067636257 | P55: =$I55 -> 0.067636257 | Q55: =$I55 -> 0.067636257 | R55: =$I55 -> 0.067636257 | S55: =$I55 -> 0.067636257 | T55: =$I55 -> 0.067636257
C56: 퇴직급여 | L56: =연결정산표!F112/10^6 -> 46.187144 | M56: =연결정산표!U112/10^6 -> 45.841642 | N56: =N57*N$51 -> 56.824535 | O56: =N56+M56 -> 102.66618 | P56: =P57*P$51 -> 167.33288 | Q56: =Q57*Q$51 -> 179.69404 | R56: =R57*R$51 -> 193.92119 | S56: =S57*S$51 -> 207.86857 | T56: =T57*T$51 -> 222.44789
D57: % of 급여 | I57: =M57 -> 0.11106312 | L57: =L56/L$51 -> 0.092178526 | M57: =M56/M$51 -> 0.11106312 | N57: =$I57 -> 0.11106312 | O57: =$I57 -> 0.11106312 | P57: =$I57 -> 0.11106312 | Q57: =$I57 -> 0.11106312 | R57: =$I57 -> 0.11106312 | S57: =$I57 -> 0.11106312 | T57: =$I57 -> 0.11106312
C58: 복리후생비 | L58: =연결정산표!F113/10^6 -> 66.7547 | M58: =연결정산표!U113/10^6 -> 60.229419 | N58: =N59*N$51 -> 74.659384 | O58: =N58+M58 -> 134.8888 | P58: =P59*P$51 -> 219.85169 | Q58: =Q59*Q$51 -> 236.09249 | R58: =R59*R$51 -> 254.78495 | S58: =S59*S$51 -> 273.10984 | T58: =T59*T$51 -> 292.26499
D59: % of 급여 | I59: =M59 -> 0.1459212 | L59: =L58/L$51 -> 0.13322646 | M59: =M58/M$51 -> 0.1459212 | N59: =$I59 -> 0.1459212 | O59: =$I59 -> 0.1459212 | P59: =$I59 -> 0.1459212 | Q59: =$I59 -> 0.1459212 | R59: =$I59 -> 0.1459212 | S59: =$I59 -> 0.1459212 | T59: =$I59 -> 0.1459212
M60: =(M65-1300+2760)/(M20-M67) -> 0.42359814
L61: 2024A | M61: 2025 1H | N61: 2025 2H | O61: 2025E | P61: 2026F | Q61: 2027F | R61: 2028F | S61: 2029F | T61: 2030F | U61: pg수수료 제외한 50%
B62: 변동비 | L62: =L64+L71+L78 -> 6247.7291 | M62: =M64+M71+M78 -> 9389.8284 | N62: =N64+N71+N78 -> 11088.007 | O62: =O64+O71+O78 -> 20477.835 | P62: =P64+P71+P78 -> 22082.324 | Q62: =Q64+Q71+Q78 -> 22127.256 | R62: =R64+R71+R78 -> 23807.677 | S62: =S64+S71+S78 -> 25498.871 | T62: =T64+T71+T78 -> 27260.819
B63: % of Revenue | L63: =L62/L$19 -> 0.55766073 | M63: =M62/M$19 -> 0.53641209 | N63: =N62/N$19 -> 0.63081766 | O63: =O62/O$19 -> 0.58371218 | P63: =P62/P$19 -> 0.58399581 | Q63: =Q62/Q$19 -> 0.5439031 | R63: =R62/R$19 -> 0.5439031 | S63: =S62/S$19 -> 0.5439031 | T63: =T62/T$19 -> 0.5439031
C64: 지급수수료(변동) | L64: =L65+L67++L69 -> 4525.0097 | M64: =M65+M67++M69 -> 6800.0647 | N64: =N65+N67++N69 -> 8486.9831 | O64: =O65+O67++O69 -> 15287.048 | P64: =P65+P67++P69 -> 17639.017 | Q64: =Q65+Q67++Q69 -> 18586.225 | R64: =R65+R67++R69 -> 19997.728 | S64: =S65+S67++S69 -> 21418.279 | T64: =T65+T67++T69 -> 22898.262
D65: 강의료 | L65: =비용취합!B4/10^6+비용취합!B6/10^6 -> 3949.2337 | M65: =비용취합!C4/10^6+비용취합!C6/10^6 -> 5483.8134 | N65: =(N$20-N$67)*N66 -> 6755.9751 | O65: =N65+M65 -> 12239.788 | P65: =(P$20-P$67)*P66 -> 14354.545 | Q65: =(Q$20-Q$67)*Q66 -> 15052.47 | R65: =(R$20-R$67)*R66 -> 16195.606 | S65: =(S$20-S$67)*S66 -> 17346.072 | T65: =(T$20-T$67)*T66 -> 18544.669
E66: % of 매출액 | I66: 0.4 | L66: =L65/L$20 -> 0.35285259 | M66: =M65/M$20 -> 0.31334097 | N66: =M83 -> 0.42080999 | O66: =O65/O$20 -> 0.34892761 | P66: =AVERAGE(N66,Q66) -> 0.410405 | Q66: =$I66 -> 0.4 | R66: =$I66 -> 0.4 | S66: =$I66 -> 0.4 | T66: =$I66 -> 0.4 | U66: 정산률 5대5 -> 6대4 변경(27년부터 하반기부터 전체 변경)
D67: PG수수료 | L67: =비용취합!B3/10^6 -> 575.77606 | M67: =비용취합!C3/10^6 -> 1108.6508 | N67: =O67-M67 -> 1522.5049 | O67: =O$19*O68 -> 2631.1557 | P67: =P$19*P68 -> 2835.9353 | Q67: =Q$19*Q68 -> 3051.1763 | R67: =R$19*R68 -> 3282.8932 | S67: =S$19*S68 -> 3516.0956 | T67: =T$19*T68 -> 3759.0545
E68: % of 매출액 | I68: 0.075 | L68: =L67/L$20 -> 0.051443924 | M68: =M67/M$20 -> 0.06334747 | N68: =$I68 -> 0.075 | O68: =I68 -> 0.075 | P68: =$I68 -> 0.075 | Q68: =$I68 -> 0.075 | R68: =$I68 -> 0.075 | S68: =$I68 -> 0.075 | T68: =$I68 -> 0.075
D69: 유튜브RS | L69: =비용취합!B8/10^6 -> 0 | M69: =비용취합!C8/10^6 -> 207.60049 | N69: =N$19*N70 -> 208.5031 | O69: =N69+M69 -> 416.10359 | P69: =P$19*P70 -> 448.53666 | Q69: =Q$19*Q70 -> 482.57956 | R69: =R$19*R70 -> 519.22833 | S69: =S$19*S70 -> 556.11204 | T69: =T$19*T70 -> 594.53886 | U69: 레드락컴퍼니
E70: % of 매출액 | I70: =M70 -> 0.011862136 | L70: =L69/L$20 -> 0 | M70: =M69/M$20 -> 0.011862136 | N70: =$I70 -> 0.011862136 | O70: =O69/O$20 -> 0.011862136 | P70: =$I70 -> 0.011862136 | Q70: =$I70 -> 0.011862136 | R70: =$I70 -> 0.011862136 | S70: =$I70 -> 0.011862136 | T70: =$I70 -> 0.011862136
C71: 광고선전비 | L71: =연결정산표!F131/10^6 -> 1288.3187 | M71: =연결정산표!U131/10^6 -> 2132.901 | N71: =N73*N74*N77 -> 2142.1745 | O71: =N71+M71 -> 4275.0755 | P71: =P73*P74*P77 -> 3456.2212 | Q71: =Q73*Q74*Q77 -> 2479.027 | R71: =R73*R74*R77 -> 2667.2929 | S71: =S73*S74*S77 -> 2856.7657 | T71: =T73*T74*T77 -> 3054.1655
D72: % of 매출액 | L72: =L71/(L20-L67) -> 0.12135028 | M72: =M71/(M20-M67) -> 0.1301148 | N72: =N71/(N20-N67) -> 0.1334298 | O72: =O71/(O20-O67) -> 0.13175505 | P72: =P71/(P20-P67) -> 0.098815425 | Q72: =Q71/(Q20-Q67) -> 0.06587695 | R72: =R71/(R20-R67) -> 0.06587695 | S72: =S71/(S20-S67) -> 0.06587695 | T72: =T71/(T20-T67) -> 0.06587695
D73: 강의수 | L73: =L31+L23 -> 75 | M73: =M31+M23 -> 46 | N73: =N23 -> 46.2 | O73: =O23 -> 92.2 | P73: =P23 -> 97.76 | Q73: =Q23 -> 103.32 | R73: =R23 -> 108.88 | S73: =S23 -> 114.44 | T73: =T23 -> 120
D74: 강의당 광고비 | L74: =L71/L73 -> 17.177583 | M74: =M71/M73 -> 46.367413 | N74: =N75*N76/1000 -> 46.367413 | O74: =O75*O76/1000 -> 46.367413 | P74: =P75*P76/1000 -> 47.138859 | Q74: =Q75*Q76/1000 -> 47.987359 | R74: =R75*R76/1000 -> 48.995093 | S74: =S75*S76/1000 -> 49.926 | T74: =T75*T76/1000 -> 50.902759
E75: CPM(백만원) | L75: =L74*10^6/(L76)*1000/10^6 -> 8.2386225 | M75: =M74*10^6/(M76)*1000/10^6 -> 10.364051 | N75: =M75 -> 10.364051 | O75: =N75 -> 10.364051 | P75: =O75*(1+'Key Assumption'!P$12) -> 10.536485 | Q75: =P75*(1+'Key Assumption'!Q$12) -> 10.726142 | R75: =Q75*(1+'Key Assumption'!R$12) -> 10.951391 | S75: =R75*(1+'Key Assumption'!S$12) -> 11.159467 | T75: =S75*(1+'Key Assumption'!T$12) -> 11.377792
E76: 강의당 톡방 유입 수 | L76: =SUMIFS(타이탄매출!$J:$J,타이탄매출!$B:$B,TITAN!L$18,타이탄매출!$C:$C,TITAN!$D21)/COUNTIFS(타이탄매출!$B:$B,TITAN!L$18,타이탄매출!$C:$C,TITAN!D$21,타이탄매출!$J:$J,">0")+SUMIFS(클래스매출!$R:$R,클래스매출!$A:$A,TITAN!L$18,클래스매출!$C:$C,TITAN!$D21)/COUNTIFS(클래스매출!$A:$A,TITAN!L$18,클래스매출!$C:$C,TITAN!$D21,클래스매출!$R:$R,">0") -> 2085.0067 | M76: =SUMIFS(타이탄매출!$J:$J,타이탄매출!$B:$B,TITAN!M$18,타이탄매출!$C:$C,TITAN!$D21)/COUNTIFS(타이탄매출!$B:$B,TITAN!M$18,타이탄매출!$J:$J,">0",타이탄매출!$C:$C,TITAN!$D21) -> 4473.8696 | N76: =N25 -> 4473.8696 | O76: =O25 -> 4473.8696 | P76: =P25 -> 4473.8696 | Q76: =Q25 -> 4473.8696 | R76: =R25 -> 4473.8696 | S76: =S25 -> 4473.8696 | T76: =T25 -> 4473.8696
D77: 분담률 | I77: 0.5 | J77: =P61 -> 2026F | L77: 1 | M77: 1 | N77: 1 | O77: =O71/(O73*O74) -> 1 | P77: =AVERAGE(O77,Q77) -> 0.75 | Q77: =$I$77 -> 0.5 | R77: =$I$77 -> 0.5 | S77: =$I$77 -> 0.5 | T77: =$I$77 -> 0.5 | U77: 50% 광고비 강사 분담 체제 전환(2027년부터 전체적용))
C78: 외주용역비 | L78: =연결정산표!F135/10^6 -> 434.40067 | M78: =연결정산표!U135/10^6 -> 456.86266 | N78: =N79*N$20 -> 458.84902 | O78: =N78+M78 -> 915.71167 | P78: =P79*P$20 -> 987.08653 | Q78: =Q79*Q$20 -> 1062.0041 | R78: =R79*R$20 -> 1142.6564 | S78: =S79*S$20 -> 1223.8257 | T78: =T79*T$20 -> 1308.3909
D79: % of 매출액 | I79: =M79 -> 0.026104788 | L79: =L78/L$20 -> 0.038812442 | M79: =M78/M$20 -> 0.026104788 | N79: =$I79 -> 0.026104788 | O79: =O78/O$20 -> 0.026104788 | P79: =$I79 -> 0.026104788 | Q79: =$I79 -> 0.026104788 | R79: =$I79 -> 0.026104788 | S79: =$I79 -> 0.026104788 | T79: =$I79 -> 0.026104788
L80: =L71/(L20-L67) -> 0.12135028 | M80: =M71/(M20-M67) -> 0.1301148 | N80: =N71/(N20-N67) -> 0.1334298 | O80: =O71/(O20-O67) -> 0.13175505 | P80: =P71/(P20-P67) -> 0.098815425 | Q80: =Q71/(Q20-Q67) -> 0.06587695 | R80: =R71/(R20-R67) -> 0.06587695 | S80: =S71/(S20-S67) -> 0.06587695 | T80: =T71/(T20-T67) -> 0.06587695
L81: 2024A | M81: 2025 1H | N81: 2025 2H | O81: 2025E | P81: 2026F | Q81: 2027F | R81: 2028F | S81: 2029F | T81: 2030F
B82: Normalization_강의료 | L82: =강의료이월!D17/10^6 -> 1312.6978 | M82: =강의료이월!D39/10^6-L82 -> 1414.2954 | N82: =(N20-N67)*N83-N65 -> 0 | O82: =(O20-O67)*O83-O65 -> 1414.2954
C83: Normalized 정산율 | L83: =(L65+L82)/(L20-L67) -> 0.49563579 | M83: =(M65+M82)/(M20-M67) -> 0.42080999 | N83: =M83 -> 0.42080999 | O83: =N83 -> 0.42080999
L85: 2024A | M85: 2025 1H | N85: 2025 2H | O85: 2025E | P85: 2026F | Q85: 2027F | R85: 2028F | S85: 2029F | T85: 2030F
B86: 고정비 | L86: =SUM(L88:L97) -> 902.64485 | M86: =SUM(M88:M97) -> 900.62095 | N86: =SUM(N88:N97) -> 905.33322 | O86: =SUM(O88:O97) -> 1805.9542 | P86: =SUM(P88:P97) -> 1822.8277 | Q86: =SUM(Q88:Q97) -> 1846.3053 | R86: =SUM(R88:R97) -> 1876.447 | S86: =SUM(S88:S97) -> 1904.4692 | T86: =SUM(T88:T97) -> 1934.8223
B87: % of Revenue | L87: =L86/L$19 -> 0.080568408 | M87: =M86/M$19 -> 0.051449712 | N87: =N86/N$19 -> 0.051506119 | O87: =O86/O$19 -> 0.051477973 | P87: =P86/P$19 -> 0.04820705 | Q87: =Q86/Q$19 -> 0.045383446 | R87: =R86/R$19 -> 0.042868748 | S87: =S86/S$19 -> 0.040623239 | T87: =T86/T$19 -> 0.038603238
C88: 지급수수료(고정) | L88: =연결정산표!F130/10^6-TITAN!L64 -> 282.12414 | M88: =SUM(비용취합!C5,비용취합!C7)/10^6 -> 222.23875 | N88: =M88 -> 222.23875 | O88: =N88+M88 -> 444.47751 | P88: =O88*(1+'Key Assumption'!P$12) -> 451.87258 | Q88: =P88*(1+'Key Assumption'!Q$12) -> 460.00629 | R88: =Q88*(1+'Key Assumption'!R$12) -> 469.66642 | S88: =R88*(1+'Key Assumption'!S$12) -> 478.59008 | T88: =S88*(1+'Key Assumption'!T$12) -> 487.95328
C89: 여비교통비 | L89: =연결정산표!F114/10^6 -> 11.800834 | M89: =연결정산표!U114/10^6 -> 46.36312 | N89: =M89 -> 46.36312 | O89: =N89+M89 -> 92.72624 | P89: =O89*(1+'Key Assumption'!P$12) -> 94.26899 | Q89: =P89*(1+'Key Assumption'!Q$12) -> 95.965831 | R89: =Q89*(1+'Key Assumption'!R$12) -> 97.981114 | S89: =R89*(1+'Key Assumption'!S$12) -> 99.842755 | T89: =S89*(1+'Key Assumption'!T$12) -> 101.79609
C90: 접대비(기업업무추진비) | L90: =연결정산표!F115/10^6 -> 30.26846 | M90: =연결정산표!U115/10^6 -> 10.65975 | N90: =M90 -> 10.65975 | O90: =N90+M90 -> 21.3195 | P90: =O90*(1+'Key Assumption'!P$12) -> 21.674207 | Q90: =P90*(1+'Key Assumption'!Q$12) -> 22.064343 | R90: =Q90*(1+'Key Assumption'!R$12) -> 22.527694 | S90: =R90*(1+'Key Assumption'!S$12) -> 22.95572 | T90: =S90*(1+'Key Assumption'!T$12) -> 23.404829
C91: 감가상각비 | L91: =연결정산표!F120/10^6 -> 127.87806 | M91: =연결정산표!U120/10^6 -> 45.914015 | N91: =N109 -> 50.626289 | O91: =N91+M91 -> 96.540304 | P91: =P109 -> 84.973118 | Q91: =Q109 -> 77.169324 | R91: =R109 -> 70.15918 | S91: =S109 -> 63.861971 | T91: =T109 -> 58.205191
C92: 지급임차료 | L92: =연결정산표!F121/10^6 -> 49.312996 | M92: =연결정산표!U121/10^6 -> 49.812207 | N92: =M92 -> 49.812207 | O92: =N92+M92 -> 99.624414 | P92: =O92*(1+'Key Assumption'!P$12) -> 101.28193 | Q92: =P92*(1+'Key Assumption'!Q$12) -> 103.10501 | R92: =Q92*(1+'Key Assumption'!R$12) -> 105.27021 | S92: =R92*(1+'Key Assumption'!S$12) -> 107.27035 | T92: =S92*(1+'Key Assumption'!T$12) -> 109.369
C93: 보험료 | L93: =연결정산표!F123/10^6 -> 57.024687 | M93: =연결정산표!U123/10^6 -> 41.440246 | N93: =M93 -> 41.440246 | O93: =N93+M93 -> 82.880492 | P93: =O93*(1+'Key Assumption'!P$12) -> 84.259431 | Q93: =P93*(1+'Key Assumption'!Q$12) -> 85.776101 | R93: =Q93*(1+'Key Assumption'!R$12) -> 87.577399 | S93: =R93*(1+'Key Assumption'!S$12) -> 89.24137 | T93: =S93*(1+'Key Assumption'!T$12) -> 90.987299
C94: 소모품비 | L94: =연결정산표!F129/10^6 -> 199.65936 | M94: =연결정산표!U129/10^6 -> 345.40256 | N94: =M94 -> 345.40256 | O94: =N94+M94 -> 690.80513 | P94: =O94*(1+'Key Assumption'!P$12) -> 702.29852 | Q94: =P94*(1+'Key Assumption'!Q$12) -> 714.9399 | R94: =Q94*(1+'Key Assumption'!R$12) -> 729.95363 | S94: =R94*(1+'Key Assumption'!S$12) -> 743.82275 | T94: =S94*(1+'Key Assumption'!T$12) -> 758.375
C95: 건물관리비 | L95: =연결정산표!F132/10^6 -> 52.947444 | M95: =연결정산표!U132/10^6 -> 52.376322 | N95: =M95 -> 52.376322 | O95: =N95+M95 -> 104.75264 | P95: =O95*(1+'Key Assumption'!P$12) -> 106.49549 | Q95: =P95*(1+'Key Assumption'!Q$12) -> 108.4124 | R95: =Q95*(1+'Key Assumption'!R$12) -> 110.68906 | S95: =R95*(1+'Key Assumption'!S$12) -> 112.79216 | T95: =S95*(1+'Key Assumption'!T$12) -> 114.99884
C96: 리스료 | L96: =연결정산표!F134/10^6 -> 48.082017 | M96: =연결정산표!U134/10^6 -> 42.200597 | N96: =M96 -> 42.200597 | O96: =N96+M96 -> 84.401194 | P96: =O96*(1+'Key Assumption'!P$12) -> 85.805434 | Q96: =P96*(1+'Key Assumption'!Q$12) -> 87.349932 | R96: =Q96*(1+'Key Assumption'!R$12) -> 89.184281 | S96: =R96*(1+'Key Assumption'!S$12) -> 90.878782 | T96: =S96*(1+'Key Assumption'!T$12) -> 92.656746
C97: 기타고정비 | L97: =SUM(연결정산표!F116:F119,연결정산표!F122,연결정산표!F124,연결정산표!F125:F128,연결정산표!F137)/10^6 -> 43.546858 | M97: =SUM(연결정산표!U116:U119,연결정산표!U122,연결정산표!U124:U128,연결정산표!U137)/10^6 -> 44.213372 | N97: =M97 -> 44.213372 | O97: =N97+M97 -> 88.426744 | P97: =O97*(1+'Key Assumption'!P$12) -> 89.89796 | Q97: =P97*(1+'Key Assumption'!Q$12) -> 91.516123 | R97: =Q97*(1+'Key Assumption'!R$12) -> 93.437962 | S97: =R97*(1+'Key Assumption'!S$12) -> 95.213283 | T97: =S97*(1+'Key Assumption'!T$12) -> 97.076048
A100: 4. D&A
L102: 2024A | M102: 2025 1H | N102: 2025 2H | O102: 2025E | P102: 2026F | Q102: 2027F | R102: 2028F | S102: 2029F | T102: 2030F
B103: CAPEX | M103: =M105+M106 -> 42.7038 | N103: =N105+N106 -> 41.794002 | O103: =O105+O106 -> 84.497802 | P103: =P105+P106 -> 62.613702 | Q103: =Q105+Q106 -> 56.245857 | R103: =R105+R106 -> 50.525625 | S103: =S105+S106 -> 45.387144 | T103: =T105+T106 -> 40.771249
C104: 건물 | M104: 0 | N104: 0 | O104: =N104+M104 -> 0 | P104: 0 | Q104: 0 | R104: 0 | S104: 0 | T104: 0
C105: 비품 | M105: =연결정산표!U35/10^6-연결정산표!G35/10^6 -> 21.4958 | N105: =G128 -> 14.022264 | O105: =N105+M105 -> 35.518064 | P105: {=TRANSPOSE(G129:G133)} -> 21.00747 | Q105: 18.871 | R105: 16.95181 | S105: 15.227802 | T105: 13.679127
C106: 시설장치 | M106: =연결정산표!U37/10^6-연결정산표!F37/10^6 -> 21.208 | N106: =G135 -> 27.771738 | O106: =N106+M106 -> 48.979738 | P106: {=TRANSPOSE(G136:G140)} -> 41.606232 | Q106: 37.374857 | R106: 33.573816 | S106: 30.159342 | T106: 27.092122
L108: 2024A | M108: 2025 1H | N108: 2025 2H | O108: 2025E | P108: 2026F | Q108: 2027F | R108: 2028F | S108: 2029F | T108: 2030F
B109: D&A | L109: =L110+L111+L112 -> 127.87806 | M109: =M110+M111+M112 -> 45.914015 | N109: =N110+N111+N112 -> 50.626289 | O109: =O110+O111+O112 -> 96.540304 | P109: =P110+P111+P112 -> 84.973118 | Q109: =Q110+Q111+Q112 -> 77.169324 | R109: =R110+R111+R112 -> 70.15918 | S109: =S110+S111+S112 -> 63.861971 | T109: =T110+T111+T112 -> 58.205191
C110: 건물 | L110: =L116+L122 -> 8.240026 | M110: =M116+M122 -> 4.120013 | N110: =N116+N122 -> 4.120013 | O110: =N110+M110 -> 8.240026 | P110: =P116+P122 -> 8.240026 | Q110: =Q116+Q122 -> 8.240026 | R110: =R116+R122 -> 8.240026 | S110: =S116+S122 -> 8.240026 | T110: =T116+T122 -> 8.240026
C111: 비품 | L111: =L117+L123 -> 23.919396 | M111: =M117+M123 -> 14.022264 | N111: =N117+N123 -> 15.603274 | O111: =N111+M111 -> 29.625538 | P111: =P117+P123 -> 25.744655 | Q111: =Q117+Q123 -> 23.126411 | R111: =R117+R123 -> 20.774443 | S111: =S117+S123 -> 18.661672 | T111: =T117+T123 -> 16.76377
...

Sheet CLASS
A1: CLASS
A3: 1. Summary
L5: 2024A | M5: 2025 1H | N5: 2025 2H | O5: 2025E | P5: 2026F | Q5: 2027F | R5: 2028F | S5: 2029F | T5: 2030F
B6: Revenue | L6: =L20 -> 19.9 | M6: =M20 -> 10266.381 | N6: =N20 -> 16569.007 | O6: =O20 -> 26835.388 | P6: =P20 -> 32543.72 | Q6: =Q20 -> 34715.24 | R6: =R20 -> 37063.293 | S6: =S20 -> 39417.29 | T6: =T20 -> 41870.527
B7: Operating Expense | L7: =L42 -> 76.833572 | M7: =M42 -> 6468.495 | N7: =N42 -> 12303.422 | O7: =O42 -> 18771.917 | P7: =P42 -> 20780.481 | Q7: =Q42 -> 21363.142 | R7: =R42 -> 22769.727 | S7: =S42 -> 24174.58 | T7: =T42 -> 25632.359
B8: EBIT | L8: =L6-L7 -> -56.933572 | M8: =M6-M7 -> 3797.886 | N8: =N6-N7 -> 4265.5856 | O8: =O6-O7 -> 8063.4716 | P8: =P6-P7 -> 11763.24 | Q8: =Q6-Q7 -> 13352.098 | R8: =R6-R7 -> 14293.566 | S8: =S6-S7 -> 15242.711 | T8: =T6-T7 -> 16238.168
B9: EBIT % | L9: =L8/L6 -> -2.8609835 | M9: =M8/M6 -> 0.36993425 | N9: =N8/N6 -> 0.25744365 | O9: =O8/O6 -> 0.30047904 | P9: =P8/P6 -> 0.36145959 | Q9: =Q8/Q6 -> 0.38461777 | R9: =R8/R6 -> 0.38565289 | S9: =S8/S6 -> 0.38670113 | T9: =T8/T6 -> 0.38781857
B10: D&A | L10: =L109 -> 0 | M10: =M109 -> 9.980253 | N10: =N109 -> 22.238234 | O10: =O109 -> 32.218487 | P10: =P109 -> 43.978483 | Q10: =Q109 -> 42.895476 | R10: =R109 -> 42.600536 | S10: =S109 -> 43.149102 | T10: =T109 -> 37.29325
B11: EBITDA | L11: =L10+L8 -> -56.933572 | M11: =M10+M8 -> 3807.8663 | N11: =N10+N8 -> 4287.8239 | O11: =O10+O8 -> 8095.6901 | P11: =P10+P8 -> 11807.218 | Q11: =Q10+Q8 -> 13394.994 | R11: =R10+R8 -> 14336.167 | S11: =S10+S8 -> 15285.86 | T11: =T10+T8 -> 16275.461
B12: EBITDA % | L12: =L11/L6 -> -2.8609835 | M12: =M11/M6 -> 0.37090638 | N12: =N11/N6 -> 0.25878581 | O12: =O11/O6 -> 0.30167964 | P12: =P11/P6 -> 0.36281096 | Q12: =Q11/Q6 -> 0.38585341 | R12: =R11/R6 -> 0.38680229 | S12: =S11/S6 -> 0.3877958 | T12: =T11/T6 -> 0.38870925
B13: Normalized EBITDA | L13: =L11-L86 -> -56.933572 | M13: =M11-M86 -> 1987.2706 | N13: =N11-N86 -> 4287.8239 | O13: =O11-O86 -> 6275.0945 | P13: =P11-P86 -> 11807.218 | Q13: =Q11-Q86 -> 13394.994 | R13: =R11-R86 -> 14336.167 | S13: =S11-S86 -> 15285.86 | T13: =T11-T86 -> 16275.461
B14: Norm EBITDA % | L14: =L13/L6 -> -2.8609835 | M14: =M13/M6 -> 0.19357071 | N14: =N13/N6 -> 0.25878581 | O14: =O13/O6 -> 0.23383655 | P14: =P13/P6 -> 0.36281096 | Q14: =Q13/Q6 -> 0.38585341 | R14: =R13/R6 -> 0.38680229 | S14: =S13/S6 -> 0.3877958 | T14: =T13/T6 -> 0.38870925
M15: =(연결정산표_우모건제외!H140)/10^6=M8 -> TRUE
A17: 2. Revenue
L19: 2024A | M19: 2025 1H | N19: 2025 2H | O19: 2025E | P19: 2026F | Q19: 2027F | R19: 2028F | S19: 2029F | T19: 2030F | V19: =(연결정산표!T98/10^6-SUMIFS(클래스매출!$J:$J,클래스매출!$A:$A,CLASS!M$19,클래스매출!$C:$C,CLASS!$D22)/10^6-SUMIFS(클래스매출!$J:$J,클래스매출!$A:$A,CLASS!M$19,클래스매출!$C:$C,CLASS!$D29)/10^6)*(SUMIFS(클래스매출!$J:$J,클래스매출!$A:$A,CLASS!M$19,클래스매출!$C:$C,CLASS!$D22)/10^6)/(SUMIFS(클래스매출!$J:$J,클래스매출!$A:$A,CLASS!M$19,클래스매출!$C:$C,CLASS!$D22)/10^6+SUMIFS(클래스매출!$J:$J,클래스매출!$A:$A,CLASS!M$19,클래스매출!$C:$C,CLASS!$D29)/10^6) -> -701.01992
B20: Revenue | L20: =L21+L36 -> 19.9 | M20: =M21 -> 10266.381 | N20: =N21 -> 16569.007 | O20: =O21 -> 26835.388 | P20: =P21 -> 32543.72 | Q20: =Q21 -> 34715.24 | R20: =R21 -> 37063.293 | S20: =S21 -> 39417.29 | T20: =T21 -> 41870.527 | V20: =(연결정산표!T98/10^6-SUMIFS(클래스매출!$J:$J,클래스매출!$A:$A,CLASS!M$19,클래스매출!$C:$C,CLASS!$D22)/10^6-SUMIFS(클래스매출!$J:$J,클래스매출!$A:$A,CLASS!M$19,클래스매출!$C:$C,CLASS!$D29)/10^6)*(SUMIFS(클래스매출!$J:$J,클래스매출!$A:$A,CLASS!M$19,클래스매출!$C:$C,CLASS!$D29)/10^6)/(SUMIFS(클래스매출!$J:$J,클래스매출!$A:$A,CLASS!M$19,클래스매출!$C:$C,CLASS!$D22)/10^6+SUMIFS(클래스매출!$J:$J,클래스매출!$A:$A,CLASS!M$19,클래스매출!$C:$C,CLASS!$D29)/10^6) -> -321.50021
C21: 용역매출 | M21: =연결정산표!T98/10^6 -> 10266.381 | N21: =N22+N29 -> 16569.007 | O21: =O22+O29 -> 26835.388 | P21: =P22+P29 -> 32543.72 | Q21: =Q22+Q29 -> 34715.24 | R21: =R22+R29 -> 37063.293 | S21: =S22+S29 -> 39417.29 | T21: =T22+T29 -> 41870.527
D22: 부업 | M22: =SUMIFS(클래스매출!$K:$K,클래스매출!$A:$A,CLASS!M$19,클래스매출!$C:$C,CLASS!$D22)/10^6+(연결정산표!T98/10^6-SUMIFS(클래스매출!$K:$K,클래스매출!$A:$A,CLASS!M$19,클래스매출!$C:$C,CLASS!$D22)/10^6-SUMIFS(클래스매출!$K:$K,클래스매출!$A:$A,CLASS!M$19,클래스매출!$C:$C,CLASS!$D29)/10^6)*(SUMIFS(클래스매출!$K:$K,클래스매출!$A:$A,CLASS!M$19,클래스매출!$C:$C,CLASS!$D22)/10^6)/(SUMIFS(클래스매출!$K:$K,클래스매출!$A:$A,CLASS!M$19,클래스매출!$C:$C,CLASS!$D22)/10^6+SUMIFS(클래스매출!$K:$K,클래스매출!$A:$A,CLASS!M$19,클래스매출!$C:$C,CLASS!$D29)/10^6) -> 7012.7521 | N22: =N23*N28 -> 16243.644 | O22: =N22+M22 -> 23256.396 | P22: =P23*P28 -> 28905.182 | Q22: =Q23*Q28 -> 31011.208 | R22: =R23*R28 -> 33281.477 | S22: =S23*S28 -> 35563.62 | T22: =T23*T28 -> 37941.462
E23: 결제 건수 | M23: =SUMIFS(클래스매출!$T:$T,클래스매출!$A:$A,CLASS!M$19,클래스매출!$C:$C,CLASS!$D22) -> 2945 | N23: =N24*N25 -> 6821.5063 | O23: =N23+M23 -> 9766.5063 | P23: =P24*P25 -> 11940.055 | Q23: =Q24*Q25 -> 12583.502 | R23: =R24*R25 -> 13226.949 | S23: =S24*S25 -> 13870.396 | T23: =T24*T25 -> 14513.843
F24: 강의 수 | M24: =COUNTIFS(클래스매출!$A:$A,CLASS!M$19,클래스매출!$C:$C,$D22) -> 37 | N24: ='Key Assumption'!N28 -> 56.4 | O24: ='Key Assumption'!O28 -> 93.4 | P24: ='Key Assumption'!P28 -> 98.72 | Q24: ='Key Assumption'!Q28 -> 104.04 | R24: ='Key Assumption'!R28 -> 109.36 | S24: ='Key Assumption'!S28 -> 114.68 | T24: ='Key Assumption'!T28 -> 120
F25: 강의당 결제건수 | M25: =M23/M24 -> 79.594595 | N25: =N26*N27 -> 120.94869 | O25: =O23/O24 -> 104.56645 | P25: =P26*P27 -> 120.94869 | Q25: =Q26*Q27 -> 120.94869 | R25: =R26*R27 -> 120.94869 | S25: =S26*S27 -> 120.94869 | T25: =T26*T27 -> 120.94869
G26: 강의당 신규 유입 수(톡방) | M26: =SUMIFS(클래스매출!$R:$R,클래스매출!$A:$A,CLASS!M$19,클래스매출!$C:$C,CLASS!D$22)/COUNTIFS(클래스매출!$A:$A,CLASS!M$19,클래스매출!$C:$C,CLASS!$D22,클래스매출!$R:$R,">0") -> 2944.1892 | N26: ='Key Assumption'!N29 -> 4473.8696 | O26: =O25/O27 -> 3867.8934 | P26: ='Key Assumption'!P29 -> 4473.8696 | Q26: ='Key Assumption'!Q29 -> 4473.8696 | R26: ='Key Assumption'!R29 -> 4473.8696 | S26: ='Key Assumption'!S29 -> 4473.8696 | T26: ='Key Assumption'!T29 -> 4473.8696
G27: 유료 전환율 | M27: =M25/M26 -> 0.02703447 | N27: ='Key Assumption'!N30 -> 0.02703447 | O27: ='Key Assumption'!O30 -> 0.02703447 | P27: ='Key Assumption'!P30 -> 0.02703447 | Q27: ='Key Assumption'!Q30 -> 0.02703447 | R27: ='Key Assumption'!R30 -> 0.02703447 | S27: ='Key Assumption'!S30 -> 0.02703447 | T27: ='Key Assumption'!T30 -> 0.02703447
E28: 건당결제액 | M28: =M22/M23 -> 2.3812401 | N28: =M28 -> 2.3812401 | O28: =N28 -> 2.3812401 | P28: =O28*(1+'Key Assumption'!P$12) -> 2.4208584 | Q28: =P28*(1+'Key Assumption'!Q$12) -> 2.4644339 | R28: =Q28*(1+'Key Assumption'!R$12) -> 2.516187 | S28: =R28*(1+'Key Assumption'!S$12) -> 2.5639945 | T28: =S28*(1+'Key Assumption'!T$12) -> 2.6141568
D29: 투자 | M29: =SUMIFS(클래스매출!$K:$K,클래스매출!$A:$A,CLASS!M$19,클래스매출!$C:$C,CLASS!$D29)/10^6+(연결정산표!T98/10^6-SUMIFS(클래스매출!$K:$K,클래스매출!$A:$A,CLASS!M$19,클래스매출!$C:$C,CLASS!$D22)/10^6-SUMIFS(클래스매출!$K:$K,클래스매출!$A:$A,CLASS!M$19,클래스매출!$C:$C,CLASS!$D29)/10^6)*(SUMIFS(클래스매출!$K:$K,클래스매출!$A:$A,CLASS!M$19,클래스매출!$C:$C,CLASS!$D29)/10^6)/(SUMIFS(클래스매출!$K:$K,클래스매출!$A:$A,CLASS!M$19,클래스매출!$C:$C,CLASS!$D22)/10^6+SUMIFS(클래스매출!$K:$K,클래스매출!$A:$A,CLASS!M$19,클래스매출!$C:$C,CLASS!$D29)/10^6) -> 3253.629 | N29: =N30*N35 -> 325.3629 | O29: =N29+M29 -> 3578.9918 | P29: =P30*P35 -> 3638.538 | Q29: =Q30*Q35 -> 3704.0317 | R29: =R30*R35 -> 3781.8163 | S29: =S30*S35 -> 3853.6708 | T29: =T30*T35 -> 3929.0645
E30: 결제 건수 | M30: =SUMIFS(클래스매출!$T:$T,클래스매출!$A:$A,CLASS!M$19,클래스매출!$C:$C,CLASS!$D29) -> 1004 | N30: =N31*N32 -> 100.4 | O30: =N30+M30 -> 1104.4 | P30: =P31*P32 -> 1104.4 | Q30: =Q31*Q32 -> 1104.4 | R30: =R31*R32 -> 1104.4 | S30: =S31*S32 -> 1104.4 | T30: =T31*T32 -> 1104.4
F31: 강의 수 | M31: =COUNTIFS(클래스매출!$A:$A,CLASS!M$19,클래스매출!$C:$C,$D29) -> 10 | N31: ='Key Assumption'!N32 -> 1 | O31: ='Key Assumption'!O32 -> 11 | P31: ='Key Assumption'!P32 -> 11 | Q31: ='Key Assumption'!Q32 -> 11 | R31: ='Key Assumption'!R32 -> 11 | S31: ='Key Assumption'!S32 -> 11 | T31: ='Key Assumption'!T32 -> 11
F32: 강의당 결제건수 | M32: =M30/M31 -> 100.4 | N32: =N33*N34 -> 100.4 | O32: =O30/O31 -> 100.4 | P32: =P33*P34 -> 100.4 | Q32: =Q33*Q34 -> 100.4 | R32: =R33*R34 -> 100.4 | S32: =S33*S34 -> 100.4 | T32: =T33*T34 -> 100.4
G33: 강의당 신규 유입 수(톡방) | M33: =SUMIFS(클래스매출!$R:$R,클래스매출!$A:$A,CLASS!M$19,클래스매출!$C:$C,D$29)/COUNTIFS(클래스매출!$A:$A,CLASS!M$19,클래스매출!$C:$C,CLASS!$D29,클래스매출!$R:$R,">0") -> 3237.7 | N33: ='Key Assumption'!N33 -> 3237.7 | O33: =O32/O34 -> 3237.7 | P33: ='Key Assumption'!P33 -> 3237.7 | Q33: ='Key Assumption'!Q33 -> 3237.7 | R33: ='Key Assumption'!R33 -> 3237.7 | S33: ='Key Assumption'!S33 -> 3237.7 | T33: ='Key Assumption'!T33 -> 3237.7
G34: 유료 전환율 | M34: =M32/M33 -> 0.031009667 | N34: ='Key Assumption'!N34 -> 0.031009667 | O34: ='Key Assumption'!O34 -> 0.031009667 | P34: ='Key Assumption'!P34 -> 0.031009667 | Q34: ='Key Assumption'!Q34 -> 0.031009667 | R34: ='Key Assumption'!R34 -> 0.031009667 | S34: ='Key Assumption'!S34 -> 0.031009667 | T34: ='Key Assumption'!T34 -> 0.031009667
E35: 건당결제액 | M35: =M29/M30 -> 3.2406663 | N35: =M35 -> 3.2406663 | O35: =N35 -> 3.2406663 | P35: =O35*(1+'Key Assumption'!P$12) -> 3.2945835 | Q35: =P35*(1+'Key Assumption'!Q$12) -> 3.353886 | R35: =Q35*(1+'Key Assumption'!R$12) -> 3.4243176 | S35: =R35*(1+'Key Assumption'!S$12) -> 3.4893796 | T35: =S35*(1+'Key Assumption'!T$12) -> 3.5576463
C36: 기타 | L36: =연결정산표!E98/10^6 -> 19.9 | M36: 0 | N36: 0 | O36: 0 | P36: 0 | Q36: 0 | R36: 0 | S36: 0 | T36: 0
A39: 3. Operating Expense
L40: =연결정산표!E108/10^6=L42 -> TRUE | M40: =연결정산표!T108/10^6=M42 -> TRUE
L41: 2024A | M41: 2025 1H | N41: 2025 2H | O41: 2025E | P41: 2026F | Q41: 2027F | R41: 2028F | S41: 2029F | T41: 2030F
B42: Operating Expense | L42: =L44+L45+L46 -> 76.833572 | M42: =M44+M45+M46 -> 6468.495 | N42: =N44+N45+N46 -> 12303.422 | O42: =O44+O45+O46 -> 18771.917 | P42: =P44+P45+P46 -> 20780.481 | Q42: =Q44+Q45+Q46 -> 21363.142 | R42: =R44+R45+R46 -> 22769.727 | S42: =S44+S45+S46 -> 24174.58 | T42: =T44+T45+T46 -> 25632.359
B43: % of Revenue | L43: =L42/L20 -> 3.8609835 | M43: =M42/M20 -> 0.63006575 | N43: =N42/N20 -> 0.74255635 | O43: =O42/O20 -> 0.69952096 | P43: =P42/P20 -> 0.63854041 | Q43: =Q42/Q20 -> 0.61538223 | R43: =R42/R20 -> 0.61434711 | S43: =S42/S20 -> 0.61329887 | T43: =T42/T20 -> 0.61218143
C44: 인건비 | L44: =L49 -> 18.623039 | M44: =M49 -> 309.49833 | N44: =N49 -> 738.17506 | O44: =O49 -> 1047.6734 | P44: =P49 -> 1886.7181 | Q44: =Q49 -> 1994.7124 | R44: =R49 -> 2121.6594 | S44: =S49 -> 2243.7552 | T44: =T49 -> 2371.0464
C45: 변동비 | L45: =L62 -> 43.055839 | M45: =M62 -> 5821.6407 | N45: =N62 -> 11215.632 | O45: =O62 -> 17037.273 | P45: =P62 -> 18184.139 | Q45: =Q62 -> 18647.907 | R45: =R62 -> 19913.61 | S45: =S62 -> 21182.673 | T45: =T62 -> 22505.224
C46: 고정비 | L46: =L90 -> 15.154694 | M46: =M90 -> 337.35601 | N46: =N90 -> 349.61399 | O46: =O90 -> 686.97 | P46: =P90 -> 709.62355 | Q46: =Q90 -> 720.52215 | R46: =R90 -> 734.45737 | S46: =S90 -> 748.15122 | T46: =T90 -> 756.08812
L48: 2024A | M48: 2025 1H | N48: 2025 2H | O48: 2025E | P48: 2026F | Q48: 2027F | R48: 2028F | S48: 2029F | T48: 2030F
B49: 인건비 | L49: =L51+L54+L56+L58 -> 18.623039 | M49: =M51+M54+M56+M58 -> 309.49833 | N49: =N51+N54+N56+N58 -> 738.17506 | O49: =O51+O54+O56+O58 -> 1047.6734 | P49: =P51+P54+P56+P58 -> 1886.7181 | Q49: =Q51+Q54+Q56+Q58 -> 1994.7124 | R49: =R51+R54+R56+R58 -> 2121.6594 | S49: =S51+S54+S56+S58 -> 2243.7552 | T49: =T51+T54+T56+T58 -> 2371.0464
B50: % of Revenue | L50: =L49/L$20 -> 0.93583111 | M50: =M49/M$20 -> 0.03014678 | N50: =N49/N$20 -> 0.044551557 | O50: =O49/O$20 -> 0.039040739 | P50: =P49/P$20 -> 0.057974873 | Q50: =Q49/Q$20 -> 0.057459272 | R50: =R49/R$20 -> 0.057244224 | S50: =S49/S$20 -> 0.056923122 | T50: =T49/T$20 -> 0.056628053
C51: 급여 | L51: =연결정산표!E109/10^6 -> 17.82422 | M51: =연결정산표!T109/10^6 -> 251.62647 | N51: =N52*N53/2 -> 553.57823 | O51: =N51+M51 -> 805.2047 | P51: =P52*P53 -> 1450.0647 | Q51: =Q52*Q53 -> 1533.0654 | R51: =R52*R53 -> 1630.6324 | S51: =S52*S53 -> 1724.4709 | T51: =T52*T53 -> 1822.3024
D52: 인원 수 | L52: =HR!B16/12 -> 0.5 | M52: =AVERAGE(HR!B16:G16) -> 11.666667 | N52: =AVERAGE(HR!H16:M16) -> 25.666667 | O52: =O51/O53 -> 18.666667 | P52: =31+2 -> 33 | Q52: =P52+1 -> 34 | R52: =Q52+1 -> 35 | S52: =R52+1 -> 36 | T52: =S52+1 -> 37 | U52: 33명 채용 완료 및 현 수준 유지
D53: 평균급여 | L53: =L51/L52 -> 35.64844 | M53: =M51/M52*2 -> 43.135966 | N53: =M53 -> 43.135966 | O53: =M53 -> 43.135966 | P53: =O53*(1+'Key Assumption'!P$14) -> 43.941356 | Q53: =P53*(1+'Key Assumption'!Q$14) -> 45.090159 | R53: =Q53*(1+'Key Assumption'!R$14) -> 46.589497 | S53: =R53*(1+'Key Assumption'!S$14) -> 47.90197 | T53: =S53*(1+'Key Assumption'!T$14) -> 49.251416
C54: 상여 | L54: =연결정산표!E110/10^6 -> 0.798819 | M54: =연결정산표!T110/10^6 -> 57.87186 | N54: 0 | O54: =N54+M54 -> 57.87186 | P54: =P55*P$51 -> 104.21939 | Q54: =Q55*Q$51 -> 110.18483 | R54: =R55*R$51 -> 117.19719 | S54: =S55*S$51 -> 123.94157 | T54: =T55*T$51 -> 130.97294
D55: % of 급여 | I55: =O55 -> 0.071872233 | L55: =L54/L$51 -> 0.044816491 | M55: =M54/M$51 -> 0.22999115 | N55: 0 | O55: =O54/O$51 -> 0.071872233 | P55: =$I55 -> 0.071872233 | Q55: =$I55 -> 0.071872233 | R55: =$I55 -> 0.071872233 | S55: =$I55 -> 0.071872233 | T55: =$I55 -> 0.071872233
C56: 퇴직급여 | L56: =연결정산표!E112/10^6 -> 0 | M56: =연결정산표!T112/10^6 -> 0 | N56: =O56 -> 67.100392 | O56: =O57*O$51 -> 67.100392 | P56: =P57*P$51 -> 120.83873 | Q56: =Q57*Q$51 -> 127.75545 | R56: =R57*R$51 -> 135.88603 | S56: =S57*S$51 -> 143.70591 | T56: =T57*T$51 -> 151.85853
D57: % of 급여 | I57: =1/12 -> 0.083333333 | L57: =L56/L$51 -> 0 | M57: =M56/M$51 -> 0 | N57: =N56/N$51 -> 0.12121212 | O57: =I57 -> 0.083333333 | P57: =$I57 -> 0.083333333 | Q57: =$I57 -> 0.083333333 | R57: =$I57 -> 0.083333333 | S57: =$I57 -> 0.083333333 | T57: =$I57 -> 0.083333333
C58: 복리후생비 | L58: =연결정산표!E113/10^6 -> 0 | M58: =연결정산표!T113/10^6 -> 0 | N58: =O58-M58 -> 117.49643 | O58: =O59*O$51 -> 117.49643 | P58: =P59*P$51 -> 211.59518 | Q58: =Q59*Q$51 -> 223.70674 | R58: =R59*R$51 -> 237.94383 | S58: =S59*S$51 -> 251.63686 | T58: =T59*T$51 -> 265.91254
D59: % of 급여 | I59: =TITAN!I59 -> 0.1459212 | L59: =L58/L$51 -> 0 | M59: =M58/M$51 -> 0 | N59: 0 | O59: =I59 -> 0.1459212 | P59: =$I59 -> 0.1459212 | Q59: =$I59 -> 0.1459212 | R59: =$I59 -> 0.1459212 | S59: =$I59 -> 0.1459212 | T59: =$I59 -> 0.1459212 | U59: 타이탄 수준 발생 가정
L61: 2024A | M61: 2025 1H | N61: 2025 2H | O61: 2025E | P61: 2026F | Q61: 2027F | R61: 2028F | S61: 2029F | T61: 2030F
B62: 변동비 | L62: =L64+L69+L82 -> 43.055839 | M62: =M64+M69+M82 -> 5821.6407 | N62: =N64+N69+N82 -> 11215.632 | O62: =O64+O69+O82 -> 17037.273 | P62: =P64+P69+P82 -> 18184.139 | Q62: =Q64+Q69+Q82 -> 18647.907 | R62: =R64+R69+R82 -> 19913.61 | S62: =S64+S69+S82 -> 21182.673 | T62: =T64+T69+T82 -> 22505.224
B63: % of Revenue | L63: =L62/L$20 -> 2.16361 | M63: =M62/M$20 -> 0.5670587 | N63: =N62/N$20 -> 0.67690432 | O63: =O62/O$20 -> 0.63488082 | P63: =P62/P$20 -> 0.5587603 | Q63: =Q62/Q$20 -> 0.53716775 | R63: =R62/R$20 -> 0.53728658 | S63: =S62/S$20 -> 0.53739547 | T63: =T62/T$20 -> 0.53749561
C64: 지급수수료 | L64: 0 | M64: =M65+M67 -> 4112.1825 | N64: =N65+N67 -> 8562.0252 | O64: =O65+O67 -> 12674.208 | P64: =P65+P67 -> 14441.235 | Q64: =Q65+Q67 -> 15448.282 | R64: =R65+R67 -> 16493.165 | S64: =S65+S67 -> 17540.694 | T64: =T65+T67 -> 18632.384
D65: 강의료 | L65: 0 | M65: =연결정산표!T136/10^6 -> 3440.9803 | N65: =N66*(N21-N67) -> 7220.5733 | O65: =N65+M65 -> 10661.554 | P65: =P66*(P21-P67) -> 12000.456 | Q65: =Q66*(Q21-Q67) -> 12844.639 | R65: =R66*(R21-R67) -> 13713.418 | S65: =S66*(S21-S67) -> 14584.397 | T65: =T66*(T21-T67) -> 15492.095
E66: % of 매출액 | I66: 0.4 | L66: 0 | M66: =M65/M20 -> 0.33516975 | N66: =AVERAGE(M87,I66) -> 0.47417811 | O66: =O65/O20 -> 0.39729456 | P66: =AVERAGE(O66,Q66) -> 0.39864728 | Q66: =$I66 -> 0.4 | R66: =$I66 -> 0.4 | S66: =$I66 -> 0.4 | T66: =$I66 -> 0.4 | U66: 정산률 5대5 -> 6대4 변경(27년부터 하반기부터 전체 변경) | Z66: =(I66+(SUM(클래스매출!N21:N26,클래스매출!N28:N31,클래스매출!N33:N36,클래스매출!N32,클래스매출!N37:N50,클래스매출!N52,클래스매출!N54:N69)/(SUM(클래스매출!J21:J26,클래스매출!J28:J31,클래스매출!J32:J36,클래스매출!J37:J50,클래스매출!J52,클래스매출!J54:J69)*0.925)+I66)/2)/2 -> 0.43091762
D67: PG수수료 | L67: 0 | M67: =비용취합!B21/10^6 -> 671.2022 | N67: =O67-M67 -> 1341.4519 | O67: =O21*O68 -> 2012.6541 | P67: =P68*P$20 -> 2440.779 | Q67: =Q68*Q$20 -> 2603.643 | R67: =R68*R$20 -> 2779.747 | S67: =S68*S$20 -> 2956.2968 | T67: =T68*T$20 -> 3140.2895
E68: % of 매출액 | I68: 0.075 | L68: 0 | M68: =M67/M$20 -> 0.065378657 | N68: =N67/N$20 -> 0.080961514 | O68: =I68 -> 0.075 | P68: =$I68 -> 0.075 | Q68: =$I68 -> 0.075 | R68: =$I68 -> 0.075 | S68: =$I68 -> 0.075 | T68: =$I68 -> 0.075
C69: 광고선전비 | L69: =연결정산표!E131/10^6 -> 43.055839 | M69: =연결정산표!T131/10^6 -> 1636.5121 | N69: =N70+N76 -> 2535.8788 | O69: =O70+O76 -> 4172.3909 | P69: =P70+P76 -> 3511.6702 | Q69: =Q70+Q76 -> 2952.9621 | R69: =R70+R76 -> 3157.0976 | S69: =S70+S76 -> 3361.906 | T69: =T70+T76 -> 3575.3358
D70: 부업 | I70: =SUMIFS(클래스매출!$V:$V,클래스매출!$A:$A,CLASS!M$61,클래스매출!$C:$C,CLASS!$D70)/SUMIFS(클래스매출!$V:$V,클래스매출!$A:$A,CLASS!M$61) -> 0.75233069 | M70: =I70*M69 -> 1231.1982 | N70: =N71*N72*N75 -> 2495.3475 | O70: =N70+M70 -> 3726.5457 | P70: =P71*P72*P75 -> 3171.7229 | Q70: =Q71*Q72*Q75 -> 2722.2512 | R70: =R71*R72*R75 -> 2921.5418 | S70: =S71*S72*S75 -> 3121.8747 | T70: =T71*T72*T75 -> 3330.6084
E71: 강의수 | M71: =M24 -> 37 | N71: =N24 -> 56.4 | O71: =N71+M71 -> 93.4 | P71: =P24 -> 98.72 | Q71: =Q24 -> 104.04 | R71: =R24 -> 109.36 | S71: =S24 -> 114.68 | T71: =T24 -> 120
E72: 강의당 광고비 | M72: =M70/M71 -> 33.275628 | N72: =N73*N74/1000 -> 50.564285 | O72: =O73*O74/1000 -> 43.71546 | P72: =P73*P74/1000 -> 51.405557 | Q72: =Q73*Q74/1000 -> 52.330857 | R72: =R73*R74/1000 -> 53.429805 | S72: =S73*S74/1000 -> 54.444972 | T72: =T73*T74/1000 -> 55.51014
F73: CPM(백만원) | M73: =M72*10^6/(M74)*1000/10^6 -> 11.302137 | N73: =M73 -> 11.302137 | O73: =N73 -> 11.302137 | P73: =O73*(1+'Key Assumption'!P$12) -> 11.490178 | Q73: =P73*(1+'Key Assumption'!Q$12) -> 11.697001 | R73: =Q73*(1+'Key Assumption'!R$12) -> 11.942638 | S73: =R73*(1+'Key Assumption'!S$12) -> 12.169548 | T73: =S73*(1+'Key Assumption'!T$12) -> 12.407635
F74: 강의당 톡방 유입 수 | M74: =M26 -> 2944.1892 | N74: =N26 -> 4473.8696 | O74: =O26 -> 3867.8934 | P74: =P26 -> 4473.8696 | Q74: =Q26 -> 4473.8696 | R74: =R26 -> 4473.8696 | S74: =S26 -> 4473.8696 | T74: =T26 -> 4473.8696
E75: 분담률 | I75: 0.5 | J75: =P61 -> 2026F | M75: 1 | N75: =IF(J75=P61,(100%+75%)/2,(100%+(100%-50%/3))/2) -> 0.875 | O75: =O70/(O71*O72) -> 0.9126926 | P75: =IF(J75=P61,(75%+50%)/2,(100%-50%/3+50%)/2) -> 0.625 | Q75: =$I75 -> 0.5 | R75: =$I75 -> 0.5 | S75: =$I75 -> 0.5 | T75: =$I75 -> 0.5
D76: 투자 | I76: =1-I70 -> 0.24766931 | M76: =M69-M70 -> 405.31381 | N76: =N77*N78*N81 -> 40.531381 | O76: =N76+M76 -> 445.8452 | P76: =P77*P78*P81 -> 339.94727 | Q76: =Q77*Q78*Q81 -> 230.71088 | R76: =R77*R78*R81 -> 235.55581 | S76: =S77*S78*S81 -> 240.03137 | T76: =T77*T78*T81 -> 244.72737
E77: 강의수 | M77: =M31 -> 10 | N77: =N31 -> 1 | O77: =O31 -> 11 | P77: =P31 -> 11 | Q77: =Q31 -> 11 | R77: =R31 -> 11 | S77: =S31 -> 11 | T77: =T31 -> 11
E78: 강의당 광고비 | M78: =M76/M77 -> 40.531381 | N78: =N79*N80/1000 -> 40.531381 | O78: =O79*O80/1000 -> 40.531381 | P78: =P79*P80/1000 -> 41.20573 | Q78: =Q79*Q80/1000 -> 41.947433 | R78: =R79*R80/1000 -> 42.828329 | S78: =S79*S80/1000 -> 43.642067 | T78: =T79*T80/1000 -> 44.495886
F79: CPM(백만원) | M79: =M78*10^6/(M80)*1000/10^6 -> 12.518572 | N79: =M79 -> 12.518572 | O79: =N79 -> 12.518572 | P79: =O79*(1+'Key Assumption'!P$12) -> 12.726852 | Q79: =P79*(1+'Key Assumption'!Q$12) -> 12.955936 | R79: =Q79*(1+'Key Assumption'!R$12) -> 13.22801 | S79: =R79*(1+'Key Assumption'!S$12) -> 13.479342 | T79: =S79*(1+'Key Assumption'!T$12) -> 13.743054 | U79: 고객획득비용 물가상승률 수준 상승 가정
F80: 강의당 톡방 유입 수 | M80: =M33 -> 3237.7 | N80: =N33 -> 3237.7 | O80: =O33 -> 3237.7 | P80: =P33 -> 3237.7 | Q80: =Q33 -> 3237.7 | R80: =R33 -> 3237.7 | S80: =S33 -> 3237.7 | T80: =T33 -> 3237.7
E81: 분담률 | I81: 0.5 | J81: =J75 -> 2026F | M81: 1 | N81: 1 | O81: =O76/(O77*O78) -> 1 | P81: =AVERAGE(O81,Q81) -> 0.75 | Q81: =$I81 -> 0.5 | R81: =$I81 -> 0.5 | S81: =$I81 -> 0.5 | T81: =$I81 -> 0.5 | U81: 50% 광고비 강사 분담 체제 전환(2027년부터 전체적용)) | Z81: =IF(J81=P61,(75%+50%)/2,(100%-50%/3+50%)/2) -> 0.625
C82: 외주용역비 | L82: 0 | M82: =연결정산표!T135/10^6 -> 72.94609 | N82: =N83*N$20 -> 117.72837 | O82: =N82+M82 -> 190.67446 | P82: =P83*P$20 -> 231.23408 | Q82: =Q83*Q$20 -> 246.66346 | R82: =R83*R$20 -> 263.34716 | S82: =S83*S$20 -> 280.07311 | T82: =T83*T$20 -> 297.50418
D83: % of 매출액 | I83: =M83 -> 0.0071053363 | L83: =L82/L$20 -> 0 | M83: =M82/M$20 -> 0.0071053363 | N83: =$I83 -> 0.0071053363 | O83: =O82/O$20 -> 0.0071053363 | P83: =$I83 -> 0.0071053363 | Q83: =$I83 -> 0.0071053363 | R83: =$I83 -> 0.0071053363 | S83: =$I83 -> 0.0071053363 | T83: =$I83 -> 0.0071053363
L85: 2024A | M85: 2025 1H | N85: 2025 2H | O85: 2025E | P85: 2026F | Q85: 2027F | R85: 2028F | S85: 2029F | T85: 2030F
B86: Normalization_강의료 | M86: =강의료이월!I42/10^6 -> 1820.5956 | N86: =(N21-N67)*N87-N65 -> 0 | O86: =N86+M86 -> 1820.5956
C87: Normalized 정산율 | M87: =(M86+M65)/(M21-M67) -> 0.54835622 | N87: =AVERAGE(M87,I66) -> 0.47417811 | O87: =N87 -> 0.47417811
L89: 2024A | M89: 2025 1H | N89: 2025 2H | O89: 2025E | P89: 2026F | Q89: 2027F | R89: 2028F | S89: 2029F | T89: 2030F
B90: 고정비 | L90: =SUM(L92:L97) -> 15.154694 | M90: =SUM(M92:M97) -> 337.35601 | N90: =SUM(N92:N97) -> 349.61399 | O90: =SUM(O92:O97) -> 686.97 | P90: =SUM(P92:P97) -> 709.62355 | Q90: =SUM(Q92:Q97) -> 720.52215 | R90: =SUM(R92:R97) -> 734.45737 | S90: =SUM(S92:S97) -> 748.15122 | T90: =SUM(T92:T97) -> 756.08812
B91: % of Revenue | L91: =L90/L$20 -> 0.76154241 | M91: =M90/M$20 -> 0.032860266 | N91: =N90/N$20 -> 0.021100479 | O91: =O90/O$20 -> 0.025599406 | P91: =P90/P$20 -> 0.021805237 | Q91: =Q90/Q$20 -> 0.020755212 | R91: =R90/R$20 -> 0.019816301 | S91: =S90/S$20 -> 0.01898028 | T91: =T90/T$20 -> 0.018057765
C92: 지급수수료 | L92: =연결정산표!E130/10^6 -> 12.706238 | M92: =비용취합!B22/10^6 -> 74.313648 | N92: =M92 -> 74.313648 | O92: =N92+M92 -> 148.6273 | P92: =O92*(1+'Key Assumption'!P$12) -> 151.10011 | Q92: =P92*(1+'Key Assumption'!Q$12) -> 153.81991 | R92: =Q92*(1+'Key Assumption'!R$12) -> 157.05013 | S92: =R92*(1+'Key Assumption'!S$12) -> 160.03408 | T92: =S92*(1+'Key Assumption'!T$12) -> 163.16501
C93: 감가상각비 | L93: =연결정산표!E120/10^6 -> 0 | M93: =연결정산표!T120/10^6 -> 8.196027 | N93: =N110+N111 -> 17.363513 | O93: =N93+M93 -> 25.55954 | P93: =P110+P111 -> 32.743413 | Q93: =Q110+Q111 -> 29.413391 | R93: =R110+R111 -> 26.422035 | S93: =S110+S111 -> 23.734901 | T93: =T110+T111 -> 21.321049
C94: 지급임차료 | L94: =연결정산표!E121/10^6 -> 0.645 | M94: =연결정산표!T121/10^6 -> 24.285432 | N94: =M94 -> 24.285432 | O94: =N94+M94 -> 48.570864 | P94: =O94*(1+'Key Assumption'!P$12) -> 49.378971 | Q94: =P94*(1+'Key Assumption'!Q$12) -> 50.267792 | R94: =Q94*(1+'Key Assumption'!R$12) -> 51.323416 | S94: =R94*(1+'Key Assumption'!S$12) -> 52.298561 | T94: =S94*(1+'Key Assumption'!T$12) -> 53.321736
C95: 건물관리비 | L95: =연결정산표!E132/10^6 -> 0 | M95: =연결정산표!T132/10^6 -> 1.116737 | N95: =M95 -> 1.116737 | O95: =N95+M95 -> 2.233474 | P95: =O95*(1+'Key Assumption'!P$12) -> 2.2706338 | Q95: =P95*(1+'Key Assumption'!Q$12) -> 2.3115052 | R95: =Q95*(1+'Key Assumption'!R$12) -> 2.3600468 | S95: =R95*(1+'Key Assumption'!S$12) -> 2.4048877 | T95: =S95*(1+'Key Assumption'!T$12) -> 2.4519373
C96: 무형자산상각비 | L96: 0 | M96: =연결정산표_우모건제외!H135/10^6 -> 1.784226 | N96: =N112 -> 4.8747205 | O96: =N96+M96 -> 6.6589465 | P96: =P112 -> 11.23507 | Q96: =Q112 -> 13.482084 | R96: =R112 -> 16.178501 | S96: =S112 -> 19.414201 | T96: =T112 -> 15.9722
C97: 기타고정비 | L97: =SUM(연결정산표!E114:E120,연결정산표!E122:E129,연결정산표!E132:E134,연결정산표!E137)/10^6 -> 1.803456 | M97: =SUM(연결정산표!T134,연결정산표!T122:T129,연결정산표!T114:T119,연결정산표!W122)/10^6 -> 227.65994 | N97: =M97 -> 227.65994 | O97: =N97+M97 -> 455.31988 | P97: =O97*(1+'Key Assumption'!P$12) -> 462.89535 | Q97: =P97*(1+'Key Assumption'!Q$12) -> 471.22747 | R97: =Q97*(1+'Key Assumption'!R$12) -> 481.12324 | S97: =R97*(1+'Key Assumption'!S$12) -> 490.26458 | T97: =S97*(1+'Key Assumption'!T$12) -> 499.85618
A100: 4. D&A
L102: 2024A | M102: 2025 1H | N102: 2025 2H | O102: 2025E | P102: 2026F | Q102: 2027F | R102: 2028F | S102: 2029F | T102: 2030F
B103: CAPEX | M103: =M104+M105+M106 -> 115.6239 | N103: =N104+N105+N106 -> 20.246737 | O103: =O104+O105+O106 -> 135.87064 | P103: =P104+P105+P106 -> 36.932111 | Q103: =Q104+Q105+Q106 -> 36.257576 | R103: =R104+R105+R106 -> 36.267936 | S103: =S104+S105+S106 -> 37.016798 | T103: =T104+T105+T106 -> 31.918019
C104: 비품 | M104: =연결정산표!T35/10^6 -> 47.647991 | N104: =G128 -> 10.744621 | O104: =N104+M104 -> 58.392612 | P104: {=TRANSPOSE(G129:G133)} -> 18.429585 | Q104: 16.555287 | R104: 14.871606 | S104: 13.359156 | T104: 12.000523
C105: 시설장치 | M105: =연결정산표!T37/10^6 -> 21.55 | N105: =G135 -> 4.859525 | O105: =N105+M105 -> 26.409525 | P105: {=TRANSPOSE(G136:G140)} -> 8.2888264 | Q105: 7.4458486 | R105: 6.6886021 | S105: 6.0083679 | T105: 5.3973139
C106: 개발비 | M106: =연결정산표!T41/10^6+M96 -> 46.42591 | N106: =G142 -> 4.642591 | O106: =N106+M106 -> 51.068501 | P106: {=TRANSPOSE(G143:G147)} -> 10.2137 | Q106: 12.25644 | R106: 14.707728 | S106: 17.649274 | T106: 14.520182
L108: 2024A | M108: 2025 1H | N108: 2025 2H | O108: 2025E | P108: 2026F | Q108: 2027F | R108: 2028F | S108: 2029F | T108: 2030F
B109: D&A | M109: =M110+M111+M112 -> 9.980253 | N109: =N110+N111+N112 -> 22.238234 | O109: =O110+O111+O112 -> 32.218487 | P109: =P110+P111+P112 -> 43.978483 | Q109: =Q110+Q111+Q112 -> 42.895476 | R109: =R110+R111+R112 -> 42.600536 | S109: =S110+S111+S112 -> 43.149102 | T109: =T110+T111+T112 -> 37.29325
C110: 비품 | M110: =M116+M122 -> 5.572711 | N110: =N116+N122 -> 11.956077 | O110: =N110+M110 -> 17.528788 | P110: =P116+P122 -> 22.585456 | Q110: =Q116+Q122 -> 20.288504 | R110: =R116+R122 -> 18.225153 | S110: =S116+S122 -> 16.371646 | T110: =T116+T122 -> 14.706641
C111: 시설장치 | M111: =M117+M123 -> 2.623316 | N111: =N117+N123 -> 5.4074364 | O111: =N111+M111 -> 8.0307524 | P111: =P117+P123 -> 10.157957 | Q111: =Q117+Q123 -> 9.1248875 | R111: =R117+R123 -> 8.1968819 | S111: =S117+S123 -> 7.3632549 | T111: =T117+T123 -> 6.6144082
C112: 개발비 | M112: =M118+M124 -> 1.784226 | N112: =N118+N124 -> 4.8747205 | O112: =N112+M112 -> 6.6589465 | P112: =P118+P124 -> 11.23507 | Q112: =Q118+Q124 -> 13.482084 | R112: =R118+R124 -> 16.178501 | S112: =S118+S124 -> 19.414201 | T112: =T118+T124 -> 15.9722
L114: 2024A | M114: 2025 1H | N114: 2025 2H | O114: 2025E | P114: 2026F | Q114: 2027F | R114: 2028F | S114: 2029F | T114: 2030F
B115: D&A_기존자산 | M115: =M116+M117+M118 -> 9.980253 | N115: =N116+N117+N118 -> 20.246737 | O115: =O116+O117+O118 -> 30.22699 | P115: =P116+P117+P118 -> 29.759598 | Q115: =Q116+Q117+Q118 -> 20.525636 | R115: =R116+R117+R118 -> 15.456191 | S115: =S116+S117+S118 -> 12.673066 | T115: =T116+T117+T118 -> 4.7183134
...

Sheet NOVA
A1: NOVA
A3: 1. Summary
L5: 2024A | M5: 2025 1H | N5: 2025 2H | O5: 2025E | P5: 2026F | Q5: 2027F | R5: 2028F | S5: 2029F | T5: 2030F
B6: Revenue | M6: =M18 -> 261.84518 | N6: =N18 -> 2351.4231 | O6: =O18 -> 2613.2683 | P6: =P18 -> 7196.2766 | Q6: =Q18 -> 9426.1391 | R6: =R18 -> 11924.423 | S6: =S18 -> 14653.889 | T6: =T18 -> 17654.417
B7: Operating Expense | M7: =M39 -> 247.98681 | N7: =N39 -> 489.71621 | O7: =O39 -> 737.70302 | P7: =P39 -> 1450.3768 | Q7: =Q39 -> 1786.275 | R7: =R39 -> 2124.0661 | S7: =S39 -> 2483.1611 | T7: =T39 -> 2871.8628
B8: EBIT | M8: =M6-M7 -> 13.858365 | N8: =N6-N7 -> 1861.7069 | O8: =O6-O7 -> 1875.5653 | P8: =P6-P7 -> 5745.8998 | Q8: =Q6-Q7 -> 7639.8641 | R8: =R6-R7 -> 9800.3568 | S8: =S6-S7 -> 12170.728 | T8: =T6-T7 -> 14782.554
B9: EBIT % | M9: =M8/M6 -> 0.052925798 | N9: =N8/N6 -> 0.79173624 | O9: =O8/O6 -> 0.71770866 | P9: =P8/P6 -> 0.79845455 | Q9: =Q8/Q6 -> 0.81049771 | R9: =R8/R6 -> 0.82187263 | S9: =S8/S6 -> 0.83054593 | T9: =T8/T6 -> 0.83732894
B10: D&A | M10: =M83 -> 2.132428 | N10: =N83 -> 10.863412 | O10: =O83 -> 12.99584 | P10: =P83 -> 20.049996 | Q10: =Q83 -> 18.010901 | R10: =R83 -> 16.179184 | S10: =S83 -> 14.533753 | T10: =T83 -> 13.055663
B11: EBITDA | M11: =M10+M8 -> 15.990793 | N11: =N10+N8 -> 1872.5703 | O11: =O10+O8 -> 1888.5611 | P11: =P10+P8 -> 5765.9498 | Q11: =Q10+Q8 -> 7657.875 | R11: =R10+R8 -> 9816.536 | S11: =S10+S8 -> 12185.262 | T11: =T10+T8 -> 14795.61
B12: EBITDA % | M12: =M11/M6 -> 0.061069649 | N12: =N11/N6 -> 0.79635617 | O12: =O11/O6 -> 0.72268168 | P12: =P11/P6 -> 0.80124072 | Q12: =Q11/Q6 -> 0.81240845 | R12: =R11/R6 -> 0.82322944 | S12: =S11/S6 -> 0.83153773 | T12: =T11/T6 -> 0.83806845
M13: =M8=연결정산표!S138/10^6 -> TRUE
A15: 2. Revenue
P16: =(P22*P23)*92.5%*P26*12+(P22*P23*12)*7.5% -> 10740.801 | Q16: =(Q22*Q23)*92.5%*Q26*12+(Q22*Q23*12)*7.5% -> 12988.016 | R16: =(R22*R23)*92.5%*R26*12+(R22*R23*12)*7.5% -> 15513.675 | S16: =(S22*S23)*92.5%*S26*12+(S22*S23*12)*7.5% -> 18263.012 | T16: =(T22*T23)*92.5%*T26*12+(T22*T23*12)*7.5% -> 21284.879
L17: 2024A | M17: 2025 1H | N17: 2025 2H | O17: 2025E | P17: 2026F | Q17: 2027F | R17: 2028F | S17: 2029F | T17: 2030F
B18: Revenue | M18: =연결정산표!S99/10^6 -> 261.84518 | N18: =N19+N34 -> 2351.4231 | O18: =O19+O34 -> 2613.2683 | P18: =P19+P34 -> 7196.2766 | Q18: =Q19+Q34 -> 9426.1391 | R18: =R19+R34 -> 11924.423 | S18: =S19+S34 -> 14653.889 | T18: =T19+T34 -> 17654.417
C19: 용역매출 | M19: =M18-M34 -> 221.34518 | N19: =N20+N27 -> 2351.4231 | O19: =O20+O27 -> 2572.7683 | P19: =P20+P27 -> 7196.2766 | Q19: =Q20+Q27 -> 9426.1391 | R19: =R20+R27 -> 11924.423 | S19: =S20+S27 -> 14653.889 | T19: =T20+T27 -> 17654.417
D20: 구축관리형 | M20: =M19 -> 221.34518 | N20: =N21*N26 -> 2351.4231 | O20: =N20+M20 -> 2572.7683 | P20: =P21*P26 -> 6130.0376 | Q20: =Q21*Q26 -> 7707.5395 | R20: =R21*R26 -> 9523.268 | S20: =S21*S26 -> 11548.364 | T20: =T21*T26 -> 13816.5
E21: 정산대상결제액 | M21: =M22*M23*2-M24 -> 2276.1076 | N21: =N22*N23*6-N24 -> 24179.845 | O21: =N21+M21 -> 26455.953 | P21: =P22*P23*12-P24 -> 56866.079 | Q21: =Q22*Q23*12-Q24 -> 65125.877 | R21: =R22*R23*12-R24 -> 73881.689 | S21: =S22*S23*12-S24 -> 82813.985 | T21: =T22*T23*12-T24 -> 92110.002
F22: 관리플랫폼수 | M22: 1 | N22: ='Key Assumption'!N44 -> 6.6666667 | O22: =AVERAGE(시스템노바매출!G21:N21) -> 5.25 | P22: ='Key Assumption'!P44 -> 8 | Q22: ='Key Assumption'!Q44 -> 9 | R22: ='Key Assumption'!R44 -> 10 | S22: ='Key Assumption'!S44 -> 11 | T22: ='Key Assumption'!T44 -> 12 | U22: 5월 개시
F23: 플랫폼당 월매출액 | M23: =SUM(시스템노바매출!G8:H8)/10^6/M22/2 -> 1217.3985 | N23: =SUM(시스템노바매출!I2:N2)/10^6/N22/6 -> 653.50932 | O23: =O21/O22/8 -> 629.90363 | P23: ='Key Assumption'!P45 -> 640.38377 | Q23: ='Key Assumption'!Q45 -> 651.91068 | R23: ='Key Assumption'!R45 -> 665.6008 | S23: ='Key Assumption'!S45 -> 678.24722 | T23: ='Key Assumption'!T45 -> 691.51653
F24: PG수수료 | M24: =비용취합!B27/10^6 -> 158.68932 | N24: =N23*N22*6*N25 -> 1960.528 | O24: =N24+M24 -> 2119.2173 | P24: =P23*P22*12*P25 -> 4610.7631 | Q24: =Q23*Q22*12*Q25 -> 5280.4765 | R24: =R23*R22*12*R25 -> 5990.4072 | S24: =S23*S22*12*S25 -> 6714.6474 | T24: =T23*T22*12*T25 -> 7468.3785
G25: PG수수료율 | M25: =M24/(M23*M22*2) -> 0.065175586 | N25: 0.075 | O25: =O24/O21 -> 0.080103609 | P25: =N25 -> 0.075 | Q25: =P25 -> 0.075 | R25: =P25 -> 0.075 | S25: =Q25 -> 0.075 | T25: =R25 -> 0.075
E26: 수수료율 | M26: =M20/M21 -> 0.097247237 | N26: ='Key Assumption'!N46 -> 0.097247237 | O26: =O19/O21 -> 0.097247237 | P26: ='Key Assumption'!P46 -> 0.10779779 | Q26: ='Key Assumption'!Q46 -> 0.11834834 | R26: ='Key Assumption'!R46 -> 0.12889889 | S26: ='Key Assumption'!S46 -> 0.13944945 | T26: ='Key Assumption'!T46 -> 0.15
D27: 구축형 | P27: =P28*P33 -> 1066.239 | Q27: =Q28*Q33 -> 1718.5995 | R27: =R28*R33 -> 2401.1549 | S27: =S28*S33 -> 3105.5244 | T27: =T28*T33 -> 3837.9167
E28: 정산대상결제액 | P28: =P29*P30*12-P31 -> 21324.779 | Q28: =Q29*Q30*12-Q31 -> 34371.99 | R28: =R29*R30*12-R31 -> 48023.098 | S28: =S29*S30*12-S31 -> 62110.489 | T28: =T29*T30*12-T31 -> 76758.335
F29: 관리플랫폼수 | P29: ='Key Assumption'!P48 -> 3 | Q29: ='Key Assumption'!Q48 -> 4.75 | R29: ='Key Assumption'!R48 -> 6.5 | S29: ='Key Assumption'!S48 -> 8.25 | T29: ='Key Assumption'!T48 -> 10
F30: 플랫폼당 월매출액 | P30: ='Key Assumption'!P49 -> 640.38377 | Q30: ='Key Assumption'!Q49 -> 651.91068 | R30: ='Key Assumption'!R49 -> 665.6008 | S30: ='Key Assumption'!S49 -> 678.24722 | T30: ='Key Assumption'!T49 -> 691.51653
F31: PG수수료 | P31: =P29*P30*12*P32 -> 1729.0362 | Q31: =Q29*Q30*12*Q32 -> 2786.9181 | R31: =R29*R30*12*R32 -> 3893.7647 | S31: =S29*S30*12*S32 -> 5035.9856 | T31: =T29*T30*12*T32 -> 6223.6488
G32: PG수수료율 | P32: =P25 -> 0.075 | Q32: =Q25 -> 0.075 | R32: =R25 -> 0.075 | S32: =S25 -> 0.075 | T32: =T25 -> 0.075
E33: 수수료율 | P33: ='Key Assumption'!P50 -> 0.05 | Q33: ='Key Assumption'!Q50 -> 0.05 | R33: ='Key Assumption'!R50 -> 0.05 | S33: ='Key Assumption'!S50 -> 0.05 | T33: ='Key Assumption'!T50 -> 0.05
C34: 기타(내부거래) | M34: =SUM(시스템노바매출!T3:T4)/10^6 -> 40.5 | N34: 0 | O34: =N34+M34 -> 40.5 | P34: 0 | Q34: 0 | R34: 0 | S34: 0 | T34: 0
A36: 3. Operating Expense
M37: =연결정산표!S108/10^6=M39 -> TRUE
L38: 2024A | M38: 2025 1H | N38: 2025 2H | O38: 2025E | P38: 2026F | Q38: 2027F | R38: 2028F | S38: 2029F | T38: 2030F
B39: Operating Expense | M39: =M41+M42+M43 -> 247.98681 | N39: =N41+N42+N43 -> 489.71621 | O39: =O41+O42+O43 -> 737.70302 | P39: =P41+P42+P43 -> 1450.3768 | Q39: =Q41+Q42+Q43 -> 1786.275 | R39: =R41+R42+R43 -> 2124.0661 | S39: =S41+S42+S43 -> 2483.1611 | T39: =T41+T42+T43 -> 2871.8628
B40: % of Revenue | M40: =M39/M$18 -> 0.9470742 | N40: =N39/N$18 -> 0.20826376 | O40: =O39/O$18 -> 0.28229134 | P40: =P39/P$18 -> 0.20154545 | Q40: =Q39/Q$18 -> 0.18950229 | R40: =R39/R$18 -> 0.17812737 | S40: =S39/S$18 -> 0.16945407 | T40: =T39/T$18 -> 0.16267106
C41: 인건비 | M41: =M46 -> 48.135155 | N41: =N46 -> 256.8716 | O41: =O46 -> 305.00675 | P41: =P46 -> 779.57835 | Q41: =Q46 -> 927.48945 | R41: =R46 -> 1054.1634 | S41: =S46 -> 1182.3929 | T41: =T46 -> 1317.0106
C42: 변동비 | M42: =M59 -> 180.91932 | N42: =N59 -> 199.62994 | O42: =O59 -> 380.54925 | P42: =P59 -> 610.94587 | Q42: =Q59 -> 800.25561 | R42: =R59 -> 1012.3537 | S42: =S59 -> 1244.0785 | T42: =T59 -> 1498.8158
C43: 고정비 | M43: =M68 -> 18.93234 | N43: =N68 -> 33.214679 | O43: =O68 -> 52.147019 | P43: =P68 -> 59.85256 | Q43: =Q68 -> 58.529912 | R43: =R68 -> 57.549093 | S43: =S68 -> 56.689691 | T43: =T68 -> 56.036345
L45: 2024A | M45: 2025 1H | N45: 2025 2H | O45: 2025E | P45: 2026F | Q45: 2027F | R45: 2028F | S45: 2029F | T45: 2030F
B46: 인건비 | M46: =M48+M51+M53+M55 -> 48.135155 | N46: =N48+N51+N53+N55 -> 256.8716 | O46: =O48+O51+O53+O55 -> 305.00675 | P46: =P48+P51+P53+P55 -> 779.57835 | Q46: =Q48+Q51+Q53+Q55 -> 927.48945 | R46: =R48+R51+R53+R55 -> 1054.1634 | S46: =S48+S51+S53+S55 -> 1182.3929 | T46: =T48+T51+T53+T55 -> 1317.0106
B47: % of Revenue | M47: =M46/M$18 -> 0.1838306 | N47: =N46/N$18 -> 0.10924091 | O47: =O46/O$18 -> 0.11671467 | P47: =P46/P$18 -> 0.10833079 | Q47: =Q46/Q$18 -> 0.098395477 | R47: =R46/R$18 -> 0.088403721 | S47: =S46/S$18 -> 0.080687997 | T47: =T46/T$18 -> 0.074599498
C48: 급여 | M48: =연결정산표!S109/10^6 -> 35.18894 | N48: =N49*N50/2 -> 228.72811 | O48: =N48+M48 -> 263.91705 | P48: =P49*P50 -> 674.55563 | Q48: =Q49*Q50 -> 802.54053 | R48: =R49*R50 -> 912.14927 | S48: =S49*S50 -> 1023.1041 | T48: =T49*T50 -> 1139.5865
D49: 인원 수 | M49: =AVERAGE(HR!B56:D56) -> 3.6666667 | N49: =AVERAGE(HR!E56:J56) -> 11.916667 | O49: =O48/O50 -> 6.875 | P49: =AVERAGE(HR!K56:V56) -> 17.25 | Q49: 20 | R49: =Q49+2 -> 22 | S49: =R49+2 -> 24 | T49: =S49+2 -> 26 | U49: 2026년 하반기까지 20명 계획
D50: 평균급여 | M50: =M48/M49*4 -> 38.387935 | N50: =M50 -> 38.387935 | O50: =M50 -> 38.387935 | P50: =O50*(1+'Key Assumption'!P$14) -> 39.104674 | Q50: =P50*(1+'Key Assumption'!Q$14) -> 40.127027 | R50: =Q50*(1+'Key Assumption'!R$14) -> 41.46133 | S50: =R50*(1+'Key Assumption'!S$14) -> 42.629338 | T50: =S50*(1+'Key Assumption'!T$14) -> 43.830249 | U50: 4월부터 지급
C51: 상여 | M51: =연결정산표!S110/10^6 -> 12 | N51: 0 | O51: =N51+M51 -> 12 | P51: =P48*P52 -> 30.671256 | Q51: =Q48*Q52 -> 36.490581 | R51: =R48*R52 -> 41.474362 | S51: =S48*S52 -> 46.519349 | T51: =T48*T52 -> 51.815666
D52: % of 급여 | I52: =O52 -> 0.045468832 | M52: =M51/M$48 -> 0.34101624 | N52: 0 | O52: =O51/O$48 -> 0.045468832 | P52: =$I52 -> 0.045468832 | Q52: =$I52 -> 0.045468832 | R52: =$I52 -> 0.045468832 | S52: =$I52 -> 0.045468832 | T52: =$I52 -> 0.045468832
C53: 퇴직급여 | M53: 0 | N53: =O53 -> 21.993088 | O53: =O$48*O54 -> 21.993088 | P53: =P$48*P54 -> 56.212969 | Q53: =Q$48*Q54 -> 66.878378 | R53: =R$48*R54 -> 76.012439 | S53: =S$48*S54 -> 85.258675 | T53: =T$48*T54 -> 94.965539
D54: % of 급여 | I54: =1/12 -> 0.083333333 | M54: =M53/M$48 -> 0 | N54: =N53/N$48 -> 0.096153846 | O54: =I54 -> 0.083333333 | P54: =$I54 -> 0.083333333 | Q54: =$I54 -> 0.083333333 | R54: =$I54 -> 0.083333333 | S54: =$I54 -> 0.083333333 | T54: =$I54 -> 0.083333333
C55: 복리후생비 | M55: =연결정산표!S113/10^6 -> 0.946215 | N55: =N$48*N56 -> 6.1503975 | O55: =N55+M55 -> 7.0966125 | P55: =P$48*P56 -> 18.138502 | Q55: =Q$48*Q56 -> 21.579959 | R55: =R$48*R56 -> 24.52729 | S55: =S$48*S56 -> 27.510816 | T55: =T$48*T56 -> 30.642975
D56: % of 급여 | I56: =O56 -> 0.026889557 | M56: =M55/M$48 -> 0.026889557 | N56: =M56 -> 0.026889557 | O56: =N56 -> 0.026889557 | P56: =$I56 -> 0.026889557 | Q56: =$I56 -> 0.026889557 | R56: =$I56 -> 0.026889557 | S56: =$I56 -> 0.026889557 | T56: =$I56 -> 0.026889557
L58: 2024A | M58: 2025 1H | N58: 2025 2H | O58: 2025E | P58: 2026F | Q58: 2027F | R58: 2028F | S58: 2029F | T58: 2030F | U58: pg수수료를 대납하고, 얹어서 청구
B59: 변동비 | M59: =M61+M64 -> 180.91932 | N59: =N61+N64 -> 199.62994 | O59: =O61+O64 -> 380.54925 | P59: =P61+P64 -> 610.94587 | Q59: =Q61+Q64 -> 800.25561 | R59: =R61+R64 -> 1012.3537 | S59: =S61+S64 -> 1244.0785 | T59: =T61+T64 -> 1498.8158
B60: % of Revenue | M60: =M59/M$18 -> 0.69094004 | N60: =N59/N$18 -> 0.084897497 | O60: =O59/O$18 -> 0.14562196 | P60: =P59/P$18 -> 0.084897497 | Q60: =Q59/Q$18 -> 0.084897497 | R60: =R59/R$18 -> 0.084897497 | S60: =S59/S$18 -> 0.084897497 | T60: =T59/T$18 -> 0.084897497
C61: 지급수수료(변동) | M61: =비용취합!B27/10^6 -> 158.68932 | N61: 0 | O61: =N61+M61 -> 158.68932 | P61: =P62*P63 -> 0 | Q61: =Q62*Q63 -> 0 | R61: =R62*R63 -> 0 | S61: =S62*S63 -> 0 | T61: =T62*T63 -> 0 | U61: PG수수료
D62: 플랫폼매출액 | M62: =SUM(시스템노바매출!G2:H2)/10^6 -> 2434.7969 | N62: =N21+N28 -> 24179.845 | O62: =N62+M62 -> 26614.642 | P62: =P21+P28 -> 78190.858 | Q62: =Q21+Q28 -> 99497.867 | R62: =R21+R28 -> 121904.79 | S62: =S21+S28 -> 144924.47 | T62: =T21+T28 -> 168868.34
D63: % of 플랫폼매출액 | I63: 0 | M63: =M61/M62 -> 0.065175586 | N63: 0 | O63: =O61/O62 -> 0.0059624817 | P63: 0 | Q63: =$I63 -> 0 | R63: =$I63 -> 0 | S63: =$I63 -> 0 | T63: =$I63 -> 0
C64: 외주용역비 | M64: =연결정산표!S135/10^6 -> 22.23 | N64: =N65*N$18 -> 199.62994 | O64: =N64+M64 -> 221.85994 | P64: =P65*P$18 -> 610.94587 | Q64: =Q65*Q$18 -> 800.25561 | R64: =R65*R$18 -> 1012.3537 | S64: =S65*S$18 -> 1244.0785 | T64: =T65*T$18 -> 1498.8158
D65: % of 매출액 | I65: =M65 -> 0.084897497 | M65: =M64/M$18 -> 0.084897497 | N65: =$I65 -> 0.084897497 | O65: =O64/O$19 -> 0.086233936 | P65: =$I65 -> 0.084897497 | Q65: =$I65 -> 0.084897497 | R65: =$I65 -> 0.084897497 | S65: =$I65 -> 0.084897497 | T65: =$I65 -> 0.084897497
M66: =M61/SUM(시스템노바매출!G2:H2)*10^6 -> 0.065175586
L67: 2024A | M67: 2025 1H | N67: 2025 2H | O67: 2025E | P67: 2026F | Q67: 2027F | R67: 2028F | S67: 2029F | T67: 2030F
B68: 고정비 | L68: =SUM(L71:L73) -> 0 | M68: =SUM(M70:M73) -> 18.93234 | N68: =SUM(N70:N73) -> 33.214679 | O68: =SUM(O70:O73) -> 52.147019 | P68: =SUM(P70:P73) -> 59.85256 | Q68: =SUM(Q70:Q73) -> 58.529912 | R68: =SUM(R70:R73) -> 57.549093 | S68: =SUM(S70:S73) -> 56.689691 | T68: =SUM(T70:T73) -> 56.036345
B69: % of Revenue | M69: =M68/M$18 -> 0.072303566 | N69: =N68/N$18 -> 0.014125352 | O69: =O68/O$18 -> 0.019954713 | P69: =P68/P$18 -> 0.0083171568 | Q69: =Q68/Q$18 -> 0.0062093198 | R69: =R68/R$18 -> 0.0048261533 | S69: =S68/S$18 -> 0.0038685765 | T69: =T68/T$18 -> 0.0031740694
C70: 지급수수료(고정) | M70: =비용취합!B28/10^6 -> 3.965254 | N70: =M70/5*12 -> 9.5166096 | O70: =N70+M70 -> 13.481864 | P70: =O70*(1+'Key Assumption'!P$12) -> 13.706171 | Q70: =P70*(1+'Key Assumption'!Q$12) -> 13.952882 | R70: =Q70*(1+'Key Assumption'!R$12) -> 14.245892 | S70: =R70*(1+'Key Assumption'!S$12) -> 14.516564 | T70: =S70*(1+'Key Assumption'!T$12) -> 14.800568
C71: 감가상각비 | M71: =연결정산표!S120/10^6 -> 2.132428 | N71: =N84 -> 10.863412 | O71: =N71+M71 -> 12.99584 | P71: =P84 -> 20.049996 | Q71: =Q84 -> 18.010901 | R71: =R84 -> 16.179184 | S71: =S84 -> 14.533753 | T71: =T84 -> 13.055663
C72: 지급임차료 | M72: =연결정산표!S121/10^6 -> 0 | N72: =M72 -> 0 | O72: =N72+M72 -> 0 | P72: =O72*(1+'Key Assumption'!P$12) -> 0 | Q72: =P72*(1+'Key Assumption'!Q$12) -> 0 | R72: =Q72*(1+'Key Assumption'!R$12) -> 0 | S72: =R72*(1+'Key Assumption'!S$12) -> 0 | T72: =S72*(1+'Key Assumption'!T$12) -> 0
C73: 기타고정비 | M73: =SUM(연결정산표!S114:S119,연결정산표!S123,연결정산표!S129)/10^6 -> 12.834658 | N73: =M73 -> 12.834658 | O73: =N73+M73 -> 25.669316 | P73: =O73*(1+'Key Assumption'!P$12) -> 26.096394 | Q73: =P73*(1+'Key Assumption'!Q$12) -> 26.566129 | R73: =Q73*(1+'Key Assumption'!R$12) -> 27.124018 | S73: =R73*(1+'Key Assumption'!S$12) -> 27.639374 | T73: =S73*(1+'Key Assumption'!T$12) -> 28.180114
A76: 4. D&A
L78: 2024A | M78: 2025 1H | N78: 2025 2H | O78: 2025E | P78: 2026F | Q78: 2027F | R78: 2028F | S78: 2029F | T78: 2030F
B79: CAPEX | M79: =M80 -> 28.309429 | N79: =N80 -> 9.7626707 | O79: =O80 -> 38.0721 | P79: =P80 -> 16.360666 | Q79: =Q80 -> 14.696778 | R79: =R80 -> 13.202108 | S79: =S80 -> 11.859447 | T79: =T80 -> 10.653336
C80: 비품 | M80: =연결정산표!S35/10^6 -> 28.309429 | N80: =G96 -> 9.7626707 | O80: =N80+M80 -> 38.0721 | P80: {=TRANSPOSE(G97:G101)} -> 16.360666 | Q80: 14.696778 | R80: 13.202108 | S80: 11.859447 | T80: 10.653336
L82: 2024A | M82: 2025 1H | N82: 2025 2H | O82: 2025E | P82: 2026F | Q82: 2027F | R82: 2028F | S82: 2029F | T82: 2030F
B83: D&A | M83: =M84 -> 2.132428 | N83: =N84 -> 10.863412 | O83: =O84 -> 12.99584 | P83: =P84 -> 20.049996 | Q83: =Q84 -> 18.010901 | R83: =R84 -> 16.179184 | S83: =S84 -> 14.533753 | T83: =T84 -> 13.055663
C84: 비품 | M84: =M87+M91 -> 2.132428 | N84: =N87+N91 -> 10.863412 | O84: =N84+M84 -> 12.99584 | P84: =P87+P91 -> 20.049996 | Q84: =Q87+Q91 -> 18.010901 | R84: =R87+R91 -> 16.179184 | S84: =S87+S91 -> 14.533753 | T84: =T87+T91 -> 13.055663
L86: 2024A | M86: 2025 1H | N86: 2025 2H | O86: 2025E | P86: 2026F | Q86: 2027F | R86: 2028F | S86: 2029F | T86: 2030F
B87: D&A_기존자산 | M87: =M88 -> 2.132428 | N87: =N88 -> 9.7626707 | O87: =O88 -> 11.895099 | P87: =P88 -> 12.454136 | Q87: =Q88 -> 6.8373204 | R87: =R88 -> 3.7536889 | S87: =S88 -> 2.0607752 | T87: =T88 -> 1.1313656
C88: 비품 | M88: =M71 -> 2.132428 | N88: =노바고정자산!K1/10^6-NOVA!M88 -> 9.7626707 | O88: =N88+M88 -> 11.895099 | P88: =노바고정자산!L1/10^6 -> 12.454136 | Q88: =노바고정자산!M1/10^6 -> 6.8373204 | R88: =노바고정자산!N1/10^6 -> 3.7536889 | S88: =노바고정자산!O1/10^6 -> 2.0607752 | T88: =노바고정자산!P1/10^6 -> 1.1313656
L90: 2024A | M90: 2025 1H | N90: 2025 2H | O90: 2025E | P90: 2026F | Q90: 2027F | R90: 2028F | S90: 2029F | T90: 2030F
B91: D&A_신규자산 | N91: =N92 -> 1.1007411 | P91: =P92 -> 7.5958604 | Q91: =Q92 -> 11.173581 | R91: =R92 -> 12.425495 | S91: =S92 -> 12.472977 | T91: =T92 -> 11.924297
C92: 비품 | N92: =N95 -> 1.1007411 | P92: =P95 -> 7.5958604 | Q92: =Q95 -> 11.173581 | R92: =R95 -> 12.425495 | S92: =S95 -> 12.472977 | T92: =T95 -> 11.924297
L94: 2024A | M94: 2025 1H | N94: 2025 2H | O94: 2025E | P94: 2026F | Q94: 2027F | R94: 2028F | S94: 2029F | T94: 2030F
B95: 비품 | G95: 취득금액 | H95: 내용연수 | I95: 상각법 | J95: 상각률 | N95: =SUM(N96:N101) -> 1.1007411 | P95: =SUM(P96:P101) -> 7.5958604 | Q95: =SUM(Q96:Q101) -> 11.173581 | R95: =SUM(R96:R101) -> 12.425495 | S95: =SUM(S96:S101) -> 12.472977 | T95: =SUM(T96:T101) -> 11.924297
C96: 2025 2H | G96: =N88 -> 9.7626707 | H96: 5 | I96: 정률법 | J96: 0.451 | N96: =$G96*$J96/2/2 -> 1.1007411 | P96: =($G96-$N96)*$J96 -> 3.9065302 | Q96: =($G96-$N96-$P96)*$J96 -> 2.1446851 | R96: =($G96-$N96-$P96-$Q96)*$J96 -> 1.1774321 | S96: =($G96-$N96-$P96-$Q96-$R96)*$J96 -> 0.64641023 | T96: =($G96-$N96-$P96-$Q96-$R96-$S96)*$J96 -> 0.35487922
C97: 2026F | G97: =P88+P96 -> 16.360666 | H97: 5 | I97: 정률법 | J97: 0.451 | P97: =$G97*$J97/2 -> 3.6893301 | Q97: =($G97-$N97-$P97)*$J97 -> 5.7147724 | R97: =($G97-$N97-$P97-$Q97)*$J97 -> 3.13741 | S97: =($G97-$N97-$P97-$Q97-$R97)*$J97 -> 1.7224381 | T97: =($G97-$N97-$P97-$Q97-$R97-$S97)*$J97 -> 0.94561852
C98: 2027F | G98: =Q88+Q96+Q97 -> 14.696778 | H98: 5 | I98: 정률법 | J98: 0.451 | Q98: =($G98-$N98-$P98)*$J98/2 -> 3.3141234 | R98: =($G98-$N98-$P98-$Q98)*$J98 -> 5.1335772 | S98: =($G98-$N98-$P98-$Q98-$R98)*$J98 -> 2.8183339 | T98: =($G98-$N98-$P98-$Q98-$R98-$S98)*$J98 -> 1.5472653
C99: 2028F | G99: =R96+R97+R98+R88 -> 13.202108 | H99: 5 | I99: 정률법 | J99: 0.451 | R99: =($G99-$N99-$P99-$Q99)*$J99/2 -> 2.9770754 | S99: =($G99-$N99-$P99-$Q99-$R99)*$J99 -> 4.6114898 | T99: =($G99-$N99-$P99-$Q99-$R99-$S99)*$J99 -> 2.5317079
C100: 2029F | G100: =SUM(S96:S99,S88) -> 11.859447 | H100: 5 | I100: 정률법 | J100: 0.451 | S100: =($G100-$N100-$P100-$Q100-$R100)*$J100/2 -> 2.6743054 | T100: =($G100-$N100-$P100-$Q100-$R100-$S100)*$J100 -> 4.142499
C101: 2030F | G101: =SUM(T96:T100,T88) -> 10.653336 | H101: 5 | I101: 정률법 | J101: 0.451 | T101: =($G101-$N101-$P101-$Q101-$R101-$S101)*$J101/2 -> 2.4023272
A104: 5. NWC
L106: 2024A | M106: 2025 1H | N106: 2025 2H | O106: 2025E | P106: 2026F | Q106: 2027F | R106: 2028F | S106: 2029F | T106: 2030F | U106: Terminal
B107: NWC 변동 | M107: =M108 -> -62.728274 | N107: =N108-M108 -> 166.07039 | O107: =O108 -> 103.34212 | P107: =P108-O108 -> 252.87454 | Q107: =Q108-P108 -> 124.37416 | R107: =R108-Q108 -> 144.09744 | S107: =S108-R108 -> 158.6589 | T107: =T108-S108 -> 175.16175 | U107: =U108-T108 -> 9.5850892
B108: NWC | M108: =M109-M113 -> -62.728274 | N108: =N109-N113 -> 103.34212 | O108: =O109-O113 -> 103.34212 | P108: =P109-P113 -> 356.21666 | Q108: =Q109-Q113 -> 480.59083 | R108: =R109-R113 -> 624.68826 | S108: =S109-S113 -> 783.34717 | T108: =T109-T113 -> 958.50892 | U108: =U109-U113 -> 968.09401
B109: 운전자산 | M109: =M110 -> 116.80631 | N109: =N110 -> 194.2918 | O109: =O110 -> 194.2918 | P109: =P110 -> 535.03024 | Q109: =Q110 -> 700.81651 | R109: =R110 -> 886.55943 | S109: =S110 -> 1089.4903 | T109: =T110 -> 1312.5742 | U109: =U110 -> 1325.6999
C110: 매출채권 | M110: =연결정산표!S11/10^6 -> 116.80631 | N110: =O110 -> 194.2918 | O110: =O18/O111 -> 194.2918 | P110: =P18/P111 -> 535.03024 | Q110: =Q18/Q111 -> 700.81651 | R110: =R18/R111 -> 886.55943 | S110: =S18/S111 -> 1089.4903 | T110: =T18/T111 -> 1312.5742 | U110: =T18*(1+DCF!$J$23)/U111 -> 1325.6999
D111: 회전율 | M111: =M18/M110*2*3 -> 13.450224 | N111: =365/N112 -> 13.450224 | O111: =365/O112 -> 13.450224 | P111: =365/P112 -> 13.450224 | Q111: =365/Q112 -> 13.450224 | R111: =365/R112 -> 13.450224 | S111: =365/S112 -> 13.450224 | T111: =365/T112 -> 13.450224 | U111: =365/U112 -> 13.450224
D112: 회전기일 | I112: =M112 -> 27.137094 | M112: =365/M111 -> 27.137094 | N112: =$I112 -> 27.137094 | O112: =$I112 -> 27.137094 | P112: =$I112 -> 27.137094 | Q112: =$I112 -> 27.137094 | R112: =$I112 -> 27.137094 | S112: =$I112 -> 27.137094 | T112: =$I112 -> 27.137094 | U112: =$I112 -> 27.137094
B113: 운전부채 | M113: =M114 -> 179.53458 | N113: =N114 -> 90.949688 | O113: =O114 -> 90.949688 | P113: =P114 -> 178.81358 | Q113: =Q114 -> 220.22568 | R113: =R114 -> 261.87116 | S113: =S114 -> 306.14315 | T113: =T114 -> 354.06528 | U113: =U114 -> 357.60593
C114: 미지급금 | M114: =연결정산표!S53/10^6 -> 179.53458 | N114: =O114 -> 90.949688 | O114: =O39/O115 -> 90.949688 | P114: =P39/P115 -> 178.81358 | Q114: =Q39/Q115 -> 220.22568 | R114: =R39/R115 -> 261.87116 | S114: =S39/S115 -> 306.14315 | T114: =T39/T115 -> 354.06528 | U114: =T39*(1+DCF!$J$23)/U115 -> 357.60593
D115: 회전율 | M115: =M39/M114*2 -> 2.762552 | N115: =365/N116 -> 8.1111111 | O115: =365/O116 -> 8.1111111 | P115: =365/P116 -> 8.1111111 | Q115: =365/Q116 -> 8.1111111 | R115: =365/R116 -> 8.1111111 | S115: =365/S116 -> 8.1111111 | T115: =365/T116 -> 8.1111111 | U115: =365/U116 -> 8.1111111
D116: 회전기일 | I116: 45 | M116: =365/M115 -> 132.12421 | N116: =$I116 -> 45 | O116: =$I116 -> 45 | P116: =$I116 -> 45 | Q116: =$I116 -> 45 | R116: =$I116 -> 45 | S116: =$I116 -> 45 | T116: =$I116 -> 45 | U116: =$I116 -> 45

Sheet TTA
A1: TTA
A3: 1. Summary
L5: 2024A | M5: 2025 1H | N5: 2025 2H | O5: 2025E | P5: 2026F | Q5: 2027F | R5: 2028F | S5: 2029F | T5: 2030F
B6: Revenue | M6: =M19 -> 5406.0864 | N6: =N19 -> 7433.9257 | O6: =O19 -> 12840.012 | P6: =P19 -> 15717.11 | Q6: =Q19 -> 18711.43 | R6: =R19 -> 21872.723 | S6: =S19 -> 25109.255 | T6: =T19 -> 28476.636
B7: Operating Expense | M7: =M33 -> 1920.4115 | N7: =N33 -> 4726.7598 | O7: =O33 -> 6647.1713 | P7: =P33 -> 9866.086 | Q7: =Q33 -> 10872.232 | R7: =R33 -> 12592.675 | S7: =S33 -> 14351.491 | T7: =T33 -> 16181.755
B8: EBIT | M8: =M6-M7 -> 3485.6748 | N8: =N6-N7 -> 2707.1659 | O8: =O6-O7 -> 6192.8407 | P8: =P6-P7 -> 5851.0241 | Q8: =Q6-Q7 -> 7839.1982 | R8: =R6-R7 -> 9280.0475 | S8: =S6-S7 -> 10757.764 | T8: =T6-T7 -> 12294.881
B9: EBIT % | M9: =M8/M6 -> 0.64476861 | N9: =N8/N6 -> 0.3641637 | O9: =O8/O6 -> 0.48230801 | P9: =P8/P6 -> 0.37227099 | Q9: =Q8/Q6 -> 0.41895237 | R9: =R8/R6 -> 0.42427491 | S9: =S8/S6 -> 0.42843821 | T9: =T8/T6 -> 0.43175328
B10: D&A | M10: =M78 -> 0.932232 | N10: =N78 -> 3.1195384 | O10: =O78 -> 4.0517704 | P10: =P78 -> 6.110769 | Q10: =Q78 -> 5.2589767 | R10: =R78 -> 4.5259174 | S10: =S78 -> 4.3193965 | T10: =T78 -> 3.2929514
B11: EBITDA | M11: =M10+M8 -> 3486.607 | N11: =N10+N8 -> 2710.2854 | O11: =O10+O8 -> 6196.8925 | P11: =P10+P8 -> 5857.1348 | Q11: =Q10+Q8 -> 7844.4572 | R11: =R10+R8 -> 9284.5734 | S11: =S10+S8 -> 10762.084 | T11: =T10+T8 -> 12298.174
B12: EBITDA % | M12: =M11/M6 -> 0.64494106 | N12: =N11/N6 -> 0.36458334 | O12: =O11/O6 -> 0.48262357 | P12: =P11/P6 -> 0.37265978 | Q12: =Q11/Q6 -> 0.41923343 | R12: =R11/R6 -> 0.42448183 | S12: =S11/S6 -> 0.42861023 | T12: =T11/T6 -> 0.43186892
B13: Normalized EBITDA | M13: =M11-M70 -> 1886.607 | N13: =N11-N70 -> 2710.2854 | O13: =O11-O70 -> 4596.8925 | P13: =P11-P70 -> 5857.1348 | Q13: =Q11-Q70 -> 7844.4572 | R13: =R11-R70 -> 9284.5734 | S13: =S11-S70 -> 10762.084 | T13: =T11-T70 -> 12298.174
B14: EBITDA % | M14: =M13/M6 -> 0.34897834 | N14: =N13/N6 -> 0.36458334 | O14: =O13/O6 -> 0.3580131 | P14: =P13/P6 -> 0.37265978 | Q14: =Q13/Q6 -> 0.41923343 | R14: =R13/R6 -> 0.42448183 | S14: =S13/S6 -> 0.42861023 | T14: =T13/T6 -> 0.43186892
M15: =(연결정산표_우모건제외!F140-연결정산표_우모건제외!K122)/10^6=M8 -> TRUE
A16: 2. Revenue
L18: 2024A | M18: 2025 1H | N18: 2025 2H | O18: 2025E | P18: 2026F | Q18: 2027F | R18: 2028F | S18: 2029F | T18: 2030F
B19: Revenue | M19: =M20 -> 5406.0864 | N19: =N20 -> 7433.9257 | O19: =O20 -> 12840.012 | P19: =P20 -> 15717.11 | Q19: =Q20 -> 18711.43 | R19: =R20 -> 21872.723 | S19: =S20 -> 25109.255 | T19: =T20 -> 28476.636
C20: 용역매출(강의매출) | M20: =연결정산표!R98/10^6 -> 5406.0864 | N20: =N21 -> 7433.9257 | O20: =O21 -> 12840.012 | P20: =P21 -> 15717.11 | Q20: =Q21 -> 18711.43 | R20: =R21 -> 21872.723 | S20: =S21 -> 25109.255 | T20: =T21 -> 28476.636
D21: 부업 | M21: =M20 -> 5406.0864 | N21: =N22*N27 -> 7433.9257 | O21: =N21+M21 -> 12840.012 | P21: =P22*P27 -> 15717.11 | Q21: =Q22*Q27 -> 18711.43 | R21: =R22*R27 -> 21872.723 | S21: =S22*S27 -> 25109.255 | T21: =T22*T27 -> 28476.636
E22: 결제 건수 | M22: =SUMIFS(티티에이매출v2!$Q:$Q,티티에이매출v2!$A:$A,TTA!M$18,티티에이매출v2!$B:$B,TTA!$D21) -> 2250 | N22: =N23*N24 -> 3093.9818 | O22: =N22+M22 -> 5343.9818 | P22: =P23*P24 -> 6434.37 | Q22: =Q23*Q24 -> 7524.7582 | R22: =R23*R24 -> 8615.1464 | S22: =S23*S24 -> 9705.5346 | T22: =T23*T24 -> 10795.923
F23: 강의 수 | M23: =COUNTIFS(티티에이매출v2!$A:$A,TTA!M$18,티티에이매출v2!$B:$B,TTA!$D21) -> 15 | N23: ='Key Assumption'!N37 -> 34.5 | O23: =N23+M23 -> 49.5 | P23: ='Key Assumption'!P37 -> 59.6 | Q23: ='Key Assumption'!Q37 -> 69.7 | R23: ='Key Assumption'!R37 -> 79.8 | S23: ='Key Assumption'!S37 -> 89.9 | T23: ='Key Assumption'!T37 -> 100
F24: 강의당 결제건수 | M24: =M22/M23 -> 150 | N24: =N25*N26 -> 89.680632 | O24: =O22/O23 -> 107.95923 | P24: =P25*P26 -> 107.95923 | Q24: =Q25*Q26 -> 107.95923 | R24: =R25*R26 -> 107.95923 | S24: =S25*S26 -> 107.95923 | T24: =T25*T26 -> 107.95923
G25: 강의당 신규유입수(톡방) | M25: =SUMIFS(티티에이매출v2!$K:$K,티티에이매출v2!$A:$A,TTA!M$18,티티에이매출v2!B:B,TTA!$D21)/M23 -> 5200 | N25: ='Key Assumption'!N38 -> 3108.9286 | O25: =O24/O26 -> 3742.5866 | P25: ='Key Assumption'!P38 -> 3742.5866 | Q25: ='Key Assumption'!Q38 -> 3742.5866 | R25: ='Key Assumption'!R38 -> 3742.5866 | S25: ='Key Assumption'!S38 -> 3742.5866 | T25: ='Key Assumption'!T38 -> 3742.5866
G26: 유료 전환율 | M26: =M24/M25 -> 0.028846154 | N26: ='Key Assumption'!N39 -> 0.028846154 | O26: ='Key Assumption'!O39 -> 0.028846154 | P26: ='Key Assumption'!P39 -> 0.028846154 | Q26: ='Key Assumption'!Q39 -> 0.028846154 | R26: ='Key Assumption'!R39 -> 0.028846154 | S26: ='Key Assumption'!S39 -> 0.028846154 | T26: ='Key Assumption'!T39 -> 0.028846154
E27: 건당결제액 | M27: =M21/M22 -> 2.402705 | N27: =M27 -> 2.402705 | O27: =N27 -> 2.402705 | P27: =O27*(1+'Key Assumption'!P$12) -> 2.4426805 | Q27: =P27*(1+'Key Assumption'!Q$12) -> 2.4866487 | R27: =Q27*(1+'Key Assumption'!R$12) -> 2.5388684 | S27: =R27*(1+'Key Assumption'!S$12) -> 2.5871069 | T27: =S27*(1+'Key Assumption'!T$12) -> 2.6377213
A30: 3. Operating Expense
L32: 2024A | M32: 2025 1H | N32: 2025 2H | O32: 2025E | P32: 2026F | Q32: 2027F | R32: 2028F | S32: 2029F | T32: 2030F
B33: Operating Expense | M33: =M35+M36+M37 -> 1920.4115 | N33: =N35+N36+N37 -> 4726.7598 | O33: =O35+O36+O37 -> 6647.1713 | P33: =P35+P36+P37 -> 9866.086 | Q33: =Q35+Q36+Q37 -> 10872.232 | R33: =R35+R36+R37 -> 12592.675 | S33: =S35+S36+S37 -> 14351.491 | T33: =T35+T36+T37 -> 16181.755
B34: % of Revenue | M34: =M33/M$19 -> 0.35523139 | N34: =N33/N$19 -> 0.6358363 | O34: =O33/O$19 -> 0.51769199 | P34: =P33/P$19 -> 0.62772901 | Q34: =Q33/Q$19 -> 0.58104763 | R34: =R33/R$19 -> 0.57572509 | S34: =S33/S$19 -> 0.57156179 | T34: =T33/T$19 -> 0.56824672
C35: 인건비 | M35: =M40 -> 49.697537 | N35: =N40 -> 168.05591 | O35: =O40 -> 217.75345 | P35: =P40 -> 935.90182 | Q35: =Q40 -> 1048.2498 | R35: =R40 -> 1173.9081 | S35: =S40 -> 1300.3382 | T35: =T40 -> 1432.96
C36: 변동비 | M36: =M53 -> 1662.9043 | N36: =N53 -> 4348.7069 | O36: =O53 -> 6011.6112 | P36: =P53 -> 8503.4346 | Q36: =Q53 -> 9390.5132 | R36: =R53 -> 10977.038 | S36: =S53 -> 12601.324 | T36: =T53 -> 14291.277
C37: 고정비 | M37: =M75 -> 207.80966 | N37: =N75 -> 209.99697 | O37: =O75 -> 417.80663 | P37: =P75 -> 426.74955 | Q37: =Q75 -> 433.46925 | R37: =R75 -> 441.72861 | S37: =S75 -> 449.82894 | T37: =T75 -> 457.5185
L39: 2024A | M39: 2025 1H | N39: 2025 2H | O39: 2025E | P39: 2026F | Q39: 2027F | R39: 2028F | S39: 2029F | T39: 2030F
B40: 인건비 | M40: =M42+M45+M47+M49 -> 49.697537 | N40: =N42+N45+N47+N49 -> 168.05591 | O40: =O42+O45+O47+O49 -> 217.75345 | P40: =P42+P45+P47+P49 -> 935.90182 | Q40: =Q42+Q45+Q47+Q49 -> 1048.2498 | R40: =R42+R45+R47+R49 -> 1173.9081 | S40: =S42+S45+S47+S49 -> 1300.3382 | T40: =T42+T45+T47+T49 -> 1432.96
B41: % of Revenue | M41: =M40/M$19 -> 0.0091928863 | N41: =N40/N$19 -> 0.022606617 | O41: =O40/O$19 -> 0.016958975 | P41: =P40/P$19 -> 0.059546686 | Q41: =Q40/Q$19 -> 0.056021895 | R41: =R40/R$19 -> 0.053669958 | S41: =S40/S$19 -> 0.051787206 | T41: =T40/T$19 -> 0.050320549
C42: 급여 | M42: =연결정산표!R109/10^6 -> 32.622618 | N42: =N43*N44/2 -> 152.6191 | O42: =N42+M42 -> 185.24172 | P42: =P43*P44 -> 796.16679 | Q42: =Q43*Q44 -> 891.74061 | R42: =R43*R44 -> 998.63749 | S42: =S43*S44 -> 1106.1909 | T42: =T43*T44 -> 1219.0115
D43: 인원 수 | M43: =SUM(HR!B86:E86)/6 -> 1.8333333 | N43: =AVERAGE(HR!F86:K86) -> 8.5769231 | O43: =O42/O44 -> 5.2051282 | P43: =AVERAGE(HR!L86:W86) -> 21.961538 | Q43: =P43+($T43-$P43)/4 -> 23.971154 | R43: =Q43+($T43-$P43)/4 -> 25.980769 | S43: =R43+($T43-$P43)/4 -> 27.990385 | T43: 30 | U43: 2025년 하반기 7명, 2026년까지 30명 수준 채용 가정
D44: 평균급여 | M44: =M42/M43*2 -> 35.588311 | N44: =M44 -> 35.588311 | O44: =N44 -> 35.588311 | P44: =O44*(1+'Key Assumption'!P$14) -> 36.252778 | Q44: =P44*(1+'Key Assumption'!Q$14) -> 37.200571 | R44: =Q44*(1+'Key Assumption'!R$14) -> 38.437564 | S44: =R44*(1+'Key Assumption'!S$14) -> 39.520389 | T44: =S44*(1+'Key Assumption'!T$14) -> 40.633718
C45: 상여 | M45: =연결정산표!R110/10^6 -> 6.8 | N45: =N$42*N46 -> 0 | O45: =N45+M45 -> 6.8 | P45: =P$42*P46 -> 29.226322 | Q45: =Q$42*Q46 -> 32.734722 | R45: =R$42*R46 -> 36.658777 | S45: =S$42*S46 -> 40.606933 | T45: =T$42*T46 -> 44.748443
D46: % of 급여 | I46: =$O46 -> 0.036708793 | M46: =M45/M$42 -> 0.20844434 | N46: 0 | O46: =O45/O$42 -> 0.036708793 | P46: =$I46 -> 0.036708793 | Q46: =$I46 -> 0.036708793 | R46: =$I46 -> 0.036708793 | S46: =$I46 -> 0.036708793 | T46: =$I46 -> 0.036708793
C47: 퇴직급여 | M47: 0 | N47: =O47 -> 15.43681 | O47: =O48*O42 -> 15.43681 | P47: =P48*P42 -> 66.347232 | Q47: =Q48*Q42 -> 74.311717 | R47: =R48*R42 -> 83.219791 | S47: =S48*S42 -> 92.182574 | T47: =T48*T42 -> 101.58429
D48: % of 급여 | I48: =1/12 -> 0.083333333 | M48: =M47/M$42 -> 0 | N48: =N47/N$42 -> 0.10114599 | O48: =$I48 -> 0.083333333 | P48: =$I48 -> 0.083333333 | Q48: =$I48 -> 0.083333333 | R48: =$I48 -> 0.083333333 | S48: =$I48 -> 0.083333333 | T48: =$I48 -> 0.083333333
C49: 복리후생비 | M49: =연결정산표!R113/10^6 -> 10.274919 | N49: =N50*N$42 -> 0 | O49: =N49+M49 -> 10.274919 | P49: =P50*P$42 -> 44.161484 | Q49: =Q50*Q$42 -> 49.462738 | R49: =R50*R$42 -> 55.392054 | S49: =S50*S$42 -> 61.357786 | T49: =T50*T$42 -> 67.61568
D50: % of 급여 | I50: =$O50 -> 0.055467629 | M50: =M49/M$42 -> 0.31496304 | N50: 0 | O50: =O49/O$42 -> 0.055467629 | P50: =$I50 -> 0.055467629 | Q50: =$I50 -> 0.055467629 | R50: =$I50 -> 0.055467629 | S50: =$I50 -> 0.055467629 | T50: =$I50 -> 0.055467629
L52: 2024A | M52: 2025 1H | N52: 2025 2H | O52: 2025E | P52: 2026F | Q52: 2027F | R52: 2028F | S52: 2029F | T52: 2030F | U52: 자체 유투브 --> 광고비 적음
B53: 변동비 | M53: =M55+M60+M66 -> 1662.9043 | N53: =N55+N60+N66 -> 4348.7069 | O53: =O55+O60+O66 -> 6011.6112 | P53: =P55+P60+P66 -> 8503.4346 | Q53: =Q55+Q60+Q66 -> 9390.5132 | R53: =R55+R60+R66 -> 10977.038 | S53: =S55+S60+S66 -> 12601.324 | T53: =T55+T60+T66 -> 14291.277
B54: % of Revenue | M54: =M53/M$19 -> 0.30759855 | N54: =N53/N$19 -> 0.58498122 | O54: =O53/O$19 -> 0.46819358 | P54: =P53/P$19 -> 0.54103042 | Q54: =Q53/Q$19 -> 0.50185972 | R54: =R53/R$19 -> 0.50185972 | S54: =S53/S$19 -> 0.50185972 | T54: =T53/T$19 -> 0.50185972
C55: 지급수수료(변동) | M55: =M56+M58 -> 1091.818 | N55: =N56+N58 -> 3563.4044 | O55: =O56+O58 -> 4655.2224 | P55: =P56+P58 -> 7226.44 | Q55: =Q56+Q58 -> 8326.5866 | R55: =R56+R58 -> 9733.3616 | S55: =S56+S58 -> 11173.619 | T55: =T56+T58 -> 12672.103
D56: 강의료 | M56: =비용취합!B14/10^6+비용취합!B16/10^6 -> 748.91867 | N56: =N57*(N$20-N$58) -> 2943.3028 | O56: =N56+M56 -> 3692.2215 | P56: =P57*(P$20-P$58) -> 6047.6567 | Q56: =Q57*(Q$20-Q$58) -> 6923.2293 | R56: =R57*(R$20-R$58) -> 8092.9074 | S56: =S57*(S$20-S$58) -> 9290.4244 | T56: =T57*(T$20-T$58) -> 10536.355
E57: % of 매출액 | I57: 0.4 | M57: =M56/M$20 -> 0.1385325 | N57: =AVERAGE(M71,I57) -> 0.43196049 | O57: =O56/O$20 -> 0.28755592 | P57: =AVERAGE(Q57,N57) -> 0.41598024 | Q57: =$I57 -> 0.4 | R57: =$I57 -> 0.4 | S57: =$I57 -> 0.4 | T57: =$I57 -> 0.4 | U57: 정산률 5대5 -> 6대4 변경(27년부터 하반기부터 전체 변경)
D58: PG수수료 | M58: =비용취합!B13/10^6 -> 342.89935 | N58: =O58-M58 -> 620.10155 | O58: =O59*O$20 -> 963.0009 | P58: =P59*P$20 -> 1178.7833 | Q58: =Q59*Q$20 -> 1403.3573 | R58: =R59*R$20 -> 1640.4542 | S58: =S59*S$20 -> 1883.1941 | T58: =T59*T$20 -> 2135.7477
E59: % of 매출액 | I59: 0.075 | M59: =M58/M$20 -> 0.063428389 | N59: =$I59 -> 0.075 | O59: =$I59 -> 0.075 | P59: =$I59 -> 0.075 | Q59: =$I59 -> 0.075 | R59: =$I59 -> 0.075 | S59: =$I59 -> 0.075 | T59: =$I59 -> 0.075
C60: 광고선전비 | M60: =연결정산표!R131/10^6 -> 527.39557 | N60: =N61*N62*N65 -> 725.22324 | O60: =N60+M60 -> 1252.6188 | P60: =P61*P62*P65 -> 1149.9725 | Q60: =Q61*Q62*Q65 -> 912.70513 | R60: =R61*R62*R65 -> 1066.9065 | S60: =S61*S62*S65 -> 1224.7779 | T60: =T61*T62*T65 -> 1389.0318
D61: 강의수 | M61: =M23 -> 15 | N61: =N23 -> 34.5 | O61: =N61+M61 -> 49.5 | P61: =P23 -> 59.6 | Q61: =Q23 -> 69.7 | R61: =R23 -> 79.8 | S61: =S23 -> 89.9 | T61: =T23 -> 100
D62: 강의당 광고비 | M62: =M60/M61 -> 35.159705 | N62: =N63*N64/1000 -> 21.020963 | O62: =O63*O64/1000 -> 25.30543 | P62: =P63*P64/1000 -> 25.726454 | Q62: =Q63*Q64/1000 -> 26.18953 | R62: =R63*R64/1000 -> 26.73951 | S62: =S63*S64/1000 -> 27.247561 | T62: =T63*T64/1000 -> 27.780636
E63: CPM(백만원) | M63: =M62*10^6/M64/1000 -> 6.7614816 | N63: =M63 -> 6.7614816 | O63: =N63 -> 6.7614816 | P63: =O63*(1+'Key Assumption'!P$12) -> 6.873977 | Q63: =P63*(1+'Key Assumption'!Q$12) -> 6.9977086 | R63: =Q63*(1+'Key Assumption'!R$12) -> 7.1446605 | S63: =R63*(1+'Key Assumption'!S$12) -> 7.280409 | T63: =S63*(1+'Key Assumption'!T$12) -> 7.4228439 | U63: 고객획득비용 물가상승률 수준 상승 가정
E64: 강의당 톡방 유입 수 | M64: =M25 -> 5200 | N64: =N25 -> 3108.9286 | O64: =O25 -> 3742.5866 | P64: =P25 -> 3742.5866 | Q64: =Q25 -> 3742.5866 | R64: =R25 -> 3742.5866 | S64: =S25 -> 3742.5866 | T64: =T25 -> 3742.5866
D65: 분담률 | I65: 0.5 | M65: 1 | N65: 1 | O65: =O60/(O61*O62) -> 1 | P65: =AVERAGE(Q65,N65) -> 0.75 | Q65: =$I$65 -> 0.5 | R65: =$I$65 -> 0.5 | S65: =$I$65 -> 0.5 | T65: =$I$65 -> 0.5 | U65: 50% 광고비 강사 분담 체제 전환(2027년부터 전체적용)) | Z65: =IF(J65=P52,(100%+75%)/2,(100%+(100%-50%/3))/2) -> 0.91666667 | AA65: =IF(J65=P52,(75%+50%)/2,(100%-50%/3+50%)/2) -> 0.66666667
C66: 외주용역비 | M66: =연결정산표!R135/10^6 -> 43.690764 | N66: =N67*N20 -> 60.079302 | O66: =N66+M66 -> 103.77007 | P66: =P67*P20 -> 127.02212 | Q66: =Q67*Q20 -> 151.22154 | R66: =R67*R20 -> 176.77038 | S66: =S67*S20 -> 202.92731 | T66: =T67*T20 -> 230.14172
D67: % of 매출액 | I67: =$M67 -> 0.0080817732 | M67: =M66/M$20 -> 0.0080817732 | N67: =M67 -> 0.0080817732 | O67: =N67 -> 0.0080817732 | P67: =$I67 -> 0.0080817732 | Q67: =$I67 -> 0.0080817732 | R67: =$I67 -> 0.0080817732 | S67: =$I67 -> 0.0080817732 | T67: =$I67 -> 0.0080817732
L69: 2024A | M69: 2025 1H | N69: 2025 2H | O69: 2025E | P69: 2026F | Q69: 2027F | R69: 2028F | S69: 2029F | T69: 2030F
B70: Normalization_강의료 | M70: =강의료이월!N42/10^6 -> 1600 | N70: =(N20-N58)*N71-N56 -> 0 | O70: =N70+M70 -> 1600
C71: Normalized 정산율 | M71: =(M56+M70)/(M20-M58) -> 0.46392098 | N71: =N57 -> 0.43196049 | O71: =N71 -> 0.43196049
C72: 차이 | M72: =M71-M50 -> 0.14895794 | N72: =N71-N50 -> 0.43196049 | O72: =O71-O50 -> 0.37649286
L74: 2024A | M74: 2025 1H | N74: 2025 2H | O74: 2025E | P74: 2026F | Q74: 2027F | R74: 2028F | S74: 2029F | T74: 2030F
B75: 고정비 | M75: =M77+M79+M80+M81+M78 -> 207.80966 | N75: =N77+N79+N80+N81+N78 -> 209.99697 | O75: =O77+O79+O80+O81+O78 -> 417.80663 | P75: =P77+P79+P80+P81+P78 -> 426.74955 | Q75: =Q77+Q79+Q80+Q81+Q78 -> 433.46925 | R75: =R77+R79+R80+R81+R78 -> 441.72861 | S75: =S77+S79+S80+S81+S78 -> 449.82894 | T75: =T77+T79+T80+T81+T78 -> 457.5185
B76: % of Revenue | M76: =M75/M$19 -> 0.038439945 | N76: =N75/N$19 -> 0.028248462 | O76: =O75/O$19 -> 0.032539426 | P76: =P75/P$19 -> 0.027151909 | Q76: =Q75/Q$19 -> 0.023166014 | R76: =R75/R$19 -> 0.02019541 | S76: =S75/S$19 -> 0.017914866 | T76: =T75/T$19 -> 0.016066452
C77: 지급수수료(고정) | M77: =연결정산표!R130/10^6-TTA!M56-TTA!M58 -> 129.50104 | N77: =M77 -> 129.50104 | O77: =N77+M77 -> 259.00207 | P77: =O77*(1+'Key Assumption'!P$12) -> 263.31127 | Q77: =P77*(1+'Key Assumption'!Q$12) -> 268.05087 | R77: =Q77*(1+'Key Assumption'!R$12) -> 273.67994 | S77: =R77*(1+'Key Assumption'!S$12) -> 278.87986 | T77: =S77*(1+'Key Assumption'!T$12) -> 284.3359
C78: 감가상각비 | M78: =연결정산표!X36/10^6 -> 0.932232 | N78: =N91 -> 3.1195384 | O78: =N78+M78 -> 4.0517704 | P78: =P91 -> 6.110769 | Q78: =Q91 -> 5.2589767 | R78: =R91 -> 4.5259174 | S78: =S91 -> 4.3193965 | T78: =T91 -> 3.2929514
C79: 지급임차료 | M79: =연결정산표!R121/10^6 -> 15.333636 | N79: =M79 -> 15.333636 | O79: =N79+M79 -> 30.667272 | P79: =O79*(1+'Key Assumption'!P$12) -> 31.177504 | Q79: =P79*(1+'Key Assumption'!Q$12) -> 31.738699 | R79: =Q79*(1+'Key Assumption'!R$12) -> 32.405212 | S79: =R79*(1+'Key Assumption'!S$12) -> 33.020911 | T79: =S79*(1+'Key Assumption'!T$12) -> 33.666936
C80: 소모품비 | M80: =연결정산표!R129/10^6 -> 52.984943 | N80: =M80 -> 52.984943 | O80: =N80+M80 -> 105.96989 | P80: =O80*(1+'Key Assumption'!P$12) -> 107.73298 | Q80: =P80*(1+'Key Assumption'!Q$12) -> 109.67217 | R80: =Q80*(1+'Key Assumption'!R$12) -> 111.97529 | S80: =R80*(1+'Key Assumption'!S$12) -> 114.10282 | T80: =S80*(1+'Key Assumption'!T$12) -> 116.33514
C81: 기타고정비 | M81: =SUM(연결정산표!R114:R120,연결정산표!R122:R128,연결정산표!R132:R134)/10^6 -> 9.057813 | N81: =M81 -> 9.057813 | O81: =N81+M81 -> 18.115626 | P81: =O81*(1+'Key Assumption'!P$12) -> 18.417028 | Q81: =P81*(1+'Key Assumption'!Q$12) -> 18.748535 | R81: =Q81*(1+'Key Assumption'!R$12) -> 19.142254 | S81: =R81*(1+'Key Assumption'!S$12) -> 19.505957 | T81: =S81*(1+'Key Assumption'!T$12) -> 19.887574
A84: 4. D&A
L86: 2024A | M86: 2025 1H | N86: 2025 2H | O86: 2025E | P86: 2026F | Q86: 2027F | R86: 2028F | S86: 2029F | T86: 2030F
B87: CAPEX | M87: =M88 -> 10.438546 | N87: =N88 -> 2.755776 | O87: =O88 -> 13.194322 | P87: =P88 -> 4.8344691 | Q87: =Q88 -> 4.1605828 | R87: =R88 -> 3.5806309 | S87: =S88 -> 3.4172441 | T87: =T88 -> 2.6051831
C88: 비품 | M88: =티티에이고정자산!G5/10^6 -> 10.438546 | N88: =G104 -> 2.755776 | O88: =N88+M88 -> 13.194322 | P88: {=TRANSPOSE(G105:G109)} -> 4.8344691 | Q88: 4.1605828 | R88: 3.5806309 | S88: 3.4172441 | T88: 2.6051831
L90: 2024A | M90: 2025 1H | N90: 2025 2H | O90: 2025E | P90: 2026F | Q90: 2027F | R90: 2028F | S90: 2029F | T90: 2030F
B91: D&A | M91: =M92 -> 0.932232 | N91: =N92 -> 3.1195384 | O91: =O92 -> 4.0517704 | P91: =P92 -> 6.110769 | Q91: =Q92 -> 5.2589767 | R91: =R92 -> 4.5259174 | S91: =S92 -> 4.3193965 | T91: =T92 -> 3.2929514
C92: 비품 | M92: =M96+M100 -> 0.932232 | N92: =N96+N100 -> 3.1195384 | O92: =N92+M92 -> 4.0517704 | P92: =P96+P100 -> 6.110769 | Q92: =Q96+Q100 -> 5.2589767 | R92: =R96+R100 -> 4.5259174 | S92: =S96+S100 -> 4.3193965 | T92: =T96+T100 -> 3.2929514
L94: 2024A | M94: 2025 1H | N94: 2025 2H | O94: 2025E | P94: 2026F | Q94: 2027F | R94: 2028F | S94: 2029F | T94: 2030F
B95: D&A_기존자산 | M95: =M96 -> 0.932232 | N95: =N96 -> 2.755776 | O95: =O96 -> 3.688008 | P95: =P96 -> 3.571486 | Q95: =Q96 -> 1.6857414 | R95: =R96 -> 0.79566993 | S95: =S96 -> 0.7112807 | T95: =T96 -> 0
C96: 비품 | M96: =TTA!M78 -> 0.932232 | N96: =SUM(티티에이고정자산!S2:S3)/10^6 -> 2.755776 | O96: =N96+M96 -> 3.688008 | P96: =SUM(티티에이고정자산!U2:U3)/10^6 -> 3.571486 | Q96: =SUM(티티에이고정자산!V2:V3)/10^6 -> 1.6857414 | R96: =SUM(티티에이고정자산!W2:W3)/10^6 -> 0.79566993 | S96: =SUM(티티에이고정자산!X2:X3)/10^6 -> 0.7112807 | T96: =SUM(티티에이고정자산!Y2:Y3)/10^6 -> 0
L98: 2024A | M98: 2025 1H | N98: 2025 2H | O98: 2025E | P98: 2026F | Q98: 2027F | R98: 2028F | S98: 2029F | T98: 2030F
B99: D&A_신규자산 | N99: =N100 -> 0.36376243 | P99: =P100 -> 2.539283 | Q99: =Q100 -> 3.5732353 | R99: =R100 -> 3.7302475 | S99: =S100 -> 3.6081158 | T99: =T100 -> 3.2929514
C100: 비품 | N100: =N103 -> 0.36376243 | P100: =P103 -> 2.539283 | Q100: =Q103 -> 3.5732353 | R100: =R103 -> 3.7302475 | S100: =S103 -> 3.6081158 | T100: =T103 -> 3.2929514
L102: 2024A | M102: 2025 1H | N102: 2025 2H | O102: 2025E | P102: 2026F | Q102: 2027F | R102: 2028F | S102: 2029F | T102: 2030F
B103: 비품 | G103: 취득금액 | H103: 내용연수 | I103: 상각법 | J103: 상각률 | N103: =SUM(N104:N109) -> 0.36376243 | P103: =SUM(P104:P109) -> 2.539283 | Q103: =SUM(Q104:Q109) -> 3.5732353 | R103: =SUM(R104:R109) -> 3.7302475 | S103: =SUM(S104:S109) -> 3.6081158 | T103: =SUM(T104:T109) -> 3.2929514
C104: 2025 2H | G104: =N96 -> 2.755776 | H104: 4 | I104: 정률법 | J104: 0.528 | N104: =$G104*$J104/2/2 -> 0.36376243 | P104: =($G104-$N104)*$J104 -> 1.2629832 | Q104: =($G104-$N104-$P104)*$J104 -> 0.59612805 | R104: =($G104-$N104-$P104-$Q104)*$J104 -> 0.28137244 | S104: =($G104-$N104-$P104-$Q104-$R104)*$J104 -> 0.13280779 | T104: =($G104-$N104-$P104-$Q104-$R104-$S104)*$J104 -> 0.062685278
C105: 2026F | G105: =P96+P104 -> 4.8344691 | H105: 4 | I105: 정률법 | J105: 0.528 | P105: =$G105*$J105/2 -> 1.2762999 | Q105: =($G105-$N105-$P105)*$J105 -> 1.8787134 | R105: =($G105-$N105-$P105-$Q105)*$J105 -> 0.88675272 | S105: =($G105-$N105-$P105-$Q105-$R105)*$J105 -> 0.41854728 | T105: =($G105-$N105-$P105-$Q105-$R105-$S105)*$J105 -> 0.19755432
C106: 2027F | G106: =Q96+Q104+Q105 -> 4.1605828 | H106: 4 | I106: 정률법 | J106: 0.528 | Q106: =($G106-$N106-$P106)*$J106/2 -> 1.0983939 | R106: =($G106-$N106-$P106-$Q106)*$J106 -> 1.6168358 | S106: =($G106-$N106-$P106-$Q106-$R106)*$J106 -> 0.76314648 | T106: =($G106-$N106-$P106-$Q106-$R106-$S106)*$J106 -> 0.36020514
C107: 2028F | G107: =R104+R105+R106+R96 -> 3.5806309 | H107: 4 | I107: 정률법 | J107: 0.528 | R107: =($G107-$N107-$P107-$Q107)*$J107/2 -> 0.94528655 | S107: =($G107-$N107-$P107-$Q107-$R107)*$J107 -> 1.3914618 | T107: =($G107-$N107-$P107-$Q107-$R107-$S107)*$J107 -> 0.65676997
C108: 2029F | G108: =SUM(S104:S107,S96) -> 3.4172441 | H108: 4 | I108: 정률법 | J108: 0.528 | S108: =($G108-$N108-$P108-$Q108-$R108)*$J108/2 -> 0.90215243 | T108: =($G108-$N108-$P108-$Q108-$R108-$S108)*$J108 -> 1.3279684
C109: 2030F | G109: =SUM(T104:T108,T96) -> 2.6051831 | H109: 4 | I109: 정률법 | J109: 0.528 | T109: =($G109-$N109-$P109-$Q109-$R109-$S109)*$J109/2 -> 0.68776833
A112: 5. NWC
L114: 2024A | M114: 2025 1H | N114: 2025 2H | O114: 2025E | P114: 2026F | Q114: 2027F | R114: 2028F | S114: 2029F | T114: 2030F | U114: Terminal
B115: NWC 변동 | M115: =M116 -> 2955.1213 | N115: =N116-M116 -> -2041.2974 | O115: =O116 -> 913.82396 | P115: =P116-O116 -> 154.87275 | Q115: =Q116-P116 -> 213.43454 | R115: =R116-Q116 -> 220.33471 | S115: =S116-R116 -> 225.72209 | T115: =T116-S116 -> 234.78432 | U115: =U116-T116 -> 19.629724
B116: NWC | M116: =M117-M124 -> 2955.1213 | N116: =N117-N124 -> 913.82396 | O116: =O117-O124 -> 913.82396 | P116: =P117-P124 -> 1068.6967 | Q116: =Q117-Q124 -> 1282.1312 | R116: =R117-R124 -> 1502.466 | S116: =S117-S124 -> 1728.188 | T116: =T117-T124 -> 1962.9724 | U116: =U117-U124 -> 1982.6021
B117: 운전자산 | M117: =M118+M121 -> 3076.9853 | N117: =N118+N121 -> 1335.6348 | O117: =O118+O121 -> 1335.6348 | P117: =P118+P121 -> 1694.7709 | Q117: =Q118+Q121 -> 1972.0527 | R117: =R118+R121 -> 2301.5619 | S117: =S118+S121 -> 2638.8935 | T117: =T118+T121 -> 2989.8212 | U117: =U118+U121 -> 3019.7194
C118: 매출채권 | M118: =연결정산표!R11/10^6 -> 2971.3597 | N118: =O118 -> 972.61265 | O118: =O20/O119 -> 972.61265 | P118: =P20/P119 -> 1190.5487 | Q118: =Q20/Q119 -> 1417.3642 | R118: =R20/R119 -> 1656.8276 | S118: =S20/S119 -> 1901.9904 | T118: =T20/T119 -> 2157.0647 | U118: =T20*(1+DCF!$J$174)/U119 -> 2178.6353
D119: 회전율 | M119: =M19/M118*4 -> 7.2775925 | N119: =365/N120 -> 13.201568 | O119: =365/O120 -> 13.201568 | P119: =365/P120 -> 13.201568 | Q119: =365/Q120 -> 13.201568 | R119: =365/R120 -> 13.201568 | S119: =365/S120 -> 13.201568 | T119: =365/T120 -> 13.201568 | U119: =365/U120 -> 13.201568
D120: 회전기일 | I120: =CLASS!I158 -> 27.648231 | M120: =365/M119 -> 50.153948 | N120: =$I120 -> 27.648231 | O120: =$I120 -> 27.648231 | P120: =$I120 -> 27.648231 | Q120: =$I120 -> 27.648231 | R120: =$I120 -> 27.648231 | S120: =$I120 -> 27.648231 | T120: =$I120 -> 27.648231 | U120: =$I120 -> 27.648231 | V120: 클래스어라운드 정산기일 준용
...

Sheet 클래스매출
L1: =L2/K2 -> 0.075 | M1: =M2/(K2-L2) -> 0.45190985 | T1: =T2/S2 -> 0.08657322
J2: =SUBTOTAL(9,J4:J149) -> 25149176182 | K2: =SUBTOTAL(9,K4:K149) -> 25204482182 | L2: =SUBTOTAL(9,L4:L149) -> 1.8903362e+09 | M2: =SUBTOTAL(9,M4:M149) -> 1.0535892e+10 | N2: =SUBTOTAL(9,N4:N80) -> #REF! | P2: =SUBTOTAL(9,P4:P80) -> 63652202 | Q2: =SUBTOTAL(9,Q4:Q80) -> 138765 | R2: =SUBTOTAL(9,R4:R80) -> 200831 | S2: =SUBTOTAL(9,S4:S80) -> 65563 | T2: =SUBTOTAL(9,T4:T80) -> 5676 | V2: =SUBTOTAL(9,V4:V80) -> 1034225156 | W2: =SUBTOTAL(9,W4:W80) -> 131813149 | X2: =SUBTOTAL(9,X4:X80) -> 797836585 | Y2: =SUBTOTAL(9,Y4:Y80) -> 572170533 | Z2: =SUBTOTAL(9,Z4:Z80) -> 28383453 | AA2: =SUBTOTAL(9,AA4:AA80) -> 21986986 | AB2: =SUBTOTAL(9,AB4:AB80) -> 592843 | AC2: =SUBTOTAL(9,AC4:AC80) -> 607632 | ... AL2: =SUBTOTAL(9,AL4:AL80) -> 9835000
A3: 기간 | B3: 카테고리 | C3: 카테고리2 | D3: 시기 | E3: 정산월 | F3: 강의주제 | G3: 강사명 | H3: 기수 | I3: 단가 | J3: 최종 매출액 | K3: 매출액(수수료포함)_v2 | L3: PG수수료_v2 | M3: 정산금_v2 | N3: 강사정산금 | O3: 강사정산금 | P3: 노출 | Q3: 톡방인원수_조정 | R3: 톡방인원수 | S3: 최고동접자 | T3: 결제건수 | U3: 전환율 | V3: 총 광고비 | W3: 광고비 (채널톡+토스+밸류맵 +문자+판다) | X3: 광고 (메타) | Y3: 광고 (gdn) | Z3: 광고 (틱톡) | AA3: 광고 (당근) | AB3: 메타 유입단가 | AC3: 구글 유입단가 | AD3: 틱톡 유입단가 | AE3: 당근 유입단가 | AF3: 상페 | AG3: 전자책 | AH3: 릴스 외주 | AI3: 기타 비용 (식비 등) | AJ3: 촬영 & 광고 편집 & 광고 수수료 | AK3: 유튜브 촬영비 | AL3: 대관비
A4: 2024A | B4: 부동산 | C4: 투자 | D4: 7/30(화) | F4: 소액으로 빌딩사기 | G4: 영끌남 | H4: 1기 | I4: 2792792.8 | J4: 620000000 | K4: 624960000 | L4: 46872000 | M4: 281795146 | N4: 299980800 | O4: =N4/J4 -> 0.48384 | P4: 121991 | R4: 5100 | S4: 1728 | T4: 222 | U4: 0.128 | W4: 2064649 | X4: 6698031 | Y4: 4578778 | Z4: 0 | AA4: 0 | AB4: 3700 | AC4: 0 | AD4: 0 | AE4: 0 | AF4: 1225000 | AG4: 350000 | AH4: 0 | AI4: 0 | AJ4: 1156250 | AK4: 0 | AL4: 0
A5: 2024A | B5: 주식 | C5: 투자 | D5: 9/11(수) | F5: 100% 성공하는 주식 투자 방법 | G5: 김피비 | H5: 1기 | I5: 2776428.6 | J5: 233220000 | K5: 233220000 | L5: 17491500 | M5: 101864354 | N5: 106709090 | O5: =N5/J5 -> 0.45754691 | P5: 175820 | R5: 1400 | S5: 516 | T5: 84 | U5: 0.163 | W5: 369682 | X5: 9249610 | Y5: 750000 | Z5: 0 | AA5: 0 | AB5: 15857 | AC5: 10000 | AD5: 0 | AE5: 0 | AF5: 1072500 | AG5: 0 | AH5: 0 | AI5: 250500 | AJ5: 1380000 | AK5: 0 | AL5: 0
A6: 2024A | B6: 부업 | C6: 부업 | D6: 10/2(수) | F6: 커머스의 신 1기 | G6: 하지혜 | H6: 1기 | I6: 2294489.8 | J6: 112430000 | K6: 112430000 | L6: 8432250 | M6: 44356219 | N6: 66341170 | O6: =N6/J6 -> 0.59006644 | P6: 118964 | R6: 2300 | S6: 738 | T6: 49 | U6: 0.066 | W6: 851844 | X6: 6974382 | Y6: 4230086 | Z6: 0 | AA6: 0 | AB6: 4026 | AC6: 7000 | AD6: 0 | AE6: 0 | AF6: 1320000 | AG6: 0 | AH6: 0 | AI6: 249000 | AJ6: 2980000 | AK6: 0 | AL6: 0
A7: 2024A | B7: 부업 | C7: 부업 | D7: 10/7(월) | F7: 공간대여 올인원 코스 | G7: 정이슬 | H7: 1기 | I7: 1223333.3 | J7: 29360000 | K7: 29360000 | L7: 2202000 | M7: 7479152.5 | P7: 127483 | R7: 1500 | S7: 518 | T7: 24 | U7: 0.046 | W7: 445347 | X7: 7277940 | Y7: 2735908 | Z7: 0 | AA7: 0 | AB7: 9313 | AC7: 6170 | AD7: 0 | AE7: 0 | AF7: 0 | AG7: 0 | AH7: 1650000 | AI7: 110500 | AJ7: 1630000 | AK7: 0 | AL7: 0
A8: 2024A | B8: 부동산 | C8: 투자 | D8: 10/10(목) | F8: 소액으로 빌딩사기 2기 | G8: 영끌남 | H8: 2기 | I8: 2984914.7 | J8: 874580000 | K8: 874580000 | L8: 65593500 | M8: 3.9391915e+08 | N8: 407396544 | O8: =N8/J8 -> 0.46581964 | P8: 240175 | R8: 3300 | S8: 1134 | T8: 293 | U8: 0.258 | W8: 1707293 | X8: 11746000 | Y8: 5914910 | Z8: 0 | AA8: 0 | AB8: 8505 | AC8: 11643 | AD8: 0 | AE8: 0 | AF8: 0 | AG8: 0 | AH8: 0 | AI8: 0 | AJ8: 1780000 | AK8: 0 | AL8: 0
A9: 2024A | B9: 부동산 | C9: 투자 | D9: 10/21(월) | F9: 부동산 | G9: 부토리 | H9: 1기 | I9: 1626842.1 | J9: 30910000 | K9: 30910000 | L9: 2318250 | M9: 8470751.5 | N9: 14513832 | O9: =N9/J9 -> 0.46955136 | P9: 154755 | R9: 1700 | S9: 656 | T9: 19 | U9: 0.029 | W9: 588273 | X9: 6700000 | Y9: 2621974 | Z9: 0 | AA9: 0 | AB9: 8445 | AC9: 12367 | AD9: 0 | AE9: 0 | AF9: 0 | AG9: 200000 | AH9: 0 | AI9: 200000 | AJ9: 1540000 | AK9: 0 | AL9: 0
A10: 2024A | B10: 부업 | C10: 부업 | D10: 10/30(수) | F10: 안마의자 | G10: 주부투잡 | H10: 1기 | I10: 1174259.3 | J10: 63410000 | K10: 63410000 | L10: 4755750 | M10: 23583418 | N10: 27054488 | O10: =N10/J10 -> 0.42665964 | P10: 68408 | R10: 800 | S10: 322 | T10: 54 | U10: 0.168 | W10: 458749 | X10: 5900000 | Y10: 3607765 | Z10: 0 | AA10: 0 | AB10: 12794 | AC10: 8500 | AD10: 0 | AE10: 0 | AF10: 0 | AG10: 240000 | AH10: 0 | AI10: 106300 | AJ10: 1414600 | AK10: 0 | AL10: 0
A11: 2024A | B11: 부동산 | C11: 투자 | D11: 11/4(월) | F11: 부동산(청약) | G11: 소나무우유 | H11: 1기 | I11: 2123241.4 | J11: 61574000 | K11: 61574000 | L11: 4618050 | M11: 23743190 | N11: 28596440 | O11: =N11/J11 -> 0.46442394 | P11: 99692 | R11: 2400 | S11: 763 | T11: 29 | U11: 0.038 | W11: 0 | X11: 6265939 | Y11: 1587730 | Z11: 0 | AA11: 0 | AB11: 13734 | AC11: 12323 | AD11: 0 | AE11: 0 | AF11: 0 | AG11: 170000 | AH11: 0 | AI11: 143000 | AJ11: 1472900 | AK11: 0 | AL11: 0
A12: 2024A | B12: 부업 | C12: 부업 | D12: 11/11(월) | F12: 해외구매대행 | G12: 오션 | H12: 12기 | I12: 2169677.4 | J12: 67260000 | K12: 67260000 | L12: 5044500 | M12: 25972764 | N12: 31094660 | O12: =N12/J12 -> 0.46230538 | P12: 59400 | R12: 1100 | S12: 348 | T12: 31 | U12: 0.089 | W12: 164289 | X12: 6024924 | Y12: 2258458 | Z12: 0 | AA12: 0 | AB12: 12500 | AC12: 8337 | AD12: 0 | AE12: 0 | AF12: 0 | AG12: 0 | AH12: 0 | AI12: 269000 | AJ12: 1553300 | AK12: 0 | AL12: 0
A13: 2024A | B13: 부동산 | C13: 투자 | D13: 11/13(수) | F13: 부동산 경공매 자동화 전략 | G13: 부자친구들 | H13: 1기 | I13: 3300000 | J13: 62700000 | K13: 62700000 | L13: 4702500 | M13: 23062006 | N13: 29619126 | O13: =N13/J13 -> 0.47239435 | P13: 94694 | R13: 700 | S13: 288 | T13: 19 | U13: 0.066 | W13: 214317 | X13: 6534371 | Y13: 3364300 | Z13: 0 | AA13: 0 | AB13: 10500 | AC13: 6932 | AD13: 0 | AE13: 0 | AF13: 0 | AG13: 300000 | AH13: 0 | AI13: 220500 | AJ13: 1540000 | AK13: 0 | AL13: 0
A14: 2024A | B14: 부업 | C14: 부업 | D14: 11/18(월) | F14: 커머스의 신 2기 | G14: 하지혜 | H14: 2기 | I14: 2451714.3 | J14: 85810000 | K14: 85810000 | L14: 6435750 | M14: 32231988 | N14: 45029840 | O14: =N14/J14 -> 0.52476214 | P14: 71322 | R14: 1500 | S14: 410 | T14: 35 | U14: 0.085 | W14: 211479 | X14: 6010947 | Y14: 5669247 | Z14: 0 | AA14: 0 | AB14: 5500 | AC14: 7200 | AD14: 0 | AE14: 0 | AF14: 0 | AG14: 0 | AH14: 0 | AI14: 387500 | AJ14: 2631100 | AK14: 0 | AL14: 0
A15: 2024A | B15: 코인 | C15: 투자 | D15: 11/20(수) | F15: 코인투자 | G15: 돈복남 | H15: 1기 | I15: 1990000 | J15: 21890000 | K15: 42460000 | L15: 3184500 | M15: 7850684 | N15: 19531600 | O15: =N15/J15 -> 0.89226131 | P15: 499990 | R15: 700 | S15: 259 | T15: 11 | U15: 0.042 | W15: 209928 | X15: 20539804 | Y15: 0 | Z15: 0 | AA15: 0 | AB15: 12000 | AC15: 0 | AD15: 0 | AE15: 0 | AF15: 0 | AG15: 1424500 | AH15: 0 | AI15: 184400 | AJ15: 2640000 | AK15: 0 | AL15: 0
A16: 2024A | B16: 부동산 | C16: 투자 | D16: 11/25(월) | F16: 소액으로 빌딩사기 3기 | G16: 영끌남 | H16: 3기 | I16: 3274838.7 | J16: 710640000 | K16: 664580000 | L16: 49843500 | M16: 294772504 | N16: 386639511 | O16: =N16/J16 -> 0.54407226 | P16: 167216 | R16: 2500 | S16: 862 | T16: 217 | U16: 0.252 | W16: 156337 | X16: 14999468 | Y16: 8338687 | Z16: 0 | AA16: 0 | AB16: 8569 | AC16: 12000 | AD16: 0 | AE16: 0 | AF16: 0 | AG16: 0 | AH16: 0 | AI16: 157000 | AJ16: 1540000 | AK16: 0 | AL16: 0
